{
  "type": "Feature",
  "properties": {
    "gn:gn_country":"CZ",
    "gn:gn_fcode":"PPL",
    "gn:gn_pop":132,
    "gn:population":132,
    "iso:country":"CZ",
    "name:ceb_x_preferred":[
        "Tet\u00edn"
    ],
    "name:ces_x_preferred":[
        "Tet\u00edn"
    ],
    "name:deu_x_preferred":[
        "Tet\u00edn"
    ],
    "name:eng_x_preferred":[
        "Tet\u00edn"
    ],
    "name:eus_x_preferred":[
        "Tet\u00edn"
    ],
    "name:fas_x_preferred":[
        "\u062a\u062a\u06cc\u0646"
    ],
    "name:fra_x_preferred":[
        "Tet\u00edn"
    ],
    "name:hun_x_preferred":[
        "Tet\u00edn"
    ],
    "name:ita_x_preferred":[
        "Tet\u00edn"
    ],
    "name:msa_x_preferred":[
        "Tet\u00edn"
    ],
    "name:nan_x_preferred":[
        "Tet\u00edn"
    ],
    "name:nld_x_preferred":[
        "Tet\u00edn"
    ],
    "name:pol_x_preferred":[
        "Tet\u00edn"
    ],
    "name:por_x_preferred":[
        "Tet\u00edn"
    ],
    "name:rup_x_preferred":[
        "Tet\u00edn"
    ],
    "name:slk_x_preferred":[
        "Tet\u00edn"
    ],
    "name:spa_x_preferred":[
        "Tet\u00edn"
    ],
    "name:srp_x_preferred":[
        "\u0422\u0435\u0442\u0438\u043d"
    ],
    "name:swe_x_preferred":[
        "Tet\u00edn"
    ],
    "name:vie_x_preferred":[
        "Tet\u00edn"
    ],
    "qs_pg:aaroncc":"CZ",
    "qs_pg:gn_country":"CZ",
    "qs_pg:gn_fcode":"PPL",
    "qs_pg:gn_pop":132,
    "qs_pg:name":"Tet\u00edn",
    "qs_pg:name_adm0":"\u010cesk\u00e1 republika",
    "qs_pg:name_adm1":"Kr\u00e1lov\u00e9hradeck\u00fd kraj",
    "qs_pg:photos_9r":0,
    "qs_pg:photos_sr":0,
    "qs_pg:pop_sr":1,
    "qs_pg:qs_pg_placetype":"locality",
    "qs_pg:qs_pg_placetype_gp":"Town",
    "qs_pg:woe_adm0":23424810,
    "woe:adm0_id":23424810,
    "woe:name_adm0":"\u010cesk\u00e1 republika",
    "woe:name_adm1":"Kr\u00e1lov\u00e9hradeck\u00fd kraj",
    "woe:placetype":"Town",
    "wof:name":"Tet\u00edn",
    "wof:placetype":"locality",
    "wof:population":132
},
  "geometry": {"coordinates":[15.63223,50.42484],"type":"Point"}
}