{
  "type": "Feature",
  "properties": {
    "gn:admin1_code":"79",
    "gn:admin2_code":"0313",
    "gn:asciiname":"Veclov",
    "gn:country_code":"CZ",
    "gn:dem":559,
    "gn:feature_class":"P",
    "gn:feature_code":"PPL",
    "gn:name":"Veclov",
    "gn:population":0,
    "gn:timezone":"Europe/Prague",
    "iso:country":"CZ",
    "name:und_x_variant":[
        "Wetzler",
        "Veclov"
    ],
    "wof:name":"Veclov",
    "wof:placetype":"locality"
},
  "geometry": {"coordinates":[15.23185,48.97948],"type":"Point"}
}