{
  "type": "Feature",
  "properties": {
    "iso:country":"CZ",
    "name:azb_x_preferred":[
        "\u0646\u062a\u0634\u062a\u06cc\u0646\u06cc"
    ],
    "name:ceb_x_preferred":[
        "Ne\u010dtiny"
    ],
    "name:ces_x_preferred":[
        "Ne\u010dtiny"
    ],
    "name:deu_x_preferred":[
        "Ne\u010dtiny"
    ],
    "name:eus_x_preferred":[
        "Ne\u010dtiny"
    ],
    "name:fas_x_preferred":[
        "\u0646\u062a\u0634\u062a\u06cc\u0646\u06cc"
    ],
    "name:fra_x_preferred":[
        "Ne\u010dtiny"
    ],
    "name:hun_x_preferred":[
        "Ne\u010dtiny"
    ],
    "name:ita_x_preferred":[
        "Ne\u010dtiny"
    ],
    "name:msa_x_preferred":[
        "Ne\u010dtiny"
    ],
    "name:nld_x_preferred":[
        "Ne\u010dtiny"
    ],
    "name:por_x_preferred":[
        "Ne\u010dtiny"
    ],
    "name:slk_x_preferred":[
        "Ne\u010dtiny"
    ],
    "name:spa_x_preferred":[
        "Ne\u010dtiny"
    ],
    "name:srp_x_preferred":[
        "\u041d\u0435\u0447\u0442\u0438\u043d\u0438"
    ],
    "name:swe_x_preferred":[
        "Ne\u010dtiny"
    ],
    "name:vie_x_preferred":[
        "Ne\u010dtiny"
    ],
    "qs_pg:aaroncc":"CZ",
    "qs_pg:name":"Ne\u010dtiny",
    "qs_pg:name_adm0":"\u010cesk\u00e1 republika",
    "qs_pg:name_adm1":"Plze\u0148sk\u00fd kraj",
    "qs_pg:photos":1,
    "qs_pg:photos_1k":1,
    "qs_pg:photos_9k":1,
    "qs_pg:photos_9r":1,
    "qs_pg:photos_all":10,
    "qs_pg:photos_sr":1,
    "qs_pg:pop_sr":0,
    "qs_pg:qs_pg_placetype":"localadmin",
    "qs_pg:qs_pg_placetype_gp":"LocalAdmin",
    "qs_pg:woe_adm0":23424810,
    "woe:adm0_id":23424810,
    "woe:name_adm0":"\u010cesk\u00e1 republika",
    "woe:name_adm1":"Plze\u0148sk\u00fd kraj",
    "woe:placetype":"LocalAdmin",
    "wof:name":"Ne\u010dtiny",
    "wof:placetype":"localadmin"
},
  "geometry": {"coordinates":[13.162887,49.960828],"type":"Point"}
}