{
  "type": "Feature",
  "properties": {
    "iso:country":"CZ",
    "name:ces_x_preferred":[
        "Dubi"
    ],
    "name:unk_x_variant":[
        "Dubi"
    ],
    "qs:gn_adm0_cc":"CZ",
    "qs:gn_fcode":"PPLX",
    "qs:gn_local":3073699,
    "qs:gn_nam_loc":"Kladno, Kladno, Kladno, St\u0159edo\u010desk\u00fd kraj, CZ",
    "qs:gn_namadm1":"88",
    "qs:gn_name":"Dub\u00ed",
    "qs:local_max":341,
    "qs:local_sum":376,
    "qs:localhoods":3,
    "qs:name":"Dubi",
    "qs:name_adm0":"\u010cesk\u00e1 republika",
    "qs:name_adm1":"St\u0159edo\u010desk\u00fd kraj",
    "qs:name_adm2":"Kladno",
    "qs:name_lau":"Kladno",
    "qs:name_local":"Kladno",
    "qs:photo_max":3,
    "qs:photo_sum":17,
    "qs:placetype":"Suburb",
    "qs:quad_count":12,
    "qs:woe_adm0":23424810,
    "qs:woe_adm1":20070468,
    "qs:woe_adm2":12582583,
    "qs:woe_lau":12608143,
    "qs:woe_local":791229,
    "qs:woe_ver":"7.10.0",
    "wof:lang":[
        "cze"
    ],
    "wof:name":"Dubi",
    "wof:placetype":"neighbourhood"
},
  "geometry": {"coordinates":[14.15346,50.163961],"type":"Point"}
}