{
  "type": "Feature",
  "properties": {
    "gn:admin1_code":"87.0",
    "gn:admin2_code":"0325",
    "gn:asciiname":"Rakolusky",
    "gn:country_code":"CZ",
    "gn:dem":304,
    "gn:feature_class":"P",
    "gn:feature_code":"PPL",
    "gn:name":"Rakolusky",
    "gn:population":0,
    "gn:timezone":"Europe/Prague",
    "iso:country":"CZ",
    "wof:name":"Rakolusky",
    "wof:placetype":"locality"
},
  "geometry": {"coordinates":[13.59661,49.92492],"type":"Point"}
}