{
  "type": "Feature",
  "properties": {
    "gn:gn_country":"CZ",
    "gn:gn_fcode":"PPL",
    "gn:gn_pop":913,
    "gn:population":913,
    "iso:country":"CZ",
    "name:cze_x_preferred":[
        "Brankovice"
    ],
    "name:dut_x_preferred":[
        "Brankovice"
    ],
    "name:eng_x_preferred":[
        "Brankovice"
    ],
    "name:fre_x_preferred":[
        "Brankovice"
    ],
    "name:ger_x_preferred":[
        "Brankovice"
    ],
    "name:hun_x_preferred":[
        "Brankovice"
    ],
    "name:ita_x_preferred":[
        "Brankovice"
    ],
    "name:may_x_preferred":[
        "Brankovice"
    ],
    "name:nan_x_preferred":[
        "Brankovice"
    ],
    "name:per_x_preferred":[
        "\u0628\u0631\u0627\u0646\u06a9\u0648\u0648\u06cc\u062a\u0633\u0647"
    ],
    "name:por_x_preferred":[
        "Brankovice"
    ],
    "name:rup_x_preferred":[
        "Brankovice"
    ],
    "name:slo_x_preferred":[
        "Brankovice"
    ],
    "name:srp_x_preferred":[
        "\u0411\u0440\u0430\u043d\u043a\u043e\u0432\u0438\u0446\u0435"
    ],
    "name:swe_x_preferred":[
        "Brankovice"
    ],
    "name:unk_x_variant":[
        "Brankowitz"
    ],
    "name:vie_x_preferred":[
        "Brankovice"
    ],
    "qs_pg:aaroncc":"CZ",
    "qs_pg:gn_country":"CZ",
    "qs_pg:gn_fcode":"PPL",
    "qs_pg:gn_pop":913,
    "qs_pg:name":"Brankovice",
    "qs_pg:photos_9r":0,
    "qs_pg:photos_sr":0,
    "qs_pg:pop_sr":2,
    "qs_pg:qs_pg_placetype":"locality",
    "wof:name":"Brankovice",
    "wof:placetype":"locality",
    "wof:population":913
},
  "geometry": {"coordinates":[17.1348,49.15598],"type":"Point"}
}