{
  "type": "Feature",
  "properties": {
    "gn:gn_country":"CZ",
    "gn:gn_fcode":"PPL",
    "gn:gn_pop":63,
    "gn:population":63,
    "iso:country":"CZ",
    "name:cze_x_preferred":[
        "T\u0159eb\u010dice"
    ],
    "name:dut_x_preferred":[
        "T\u0159eb\u010dice"
    ],
    "name:eng_x_preferred":[
        "T\u0159eb\u010dice"
    ],
    "name:fre_x_preferred":[
        "T\u0159eb\u010dice"
    ],
    "name:ger_x_preferred":[
        "T\u0159eb\u010dice"
    ],
    "name:hun_x_preferred":[
        "T\u0159eb\u010dice"
    ],
    "name:ita_x_preferred":[
        "T\u0159eb\u010dice"
    ],
    "name:may_x_preferred":[
        "T\u0159eb\u010dice"
    ],
    "name:per_x_preferred":[
        "\u062a\u0631\u0628\u0686\u06cc\u062a\u0633"
    ],
    "name:pol_x_preferred":[
        "T\u0159eb\u010dice"
    ],
    "name:por_x_preferred":[
        "T\u0159eb\u010dice"
    ],
    "name:slo_x_preferred":[
        "T\u0159eb\u010dice"
    ],
    "name:srp_x_preferred":[
        "\u0422\u0440\u0435\u043f\u0447\u0438\u0446\u0435"
    ],
    "name:vie_x_preferred":[
        "T\u0159eb\u010dice"
    ],
    "qs_pg:aaroncc":"CZ",
    "qs_pg:gn_country":"CZ",
    "qs_pg:gn_fcode":"PPL",
    "qs_pg:gn_pop":63,
    "qs_pg:name":"T\u0159eb\u010dice",
    "qs_pg:name_adm0":"\u010cesk\u00e1 republika",
    "qs_pg:name_adm1":"Plze\u0148sk\u00fd kraj",
    "qs_pg:photos_9r":0,
    "qs_pg:photos_sr":0,
    "qs_pg:pop_sr":1,
    "qs_pg:qs_pg_placetype":"locality",
    "qs_pg:qs_pg_placetype_gp":"Town",
    "qs_pg:woe_adm0":23424810,
    "woe:adm0_id":23424810,
    "woe:name_adm0":"\u010cesk\u00e1 republika",
    "woe:name_adm1":"Plze\u0148sk\u00fd kraj",
    "woe:placetype":"Town",
    "wof:name":"T\u0159eb\u010dice",
    "wof:placetype":"locality",
    "wof:population":63
},
  "geometry": {"coordinates":[13.61207,49.48337],"type":"Point"}
}