{
  "type": "Feature",
  "properties": {
    "gn:admin1_code":"84.0",
    "gn:admin2_code":"0714",
    "gn:asciiname":"Podhori",
    "gn:country_code":"CZ",
    "gn:dem":356,
    "gn:feature_class":"P",
    "gn:feature_code":"PPL",
    "gn:name":"Podho\u0159\u00ed",
    "gn:population":0,
    "gn:timezone":"Europe/Prague",
    "iso:country":"CZ",
    "wof:name":"Podhori",
    "wof:placetype":"locality"
},
  "geometry": {"coordinates":[17.62965,49.56964],"type":"Point"}
}