{
  "type": "Feature",
  "properties": {
    "gn:admin1_code":"88.0",
    "gn:admin2_code":"0208",
    "gn:asciiname":"Osek",
    "gn:country_code":"CZ",
    "gn:dem":249,
    "gn:feature_class":"P",
    "gn:feature_code":"PPL",
    "gn:name":"Osek",
    "gn:population":165,
    "gn:timezone":"Europe/Prague",
    "iso:country":"CZ",
    "wof:name":"Osek",
    "wof:placetype":"locality",
    "wof:population":165
},
  "geometry": {"coordinates":[15.36546,50.26844000000001],"type":"Point"}
}