{
  "type": "Feature",
  "properties": {
    "gn:admin1_code":"79.0",
    "gn:admin2_code":"0316",
    "gn:asciiname":"Podsrp",
    "gn:country_code":"CZ",
    "gn:dem":471,
    "gn:feature_class":"P",
    "gn:feature_code":"PPL",
    "gn:name":"Podsrp",
    "gn:population":0,
    "gn:timezone":"Europe/Prague",
    "iso:country":"CZ",
    "wof:name":"Podsrp",
    "wof:placetype":"locality"
},
  "geometry": {"coordinates":[13.93736,49.25],"type":"Point"}
}