{
  "type": "Feature",
  "properties": {
    "gn:country":"CZ",
    "gn:fcode":"PPL",
    "gn:population":171,
    "iso:country":"CZ",
    "name:ceb_x_preferred":[
        "Rado\u0161ovice"
    ],
    "name:ces_x_preferred":[
        "Rado\u0161ovice"
    ],
    "name:deu_x_preferred":[
        "Rado\u0161ovice"
    ],
    "name:fra_x_preferred":[
        "Rado\u0161ovice"
    ],
    "name:hun_x_preferred":[
        "Rado\u0161ovice"
    ],
    "name:ita_x_preferred":[
        "Rado\u0161ovice"
    ],
    "name:nld_x_preferred":[
        "Rado\u0161ovice"
    ],
    "name:oci_x_preferred":[
        "Rado\u0161ovice"
    ],
    "name:pol_x_preferred":[
        "Rado\u0161ovice"
    ],
    "name:slk_x_preferred":[
        "Rado\u0161ovice"
    ],
    "name:srp_x_preferred":[
        "\u0420\u0430\u0434\u043e\u0448\u043e\u0432\u0438\u0446\u0435"
    ],
    "name:swe_x_preferred":[
        "Rado\u0161ovice"
    ],
    "qs_pg:aaroncc":"CZ",
    "qs_pg:gn_country":"CZ",
    "qs_pg:gn_fcode":"PPL",
    "qs_pg:gn_pop":171,
    "qs_pg:name":"Rado\u0161ovice",
    "qs_pg:name_adm0":"\u010cesk\u00e1 republika",
    "qs_pg:name_adm1":"Jiho\u010desk\u00fd kraj",
    "qs_pg:photos_9r":0,
    "qs_pg:photos_sr":0,
    "qs_pg:pop_sr":1,
    "qs_pg:qs_pg_placetype":"locality",
    "qs_pg:qs_pg_placetype_gp":"Town",
    "qs_pg:woe_adm0":23424810,
    "woe:adm0_id":23424810,
    "woe:name_adm0":"\u010cesk\u00e1 republika",
    "woe:name_adm1":"Jiho\u010desk\u00fd kraj",
    "woe:placetype":"Town",
    "wof:name":"Rado\u0161ovice",
    "wof:placetype":"locality",
    "wof:population":171
},
  "geometry": {"coordinates":[14.27293,49.01959],"type":"Point"}
}