{
  "type": "Feature",
  "properties": {
    "iso:country":"CZ",
    "name:azb_x_preferred":[
        "\u0627\u0648\u0645\u06cc\u062a\u0633\u0647"
    ],
    "name:ceb_x_preferred":[
        "Omice"
    ],
    "name:ces_x_preferred":[
        "Omice"
    ],
    "name:deu_x_preferred":[
        "Omice"
    ],
    "name:eus_x_preferred":[
        "Omice"
    ],
    "name:fas_x_preferred":[
        "\u0627\u0648\u0645\u06cc\u062a\u0633\u0647"
    ],
    "name:fra_x_preferred":[
        "Omice"
    ],
    "name:hun_x_preferred":[
        "Omice"
    ],
    "name:ita_x_preferred":[
        "Omice"
    ],
    "name:msa_x_preferred":[
        "Omice"
    ],
    "name:nld_x_preferred":[
        "Omice"
    ],
    "name:pol_x_preferred":[
        "Omice"
    ],
    "name:por_x_preferred":[
        "Omice"
    ],
    "name:slk_x_preferred":[
        "Omice"
    ],
    "name:spa_x_preferred":[
        "Omice"
    ],
    "name:swe_x_preferred":[
        "Omice"
    ],
    "name:vie_x_preferred":[
        "Omice"
    ],
    "qs_pg:aaroncc":"CZ",
    "qs_pg:name":"Omice",
    "qs_pg:name_adm0":"\u010cesk\u00e1 republika",
    "qs_pg:name_adm1":"Jihomoravsk\u00fd kraj",
    "qs_pg:photos":2,
    "qs_pg:photos_1k":1,
    "qs_pg:photos_9k":1,
    "qs_pg:photos_9r":1,
    "qs_pg:photos_all":2,
    "qs_pg:photos_sr":1,
    "qs_pg:pop_sr":0,
    "qs_pg:qs_pg_placetype":"localadmin",
    "qs_pg:qs_pg_placetype_gp":"LocalAdmin",
    "qs_pg:woe_adm0":23424810,
    "woe:adm0_id":23424810,
    "woe:name_adm0":"\u010cesk\u00e1 republika",
    "woe:name_adm1":"Jihomoravsk\u00fd kraj",
    "woe:placetype":"LocalAdmin",
    "wof:name":"Omice",
    "wof:placetype":"localadmin"
},
  "geometry": {"coordinates":[16.443142,49.180272],"type":"Point"}
}