{
  "type": "Feature",
  "properties": {
    "iso:country":"CZ",
    "name:ces_x_preferred":[
        "\u010cern\u00e1 Pole"
    ],
    "name:cze_x_colloquial":[
        "Cerna Pole",
        "Eerna Pole"
    ],
    "name:cze_x_variant":[
        "\u00c8ern\u00e1 Pole"
    ],
    "name:eng_x_preferred":[
        "\u010cern\u00e1 Pole"
    ],
    "name:fin_x_preferred":[
        "\u010cern\u00e1 Pole"
    ],
    "name:fra_x_preferred":[
        "\u010cern\u00e1 Pole"
    ],
    "name:pol_x_preferred":[
        "\u010cern\u00e1 Pole"
    ],
    "name:slk_x_preferred":[
        "\u010cern\u00e1 Pole"
    ],
    "wof:lang":[
        "cze"
    ],
    "wof:name":"\u010cern\u00e1 Pole",
    "wof:placetype":"neighbourhood"
},
  "geometry": {"coordinates":[16.6143,49.209231],"type":"Point"}
}