{
  "type": "Feature",
  "properties": {
    "gn:gn_country":"CZ",
    "gn:gn_fcode":"PPL",
    "gn:gn_pop":258,
    "gn:population":258,
    "iso:country":"CZ",
    "name:ces_x_preferred":[
        "Slatina"
    ],
    "name:deu_x_preferred":[
        "Slatina"
    ],
    "name:eng_x_preferred":[
        "Slatina"
    ],
    "name:fas_x_preferred":[
        "\u0633\u0644\u0627\u062a\u06cc\u0646\u0627"
    ],
    "name:fra_x_preferred":[
        "Slatina"
    ],
    "name:hun_x_preferred":[
        "Slatina"
    ],
    "name:ita_x_preferred":[
        "Slatina"
    ],
    "name:msa_x_preferred":[
        "Slatina"
    ],
    "name:nld_x_preferred":[
        "Slatina"
    ],
    "name:pol_x_preferred":[
        "Slatina"
    ],
    "name:por_x_preferred":[
        "Slatina"
    ],
    "name:rup_x_preferred":[
        "Slatina"
    ],
    "name:slk_x_preferred":[
        "Slatina"
    ],
    "name:srp_x_preferred":[
        "\u0421\u043b\u0430\u0442\u0438\u043d\u0430"
    ],
    "name:swe_x_preferred":[
        "Slatina"
    ],
    "name:vie_x_preferred":[
        "Slatina"
    ],
    "qs_pg:aaroncc":"CZ",
    "qs_pg:gn_country":"CZ",
    "qs_pg:gn_fcode":"PPL",
    "qs_pg:gn_pop":258,
    "qs_pg:name":"Slatina",
    "qs_pg:name_adm0":"\u010cesk\u00e1 republika",
    "qs_pg:name_adm1":"Jihomoravsk\u00fd kraj",
    "qs_pg:photos_9r":0,
    "qs_pg:photos_sr":0,
    "qs_pg:pop_sr":2,
    "qs_pg:qs_pg_placetype":"locality",
    "qs_pg:qs_pg_placetype_gp":"Town",
    "qs_pg:woe_adm0":23424810,
    "woe:adm0_id":23424810,
    "woe:name_adm0":"\u010cesk\u00e1 republika",
    "woe:name_adm1":"Jihomoravsk\u00fd kraj",
    "woe:placetype":"Town",
    "wof:name":"Slatina",
    "wof:placetype":"locality",
    "wof:population":258
},
  "geometry": {"coordinates":[16.01835,49.01965],"type":"Point"}
}