{
  "type": "Feature",
  "properties": {
    "gn:admin1_code":"82.0",
    "gn:admin2_code":"0521",
    "gn:asciiname":"Nepasice",
    "gn:country_code":"CZ",
    "gn:dem":235,
    "gn:feature_class":"P",
    "gn:feature_code":"PPL",
    "gn:name":"Nepasice",
    "gn:population":0,
    "gn:timezone":"Europe/Prague",
    "iso:country":"CZ",
    "wof:name":"Nepasice",
    "wof:placetype":"locality"
},
  "geometry": {"coordinates":[15.94487,50.20927],"type":"Point"}
}