{
  "type": "Feature",
  "properties": {
    "gn:admin1_code":"80.0",
    "gn:admin2_code":"0611",
    "gn:asciiname":"Dobrovitova Lhota",
    "gn:country_code":"CZ",
    "gn:dem":460,
    "gn:feature_class":"P",
    "gn:feature_code":"PPL",
    "gn:name":"Dobrov\u00edtova Lhota",
    "gn:population":0,
    "gn:timezone":"Europe/Prague",
    "iso:country":"CZ",
    "wof:name":"Dobrovitova Lhota",
    "wof:placetype":"locality"
},
  "geometry": {"coordinates":[15.31589,49.66457],"type":"Point"}
}