{
  "type": "Feature",
  "properties": {
    "gn:admin1_code":"79.0",
    "gn:admin2_code":"0316",
    "gn:asciiname":"Skudra",
    "gn:country_code":"CZ",
    "gn:dem":559,
    "gn:feature_class":"P",
    "gn:feature_code":"PPL",
    "gn:name":"\u0160k\u016fdra",
    "gn:population":0,
    "gn:timezone":"Europe/Prague",
    "iso:country":"CZ",
    "wof:name":"Skudra",
    "wof:placetype":"locality"
},
  "geometry": {"coordinates":[13.74038,49.21833],"type":"Point"}
}