{
  "type": "Feature",
  "properties": {
    "gn:admin1_code":"87.0",
    "gn:admin2_code":"0325",
    "gn:asciiname":"Plan",
    "gn:country_code":"CZ",
    "gn:dem":558,
    "gn:feature_class":"P",
    "gn:feature_code":"PPL",
    "gn:name":"Pl\u00e1\u0148",
    "gn:population":0,
    "gn:timezone":"Europe/Prague",
    "iso:country":"CZ",
    "name:und_x_variant":[
        "Planes",
        "Pl\u00e1\u0148"
    ],
    "wof:name":"Plan",
    "wof:placetype":"locality"
},
  "geometry": {"coordinates":[13.07734,49.90757],"type":"Point"}
}