{
  "type": "Feature",
  "properties": {
    "gn:admin1_code":"89.0",
    "gn:admin2_code":"0423",
    "gn:asciiname":"Bohdal",
    "gn:country_code":"CZ",
    "gn:dem":276,
    "gn:feature_class":"P",
    "gn:feature_code":"PPL",
    "gn:name":"Bohdal",
    "gn:population":0,
    "gn:timezone":"Europe/Prague",
    "iso:country":"CZ",
    "wof:name":"Bohdal",
    "wof:placetype":"locality"
},
  "geometry": {"coordinates":[14.04599,50.35072],"type":"Point"}
}