{
  "type": "Feature",
  "properties": {
    "gn:admin1_code":"89.0",
    "gn:admin2_code":"0422",
    "gn:asciiname":"Nasi",
    "gn:country_code":"CZ",
    "gn:dem":215,
    "gn:feature_class":"P",
    "gn:feature_code":"PPL",
    "gn:name":"Nasi",
    "gn:population":0,
    "gn:timezone":"Europe/Prague",
    "iso:country":"CZ",
    "name:ceb_x_preferred":[
        "Nasi"
    ],
    "name:ces_x_historical":[
        "Na\u0161\u00ed"
    ],
    "name:ces_x_preferred":[
        "Na\u0161\u00ed"
    ],
    "name:deu_x_historical":[
        "Naschau"
    ],
    "name:deu_x_preferred":[
        "Naschau"
    ],
    "name:deu_x_variant":[
        "Nasi"
    ],
    "name:fra_x_preferred":[
        "Nasi"
    ],
    "name:ita_x_preferred":[
        "Nasi"
    ],
    "name:lat_x_preferred":[
        "Nasi"
    ],
    "name:nld_x_preferred":[
        "Nasi"
    ],
    "name:rus_x_preferred":[
        "\u041d\u0430\u0441\u0438"
    ],
    "name:spa_x_preferred":[
        "Nasi"
    ],
    "name:swe_x_preferred":[
        "Nasi"
    ],
    "wof:name":"Nasi",
    "wof:placetype":"locality"
},
  "geometry": {"coordinates":[13.36667,50.41667],"type":"Point"}
}