{
  "type": "Feature",
  "properties": {
    "gn:admin1_code":"86.0",
    "gn:admin2_code":"0531",
    "gn:asciiname":"Skala",
    "gn:country_code":"CZ",
    "gn:dem":368,
    "gn:feature_class":"P",
    "gn:feature_code":"PPL",
    "gn:name":"Sk\u00e1la",
    "gn:population":0,
    "gn:timezone":"Europe/Prague",
    "iso:country":"CZ",
    "wof:name":"Skala",
    "wof:placetype":"locality"
},
  "geometry": {"coordinates":[15.94891,49.86748],"type":"Point"}
}