{
  "type": "Feature",
  "properties": {
    "gn:admin1_code":"87.0",
    "gn:admin2_code":"0324",
    "gn:asciiname":"Maskrov",
    "gn:country_code":"CZ",
    "gn:dem":391,
    "gn:feature_class":"P",
    "gn:feature_code":"PPL",
    "gn:name":"Ma\u0161krov",
    "gn:population":0,
    "gn:timezone":"Europe/Prague",
    "iso:country":"CZ",
    "name:und_x_variant":[
        "Maschkrawen",
        "Ma\u0161krov"
    ],
    "wof:name":"Maskrov",
    "wof:placetype":"locality"
},
  "geometry": {"coordinates":[13.19684,49.6051],"type":"Point"}
}