{
  "type": "Feature",
  "properties": {
    "gn:gn_country":"CZ",
    "gn:gn_fcode":"PPL",
    "gn:gn_pop":131,
    "gn:population":131,
    "iso:country":"CZ",
    "name:cze_x_preferred":[
        "Chot\u011bnov"
    ],
    "name:dut_x_preferred":[
        "Chot\u011bnov"
    ],
    "name:eng_x_preferred":[
        "Chot\u011bnov"
    ],
    "name:epo_x_preferred":[
        "Chot\u011bnov"
    ],
    "name:fre_x_preferred":[
        "Chot\u011bnov"
    ],
    "name:hun_x_preferred":[
        "Chot\u011bnov"
    ],
    "name:ita_x_preferred":[
        "Chot\u011bnov"
    ],
    "name:may_x_preferred":[
        "Chot\u011bnov"
    ],
    "name:per_x_preferred":[
        "\u062e\u0648\u062a\u06cc\u0646\u0648\u0648"
    ],
    "name:pol_x_preferred":[
        "Chot\u011bnov"
    ],
    "name:por_x_preferred":[
        "Chot\u011bnov"
    ],
    "name:slo_x_preferred":[
        "Chot\u011bnov"
    ],
    "name:srp_x_preferred":[
        "\u0425\u043e\u0442\u0458\u0435\u043d\u043e\u0432"
    ],
    "name:swe_x_preferred":[
        "Chot\u011bnov"
    ],
    "name:vie_x_preferred":[
        "Chot\u011bnov"
    ],
    "qs_pg:aaroncc":"CZ",
    "qs_pg:gn_country":"CZ",
    "qs_pg:gn_fcode":"PPL",
    "qs_pg:gn_pop":131,
    "qs_pg:name":"Chot\u011bnov",
    "qs_pg:name_adm0":"\u010cesk\u00e1 republika",
    "qs_pg:name_adm1":"Pardubick\u00fd kraj",
    "qs_pg:photos_9r":0,
    "qs_pg:photos_sr":0,
    "qs_pg:pop_sr":1,
    "qs_pg:qs_pg_placetype":"locality",
    "qs_pg:qs_pg_placetype_gp":"Town",
    "qs_pg:woe_adm0":23424810,
    "woe:adm0_id":23424810,
    "woe:name_adm0":"\u010cesk\u00e1 republika",
    "woe:name_adm1":"Pardubick\u00fd kraj",
    "woe:placetype":"Town",
    "wof:name":"Chot\u011bnov",
    "wof:placetype":"locality",
    "wof:population":131
},
  "geometry": {"coordinates":[16.18987,49.82326],"type":"Point"}
}