{
  "type": "Feature",
  "properties": {
    "gn:country":"CZ",
    "gn:fcode":"PPL",
    "gn:population":180,
    "iso:country":"CZ",
    "name:azb_x_preferred":[
        "\u0628\u0627\u0648\u0648\u0631\u06cc\u0646\u06cc"
    ],
    "name:ceb_x_preferred":[
        "Bavoryn\u011b"
    ],
    "name:ces_x_preferred":[
        "Bavoryn\u011b"
    ],
    "name:deu_x_preferred":[
        "Bavoryn\u011b"
    ],
    "name:eng_x_preferred":[
        "Bavoryn\u011b"
    ],
    "name:eus_x_preferred":[
        "Bavoryn\u011b"
    ],
    "name:fas_x_preferred":[
        "\u0628\u0627\u0648\u0648\u0631\u06cc\u0646\u06cc"
    ],
    "name:fra_x_preferred":[
        "Bavoryn\u011b"
    ],
    "name:hun_x_preferred":[
        "Bavoryn\u011b"
    ],
    "name:ita_x_preferred":[
        "Bavoryn\u011b"
    ],
    "name:msa_x_preferred":[
        "Bavoryn\u011b"
    ],
    "name:nan_x_preferred":[
        "Bavoryn\u011b"
    ],
    "name:nld_x_preferred":[
        "Bavoryn\u011b"
    ],
    "name:oci_x_preferred":[
        "Bavoryn\u011b"
    ],
    "name:pol_x_preferred":[
        "Bavoryn\u011b"
    ],
    "name:por_x_preferred":[
        "Bavoryn\u011b"
    ],
    "name:rup_x_preferred":[
        "Bavoryn\u011b"
    ],
    "name:slk_x_preferred":[
        "Bavoryn\u011b"
    ],
    "name:spa_x_preferred":[
        "Bavoryn\u011b"
    ],
    "name:srp_x_preferred":[
        "\u0411\u0430\u0432\u043e\u0440\u0438\u045a\u0435"
    ],
    "name:swe_x_preferred":[
        "Bavoryn\u011b"
    ],
    "name:vie_x_preferred":[
        "Bavoryn\u011b"
    ],
    "qs_pg:aaroncc":"CZ",
    "qs_pg:gn_country":"CZ",
    "qs_pg:gn_fcode":"PPL",
    "qs_pg:gn_pop":180,
    "qs_pg:name":"Bavoryn\u011b",
    "qs_pg:name_adm0":"\u010cesk\u00e1 republika",
    "qs_pg:name_adm1":"St\u0159edo\u010desk\u00fd kraj",
    "qs_pg:photos_9r":0,
    "qs_pg:photos_sr":0,
    "qs_pg:pop_sr":1,
    "qs_pg:qs_pg_placetype":"locality",
    "qs_pg:qs_pg_placetype_gp":"Town",
    "qs_pg:woe_adm0":23424810,
    "woe:adm0_id":23424810,
    "woe:name_adm0":"\u010cesk\u00e1 republika",
    "woe:name_adm1":"St\u0159edo\u010desk\u00fd kraj",
    "woe:placetype":"Town",
    "wof:name":"Bavoryn\u011b",
    "wof:placetype":"locality",
    "wof:population":180
},
  "geometry": {"coordinates":[13.96102,49.8958],"type":"Point"}
}