{
  "type": "Feature",
  "properties": {
    "gn:gn_country":"CZ",
    "gn:gn_fcode":"PPL",
    "gn:gn_pop":0,
    "iso:country":"CZ",
    "name:ces_x_preferred":[
        "Josefov"
    ],
    "name:deu_x_preferred":[
        "Josefov"
    ],
    "name:eng_x_preferred":[
        "Josefov"
    ],
    "name:epo_x_preferred":[
        "Josefov"
    ],
    "name:fra_x_preferred":[
        "Josefov"
    ],
    "name:jpn_x_preferred":[
        "\u30e8\u30bc\u30d5\u30a9\u30d5"
    ],
    "name:nld_x_preferred":[
        "Fortress Josefov"
    ],
    "name:pol_x_preferred":[
        "Twierdza Josefov"
    ],
    "name:rus_x_preferred":[
        "\u042f\u0440\u043e\u043c\u0435\u0440\u0436"
    ],
    "name:unk_x_variant":[
        "Josefstadt"
    ],
    "name:zho_x_preferred":[
        "\u7d04\u745f\u592b\u5821"
    ],
    "qs_pg:aaroncc":"CZ",
    "qs_pg:gn_country":"CZ",
    "qs_pg:gn_fcode":"PPL",
    "qs_pg:gn_pop":0,
    "qs_pg:name":"Josefov",
    "qs_pg:name_adm0":"\u010cesk\u00e1 republika",
    "qs_pg:name_adm1":"Kr\u00e1lov\u00e9hradeck\u00fd kraj",
    "qs_pg:photos":748,
    "qs_pg:photos_1k":152,
    "qs_pg:photos_9k":3,
    "qs_pg:photos_9r":5,
    "qs_pg:photos_all":748,
    "qs_pg:photos_sr":8,
    "qs_pg:pop_sr":0,
    "qs_pg:qs_pg_placetype":"locality",
    "qs_pg:qs_pg_placetype_gp":"Town",
    "qs_pg:woe_adm0":23424810,
    "woe:adm0_id":23424810,
    "woe:name_adm0":"\u010cesk\u00e1 republika",
    "woe:name_adm1":"Kr\u00e1lov\u00e9hradeck\u00fd kraj",
    "woe:placetype":"Town",
    "wof:name":"Josefov",
    "wof:placetype":"locality"
},
  "geometry": {"coordinates":[15.93016,50.33905],"type":"Point"}
}