{
  "type": "Feature",
  "properties": {
    "gn:gn_country":"CZ",
    "gn:gn_fcode":"PPL",
    "gn:gn_pop":355,
    "gn:population":355,
    "iso:country":"CZ",
    "name:bul_x_preferred":[
        "\u0422\u0443\u0447\u043e\u0440\u0430\u0437"
    ],
    "name:ces_x_preferred":[
        "Tuchoraz"
    ],
    "name:deu_x_preferred":[
        "Tuchoraz"
    ],
    "name:eng_x_preferred":[
        "Tuchoraz"
    ],
    "name:fas_x_preferred":[
        "\u062a\u0648\u0686\u0631\u0632"
    ],
    "name:fra_x_preferred":[
        "Tuchoraz"
    ],
    "name:hun_x_preferred":[
        "Tuchoraz"
    ],
    "name:ita_x_preferred":[
        "Tuchoraz"
    ],
    "name:msa_x_preferred":[
        "Tuchoraz"
    ],
    "name:nan_x_preferred":[
        "Tuchoraz"
    ],
    "name:nld_x_preferred":[
        "Tuchoraz"
    ],
    "name:pol_x_preferred":[
        "Tuchoraz"
    ],
    "name:por_x_preferred":[
        "Tuchoraz"
    ],
    "name:rup_x_preferred":[
        "Tuchoraz"
    ],
    "name:slk_x_preferred":[
        "Tuchoraz"
    ],
    "name:srp_x_preferred":[
        "\u0422\u0443\u0445\u043e\u0440\u0430\u0437"
    ],
    "name:swe_x_preferred":[
        "Tuchoraz"
    ],
    "name:urd_x_preferred":[
        "\u062a\u0648\u0686\u0631\u0632"
    ],
    "name:vie_x_preferred":[
        "Tuchoraz"
    ],
    "qs_pg:aaroncc":"CZ",
    "qs_pg:gn_country":"CZ",
    "qs_pg:gn_fcode":"PPL",
    "qs_pg:gn_pop":355,
    "qs_pg:name":"Tuchoraz",
    "qs_pg:name_adm0":"\u010cesk\u00e1 republika",
    "qs_pg:name_adm1":"St\u0159edo\u010desk\u00fd kraj",
    "qs_pg:photos_9k":2,
    "qs_pg:photos_9r":5,
    "qs_pg:photos_all":372,
    "qs_pg:photos_sr":0,
    "qs_pg:pop_sr":2,
    "qs_pg:qs_pg_placetype":"locality",
    "qs_pg:qs_pg_placetype_gp":"Town",
    "qs_pg:woe_adm0":23424810,
    "woe:adm0_id":23424810,
    "woe:name_adm0":"\u010cesk\u00e1 republika",
    "woe:name_adm1":"St\u0159edo\u010desk\u00fd kraj",
    "woe:placetype":"Town",
    "wof:name":"Tuchoraz",
    "wof:placetype":"locality",
    "wof:population":355
},
  "geometry": {"coordinates":[14.8492,50.04862],"type":"Point"}
}