{
  "type": "Feature",
  "properties": {
    "gn:admin1_code":"87.0",
    "gn:admin2_code":"0321",
    "gn:asciiname":"Horni Metelsko",
    "gn:country_code":"CZ",
    "gn:dem":427,
    "gn:feature_class":"P",
    "gn:feature_code":"PPL",
    "gn:name":"Horn\u00ed Metelsko",
    "gn:population":0,
    "gn:timezone":"Europe/Prague",
    "iso:country":"CZ",
    "name:und_x_variant":[
        "Ober Medelzen",
        "Horn\u00ed Metelsko"
    ],
    "wof:name":"Horni Metelsko",
    "wof:placetype":"locality"
},
  "geometry": {"coordinates":[12.89333,49.56514],"type":"Point"}
}