{
  "type": "Feature",
  "properties": {
    "gn:admin1_code":"80",
    "gn:admin2_code":"0613",
    "gn:asciiname":"Vratisov",
    "gn:country_code":"CZ",
    "gn:dem":622,
    "gn:feature_class":"P",
    "gn:feature_code":"PPL",
    "gn:name":"Vrati\u0161ov",
    "gn:population":0,
    "gn:timezone":"Europe/Prague",
    "iso:country":"CZ",
    "wof:name":"Vratisov",
    "wof:placetype":"locality"
},
  "geometry": {"coordinates":[15.22531,49.36027],"type":"Point"}
}