{
  "type": "Feature",
  "properties": {
    "gn:admin1_code":"89",
    "gn:admin2_code":"0427",
    "gn:asciiname":"Stadice",
    "gn:country_code":"CZ",
    "gn:dem":156,
    "gn:feature_class":"P",
    "gn:feature_code":"PPL",
    "gn:name":"Stadice",
    "gn:population":0,
    "gn:timezone":"Europe/Prague",
    "iso:country":"CZ",
    "name:ces_x_preferred":[
        "Stadice"
    ],
    "name:deu_x_preferred":[
        "Staditz"
    ],
    "wof:name":"Stadice",
    "wof:placetype":"locality"
},
  "geometry": {"coordinates":[13.96687,50.61821],"type":"Point"}
}