{
  "type": "Feature",
  "properties": {
    "gn:admin1_code":"79.0",
    "gn:admin2_code":"0312",
    "gn:asciiname":"Dluhoste",
    "gn:country_code":"CZ",
    "gn:dem":608,
    "gn:feature_class":"P",
    "gn:feature_code":"PPL",
    "gn:name":"Dluho\u0161t\u011b",
    "gn:population":0,
    "gn:timezone":"Europe/Prague",
    "iso:country":"CZ",
    "name:und_x_variant":[
        "Ottenschlag",
        "Dluho\u0161t\u011b"
    ],
    "wof:name":"Dluhoste",
    "wof:placetype":"locality"
},
  "geometry": {"coordinates":[14.59257,48.73782],"type":"Point"}
}