{
  "type": "Feature",
  "properties": {
    "gn:admin1_code":"89.0",
    "gn:admin2_code":"0421",
    "gn:asciiname":"Kamenec",
    "gn:country_code":"CZ",
    "gn:dem":352,
    "gn:feature_class":"P",
    "gn:feature_code":"PPL",
    "gn:name":"Kamenec",
    "gn:population":0,
    "gn:timezone":"Europe/Prague",
    "iso:country":"CZ",
    "name:und_x_variant":[
        "Steinsdorf",
        "Kamenec"
    ],
    "wof:name":"Kamenec",
    "wof:placetype":"locality"
},
  "geometry": {"coordinates":[14.07299,50.76578],"type":"Point"}
}