{
  "type": "Feature",
  "properties": {
    "iso:country":"CZ",
    "name:cze_x_preferred":[
        "Hodolany"
    ],
    "name:cze_x_variant":[
        "Hodolein"
    ],
    "name:unk_x_variant":[
        "Hodolein",
        "Hodolany"
    ],
    "qs:gn_adm0_cc":"CZ",
    "qs:gn_fcode":"PPLX",
    "qs:gn_local":3069011,
    "qs:gn_nam_loc":"Olomouc, Olomouc, Olomouc, Olomouck\u00fd kraj, CZ",
    "qs:gn_namadm1":"84",
    "qs:gn_name":"Hodolany",
    "qs:local_max":2195,
    "qs:local_sum":3887,
    "qs:localhoods":9,
    "qs:name":"Hodolany",
    "qs:name_adm0":"\u010cesk\u00e1 republika",
    "qs:name_adm1":"Olomouck\u00fd kraj",
    "qs:name_adm2":"Olomouc",
    "qs:name_lau":"Olomouc",
    "qs:name_local":"Olomouc",
    "qs:photo_max":493,
    "qs:photo_sum":559,
    "qs:placetype":"Suburb",
    "qs:quad_count":12,
    "qs:woe_adm0":23424810,
    "qs:woe_adm1":20070470,
    "qs:woe_adm2":12582575,
    "qs:woe_lau":12607265,
    "qs:woe_local":795429,
    "qs:woe_ver":"7.10.0",
    "wof:lang":[
        "cze"
    ],
    "wof:name":"Hodolany",
    "wof:placetype":"neighbourhood"
},
  "geometry": {"coordinates":[17.279763,49.592018],"type":"Point"}
}