{
  "type": "Feature",
  "properties": {
    "gn:admin1_code":"88.0",
    "gn:admin2_code":"0201",
    "gn:asciiname":"Rousinov",
    "gn:country_code":"CZ",
    "gn:dem":478,
    "gn:feature_class":"P",
    "gn:feature_code":"PPL",
    "gn:name":"Rous\u00ednov",
    "gn:population":0,
    "gn:timezone":"Europe/Prague",
    "iso:country":"CZ",
    "name:und_x_variant":[
        "Rousinow",
        "Rous\u00ednov"
    ],
    "wof:name":"Rousinov",
    "wof:placetype":"locality"
},
  "geometry": {"coordinates":[14.81314,49.82358],"type":"Point"}
}