{
  "type": "Feature",
  "properties": {
    "gn:admin1_code":"82",
    "gn:admin2_code":"0525",
    "gn:asciiname":"Soberle",
    "gn:country_code":"CZ",
    "gn:dem":477,
    "gn:feature_class":"P",
    "gn:feature_code":"PPL",
    "gn:name":"Soberle",
    "gn:population":0,
    "gn:timezone":"Europe/Prague",
    "iso:country":"CZ",
    "name:und_x_variant":[
        "Z\u00e1bo\u0159\u00ed"
    ],
    "wof:name":"Soberle",
    "wof:placetype":"locality"
},
  "geometry": {"coordinates":[15.82841,50.48032],"type":"Point"}
}