{
  "type": "Feature",
  "properties": {
    "gn:admin1_code":"89",
    "gn:admin2_code":"0422",
    "gn:asciiname":"Zahorany",
    "gn:cc2":"CZ",
    "gn:country_code":"CZ",
    "gn:dem":294,
    "gn:feature_class":"P",
    "gn:feature_code":"PPL",
    "gn:name":"Zaho\u0159any",
    "gn:population":0,
    "gn:timezone":"Europe/Prague",
    "iso:country":"CZ",
    "name:und_x_variant":[
        "Sehrles"
    ],
    "wof:name":"Zahorany",
    "wof:placetype":"locality"
},
  "geometry": {"coordinates":[13.30959,50.31149],"type":"Point"}
}