{
  "type": "Feature",
  "properties": {
    "gn:admin1_code":"80.0",
    "gn:admin2_code":"0613",
    "gn:asciiname":"Mala Cerna",
    "gn:country_code":"CZ",
    "gn:dem":525,
    "gn:feature_class":"P",
    "gn:feature_code":"PPL",
    "gn:name":"Mal\u00e1 \u010cern\u00e1",
    "gn:population":0,
    "gn:timezone":"Europe/Prague",
    "iso:country":"CZ",
    "wof:name":"Mala Cerna",
    "wof:placetype":"locality"
},
  "geometry": {"coordinates":[14.97701,49.51549],"type":"Point"}
}