{
  "type": "Feature",
  "properties": {
    "gn:admin1_code":"88",
    "gn:admin2_code":"0201",
    "gn:asciiname":"Zadoli",
    "gn:country_code":"CZ",
    "gn:dem":418,
    "gn:feature_class":"P",
    "gn:feature_code":"PPL",
    "gn:name":"Z\u00e1dol\u00ed",
    "gn:population":0,
    "gn:timezone":"Europe/Prague",
    "iso:country":"CZ",
    "wof:name":"Zadoli",
    "wof:placetype":"locality"
},
  "geometry": {"coordinates":[14.51461,49.73532],"type":"Point"}
}