{
  "type": "Feature",
  "properties": {
    "gn:admin1_code":"83",
    "gn:admin2_code":"0514",
    "gn:asciiname":"Stepanovice",
    "gn:country_code":"CZ",
    "gn:dem":332,
    "gn:feature_class":"P",
    "gn:feature_code":"PPL",
    "gn:name":"\u0160t\u011bp\u00e1novice",
    "gn:population":0,
    "gn:timezone":"Europe/Prague",
    "iso:country":"CZ",
    "wof:name":"Stepanovice",
    "wof:placetype":"locality"
},
  "geometry": {"coordinates":[15.24203,50.54536],"type":"Point"}
}