{
  "type": "Feature",
  "properties": {
    "gn:admin1_code":"87.0",
    "gn:admin2_code":"0327",
    "gn:asciiname":"Milikov",
    "gn:country_code":"CZ",
    "gn:dem":386,
    "gn:feature_class":"P",
    "gn:feature_code":"PPL",
    "gn:name":"Mil\u00edkov",
    "gn:population":0,
    "gn:timezone":"Europe/Prague",
    "iso:country":"CZ",
    "name:und_x_variant":[
        "Milikau",
        "Mil\u00edkov"
    ],
    "wof:name":"Milikov",
    "wof:placetype":"locality"
},
  "geometry": {"coordinates":[12.93466,49.75071],"type":"Point"}
}