{
  "type": "Feature",
  "properties": {
    "gn:admin1_code":"84",
    "gn:admin2_code":"0715",
    "gn:asciiname":"Tremesek",
    "gn:cc2":"CZ",
    "gn:country_code":"CZ",
    "gn:dem":496,
    "gn:feature_class":"P",
    "gn:feature_code":"PPL",
    "gn:name":"T\u0159eme\u0161ek",
    "gn:population":0,
    "gn:timezone":"Europe/Prague",
    "iso:country":"CZ",
    "name:und_x_variant":[
        "Tschimischl"
    ],
    "wof:name":"Tremesek",
    "wof:placetype":"locality"
},
  "geometry": {"coordinates":[17.12142,49.91879],"type":"Point"}
}