{
  "type": "Feature",
  "properties": {
    "gn:admin1_code":"79",
    "gn:admin2_code":"0313",
    "gn:asciiname":"Urbanec",
    "gn:country_code":"CZ",
    "gn:dem":467,
    "gn:feature_class":"P",
    "gn:feature_code":"PPL",
    "gn:name":"Urbane\u010d",
    "gn:population":0,
    "gn:timezone":"Europe/Prague",
    "iso:country":"CZ",
    "wof:name":"Urbanec",
    "wof:placetype":"locality"
},
  "geometry": {"coordinates":[15.41568,49.05405],"type":"Point"}
}