{
  "type": "Feature",
  "properties": {
    "gn:admin1_code":"89",
    "gn:admin2_code":"0424",
    "gn:asciiname":"Strojetice",
    "gn:country_code":"CZ",
    "gn:dem":373,
    "gn:feature_class":"P",
    "gn:feature_code":"PPL",
    "gn:name":"Strojetice",
    "gn:population":0,
    "gn:timezone":"Europe/Prague",
    "iso:country":"CZ",
    "name:azb_x_preferred":[
        "\u0633\u062a\u0631\u0648\u06cc\u062a\u06cc\u062a\u0633\u0647"
    ],
    "name:ceb_x_preferred":[
        "Strojetice"
    ],
    "name:ces_x_preferred":[
        "Strojetice"
    ],
    "name:eus_x_preferred":[
        "Strojetice"
    ],
    "name:fas_x_preferred":[
        "\u0633\u062a\u0631\u0648\u06cc\u062a\u06cc\u062a\u0633\u0647"
    ],
    "name:fra_x_preferred":[
        "Strojetice"
    ],
    "name:hun_x_preferred":[
        "Strojetice"
    ],
    "name:ita_x_preferred":[
        "Strojetice"
    ],
    "name:msa_x_preferred":[
        "Strojetice"
    ],
    "name:nld_x_preferred":[
        "Strojetice"
    ],
    "name:oci_x_preferred":[
        "Strojetice"
    ],
    "name:pol_x_preferred":[
        "Strojetice"
    ],
    "name:por_x_preferred":[
        "Strojetice"
    ],
    "name:slk_x_preferred":[
        "Strojetice"
    ],
    "name:spa_x_preferred":[
        "Strojetice"
    ],
    "name:srp_x_preferred":[
        "\u0421\u0442\u0440\u043e\u0458\u0435\u0442\u0438\u0446\u0435"
    ],
    "name:swe_x_preferred":[
        "Strojetice"
    ],
    "name:vie_x_preferred":[
        "Strojetice"
    ],
    "wof:name":"Strojetice",
    "wof:placetype":"locality"
},
  "geometry": {"coordinates":[13.47937,50.17382],"type":"Point"}
}