{
  "type": "Feature",
  "properties": {
    "gn:admin1_code":"89",
    "gn:admin2_code":"0424",
    "gn:asciiname":"Strojetice",
    "gn:country_code":"CZ",
    "gn:dem":373,
    "gn:feature_class":"P",
    "gn:feature_code":"PPL",
    "gn:name":"Strojetice",
    "gn:population":0,
    "gn:timezone":"Europe/Prague",
    "iso:country":"CZ",
    "wof:name":"Strojetice",
    "wof:placetype":"locality"
},
  "geometry": {"coordinates":[13.47937,50.17382],"type":"Point"}
}