{
  "type": "Feature",
  "properties": {
    "gn:admin1_code":"82.0",
    "gn:admin2_code":"0521",
    "gn:asciiname":"Nerosov",
    "gn:country_code":"CZ",
    "gn:dem":254,
    "gn:feature_class":"P",
    "gn:feature_code":"PPL",
    "gn:name":"Nero\u0161ov",
    "gn:population":0,
    "gn:timezone":"Europe/Prague",
    "iso:country":"CZ",
    "wof:name":"Nerosov",
    "wof:placetype":"locality"
},
  "geometry": {"coordinates":[15.63063,50.28135],"type":"Point"}
}