{
  "type": "Feature",
  "properties": {
    "gn:admin1_code":"78.0",
    "gn:admin2_code":"0623",
    "gn:asciiname":"Jilmovi",
    "gn:country_code":"CZ",
    "gn:dem":468,
    "gn:feature_class":"P",
    "gn:feature_code":"PPL",
    "gn:name":"Jilmov\u00ed",
    "gn:population":0,
    "gn:timezone":"Europe/Prague",
    "iso:country":"CZ",
    "wof:name":"Jilmovi",
    "wof:placetype":"locality"
},
  "geometry": {"coordinates":[16.3219,49.39429000000001],"type":"Point"}
}