{
  "type": "Feature",
  "properties": {
    "gn:gn_country":"CZ",
    "gn:gn_fcode":"PPL",
    "gn:gn_pop":436,
    "gn:population":436,
    "iso:country":"CZ",
    "name:ces_x_preferred":[
        "Vit\u011bjovice"
    ],
    "name:deu_x_preferred":[
        "Vit\u011bjovice"
    ],
    "name:eng_x_preferred":[
        "Vit\u011bjovice"
    ],
    "name:fas_x_preferred":[
        "\u0648\u06cc\u062a\u06cc\u06cc\u0648\u0648\u06cc\u062a\u0633\u0647"
    ],
    "name:fra_x_preferred":[
        "Vit\u011bjovice"
    ],
    "name:hun_x_preferred":[
        "Vit\u011bjovice"
    ],
    "name:ita_x_preferred":[
        "Vit\u011bjovice"
    ],
    "name:msa_x_preferred":[
        "Vit\u011bjovice"
    ],
    "name:nld_x_preferred":[
        "Vit\u011bjovice"
    ],
    "name:por_x_preferred":[
        "Vit\u011bjovice"
    ],
    "name:rup_x_preferred":[
        "Vit\u011bjovice"
    ],
    "name:slk_x_preferred":[
        "Vit\u011bjovice"
    ],
    "name:srp_x_preferred":[
        "\u0412\u0438\u0442\u0458\u0435\u0458\u043e\u0432\u0438\u0446\u0435"
    ],
    "name:swe_x_preferred":[
        "Vit\u011bjovice"
    ],
    "name:unk_x_variant":[
        "Wit\u011bjitz"
    ],
    "name:vie_x_preferred":[
        "Vit\u011bjovice"
    ],
    "qs_pg:aaroncc":"CZ",
    "qs_pg:gn_country":"CZ",
    "qs_pg:gn_fcode":"PPL",
    "qs_pg:gn_pop":436,
    "qs_pg:name":"Vit\u011bjovice",
    "qs_pg:name_adm0":"\u010cesk\u00e1 republika",
    "qs_pg:name_adm1":"Jiho\u010desk\u00fd kraj",
    "qs_pg:photos_9k":1,
    "qs_pg:photos_9r":1,
    "qs_pg:photos_all":6,
    "qs_pg:photos_sr":0,
    "qs_pg:pop_sr":2,
    "qs_pg:qs_pg_placetype":"locality",
    "qs_pg:qs_pg_placetype_gp":"Town",
    "qs_pg:woe_adm0":23424810,
    "woe:adm0_id":23424810,
    "woe:name_adm0":"\u010cesk\u00e1 republika",
    "woe:name_adm1":"Jiho\u010desk\u00fd kraj",
    "woe:placetype":"Town",
    "wof:name":"Vit\u011bjovice",
    "wof:placetype":"locality",
    "wof:population":436
},
  "geometry": {"coordinates":[14.07337,49.04639],"type":"Point"}
}