{
  "type": "Feature",
  "properties": {
    "iso:country":"CZ",
    "name:ceb_x_preferred":[
        "L\u00e1zn\u011b Libverda"
    ],
    "name:ces_x_preferred":[
        "L\u00e1zn\u011b Libverda"
    ],
    "name:deu_x_preferred":[
        "L\u00e1zn\u011b Libverda"
    ],
    "name:eus_x_preferred":[
        "L\u00e1zn\u011b Libverda"
    ],
    "name:fra_x_preferred":[
        "L\u00e1zn\u011b Libverda"
    ],
    "name:hun_x_preferred":[
        "L\u00e1zn\u011b Libverda"
    ],
    "name:ita_x_preferred":[
        "L\u00e1zn\u011b Libverda"
    ],
    "name:msa_x_preferred":[
        "L\u00e1zn\u011b Libverda"
    ],
    "name:nld_x_preferred":[
        "L\u00e1zn\u011b Libverda"
    ],
    "name:pol_x_preferred":[
        "L\u00e1zn\u011b Libverda"
    ],
    "name:por_x_preferred":[
        "L\u00e1zn\u011b Libverda"
    ],
    "name:slk_x_preferred":[
        "L\u00e1zn\u011b Libverda"
    ],
    "name:spa_x_preferred":[
        "L\u00e1zn\u011b Libverda"
    ],
    "name:srp_x_preferred":[
        "\u041b\u0430\u0437\u045a\u0435 \u041b\u0438\u0431\u0432\u0435\u0440\u0434\u0430"
    ],
    "name:swe_x_preferred":[
        "L\u00e1zn\u011b Libverda"
    ],
    "name:vie_x_preferred":[
        "L\u00e1zn\u011b Libverda"
    ],
    "qs_pg:aaroncc":"CZ",
    "qs_pg:name":"L\u00e1zn\u011b Libverda",
    "qs_pg:name_adm0":"\u010cesk\u00e1 republika",
    "qs_pg:name_adm1":"Libereck\u00fd kraj",
    "qs_pg:photos":12,
    "qs_pg:photos_1k":2,
    "qs_pg:photos_9k":1,
    "qs_pg:photos_9r":1,
    "qs_pg:photos_all":12,
    "qs_pg:photos_sr":1,
    "qs_pg:pop_sr":0,
    "qs_pg:qs_pg_placetype":"localadmin",
    "qs_pg:qs_pg_placetype_gp":"LocalAdmin",
    "qs_pg:woe_adm0":23424810,
    "woe:adm0_id":23424810,
    "woe:name_adm0":"\u010cesk\u00e1 republika",
    "woe:name_adm1":"Libereck\u00fd kraj",
    "woe:placetype":"LocalAdmin",
    "wof:name":"L\u00e1zn\u011b Libverda",
    "wof:placetype":"localadmin"
},
  "geometry": {"coordinates":[15.190916,50.891055],"type":"Point"}
}