{
  "type": "Feature",
  "properties": {
    "gn:admin1_code":"82",
    "gn:admin2_code":"0522",
    "gn:asciiname":"Zahuby",
    "gn:country_code":"CZ",
    "gn:dem":318,
    "gn:feature_class":"P",
    "gn:feature_code":"PPL",
    "gn:name":"Z\u00e1huby",
    "gn:population":0,
    "gn:timezone":"Europe/Prague",
    "iso:country":"CZ",
    "wof:name":"Zahuby",
    "wof:placetype":"locality"
},
  "geometry": {"coordinates":[15.17028,50.39742],"type":"Point"}
}