{
  "type": "Feature",
  "properties": {
    "gn:admin1_code":"89.0",
    "gn:admin2_code":"0424",
    "gn:asciiname":"Drahomysl",
    "gn:country_code":"CZ",
    "gn:dem":228,
    "gn:feature_class":"P",
    "gn:feature_code":"PPL",
    "gn:name":"Drahomy\u0161l",
    "gn:population":0,
    "gn:timezone":"Europe/Prague",
    "iso:country":"CZ",
    "wof:name":"Drahomysl",
    "wof:placetype":"locality"
},
  "geometry": {"coordinates":[13.64708,50.30919],"type":"Point"}
}