{
  "type": "Feature",
  "properties": {
    "gn:admin1_code":"86",
    "gn:admin2_code":"0531",
    "gn:asciiname":"Studena Voda",
    "gn:country_code":"CZ",
    "gn:dem":317,
    "gn:feature_class":"P",
    "gn:feature_code":"PPL",
    "gn:name":"Studen\u00e1 Voda",
    "gn:population":0,
    "gn:timezone":"Europe/Prague",
    "iso:country":"CZ",
    "wof:name":"Studena Voda",
    "wof:placetype":"locality"
},
  "geometry": {"coordinates":[15.88333,49.88293],"type":"Point"}
}