{
  "type": "Feature",
  "properties": {
    "gn:gn_country":"CZ",
    "gn:gn_fcode":"PPL",
    "gn:gn_pop":680,
    "gn:population":680,
    "iso:country":"CZ",
    "name:cze_x_preferred":[
        "Chval\u00edkovice"
    ],
    "name:dut_x_preferred":[
        "Chval\u00edkovice"
    ],
    "name:eng_x_preferred":[
        "Chval\u00edkovice"
    ],
    "name:epo_x_preferred":[
        "Chval\u00edkovice"
    ],
    "name:fre_x_preferred":[
        "Chval\u00edkovice"
    ],
    "name:hun_x_preferred":[
        "Chval\u00edkovice"
    ],
    "name:ita_x_preferred":[
        "Chval\u00edkovice"
    ],
    "name:may_x_preferred":[
        "Chval\u00edkovice"
    ],
    "name:pol_x_preferred":[
        "Chval\u00edkovice"
    ],
    "name:por_x_preferred":[
        "Chval\u00edkovice"
    ],
    "name:rup_x_preferred":[
        "Chval\u00edkovice"
    ],
    "name:slo_x_preferred":[
        "Chval\u00edkovice"
    ],
    "name:srp_x_preferred":[
        "\u0425\u0432\u0430\u043b\u0438\u043a\u043e\u0432\u0438\u0446\u0435"
    ],
    "name:swe_x_preferred":[
        "Chval\u00edkovice"
    ],
    "name:vie_x_preferred":[
        "Chval\u00edkovice"
    ],
    "qs_pg:aaroncc":"CZ",
    "qs_pg:gn_country":"CZ",
    "qs_pg:gn_fcode":"PPL",
    "qs_pg:gn_pop":680,
    "qs_pg:name":"Chval\u00edkovice",
    "qs_pg:name_adm0":"\u010cesk\u00e1 republika",
    "qs_pg:name_adm1":"Moravskoslezsk\u00fd kraj",
    "qs_pg:photos_9r":0,
    "qs_pg:photos_sr":0,
    "qs_pg:pop_sr":2,
    "qs_pg:qs_pg_placetype":"locality",
    "qs_pg:qs_pg_placetype_gp":"Town",
    "qs_pg:woe_adm0":23424810,
    "woe:adm0_id":23424810,
    "woe:name_adm0":"\u010cesk\u00e1 republika",
    "woe:name_adm1":"Moravskoslezsk\u00fd kraj",
    "woe:placetype":"Town",
    "wof:name":"Chval\u00edkovice",
    "wof:placetype":"locality",
    "wof:population":680
},
  "geometry": {"coordinates":[17.91095,49.88564],"type":"Point"}
}