{
  "type": "Feature",
  "properties": {
    "gn:admin1_code":"80.0",
    "gn:admin2_code":"0611",
    "gn:asciiname":"Dobrohostov",
    "gn:country_code":"CZ",
    "gn:dem":542,
    "gn:feature_class":"P",
    "gn:feature_code":"PPL",
    "gn:name":"Dobrohostov",
    "gn:population":0,
    "gn:timezone":"Europe/Prague",
    "iso:country":"CZ",
    "wof:name":"Dobrohostov",
    "wof:placetype":"locality"
},
  "geometry": {"coordinates":[15.51408,49.53925],"type":"Point"}
}