{
  "type": "Feature",
  "properties": {
    "gn:gn_country":"CZ",
    "gn:gn_fcode":"PPL",
    "gn:gn_pop":385,
    "gn:population":385,
    "iso:country":"CZ",
    "name:cze_x_preferred":[
        "Ostr\u00e1"
    ],
    "name:dut_x_preferred":[
        "Ostr\u00e1"
    ],
    "name:eng_x_preferred":[
        "Ostr\u00e1"
    ],
    "name:fre_x_preferred":[
        "Ostr\u00e1"
    ],
    "name:ger_x_preferred":[
        "Ostr\u00e1"
    ],
    "name:hun_x_preferred":[
        "Ostr\u00e1"
    ],
    "name:ita_x_preferred":[
        "Ostr\u00e1"
    ],
    "name:may_x_preferred":[
        "Ostr\u00e1"
    ],
    "name:per_x_preferred":[
        "\u0627\u0648\u0633\u062a\u0631\u0627"
    ],
    "name:pol_x_preferred":[
        "Ostr\u00e1"
    ],
    "name:por_x_preferred":[
        "Ostr\u00e1"
    ],
    "name:slo_x_preferred":[
        "Ostr\u00e1"
    ],
    "name:srp_x_preferred":[
        "\u041e\u0441\u0442\u0440\u0430"
    ],
    "name:swe_x_preferred":[
        "Ostr\u00e1"
    ],
    "name:vie_x_preferred":[
        "Ostr\u00e1"
    ],
    "qs_pg:aaroncc":"CZ",
    "qs_pg:gn_country":"CZ",
    "qs_pg:gn_fcode":"PPL",
    "qs_pg:gn_pop":385,
    "qs_pg:name":"Ostr\u00e1",
    "qs_pg:name_adm0":"\u010cesk\u00e1 republika",
    "qs_pg:name_adm1":"St\u0159edo\u010desk\u00fd kraj",
    "qs_pg:photos_9k":2,
    "qs_pg:photos_9r":5,
    "qs_pg:photos_all":373,
    "qs_pg:photos_sr":0,
    "qs_pg:pop_sr":2,
    "qs_pg:qs_pg_placetype":"locality",
    "qs_pg:qs_pg_placetype_gp":"Town",
    "qs_pg:woe_adm0":23424810,
    "woe:adm0_id":23424810,
    "woe:name_adm0":"\u010cesk\u00e1 republika",
    "woe:name_adm1":"St\u0159edo\u010desk\u00fd kraj",
    "woe:placetype":"Town",
    "wof:name":"Ostr\u00e1",
    "wof:placetype":"locality",
    "wof:population":385
},
  "geometry": {"coordinates":[14.8929,50.18044],"type":"Point"}
}