{
  "type": "Feature",
  "properties": {
    "iso:country":"CZ",
    "name:ceb_x_preferred":[
        "Gro\u00dfer Garten"
    ],
    "name:deu_x_colloquial":[
        "Grosser Garten"
    ],
    "name:deu_x_preferred":[
        "Gro\u00dfer Garten"
    ],
    "name:deu_x_variant":[
        "Gro\u00dfergarten"
    ],
    "name:nld_x_preferred":[
        "Gro\u00dfer Garten"
    ],
    "name:nor_x_preferred":[
        "Grosser Garten"
    ],
    "name:pol_x_preferred":[
        "Gro\u00dfer Garten"
    ],
    "name:spa_x_preferred":[
        "Gro\u00dfer Garten"
    ],
    "name:und_x_variant":[
        "Pfaffendorf"
    ],
    "qs:gn_fcode":"PPL",
    "qs:gn_local":0,
    "qs:gn_namadm1":"00",
    "qs:gn_name":"Popovice",
    "qs:local_max":13108,
    "qs:local_sum":52556,
    "qs:localhoods":61,
    "qs:name":"Gro\u00dfer Garten",
    "qs:name_adm0":"Deutschland",
    "qs:name_adm1":"Sachsen",
    "qs:name_adm2":"Kreisfreie Stadt Dresden",
    "qs:name_lau":"Seevorstadt-Ost/Gro\u00dfer Garten",
    "qs:name_local":"Dresden",
    "qs:photo_max":286,
    "qs:photo_sum":2981,
    "qs:placetype":"Suburb",
    "qs:quad_count":73,
    "qs:woe_adm0":23424829,
    "qs:woe_adm1":2345493,
    "qs:woe_adm2":12596943,
    "qs:woe_lau":26822154,
    "qs:woe_local":645686,
    "qs:woe_ver":"7.10.0",
    "wof:lang":[
        "ger"
    ],
    "wof:name":"Gro\u00dfer Garten",
    "wof:placetype":"neighbourhood"
},
  "geometry": {"coordinates":[13.761707,51.037489],"type":"Point"}
}