{
  "type": "Feature",
  "properties": {
    "gn:admin1_code":"79.0",
    "gn:admin2_code":"0313",
    "gn:asciiname":"Mutna",
    "gn:country_code":"CZ",
    "gn:dem":472,
    "gn:feature_class":"P",
    "gn:feature_code":"PPL",
    "gn:name":"Mutn\u00e1",
    "gn:population":0,
    "gn:timezone":"Europe/Prague",
    "iso:country":"CZ",
    "name:und_x_variant":[
        "Mutten",
        "Mutn\u00e1"
    ],
    "wof:name":"Mutna",
    "wof:placetype":"locality"
},
  "geometry": {"coordinates":[15.40411,49.01644],"type":"Point"}
}