{
  "type": "Feature",
  "properties": {
    "gn:admin1_code":"87",
    "gn:admin2_code":"0322",
    "gn:asciiname":"Stribrne Hory",
    "gn:country_code":"CZ",
    "gn:dem":521,
    "gn:feature_class":"P",
    "gn:feature_code":"PPL",
    "gn:name":"St\u0159\u00edbrn\u00e9 Hory",
    "gn:population":0,
    "gn:timezone":"Europe/Prague",
    "iso:country":"CZ",
    "name:und_x_variant":[
        "Silberberg",
        "St\u0159\u00edbrn\u00e9 Hory"
    ],
    "wof:name":"Stribrne Hory",
    "wof:placetype":"locality"
},
  "geometry": {"coordinates":[13.54481,49.33097],"type":"Point"}
}