{
  "type": "Feature",
  "properties": {
    "gn:admin1_code":"83.0",
    "gn:admin2_code":"0514",
    "gn:asciiname":"Krecovice",
    "gn:country_code":"CZ",
    "gn:dem":342,
    "gn:feature_class":"P",
    "gn:feature_code":"PPL",
    "gn:name":"K\u0159e\u010dovice",
    "gn:population":0,
    "gn:timezone":"Europe/Prague",
    "iso:country":"CZ",
    "wof:name":"Krecovice",
    "wof:placetype":"locality"
},
  "geometry": {"coordinates":[15.28717,50.54822],"type":"Point"}
}