{
  "type": "Feature",
  "properties": {
    "gn:gn_country":"CZ",
    "gn:gn_fcode":"PPL",
    "gn:gn_pop":0,
    "iso:country":"CZ",
    "name:ces_x_preferred":[
        "Z\u00e1lu\u017e\u00ed"
    ],
    "name:deu_x_preferred":[
        "Z\u00e1lu\u017e\u00ed"
    ],
    "name:fra_x_preferred":[
        "Z\u00e1lu\u017e\u00ed"
    ],
    "name:ita_x_preferred":[
        "Z\u00e1lu\u017e\u00ed"
    ],
    "name:nld_x_preferred":[
        "Z\u00e1lu\u017e\u00ed"
    ],
    "name:pol_x_preferred":[
        "Z\u00e1lu\u017e\u00ed"
    ],
    "name:slk_x_preferred":[
        "Z\u00e1lu\u017e\u00ed"
    ],
    "name:srp_x_preferred":[
        "\u0417\u0430\u043b\u0443\u0436\u0438"
    ],
    "qs_pg:aaroncc":"CZ",
    "qs_pg:gn_country":"CZ",
    "qs_pg:gn_fcode":"PPL",
    "qs_pg:gn_pop":0,
    "qs_pg:name":"Z\u00e1lu\u017e\u00ed",
    "qs_pg:name_adm0":"\u010cesk\u00e1 republika",
    "qs_pg:name_adm1":"Jiho\u010desk\u00fd kraj",
    "qs_pg:photos_9r":0,
    "qs_pg:photos_sr":0,
    "qs_pg:pop_sr":0,
    "qs_pg:qs_pg_placetype":"locality",
    "qs_pg:qs_pg_placetype_gp":"Town",
    "qs_pg:woe_adm0":23424810,
    "woe:adm0_id":23424810,
    "woe:name_adm0":"\u010cesk\u00e1 republika",
    "woe:name_adm1":"Jiho\u010desk\u00fd kraj",
    "woe:placetype":"Town",
    "wof:name":"Z\u00e1lu\u017e\u00ed",
    "wof:placetype":"locality"
},
  "geometry": {"coordinates":[14.38061,48.87508],"type":"Point"}
}