{
  "type": "Feature",
  "properties": {
    "gn:admin1_code":"88.0",
    "gn:admin2_code":"020A",
    "gn:asciiname":"Knezivka",
    "gn:country_code":"CZ",
    "gn:dem":286,
    "gn:feature_class":"P",
    "gn:feature_code":"PPL",
    "gn:name":"Kn\u011b\u017e\u00edvka",
    "gn:population":0,
    "gn:timezone":"Europe/Prague",
    "iso:country":"CZ",
    "wof:name":"Knezivka",
    "wof:placetype":"locality"
},
  "geometry": {"coordinates":[14.28333,50.13333],"type":"Point"}
}