{
  "type": "Feature",
  "properties": {
    "gn:admin1_code":"89",
    "gn:admin2_code":"0423",
    "gn:asciiname":"Tepla",
    "gn:cc2":"CZ",
    "gn:country_code":"CZ",
    "gn:dem":267,
    "gn:feature_class":"P",
    "gn:feature_code":"PPL",
    "gn:name":"Tepl\u00e1",
    "gn:population":0,
    "gn:timezone":"Europe/Prague",
    "iso:country":"CZ",
    "name:und_x_variant":[
        "Tepley"
    ],
    "wof:name":"Tepla",
    "wof:placetype":"locality"
},
  "geometry": {"coordinates":[13.96585,50.4893],"type":"Point"}
}