{
  "type": "Feature",
  "properties": {
    "gn:admin1_code":"89.0",
    "gn:admin2_code":"0422",
    "gn:asciiname":"Brodce",
    "gn:cc2":"CZ",
    "gn:country_code":"CZ",
    "gn:dem":401,
    "gn:feature_class":"P",
    "gn:feature_code":"PPL",
    "gn:name":"Brodce",
    "gn:population":0,
    "gn:timezone":"Europe/Prague",
    "iso:country":"CZ",
    "name:und_x_variant":[
        "Pr\u00f6dlas"
    ],
    "wof:name":"Brodce",
    "wof:placetype":"locality"
},
  "geometry": {"coordinates":[13.23063,50.35072],"type":"Point"}
}