{
  "type": "Feature",
  "properties": {
    "gn:admin1_code":"89.0",
    "gn:admin2_code":"0422",
    "gn:asciiname":"Brodce",
    "gn:cc2":"CZ",
    "gn:country_code":"CZ",
    "gn:dem":401,
    "gn:feature_class":"P",
    "gn:feature_code":"PPL",
    "gn:name":"Brodce",
    "gn:population":0,
    "gn:timezone":"Europe/Prague",
    "iso:country":"CZ",
    "name:azb_x_preferred":[
        "\u0628\u0631\u0648\u062f\u062a\u0633\u0647"
    ],
    "name:ceb_x_preferred":[
        "Brodce"
    ],
    "name:ces_x_preferred":[
        "Brodce"
    ],
    "name:eus_x_preferred":[
        "Brodce"
    ],
    "name:fas_x_preferred":[
        "\u0628\u0631\u0648\u062f\u062a\u0633\u0647"
    ],
    "name:fra_x_preferred":[
        "Brodce"
    ],
    "name:hun_x_preferred":[
        "Brodce"
    ],
    "name:ita_x_preferred":[
        "Brodce"
    ],
    "name:msa_x_preferred":[
        "Brodce"
    ],
    "name:nld_x_preferred":[
        "Brodce"
    ],
    "name:pol_x_preferred":[
        "Brodce"
    ],
    "name:por_x_preferred":[
        "Brodce"
    ],
    "name:slk_x_preferred":[
        "Brodce"
    ],
    "name:spa_x_preferred":[
        "Brodce"
    ],
    "name:srp_x_preferred":[
        "\u0411\u0440\u043e\u0434\u0446\u0435"
    ],
    "name:swe_x_preferred":[
        "Brodce"
    ],
    "name:und_x_variant":[
        "Pr\u00f6dlas"
    ],
    "name:vie_x_preferred":[
        "Brodce"
    ],
    "wof:name":"Brodce",
    "wof:placetype":"locality"
},
  "geometry": {"coordinates":[13.23063,50.35072],"type":"Point"}
}