{
  "type": "Feature",
  "properties": {
    "gn:admin1_code":"83",
    "gn:admin2_code":"0514",
    "gn:asciiname":"Studena",
    "gn:country_code":"CZ",
    "gn:dem":783,
    "gn:feature_class":"P",
    "gn:feature_code":"PPL",
    "gn:name":"Studen\u00e1",
    "gn:population":0,
    "gn:timezone":"Europe/Prague",
    "iso:country":"CZ",
    "name:bos_x_preferred":[
        "Studena"
    ],
    "name:ceb_x_preferred":[
        "Studena"
    ],
    "name:eus_x_preferred":[
        "Studena"
    ],
    "name:fra_x_preferred":[
        "Studena"
    ],
    "name:hrv_x_preferred":[
        "Studena"
    ],
    "name:slv_x_preferred":[
        "Studena"
    ],
    "name:swe_x_preferred":[
        "Studena"
    ],
    "name:und_x_variant":[
        "Kaltenberg",
        "Studen\u00e1"
    ],
    "wof:name":"Studena",
    "wof:placetype":"locality"
},
  "geometry": {"coordinates":[15.44887,50.743],"type":"Point"}
}