{
  "type": "Feature",
  "properties": {
    "gn:admin1_code":"87.0",
    "gn:admin2_code":"0325",
    "gn:asciiname":"Lukova",
    "gn:country_code":"CZ",
    "gn:dem":506,
    "gn:feature_class":"P",
    "gn:feature_code":"PPL",
    "gn:name":"Lukov\u00e1",
    "gn:population":0,
    "gn:timezone":"Europe/Prague",
    "iso:country":"CZ",
    "wof:name":"Lukova",
    "wof:placetype":"locality"
},
  "geometry": {"coordinates":[13.1599,50.01623],"type":"Point"}
}