{
  "type": "Feature",
  "properties": {
    "gn:country":"CZ",
    "gn:fcode":"PPL",
    "gn:population":23,
    "iso:country":"CZ",
    "name:cat_x_preferred":[
        "Vesec"
    ],
    "name:ceb_x_preferred":[
        "Vesec"
    ],
    "name:ces_x_preferred":[
        "Liberec XXV-Vesec"
    ],
    "name:deu_x_preferred":[
        "Vesec"
    ],
    "name:eng_x_preferred":[
        "Vesec"
    ],
    "name:fra_x_preferred":[
        "Liberec XXV-Vesec"
    ],
    "name:fra_x_variant":[
        "Vesec"
    ],
    "name:pol_x_preferred":[
        "Vesec"
    ],
    "name:swe_x_preferred":[
        "Vesec"
    ],
    "qs_pg:aaroncc":"CZ",
    "qs_pg:gn_country":"CZ",
    "qs_pg:gn_fcode":"PPL",
    "qs_pg:gn_pop":23,
    "qs_pg:name":"Vesec",
    "qs_pg:photos_9r":0,
    "qs_pg:photos_sr":0,
    "qs_pg:pop_sr":1,
    "qs_pg:qs_pg_placetype":"locality",
    "wof:name":"Vesec",
    "wof:placetype":"locality",
    "wof:population":23
},
  "geometry": {"coordinates":[15.15551,50.48093],"type":"Point"}
}