{
  "type": "Feature",
  "properties": {
    "gn:admin1_code":"81.0",
    "gn:admin2_code":"0413",
    "gn:asciiname":"Novina",
    "gn:country_code":"CZ",
    "gn:dem":618,
    "gn:feature_class":"P",
    "gn:feature_code":"PPL",
    "gn:name":"Novina",
    "gn:population":0,
    "gn:timezone":"Europe/Prague",
    "iso:country":"CZ",
    "name:und_x_variant":[
        "Gr\u00fcn",
        "Novina"
    ],
    "wof:name":"Novina",
    "wof:placetype":"locality"
},
  "geometry": {"coordinates":[12.67876,50.14886],"type":"Point"}
}