{
  "type": "Feature",
  "properties": {
    "gn:admin1_code":"88.0",
    "gn:admin2_code":"0206",
    "gn:asciiname":"Krivenice",
    "gn:country_code":"CZ",
    "gn:dem":162,
    "gn:feature_class":"P",
    "gn:feature_code":"PPL",
    "gn:name":"K\u0159ivenice",
    "gn:population":0,
    "gn:timezone":"Europe/Prague",
    "iso:country":"CZ",
    "name:und_x_variant":[
        "K\u0159wenitz",
        "K\u0159ivenice"
    ],
    "wof:name":"Krivenice",
    "wof:placetype":"locality"
},
  "geometry": {"coordinates":[14.43058,50.40936],"type":"Point"}
}