{
  "type": "Feature",
  "properties": {
    "gn:country":"CZ",
    "gn:fcode":"PPL",
    "gn:population":131,
    "iso:country":"CZ",
    "name:azb_x_preferred":[
        "\u0631\u0648\u0648\u0628\u0627\u0646\u06cc\u0646\u0627"
    ],
    "name:bul_x_preferred":[
        "\u0420\u043e\u0443\u0431\u0430\u043d\u0438\u043d\u0430"
    ],
    "name:ceb_x_preferred":[
        "Roubanina"
    ],
    "name:ces_x_preferred":[
        "Roubanina"
    ],
    "name:deu_x_preferred":[
        "Roubanina"
    ],
    "name:eng_x_preferred":[
        "Roubanina"
    ],
    "name:eus_x_preferred":[
        "Roubanina"
    ],
    "name:fas_x_preferred":[
        "\u0631\u0648\u0648\u0628\u0627\u0646\u06cc\u0646\u0627"
    ],
    "name:fra_x_preferred":[
        "Roubanina"
    ],
    "name:hun_x_preferred":[
        "Roubanina"
    ],
    "name:ita_x_preferred":[
        "Roubanina"
    ],
    "name:msa_x_preferred":[
        "Roubanina"
    ],
    "name:nan_x_preferred":[
        "Roubanina"
    ],
    "name:nld_x_preferred":[
        "Roubanina"
    ],
    "name:por_x_preferred":[
        "Roubanina"
    ],
    "name:slk_x_preferred":[
        "Roubanina"
    ],
    "name:spa_x_preferred":[
        "Roubanina"
    ],
    "name:srp_x_preferred":[
        "\u0420\u043e\u0443\u0431\u0430\u045a\u0438\u043d\u0430"
    ],
    "name:swe_x_preferred":[
        "Roubanina"
    ],
    "name:vie_x_preferred":[
        "Roubanina"
    ],
    "qs_pg:aaroncc":"CZ",
    "qs_pg:gn_country":"CZ",
    "qs_pg:gn_fcode":"PPL",
    "qs_pg:gn_pop":131,
    "qs_pg:name":"Roubanina",
    "qs_pg:name_adm0":"\u010cesk\u00e1 republika",
    "qs_pg:name_adm1":"Jihomoravsk\u00fd kraj",
    "qs_pg:photos_9r":0,
    "qs_pg:photos_sr":0,
    "qs_pg:pop_sr":1,
    "qs_pg:qs_pg_placetype":"locality",
    "qs_pg:qs_pg_placetype_gp":"Town",
    "qs_pg:woe_adm0":23424810,
    "woe:adm0_id":23424810,
    "woe:name_adm0":"\u010cesk\u00e1 republika",
    "woe:name_adm1":"Jihomoravsk\u00fd kraj",
    "woe:placetype":"Town",
    "wof:name":"Roubanina",
    "wof:placetype":"locality",
    "wof:population":131
},
  "geometry": {"coordinates":[16.59406,49.61541],"type":"Point"}
}