{
  "type": "Feature",
  "properties": {
    "gn:admin1_code":"86",
    "gn:admin2_code":"0533",
    "gn:asciiname":"Studenec",
    "gn:country_code":"CZ",
    "gn:dem":529,
    "gn:feature_class":"P",
    "gn:feature_code":"PPL",
    "gn:name":"Studenec",
    "gn:population":0,
    "gn:timezone":"Europe/Prague",
    "iso:country":"CZ",
    "wof:name":"Studenec",
    "wof:placetype":"locality"
},
  "geometry": {"coordinates":[16.43702,49.60643],"type":"Point"}
}