{
  "type": "Feature",
  "properties": {
    "gn:gn_country":"CZ",
    "gn:gn_fcode":"PPL",
    "gn:gn_pop":389,
    "gn:population":389,
    "iso:country":"CZ",
    "name:ceb_x_preferred":[
        "H\u00fdsly"
    ],
    "name:ces_x_preferred":[
        "H\u00fdsly"
    ],
    "name:deu_x_preferred":[
        "H\u00fdsly"
    ],
    "name:eng_x_preferred":[
        "H\u00fdsly"
    ],
    "name:eus_x_preferred":[
        "H\u00fdsly"
    ],
    "name:fas_x_preferred":[
        "\u0647\u06cc\u0633\u0644\u06cc"
    ],
    "name:fra_x_preferred":[
        "H\u00fdsly"
    ],
    "name:hun_x_preferred":[
        "H\u00fdsly"
    ],
    "name:ita_x_preferred":[
        "H\u00fdsly"
    ],
    "name:msa_x_preferred":[
        "H\u00fdsly"
    ],
    "name:nan_x_preferred":[
        "H\u00fdsly"
    ],
    "name:nld_x_preferred":[
        "H\u00fdsly"
    ],
    "name:pol_x_preferred":[
        "H\u00fdsly"
    ],
    "name:por_x_preferred":[
        "H\u00fdsly"
    ],
    "name:slk_x_preferred":[
        "H\u00fdsly"
    ],
    "name:spa_x_preferred":[
        "H\u00fdsly"
    ],
    "name:srp_x_preferred":[
        "\u0425\u0438\u0441\u043b\u0438"
    ],
    "name:swe_x_preferred":[
        "H\u00fdsly"
    ],
    "name:vie_x_preferred":[
        "H\u00fdsly"
    ],
    "qs_pg:aaroncc":"CZ",
    "qs_pg:gn_country":"CZ",
    "qs_pg:gn_fcode":"PPL",
    "qs_pg:gn_pop":389,
    "qs_pg:name":"H\u00fdsly",
    "qs_pg:name_adm0":"\u010cesk\u00e1 republika",
    "qs_pg:name_adm1":"Jihomoravsk\u00fd kraj",
    "qs_pg:photos_9r":0,
    "qs_pg:photos_sr":0,
    "qs_pg:pop_sr":2,
    "qs_pg:qs_pg_placetype":"locality",
    "qs_pg:qs_pg_placetype_gp":"Town",
    "qs_pg:woe_adm0":23424810,
    "woe:adm0_id":23424810,
    "woe:name_adm0":"\u010cesk\u00e1 republika",
    "woe:name_adm1":"Jihomoravsk\u00fd kraj",
    "woe:placetype":"Town",
    "wof:name":"H\u00fdsly",
    "wof:placetype":"locality",
    "wof:population":389
},
  "geometry": {"coordinates":[17.17983,49.02329],"type":"Point"}
}