{
  "type": "Feature",
  "properties": {
    "gn:admin1_code":"82.0",
    "gn:admin2_code":"0522",
    "gn:asciiname":"Markvartice",
    "gn:country_code":"CZ",
    "gn:dem":357,
    "gn:feature_class":"P",
    "gn:feature_code":"PPL",
    "gn:name":"Markvartice",
    "gn:population":458,
    "gn:timezone":"Europe/Prague",
    "iso:country":"CZ",
    "name:azb_x_preferred":[
        "\u0645\u0627\u0631\u06a9\u0648\u0627\u0631\u062a\u06cc\u062a\u0633\u0647"
    ],
    "name:ces_x_preferred":[
        "Markvartice"
    ],
    "name:eus_x_preferred":[
        "Markvartice"
    ],
    "name:fas_x_preferred":[
        "\u0645\u0627\u0631\u06a9\u0648\u0627\u0631\u062a\u06cc\u062a\u0633\u0647"
    ],
    "name:hun_x_preferred":[
        "Markvartice"
    ],
    "name:ita_x_preferred":[
        "Markvartice"
    ],
    "name:msa_x_preferred":[
        "Markvartice"
    ],
    "name:nld_x_preferred":[
        "Markvartice"
    ],
    "name:pol_x_preferred":[
        "Markvartice"
    ],
    "name:por_x_preferred":[
        "Markvartice"
    ],
    "name:slk_x_preferred":[
        "Markvartice"
    ],
    "name:spa_x_preferred":[
        "Markvartice"
    ],
    "name:srp_x_preferred":[
        "\u041c\u0430\u0440\u043a\u0432\u0430\u0440\u0442\u0438\u0446\u0435"
    ],
    "name:vie_x_preferred":[
        "Markvartice"
    ],
    "wof:name":"Markvartice",
    "wof:placetype":"locality",
    "wof:population":458
},
  "geometry": {"coordinates":[15.19607,50.43077],"type":"Point"}
}