{
  "type": "Feature",
  "properties": {
    "gn:admin1_code":"82.0",
    "gn:admin2_code":"0522",
    "gn:asciiname":"Markvartice",
    "gn:country_code":"CZ",
    "gn:dem":357,
    "gn:feature_class":"P",
    "gn:feature_code":"PPL",
    "gn:name":"Markvartice",
    "gn:population":458,
    "gn:timezone":"Europe/Prague",
    "iso:country":"CZ",
    "wof:name":"Markvartice",
    "wof:placetype":"locality",
    "wof:population":458
},
  "geometry": {"coordinates":[15.19607,50.43077],"type":"Point"}
}