{
  "type": "Feature",
  "properties": {
    "gn:admin1_code":"82",
    "gn:admin2_code":"0522",
    "gn:asciiname":"Zelejov",
    "gn:country_code":"CZ",
    "gn:dem":433,
    "gn:feature_class":"P",
    "gn:feature_code":"PPL",
    "gn:name":"\u017delejov",
    "gn:population":0,
    "gn:timezone":"Europe/Prague",
    "iso:country":"CZ",
    "wof:name":"Zelejov",
    "wof:placetype":"locality"
},
  "geometry": {"coordinates":[15.66184,50.43116],"type":"Point"}
}