{
  "type": "Feature",
  "properties": {
    "gn:gn_country":"CZ",
    "gn:gn_fcode":"PPL",
    "gn:gn_pop":293,
    "gn:population":293,
    "iso:country":"CZ",
    "name:ces_x_preferred":[
        "Zl\u00e1manec"
    ],
    "name:deu_x_preferred":[
        "Zl\u00e1manec"
    ],
    "name:eng_x_preferred":[
        "Zl\u00e1manec"
    ],
    "name:fas_x_preferred":[
        "\u0632\u0644\u0627\u0645\u0627\u0646\u062a\u0633"
    ],
    "name:fra_x_preferred":[
        "Zl\u00e1manec"
    ],
    "name:hun_x_preferred":[
        "Zl\u00e1manec"
    ],
    "name:ita_x_preferred":[
        "Zl\u00e1manec"
    ],
    "name:msa_x_preferred":[
        "Zl\u00e1manec"
    ],
    "name:nan_x_preferred":[
        "Zl\u00e1manec"
    ],
    "name:nld_x_preferred":[
        "Zl\u00e1manec"
    ],
    "name:pol_x_preferred":[
        "Zl\u00e1manec"
    ],
    "name:por_x_preferred":[
        "Zl\u00e1manec"
    ],
    "name:rup_x_preferred":[
        "Zl\u00e1manec"
    ],
    "name:slk_x_preferred":[
        "Zl\u00e1manec"
    ],
    "name:srp_x_preferred":[
        "\u0417\u043b\u0430\u043c\u0430\u043d\u0435\u0446"
    ],
    "name:swe_x_preferred":[
        "Zl\u00e1manec"
    ],
    "name:vie_x_preferred":[
        "Zl\u00e1manec"
    ],
    "qs_pg:aaroncc":"CZ",
    "qs_pg:gn_country":"CZ",
    "qs_pg:gn_fcode":"PPL",
    "qs_pg:gn_pop":293,
    "qs_pg:name":"Zl\u00e1manec",
    "qs_pg:name_adm0":"\u010cesk\u00e1 republika",
    "qs_pg:name_adm1":"Zl\u00ednsk\u00fd kraj",
    "qs_pg:photos_9k":1,
    "qs_pg:photos_9r":1,
    "qs_pg:photos_all":2,
    "qs_pg:photos_sr":0,
    "qs_pg:pop_sr":2,
    "qs_pg:qs_pg_placetype":"locality",
    "qs_pg:qs_pg_placetype_gp":"Town",
    "qs_pg:woe_adm0":23424810,
    "woe:adm0_id":23424810,
    "woe:name_adm0":"\u010cesk\u00e1 republika",
    "woe:name_adm1":"Zl\u00ednsk\u00fd kraj",
    "woe:placetype":"Town",
    "wof:name":"Zl\u00e1manec",
    "wof:placetype":"locality",
    "wof:population":293
},
  "geometry": {"coordinates":[17.6282,49.12985],"type":"Point"}
}