{
  "type": "Feature",
  "properties": {
    "gn:admin1_code":"83",
    "gn:admin2_code":"0512",
    "gn:asciiname":"Tepere",
    "gn:country_code":"CZ",
    "gn:dem":441,
    "gn:feature_class":"P",
    "gn:feature_code":"PPL",
    "gn:name":"T\u011bpe\u0159e",
    "gn:population":0,
    "gn:timezone":"Europe/Prague",
    "iso:country":"CZ",
    "wof:name":"Tepere",
    "wof:placetype":"locality"
},
  "geometry": {"coordinates":[15.24367,50.65833],"type":"Point"}
}