{
  "type": "Feature",
  "properties": {
    "gn:admin1_code":"79",
    "gn:admin2_code":"0316",
    "gn:asciiname":"Vrbno",
    "gn:country_code":"CZ",
    "gn:dem":477,
    "gn:feature_class":"P",
    "gn:feature_code":"PPL",
    "gn:name":"Vrbno",
    "gn:population":0,
    "gn:timezone":"Europe/Prague",
    "iso:country":"CZ",
    "wof:name":"Vrbno",
    "wof:placetype":"locality"
},
  "geometry": {"coordinates":[13.80896,49.40567],"type":"Point"}
}