{
  "type": "Feature",
  "properties": {
    "gn:admin1_code":"79.0",
    "gn:admin2_code":"0311",
    "gn:asciiname":"Brezi",
    "gn:country_code":"CZ",
    "gn:dem":449,
    "gn:feature_class":"P",
    "gn:feature_code":"PPL",
    "gn:name":"B\u0159ez\u00ed",
    "gn:population":0,
    "gn:timezone":"Europe/Prague",
    "iso:country":"CZ",
    "wof:name":"Brezi",
    "wof:placetype":"locality"
},
  "geometry": {"coordinates":[14.5993,48.84483],"type":"Point"}
}