{
  "type": "Feature",
  "properties": {
    "gn:admin1_code":"79",
    "gn:admin2_code":"0311",
    "gn:asciiname":"Svebohy",
    "gn:country_code":"CZ",
    "gn:dem":534,
    "gn:feature_class":"P",
    "gn:feature_code":"PPL",
    "gn:name":"Sv\u00e9bohy",
    "gn:population":0,
    "gn:timezone":"Europe/Prague",
    "iso:country":"CZ",
    "name:und_x_variant":[
        "Zweiendorf",
        "Sv\u00e9bohy"
    ],
    "wof:name":"Svebohy",
    "wof:placetype":"locality"
},
  "geometry": {"coordinates":[14.72248,48.78135],"type":"Point"}
}