{
  "type": "Feature",
  "properties": {
    "gn:admin1_code":"79",
    "gn:admin2_code":"0315",
    "gn:asciiname":"Zdikovec",
    "gn:cc2":"CZ",
    "gn:country_code":"CZ",
    "gn:dem":736,
    "gn:feature_class":"P",
    "gn:feature_code":"PPL",
    "gn:name":"Zd\u00edkovec",
    "gn:population":0,
    "gn:timezone":"Europe/Prague",
    "iso:country":"CZ",
    "name:und_x_variant":[
        "Klein \u017ddikau"
    ],
    "wof:name":"Zdikovec",
    "wof:placetype":"locality"
},
  "geometry": {"coordinates":[13.68922,49.0968],"type":"Point"}
}