{
  "type": "Feature",
  "properties": {
    "gn:admin1_code":"80.0",
    "gn:admin2_code":"0612",
    "gn:asciiname":"Jestrebi",
    "gn:country_code":"CZ",
    "gn:dem":578,
    "gn:feature_class":"P",
    "gn:feature_code":"PPL",
    "gn:name":"Jest\u0159eb\u00ed",
    "gn:population":0,
    "gn:timezone":"Europe/Prague",
    "iso:country":"CZ",
    "wof:name":"Jestrebi",
    "wof:placetype":"locality"
},
  "geometry": {"coordinates":[15.64309,49.29023],"type":"Point"}
}