{
  "type": "Feature",
  "properties": {
    "gn:gn_country":"CZ",
    "gn:gn_fcode":"PPL",
    "gn:gn_pop":55,
    "gn:population":55,
    "iso:country":"CZ",
    "name:cze_x_preferred":[
        "\u0160t\u00edtov"
    ],
    "name:dut_x_preferred":[
        "\u0160t\u00edtov"
    ],
    "name:eng_x_preferred":[
        "\u0160t\u00edtov"
    ],
    "name:fre_x_preferred":[
        "\u0160t\u00edtov"
    ],
    "name:hun_x_preferred":[
        "\u0160t\u00edtov"
    ],
    "name:ita_x_preferred":[
        "\u0160t\u00edtov"
    ],
    "name:may_x_preferred":[
        "\u0160t\u00edtov"
    ],
    "name:per_x_preferred":[
        "\u0634\u062a\u06cc\u062a\u0648\u0648"
    ],
    "name:por_x_preferred":[
        "\u0160t\u00edtov"
    ],
    "name:slo_x_preferred":[
        "\u0160t\u00edtov"
    ],
    "name:srp_x_preferred":[
        "\u0428\u0442\u0438\u0442\u043e\u0432"
    ],
    "name:vie_x_preferred":[
        "\u0160t\u00edtov"
    ],
    "qs_pg:aaroncc":"CZ",
    "qs_pg:gn_country":"CZ",
    "qs_pg:gn_fcode":"PPL",
    "qs_pg:gn_pop":55,
    "qs_pg:name":"\u0160t\u00edtov",
    "qs_pg:photos_9r":0,
    "qs_pg:photos_sr":0,
    "qs_pg:pop_sr":1,
    "qs_pg:qs_pg_placetype":"locality",
    "wof:name":"\u0160t\u00edtov",
    "wof:placetype":"locality",
    "wof:population":55
},
  "geometry": {"coordinates":[13.67792,49.66593],"type":"Point"}
}