{
  "type": "Feature",
  "properties": {
    "gn:admin1_code":"84.0",
    "gn:admin2_code":"0711",
    "gn:asciiname":"Hranicna",
    "gn:country_code":"CZ",
    "gn:dem":519,
    "gn:feature_class":"P",
    "gn:feature_code":"PPL",
    "gn:name":"Hrani\u010dn\u00e1",
    "gn:population":0,
    "gn:timezone":"Europe/Prague",
    "iso:country":"CZ",
    "name:und_x_variant":[
        "Granzgrund",
        "Grenzgrund",
        "Hrani\u010dn\u00e1"
    ],
    "wof:name":"Hranicna",
    "wof:placetype":"locality"
},
  "geometry": {"coordinates":[17.01667,50.31667],"type":"Point"}
}