{
  "type": "Feature",
  "properties": {
    "gn:admin1_code":"79",
    "gn:admin2_code":"0312",
    "gn:asciiname":"Vsemerice",
    "gn:country_code":"CZ",
    "gn:dem":616,
    "gn:feature_class":"P",
    "gn:feature_code":"PPL",
    "gn:name":"V\u0161em\u011b\u0159ice",
    "gn:population":0,
    "gn:timezone":"Europe/Prague",
    "iso:country":"CZ",
    "name:und_x_variant":[
        "Sch\u00f6mersdorf",
        "V\u0161em\u011b\u0159ice"
    ],
    "wof:name":"Vsemerice",
    "wof:placetype":"locality"
},
  "geometry": {"coordinates":[14.47641,48.68786],"type":"Point"}
}