{
  "type": "Feature",
  "properties": {
    "iso:country":"CZ",
    "name:ceb_x_preferred":[
        "\u010cejkovice"
    ],
    "name:ces_x_preferred":[
        "\u010cejkovice"
    ],
    "name:deu_x_preferred":[
        "\u010cejkovice"
    ],
    "name:epo_x_preferred":[
        "\u010cejkovice"
    ],
    "name:fra_x_preferred":[
        "\u010cejkovice"
    ],
    "name:ita_x_preferred":[
        "\u010cejkovice"
    ],
    "name:nld_x_preferred":[
        "\u010cejkovice"
    ],
    "name:pol_x_preferred":[
        "\u010cejkovice"
    ],
    "name:slk_x_preferred":[
        "\u010cejkovice"
    ],
    "name:srp_x_preferred":[
        "\u0427\u0435\u0458\u043a\u043e\u0432\u0438\u0446\u0435"
    ],
    "name:swe_x_preferred":[
        "\u010cejkovice"
    ],
    "qs_pg:aaroncc":"CZ",
    "qs_pg:name":"\u010cejkovice",
    "qs_pg:name_adm0":"\u010cesk\u00e1 republika",
    "qs_pg:name_adm1":"Jihomoravsk\u00fd kraj",
    "qs_pg:photos":3,
    "qs_pg:photos_1k":1,
    "qs_pg:photos_9k":1,
    "qs_pg:photos_9r":2,
    "qs_pg:photos_all":30,
    "qs_pg:photos_sr":1,
    "qs_pg:pop_sr":0,
    "qs_pg:qs_pg_placetype":"localadmin",
    "qs_pg:qs_pg_placetype_gp":"LocalAdmin",
    "qs_pg:woe_adm0":23424810,
    "woe:adm0_id":23424810,
    "woe:name_adm0":"\u010cesk\u00e1 republika",
    "woe:name_adm1":"Jihomoravsk\u00fd kraj",
    "woe:placetype":"LocalAdmin",
    "wof:name":"\u010cejkovice",
    "wof:placetype":"localadmin"
},
  "geometry": {"coordinates":[16.946797,48.90447],"type":"Point"}
}