{
  "type": "Feature",
  "properties": {
    "gn:country":"CZ",
    "gn:fcode":"PPL",
    "gn:population":462,
    "iso:country":"CZ",
    "name:ceb_x_preferred":[
        "D\u011btkovice"
    ],
    "name:ces_x_preferred":[
        "D\u011btkovice"
    ],
    "name:deu_x_preferred":[
        "D\u011btkovice"
    ],
    "name:fra_x_preferred":[
        "D\u011btkovice"
    ],
    "name:ita_x_preferred":[
        "D\u011btkovice"
    ],
    "name:nld_x_preferred":[
        "D\u011btkovice"
    ],
    "name:pol_x_preferred":[
        "D\u011btkovice"
    ],
    "name:slk_x_preferred":[
        "D\u011btkovice"
    ],
    "name:srp_x_preferred":[
        "\u0414\u0458\u0435\u0442\u043a\u043e\u0432\u0438\u0446\u0435"
    ],
    "name:swe_x_preferred":[
        "D\u011btkovice"
    ],
    "qs_pg:aaroncc":"CZ",
    "qs_pg:gn_country":"CZ",
    "qs_pg:gn_fcode":"PPL",
    "qs_pg:gn_pop":462,
    "qs_pg:name":"D\u011btkovice",
    "qs_pg:name_adm0":"\u010cesk\u00e1 republika",
    "qs_pg:name_adm1":"Jihomoravsk\u00fd kraj",
    "qs_pg:photos_9r":0,
    "qs_pg:photos_sr":0,
    "qs_pg:pop_sr":2,
    "qs_pg:qs_pg_placetype":"locality",
    "qs_pg:qs_pg_placetype_gp":"Town",
    "qs_pg:woe_adm0":23424810,
    "woe:adm0_id":23424810,
    "woe:name_adm0":"\u010cesk\u00e1 republika",
    "woe:name_adm1":"Jihomoravsk\u00fd kraj",
    "woe:placetype":"Town",
    "wof:name":"D\u011btkovice",
    "wof:placetype":"locality",
    "wof:population":462
},
  "geometry": {"coordinates":[17.08218,49.41536],"type":"Point"}
}