{
  "type": "Feature",
  "properties": {
    "gn:admin1_code":"79",
    "gn:admin2_code":"0313",
    "gn:asciiname":"Stary Bozdechov",
    "gn:country_code":"CZ",
    "gn:dem":606,
    "gn:feature_class":"P",
    "gn:feature_code":"PPL",
    "gn:name":"Star\u00fd Bozd\u011bchov",
    "gn:population":0,
    "gn:timezone":"Europe/Prague",
    "iso:country":"CZ",
    "wof:name":"Stary Bozdechov",
    "wof:placetype":"locality"
},
  "geometry": {"coordinates":[15.01343,49.27292],"type":"Point"}
}