{
  "type": "Feature",
  "properties": {
    "gn:admin1_code":"83.0",
    "gn:admin2_code":"0514",
    "gn:asciiname":"Olesnice",
    "gn:country_code":"CZ",
    "gn:dem":292,
    "gn:feature_class":"P",
    "gn:feature_code":"PPL",
    "gn:name":"Ole\u0161nice",
    "gn:population":184,
    "gn:timezone":"Europe/Prague",
    "iso:country":"CZ",
    "wof:name":"Olesnice",
    "wof:placetype":"locality",
    "wof:population":184
},
  "geometry": {"coordinates":[15.1192,50.54495],"type":"Point"}
}