{
  "type": "Feature",
  "properties": {
    "gn:admin1_code":"82",
    "gn:admin2_code":"0522",
    "gn:asciiname":"Velke Bilsko",
    "gn:country_code":"CZ",
    "gn:dem":292,
    "gn:feature_class":"P",
    "gn:feature_code":"PPL",
    "gn:name":"Velk\u00e9 B\u00edlsko",
    "gn:population":0,
    "gn:timezone":"Europe/Prague",
    "iso:country":"CZ",
    "wof:name":"Velke Bilsko",
    "wof:placetype":"locality"
},
  "geometry": {"coordinates":[15.60083,50.36947],"type":"Point"}
}