{
  "type": "Feature",
  "properties": {
    "gn:admin1_code":"88.0",
    "gn:admin2_code":"0205",
    "gn:asciiname":"Katerinky",
    "gn:country_code":"CZ",
    "gn:dem":487,
    "gn:feature_class":"P",
    "gn:feature_code":"PPL",
    "gn:name":"Kate\u0159inky",
    "gn:population":0,
    "gn:timezone":"Europe/Prague",
    "iso:country":"CZ",
    "wof:name":"Katerinky",
    "wof:placetype":"locality"
},
  "geometry": {"coordinates":[15.17899,49.82774000000001],"type":"Point"}
}