{
  "type": "Feature",
  "properties": {
    "gn:admin1_code":"79",
    "gn:admin2_code":"0314",
    "gn:asciiname":"Zdakov u Chrastu",
    "gn:country_code":"CZ",
    "gn:dem":392,
    "gn:feature_class":"P",
    "gn:feature_code":"PPL",
    "gn:name":"\u017dd\u00e1kov u Chr\u00e1stu",
    "gn:population":0,
    "gn:timezone":"Europe/Prague",
    "iso:country":"CZ",
    "wof:name":"Zdakov u Chrastu",
    "wof:placetype":"locality"
},
  "geometry": {"coordinates":[14.18333,49.51667],"type":"Point"}
}