{
  "type": "Feature",
  "properties": {
    "gn:admin1_code":"90.0",
    "gn:admin2_code":"0722",
    "gn:asciiname":"Smradavka",
    "gn:country_code":"CZ",
    "gn:dem":235,
    "gn:feature_class":"P",
    "gn:feature_code":"PPL",
    "gn:name":"Smrad\u00e1vka",
    "gn:population":0,
    "gn:timezone":"Europe/Prague",
    "iso:country":"CZ",
    "wof:name":"Smradavka",
    "wof:placetype":"locality"
},
  "geometry": {"coordinates":[17.31996,49.07741],"type":"Point"}
}