{
  "type": "Feature",
  "properties": {
    "gn:admin1_code":"84.0",
    "gn:admin2_code":"0715",
    "gn:asciiname":"Repova",
    "gn:cc2":"CZ",
    "gn:country_code":"CZ",
    "gn:dem":352,
    "gn:feature_class":"P",
    "gn:feature_code":"PPL",
    "gn:name":"\u0158epov\u00e1",
    "gn:population":0,
    "gn:timezone":"Europe/Prague",
    "iso:country":"CZ",
    "name:und_x_variant":[
        "Rippau"
    ],
    "wof:name":"Repova",
    "wof:placetype":"locality"
},
  "geometry": {"coordinates":[16.86976,49.80603],"type":"Point"}
}