{
  "type": "Feature",
  "properties": {
    "gn:admin1_code":"82",
    "gn:admin2_code":"0522",
    "gn:asciiname":"Zliv",
    "gn:country_code":"CZ",
    "gn:dem":223,
    "gn:feature_class":"P",
    "gn:feature_code":"PPL",
    "gn:name":"Zliv",
    "gn:population":0,
    "gn:timezone":"Europe/Prague",
    "iso:country":"CZ",
    "wof:name":"Zliv",
    "wof:placetype":"locality"
},
  "geometry": {"coordinates":[15.23268,50.35976],"type":"Point"}
}