{
  "type": "Feature",
  "properties": {
    "gn:admin1_code":"80.0",
    "gn:admin2_code":"0612",
    "gn:asciiname":"Kasarna",
    "gn:country_code":"CZ",
    "gn:dem":666,
    "gn:feature_class":"P",
    "gn:feature_code":"PPL",
    "gn:name":"Kas\u00e1rna",
    "gn:population":0,
    "gn:timezone":"Europe/Prague",
    "iso:country":"CZ",
    "wof:name":"Kasarna",
    "wof:placetype":"locality"
},
  "geometry": {"coordinates":[15.63256,49.18242],"type":"Point"}
}