{
  "type": "Feature",
  "properties": {
    "gn:admin1_code":"85",
    "gn:admin2_code":"0804",
    "gn:asciiname":"Sykorec",
    "gn:country_code":"CZ",
    "gn:dem":314,
    "gn:feature_class":"P",
    "gn:feature_code":"PPL",
    "gn:name":"S\u00fdkorec",
    "gn:population":0,
    "gn:timezone":"Europe/Prague",
    "iso:country":"CZ",
    "wof:name":"Sykorec",
    "wof:placetype":"locality"
},
  "geometry": {"coordinates":[18.16917,49.60595],"type":"Point"}
}