{
  "type": "Feature",
  "properties": {
    "gn:admin1_code":"90.0",
    "gn:admin2_code":"0724",
    "gn:asciiname":"Homole",
    "gn:country_code":"CZ",
    "gn:dem":466,
    "gn:feature_class":"P",
    "gn:feature_code":"PPL",
    "gn:name":"Homole",
    "gn:population":0,
    "gn:timezone":"Europe/Prague",
    "iso:country":"CZ",
    "name:ceb_x_preferred":[
        "Homole"
    ],
    "name:ces_x_preferred":[
        "Homole"
    ],
    "name:deu_x_preferred":[
        "Homole"
    ],
    "name:fra_x_preferred":[
        "Homole"
    ],
    "name:pol_x_preferred":[
        "Homole"
    ],
    "name:swe_x_preferred":[
        "Homole"
    ],
    "wof:name":"Homole",
    "wof:placetype":"locality"
},
  "geometry": {"coordinates":[17.81183,49.16055],"type":"Point"}
}