{
  "type": "Feature",
  "properties": {
    "gn:admin1_code":"87.0",
    "gn:admin2_code":"0322",
    "gn:asciiname":"Jindrichovice",
    "gn:country_code":"CZ",
    "gn:dem":561,
    "gn:feature_class":"P",
    "gn:feature_code":"PPL",
    "gn:name":"Jind\u0159ichovice",
    "gn:population":0,
    "gn:timezone":"Europe/Prague",
    "iso:country":"CZ",
    "wof:name":"Jindrichovice",
    "wof:placetype":"locality"
},
  "geometry": {"coordinates":[13.39525,49.29787],"type":"Point"}
}