{
  "type": "Feature",
  "properties": {
    "gn:admin1_code":"78.0",
    "gn:admin2_code":"0625",
    "gn:asciiname":"Bukovany",
    "gn:country_code":"CZ",
    "gn:dem":305,
    "gn:feature_class":"P",
    "gn:feature_code":"PPL",
    "gn:name":"Bukovany",
    "gn:population":761,
    "gn:timezone":"Europe/Prague",
    "iso:country":"CZ",
    "name:azb_x_preferred":[
        "\u0628\u0648\u06a9\u0648\u0648\u0627\u0646\u06cc"
    ],
    "name:ceb_x_preferred":[
        "Bukovany"
    ],
    "name:ces_x_preferred":[
        "Bukovany"
    ],
    "name:eus_x_preferred":[
        "Bukovany"
    ],
    "name:fas_x_preferred":[
        "\u0628\u0648\u06a9\u0648\u0648\u0627\u0646\u06cc"
    ],
    "name:hun_x_preferred":[
        "Bukovany"
    ],
    "name:ita_x_preferred":[
        "Bukovany"
    ],
    "name:msa_x_preferred":[
        "Bukovany"
    ],
    "name:nld_x_preferred":[
        "Bukovany"
    ],
    "name:pol_x_preferred":[
        "Bukovany"
    ],
    "name:slk_x_preferred":[
        "Bukovany"
    ],
    "name:spa_x_preferred":[
        "Bukovany"
    ],
    "name:srp_x_preferred":[
        "\u0411\u0443\u043a\u043e\u0432\u0430\u043d\u0438"
    ],
    "name:vie_x_preferred":[
        "Bukovany"
    ],
    "wof:name":"Bukovany",
    "wof:placetype":"locality",
    "wof:population":761
},
  "geometry": {"coordinates":[17.10085,49.04217],"type":"Point"}
}