{
  "type": "Feature",
  "properties": {
    "gn:admin1_code":"78.0",
    "gn:admin2_code":"0625",
    "gn:asciiname":"Bukovany",
    "gn:country_code":"CZ",
    "gn:dem":305,
    "gn:feature_class":"P",
    "gn:feature_code":"PPL",
    "gn:name":"Bukovany",
    "gn:population":761,
    "gn:timezone":"Europe/Prague",
    "iso:country":"CZ",
    "wof:name":"Bukovany",
    "wof:placetype":"locality",
    "wof:population":761
},
  "geometry": {"coordinates":[17.10085,49.04217],"type":"Point"}
}