{
  "type": "Feature",
  "properties": {
    "gn:gn_country":"CZ",
    "gn:gn_fcode":"PPL",
    "gn:gn_pop":299,
    "gn:population":299,
    "iso:country":"CZ",
    "name:unk_x_variant":[
        "Lang Lhota"
    ],
    "qs_pg:aaroncc":"CZ",
    "qs_pg:gn_country":"CZ",
    "qs_pg:gn_fcode":"PPL",
    "qs_pg:gn_pop":299,
    "qs_pg:name":"Dlouh\u00e1 Lhota",
    "qs_pg:photos_9r":0,
    "qs_pg:photos_sr":0,
    "qs_pg:pop_sr":2,
    "qs_pg:qs_pg_placetype":"locality",
    "wof:name":"Dlouh\u00e1 Lhota",
    "wof:placetype":"locality",
    "wof:population":299
},
  "geometry": {"coordinates":[14.1206,49.72112],"type":"Point"}
}