{
  "type": "Feature",
  "properties": {
    "gn:country":"CZ",
    "gn:fcode":"PPL",
    "gn:population":299,
    "iso:country":"CZ",
    "name:ceb_x_preferred":[
        "Dlouh\u00e1 Lhota"
    ],
    "name:ces_x_preferred":[
        "Dlouh\u00e1 Lhota"
    ],
    "name:deu_x_preferred":[
        "Dlouh\u00e1 Lhota"
    ],
    "name:epo_x_preferred":[
        "Dlouh\u00e1 Lhota"
    ],
    "name:fra_x_preferred":[
        "Dlouh\u00e1 Lhota"
    ],
    "name:ita_x_preferred":[
        "Dlouh\u00e1 Lhota"
    ],
    "name:nld_x_preferred":[
        "Dlouh\u00e1 Lhota"
    ],
    "name:slk_x_preferred":[
        "Dlouh\u00e1 Lhota"
    ],
    "name:srp_x_preferred":[
        "\u0414\u043b\u043e\u0443\u0445\u0430 \u041b\u0445\u043e\u0442\u0430"
    ],
    "name:swe_x_preferred":[
        "Dlouh\u00e1 Lhota"
    ],
    "name:und_x_variant":[
        "Lang Lhota"
    ],
    "qs_pg:aaroncc":"CZ",
    "qs_pg:gn_country":"CZ",
    "qs_pg:gn_fcode":"PPL",
    "qs_pg:gn_pop":299,
    "qs_pg:name":"Dlouh\u00e1 Lhota",
    "qs_pg:photos_9r":0,
    "qs_pg:photos_sr":0,
    "qs_pg:pop_sr":2,
    "qs_pg:qs_pg_placetype":"locality",
    "wof:name":"Dlouh\u00e1 Lhota",
    "wof:placetype":"locality",
    "wof:population":299
},
  "geometry": {"coordinates":[14.1206,49.72112],"type":"Point"}
}