{
  "type": "Feature",
  "properties": {
    "gn:admin1_code":"87.0",
    "gn:admin2_code":"0326",
    "gn:asciiname":"Frantiskov",
    "gn:country_code":"CZ",
    "gn:dem":410,
    "gn:feature_class":"P",
    "gn:feature_code":"PPL",
    "gn:name":"Franti\u0161kov",
    "gn:population":0,
    "gn:timezone":"Europe/Prague",
    "iso:country":"CZ",
    "wof:name":"Frantiskov",
    "wof:placetype":"locality"
},
  "geometry": {"coordinates":[13.75952,49.86886],"type":"Point"}
}