{
  "type": "Feature",
  "properties": {
    "gn:gn_country":"CZ",
    "gn:gn_fcode":"PPL",
    "gn:gn_pop":204,
    "gn:population":204,
    "iso:country":"CZ",
    "name:cze_x_preferred":[
        "Libkova Voda"
    ],
    "name:dut_x_preferred":[
        "Libkova Voda"
    ],
    "name:eng_x_preferred":[
        "Libkova Voda"
    ],
    "name:fre_x_preferred":[
        "Libkova Voda"
    ],
    "name:ger_x_preferred":[
        "Libkova Voda"
    ],
    "name:hun_x_preferred":[
        "Libkova Voda"
    ],
    "name:ita_x_preferred":[
        "Libkova Voda"
    ],
    "name:may_x_preferred":[
        "Libkova Voda"
    ],
    "name:nan_x_preferred":[
        "Libkova Voda"
    ],
    "name:per_x_preferred":[
        "\u0644\u06cc\u0628\u06a9\u0648\u0648\u0627 \u0648\u0648\u062f\u0627"
    ],
    "name:pol_x_preferred":[
        "Libkova Voda"
    ],
    "name:por_x_preferred":[
        "Libkova Voda"
    ],
    "name:rup_x_preferred":[
        "Libkova Voda"
    ],
    "name:slo_x_preferred":[
        "Libkova Voda"
    ],
    "name:srp_x_preferred":[
        "\u041b\u0438\u043f\u043a\u043e\u0432\u0430 \u0412\u043e\u0434\u0430"
    ],
    "name:swe_x_preferred":[
        "Libkova Voda"
    ],
    "name:unk_x_variant":[
        "Lipkowawoda"
    ],
    "name:vie_x_preferred":[
        "Libkova Voda"
    ],
    "qs_pg:aaroncc":"CZ",
    "qs_pg:gn_country":"CZ",
    "qs_pg:gn_fcode":"PPL",
    "qs_pg:gn_pop":204,
    "qs_pg:name":"Libkova Voda",
    "qs_pg:name_adm0":"\u010cesk\u00e1 republika",
    "qs_pg:name_adm1":"Kraj Vyso\u010dina",
    "qs_pg:photos_9r":0,
    "qs_pg:photos_sr":0,
    "qs_pg:pop_sr":2,
    "qs_pg:qs_pg_placetype":"locality",
    "qs_pg:qs_pg_placetype_gp":"Town",
    "qs_pg:woe_adm0":23424810,
    "woe:adm0_id":23424810,
    "woe:name_adm0":"\u010cesk\u00e1 republika",
    "woe:name_adm1":"Kraj Vyso\u010dina",
    "woe:placetype":"Town",
    "wof:name":"Libkova Voda",
    "wof:placetype":"locality",
    "wof:population":204
},
  "geometry": {"coordinates":[15.19101,49.37649],"type":"Point"}
}