{
  "type": "Feature",
  "properties": {
    "gn:country":"CZ",
    "gn:fcode":"PPL",
    "gn:population":0,
    "iso:country":"CZ",
    "name:ces_x_preferred":[
        "Star\u00e1 Role"
    ],
    "name:deu_x_historical":[
        "Altrohlau"
    ],
    "name:deu_x_preferred":[
        "Altrohlau"
    ],
    "name:deu_x_variant":[
        "Star\u00e1 Role"
    ],
    "name:eng_x_preferred":[
        "Star\u00e1 Role"
    ],
    "name:fra_x_preferred":[
        "Star\u00e1 Role"
    ],
    "name:und_x_variant":[
        "Alt-Rohlau"
    ],
    "name:zho_x_preferred":[
        "\u65e7\u7f57\u83b1"
    ],
    "qs_pg:aaroncc":"CZ",
    "qs_pg:gn_country":"CZ",
    "qs_pg:gn_fcode":"PPL",
    "qs_pg:gn_pop":0,
    "qs_pg:name":"Star\u00e1 Role",
    "qs_pg:name_adm0":"\u010cesk\u00e1 republika",
    "qs_pg:name_adm1":"Karlovarsk\u00fd kraj",
    "qs_pg:photos":1,
    "qs_pg:photos_1k":1,
    "qs_pg:photos_9k":1,
    "qs_pg:photos_9r":1,
    "qs_pg:photos_all":1,
    "qs_pg:photos_sr":1,
    "qs_pg:pop_sr":0,
    "qs_pg:qs_pg_placetype":"neighbourhood",
    "qs_pg:qs_pg_placetype_gp":"Suburb",
    "qs_pg:woe_adm0":23424810,
    "woe:adm0_id":23424810,
    "woe:name_adm0":"\u010cesk\u00e1 republika",
    "woe:name_adm1":"Karlovarsk\u00fd kraj",
    "woe:placetype":"Suburb",
    "wof:name":"Star\u00e1 Role",
    "wof:placetype":"neighbourhood"
},
  "geometry": {"coordinates":[12.83038,50.24621],"type":"Point"}
}