{
  "type": "Feature",
  "properties": {
    "gn:admin1_code":"88.0",
    "gn:admin2_code":"0203",
    "gn:asciiname":"Kokovice",
    "gn:country_code":"CZ",
    "gn:dem":282,
    "gn:feature_class":"P",
    "gn:feature_code":"PPL",
    "gn:name":"Kokovice",
    "gn:population":0,
    "gn:timezone":"Europe/Prague",
    "iso:country":"CZ",
    "wof:name":"Kokovice",
    "wof:placetype":"locality"
},
  "geometry": {"coordinates":[13.96465,50.29581],"type":"Point"}
}