{
  "type": "Feature",
  "properties": {
    "gn:admin1_code":"78.0",
    "gn:admin2_code":"0621",
    "gn:asciiname":"Petrov",
    "gn:country_code":"CZ",
    "gn:dem":521,
    "gn:feature_class":"P",
    "gn:feature_code":"PPL",
    "gn:name":"Petrov",
    "gn:population":147,
    "gn:timezone":"Europe/Prague",
    "iso:country":"CZ",
    "wof:name":"Petrov",
    "wof:placetype":"locality",
    "wof:population":147
},
  "geometry": {"coordinates":[16.48959,49.53367],"type":"Point"}
}