{
  "type": "Feature",
  "properties": {
    "gn:admin1_code":"78.0",
    "gn:admin2_code":"0621",
    "gn:asciiname":"Petrov",
    "gn:country_code":"CZ",
    "gn:dem":521,
    "gn:feature_class":"P",
    "gn:feature_code":"PPL",
    "gn:name":"Petrov",
    "gn:population":147,
    "gn:timezone":"Europe/Prague",
    "iso:country":"CZ",
    "name:azb_x_preferred":[
        "\u067e\u062a\u0631\u0648\u0641"
    ],
    "name:ces_x_preferred":[
        "Petrov"
    ],
    "name:epo_x_preferred":[
        "Petrov"
    ],
    "name:eus_x_preferred":[
        "Petrov"
    ],
    "name:fas_x_preferred":[
        "\u067e\u062a\u0631\u0648\u0641"
    ],
    "name:hun_x_preferred":[
        "Petrov"
    ],
    "name:ita_x_preferred":[
        "Petrov"
    ],
    "name:msa_x_preferred":[
        "Petrov"
    ],
    "name:nld_x_preferred":[
        "Petrov"
    ],
    "name:por_x_preferred":[
        "Petrov"
    ],
    "name:slk_x_preferred":[
        "Petrov"
    ],
    "name:spa_x_preferred":[
        "Petrov"
    ],
    "name:srp_x_preferred":[
        "\u041f\u0435\u0442\u0440\u043e\u0432"
    ],
    "name:vie_x_preferred":[
        "Petrov"
    ],
    "wof:name":"Petrov",
    "wof:placetype":"locality",
    "wof:population":147
},
  "geometry": {"coordinates":[16.48959,49.53367],"type":"Point"}
}