{
  "type": "Feature",
  "properties": {
    "gn:admin1_code":"87.0",
    "gn:admin2_code":"0322",
    "gn:asciiname":"Milence",
    "gn:country_code":"CZ",
    "gn:dem":499,
    "gn:feature_class":"P",
    "gn:feature_code":"PPL",
    "gn:name":"Milence",
    "gn:population":0,
    "gn:timezone":"Europe/Prague",
    "iso:country":"CZ",
    "name:und_x_variant":[
        "Millik",
        "Milence"
    ],
    "wof:name":"Milence",
    "wof:placetype":"locality"
},
  "geometry": {"coordinates":[13.15917,49.27477],"type":"Point"}
}