{
  "type": "Feature",
  "properties": {
    "gn:admin1_code":"52.0",
    "gn:admin2_code":"8378792",
    "gn:asciiname":"Kolodeje",
    "gn:country_code":"CZ",
    "gn:dem":278,
    "gn:feature_class":"P",
    "gn:feature_code":"PPL",
    "gn:name":"Kolod\u011bje",
    "gn:population":0,
    "gn:timezone":"Europe/Prague",
    "iso:country":"CZ",
    "wof:name":"Kolodeje",
    "wof:placetype":"locality"
},
  "geometry": {"coordinates":[14.64265,50.06257],"type":"Point"}
}