{
  "type": "Feature",
  "properties": {
    "gn:admin1_code":"52.0",
    "gn:admin2_code":"8378792",
    "gn:asciiname":"Kolodeje",
    "gn:country_code":"CZ",
    "gn:dem":278,
    "gn:feature_class":"P",
    "gn:feature_code":"PPL",
    "gn:name":"Kolod\u011bje",
    "gn:population":0,
    "gn:timezone":"Europe/Prague",
    "iso:country":"CZ",
    "name:ces_x_preferred":[
        "Kolod\u011bje"
    ],
    "name:fas_x_preferred":[
        "\u06a9\u0648\u0644\u0648\u062f\u06cc\u06cc\u0647"
    ],
    "name:fra_x_preferred":[
        "Kolod\u011bje"
    ],
    "name:pol_x_preferred":[
        "Kolod\u011bje"
    ],
    "name:rus_x_preferred":[
        "\u041a\u043e\u043b\u043e\u0434\u0435\u0435"
    ],
    "name:slk_x_preferred":[
        "Kolod\u011bje"
    ],
    "wof:name":"Kolodeje",
    "wof:placetype":"locality"
},
  "geometry": {"coordinates":[14.64265,50.06257],"type":"Point"}
}