{
  "type": "Feature",
  "properties": {
    "gn:gn_country":"CZ",
    "gn:gn_fcode":"PPL",
    "gn:gn_pop":408,
    "gn:population":408,
    "iso:country":"CZ",
    "name:ceb_x_preferred":[
        "\u00dater\u00fd"
    ],
    "name:ces_x_preferred":[
        "\u00dater\u00fd"
    ],
    "name:deu_x_preferred":[
        "Neumarkt"
    ],
    "name:deu_x_variant":[
        "\u00dater\u00fd"
    ],
    "name:eng_x_preferred":[
        "\u00dater\u00fd"
    ],
    "name:epo_x_preferred":[
        "\u00dater\u00fd"
    ],
    "name:eus_x_preferred":[
        "\u00dater\u00fd"
    ],
    "name:fas_x_preferred":[
        "\u0627\u0648\u062a\u0631\u06cc"
    ],
    "name:fra_x_preferred":[
        "\u00dater\u00fd"
    ],
    "name:hun_x_preferred":[
        "\u00dater\u00fd"
    ],
    "name:ita_x_preferred":[
        "\u00dater\u00fd"
    ],
    "name:msa_x_preferred":[
        "\u00dater\u00fd"
    ],
    "name:nan_x_preferred":[
        "\u00dater\u00fd"
    ],
    "name:nld_x_preferred":[
        "\u00dater\u00fd"
    ],
    "name:pol_x_preferred":[
        "\u00dater\u00fd"
    ],
    "name:por_x_preferred":[
        "\u00dater\u00fd"
    ],
    "name:rup_x_preferred":[
        "\u00dater\u00fd"
    ],
    "name:slk_x_preferred":[
        "\u00dater\u00fd"
    ],
    "name:spa_x_preferred":[
        "\u00dater\u00fd"
    ],
    "name:srp_x_preferred":[
        "\u0423\u0442\u0435\u0440\u0438"
    ],
    "name:swe_x_preferred":[
        "\u00dater\u00fd"
    ],
    "name:tat_x_preferred":[
        "\u0423\u0442\u0435\u0440\u0438"
    ],
    "name:vie_x_preferred":[
        "\u00dater\u00fd"
    ],
    "name:zho_x_preferred":[
        "\u70cf\u7279\u91cc"
    ],
    "qs_pg:aaroncc":"CZ",
    "qs_pg:gn_country":"CZ",
    "qs_pg:gn_fcode":"PPL",
    "qs_pg:gn_pop":408,
    "qs_pg:name":"\u00dater\u00fd",
    "qs_pg:name_adm0":"\u010cesk\u00e1 republika",
    "qs_pg:name_adm1":"Plze\u0148sk\u00fd kraj",
    "qs_pg:photos_9k":1,
    "qs_pg:photos_9r":1,
    "qs_pg:photos_all":2,
    "qs_pg:photos_sr":0,
    "qs_pg:pop_sr":2,
    "qs_pg:qs_pg_placetype":"locality",
    "qs_pg:qs_pg_placetype_gp":"Town",
    "qs_pg:woe_adm0":23424810,
    "woe:adm0_id":23424810,
    "woe:name_adm0":"\u010cesk\u00e1 republika",
    "woe:name_adm1":"Plze\u0148sk\u00fd kraj",
    "woe:placetype":"Town",
    "wof:name":"\u00dater\u00fd",
    "wof:placetype":"locality",
    "wof:population":408
},
  "geometry": {"coordinates":[13.00418,49.94007],"type":"Point"}
}