{
  "type": "Feature",
  "properties": {
    "gn:admin1_code":"79.0",
    "gn:admin2_code":"0311",
    "gn:asciiname":"Nova Ves",
    "gn:country_code":"CZ",
    "gn:dem":451,
    "gn:feature_class":"P",
    "gn:feature_code":"PPL",
    "gn:name":"Nov\u00e1 Ves",
    "gn:population":607,
    "gn:timezone":"Europe/Prague",
    "iso:country":"CZ",
    "wof:name":"Nova Ves",
    "wof:placetype":"locality",
    "wof:population":607
},
  "geometry": {"coordinates":[14.52864,48.9206],"type":"Point"}
}