{
  "type": "Feature",
  "properties": {
    "gn:admin1_code":"88.0",
    "gn:admin2_code":"020C",
    "gn:asciiname":"Novosedly",
    "gn:country_code":"CZ",
    "gn:dem":397,
    "gn:feature_class":"P",
    "gn:feature_code":"PPL",
    "gn:name":"Novosedly",
    "gn:population":0,
    "gn:timezone":"Europe/Prague",
    "iso:country":"CZ",
    "name:ceb_x_preferred":[
        "Novosedly"
    ],
    "name:ces_x_preferred":[
        "Novosedly"
    ],
    "name:deu_x_preferred":[
        "Novosedly"
    ],
    "name:fra_x_preferred":[
        "Novosedly"
    ],
    "name:hun_x_preferred":[
        "Novosedly"
    ],
    "name:ita_x_preferred":[
        "Novosedly"
    ],
    "name:nld_x_preferred":[
        "Novosedly"
    ],
    "name:pol_x_preferred":[
        "Novosedly"
    ],
    "name:slk_x_preferred":[
        "Novosedly"
    ],
    "name:srp_x_preferred":[
        "\u041d\u043e\u0432\u043e\u0441\u0435\u0434\u043b\u0438"
    ],
    "name:swe_x_preferred":[
        "Novosedly"
    ],
    "wof:name":"Novosedly",
    "wof:placetype":"locality"
},
  "geometry": {"coordinates":[13.75385,50.0084],"type":"Point"}
}