{
  "type": "Feature",
  "properties": {
    "gn:admin1_code":"88.0",
    "gn:admin2_code":"020C",
    "gn:asciiname":"Novosedly",
    "gn:country_code":"CZ",
    "gn:dem":397,
    "gn:feature_class":"P",
    "gn:feature_code":"PPL",
    "gn:name":"Novosedly",
    "gn:population":0,
    "gn:timezone":"Europe/Prague",
    "iso:country":"CZ",
    "wof:name":"Novosedly",
    "wof:placetype":"locality"
},
  "geometry": {"coordinates":[13.75385,50.0084],"type":"Point"}
}