{
  "type": "Feature",
  "properties": {
    "gn:gn_country":"CZ",
    "gn:gn_fcode":"PPL",
    "gn:gn_pop":427,
    "gn:population":427,
    "iso:country":"CZ",
    "name:azb_x_preferred":[
        "\u062f\u06cc\u06cc\u0627\u06a9\u0648\u0648\u06cc\u062a\u0634\u06a9\u06cc"
    ],
    "name:ceb_x_preferred":[
        "Dyj\u00e1kovi\u010dky"
    ],
    "name:ces_x_preferred":[
        "Dyj\u00e1kovi\u010dky"
    ],
    "name:deu_x_preferred":[
        "Dyj\u00e1kovi\u010dky"
    ],
    "name:eng_x_preferred":[
        "Dyj\u00e1kovi\u010dky"
    ],
    "name:eus_x_preferred":[
        "Dyj\u00e1kovi\u010dky"
    ],
    "name:fas_x_preferred":[
        "\u062f\u06cc\u06cc\u0627\u06a9\u0648\u0648\u06cc\u062a\u0634\u06a9\u06cc"
    ],
    "name:fra_x_preferred":[
        "Dyj\u00e1kovi\u010dky"
    ],
    "name:hun_x_preferred":[
        "Dyj\u00e1kovi\u010dky"
    ],
    "name:ita_x_preferred":[
        "Dyj\u00e1kovi\u010dky"
    ],
    "name:msa_x_preferred":[
        "Dyj\u00e1kovi\u010dky"
    ],
    "name:nan_x_preferred":[
        "Dyj\u00e1kovi\u010dky"
    ],
    "name:nld_x_preferred":[
        "Dyj\u00e1kovi\u010dky"
    ],
    "name:pol_x_preferred":[
        "Dyj\u00e1kovi\u010dky"
    ],
    "name:por_x_preferred":[
        "Dyj\u00e1kovi\u010dky"
    ],
    "name:rup_x_preferred":[
        "Dyj\u00e1kovi\u010dky"
    ],
    "name:slk_x_preferred":[
        "Dyj\u00e1kovi\u010dky"
    ],
    "name:spa_x_preferred":[
        "Dyj\u00e1kovi\u010dky"
    ],
    "name:srp_x_preferred":[
        "\u0414\u0438\u0458\u0430\u043a\u043e\u0432\u0438\u0447\u043a\u0438"
    ],
    "name:swe_x_preferred":[
        "Dyj\u00e1kovi\u010dky"
    ],
    "name:unk_x_variant":[
        "Klein-Tajax"
    ],
    "name:vie_x_preferred":[
        "Dyj\u00e1kovi\u010dky"
    ],
    "qs_pg:aaroncc":"CZ",
    "qs_pg:gn_country":"CZ",
    "qs_pg:gn_fcode":"PPL",
    "qs_pg:gn_pop":427,
    "qs_pg:name":"Dyj\u00e1kovi\u010dky",
    "qs_pg:name_adm0":"\u010cesk\u00e1 republika",
    "qs_pg:name_adm1":"Jihomoravsk\u00fd kraj",
    "qs_pg:photos_9k":1,
    "qs_pg:photos_9r":1,
    "qs_pg:photos_all":2,
    "qs_pg:photos_sr":0,
    "qs_pg:pop_sr":2,
    "qs_pg:qs_pg_placetype":"locality",
    "qs_pg:qs_pg_placetype_gp":"Town",
    "qs_pg:woe_adm0":23424810,
    "woe:adm0_id":23424810,
    "woe:name_adm0":"\u010cesk\u00e1 republika",
    "woe:name_adm1":"Jihomoravsk\u00fd kraj",
    "woe:placetype":"Town",
    "wof:name":"Dyj\u00e1kovi\u010dky",
    "wof:placetype":"locality",
    "wof:population":427
},
  "geometry": {"coordinates":[16.09563,48.7823],"type":"Point"}
}