{
  "type": "Feature",
  "properties": {
    "gn:country":"CZ",
    "gn:fcode":"PPL",
    "gn:population":399,
    "iso:country":"CZ",
    "name:bel_x_preferred":[
        "\u0425\u0430\u0446\u043d\u0435\u0451\u0432\u0456\u0446\u044d"
    ],
    "name:ceb_x_preferred":[
        "Chocn\u011bjovice"
    ],
    "name:ces_x_preferred":[
        "Chocn\u011bjovice"
    ],
    "name:deu_x_preferred":[
        "Chocn\u011bjovice"
    ],
    "name:eng_x_preferred":[
        "Chocn\u011bjovice"
    ],
    "name:eus_x_preferred":[
        "Chocn\u011bjovice"
    ],
    "name:fas_x_preferred":[
        "\u062e\u0648\u062a\u0633\u0646\u06cc\u06cc\u0648\u0648\u06cc\u062a\u0633\u0647"
    ],
    "name:fra_x_preferred":[
        "Chocn\u011bjovice"
    ],
    "name:hun_x_preferred":[
        "Chocn\u011bjovice"
    ],
    "name:ita_x_preferred":[
        "Chocn\u011bjovice"
    ],
    "name:msa_x_preferred":[
        "Chocn\u011bjovice"
    ],
    "name:nan_x_preferred":[
        "Chocn\u011bjovice"
    ],
    "name:nld_x_preferred":[
        "Chocn\u011bjovice"
    ],
    "name:pol_x_preferred":[
        "Chocn\u011bjovice"
    ],
    "name:por_x_preferred":[
        "Chocn\u011bjovice"
    ],
    "name:rup_x_preferred":[
        "Chocn\u011bjovice"
    ],
    "name:slk_x_preferred":[
        "Chocn\u011bjovice"
    ],
    "name:spa_x_preferred":[
        "Chocn\u011bjovice"
    ],
    "name:srp_x_preferred":[
        "\u0425\u043e\u0446\u045a\u0435\u0458\u043e\u0432\u0438\u0446\u0435"
    ],
    "name:swe_x_preferred":[
        "Chocn\u011bjovice"
    ],
    "name:vie_x_preferred":[
        "Chocn\u011bjovice"
    ],
    "qs_pg:aaroncc":"CZ",
    "qs_pg:gn_country":"CZ",
    "qs_pg:gn_fcode":"PPL",
    "qs_pg:gn_pop":399,
    "qs_pg:name":"Chocn\u011bjovice",
    "qs_pg:name_adm0":"\u010cesk\u00e1 republika",
    "qs_pg:name_adm1":"St\u0159edo\u010desk\u00fd kraj",
    "qs_pg:photos_9r":0,
    "qs_pg:photos_sr":0,
    "qs_pg:pop_sr":2,
    "qs_pg:qs_pg_placetype":"locality",
    "qs_pg:qs_pg_placetype_gp":"Town",
    "qs_pg:woe_adm0":23424810,
    "woe:adm0_id":23424810,
    "woe:name_adm0":"\u010cesk\u00e1 republika",
    "woe:name_adm1":"St\u0159edo\u010desk\u00fd kraj",
    "woe:placetype":"Town",
    "wof:name":"Chocn\u011bjovice",
    "wof:placetype":"locality",
    "wof:population":399
},
  "geometry": {"coordinates":[14.97139,50.57691],"type":"Point"}
}