{
  "type": "Feature",
  "properties": {
    "gn:admin1_code":"79.0",
    "gn:admin2_code":"0312",
    "gn:asciiname":"Ostrov",
    "gn:country_code":"CZ",
    "gn:dem":767,
    "gn:feature_class":"P",
    "gn:feature_code":"PPL",
    "gn:name":"Ostrov",
    "gn:population":0,
    "gn:timezone":"Europe/Prague",
    "iso:country":"CZ",
    "name:und_x_variant":[
        "W\u00f6rles",
        "Ostrov"
    ],
    "wof:name":"Ostrov",
    "wof:placetype":"locality"
},
  "geometry": {"coordinates":[14.28922,48.67425],"type":"Point"}
}