{
  "type": "Feature",
  "properties": {
    "iso:country":"CZ",
    "name:ceb_x_preferred":[
        "Doln\u00ed Be\u010dva"
    ],
    "name:ces_x_preferred":[
        "Doln\u00ed Be\u010dva"
    ],
    "name:deu_x_preferred":[
        "Doln\u00ed Be\u010dva"
    ],
    "name:epo_x_preferred":[
        "Doln\u00ed Be\u010dva"
    ],
    "name:eus_x_preferred":[
        "Doln\u00ed Be\u010dva"
    ],
    "name:fra_x_preferred":[
        "Doln\u00ed Be\u010dva"
    ],
    "name:hun_x_preferred":[
        "Doln\u00ed Be\u010dva"
    ],
    "name:ita_x_preferred":[
        "Doln\u00ed Be\u010dva"
    ],
    "name:msa_x_preferred":[
        "Doln\u00ed Be\u010dva"
    ],
    "name:nld_x_preferred":[
        "Doln\u00ed Be\u010dva"
    ],
    "name:pol_x_preferred":[
        "Doln\u00ed Be\u010dva"
    ],
    "name:por_x_preferred":[
        "Doln\u00ed Be\u010dva"
    ],
    "name:slk_x_preferred":[
        "Doln\u00ed Be\u010dva"
    ],
    "name:spa_x_preferred":[
        "Doln\u00ed Be\u010dva"
    ],
    "name:srp_x_preferred":[
        "\u0414\u043e\u043b\u045a\u0438 \u0411\u0435\u0447\u0432\u0430"
    ],
    "name:swe_x_preferred":[
        "Doln\u00ed Be\u010dva"
    ],
    "name:vie_x_preferred":[
        "Doln\u00ed Be\u010dva"
    ],
    "qs_pg:aaroncc":"CZ",
    "qs_pg:name":"Doln\u00ed Be\u010dva",
    "qs_pg:name_adm0":"\u010cesk\u00e1 republika",
    "qs_pg:name_adm1":"Zl\u00ednsk\u00fd kraj",
    "qs_pg:photos":1,
    "qs_pg:photos_1k":1,
    "qs_pg:photos_9k":1,
    "qs_pg:photos_9r":1,
    "qs_pg:photos_all":7,
    "qs_pg:photos_sr":1,
    "qs_pg:pop_sr":0,
    "qs_pg:qs_pg_placetype":"localadmin",
    "qs_pg:qs_pg_placetype_gp":"LocalAdmin",
    "qs_pg:woe_adm0":23424810,
    "woe:adm0_id":23424810,
    "woe:name_adm0":"\u010cesk\u00e1 republika",
    "woe:name_adm1":"Zl\u00ednsk\u00fd kraj",
    "woe:placetype":"LocalAdmin",
    "wof:name":"Doln\u00ed Be\u010dva",
    "wof:placetype":"localadmin"
},
  "geometry": {"coordinates":[18.1669875,49.461932],"type":"Point"}
}