{
  "type": "Feature",
  "properties": {
    "gn:admin1_code":"80.0",
    "gn:admin2_code":"0615",
    "gn:asciiname":"Rovne",
    "gn:country_code":"CZ",
    "gn:dem":604,
    "gn:feature_class":"P",
    "gn:feature_code":"PPL",
    "gn:name":"Rovn\u00e9",
    "gn:population":0,
    "gn:timezone":"Europe/Prague",
    "iso:country":"CZ",
    "wof:name":"Rovne",
    "wof:placetype":"locality"
},
  "geometry": {"coordinates":[16.16774,49.54738],"type":"Point"}
}