{
  "type": "Feature",
  "properties": {
    "iso:country":"CZ",
    "name:azb_x_preferred":[
        "\u067e\u0631\u0648\u0647\u0648\u0646\u06cc\u062a\u0633\u0647"
    ],
    "name:ceb_x_preferred":[
        "Pr\u016fhonice"
    ],
    "name:ces_x_preferred":[
        "Pr\u016fhonice"
    ],
    "name:deu_x_preferred":[
        "Pr\u016fhonice"
    ],
    "name:epo_x_preferred":[
        "Pr\u016fhonice"
    ],
    "name:eus_x_preferred":[
        "Pr\u016fhonice"
    ],
    "name:fas_x_preferred":[
        "\u067e\u0631\u0648\u0647\u0648\u0646\u06cc\u062a\u0633\u0647"
    ],
    "name:fra_x_preferred":[
        "Pr\u016fhonice"
    ],
    "name:hun_x_preferred":[
        "Pr\u016fhonice"
    ],
    "name:ita_x_preferred":[
        "Pr\u016fhonice"
    ],
    "name:msa_x_preferred":[
        "Pr\u016fhonice"
    ],
    "name:nld_x_preferred":[
        "Pr\u016fhonice"
    ],
    "name:pol_x_preferred":[
        "Pr\u016fhonice"
    ],
    "name:por_x_preferred":[
        "Pr\u016fhonice"
    ],
    "name:slk_x_preferred":[
        "Pr\u016fhonice"
    ],
    "name:spa_x_preferred":[
        "Pr\u016fhonice"
    ],
    "name:srp_x_preferred":[
        "\u041f\u0440\u0443\u0445\u043e\u045a\u0438\u0446\u0435"
    ],
    "name:swe_x_preferred":[
        "Pr\u016fhonice"
    ],
    "name:vie_x_preferred":[
        "Pr\u016fhonice"
    ],
    "qs_pg:aaroncc":"CZ",
    "qs_pg:name":"Pr\u016fhonice",
    "qs_pg:name_adm0":"\u010cesk\u00e1 republika",
    "qs_pg:name_adm1":"St\u0159edo\u010desk\u00fd kraj",
    "qs_pg:photos":10,
    "qs_pg:photos_1k":2,
    "qs_pg:photos_9k":1,
    "qs_pg:photos_9r":5,
    "qs_pg:photos_all":336,
    "qs_pg:photos_sr":1,
    "qs_pg:pop_sr":0,
    "qs_pg:qs_pg_placetype":"localadmin",
    "qs_pg:qs_pg_placetype_gp":"LocalAdmin",
    "qs_pg:woe_adm0":23424810,
    "woe:adm0_id":23424810,
    "woe:name_adm0":"\u010cesk\u00e1 republika",
    "woe:name_adm1":"St\u0159edo\u010desk\u00fd kraj",
    "woe:placetype":"LocalAdmin",
    "wof:name":"Pr\u016fhonice",
    "wof:placetype":"localadmin"
},
  "geometry": {"coordinates":[14.557308,50.000335],"type":"Point"}
}