{
  "type": "Feature",
  "properties": {
    "gn:admin1_code":"81.0",
    "gn:admin2_code":"0412",
    "gn:asciiname":"Kovarov",
    "gn:country_code":"CZ",
    "gn:dem":532,
    "gn:feature_class":"P",
    "gn:feature_code":"PPL",
    "gn:name":"Kov\u00e1\u0159ov",
    "gn:population":0,
    "gn:timezone":"Europe/Prague",
    "iso:country":"CZ",
    "wof:name":"Kovarov",
    "wof:placetype":"locality"
},
  "geometry": {"coordinates":[13.18295,50.11382],"type":"Point"}
}