{
  "type": "Feature",
  "properties": {
    "gn:admin1_code":"81.0",
    "gn:admin2_code":"0413",
    "gn:asciiname":"Liboc",
    "gn:country_code":"CZ",
    "gn:dem":590,
    "gn:feature_class":"P",
    "gn:feature_code":"PPL",
    "gn:name":"Liboc",
    "gn:population":0,
    "gn:timezone":"Europe/Prague",
    "iso:country":"CZ",
    "name:ces_x_preferred":[
        "Liboc"
    ],
    "name:nld_x_preferred":[
        "Liboc"
    ],
    "name:pol_x_preferred":[
        "Liboc"
    ],
    "name:rus_x_preferred":[
        "\u041b\u0438\u0431\u043e\u0446"
    ],
    "name:slk_x_preferred":[
        "Liboc"
    ],
    "name:und_x_variant":[
        "Frankenhammer",
        "Liboc"
    ],
    "wof:name":"Liboc",
    "wof:placetype":"locality"
},
  "geometry": {"coordinates":[12.48271,50.27235],"type":"Point"}
}