{
  "type": "Feature",
  "properties": {
    "gn:admin1_code":"85.0",
    "gn:admin2_code":"0803",
    "gn:asciiname":"Mistrovice",
    "gn:country_code":"CZ",
    "gn:dem":360,
    "gn:feature_class":"P",
    "gn:feature_code":"PPL",
    "gn:name":"Mist\u0159ovice",
    "gn:population":0,
    "gn:timezone":"Europe/Prague",
    "iso:country":"CZ",
    "name:ces_x_preferred":[
        "Mist\u0159ovice"
    ],
    "name:pol_x_preferred":[
        "Mistrzowice"
    ],
    "name:und_x_variant":[
        "Mist\u0159ovice"
    ],
    "wof:name":"Mistrovice",
    "wof:placetype":"locality"
},
  "geometry": {"coordinates":[18.57999,49.74762],"type":"Point"}
}