{
  "type": "Feature",
  "properties": {
    "gn:admin1_code":"89.0",
    "gn:admin2_code":"0426",
    "gn:asciiname":"Cinovec",
    "gn:cc2":"CZ",
    "gn:country_code":"CZ",
    "gn:dem":815,
    "gn:feature_class":"P",
    "gn:feature_code":"PPL",
    "gn:name":"C\u00ednovec",
    "gn:population":0,
    "gn:timezone":"Europe/Prague",
    "iso:country":"CZ",
    "name:und_x_variant":[
        "Zinnwald",
        "Cinvald"
    ],
    "wof:name":"Cinovec",
    "wof:placetype":"locality"
},
  "geometry": {"coordinates":[13.76898,50.7322],"type":"Point"}
}