{
  "type": "Feature",
  "properties": {
    "gn:admin1_code":"80",
    "gn:admin2_code":"0611",
    "gn:asciiname":"Zalesi",
    "gn:country_code":"CZ",
    "gn:dem":543,
    "gn:feature_class":"P",
    "gn:feature_code":"PPL",
    "gn:name":"Z\u00e1les\u00ed",
    "gn:population":0,
    "gn:timezone":"Europe/Prague",
    "iso:country":"CZ",
    "name:und_x_variant":[
        "Ger\u0161tejn",
        "Z\u00e1les\u00ed"
    ],
    "wof:name":"Zalesi",
    "wof:placetype":"locality"
},
  "geometry": {"coordinates":[15.60724,49.68293],"type":"Point"}
}