{
  "type": "Feature",
  "properties": {
    "gn:admin1_code":"84.0",
    "gn:admin2_code":"0712",
    "gn:asciiname":"Ascherwinkel",
    "gn:country_code":"CZ",
    "gn:dem":575,
    "gn:feature_class":"P",
    "gn:feature_code":"PPL",
    "gn:name":"Ascherwinkel",
    "gn:population":0,
    "gn:timezone":"Europe/Prague",
    "iso:country":"CZ",
    "wof:name":"Ascherwinkel",
    "wof:placetype":"locality"
},
  "geometry": {"coordinates":[17.56667,49.66667],"type":"Point"}
}