{
  "type": "Feature",
  "properties": {
    "gn:gn_country":"CZ",
    "gn:gn_fcode":"PPL",
    "gn:gn_pop":1051,
    "gn:population":1051,
    "iso:country":"CZ",
    "name:ces_x_preferred":[
        "Os\u00edk"
    ],
    "name:eng_x_preferred":[
        "Os\u00edk"
    ],
    "name:epo_x_preferred":[
        "Os\u00edk"
    ],
    "name:fas_x_preferred":[
        "\u0627\u0648\u0633\u06cc\u06a9"
    ],
    "name:fra_x_preferred":[
        "Os\u00edk"
    ],
    "name:hun_x_preferred":[
        "Os\u00edk"
    ],
    "name:ita_x_preferred":[
        "Os\u00edk"
    ],
    "name:msa_x_preferred":[
        "Os\u00edk"
    ],
    "name:nld_x_preferred":[
        "Os\u00edk"
    ],
    "name:por_x_preferred":[
        "Os\u00edk"
    ],
    "name:slk_x_preferred":[
        "Os\u00edk"
    ],
    "name:srp_x_preferred":[
        "\u041e\u0441\u0438\u043a"
    ],
    "name:swe_x_preferred":[
        "Os\u00edk"
    ],
    "name:vie_x_preferred":[
        "Os\u00edk"
    ],
    "qs_pg:aaroncc":"CZ",
    "qs_pg:gn_country":"CZ",
    "qs_pg:gn_fcode":"PPL",
    "qs_pg:gn_pop":1051,
    "qs_pg:name":"Os\u00edk",
    "qs_pg:name_adm0":"\u010cesk\u00e1 republika",
    "qs_pg:name_adm1":"Pardubick\u00fd kraj",
    "qs_pg:photos_9k":1,
    "qs_pg:photos_9r":1,
    "qs_pg:photos_all":2,
    "qs_pg:photos_sr":0,
    "qs_pg:pop_sr":3,
    "qs_pg:qs_pg_placetype":"locality",
    "qs_pg:qs_pg_placetype_gp":"Town",
    "qs_pg:woe_adm0":23424810,
    "woe:adm0_id":23424810,
    "woe:name_adm0":"\u010cesk\u00e1 republika",
    "woe:name_adm1":"Pardubick\u00fd kraj",
    "woe:placetype":"Town",
    "wof:name":"Os\u00edk",
    "wof:placetype":"locality",
    "wof:population":1051
},
  "geometry": {"coordinates":[16.28467,49.84355],"type":"Point"}
}