{
  "type": "Feature",
  "properties": {
    "gn:admin1_code":"88.0",
    "gn:admin2_code":"0209",
    "gn:asciiname":"Horni Jircany",
    "gn:country_code":"CZ",
    "gn:dem":406,
    "gn:feature_class":"P",
    "gn:feature_code":"PPL",
    "gn:name":"Horn\u00ed Jir\u010dany",
    "gn:population":0,
    "gn:timezone":"Europe/Prague",
    "iso:country":"CZ",
    "name:und_x_variant":[
        "Ober Jirtschan",
        "Horn\u00ed Jir\u010dany"
    ],
    "wof:name":"Horni Jircany",
    "wof:placetype":"locality"
},
  "geometry": {"coordinates":[14.55485,49.94434],"type":"Point"}
}