{
  "type": "Feature",
  "properties": {
    "gn:country":"CZ",
    "gn:fcode":"PPL",
    "gn:population":100,
    "iso:country":"CZ",
    "name:cat_x_preferred":[
        "Lito\u0161ice"
    ],
    "name:ces_x_preferred":[
        "Lito\u0161ice"
    ],
    "name:che_x_preferred":[
        "\u041b\u0438\u0442\u043e\u0448\u0438\u0446\u0435"
    ],
    "name:deu_x_preferred":[
        "Lito\u0161ice"
    ],
    "name:eng_x_preferred":[
        "Lito\u0161ice"
    ],
    "name:epo_x_preferred":[
        "Lito\u0161ice"
    ],
    "name:eus_x_preferred":[
        "Lito\u0161ice"
    ],
    "name:fra_x_preferred":[
        "Lito\u0161ice"
    ],
    "name:gle_x_preferred":[
        "Lito\u0161ice"
    ],
    "name:hun_x_preferred":[
        "Lito\u0161ice"
    ],
    "name:ita_x_preferred":[
        "Lito\u0161ice"
    ],
    "name:lmo_x_preferred":[
        "Lito\u0161ice"
    ],
    "name:msa_x_preferred":[
        "Lito\u0161ice"
    ],
    "name:nan_x_preferred":[
        "Lito\u0161ice"
    ],
    "name:nld_x_preferred":[
        "Lito\u0161ice"
    ],
    "name:pol_x_preferred":[
        "Lito\u0161ice"
    ],
    "name:por_x_preferred":[
        "Lito\u0161ice"
    ],
    "name:slk_x_preferred":[
        "Lito\u0161ice"
    ],
    "name:spa_x_preferred":[
        "Lito\u0161ice"
    ],
    "name:srp_x_preferred":[
        "\u041b\u0438\u0442\u043e\u0448\u0438\u0446\u0435"
    ],
    "name:tat_x_preferred":[
        "\u041b\u0438\u0442\u043e\u0448\u0438\u0446\u0435"
    ],
    "name:vie_x_preferred":[
        "Lito\u0161ice"
    ],
    "qs_pg:aaroncc":"CZ",
    "qs_pg:gn_country":"CZ",
    "qs_pg:gn_fcode":"PPL",
    "qs_pg:gn_pop":100,
    "qs_pg:name":"Lito\u0161ice",
    "qs_pg:name_adm0":"\u010cesk\u00e1 republika",
    "qs_pg:name_adm1":"Pardubick\u00fd kraj",
    "qs_pg:photos_9r":0,
    "qs_pg:photos_sr":0,
    "qs_pg:pop_sr":1,
    "qs_pg:qs_pg_placetype":"locality",
    "qs_pg:qs_pg_placetype_gp":"Town",
    "qs_pg:woe_adm0":23424810,
    "woe:adm0_id":23424810,
    "woe:name_adm0":"\u010cesk\u00e1 republika",
    "woe:name_adm1":"Pardubick\u00fd kraj",
    "woe:placetype":"Town",
    "wof:name":"Lito\u0161ice",
    "wof:placetype":"locality",
    "wof:population":100
},
  "geometry": {"coordinates":[15.51423,49.98483],"type":"Point"}
}