{
  "type": "Feature",
  "properties": {
    "gn:gn_country":"CZ",
    "gn:gn_fcode":"PPL",
    "gn:gn_pop":459,
    "gn:population":459,
    "iso:country":"CZ",
    "name:ceb_x_preferred":[
        "Hrusice"
    ],
    "name:ces_x_preferred":[
        "Hrusice"
    ],
    "name:eng_x_preferred":[
        "Hrusice"
    ],
    "name:epo_x_preferred":[
        "Hrusice"
    ],
    "name:eus_x_preferred":[
        "Hrusice"
    ],
    "name:fas_x_preferred":[
        "\u0647\u0631\u0648\u0633\u06cc\u062a\u0633\u0647"
    ],
    "name:fra_x_preferred":[
        "Hrusice"
    ],
    "name:hun_x_preferred":[
        "Hrusice"
    ],
    "name:hye_x_preferred":[
        "\u0540\u0580\u0578\u0582\u057d\u056b\u0581\u0565"
    ],
    "name:ita_x_preferred":[
        "Hrusice"
    ],
    "name:msa_x_preferred":[
        "Hrusice"
    ],
    "name:nan_x_preferred":[
        "Hrusice"
    ],
    "name:nld_x_preferred":[
        "Hrusice"
    ],
    "name:pol_x_preferred":[
        "Hrusice"
    ],
    "name:por_x_preferred":[
        "Hrusice"
    ],
    "name:rus_x_preferred":[
        "\u0413\u0440\u0443\u0441\u0438\u0446\u0435"
    ],
    "name:slk_x_preferred":[
        "Hrusice"
    ],
    "name:slv_x_preferred":[
        "Hrusice"
    ],
    "name:spa_x_preferred":[
        "Hrusice"
    ],
    "name:srp_x_preferred":[
        "\u0425\u0440\u0443\u0441\u0438\u0446\u0435"
    ],
    "name:swe_x_preferred":[
        "Hrusice"
    ],
    "name:unk_x_variant":[
        "Hrusitz"
    ],
    "name:vie_x_preferred":[
        "Hrusice"
    ],
    "qs_pg:aaroncc":"CZ",
    "qs_pg:gn_country":"CZ",
    "qs_pg:gn_fcode":"PPL",
    "qs_pg:gn_pop":459,
    "qs_pg:name":"Hrusice",
    "qs_pg:name_adm0":"\u010cesk\u00e1 republika",
    "qs_pg:name_adm1":"St\u0159edo\u010desk\u00fd kraj",
    "qs_pg:photos_9k":1,
    "qs_pg:photos_9r":1,
    "qs_pg:photos_all":7,
    "qs_pg:photos_sr":0,
    "qs_pg:pop_sr":2,
    "qs_pg:qs_pg_placetype":"locality",
    "qs_pg:qs_pg_placetype_gp":"Town",
    "qs_pg:woe_adm0":23424810,
    "woe:adm0_id":23424810,
    "woe:name_adm0":"\u010cesk\u00e1 republika",
    "woe:name_adm1":"St\u0159edo\u010desk\u00fd kraj",
    "woe:placetype":"Town",
    "wof:name":"Hrusice",
    "wof:placetype":"locality",
    "wof:population":459
},
  "geometry": {"coordinates":[14.73806,49.90985],"type":"Point"}
}