{
  "type": "Feature",
  "properties": {
    "gn:country":"CZ",
    "gn:fcode":"PPL",
    "gn:population":150,
    "iso:country":"CZ",
    "name:azb_x_preferred":[
        "\u06a9\u0631\u0627\u062a\u06a9\u0627 \u0648\u0633"
    ],
    "name:cat_x_preferred":[
        "Kr\u00e1tk\u00e1 Ves"
    ],
    "name:ceb_x_preferred":[
        "Kr\u00e1tk\u00e1 Ves"
    ],
    "name:ces_x_preferred":[
        "Kr\u00e1tk\u00e1 Ves"
    ],
    "name:che_x_preferred":[
        "\u041a\u0440\u0430\u0442\u043a\u0430 \u0412\u0435\u0441"
    ],
    "name:deu_x_preferred":[
        "Kr\u00e1tk\u00e1 Ves"
    ],
    "name:eng_x_preferred":[
        "Kr\u00e1tk\u00e1 Ves"
    ],
    "name:epo_x_preferred":[
        "Kr\u00e1tk\u00e1 Ves"
    ],
    "name:eus_x_preferred":[
        "Kr\u00e1tk\u00e1 Ves"
    ],
    "name:fas_x_preferred":[
        "\u06a9\u0631\u0627\u062a\u06a9\u0627 \u0648\u0633"
    ],
    "name:fra_x_preferred":[
        "Kr\u00e1tk\u00e1 Ves"
    ],
    "name:gle_x_preferred":[
        "Kr\u00e1tk\u00e1 Ves"
    ],
    "name:hun_x_preferred":[
        "Kr\u00e1tk\u00e1 Ves"
    ],
    "name:ita_x_preferred":[
        "Kr\u00e1tk\u00e1 Ves"
    ],
    "name:lmo_x_preferred":[
        "Kr\u00e1tk\u00e1 Ves"
    ],
    "name:msa_x_preferred":[
        "Kr\u00e1tk\u00e1 Ves"
    ],
    "name:nan_x_preferred":[
        "Kr\u00e1tk\u00e1 Ves"
    ],
    "name:nld_x_preferred":[
        "Kr\u00e1tk\u00e1 Ves"
    ],
    "name:pol_x_preferred":[
        "Kr\u00e1tk\u00e1 Ves"
    ],
    "name:por_x_preferred":[
        "Kr\u00e1tk\u00e1 Ves"
    ],
    "name:slk_x_preferred":[
        "Kr\u00e1tk\u00e1 Ves"
    ],
    "name:spa_x_preferred":[
        "Kr\u00e1tk\u00e1 Ves"
    ],
    "name:srp_x_preferred":[
        "\u041a\u0440\u0430\u0442\u043a\u0430 \u0412\u0435\u0441"
    ],
    "name:swe_x_preferred":[
        "Kr\u00e1tk\u00e1 Ves"
    ],
    "name:tat_x_preferred":[
        "\u041a\u0440\u0430\u0442\u043a\u0430 \u0412\u0435\u0441"
    ],
    "name:vie_x_preferred":[
        "Kr\u00e1tk\u00e1 Ves"
    ],
    "qs_pg:aaroncc":"CZ",
    "qs_pg:gn_country":"CZ",
    "qs_pg:gn_fcode":"PPL",
    "qs_pg:gn_pop":150,
    "qs_pg:name":"Kr\u00e1tk\u00e1 Ves",
    "qs_pg:name_adm0":"\u010cesk\u00e1 republika",
    "qs_pg:name_adm1":"Kraj Vyso\u010dina",
    "qs_pg:photos_9r":0,
    "qs_pg:photos_sr":0,
    "qs_pg:pop_sr":1,
    "qs_pg:qs_pg_placetype":"locality",
    "qs_pg:qs_pg_placetype_gp":"Town",
    "qs_pg:woe_adm0":23424810,
    "woe:adm0_id":23424810,
    "woe:name_adm0":"\u010cesk\u00e1 republika",
    "woe:name_adm1":"Kraj Vyso\u010dina",
    "woe:placetype":"Town",
    "wof:name":"Kr\u00e1tk\u00e1 Ves",
    "wof:placetype":"locality",
    "wof:population":150
},
  "geometry": {"coordinates":[15.68451,49.62574],"type":"Point"}
}