{
  "type": "Feature",
  "properties": {
    "gn:admin1_code":"88",
    "gn:admin2_code":"0204",
    "gn:asciiname":"Velke Chvalovice",
    "gn:country_code":"CZ",
    "gn:dem":190,
    "gn:feature_class":"P",
    "gn:feature_code":"PPL",
    "gn:name":"Velk\u00e9 Chvalovice",
    "gn:population":0,
    "gn:timezone":"Europe/Prague",
    "iso:country":"CZ",
    "wof:name":"Velke Chvalovice",
    "wof:placetype":"locality"
},
  "geometry": {"coordinates":[15.01335,50.09892],"type":"Point"}
}