{
  "type": "Feature",
  "properties": {
    "gn:gn_country":"CZ",
    "gn:gn_fcode":"PPL",
    "gn:gn_pop":86,
    "gn:population":86,
    "iso:country":"CZ",
    "name:cze_x_preferred":[
        "Kolaje"
    ],
    "name:dut_x_preferred":[
        "Kolaje"
    ],
    "name:eng_x_preferred":[
        "Kolaje"
    ],
    "name:fre_x_preferred":[
        "Kolaje"
    ],
    "name:ger_x_preferred":[
        "Kolaje"
    ],
    "name:hun_x_preferred":[
        "Kolaje"
    ],
    "name:ita_x_preferred":[
        "Kolaje"
    ],
    "name:may_x_preferred":[
        "Kolaje"
    ],
    "name:per_x_preferred":[
        "\u06a9\u0648\u0644\u0627\u06cc\u0647"
    ],
    "name:pol_x_preferred":[
        "Kolaje"
    ],
    "name:por_x_preferred":[
        "Kolaje"
    ],
    "name:slo_x_preferred":[
        "Kolaje"
    ],
    "name:srp_x_preferred":[
        "\u041a\u043e\u043b\u0430\u0458\u0435"
    ],
    "name:vie_x_preferred":[
        "Kolaje"
    ],
    "qs_pg:aaroncc":"CZ",
    "qs_pg:gn_country":"CZ",
    "qs_pg:gn_fcode":"PPL",
    "qs_pg:gn_pop":86,
    "qs_pg:name":"Kolaje",
    "qs_pg:name_adm0":"\u010cesk\u00e1 republika",
    "qs_pg:name_adm1":"St\u0159edo\u010desk\u00fd kraj",
    "qs_pg:photos_9r":0,
    "qs_pg:photos_sr":0,
    "qs_pg:pop_sr":1,
    "qs_pg:qs_pg_placetype":"locality",
    "qs_pg:qs_pg_placetype_gp":"Town",
    "qs_pg:woe_adm0":23424810,
    "woe:adm0_id":23424810,
    "woe:name_adm0":"\u010cesk\u00e1 republika",
    "woe:name_adm1":"St\u0159edo\u010desk\u00fd kraj",
    "woe:placetype":"Town",
    "wof:name":"Kolaje",
    "wof:placetype":"locality",
    "wof:population":86
},
  "geometry": {"coordinates":[15.23844,50.15537],"type":"Point"}
}