{
  "type": "Feature",
  "properties": {
    "gn:country":"CZ",
    "gn:fcode":"PPL",
    "gn:population":841,
    "iso:country":"CZ",
    "name:azb_x_preferred":[
        "\u0627\u0648\u0644\u0634\u06a9\u0627"
    ],
    "name:ceb_x_preferred":[
        "Ole\u0161ka"
    ],
    "name:ces_x_preferred":[
        "Ole\u0161ka"
    ],
    "name:deu_x_preferred":[
        "Ole\u0161ka"
    ],
    "name:eng_x_preferred":[
        "Ole\u0161ka"
    ],
    "name:eus_x_preferred":[
        "Ole\u0161ka"
    ],
    "name:fas_x_preferred":[
        "\u0627\u0648\u0644\u0634\u06a9\u0627"
    ],
    "name:fra_x_preferred":[
        "Ole\u0161ka"
    ],
    "name:hun_x_preferred":[
        "Ole\u0161ka"
    ],
    "name:ita_x_preferred":[
        "Ole\u0161ka"
    ],
    "name:kat_x_preferred":[
        "\u10dd\u10da\u10d4\u10e8\u10d9\u10d0"
    ],
    "name:msa_x_preferred":[
        "Ole\u0161ka"
    ],
    "name:nan_x_preferred":[
        "Ole\u0161ka"
    ],
    "name:nld_x_preferred":[
        "Ole\u0161ka"
    ],
    "name:pol_x_preferred":[
        "Ole\u0161ka"
    ],
    "name:por_x_preferred":[
        "Ole\u0161ka"
    ],
    "name:slk_x_preferred":[
        "Ole\u0161ka"
    ],
    "name:spa_x_preferred":[
        "Ole\u0161ka"
    ],
    "name:srp_x_preferred":[
        "\u041e\u043b\u0435\u0448\u043a\u0430"
    ],
    "name:swe_x_preferred":[
        "Ole\u0161ka"
    ],
    "name:und_x_variant":[
        "Woleschetz"
    ],
    "name:vie_x_preferred":[
        "Ole\u0161ka"
    ],
    "qs_pg:aaroncc":"CZ",
    "qs_pg:gn_country":"CZ",
    "qs_pg:gn_fcode":"PPL",
    "qs_pg:gn_pop":841,
    "qs_pg:name":"Ole\u0161ka",
    "qs_pg:name_adm0":"\u010cesk\u00e1 republika",
    "qs_pg:name_adm1":"St\u0159edo\u010desk\u00fd kraj",
    "qs_pg:photos_9r":0,
    "qs_pg:photos_sr":0,
    "qs_pg:pop_sr":2,
    "qs_pg:qs_pg_placetype":"locality",
    "qs_pg:qs_pg_placetype_gp":"Town",
    "qs_pg:woe_adm0":23424810,
    "woe:adm0_id":23424810,
    "woe:name_adm0":"\u010cesk\u00e1 republika",
    "woe:name_adm1":"St\u0159edo\u010desk\u00fd kraj",
    "woe:placetype":"Town",
    "wof:name":"Ole\u0161ka",
    "wof:placetype":"locality",
    "wof:population":841
},
  "geometry": {"coordinates":[14.91668,49.97159],"type":"Point"}
}