{
  "type": "Feature",
  "properties": {
    "gn:admin1_code":"84",
    "gn:admin2_code":"0715",
    "gn:asciiname":"Svobodin",
    "gn:country_code":"CZ",
    "gn:dem":630,
    "gn:feature_class":"P",
    "gn:feature_code":"PPL",
    "gn:name":"Svobod\u00edn",
    "gn:population":0,
    "gn:timezone":"Europe/Prague",
    "iso:country":"CZ",
    "name:und_x_variant":[
        "Freiheitsberg",
        "Svobod\u00edn"
    ],
    "wof:name":"Svobodin",
    "wof:placetype":"locality"
},
  "geometry": {"coordinates":[17.1275,50.01798],"type":"Point"}
}