{
  "type": "Feature",
  "properties": {
    "gn:admin1_code":"84.0",
    "gn:admin2_code":"0712",
    "gn:asciiname":"Olejovice",
    "gn:country_code":"CZ",
    "gn:dem":556,
    "gn:feature_class":"P",
    "gn:feature_code":"PPL",
    "gn:name":"Olejovice",
    "gn:population":0,
    "gn:timezone":"Europe/Prague",
    "iso:country":"CZ",
    "name:und_x_variant":[
        "Olstadtl",
        "Olejovice"
    ],
    "wof:name":"Olejovice",
    "wof:placetype":"locality"
},
  "geometry": {"coordinates":[17.53024,49.68024000000001],"type":"Point"}
}