{
  "type": "Feature",
  "properties": {
    "gn:country":"CZ",
    "gn:fcode":"PPL",
    "gn:population":392,
    "iso:country":"CZ",
    "name:azb_x_preferred":[
        "\u0648\u0631\u0627\u0698\u06a9\u0648\u0648"
    ],
    "name:ceb_x_preferred":[
        "Vra\u017ekov"
    ],
    "name:ces_x_preferred":[
        "Vra\u017ekov"
    ],
    "name:deu_x_preferred":[
        "Vra\u017ekov"
    ],
    "name:eng_x_preferred":[
        "Vra\u017ekov"
    ],
    "name:epo_x_preferred":[
        "Vra\u017ekov"
    ],
    "name:eus_x_preferred":[
        "Vra\u017ekov"
    ],
    "name:fas_x_preferred":[
        "\u0648\u0631\u0627\u0698\u06a9\u0648\u0648"
    ],
    "name:fra_x_preferred":[
        "Vra\u017ekov"
    ],
    "name:hun_x_preferred":[
        "Vra\u017ekov"
    ],
    "name:ita_x_preferred":[
        "Vra\u017ekov"
    ],
    "name:msa_x_preferred":[
        "Vra\u017ekov"
    ],
    "name:nan_x_preferred":[
        "Vra\u017ekov"
    ],
    "name:nld_x_preferred":[
        "Vra\u017ekov"
    ],
    "name:por_x_preferred":[
        "Vra\u017ekov"
    ],
    "name:slk_x_preferred":[
        "Vra\u017ekov"
    ],
    "name:spa_x_preferred":[
        "Vra\u017ekov"
    ],
    "name:srp_x_preferred":[
        "\u0412\u0440\u0430\u0448\u043a\u043e\u0432"
    ],
    "name:swe_x_preferred":[
        "Vra\u017ekov"
    ],
    "name:vie_x_preferred":[
        "Vra\u017ekov"
    ],
    "qs_pg:aaroncc":"CZ",
    "qs_pg:gn_country":"CZ",
    "qs_pg:gn_fcode":"PPL",
    "qs_pg:gn_pop":392,
    "qs_pg:name":"Vra\u017ekov",
    "qs_pg:name_adm0":"\u010cesk\u00e1 republika",
    "qs_pg:name_adm1":"\u00dasteck\u00fd kraj",
    "qs_pg:photos_9k":1,
    "qs_pg:photos_9r":1,
    "qs_pg:photos_all":1,
    "qs_pg:photos_sr":0,
    "qs_pg:pop_sr":2,
    "qs_pg:qs_pg_placetype":"locality",
    "qs_pg:qs_pg_placetype_gp":"Town",
    "qs_pg:woe_adm0":23424810,
    "woe:adm0_id":23424810,
    "woe:name_adm0":"\u010cesk\u00e1 republika",
    "woe:name_adm1":"\u00dasteck\u00fd kraj",
    "woe:placetype":"Town",
    "wof:name":"Vra\u017ekov",
    "wof:placetype":"locality",
    "wof:population":392
},
  "geometry": {"coordinates":[14.26804,50.37343],"type":"Point"}
}