{
  "type": "Feature",
  "properties": {
    "gn:admin1_code":"88.0",
    "gn:admin2_code":"020B",
    "gn:asciiname":"Pnovice",
    "gn:country_code":"CZ",
    "gn:dem":511,
    "gn:feature_class":"P",
    "gn:feature_code":"PPL",
    "gn:name":"P\u0148ovice",
    "gn:population":0,
    "gn:timezone":"Europe/Prague",
    "iso:country":"CZ",
    "wof:name":"Pnovice",
    "wof:placetype":"locality"
},
  "geometry": {"coordinates":[13.91329,49.58861],"type":"Point"}
}