{
  "type": "Feature",
  "properties": {
    "iso:country":"CZ",
    "name:ceb_x_preferred":[
        "Vranov"
    ],
    "name:ces_x_preferred":[
        "Vranov nad Dyj\u00ed"
    ],
    "name:deu_x_preferred":[
        "Vranov nad Dyj\u00ed"
    ],
    "name:epo_x_preferred":[
        "Vranov nad Dyj\u00ed"
    ],
    "name:est_x_preferred":[
        "Vranov nad Dyj\u00ed"
    ],
    "name:eus_x_preferred":[
        "Vranov nad Dyj\u00ed"
    ],
    "name:fas_x_preferred":[
        "\u0648\u0631\u0627\u0646\u0648\u0641 \u0646\u0627\u062f \u062f\u06cc\u06cc\u06cc"
    ],
    "name:fra_x_preferred":[
        "Vranov nad Dyj\u00ed"
    ],
    "name:hun_x_preferred":[
        "Vranov nad Dyj\u00ed"
    ],
    "name:ita_x_preferred":[
        "Vranov nad Dyj\u00ed"
    ],
    "name:msa_x_preferred":[
        "Vranov nad Dyj\u00ed"
    ],
    "name:nld_x_preferred":[
        "Vranov nad Dyj\u00ed"
    ],
    "name:pol_x_preferred":[
        "Vranov nad Dyj\u00ed"
    ],
    "name:por_x_preferred":[
        "Vranov nad Dyj\u00ed"
    ],
    "name:rus_x_preferred":[
        "\u0412\u0440\u0430\u043d\u043e\u0432-\u043d\u0430\u0434-\u0414\u0438\u0439\u0438"
    ],
    "name:slk_x_preferred":[
        "Vranov nad Dyj\u00ed"
    ],
    "name:spa_x_preferred":[
        "Vranov nad Dyj\u00ed"
    ],
    "name:sqi_x_preferred":[
        "Vranov nad Dyji"
    ],
    "name:srp_x_preferred":[
        "\u0412\u0440\u0430\u043d\u043e\u0432 \u043d\u0430 \u0414\u0438\u0458\u0438"
    ],
    "name:swe_x_preferred":[
        "Vranov nad Dyj\u00ed"
    ],
    "name:vie_x_preferred":[
        "Vranov nad Dyj\u00ed"
    ],
    "qs_pg:aaroncc":"CZ",
    "qs_pg:name":"Vranov nad Dyj\u00ed",
    "qs_pg:name_adm0":"\u010cesk\u00e1 republika",
    "qs_pg:name_adm1":"Jihomoravsk\u00fd kraj",
    "qs_pg:photos":1,
    "qs_pg:photos_1k":1,
    "qs_pg:photos_9k":1,
    "qs_pg:photos_9r":4,
    "qs_pg:photos_all":223,
    "qs_pg:photos_sr":1,
    "qs_pg:pop_sr":0,
    "qs_pg:qs_pg_placetype":"localadmin",
    "qs_pg:qs_pg_placetype_gp":"LocalAdmin",
    "qs_pg:woe_adm0":23424810,
    "woe:adm0_id":23424810,
    "woe:name_adm0":"\u010cesk\u00e1 republika",
    "woe:name_adm1":"Jihomoravsk\u00fd kraj",
    "woe:placetype":"LocalAdmin",
    "wof:name":"Vranov nad Dyj\u00ed",
    "wof:placetype":"localadmin"
},
  "geometry": {"coordinates":[15.815806,48.91217],"type":"Point"}
}