{
  "type": "Feature",
  "properties": {
    "gn:country":"CZ",
    "gn:fcode":"PPL",
    "gn:population":214,
    "iso:country":"CZ",
    "name:ceb_x_preferred":[
        "La\u017eany"
    ],
    "name:ces_x_preferred":[
        "La\u017eany"
    ],
    "name:deu_x_preferred":[
        "La\u017eany u Sychrova"
    ],
    "name:eng_x_preferred":[
        "La\u017eany"
    ],
    "name:eus_x_preferred":[
        "La\u017eany"
    ],
    "name:fra_x_preferred":[
        "La\u017eany"
    ],
    "name:hun_x_preferred":[
        "La\u017eany"
    ],
    "name:ita_x_preferred":[
        "La\u017eany"
    ],
    "name:msa_x_preferred":[
        "La\u017eany"
    ],
    "name:nan_x_preferred":[
        "La\u017eany"
    ],
    "name:nld_x_preferred":[
        "La\u017eany"
    ],
    "name:pol_x_preferred":[
        "La\u017eany"
    ],
    "name:por_x_preferred":[
        "La\u017eany"
    ],
    "name:rup_x_preferred":[
        "La\u017eany"
    ],
    "name:slk_x_preferred":[
        "La\u017eany"
    ],
    "name:srp_x_preferred":[
        "\u041b\u0430\u0436\u0430\u043d\u0438"
    ],
    "name:swe_x_preferred":[
        "La\u017eany"
    ],
    "name:vie_x_preferred":[
        "La\u017eany"
    ],
    "qs_pg:aaroncc":"CZ",
    "qs_pg:gn_country":"CZ",
    "qs_pg:gn_fcode":"PPL",
    "qs_pg:gn_pop":214,
    "qs_pg:name":"La\u017eany",
    "qs_pg:name_adm0":"\u010cesk\u00e1 republika",
    "qs_pg:name_adm1":"Libereck\u00fd kraj",
    "qs_pg:photos_9k":1,
    "qs_pg:photos_9r":1,
    "qs_pg:photos_all":1,
    "qs_pg:photos_sr":0,
    "qs_pg:pop_sr":2,
    "qs_pg:qs_pg_placetype":"locality",
    "qs_pg:qs_pg_placetype_gp":"Town",
    "qs_pg:woe_adm0":23424810,
    "woe:adm0_id":23424810,
    "woe:name_adm0":"\u010cesk\u00e1 republika",
    "woe:name_adm1":"Libereck\u00fd kraj",
    "woe:placetype":"Town",
    "wof:name":"La\u017eany",
    "wof:placetype":"locality",
    "wof:population":214
},
  "geometry": {"coordinates":[15.10974,50.6009],"type":"Point"}
}