{
  "type": "Feature",
  "properties": {
    "gn:admin1_code":"82",
    "gn:admin2_code":"0522",
    "gn:asciiname":"Zebin",
    "gn:country_code":"CZ",
    "gn:dem":333,
    "gn:feature_class":"P",
    "gn:feature_code":"PPL",
    "gn:name":"Zeb\u00edn",
    "gn:population":0,
    "gn:timezone":"Europe/Prague",
    "iso:country":"CZ",
    "wof:name":"Zebin",
    "wof:placetype":"locality"
},
  "geometry": {"coordinates":[15.3731,50.4516],"type":"Point"}
}