{
  "type": "Feature",
  "properties": {
    "gn:admin1_code":"87.0",
    "gn:admin2_code":"0324",
    "gn:asciiname":"Kbelnice",
    "gn:country_code":"CZ",
    "gn:dem":527,
    "gn:feature_class":"P",
    "gn:feature_code":"PPL",
    "gn:name":"Kbelnice",
    "gn:population":0,
    "gn:timezone":"Europe/Prague",
    "iso:country":"CZ",
    "wof:name":"Kbelnice",
    "wof:placetype":"locality"
},
  "geometry": {"coordinates":[13.44057,49.5417],"type":"Point"}
}