{
  "type": "Feature",
  "properties": {
    "gn:admin1_code":"87.0",
    "gn:admin2_code":"0322",
    "gn:asciiname":"Bernartice",
    "gn:country_code":"CZ",
    "gn:dem":592,
    "gn:feature_class":"P",
    "gn:feature_code":"PPL",
    "gn:name":"Bernartice",
    "gn:population":0,
    "gn:timezone":"Europe/Prague",
    "iso:country":"CZ",
    "name:ceb_x_preferred":[
        "Bernartice"
    ],
    "name:ces_x_preferred":[
        "Bernartice"
    ],
    "name:deu_x_preferred":[
        "Bernartice"
    ],
    "name:epo_x_preferred":[
        "Bernartice"
    ],
    "name:fra_x_preferred":[
        "Bernartice"
    ],
    "name:ita_x_preferred":[
        "Bernartice"
    ],
    "name:nld_x_preferred":[
        "Bernartice"
    ],
    "name:slk_x_preferred":[
        "Bernartice"
    ],
    "name:srp_x_preferred":[
        "\u0411\u0435\u0440\u043d\u0430\u0440\u0442\u0438\u0446\u0435"
    ],
    "name:swe_x_preferred":[
        "Bernartice"
    ],
    "wof:name":"Bernartice",
    "wof:placetype":"locality"
},
  "geometry": {"coordinates":[13.38427,49.31947],"type":"Point"}
}