{
  "type": "Feature",
  "properties": {
    "gn:admin1_code":"87.0",
    "gn:admin2_code":"0322",
    "gn:asciiname":"Bernartice",
    "gn:country_code":"CZ",
    "gn:dem":592,
    "gn:feature_class":"P",
    "gn:feature_code":"PPL",
    "gn:name":"Bernartice",
    "gn:population":0,
    "gn:timezone":"Europe/Prague",
    "iso:country":"CZ",
    "wof:name":"Bernartice",
    "wof:placetype":"locality"
},
  "geometry": {"coordinates":[13.38427,49.31947],"type":"Point"}
}