{
  "type": "Feature",
  "properties": {
    "gn:admin1_code":"79.0",
    "gn:admin2_code":"0312",
    "gn:asciiname":"Smrhov",
    "gn:country_code":"CZ",
    "gn:dem":588,
    "gn:feature_class":"P",
    "gn:feature_code":"PPL",
    "gn:name":"Smrhov",
    "gn:population":0,
    "gn:timezone":"Europe/Prague",
    "iso:country":"CZ",
    "wof:name":"Smrhov",
    "wof:placetype":"locality"
},
  "geometry": {"coordinates":[14.52528,48.77116],"type":"Point"}
}