{
  "type": "Feature",
  "properties": {
    "gn:gn_country":"CZ",
    "gn:gn_fcode":"PPL",
    "gn:gn_pop":419,
    "gn:population":419,
    "iso:country":"CZ",
    "name:cze_x_preferred":[
        "B\u011bha\u0159ovice"
    ],
    "name:dut_x_preferred":[
        "B\u011bha\u0159ovice"
    ],
    "name:eng_x_preferred":[
        "B\u011bha\u0159ovice"
    ],
    "name:fre_x_preferred":[
        "B\u011bha\u0159ovice"
    ],
    "name:hun_x_preferred":[
        "B\u011bha\u0159ovice"
    ],
    "name:ita_x_preferred":[
        "B\u011bha\u0159ovice"
    ],
    "name:may_x_preferred":[
        "B\u011bha\u0159ovice"
    ],
    "name:per_x_preferred":[
        "\u0628\u06cc\u0647\u0627\u0631\u0648\u0648\u06cc\u062a\u0633\u0647"
    ],
    "name:pol_x_preferred":[
        "B\u011bha\u0159ovice"
    ],
    "name:por_x_preferred":[
        "B\u011bha\u0159ovice"
    ],
    "name:slo_x_preferred":[
        "B\u011bha\u0159ovice"
    ],
    "name:srp_x_preferred":[
        "\u0411\u0458\u0435\u0445\u0430\u0440\u0436\u043e\u0432\u0438\u0446\u0435"
    ],
    "name:swe_x_preferred":[
        "B\u011bharovice"
    ],
    "name:unk_x_variant":[
        "Biharzowitz"
    ],
    "name:vie_x_preferred":[
        "B\u011bha\u0159ovice"
    ],
    "qs_pg:aaroncc":"CZ",
    "qs_pg:gn_country":"CZ",
    "qs_pg:gn_fcode":"PPL",
    "qs_pg:gn_pop":419,
    "qs_pg:name":"B\u011bha\u0159ovice",
    "qs_pg:name_adm0":"\u010cesk\u00e1 republika",
    "qs_pg:name_adm1":"Jihomoravsk\u00fd kraj",
    "qs_pg:photos_9r":0,
    "qs_pg:photos_sr":0,
    "qs_pg:pop_sr":2,
    "qs_pg:qs_pg_placetype":"locality",
    "qs_pg:qs_pg_placetype_gp":"Town",
    "qs_pg:woe_adm0":23424810,
    "woe:adm0_id":23424810,
    "woe:name_adm0":"\u010cesk\u00e1 republika",
    "woe:name_adm1":"Jihomoravsk\u00fd kraj",
    "woe:placetype":"Town",
    "wof:name":"B\u011bha\u0159ovice",
    "wof:placetype":"locality",
    "wof:population":419
},
  "geometry": {"coordinates":[16.07862,49.00394],"type":"Point"}
}