{
  "type": "Feature",
  "properties": {
    "gn:admin1_code":"88.0",
    "gn:admin2_code":"0201",
    "gn:asciiname":"Dalesice",
    "gn:country_code":"CZ",
    "gn:dem":382,
    "gn:feature_class":"P",
    "gn:feature_code":"PPL",
    "gn:name":"Dale\u0161ice",
    "gn:population":0,
    "gn:timezone":"Europe/Prague",
    "iso:country":"CZ",
    "name:und_x_variant":[
        "Daleschitz",
        "Dale\u0161ice"
    ],
    "wof:name":"Dalesice",
    "wof:placetype":"locality"
},
  "geometry": {"coordinates":[14.48076,49.78811],"type":"Point"}
}