{
  "type": "Feature",
  "properties": {
    "gn:admin1_code":"81.0",
    "gn:admin2_code":"0413",
    "gn:asciiname":"Kamen",
    "gn:country_code":"CZ",
    "gn:dem":716,
    "gn:feature_class":"P",
    "gn:feature_code":"PPL",
    "gn:name":"K\u00e1men",
    "gn:population":0,
    "gn:timezone":"Europe/Prague",
    "iso:country":"CZ",
    "name:ara_x_preferred":[
        "\u0643\u0627\u0645\u0646"
    ],
    "name:azb_x_preferred":[
        "\u06a9\u0627\u0645\u0646"
    ],
    "name:cat_x_preferred":[
        "Kamen"
    ],
    "name:deu_x_preferred":[
        "Kamen"
    ],
    "name:epo_x_preferred":[
        "Kamen"
    ],
    "name:est_x_preferred":[
        "Kamen"
    ],
    "name:fas_x_preferred":[
        "\u06a9\u0627\u0645\u0646"
    ],
    "name:fin_x_preferred":[
        "Kamen"
    ],
    "name:fra_x_preferred":[
        "Kamen"
    ],
    "name:hun_x_preferred":[
        "Kamen"
    ],
    "name:ita_x_preferred":[
        "Kamen"
    ],
    "name:jpn_x_preferred":[
        "\u30ab\u30fc\u30e1\u30f3"
    ],
    "name:kaz_x_preferred":[
        "\u041a\u0430\u043c\u0435\u043d"
    ],
    "name:kir_x_preferred":[
        "\u041a\u0430\u043c\u0435\u043d"
    ],
    "name:lat_x_preferred":[
        "Camena"
    ],
    "name:lit_x_preferred":[
        "Kamenas"
    ],
    "name:msa_x_preferred":[
        "Kamen"
    ],
    "name:nds_x_preferred":[
        "Kamen"
    ],
    "name:nld_x_preferred":[
        "Kamen"
    ],
    "name:oci_x_preferred":[
        "Kamen"
    ],
    "name:pol_x_preferred":[
        "Kamen"
    ],
    "name:por_x_preferred":[
        "Kamen"
    ],
    "name:ron_x_preferred":[
        "Kamen"
    ],
    "name:rus_x_preferred":[
        "\u041a\u0430\u043c\u0435\u043d"
    ],
    "name:spa_x_preferred":[
        "Kamen"
    ],
    "name:srp_x_preferred":[
        "\u041a\u0430\u043c\u0435\u043d"
    ],
    "name:swe_x_preferred":[
        "Kamen"
    ],
    "name:szl_x_preferred":[
        "Kamen"
    ],
    "name:tat_x_preferred":[
        "\u041a\u0430\u043c\u0435\u043d"
    ],
    "name:tur_x_preferred":[
        "Kamen"
    ],
    "name:ukr_x_preferred":[
        "\u041a\u0430\u043c\u0435\u043d"
    ],
    "name:und_x_variant":[
        "Stein",
        "K\u00e1men"
    ],
    "name:uzb_x_preferred":[
        "Kamen"
    ],
    "name:vol_x_preferred":[
        "Kamen"
    ],
    "name:war_x_preferred":[
        "Kamen"
    ],
    "name:zho_x_preferred":[
        "\u5361\u9580"
    ],
    "wof:name":"Kamen",
    "wof:placetype":"locality"
},
  "geometry": {"coordinates":[12.41424,50.30236],"type":"Point"}
}