{
  "type": "Feature",
  "properties": {
    "gn:admin1_code":"81.0",
    "gn:admin2_code":"0413",
    "gn:asciiname":"Kamen",
    "gn:country_code":"CZ",
    "gn:dem":716,
    "gn:feature_class":"P",
    "gn:feature_code":"PPL",
    "gn:name":"K\u00e1men",
    "gn:population":0,
    "gn:timezone":"Europe/Prague",
    "iso:country":"CZ",
    "name:und_x_variant":[
        "Stein",
        "K\u00e1men"
    ],
    "wof:name":"Kamen",
    "wof:placetype":"locality"
},
  "geometry": {"coordinates":[12.41424,50.30236],"type":"Point"}
}