{
  "type": "Feature",
  "properties": {
    "gn:country":"CZ",
    "gn:fcode":"PPL",
    "gn:population":949,
    "iso:country":"CZ",
    "name:cat_x_preferred":[
        "\u010ceperka"
    ],
    "name:ceb_x_preferred":[
        "\u010ceperka"
    ],
    "name:ces_x_preferred":[
        "\u010ceperka"
    ],
    "name:che_x_preferred":[
        "\u0427\u0435\u043f\u0435\u0440\u043a\u0430"
    ],
    "name:deu_x_preferred":[
        "\u010ceperka"
    ],
    "name:eng_x_preferred":[
        "\u010ceperka"
    ],
    "name:epo_x_preferred":[
        "\u010ceperka"
    ],
    "name:eus_x_preferred":[
        "\u010ceperka"
    ],
    "name:fas_x_preferred":[
        "\u062a\u0634\u067e\u0631\u06a9\u0627"
    ],
    "name:fra_x_preferred":[
        "\u010ceperka"
    ],
    "name:gle_x_preferred":[
        "\u010ceperka"
    ],
    "name:hun_x_preferred":[
        "\u010ceperka"
    ],
    "name:ita_x_preferred":[
        "\u010ceperka"
    ],
    "name:lmo_x_preferred":[
        "\u010ceperka"
    ],
    "name:msa_x_preferred":[
        "\u010ceperka"
    ],
    "name:nan_x_preferred":[
        "\u010ceperka"
    ],
    "name:nld_x_preferred":[
        "\u010ceperka"
    ],
    "name:pol_x_preferred":[
        "\u010ceperka"
    ],
    "name:por_x_preferred":[
        "\u010ceperka"
    ],
    "name:slk_x_preferred":[
        "\u010ceperka"
    ],
    "name:spa_x_preferred":[
        "\u010ceperka"
    ],
    "name:srp_x_preferred":[
        "\u0427\u0435\u043f\u0435\u0440\u043a\u0430"
    ],
    "name:swe_x_preferred":[
        "\u010ceperka"
    ],
    "name:tat_x_preferred":[
        "\u0427\u0435\u043f\u0435\u0440\u043a\u0430"
    ],
    "name:vie_x_preferred":[
        "\u010ceperka"
    ],
    "qs_pg:aaroncc":"CZ",
    "qs_pg:gn_country":"CZ",
    "qs_pg:gn_fcode":"PPL",
    "qs_pg:gn_pop":949,
    "qs_pg:name":"\u010ceperka",
    "qs_pg:name_adm0":"\u010cesk\u00e1 republika",
    "qs_pg:name_adm1":"Pardubick\u00fd kraj",
    "qs_pg:photos_9k":1,
    "qs_pg:photos_9r":1,
    "qs_pg:photos_all":1,
    "qs_pg:photos_sr":0,
    "qs_pg:pop_sr":2,
    "qs_pg:qs_pg_placetype":"locality",
    "qs_pg:qs_pg_placetype_gp":"Town",
    "qs_pg:woe_adm0":23424810,
    "woe:adm0_id":23424810,
    "woe:name_adm0":"\u010cesk\u00e1 republika",
    "woe:name_adm1":"Pardubick\u00fd kraj",
    "woe:placetype":"Town",
    "wof:name":"\u010ceperka",
    "wof:placetype":"locality",
    "wof:population":949
},
  "geometry": {"coordinates":[15.77323,50.13302],"type":"Point"}
}