{
  "type": "Feature",
  "properties": {
    "gn:admin1_code":"86",
    "gn:admin2_code":"0531",
    "gn:asciiname":"Stary Dvur",
    "gn:country_code":"CZ",
    "gn:dem":418,
    "gn:feature_class":"P",
    "gn:feature_code":"PPL",
    "gn:name":"Star\u00fd Dv\u016fr",
    "gn:population":0,
    "gn:timezone":"Europe/Prague",
    "iso:country":"CZ",
    "wof:name":"Stary Dvur",
    "wof:placetype":"locality"
},
  "geometry": {"coordinates":[15.60792,49.87583],"type":"Point"}
}