{
  "type": "Feature",
  "properties": {
    "gn:admin1_code":"86.0",
    "gn:admin2_code":"0534",
    "gn:asciiname":"Mlynice",
    "gn:country_code":"CZ",
    "gn:dem":493,
    "gn:feature_class":"P",
    "gn:feature_code":"PPL",
    "gn:name":"Ml\u00fdnice",
    "gn:population":0,
    "gn:timezone":"Europe/Prague",
    "iso:country":"CZ",
    "name:und_x_variant":[
        "Lenzdorf"
    ],
    "wof:name":"Mlynice",
    "wof:placetype":"locality"
},
  "geometry": {"coordinates":[16.74419,50.01265],"type":"Point"}
}