{
  "type": "Feature",
  "properties": {
    "gn:gn_country":"CZ",
    "gn:gn_fcode":"PPL",
    "gn:gn_pop":349,
    "gn:population":349,
    "iso:country":"CZ",
    "name:cze_x_preferred":[
        "P\u0159edboj"
    ],
    "name:dut_x_preferred":[
        "P\u0159edboj"
    ],
    "name:eng_x_preferred":[
        "P\u0159edboj"
    ],
    "name:fre_x_preferred":[
        "P\u0159edboj"
    ],
    "name:hun_x_preferred":[
        "P\u0159edboj"
    ],
    "name:ita_x_preferred":[
        "P\u0159edboj"
    ],
    "name:may_x_preferred":[
        "P\u0159edboj"
    ],
    "name:per_x_preferred":[
        "\u067e\u0631\u062f\u0628\u0648\u06cc"
    ],
    "name:pol_x_preferred":[
        "P\u0159edboj"
    ],
    "name:por_x_preferred":[
        "P\u0159edboj"
    ],
    "name:slo_x_preferred":[
        "P\u0159edboj"
    ],
    "name:srp_x_preferred":[
        "\u041f\u0440\u0435\u0434\u0431\u043e\u0458"
    ],
    "name:swe_x_preferred":[
        "P\u0159edboj"
    ],
    "name:vie_x_preferred":[
        "P\u0159edboj"
    ],
    "qs_pg:aaroncc":"CZ",
    "qs_pg:gn_country":"CZ",
    "qs_pg:gn_fcode":"PPL",
    "qs_pg:gn_pop":349,
    "qs_pg:name":"P\u0159edboj",
    "qs_pg:name_adm0":"\u010cesk\u00e1 republika",
    "qs_pg:name_adm1":"St\u0159edo\u010desk\u00fd kraj",
    "qs_pg:photos_9k":1,
    "qs_pg:photos_9r":1,
    "qs_pg:photos_all":1,
    "qs_pg:photos_sr":0,
    "qs_pg:pop_sr":2,
    "qs_pg:qs_pg_placetype":"locality",
    "qs_pg:qs_pg_placetype_gp":"Town",
    "qs_pg:woe_adm0":23424810,
    "woe:adm0_id":23424810,
    "woe:name_adm0":"\u010cesk\u00e1 republika",
    "woe:name_adm1":"St\u0159edo\u010desk\u00fd kraj",
    "woe:placetype":"Town",
    "wof:name":"P\u0159edboj",
    "wof:placetype":"locality",
    "wof:population":349
},
  "geometry": {"coordinates":[14.47673,50.22539],"type":"Point"}
}