{
  "type": "Feature",
  "properties": {
    "gn:admin1_code":"84",
    "gn:admin2_code":"0714",
    "gn:asciiname":"Zeravice",
    "gn:country_code":"CZ",
    "gn:dem":226,
    "gn:feature_class":"P",
    "gn:feature_code":"PPL",
    "gn:name":"\u017deravice",
    "gn:population":0,
    "gn:timezone":"Europe/Prague",
    "iso:country":"CZ",
    "wof:name":"Zeravice",
    "wof:placetype":"locality"
},
  "geometry": {"coordinates":[17.39805,49.49049],"type":"Point"}
}