{
  "type": "Feature",
  "properties": {
    "gn:admin1_code":"80.0",
    "gn:admin2_code":"0613",
    "gn:asciiname":"Bitetice",
    "gn:country_code":"CZ",
    "gn:dem":582,
    "gn:feature_class":"P",
    "gn:feature_code":"PPL",
    "gn:name":"Bit\u011btice",
    "gn:population":0,
    "gn:timezone":"Europe/Prague",
    "iso:country":"CZ",
    "wof:name":"Bitetice",
    "wof:placetype":"locality"
},
  "geometry": {"coordinates":[15.14826,49.46578],"type":"Point"}
}