{
  "type": "Feature",
  "properties": {
    "gn:admin1_code":"87",
    "gn:admin2_code":"0322",
    "gn:asciiname":"Zelena Hora",
    "gn:country_code":"CZ",
    "gn:dem":868,
    "gn:feature_class":"P",
    "gn:feature_code":"PPL",
    "gn:name":"Zelen\u00e1 Hora",
    "gn:population":0,
    "gn:timezone":"Europe/Prague",
    "iso:country":"CZ",
    "name:und_x_variant":[
        "Gr\u00fcnberg",
        "Zelen\u00e1 Hora"
    ],
    "wof:name":"Zelena Hora",
    "wof:placetype":"locality"
},
  "geometry": {"coordinates":[13.45547,49.08167],"type":"Point"}
}