{
  "type": "Feature",
  "properties": {
    "gn:gn_country":"CZ",
    "gn:gn_fcode":"PPL",
    "gn:gn_pop":84,
    "gn:population":84,
    "iso:country":"CZ",
    "name:unk_x_variant":[
        "Moosh\u00e4user"
    ],
    "qs_pg:aaroncc":"CZ",
    "qs_pg:gn_country":"CZ",
    "qs_pg:gn_fcode":"PPL",
    "qs_pg:gn_pop":84,
    "qs_pg:name":"Z\u00e1blat\u00ed",
    "qs_pg:photos_9r":0,
    "qs_pg:photos_sr":0,
    "qs_pg:pop_sr":1,
    "qs_pg:qs_pg_placetype":"locality",
    "wof:name":"Z\u00e1blat\u00ed",
    "wof:placetype":"locality",
    "wof:population":84
},
  "geometry": {"coordinates":[14.92262,48.80733],"type":"Point"}
}