{
  "type": "Feature",
  "properties": {
    "gn:admin1_code":"79.0",
    "gn:admin2_code":"0316",
    "gn:asciiname":"Sedlikovice",
    "gn:country_code":"CZ",
    "gn:dem":401,
    "gn:feature_class":"P",
    "gn:feature_code":"PPL",
    "gn:name":"Sedl\u00edkovice",
    "gn:population":0,
    "gn:timezone":"Europe/Prague",
    "iso:country":"CZ",
    "wof:name":"Sedlikovice",
    "wof:placetype":"locality"
},
  "geometry": {"coordinates":[13.99245,49.25166],"type":"Point"}
}