{
  "type": "Feature",
  "properties": {
    "gn:admin1_code":"89.0",
    "gn:admin2_code":"0423",
    "gn:asciiname":"Skalice",
    "gn:cc2":"CZ",
    "gn:country_code":"CZ",
    "gn:dem":495,
    "gn:feature_class":"P",
    "gn:feature_code":"PPL",
    "gn:name":"Skalice",
    "gn:population":0,
    "gn:timezone":"Europe/Prague",
    "iso:country":"CZ",
    "name:ceb_x_preferred":[
        "Skalice"
    ],
    "name:ces_x_preferred":[
        "Skalice"
    ],
    "name:deu_x_preferred":[
        "Skalice"
    ],
    "name:fra_x_preferred":[
        "Skalice"
    ],
    "name:ita_x_preferred":[
        "Skalice"
    ],
    "name:nld_x_preferred":[
        "Skalice"
    ],
    "name:slk_x_preferred":[
        "Skalice"
    ],
    "name:srp_x_preferred":[
        "\u0421\u043a\u0430\u043b\u0438\u0446\u0435"
    ],
    "name:swe_x_preferred":[
        "Skalice"
    ],
    "name:und_x_variant":[
        "Skalitz"
    ],
    "wof:name":"Skalice",
    "wof:placetype":"locality"
},
  "geometry": {"coordinates":[13.88603,50.49574000000001],"type":"Point"}
}