{
  "type": "Feature",
  "properties": {
    "gn:admin1_code":"88",
    "gn:admin2_code":"0202",
    "gn:asciiname":"Trenice",
    "gn:country_code":"CZ",
    "gn:dem":419,
    "gn:feature_class":"P",
    "gn:feature_code":"PPL",
    "gn:name":"T\u0159enice",
    "gn:population":0,
    "gn:timezone":"Europe/Prague",
    "iso:country":"CZ",
    "wof:name":"Trenice",
    "wof:placetype":"locality"
},
  "geometry": {"coordinates":[13.82756,49.85658],"type":"Point"}
}