{
  "type": "Feature",
  "properties": {
    "gn:gn_country":"CZ",
    "gn:gn_fcode":"PPL",
    "gn:gn_pop":165,
    "gn:population":165,
    "iso:country":"CZ",
    "name:cze_x_preferred":[
        "\u010cernv\u00edr"
    ],
    "name:dut_x_preferred":[
        "\u010cernv\u00edr"
    ],
    "name:eng_x_preferred":[
        "\u010cernv\u00edr"
    ],
    "name:fre_x_preferred":[
        "\u010cernv\u00edr"
    ],
    "name:ger_x_preferred":[
        "\u010cernv\u00edr"
    ],
    "name:hun_x_preferred":[
        "\u010cernv\u00edr"
    ],
    "name:ita_x_preferred":[
        "\u010cernv\u00edr"
    ],
    "name:may_x_preferred":[
        "\u010cernv\u00edr"
    ],
    "name:nan_x_preferred":[
        "\u010cernv\u00edr"
    ],
    "name:per_x_preferred":[
        "\u062a\u0634\u0631\u0646\u0648\u06cc\u0631"
    ],
    "name:pol_x_preferred":[
        "\u010cernv\u00edr"
    ],
    "name:por_x_preferred":[
        "\u010cernv\u00edr"
    ],
    "name:rup_x_preferred":[
        "\u010cernv\u00edr"
    ],
    "name:slo_x_preferred":[
        "\u010cernv\u00edr"
    ],
    "name:swe_x_preferred":[
        "\u010cernv\u00edr"
    ],
    "name:vie_x_preferred":[
        "\u010cernv\u00edr"
    ],
    "qs_pg:aaroncc":"CZ",
    "qs_pg:gn_country":"CZ",
    "qs_pg:gn_fcode":"PPL",
    "qs_pg:gn_pop":165,
    "qs_pg:name":"\u010cernv\u00edr",
    "qs_pg:name_adm0":"\u010cesk\u00e1 republika",
    "qs_pg:name_adm1":"Kraj Vyso\u010dina",
    "qs_pg:photos_9k":1,
    "qs_pg:photos_9r":1,
    "qs_pg:photos_all":1,
    "qs_pg:photos_sr":0,
    "qs_pg:pop_sr":1,
    "qs_pg:qs_pg_placetype":"locality",
    "qs_pg:qs_pg_placetype_gp":"Town",
    "qs_pg:woe_adm0":23424810,
    "woe:adm0_id":23424810,
    "woe:name_adm0":"\u010cesk\u00e1 republika",
    "woe:name_adm1":"Kraj Vyso\u010dina",
    "woe:placetype":"Town",
    "wof:name":"\u010cernv\u00edr",
    "wof:placetype":"locality",
    "wof:population":165
},
  "geometry": {"coordinates":[16.34618,49.44531],"type":"Point"}
}