{
  "type": "Feature",
  "properties": {
    "gn:country":"CZ",
    "gn:fcode":"PPL",
    "gn:population":1014,
    "iso:country":"CZ",
    "name:ceb_x_preferred":[
        "Vil\u00e9mov"
    ],
    "name:ces_x_preferred":[
        "Vil\u00e9mov"
    ],
    "name:deu_x_preferred":[
        "Vil\u00e9mov"
    ],
    "name:fra_x_preferred":[
        "Vil\u00e9mov"
    ],
    "name:hsb_x_preferred":[
        "Vil\u00e9mov"
    ],
    "name:ita_x_preferred":[
        "Vil\u00e9mov"
    ],
    "name:nld_x_preferred":[
        "Vil\u00e9mov"
    ],
    "name:slk_x_preferred":[
        "Vil\u00e9mov"
    ],
    "name:srp_x_preferred":[
        "\u0412\u0438\u043b\u0435\u043c\u043e\u0432"
    ],
    "name:swe_x_preferred":[
        "Vil\u00e9mov"
    ],
    "qs_pg:aaroncc":"CZ",
    "qs_pg:gn_country":"CZ",
    "qs_pg:gn_fcode":"PPL",
    "qs_pg:gn_pop":1014,
    "qs_pg:name":"Vil\u00e9mov",
    "qs_pg:name_adm0":"\u010cesk\u00e1 republika",
    "qs_pg:name_adm1":"Kraj Vyso\u010dina",
    "qs_pg:photos_9r":0,
    "qs_pg:photos_sr":0,
    "qs_pg:pop_sr":3,
    "qs_pg:qs_pg_placetype":"locality",
    "qs_pg:qs_pg_placetype_gp":"Town",
    "qs_pg:woe_adm0":23424810,
    "woe:adm0_id":23424810,
    "woe:name_adm0":"\u010cesk\u00e1 republika",
    "woe:name_adm1":"Kraj Vyso\u010dina",
    "woe:placetype":"Town",
    "wof:name":"Vil\u00e9mov",
    "wof:placetype":"locality",
    "wof:population":1014
},
  "geometry": {"coordinates":[15.38347,49.53578],"type":"Point"}
}