{
  "type": "Feature",
  "properties": {
    "gn:country":"CZ",
    "gn:fcode":"PPL",
    "gn:population":545,
    "iso:country":"CZ",
    "name:azb_x_preferred":[
        "\u0628\u0648\u0644\u0647\u0648\u0634\u0633"
    ],
    "name:ceb_x_preferred":[
        "Boleho\u0161\u0165"
    ],
    "name:ces_x_preferred":[
        "Boleho\u0161\u0165"
    ],
    "name:deu_x_preferred":[
        "Boleho\u0161\u0165"
    ],
    "name:eng_x_preferred":[
        "Boleho\u0161\u0165"
    ],
    "name:eus_x_preferred":[
        "Boleho\u0161\u0165"
    ],
    "name:fas_x_preferred":[
        "\u0628\u0648\u0644\u0647\u0648\u0634\u0633"
    ],
    "name:fra_x_preferred":[
        "Boleho\u0161\u0165"
    ],
    "name:hun_x_preferred":[
        "Boleho\u0161\u0165"
    ],
    "name:ita_x_preferred":[
        "Boleho\u0161\u0165"
    ],
    "name:msa_x_preferred":[
        "Boleho\u0161\u0165"
    ],
    "name:nan_x_preferred":[
        "Boleho\u0161\u0165"
    ],
    "name:nld_x_preferred":[
        "Boleho\u0161\u0165"
    ],
    "name:pol_x_preferred":[
        "Boleho\u0161\u0165"
    ],
    "name:por_x_preferred":[
        "Boleho\u0161\u0165"
    ],
    "name:rup_x_preferred":[
        "Boleho\u0161\u0165"
    ],
    "name:slk_x_preferred":[
        "Boleho\u0161\u0165"
    ],
    "name:spa_x_preferred":[
        "Boleho\u0161\u0165"
    ],
    "name:srp_x_preferred":[
        "\u0411\u043e\u043b\u0435\u0445\u043e\u0448\u0442"
    ],
    "name:swe_x_preferred":[
        "Boleho\u0161\u0165"
    ],
    "name:und_x_variant":[
        "Bolehoscht"
    ],
    "name:vie_x_preferred":[
        "Boleho\u0161\u0165"
    ],
    "qs_pg:aaroncc":"CZ",
    "qs_pg:gn_country":"CZ",
    "qs_pg:gn_fcode":"PPL",
    "qs_pg:gn_pop":545,
    "qs_pg:name":"Boleho\u0161\u0165",
    "qs_pg:name_adm0":"\u010cesk\u00e1 republika",
    "qs_pg:name_adm1":"Kr\u00e1lov\u00e9hradeck\u00fd kraj",
    "qs_pg:photos_9r":0,
    "qs_pg:photos_sr":0,
    "qs_pg:pop_sr":2,
    "qs_pg:qs_pg_placetype":"locality",
    "qs_pg:qs_pg_placetype_gp":"Town",
    "qs_pg:woe_adm0":23424810,
    "woe:adm0_id":23424810,
    "woe:name_adm0":"\u010cesk\u00e1 republika",
    "woe:name_adm1":"Kr\u00e1lov\u00e9hradeck\u00fd kraj",
    "woe:placetype":"Town",
    "wof:name":"Boleho\u0161\u0165",
    "wof:placetype":"locality",
    "wof:population":545
},
  "geometry": {"coordinates":[16.07697,50.21363],"type":"Point"}
}