{
  "type": "Feature",
  "properties": {
    "gn:country":"CZ",
    "gn:fcode":"PPL",
    "gn:population":278,
    "iso:country":"CZ",
    "name:azb_x_preferred":[
        "\u0628\u0631\u0627\u062a\u06a9\u0648\u0648\u06cc\u062a\u0633\u0647"
    ],
    "name:ceb_x_preferred":[
        "Bratkovice"
    ],
    "name:ces_x_preferred":[
        "Bratkovice"
    ],
    "name:deu_x_preferred":[
        "Bratkovice"
    ],
    "name:eus_x_preferred":[
        "Bratkovice"
    ],
    "name:fas_x_preferred":[
        "\u0628\u0631\u0627\u062a\u06a9\u0648\u0648\u06cc\u062a\u0633\u0647"
    ],
    "name:fra_x_preferred":[
        "Bratkovice"
    ],
    "name:hun_x_preferred":[
        "Bratkovice"
    ],
    "name:ita_x_preferred":[
        "Bratkovice"
    ],
    "name:msa_x_preferred":[
        "Bratkovice"
    ],
    "name:nld_x_preferred":[
        "Bratkovice"
    ],
    "name:pol_x_preferred":[
        "Bratkovice"
    ],
    "name:por_x_preferred":[
        "Bratkovice"
    ],
    "name:slk_x_preferred":[
        "Bratkovice"
    ],
    "name:spa_x_preferred":[
        "Bratkovice"
    ],
    "name:srp_x_preferred":[
        "\u0411\u0440\u0430\u0442\u043a\u043e\u0432\u0438\u0446\u0435"
    ],
    "name:swe_x_preferred":[
        "Bratkovice"
    ],
    "name:vie_x_preferred":[
        "Bratkovice"
    ],
    "qs_pg:aaroncc":"CZ",
    "qs_pg:gn_country":"CZ",
    "qs_pg:gn_fcode":"PPL",
    "qs_pg:gn_pop":278,
    "qs_pg:name":"Bratkovice",
    "qs_pg:name_adm0":"\u010cesk\u00e1 republika",
    "qs_pg:name_adm1":"St\u0159edo\u010desk\u00fd kraj",
    "qs_pg:photos_9r":0,
    "qs_pg:photos_sr":0,
    "qs_pg:pop_sr":2,
    "qs_pg:qs_pg_placetype":"locality",
    "qs_pg:qs_pg_placetype_gp":"Town",
    "qs_pg:woe_adm0":23424810,
    "woe:adm0_id":23424810,
    "woe:name_adm0":"\u010cesk\u00e1 republika",
    "woe:name_adm1":"St\u0159edo\u010desk\u00fd kraj",
    "woe:placetype":"Town",
    "wof:name":"Bratkovice",
    "wof:placetype":"locality",
    "wof:population":278
},
  "geometry": {"coordinates":[13.99894,49.74041],"type":"Point"}
}