{
  "type": "Feature",
  "properties": {
    "gn:admin1_code":"79.0",
    "gn:admin2_code":"0316",
    "gn:asciiname":"Brusy",
    "gn:country_code":"CZ",
    "gn:dem":428,
    "gn:feature_class":"P",
    "gn:feature_code":"PPL",
    "gn:name":"Brusy",
    "gn:population":0,
    "gn:timezone":"Europe/Prague",
    "iso:country":"CZ",
    "name:azb_x_preferred":[
        "\u0628\u0631\u0648\u0633\u0647"
    ],
    "name:bel_x_preferred":[
        "\u0411\u0440\u0443\u0441\u044b"
    ],
    "name:ceb_x_preferred":[
        "Brusy"
    ],
    "name:csb_x_preferred":[
        "Brus\u00eb"
    ],
    "name:deu_x_preferred":[
        "Brusy"
    ],
    "name:dsb_x_preferred":[
        "Brusy"
    ],
    "name:epo_x_preferred":[
        "Brusy"
    ],
    "name:fas_x_preferred":[
        "\u0628\u0631\u0648\u0633\u0647"
    ],
    "name:fra_x_preferred":[
        "Brusy"
    ],
    "name:jav_x_preferred":[
        "Brusy"
    ],
    "name:lav_x_preferred":[
        "Brusi"
    ],
    "name:msa_x_preferred":[
        "Brusy"
    ],
    "name:nau_x_preferred":[
        "Brusy"
    ],
    "name:nld_x_preferred":[
        "Brusy"
    ],
    "name:pol_x_preferred":[
        "Brusy"
    ],
    "name:por_x_preferred":[
        "Brusy"
    ],
    "name:ron_x_preferred":[
        "Brusy"
    ],
    "name:rus_x_preferred":[
        "\u0411\u0440\u0443\u0441\u044b"
    ],
    "name:slk_x_preferred":[
        "Brusy"
    ],
    "name:srp_x_preferred":[
        "\u0411\u0440\u0443\u0441\u0438"
    ],
    "name:szl_x_preferred":[
        "Brusy"
    ],
    "name:ukr_x_preferred":[
        "\u0411\u0440\u0443\u0441\u0438"
    ],
    "name:vie_x_preferred":[
        "Brusy"
    ],
    "name:zho_x_preferred":[
        "\u5e03\u9b6f\u745f"
    ],
    "wof:name":"Brusy",
    "wof:placetype":"locality"
},
  "geometry": {"coordinates":[14.01529,49.3033],"type":"Point"}
}