{
  "type": "Feature",
  "properties": {
    "gn:admin1_code":"79.0",
    "gn:admin2_code":"0316",
    "gn:asciiname":"Brusy",
    "gn:country_code":"CZ",
    "gn:dem":428,
    "gn:feature_class":"P",
    "gn:feature_code":"PPL",
    "gn:name":"Brusy",
    "gn:population":0,
    "gn:timezone":"Europe/Prague",
    "iso:country":"CZ",
    "wof:name":"Brusy",
    "wof:placetype":"locality"
},
  "geometry": {"coordinates":[14.01529,49.3033],"type":"Point"}
}