{
  "type": "Feature",
  "properties": {
    "gn:country":"CZ",
    "gn:fcode":"PPL",
    "gn:population":0,
    "iso:country":"CZ",
    "name:cat_x_preferred":[
        "Makov"
    ],
    "name:ces_x_preferred":[
        "Makov"
    ],
    "name:deu_x_preferred":[
        "Makov"
    ],
    "name:epo_x_preferred":[
        "Makov"
    ],
    "name:eus_x_preferred":[
        "Makov"
    ],
    "name:hun_x_preferred":[
        "Trencs\u00e9nmak\u00f3"
    ],
    "name:ita_x_preferred":[
        "Makov"
    ],
    "name:msa_x_preferred":[
        "Makov"
    ],
    "name:nld_x_preferred":[
        "Makov"
    ],
    "name:pol_x_preferred":[
        "Mak\u00f3w"
    ],
    "name:ron_x_preferred":[
        "Makov"
    ],
    "name:slk_x_preferred":[
        "Makov"
    ],
    "name:spa_x_preferred":[
        "Makov"
    ],
    "name:srp_x_preferred":[
        "\u041c\u0430\u043a\u043e\u0432"
    ],
    "name:ukr_x_preferred":[
        "\u041c\u0430\u043a\u043e\u0432"
    ],
    "name:war_x_preferred":[
        "Makov"
    ],
    "qs_pg:aaroncc":"CZ",
    "qs_pg:gn_country":"CZ",
    "qs_pg:gn_fcode":"PPL",
    "qs_pg:gn_pop":0,
    "qs_pg:name":"Makov",
    "qs_pg:name_adm0":"\u010cesk\u00e1 republika",
    "qs_pg:name_adm1":"Plze\u0148sk\u00fd kraj",
    "qs_pg:photos_9k":1,
    "qs_pg:photos_9r":1,
    "qs_pg:photos_all":2,
    "qs_pg:photos_sr":0,
    "qs_pg:pop_sr":0,
    "qs_pg:qs_pg_placetype":"locality",
    "qs_pg:qs_pg_placetype_gp":"Town",
    "qs_pg:woe_adm0":23424810,
    "woe:adm0_id":23424810,
    "woe:name_adm0":"\u010cesk\u00e1 republika",
    "woe:name_adm1":"Plze\u0148sk\u00fd kraj",
    "woe:placetype":"Town",
    "wof:name":"Makov",
    "wof:placetype":"locality"
},
  "geometry": {"coordinates":[13.39078,49.44878],"type":"Point"}
}