{
  "type": "Feature",
  "properties": {
    "gn:country":"CZ",
    "gn:fcode":"PPL",
    "gn:population":608,
    "iso:country":"CZ",
    "name:azb_x_preferred":[
        "\u06a9\u0648\u0634\u062a\u06cc\u062a\u0633\u0647"
    ],
    "name:ceb_x_preferred":[
        "Ko\u0161tice"
    ],
    "name:ces_x_preferred":[
        "Ko\u0161tice"
    ],
    "name:eng_x_preferred":[
        "Ko\u0161tice"
    ],
    "name:eus_x_preferred":[
        "Ko\u0161tice"
    ],
    "name:fas_x_preferred":[
        "\u06a9\u0648\u0634\u062a\u06cc\u062a\u0633\u0647"
    ],
    "name:fra_x_preferred":[
        "Ko\u0161tice"
    ],
    "name:hun_x_preferred":[
        "Ko\u0161tice"
    ],
    "name:ita_x_preferred":[
        "Ko\u0161tice"
    ],
    "name:msa_x_preferred":[
        "Ko\u0161tice"
    ],
    "name:nan_x_preferred":[
        "Ko\u0161tice"
    ],
    "name:nld_x_preferred":[
        "Ko\u0161tice"
    ],
    "name:por_x_preferred":[
        "Ko\u0161tice"
    ],
    "name:slk_x_preferred":[
        "Ko\u0161tice"
    ],
    "name:spa_x_preferred":[
        "Ko\u0161tice"
    ],
    "name:srp_x_preferred":[
        "\u041a\u043e\u0448\u0442\u0438\u0446\u0435"
    ],
    "name:swe_x_preferred":[
        "Ko\u0161tice"
    ],
    "name:vie_x_preferred":[
        "Ko\u0161tice"
    ],
    "qs_pg:aaroncc":"CZ",
    "qs_pg:gn_country":"CZ",
    "qs_pg:gn_fcode":"PPL",
    "qs_pg:gn_pop":608,
    "qs_pg:name":"Ko\u0161tice",
    "qs_pg:name_adm0":"\u010cesk\u00e1 republika",
    "qs_pg:name_adm1":"\u00dasteck\u00fd kraj",
    "qs_pg:photos_9k":1,
    "qs_pg:photos_9r":1,
    "qs_pg:photos_all":1,
    "qs_pg:photos_sr":0,
    "qs_pg:pop_sr":2,
    "qs_pg:qs_pg_placetype":"locality",
    "qs_pg:qs_pg_placetype_gp":"Town",
    "qs_pg:woe_adm0":23424810,
    "woe:adm0_id":23424810,
    "woe:name_adm0":"\u010cesk\u00e1 republika",
    "woe:name_adm1":"\u00dasteck\u00fd kraj",
    "woe:placetype":"Town",
    "wof:name":"Ko\u0161tice",
    "wof:placetype":"locality",
    "wof:population":608
},
  "geometry": {"coordinates":[13.94194,50.40272],"type":"Point"}
}