{
  "type": "Feature",
  "properties": {
    "gn:admin1_code":"85.0",
    "gn:admin2_code":"0801",
    "gn:asciiname":"Radim",
    "gn:country_code":"CZ",
    "gn:dem":383,
    "gn:feature_class":"P",
    "gn:feature_code":"PPL",
    "gn:name":"Radim",
    "gn:population":0,
    "gn:timezone":"Europe/Prague",
    "iso:country":"CZ",
    "name:ceb_x_preferred":[
        "Radim"
    ],
    "name:ces_x_preferred":[
        "Radim"
    ],
    "name:deu_x_preferred":[
        "Radim"
    ],
    "name:fra_x_preferred":[
        "Radim"
    ],
    "name:ita_x_preferred":[
        "Radim"
    ],
    "name:nld_x_preferred":[
        "Radim"
    ],
    "name:slk_x_preferred":[
        "Radim"
    ],
    "name:srp_x_preferred":[
        "\u0420\u0430\u0434\u0438\u043c"
    ],
    "name:swe_x_preferred":[
        "Radim"
    ],
    "name:und_x_variant":[
        "Gross-Raden"
    ],
    "wof:name":"Radim",
    "wof:placetype":"locality"
},
  "geometry": {"coordinates":[17.59941,50.07565],"type":"Point"}
}