{
  "type": "Feature",
  "properties": {
    "gn:admin1_code":"83.0",
    "gn:admin2_code":"0512",
    "gn:asciiname":"Navarov",
    "gn:country_code":"CZ",
    "gn:dem":460,
    "gn:feature_class":"P",
    "gn:feature_code":"PPL",
    "gn:name":"N\u00e1varov",
    "gn:population":0,
    "gn:timezone":"Europe/Prague",
    "iso:country":"CZ",
    "wof:name":"Navarov",
    "wof:placetype":"locality"
},
  "geometry": {"coordinates":[15.32227,50.67956],"type":"Point"}
}