{
  "type": "Feature",
  "properties": {
    "gn:admin1_code":"80.0",
    "gn:admin2_code":"0612",
    "gn:asciiname":"Na Karlove Zamecku",
    "gn:country_code":"CZ",
    "gn:dem":503,
    "gn:feature_class":"P",
    "gn:feature_code":"PPL",
    "gn:name":"Na Karlov\u011b Z\u00e1me\u010dku",
    "gn:population":0,
    "gn:timezone":"Europe/Prague",
    "iso:country":"CZ",
    "wof:name":"Na Karlove Zamecku",
    "wof:placetype":"locality"
},
  "geometry": {"coordinates":[15.61449,49.44442],"type":"Point"}
}