{
  "type": "Feature",
  "properties": {
    "gn:admin1_code":"83",
    "gn:admin2_code":"0511",
    "gn:asciiname":"Vitkov",
    "gn:country_code":"CZ",
    "gn:dem":263,
    "gn:feature_class":"P",
    "gn:feature_code":"PPL",
    "gn:name":"V\u00edtkov",
    "gn:population":0,
    "gn:timezone":"Europe/Prague",
    "iso:country":"CZ",
    "name:und_x_variant":[
        "Leskenthal",
        "V\u00edtkov"
    ],
    "wof:name":"Vitkov",
    "wof:placetype":"locality"
},
  "geometry": {"coordinates":[14.60744,50.66982],"type":"Point"}
}