{
  "type": "Feature",
  "properties": {
    "gn:admin1_code":"85",
    "gn:admin2_code":"0803",
    "gn:asciiname":"Vernovice",
    "gn:country_code":"CZ",
    "gn:dem":200,
    "gn:feature_class":"P",
    "gn:feature_code":"PPL",
    "gn:name":"V\u011b\u0159\u0148ovice",
    "gn:population":0,
    "gn:timezone":"Europe/Prague",
    "iso:country":"CZ",
    "name:ces_x_preferred":[
        "V\u011b\u0159\u0148ovice"
    ],
    "name:pol_x_preferred":[
        "Wierzniowice"
    ],
    "name:slk_x_preferred":[
        "V\u011b\u0159\u0148ovice"
    ],
    "name:spa_x_preferred":[
        "V\u011b\u0159\u0148ovice"
    ],
    "wof:name":"Vernovice",
    "wof:placetype":"locality"
},
  "geometry": {"coordinates":[18.41524,49.92655],"type":"Point"}
}