{
  "type": "Feature",
  "properties": {
    "gn:admin1_code":"84.0",
    "gn:admin2_code":"0715",
    "gn:asciiname":"Rudolfov",
    "gn:country_code":"CZ",
    "gn:dem":277,
    "gn:feature_class":"P",
    "gn:feature_code":"PPL",
    "gn:name":"Rudolfov",
    "gn:population":0,
    "gn:timezone":"Europe/Prague",
    "iso:country":"CZ",
    "wof:name":"Rudolfov",
    "wof:placetype":"locality"
},
  "geometry": {"coordinates":[16.88815,49.87523],"type":"Point"}
}