{
  "type": "Feature",
  "properties": {
    "gn:gn_country":"CZ",
    "gn:gn_fcode":"PPL",
    "gn:gn_pop":399,
    "gn:population":399,
    "iso:country":"CZ",
    "name:azb_x_preferred":[
        "\u0627\u0648\u0644\u06cc\u062a\u0633\u0647"
    ],
    "name:ceb_x_preferred":[
        "\u00dalice"
    ],
    "name:ces_x_preferred":[
        "\u00dalice"
    ],
    "name:eng_x_preferred":[
        "\u00dalice"
    ],
    "name:eus_x_preferred":[
        "\u00dalice"
    ],
    "name:fas_x_preferred":[
        "\u0627\u0648\u0644\u06cc\u062a\u0633\u0647"
    ],
    "name:fra_x_preferred":[
        "\u00dalice"
    ],
    "name:hun_x_preferred":[
        "\u00dalice"
    ],
    "name:ita_x_preferred":[
        "\u00dalice"
    ],
    "name:msa_x_preferred":[
        "\u00dalice"
    ],
    "name:nan_x_preferred":[
        "\u00dalice"
    ],
    "name:nld_x_preferred":[
        "\u00dalice"
    ],
    "name:pol_x_preferred":[
        "\u00dalice"
    ],
    "name:por_x_preferred":[
        "\u00dalice"
    ],
    "name:slk_x_preferred":[
        "\u00dalice"
    ],
    "name:spa_x_preferred":[
        "\u00dalice"
    ],
    "name:srp_x_preferred":[
        "\u0423\u043b\u0438\u0446\u0435"
    ],
    "name:swe_x_preferred":[
        "\u00dalice"
    ],
    "name:vie_x_preferred":[
        "\u00dalice"
    ],
    "qs_pg:aaroncc":"CZ",
    "qs_pg:gn_country":"CZ",
    "qs_pg:gn_fcode":"PPL",
    "qs_pg:gn_pop":399,
    "qs_pg:name":"\u00dalice",
    "qs_pg:name_adm0":"\u010cesk\u00e1 republika",
    "qs_pg:name_adm1":"Plze\u0148sk\u00fd kraj",
    "qs_pg:photos_9r":0,
    "qs_pg:photos_sr":0,
    "qs_pg:pop_sr":2,
    "qs_pg:qs_pg_placetype":"locality",
    "qs_pg:qs_pg_placetype_gp":"Town",
    "qs_pg:woe_adm0":23424810,
    "woe:adm0_id":23424810,
    "woe:name_adm0":"\u010cesk\u00e1 republika",
    "woe:name_adm1":"Plze\u0148sk\u00fd kraj",
    "woe:placetype":"Town",
    "wof:name":"\u00dalice",
    "wof:placetype":"locality",
    "wof:population":399
},
  "geometry": {"coordinates":[13.14817,49.76079],"type":"Point"}
}