{
  "type": "Feature",
  "properties": {
    "gn:admin1_code":"79.0",
    "gn:admin2_code":"0315",
    "gn:asciiname":"Belecska Lhota",
    "gn:country_code":"CZ",
    "gn:dem":580,
    "gn:feature_class":"P",
    "gn:feature_code":"PPL",
    "gn:name":"B\u011ble\u010dsk\u00e1 Lhota",
    "gn:population":0,
    "gn:timezone":"Europe/Prague",
    "iso:country":"CZ",
    "wof:name":"Belecska Lhota",
    "wof:placetype":"locality"
},
  "geometry": {"coordinates":[14.03215,49.03771],"type":"Point"}
}