{
  "type": "Feature",
  "properties": {
    "iso:country":"CZ",
    "name:ces_x_preferred":[
        "Brno hlavn\u00ed n\u00e1dra\u017e\u00ed"
    ],
    "name:ces_x_variant":[
        "Horn\u00ed Her\u0161pice"
    ],
    "name:cze_x_colloquial":[
        "Horni Herpice",
        "Horni Herspice",
        "Horni Hertpice"
    ],
    "name:cze_x_variant":[
        "Horn\u00ed Herpice"
    ],
    "name:deu_x_preferred":[
        "Brno hlavn\u00ed n\u00e1dra\u017e\u00ed"
    ],
    "name:eng_x_preferred":[
        "Horn\u00ed Her\u0161pice"
    ],
    "name:fra_x_preferred":[
        "Horn\u00ed Her\u0161pice"
    ],
    "name:hsb_x_preferred":[
        "Brno h\u0142owne dw\u00f3rni\u0161\u0107o"
    ],
    "name:hun_x_preferred":[
        "Brn\u00f3i f\u0151p\u00e1lyaudvar"
    ],
    "name:ita_x_preferred":[
        "Stazione di Brno hlavn\u00ed"
    ],
    "name:jpn_x_preferred":[
        "\u30d6\u30eb\u30ce\u672c\u99c5"
    ],
    "name:pol_x_preferred":[
        "Brno hlavn\u00ed n\u00e1dra\u017e\u00ed"
    ],
    "name:pol_x_variant":[
        "Horn\u00ed Her\u0161pice"
    ],
    "name:slk_x_preferred":[
        "Brno hlavn\u00ed n\u00e1dra\u017e\u00ed"
    ],
    "name:slk_x_variant":[
        "Horn\u00ed Her\u0161pice"
    ],
    "name:szl_x_preferred":[
        "Brno hlavn\u00ed n\u00e1dra\u017e\u00ed"
    ],
    "qs:gn_adm0_cc":"CZ",
    "qs:gn_fcode":"PPLX",
    "qs:gn_local":3078610,
    "qs:gn_namadm1":"00",
    "qs:gn_name":"Horn\u00ed Her\u0161pice",
    "qs:local_max":6134,
    "qs:local_sum":32721,
    "qs:localhoods":44,
    "qs:name":"Horn\u00ed Her\u0161pice",
    "qs:name_adm0":"\u010cesk\u00e1 republika",
    "qs:name_adm1":"Jihomoravsk\u00fd kraj",
    "qs:name_adm2":"Brno-M\u011bsto",
    "qs:name_lau":"Brno",
    "qs:name_local":"Brno",
    "qs:photo_max":189,
    "qs:photo_sum":429,
    "qs:placetype":"Suburb",
    "qs:quad_count":33,
    "qs:woe_adm0":23424810,
    "qs:woe_adm1":20070503,
    "qs:woe_adm2":12582547,
    "qs:woe_lau":12605174,
    "qs:woe_local":786869,
    "qs:woe_ver":"7.10.0",
    "wof:lang":[
        "cze"
    ],
    "wof:name":"Horn\u00ed Her\u0161pice",
    "wof:placetype":"neighbourhood"
},
  "geometry": {"coordinates":[16.623553,49.155974],"type":"Point"}
}