{
  "type": "Feature",
  "properties": {
    "gn:admin1_code":"86",
    "gn:admin2_code":"0531",
    "gn:asciiname":"Zilovice",
    "gn:country_code":"CZ",
    "gn:dem":267,
    "gn:feature_class":"P",
    "gn:feature_code":"PPL",
    "gn:name":"\u017dilovice",
    "gn:population":0,
    "gn:timezone":"Europe/Prague",
    "iso:country":"CZ",
    "wof:name":"Zilovice",
    "wof:placetype":"locality"
},
  "geometry": {"coordinates":[15.9812,49.93911],"type":"Point"}
}