{
  "type": "Feature",
  "properties": {
    "gn:gn_country":"CZ",
    "gn:gn_fcode":"PPL",
    "gn:gn_pop":334,
    "gn:population":334,
    "iso:country":"CZ",
    "name:bul_x_preferred":[
        "\u0411\u0443\u0431\u043b\u0430\u0432\u0430"
    ],
    "name:cze_x_preferred":[
        "Bublava"
    ],
    "name:dut_x_preferred":[
        "Bublava"
    ],
    "name:eng_x_preferred":[
        "Bublava"
    ],
    "name:fre_x_preferred":[
        "Bublava"
    ],
    "name:ger_x_preferred":[
        "Bublava"
    ],
    "name:hun_x_preferred":[
        "Bublava"
    ],
    "name:ita_x_preferred":[
        "Bublava"
    ],
    "name:may_x_preferred":[
        "Bublava"
    ],
    "name:per_x_preferred":[
        "\u0628\u0648\u0628\u0644\u0627\u0648\u0627"
    ],
    "name:pol_x_preferred":[
        "Bublava"
    ],
    "name:por_x_preferred":[
        "Bublava"
    ],
    "name:rup_x_preferred":[
        "Bublava"
    ],
    "name:slo_x_preferred":[
        "Bublava"
    ],
    "name:srp_x_preferred":[
        "\u0411\u0443\u0431\u043b\u0430\u0432\u0430"
    ],
    "name:swe_x_preferred":[
        "Bublava"
    ],
    "name:unk_x_variant":[
        "Schwaderbach"
    ],
    "name:vie_x_preferred":[
        "Bublava"
    ],
    "qs_pg:aaroncc":"CZ",
    "qs_pg:gn_country":"CZ",
    "qs_pg:gn_fcode":"PPL",
    "qs_pg:gn_pop":334,
    "qs_pg:name":"Bublava",
    "qs_pg:name_adm0":"\u010cesk\u00e1 republika",
    "qs_pg:name_adm1":"Karlovarsk\u00fd kraj",
    "qs_pg:photos_9k":1,
    "qs_pg:photos_9r":1,
    "qs_pg:photos_all":1,
    "qs_pg:photos_sr":0,
    "qs_pg:pop_sr":2,
    "qs_pg:qs_pg_placetype":"locality",
    "qs_pg:qs_pg_placetype_gp":"Town",
    "qs_pg:woe_adm0":23424810,
    "woe:adm0_id":23424810,
    "woe:name_adm0":"\u010cesk\u00e1 republika",
    "woe:name_adm1":"Karlovarsk\u00fd kraj",
    "woe:placetype":"Town",
    "wof:name":"Bublava",
    "wof:placetype":"locality",
    "wof:population":334
},
  "geometry": {"coordinates":[12.50517,50.37438],"type":"Point"}
}