{
  "type": "Feature",
  "properties": {
    "gn:admin1_code":"87",
    "gn:admin2_code":"0325",
    "gn:asciiname":"Zebnice",
    "gn:country_code":"CZ",
    "gn:dem":440,
    "gn:feature_class":"P",
    "gn:feature_code":"PPL",
    "gn:name":"\u017debnice",
    "gn:population":0,
    "gn:timezone":"Europe/Prague",
    "iso:country":"CZ",
    "name:und_x_variant":[
        "\u017debnitz",
        "\u017debnice"
    ],
    "wof:name":"Zebnice",
    "wof:placetype":"locality"
},
  "geometry": {"coordinates":[13.39424,49.95724000000001],"type":"Point"}
}