{
  "type": "Feature",
  "properties": {
    "gn:admin1_code":"85.0",
    "gn:admin2_code":"0801",
    "gn:asciiname":"Mnichov",
    "gn:country_code":"CZ",
    "gn:dem":557,
    "gn:feature_class":"P",
    "gn:feature_code":"PPL",
    "gn:name":"Mnichov",
    "gn:population":0,
    "gn:timezone":"Europe/Prague",
    "iso:country":"CZ",
    "name:ceb_x_preferred":[
        "Mnichov"
    ],
    "name:ces_x_preferred":[
        "Mnichov"
    ],
    "name:deu_x_preferred":[
        "Mnichov"
    ],
    "name:epo_x_preferred":[
        "Mnichov"
    ],
    "name:fra_x_preferred":[
        "Mnichov"
    ],
    "name:hun_x_preferred":[
        "Mnichov"
    ],
    "name:ita_x_preferred":[
        "Mnichov"
    ],
    "name:nld_x_preferred":[
        "Mnichov"
    ],
    "name:pol_x_preferred":[
        "Mnichov"
    ],
    "name:slk_x_preferred":[
        "Mnichov"
    ],
    "name:srp_x_preferred":[
        "\u041c\u045a\u0438\u0445\u043e\u0432"
    ],
    "name:swe_x_preferred":[
        "Mnichov"
    ],
    "name:und_x_variant":[
        "Einsiedel"
    ],
    "wof:name":"Mnichov",
    "wof:placetype":"locality"
},
  "geometry": {"coordinates":[17.37823,50.14393],"type":"Point"}
}