{
  "type": "Feature",
  "properties": {
    "iso:country":"CZ",
    "name:azb_x_preferred":[
        "\u0628\u0647\u0648\u0645\u06cc\u0646"
    ],
    "name:bul_x_preferred":[
        "\u0411\u043e\u0445\u0443\u043c\u0438\u043d"
    ],
    "name:ceb_x_preferred":[
        "Bohum\u00edn"
    ],
    "name:ces_x_preferred":[
        "Bohum\u00edn"
    ],
    "name:deu_x_preferred":[
        "Bohum\u00edn"
    ],
    "name:epo_x_preferred":[
        "Bohum\u00edn"
    ],
    "name:eus_x_preferred":[
        "Bohum\u00edn"
    ],
    "name:fas_x_preferred":[
        "\u0628\u0647\u0648\u0645\u06cc\u0646"
    ],
    "name:fra_x_preferred":[
        "Bohum\u00edn"
    ],
    "name:hun_x_preferred":[
        "Bohum\u00edn"
    ],
    "name:ita_x_preferred":[
        "Bohum\u00edn"
    ],
    "name:kor_x_preferred":[
        "\ubcf4\ud6c4\ubbfc"
    ],
    "name:lav_x_preferred":[
        "Bohum\u012bna"
    ],
    "name:lit_x_preferred":[
        "Bohumynas"
    ],
    "name:msa_x_preferred":[
        "Bohum\u00edn"
    ],
    "name:nld_x_preferred":[
        "Bohum\u00edn"
    ],
    "name:pol_x_preferred":[
        "Bogumin"
    ],
    "name:por_x_preferred":[
        "Bohum\u00edn"
    ],
    "name:rus_x_preferred":[
        "\u0411\u043e\u0433\u0443\u043c\u0438\u043d"
    ],
    "name:slk_x_preferred":[
        "Bohum\u00edn"
    ],
    "name:spa_x_preferred":[
        "Bohum\u00edn"
    ],
    "name:srp_x_preferred":[
        "\u0411\u043e\u0445\u0443\u043c\u0438\u043d"
    ],
    "name:szl_x_preferred":[
        "Bohum\u00edn"
    ],
    "name:tur_x_preferred":[
        "Bohum\u00edn"
    ],
    "name:ukr_x_preferred":[
        "\u0411\u043e\u0433\u0443\u043c\u0456\u043d"
    ],
    "name:vie_x_preferred":[
        "Bohum\u00edn"
    ],
    "qs_pg:aaroncc":"CZ",
    "qs_pg:name":"Bohum\u00edn",
    "qs_pg:name_adm0":"\u010cesk\u00e1 republika",
    "qs_pg:name_adm1":"Moravskoslezsk\u00fd kraj",
    "qs_pg:photos":20,
    "qs_pg:photos_1k":4,
    "qs_pg:photos_9k":1,
    "qs_pg:photos_9r":2,
    "qs_pg:photos_all":73,
    "qs_pg:photos_sr":1,
    "qs_pg:pop_sr":0,
    "qs_pg:qs_pg_placetype":"localadmin",
    "qs_pg:qs_pg_placetype_gp":"LocalAdmin",
    "qs_pg:woe_adm0":23424810,
    "woe:adm0_id":23424810,
    "woe:name_adm0":"\u010cesk\u00e1 republika",
    "woe:name_adm1":"Moravskoslezsk\u00fd kraj",
    "woe:placetype":"LocalAdmin",
    "wof:name":"Bohum\u00edn",
    "wof:placetype":"localadmin"
},
  "geometry": {"coordinates":[18.358926,49.901711],"type":"Point"}
}