{
  "type": "Feature",
  "properties": {
    "iso:country":"CZ",
    "name:ceb_x_preferred":[
        "Sadov\u00e1"
    ],
    "name:ces_x_preferred":[
        "Sadov\u00e1"
    ],
    "name:cze_x_colloquial":[
        "Sadova"
    ],
    "name:deu_x_preferred":[
        "Sadov\u00e1"
    ],
    "name:eng_x_preferred":[
        "Sadov\u00e1"
    ],
    "name:epo_x_preferred":[
        "Sadov\u00e1"
    ],
    "name:fra_x_preferred":[
        "Sadov\u00e1"
    ],
    "name:hun_x_preferred":[
        "Sadov\u00e1"
    ],
    "name:ind_x_preferred":[
        "Sadov\u00e1"
    ],
    "name:ita_x_preferred":[
        "Sadov\u00e1"
    ],
    "name:msa_x_preferred":[
        "Sadov\u00e1"
    ],
    "name:nld_x_preferred":[
        "Sadov\u00e1"
    ],
    "name:pol_x_preferred":[
        "Sadov\u00e1"
    ],
    "name:slk_x_preferred":[
        "Sadov\u00e1"
    ],
    "wd:wordcount":317,
    "wof:lang":[
        "cze"
    ],
    "wof:name":"Sadov\u00e1",
    "wof:placetype":"neighbourhood"
},
  "geometry": {"coordinates":[16.601963,49.226495],"type":"Point"}
}