{
  "type": "Feature",
  "properties": {
    "gn:admin1_code":"86.0",
    "gn:admin2_code":"0534",
    "gn:asciiname":"Doubravice",
    "gn:country_code":"CZ",
    "gn:dem":380,
    "gn:feature_class":"P",
    "gn:feature_code":"PPL",
    "gn:name":"Doubravice",
    "gn:population":0,
    "gn:timezone":"Europe/Prague",
    "iso:country":"CZ",
    "name:ceb_x_preferred":[
        "Doubravice"
    ],
    "name:ces_x_preferred":[
        "Doubravice"
    ],
    "name:deu_x_preferred":[
        "Doubravice"
    ],
    "name:epo_x_preferred":[
        "Doubravice"
    ],
    "name:fra_x_preferred":[
        "Doubravice"
    ],
    "name:hun_x_preferred":[
        "Doubravice"
    ],
    "name:ita_x_preferred":[
        "Doubravice"
    ],
    "name:nld_x_preferred":[
        "Doubravice"
    ],
    "name:pol_x_preferred":[
        "Doubravice"
    ],
    "name:slk_x_preferred":[
        "Doubravice"
    ],
    "name:srp_x_preferred":[
        "\u0414\u043e\u0443\u0431\u0440\u0430\u0432\u0438\u0446\u0435"
    ],
    "name:swe_x_preferred":[
        "Doubravice"
    ],
    "wof:name":"Doubravice",
    "wof:placetype":"locality"
},
  "geometry": {"coordinates":[16.09858,49.87627],"type":"Point"}
}