{
  "type": "Feature",
  "properties": {
    "gn:country":"CZ",
    "gn:fcode":"PPL",
    "gn:population":154,
    "iso:country":"CZ",
    "name:azb_x_preferred":[
        "\u0645\u0627\u0647\u0648\u0648\u0634"
    ],
    "name:ceb_x_preferred":[
        "Mahou\u0161"
    ],
    "name:ces_x_preferred":[
        "Mahou\u0161"
    ],
    "name:deu_x_preferred":[
        "Mahou\u0161"
    ],
    "name:eng_x_preferred":[
        "Mahou\u0161"
    ],
    "name:eus_x_preferred":[
        "Mahou\u0161"
    ],
    "name:fas_x_preferred":[
        "\u0645\u0627\u0647\u0648\u0648\u0634"
    ],
    "name:fra_x_preferred":[
        "Mahou\u0161"
    ],
    "name:hun_x_preferred":[
        "Mahou\u0161"
    ],
    "name:ita_x_preferred":[
        "Mahou\u0161"
    ],
    "name:msa_x_preferred":[
        "Mahou\u0161"
    ],
    "name:nan_x_preferred":[
        "Mahou\u0161"
    ],
    "name:nld_x_preferred":[
        "Mahou\u0161"
    ],
    "name:por_x_preferred":[
        "Mahou\u0161"
    ],
    "name:slk_x_preferred":[
        "Mahou\u0161"
    ],
    "name:spa_x_preferred":[
        "Mahou\u0161"
    ],
    "name:srp_x_preferred":[
        "\u041c\u0430\u0445\u043e\u0443\u0448"
    ],
    "name:swe_x_preferred":[
        "Mahou\u0161"
    ],
    "name:vie_x_preferred":[
        "Mahou\u0161"
    ],
    "qs_pg:aaroncc":"CZ",
    "qs_pg:gn_country":"CZ",
    "qs_pg:gn_fcode":"PPL",
    "qs_pg:gn_pop":154,
    "qs_pg:name":"Mahou\u0161",
    "qs_pg:name_adm0":"\u010cesk\u00e1 republika",
    "qs_pg:name_adm1":"Jiho\u010desk\u00fd kraj",
    "qs_pg:photos_9r":0,
    "qs_pg:photos_sr":0,
    "qs_pg:pop_sr":1,
    "qs_pg:qs_pg_placetype":"locality",
    "qs_pg:qs_pg_placetype_gp":"Town",
    "qs_pg:woe_adm0":23424810,
    "woe:adm0_id":23424810,
    "woe:name_adm0":"\u010cesk\u00e1 republika",
    "woe:name_adm1":"Jiho\u010desk\u00fd kraj",
    "woe:placetype":"Town",
    "wof:name":"Mahou\u0161",
    "wof:placetype":"locality",
    "wof:population":154
},
  "geometry": {"coordinates":[14.25596,49.04784],"type":"Point"}
}