{
  "type": "Feature",
  "properties": {
    "gn:admin1_code":"87.0",
    "gn:admin2_code":"0321",
    "gn:asciiname":"Mytnice",
    "gn:country_code":"CZ",
    "gn:dem":576,
    "gn:feature_class":"P",
    "gn:feature_code":"PPL",
    "gn:name":"M\u00fdtnice",
    "gn:population":0,
    "gn:timezone":"Europe/Prague",
    "iso:country":"CZ",
    "name:und_x_variant":[
        "Mauthaus",
        "M\u00fdtnice"
    ],
    "wof:name":"Mytnice",
    "wof:placetype":"locality"
},
  "geometry": {"coordinates":[12.70749,49.4496],"type":"Point"}
}