{
  "type": "Feature",
  "properties": {
    "gn:admin1_code":"86.0",
    "gn:admin2_code":"0531",
    "gn:asciiname":"Mala Stritez",
    "gn:country_code":"CZ",
    "gn:dem":546,
    "gn:feature_class":"P",
    "gn:feature_code":"PPL",
    "gn:name":"Mal\u00e1 St\u0159\u00edte\u017e",
    "gn:population":0,
    "gn:timezone":"Europe/Prague",
    "iso:country":"CZ",
    "wof:name":"Mala Stritez",
    "wof:placetype":"locality"
},
  "geometry": {"coordinates":[15.74656,49.79543],"type":"Point"}
}