{
  "type": "Feature",
  "properties": {
    "gn:country":"CZ",
    "gn:fcode":"PPL",
    "gn:population":91,
    "iso:country":"CZ",
    "name:azb_x_preferred":[
        "\u0627\u0648\u062f\u0648\u0646\u062a\u0633"
    ],
    "name:ces_x_preferred":[
        "Odunec"
    ],
    "name:eng_x_preferred":[
        "Odunec"
    ],
    "name:eus_x_preferred":[
        "Odunec"
    ],
    "name:fas_x_preferred":[
        "\u0627\u0648\u062f\u0648\u0646\u062a\u0633"
    ],
    "name:fra_x_preferred":[
        "Odunec"
    ],
    "name:hun_x_preferred":[
        "Odunec"
    ],
    "name:ita_x_preferred":[
        "Odunec"
    ],
    "name:msa_x_preferred":[
        "Odunec"
    ],
    "name:nan_x_preferred":[
        "Odunec"
    ],
    "name:nld_x_preferred":[
        "Odunec"
    ],
    "name:por_x_preferred":[
        "Odunec"
    ],
    "name:rup_x_preferred":[
        "Odunec"
    ],
    "name:slk_x_preferred":[
        "Odunec"
    ],
    "name:spa_x_preferred":[
        "Odunec"
    ],
    "name:vie_x_preferred":[
        "Odunec"
    ],
    "qs_pg:aaroncc":"CZ",
    "qs_pg:gn_country":"CZ",
    "qs_pg:gn_fcode":"PPL",
    "qs_pg:gn_pop":91,
    "qs_pg:name":"Odunec",
    "qs_pg:name_adm0":"\u010cesk\u00e1 republika",
    "qs_pg:name_adm1":"Kraj Vyso\u010dina",
    "qs_pg:photos_9k":1,
    "qs_pg:photos_9r":1,
    "qs_pg:photos_all":2,
    "qs_pg:photos_sr":0,
    "qs_pg:pop_sr":1,
    "qs_pg:qs_pg_placetype":"locality",
    "qs_pg:qs_pg_placetype_gp":"Town",
    "qs_pg:woe_adm0":23424810,
    "woe:adm0_id":23424810,
    "woe:name_adm0":"\u010cesk\u00e1 republika",
    "woe:name_adm1":"Kraj Vyso\u010dina",
    "woe:placetype":"Town",
    "wof:name":"Odunec",
    "wof:placetype":"locality",
    "wof:population":91
},
  "geometry": {"coordinates":[16.01427,49.12021],"type":"Point"}
}