{
  "type": "Feature",
  "properties": {
    "gn:gn_country":"CZ",
    "gn:gn_fcode":"PPL",
    "gn:gn_pop":47,
    "gn:population":47,
    "iso:country":"CZ",
    "name:cze_x_preferred":[
        "Libochovi\u010dky"
    ],
    "name:dut_x_preferred":[
        "Libochovi\u010dky"
    ],
    "name:eng_x_preferred":[
        "Libochovi\u010dky"
    ],
    "name:fre_x_preferred":[
        "Libochovi\u010dky"
    ],
    "name:hun_x_preferred":[
        "Libochovi\u010dky"
    ],
    "name:ita_x_preferred":[
        "Libochovi\u010dky"
    ],
    "name:may_x_preferred":[
        "Libochovi\u010dky"
    ],
    "name:per_x_preferred":[
        "\u0644\u06cc\u0628\u0648\u062e\u0648\u0648\u06cc\u062a\u0634\u06a9\u06cc"
    ],
    "name:pol_x_preferred":[
        "Libochovi\u010dky"
    ],
    "name:por_x_preferred":[
        "Libochovi\u010dky"
    ],
    "name:rup_x_preferred":[
        "Libochovi\u010dky"
    ],
    "name:slo_x_preferred":[
        "Libochovi\u010dky"
    ],
    "name:srp_x_preferred":[
        "\u041b\u0438\u0431\u043e\u0445\u043e\u0432\u0438\u0447\u043a\u0438"
    ],
    "name:vie_x_preferred":[
        "Libochovi\u010dky"
    ],
    "qs_pg:aaroncc":"CZ",
    "qs_pg:gn_country":"CZ",
    "qs_pg:gn_fcode":"PPL",
    "qs_pg:gn_pop":47,
    "qs_pg:name":"Libochovi\u010dky",
    "qs_pg:name_adm0":"\u010cesk\u00e1 republika",
    "qs_pg:name_adm1":"St\u0159edo\u010desk\u00fd kraj",
    "qs_pg:photos_9r":0,
    "qs_pg:photos_sr":0,
    "qs_pg:pop_sr":1,
    "qs_pg:qs_pg_placetype":"locality",
    "qs_pg:qs_pg_placetype_gp":"Town",
    "qs_pg:woe_adm0":23424810,
    "woe:adm0_id":23424810,
    "woe:name_adm0":"\u010cesk\u00e1 republika",
    "woe:name_adm1":"St\u0159edo\u010desk\u00fd kraj",
    "woe:placetype":"Town",
    "wof:name":"Libochovi\u010dky",
    "wof:placetype":"locality",
    "wof:population":47
},
  "geometry": {"coordinates":[14.2396,50.17257],"type":"Point"}
}