{
  "type": "Feature",
  "properties": {
    "gn:admin1_code":"87.0",
    "gn:admin2_code":"0325",
    "gn:asciiname":"Skelna Hut'",
    "gn:country_code":"CZ",
    "gn:dem":640,
    "gn:feature_class":"P",
    "gn:feature_code":"PPL",
    "gn:name":"Skeln\u00e1 Hut\u2019",
    "gn:population":0,
    "gn:timezone":"Europe/Prague",
    "iso:country":"CZ",
    "wof:name":"Skelna Hut'",
    "wof:placetype":"locality"
},
  "geometry": {"coordinates":[13.0868,49.94439000000001],"type":"Point"}
}