{
  "type": "Feature",
  "properties": {
    "gn:admin1_code":"88",
    "gn:admin2_code":"0207",
    "gn:asciiname":"Stare Kosatky",
    "gn:country_code":"CZ",
    "gn:dem":202,
    "gn:feature_class":"P",
    "gn:feature_code":"PPL",
    "gn:name":"Star\u00e9 Ko\u0161\u00e1tky",
    "gn:population":0,
    "gn:timezone":"Europe/Prague",
    "iso:country":"CZ",
    "wof:name":"Stare Kosatky",
    "wof:placetype":"locality"
},
  "geometry": {"coordinates":[14.66667,50.31667],"type":"Point"}
}