{
  "type": "Feature",
  "properties": {
    "gn:admin1_code":"87.0",
    "gn:admin2_code":"0321",
    "gn:asciiname":"Mrchojedy",
    "gn:cc2":"CZ",
    "gn:country_code":"CZ",
    "gn:dem":465,
    "gn:feature_class":"P",
    "gn:feature_code":"PPL",
    "gn:name":"Mrchojedy",
    "gn:population":0,
    "gn:timezone":"Europe/Prague",
    "iso:country":"CZ",
    "name:und_x_variant":[
        "Murchowa"
    ],
    "wof:name":"Mrchojedy",
    "wof:placetype":"locality"
},
  "geometry": {"coordinates":[12.957,49.49339000000001],"type":"Point"}
}