{
  "type": "Feature",
  "properties": {
    "gn:gn_country":"CZ",
    "gn:gn_fcode":"PPL",
    "gn:gn_pop":131,
    "gn:population":131,
    "iso:country":"CZ",
    "name:cze_x_preferred":[
        "Vohan\u010dice"
    ],
    "name:dut_x_preferred":[
        "Vohan\u010dice"
    ],
    "name:eng_x_preferred":[
        "Vohan\u010dice"
    ],
    "name:fre_x_preferred":[
        "Vohan\u010dice"
    ],
    "name:ger_x_preferred":[
        "Vohan\u010dice"
    ],
    "name:hun_x_preferred":[
        "Vohan\u010dice"
    ],
    "name:ita_x_preferred":[
        "Vohan\u010dice"
    ],
    "name:may_x_preferred":[
        "Vohan\u010dice"
    ],
    "name:per_x_preferred":[
        "\u0648\u0648\u0647\u0627\u0646\u062a\u0634\u06cc\u062a\u0633\u0647"
    ],
    "name:pol_x_preferred":[
        "Vohan\u010dice"
    ],
    "name:por_x_preferred":[
        "Vohan\u010dice"
    ],
    "name:slo_x_preferred":[
        "Vohan\u010dice"
    ],
    "name:swe_x_preferred":[
        "Vohan\u010dice"
    ],
    "name:vie_x_preferred":[
        "Vohan\u010dice"
    ],
    "qs_pg:aaroncc":"CZ",
    "qs_pg:gn_country":"CZ",
    "qs_pg:gn_fcode":"PPL",
    "qs_pg:gn_pop":131,
    "qs_pg:name":"Vohan\u010dice",
    "qs_pg:name_adm0":"\u010cesk\u00e1 republika",
    "qs_pg:name_adm1":"Jihomoravsk\u00fd kraj",
    "qs_pg:photos_9r":0,
    "qs_pg:photos_sr":0,
    "qs_pg:pop_sr":1,
    "qs_pg:qs_pg_placetype":"locality",
    "qs_pg:qs_pg_placetype_gp":"Town",
    "qs_pg:woe_adm0":23424810,
    "woe:adm0_id":23424810,
    "woe:name_adm0":"\u010cesk\u00e1 republika",
    "woe:name_adm1":"Jihomoravsk\u00fd kraj",
    "woe:placetype":"Town",
    "wof:name":"Vohan\u010dice",
    "wof:placetype":"locality",
    "wof:population":131
},
  "geometry": {"coordinates":[16.39386,49.32159],"type":"Point"}
}