{
  "type": "Feature",
  "properties": {
    "gn:admin1_code":"89",
    "gn:admin2_code":"0424",
    "gn:asciiname":"Velichov",
    "gn:country_code":"CZ",
    "gn:dem":249,
    "gn:feature_class":"P",
    "gn:feature_code":"PPL",
    "gn:name":"Velichov",
    "gn:population":0,
    "gn:timezone":"Europe/Prague",
    "iso:country":"CZ",
    "name:und_x_variant":[
        "Welchau",
        "Velichov"
    ],
    "wof:name":"Velichov",
    "wof:placetype":"locality"
},
  "geometry": {"coordinates":[13.54843,50.35124],"type":"Point"}
}