{
  "type": "Feature",
  "properties": {
    "gn:admin1_code":"89",
    "gn:admin2_code":"0424",
    "gn:asciiname":"Velichov",
    "gn:country_code":"CZ",
    "gn:dem":249,
    "gn:feature_class":"P",
    "gn:feature_code":"PPL",
    "gn:name":"Velichov",
    "gn:population":0,
    "gn:timezone":"Europe/Prague",
    "iso:country":"CZ",
    "name:azb_x_preferred":[
        "\u0648\u0644\u06cc\u0686\u0648"
    ],
    "name:ceb_x_preferred":[
        "Velichov"
    ],
    "name:ces_x_preferred":[
        "Velichov"
    ],
    "name:deu_x_preferred":[
        "Velichov"
    ],
    "name:eus_x_preferred":[
        "Velichov"
    ],
    "name:fas_x_preferred":[
        "\u0648\u0644\u06cc\u0686\u0648"
    ],
    "name:fra_x_preferred":[
        "Velichov"
    ],
    "name:hun_x_preferred":[
        "Velichov"
    ],
    "name:ita_x_preferred":[
        "Velichov"
    ],
    "name:msa_x_preferred":[
        "Velichov"
    ],
    "name:nld_x_preferred":[
        "Velichov"
    ],
    "name:pol_x_preferred":[
        "Velichov"
    ],
    "name:por_x_preferred":[
        "Velichov"
    ],
    "name:slk_x_preferred":[
        "Velichov"
    ],
    "name:spa_x_preferred":[
        "Velichov"
    ],
    "name:srp_x_preferred":[
        "\u0412\u0435\u043b\u0438\u0445\u043e\u0432"
    ],
    "name:swe_x_preferred":[
        "Velichov"
    ],
    "name:und_x_variant":[
        "Welchau",
        "Velichov"
    ],
    "name:vie_x_preferred":[
        "Velichov"
    ],
    "wof:name":"Velichov",
    "wof:placetype":"locality"
},
  "geometry": {"coordinates":[13.54843,50.35124],"type":"Point"}
}