{
  "type": "Feature",
  "properties": {
    "gn:admin1_code":"88.0",
    "gn:admin2_code":"0206",
    "gn:asciiname":"Mikovice",
    "gn:country_code":"CZ",
    "gn:dem":186,
    "gn:feature_class":"P",
    "gn:feature_code":"PPL",
    "gn:name":"Mikovice",
    "gn:population":0,
    "gn:timezone":"Europe/Prague",
    "iso:country":"CZ",
    "wof:name":"Mikovice",
    "wof:placetype":"locality"
},
  "geometry": {"coordinates":[14.29265,50.23058],"type":"Point"}
}