{
  "type": "Feature",
  "properties": {
    "gn:admin1_code":"88.0",
    "gn:admin2_code":"0209",
    "gn:asciiname":"Nechanice",
    "gn:country_code":"CZ",
    "gn:dem":402,
    "gn:feature_class":"P",
    "gn:feature_code":"PPL",
    "gn:name":"Nech\u00e1nice",
    "gn:population":0,
    "gn:timezone":"Europe/Prague",
    "iso:country":"CZ",
    "name:und_x_variant":[
        "Nechanitz"
    ],
    "wof:name":"Nechanice",
    "wof:placetype":"locality"
},
  "geometry": {"coordinates":[14.53938,49.91398],"type":"Point"}
}