{
  "type": "Feature",
  "properties": {
    "gn:admin1_code":"88.0",
    "gn:admin2_code":"0209",
    "gn:asciiname":"Nechanice",
    "gn:country_code":"CZ",
    "gn:dem":402,
    "gn:feature_class":"P",
    "gn:feature_code":"PPL",
    "gn:name":"Nech\u00e1nice",
    "gn:population":0,
    "gn:timezone":"Europe/Prague",
    "iso:country":"CZ",
    "name:ceb_x_preferred":[
        "Nechanice"
    ],
    "name:ces_x_preferred":[
        "Nechanice"
    ],
    "name:deu_x_preferred":[
        "Nechanice"
    ],
    "name:epo_x_preferred":[
        "Nechanice"
    ],
    "name:eus_x_preferred":[
        "Nechanice"
    ],
    "name:fas_x_preferred":[
        "\u0646\u062e\u0627\u0646\u06cc\u062a\u0633\u0647"
    ],
    "name:fra_x_preferred":[
        "Nechanice"
    ],
    "name:hun_x_preferred":[
        "Nechanice"
    ],
    "name:ita_x_preferred":[
        "Nechanice"
    ],
    "name:lit_x_preferred":[
        "Nechanic\u0117s"
    ],
    "name:msa_x_preferred":[
        "Nechanice"
    ],
    "name:nld_x_preferred":[
        "Nechanice"
    ],
    "name:pol_x_preferred":[
        "Nechanice"
    ],
    "name:por_x_preferred":[
        "Nechanice"
    ],
    "name:slk_x_preferred":[
        "Nechanice"
    ],
    "name:spa_x_preferred":[
        "Nechanice"
    ],
    "name:srp_x_preferred":[
        "\u041d\u0435\u0445\u0430\u045a\u0438\u0446\u0435"
    ],
    "name:swe_x_preferred":[
        "Nechanice"
    ],
    "name:und_x_variant":[
        "Nechanitz"
    ],
    "name:vie_x_preferred":[
        "Nechanice"
    ],
    "name:zho_x_preferred":[
        "\u5167\u54c8\u5c3c\u91c7"
    ],
    "wof:name":"Nechanice",
    "wof:placetype":"locality"
},
  "geometry": {"coordinates":[14.53938,49.91398],"type":"Point"}
}