{
  "type": "Feature",
  "properties": {
    "gn:admin1_code":"90.0",
    "gn:admin2_code":"0722",
    "gn:asciiname":"Novy Dvur",
    "gn:country_code":"CZ",
    "gn:dem":333,
    "gn:feature_class":"P",
    "gn:feature_code":"PPL",
    "gn:name":"Nov\u00fd Dv\u016fr",
    "gn:population":0,
    "gn:timezone":"Europe/Prague",
    "iso:country":"CZ",
    "wof:name":"Novy Dvur",
    "wof:placetype":"locality"
},
  "geometry": {"coordinates":[17.36667000000001,49.11667],"type":"Point"}
}