{
  "type": "Feature",
  "properties": {
    "gn:admin1_code":"89.0",
    "gn:admin2_code":"0424",
    "gn:asciiname":"Solopysky",
    "gn:country_code":"CZ",
    "gn:dem":303,
    "gn:feature_class":"P",
    "gn:feature_code":"PPL",
    "gn:name":"Solopysky",
    "gn:population":0,
    "gn:timezone":"Europe/Prague",
    "iso:country":"CZ",
    "wof:name":"Solopysky",
    "wof:placetype":"locality"
},
  "geometry": {"coordinates":[13.74647,50.25895],"type":"Point"}
}