{
  "type": "Feature",
  "properties": {
    "iso:country":"CZ",
    "name:azb_x_preferred":[
        "\u0647\u0648\u0644\u0634\u062a\u06cc\u0646"
    ],
    "name:ceb_x_preferred":[
        "Hol\u0161tejn"
    ],
    "name:ces_x_preferred":[
        "Hol\u0161tejn"
    ],
    "name:deu_x_preferred":[
        "Hol\u0161tejn"
    ],
    "name:eus_x_preferred":[
        "Hol\u0161tejn"
    ],
    "name:fas_x_preferred":[
        "\u0647\u0648\u0644\u0634\u062a\u06cc\u0646"
    ],
    "name:fra_x_preferred":[
        "Hol\u0161tejn"
    ],
    "name:hun_x_preferred":[
        "Hol\u0161tejn"
    ],
    "name:ita_x_preferred":[
        "Hol\u0161tejn"
    ],
    "name:msa_x_preferred":[
        "Hol\u0161tejn"
    ],
    "name:nld_x_preferred":[
        "Hol\u0161tejn"
    ],
    "name:por_x_preferred":[
        "Hol\u0161tejn"
    ],
    "name:slk_x_preferred":[
        "Hol\u0161tejn"
    ],
    "name:spa_x_preferred":[
        "Hol\u0161tejn"
    ],
    "name:srp_x_preferred":[
        "\u0425\u043e\u043b\u0448\u0442\u0435\u0458\u043d"
    ],
    "name:swe_x_preferred":[
        "Hol\u0161tejn"
    ],
    "name:vie_x_preferred":[
        "Hol\u0161tejn"
    ],
    "qs_pg:aaroncc":"CZ",
    "qs_pg:name":"Hol\u0161tejn",
    "qs_pg:name_adm0":"\u010cesk\u00e1 republika",
    "qs_pg:name_adm1":"Jihomoravsk\u00fd kraj",
    "qs_pg:photos":1,
    "qs_pg:photos_1k":1,
    "qs_pg:photos_9k":1,
    "qs_pg:photos_9r":1,
    "qs_pg:photos_all":7,
    "qs_pg:photos_sr":1,
    "qs_pg:pop_sr":0,
    "qs_pg:qs_pg_placetype":"localadmin",
    "qs_pg:qs_pg_placetype_gp":"LocalAdmin",
    "qs_pg:woe_adm0":23424810,
    "woe:adm0_id":23424810,
    "woe:name_adm0":"\u010cesk\u00e1 republika",
    "woe:name_adm1":"Jihomoravsk\u00fd kraj",
    "woe:placetype":"LocalAdmin",
    "wof:name":"Hol\u0161tejn",
    "wof:placetype":"localadmin"
},
  "geometry": {"coordinates":[16.773848,49.401688],"type":"Point"}
}