{
  "type": "Feature",
  "properties": {
    "gn:admin1_code":"90.0",
    "gn:admin2_code":"0724",
    "gn:asciiname":"Bylnice",
    "gn:country_code":"CZ",
    "gn:dem":311,
    "gn:feature_class":"P",
    "gn:feature_code":"PPL",
    "gn:name":"Bylnice",
    "gn:population":0,
    "gn:timezone":"Europe/Prague",
    "iso:country":"CZ",
    "name:und_x_variant":[
        "Bilnitz",
        "Bylnice"
    ],
    "wof:name":"Bylnice",
    "wof:placetype":"locality"
},
  "geometry": {"coordinates":[18.01142999999999,49.07429000000001],"type":"Point"}
}