{
  "type": "Feature",
  "properties": {
    "gn:country":"CZ",
    "gn:fcode":"PPL",
    "gn:population":976,
    "iso:country":"CZ",
    "name:azb_x_preferred":[
        "\u0648\u06cc\u062a\u06cc\u062a\u0633\u0647"
    ],
    "name:cat_x_preferred":[
        "Vitice"
    ],
    "name:ceb_x_preferred":[
        "Vitice"
    ],
    "name:ces_x_preferred":[
        "Vitice"
    ],
    "name:che_x_preferred":[
        "\u0412\u0438\u0442\u0438\u0446\u0435"
    ],
    "name:eng_x_preferred":[
        "Vitice"
    ],
    "name:eus_x_preferred":[
        "Vitice"
    ],
    "name:fas_x_preferred":[
        "\u0648\u06cc\u062a\u06cc\u062a\u0633\u0647"
    ],
    "name:fra_x_preferred":[
        "Vitice"
    ],
    "name:gle_x_preferred":[
        "Vitice"
    ],
    "name:hun_x_preferred":[
        "Vitice"
    ],
    "name:ita_x_preferred":[
        "Vitice"
    ],
    "name:lmo_x_preferred":[
        "Vitice"
    ],
    "name:msa_x_preferred":[
        "Vitice"
    ],
    "name:nan_x_preferred":[
        "Vitice"
    ],
    "name:nld_x_preferred":[
        "Vitice"
    ],
    "name:pol_x_preferred":[
        "Vitice"
    ],
    "name:por_x_preferred":[
        "Vitice"
    ],
    "name:slk_x_preferred":[
        "Vitice"
    ],
    "name:spa_x_preferred":[
        "Vitice"
    ],
    "name:srp_x_preferred":[
        "\u0412\u0438\u0442\u0438\u0446\u0435"
    ],
    "name:swe_x_preferred":[
        "Vitice"
    ],
    "name:tat_x_preferred":[
        "\u0412\u0438\u0442\u0438\u0446\u0435"
    ],
    "name:vie_x_preferred":[
        "Vitice"
    ],
    "qs_pg:aaroncc":"CZ",
    "qs_pg:gn_country":"CZ",
    "qs_pg:gn_fcode":"PPL",
    "qs_pg:gn_pop":976,
    "qs_pg:name":"Vitice",
    "qs_pg:name_adm0":"\u010cesk\u00e1 republika",
    "qs_pg:name_adm1":"St\u0159edo\u010desk\u00fd kraj",
    "qs_pg:photos_9k":1,
    "qs_pg:photos_9r":1,
    "qs_pg:photos_all":1,
    "qs_pg:photos_sr":0,
    "qs_pg:pop_sr":2,
    "qs_pg:qs_pg_placetype":"locality",
    "qs_pg:qs_pg_placetype_gp":"Town",
    "qs_pg:woe_adm0":23424810,
    "woe:adm0_id":23424810,
    "woe:name_adm0":"\u010cesk\u00e1 republika",
    "woe:name_adm1":"St\u0159edo\u010desk\u00fd kraj",
    "woe:placetype":"Town",
    "wof:name":"Vitice",
    "wof:placetype":"locality",
    "wof:population":976
},
  "geometry": {"coordinates":[14.91451,50.031],"type":"Point"}
}