{
  "type": "Feature",
  "properties": {
    "gn:admin1_code":"80",
    "gn:admin2_code":"0615",
    "gn:asciiname":"Vrtezir",
    "gn:country_code":"CZ",
    "gn:dem":456,
    "gn:feature_class":"P",
    "gn:feature_code":"PPL",
    "gn:name":"Vrt\u011b\u017e\u00ed\u0159",
    "gn:population":0,
    "gn:timezone":"Europe/Prague",
    "iso:country":"CZ",
    "wof:name":"Vrtezir",
    "wof:placetype":"locality"
},
  "geometry": {"coordinates":[16.30957,49.50147],"type":"Point"}
}