{
  "type": "Feature",
  "properties": {
    "iso:country":"CZ",
    "name:ceb_x_preferred":[
        "Rajhrad"
    ],
    "name:ces_x_preferred":[
        "Rajhrad"
    ],
    "name:deu_x_preferred":[
        "Rajhrad"
    ],
    "name:eus_x_preferred":[
        "Rajhrad"
    ],
    "name:fas_x_preferred":[
        "\u0631\u0627\u06cc\u0647\u0631\u0627\u062f"
    ],
    "name:fra_x_preferred":[
        "Rajhrad"
    ],
    "name:hun_x_preferred":[
        "Rajhrad"
    ],
    "name:ita_x_preferred":[
        "Rajhrad"
    ],
    "name:lav_x_preferred":[
        "Rajhrada"
    ],
    "name:msa_x_preferred":[
        "Rajhrad"
    ],
    "name:nld_x_preferred":[
        "Rajhrad"
    ],
    "name:pol_x_preferred":[
        "Rajhrad"
    ],
    "name:por_x_preferred":[
        "Rajhrad"
    ],
    "name:slk_x_preferred":[
        "Rajhrad"
    ],
    "name:spa_x_preferred":[
        "Rajhrad"
    ],
    "name:srp_x_preferred":[
        "\u0420\u0430\u0458\u0445\u0440\u0430\u0434"
    ],
    "name:swe_x_preferred":[
        "Rajhrad"
    ],
    "name:vie_x_preferred":[
        "Rajhrad"
    ],
    "name:zho_x_preferred":[
        "\u8cf4\u8d6b\u62c9\u5fb7"
    ],
    "qs_pg:aaroncc":"CZ",
    "qs_pg:name":"Rajhrad",
    "qs_pg:name_adm0":"\u010cesk\u00e1 republika",
    "qs_pg:name_adm1":"Jihomoravsk\u00fd kraj",
    "qs_pg:photos":1,
    "qs_pg:photos_1k":1,
    "qs_pg:photos_9k":1,
    "qs_pg:photos_9r":2,
    "qs_pg:photos_all":56,
    "qs_pg:photos_sr":1,
    "qs_pg:pop_sr":0,
    "qs_pg:qs_pg_placetype":"localadmin",
    "qs_pg:qs_pg_placetype_gp":"LocalAdmin",
    "qs_pg:woe_adm0":23424810,
    "woe:adm0_id":23424810,
    "woe:name_adm0":"\u010cesk\u00e1 republika",
    "woe:name_adm1":"Jihomoravsk\u00fd kraj",
    "woe:placetype":"LocalAdmin",
    "wof:name":"Rajhrad",
    "wof:placetype":"localadmin"
},
  "geometry": {"coordinates":[16.615261,49.08953],"type":"Point"}
}