{
  "type": "Feature",
  "properties": {
    "gn:admin1_code":"88",
    "gn:admin2_code":"0201",
    "gn:asciiname":"Strelitov",
    "gn:country_code":"CZ",
    "gn:dem":494,
    "gn:feature_class":"P",
    "gn:feature_code":"PPL",
    "gn:name":"St\u0159el\u00edtov",
    "gn:population":0,
    "gn:timezone":"Europe/Prague",
    "iso:country":"CZ",
    "wof:name":"Strelitov",
    "wof:placetype":"locality"
},
  "geometry": {"coordinates":[14.61799,49.63495],"type":"Point"}
}