{
  "type": "Feature",
  "properties": {
    "gn:country":"CZ",
    "gn:fcode":"PPL",
    "gn:population":437,
    "iso:country":"CZ",
    "name:azb_x_preferred":[
        "\u0632\u0628\u062a\u0634\u0646\u0648"
    ],
    "name:cat_x_preferred":[
        "Zbe\u010dno"
    ],
    "name:ceb_x_preferred":[
        "Zbe\u010dno"
    ],
    "name:ces_x_preferred":[
        "Zbe\u010dno"
    ],
    "name:che_x_preferred":[
        "\u0417\u0431\u0435\u0447\u043d\u043e"
    ],
    "name:deu_x_preferred":[
        "Zbe\u010dno"
    ],
    "name:ell_x_preferred":[
        "\u0396\u03bc\u03c0\u03ad\u03c4\u03c3\u03bd\u03bf"
    ],
    "name:eng_x_preferred":[
        "Zbe\u010dno"
    ],
    "name:epo_x_preferred":[
        "Zbe\u010dno"
    ],
    "name:eus_x_preferred":[
        "Zbe\u010dno"
    ],
    "name:fas_x_preferred":[
        "\u0632\u0628\u062a\u0634\u0646\u0648"
    ],
    "name:fra_x_preferred":[
        "Zbe\u010dno"
    ],
    "name:gle_x_preferred":[
        "Zbe\u010dno"
    ],
    "name:hun_x_preferred":[
        "Zbe\u010dno"
    ],
    "name:ita_x_preferred":[
        "Zbe\u010dno"
    ],
    "name:lmo_x_preferred":[
        "Zbe\u010dno"
    ],
    "name:msa_x_preferred":[
        "Zbe\u010dno"
    ],
    "name:nan_x_preferred":[
        "Zbe\u010dno"
    ],
    "name:nld_x_preferred":[
        "Zbe\u010dno"
    ],
    "name:pol_x_preferred":[
        "Zbe\u010dno"
    ],
    "name:por_x_preferred":[
        "Zbe\u010dno"
    ],
    "name:slk_x_preferred":[
        "Zbe\u010dno"
    ],
    "name:spa_x_preferred":[
        "Zbe\u010dno"
    ],
    "name:srp_x_preferred":[
        "\u0417\u0431\u0435\u0447\u043d\u043e"
    ],
    "name:swe_x_preferred":[
        "Zbe\u010dno"
    ],
    "name:tat_x_preferred":[
        "\u0417\u0431\u0435\u0447\u043d\u043e"
    ],
    "name:und_x_variant":[
        "Zbetschno"
    ],
    "name:vie_x_preferred":[
        "Zbe\u010dno"
    ],
    "qs_pg:aaroncc":"CZ",
    "qs_pg:gn_country":"CZ",
    "qs_pg:gn_fcode":"PPL",
    "qs_pg:gn_pop":437,
    "qs_pg:name":"Zbe\u010dno",
    "qs_pg:name_adm0":"\u010cesk\u00e1 republika",
    "qs_pg:name_adm1":"St\u0159edo\u010desk\u00fd kraj",
    "qs_pg:photos_9k":1,
    "qs_pg:photos_9r":1,
    "qs_pg:photos_all":1,
    "qs_pg:photos_sr":0,
    "qs_pg:pop_sr":2,
    "qs_pg:qs_pg_placetype":"locality",
    "qs_pg:qs_pg_placetype_gp":"Town",
    "qs_pg:woe_adm0":23424810,
    "woe:adm0_id":23424810,
    "woe:name_adm0":"\u010cesk\u00e1 republika",
    "woe:name_adm1":"St\u0159edo\u010desk\u00fd kraj",
    "woe:placetype":"Town",
    "wof:name":"Zbe\u010dno",
    "wof:placetype":"locality",
    "wof:population":437
},
  "geometry": {"coordinates":[13.92036,50.04179],"type":"Point"}
}