{
  "type": "Feature",
  "properties": {
    "gn:gn_country":"CZ",
    "gn:gn_fcode":"PPL",
    "gn:gn_pop":182,
    "gn:population":182,
    "iso:country":"CZ",
    "name:azb_x_preferred":[
        "\u0644\u06cc\u0634\u0646\u06cc\u062a\u0633\u0647"
    ],
    "name:ceb_x_preferred":[
        "Li\u0161nice"
    ],
    "name:ces_x_preferred":[
        "Li\u0161nice"
    ],
    "name:deu_x_preferred":[
        "Li\u0161nice"
    ],
    "name:eng_x_preferred":[
        "Li\u0161nice"
    ],
    "name:eus_x_preferred":[
        "Li\u0161nice"
    ],
    "name:fas_x_preferred":[
        "\u0644\u06cc\u0634\u0646\u06cc\u062a\u0633\u0647"
    ],
    "name:fra_x_preferred":[
        "Li\u0161nice"
    ],
    "name:hun_x_preferred":[
        "Li\u0161nice"
    ],
    "name:ita_x_preferred":[
        "Li\u0161nice"
    ],
    "name:msa_x_preferred":[
        "Li\u0161nice"
    ],
    "name:nan_x_preferred":[
        "Li\u0161nice"
    ],
    "name:nld_x_preferred":[
        "Li\u0161nice"
    ],
    "name:por_x_preferred":[
        "Li\u0161nice"
    ],
    "name:slk_x_preferred":[
        "Li\u0161nice"
    ],
    "name:spa_x_preferred":[
        "Li\u0161nice"
    ],
    "name:srp_x_preferred":[
        "\u041b\u0438\u0448\u045a\u0438\u0446\u0435"
    ],
    "name:swe_x_preferred":[
        "Li\u0161nice"
    ],
    "name:vie_x_preferred":[
        "Li\u0161nice"
    ],
    "qs_pg:aaroncc":"CZ",
    "qs_pg:gn_country":"CZ",
    "qs_pg:gn_fcode":"PPL",
    "qs_pg:gn_pop":182,
    "qs_pg:name":"Li\u0161nice",
    "qs_pg:name_adm0":"\u010cesk\u00e1 republika",
    "qs_pg:name_adm1":"\u00dasteck\u00fd kraj",
    "qs_pg:photos_9r":0,
    "qs_pg:photos_sr":0,
    "qs_pg:pop_sr":1,
    "qs_pg:qs_pg_placetype":"locality",
    "qs_pg:qs_pg_placetype_gp":"Town",
    "qs_pg:woe_adm0":23424810,
    "woe:adm0_id":23424810,
    "woe:name_adm0":"\u010cesk\u00e1 republika",
    "woe:name_adm1":"\u00dasteck\u00fd kraj",
    "woe:placetype":"Town",
    "wof:name":"Li\u0161nice",
    "wof:placetype":"locality",
    "wof:population":182
},
  "geometry": {"coordinates":[13.63301,50.45445],"type":"Point"}
}