{
  "type": "Feature",
  "properties": {
    "gn:gn_country":"CZ",
    "gn:gn_fcode":"PPL",
    "gn:gn_pop":68,
    "gn:population":68,
    "iso:country":"CZ",
    "name:azb_x_preferred":[
        "\u0648\u0631\u062e\u0648\u0648\u0646\u06cc\u062a\u0633\u0647"
    ],
    "name:ces_x_preferred":[
        "Vrchovnice"
    ],
    "name:deu_x_preferred":[
        "Vrchovnice"
    ],
    "name:eng_x_preferred":[
        "Vrchovnice"
    ],
    "name:eus_x_preferred":[
        "Vrchovnice"
    ],
    "name:fas_x_preferred":[
        "\u0648\u0631\u062e\u0648\u0648\u0646\u06cc\u062a\u0633\u0647"
    ],
    "name:fra_x_preferred":[
        "Vrchovnice"
    ],
    "name:hun_x_preferred":[
        "Vrchovnice"
    ],
    "name:ita_x_preferred":[
        "Vrchovnice"
    ],
    "name:msa_x_preferred":[
        "Vrchovnice"
    ],
    "name:nan_x_preferred":[
        "Vrchovnice"
    ],
    "name:nld_x_preferred":[
        "Vrchovnice"
    ],
    "name:pol_x_preferred":[
        "Vrchovnice"
    ],
    "name:por_x_preferred":[
        "Vrchovnice"
    ],
    "name:slk_x_preferred":[
        "Vrchovnice"
    ],
    "name:spa_x_preferred":[
        "Vrchovnice"
    ],
    "name:srp_x_preferred":[
        "\u0412\u0440\u0445\u043e\u0432\u045a\u0438\u0446\u0435"
    ],
    "name:vie_x_preferred":[
        "Vrchovnice"
    ],
    "qs_pg:aaroncc":"CZ",
    "qs_pg:gn_country":"CZ",
    "qs_pg:gn_fcode":"PPL",
    "qs_pg:gn_pop":68,
    "qs_pg:name":"Vrchovnice",
    "qs_pg:name_adm0":"\u010cesk\u00e1 republika",
    "qs_pg:name_adm1":"Kr\u00e1lov\u00e9hradeck\u00fd kraj",
    "qs_pg:photos_9r":0,
    "qs_pg:photos_sr":0,
    "qs_pg:pop_sr":1,
    "qs_pg:qs_pg_placetype":"locality",
    "qs_pg:qs_pg_placetype_gp":"Town",
    "qs_pg:woe_adm0":23424810,
    "woe:adm0_id":23424810,
    "woe:name_adm0":"\u010cesk\u00e1 republika",
    "woe:name_adm1":"Kr\u00e1lov\u00e9hradeck\u00fd kraj",
    "woe:placetype":"Town",
    "wof:name":"Vrchovnice",
    "wof:placetype":"locality",
    "wof:population":68
},
  "geometry": {"coordinates":[15.75752,50.32293],"type":"Point"}
}