{
  "type": "Feature",
  "properties": {
    "gn:admin1_code":"79",
    "gn:admin2_code":"0311",
    "gn:asciiname":"Stipoklasy",
    "gn:country_code":"CZ",
    "gn:dem":456,
    "gn:feature_class":"P",
    "gn:feature_code":"PPL",
    "gn:name":"\u0160tipoklasy",
    "gn:population":0,
    "gn:timezone":"Europe/Prague",
    "iso:country":"CZ",
    "wof:name":"Stipoklasy",
    "wof:placetype":"locality"
},
  "geometry": {"coordinates":[14.50972,49.18935],"type":"Point"}
}