{
  "type": "Feature",
  "properties": {
    "gn:country":"CZ",
    "gn:fcode":"PPL",
    "gn:population":50,
    "iso:country":"CZ",
    "name:azb_x_preferred":[
        "\u0632\u0627\u062f\u0646\u06cc \u0648\u06cc\u062f\u0631\u06cc"
    ],
    "name:ces_x_preferred":[
        "Zadn\u00ed Vyd\u0159\u00ed"
    ],
    "name:deu_x_preferred":[
        "Zadn\u00ed Vyd\u0159\u00ed"
    ],
    "name:eng_x_preferred":[
        "Zadn\u00ed Vyd\u0159\u00ed"
    ],
    "name:eus_x_preferred":[
        "Zadn\u00ed Vyd\u0159\u00ed"
    ],
    "name:fas_x_preferred":[
        "\u0632\u0627\u062f\u0646\u06cc \u0648\u06cc\u062f\u0631\u06cc"
    ],
    "name:fra_x_preferred":[
        "Zadn\u00ed Vyd\u0159\u00ed"
    ],
    "name:hun_x_preferred":[
        "Zadn\u00ed Vyd\u0159\u00ed"
    ],
    "name:ita_x_preferred":[
        "Zadn\u00ed Vyd\u0159\u00ed"
    ],
    "name:msa_x_preferred":[
        "Zadn\u00ed Vyd\u0159\u00ed"
    ],
    "name:nan_x_preferred":[
        "Zadn\u00ed Vyd\u0159\u00ed"
    ],
    "name:nld_x_preferred":[
        "Zadn\u00ed Vyd\u0159\u00ed"
    ],
    "name:pol_x_preferred":[
        "Zadn\u00ed Vyd\u0159\u00ed"
    ],
    "name:por_x_preferred":[
        "Zadn\u00ed Vyd\u0159\u00ed"
    ],
    "name:rup_x_preferred":[
        "Zadn\u00ed Vyd\u0159\u00ed"
    ],
    "name:slk_x_preferred":[
        "Zadn\u00ed Vyd\u0159\u00ed"
    ],
    "name:spa_x_preferred":[
        "Zadn\u00ed Vyd\u0159\u00ed"
    ],
    "name:srp_x_preferred":[
        "\u0417\u0430\u0434\u045a\u0438 \u0412\u0438\u0434\u0440\u0438"
    ],
    "name:urd_x_preferred":[
        "\u0632\u062f\u0646\u06cc \u0648\u06cc\u062f\u06cc\u06cc"
    ],
    "name:vie_x_preferred":[
        "Zadn\u00ed Vyd\u0159\u00ed"
    ],
    "qs_pg:aaroncc":"CZ",
    "qs_pg:gn_country":"CZ",
    "qs_pg:gn_fcode":"PPL",
    "qs_pg:gn_pop":50,
    "qs_pg:name":"Zadn\u00ed Vyd\u0159\u00ed",
    "qs_pg:name_adm0":"\u010cesk\u00e1 republika",
    "qs_pg:name_adm1":"Kraj Vyso\u010dina",
    "qs_pg:photos_9r":0,
    "qs_pg:photos_sr":0,
    "qs_pg:pop_sr":1,
    "qs_pg:qs_pg_placetype":"locality",
    "qs_pg:qs_pg_placetype_gp":"Town",
    "qs_pg:woe_adm0":23424810,
    "woe:adm0_id":23424810,
    "woe:name_adm0":"\u010cesk\u00e1 republika",
    "woe:name_adm1":"Kraj Vyso\u010dina",
    "woe:placetype":"Town",
    "wof:name":"Zadn\u00ed Vyd\u0159\u00ed",
    "wof:placetype":"locality",
    "wof:population":50
},
  "geometry": {"coordinates":[15.4171,49.13434],"type":"Point"}
}