{
  "type": "Feature",
  "properties": {
    "gn:admin1_code":"79.0",
    "gn:admin2_code":"0314",
    "gn:asciiname":"Sobesice",
    "gn:country_code":"CZ",
    "gn:dem":472,
    "gn:feature_class":"P",
    "gn:feature_code":"PPL",
    "gn:name":"Sob\u011b\u0161ice",
    "gn:population":0,
    "gn:timezone":"Europe/Prague",
    "iso:country":"CZ",
    "wof:name":"Sobesice",
    "wof:placetype":"locality"
},
  "geometry": {"coordinates":[14.03461,49.37025],"type":"Point"}
}