{
  "type": "Feature",
  "properties": {
    "gn:admin1_code":"79.0",
    "gn:admin2_code":"0312",
    "gn:asciiname":"Sedlikov",
    "gn:country_code":"CZ",
    "gn:dem":688,
    "gn:feature_class":"P",
    "gn:feature_code":"PPL",
    "gn:name":"Sedl\u00edkov",
    "gn:population":0,
    "gn:timezone":"Europe/Prague",
    "iso:country":"CZ",
    "name:und_x_variant":[
        "Zettlesreith",
        "Sedl\u00edkov"
    ],
    "wof:name":"Sedlikov",
    "wof:placetype":"locality"
},
  "geometry": {"coordinates":[14.39621,48.68215],"type":"Point"}
}