{
  "type": "Feature",
  "properties": {
    "gn:gn_country":"CZ",
    "gn:gn_fcode":"PPL",
    "gn:gn_pop":380,
    "gn:population":380,
    "iso:country":"CZ",
    "name:cze_x_preferred":[
        "Bukovice"
    ],
    "name:dut_x_preferred":[
        "Bukovice"
    ],
    "name:eng_x_preferred":[
        "Bukovice"
    ],
    "name:fre_x_preferred":[
        "Bukovice"
    ],
    "name:ger_x_preferred":[
        "Bukovice"
    ],
    "name:hun_x_preferred":[
        "Bukovice"
    ],
    "name:ita_x_preferred":[
        "Bukovice"
    ],
    "name:may_x_preferred":[
        "Bukovice"
    ],
    "name:per_x_preferred":[
        "\u0628\u0648\u06a9\u0648\u0648\u06cc\u062a\u0633\u0647"
    ],
    "name:pol_x_preferred":[
        "Bukovice"
    ],
    "name:por_x_preferred":[
        "Bukovice"
    ],
    "name:rup_x_preferred":[
        "Bukovice"
    ],
    "name:slo_x_preferred":[
        "Bukovice"
    ],
    "name:srp_x_preferred":[
        "\u0411\u0443\u043a\u043e\u0432\u0438\u0446\u0435"
    ],
    "name:swe_x_preferred":[
        "Bukovice"
    ],
    "name:vie_x_preferred":[
        "Bukovice"
    ],
    "qs_pg:aaroncc":"CZ",
    "qs_pg:gn_country":"CZ",
    "qs_pg:gn_fcode":"PPL",
    "qs_pg:gn_pop":380,
    "qs_pg:name":"Bukovice",
    "qs_pg:name_adm0":"\u010cesk\u00e1 republika",
    "qs_pg:name_adm1":"Kr\u00e1lov\u00e9hradeck\u00fd kraj",
    "qs_pg:photos_9k":1,
    "qs_pg:photos_9r":1,
    "qs_pg:photos_all":2,
    "qs_pg:photos_sr":0,
    "qs_pg:pop_sr":2,
    "qs_pg:qs_pg_placetype":"locality",
    "qs_pg:qs_pg_placetype_gp":"Town",
    "qs_pg:woe_adm0":23424810,
    "woe:adm0_id":23424810,
    "woe:name_adm0":"\u010cesk\u00e1 republika",
    "woe:name_adm1":"Kr\u00e1lov\u00e9hradeck\u00fd kraj",
    "woe:placetype":"Town",
    "wof:name":"Bukovice",
    "wof:placetype":"locality",
    "wof:population":380
},
  "geometry": {"coordinates":[16.22793,50.54955],"type":"Point"}
}