{
  "type": "Feature",
  "properties": {
    "gn:gn_country":"CZ",
    "gn:gn_fcode":"PPL",
    "gn:gn_pop":389,
    "gn:population":389,
    "iso:country":"CZ",
    "name:cze_x_preferred":[
        "Dla\u017eov"
    ],
    "name:dut_x_preferred":[
        "Dla\u017eov"
    ],
    "name:eng_x_preferred":[
        "Dla\u017eov"
    ],
    "name:fre_x_preferred":[
        "Dla\u017eov"
    ],
    "name:ger_x_preferred":[
        "Dla\u017eov"
    ],
    "name:hun_x_preferred":[
        "Dla\u017eov"
    ],
    "name:ita_x_preferred":[
        "Dla\u017eov"
    ],
    "name:may_x_preferred":[
        "Dla\u017eov"
    ],
    "name:per_x_preferred":[
        "\u062f\u0644\u0627\u0698\u0648\u0648"
    ],
    "name:pol_x_preferred":[
        "Dla\u017eov"
    ],
    "name:por_x_preferred":[
        "Dla\u017eov"
    ],
    "name:slo_x_preferred":[
        "Dla\u017eov"
    ],
    "name:srp_x_preferred":[
        "\u0414\u043b\u0430\u0436\u043e\u0432"
    ],
    "name:swe_x_preferred":[
        "Dla\u017eov"
    ],
    "name:vie_x_preferred":[
        "Dla\u017eov"
    ],
    "qs_pg:aaroncc":"CZ",
    "qs_pg:gn_country":"CZ",
    "qs_pg:gn_fcode":"PPL",
    "qs_pg:gn_pop":389,
    "qs_pg:name":"Dla\u017eov",
    "qs_pg:name_adm0":"\u010cesk\u00e1 republika",
    "qs_pg:name_adm1":"Plze\u0148sk\u00fd kraj",
    "qs_pg:photos_9k":1,
    "qs_pg:photos_9r":1,
    "qs_pg:photos_all":1,
    "qs_pg:photos_sr":0,
    "qs_pg:pop_sr":2,
    "qs_pg:qs_pg_placetype":"locality",
    "qs_pg:qs_pg_placetype_gp":"Town",
    "qs_pg:woe_adm0":23424810,
    "woe:adm0_id":23424810,
    "woe:name_adm0":"\u010cesk\u00e1 republika",
    "woe:name_adm1":"Plze\u0148sk\u00fd kraj",
    "woe:placetype":"Town",
    "wof:name":"Dla\u017eov",
    "wof:placetype":"locality",
    "wof:population":389
},
  "geometry": {"coordinates":[13.16634,49.36574],"type":"Point"}
}