{
  "type": "Feature",
  "properties": {
    "gn:admin1_code":"89.0",
    "gn:admin2_code":"0422",
    "gn:asciiname":"Kysovice",
    "gn:country_code":"CZ",
    "gn:dem":740,
    "gn:feature_class":"P",
    "gn:feature_code":"PPL",
    "gn:name":"K\u00fd\u0161ovice",
    "gn:population":0,
    "gn:timezone":"Europe/Prague",
    "iso:country":"CZ",
    "name:und_x_variant":[
        "Gaischwitz",
        "K\u00fd\u0161ovice"
    ],
    "wof:name":"Kysovice",
    "wof:placetype":"locality"
},
  "geometry": {"coordinates":[13.25392,50.47304000000001],"type":"Point"}
}