{
  "type": "Feature",
  "properties": {
    "gn:admin1_code":"85.0",
    "gn:admin2_code":"0802",
    "gn:asciiname":"Hradek",
    "gn:country_code":"CZ",
    "gn:dem":356,
    "gn:feature_class":"P",
    "gn:feature_code":"PPL",
    "gn:name":"Hr\u00e1dek",
    "gn:population":1753,
    "gn:timezone":"Europe/Prague",
    "iso:country":"CZ",
    "wof:name":"Hradek",
    "wof:placetype":"locality",
    "wof:population":1753
},
  "geometry": {"coordinates":[18.7372,49.61661],"type":"Point"}
}