{
  "type": "Feature",
  "properties": {
    "gn:admin1_code":"85.0",
    "gn:admin2_code":"0802",
    "gn:asciiname":"Hradek",
    "gn:country_code":"CZ",
    "gn:dem":356,
    "gn:feature_class":"P",
    "gn:feature_code":"PPL",
    "gn:name":"Hr\u00e1dek",
    "gn:population":1753,
    "gn:timezone":"Europe/Prague",
    "iso:country":"CZ",
    "name:azb_x_preferred":[
        "\u0647\u0631\u0627\u062f\u06a9"
    ],
    "name:ces_x_preferred":[
        "Hr\u00e1dek"
    ],
    "name:eus_x_preferred":[
        "Hr\u00e1dek"
    ],
    "name:fas_x_preferred":[
        "\u0647\u0631\u0627\u062f\u06a9"
    ],
    "name:hun_x_preferred":[
        "Hr\u00e1dek"
    ],
    "name:ita_x_preferred":[
        "Hr\u00e1dek"
    ],
    "name:msa_x_preferred":[
        "Hr\u00e1dek"
    ],
    "name:nld_x_preferred":[
        "Hr\u00e1dek"
    ],
    "name:pol_x_preferred":[
        "Gr\u00f3dek"
    ],
    "name:por_x_preferred":[
        "Hr\u00e1dek"
    ],
    "name:slk_x_preferred":[
        "Hr\u00e1dek"
    ],
    "name:spa_x_preferred":[
        "Hr\u00e1dek"
    ],
    "name:srp_x_preferred":[
        "\u0425\u0440\u0430\u0434\u0435\u043a"
    ],
    "name:vie_x_preferred":[
        "Hr\u00e1dek"
    ],
    "wof:name":"Hradek",
    "wof:placetype":"locality",
    "wof:population":1753
},
  "geometry": {"coordinates":[18.7372,49.61661],"type":"Point"}
}