{
  "type": "Feature",
  "properties": {
    "gn:admin1_code":"89.0",
    "gn:admin2_code":"0423",
    "gn:asciiname":"Kresov",
    "gn:country_code":"CZ",
    "gn:dem":223,
    "gn:feature_class":"P",
    "gn:feature_code":"PPL",
    "gn:name":"K\u0159e\u0161ov",
    "gn:population":0,
    "gn:timezone":"Europe/Prague",
    "iso:country":"CZ",
    "wof:name":"Kresov",
    "wof:placetype":"locality"
},
  "geometry": {"coordinates":[14.3969,50.49246],"type":"Point"}
}