{
  "type": "Feature",
  "properties": {
    "gn:admin1_code":"82.0",
    "gn:admin2_code":"0521",
    "gn:asciiname":"Lhota pod Strani",
    "gn:country_code":"CZ",
    "gn:dem":238,
    "gn:feature_class":"P",
    "gn:feature_code":"PPL",
    "gn:name":"Lhota pod Str\u00e1n\u00ed",
    "gn:population":0,
    "gn:timezone":"Europe/Prague",
    "iso:country":"CZ",
    "wof:name":"Lhota pod Strani",
    "wof:placetype":"locality"
},
  "geometry": {"coordinates":[15.84543,50.18737],"type":"Point"}
}