{
  "type": "Feature",
  "properties": {
    "gn:admin1_code":"79.0",
    "gn:admin2_code":"0313",
    "gn:asciiname":"Maly Jenikov",
    "gn:country_code":"CZ",
    "gn:dem":578,
    "gn:feature_class":"P",
    "gn:feature_code":"PPL",
    "gn:name":"Mal\u00fd Jen\u00edkov",
    "gn:population":0,
    "gn:timezone":"Europe/Prague",
    "iso:country":"CZ",
    "wof:name":"Maly Jenikov",
    "wof:placetype":"locality"
},
  "geometry": {"coordinates":[15.23491,49.15049000000001],"type":"Point"}
}