{
  "type": "Feature",
  "properties": {
    "gn:admin1_code":"80.0",
    "gn:admin2_code":"0612",
    "gn:asciiname":"Nepomuky",
    "gn:country_code":"CZ",
    "gn:dem":670,
    "gn:feature_class":"P",
    "gn:feature_code":"PPL",
    "gn:name":"Nepomuky",
    "gn:population":0,
    "gn:timezone":"Europe/Prague",
    "iso:country":"CZ",
    "wof:name":"Nepomuky",
    "wof:placetype":"locality"
},
  "geometry": {"coordinates":[15.57311,49.21312],"type":"Point"}
}