{
  "type": "Feature",
  "properties": {
    "gn:gn_country":"CZ",
    "gn:gn_fcode":"PPL",
    "gn:gn_pop":447,
    "gn:population":447,
    "iso:country":"CZ",
    "name:cze_x_preferred":[
        "T\u0159ebusice"
    ],
    "name:dut_x_preferred":[
        "T\u0159ebusice"
    ],
    "name:eng_x_preferred":[
        "T\u0159ebusice"
    ],
    "name:fre_x_preferred":[
        "T\u0159ebusice"
    ],
    "name:hun_x_preferred":[
        "T\u0159ebusice"
    ],
    "name:ita_x_preferred":[
        "T\u0159ebusice"
    ],
    "name:may_x_preferred":[
        "T\u0159ebusice"
    ],
    "name:per_x_preferred":[
        "\u062a\u0631\u0628\u0648\u0633\u06cc\u0686"
    ],
    "name:por_x_preferred":[
        "T\u0159ebusice"
    ],
    "name:slo_x_preferred":[
        "T\u0159ebusice"
    ],
    "name:srp_x_preferred":[
        "\u0422\u0440\u0435\u0431\u0443\u0441\u0438\u0446\u0435"
    ],
    "name:swe_x_preferred":[
        "T\u0159ebusice"
    ],
    "name:vie_x_preferred":[
        "T\u0159ebusice"
    ],
    "qs_pg:aaroncc":"CZ",
    "qs_pg:gn_country":"CZ",
    "qs_pg:gn_fcode":"PPL",
    "qs_pg:gn_pop":447,
    "qs_pg:name":"T\u0159ebusice",
    "qs_pg:name_adm0":"\u010cesk\u00e1 republika",
    "qs_pg:name_adm1":"St\u0159edo\u010desk\u00fd kraj",
    "qs_pg:photos_9r":0,
    "qs_pg:photos_sr":0,
    "qs_pg:pop_sr":2,
    "qs_pg:qs_pg_placetype":"locality",
    "qs_pg:qs_pg_placetype_gp":"Town",
    "qs_pg:woe_adm0":23424810,
    "woe:adm0_id":23424810,
    "woe:name_adm0":"\u010cesk\u00e1 republika",
    "woe:name_adm1":"St\u0159edo\u010desk\u00fd kraj",
    "woe:placetype":"Town",
    "wof:name":"T\u0159ebusice",
    "wof:placetype":"locality",
    "wof:population":447
},
  "geometry": {"coordinates":[14.18064,50.20077],"type":"Point"}
}