{
  "type": "Feature",
  "properties": {
    "gn:admin1_code":"82.0",
    "gn:admin2_code":"0525",
    "gn:asciiname":"Huntirov",
    "gn:country_code":"CZ",
    "gn:dem":478,
    "gn:feature_class":"P",
    "gn:feature_code":"PPL",
    "gn:name":"Hunt\u00ed\u0159ov",
    "gn:population":0,
    "gn:timezone":"Europe/Prague",
    "iso:country":"CZ",
    "name:und_x_variant":[
        "G\u00fcntersdorf",
        "Hunt\u00ed\u0159ov"
    ],
    "wof:name":"Huntirov",
    "wof:placetype":"locality"
},
  "geometry": {"coordinates":[15.80555,50.47753],"type":"Point"}
}