{
  "type": "Feature",
  "properties": {
    "gn:admin1_code":"84.0",
    "gn:admin2_code":"0712",
    "gn:asciiname":"Sedm Dvoru",
    "gn:cc2":"CZ",
    "gn:country_code":"CZ",
    "gn:dem":549,
    "gn:feature_class":"P",
    "gn:feature_code":"PPL",
    "gn:name":"Sedm Dvor\u016f",
    "gn:population":0,
    "gn:timezone":"Europe/Prague",
    "iso:country":"CZ",
    "name:und_x_variant":[
        "Siebenh\u00f6fen"
    ],
    "wof:name":"Sedm Dvoru",
    "wof:placetype":"locality"
},
  "geometry": {"coordinates":[17.43333,49.78333],"type":"Point"}
}