{
  "type": "Feature",
  "properties": {
    "gn:admin1_code":"81",
    "gn:admin2_code":"0411",
    "gn:asciiname":"Vsebor",
    "gn:country_code":"CZ",
    "gn:dem":441,
    "gn:feature_class":"P",
    "gn:feature_code":"PPL",
    "gn:name":"V\u0161ebo\u0159",
    "gn:population":0,
    "gn:timezone":"Europe/Prague",
    "iso:country":"CZ",
    "name:und_x_variant":[
        "Sch\u00f6ba",
        "\u0160ebor"
    ],
    "wof:name":"Vsebor",
    "wof:placetype":"locality"
},
  "geometry": {"coordinates":[12.40923,50.04413],"type":"Point"}
}