{
  "type": "Feature",
  "properties": {
    "gn:gn_country":"CZ",
    "gn:gn_fcode":"PPL",
    "gn:gn_pop":569,
    "gn:population":569,
    "iso:country":"CZ",
    "name:bul_x_preferred":[
        "\u041d\u0435\u043c\u0438\u043b\u0435"
    ],
    "name:ces_x_preferred":[
        "Nemile"
    ],
    "name:deu_x_preferred":[
        "Nemile"
    ],
    "name:eng_x_preferred":[
        "Nemile"
    ],
    "name:fas_x_preferred":[
        "\u0646\u0645\u06cc\u0644\u0647"
    ],
    "name:fra_x_preferred":[
        "Nemile"
    ],
    "name:hun_x_preferred":[
        "Nemile"
    ],
    "name:ita_x_preferred":[
        "Nemile"
    ],
    "name:msa_x_preferred":[
        "Nemile"
    ],
    "name:nld_x_preferred":[
        "Nemile"
    ],
    "name:pol_x_preferred":[
        "Nemile"
    ],
    "name:por_x_preferred":[
        "Nemile"
    ],
    "name:slk_x_preferred":[
        "Nemile"
    ],
    "name:srp_x_preferred":[
        "\u041d\u0435\u043c\u0438\u043b\u0435"
    ],
    "name:swe_x_preferred":[
        "Nemile"
    ],
    "name:vie_x_preferred":[
        "Nemile"
    ],
    "qs_pg:aaroncc":"CZ",
    "qs_pg:gn_country":"CZ",
    "qs_pg:gn_fcode":"PPL",
    "qs_pg:gn_pop":569,
    "qs_pg:name":"Nemile",
    "qs_pg:name_adm0":"\u010cesk\u00e1 republika",
    "qs_pg:name_adm1":"Olomouck\u00fd kraj",
    "qs_pg:photos_9r":0,
    "qs_pg:photos_sr":0,
    "qs_pg:pop_sr":2,
    "qs_pg:qs_pg_placetype":"locality",
    "qs_pg:qs_pg_placetype_gp":"Town",
    "qs_pg:woe_adm0":23424810,
    "woe:adm0_id":23424810,
    "woe:name_adm0":"\u010cesk\u00e1 republika",
    "woe:name_adm1":"Olomouck\u00fd kraj",
    "woe:placetype":"Town",
    "wof:name":"Nemile",
    "wof:placetype":"locality",
    "wof:population":569
},
  "geometry": {"coordinates":[16.84745,49.87477],"type":"Point"}
}