{
  "type": "Feature",
  "properties": {
    "gn:country":"CZ",
    "gn:fcode":"PPL",
    "gn:population":85,
    "iso:country":"CZ",
    "name:azb_x_preferred":[
        "\u06a9\u0648\u06cc\u062a\u06a9\u0648\u0648\u06cc\u062a\u0633\u0647"
    ],
    "name:cat_x_preferred":[
        "Kv\u00edtkovice"
    ],
    "name:ces_x_preferred":[
        "Kv\u00edtkovice"
    ],
    "name:che_x_preferred":[
        "\u041a\u0432\u0438\u0442\u043a\u043e\u0432\u0438\u0446\u0435"
    ],
    "name:deu_x_preferred":[
        "Kv\u00edtkovice"
    ],
    "name:eng_x_preferred":[
        "Kv\u00edtkovice"
    ],
    "name:epo_x_preferred":[
        "Kv\u00edtkovice"
    ],
    "name:eus_x_preferred":[
        "Kv\u00edtkovice"
    ],
    "name:fas_x_preferred":[
        "\u06a9\u0648\u06cc\u062a\u06a9\u0648\u0648\u06cc\u062a\u0633\u0647"
    ],
    "name:fra_x_preferred":[
        "Kv\u00edtkovice"
    ],
    "name:gle_x_preferred":[
        "Kv\u00edtkovice"
    ],
    "name:hun_x_preferred":[
        "Kv\u00edtkovice"
    ],
    "name:ita_x_preferred":[
        "Kv\u00edtkovice"
    ],
    "name:lmo_x_preferred":[
        "Kv\u00edtkovice"
    ],
    "name:msa_x_preferred":[
        "Kv\u00edtkovice"
    ],
    "name:nan_x_preferred":[
        "Kv\u00edtkovice"
    ],
    "name:nld_x_preferred":[
        "Kv\u00edtkovice"
    ],
    "name:pol_x_preferred":[
        "Kv\u00edtkovice"
    ],
    "name:por_x_preferred":[
        "Kv\u00edtkovice"
    ],
    "name:rup_x_preferred":[
        "Kv\u00edtkovice"
    ],
    "name:slk_x_preferred":[
        "Kv\u00edtkovice"
    ],
    "name:spa_x_preferred":[
        "Kv\u00edtkovice"
    ],
    "name:srp_x_preferred":[
        "\u041a\u0432\u0438\u0442\u043a\u043e\u0432\u0438\u0446\u0435"
    ],
    "name:tat_x_preferred":[
        "\u041a\u0432\u0438\u0442\u043a\u043e\u0432\u0438\u0446\u0435"
    ],
    "name:vie_x_preferred":[
        "Kv\u00edtkovice"
    ],
    "qs_pg:aaroncc":"CZ",
    "qs_pg:gn_country":"CZ",
    "qs_pg:gn_fcode":"PPL",
    "qs_pg:gn_pop":85,
    "qs_pg:name":"Kv\u00edtkovice",
    "qs_pg:name_adm0":"\u010cesk\u00e1 republika",
    "qs_pg:name_adm1":"Jiho\u010desk\u00fd kraj",
    "qs_pg:photos_9k":1,
    "qs_pg:photos_9r":1,
    "qs_pg:photos_all":1,
    "qs_pg:photos_sr":0,
    "qs_pg:pop_sr":1,
    "qs_pg:qs_pg_placetype":"locality",
    "qs_pg:qs_pg_placetype_gp":"Town",
    "qs_pg:woe_adm0":23424810,
    "woe:adm0_id":23424810,
    "woe:name_adm0":"\u010cesk\u00e1 republika",
    "woe:name_adm1":"Jiho\u010desk\u00fd kraj",
    "woe:placetype":"Town",
    "wof:name":"Kv\u00edtkovice",
    "wof:placetype":"locality",
    "wof:population":85
},
  "geometry": {"coordinates":[14.33116,48.9574],"type":"Point"}
}