{
  "type": "Feature",
  "properties": {
    "gn:gn_country":"CZ",
    "gn:gn_fcode":"PPL",
    "gn:gn_pop":85,
    "gn:population":85,
    "iso:country":"CZ",
    "name:cze_x_preferred":[
        "Kv\u00edtkovice"
    ],
    "name:dut_x_preferred":[
        "Kv\u00edtkovice"
    ],
    "name:eng_x_preferred":[
        "Kv\u00edtkovice"
    ],
    "name:fre_x_preferred":[
        "Kv\u00edtkovice"
    ],
    "name:ger_x_preferred":[
        "Kv\u00edtkovice"
    ],
    "name:hun_x_preferred":[
        "Kv\u00edtkovice"
    ],
    "name:ita_x_preferred":[
        "Kv\u00edtkovice"
    ],
    "name:may_x_preferred":[
        "Kv\u00edtkovice"
    ],
    "name:per_x_preferred":[
        "\u06a9\u0648\u06cc\u062a\u06a9\u0648\u0648\u06cc\u062a\u0633\u0647"
    ],
    "name:pol_x_preferred":[
        "Kv\u00edtkovice"
    ],
    "name:por_x_preferred":[
        "Kv\u00edtkovice"
    ],
    "name:rup_x_preferred":[
        "Kv\u00edtkovice"
    ],
    "name:slo_x_preferred":[
        "Kv\u00edtkovice"
    ],
    "name:srp_x_preferred":[
        "\u041a\u0432\u0438\u0442\u043a\u043e\u0432\u0438\u0446\u0435"
    ],
    "name:vie_x_preferred":[
        "Kv\u00edtkovice"
    ],
    "qs_pg:aaroncc":"CZ",
    "qs_pg:gn_country":"CZ",
    "qs_pg:gn_fcode":"PPL",
    "qs_pg:gn_pop":85,
    "qs_pg:name":"Kv\u00edtkovice",
    "qs_pg:name_adm0":"\u010cesk\u00e1 republika",
    "qs_pg:name_adm1":"Jiho\u010desk\u00fd kraj",
    "qs_pg:photos_9k":1,
    "qs_pg:photos_9r":1,
    "qs_pg:photos_all":1,
    "qs_pg:photos_sr":0,
    "qs_pg:pop_sr":1,
    "qs_pg:qs_pg_placetype":"locality",
    "qs_pg:qs_pg_placetype_gp":"Town",
    "qs_pg:woe_adm0":23424810,
    "woe:adm0_id":23424810,
    "woe:name_adm0":"\u010cesk\u00e1 republika",
    "woe:name_adm1":"Jiho\u010desk\u00fd kraj",
    "woe:placetype":"Town",
    "wof:name":"Kv\u00edtkovice",
    "wof:placetype":"locality",
    "wof:population":85
},
  "geometry": {"coordinates":[14.33116,48.9574],"type":"Point"}
}