{
  "type": "Feature",
  "properties": {
    "gn:admin1_code":"78",
    "gn:admin2_code":"0623",
    "gn:asciiname":"Zernuvka",
    "gn:country_code":"CZ",
    "gn:dem":343,
    "gn:feature_class":"P",
    "gn:feature_code":"PPL",
    "gn:name":"\u017dern\u016fvka",
    "gn:population":0,
    "gn:timezone":"Europe/Prague",
    "iso:country":"CZ",
    "wof:name":"Zernuvka",
    "wof:placetype":"locality"
},
  "geometry": {"coordinates":[16.38332999999999,49.33333],"type":"Point"}
}