{
  "type": "Feature",
  "properties": {
    "gn:country":"CZ",
    "gn:fcode":"PPL",
    "gn:population":601,
    "iso:country":"CZ",
    "name:azb_x_preferred":[
        "\u0648\u0631\u062e\u0648\u0633\u0644\u0627\u0648\u06cc\u062a\u0633\u0647"
    ],
    "name:ceb_x_preferred":[
        "Vrchoslavice"
    ],
    "name:ces_x_preferred":[
        "Vrchoslavice"
    ],
    "name:eng_x_preferred":[
        "Vrchoslavice"
    ],
    "name:eus_x_preferred":[
        "Vrchoslavice"
    ],
    "name:fas_x_preferred":[
        "\u0648\u0631\u062e\u0648\u0633\u0644\u0627\u0648\u06cc\u062a\u0633\u0647"
    ],
    "name:fra_x_preferred":[
        "Vrchoslavice"
    ],
    "name:hun_x_preferred":[
        "Vrchoslavice"
    ],
    "name:ita_x_preferred":[
        "Vrchoslavice"
    ],
    "name:msa_x_preferred":[
        "Vrchoslavice"
    ],
    "name:nan_x_preferred":[
        "Vrchoslavice"
    ],
    "name:nld_x_preferred":[
        "Vrchoslavice"
    ],
    "name:pol_x_preferred":[
        "Vrchoslavice"
    ],
    "name:por_x_preferred":[
        "Vrchoslavice"
    ],
    "name:rup_x_preferred":[
        "Vrchoslavice"
    ],
    "name:slk_x_preferred":[
        "Vrchoslavice"
    ],
    "name:spa_x_preferred":[
        "Vrchoslavice"
    ],
    "name:srp_x_preferred":[
        "\u0412\u0440\u0445\u043e\u0441\u043b\u0430\u0432\u0438\u0446\u0435"
    ],
    "name:swe_x_preferred":[
        "Vrchoslavice"
    ],
    "name:vie_x_preferred":[
        "Vrchoslavice"
    ],
    "qs_pg:aaroncc":"CZ",
    "qs_pg:gn_country":"CZ",
    "qs_pg:gn_fcode":"PPL",
    "qs_pg:gn_pop":601,
    "qs_pg:name":"Vrchoslavice",
    "qs_pg:name_adm0":"\u010cesk\u00e1 republika",
    "qs_pg:name_adm1":"Olomouck\u00fd kraj",
    "qs_pg:photos_9r":0,
    "qs_pg:photos_sr":0,
    "qs_pg:pop_sr":2,
    "qs_pg:qs_pg_placetype":"locality",
    "qs_pg:qs_pg_placetype_gp":"Town",
    "qs_pg:woe_adm0":23424810,
    "woe:adm0_id":23424810,
    "woe:name_adm0":"\u010cesk\u00e1 republika",
    "woe:name_adm1":"Olomouck\u00fd kraj",
    "woe:placetype":"Town",
    "wof:name":"Vrchoslavice",
    "wof:placetype":"locality",
    "wof:population":601
},
  "geometry": {"coordinates":[17.21833,49.33301],"type":"Point"}
}