{
  "type": "Feature",
  "properties": {
    "gn:admin1_code":"85.0",
    "gn:admin2_code":"0801",
    "gn:asciiname":"Moravsky Kocov",
    "gn:country_code":"CZ",
    "gn:dem":564,
    "gn:feature_class":"P",
    "gn:feature_code":"PPL",
    "gn:name":"Moravsk\u00fd Ko\u010dov",
    "gn:population":0,
    "gn:timezone":"Europe/Prague",
    "iso:country":"CZ",
    "name:und_x_variant":[
        "Kotzendorf",
        "M\u00e4hrisch Kotzendorf",
        "Moravsk\u00fd Ko\u010dov"
    ],
    "wof:name":"Moravsky Kocov",
    "wof:placetype":"locality"
},
  "geometry": {"coordinates":[17.4412,49.95583],"type":"Point"}
}