{
  "type": "Feature",
  "properties": {
    "gn:country":"CZ",
    "gn:fcode":"PPL",
    "gn:population":685,
    "iso:country":"CZ",
    "name:azb_x_preferred":[
        "\u0627\u0648\u0631\u062e"
    ],
    "name:ceb_x_preferred":[
        "O\u0159ech"
    ],
    "name:ces_x_preferred":[
        "O\u0159ech"
    ],
    "name:deu_x_preferred":[
        "O\u0159ech"
    ],
    "name:eng_x_preferred":[
        "O\u0159ech"
    ],
    "name:eus_x_preferred":[
        "O\u0159ech"
    ],
    "name:fas_x_preferred":[
        "\u0627\u0648\u0631\u062e"
    ],
    "name:fra_x_preferred":[
        "O\u0159ech"
    ],
    "name:hun_x_preferred":[
        "O\u0159ech"
    ],
    "name:ita_x_preferred":[
        "O\u0159ech"
    ],
    "name:msa_x_preferred":[
        "O\u0159ech"
    ],
    "name:nan_x_preferred":[
        "O\u0159ech"
    ],
    "name:nld_x_preferred":[
        "O\u0159ech"
    ],
    "name:pol_x_preferred":[
        "O\u0159ech"
    ],
    "name:por_x_preferred":[
        "O\u0159ech"
    ],
    "name:slk_x_preferred":[
        "O\u0159ech"
    ],
    "name:spa_x_preferred":[
        "O\u0159ech"
    ],
    "name:srp_x_preferred":[
        "\u041e\u0440\u0436\u0435\u0445"
    ],
    "name:swe_x_preferred":[
        "O\u0159ech"
    ],
    "name:vie_x_preferred":[
        "O\u0159ech"
    ],
    "qs_pg:aaroncc":"CZ",
    "qs_pg:gn_country":"CZ",
    "qs_pg:gn_fcode":"PPL",
    "qs_pg:gn_pop":685,
    "qs_pg:name":"O\u0159ech",
    "qs_pg:name_adm0":"\u010cesk\u00e1 republika",
    "qs_pg:name_adm1":"St\u0159edo\u010desk\u00fd kraj",
    "qs_pg:photos_9k":1,
    "qs_pg:photos_9r":1,
    "qs_pg:photos_all":3,
    "qs_pg:photos_sr":0,
    "qs_pg:pop_sr":2,
    "qs_pg:qs_pg_placetype":"locality",
    "qs_pg:qs_pg_placetype_gp":"Town",
    "qs_pg:woe_adm0":23424810,
    "woe:adm0_id":23424810,
    "woe:name_adm0":"\u010cesk\u00e1 republika",
    "woe:name_adm1":"St\u0159edo\u010desk\u00fd kraj",
    "woe:placetype":"Town",
    "wof:name":"O\u0159ech",
    "wof:placetype":"locality",
    "wof:population":685
},
  "geometry": {"coordinates":[14.29655,50.02011],"type":"Point"}
}