{
  "type": "Feature",
  "properties": {
    "gn:admin1_code":"85.0",
    "gn:admin2_code":"0804",
    "gn:asciiname":"Moravske Vlkovice",
    "gn:country_code":"CZ",
    "gn:dem":333,
    "gn:feature_class":"P",
    "gn:feature_code":"PPL",
    "gn:name":"Moravsk\u00e9 Vlkovice",
    "gn:population":0,
    "gn:timezone":"Europe/Prague",
    "iso:country":"CZ",
    "name:und_x_variant":[
        "M\u00e4hrisch Wolfsdorf"
    ],
    "wof:name":"Moravske Vlkovice",
    "wof:placetype":"locality"
},
  "geometry": {"coordinates":[17.85072000000001,49.72254],"type":"Point"}
}