{
  "type": "Feature",
  "properties": {
    "gn:gn_country":"CZ",
    "gn:gn_fcode":"PPL",
    "gn:gn_pop":117,
    "gn:population":117,
    "iso:country":"CZ",
    "name:cze_x_preferred":[
        "Bystr\u00e1 nad Jizerou"
    ],
    "name:dut_x_preferred":[
        "Bystr\u00e1 nad Jizerou"
    ],
    "name:eng_x_preferred":[
        "Bystr\u00e1 nad Jizerou"
    ],
    "name:fre_x_preferred":[
        "Bystr\u00e1 nad Jizerou"
    ],
    "name:ger_x_preferred":[
        "Bystr\u00e1 nad Jizerou"
    ],
    "name:hun_x_preferred":[
        "Bystr\u00e1 nad Jizerou"
    ],
    "name:ita_x_preferred":[
        "Bystr\u00e1 nad Jizerou"
    ],
    "name:may_x_preferred":[
        "Bystr\u00e1 nad Jizerou"
    ],
    "name:per_x_preferred":[
        "\u0628\u06cc\u0633\u062a\u0631\u0627 \u0646\u0627\u062f \u06cc\u06cc\u0632\u0631\u0648\u0648"
    ],
    "name:pol_x_preferred":[
        "Bystr\u00e1 nad Jizerou"
    ],
    "name:por_x_preferred":[
        "Bystr\u00e1 nad Jizerou"
    ],
    "name:rup_x_preferred":[
        "Bystr\u00e1 nad Jizerou"
    ],
    "name:slo_x_preferred":[
        "Bystr\u00e1 nad Jizerou"
    ],
    "name:srp_x_preferred":[
        "\u0411\u0438\u0441\u0442\u0440\u0430 \u043d\u0430 \u0408\u0438\u0437\u0435\u0440\u0438"
    ],
    "name:swe_x_preferred":[
        "Bystr\u00e1 nad Jizerou"
    ],
    "name:vie_x_preferred":[
        "Bystr\u00e1 nad Jizerou"
    ],
    "qs_pg:aaroncc":"CZ",
    "qs_pg:gn_country":"CZ",
    "qs_pg:gn_fcode":"PPL",
    "qs_pg:gn_pop":117,
    "qs_pg:name":"Bystr\u00e1 nad Jizerou",
    "qs_pg:name_adm0":"\u010cesk\u00e1 republika",
    "qs_pg:name_adm1":"Libereck\u00fd kraj",
    "qs_pg:photos_9r":0,
    "qs_pg:photos_sr":0,
    "qs_pg:pop_sr":1,
    "qs_pg:qs_pg_placetype":"locality",
    "qs_pg:qs_pg_placetype_gp":"Town",
    "qs_pg:woe_adm0":23424810,
    "woe:adm0_id":23424810,
    "woe:name_adm0":"\u010cesk\u00e1 republika",
    "woe:name_adm1":"Libereck\u00fd kraj",
    "woe:placetype":"Town",
    "wof:name":"Bystr\u00e1 nad Jizerou",
    "wof:placetype":"locality",
    "wof:population":117
},
  "geometry": {"coordinates":[15.40187,50.60473],"type":"Point"}
}