{
  "type": "Feature",
  "properties": {
    "gn:admin1_code":"84",
    "gn:admin2_code":"0711",
    "gn:asciiname":"Vojtovice",
    "gn:country_code":"CZ",
    "gn:dem":465,
    "gn:feature_class":"P",
    "gn:feature_code":"PPL",
    "gn:name":"Vojtovice",
    "gn:population":0,
    "gn:timezone":"Europe/Prague",
    "iso:country":"CZ",
    "name:und_x_variant":[
        "Woitzdorf",
        "Vojtovice"
    ],
    "wof:name":"Vojtovice",
    "wof:placetype":"locality"
},
  "geometry": {"coordinates":[17.03462,50.32281],"type":"Point"}
}