{
  "type": "Feature",
  "properties": {
    "gn:gn_country":"CZ",
    "gn:gn_fcode":"PPL",
    "gn:gn_pop":62,
    "gn:population":62,
    "iso:country":"CZ",
    "name:ces_x_preferred":[
        "Lov\u010dovice"
    ],
    "name:eng_x_preferred":[
        "Lov\u010dovice"
    ],
    "name:fra_x_preferred":[
        "Lov\u010dovice"
    ],
    "name:hun_x_preferred":[
        "Lov\u010dovice"
    ],
    "name:ita_x_preferred":[
        "Lov\u010dovice"
    ],
    "name:msa_x_preferred":[
        "Lov\u010dovice"
    ],
    "name:nan_x_preferred":[
        "Lov\u010dovice"
    ],
    "name:nld_x_preferred":[
        "Lov\u010dovice"
    ],
    "name:por_x_preferred":[
        "Lov\u010dovice"
    ],
    "name:rup_x_preferred":[
        "Lov\u010dovice"
    ],
    "name:slk_x_preferred":[
        "Lov\u010dovice"
    ],
    "name:unk_x_variant":[
        "Lospitz"
    ],
    "name:vie_x_preferred":[
        "Lov\u010dovice"
    ],
    "qs_pg:aaroncc":"CZ",
    "qs_pg:gn_country":"CZ",
    "qs_pg:gn_fcode":"PPL",
    "qs_pg:gn_pop":62,
    "qs_pg:name":"Lov\u010dovice",
    "qs_pg:name_adm0":"\u010cesk\u00e1 republika",
    "qs_pg:name_adm1":"Kraj Vyso\u010dina",
    "qs_pg:photos_9r":0,
    "qs_pg:photos_sr":0,
    "qs_pg:pop_sr":1,
    "qs_pg:qs_pg_placetype":"locality",
    "qs_pg:qs_pg_placetype_gp":"Town",
    "qs_pg:woe_adm0":23424810,
    "woe:adm0_id":23424810,
    "woe:name_adm0":"\u010cesk\u00e1 republika",
    "woe:name_adm1":"Kraj Vyso\u010dina",
    "woe:placetype":"Town",
    "wof:name":"Lov\u010dovice",
    "wof:placetype":"locality",
    "wof:population":62
},
  "geometry": {"coordinates":[15.53432,48.98148],"type":"Point"}
}