{
  "type": "Feature",
  "properties": {
    "gn:gn_country":"CZ",
    "gn:gn_fcode":"PPL",
    "gn:gn_pop":820,
    "gn:population":820,
    "iso:country":"CZ",
    "name:ces_x_preferred":[
        "Klu\u010dov"
    ],
    "name:deu_x_preferred":[
        "Klu\u010dov u \u010cesk\u00e9ho Brodu"
    ],
    "name:eng_x_preferred":[
        "Klu\u010dov"
    ],
    "name:fra_x_preferred":[
        "Klu\u010dov"
    ],
    "name:hun_x_preferred":[
        "Klu\u010dov"
    ],
    "name:ita_x_preferred":[
        "Klu\u010dov"
    ],
    "name:msa_x_preferred":[
        "Klu\u010dov"
    ],
    "name:nan_x_preferred":[
        "Klu\u010dov"
    ],
    "name:nld_x_preferred":[
        "Klu\u010dov"
    ],
    "name:pol_x_preferred":[
        "Klu\u010dov"
    ],
    "name:por_x_preferred":[
        "Klu\u010dov"
    ],
    "name:rup_x_preferred":[
        "Klu\u010dov"
    ],
    "name:rus_x_preferred":[
        "\u041a\u043b\u0443\u0447\u043e\u0432"
    ],
    "name:slk_x_preferred":[
        "Klu\u010dov"
    ],
    "name:srp_x_preferred":[
        "\u041a\u043b\u0443\u0447\u043e\u0432"
    ],
    "name:swe_x_preferred":[
        "Klu\u010dov"
    ],
    "name:vie_x_preferred":[
        "Klu\u010dov"
    ],
    "qs_pg:aaroncc":"CZ",
    "qs_pg:gn_country":"CZ",
    "qs_pg:gn_fcode":"PPL",
    "qs_pg:gn_pop":820,
    "qs_pg:name":"Klu\u010dov",
    "qs_pg:name_adm0":"\u010cesk\u00e1 republika",
    "qs_pg:name_adm1":"St\u0159edo\u010desk\u00fd kraj",
    "qs_pg:photos_9k":1,
    "qs_pg:photos_9r":1,
    "qs_pg:photos_all":2,
    "qs_pg:photos_sr":0,
    "qs_pg:pop_sr":2,
    "qs_pg:qs_pg_placetype":"locality",
    "qs_pg:qs_pg_placetype_gp":"Town",
    "qs_pg:woe_adm0":23424810,
    "woe:adm0_id":23424810,
    "woe:name_adm0":"\u010cesk\u00e1 republika",
    "woe:name_adm1":"St\u0159edo\u010desk\u00fd kraj",
    "woe:placetype":"Town",
    "wof:name":"Klu\u010dov",
    "wof:placetype":"locality",
    "wof:population":820
},
  "geometry": {"coordinates":[14.91006,50.09501],"type":"Point"}
}