{
  "type": "Feature",
  "properties": {
    "gn:admin1_code":"80.0",
    "gn:admin2_code":"0611",
    "gn:asciiname":"Radnov",
    "gn:country_code":"CZ",
    "gn:dem":524,
    "gn:feature_class":"P",
    "gn:feature_code":"PPL",
    "gn:name":"Rad\u0148ov",
    "gn:population":0,
    "gn:timezone":"Europe/Prague",
    "iso:country":"CZ",
    "wof:name":"Radnov",
    "wof:placetype":"locality"
},
  "geometry": {"coordinates":[15.50085,49.55497],"type":"Point"}
}