{
  "type": "Feature",
  "properties": {
    "gn:admin1_code":"88.0",
    "gn:admin2_code":"020B",
    "gn:asciiname":"Hradist'ko",
    "gn:country_code":"CZ",
    "gn:dem":432,
    "gn:feature_class":"P",
    "gn:feature_code":"PPL",
    "gn:name":"Hradi\u0161\u0165ko",
    "gn:population":0,
    "gn:timezone":"Europe/Prague",
    "iso:country":"CZ",
    "wof:name":"Hradist'ko",
    "wof:placetype":"locality"
},
  "geometry": {"coordinates":[14.46074,49.6754],"type":"Point"}
}