{
  "type": "Feature",
  "properties": {
    "gn:admin1_code":"88",
    "gn:admin2_code":"0201",
    "gn:asciiname":"Vranovska Lhota",
    "gn:country_code":"CZ",
    "gn:dem":413,
    "gn:feature_class":"P",
    "gn:feature_code":"PPL",
    "gn:name":"Vranovsk\u00e1 Lhota",
    "gn:population":0,
    "gn:timezone":"Europe/Prague",
    "iso:country":"CZ",
    "name:und_x_variant":[
        "Wranow-Lhota",
        "Vranovsk\u00e1 Lhota"
    ],
    "wof:name":"Vranovska Lhota",
    "wof:placetype":"locality"
},
  "geometry": {"coordinates":[14.76101,49.84662],"type":"Point"}
}