{
  "type": "Feature",
  "properties": {
    "gn:admin1_code":"82",
    "gn:admin2_code":"0525",
    "gn:asciiname":"Zabor",
    "gn:country_code":"CZ",
    "gn:dem":687,
    "gn:feature_class":"P",
    "gn:feature_code":"PPL",
    "gn:name":"Z\u00e1bo\u0159",
    "gn:population":0,
    "gn:timezone":"Europe/Prague",
    "iso:country":"CZ",
    "wof:name":"Zabor",
    "wof:placetype":"locality"
},
  "geometry": {"coordinates":[16.11667000000001,50.58333],"type":"Point"}
}