{
  "type": "Feature",
  "properties": {
    "gn:admin1_code":"88",
    "gn:admin2_code":"0203",
    "gn:asciiname":"Vitov",
    "gn:country_code":"CZ",
    "gn:dem":231,
    "gn:feature_class":"P",
    "gn:feature_code":"PPL",
    "gn:name":"V\u00edtov",
    "gn:population":0,
    "gn:timezone":"Europe/Prague",
    "iso:country":"CZ",
    "wof:name":"Vitov",
    "wof:placetype":"locality"
},
  "geometry": {"coordinates":[14.14117,50.2467],"type":"Point"}
}