{
  "type": "Feature",
  "properties": {
    "gn:admin1_code":"85.0",
    "gn:admin2_code":"0802",
    "gn:asciiname":"Maly Lipovy",
    "gn:country_code":"CZ",
    "gn:dem":510,
    "gn:feature_class":"P",
    "gn:feature_code":"PPL",
    "gn:name":"Mal\u00fd Lipov\u00fd",
    "gn:population":0,
    "gn:timezone":"Europe/Prague",
    "iso:country":"CZ",
    "wof:name":"Maly Lipovy",
    "wof:placetype":"locality"
},
  "geometry": {"coordinates":[18.52448,49.61334],"type":"Point"}
}