{
  "type": "Feature",
  "properties": {
    "gn:gn_country":"CZ",
    "gn:gn_fcode":"PPL",
    "gn:gn_pop":529,
    "gn:population":529,
    "iso:country":"CZ",
    "name:ces_x_preferred":[
        "Dubnice"
    ],
    "name:deu_x_preferred":[
        "Dubnice pod Ralskem"
    ],
    "name:eng_x_preferred":[
        "Dubnice"
    ],
    "name:fas_x_preferred":[
        "\u062f\u0648\u0628\u0646\u06cc\u062a\u0633\u0647"
    ],
    "name:fra_x_preferred":[
        "Dubnice"
    ],
    "name:hun_x_preferred":[
        "Dubnice"
    ],
    "name:ita_x_preferred":[
        "Dubnice"
    ],
    "name:msa_x_preferred":[
        "Dubnice"
    ],
    "name:nld_x_preferred":[
        "Dubnice"
    ],
    "name:pol_x_preferred":[
        "Dubnice"
    ],
    "name:por_x_preferred":[
        "Dubnice"
    ],
    "name:slk_x_preferred":[
        "Dubnice"
    ],
    "name:srp_x_preferred":[
        "\u0414\u0443\u0431\u045a\u0438\u0446\u0435"
    ],
    "name:swe_x_preferred":[
        "Dubnice"
    ],
    "name:unk_x_variant":[
        "Hennersdorf"
    ],
    "name:vie_x_preferred":[
        "Dubnice"
    ],
    "qs_pg:aaroncc":"CZ",
    "qs_pg:gn_country":"CZ",
    "qs_pg:gn_fcode":"PPL",
    "qs_pg:gn_pop":529,
    "qs_pg:name":"Dubnice",
    "qs_pg:name_adm0":"\u010cesk\u00e1 republika",
    "qs_pg:name_adm1":"Libereck\u00fd kraj",
    "qs_pg:photos_9k":1,
    "qs_pg:photos_9r":1,
    "qs_pg:photos_all":2,
    "qs_pg:photos_sr":0,
    "qs_pg:pop_sr":2,
    "qs_pg:qs_pg_placetype":"locality",
    "qs_pg:qs_pg_placetype_gp":"Town",
    "qs_pg:woe_adm0":23424810,
    "woe:adm0_id":23424810,
    "woe:name_adm0":"\u010cesk\u00e1 republika",
    "woe:name_adm1":"Libereck\u00fd kraj",
    "woe:placetype":"Town",
    "wof:name":"Dubnice",
    "wof:placetype":"locality",
    "wof:population":529
},
  "geometry": {"coordinates":[14.80871,50.72597],"type":"Point"}
}