{
  "type": "Feature",
  "properties": {
    "gn:admin1_code":"84",
    "gn:admin2_code":"0712",
    "gn:asciiname":"Topolany",
    "gn:country_code":"CZ",
    "gn:dem":243,
    "gn:feature_class":"P",
    "gn:feature_code":"PPL",
    "gn:name":"Topolany",
    "gn:population":0,
    "gn:timezone":"Europe/Prague",
    "iso:country":"CZ",
    "wof:name":"Topolany",
    "wof:placetype":"locality"
},
  "geometry": {"coordinates":[17.17786,49.58512],"type":"Point"}
}