{
  "type": "Feature",
  "properties": {
    "gn:admin1_code":"84",
    "gn:admin2_code":"0712",
    "gn:asciiname":"Topolany",
    "gn:country_code":"CZ",
    "gn:dem":243,
    "gn:feature_class":"P",
    "gn:feature_code":"PPL",
    "gn:name":"Topolany",
    "gn:population":0,
    "gn:timezone":"Europe/Prague",
    "iso:country":"CZ",
    "name:azb_x_preferred":[
        "\u062a\u0648\u067e\u0648\u0644\u0627\u0646\u06cc"
    ],
    "name:ceb_x_preferred":[
        "Topolany"
    ],
    "name:ces_x_preferred":[
        "Topolany"
    ],
    "name:deu_x_preferred":[
        "Topolany"
    ],
    "name:eus_x_preferred":[
        "Topolany"
    ],
    "name:fas_x_preferred":[
        "\u062a\u0648\u067e\u0648\u0644\u0627\u0646\u06cc"
    ],
    "name:fra_x_preferred":[
        "Topolany"
    ],
    "name:hun_x_preferred":[
        "Topolany"
    ],
    "name:ita_x_preferred":[
        "Topolany"
    ],
    "name:msa_x_preferred":[
        "Topolany"
    ],
    "name:nld_x_preferred":[
        "Topolany"
    ],
    "name:por_x_preferred":[
        "Topolany"
    ],
    "name:slk_x_preferred":[
        "Topolany"
    ],
    "name:spa_x_preferred":[
        "Topolany"
    ],
    "name:srp_x_preferred":[
        "\u0422\u043e\u043f\u043e\u043b\u0430\u043d\u0438"
    ],
    "name:swe_x_preferred":[
        "Topolany"
    ],
    "name:vie_x_preferred":[
        "Topolany"
    ],
    "wof:name":"Topolany",
    "wof:placetype":"locality"
},
  "geometry": {"coordinates":[17.17786,49.58512],"type":"Point"}
}