{
  "type": "Feature",
  "properties": {
    "gn:admin1_code":"89.0",
    "gn:admin2_code":"0426",
    "gn:asciiname":"Barbora",
    "gn:country_code":"CZ",
    "gn:dem":295,
    "gn:feature_class":"P",
    "gn:feature_code":"PPL",
    "gn:name":"Barbora",
    "gn:population":0,
    "gn:timezone":"Europe/Prague",
    "iso:country":"CZ",
    "name:jpn_x_preferred":[
        "\u30d0\u30eb\u30dc\u30e9"
    ],
    "name:slk_x_preferred":[
        "Barbora"
    ],
    "wof:name":"Barbora",
    "wof:placetype":"locality"
},
  "geometry": {"coordinates":[13.73333,50.65],"type":"Point"}
}