{
  "type": "Feature",
  "properties": {
    "gn:gn_country":"CZ",
    "gn:gn_fcode":"PPL",
    "gn:gn_pop":317,
    "gn:population":317,
    "iso:country":"CZ",
    "name:ceb_x_preferred":[
        "Obora"
    ],
    "name:ces_x_preferred":[
        "Obora"
    ],
    "name:deu_x_preferred":[
        "Obora"
    ],
    "name:fra_x_preferred":[
        "Obora"
    ],
    "name:ita_x_preferred":[
        "Obora"
    ],
    "name:nld_x_preferred":[
        "Obora"
    ],
    "name:pol_x_preferred":[
        "Obora"
    ],
    "name:slk_x_preferred":[
        "Obora"
    ],
    "name:srp_x_preferred":[
        "\u041e\u0431\u043e\u0440\u0430"
    ],
    "name:swe_x_preferred":[
        "Obora"
    ],
    "name:ukr_x_preferred":[
        "\u041e\u0431\u043e\u0440\u0430"
    ],
    "qs_pg:aaroncc":"CZ",
    "qs_pg:gn_country":"CZ",
    "qs_pg:gn_fcode":"PPL",
    "qs_pg:gn_pop":317,
    "qs_pg:name":"Obora",
    "qs_pg:name_adm0":"\u010cesk\u00e1 republika",
    "qs_pg:name_adm1":"\u00dasteck\u00fd kraj",
    "qs_pg:photos_9r":0,
    "qs_pg:photos_sr":0,
    "qs_pg:pop_sr":2,
    "qs_pg:qs_pg_placetype":"locality",
    "qs_pg:qs_pg_placetype_gp":"Town",
    "qs_pg:woe_adm0":23424810,
    "woe:adm0_id":23424810,
    "woe:name_adm0":"\u010cesk\u00e1 republika",
    "woe:name_adm1":"\u00dasteck\u00fd kraj",
    "woe:placetype":"Town",
    "wof:name":"Obora",
    "wof:placetype":"locality",
    "wof:population":317
},
  "geometry": {"coordinates":[13.86297,50.37325],"type":"Point"}
}