{
  "type": "Feature",
  "properties": {
    "gn:country":"CZ",
    "gn:fcode":"PPL",
    "gn:population":222,
    "iso:country":"CZ",
    "name:azb_x_preferred":[
        "\u062f\u0631\u0627\u0647\u0648\u0628\u0648\u0632"
    ],
    "name:bul_x_preferred":[
        "\u0414\u0440\u0430\u0445\u043e\u0431\u0443\u0437"
    ],
    "name:cat_x_preferred":[
        "Drahobuz"
    ],
    "name:ceb_x_preferred":[
        "Drahobuz"
    ],
    "name:ces_x_preferred":[
        "Drahobuz"
    ],
    "name:che_x_preferred":[
        "\u0414\u0440\u0430\u0433\u043e\u0431\u0443\u0437"
    ],
    "name:deu_x_preferred":[
        "Drahobuz"
    ],
    "name:eng_x_preferred":[
        "Drahobuz"
    ],
    "name:epo_x_preferred":[
        "Drahobuz"
    ],
    "name:eus_x_preferred":[
        "Drahobuz"
    ],
    "name:fas_x_preferred":[
        "\u062f\u0631\u0627\u0647\u0648\u0628\u0648\u0632"
    ],
    "name:fra_x_preferred":[
        "Drahobuz"
    ],
    "name:gle_x_preferred":[
        "Drahobuz"
    ],
    "name:hun_x_preferred":[
        "Drahobuz"
    ],
    "name:ita_x_preferred":[
        "Drahobuz"
    ],
    "name:lmo_x_preferred":[
        "Drahobuz"
    ],
    "name:msa_x_preferred":[
        "Drahobuz"
    ],
    "name:nan_x_preferred":[
        "Drahobuz"
    ],
    "name:nld_x_preferred":[
        "Drahobuz"
    ],
    "name:pol_x_preferred":[
        "Drahobuz"
    ],
    "name:por_x_preferred":[
        "Drahobuz"
    ],
    "name:rup_x_preferred":[
        "Drahobuz"
    ],
    "name:slk_x_preferred":[
        "Drahobuz"
    ],
    "name:spa_x_preferred":[
        "Drahobuz"
    ],
    "name:srp_x_preferred":[
        "\u0414\u0440\u0430\u0445\u043e\u0431\u0443\u0437"
    ],
    "name:swe_x_preferred":[
        "Drahobuz"
    ],
    "name:tat_x_preferred":[
        "\u0414\u0440\u0430\u0433\u043e\u0431\u0443\u0437"
    ],
    "name:vie_x_preferred":[
        "Drahobuz"
    ],
    "qs_pg:aaroncc":"CZ",
    "qs_pg:gn_country":"CZ",
    "qs_pg:gn_fcode":"PPL",
    "qs_pg:gn_pop":222,
    "qs_pg:name":"Drahobuz",
    "qs_pg:name_adm0":"\u010cesk\u00e1 republika",
    "qs_pg:name_adm1":"\u00dasteck\u00fd kraj",
    "qs_pg:photos_9r":0,
    "qs_pg:photos_sr":0,
    "qs_pg:pop_sr":2,
    "qs_pg:qs_pg_placetype":"locality",
    "qs_pg:qs_pg_placetype_gp":"Town",
    "qs_pg:woe_adm0":23424810,
    "woe:adm0_id":23424810,
    "woe:name_adm0":"\u010cesk\u00e1 republika",
    "woe:name_adm1":"\u00dasteck\u00fd kraj",
    "woe:placetype":"Town",
    "wof:name":"Drahobuz",
    "wof:placetype":"locality",
    "wof:population":222
},
  "geometry": {"coordinates":[14.3207,50.52512],"type":"Point"}
}