{
  "type": "Feature",
  "properties": {
    "gn:admin1_code":"88.0",
    "gn:admin2_code":"0201",
    "gn:asciiname":"Bolina",
    "gn:country_code":"CZ",
    "gn:dem":471,
    "gn:feature_class":"P",
    "gn:feature_code":"PPL",
    "gn:name":"Bolina",
    "gn:population":0,
    "gn:timezone":"Europe/Prague",
    "iso:country":"CZ",
    "name:ces_x_preferred":[
        "Bolina"
    ],
    "name:ell_x_preferred":[
        "\u0392\u03bf\u03bb\u03af\u03bd\u03b1"
    ],
    "name:spa_x_preferred":[
        "Bolina"
    ],
    "wof:name":"Bolina",
    "wof:placetype":"locality"
},
  "geometry": {"coordinates":[14.95515,49.68142],"type":"Point"}
}