{
  "type": "Feature",
  "properties": {
    "gn:admin1_code":"85.0",
    "gn:admin2_code":"0803",
    "gn:asciiname":"Mosty u Ceskeho Tesina",
    "gn:country_code":"CZ",
    "gn:dem":311,
    "gn:feature_class":"P",
    "gn:feature_code":"PPL",
    "gn:name":"Mosty u \u010cesk\u00e9ho T\u011b\u0161\u00edna",
    "gn:population":0,
    "gn:timezone":"Europe/Prague",
    "iso:country":"CZ",
    "name:und_x_variant":[
        "Mosty",
        "Mosty u \u010cesk\u00e9ho T\u011b\u0161\u00edna"
    ],
    "wof:name":"Mosty u Ceskeho Tesina",
    "wof:placetype":"locality"
},
  "geometry": {"coordinates":[18.5917,49.75134],"type":"Point"}
}