{
  "type": "Feature",
  "properties": {
    "gn:gn_country":"CZ",
    "gn:gn_fcode":"PPL",
    "gn:gn_pop":210,
    "gn:population":210,
    "iso:country":"CZ",
    "name:cze_x_preferred":[
        "\u017dumberk"
    ],
    "name:dut_x_preferred":[
        "\u017dumberk"
    ],
    "name:eng_x_preferred":[
        "\u017dumberk"
    ],
    "name:epo_x_preferred":[
        "\u017dumberk"
    ],
    "name:fre_x_preferred":[
        "\u017dumberk"
    ],
    "name:ger_x_preferred":[
        "\u017dumberk"
    ],
    "name:hun_x_preferred":[
        "\u017dumberk"
    ],
    "name:ita_x_preferred":[
        "\u017dumberk"
    ],
    "name:may_x_preferred":[
        "\u017dumberk"
    ],
    "name:nan_x_preferred":[
        "\u017dumberk"
    ],
    "name:per_x_preferred":[
        "\u0698\u0648\u0645\u0628\u0631\u06a9"
    ],
    "name:pol_x_preferred":[
        "\u017dumberk"
    ],
    "name:por_x_preferred":[
        "\u017dumberk"
    ],
    "name:rup_x_preferred":[
        "\u017dumberk"
    ],
    "name:slo_x_preferred":[
        "\u017dumberk"
    ],
    "name:srp_x_preferred":[
        "\u0416\u0443\u043c\u0431\u0435\u0440\u043a"
    ],
    "name:swe_x_preferred":[
        "\u017dumberk"
    ],
    "name:unk_x_variant":[
        "\u017dumberg"
    ],
    "name:vie_x_preferred":[
        "\u017dumberk"
    ],
    "qs_pg:aaroncc":"CZ",
    "qs_pg:gn_country":"CZ",
    "qs_pg:gn_fcode":"PPL",
    "qs_pg:gn_pop":210,
    "qs_pg:name":"\u017dumberk",
    "qs_pg:name_adm0":"\u010cesk\u00e1 republika",
    "qs_pg:name_adm1":"Pardubick\u00fd kraj",
    "qs_pg:photos_9r":0,
    "qs_pg:photos_sr":0,
    "qs_pg:pop_sr":2,
    "qs_pg:qs_pg_placetype":"locality",
    "qs_pg:qs_pg_placetype_gp":"Town",
    "qs_pg:woe_adm0":23424810,
    "woe:adm0_id":23424810,
    "woe:name_adm0":"\u010cesk\u00e1 republika",
    "woe:name_adm1":"Pardubick\u00fd kraj",
    "woe:placetype":"Town",
    "wof:name":"\u017dumberk",
    "wof:placetype":"locality",
    "wof:population":210
},
  "geometry": {"coordinates":[15.85822,49.87271],"type":"Point"}
}