{
  "type": "Feature",
  "properties": {
    "gn:admin1_code":"79.0",
    "gn:admin2_code":"0313",
    "gn:asciiname":"Planina",
    "gn:country_code":"CZ",
    "gn:dem":480,
    "gn:feature_class":"P",
    "gn:feature_code":"PPL",
    "gn:name":"Planina",
    "gn:population":0,
    "gn:timezone":"Europe/Prague",
    "iso:country":"CZ",
    "name:bos_x_preferred":[
        "Planina"
    ],
    "name:ceb_x_preferred":[
        "Planina"
    ],
    "name:hrv_x_preferred":[
        "Planina"
    ],
    "name:ita_x_preferred":[
        "Planina"
    ],
    "name:nld_x_preferred":[
        "Planina"
    ],
    "name:sco_x_preferred":[
        "Planina"
    ],
    "name:slk_x_preferred":[
        "Planina"
    ],
    "name:slv_x_preferred":[
        "Planina"
    ],
    "name:swe_x_preferred":[
        "Planina"
    ],
    "wof:name":"Planina",
    "wof:placetype":"locality"
},
  "geometry": {"coordinates":[14.93333,48.98333],"type":"Point"}
}