{
  "type": "Feature",
  "properties": {
    "gn:country":"CZ",
    "gn:fcode":"PPL",
    "gn:population":113,
    "iso:country":"CZ",
    "name:azb_x_preferred":[
        "\u0627\u0648\u0628\u0648\u062a\u0634"
    ],
    "name:ceb_x_preferred":[
        "\u00dabo\u010d"
    ],
    "name:ces_x_preferred":[
        "\u00dabo\u010d"
    ],
    "name:deu_x_preferred":[
        "\u00dabo\u010d"
    ],
    "name:eng_x_preferred":[
        "\u00dabo\u010d"
    ],
    "name:eus_x_preferred":[
        "\u00dabo\u010d"
    ],
    "name:fas_x_preferred":[
        "\u0627\u0648\u0628\u0648\u062a\u0634"
    ],
    "name:fra_x_preferred":[
        "\u00dabo\u010d"
    ],
    "name:hun_x_preferred":[
        "\u00dabo\u010d"
    ],
    "name:ita_x_preferred":[
        "\u00dabo\u010d"
    ],
    "name:msa_x_preferred":[
        "\u00dabo\u010d"
    ],
    "name:nan_x_preferred":[
        "\u00dabo\u010d"
    ],
    "name:nld_x_preferred":[
        "\u00dabo\u010d"
    ],
    "name:pol_x_preferred":[
        "\u00dabo\u010d"
    ],
    "name:por_x_preferred":[
        "\u00dabo\u010d"
    ],
    "name:slk_x_preferred":[
        "\u00dabo\u010d"
    ],
    "name:spa_x_preferred":[
        "\u00dabo\u010d"
    ],
    "name:srp_x_preferred":[
        "\u0423\u0431\u043e\u0447"
    ],
    "name:swe_x_preferred":[
        "\u00dabo\u010d"
    ],
    "name:urd_x_preferred":[
        "\u0627\u0628\u0648\u0686"
    ],
    "name:vie_x_preferred":[
        "\u00dabo\u010d"
    ],
    "qs_pg:aaroncc":"CZ",
    "qs_pg:gn_country":"CZ",
    "qs_pg:gn_fcode":"PPL",
    "qs_pg:gn_pop":113,
    "qs_pg:name":"\u00dabo\u010d",
    "qs_pg:name_adm0":"\u010cesk\u00e1 republika",
    "qs_pg:name_adm1":"Plze\u0148sk\u00fd kraj",
    "qs_pg:photos_9k":1,
    "qs_pg:photos_9r":1,
    "qs_pg:photos_all":1,
    "qs_pg:photos_sr":0,
    "qs_pg:pop_sr":1,
    "qs_pg:qs_pg_placetype":"locality",
    "qs_pg:qs_pg_placetype_gp":"Town",
    "qs_pg:woe_adm0":23424810,
    "woe:adm0_id":23424810,
    "woe:name_adm0":"\u010cesk\u00e1 republika",
    "woe:name_adm1":"Plze\u0148sk\u00fd kraj",
    "woe:placetype":"Town",
    "wof:name":"\u00dabo\u010d",
    "wof:placetype":"locality",
    "wof:population":113
},
  "geometry": {"coordinates":[13.08688,49.44359],"type":"Point"}
}