{
  "type": "Feature",
  "properties": {
    "gn:admin1_code":"84",
    "gn:admin2_code":"0712",
    "gn:asciiname":"Veselicko",
    "gn:country_code":"CZ",
    "gn:dem":422,
    "gn:feature_class":"P",
    "gn:feature_code":"PPL",
    "gn:name":"Vesel\u00ed\u010dko",
    "gn:population":0,
    "gn:timezone":"Europe/Prague",
    "iso:country":"CZ",
    "wof:name":"Veselicko",
    "wof:placetype":"locality"
},
  "geometry": {"coordinates":[16.93354,49.66899],"type":"Point"}
}