{
  "type": "Feature",
  "properties": {
    "gn:admin1_code":"89.0",
    "gn:admin2_code":"0426",
    "gn:asciiname":"Radovesice",
    "gn:country_code":"CZ",
    "gn:dem":403,
    "gn:feature_class":"P",
    "gn:feature_code":"PPL",
    "gn:name":"Radovesice",
    "gn:population":0,
    "gn:timezone":"Europe/Prague",
    "iso:country":"CZ",
    "name:azb_x_preferred":[
        "\u0631\u0627\u062f\u0648\u0648\u0633\u06cc\u062a\u0633\u0647"
    ],
    "name:ceb_x_preferred":[
        "Radovesice"
    ],
    "name:ces_x_preferred":[
        "Radovesice"
    ],
    "name:deu_x_preferred":[
        "Radovesice"
    ],
    "name:epo_x_preferred":[
        "Radovesice"
    ],
    "name:eus_x_preferred":[
        "Radovesice"
    ],
    "name:fas_x_preferred":[
        "\u0631\u0627\u062f\u0648\u0648\u0633\u06cc\u062a\u0633\u0647"
    ],
    "name:fra_x_preferred":[
        "Radovesice"
    ],
    "name:hun_x_preferred":[
        "Radovesice"
    ],
    "name:ita_x_preferred":[
        "Radovesice"
    ],
    "name:msa_x_preferred":[
        "Radovesice"
    ],
    "name:nld_x_preferred":[
        "Radovesice"
    ],
    "name:por_x_preferred":[
        "Radovesice"
    ],
    "name:slk_x_preferred":[
        "Radovesice"
    ],
    "name:spa_x_preferred":[
        "Radovesice"
    ],
    "name:srp_x_preferred":[
        "\u0420\u0430\u0434\u043e\u0432\u0435\u0441\u0438\u0446\u0435"
    ],
    "name:swe_x_preferred":[
        "Radovesice"
    ],
    "name:vie_x_preferred":[
        "Radovesice"
    ],
    "wof:name":"Radovesice",
    "wof:placetype":"locality"
},
  "geometry": {"coordinates":[13.83333,50.55],"type":"Point"}
}