{
  "type": "Feature",
  "properties": {
    "gn:admin1_code":"79",
    "gn:admin2_code":"0312",
    "gn:asciiname":"Velky Stradov",
    "gn:country_code":"CZ",
    "gn:dem":578,
    "gn:feature_class":"P",
    "gn:feature_code":"PPL",
    "gn:name":"Velk\u00fd Stradov",
    "gn:population":0,
    "gn:timezone":"Europe/Prague",
    "iso:country":"CZ",
    "name:und_x_variant":[
        "Gross Strodau",
        "Velk\u00fd Stradov"
    ],
    "wof:name":"Velky Stradov",
    "wof:placetype":"locality"
},
  "geometry": {"coordinates":[14.46915,48.7344],"type":"Point"}
}