{
  "type": "Feature",
  "properties": {
    "gn:admin1_code":"80.0",
    "gn:admin2_code":"0611",
    "gn:asciiname":"Dolni Dvur",
    "gn:country_code":"CZ",
    "gn:dem":483,
    "gn:feature_class":"P",
    "gn:feature_code":"PPL",
    "gn:name":"Doln\u00ed Dv\u016fr",
    "gn:population":0,
    "gn:timezone":"Europe/Prague",
    "iso:country":"CZ",
    "wof:name":"Dolni Dvur",
    "wof:placetype":"locality"
},
  "geometry": {"coordinates":[15.43333,49.61667],"type":"Point"}
}