{
  "type": "Feature",
  "properties": {
    "gn:admin1_code":"89",
    "gn:admin2_code":"0422",
    "gn:asciiname":"Zieberle",
    "gn:country_code":"CZ",
    "gn:dem":583,
    "gn:feature_class":"P",
    "gn:feature_code":"PPL",
    "gn:name":"Zieberle",
    "gn:population":0,
    "gn:timezone":"Europe/Prague",
    "iso:country":"CZ",
    "name:und_x_variant":[
        "Cibrle",
        "Zieberle",
        "Ciberle",
        "\u00dabo\u010d\u00ed"
    ],
    "wof:name":"Zieberle",
    "wof:placetype":"locality"
},
  "geometry": {"coordinates":[13.23333,50.45],"type":"Point"}
}