{
  "type": "Feature",
  "properties": {
    "iso:country":"CZ",
    "name:ceb_x_preferred":[
        "Pl\u00e1nice"
    ],
    "name:ces_x_preferred":[
        "Pl\u00e1nice"
    ],
    "name:deu_x_preferred":[
        "Pl\u00e1nice"
    ],
    "name:epo_x_preferred":[
        "Pl\u00e1nice"
    ],
    "name:eus_x_preferred":[
        "Pl\u00e1nice"
    ],
    "name:fas_x_preferred":[
        "\u067e\u0644\u0627\u0646\u06cc\u062a\u0633\u0647"
    ],
    "name:fra_x_preferred":[
        "Pl\u00e1nice"
    ],
    "name:hun_x_preferred":[
        "Pl\u00e1nice"
    ],
    "name:ita_x_preferred":[
        "Pl\u00e1nice"
    ],
    "name:msa_x_preferred":[
        "Pl\u00e1nice"
    ],
    "name:nld_x_preferred":[
        "Pl\u00e1nice"
    ],
    "name:pol_x_preferred":[
        "Pl\u00e1nice"
    ],
    "name:por_x_preferred":[
        "Pl\u00e1nice"
    ],
    "name:rus_x_preferred":[
        "\u041f\u043b\u0430\u043d\u0438\u0446\u0435"
    ],
    "name:slk_x_preferred":[
        "Pl\u00e1nice"
    ],
    "name:spa_x_preferred":[
        "Pl\u00e1nice"
    ],
    "name:srp_x_preferred":[
        "\u041f\u043b\u0430\u045a\u0438\u0446\u0435"
    ],
    "name:swe_x_preferred":[
        "Pl\u00e1nice"
    ],
    "name:vie_x_preferred":[
        "Pl\u00e1nice"
    ],
    "name:zho_x_preferred":[
        "\u666e\u62c9\u5c3c\u91c7"
    ],
    "qs_pg:aaroncc":"CZ",
    "qs_pg:name":"Pl\u00e1nice",
    "qs_pg:name_adm0":"\u010cesk\u00e1 republika",
    "qs_pg:name_adm1":"Plze\u0148sk\u00fd kraj",
    "qs_pg:photos":1,
    "qs_pg:photos_1k":1,
    "qs_pg:photos_9k":1,
    "qs_pg:photos_9r":1,
    "qs_pg:photos_all":11,
    "qs_pg:photos_sr":1,
    "qs_pg:pop_sr":0,
    "qs_pg:qs_pg_placetype":"localadmin",
    "qs_pg:qs_pg_placetype_gp":"LocalAdmin",
    "qs_pg:woe_adm0":23424810,
    "woe:adm0_id":23424810,
    "woe:name_adm0":"\u010cesk\u00e1 republika",
    "woe:name_adm1":"Plze\u0148sk\u00fd kraj",
    "woe:placetype":"LocalAdmin",
    "wof:name":"Pl\u00e1nice",
    "wof:placetype":"localadmin"
},
  "geometry": {"coordinates":[13.474323,49.391842],"type":"Point"}
}