{
  "type": "Feature",
  "properties": {
    "gn:admin1_code":"80.0",
    "gn:admin2_code":"0612",
    "gn:asciiname":"Pankovsko",
    "gn:country_code":"CZ",
    "gn:dem":624,
    "gn:feature_class":"P",
    "gn:feature_code":"PPL",
    "gn:name":"Pankovsko",
    "gn:population":0,
    "gn:timezone":"Europe/Prague",
    "iso:country":"CZ",
    "wof:name":"Pankovsko",
    "wof:placetype":"locality"
},
  "geometry": {"coordinates":[15.42966,49.42116],"type":"Point"}
}