{
  "type": "Feature",
  "properties": {
    "gn:gn_country":"CZ",
    "gn:gn_fcode":"PPL",
    "gn:gn_pop":477,
    "gn:population":477,
    "iso:country":"CZ",
    "name:cze_x_preferred":[
        "D\u0159evnovice"
    ],
    "name:dut_x_preferred":[
        "D\u0159evnovice"
    ],
    "name:eng_x_preferred":[
        "D\u0159evnovice"
    ],
    "name:fre_x_preferred":[
        "D\u0159evnovice"
    ],
    "name:hun_x_preferred":[
        "D\u0159evnovice"
    ],
    "name:ita_x_preferred":[
        "D\u0159evnovice"
    ],
    "name:may_x_preferred":[
        "D\u0159evnovice"
    ],
    "name:per_x_preferred":[
        "\u062f\u0631\u0648\u0646\u0648\u0648\u06cc\u062a\u0633\u0647"
    ],
    "name:pol_x_preferred":[
        "D\u0159evnovice"
    ],
    "name:por_x_preferred":[
        "D\u0159evnovice"
    ],
    "name:slo_x_preferred":[
        "D\u0159evnovice"
    ],
    "name:srp_x_preferred":[
        "\u0414\u0440\u0435\u0432\u043d\u043e\u0432\u0438\u0446\u0435"
    ],
    "name:swe_x_preferred":[
        "D\u0159evnovice"
    ],
    "name:vie_x_preferred":[
        "D\u0159evnovice"
    ],
    "qs_pg:aaroncc":"CZ",
    "qs_pg:gn_country":"CZ",
    "qs_pg:gn_fcode":"PPL",
    "qs_pg:gn_pop":477,
    "qs_pg:name":"D\u0159evnovice",
    "qs_pg:name_adm0":"\u010cesk\u00e1 republika",
    "qs_pg:name_adm1":"Olomouck\u00fd kraj",
    "qs_pg:photos_9r":0,
    "qs_pg:photos_sr":0,
    "qs_pg:pop_sr":2,
    "qs_pg:qs_pg_placetype":"locality",
    "qs_pg:qs_pg_placetype_gp":"Town",
    "qs_pg:woe_adm0":23424810,
    "woe:adm0_id":23424810,
    "woe:name_adm0":"\u010cesk\u00e1 republika",
    "woe:name_adm1":"Olomouck\u00fd kraj",
    "woe:placetype":"Town",
    "wof:name":"D\u0159evnovice",
    "wof:placetype":"locality",
    "wof:population":477
},
  "geometry": {"coordinates":[17.14326,49.32809],"type":"Point"}
}