{
  "type": "Feature",
  "properties": {
    "iso:country":"CZ",
    "name:ces_x_preferred":[
        "Kozlovice"
    ],
    "name:deu_x_preferred":[
        "Kozlovice"
    ],
    "name:fra_x_preferred":[
        "Kozlovice"
    ],
    "name:ita_x_preferred":[
        "Kozlovice"
    ],
    "name:nld_x_preferred":[
        "Kozlovice"
    ],
    "name:slk_x_preferred":[
        "Kozlovice"
    ],
    "name:srp_x_preferred":[
        "\u041a\u043e\u0437\u043b\u043e\u0432\u0438\u0446\u0435"
    ],
    "qs_pg:aaroncc":"CZ",
    "qs_pg:name":"Kozlovice",
    "qs_pg:name_adm0":"\u010cesk\u00e1 republika",
    "qs_pg:name_adm1":"Moravskoslezsk\u00fd kraj",
    "qs_pg:photos":1,
    "qs_pg:photos_1k":1,
    "qs_pg:photos_9k":1,
    "qs_pg:photos_9r":2,
    "qs_pg:photos_all":67,
    "qs_pg:photos_sr":1,
    "qs_pg:pop_sr":0,
    "qs_pg:qs_pg_placetype":"localadmin",
    "qs_pg:qs_pg_placetype_gp":"LocalAdmin",
    "qs_pg:woe_adm0":23424810,
    "woe:adm0_id":23424810,
    "woe:name_adm0":"\u010cesk\u00e1 republika",
    "woe:name_adm1":"Moravskoslezsk\u00fd kraj",
    "woe:placetype":"LocalAdmin",
    "wof:name":"Kozlovice",
    "wof:placetype":"localadmin"
},
  "geometry": {"coordinates":[18.256702,49.593521],"type":"Point"}
}