{
  "type": "Feature",
  "properties": {
    "gn:admin1_code":"79.0",
    "gn:admin2_code":"0312",
    "gn:asciiname":"Bilovice",
    "gn:country_code":"CZ",
    "gn:dem":627,
    "gn:feature_class":"P",
    "gn:feature_code":"PPL",
    "gn:name":"B\u00edlovice",
    "gn:population":0,
    "gn:timezone":"Europe/Prague",
    "iso:country":"CZ",
    "name:und_x_variant":[
        "Biletitz",
        "B\u00edlovice"
    ],
    "wof:name":"Bilovice",
    "wof:placetype":"locality"
},
  "geometry": {"coordinates":[14.18333,48.83404],"type":"Point"}
}