{
  "type": "Feature",
  "properties": {
    "gn:admin1_code":"88",
    "gn:admin2_code":"0205",
    "gn:asciiname":"Vinice",
    "gn:country_code":"CZ",
    "gn:dem":236,
    "gn:feature_class":"P",
    "gn:feature_code":"PPL",
    "gn:name":"Vinice",
    "gn:population":0,
    "gn:timezone":"Europe/Prague",
    "iso:country":"CZ",
    "wof:name":"Vinice",
    "wof:placetype":"locality"
},
  "geometry": {"coordinates":[15.49068,49.92075],"type":"Point"}
}