{
  "type": "Feature",
  "properties": {
    "gn:gn_country":"CZ",
    "gn:gn_fcode":"PPL",
    "gn:gn_pop":270,
    "gn:population":270,
    "iso:country":"CZ",
    "name:azb_x_preferred":[
        "\u067e\u0648\u062f\u0645\u0648\u06a9\u0644\u06cc"
    ],
    "name:ceb_x_preferred":[
        "Podmokly"
    ],
    "name:ces_x_preferred":[
        "Podmokly"
    ],
    "name:deu_x_preferred":[
        "Podmokly nad Berounkou"
    ],
    "name:eng_x_preferred":[
        "Podmokly"
    ],
    "name:eus_x_preferred":[
        "Podmokly"
    ],
    "name:fas_x_preferred":[
        "\u067e\u0648\u062f\u0645\u0648\u06a9\u0644\u06cc"
    ],
    "name:fra_x_preferred":[
        "Podmokly"
    ],
    "name:hun_x_preferred":[
        "Podmokly"
    ],
    "name:ita_x_preferred":[
        "Podmokly"
    ],
    "name:msa_x_preferred":[
        "Podmokly"
    ],
    "name:nan_x_preferred":[
        "Podmokly"
    ],
    "name:nld_x_preferred":[
        "Podmokly"
    ],
    "name:pol_x_preferred":[
        "Podmokly"
    ],
    "name:por_x_preferred":[
        "Podmokly"
    ],
    "name:rup_x_preferred":[
        "Podmokly"
    ],
    "name:slk_x_preferred":[
        "Podmokly"
    ],
    "name:spa_x_preferred":[
        "Podmokly"
    ],
    "name:srp_x_preferred":[
        "\u041f\u043e\u0434\u043c\u043e\u043a\u043b\u0438"
    ],
    "name:swe_x_preferred":[
        "Podmokly"
    ],
    "name:vie_x_preferred":[
        "Podmokly"
    ],
    "qs_pg:aaroncc":"CZ",
    "qs_pg:gn_country":"CZ",
    "qs_pg:gn_fcode":"PPL",
    "qs_pg:gn_pop":270,
    "qs_pg:name":"Podmokly",
    "qs_pg:name_adm0":"\u010cesk\u00e1 republika",
    "qs_pg:name_adm1":"Plze\u0148sk\u00fd kraj",
    "qs_pg:photos_9r":0,
    "qs_pg:photos_sr":0,
    "qs_pg:pop_sr":2,
    "qs_pg:qs_pg_placetype":"locality",
    "qs_pg:qs_pg_placetype_gp":"Town",
    "qs_pg:woe_adm0":23424810,
    "woe:adm0_id":23424810,
    "woe:name_adm0":"\u010cesk\u00e1 republika",
    "woe:name_adm1":"Plze\u0148sk\u00fd kraj",
    "woe:placetype":"Town",
    "wof:name":"Podmokly",
    "wof:placetype":"locality",
    "wof:population":270
},
  "geometry": {"coordinates":[13.70437,49.94323],"type":"Point"}
}