{
  "type": "Feature",
  "properties": {
    "gn:gn_country":"CZ",
    "gn:gn_fcode":"PPL",
    "gn:gn_pop":150,
    "gn:population":150,
    "iso:country":"CZ",
    "name:cze_x_preferred":[
        "Chrtn\u00ed\u010d"
    ],
    "name:dut_x_preferred":[
        "Chrtn\u00ed\u010d"
    ],
    "name:eng_x_preferred":[
        "Chrtn\u00ed\u010d"
    ],
    "name:fre_x_preferred":[
        "Chrtn\u00ed\u010d"
    ],
    "name:hun_x_preferred":[
        "Chrtn\u00ed\u010d"
    ],
    "name:ita_x_preferred":[
        "Chrtn\u00ed\u010d"
    ],
    "name:may_x_preferred":[
        "Chrtn\u00ed\u010d"
    ],
    "name:per_x_preferred":[
        "\u062e\u0631\u062a\u0646\u06cc\u062a\u0634"
    ],
    "name:por_x_preferred":[
        "Chrtn\u00ed\u010d"
    ],
    "name:slo_x_preferred":[
        "Chrtn\u00ed\u010d"
    ],
    "name:srp_x_preferred":[
        "\u0425\u0440\u0442\u045a\u0438\u0447"
    ],
    "name:swe_x_preferred":[
        "Chrtn\u00ed\u010d"
    ],
    "name:vie_x_preferred":[
        "Chrtn\u00ed\u010d"
    ],
    "qs_pg:aaroncc":"CZ",
    "qs_pg:gn_country":"CZ",
    "qs_pg:gn_fcode":"PPL",
    "qs_pg:gn_pop":150,
    "qs_pg:name":"Chrtn\u00ed\u010d",
    "qs_pg:name_adm0":"\u010cesk\u00e1 republika",
    "qs_pg:name_adm1":"Kraj Vyso\u010dina",
    "qs_pg:photos_9r":0,
    "qs_pg:photos_sr":0,
    "qs_pg:pop_sr":1,
    "qs_pg:qs_pg_placetype":"locality",
    "qs_pg:qs_pg_placetype_gp":"Town",
    "qs_pg:woe_adm0":23424810,
    "woe:adm0_id":23424810,
    "woe:name_adm0":"\u010cesk\u00e1 republika",
    "woe:name_adm1":"Kraj Vyso\u010dina",
    "woe:placetype":"Town",
    "wof:name":"Chrtn\u00ed\u010d",
    "wof:placetype":"locality",
    "wof:population":150
},
  "geometry": {"coordinates":[15.44361,49.76754],"type":"Point"}
}