{
  "type": "Feature",
  "properties": {
    "gn:gn_country":"CZ",
    "gn:gn_fcode":"PPL",
    "gn:gn_pop":209,
    "gn:population":209,
    "iso:country":"CZ",
    "name:bul_x_preferred":[
        "\u041c\u0430\u0437\u0435\u043b\u043e\u0432"
    ],
    "name:cze_x_preferred":[
        "Mazelov"
    ],
    "name:dut_x_preferred":[
        "Mazelov"
    ],
    "name:eng_x_preferred":[
        "Mazelov"
    ],
    "name:fre_x_preferred":[
        "Mazelov"
    ],
    "name:ger_x_preferred":[
        "Mazelov"
    ],
    "name:hun_x_preferred":[
        "Mazelov"
    ],
    "name:ita_x_preferred":[
        "Mazelov"
    ],
    "name:may_x_preferred":[
        "Mazelov"
    ],
    "name:per_x_preferred":[
        "\u0645\u0627\u0632\u0644\u0648\u0648"
    ],
    "name:pol_x_preferred":[
        "Mazelov"
    ],
    "name:por_x_preferred":[
        "Mazelov"
    ],
    "name:slo_x_preferred":[
        "Mazelov"
    ],
    "name:srp_x_preferred":[
        "\u041c\u0430\u0437\u0435\u043b\u043e\u0432"
    ],
    "name:swe_x_preferred":[
        "Mazelov"
    ],
    "name:vie_x_preferred":[
        "Mazelov"
    ],
    "qs_pg:aaroncc":"CZ",
    "qs_pg:gn_country":"CZ",
    "qs_pg:gn_fcode":"PPL",
    "qs_pg:gn_pop":209,
    "qs_pg:name":"Mazelov",
    "qs_pg:name_adm0":"\u010cesk\u00e1 republika",
    "qs_pg:name_adm1":"Jiho\u010desk\u00fd kraj",
    "qs_pg:photos_9r":0,
    "qs_pg:photos_sr":0,
    "qs_pg:pop_sr":2,
    "qs_pg:qs_pg_placetype":"locality",
    "qs_pg:qs_pg_placetype_gp":"Town",
    "qs_pg:woe_adm0":23424810,
    "woe:adm0_id":23424810,
    "woe:name_adm0":"\u010cesk\u00e1 republika",
    "woe:name_adm1":"Jiho\u010desk\u00fd kraj",
    "woe:placetype":"Town",
    "wof:name":"Mazelov",
    "wof:placetype":"locality",
    "wof:population":209
},
  "geometry": {"coordinates":[14.61778,49.10295],"type":"Point"}
}