{
  "type": "Feature",
  "properties": {
    "gn:admin1_code":"89.0",
    "gn:admin2_code":"0426",
    "gn:asciiname":"Razice",
    "gn:cc2":"CZ",
    "gn:country_code":"CZ",
    "gn:dem":329,
    "gn:feature_class":"P",
    "gn:feature_code":"PPL",
    "gn:name":"Razice",
    "gn:population":0,
    "gn:timezone":"Europe/Prague",
    "iso:country":"CZ",
    "name:und_x_variant":[
        "Rasitz"
    ],
    "wof:name":"Razice",
    "wof:placetype":"locality"
},
  "geometry": {"coordinates":[13.80947,50.52172],"type":"Point"}
}