{
  "type": "Feature",
  "properties": {
    "gn:gn_country":"CZ",
    "gn:gn_fcode":"PPL",
    "gn:gn_pop":232,
    "gn:population":232,
    "iso:country":"CZ",
    "name:cze_x_preferred":[
        "Nov\u00e1 Ves u Bakova"
    ],
    "name:dut_x_preferred":[
        "Nov\u00e1 Ves u Bakova"
    ],
    "name:eng_x_preferred":[
        "Nov\u00e1 Ves u Bakova"
    ],
    "name:fre_x_preferred":[
        "Nov\u00e1 Ves u Bakova"
    ],
    "name:ger_x_preferred":[
        "Nov\u00e1 Ves u Bakova"
    ],
    "name:hun_x_preferred":[
        "Nov\u00e1 Ves u Bakova"
    ],
    "name:ita_x_preferred":[
        "Nov\u00e1 Ves u Bakova"
    ],
    "name:may_x_preferred":[
        "Nov\u00e1 Ves u Bakova"
    ],
    "name:nan_x_preferred":[
        "Nov\u00e1 Ves u Bakova"
    ],
    "name:per_x_preferred":[
        "\u0646\u0648\u0648\u0627 \u0648\u0633 \u0648 \u0628\u0627\u06a9\u0648\u0648\u0627"
    ],
    "name:pol_x_preferred":[
        "Nov\u00e1 Ves u Bakova"
    ],
    "name:por_x_preferred":[
        "Nov\u00e1 Ves u Bakova"
    ],
    "name:rup_x_preferred":[
        "Nov\u00e1 Ves u Bakova"
    ],
    "name:rus_x_preferred":[
        "\u041d\u043e\u0432\u0430-\u0412\u0435\u0441-\u0443-\u0411\u0430\u043a\u043e\u0432\u0430"
    ],
    "name:slo_x_preferred":[
        "Nov\u00e1 Ves u Bakova"
    ],
    "name:srp_x_preferred":[
        "\u041d\u043e\u0432\u0430 \u0412\u0435\u0441 \u0443 \u0411\u0430\u043a\u043e\u0432\u0443"
    ],
    "name:swe_x_preferred":[
        "Nov\u00e1 Ves u Bakova"
    ],
    "name:vie_x_preferred":[
        "Nov\u00e1 Ves u Bakova"
    ],
    "qs_pg:aaroncc":"CZ",
    "qs_pg:gn_country":"CZ",
    "qs_pg:gn_fcode":"PPL",
    "qs_pg:gn_pop":232,
    "qs_pg:name":"Nov\u00e1 Ves u Bakova",
    "qs_pg:name_adm0":"\u010cesk\u00e1 republika",
    "qs_pg:name_adm1":"St\u0159edo\u010desk\u00fd kraj",
    "qs_pg:photos_9r":0,
    "qs_pg:photos_sr":0,
    "qs_pg:pop_sr":2,
    "qs_pg:qs_pg_placetype":"locality",
    "qs_pg:qs_pg_placetype_gp":"Town",
    "qs_pg:woe_adm0":23424810,
    "woe:adm0_id":23424810,
    "woe:name_adm0":"\u010cesk\u00e1 republika",
    "woe:name_adm1":"St\u0159edo\u010desk\u00fd kraj",
    "woe:placetype":"Town",
    "wof:name":"Nov\u00e1 Ves u Bakova",
    "wof:placetype":"locality",
    "wof:population":232
},
  "geometry": {"coordinates":[14.92639,50.49067],"type":"Point"}
}