{
  "type": "Feature",
  "properties": {
    "gn:admin1_code":"81.0",
    "gn:admin2_code":"0411",
    "gn:asciiname":"Devin",
    "gn:country_code":"CZ",
    "gn:dem":459,
    "gn:feature_class":"P",
    "gn:feature_code":"PPL",
    "gn:name":"D\u011bv\u00edn",
    "gn:population":0,
    "gn:timezone":"Europe/Prague",
    "iso:country":"CZ",
    "name:und_x_variant":[
        "D\u00f6ba",
        "D\u011bv\u00edn"
    ],
    "wof:name":"Devin",
    "wof:placetype":"locality"
},
  "geometry": {"coordinates":[12.43123,50.16577],"type":"Point"}
}