{
  "type": "Feature",
  "properties": {
    "gn:gn_country":"CZ",
    "gn:gn_fcode":"PPL",
    "gn:gn_pop":719,
    "gn:population":719,
    "iso:country":"CZ",
    "name:azb_x_preferred":[
        "\u0631\u0648\u0648\u0646\u0633\u06a9\u0648"
    ],
    "name:ceb_x_preferred":[
        "Rovensko"
    ],
    "name:ces_x_preferred":[
        "Rovensko"
    ],
    "name:deu_x_preferred":[
        "Rovensko u Z\u00e1b\u0159eha"
    ],
    "name:eng_x_preferred":[
        "Rovensko"
    ],
    "name:eus_x_preferred":[
        "Rovensko"
    ],
    "name:fas_x_preferred":[
        "\u0631\u0648\u0648\u0646\u0633\u06a9\u0648"
    ],
    "name:fra_x_preferred":[
        "Rovensko"
    ],
    "name:hun_x_preferred":[
        "Rovensko"
    ],
    "name:ita_x_preferred":[
        "Rovensko"
    ],
    "name:msa_x_preferred":[
        "Rovensko"
    ],
    "name:nan_x_preferred":[
        "Rovensko"
    ],
    "name:nld_x_preferred":[
        "Rovensko"
    ],
    "name:pol_x_preferred":[
        "Rovensko"
    ],
    "name:por_x_preferred":[
        "Rovensko"
    ],
    "name:rup_x_preferred":[
        "Rovensko"
    ],
    "name:slk_x_preferred":[
        "Rovensko"
    ],
    "name:spa_x_preferred":[
        "Rovensko"
    ],
    "name:srp_x_preferred":[
        "\u0420\u043e\u0432\u0435\u043d\u0441\u043a\u043e"
    ],
    "name:swe_x_preferred":[
        "Rovensko"
    ],
    "name:vie_x_preferred":[
        "Rovensko"
    ],
    "qs_pg:aaroncc":"CZ",
    "qs_pg:gn_country":"CZ",
    "qs_pg:gn_fcode":"PPL",
    "qs_pg:gn_pop":719,
    "qs_pg:name":"Rove\u0148sko",
    "qs_pg:name_adm0":"\u010cesk\u00e1 republika",
    "qs_pg:name_adm1":"Pardubick\u00fd kraj",
    "qs_pg:photos_9r":0,
    "qs_pg:photos_sr":0,
    "qs_pg:pop_sr":2,
    "qs_pg:qs_pg_placetype":"locality",
    "qs_pg:qs_pg_placetype_gp":"Town",
    "qs_pg:woe_adm0":23424810,
    "woe:adm0_id":23424810,
    "woe:name_adm0":"\u010cesk\u00e1 republika",
    "woe:name_adm1":"Pardubick\u00fd kraj",
    "woe:placetype":"Town",
    "wof:name":"Rove\u0148sko",
    "wof:placetype":"locality",
    "wof:population":719
},
  "geometry": {"coordinates":[16.87624,49.90769],"type":"Point"}
}