{
  "type": "Feature",
  "properties": {
    "gn:country":"CZ",
    "gn:fcode":"PPL",
    "gn:population":69,
    "iso:country":"CZ",
    "name:azb_x_preferred":[
        "\u0633\u0648\u0648\u06cc\u06a9\u0648\u0648\u06cc\u062a\u0633\u0647"
    ],
    "name:cat_x_preferred":[
        "Svojkovice"
    ],
    "name:ces_x_preferred":[
        "Svojkovice"
    ],
    "name:che_x_preferred":[
        "\u0421\u0432\u043e\u0439\u043a\u043e\u0432\u0438\u0446\u0435"
    ],
    "name:deu_x_preferred":[
        "Svojkovice"
    ],
    "name:eng_x_preferred":[
        "Svojkovice"
    ],
    "name:epo_x_preferred":[
        "Svojkovice"
    ],
    "name:eus_x_preferred":[
        "Svojkovice"
    ],
    "name:fas_x_preferred":[
        "\u0633\u0648\u0648\u06cc\u06a9\u0648\u0648\u06cc\u062a\u0633\u0647"
    ],
    "name:fra_x_preferred":[
        "Svojkovice"
    ],
    "name:gle_x_preferred":[
        "Svojkovice"
    ],
    "name:hun_x_preferred":[
        "Svojkovice"
    ],
    "name:ita_x_preferred":[
        "Svojkovice"
    ],
    "name:lmo_x_preferred":[
        "Svojkovice"
    ],
    "name:msa_x_preferred":[
        "Svojkovice"
    ],
    "name:nan_x_preferred":[
        "Svojkovice"
    ],
    "name:nld_x_preferred":[
        "Svojkovice"
    ],
    "name:pol_x_preferred":[
        "Svojkovice"
    ],
    "name:por_x_preferred":[
        "Svojkovice"
    ],
    "name:rup_x_preferred":[
        "Svojkovice"
    ],
    "name:slk_x_preferred":[
        "Svojkovice"
    ],
    "name:spa_x_preferred":[
        "Svojkovice"
    ],
    "name:srp_x_preferred":[
        "\u0421\u0432\u043e\u0458\u043a\u043e\u0432\u0438\u0446\u0435"
    ],
    "name:tat_x_preferred":[
        "\u0421\u0432\u043e\u0439\u043a\u043e\u0432\u0438\u0446\u0435"
    ],
    "name:vie_x_preferred":[
        "Svojkovice"
    ],
    "qs_pg:aaroncc":"CZ",
    "qs_pg:gn_country":"CZ",
    "qs_pg:gn_fcode":"PPL",
    "qs_pg:gn_pop":69,
    "qs_pg:name":"Svojkovice",
    "qs_pg:name_adm0":"\u010cesk\u00e1 republika",
    "qs_pg:name_adm1":"Kraj Vyso\u010dina",
    "qs_pg:photos_9r":0,
    "qs_pg:photos_sr":0,
    "qs_pg:pop_sr":1,
    "qs_pg:qs_pg_placetype":"locality",
    "qs_pg:qs_pg_placetype_gp":"Town",
    "qs_pg:woe_adm0":23424810,
    "woe:adm0_id":23424810,
    "woe:name_adm0":"\u010cesk\u00e1 republika",
    "woe:name_adm1":"Kraj Vyso\u010dina",
    "woe:placetype":"Town",
    "wof:name":"Svojkovice",
    "wof:placetype":"locality",
    "wof:population":69
},
  "geometry": {"coordinates":[15.63551,49.16614],"type":"Point"}
}