{
  "type": "Feature",
  "properties": {
    "gn:gn_country":"CZ",
    "gn:gn_fcode":"PPL",
    "gn:gn_pop":403,
    "gn:population":403,
    "iso:country":"CZ",
    "name:azb_x_preferred":[
        "\u0631\u06cc\u0628\u0646\u06cc\u06a9\u06cc"
    ],
    "name:ceb_x_preferred":[
        "Rybn\u00edky"
    ],
    "name:ces_x_preferred":[
        "Rybn\u00edky"
    ],
    "name:deu_x_preferred":[
        "Rybn\u00edky"
    ],
    "name:eng_x_preferred":[
        "Rybn\u00edky"
    ],
    "name:eus_x_preferred":[
        "Rybn\u00edky"
    ],
    "name:fas_x_preferred":[
        "\u0631\u06cc\u0628\u0646\u06cc\u06a9\u06cc"
    ],
    "name:fra_x_preferred":[
        "Rybn\u00edky"
    ],
    "name:hun_x_preferred":[
        "Rybn\u00edky"
    ],
    "name:ita_x_preferred":[
        "Rybn\u00edky"
    ],
    "name:msa_x_preferred":[
        "Rybn\u00edky"
    ],
    "name:nan_x_preferred":[
        "Rybn\u00edky"
    ],
    "name:nld_x_preferred":[
        "Rybn\u00edky"
    ],
    "name:pol_x_preferred":[
        "Rybn\u00edky"
    ],
    "name:por_x_preferred":[
        "Rybn\u00edky"
    ],
    "name:rup_x_preferred":[
        "Rybn\u00edky"
    ],
    "name:slk_x_preferred":[
        "Rybn\u00edky"
    ],
    "name:spa_x_preferred":[
        "Rybn\u00edky"
    ],
    "name:srp_x_preferred":[
        "\u0420\u0438\u0431\u045a\u0438\u043a\u0438"
    ],
    "name:swe_x_preferred":[
        "Rybn\u00edky"
    ],
    "name:vie_x_preferred":[
        "Rybn\u00edky"
    ],
    "qs_pg:aaroncc":"CZ",
    "qs_pg:gn_country":"CZ",
    "qs_pg:gn_fcode":"PPL",
    "qs_pg:gn_pop":403,
    "qs_pg:name":"Rybn\u00edky",
    "qs_pg:name_adm0":"\u010cesk\u00e1 republika",
    "qs_pg:name_adm1":"Jihomoravsk\u00fd kraj",
    "qs_pg:photos_9r":0,
    "qs_pg:photos_sr":0,
    "qs_pg:pop_sr":2,
    "qs_pg:qs_pg_placetype":"locality",
    "qs_pg:qs_pg_placetype_gp":"Town",
    "qs_pg:woe_adm0":23424810,
    "woe:adm0_id":23424810,
    "woe:name_adm0":"\u010cesk\u00e1 republika",
    "woe:name_adm1":"Jihomoravsk\u00fd kraj",
    "woe:placetype":"Town",
    "wof:name":"Rybn\u00edky",
    "wof:placetype":"locality",
    "wof:population":403
},
  "geometry": {"coordinates":[16.27937,49.02626],"type":"Point"}
}