{
  "type": "Feature",
  "properties": {
    "gn:admin1_code":"79",
    "gn:admin2_code":"0314",
    "gn:asciiname":"Uverka",
    "gn:country_code":"CZ",
    "gn:dem":412,
    "gn:feature_class":"P",
    "gn:feature_code":"PPL",
    "gn:name":"\u00dav\u011brka",
    "gn:population":0,
    "gn:timezone":"Europe/Prague",
    "iso:country":"CZ",
    "wof:name":"Uverka",
    "wof:placetype":"locality"
},
  "geometry": {"coordinates":[14.12066,49.4098],"type":"Point"}
}