{
  "type": "Feature",
  "properties": {
    "iso:country":"CZ",
    "name:ces_x_preferred":[
        "\u010cAFC \u017didenice Brno"
    ],
    "name:cze_x_colloquial":[
        "Julianov"
    ],
    "name:cze_x_preferred":[
        "Juli\u00e1nov"
    ],
    "name:unk_x_variant":[
        "Juli\u00e1nov"
    ],
    "qs:gn_adm0_cc":"CZ",
    "qs:gn_local":3078610,
    "qs:local_max":6134,
    "qs:local_sum":32721,
    "qs:localhoods":44,
    "qs:name":"Juli\u00e1nov",
    "qs:name_adm0":"\u010cesk\u00e1 republika",
    "qs:name_adm1":"Jihomoravsk\u00fd kraj",
    "qs:name_adm2":"Brno-M\u011bsto",
    "qs:name_lau":"Brno",
    "qs:name_local":"Brno",
    "qs:photo_max":30,
    "qs:photo_sum":146,
    "qs:placetype":"Suburb",
    "qs:quad_count":12,
    "qs:woe_adm0":23424810,
    "qs:woe_adm1":20070503,
    "qs:woe_adm2":12582547,
    "qs:woe_lau":12605174,
    "qs:woe_local":786869,
    "qs:woe_ver":"7.10.0",
    "wof:lang":[
        "cze"
    ],
    "wof:name":"Juli\u00e1nov",
    "wof:placetype":"neighbourhood"
},
  "geometry": {"coordinates":[16.650453,49.193104],"type":"Point"}
}