{
  "type": "Feature",
  "properties": {
    "iso:country":"CZ",
    "name:ceb_x_preferred":[
        "Chl\u00edstov"
    ],
    "name:ces_x_preferred":[
        "Chl\u00edstov"
    ],
    "name:deu_x_preferred":[
        "Chl\u00edstov"
    ],
    "name:fra_x_preferred":[
        "Chl\u00edstov"
    ],
    "name:ita_x_preferred":[
        "Chl\u00edstov"
    ],
    "name:nld_x_preferred":[
        "Chl\u00edstov"
    ],
    "name:oci_x_preferred":[
        "Chl\u00edstov"
    ],
    "name:pol_x_preferred":[
        "Chl\u00edstov"
    ],
    "name:slk_x_preferred":[
        "Chl\u00edstov"
    ],
    "name:srp_x_preferred":[
        "\u0425\u043b\u0438\u0441\u0442\u043e\u0432"
    ],
    "name:swe_x_preferred":[
        "Chl\u00edstov"
    ],
    "qs_pg:aaroncc":"CZ",
    "qs_pg:name":"Chl\u00edstov",
    "qs_pg:name_adm0":"\u010cesk\u00e1 republika",
    "qs_pg:name_adm1":"St\u0159edo\u010desk\u00fd kraj",
    "qs_pg:photos":2,
    "qs_pg:photos_1k":1,
    "qs_pg:photos_9k":1,
    "qs_pg:photos_9r":1,
    "qs_pg:photos_all":2,
    "qs_pg:photos_sr":1,
    "qs_pg:pop_sr":0,
    "qs_pg:qs_pg_placetype":"localadmin",
    "qs_pg:qs_pg_placetype_gp":"LocalAdmin",
    "qs_pg:woe_adm0":23424810,
    "woe:adm0_id":23424810,
    "woe:name_adm0":"\u010cesk\u00e1 republika",
    "woe:name_adm1":"St\u0159edo\u010desk\u00fd kraj",
    "woe:placetype":"LocalAdmin",
    "wof:name":"Chl\u00edstov",
    "wof:placetype":"localadmin"
},
  "geometry": {"coordinates":[14.655075,49.781374],"type":"Point"}
}