{
  "type": "Feature",
  "properties": {
    "gn:admin1_code":"78.0",
    "gn:admin2_code":"0621",
    "gn:asciiname":"Horky",
    "gn:country_code":"CZ",
    "gn:dem":507,
    "gn:feature_class":"P",
    "gn:feature_code":"PPL",
    "gn:name":"Horky",
    "gn:population":0,
    "gn:timezone":"Europe/Prague",
    "iso:country":"CZ",
    "wof:name":"Horky",
    "wof:placetype":"locality"
},
  "geometry": {"coordinates":[16.61667000000001,49.58333],"type":"Point"}
}