{
  "type": "Feature",
  "properties": {
    "gn:admin1_code":"78.0",
    "gn:admin2_code":"0621",
    "gn:asciiname":"Horky",
    "gn:country_code":"CZ",
    "gn:dem":507,
    "gn:feature_class":"P",
    "gn:feature_code":"PPL",
    "gn:name":"Horky",
    "gn:population":0,
    "gn:timezone":"Europe/Prague",
    "iso:country":"CZ",
    "name:ceb_x_preferred":[
        "Horky"
    ],
    "name:ces_x_preferred":[
        "Horky"
    ],
    "name:deu_x_preferred":[
        "Horky"
    ],
    "name:epo_x_preferred":[
        "Horky"
    ],
    "name:fra_x_preferred":[
        "Horky"
    ],
    "name:ita_x_preferred":[
        "Horky"
    ],
    "name:nld_x_preferred":[
        "Horky"
    ],
    "name:pol_x_preferred":[
        "Horky"
    ],
    "name:slk_x_preferred":[
        "Horky"
    ],
    "name:srp_x_preferred":[
        "\u0425\u043e\u0440\u043a\u0438"
    ],
    "name:swe_x_preferred":[
        "Horky"
    ],
    "wof:name":"Horky",
    "wof:placetype":"locality"
},
  "geometry": {"coordinates":[16.61667000000001,49.58333],"type":"Point"}
}