{
  "type": "Feature",
  "properties": {
    "gn:admin1_code":"85.0",
    "gn:admin2_code":"0801",
    "gn:asciiname":"Pochen",
    "gn:country_code":"CZ",
    "gn:dem":322,
    "gn:feature_class":"P",
    "gn:feature_code":"PPL",
    "gn:name":"Poche\u0148",
    "gn:population":0,
    "gn:timezone":"Europe/Prague",
    "iso:country":"CZ",
    "name:und_x_variant":[
        "Pochm\u00fchl",
        "Poche\u0148"
    ],
    "wof:name":"Pochen",
    "wof:placetype":"locality"
},
  "geometry": {"coordinates":[17.71258,50.03219],"type":"Point"}
}