{
  "type": "Feature",
  "properties": {
    "gn:admin1_code":"81.0",
    "gn:admin2_code":"0411",
    "gn:asciiname":"Horni Lipina",
    "gn:country_code":"CZ",
    "gn:dem":477,
    "gn:feature_class":"P",
    "gn:feature_code":"PPL",
    "gn:name":"Horn\u00ed Lipina",
    "gn:population":0,
    "gn:timezone":"Europe/Prague",
    "iso:country":"CZ",
    "name:und_x_variant":[
        "Ober Lindau",
        "Horn\u00ed Lindov",
        "Horn\u00ed Lipina"
    ],
    "wof:name":"Horni Lipina",
    "wof:placetype":"locality"
},
  "geometry": {"coordinates":[12.43213,50.02635],"type":"Point"}
}