{
  "type": "Feature",
  "properties": {
    "gn:admin1_code":"80.0",
    "gn:admin2_code":"0613",
    "gn:asciiname":"Ovcin",
    "gn:country_code":"CZ",
    "gn:dem":505,
    "gn:feature_class":"P",
    "gn:feature_code":"PPL",
    "gn:name":"Ov\u010d\u00edn",
    "gn:population":0,
    "gn:timezone":"Europe/Prague",
    "iso:country":"CZ",
    "wof:name":"Ovcin",
    "wof:placetype":"locality"
},
  "geometry": {"coordinates":[15.26177,49.5515],"type":"Point"}
}