{
  "type": "Feature",
  "properties": {
    "gn:admin1_code":"83.0",
    "gn:admin2_code":"0512",
    "gn:asciiname":"Krasna",
    "gn:country_code":"CZ",
    "gn:dem":656,
    "gn:feature_class":"P",
    "gn:feature_code":"PPL",
    "gn:name":"Kr\u00e1sn\u00e1",
    "gn:population":0,
    "gn:timezone":"Europe/Prague",
    "iso:country":"CZ",
    "name:ceb_x_preferred":[
        "Krasna"
    ],
    "name:ces_x_preferred":[
        "Kr\u00e1sn\u00e1"
    ],
    "name:deu_x_preferred":[
        "Krasna"
    ],
    "name:fra_x_preferred":[
        "Krasna"
    ],
    "name:hun_x_preferred":[
        "Kr\u00e1sn\u00e1"
    ],
    "name:ita_x_preferred":[
        "Kr\u00e1sn\u00e1"
    ],
    "name:nld_x_preferred":[
        "Kr\u00e1sn\u00e1"
    ],
    "name:pol_x_preferred":[
        "Krasna"
    ],
    "name:ron_x_preferred":[
        "Krasna"
    ],
    "name:slk_x_preferred":[
        "Kr\u00e1sn\u00e1"
    ],
    "name:srp_x_preferred":[
        "\u041a\u0440\u0430\u0441\u043d\u0430"
    ],
    "name:swe_x_preferred":[
        "Krasna"
    ],
    "name:ukr_x_preferred":[
        "\u041a\u0440\u0430\u0441\u043d\u0430"
    ],
    "name:und_x_variant":[
        "\u0160umburk",
        "Kr\u00e1sn\u00e1"
    ],
    "wof:name":"Krasna",
    "wof:placetype":"locality"
},
  "geometry": {"coordinates":[15.21593,50.69503],"type":"Point"}
}