{
  "type": "Feature",
  "properties": {
    "gn:admin1_code":"86.0",
    "gn:admin2_code":"0531",
    "gn:asciiname":"Brcekoly",
    "gn:country_code":"CZ",
    "gn:dem":265,
    "gn:feature_class":"P",
    "gn:feature_code":"PPL",
    "gn:name":"Br\u010dekoly",
    "gn:population":0,
    "gn:timezone":"Europe/Prague",
    "iso:country":"CZ",
    "wof:name":"Brcekoly",
    "wof:placetype":"locality"
},
  "geometry": {"coordinates":[15.96599,49.93524],"type":"Point"}
}