{
  "type": "Feature",
  "properties": {
    "gn:gn_country":"CZ",
    "gn:gn_fcode":"PPL",
    "gn:gn_pop":399,
    "gn:population":399,
    "iso:country":"CZ",
    "name:azb_x_preferred":[
        "\u06a9\u0631\u06cc\u0648\u0633\u0648\u0648\u062f\u0648\u0648"
    ],
    "name:ceb_x_preferred":[
        "K\u0159ivsoudov"
    ],
    "name:ces_x_preferred":[
        "K\u0159ivsoudov"
    ],
    "name:deu_x_preferred":[
        "K\u0159ivsoudov"
    ],
    "name:eng_x_preferred":[
        "K\u0159ivsoudov"
    ],
    "name:eus_x_preferred":[
        "K\u0159ivsoudov"
    ],
    "name:fas_x_preferred":[
        "\u06a9\u0631\u06cc\u0648\u0633\u0648\u0648\u062f\u0648\u0648"
    ],
    "name:fra_x_preferred":[
        "K\u0159ivsoudov"
    ],
    "name:hun_x_preferred":[
        "K\u0159ivsoudov"
    ],
    "name:ita_x_preferred":[
        "K\u0159ivsoudov"
    ],
    "name:msa_x_preferred":[
        "K\u0159ivsoudov"
    ],
    "name:nan_x_preferred":[
        "K\u0159ivsoudov"
    ],
    "name:nld_x_preferred":[
        "K\u0159ivsoudov"
    ],
    "name:oci_x_preferred":[
        "K\u0159ivsoudov"
    ],
    "name:pol_x_preferred":[
        "K\u0159ivsoudov"
    ],
    "name:por_x_preferred":[
        "K\u0159ivsoudov"
    ],
    "name:slk_x_preferred":[
        "K\u0159ivsoudov"
    ],
    "name:spa_x_preferred":[
        "K\u0159ivsoudov"
    ],
    "name:srp_x_preferred":[
        "\u041a\u0440\u0438\u0432\u0441\u043e\u0443\u0434\u043e\u0432"
    ],
    "name:swe_x_preferred":[
        "K\u0159ivsoudov"
    ],
    "name:unk_x_variant":[
        "K\u0159iwsoudow"
    ],
    "name:vie_x_preferred":[
        "K\u0159ivsoudov"
    ],
    "qs_pg:aaroncc":"CZ",
    "qs_pg:gn_country":"CZ",
    "qs_pg:gn_fcode":"PPL",
    "qs_pg:gn_pop":399,
    "qs_pg:name":"K\u0159ivsoudov",
    "qs_pg:name_adm0":"\u010cesk\u00e1 republika",
    "qs_pg:name_adm1":"St\u0159edo\u010desk\u00fd kraj",
    "qs_pg:photos_9r":0,
    "qs_pg:photos_sr":0,
    "qs_pg:pop_sr":2,
    "qs_pg:qs_pg_placetype":"locality",
    "qs_pg:qs_pg_placetype_gp":"Town",
    "qs_pg:woe_adm0":23424810,
    "woe:adm0_id":23424810,
    "woe:name_adm0":"\u010cesk\u00e1 republika",
    "woe:name_adm1":"St\u0159edo\u010desk\u00fd kraj",
    "woe:placetype":"Town",
    "wof:name":"K\u0159ivsoudov",
    "wof:placetype":"locality",
    "wof:population":399
},
  "geometry": {"coordinates":[15.08736,49.63297],"type":"Point"}
}