{
  "type": "Feature",
  "properties": {
    "gn:admin1_code":"87.0",
    "gn:admin2_code":"0327",
    "gn:asciiname":"Dolni Viska",
    "gn:country_code":"CZ",
    "gn:dem":570,
    "gn:feature_class":"P",
    "gn:feature_code":"PPL",
    "gn:name":"Doln\u00ed V\u00edska",
    "gn:population":0,
    "gn:timezone":"Europe/Prague",
    "iso:country":"CZ",
    "name:und_x_variant":[
        "Unter D\u00f6rfles",
        "Doln\u00ed V\u00edska"
    ],
    "wof:name":"Dolni Viska",
    "wof:placetype":"locality"
},
  "geometry": {"coordinates":[12.86728,49.85632],"type":"Point"}
}