{
  "type": "Feature",
  "properties": {
    "gn:admin1_code":"82.0",
    "gn:admin2_code":"0521",
    "gn:asciiname":"Komarov",
    "gn:country_code":"CZ",
    "gn:dem":241,
    "gn:feature_class":"P",
    "gn:feature_code":"PPL",
    "gn:name":"Kom\u00e1rov",
    "gn:population":0,
    "gn:timezone":"Europe/Prague",
    "iso:country":"CZ",
    "wof:name":"Komarov",
    "wof:placetype":"locality"
},
  "geometry": {"coordinates":[15.64307,50.24416],"type":"Point"}
}