{
  "type": "Feature",
  "properties": {
    "gn:admin1_code":"82.0",
    "gn:admin2_code":"0521",
    "gn:asciiname":"Komarov",
    "gn:country_code":"CZ",
    "gn:dem":241,
    "gn:feature_class":"P",
    "gn:feature_code":"PPL",
    "gn:name":"Kom\u00e1rov",
    "gn:population":0,
    "gn:timezone":"Europe/Prague",
    "iso:country":"CZ",
    "name:bel_x_preferred":[
        "\u041a\u0430\u043c\u0430\u0440\u043e\u045e"
    ],
    "name:deu_x_preferred":[
        "Komarow"
    ],
    "name:fin_x_preferred":[
        "Komarov"
    ],
    "name:fra_x_preferred":[
        "Komarov"
    ],
    "name:heb_x_preferred":[
        "\u05e7\u05d5\u05de\u05e8\u05d5\u05d1"
    ],
    "name:hun_x_preferred":[
        "Komarov"
    ],
    "name:hye_x_preferred":[
        "\u053f\u0578\u0574\u0561\u0580\u0578\u057e"
    ],
    "name:ita_x_preferred":[
        "Komarov"
    ],
    "name:jpn_x_preferred":[
        "\u30b3\u30de\u30ed\u30d5"
    ],
    "name:kat_x_preferred":[
        "\u10d9\u10dd\u10db\u10d0\u10e0\u10dd\u10d5\u10d8"
    ],
    "name:lav_x_preferred":[
        "Komarovs"
    ],
    "name:nld_x_preferred":[
        "Komarov"
    ],
    "name:pol_x_preferred":[
        "Komarow"
    ],
    "name:rus_x_preferred":[
        "\u041a\u043e\u043c\u0430\u0440\u043e\u0432"
    ],
    "name:spa_x_preferred":[
        "Komarov"
    ],
    "name:srp_x_preferred":[
        "\u041a\u043e\u043c\u0430\u0440\u043e\u0432"
    ],
    "name:tat_x_preferred":[
        "\u041a\u043e\u043c\u0430\u0440\u043e\u0432"
    ],
    "name:ukr_x_preferred":[
        "\u041a\u043e\u043c\u0430\u0440\u043e\u0432"
    ],
    "wof:name":"Komarov",
    "wof:placetype":"locality"
},
  "geometry": {"coordinates":[15.64307,50.24416],"type":"Point"}
}