{
  "type": "Feature",
  "properties": {
    "gn:admin1_code":"85",
    "gn:admin2_code":"0801",
    "gn:asciiname":"Ztracena Voda",
    "gn:country_code":"CZ",
    "gn:dem":693,
    "gn:feature_class":"P",
    "gn:feature_code":"PPL",
    "gn:name":"Ztracen\u00e1 Voda",
    "gn:population":0,
    "gn:timezone":"Europe/Prague",
    "iso:country":"CZ",
    "name:und_x_variant":[
        "Verlorenwasser",
        "Ztracen\u00e1 Voda"
    ],
    "wof:name":"Ztracena Voda",
    "wof:placetype":"locality"
},
  "geometry": {"coordinates":[17.48897,50.20321],"type":"Point"}
}