{
  "type": "Feature",
  "properties": {
    "gn:admin1_code":"85.0",
    "gn:admin2_code":"0801",
    "gn:asciiname":"Mala Veska",
    "gn:country_code":"CZ",
    "gn:dem":565,
    "gn:feature_class":"P",
    "gn:feature_code":"PPL",
    "gn:name":"Mal\u00e1 V\u00e9ska",
    "gn:population":0,
    "gn:timezone":"Europe/Prague",
    "iso:country":"CZ",
    "name:und_x_variant":[
        "Neud\u00f6rfel",
        "Nov\u00e1 V\u00e9ska"
    ],
    "wof:name":"Mala Veska",
    "wof:placetype":"locality"
},
  "geometry": {"coordinates":[17.41041,50.01359],"type":"Point"}
}