{
  "type": "Feature",
  "properties": {
    "gn:admin1_code":"80.0",
    "gn:admin2_code":"0611",
    "gn:asciiname":"Dolni Paseka",
    "gn:country_code":"CZ",
    "gn:dem":466,
    "gn:feature_class":"P",
    "gn:feature_code":"PPL",
    "gn:name":"Doln\u00ed Paseka",
    "gn:population":0,
    "gn:timezone":"Europe/Prague",
    "iso:country":"CZ",
    "wof:name":"Dolni Paseka",
    "wof:placetype":"locality"
},
  "geometry": {"coordinates":[15.26354,49.63728],"type":"Point"}
}