{
  "type": "Feature",
  "properties": {
    "gn:admin1_code":"79.0",
    "gn:admin2_code":"0312",
    "gn:asciiname":"Haslovice",
    "gn:country_code":"CZ",
    "gn:dem":601,
    "gn:feature_class":"P",
    "gn:feature_code":"PPL",
    "gn:name":"Ha\u0161lovice",
    "gn:population":0,
    "gn:timezone":"Europe/Prague",
    "iso:country":"CZ",
    "wof:name":"Haslovice",
    "wof:placetype":"locality"
},
  "geometry": {"coordinates":[14.31244,48.7434],"type":"Point"}
}