{
  "type": "Feature",
  "properties": {
    "gn:admin1_code":"86",
    "gn:admin2_code":"0532",
    "gn:asciiname":"Vysoka u Holic",
    "gn:country_code":"CZ",
    "gn:dem":275,
    "gn:feature_class":"P",
    "gn:feature_code":"PPL",
    "gn:name":"Vysok\u00e1 u Holic",
    "gn:population":0,
    "gn:timezone":"Europe/Prague",
    "iso:country":"CZ",
    "wof:name":"Vysoka u Holic",
    "wof:placetype":"locality"
},
  "geometry": {"coordinates":[16.05617,50.0269],"type":"Point"}
}