{
  "type": "Feature",
  "properties": {
    "gn:admin1_code":"84",
    "gn:admin2_code":"0712",
    "gn:asciiname":"Vacanovice",
    "gn:country_code":"CZ",
    "gn:dem":278,
    "gn:feature_class":"P",
    "gn:feature_code":"PPL",
    "gn:name":"Vacanovice",
    "gn:population":0,
    "gn:timezone":"Europe/Prague",
    "iso:country":"CZ",
    "wof:name":"Vacanovice",
    "wof:placetype":"locality"
},
  "geometry": {"coordinates":[17.39058,49.54493],"type":"Point"}
}