{
  "type": "Feature",
  "properties": {
    "gn:gn_country":"CZ",
    "gn:gn_fcode":"PPL",
    "gn:gn_pop":591,
    "gn:population":591,
    "iso:country":"CZ",
    "name:azb_x_preferred":[
        "\u0645\u0648\u0631\u06cc\u0646\u0627"
    ],
    "name:ceb_x_preferred":[
        "Mo\u0159ina"
    ],
    "name:ces_x_preferred":[
        "Mo\u0159ina"
    ],
    "name:deu_x_preferred":[
        "Mo\u0159ina"
    ],
    "name:epo_x_preferred":[
        "Mo\u0159ina"
    ],
    "name:eus_x_preferred":[
        "Mo\u0159ina"
    ],
    "name:fas_x_preferred":[
        "\u0645\u0648\u0631\u06cc\u0646\u0627"
    ],
    "name:fra_x_preferred":[
        "Mo\u0159ina"
    ],
    "name:hun_x_preferred":[
        "Mo\u0159ina"
    ],
    "name:ita_x_preferred":[
        "Mo\u0159ina"
    ],
    "name:msa_x_preferred":[
        "Mo\u0159ina"
    ],
    "name:nld_x_preferred":[
        "Mo\u0159ina"
    ],
    "name:oci_x_preferred":[
        "Mo\u0159ina"
    ],
    "name:pol_x_preferred":[
        "Mo\u0159ina"
    ],
    "name:por_x_preferred":[
        "Mo\u0159ina"
    ],
    "name:slk_x_preferred":[
        "Mo\u0159ina"
    ],
    "name:spa_x_preferred":[
        "Mo\u0159ina"
    ],
    "name:srp_x_preferred":[
        "\u041c\u043e\u0440\u0436\u0438\u043d\u0430"
    ],
    "name:swe_x_preferred":[
        "Mo\u0159ina"
    ],
    "name:vie_x_preferred":[
        "Mo\u0159ina"
    ],
    "qs_pg:aaroncc":"CZ",
    "qs_pg:gn_country":"CZ",
    "qs_pg:gn_fcode":"PPL",
    "qs_pg:gn_pop":591,
    "qs_pg:name":"Mo\u0159ina",
    "qs_pg:name_adm0":"\u010cesk\u00e1 republika",
    "qs_pg:name_adm1":"St\u0159edo\u010desk\u00fd kraj",
    "qs_pg:photos":82,
    "qs_pg:photos_1k":17,
    "qs_pg:photos_9k":1,
    "qs_pg:photos_9r":3,
    "qs_pg:photos_all":82,
    "qs_pg:photos_sr":3,
    "qs_pg:pop_sr":2,
    "qs_pg:qs_pg_placetype":"locality",
    "qs_pg:qs_pg_placetype_gp":"Town",
    "qs_pg:woe_adm0":23424810,
    "woe:adm0_id":23424810,
    "woe:name_adm0":"\u010cesk\u00e1 republika",
    "woe:name_adm1":"St\u0159edo\u010desk\u00fd kraj",
    "woe:placetype":"Town",
    "wof:name":"Mo\u0159ina",
    "wof:placetype":"locality",
    "wof:population":591
},
  "geometry": {"coordinates":[14.20863,49.95284],"type":"Point"}
}