{
  "type": "Feature",
  "properties": {
    "gn:admin1_code":"88.0",
    "gn:admin2_code":"0207",
    "gn:asciiname":"Drazice",
    "gn:country_code":"CZ",
    "gn:dem":210,
    "gn:feature_class":"P",
    "gn:feature_code":"PPL",
    "gn:name":"Dra\u017eice",
    "gn:population":0,
    "gn:timezone":"Europe/Prague",
    "iso:country":"CZ",
    "name:und_x_variant":[
        "Draschitz",
        "Drazice nad Jizerou",
        "Dra\u017eice"
    ],
    "wof:name":"Drazice",
    "wof:placetype":"locality"
},
  "geometry": {"coordinates":[14.84459,50.30658],"type":"Point"}
}