{
  "type": "Feature",
  "properties": {
    "gn:admin1_code":"86.0",
    "gn:admin2_code":"0531",
    "gn:asciiname":"Smrkovy Tynec",
    "gn:country_code":"CZ",
    "gn:dem":381,
    "gn:feature_class":"P",
    "gn:feature_code":"PPL",
    "gn:name":"Smrkov\u00fd T\u00fdnec",
    "gn:population":0,
    "gn:timezone":"Europe/Prague",
    "iso:country":"CZ",
    "wof:name":"Smrkovy Tynec",
    "wof:placetype":"locality"
},
  "geometry": {"coordinates":[15.76206,49.89591],"type":"Point"}
}