{
  "type": "Feature",
  "properties": {
    "gn:admin1_code":"85.0",
    "gn:admin2_code":"0803",
    "gn:asciiname":"Prstna",
    "gn:country_code":"CZ",
    "gn:dem":248,
    "gn:feature_class":"P",
    "gn:feature_code":"PPL",
    "gn:name":"Prstn\u00e1",
    "gn:population":0,
    "gn:timezone":"Europe/Prague",
    "iso:country":"CZ",
    "wof:name":"Prstna",
    "wof:placetype":"locality"
},
  "geometry": {"coordinates":[18.54801,49.91271],"type":"Point"}
}