{
  "type": "Feature",
  "properties": {
    "iso:country":"CZ",
    "name:cze_x_preferred":[
        "Kramoly"
    ],
    "name:cze_x_variant":[
        "Krammel"
    ],
    "name:unk_x_variant":[
        "Krammel",
        "Kramoly"
    ],
    "qs:gn_adm0_cc":"CZ",
    "qs:gn_fcode":"PPLX",
    "qs:gn_local":3063548,
    "qs:gn_nam_loc":"\u00dast\u00ed nad Labem, \u00dasteck\u00fd kraj, CZ",
    "qs:gn_namadm1":"00",
    "qs:gn_name":"Kramoly",
    "qs:local_max":552,
    "qs:local_sum":1115,
    "qs:localhoods":8,
    "qs:name":"Kramoly",
    "qs:name_adm0":"\u010cesk\u00e1 republika",
    "qs:name_adm1":"\u00dasteck\u00fd kraj",
    "qs:name_adm2":"\u00dast\u00ed nad Labem",
    "qs:name_lau":"\u00dast\u00ed nad Labem",
    "qs:name_local":"\u00dast\u00ed nad Labem",
    "qs:photo_max":117,
    "qs:photo_sum":552,
    "qs:placetype":"Suburb",
    "qs:quad_count":18,
    "qs:woe_adm0":23424810,
    "qs:woe_adm1":20070499,
    "qs:woe_adm2":12582569,
    "qs:woe_lau":12606615,
    "qs:woe_local":800260,
    "qs:woe_ver":"7.10.0",
    "wof:lang":[
        "cze"
    ],
    "wof:name":"Kramoly",
    "wof:placetype":"neighbourhood"
},
  "geometry": {"coordinates":[14.039139,50.645506],"type":"Point"}
}