{
  "type": "Feature",
  "properties": {
    "gn:gn_country":"CZ",
    "iso:country":"CZ",
    "name:ces_x_preferred":[
        "He\u0159manice"
    ],
    "name:deu_x_preferred":[
        "He\u0159manice"
    ],
    "name:epo_x_preferred":[
        "He\u0159manice"
    ],
    "name:fra_x_preferred":[
        "He\u0159manice"
    ],
    "name:ita_x_preferred":[
        "He\u0159manice"
    ],
    "name:nld_x_preferred":[
        "He\u0159manice"
    ],
    "name:pol_x_preferred":[
        "He\u0159manice"
    ],
    "name:slk_x_preferred":[
        "He\u0159manice"
    ],
    "name:srp_x_preferred":[
        "\u0425\u0435\u0440\u043c\u0430\u045a\u0438\u0446\u0435"
    ],
    "qs_pg:aaroncc":"CZ",
    "qs_pg:gn_country":"CZ",
    "qs_pg:name":"He\u0159manice",
    "qs_pg:name_adm0":"\u010cesk\u00e1 republika",
    "qs_pg:name_adm1":"Libereck\u00fd kraj",
    "qs_pg:photos":1,
    "qs_pg:photos_1k":1,
    "qs_pg:photos_9k":1,
    "qs_pg:photos_9r":1,
    "qs_pg:photos_all":20,
    "qs_pg:photos_sr":1,
    "qs_pg:pop_sr":0,
    "qs_pg:qs_pg_placetype":"localadmin",
    "qs_pg:qs_pg_placetype_gp":"LocalAdmin",
    "qs_pg:woe_adm0":23424810,
    "woe:adm0_id":23424810,
    "woe:name_adm0":"\u010cesk\u00e1 republika",
    "woe:name_adm1":"Libereck\u00fd kraj",
    "woe:placetype":"LocalAdmin",
    "wof:name":"He\u0159manice",
    "wof:placetype":"localadmin"
},
  "geometry": {"coordinates":[14.9925825,50.902261],"type":"Point"}
}