{
  "type": "Feature",
  "properties": {
    "gn:admin1_code":"88.0",
    "gn:admin2_code":"020B",
    "gn:asciiname":"Kremenice",
    "gn:country_code":"CZ",
    "gn:dem":465,
    "gn:feature_class":"P",
    "gn:feature_code":"PPL",
    "gn:name":"K\u0159emenice",
    "gn:population":0,
    "gn:timezone":"Europe/Prague",
    "iso:country":"CZ",
    "wof:name":"Kremenice",
    "wof:placetype":"locality"
},
  "geometry": {"coordinates":[14.41761,49.58188],"type":"Point"}
}