{
  "type": "Feature",
  "properties": {
    "gn:gn_country":"CZ",
    "gn:gn_fcode":"PPL",
    "gn:gn_pop":398,
    "gn:population":398,
    "iso:country":"CZ",
    "name:azb_x_preferred":[
        "\u062a\u0645\u06cc\u06a9"
    ],
    "name:ceb_x_preferred":[
        "T\u011bmice"
    ],
    "name:ces_x_preferred":[
        "T\u011bmice"
    ],
    "name:deu_x_preferred":[
        "T\u011bmice u Kamenice nad Lipou"
    ],
    "name:eng_x_preferred":[
        "T\u011bmice"
    ],
    "name:eus_x_preferred":[
        "T\u011bmice"
    ],
    "name:fas_x_preferred":[
        "\u062a\u0645\u06cc\u06a9"
    ],
    "name:fra_x_preferred":[
        "T\u011bmice"
    ],
    "name:hun_x_preferred":[
        "T\u011bmice"
    ],
    "name:ita_x_preferred":[
        "T\u011bmice"
    ],
    "name:msa_x_preferred":[
        "T\u011bmice"
    ],
    "name:nan_x_preferred":[
        "T\u011bmice"
    ],
    "name:nld_x_preferred":[
        "T\u011bmice"
    ],
    "name:por_x_preferred":[
        "T\u011bmice"
    ],
    "name:rup_x_preferred":[
        "T\u011bmice"
    ],
    "name:slk_x_preferred":[
        "T\u011bmice"
    ],
    "name:spa_x_preferred":[
        "T\u011bmice"
    ],
    "name:srp_x_preferred":[
        "\u0422\u0458\u0435\u043c\u0438\u0446\u0435"
    ],
    "name:swe_x_preferred":[
        "T\u011bmice"
    ],
    "name:unk_x_variant":[
        "Temnitz"
    ],
    "name:vie_x_preferred":[
        "T\u011bmice"
    ],
    "qs_pg:aaroncc":"CZ",
    "qs_pg:gn_country":"CZ",
    "qs_pg:gn_fcode":"PPL",
    "qs_pg:gn_pop":398,
    "qs_pg:name":"T\u011bmice",
    "qs_pg:name_adm0":"\u010cesk\u00e1 republika",
    "qs_pg:name_adm1":"Kraj Vyso\u010dina",
    "qs_pg:photos_9r":0,
    "qs_pg:photos_sr":0,
    "qs_pg:pop_sr":2,
    "qs_pg:qs_pg_placetype":"locality",
    "qs_pg:qs_pg_placetype_gp":"Town",
    "qs_pg:woe_adm0":23424810,
    "woe:adm0_id":23424810,
    "woe:name_adm0":"\u010cesk\u00e1 republika",
    "woe:name_adm1":"Kraj Vyso\u010dina",
    "woe:placetype":"Town",
    "wof:name":"T\u011bmice",
    "wof:placetype":"locality",
    "wof:population":398
},
  "geometry": {"coordinates":[15.06045,49.35179],"type":"Point"}
}