{
  "type": "Feature",
  "properties": {
    "gn:gn_country":"CZ",
    "gn:gn_fcode":"PPL",
    "gn:gn_pop":720,
    "gn:population":720,
    "iso:country":"CZ",
    "name:cze_x_preferred":[
        "Vojn\u016fv M\u011bstec"
    ],
    "name:dut_x_preferred":[
        "Vojn\u016fv M\u011bstec"
    ],
    "name:eng_x_preferred":[
        "Vojn\u016fv M\u011bstec"
    ],
    "name:fre_x_preferred":[
        "Vojn\u016fv M\u011bstec"
    ],
    "name:ger_x_preferred":[
        "Vojn\u016fv M\u011bstec"
    ],
    "name:hun_x_preferred":[
        "Vojn\u016fv M\u011bstec"
    ],
    "name:ita_x_preferred":[
        "Vojn\u016fv M\u011bstec"
    ],
    "name:may_x_preferred":[
        "Vojn\u016fv M\u011bstec"
    ],
    "name:nob_x_preferred":[
        "Vojn\u016fv M\u011bstec"
    ],
    "name:per_x_preferred":[
        "\u0648\u0648\u06cc\u0646\u0648\u0641 \u0645\u06cc\u0633\u062a\u062a\u0633"
    ],
    "name:por_x_preferred":[
        "Vojn\u016fv M\u011bstec"
    ],
    "name:rup_x_preferred":[
        "Vojn\u016fv M\u011bstec"
    ],
    "name:slo_x_preferred":[
        "Vojn\u016fv M\u011bstec"
    ],
    "name:srp_x_preferred":[
        "\u0412\u043e\u0458\u043d\u0443\u0432 \u041c\u0458\u0435\u0441\u0442\u0435\u0446"
    ],
    "name:swe_x_preferred":[
        "Vojn\u016fv M\u011bstec"
    ],
    "name:unk_x_variant":[
        "Wojnowm\u011bstetz"
    ],
    "name:vie_x_preferred":[
        "Vojn\u016fv M\u011bstec"
    ],
    "qs_pg:aaroncc":"CZ",
    "qs_pg:gn_country":"CZ",
    "qs_pg:gn_fcode":"PPL",
    "qs_pg:gn_pop":720,
    "qs_pg:name":"Vojn\u016fv M\u011bstec",
    "qs_pg:name_adm0":"\u010cesk\u00e1 republika",
    "qs_pg:name_adm1":"Kraj Vyso\u010dina",
    "qs_pg:photos_9r":0,
    "qs_pg:photos_sr":0,
    "qs_pg:pop_sr":2,
    "qs_pg:qs_pg_placetype":"locality",
    "qs_pg:qs_pg_placetype_gp":"Town",
    "qs_pg:woe_adm0":23424810,
    "woe:adm0_id":23424810,
    "woe:name_adm0":"\u010cesk\u00e1 republika",
    "woe:name_adm1":"Kraj Vyso\u010dina",
    "woe:placetype":"Town",
    "wof:name":"Vojn\u016fv M\u011bstec",
    "wof:placetype":"locality",
    "wof:population":720
},
  "geometry": {"coordinates":[15.87828,49.67945],"type":"Point"}
}