{
  "type": "Feature",
  "properties": {
    "gn:admin1_code":"78.0",
    "gn:admin2_code":"0627",
    "gn:asciiname":"Hermanov",
    "gn:country_code":"CZ",
    "gn:dem":231,
    "gn:feature_class":"P",
    "gn:feature_code":"PPL",
    "gn:name":"He\u0159manov",
    "gn:population":0,
    "gn:timezone":"Europe/Prague",
    "iso:country":"CZ",
    "name:und_x_variant":[
        "Herrmannsdorf",
        "He\u0159manice",
        "Hermannsdorf",
        "He\u0159manov"
    ],
    "wof:name":"Hermanov",
    "wof:placetype":"locality"
},
  "geometry": {"coordinates":[16.28333,48.88333],"type":"Point"}
}