{
  "type": "Feature",
  "properties": {
    "gn:admin1_code":"82.0",
    "gn:admin2_code":"0524",
    "gn:asciiname":"Melcany",
    "gn:country_code":"CZ",
    "gn:dem":292,
    "gn:feature_class":"P",
    "gn:feature_code":"PPL",
    "gn:name":"M\u011bl\u010dany",
    "gn:population":0,
    "gn:timezone":"Europe/Prague",
    "iso:country":"CZ",
    "wof:name":"Melcany",
    "wof:placetype":"locality"
},
  "geometry": {"coordinates":[16.16612000000001,50.27571],"type":"Point"}
}