{
  "type": "Feature",
  "properties": {
    "gn:admin1_code":"88.0",
    "gn:admin2_code":"0202",
    "gn:asciiname":"Sedlec",
    "gn:country_code":"CZ",
    "gn:dem":356,
    "gn:feature_class":"P",
    "gn:feature_code":"PPL",
    "gn:name":"Sedlec",
    "gn:population":0,
    "gn:timezone":"Europe/Prague",
    "iso:country":"CZ",
    "name:ceb_x_preferred":[
        "Sedlec"
    ],
    "name:ces_x_preferred":[
        "Sedlec"
    ],
    "name:deu_x_preferred":[
        "Sedlec"
    ],
    "name:epo_x_preferred":[
        "Sedlec"
    ],
    "name:fra_x_preferred":[
        "Sedlec"
    ],
    "name:ita_x_preferred":[
        "Sedlec"
    ],
    "name:kor_x_preferred":[
        "\uc138\ub4e4\ub808\uce20"
    ],
    "name:nld_x_preferred":[
        "Sedlec"
    ],
    "name:pol_x_preferred":[
        "Sedlec"
    ],
    "name:rus_x_preferred":[
        "\u0421\u0435\u0434\u043b\u0435\u0446"
    ],
    "name:slk_x_preferred":[
        "Sedlec"
    ],
    "name:srp_x_preferred":[
        "\u0421\u0435\u0434\u043b\u0435\u0446"
    ],
    "name:swe_x_preferred":[
        "Sedlec"
    ],
    "wof:name":"Sedlec",
    "wof:placetype":"locality"
},
  "geometry": {"coordinates":[13.90766,49.86705],"type":"Point"}
}