{
  "type": "Feature",
  "properties": {
    "gn:admin1_code":"88.0",
    "gn:admin2_code":"0203",
    "gn:asciiname":"Horni Kamenice",
    "gn:country_code":"CZ",
    "gn:dem":245,
    "gn:feature_class":"P",
    "gn:feature_code":"PPL",
    "gn:name":"Horn\u00ed Kamenice",
    "gn:population":0,
    "gn:timezone":"Europe/Prague",
    "iso:country":"CZ",
    "wof:name":"Horni Kamenice",
    "wof:placetype":"locality"
},
  "geometry": {"coordinates":[14.06202,50.32313],"type":"Point"}
}