{
  "type": "Feature",
  "properties": {
    "gn:country":"CZ",
    "gn:fcode":"PPL",
    "gn:population":733,
    "iso:country":"CZ",
    "name:bul_x_preferred":[
        "\u0411\u043e\u0440\u043a\u043e\u0432\u0430\u043d\u0439"
    ],
    "name:ceb_x_preferred":[
        "Borkovany"
    ],
    "name:ces_x_preferred":[
        "Borkovany"
    ],
    "name:deu_x_preferred":[
        "Borkovany"
    ],
    "name:eng_x_preferred":[
        "Borkovany"
    ],
    "name:eus_x_preferred":[
        "Borkovany"
    ],
    "name:fas_x_preferred":[
        "\u0628\u0648\u0631\u06a9\u0648\u0648\u0627\u0646\u06cc"
    ],
    "name:fra_x_preferred":[
        "Borkovany"
    ],
    "name:hun_x_preferred":[
        "Borkovany"
    ],
    "name:ita_x_preferred":[
        "Borkovany"
    ],
    "name:msa_x_preferred":[
        "Borkovany"
    ],
    "name:nld_x_preferred":[
        "Borkovany"
    ],
    "name:pol_x_preferred":[
        "Borkovany"
    ],
    "name:por_x_preferred":[
        "Borkovany"
    ],
    "name:rup_x_preferred":[
        "Borkovany"
    ],
    "name:sgs_x_preferred":[
        "Buorkuovan\u0113"
    ],
    "name:slk_x_preferred":[
        "Borkovany"
    ],
    "name:spa_x_preferred":[
        "Borkovany"
    ],
    "name:srp_x_preferred":[
        "\u0411\u043e\u0440\u043a\u043e\u0432\u0430\u043d\u0438"
    ],
    "name:swe_x_preferred":[
        "Borkovany"
    ],
    "name:und_x_variant":[
        "Borkowan"
    ],
    "name:vie_x_preferred":[
        "Borkovany"
    ],
    "qs_pg:aaroncc":"CZ",
    "qs_pg:gn_country":"CZ",
    "qs_pg:gn_fcode":"PPL",
    "qs_pg:gn_pop":733,
    "qs_pg:name":"Borkovany",
    "qs_pg:name_adm0":"\u010cesk\u00e1 republika",
    "qs_pg:name_adm1":"Jihomoravsk\u00fd kraj",
    "qs_pg:photos_9k":1,
    "qs_pg:photos_9r":1,
    "qs_pg:photos_all":3,
    "qs_pg:photos_sr":0,
    "qs_pg:pop_sr":2,
    "qs_pg:qs_pg_placetype":"locality",
    "qs_pg:qs_pg_placetype_gp":"Town",
    "qs_pg:woe_adm0":23424810,
    "woe:adm0_id":23424810,
    "woe:name_adm0":"\u010cesk\u00e1 republika",
    "woe:name_adm1":"Jihomoravsk\u00fd kraj",
    "woe:placetype":"Town",
    "wof:name":"Borkovany",
    "wof:placetype":"locality",
    "wof:population":733
},
  "geometry": {"coordinates":[16.81011,49.02816],"type":"Point"}
}