{
  "type": "Feature",
  "properties": {
    "gn:admin1_code":"86",
    "gn:admin2_code":"0531",
    "gn:asciiname":"Strkov",
    "gn:country_code":"CZ",
    "gn:dem":490,
    "gn:feature_class":"P",
    "gn:feature_code":"PPL",
    "gn:name":"Strkov",
    "gn:population":0,
    "gn:timezone":"Europe/Prague",
    "iso:country":"CZ",
    "wof:name":"Strkov",
    "wof:placetype":"locality"
},
  "geometry": {"coordinates":[15.85218,49.83061],"type":"Point"}
}