{
  "type": "Feature",
  "properties": {
    "gn:admin1_code":"88.0",
    "gn:admin2_code":"0201",
    "gn:asciiname":"Podlesi",
    "gn:country_code":"CZ",
    "gn:dem":584,
    "gn:feature_class":"P",
    "gn:feature_code":"PPL",
    "gn:name":"Podles\u00ed",
    "gn:population":0,
    "gn:timezone":"Europe/Prague",
    "iso:country":"CZ",
    "wof:name":"Podlesi",
    "wof:placetype":"locality"
},
  "geometry": {"coordinates":[14.68164,49.60265],"type":"Point"}
}