{
  "type": "Feature",
  "properties": {
    "iso:country":"CZ",
    "name:ces_x_preferred":[
        "Hru\u0161kov\u00e9 Dvory"
    ],
    "name:cze_x_colloquial":[
        "Hrukove Dvory",
        "Hruskove Dvory",
        "Hrutkove Dvory"
    ],
    "name:cze_x_variant":[
        "Birnbaumhof",
        "Hrukov\u00e9 Dvory"
    ],
    "name:unk_x_variant":[
        "Birnbaumhof",
        "Hru\u0161kov\u00e9 Dvory"
    ],
    "qs:gn_adm0_cc":"CZ",
    "qs:gn_fcode":"PPL",
    "qs:gn_local":3074199,
    "qs:gn_nam_loc":"Jihlava, Jihlava, Jihlava, Kraj Vyso\u010dina, CZ",
    "qs:gn_namadm1":"80",
    "qs:gn_name":"Hru\u0161kov\u00e9 Dvory",
    "qs:local_max":2286,
    "qs:local_sum":2296,
    "qs:localhoods":2,
    "qs:name":"Hru\u0161kov\u00e9 Dvory",
    "qs:name_adm0":"\u010cesk\u00e1 republika",
    "qs:name_adm1":"Kraj Vyso\u010dina",
    "qs:name_adm2":"Jihlava",
    "qs:name_lau":"Jihlava",
    "qs:name_local":"Jihlava",
    "qs:photo_max":8,
    "qs:photo_sum":10,
    "qs:placetype":"Suburb",
    "qs:quad_count":3,
    "qs:woe_adm0":23424810,
    "qs:woe_adm1":20070467,
    "qs:woe_adm2":12582550,
    "qs:woe_lau":12605130,
    "qs:woe_local":790803,
    "qs:woe_ver":"7.10.0",
    "wof:lang":[
        "cze"
    ],
    "wof:name":"Hru\u0161kov\u00e9 Dvory",
    "wof:placetype":"neighbourhood"
},
  "geometry": {"coordinates":[15.590698,49.40311],"type":"Point"}
}