{
  "type": "Feature",
  "properties": {
    "gn:country":"CZ",
    "gn:fcode":"PPL",
    "gn:population":354,
    "iso:country":"CZ",
    "name:azb_x_preferred":[
        "\u067e\u0646\u0648\u0648\u0627\u0646\u06cc"
    ],
    "name:cat_x_preferred":[
        "P\u0148ovany"
    ],
    "name:ceb_x_preferred":[
        "P\u0148ovany"
    ],
    "name:ces_x_preferred":[
        "P\u0148ovany"
    ],
    "name:che_x_preferred":[
        "\u041f\u043d\u0451\u0432\u0430\u043d\u0438"
    ],
    "name:deu_x_preferred":[
        "P\u0148ovany"
    ],
    "name:eng_x_preferred":[
        "P\u0148ovany"
    ],
    "name:epo_x_preferred":[
        "P\u0148ovany"
    ],
    "name:eus_x_preferred":[
        "P\u0148ovany"
    ],
    "name:fas_x_preferred":[
        "\u067e\u0646\u0648\u0648\u0627\u0646\u06cc"
    ],
    "name:fra_x_preferred":[
        "P\u0148ovany"
    ],
    "name:gle_x_preferred":[
        "P\u0148ovany"
    ],
    "name:hun_x_preferred":[
        "P\u0148ovany"
    ],
    "name:ita_x_preferred":[
        "P\u0148ovany"
    ],
    "name:lmo_x_preferred":[
        "P\u0148ovany"
    ],
    "name:msa_x_preferred":[
        "P\u0148ovany"
    ],
    "name:nan_x_preferred":[
        "P\u0148ovany"
    ],
    "name:nld_x_preferred":[
        "P\u0148ovany"
    ],
    "name:pol_x_preferred":[
        "P\u0148ovany"
    ],
    "name:por_x_preferred":[
        "P\u0148ovany"
    ],
    "name:slk_x_preferred":[
        "P\u0148ovany"
    ],
    "name:spa_x_preferred":[
        "P\u0148ovany"
    ],
    "name:srp_x_preferred":[
        "\u041f\u045a\u043e\u0432\u0430\u043d\u0438"
    ],
    "name:swe_x_preferred":[
        "P\u0148ovany"
    ],
    "name:tat_x_preferred":[
        "\u041f\u043d\u0451\u0432\u0430\u043d\u0438"
    ],
    "name:und_x_variant":[
        "Piwana"
    ],
    "name:vie_x_preferred":[
        "P\u0148ovany"
    ],
    "qs_pg:aaroncc":"CZ",
    "qs_pg:gn_country":"CZ",
    "qs_pg:gn_fcode":"PPL",
    "qs_pg:gn_pop":354,
    "qs_pg:name":"P\u0148ovany",
    "qs_pg:name_adm0":"\u010cesk\u00e1 republika",
    "qs_pg:name_adm1":"Plze\u0148sk\u00fd kraj",
    "qs_pg:photos_9k":1,
    "qs_pg:photos_9r":1,
    "qs_pg:photos_all":6,
    "qs_pg:photos_sr":0,
    "qs_pg:pop_sr":2,
    "qs_pg:qs_pg_placetype":"locality",
    "qs_pg:qs_pg_placetype_gp":"Town",
    "qs_pg:woe_adm0":23424810,
    "woe:adm0_id":23424810,
    "woe:name_adm0":"\u010cesk\u00e1 republika",
    "woe:name_adm1":"Plze\u0148sk\u00fd kraj",
    "woe:placetype":"Town",
    "wof:name":"P\u0148ovany",
    "wof:placetype":"locality",
    "wof:population":354
},
  "geometry": {"coordinates":[13.12175,49.77888],"type":"Point"}
}