{
  "type": "Feature",
  "properties": {
    "gn:admin1_code":"83.0",
    "gn:admin2_code":"0511",
    "gn:asciiname":"Borecek",
    "gn:country_code":"CZ",
    "gn:dem":294,
    "gn:feature_class":"P",
    "gn:feature_code":"PPL",
    "gn:name":"Bore\u010dek",
    "gn:population":0,
    "gn:timezone":"Europe/Prague",
    "iso:country":"CZ",
    "name:und_x_variant":[
        "Haided\u00f6rfel",
        "Bore\u010dek"
    ],
    "wof:name":"Borecek",
    "wof:placetype":"locality"
},
  "geometry": {"coordinates":[14.71708,50.63987],"type":"Point"}
}