{
  "type": "Feature",
  "properties": {
    "gn:gn_country":"CZ",
    "gn:gn_fcode":"PPL",
    "gn:gn_pop":222,
    "gn:population":222,
    "iso:country":"CZ",
    "name:azb_x_preferred":[
        "\u06a9\u0631\u0644\u0648\u0648\u06cc\u062a\u0633\u0647"
    ],
    "name:ceb_x_preferred":[
        "K\u0159elovice"
    ],
    "name:ces_x_preferred":[
        "K\u0159elovice"
    ],
    "name:deu_x_preferred":[
        "K\u0159elovice u Pernarce"
    ],
    "name:eng_x_preferred":[
        "K\u0159elovice"
    ],
    "name:eus_x_preferred":[
        "K\u0159elovice"
    ],
    "name:fas_x_preferred":[
        "\u06a9\u0631\u0644\u0648\u0648\u06cc\u062a\u0633\u0647"
    ],
    "name:fra_x_preferred":[
        "K\u0159elovice"
    ],
    "name:hun_x_preferred":[
        "K\u0159elovice"
    ],
    "name:ita_x_preferred":[
        "K\u0159elovice"
    ],
    "name:msa_x_preferred":[
        "K\u0159elovice"
    ],
    "name:nan_x_preferred":[
        "K\u0159elovice"
    ],
    "name:nld_x_preferred":[
        "K\u0159elovice"
    ],
    "name:por_x_preferred":[
        "K\u0159elovice"
    ],
    "name:rup_x_preferred":[
        "K\u0159elovice"
    ],
    "name:slk_x_preferred":[
        "K\u0159elovice"
    ],
    "name:spa_x_preferred":[
        "K\u0159elovice"
    ],
    "name:srp_x_preferred":[
        "\u041a\u0440\u0435\u043b\u043e\u0432\u0438\u0446\u0435"
    ],
    "name:swe_x_preferred":[
        "K\u0159elovice"
    ],
    "name:vie_x_preferred":[
        "K\u0159elovice"
    ],
    "qs_pg:aaroncc":"CZ",
    "qs_pg:gn_country":"CZ",
    "qs_pg:gn_fcode":"PPL",
    "qs_pg:gn_pop":222,
    "qs_pg:name":"K\u0159elovice",
    "qs_pg:name_adm0":"\u010cesk\u00e1 republika",
    "qs_pg:name_adm1":"Plze\u0148sk\u00fd kraj",
    "qs_pg:photos_9r":0,
    "qs_pg:photos_sr":0,
    "qs_pg:pop_sr":2,
    "qs_pg:qs_pg_placetype":"locality",
    "qs_pg:qs_pg_placetype_gp":"Town",
    "qs_pg:woe_adm0":23424810,
    "woe:adm0_id":23424810,
    "woe:name_adm0":"\u010cesk\u00e1 republika",
    "woe:name_adm1":"Plze\u0148sk\u00fd kraj",
    "woe:placetype":"Town",
    "wof:name":"K\u0159elovice",
    "wof:placetype":"locality",
    "wof:population":222
},
  "geometry": {"coordinates":[13.0758,49.87431],"type":"Point"}
}