{
  "type": "Feature",
  "properties": {
    "gn:gn_country":"CZ",
    "gn:gn_fcode":"PPL",
    "gn:gn_pop":726,
    "gn:population":726,
    "iso:country":"CZ",
    "name:azb_x_preferred":[
        "\u0627\u0648\u0644\u0634\u0646\u06cc\u06a9"
    ],
    "name:ceb_x_preferred":[
        "Ole\u0161n\u00edk"
    ],
    "name:ces_x_preferred":[
        "Ole\u0161n\u00edk"
    ],
    "name:deu_x_preferred":[
        "Ole\u0161n\u00edk"
    ],
    "name:eng_x_preferred":[
        "Ole\u0161n\u00edk"
    ],
    "name:eus_x_preferred":[
        "Ole\u0161n\u00edk"
    ],
    "name:fas_x_preferred":[
        "\u0627\u0648\u0644\u0634\u0646\u06cc\u06a9"
    ],
    "name:fra_x_preferred":[
        "Ole\u0161n\u00edk"
    ],
    "name:hun_x_preferred":[
        "Ole\u0161n\u00edk"
    ],
    "name:ita_x_preferred":[
        "Ole\u0161n\u00edk"
    ],
    "name:msa_x_preferred":[
        "Ole\u0161n\u00edk"
    ],
    "name:nan_x_preferred":[
        "Ole\u0161n\u00edk"
    ],
    "name:nld_x_preferred":[
        "Ole\u0161n\u00edk"
    ],
    "name:pol_x_preferred":[
        "Ole\u0161n\u00edk"
    ],
    "name:por_x_preferred":[
        "Ole\u0161n\u00edk"
    ],
    "name:rup_x_preferred":[
        "Ole\u0161n\u00edk"
    ],
    "name:slk_x_preferred":[
        "Ole\u0161n\u00edk"
    ],
    "name:spa_x_preferred":[
        "Ole\u0161n\u00edk"
    ],
    "name:srp_x_preferred":[
        "\u041e\u043b\u0435\u0448\u045a\u0438\u043a"
    ],
    "name:swe_x_preferred":[
        "Ole\u0161n\u00edk"
    ],
    "name:vie_x_preferred":[
        "Ole\u0161n\u00edk"
    ],
    "qs_pg:aaroncc":"CZ",
    "qs_pg:gn_country":"CZ",
    "qs_pg:gn_fcode":"PPL",
    "qs_pg:gn_pop":726,
    "qs_pg:name":"Ole\u0161n\u00edk",
    "qs_pg:name_adm0":"\u010cesk\u00e1 republika",
    "qs_pg:name_adm1":"Jiho\u010desk\u00fd kraj",
    "qs_pg:photos_9r":0,
    "qs_pg:photos_sr":0,
    "qs_pg:pop_sr":2,
    "qs_pg:qs_pg_placetype":"locality",
    "qs_pg:qs_pg_placetype_gp":"Town",
    "qs_pg:woe_adm0":23424810,
    "woe:adm0_id":23424810,
    "woe:name_adm0":"\u010cesk\u00e1 republika",
    "woe:name_adm1":"Jiho\u010desk\u00fd kraj",
    "woe:placetype":"Town",
    "wof:name":"Ole\u0161n\u00edk",
    "wof:placetype":"locality",
    "wof:population":726
},
  "geometry": {"coordinates":[14.36382,49.10713],"type":"Point"}
}