{
  "type": "Feature",
  "properties": {
    "gn:admin1_code":"84",
    "gn:admin2_code":"0712",
    "gn:asciiname":"U Urbanu",
    "gn:country_code":"CZ",
    "gn:dem":689,
    "gn:feature_class":"P",
    "gn:feature_code":"PPL",
    "gn:name":"U Urban\u016f",
    "gn:population":0,
    "gn:timezone":"Europe/Prague",
    "iso:country":"CZ",
    "wof:name":"U Urbanu",
    "wof:placetype":"locality"
},
  "geometry": {"coordinates":[17.36667000000001,49.85],"type":"Point"}
}