{
  "type": "Feature",
  "properties": {
    "gn:gn_country":"CZ",
    "gn:gn_fcode":"PPL",
    "gn:gn_pop":218,
    "gn:population":218,
    "iso:country":"CZ",
    "name:cze_x_preferred":[
        "Karlovice"
    ],
    "name:dut_x_preferred":[
        "Karlovice"
    ],
    "name:eng_x_preferred":[
        "Karlovice"
    ],
    "name:fre_x_preferred":[
        "Karlovice"
    ],
    "name:ger_x_preferred":[
        "Karlovice u Zl\u00edna"
    ],
    "name:hun_x_preferred":[
        "Karlovice"
    ],
    "name:ita_x_preferred":[
        "Karlovice"
    ],
    "name:may_x_preferred":[
        "Karlovice"
    ],
    "name:per_x_preferred":[
        "\u06a9\u0627\u0631\u0644\u0648\u0648\u06cc\u062a\u0633\u0647"
    ],
    "name:pol_x_preferred":[
        "Karlovice"
    ],
    "name:por_x_preferred":[
        "Karlovice"
    ],
    "name:rup_x_preferred":[
        "Karlovice"
    ],
    "name:slo_x_preferred":[
        "Karlovice"
    ],
    "name:srp_x_preferred":[
        "\u041a\u0430\u0440\u043b\u043e\u0432\u0438\u0446\u0435"
    ],
    "name:swe_x_preferred":[
        "Karlovice"
    ],
    "name:vie_x_preferred":[
        "Karlovice"
    ],
    "qs_pg:aaroncc":"CZ",
    "qs_pg:gn_country":"CZ",
    "qs_pg:gn_fcode":"PPL",
    "qs_pg:gn_pop":218,
    "qs_pg:name":"M. Karlovice",
    "qs_pg:name_adm0":"\u010cesk\u00e1 republika",
    "qs_pg:name_adm1":"Zl\u00ednsk\u00fd kraj",
    "qs_pg:photos_9k":1,
    "qs_pg:photos_9r":1,
    "qs_pg:photos_all":1,
    "qs_pg:photos_sr":0,
    "qs_pg:pop_sr":2,
    "qs_pg:qs_pg_placetype":"locality",
    "qs_pg:qs_pg_placetype_gp":"Town",
    "qs_pg:woe_adm0":23424810,
    "woe:adm0_id":23424810,
    "woe:name_adm0":"\u010cesk\u00e1 republika",
    "woe:name_adm1":"Zl\u00ednsk\u00fd kraj",
    "woe:placetype":"Town",
    "wof:name":"M. Karlovice",
    "wof:placetype":"locality",
    "wof:population":218
},
  "geometry": {"coordinates":[17.58582,49.17641],"type":"Point"}
}