{
  "type": "Feature",
  "properties": {
    "gn:admin1_code":"90.0",
    "gn:admin2_code":"0721",
    "gn:asciiname":"Sovadina",
    "gn:country_code":"CZ",
    "gn:dem":276,
    "gn:feature_class":"P",
    "gn:feature_code":"PPL",
    "gn:name":"Sovadina",
    "gn:population":0,
    "gn:timezone":"Europe/Prague",
    "iso:country":"CZ",
    "wof:name":"Sovadina",
    "wof:placetype":"locality"
},
  "geometry": {"coordinates":[17.65202,49.43333],"type":"Point"}
}