{
  "type": "Feature",
  "properties": {
    "gn:admin1_code":"87.0",
    "gn:admin2_code":"0321",
    "gn:asciiname":"Hrichovice",
    "gn:country_code":"CZ",
    "gn:dem":430,
    "gn:feature_class":"P",
    "gn:feature_code":"PPL",
    "gn:name":"H\u0159\u00edchovice",
    "gn:population":0,
    "gn:timezone":"Europe/Prague",
    "iso:country":"CZ",
    "wof:name":"Hrichovice",
    "wof:placetype":"locality"
},
  "geometry": {"coordinates":[13.03731,49.45551],"type":"Point"}
}