{
  "type": "Feature",
  "properties": {
    "iso:country":"CZ",
    "name:azb_x_preferred":[
        "\u062f\u0648\u0644\u0646\u06cc \u0644\u0648\u062e\u0648\u0648"
    ],
    "name:ces_x_preferred":[
        "Doln\u00ed Lochov"
    ],
    "name:eus_x_preferred":[
        "Doln\u00ed Lochov"
    ],
    "name:fas_x_preferred":[
        "\u062f\u0648\u0644\u0646\u06cc \u0644\u0648\u062e\u0648\u0648"
    ],
    "name:fra_x_preferred":[
        "Doln\u00ed Lochov"
    ],
    "name:hun_x_preferred":[
        "Doln\u00ed Lochov"
    ],
    "name:ita_x_preferred":[
        "Doln\u00ed Lochov"
    ],
    "name:msa_x_preferred":[
        "Doln\u00ed Lochov"
    ],
    "name:nld_x_preferred":[
        "Doln\u00ed Lochov"
    ],
    "name:pol_x_preferred":[
        "Doln\u00ed Lochov"
    ],
    "name:por_x_preferred":[
        "Doln\u00ed Lochov"
    ],
    "name:slk_x_preferred":[
        "Doln\u00ed Lochov"
    ],
    "name:spa_x_preferred":[
        "Doln\u00ed Lochov"
    ],
    "name:srp_x_preferred":[
        "\u0414\u043e\u043b\u045a\u0438 \u041b\u043e\u0445\u043e\u0432"
    ],
    "name:vie_x_preferred":[
        "Doln\u00ed Lochov"
    ],
    "qs_pg:aaroncc":"CZ",
    "qs_pg:name":"Doln\u00ed Lochov",
    "qs_pg:name_adm0":"\u010cesk\u00e1 republika",
    "qs_pg:name_adm1":"Kr\u00e1lov\u00e9hradeck\u00fd kraj",
    "qs_pg:photos":1,
    "qs_pg:photos_1k":1,
    "qs_pg:photos_9k":1,
    "qs_pg:photos_9r":1,
    "qs_pg:photos_all":1,
    "qs_pg:photos_sr":1,
    "qs_pg:pop_sr":0,
    "qs_pg:qs_pg_placetype":"localadmin",
    "qs_pg:qs_pg_placetype_gp":"LocalAdmin",
    "qs_pg:woe_adm0":23424810,
    "woe:adm0_id":23424810,
    "woe:name_adm0":"\u010cesk\u00e1 republika",
    "woe:name_adm1":"Kr\u00e1lov\u00e9hradeck\u00fd kraj",
    "woe:placetype":"LocalAdmin",
    "wof:name":"Doln\u00ed Lochov",
    "wof:placetype":"localadmin"
},
  "geometry": {"coordinates":[15.289192,50.467557],"type":"Point"}
}