{
  "type": "Feature",
  "properties": {
    "gn:admin1_code":"79.0",
    "gn:admin2_code":"0314",
    "gn:asciiname":"Horni Novosedly",
    "gn:country_code":"CZ",
    "gn:dem":522,
    "gn:feature_class":"P",
    "gn:feature_code":"PPL",
    "gn:name":"Horn\u00ed Novosedly",
    "gn:population":0,
    "gn:timezone":"Europe/Prague",
    "iso:country":"CZ",
    "wof:name":"Horni Novosedly",
    "wof:placetype":"locality"
},
  "geometry": {"coordinates":[14.19524,49.32257],"type":"Point"}
}