{
  "type": "Feature",
  "properties": {
    "gn:admin1_code":"79.0",
    "gn:admin2_code":"0315",
    "gn:asciiname":"Solna Lhota",
    "gn:country_code":"CZ",
    "gn:dem":818,
    "gn:feature_class":"P",
    "gn:feature_code":"PPL",
    "gn:name":"Soln\u00e1 Lhota",
    "gn:population":0,
    "gn:timezone":"Europe/Prague",
    "iso:country":"CZ",
    "name:und_x_variant":[
        "Salzweg",
        "Soln\u00e1 Lhota"
    ],
    "wof:name":"Solna Lhota",
    "wof:placetype":"locality"
},
  "geometry": {"coordinates":[13.76315,49.02989],"type":"Point"}
}