{
  "type": "Feature",
  "properties": {
    "gn:admin1_code":"80.0",
    "gn:admin2_code":"0614",
    "gn:asciiname":"Kolovraty",
    "gn:country_code":"CZ",
    "gn:dem":475,
    "gn:feature_class":"P",
    "gn:feature_code":"PPL",
    "gn:name":"Kolovraty",
    "gn:population":0,
    "gn:timezone":"Europe/Prague",
    "iso:country":"CZ",
    "name:ces_x_preferred":[
        "Kolovraty"
    ],
    "name:fas_x_preferred":[
        "\u06a9\u0648\u0644\u0648\u0648\u0631\u0627\u062a\u06cc"
    ],
    "name:pol_x_preferred":[
        "Kolovraty"
    ],
    "name:slk_x_preferred":[
        "Kolovraty"
    ],
    "wof:name":"Kolovraty",
    "wof:placetype":"locality"
},
  "geometry": {"coordinates":[15.7645,49.07052],"type":"Point"}
}