{
  "type": "Feature",
  "properties": {
    "gn:country":"CZ",
    "gn:fcode":"PPL",
    "gn:population":0,
    "iso:country":"CZ",
    "name:und_x_variant":[
        "V Pa\u0159ez\u00ed"
    ],
    "qs_pg:aaroncc":"CZ",
    "qs_pg:gn_country":"CZ",
    "qs_pg:gn_fcode":"PPL",
    "qs_pg:gn_pop":0,
    "qs_pg:name":"Pa\u0159ez\u00ed",
    "qs_pg:name_adm0":"\u010cesk\u00e1 republika",
    "qs_pg:name_adm1":"Plze\u0148sk\u00fd kraj",
    "qs_pg:photos_9k":1,
    "qs_pg:photos_9r":1,
    "qs_pg:photos_all":8,
    "qs_pg:photos_sr":0,
    "qs_pg:pop_sr":0,
    "qs_pg:qs_pg_placetype":"locality",
    "qs_pg:qs_pg_placetype_gp":"Town",
    "qs_pg:woe_adm0":23424810,
    "woe:adm0_id":23424810,
    "woe:name_adm0":"\u010cesk\u00e1 republika",
    "woe:name_adm1":"Plze\u0148sk\u00fd kraj",
    "woe:placetype":"Town",
    "wof:name":"Pa\u0159ez\u00ed",
    "wof:placetype":"locality"
},
  "geometry": {"coordinates":[14.2675,49.20885],"type":"Point"}
}