{
  "type": "Feature",
  "properties": {
    "gn:admin1_code":"85.0",
    "gn:admin2_code":"0802",
    "gn:asciiname":"Jamnik",
    "gn:country_code":"CZ",
    "gn:dem":610,
    "gn:feature_class":"P",
    "gn:feature_code":"PPL",
    "gn:name":"Jamn\u00edk",
    "gn:population":0,
    "gn:timezone":"Europe/Prague",
    "iso:country":"CZ",
    "wof:name":"Jamnik",
    "wof:placetype":"locality"
},
  "geometry": {"coordinates":[18.44856,49.48345],"type":"Point"}
}