{
  "type": "Feature",
  "properties": {
    "gn:admin1_code":"87.0",
    "gn:admin2_code":"0324",
    "gn:asciiname":"Osobovy",
    "gn:country_code":"CZ",
    "gn:dem":512,
    "gn:feature_class":"P",
    "gn:feature_code":"PPL",
    "gn:name":"Osobovy",
    "gn:population":0,
    "gn:timezone":"Europe/Prague",
    "iso:country":"CZ",
    "wof:name":"Osobovy",
    "wof:placetype":"locality"
},
  "geometry": {"coordinates":[13.46065,49.4734],"type":"Point"}
}