{
  "type": "Feature",
  "properties": {
    "gn:admin1_code":"79.0",
    "gn:admin2_code":"0311",
    "gn:asciiname":"Ctyri Dvory",
    "gn:country_code":"CZ",
    "gn:dem":388,
    "gn:feature_class":"P",
    "gn:feature_code":"PPL",
    "gn:name":"\u010cty\u0159i Dvory",
    "gn:population":0,
    "gn:timezone":"Europe/Prague",
    "iso:country":"CZ",
    "wof:name":"Ctyri Dvory",
    "wof:placetype":"locality"
},
  "geometry": {"coordinates":[14.45269,48.98274],"type":"Point"}
}