{
  "type": "Feature",
  "properties": {
    "iso:country":"CZ",
    "name:ara_x_preferred":[
        "\u0631\u0648\u0643\u064a\u062a\u0633\u0627\u0646\u064a"
    ],
    "name:ceb_x_preferred":[
        "Rokycany"
    ],
    "name:ces_x_preferred":[
        "Rokycany"
    ],
    "name:deu_x_preferred":[
        "Rokycany"
    ],
    "name:epo_x_preferred":[
        "Rokycany"
    ],
    "name:eus_x_preferred":[
        "Rokycany"
    ],
    "name:fas_x_preferred":[
        "\u0631\u0648\u06a9\u06cc\u062a\u0633\u0627\u0646\u06cc"
    ],
    "name:hun_x_preferred":[
        "Rokycany"
    ],
    "name:ita_x_preferred":[
        "Rokycany"
    ],
    "name:lit_x_preferred":[
        "Rokicanai"
    ],
    "name:msa_x_preferred":[
        "Rokycany"
    ],
    "name:nld_x_preferred":[
        "Rokycany"
    ],
    "name:pol_x_preferred":[
        "Rokycany"
    ],
    "name:por_x_preferred":[
        "Rokycany"
    ],
    "name:rus_x_preferred":[
        "\u0420\u043e\u043a\u0438\u0446\u0430\u043d\u0438"
    ],
    "name:slk_x_preferred":[
        "Rokycany"
    ],
    "name:spa_x_preferred":[
        "Rokycany"
    ],
    "name:srp_x_preferred":[
        "\u0420\u043e\u043a\u0438\u0446\u0430\u043d\u0438"
    ],
    "name:szl_x_preferred":[
        "Rokycany"
    ],
    "name:tur_x_preferred":[
        "Rokycany"
    ],
    "name:vie_x_preferred":[
        "Rokycany"
    ],
    "name:war_x_preferred":[
        "Rokycany"
    ],
    "name:zho_x_preferred":[
        "\u7f85\u57fa\u5bdf\u5c3c"
    ],
    "qs_pg:aaroncc":"CZ",
    "qs_pg:name":"Rokycany",
    "qs_pg:name_adm0":"\u010cesk\u00e1 republika",
    "qs_pg:name_adm1":"Plze\u0148sk\u00fd kraj",
    "qs_pg:photos":2,
    "qs_pg:photos_1k":1,
    "qs_pg:photos_9k":2,
    "qs_pg:photos_9r":5,
    "qs_pg:photos_all":446,
    "qs_pg:photos_sr":1,
    "qs_pg:pop_sr":0,
    "qs_pg:qs_pg_placetype":"localadmin",
    "qs_pg:qs_pg_placetype_gp":"LocalAdmin",
    "qs_pg:woe_adm0":23424810,
    "woe:adm0_id":23424810,
    "woe:name_adm0":"\u010cesk\u00e1 republika",
    "woe:name_adm1":"Plze\u0148sk\u00fd kraj",
    "woe:placetype":"LocalAdmin",
    "wof:name":"Rokycany",
    "wof:placetype":"localadmin"
},
  "geometry": {"coordinates":[13.586826,49.750902],"type":"Point"}
}