{
  "type": "Feature",
  "properties": {
    "gn:country":"CZ",
    "gn:fcode":"PPL",
    "gn:population":361,
    "iso:country":"CZ",
    "name:azb_x_preferred":[
        "\u06a9\u0648\u06cc\u0627\u062a\u06a9\u06cc"
    ],
    "name:cat_x_preferred":[
        "Koj\u00e1tky"
    ],
    "name:ceb_x_preferred":[
        "Koj\u00e1tky"
    ],
    "name:ces_x_preferred":[
        "Koj\u00e1tky"
    ],
    "name:che_x_preferred":[
        "\u041a\u043e\u044f\u0442\u043a\u0438"
    ],
    "name:deu_x_preferred":[
        "Koj\u00e1tky"
    ],
    "name:eng_x_preferred":[
        "Koj\u00e1tky"
    ],
    "name:epo_x_preferred":[
        "Koj\u00e1tky"
    ],
    "name:eus_x_preferred":[
        "Koj\u00e1tky"
    ],
    "name:fas_x_preferred":[
        "\u06a9\u0648\u06cc\u0627\u062a\u06a9\u06cc"
    ],
    "name:fra_x_preferred":[
        "Koj\u00e1tky"
    ],
    "name:gle_x_preferred":[
        "Koj\u00e1tky"
    ],
    "name:hun_x_preferred":[
        "Koj\u00e1tky"
    ],
    "name:ita_x_preferred":[
        "Koj\u00e1tky"
    ],
    "name:lmo_x_preferred":[
        "Koj\u00e1tky"
    ],
    "name:msa_x_preferred":[
        "Koj\u00e1tky"
    ],
    "name:nan_x_preferred":[
        "Koj\u00e1tky"
    ],
    "name:nld_x_preferred":[
        "Koj\u00e1tky"
    ],
    "name:pol_x_preferred":[
        "Koj\u00e1tky"
    ],
    "name:por_x_preferred":[
        "Koj\u00e1tky"
    ],
    "name:slk_x_preferred":[
        "Koj\u00e1tky"
    ],
    "name:spa_x_preferred":[
        "Koj\u00e1tky"
    ],
    "name:srp_x_preferred":[
        "\u041a\u043e\u0458\u0430\u0442\u043a\u0438"
    ],
    "name:swe_x_preferred":[
        "Koj\u00e1tky"
    ],
    "name:tat_x_preferred":[
        "\u041a\u043e\u044f\u0442\u043a\u0438"
    ],
    "name:vie_x_preferred":[
        "Koj\u00e1tky"
    ],
    "qs_pg:aaroncc":"CZ",
    "qs_pg:gn_country":"CZ",
    "qs_pg:gn_fcode":"PPL",
    "qs_pg:gn_pop":361,
    "qs_pg:name":"Koj\u00e1tky",
    "qs_pg:name_adm0":"\u010cesk\u00e1 republika",
    "qs_pg:name_adm1":"Jihomoravsk\u00fd kraj",
    "qs_pg:photos_9r":0,
    "qs_pg:photos_sr":0,
    "qs_pg:pop_sr":2,
    "qs_pg:qs_pg_placetype":"locality",
    "qs_pg:qs_pg_placetype_gp":"Town",
    "qs_pg:woe_adm0":23424810,
    "woe:adm0_id":23424810,
    "woe:name_adm0":"\u010cesk\u00e1 republika",
    "woe:name_adm1":"Jihomoravsk\u00fd kraj",
    "woe:placetype":"Town",
    "wof:name":"Koj\u00e1tky",
    "wof:placetype":"locality",
    "wof:population":361
},
  "geometry": {"coordinates":[17.02613,49.1718],"type":"Point"}
}