{
  "type": "Feature",
  "properties": {
    "gn:admin1_code":"89.0",
    "gn:admin2_code":"0425",
    "gn:asciiname":"Horni Ves",
    "gn:country_code":"CZ",
    "gn:dem":503,
    "gn:feature_class":"P",
    "gn:feature_code":"PPL",
    "gn:name":"Horn\u00ed Ves",
    "gn:population":0,
    "gn:timezone":"Europe/Prague",
    "iso:country":"CZ",
    "name:und_x_variant":[
        "Oberdorf",
        "Horn\u00ed Ves"
    ],
    "wof:name":"Horni Ves",
    "wof:placetype":"locality"
},
  "geometry": {"coordinates":[13.57849,50.61157],"type":"Point"}
}