{
  "type": "Feature",
  "properties": {
    "gn:gn_country":"CZ",
    "gn:gn_fcode":"PPL",
    "gn:gn_pop":188,
    "gn:population":188,
    "iso:country":"CZ",
    "name:azb_x_preferred":[
        "\u0628\u0648\u0647\u0648\u0633\u062a\u06cc\u062a\u0633\u0647"
    ],
    "name:ceb_x_preferred":[
        "Bohostice"
    ],
    "name:ces_x_preferred":[
        "Bohostice"
    ],
    "name:eng_x_preferred":[
        "Bohostice"
    ],
    "name:eus_x_preferred":[
        "Bohostice"
    ],
    "name:fas_x_preferred":[
        "\u0628\u0648\u0647\u0648\u0633\u062a\u06cc\u062a\u0633\u0647"
    ],
    "name:fra_x_preferred":[
        "Bohostice"
    ],
    "name:hun_x_preferred":[
        "Bohostice"
    ],
    "name:ita_x_preferred":[
        "Bohostice"
    ],
    "name:msa_x_preferred":[
        "Bohostice"
    ],
    "name:nan_x_preferred":[
        "Bohostice"
    ],
    "name:nld_x_preferred":[
        "Bohostice"
    ],
    "name:pol_x_preferred":[
        "Bohostice"
    ],
    "name:por_x_preferred":[
        "Bohostice"
    ],
    "name:rup_x_preferred":[
        "Bohostice"
    ],
    "name:slk_x_preferred":[
        "Bohostice"
    ],
    "name:spa_x_preferred":[
        "Bohostice"
    ],
    "name:srp_x_preferred":[
        "\u0411\u043e\u0445\u043e\u0441\u0442\u0438\u0446\u0435"
    ],
    "name:swe_x_preferred":[
        "Bohostice"
    ],
    "name:vie_x_preferred":[
        "Bohostice"
    ],
    "qs_pg:aaroncc":"CZ",
    "qs_pg:gn_country":"CZ",
    "qs_pg:gn_fcode":"PPL",
    "qs_pg:gn_pop":188,
    "qs_pg:name":"Bohostice",
    "qs_pg:name_adm0":"\u010cesk\u00e1 republika",
    "qs_pg:name_adm1":"St\u0159edo\u010desk\u00fd kraj",
    "qs_pg:photos_9k":1,
    "qs_pg:photos_9r":1,
    "qs_pg:photos_all":1,
    "qs_pg:photos_sr":0,
    "qs_pg:pop_sr":1,
    "qs_pg:qs_pg_placetype":"locality",
    "qs_pg:qs_pg_placetype_gp":"Town",
    "qs_pg:woe_adm0":23424810,
    "woe:adm0_id":23424810,
    "woe:name_adm0":"\u010cesk\u00e1 republika",
    "woe:name_adm1":"St\u0159edo\u010desk\u00fd kraj",
    "woe:placetype":"Town",
    "wof:name":"Bohostice",
    "wof:placetype":"locality",
    "wof:population":188
},
  "geometry": {"coordinates":[14.13813,49.60214],"type":"Point"}
}