{
  "type": "Feature",
  "properties": {
    "gn:country":"CZ",
    "gn:fcode":"PPL",
    "gn:population":240,
    "iso:country":"CZ",
    "name:ceb_x_preferred":[
        "Kaly"
    ],
    "name:ces_x_preferred":[
        "Kaly"
    ],
    "name:deu_x_preferred":[
        "Kaly"
    ],
    "name:eng_x_preferred":[
        "Kaly"
    ],
    "name:eus_x_preferred":[
        "Kaly"
    ],
    "name:fra_x_preferred":[
        "Kaly"
    ],
    "name:hun_x_preferred":[
        "Kaly"
    ],
    "name:ita_x_preferred":[
        "Kaly"
    ],
    "name:msa_x_preferred":[
        "Kaly"
    ],
    "name:nan_x_preferred":[
        "Kaly"
    ],
    "name:nld_x_preferred":[
        "Kaly"
    ],
    "name:pol_x_preferred":[
        "Kaly"
    ],
    "name:por_x_preferred":[
        "Kaly"
    ],
    "name:rup_x_preferred":[
        "Kaly"
    ],
    "name:slk_x_preferred":[
        "Kaly"
    ],
    "name:spa_x_preferred":[
        "Kaly"
    ],
    "name:swe_x_preferred":[
        "Kaly"
    ],
    "name:vie_x_preferred":[
        "Kaly"
    ],
    "qs_pg:aaroncc":"CZ",
    "qs_pg:gn_country":"CZ",
    "qs_pg:gn_fcode":"PPL",
    "qs_pg:gn_pop":240,
    "qs_pg:name":"Kaly",
    "qs_pg:name_adm0":"\u010cesk\u00e1 republika",
    "qs_pg:name_adm1":"Kraj Vyso\u010dina",
    "qs_pg:photos_9k":1,
    "qs_pg:photos_9r":1,
    "qs_pg:photos_all":2,
    "qs_pg:photos_sr":0,
    "qs_pg:pop_sr":2,
    "qs_pg:qs_pg_placetype":"locality",
    "qs_pg:qs_pg_placetype_gp":"Town",
    "qs_pg:woe_adm0":23424810,
    "woe:adm0_id":23424810,
    "woe:name_adm0":"\u010cesk\u00e1 republika",
    "woe:name_adm1":"Kraj Vyso\u010dina",
    "woe:placetype":"Town",
    "wof:name":"Kaly",
    "wof:placetype":"locality",
    "wof:population":240
},
  "geometry": {"coordinates":[16.3516,49.37932],"type":"Point"}
}