{
  "type": "Feature",
  "properties": {
    "gn:admin1_code":"89",
    "gn:admin2_code":"0422",
    "gn:asciiname":"Vintirov",
    "gn:cc2":"CZ",
    "gn:country_code":"CZ",
    "gn:dem":343,
    "gn:feature_class":"P",
    "gn:feature_code":"PPL",
    "gn:name":"Vint\u00ed\u0159ov",
    "gn:population":0,
    "gn:timezone":"Europe/Prague",
    "iso:country":"CZ",
    "name:und_x_variant":[
        "Winteritz"
    ],
    "wof:name":"Vintirov",
    "wof:placetype":"locality"
},
  "geometry": {"coordinates":[13.27269,50.30491],"type":"Point"}
}