{
  "type": "Feature",
  "properties": {
    "gn:admin1_code":"85.0",
    "gn:admin2_code":"0805",
    "gn:asciiname":"Jamnice",
    "gn:country_code":"CZ",
    "gn:dem":340,
    "gn:feature_class":"P",
    "gn:feature_code":"PPL",
    "gn:name":"Jamnice",
    "gn:population":0,
    "gn:timezone":"Europe/Prague",
    "iso:country":"CZ",
    "wof:name":"Jamnice",
    "wof:placetype":"locality"
},
  "geometry": {"coordinates":[17.78809,49.96024],"type":"Point"}
}