{
  "type": "Feature",
  "properties": {
    "gn:admin1_code":"84.0",
    "gn:admin2_code":"0711",
    "gn:asciiname":"Pasicka",
    "gn:country_code":"CZ",
    "gn:dem":570,
    "gn:feature_class":"P",
    "gn:feature_code":"PPL",
    "gn:name":"Pas\u00ed\u010dka",
    "gn:population":0,
    "gn:timezone":"Europe/Prague",
    "iso:country":"CZ",
    "name:und_x_variant":[
        "\u0160treitov\u00e1",
        "Pas\u00ed\u010dka"
    ],
    "wof:name":"Pasicka",
    "wof:placetype":"locality"
},
  "geometry": {"coordinates":[17.22586,50.22317],"type":"Point"}
}