{
  "type": "Feature",
  "properties": {
    "gn:admin1_code":"87",
    "gn:admin2_code":"0322",
    "gn:asciiname":"Zelena Lhota",
    "gn:country_code":"CZ",
    "gn:dem":548,
    "gn:feature_class":"P",
    "gn:feature_code":"PPL",
    "gn:name":"Zelen\u00e1 Lhota",
    "gn:population":0,
    "gn:timezone":"Europe/Prague",
    "iso:country":"CZ",
    "name:und_x_variant":[
        "Gr\u00fcn",
        "Zelen\u00e1 Lhota"
    ],
    "wof:name":"Zelena Lhota",
    "wof:placetype":"locality"
},
  "geometry": {"coordinates":[13.17271,49.24258],"type":"Point"}
}