{
  "type": "Feature",
  "properties": {
    "gn:admin1_code":"88.0",
    "gn:admin2_code":"0201",
    "gn:asciiname":"Bukova Lhota",
    "gn:country_code":"CZ",
    "gn:dem":365,
    "gn:feature_class":"P",
    "gn:feature_code":"PPL",
    "gn:name":"Bukov\u00e1 Lhota",
    "gn:population":0,
    "gn:timezone":"Europe/Prague",
    "iso:country":"CZ",
    "name:und_x_variant":[
        "Buchen Lhota",
        "Bukov\u00e1 Lhota"
    ],
    "wof:name":"Bukova Lhota",
    "wof:placetype":"locality"
},
  "geometry": {"coordinates":[14.65154,49.8149],"type":"Point"}
}