{
  "type": "Feature",
  "properties": {
    "gn:admin1_code":"82",
    "gn:admin2_code":"0525",
    "gn:asciiname":"Zvicina",
    "gn:country_code":"CZ",
    "gn:dem":614,
    "gn:feature_class":"P",
    "gn:feature_code":"PPL",
    "gn:name":"Zvi\u010dina",
    "gn:population":0,
    "gn:timezone":"Europe/Prague",
    "iso:country":"CZ",
    "name:und_x_variant":[
        "Switschin",
        "Zvi\u010dina"
    ],
    "wof:name":"Zvicina",
    "wof:placetype":"locality"
},
  "geometry": {"coordinates":[15.68635,50.45595],"type":"Point"}
}