{
  "type": "Feature",
  "properties": {
    "gn:country":"CZ",
    "gn:fcode":"PPL",
    "gn:population":73,
    "iso:country":"CZ",
    "name:ceb_x_preferred":[
        "Urbanice"
    ],
    "name:ces_x_preferred":[
        "Urbanice"
    ],
    "name:deu_x_preferred":[
        "Urbanice"
    ],
    "name:epo_x_preferred":[
        "Urbanice"
    ],
    "name:fra_x_preferred":[
        "Urbanice"
    ],
    "name:ita_x_preferred":[
        "Urbanice"
    ],
    "name:nld_x_preferred":[
        "Urbanice"
    ],
    "name:slk_x_preferred":[
        "Urbanice"
    ],
    "name:srp_x_preferred":[
        "\u0423\u0440\u0431\u0430\u045a\u0438\u0446\u0435"
    ],
    "name:swe_x_preferred":[
        "Urbanice"
    ],
    "qs_pg:aaroncc":"CZ",
    "qs_pg:gn_country":"CZ",
    "qs_pg:gn_fcode":"PPL",
    "qs_pg:gn_pop":73,
    "qs_pg:name":"Urbanice",
    "qs_pg:photos_9r":0,
    "qs_pg:photos_sr":0,
    "qs_pg:pop_sr":1,
    "qs_pg:qs_pg_placetype":"locality",
    "wof:name":"Urbanice",
    "wof:placetype":"locality",
    "wof:population":73
},
  "geometry": {"coordinates":[15.56701,49.97394],"type":"Point"}
}