{
  "type": "Feature",
  "properties": {
    "gn:admin1_code":"79.0",
    "gn:admin2_code":"0315",
    "gn:asciiname":"Libotyne",
    "gn:country_code":"CZ",
    "gn:dem":697,
    "gn:feature_class":"P",
    "gn:feature_code":"PPL",
    "gn:name":"Libotyn\u011b",
    "gn:population":0,
    "gn:timezone":"Europe/Prague",
    "iso:country":"CZ",
    "wof:name":"Libotyne",
    "wof:placetype":"locality"
},
  "geometry": {"coordinates":[13.89572,49.08144],"type":"Point"}
}