{
  "type": "Feature",
  "properties": {
    "gn:gn_country":"CZ",
    "gn:gn_fcode":"PPL",
    "gn:gn_pop":172,
    "gn:population":172,
    "iso:country":"CZ",
    "name:azb_x_preferred":[
        "\u0633\u0648\u0633\u062f\u0644\u06cc\u062a\u0633\u0647"
    ],
    "name:ceb_x_preferred":[
        "Sv\u00e9sedlice"
    ],
    "name:ces_x_preferred":[
        "Sv\u00e9sedlice"
    ],
    "name:deu_x_preferred":[
        "Sv\u00e9sedlice"
    ],
    "name:eng_x_preferred":[
        "Sv\u00e9sedlice"
    ],
    "name:eus_x_preferred":[
        "Sv\u00e9sedlice"
    ],
    "name:fas_x_preferred":[
        "\u0633\u0648\u0633\u062f\u0644\u06cc\u062a\u0633\u0647"
    ],
    "name:fra_x_preferred":[
        "Sv\u00e9sedlice"
    ],
    "name:hun_x_preferred":[
        "Sv\u00e9sedlice"
    ],
    "name:ita_x_preferred":[
        "Sv\u00e9sedlice"
    ],
    "name:msa_x_preferred":[
        "Sv\u00e9sedlice"
    ],
    "name:nan_x_preferred":[
        "Sv\u00e9sedlice"
    ],
    "name:nld_x_preferred":[
        "Sv\u00e9sedlice"
    ],
    "name:pol_x_preferred":[
        "Sv\u00e9sedlice"
    ],
    "name:por_x_preferred":[
        "Sv\u00e9sedlice"
    ],
    "name:rup_x_preferred":[
        "Sv\u00e9sedlice"
    ],
    "name:slk_x_preferred":[
        "Sv\u00e9sedlice"
    ],
    "name:spa_x_preferred":[
        "Sv\u00e9sedlice"
    ],
    "name:srp_x_preferred":[
        "\u0421\u0432\u0435\u0441\u0435\u0434\u043b\u0438\u0446\u0435"
    ],
    "name:swe_x_preferred":[
        "Sv\u00e9sedlice"
    ],
    "name:vie_x_preferred":[
        "Sv\u00e9sedlice"
    ],
    "qs_pg:aaroncc":"CZ",
    "qs_pg:gn_country":"CZ",
    "qs_pg:gn_fcode":"PPL",
    "qs_pg:gn_pop":172,
    "qs_pg:name":"Sv\u00e9sedlice",
    "qs_pg:name_adm0":"\u010cesk\u00e1 republika",
    "qs_pg:name_adm1":"Olomouck\u00fd kraj",
    "qs_pg:photos_9r":0,
    "qs_pg:photos_sr":0,
    "qs_pg:pop_sr":1,
    "qs_pg:qs_pg_placetype":"locality",
    "qs_pg:qs_pg_placetype_gp":"Town",
    "qs_pg:woe_adm0":23424810,
    "woe:adm0_id":23424810,
    "woe:name_adm0":"\u010cesk\u00e1 republika",
    "woe:name_adm1":"Olomouck\u00fd kraj",
    "woe:placetype":"Town",
    "wof:name":"Sv\u00e9sedlice",
    "wof:placetype":"locality",
    "wof:population":172
},
  "geometry": {"coordinates":[17.38003,49.57282],"type":"Point"}
}