{
  "type": "Feature",
  "properties": {
    "gn:admin1_code":"81",
    "gn:admin2_code":"0412",
    "gn:asciiname":"Treboun",
    "gn:country_code":"CZ",
    "gn:dem":692,
    "gn:feature_class":"P",
    "gn:feature_code":"PPL",
    "gn:name":"T\u0159ebou\u0148",
    "gn:population":0,
    "gn:timezone":"Europe/Prague",
    "iso:country":"CZ",
    "name:und_x_variant":[
        "Tschebon",
        "T\u0159ebou\u0148"
    ],
    "wof:name":"Treboun",
    "wof:placetype":"locality"
},
  "geometry": {"coordinates":[13.01289,50.0234],"type":"Point"}
}