{
  "type": "Feature",
  "properties": {
    "gn:admin1_code":"79.0",
    "gn:admin2_code":"0313",
    "gn:asciiname":"Horni Radikov",
    "gn:country_code":"CZ",
    "gn:dem":596,
    "gn:feature_class":"P",
    "gn:feature_code":"PPL",
    "gn:name":"Horn\u00ed Rad\u00edkov",
    "gn:population":0,
    "gn:timezone":"Europe/Prague",
    "iso:country":"CZ",
    "name:und_x_variant":[
        "Ober Radisch",
        "Horn\u00ed Rad\u00edkov"
    ],
    "wof:name":"Horni Radikov",
    "wof:placetype":"locality"
},
  "geometry": {"coordinates":[15.28669,49.08491],"type":"Point"}
}