{
  "type": "Feature",
  "properties": {
    "gn:admin1_code":"79",
    "gn:admin2_code":"0316",
    "gn:asciiname":"Ujezd u Skalican",
    "gn:country_code":"CZ",
    "gn:dem":476,
    "gn:feature_class":"P",
    "gn:feature_code":"PPL",
    "gn:name":"\u00dajezd u Skali\u010dan",
    "gn:population":0,
    "gn:timezone":"Europe/Prague",
    "iso:country":"CZ",
    "wof:name":"Ujezd u Skalican",
    "wof:placetype":"locality"
},
  "geometry": {"coordinates":[13.92433,49.45219],"type":"Point"}
}