{
  "type": "Feature",
  "properties": {
    "gn:gn_country":"CZ",
    "gn:gn_fcode":"PPL",
    "gn:gn_pop":106,
    "gn:population":106,
    "iso:country":"CZ",
    "name:azb_x_preferred":[
        "\u0648\u0631\u0627\u062a\u0646\u0648"
    ],
    "name:ceb_x_preferred":[
        "Vr\u00e1tno"
    ],
    "name:ces_x_preferred":[
        "Vr\u00e1tno"
    ],
    "name:eng_x_preferred":[
        "Vr\u00e1tno"
    ],
    "name:eus_x_preferred":[
        "Vr\u00e1tno"
    ],
    "name:fas_x_preferred":[
        "\u0648\u0631\u0627\u062a\u0646\u0648"
    ],
    "name:fra_x_preferred":[
        "Vr\u00e1tno"
    ],
    "name:hun_x_preferred":[
        "Vr\u00e1tno"
    ],
    "name:ita_x_preferred":[
        "Vr\u00e1tno"
    ],
    "name:msa_x_preferred":[
        "Vr\u00e1tno"
    ],
    "name:nan_x_preferred":[
        "Vr\u00e1tno"
    ],
    "name:nld_x_preferred":[
        "Vr\u00e1tno"
    ],
    "name:pol_x_preferred":[
        "Vr\u00e1tno"
    ],
    "name:por_x_preferred":[
        "Vr\u00e1tno"
    ],
    "name:rus_x_preferred":[
        "\u0412\u0440\u0430\u0442\u043d\u043e"
    ],
    "name:slk_x_preferred":[
        "Vr\u00e1tno"
    ],
    "name:spa_x_preferred":[
        "Vr\u00e1tno"
    ],
    "name:srp_x_preferred":[
        "\u0412\u0440\u0430\u0442\u043d\u043e"
    ],
    "name:swe_x_preferred":[
        "Vr\u00e1tno"
    ],
    "name:vie_x_preferred":[
        "Vr\u00e1tno"
    ],
    "qs_pg:aaroncc":"CZ",
    "qs_pg:gn_country":"CZ",
    "qs_pg:gn_fcode":"PPL",
    "qs_pg:gn_pop":106,
    "qs_pg:name":"Vr\u00e1tno",
    "qs_pg:name_adm0":"\u010cesk\u00e1 republika",
    "qs_pg:name_adm1":"St\u0159edo\u010desk\u00fd kraj",
    "qs_pg:photos_9r":0,
    "qs_pg:photos_sr":0,
    "qs_pg:pop_sr":1,
    "qs_pg:qs_pg_placetype":"locality",
    "qs_pg:qs_pg_placetype_gp":"Town",
    "qs_pg:woe_adm0":23424810,
    "woe:adm0_id":23424810,
    "woe:name_adm0":"\u010cesk\u00e1 republika",
    "woe:name_adm1":"St\u0159edo\u010desk\u00fd kraj",
    "woe:placetype":"Town",
    "wof:name":"Vr\u00e1tno",
    "wof:placetype":"locality",
    "wof:population":106
},
  "geometry": {"coordinates":[14.69359,50.4326],"type":"Point"}
}