{
  "type": "Feature",
  "properties": {
    "gn:admin1_code":"78.0",
    "gn:admin2_code":"0627",
    "gn:asciiname":"Jazovice",
    "gn:country_code":"CZ",
    "gn:dem":435,
    "gn:feature_class":"P",
    "gn:feature_code":"PPL",
    "gn:name":"Jazovice",
    "gn:population":0,
    "gn:timezone":"Europe/Prague",
    "iso:country":"CZ",
    "wof:name":"Jazovice",
    "wof:placetype":"locality"
},
  "geometry": {"coordinates":[15.74349,48.89931],"type":"Point"}
}