{
  "type": "Feature",
  "properties": {
    "gn:admin1_code":"88",
    "gn:admin2_code":"0202",
    "gn:asciiname":"Vystrkov",
    "gn:country_code":"CZ",
    "gn:dem":375,
    "gn:feature_class":"P",
    "gn:feature_code":"PPL",
    "gn:name":"Vystrkov",
    "gn:population":0,
    "gn:timezone":"Europe/Prague",
    "iso:country":"CZ",
    "name:azb_x_preferred":[
        "\u0648\u06cc\u0633\u062a\u0631\u06a9\u0648\u0641"
    ],
    "name:ceb_x_preferred":[
        "Vystrkov"
    ],
    "name:ces_x_preferred":[
        "Vystrkov"
    ],
    "name:deu_x_preferred":[
        "Vystrkov"
    ],
    "name:eus_x_preferred":[
        "Vystrkov"
    ],
    "name:fas_x_preferred":[
        "\u0648\u06cc\u0633\u062a\u0631\u06a9\u0648\u0641"
    ],
    "name:fra_x_preferred":[
        "Vystrkov"
    ],
    "name:hsb_x_preferred":[
        "Vystrkov"
    ],
    "name:hun_x_preferred":[
        "Vystrkov"
    ],
    "name:ita_x_preferred":[
        "Vystrkov"
    ],
    "name:msa_x_preferred":[
        "Vystrkov"
    ],
    "name:nld_x_preferred":[
        "Vystrkov"
    ],
    "name:por_x_preferred":[
        "Vystrkov"
    ],
    "name:slk_x_preferred":[
        "Vystrkov"
    ],
    "name:spa_x_preferred":[
        "Vystrkov"
    ],
    "name:srp_x_preferred":[
        "\u0412\u0438\u0441\u0442\u0440\u043a\u043e\u0432"
    ],
    "name:swe_x_preferred":[
        "Vystrkov"
    ],
    "name:szl_x_preferred":[
        "Vystrkov"
    ],
    "name:vie_x_preferred":[
        "Vystrkov"
    ],
    "wof:name":"Vystrkov",
    "wof:placetype":"locality"
},
  "geometry": {"coordinates":[13.87337,49.82431],"type":"Point"}
}