{
  "type": "Feature",
  "properties": {
    "gn:admin1_code":"88",
    "gn:admin2_code":"0202",
    "gn:asciiname":"Vystrkov",
    "gn:country_code":"CZ",
    "gn:dem":375,
    "gn:feature_class":"P",
    "gn:feature_code":"PPL",
    "gn:name":"Vystrkov",
    "gn:population":0,
    "gn:timezone":"Europe/Prague",
    "iso:country":"CZ",
    "wof:name":"Vystrkov",
    "wof:placetype":"locality"
},
  "geometry": {"coordinates":[13.87337,49.82431],"type":"Point"}
}