{
  "type": "Feature",
  "properties": {
    "gn:admin1_code":"88.0",
    "gn:admin2_code":"0204",
    "gn:asciiname":"Miskovice",
    "gn:country_code":"CZ",
    "gn:dem":229,
    "gn:feature_class":"P",
    "gn:feature_code":"PPL",
    "gn:name":"Mi\u0161kovice",
    "gn:population":0,
    "gn:timezone":"Europe/Prague",
    "iso:country":"CZ",
    "name:ceb_x_preferred":[
        "Miskovice"
    ],
    "name:ces_x_preferred":[
        "Miskovice"
    ],
    "name:eus_x_preferred":[
        "Miskovice"
    ],
    "name:fra_x_preferred":[
        "Miskovice"
    ],
    "name:hun_x_preferred":[
        "Miskovice"
    ],
    "name:ita_x_preferred":[
        "Miskovice"
    ],
    "name:msa_x_preferred":[
        "Miskovice"
    ],
    "name:nld_x_preferred":[
        "Miskovice"
    ],
    "name:pol_x_preferred":[
        "Miskovice"
    ],
    "name:por_x_preferred":[
        "Miskovice"
    ],
    "name:slk_x_preferred":[
        "Miskovice"
    ],
    "name:spa_x_preferred":[
        "Miskovice"
    ],
    "name:srp_x_preferred":[
        "\u041c\u0438\u0441\u043a\u043e\u0432\u0438\u0446\u0435"
    ],
    "name:vie_x_preferred":[
        "Miskovice"
    ],
    "wof:name":"Miskovice",
    "wof:placetype":"locality"
},
  "geometry": {"coordinates":[14.99368,50.03495],"type":"Point"}
}