{
  "type": "Feature",
  "properties": {
    "gn:admin1_code":"88.0",
    "gn:admin2_code":"0204",
    "gn:asciiname":"Miskovice",
    "gn:country_code":"CZ",
    "gn:dem":229,
    "gn:feature_class":"P",
    "gn:feature_code":"PPL",
    "gn:name":"Mi\u0161kovice",
    "gn:population":0,
    "gn:timezone":"Europe/Prague",
    "iso:country":"CZ",
    "wof:name":"Miskovice",
    "wof:placetype":"locality"
},
  "geometry": {"coordinates":[14.99368,50.03495],"type":"Point"}
}