{
  "type": "Feature",
  "properties": {
    "gn:admin1_code":"86",
    "gn:admin2_code":"0533",
    "gn:asciiname":"Tremosna",
    "gn:country_code":"CZ",
    "gn:dem":519,
    "gn:feature_class":"P",
    "gn:feature_code":"PPL",
    "gn:name":"T\u0159emo\u0161n\u00e1",
    "gn:population":0,
    "gn:timezone":"Europe/Prague",
    "iso:country":"CZ",
    "wof:name":"Tremosna",
    "wof:placetype":"locality"
},
  "geometry": {"coordinates":[16.25907,49.76578],"type":"Point"}
}