{
  "type": "Feature",
  "properties": {
    "gn:admin1_code":"88.0",
    "gn:admin2_code":"0201",
    "gn:asciiname":"Kahlovice",
    "gn:country_code":"CZ",
    "gn:dem":542,
    "gn:feature_class":"P",
    "gn:feature_code":"PPL",
    "gn:name":"Kahlovice",
    "gn:population":0,
    "gn:timezone":"Europe/Prague",
    "iso:country":"CZ",
    "wof:name":"Kahlovice",
    "wof:placetype":"locality"
},
  "geometry": {"coordinates":[14.71946,49.56402],"type":"Point"}
}