{
  "type": "Feature",
  "properties": {
    "gn:admin1_code":"78",
    "gn:admin2_code":"0622",
    "gn:asciiname":"Utechov",
    "gn:country_code":"CZ",
    "gn:dem":461,
    "gn:feature_class":"P",
    "gn:feature_code":"PPL",
    "gn:name":"\u00dat\u011bchov",
    "gn:population":0,
    "gn:timezone":"Europe/Prague",
    "iso:country":"CZ",
    "wof:name":"Utechov",
    "wof:placetype":"locality"
},
  "geometry": {"coordinates":[16.63073,49.28707],"type":"Point"}
}