{
  "type": "Feature",
  "properties": {
    "gn:admin1_code":"79.0",
    "gn:admin2_code":"0313",
    "gn:asciiname":"Krabonos",
    "gn:country_code":"CZ",
    "gn:dem":484,
    "gn:feature_class":"P",
    "gn:feature_code":"PPL",
    "gn:name":"Krabono\u0161",
    "gn:population":0,
    "gn:timezone":"Europe/Prague",
    "iso:country":"CZ",
    "name:und_x_variant":[
        "Zuggers",
        "Krabono\u0161"
    ],
    "wof:name":"Krabonos",
    "wof:placetype":"locality"
},
  "geometry": {"coordinates":[14.94736,48.8066],"type":"Point"}
}