{
  "type": "Feature",
  "properties": {
    "gn:admin1_code":"86.0",
    "gn:admin2_code":"0532",
    "gn:asciiname":"Luhy",
    "gn:country_code":"CZ",
    "gn:dem":233,
    "gn:feature_class":"P",
    "gn:feature_code":"PPL",
    "gn:name":"Luhy",
    "gn:population":0,
    "gn:timezone":"Europe/Prague",
    "iso:country":"CZ",
    "name:und_x_variant":[
        "Dv\u016dr Luhy",
        "Luhy"
    ],
    "wof:name":"Luhy",
    "wof:placetype":"locality"
},
  "geometry": {"coordinates":[15.64195,49.99722],"type":"Point"}
}