{
  "type": "Feature",
  "properties": {
    "gn:admin1_code":"80.0",
    "gn:admin2_code":"0612",
    "gn:asciiname":"Kamenicka",
    "gn:country_code":"CZ",
    "gn:dem":572,
    "gn:feature_class":"P",
    "gn:feature_code":"PPL",
    "gn:name":"Kameni\u010dka",
    "gn:population":0,
    "gn:timezone":"Europe/Prague",
    "iso:country":"CZ",
    "wof:name":"Kamenicka",
    "wof:placetype":"locality"
},
  "geometry": {"coordinates":[15.802,49.37265],"type":"Point"}
}