{
  "type": "Feature",
  "properties": {
    "gn:admin1_code":"79.0",
    "gn:admin2_code":"0312",
    "gn:asciiname":"Brezovice",
    "gn:country_code":"CZ",
    "gn:dem":731,
    "gn:feature_class":"P",
    "gn:feature_code":"PPL",
    "gn:name":"B\u0159ezovice",
    "gn:population":0,
    "gn:timezone":"Europe/Prague",
    "iso:country":"CZ",
    "name:und_x_variant":[
        "Prislowitz",
        "B\u0159ezovice"
    ],
    "wof:name":"Brezovice",
    "wof:placetype":"locality"
},
  "geometry": {"coordinates":[14.23729,48.66224],"type":"Point"}
}