{
  "type": "Feature",
  "properties": {
    "gn:gn_country":"CZ",
    "gn:gn_fcode":"PPL",
    "gn:gn_pop":86,
    "gn:population":86,
    "iso:country":"CZ",
    "name:ces_x_preferred":[
        "Budkov"
    ],
    "name:deu_x_preferred":[
        "Budkov u Husince"
    ],
    "name:eng_x_preferred":[
        "Budkov"
    ],
    "name:fas_x_preferred":[
        "\u0628\u0648\u062f\u06a9\u0648\u0641"
    ],
    "name:fra_x_preferred":[
        "Budkov"
    ],
    "name:hun_x_preferred":[
        "Budkov"
    ],
    "name:ita_x_preferred":[
        "Budkov"
    ],
    "name:msa_x_preferred":[
        "Budkov"
    ],
    "name:nan_x_preferred":[
        "Budkov"
    ],
    "name:nld_x_preferred":[
        "Budkov"
    ],
    "name:por_x_preferred":[
        "Budkov"
    ],
    "name:rup_x_preferred":[
        "Budkov"
    ],
    "name:slk_x_preferred":[
        "Budkov"
    ],
    "name:srp_x_preferred":[
        "\u0411\u0443\u0442\u043a\u043e\u0432"
    ],
    "name:vie_x_preferred":[
        "Budkov"
    ],
    "qs_pg:aaroncc":"CZ",
    "qs_pg:gn_country":"CZ",
    "qs_pg:gn_fcode":"PPL",
    "qs_pg:gn_pop":86,
    "qs_pg:name":"Budkov",
    "qs_pg:name_adm0":"\u010cesk\u00e1 republika",
    "qs_pg:name_adm1":"Jiho\u010desk\u00fd kraj",
    "qs_pg:photos_9r":0,
    "qs_pg:photos_sr":0,
    "qs_pg:pop_sr":1,
    "qs_pg:qs_pg_placetype":"locality",
    "qs_pg:qs_pg_placetype_gp":"Town",
    "qs_pg:woe_adm0":23424810,
    "woe:adm0_id":23424810,
    "woe:name_adm0":"\u010cesk\u00e1 republika",
    "woe:name_adm1":"Jiho\u010desk\u00fd kraj",
    "woe:placetype":"Town",
    "wof:name":"Budkov",
    "wof:placetype":"locality",
    "wof:population":86
},
  "geometry": {"coordinates":[14.00697,49.07005],"type":"Point"}
}