{
  "type": "Feature",
  "properties": {
    "gn:admin1_code":"79.0",
    "gn:admin2_code":"0313",
    "gn:asciiname":"Matejovec",
    "gn:country_code":"CZ",
    "gn:dem":652,
    "gn:feature_class":"P",
    "gn:feature_code":"PPL",
    "gn:name":"Mat\u011bjovec",
    "gn:population":0,
    "gn:timezone":"Europe/Prague",
    "iso:country":"CZ",
    "name:und_x_variant":[
        "Modes",
        "Mat\u011bjovec"
    ],
    "wof:name":"Matejovec",
    "wof:placetype":"locality"
},
  "geometry": {"coordinates":[15.26696,49.06164],"type":"Point"}
}