{
  "type": "Feature",
  "properties": {
    "gn:country":"CZ",
    "gn:fcode":"PPL",
    "gn:population":219,
    "iso:country":"CZ",
    "name:azb_x_preferred":[
        "\u0628\u06cc\u062e\u0627\u0631\u06cc"
    ],
    "name:cat_x_preferred":[
        "B\u011bchary"
    ],
    "name:ceb_x_preferred":[
        "B\u011bchary"
    ],
    "name:ces_x_preferred":[
        "B\u011bchary"
    ],
    "name:che_x_preferred":[
        "\u0411\u0435\u0445\u0430\u0440\u0438"
    ],
    "name:deu_x_preferred":[
        "B\u011bchary"
    ],
    "name:eng_x_preferred":[
        "B\u011bchary"
    ],
    "name:eus_x_preferred":[
        "B\u011bchary"
    ],
    "name:fas_x_preferred":[
        "\u0628\u06cc\u062e\u0627\u0631\u06cc"
    ],
    "name:fra_x_preferred":[
        "B\u011bchary"
    ],
    "name:gle_x_preferred":[
        "B\u011bchary"
    ],
    "name:hun_x_preferred":[
        "B\u011bchary"
    ],
    "name:ita_x_preferred":[
        "B\u011bchary"
    ],
    "name:lmo_x_preferred":[
        "B\u011bchary"
    ],
    "name:msa_x_preferred":[
        "B\u011bchary"
    ],
    "name:nan_x_preferred":[
        "B\u011bchary"
    ],
    "name:nld_x_preferred":[
        "B\u011bchary"
    ],
    "name:pol_x_preferred":[
        "B\u011bchary"
    ],
    "name:por_x_preferred":[
        "B\u011bchary"
    ],
    "name:rup_x_preferred":[
        "B\u011bchary"
    ],
    "name:slk_x_preferred":[
        "B\u011bchary"
    ],
    "name:spa_x_preferred":[
        "B\u011bchary"
    ],
    "name:srp_x_preferred":[
        "\u0411\u0458\u0435\u0445\u0430\u0440\u0438"
    ],
    "name:swe_x_preferred":[
        "B\u011bchary"
    ],
    "name:tat_x_preferred":[
        "\u0411\u0435\u0445\u0430\u0440\u0438"
    ],
    "name:und_x_variant":[
        "Gross B\u011bchar"
    ],
    "name:vie_x_preferred":[
        "B\u011bchary"
    ],
    "qs_pg:aaroncc":"CZ",
    "qs_pg:gn_country":"CZ",
    "qs_pg:gn_fcode":"PPL",
    "qs_pg:gn_pop":219,
    "qs_pg:name":"B\u011bchary",
    "qs_pg:name_adm0":"\u010cesk\u00e1 republika",
    "qs_pg:name_adm1":"Kr\u00e1lov\u00e9hradeck\u00fd kraj",
    "qs_pg:photos_9r":0,
    "qs_pg:photos_sr":0,
    "qs_pg:pop_sr":2,
    "qs_pg:qs_pg_placetype":"locality",
    "qs_pg:qs_pg_placetype_gp":"Town",
    "qs_pg:woe_adm0":23424810,
    "woe:adm0_id":23424810,
    "woe:name_adm0":"\u010cesk\u00e1 republika",
    "woe:name_adm1":"Kr\u00e1lov\u00e9hradeck\u00fd kraj",
    "woe:placetype":"Town",
    "wof:name":"B\u011bchary",
    "wof:placetype":"locality",
    "wof:population":219
},
  "geometry": {"coordinates":[15.29251,50.31403],"type":"Point"}
}