{
  "type": "Feature",
  "properties": {
    "iso:country":"CZ",
    "name:azb_x_preferred":[
        "\u0646\u0648\u0648\u0627 \u0648\u0633 \u0627\u06cc"
    ],
    "name:ces_x_preferred":[
        "Nov\u00e1 Ves"
    ],
    "name:deu_x_preferred":[
        "Nov\u00e1 Ves"
    ],
    "name:eus_x_preferred":[
        "Nov\u00e1 Ves"
    ],
    "name:fas_x_preferred":[
        "\u0646\u0648\u0648\u0627 \u0648\u0633 \u0627\u06cc"
    ],
    "name:fra_x_preferred":[
        "Nov\u00e1 Ves"
    ],
    "name:hun_x_preferred":[
        "Nov\u00e1 Ves"
    ],
    "name:ita_x_preferred":[
        "Nov\u00e1 Ves"
    ],
    "name:msa_x_preferred":[
        "Nov\u00e1 Ves"
    ],
    "name:nld_x_preferred":[
        "Nov\u00e1 Ves"
    ],
    "name:pol_x_preferred":[
        "Nov\u00e1 Ves"
    ],
    "name:por_x_preferred":[
        "Nov\u00e1 Ves"
    ],
    "name:slk_x_preferred":[
        "Nov\u00e1 Ves"
    ],
    "name:spa_x_preferred":[
        "Nov\u00e1 Ves"
    ],
    "name:srp_x_preferred":[
        "\u041d\u043e\u0432\u0430 \u0412\u0435\u0441"
    ],
    "name:vie_x_preferred":[
        "Nov\u00e1 Ves"
    ],
    "qs_pg:aaroncc":"CZ",
    "qs_pg:name":"Nov\u00e1 Ves I",
    "qs_pg:name_adm0":"\u010cesk\u00e1 republika",
    "qs_pg:name_adm1":"St\u0159edo\u010desk\u00fd kraj",
    "qs_pg:photos":1,
    "qs_pg:photos_1k":1,
    "qs_pg:photos_9k":1,
    "qs_pg:photos_9r":1,
    "qs_pg:photos_all":22,
    "qs_pg:photos_sr":1,
    "qs_pg:pop_sr":0,
    "qs_pg:qs_pg_placetype":"localadmin",
    "qs_pg:qs_pg_placetype_gp":"LocalAdmin",
    "qs_pg:woe_adm0":23424810,
    "woe:adm0_id":23424810,
    "woe:name_adm0":"\u010cesk\u00e1 republika",
    "woe:name_adm1":"St\u0159edo\u010desk\u00fd kraj",
    "woe:placetype":"LocalAdmin",
    "wof:name":"Nov\u00e1 Ves I",
    "wof:placetype":"localadmin"
},
  "geometry": {"coordinates":[15.140876,50.060665],"type":"Point"}
}