{
  "type": "Feature",
  "properties": {
    "gn:admin1_code":"80.0",
    "gn:admin2_code":"0613",
    "gn:asciiname":"Ostrovec",
    "gn:country_code":"CZ",
    "gn:dem":617,
    "gn:feature_class":"P",
    "gn:feature_code":"PPL",
    "gn:name":"Ostrovec",
    "gn:population":0,
    "gn:timezone":"Europe/Prague",
    "iso:country":"CZ",
    "name:azb_x_preferred":[
        "\u0627\u0648\u0633\u062a\u0631\u0648\u0648\u062a\u0633"
    ],
    "name:ces_x_preferred":[
        "Ostrovec"
    ],
    "name:eus_x_preferred":[
        "Ostrovec"
    ],
    "name:fas_x_preferred":[
        "\u0627\u0648\u0633\u062a\u0631\u0648\u0648\u062a\u0633"
    ],
    "name:fra_x_preferred":[
        "Ostrovec"
    ],
    "name:hun_x_preferred":[
        "Ostrovec"
    ],
    "name:ita_x_preferred":[
        "Ostrovec"
    ],
    "name:msa_x_preferred":[
        "Ostrovec"
    ],
    "name:nld_x_preferred":[
        "Ostrovec"
    ],
    "name:por_x_preferred":[
        "Ostrovec"
    ],
    "name:slk_x_preferred":[
        "Ostrovec"
    ],
    "name:spa_x_preferred":[
        "Ostrovec"
    ],
    "name:srp_x_preferred":[
        "\u041e\u0441\u0442\u0440\u043e\u0432\u0435\u0446"
    ],
    "name:vie_x_preferred":[
        "Ostrovec"
    ],
    "wof:name":"Ostrovec",
    "wof:placetype":"locality"
},
  "geometry": {"coordinates":[15.25907,49.33254],"type":"Point"}
}