{
  "type": "Feature",
  "properties": {
    "gn:admin1_code":"87.0",
    "gn:admin2_code":"0327",
    "gn:asciiname":"Muckov",
    "gn:country_code":"CZ",
    "gn:dem":502,
    "gn:feature_class":"P",
    "gn:feature_code":"PPL",
    "gn:name":"Muckov",
    "gn:population":0,
    "gn:timezone":"Europe/Prague",
    "iso:country":"CZ",
    "name:und_x_variant":[
        "Mutzken",
        "Muckov"
    ],
    "wof:name":"Muckov",
    "wof:placetype":"locality"
},
  "geometry": {"coordinates":[12.73943,49.69146],"type":"Point"}
}