{
  "type": "Feature",
  "properties": {
    "gn:admin1_code":"88.0",
    "gn:admin2_code":"0205",
    "gn:asciiname":"Bykan",
    "gn:country_code":"CZ",
    "gn:dem":371,
    "gn:feature_class":"P",
    "gn:feature_code":"PPL",
    "gn:name":"Byk\u00e1\u0148",
    "gn:population":0,
    "gn:timezone":"Europe/Prague",
    "iso:country":"CZ",
    "wof:name":"Bykan",
    "wof:placetype":"locality"
},
  "geometry": {"coordinates":[15.24509,49.89835],"type":"Point"}
}