{
  "type": "Feature",
  "properties": {
    "gn:gn_country":"CZ",
    "gn:gn_fcode":"PPL",
    "gn:gn_pop":85,
    "gn:population":85,
    "iso:country":"CZ",
    "name:ceb_x_preferred":[
        "Kobylnice"
    ],
    "name:ces_x_preferred":[
        "Kobylnice"
    ],
    "name:deu_x_preferred":[
        "Kobylnice"
    ],
    "name:epo_x_preferred":[
        "Kobylnice"
    ],
    "name:eus_x_preferred":[
        "Kobylnice"
    ],
    "name:fra_x_preferred":[
        "Kobylnice"
    ],
    "name:ita_x_preferred":[
        "Kobylnice"
    ],
    "name:nld_x_preferred":[
        "Kobylnice"
    ],
    "name:pol_x_preferred":[
        "Kobylnice"
    ],
    "name:slk_x_preferred":[
        "Kobylnice"
    ],
    "name:srp_x_preferred":[
        "\u041a\u043e\u0431\u0438\u043b\u045a\u0438\u0446\u0435"
    ],
    "name:swe_x_preferred":[
        "Kobylnice"
    ],
    "qs_pg:aaroncc":"CZ",
    "qs_pg:gn_country":"CZ",
    "qs_pg:gn_fcode":"PPL",
    "qs_pg:gn_pop":85,
    "qs_pg:name":"Kobylnice",
    "qs_pg:name_adm0":"\u010cesk\u00e1 republika",
    "qs_pg:name_adm1":"St\u0159edo\u010desk\u00fd kraj",
    "qs_pg:photos_9r":0,
    "qs_pg:photos_sr":0,
    "qs_pg:pop_sr":1,
    "qs_pg:qs_pg_placetype":"locality",
    "qs_pg:qs_pg_placetype_gp":"Town",
    "qs_pg:woe_adm0":23424810,
    "woe:adm0_id":23424810,
    "woe:name_adm0":"\u010cesk\u00e1 republika",
    "woe:name_adm1":"St\u0159edo\u010desk\u00fd kraj",
    "woe:placetype":"Town",
    "wof:name":"Kobylnice",
    "wof:placetype":"locality",
    "wof:population":85
},
  "geometry": {"coordinates":[15.05386,50.37164],"type":"Point"}
}