{
  "type": "Feature",
  "properties": {
    "gn:gn_country":"CZ",
    "gn:gn_fcode":"PPL",
    "gn:gn_pop":823,
    "gn:population":823,
    "iso:country":"CZ",
    "name:ces_x_preferred":[
        "Tlustice"
    ],
    "name:eng_x_preferred":[
        "Tlustice"
    ],
    "name:fas_x_preferred":[
        "\u062a\u0644\u0648\u0633\u062a\u06cc\u062a\u0633\u0647"
    ],
    "name:fra_x_preferred":[
        "Tlustice"
    ],
    "name:hun_x_preferred":[
        "Tlustice"
    ],
    "name:ita_x_preferred":[
        "Tlustice"
    ],
    "name:msa_x_preferred":[
        "Tlustice"
    ],
    "name:nld_x_preferred":[
        "Tlustice"
    ],
    "name:pol_x_preferred":[
        "Tlustice"
    ],
    "name:por_x_preferred":[
        "Tlustice"
    ],
    "name:slk_x_preferred":[
        "Tlustice"
    ],
    "name:srp_x_preferred":[
        "\u0422\u043b\u0443\u0441\u0442\u0438\u0446\u0435"
    ],
    "name:swe_x_preferred":[
        "Tlustice"
    ],
    "name:vie_x_preferred":[
        "Tlustice"
    ],
    "qs_pg:aaroncc":"CZ",
    "qs_pg:gn_country":"CZ",
    "qs_pg:gn_fcode":"PPL",
    "qs_pg:gn_pop":823,
    "qs_pg:name":"Tlustice",
    "qs_pg:name_adm0":"\u010cesk\u00e1 republika",
    "qs_pg:name_adm1":"St\u0159edo\u010desk\u00fd kraj",
    "qs_pg:photos_9k":1,
    "qs_pg:photos_9r":1,
    "qs_pg:photos_all":5,
    "qs_pg:photos_sr":0,
    "qs_pg:pop_sr":2,
    "qs_pg:qs_pg_placetype":"locality",
    "qs_pg:qs_pg_placetype_gp":"Town",
    "qs_pg:woe_adm0":23424810,
    "woe:adm0_id":23424810,
    "woe:name_adm0":"\u010cesk\u00e1 republika",
    "woe:name_adm1":"St\u0159edo\u010desk\u00fd kraj",
    "woe:placetype":"Town",
    "wof:name":"Tlustice",
    "wof:placetype":"locality",
    "wof:population":823
},
  "geometry": {"coordinates":[13.88561,49.85003],"type":"Point"}
}