{
  "type": "Feature",
  "properties": {
    "gn:gn_country":"CZ",
    "gn:gn_fcode":"PPL",
    "gn:gn_pop":0,
    "iso:country":"CZ",
    "name:azb_x_preferred":[
        "\u06a9\u0644\u0627\u0634\u062a\u0631"
    ],
    "name:ceb_x_preferred":[
        "Kl\u00e1\u0161ter"
    ],
    "name:ces_x_preferred":[
        "Kl\u00e1\u0161ter"
    ],
    "name:deu_x_preferred":[
        "Kl\u00e1\u0161ter"
    ],
    "name:eus_x_preferred":[
        "Kl\u00e1\u0161ter"
    ],
    "name:fas_x_preferred":[
        "\u06a9\u0644\u0627\u0634\u062a\u0631"
    ],
    "name:hun_x_preferred":[
        "Kl\u00e1\u0161ter"
    ],
    "name:ita_x_preferred":[
        "Kl\u00e1\u0161ter"
    ],
    "name:msa_x_preferred":[
        "Kl\u00e1\u0161ter"
    ],
    "name:nld_x_preferred":[
        "Kl\u00e1\u0161ter"
    ],
    "name:pol_x_preferred":[
        "Kl\u00e1\u0161ter"
    ],
    "name:por_x_preferred":[
        "Kl\u00e1\u0161ter"
    ],
    "name:slk_x_preferred":[
        "Kl\u00e1\u0161ter"
    ],
    "name:spa_x_preferred":[
        "Kl\u00e1\u0161ter"
    ],
    "name:srp_x_preferred":[
        "\u041a\u043b\u0430\u0448\u0442\u0435\u0440"
    ],
    "name:unk_x_variant":[
        "Kloster"
    ],
    "name:vie_x_preferred":[
        "Kl\u00e1\u0161ter"
    ],
    "qs_pg:aaroncc":"CZ",
    "qs_pg:gn_country":"CZ",
    "qs_pg:gn_fcode":"PPL",
    "qs_pg:gn_pop":0,
    "qs_pg:name":"Kl\u00e1\u0161ter",
    "qs_pg:name_adm0":"\u010cesk\u00e1 republika",
    "qs_pg:name_adm1":"Jiho\u010desk\u00fd kraj",
    "qs_pg:photos":26,
    "qs_pg:photos_1k":5,
    "qs_pg:photos_9k":1,
    "qs_pg:photos_9r":2,
    "qs_pg:photos_all":26,
    "qs_pg:photos_sr":2,
    "qs_pg:pop_sr":0,
    "qs_pg:qs_pg_placetype":"locality",
    "qs_pg:qs_pg_placetype_gp":"Town",
    "qs_pg:woe_adm0":23424810,
    "woe:adm0_id":23424810,
    "woe:name_adm0":"\u010cesk\u00e1 republika",
    "woe:name_adm1":"Jiho\u010desk\u00fd kraj",
    "woe:placetype":"Town",
    "wof:name":"Kl\u00e1\u0161ter",
    "wof:placetype":"locality"
},
  "geometry": {"coordinates":[15.1767,49.02454],"type":"Point"}
}