{
  "type": "Feature",
  "properties": {
    "gn:gn_country":"CZ",
    "gn:gn_fcode":"PPL",
    "gn:gn_pop":0,
    "iso:country":"CZ",
    "name:unk_x_variant":[
        "Kloster"
    ],
    "qs_pg:aaroncc":"CZ",
    "qs_pg:gn_country":"CZ",
    "qs_pg:gn_fcode":"PPL",
    "qs_pg:gn_pop":0,
    "qs_pg:name":"Kl\u00e1\u0161ter",
    "qs_pg:name_adm0":"\u010cesk\u00e1 republika",
    "qs_pg:name_adm1":"Jiho\u010desk\u00fd kraj",
    "qs_pg:photos":26,
    "qs_pg:photos_1k":5,
    "qs_pg:photos_9k":1,
    "qs_pg:photos_9r":2,
    "qs_pg:photos_all":26,
    "qs_pg:photos_sr":2,
    "qs_pg:pop_sr":0,
    "qs_pg:qs_pg_placetype":"locality",
    "qs_pg:qs_pg_placetype_gp":"Town",
    "qs_pg:woe_adm0":23424810,
    "woe:adm0_id":23424810,
    "woe:name_adm0":"\u010cesk\u00e1 republika",
    "woe:name_adm1":"Jiho\u010desk\u00fd kraj",
    "woe:placetype":"Town",
    "wof:name":"Kl\u00e1\u0161ter",
    "wof:placetype":"locality"
},
  "geometry": {"coordinates":[15.1767,49.02454],"type":"Point"}
}