{
  "type": "Feature",
  "properties": {
    "gn:admin1_code":"89.0",
    "gn:admin2_code":"0424",
    "gn:asciiname":"Malmerice",
    "gn:country_code":"CZ",
    "gn:dem":404,
    "gn:feature_class":"P",
    "gn:feature_code":"PPL",
    "gn:name":"Malm\u011b\u0159ice",
    "gn:population":0,
    "gn:timezone":"Europe/Prague",
    "iso:country":"CZ",
    "name:und_x_variant":[
        "Alberitz",
        "Malm\u011b\u0159ice"
    ],
    "wof:name":"Malmerice",
    "wof:placetype":"locality"
},
  "geometry": {"coordinates":[13.38485,50.11654],"type":"Point"}
}