{
  "type": "Feature",
  "properties": {
    "gn:admin1_code":"84.0",
    "gn:admin2_code":"0711",
    "gn:asciiname":"Schlippengrund",
    "gn:country_code":"CZ",
    "gn:dem":393,
    "gn:feature_class":"P",
    "gn:feature_code":"PPL",
    "gn:name":"Schlippengrund",
    "gn:population":0,
    "gn:timezone":"Europe/Prague",
    "iso:country":"CZ",
    "wof:name":"Schlippengrund",
    "wof:placetype":"locality"
},
  "geometry": {"coordinates":[17.11667000000001,50.31667],"type":"Point"}
}