{
  "type": "Feature",
  "properties": {
    "gn:gn_country":"CZ",
    "gn:gn_fcode":"PPL",
    "gn:gn_pop":211,
    "gn:population":211,
    "iso:country":"CZ",
    "name:ces_x_preferred":[
        "Rad\u00ed\u010d"
    ],
    "name:eng_x_preferred":[
        "Rad\u00ed\u010d"
    ],
    "name:fas_x_preferred":[
        "\u0631\u0627\u062f\u06cc\u062a\u0634"
    ],
    "name:fra_x_preferred":[
        "Rad\u00ed\u010d"
    ],
    "name:hun_x_preferred":[
        "Rad\u00ed\u010d"
    ],
    "name:ita_x_preferred":[
        "Rad\u00ed\u010d"
    ],
    "name:msa_x_preferred":[
        "Rad\u00ed\u010d"
    ],
    "name:nld_x_preferred":[
        "Rad\u00ed\u010d"
    ],
    "name:por_x_preferred":[
        "Rad\u00ed\u010d"
    ],
    "name:slk_x_preferred":[
        "Rad\u00ed\u010d"
    ],
    "name:srp_x_preferred":[
        "\u0420\u0430\u0434\u0438\u0447"
    ],
    "name:swe_x_preferred":[
        "Rad\u00ed\u010d"
    ],
    "name:vie_x_preferred":[
        "Rad\u00ed\u010d"
    ],
    "qs_pg:aaroncc":"CZ",
    "qs_pg:gn_country":"CZ",
    "qs_pg:gn_fcode":"PPL",
    "qs_pg:gn_pop":211,
    "qs_pg:name":"Rad\u00ed\u010d",
    "qs_pg:name_adm0":"\u010cesk\u00e1 republika",
    "qs_pg:name_adm1":"St\u0159edo\u010desk\u00fd kraj",
    "qs_pg:photos_9k":1,
    "qs_pg:photos_9r":1,
    "qs_pg:photos_all":1,
    "qs_pg:photos_sr":0,
    "qs_pg:pop_sr":2,
    "qs_pg:qs_pg_placetype":"locality",
    "qs_pg:qs_pg_placetype_gp":"Town",
    "qs_pg:woe_adm0":23424810,
    "woe:adm0_id":23424810,
    "woe:name_adm0":"\u010cesk\u00e1 republika",
    "woe:name_adm1":"St\u0159edo\u010desk\u00fd kraj",
    "woe:placetype":"Town",
    "wof:name":"Rad\u00ed\u010d",
    "wof:placetype":"locality",
    "wof:population":211
},
  "geometry": {"coordinates":[14.41739,49.71466],"type":"Point"}
}