{
  "type": "Feature",
  "properties": {
    "gn:gn_country":"CZ",
    "gn:gn_fcode":"PPL",
    "gn:gn_pop":539,
    "gn:population":539,
    "iso:country":"CZ",
    "name:cze_x_preferred":[
        "M\u00e1lkov"
    ],
    "name:dut_x_preferred":[
        "M\u00e1lkov"
    ],
    "name:eng_x_preferred":[
        "M\u00e1lkov"
    ],
    "name:fre_x_preferred":[
        "M\u00e1lkov"
    ],
    "name:ger_x_preferred":[
        "M\u00e1lkov u Chomutova"
    ],
    "name:hun_x_preferred":[
        "M\u00e1lkov"
    ],
    "name:ita_x_preferred":[
        "M\u00e1lkov"
    ],
    "name:may_x_preferred":[
        "M\u00e1lkov"
    ],
    "name:per_x_preferred":[
        "\u0645\u0627\u0644\u06a9\u0648\u0641"
    ],
    "name:pol_x_preferred":[
        "M\u00e1lkov"
    ],
    "name:por_x_preferred":[
        "M\u00e1lkov"
    ],
    "name:rup_x_preferred":[
        "M\u00e1lkov"
    ],
    "name:slo_x_preferred":[
        "M\u00e1lkov"
    ],
    "name:srp_x_preferred":[
        "\u041c\u0430\u043b\u043a\u043e\u0432"
    ],
    "name:swe_x_preferred":[
        "M\u00e1lkov"
    ],
    "name:unk_x_variant":[
        "Malkau"
    ],
    "name:vie_x_preferred":[
        "M\u00e1lkov"
    ],
    "qs_pg:aaroncc":"CZ",
    "qs_pg:gn_country":"CZ",
    "qs_pg:gn_fcode":"PPL",
    "qs_pg:gn_pop":539,
    "qs_pg:name":"M\u00e1lkov",
    "qs_pg:name_adm0":"\u010cesk\u00e1 republika",
    "qs_pg:name_adm1":"\u00dasteck\u00fd kraj",
    "qs_pg:photos_9r":0,
    "qs_pg:photos_sr":0,
    "qs_pg:pop_sr":2,
    "qs_pg:qs_pg_placetype":"locality",
    "qs_pg:qs_pg_placetype_gp":"Town",
    "qs_pg:woe_adm0":23424810,
    "woe:adm0_id":23424810,
    "woe:name_adm0":"\u010cesk\u00e1 republika",
    "woe:name_adm1":"\u00dasteck\u00fd kraj",
    "woe:placetype":"Town",
    "wof:name":"M\u00e1lkov",
    "wof:placetype":"locality",
    "wof:population":539
},
  "geometry": {"coordinates":[13.33338,50.44617],"type":"Point"}
}