{
  "type": "Feature",
  "properties": {
    "gn:gn_country":"CZ",
    "gn:gn_fcode":"PPL",
    "gn:gn_pop":100,
    "gn:population":100,
    "iso:country":"CZ",
    "name:ces_x_preferred":[
        "Sedli\u0161t\u011b"
    ],
    "name:eng_x_preferred":[
        "Sedli\u0161t\u011b"
    ],
    "name:fas_x_preferred":[
        "\u0633\u062f\u0644\u06cc\u0634\u062a\u06cc"
    ],
    "name:fra_x_preferred":[
        "Sedli\u0161t\u011b"
    ],
    "name:hun_x_preferred":[
        "Sedli\u0161t\u011b"
    ],
    "name:ita_x_preferred":[
        "Sedli\u0161t\u011b"
    ],
    "name:msa_x_preferred":[
        "Sedli\u0161t\u011b"
    ],
    "name:nld_x_preferred":[
        "Sedli\u0161t\u011b"
    ],
    "name:pol_x_preferred":[
        "Sedli\u0161t\u011b"
    ],
    "name:por_x_preferred":[
        "Sedli\u0161t\u011b"
    ],
    "name:rup_x_preferred":[
        "Sedli\u0161t\u011b"
    ],
    "name:slk_x_preferred":[
        "Sedli\u0161t\u011b"
    ],
    "name:srp_x_preferred":[
        "\u0421\u0435\u0434\u043b\u0438\u0448\u0442\u0435"
    ],
    "name:vie_x_preferred":[
        "Sedli\u0161t\u011b"
    ],
    "qs_pg:aaroncc":"CZ",
    "qs_pg:gn_country":"CZ",
    "qs_pg:gn_fcode":"PPL",
    "qs_pg:gn_pop":100,
    "qs_pg:name":"Sedli\u0161t\u011b",
    "qs_pg:name_adm0":"\u010cesk\u00e1 republika",
    "qs_pg:name_adm1":"Kr\u00e1lov\u00e9hradeck\u00fd kraj",
    "qs_pg:photos_9r":0,
    "qs_pg:photos_sr":0,
    "qs_pg:pop_sr":1,
    "qs_pg:qs_pg_placetype":"locality",
    "qs_pg:qs_pg_placetype_gp":"Town",
    "qs_pg:woe_adm0":23424810,
    "woe:adm0_id":23424810,
    "woe:name_adm0":"\u010cesk\u00e1 republika",
    "woe:name_adm1":"Kr\u00e1lov\u00e9hradeck\u00fd kraj",
    "woe:placetype":"Town",
    "wof:name":"Sedli\u0161t\u011b",
    "wof:placetype":"locality",
    "wof:population":100
},
  "geometry": {"coordinates":[15.21904,50.39413],"type":"Point"}
}