{
  "type": "Feature",
  "properties": {
    "gn:admin1_code":"82.0",
    "gn:admin2_code":"0522",
    "gn:asciiname":"Chlum",
    "gn:country_code":"CZ",
    "gn:dem":381,
    "gn:feature_class":"P",
    "gn:feature_code":"PPL",
    "gn:name":"Chlum",
    "gn:population":0,
    "gn:timezone":"Europe/Prague",
    "iso:country":"CZ",
    "wof:name":"Chlum",
    "wof:placetype":"locality"
},
  "geometry": {"coordinates":[15.60362,50.38128],"type":"Point"}
}