{
  "type": "Feature",
  "properties": {
    "gn:gn_country":"CZ",
    "gn:gn_fcode":"PPL",
    "gn:gn_pop":810,
    "gn:population":810,
    "iso:country":"CZ",
    "name:ces_x_preferred":[
        "B\u011b\u0161iny"
    ],
    "name:deu_x_preferred":[
        "B\u011b\u0161iny"
    ],
    "name:eng_x_preferred":[
        "B\u011b\u0161iny"
    ],
    "name:fas_x_preferred":[
        "\u0628\u06cc\u0634\u06cc\u0646\u06cc"
    ],
    "name:fra_x_preferred":[
        "B\u011b\u0161iny"
    ],
    "name:hun_x_preferred":[
        "B\u011b\u0161iny"
    ],
    "name:ita_x_preferred":[
        "B\u011b\u0161iny"
    ],
    "name:msa_x_preferred":[
        "B\u011b\u0161iny"
    ],
    "name:nan_x_preferred":[
        "B\u011b\u0161iny"
    ],
    "name:nld_x_preferred":[
        "B\u011b\u0161iny"
    ],
    "name:pol_x_preferred":[
        "B\u011b\u0161iny"
    ],
    "name:por_x_preferred":[
        "B\u011b\u0161iny"
    ],
    "name:rup_x_preferred":[
        "B\u011b\u0161iny"
    ],
    "name:slk_x_preferred":[
        "B\u011b\u0161iny"
    ],
    "name:srp_x_preferred":[
        "\u0411\u0458\u0435\u0448\u0438\u043d\u0438"
    ],
    "name:swe_x_preferred":[
        "B\u011b\u0161iny"
    ],
    "name:unk_x_variant":[
        "B\u011bschin"
    ],
    "name:vie_x_preferred":[
        "B\u011b\u0161iny"
    ],
    "qs_pg:aaroncc":"CZ",
    "qs_pg:gn_country":"CZ",
    "qs_pg:gn_fcode":"PPL",
    "qs_pg:gn_pop":810,
    "qs_pg:name":"B\u011b\u0161iny",
    "qs_pg:name_adm0":"\u010cesk\u00e1 republika",
    "qs_pg:name_adm1":"Plze\u0148sk\u00fd kraj",
    "qs_pg:photos_9r":0,
    "qs_pg:photos_sr":0,
    "qs_pg:pop_sr":2,
    "qs_pg:qs_pg_placetype":"locality",
    "qs_pg:qs_pg_placetype_gp":"Town",
    "qs_pg:woe_adm0":23424810,
    "woe:adm0_id":23424810,
    "woe:name_adm0":"\u010cesk\u00e1 republika",
    "woe:name_adm1":"Plze\u0148sk\u00fd kraj",
    "woe:placetype":"Town",
    "wof:name":"B\u011b\u0161iny",
    "wof:placetype":"locality",
    "wof:population":810
},
  "geometry": {"coordinates":[13.31257,49.3016],"type":"Point"}
}