{
  "type": "Feature",
  "properties": {
    "gn:admin1_code":"79.0",
    "gn:admin2_code":"0313",
    "gn:asciiname":"Rehorinky",
    "gn:country_code":"CZ",
    "gn:dem":437,
    "gn:feature_class":"P",
    "gn:feature_code":"PPL",
    "gn:name":"Reho\u0159inky",
    "gn:population":0,
    "gn:timezone":"Europe/Prague",
    "iso:country":"CZ",
    "wof:name":"Rehorinky",
    "wof:placetype":"locality"
},
  "geometry": {"coordinates":[14.8323,49.16034000000001],"type":"Point"}
}