{
  "type": "Feature",
  "properties": {
    "gn:country":"CZ",
    "gn:fcode":"PPL",
    "gn:population":576,
    "iso:country":"CZ",
    "name:azb_x_preferred":[
        "\u06a9\u0631\u0648\u0634\u0648\u0648\u06cc\u062a\u0633\u0647"
    ],
    "name:cat_x_preferred":[
        "Kru\u0161ovice"
    ],
    "name:ceb_x_preferred":[
        "Kru\u0161ovice"
    ],
    "name:ces_x_preferred":[
        "Kru\u0161ovice"
    ],
    "name:che_x_preferred":[
        "\u041a\u0440\u0443\u0448\u043e\u0432\u0438\u0446\u0435"
    ],
    "name:deu_x_preferred":[
        "Kru\u0161ovice"
    ],
    "name:eng_x_preferred":[
        "Kru\u0161ovice"
    ],
    "name:epo_x_preferred":[
        "Kru\u0161ovice"
    ],
    "name:eus_x_preferred":[
        "Kru\u0161ovice"
    ],
    "name:fas_x_preferred":[
        "\u06a9\u0631\u0648\u0634\u0648\u0648\u06cc\u062a\u0633\u0647"
    ],
    "name:fra_x_preferred":[
        "Kru\u0161ovice"
    ],
    "name:gle_x_preferred":[
        "Kru\u0161ovice"
    ],
    "name:hun_x_preferred":[
        "Kru\u0161ovice"
    ],
    "name:ita_x_preferred":[
        "Kru\u0161ovice"
    ],
    "name:lmo_x_preferred":[
        "Kru\u0161ovice"
    ],
    "name:msa_x_preferred":[
        "Kru\u0161ovice"
    ],
    "name:nan_x_preferred":[
        "Kru\u0161ovice"
    ],
    "name:nld_x_preferred":[
        "Kru\u0161ovice"
    ],
    "name:pol_x_preferred":[
        "Kru\u0161ovice"
    ],
    "name:por_x_preferred":[
        "Kru\u0161ovice"
    ],
    "name:rup_x_preferred":[
        "Kru\u0161ovice"
    ],
    "name:rus_x_preferred":[
        "\u041a\u0440\u0443\u0448\u043e\u0432\u0438\u0446\u0435"
    ],
    "name:slk_x_preferred":[
        "Kru\u0161ovice"
    ],
    "name:spa_x_preferred":[
        "Kru\u0161ovice"
    ],
    "name:srp_x_preferred":[
        "\u041a\u0440\u0443\u0448\u043e\u0432\u0438\u0446\u0435"
    ],
    "name:swe_x_preferred":[
        "Kru\u0161ovice"
    ],
    "name:tat_x_preferred":[
        "\u041a\u0440\u0443\u0448\u043e\u0432\u0438\u0446\u0435"
    ],
    "name:vie_x_preferred":[
        "Kru\u0161ovice"
    ],
    "qs_pg:aaroncc":"CZ",
    "qs_pg:gn_country":"CZ",
    "qs_pg:gn_fcode":"PPL",
    "qs_pg:gn_pop":576,
    "qs_pg:name":"Kru\u0161ovice",
    "qs_pg:name_adm0":"\u010cesk\u00e1 republika",
    "qs_pg:name_adm1":"St\u0159edo\u010desk\u00fd kraj",
    "qs_pg:photos_9k":1,
    "qs_pg:photos_9r":1,
    "qs_pg:photos_all":8,
    "qs_pg:photos_sr":0,
    "qs_pg:pop_sr":2,
    "qs_pg:qs_pg_placetype":"locality",
    "qs_pg:qs_pg_placetype_gp":"Town",
    "qs_pg:woe_adm0":23424810,
    "woe:adm0_id":23424810,
    "woe:name_adm0":"\u010cesk\u00e1 republika",
    "woe:name_adm1":"St\u0159edo\u010desk\u00fd kraj",
    "woe:placetype":"Town",
    "wof:name":"Kru\u0161ovice",
    "wof:placetype":"locality",
    "wof:population":576
},
  "geometry": {"coordinates":[13.77602,50.17179],"type":"Point"}
}