{
  "type": "Feature",
  "properties": {
    "gn:gn_country":"CZ",
    "gn:gn_fcode":"PPL",
    "gn:gn_pop":860,
    "gn:population":860,
    "iso:country":"CZ",
    "name:bul_x_preferred":[
        "\u041d\u0435\u043f\u043e\u043b\u0438\u0441\u0439"
    ],
    "name:ces_x_preferred":[
        "Nepolisy"
    ],
    "name:eng_x_preferred":[
        "Nepolisy"
    ],
    "name:fas_x_preferred":[
        "\u0646\u067e\u0648\u0644\u06cc\u0633\u06cc"
    ],
    "name:fra_x_preferred":[
        "Nepolisy"
    ],
    "name:hun_x_preferred":[
        "Nepolisy"
    ],
    "name:ita_x_preferred":[
        "Nepolisy"
    ],
    "name:msa_x_preferred":[
        "Nepolisy"
    ],
    "name:nld_x_preferred":[
        "Nepolisy"
    ],
    "name:pol_x_preferred":[
        "Nepolisy"
    ],
    "name:por_x_preferred":[
        "Nepolisy"
    ],
    "name:slk_x_preferred":[
        "Nepolisy"
    ],
    "name:srp_x_preferred":[
        "\u041d\u0435\u043f\u043e\u043b\u0438\u0441\u0438"
    ],
    "name:swe_x_preferred":[
        "Nepolisy"
    ],
    "name:szl_x_preferred":[
        "Nepolisy"
    ],
    "name:unk_x_variant":[
        "Nepolis"
    ],
    "name:vie_x_preferred":[
        "Nepolisy"
    ],
    "qs_pg:aaroncc":"CZ",
    "qs_pg:gn_country":"CZ",
    "qs_pg:gn_fcode":"PPL",
    "qs_pg:gn_pop":860,
    "qs_pg:name":"Nepolisy",
    "qs_pg:name_adm0":"\u010cesk\u00e1 republika",
    "qs_pg:name_adm1":"Kr\u00e1lov\u00e9hradeck\u00fd kraj",
    "qs_pg:photos_9r":0,
    "qs_pg:photos_sr":0,
    "qs_pg:pop_sr":2,
    "qs_pg:qs_pg_placetype":"locality",
    "qs_pg:qs_pg_placetype_gp":"Town",
    "qs_pg:woe_adm0":23424810,
    "woe:adm0_id":23424810,
    "woe:name_adm0":"\u010cesk\u00e1 republika",
    "woe:name_adm1":"Kr\u00e1lov\u00e9hradeck\u00fd kraj",
    "woe:placetype":"Town",
    "wof:name":"Nepolisy",
    "wof:placetype":"locality",
    "wof:population":860
},
  "geometry": {"coordinates":[15.46335,50.19221],"type":"Point"}
}