{
  "type": "Feature",
  "properties": {
    "gn:admin1_code":"89.0",
    "gn:admin2_code":"0423",
    "gn:asciiname":"Brehoryje",
    "gn:cc2":"CZ",
    "gn:country_code":"CZ",
    "gn:dem":212,
    "gn:feature_class":"P",
    "gn:feature_code":"PPL",
    "gn:name":"B\u0159ehoryje",
    "gn:population":0,
    "gn:timezone":"Europe/Prague",
    "iso:country":"CZ",
    "name:und_x_variant":[
        "B\u0159ehor"
    ],
    "wof:name":"Brehoryje",
    "wof:placetype":"locality"
},
  "geometry": {"coordinates":[14.30901,50.54136],"type":"Point"}
}