{
  "type": "Feature",
  "properties": {
    "gn:admin1_code":"84.0",
    "gn:admin2_code":"0711",
    "gn:asciiname":"Adolfovice",
    "gn:country_code":"CZ",
    "gn:dem":481,
    "gn:feature_class":"P",
    "gn:feature_code":"PPL",
    "gn:name":"Adolfovice",
    "gn:population":0,
    "gn:timezone":"Europe/Prague",
    "iso:country":"CZ",
    "name:und_x_variant":[
        "Adelsdorf"
    ],
    "wof:name":"Adolfovice",
    "wof:placetype":"locality"
},
  "geometry": {"coordinates":[17.19275,50.19932],"type":"Point"}
}