{
  "type": "Feature",
  "properties": {
    "iso:country":"CZ",
    "name:azb_x_preferred":[
        "\u0698\u0644\u0632\u0646\u06cc\u062a\u0633\u0647"
    ],
    "name:bul_x_preferred":[
        "\u0416\u0435\u043b\u0435\u0437\u043d\u0438\u0446\u0435"
    ],
    "name:ceb_x_preferred":[
        "\u017deleznice"
    ],
    "name:ces_x_preferred":[
        "\u017deleznice"
    ],
    "name:deu_x_preferred":[
        "\u017deleznice"
    ],
    "name:eus_x_preferred":[
        "\u017deleznice"
    ],
    "name:fas_x_preferred":[
        "\u0698\u0644\u0632\u0646\u06cc\u062a\u0633\u0647"
    ],
    "name:fra_x_preferred":[
        "\u017deleznice"
    ],
    "name:hun_x_preferred":[
        "\u017deleznice"
    ],
    "name:ita_x_preferred":[
        "\u017deleznice"
    ],
    "name:msa_x_preferred":[
        "\u017deleznice"
    ],
    "name:nld_x_preferred":[
        "\u017deleznice"
    ],
    "name:pol_x_preferred":[
        "\u017deleznice"
    ],
    "name:por_x_preferred":[
        "\u017deleznice"
    ],
    "name:slk_x_preferred":[
        "\u017deleznice"
    ],
    "name:spa_x_preferred":[
        "\u017deleznice"
    ],
    "name:srp_x_preferred":[
        "\u0416\u0435\u043b\u0435\u0437\u045a\u0438\u0446\u0435"
    ],
    "name:swe_x_preferred":[
        "\u017deleznice"
    ],
    "name:vie_x_preferred":[
        "\u017deleznice"
    ],
    "qs_pg:aaroncc":"CZ",
    "qs_pg:name":"\u017deleznice",
    "qs_pg:name_adm0":"\u010cesk\u00e1 republika",
    "qs_pg:name_adm1":"Kr\u00e1lov\u00e9hradeck\u00fd kraj",
    "qs_pg:photos":1,
    "qs_pg:photos_1k":1,
    "qs_pg:photos_9k":1,
    "qs_pg:photos_9r":1,
    "qs_pg:photos_all":1,
    "qs_pg:photos_sr":1,
    "qs_pg:pop_sr":0,
    "qs_pg:qs_pg_placetype":"localadmin",
    "qs_pg:qs_pg_placetype_gp":"LocalAdmin",
    "qs_pg:woe_adm0":23424810,
    "woe:adm0_id":23424810,
    "woe:name_adm0":"\u010cesk\u00e1 republika",
    "woe:name_adm1":"Kr\u00e1lov\u00e9hradeck\u00fd kraj",
    "woe:placetype":"LocalAdmin",
    "wof:name":"\u017deleznice",
    "wof:placetype":"localadmin"
},
  "geometry": {"coordinates":[15.28085,50.467666],"type":"Point"}
}