{
  "type": "Feature",
  "properties": {
    "gn:admin1_code":"79.0",
    "gn:admin2_code":"0317",
    "gn:asciiname":"Hodussin",
    "gn:country_code":"CZ",
    "gn:dem":522,
    "gn:feature_class":"P",
    "gn:feature_code":"PPL",
    "gn:name":"Hodu\u0161s\u00edn",
    "gn:population":0,
    "gn:timezone":"Europe/Prague",
    "iso:country":"CZ",
    "wof:name":"Hodussin",
    "wof:placetype":"locality"
},
  "geometry": {"coordinates":[14.47311,49.43453],"type":"Point"}
}