{
  "type": "Feature",
  "properties": {
    "gn:admin1_code":"79.0",
    "gn:admin2_code":"0312",
    "gn:asciiname":"Pribyslavov",
    "gn:cc2":"CZ",
    "gn:country_code":"CZ",
    "gn:dem":671,
    "gn:feature_class":"P",
    "gn:feature_code":"PPL",
    "gn:name":"P\u0159ibyslavov",
    "gn:population":0,
    "gn:timezone":"Europe/Prague",
    "iso:country":"CZ",
    "name:und_x_variant":[
        "Unter Steind\u00f6rfl",
        "P\u0159ibyslavov"
    ],
    "wof:name":"Pribyslavov",
    "wof:placetype":"locality"
},
  "geometry": {"coordinates":[14.45,48.63333],"type":"Point"}
}