{
  "type": "Feature",
  "properties": {
    "gn:country":"CZ",
    "gn:fcode":"PPL",
    "gn:population":444,
    "iso:country":"CZ",
    "name:azb_x_preferred":[
        "\u06a9\u0631\u0627\u0633\u0646\u0633\u06a9\u0648"
    ],
    "name:cat_x_preferred":[
        "Kr\u00e1sensko"
    ],
    "name:ceb_x_preferred":[
        "Kr\u00e1sensko"
    ],
    "name:ces_x_preferred":[
        "Kr\u00e1sensko"
    ],
    "name:che_x_preferred":[
        "\u041a\u0440\u0430\u0441\u0435\u043d\u0441\u043a\u043e"
    ],
    "name:deu_x_preferred":[
        "Kr\u00e1sensko"
    ],
    "name:eng_x_preferred":[
        "Kr\u00e1sensko"
    ],
    "name:epo_x_preferred":[
        "Kr\u00e1sensko"
    ],
    "name:eus_x_preferred":[
        "Kr\u00e1sensko"
    ],
    "name:fas_x_preferred":[
        "\u06a9\u0631\u0627\u0633\u0646\u0633\u06a9\u0648"
    ],
    "name:fra_x_preferred":[
        "Kr\u00e1sensko"
    ],
    "name:gle_x_preferred":[
        "Kr\u00e1sensko"
    ],
    "name:hun_x_preferred":[
        "Kr\u00e1sensko"
    ],
    "name:ita_x_preferred":[
        "Kr\u00e1sensko"
    ],
    "name:lmo_x_preferred":[
        "Kr\u00e1sensko"
    ],
    "name:msa_x_preferred":[
        "Kr\u00e1sensko"
    ],
    "name:nan_x_preferred":[
        "Kr\u00e1sensko"
    ],
    "name:nld_x_preferred":[
        "Kr\u00e1sensko"
    ],
    "name:pol_x_preferred":[
        "Kr\u00e1sensko"
    ],
    "name:por_x_preferred":[
        "Kr\u00e1sensko"
    ],
    "name:rup_x_preferred":[
        "Kr\u00e1sensko"
    ],
    "name:slk_x_preferred":[
        "Kr\u00e1sensko"
    ],
    "name:spa_x_preferred":[
        "Kr\u00e1sensko"
    ],
    "name:srp_x_preferred":[
        "\u041a\u0440\u0430\u0441\u0435\u043d\u0441\u043a\u043e"
    ],
    "name:swe_x_preferred":[
        "Kr\u00e1sensko"
    ],
    "name:tat_x_preferred":[
        "\u041a\u0440\u0430\u0441\u0435\u043d\u0441\u043a\u043e"
    ],
    "name:vie_x_preferred":[
        "Kr\u00e1sensko"
    ],
    "qs_pg:aaroncc":"CZ",
    "qs_pg:gn_country":"CZ",
    "qs_pg:gn_fcode":"PPL",
    "qs_pg:gn_pop":444,
    "qs_pg:name":"Kr\u00e1sensko",
    "qs_pg:name_adm0":"\u010cesk\u00e1 republika",
    "qs_pg:name_adm1":"Jihomoravsk\u00fd kraj",
    "qs_pg:photos_9r":0,
    "qs_pg:photos_sr":0,
    "qs_pg:pop_sr":2,
    "qs_pg:qs_pg_placetype":"locality",
    "qs_pg:qs_pg_placetype_gp":"Town",
    "qs_pg:woe_adm0":23424810,
    "woe:adm0_id":23424810,
    "woe:name_adm0":"\u010cesk\u00e1 republika",
    "woe:name_adm1":"Jihomoravsk\u00fd kraj",
    "woe:placetype":"Town",
    "wof:name":"Kr\u00e1sensko",
    "wof:placetype":"locality",
    "wof:population":444
},
  "geometry": {"coordinates":[16.82987,49.36453],"type":"Point"}
}