{
  "type": "Feature",
  "properties": {
    "gn:admin1_code":"88.0",
    "gn:admin2_code":"0204",
    "gn:asciiname":"Slunce",
    "gn:country_code":"CZ",
    "gn:dem":241,
    "gn:feature_class":"P",
    "gn:feature_code":"PPL",
    "gn:name":"Slunce",
    "gn:population":0,
    "gn:timezone":"Europe/Prague",
    "iso:country":"CZ",
    "name:und_x_variant":[
        "U Slunce",
        "Slunce"
    ],
    "wof:name":"Slunce",
    "wof:placetype":"locality"
},
  "geometry": {"coordinates":[15.11191,50.03899000000001],"type":"Point"}
}