{
  "type": "Feature",
  "properties": {
    "gn:admin1_code":"87.0",
    "gn:admin2_code":"0327",
    "gn:asciiname":"Hranicna",
    "gn:country_code":"CZ",
    "gn:dem":754,
    "gn:feature_class":"P",
    "gn:feature_code":"PPL",
    "gn:name":"Hrani\u010dn\u00e1",
    "gn:population":0,
    "gn:timezone":"Europe/Prague",
    "iso:country":"CZ",
    "name:und_x_variant":[
        "Hermannsreith",
        "Hrani\u010dn\u00e1"
    ],
    "wof:name":"Hranicna",
    "wof:placetype":"locality"
},
  "geometry": {"coordinates":[12.47128,49.83219],"type":"Point"}
}