{
  "type": "Feature",
  "properties": {
    "gn:admin1_code":"81.0",
    "gn:admin2_code":"0412",
    "gn:asciiname":"Prestani",
    "gn:country_code":"CZ",
    "gn:dem":579,
    "gn:feature_class":"P",
    "gn:feature_code":"PPL",
    "gn:name":"P\u0159est\u00e1n\u00ed",
    "gn:population":0,
    "gn:timezone":"Europe/Prague",
    "iso:country":"CZ",
    "wof:name":"Prestani",
    "wof:placetype":"locality"
},
  "geometry": {"coordinates":[13.0868,50.07493],"type":"Point"}
}