{
  "type": "Feature",
  "properties": {
    "iso:country":"CZ",
    "name:ceb_x_preferred":[
        "Hartmanice"
    ],
    "name:ces_x_preferred":[
        "Hartmanice"
    ],
    "name:deu_x_preferred":[
        "Hartmanice"
    ],
    "name:epo_x_preferred":[
        "Hartmanice"
    ],
    "name:fra_x_preferred":[
        "Hartmanice"
    ],
    "name:ita_x_preferred":[
        "Hartmanice"
    ],
    "name:nld_x_preferred":[
        "Hartmanice"
    ],
    "name:slk_x_preferred":[
        "Hartmanice"
    ],
    "name:srp_x_preferred":[
        "\u0425\u0430\u0440\u0442\u043c\u0430\u045a\u0438\u0446\u0435"
    ],
    "name:swe_x_preferred":[
        "Hartmanice"
    ],
    "qs_pg:aaroncc":"CZ",
    "qs_pg:name":"Hartmanice",
    "qs_pg:name_adm0":"\u010cesk\u00e1 republika",
    "qs_pg:name_adm1":"Plze\u0148sk\u00fd kraj",
    "qs_pg:photos":1,
    "qs_pg:photos_1k":1,
    "qs_pg:photos_9k":1,
    "qs_pg:photos_9r":1,
    "qs_pg:photos_all":16,
    "qs_pg:photos_sr":1,
    "qs_pg:pop_sr":0,
    "qs_pg:qs_pg_placetype":"localadmin",
    "qs_pg:qs_pg_placetype_gp":"LocalAdmin",
    "qs_pg:woe_adm0":23424810,
    "woe:adm0_id":23424810,
    "woe:name_adm0":"\u010cesk\u00e1 republika",
    "woe:name_adm1":"Plze\u0148sk\u00fd kraj",
    "woe:placetype":"LocalAdmin",
    "wof:name":"Hartmanice",
    "wof:placetype":"localadmin"
},
  "geometry": {"coordinates":[13.369331,49.173287],"type":"Point"}
}