{
  "type": "Feature",
  "properties": {
    "gn:admin1_code":"82",
    "gn:admin2_code":"0521",
    "gn:asciiname":"Travnik",
    "gn:country_code":"CZ",
    "gn:dem":267,
    "gn:feature_class":"P",
    "gn:feature_code":"PPL",
    "gn:name":"Tr\u00e1vn\u00edk",
    "gn:population":0,
    "gn:timezone":"Europe/Prague",
    "iso:country":"CZ",
    "name:ara_x_preferred":[
        "\u062a\u0631\u0627\u0648\u0646\u064a\u0643"
    ],
    "name:aze_x_preferred":[
        "Travnik"
    ],
    "name:bos_x_preferred":[
        "Travnik"
    ],
    "name:cat_x_preferred":[
        "Travnik"
    ],
    "name:ceb_x_preferred":[
        "Travnik"
    ],
    "name:ces_x_preferred":[
        "Travnik"
    ],
    "name:dan_x_preferred":[
        "Travnik"
    ],
    "name:deu_x_preferred":[
        "Travnik"
    ],
    "name:fas_x_preferred":[
        "\u062a\u0631\u0627\u0648\u0646\u06cc\u06a9"
    ],
    "name:fra_x_preferred":[
        "Travnik"
    ],
    "name:gag_x_preferred":[
        "Travnik"
    ],
    "name:gla_x_preferred":[
        "Travnik"
    ],
    "name:heb_x_preferred":[
        "\u05d8\u05e8\u05d0\u05d5\u05d5\u05e0\u05d9\u05e7"
    ],
    "name:hrv_x_preferred":[
        "Travnik"
    ],
    "name:hsb_x_preferred":[
        "Travnik"
    ],
    "name:hun_x_preferred":[
        "Travnik"
    ],
    "name:hye_x_preferred":[
        "\u054f\u0580\u0561\u057e\u0576\u056b\u056f"
    ],
    "name:ile_x_preferred":[
        "Travnik"
    ],
    "name:ita_x_preferred":[
        "Travnik"
    ],
    "name:jav_x_preferred":[
        "Travnik"
    ],
    "name:jpn_x_preferred":[
        "\u30c8\u30e9\u30f4\u30cb\u30af"
    ],
    "name:kor_x_preferred":[
        "\ud2b8\ub77c\ube0c\ub2c8\ud06c"
    ],
    "name:lit_x_preferred":[
        "Travnikas"
    ],
    "name:mkd_x_preferred":[
        "\u0422\u0440\u0430\u0432\u043d\u0438\u043a"
    ],
    "name:nah_x_preferred":[
        "Travnik"
    ],
    "name:nld_x_preferred":[
        "Travnik"
    ],
    "name:nor_x_preferred":[
        "Travnik"
    ],
    "name:pol_x_preferred":[
        "Travnik"
    ],
    "name:por_x_preferred":[
        "Travnik"
    ],
    "name:ron_x_preferred":[
        "Travnik"
    ],
    "name:rus_x_preferred":[
        "\u0422\u0440\u0430\u0432\u043d\u0438\u043a"
    ],
    "name:sco_x_preferred":[
        "Travnik"
    ],
    "name:slk_x_preferred":[
        "Travnik"
    ],
    "name:slv_x_preferred":[
        "Travnik"
    ],
    "name:spa_x_preferred":[
        "Travnik"
    ],
    "name:sqi_x_preferred":[
        "Travniku"
    ],
    "name:srp_x_preferred":[
        "\u0422\u0440\u0430\u0432\u043d\u0438\u043a"
    ],
    "name:swe_x_preferred":[
        "Travnik"
    ],
    "name:tat_x_preferred":[
        "\u0422\u0440\u0430\u0432\u043d\u0438\u043a"
    ],
    "name:tur_x_preferred":[
        "Travnik"
    ],
    "name:ukr_x_preferred":[
        "\u0422\u0440\u0430\u0432\u043d\u0438\u043a"
    ],
    "name:urd_x_preferred":[
        "\u062a\u0631\u0627\u0648\u0646\u06cc\u06a9"
    ],
    "name:vie_x_preferred":[
        "Travnik"
    ],
    "name:zho_x_preferred":[
        "\u7279\u62c9\u592b\u5c3c\u514b"
    ],
    "wof:name":"Travnik",
    "wof:placetype":"locality"
},
  "geometry": {"coordinates":[15.68245,50.15446],"type":"Point"}
}