{
  "type": "Feature",
  "properties": {
    "gn:admin1_code":"82",
    "gn:admin2_code":"0521",
    "gn:asciiname":"Travnik",
    "gn:country_code":"CZ",
    "gn:dem":267,
    "gn:feature_class":"P",
    "gn:feature_code":"PPL",
    "gn:name":"Tr\u00e1vn\u00edk",
    "gn:population":0,
    "gn:timezone":"Europe/Prague",
    "iso:country":"CZ",
    "wof:name":"Travnik",
    "wof:placetype":"locality"
},
  "geometry": {"coordinates":[15.68245,50.15446],"type":"Point"}
}