{
  "type": "Feature",
  "properties": {
    "gn:admin1_code":"90.0",
    "gn:admin2_code":"0723",
    "gn:asciiname":"Mala Lhota",
    "gn:country_code":"CZ",
    "gn:dem":622,
    "gn:feature_class":"P",
    "gn:feature_code":"PPL",
    "gn:name":"Mal\u00e1 Lhota",
    "gn:population":0,
    "gn:timezone":"Europe/Prague",
    "iso:country":"CZ",
    "wof:name":"Mala Lhota",
    "wof:placetype":"locality"
},
  "geometry": {"coordinates":[18.0194,49.44047],"type":"Point"}
}