{
  "type": "Feature",
  "properties": {
    "gn:gn_country":"CZ",
    "gn:gn_fcode":"PPL",
    "gn:gn_pop":560,
    "gn:population":560,
    "iso:country":"CZ",
    "name:cze_x_preferred":[
        "R\u00e1by"
    ],
    "name:dut_x_preferred":[
        "R\u00e1by"
    ],
    "name:eng_x_preferred":[
        "R\u00e1by"
    ],
    "name:epo_x_preferred":[
        "R\u00e1by"
    ],
    "name:fre_x_preferred":[
        "R\u00e1by"
    ],
    "name:ger_x_preferred":[
        "R\u00e1by"
    ],
    "name:hun_x_preferred":[
        "R\u00e1by"
    ],
    "name:ita_x_preferred":[
        "R\u00e1by"
    ],
    "name:may_x_preferred":[
        "R\u00e1by"
    ],
    "name:nan_x_preferred":[
        "R\u00e1by"
    ],
    "name:per_x_preferred":[
        "\u0631\u0628\u06cc\u060c \u067e\u0627\u0631\u062f\u0648\u0628\u06cc\u06a9\u06cc"
    ],
    "name:pol_x_preferred":[
        "R\u00e1by"
    ],
    "name:por_x_preferred":[
        "R\u00e1by"
    ],
    "name:rup_x_preferred":[
        "R\u00e1by"
    ],
    "name:slo_x_preferred":[
        "R\u00e1by"
    ],
    "name:srp_x_preferred":[
        "\u0420\u0430\u0431\u0438"
    ],
    "name:swe_x_preferred":[
        "R\u00e1by"
    ],
    "name:vie_x_preferred":[
        "R\u00e1by"
    ],
    "qs_pg:aaroncc":"CZ",
    "qs_pg:gn_country":"CZ",
    "qs_pg:gn_fcode":"PPL",
    "qs_pg:gn_pop":560,
    "qs_pg:name":"R\u00e1by",
    "qs_pg:name_adm0":"\u010cesk\u00e1 republika",
    "qs_pg:name_adm1":"Pardubick\u00fd kraj",
    "qs_pg:photos_9k":1,
    "qs_pg:photos_9r":1,
    "qs_pg:photos_all":1,
    "qs_pg:photos_sr":0,
    "qs_pg:pop_sr":2,
    "qs_pg:qs_pg_placetype":"locality",
    "qs_pg:qs_pg_placetype_gp":"Town",
    "qs_pg:woe_adm0":23424810,
    "woe:adm0_id":23424810,
    "woe:name_adm0":"\u010cesk\u00e1 republika",
    "woe:name_adm1":"Pardubick\u00fd kraj",
    "woe:placetype":"Town",
    "wof:name":"R\u00e1by",
    "wof:placetype":"locality",
    "wof:population":560
},
  "geometry": {"coordinates":[15.80252,50.07278],"type":"Point"}
}