{
  "type": "Feature",
  "properties": {
    "gn:admin1_code":"88.0",
    "gn:admin2_code":"020C",
    "gn:asciiname":"Rousinov",
    "gn:country_code":"CZ",
    "gn:dem":446,
    "gn:feature_class":"P",
    "gn:feature_code":"PPL",
    "gn:name":"Rous\u00ednov",
    "gn:population":0,
    "gn:timezone":"Europe/Prague",
    "iso:country":"CZ",
    "wof:name":"Rousinov",
    "wof:placetype":"locality"
},
  "geometry": {"coordinates":[13.67729,50.01987],"type":"Point"}
}