{
  "type": "Feature",
  "properties": {
    "gn:admin1_code":"80.0",
    "gn:admin2_code":"0611",
    "gn:asciiname":"Kamenna Lhota",
    "gn:country_code":"CZ",
    "gn:dem":468,
    "gn:feature_class":"P",
    "gn:feature_code":"PPL",
    "gn:name":"Kamenn\u00e1 Lhota",
    "gn:population":0,
    "gn:timezone":"Europe/Prague",
    "iso:country":"CZ",
    "wof:name":"Kamenna Lhota",
    "wof:placetype":"locality"
},
  "geometry": {"coordinates":[15.41253,49.78823],"type":"Point"}
}