{
  "type": "Feature",
  "properties": {
    "gn:admin1_code":"87.0",
    "gn:admin2_code":"0327",
    "gn:asciiname":"Jezerce",
    "gn:country_code":"CZ",
    "gn:dem":429,
    "gn:feature_class":"P",
    "gn:feature_code":"PPL",
    "gn:name":"Jezerce",
    "gn:population":0,
    "gn:timezone":"Europe/Prague",
    "iso:country":"CZ",
    "name:bos_x_preferred":[
        "Jezerce"
    ],
    "name:ceb_x_preferred":[
        "Jezerce"
    ],
    "name:ces_x_preferred":[
        "Jezerce"
    ],
    "name:slv_x_preferred":[
        "Jezerce"
    ],
    "name:swe_x_preferred":[
        "Jezerce"
    ],
    "name:und_x_variant":[
        "Geserzen"
    ],
    "wof:name":"Jezerce",
    "wof:placetype":"locality"
},
  "geometry": {"coordinates":[12.93456,49.7554],"type":"Point"}
}