{
  "type": "Feature",
  "properties": {
    "gn:admin1_code":"88.0",
    "gn:admin2_code":"0202",
    "gn:asciiname":"Lsten",
    "gn:country_code":"CZ",
    "gn:dem":397,
    "gn:feature_class":"P",
    "gn:feature_code":"PPL",
    "gn:name":"L\u0161t\u011b\u0148",
    "gn:population":0,
    "gn:timezone":"Europe/Prague",
    "iso:country":"CZ",
    "wof:name":"Lsten",
    "wof:placetype":"locality"
},
  "geometry": {"coordinates":[14.06216,49.81761],"type":"Point"}
}