{
  "type": "Feature",
  "properties": {
    "gn:admin1_code":"81.0",
    "gn:admin2_code":"0412",
    "gn:asciiname":"Mala Lesna",
    "gn:country_code":"CZ",
    "gn:dem":541,
    "gn:feature_class":"P",
    "gn:feature_code":"PPL",
    "gn:name":"Mal\u00e1 Lesn\u00e1",
    "gn:population":0,
    "gn:timezone":"Europe/Prague",
    "iso:country":"CZ",
    "name:und_x_variant":[
        "Klein \u0160pinelsdorf",
        "Mal\u00fd \u0160pinelsdorf",
        "Mal\u00e1 Lesn\u00e1"
    ],
    "wof:name":"Mala Lesna",
    "wof:placetype":"locality"
},
  "geometry": {"coordinates":[13.18333,50.35],"type":"Point"}
}