{
  "type": "Feature",
  "properties": {
    "gn:admin1_code":"88",
    "gn:admin2_code":"020B",
    "gn:asciiname":"Tesliny",
    "gn:country_code":"CZ",
    "gn:dem":709,
    "gn:feature_class":"P",
    "gn:feature_code":"PPL",
    "gn:name":"Tesl\u00edny",
    "gn:population":0,
    "gn:timezone":"Europe/Prague",
    "iso:country":"CZ",
    "wof:name":"Tesliny",
    "wof:placetype":"locality"
},
  "geometry": {"coordinates":[13.75474,49.6234],"type":"Point"}
}