{
  "type": "Feature",
  "properties": {
    "gn:gn_country":"CZ",
    "gn:gn_fcode":"PPL",
    "gn:gn_pop":954,
    "gn:population":954,
    "iso:country":"CZ",
    "name:ces_x_preferred":[
        "B\u0159est"
    ],
    "name:deu_x_preferred":[
        "B\u0159est"
    ],
    "name:eng_x_preferred":[
        "B\u0159est"
    ],
    "name:fra_x_preferred":[
        "B\u0159est"
    ],
    "name:hun_x_preferred":[
        "B\u0159est"
    ],
    "name:ita_x_preferred":[
        "B\u0159est"
    ],
    "name:msa_x_preferred":[
        "B\u0159est"
    ],
    "name:nan_x_preferred":[
        "B\u0159est"
    ],
    "name:nld_x_preferred":[
        "B\u0159est"
    ],
    "name:pol_x_preferred":[
        "B\u0159est"
    ],
    "name:por_x_preferred":[
        "B\u0159est"
    ],
    "name:rup_x_preferred":[
        "B\u0159est"
    ],
    "name:slk_x_preferred":[
        "B\u0159est"
    ],
    "name:srp_x_preferred":[
        "\u0411\u0440\u0435\u0441\u0442"
    ],
    "name:swe_x_preferred":[
        "B\u0159est"
    ],
    "name:vie_x_preferred":[
        "B\u0159est"
    ],
    "qs_pg:aaroncc":"CZ",
    "qs_pg:gn_country":"CZ",
    "qs_pg:gn_fcode":"PPL",
    "qs_pg:gn_pop":954,
    "qs_pg:name":"B\u0159est",
    "qs_pg:name_adm0":"\u010cesk\u00e1 republika",
    "qs_pg:name_adm1":"Zl\u00ednsk\u00fd kraj",
    "qs_pg:photos_9k":1,
    "qs_pg:photos_9r":1,
    "qs_pg:photos_all":1,
    "qs_pg:photos_sr":0,
    "qs_pg:pop_sr":2,
    "qs_pg:qs_pg_placetype":"locality",
    "qs_pg:qs_pg_placetype_gp":"Town",
    "qs_pg:woe_adm0":23424810,
    "woe:adm0_id":23424810,
    "woe:name_adm0":"\u010cesk\u00e1 republika",
    "woe:name_adm1":"Zl\u00ednsk\u00fd kraj",
    "woe:placetype":"Town",
    "wof:name":"B\u0159est",
    "wof:placetype":"locality",
    "wof:population":954
},
  "geometry": {"coordinates":[17.44072,49.35107],"type":"Point"}
}