{
  "type": "Feature",
  "properties": {
    "gn:country":"CZ",
    "gn:fcode":"PPL",
    "gn:population":284,
    "iso:country":"CZ",
    "name:azb_x_preferred":[
        "\u0628\u0648\u06a9"
    ],
    "name:cat_x_preferred":[
        "Buk"
    ],
    "name:ceb_x_preferred":[
        "Buk"
    ],
    "name:ces_x_preferred":[
        "Buk"
    ],
    "name:che_x_preferred":[
        "\u0411\u0443\u043a"
    ],
    "name:deu_x_preferred":[
        "Buk pod Boub\u00ednem"
    ],
    "name:eng_x_preferred":[
        "Buk"
    ],
    "name:epo_x_preferred":[
        "Buk"
    ],
    "name:eus_x_preferred":[
        "Buk"
    ],
    "name:fas_x_preferred":[
        "\u0628\u0648\u06a9"
    ],
    "name:fra_x_preferred":[
        "Buk"
    ],
    "name:gle_x_preferred":[
        "Buk"
    ],
    "name:hun_x_preferred":[
        "Buk"
    ],
    "name:ita_x_preferred":[
        "Buk"
    ],
    "name:msa_x_preferred":[
        "Buk"
    ],
    "name:nan_x_preferred":[
        "Buk"
    ],
    "name:nld_x_preferred":[
        "Buk"
    ],
    "name:pol_x_preferred":[
        "Buk"
    ],
    "name:por_x_preferred":[
        "Buk"
    ],
    "name:rup_x_preferred":[
        "Buk"
    ],
    "name:slk_x_preferred":[
        "Buk"
    ],
    "name:spa_x_preferred":[
        "Buk"
    ],
    "name:srp_x_preferred":[
        "\u0411\u0443\u043a"
    ],
    "name:swe_x_preferred":[
        "Buk"
    ],
    "name:tat_x_preferred":[
        "\u0411\u0443\u043a"
    ],
    "name:vie_x_preferred":[
        "Buk"
    ],
    "qs_pg:aaroncc":"CZ",
    "qs_pg:gn_country":"CZ",
    "qs_pg:gn_fcode":"PPL",
    "qs_pg:gn_pop":284,
    "qs_pg:name":"Buk",
    "qs_pg:name_adm0":"\u010cesk\u00e1 republika",
    "qs_pg:name_adm1":"Jiho\u010desk\u00fd kraj",
    "qs_pg:photos_9r":0,
    "qs_pg:photos_sr":0,
    "qs_pg:pop_sr":2,
    "qs_pg:qs_pg_placetype":"locality",
    "qs_pg:qs_pg_placetype_gp":"Town",
    "qs_pg:woe_adm0":23424810,
    "woe:adm0_id":23424810,
    "woe:name_adm0":"\u010cesk\u00e1 republika",
    "woe:name_adm1":"Jiho\u010desk\u00fd kraj",
    "woe:placetype":"Town",
    "wof:name":"Buk",
    "wof:placetype":"locality",
    "wof:population":284
},
  "geometry": {"coordinates":[13.84515,49.0379],"type":"Point"}
}