{
  "type": "Feature",
  "properties": {
    "gn:gn_country":"CZ",
    "gn:gn_fcode":"PPL",
    "gn:gn_pop":268,
    "gn:population":268,
    "iso:country":"CZ",
    "name:cze_x_preferred":[
        "Horn\u00ed Po\u0159\u00ed\u010d\u00ed"
    ],
    "name:dut_x_preferred":[
        "Horn\u00ed Po\u0159\u00ed\u010d\u00ed"
    ],
    "name:eng_x_preferred":[
        "Horn\u00ed Po\u0159\u00ed\u010d\u00ed"
    ],
    "name:fre_x_preferred":[
        "Horn\u00ed Po\u0159\u00ed\u010d\u00ed"
    ],
    "name:ger_x_preferred":[
        "Horn\u00ed Po\u0159\u00ed\u010d\u00ed u Letovic"
    ],
    "name:hun_x_preferred":[
        "Horn\u00ed Po\u0159\u00ed\u010d\u00ed"
    ],
    "name:ita_x_preferred":[
        "Horn\u00ed Po\u0159\u00ed\u010d\u00ed"
    ],
    "name:may_x_preferred":[
        "Horn\u00ed Po\u0159\u00ed\u010d\u00ed"
    ],
    "name:nan_x_preferred":[
        "Horn\u00ed Po\u0159\u00ed\u010d\u00ed"
    ],
    "name:per_x_preferred":[
        "\u0647\u0648\u0631\u0646\u06cc \u067e\u0648\u0631\u06cc\u062a\u0634\u06cc"
    ],
    "name:por_x_preferred":[
        "Horn\u00ed Po\u0159\u00ed\u010d\u00ed"
    ],
    "name:rup_x_preferred":[
        "Horn\u00ed Po\u0159\u00ed\u010d\u00ed"
    ],
    "name:slo_x_preferred":[
        "Horn\u00ed Po\u0159\u00ed\u010d\u00ed"
    ],
    "name:srp_x_preferred":[
        "\u0425\u043e\u0440\u045a\u0438 \u041f\u043e\u0440\u0436\u0438\u0447\u0438"
    ],
    "name:swe_x_preferred":[
        "Horn\u00ed Po\u0159\u00ed\u010d\u00ed"
    ],
    "name:vie_x_preferred":[
        "Horn\u00ed Po\u0159\u00ed\u010d\u00ed"
    ],
    "qs_pg:aaroncc":"CZ",
    "qs_pg:gn_country":"CZ",
    "qs_pg:gn_fcode":"PPL",
    "qs_pg:gn_pop":268,
    "qs_pg:name":"Horn\u00ed Po\u0159\u00ed\u010d\u00ed",
    "qs_pg:name_adm0":"\u010cesk\u00e1 republika",
    "qs_pg:name_adm1":"Jihomoravsk\u00fd kraj",
    "qs_pg:photos_9r":0,
    "qs_pg:photos_sr":0,
    "qs_pg:pop_sr":2,
    "qs_pg:qs_pg_placetype":"locality",
    "qs_pg:qs_pg_placetype_gp":"Town",
    "qs_pg:woe_adm0":23424810,
    "woe:adm0_id":23424810,
    "woe:name_adm0":"\u010cesk\u00e1 republika",
    "woe:name_adm1":"Jihomoravsk\u00fd kraj",
    "woe:placetype":"Town",
    "wof:name":"Horn\u00ed Po\u0159\u00ed\u010d\u00ed",
    "wof:placetype":"locality",
    "wof:population":268
},
  "geometry": {"coordinates":[16.47733,49.5876],"type":"Point"}
}