{
  "type": "Feature",
  "properties": {
    "gn:admin1_code":"87",
    "gn:admin2_code":"0322",
    "gn:asciiname":"Ustalec",
    "gn:country_code":"CZ",
    "gn:dem":576,
    "gn:feature_class":"P",
    "gn:feature_code":"PPL",
    "gn:name":"\u00dastale\u010d",
    "gn:population":0,
    "gn:timezone":"Europe/Prague",
    "iso:country":"CZ",
    "wof:name":"Ustalec",
    "wof:placetype":"locality"
},
  "geometry": {"coordinates":[13.49791,49.31603],"type":"Point"}
}