{
  "type": "Feature",
  "properties": {
    "gn:gn_country":"CZ",
    "gn:gn_fcode":"PPL",
    "gn:gn_pop":121,
    "gn:population":121,
    "iso:country":"CZ",
    "name:azb_x_preferred":[
        "\u0648\u0644\u06a9 \u062c\u0646\u0648\u06cc\u06a9"
    ],
    "name:cat_x_preferred":[
        "Velk\u00e9 Janovice"
    ],
    "name:ceb_x_preferred":[
        "Velk\u00e9 Janovice"
    ],
    "name:ces_x_preferred":[
        "Velk\u00e9 Janovice"
    ],
    "name:deu_x_preferred":[
        "Velk\u00e9 Janovice"
    ],
    "name:eng_x_preferred":[
        "Velk\u00e9 Janovice"
    ],
    "name:eus_x_preferred":[
        "Velk\u00e9 Janovice"
    ],
    "name:fas_x_preferred":[
        "\u0648\u0644\u06a9 \u062c\u0646\u0648\u06cc\u06a9"
    ],
    "name:fra_x_preferred":[
        "Velk\u00e9 Janovice"
    ],
    "name:hun_x_preferred":[
        "Velk\u00e9 Janovice"
    ],
    "name:ita_x_preferred":[
        "Velk\u00e9 Janovice"
    ],
    "name:msa_x_preferred":[
        "Velk\u00e9 Janovice"
    ],
    "name:nan_x_preferred":[
        "Velk\u00e9 Janovice"
    ],
    "name:nld_x_preferred":[
        "Velk\u00e9 Janovice"
    ],
    "name:oci_x_preferred":[
        "Velk\u00e9 Janovice"
    ],
    "name:por_x_preferred":[
        "Velk\u00e9 Janovice"
    ],
    "name:rup_x_preferred":[
        "Velk\u00e9 Janovice"
    ],
    "name:slk_x_preferred":[
        "Velk\u00e9 Janovice"
    ],
    "name:spa_x_preferred":[
        "Velk\u00e9 Janovice"
    ],
    "name:swe_x_preferred":[
        "Velk\u00e9 Janovice"
    ],
    "name:vie_x_preferred":[
        "Velk\u00e9 Janovice"
    ],
    "qs_pg:aaroncc":"CZ",
    "qs_pg:gn_country":"CZ",
    "qs_pg:gn_fcode":"PPL",
    "qs_pg:gn_pop":121,
    "qs_pg:name":"Velk\u00e9 Janovice",
    "qs_pg:name_adm0":"\u010cesk\u00e1 republika",
    "qs_pg:name_adm1":"Kraj Vyso\u010dina",
    "qs_pg:photos_9r":0,
    "qs_pg:photos_sr":0,
    "qs_pg:pop_sr":1,
    "qs_pg:qs_pg_placetype":"locality",
    "qs_pg:qs_pg_placetype_gp":"Town",
    "qs_pg:woe_adm0":23424810,
    "woe:adm0_id":23424810,
    "woe:name_adm0":"\u010cesk\u00e1 republika",
    "woe:name_adm1":"Kraj Vyso\u010dina",
    "woe:placetype":"Town",
    "wof:name":"Velk\u00e9 Janovice",
    "wof:placetype":"locality",
    "wof:population":121
},
  "geometry": {"coordinates":[16.22005,49.58784],"type":"Point"}
}