{
  "type": "Feature",
  "properties": {
    "gn:admin1_code":"79.0",
    "gn:admin2_code":"0316",
    "gn:asciiname":"Hvozd'any",
    "gn:country_code":"CZ",
    "gn:dem":427,
    "gn:feature_class":"P",
    "gn:feature_code":"PPL",
    "gn:name":"Hvo\u017e\u010fany",
    "gn:population":0,
    "gn:timezone":"Europe/Prague",
    "iso:country":"CZ",
    "wof:name":"Hvozd'any",
    "wof:placetype":"locality"
},
  "geometry": {"coordinates":[14.19115,49.12354000000001],"type":"Point"}
}