{
  "type": "Feature",
  "properties": {
    "gn:admin1_code":"80.0",
    "gn:asciiname":"Olsany u Sumperka",
    "gn:country_code":"CZ",
    "gn:dem":595,
    "gn:feature_class":"P",
    "gn:feature_code":"PPL",
    "gn:name":"Olsany u Sumperka",
    "gn:population":0,
    "gn:timezone":"Europe/Prague",
    "iso:country":"CZ",
    "wof:name":"Olsany u Sumperka",
    "wof:placetype":"locality"
},
  "geometry": {"coordinates":[15.58067,49.18241],"type":"Point"}
}