{
  "type": "Feature",
  "properties": {
    "iso:country":"CZ",
    "name:ces_x_preferred":[
        "Leti\u0161t\u011b Ran\u00e1"
    ],
    "name:eng_x_preferred":[
        "Ran\u00e1"
    ],
    "name:eng_x_variant":[
        "LKRA"
    ],
    "name:fra_x_preferred":[
        "Ran\u00e1"
    ],
    "name:msa_x_preferred":[
        "Lapangan Terbang Rana"
    ],
    "oa:elevation_ft":"879",
    "oa:type":"small_airport",
    "woe:hierarchy":{
        "country_id":23424810,
        "county_id":12582566,
        "localadmin_id":12606960,
        "planet_id":1,
        "state_id":20070499
    },
    "wof:name":"Rana Airport",
    "wof:placetype":"campus"
},
  "geometry": {"coordinates":[13.751942,50.403886],"type":"Point"}
}