{
  "type": "Feature",
  "properties": {
    "gn:admin1_code":"88.0",
    "gn:admin2_code":"0206",
    "gn:asciiname":"Dolanky",
    "gn:country_code":"CZ",
    "gn:dem":180,
    "gn:feature_class":"P",
    "gn:feature_code":"PPL",
    "gn:name":"Dol\u00e1nky",
    "gn:population":0,
    "gn:timezone":"Europe/Prague",
    "iso:country":"CZ",
    "wof:name":"Dolanky",
    "wof:placetype":"locality"
},
  "geometry": {"coordinates":[14.35524,50.21756],"type":"Point"}
}