{
  "type": "Feature",
  "properties": {
    "gn:admin1_code":"79",
    "gn:admin2_code":"0315",
    "gn:asciiname":"Vcelna pod Boubinem",
    "gn:country_code":"CZ",
    "gn:dem":883,
    "gn:feature_class":"P",
    "gn:feature_code":"PPL",
    "gn:name":"V\u010deln\u00e1 pod Boub\u00ednem",
    "gn:population":0,
    "gn:timezone":"Europe/Prague",
    "iso:country":"CZ",
    "wof:name":"Vcelna pod Boubinem",
    "wof:placetype":"locality"
},
  "geometry": {"coordinates":[13.85901,49.02264],"type":"Point"}
}