{
  "type": "Feature",
  "properties": {
    "gn:admin1_code":"83.0",
    "gn:admin2_code":"0511",
    "gn:asciiname":"Marsovice",
    "gn:country_code":"CZ",
    "gn:dem":400,
    "gn:feature_class":"P",
    "gn:feature_code":"PPL",
    "gn:name":"Mar\u0161ovice",
    "gn:population":0,
    "gn:timezone":"Europe/Prague",
    "iso:country":"CZ",
    "wof:name":"Marsovice",
    "wof:placetype":"locality"
},
  "geometry": {"coordinates":[14.56802,50.58774],"type":"Point"}
}