{
  "type": "Feature",
  "properties": {
    "iso:country":"CZ",
    "name:ces_x_preferred":[
        "Hlavatce"
    ],
    "name:fra_x_preferred":[
        "Hlavatce"
    ],
    "name:ita_x_preferred":[
        "Hlavatce"
    ],
    "name:nld_x_preferred":[
        "Hlavatce"
    ],
    "name:pol_x_preferred":[
        "Hlavatce"
    ],
    "name:slk_x_preferred":[
        "Hlavatce"
    ],
    "name:srp_x_preferred":[
        "\u0425\u043b\u0430\u0432\u0430\u0442\u0446\u0435"
    ],
    "qs_pg:aaroncc":"CZ",
    "qs_pg:name":"Hlavatce",
    "qs_pg:name_adm0":"\u010cesk\u00e1 republika",
    "qs_pg:name_adm1":"Jiho\u010desk\u00fd kraj",
    "qs_pg:photos":2,
    "qs_pg:photos_1k":1,
    "qs_pg:photos_9k":1,
    "qs_pg:photos_9r":1,
    "qs_pg:photos_all":2,
    "qs_pg:photos_sr":1,
    "qs_pg:pop_sr":0,
    "qs_pg:qs_pg_placetype":"localadmin",
    "qs_pg:qs_pg_placetype_gp":"LocalAdmin",
    "qs_pg:woe_adm0":23424810,
    "woe:adm0_id":23424810,
    "woe:name_adm0":"\u010cesk\u00e1 republika",
    "woe:name_adm1":"Jiho\u010desk\u00fd kraj",
    "woe:placetype":"LocalAdmin",
    "wof:name":"Hlavatce",
    "wof:placetype":"localadmin"
},
  "geometry": {"coordinates":[14.459724,49.002628],"type":"Point"}
}