{
  "type": "Feature",
  "properties": {
    "gn:admin1_code":"87.0",
    "gn:admin2_code":"0327",
    "gn:asciiname":"Hanov",
    "gn:country_code":"CZ",
    "gn:dem":646,
    "gn:feature_class":"P",
    "gn:feature_code":"PPL",
    "gn:name":"Hanov",
    "gn:population":0,
    "gn:timezone":"Europe/Prague",
    "iso:country":"CZ",
    "name:und_x_variant":[
        "Honau",
        "Hanov"
    ],
    "wof:name":"Hanov",
    "wof:placetype":"locality"
},
  "geometry": {"coordinates":[12.87146,49.90867],"type":"Point"}
}