{
  "type": "Feature",
  "properties": {
    "gn:admin1_code":"82",
    "gn:admin2_code":"0525",
    "gn:asciiname":"Stary Sedlonov",
    "gn:country_code":"CZ",
    "gn:dem":468,
    "gn:feature_class":"P",
    "gn:feature_code":"PPL",
    "gn:name":"Star\u00fd Sedlo\u0148ov",
    "gn:population":0,
    "gn:timezone":"Europe/Prague",
    "iso:country":"CZ",
    "name:und_x_variant":[
        "Alt-Sedlowitz",
        "Star\u00fd Sedlo\u0148ov"
    ],
    "wof:name":"Stary Sedlonov",
    "wof:placetype":"locality"
},
  "geometry": {"coordinates":[16.00709,50.54901],"type":"Point"}
}