{
  "type": "Feature",
  "properties": {
    "gn:admin1_code":"89.0",
    "gn:admin2_code":"0427",
    "gn:asciiname":"Cesky Ujezd",
    "gn:country_code":"CZ",
    "gn:dem":188,
    "gn:feature_class":"P",
    "gn:feature_code":"PPL",
    "gn:name":"\u010cesk\u00fd \u00dajezd",
    "gn:population":0,
    "gn:timezone":"Europe/Prague",
    "iso:country":"CZ",
    "name:und_x_variant":[
        "B\u00f6hmisch Neud\u00f6rfel",
        "\u010cesk\u00fd \u00dajezd"
    ],
    "wof:name":"Cesky Ujezd",
    "wof:placetype":"locality"
},
  "geometry": {"coordinates":[13.96448,50.6784],"type":"Point"}
}