{
  "type": "Feature",
  "properties": {
    "gn:admin1_code":"87.0",
    "gn:admin2_code":"0323",
    "gn:asciiname":"Lhota",
    "gn:cc2":"CZ",
    "gn:country_code":"CZ",
    "gn:dem":325,
    "gn:feature_class":"P",
    "gn:feature_code":"PPL",
    "gn:name":"Lhota",
    "gn:population":0,
    "gn:timezone":"Europe/Prague",
    "iso:country":"CZ",
    "name:ces_x_preferred":[
        "Lhota"
    ],
    "name:deu_x_preferred":[
        "Elhoten bei Pilsen"
    ],
    "name:deu_x_variant":[
        "Lhota"
    ],
    "wof:name":"Lhota",
    "wof:placetype":"locality"
},
  "geometry": {"coordinates":[13.32281,49.6904],"type":"Point"}
}