{
  "type": "Feature",
  "properties": {
    "gn:admin1_code":"88",
    "gn:admin2_code":"0207",
    "gn:asciiname":"Studenka",
    "gn:country_code":"CZ",
    "gn:dem":245,
    "gn:feature_class":"P",
    "gn:feature_code":"PPL",
    "gn:name":"Stud\u00e9nka",
    "gn:population":0,
    "gn:timezone":"Europe/Prague",
    "iso:country":"CZ",
    "wof:name":"Studenka",
    "wof:placetype":"locality"
},
  "geometry": {"coordinates":[14.97247,50.45424000000001],"type":"Point"}
}