{
  "type": "Feature",
  "properties": {
    "gn:admin1_code":"87",
    "gn:admin2_code":"0322",
    "gn:asciiname":"Vysoke Lavky",
    "gn:country_code":"CZ",
    "gn:dem":813,
    "gn:feature_class":"P",
    "gn:feature_code":"PPL",
    "gn:name":"Vysok\u00e9 L\u00e1vky",
    "gn:population":0,
    "gn:timezone":"Europe/Prague",
    "iso:country":"CZ",
    "name:und_x_variant":[
        "Hohenstegen",
        "Vysok\u00e9 L\u00e1vky"
    ],
    "wof:name":"Vysoke Lavky",
    "wof:placetype":"locality"
},
  "geometry": {"coordinates":[13.38463,49.13318],"type":"Point"}
}