{
  "type": "Feature",
  "properties": {
    "gn:gn_country":"CZ",
    "gn:gn_fcode":"PPL",
    "gn:gn_pop":184,
    "gn:population":184,
    "iso:country":"CZ",
    "name:ces_x_preferred":[
        "Jakubovice"
    ],
    "name:deu_x_preferred":[
        "Jakubovice"
    ],
    "name:eng_x_preferred":[
        "Jakubovice"
    ],
    "name:fra_x_preferred":[
        "Jakubovice"
    ],
    "name:hun_x_preferred":[
        "Jakubovice"
    ],
    "name:ita_x_preferred":[
        "Jakubovice"
    ],
    "name:msa_x_preferred":[
        "Jakubovice"
    ],
    "name:nld_x_preferred":[
        "Jakubovice"
    ],
    "name:pol_x_preferred":[
        "Jakubovice"
    ],
    "name:por_x_preferred":[
        "Jakubovice"
    ],
    "name:rup_x_preferred":[
        "Jakubovice"
    ],
    "name:slk_x_preferred":[
        "Jakubovice"
    ],
    "name:srp_x_preferred":[
        "\u0408\u0430\u043a\u0443\u0431\u043e\u0432\u0438\u0446\u0435"
    ],
    "name:swe_x_preferred":[
        "Jakubovice"
    ],
    "name:urd_x_preferred":[
        "\u062c\u06a9\u0628\u0648\u0648\u06a9\u06d2"
    ],
    "name:vie_x_preferred":[
        "Jakubovice"
    ],
    "qs_pg:aaroncc":"CZ",
    "qs_pg:gn_country":"CZ",
    "qs_pg:gn_fcode":"PPL",
    "qs_pg:gn_pop":184,
    "qs_pg:name":"Jakubovice",
    "qs_pg:name_adm0":"\u010cesk\u00e1 republika",
    "qs_pg:name_adm1":"Olomouck\u00fd kraj",
    "qs_pg:photos_9r":0,
    "qs_pg:photos_sr":0,
    "qs_pg:pop_sr":1,
    "qs_pg:qs_pg_placetype":"locality",
    "qs_pg:qs_pg_placetype_gp":"Town",
    "qs_pg:woe_adm0":23424810,
    "woe:adm0_id":23424810,
    "woe:name_adm0":"\u010cesk\u00e1 republika",
    "woe:name_adm1":"Olomouck\u00fd kraj",
    "woe:placetype":"Town",
    "wof:name":"Jakubovice",
    "wof:placetype":"locality",
    "wof:population":184
},
  "geometry": {"coordinates":[16.82877,49.99431],"type":"Point"}
}