{
  "type": "Feature",
  "properties": {
    "gn:country":"CZ",
    "gn:fcode":"PPL",
    "gn:population":103,
    "iso:country":"CZ",
    "name:cat_x_preferred":[
        "\u010cesk\u00e9 Lhotice"
    ],
    "name:ceb_x_preferred":[
        "\u010cesk\u00e9 Lhotice"
    ],
    "name:ces_x_preferred":[
        "\u010cesk\u00e9 Lhotice"
    ],
    "name:che_x_preferred":[
        "\u0427\u0435\u0441\u043a\u0435 \u041b\u0433\u043e\u0442\u0438\u0446\u0435"
    ],
    "name:deu_x_preferred":[
        "\u010cesk\u00e9 Lhotice"
    ],
    "name:eng_x_preferred":[
        "\u010cesk\u00e9 Lhotice"
    ],
    "name:epo_x_preferred":[
        "\u010cesk\u00e9 Lhotice"
    ],
    "name:eus_x_preferred":[
        "\u010cesk\u00e9 Lhotice"
    ],
    "name:fra_x_preferred":[
        "\u010cesk\u00e9 Lhotice"
    ],
    "name:gle_x_preferred":[
        "\u010cesk\u00e9 Lhotice"
    ],
    "name:hun_x_preferred":[
        "\u010cesk\u00e9 Lhotice"
    ],
    "name:ita_x_preferred":[
        "\u010cesk\u00e9 Lhotice"
    ],
    "name:lmo_x_preferred":[
        "\u010cesk\u00e9 Lhotice"
    ],
    "name:msa_x_preferred":[
        "\u010cesk\u00e9 Lhotice"
    ],
    "name:nan_x_preferred":[
        "\u010cesk\u00e9 Lhotice"
    ],
    "name:nld_x_preferred":[
        "\u010cesk\u00e9 Lhotice"
    ],
    "name:pol_x_preferred":[
        "\u010cesk\u00e9 Lhotice"
    ],
    "name:por_x_preferred":[
        "\u010cesk\u00e9 Lhotice"
    ],
    "name:rup_x_preferred":[
        "\u010cesk\u00e9 Lhotice"
    ],
    "name:slk_x_preferred":[
        "\u010cesk\u00e9 Lhotice"
    ],
    "name:spa_x_preferred":[
        "\u010cesk\u00e9 Lhotice"
    ],
    "name:srp_x_preferred":[
        "\u0427\u0435\u0448\u043a\u0435 \u041b\u0445\u043e\u0442\u0438\u0446\u0435"
    ],
    "name:swe_x_preferred":[
        "\u010cesk\u00e9 Lhotice"
    ],
    "name:tat_x_preferred":[
        "\u0427\u0435\u0441\u043a\u0435 \u041b\u0433\u043e\u0442\u0438\u0446\u0435"
    ],
    "name:vie_x_preferred":[
        "\u010cesk\u00e9 Lhotice"
    ],
    "qs_pg:aaroncc":"CZ",
    "qs_pg:gn_country":"CZ",
    "qs_pg:gn_fcode":"PPL",
    "qs_pg:gn_pop":103,
    "qs_pg:name":"\u010cesk\u00e9 Lhotice",
    "qs_pg:name_adm0":"\u010cesk\u00e1 republika",
    "qs_pg:name_adm1":"Pardubick\u00fd kraj",
    "qs_pg:photos_9r":0,
    "qs_pg:photos_sr":0,
    "qs_pg:pop_sr":1,
    "qs_pg:qs_pg_placetype":"locality",
    "qs_pg:qs_pg_placetype_gp":"Town",
    "qs_pg:woe_adm0":23424810,
    "woe:adm0_id":23424810,
    "woe:name_adm0":"\u010cesk\u00e1 republika",
    "woe:name_adm1":"Pardubick\u00fd kraj",
    "woe:placetype":"Town",
    "wof:name":"\u010cesk\u00e9 Lhotice",
    "wof:placetype":"locality",
    "wof:population":103
},
  "geometry": {"coordinates":[15.77783,49.84694],"type":"Point"}
}