{
  "type": "Feature",
  "properties": {
    "gn:gn_country":"CZ",
    "gn:gn_fcode":"PPL",
    "gn:gn_pop":143,
    "gn:population":143,
    "iso:country":"CZ",
    "name:cze_x_preferred":[
        "Kbelnice"
    ],
    "name:dut_x_preferred":[
        "Kbelnice"
    ],
    "name:eng_x_preferred":[
        "Kbelnice"
    ],
    "name:fre_x_preferred":[
        "Kbelnice"
    ],
    "name:hun_x_preferred":[
        "Kbelnice"
    ],
    "name:ita_x_preferred":[
        "Kbelnice"
    ],
    "name:may_x_preferred":[
        "Kbelnice"
    ],
    "name:per_x_preferred":[
        "\u06a9\u0628\u0644\u0646\u06cc\u062a\u0633\u0647"
    ],
    "name:pol_x_preferred":[
        "Kbelnice"
    ],
    "name:por_x_preferred":[
        "Kbelnice"
    ],
    "name:slo_x_preferred":[
        "Kbelnice"
    ],
    "name:srp_x_preferred":[
        "\u041a\u0431\u0435\u043b\u045a\u0438\u0446\u0435"
    ],
    "name:swe_x_preferred":[
        "Kbelnice"
    ],
    "name:vie_x_preferred":[
        "Kbelnice"
    ],
    "qs_pg:aaroncc":"CZ",
    "qs_pg:gn_country":"CZ",
    "qs_pg:gn_fcode":"PPL",
    "qs_pg:gn_pop":143,
    "qs_pg:name":"Kbelnice",
    "qs_pg:name_adm0":"\u010cesk\u00e1 republika",
    "qs_pg:name_adm1":"Kr\u00e1lov\u00e9hradeck\u00fd kraj",
    "qs_pg:photos_9r":0,
    "qs_pg:photos_sr":0,
    "qs_pg:pop_sr":1,
    "qs_pg:qs_pg_placetype":"locality",
    "qs_pg:qs_pg_placetype_gp":"Town",
    "qs_pg:woe_adm0":23424810,
    "woe:adm0_id":23424810,
    "woe:name_adm0":"\u010cesk\u00e1 republika",
    "woe:name_adm1":"Kr\u00e1lov\u00e9hradeck\u00fd kraj",
    "woe:placetype":"Town",
    "wof:name":"Kbelnice",
    "wof:placetype":"locality",
    "wof:population":143
},
  "geometry": {"coordinates":[15.35061,50.45483],"type":"Point"}
}