{
  "type": "Feature",
  "properties": {
    "gn:admin1_code":"87.0",
    "gn:admin2_code":"0321",
    "gn:asciiname":"Mezholezy",
    "gn:country_code":"CZ",
    "gn:dem":438,
    "gn:feature_class":"P",
    "gn:feature_code":"PPL",
    "gn:name":"Mezholezy",
    "gn:population":0,
    "gn:timezone":"Europe/Prague",
    "iso:country":"CZ",
    "name:und_x_variant":[
        "Messhals",
        "Mezholezy"
    ],
    "wof:name":"Mezholezy",
    "wof:placetype":"locality"
},
  "geometry": {"coordinates":[12.90478,49.62416],"type":"Point"}
}