{
  "type": "Feature",
  "properties": {
    "gn:admin1_code":"87.0",
    "gn:admin2_code":"0321",
    "gn:asciiname":"Mezholezy",
    "gn:country_code":"CZ",
    "gn:dem":438,
    "gn:feature_class":"P",
    "gn:feature_code":"PPL",
    "gn:name":"Mezholezy",
    "gn:population":0,
    "gn:timezone":"Europe/Prague",
    "iso:country":"CZ",
    "name:azb_x_preferred":[
        "\u0645\u0632\u0647\u0648\u0644\u0632\u06cc"
    ],
    "name:ces_x_preferred":[
        "Mezholezy"
    ],
    "name:fas_x_preferred":[
        "\u0645\u0632\u0647\u0648\u0644\u0632\u06cc"
    ],
    "name:ita_x_preferred":[
        "Mezholezy"
    ],
    "name:msa_x_preferred":[
        "Mezholezy"
    ],
    "name:nld_x_preferred":[
        "Mezholezy"
    ],
    "name:por_x_preferred":[
        "Mezholezy"
    ],
    "name:slk_x_preferred":[
        "Mezholezy"
    ],
    "name:srp_x_preferred":[
        "\u041c\u0435\u0437\u0445\u043e\u043b\u0435\u0437\u0438"
    ],
    "name:und_x_variant":[
        "Messhals"
    ],
    "name:vie_x_preferred":[
        "Mezholezy"
    ],
    "wof:name":"Mezholezy",
    "wof:placetype":"locality"
},
  "geometry": {"coordinates":[12.90478,49.62416],"type":"Point"}
}