{
  "type": "Feature",
  "properties": {
    "gn:admin1_code":"79.0",
    "gn:admin2_code":"0312",
    "gn:asciiname":"Manava",
    "gn:country_code":"CZ",
    "gn:dem":771,
    "gn:feature_class":"P",
    "gn:feature_code":"PPL",
    "gn:name":"Ma\u0148ava",
    "gn:population":0,
    "gn:timezone":"Europe/Prague",
    "iso:country":"CZ",
    "name:und_x_variant":[
        "Deutsch Haidl",
        "N\u011bmeck\u00e1 Ma\u0148ava",
        "Ma\u0148ava"
    ],
    "wof:name":"Manava",
    "wof:placetype":"locality"
},
  "geometry": {"coordinates":[14.01347,48.78641],"type":"Point"}
}