{
  "type": "Feature",
  "properties": {
    "gn:country":"CZ",
    "gn:fcode":"PPL",
    "gn:population":235,
    "iso:country":"CZ",
    "name:azb_x_preferred":[
        "\u0631\u0627\u0646\u0627"
    ],
    "name:cat_x_preferred":[
        "Ran\u00e1"
    ],
    "name:ceb_x_preferred":[
        "Ran\u00e1"
    ],
    "name:ces_x_preferred":[
        "Ran\u00e1"
    ],
    "name:che_x_preferred":[
        "\u0420\u0436\u0430\u043d\u0430"
    ],
    "name:deu_x_preferred":[
        "Ran\u00e1 u Loun"
    ],
    "name:eng_x_preferred":[
        "Ran\u00e1"
    ],
    "name:epo_x_preferred":[
        "Ran\u00e1"
    ],
    "name:eus_x_preferred":[
        "Ran\u00e1"
    ],
    "name:fas_x_preferred":[
        "\u0631\u0627\u0646\u0627"
    ],
    "name:fra_x_preferred":[
        "Ran\u00e1"
    ],
    "name:gle_x_preferred":[
        "Ran\u00e1"
    ],
    "name:hun_x_preferred":[
        "Ran\u00e1"
    ],
    "name:ita_x_preferred":[
        "Ran\u00e1"
    ],
    "name:lmo_x_preferred":[
        "Ran\u00e1"
    ],
    "name:msa_x_preferred":[
        "Ran\u00e1"
    ],
    "name:nan_x_preferred":[
        "Ran\u00e1"
    ],
    "name:nld_x_preferred":[
        "Ran\u00e1"
    ],
    "name:pol_x_preferred":[
        "Ran\u00e1"
    ],
    "name:por_x_preferred":[
        "Ran\u00e1"
    ],
    "name:rup_x_preferred":[
        "Ran\u00e1"
    ],
    "name:slk_x_preferred":[
        "Ran\u00e1"
    ],
    "name:spa_x_preferred":[
        "Ran\u00e1"
    ],
    "name:srp_x_preferred":[
        "\u0420\u0430\u043d\u0430"
    ],
    "name:swe_x_preferred":[
        "Ran\u00e1"
    ],
    "name:tat_x_preferred":[
        "\u0420\u0436\u0430\u043d\u0430"
    ],
    "name:vie_x_preferred":[
        "Ran\u00e1"
    ],
    "qs_pg:aaroncc":"CZ",
    "qs_pg:gn_country":"CZ",
    "qs_pg:gn_fcode":"PPL",
    "qs_pg:gn_pop":235,
    "qs_pg:name":"Ran\u00e1",
    "qs_pg:name_adm0":"\u010cesk\u00e1 republika",
    "qs_pg:name_adm1":"\u00dasteck\u00fd kraj",
    "qs_pg:photos":24,
    "qs_pg:photos_1k":5,
    "qs_pg:photos_9k":1,
    "qs_pg:photos_9r":1,
    "qs_pg:photos_all":24,
    "qs_pg:photos_sr":1,
    "qs_pg:pop_sr":2,
    "qs_pg:qs_pg_placetype":"locality",
    "qs_pg:qs_pg_placetype_gp":"Town",
    "qs_pg:woe_adm0":23424810,
    "woe:adm0_id":23424810,
    "woe:name_adm0":"\u010cesk\u00e1 republika",
    "woe:name_adm1":"\u00dasteck\u00fd kraj",
    "woe:placetype":"Town",
    "wof:name":"Ran\u00e1",
    "wof:placetype":"locality",
    "wof:population":235
},
  "geometry": {"coordinates":[13.77926,50.41156],"type":"Point"}
}