{
  "type": "Feature",
  "properties": {
    "gn:country":"CZ",
    "gn:fcode":"PPL",
    "gn:population":744,
    "iso:country":"CZ",
    "name:azb_x_preferred":[
        "\u0644\u0647\u0648\u062a\u0627 \u0648 \u0648\u0633\u062a\u06cc\u0646\u0627"
    ],
    "name:ceb_x_preferred":[
        "Lhota u Vset\u00edna"
    ],
    "name:ces_x_preferred":[
        "Lhota u Vset\u00edna"
    ],
    "name:deu_x_preferred":[
        "Lhota u Vset\u00edna"
    ],
    "name:eng_x_preferred":[
        "Lhota u Vset\u00edna"
    ],
    "name:epo_x_preferred":[
        "Lhota u Vset\u00edna"
    ],
    "name:eus_x_preferred":[
        "Lhota u Vset\u00edna"
    ],
    "name:fas_x_preferred":[
        "\u0644\u0647\u0648\u062a\u0627 \u0648 \u0648\u0633\u062a\u06cc\u0646\u0627"
    ],
    "name:fra_x_preferred":[
        "Lhota u Vset\u00edna"
    ],
    "name:hun_x_preferred":[
        "Lhota u Vset\u00edna"
    ],
    "name:ita_x_preferred":[
        "Lhota u Vset\u00edna"
    ],
    "name:msa_x_preferred":[
        "Lhota u Vset\u00edna"
    ],
    "name:nan_x_preferred":[
        "Lhota u Vset\u00edna"
    ],
    "name:nld_x_preferred":[
        "Lhota u Vset\u00edna"
    ],
    "name:pol_x_preferred":[
        "Lhota u Vset\u00edna"
    ],
    "name:por_x_preferred":[
        "Lhota u Vset\u00edna"
    ],
    "name:rup_x_preferred":[
        "Lhota u Vset\u00edna"
    ],
    "name:slk_x_preferred":[
        "Lhota u Vset\u00edna"
    ],
    "name:spa_x_preferred":[
        "Lhota u Vset\u00edna"
    ],
    "name:srp_x_preferred":[
        "\u041b\u0445\u043e\u0442\u0430 \u0443 \u0412\u0441\u0435\u0442\u0438\u043d\u0438"
    ],
    "name:swe_x_preferred":[
        "Lhota u Vset\u00edna"
    ],
    "name:vie_x_preferred":[
        "Lhota u Vset\u00edna"
    ],
    "qs_pg:aaroncc":"CZ",
    "qs_pg:gn_country":"CZ",
    "qs_pg:gn_fcode":"PPL",
    "qs_pg:gn_pop":744,
    "qs_pg:name":"Lhota u Vset\u00edna",
    "qs_pg:name_adm0":"\u010cesk\u00e1 republika",
    "qs_pg:name_adm1":"Zl\u00ednsk\u00fd kraj",
    "qs_pg:photos_9r":0,
    "qs_pg:photos_sr":0,
    "qs_pg:pop_sr":2,
    "qs_pg:qs_pg_placetype":"locality",
    "qs_pg:qs_pg_placetype_gp":"Town",
    "qs_pg:woe_adm0":23424810,
    "woe:adm0_id":23424810,
    "woe:name_adm0":"\u010cesk\u00e1 republika",
    "woe:name_adm1":"Zl\u00ednsk\u00fd kraj",
    "woe:placetype":"Town",
    "wof:name":"Lhota u Vset\u00edna",
    "wof:placetype":"locality",
    "wof:population":744
},
  "geometry": {"coordinates":[17.95798,49.30458],"type":"Point"}
}