{
  "type": "Feature",
  "properties": {
    "gn:admin1_code":"83.0",
    "gn:admin2_code":"0513",
    "gn:asciiname":"Filipov",
    "gn:country_code":"CZ",
    "gn:dem":430,
    "gn:feature_class":"P",
    "gn:feature_code":"PPL",
    "gn:name":"Filipov",
    "gn:population":0,
    "gn:timezone":"Europe/Prague",
    "iso:country":"CZ",
    "name:und_x_variant":[
        "Philippsberg",
        "Filipovo",
        "Filipov"
    ],
    "wof:name":"Filipov",
    "wof:placetype":"locality"
},
  "geometry": {"coordinates":[15.03333,50.85],"type":"Point"}
}