{
  "type": "Feature",
  "properties": {
    "gn:gn_country":"CZ",
    "gn:gn_fcode":"PPL",
    "gn:gn_pop":140,
    "gn:population":140,
    "iso:country":"CZ",
    "name:ces_x_preferred":[
        "Labsk\u00e9 Chr\u010dice"
    ],
    "name:deu_x_preferred":[
        "Labsk\u00e9 Chr\u010dice"
    ],
    "name:eng_x_preferred":[
        "Labsk\u00e9 Chr\u010dice"
    ],
    "name:epo_x_preferred":[
        "Labsk\u00e9 Chr\u010dice"
    ],
    "name:fra_x_preferred":[
        "Labsk\u00e9 Chr\u010dice"
    ],
    "name:hun_x_preferred":[
        "Labsk\u00e9 Chr\u010dice"
    ],
    "name:ita_x_preferred":[
        "Labsk\u00e9 Chr\u010dice"
    ],
    "name:msa_x_preferred":[
        "Labsk\u00e9 Chr\u010dice"
    ],
    "name:nan_x_preferred":[
        "Labsk\u00e9 Chr\u010dice"
    ],
    "name:nld_x_preferred":[
        "Labsk\u00e9 Chr\u010dice"
    ],
    "name:por_x_preferred":[
        "Labsk\u00e9 Chr\u010dice"
    ],
    "name:rup_x_preferred":[
        "Labsk\u00e9 Chr\u010dice"
    ],
    "name:slk_x_preferred":[
        "Labsk\u00e9 Chr\u010dice"
    ],
    "name:srp_x_preferred":[
        "\u041b\u0430\u043f\u0441\u043a\u0435 \u0425\u0440\u0447\u0438\u0446\u0435"
    ],
    "name:swe_x_preferred":[
        "Labsk\u00e9 Chr\u010dice"
    ],
    "name:vie_x_preferred":[
        "Labsk\u00e9 Chr\u010dice"
    ],
    "qs_pg:aaroncc":"CZ",
    "qs_pg:gn_country":"CZ",
    "qs_pg:gn_fcode":"PPL",
    "qs_pg:gn_pop":140,
    "qs_pg:name":"Labsk\u00e9 Chr\u010dice",
    "qs_pg:name_adm0":"\u010cesk\u00e1 republika",
    "qs_pg:name_adm1":"Pardubick\u00fd kraj",
    "qs_pg:photos_9r":0,
    "qs_pg:photos_sr":0,
    "qs_pg:pop_sr":1,
    "qs_pg:qs_pg_placetype":"locality",
    "qs_pg:qs_pg_placetype_gp":"Town",
    "qs_pg:woe_adm0":23424810,
    "woe:adm0_id":23424810,
    "woe:name_adm0":"\u010cesk\u00e1 republika",
    "woe:name_adm1":"Pardubick\u00fd kraj",
    "woe:placetype":"Town",
    "wof:name":"Labsk\u00e9 Chr\u010dice",
    "wof:placetype":"locality",
    "wof:population":140
},
  "geometry": {"coordinates":[15.41017,50.05142],"type":"Point"}
}