{
  "type": "Feature",
  "properties": {
    "iso:country":"CZ",
    "name:cze_x_colloquial":[
        "Stare Mesto",
        "Stare Msto"
    ],
    "name:cze_x_preferred":[
        "Star\u00e9 Msto"
    ],
    "name:cze_x_variant":[
        "Altstadt"
    ],
    "name:unk_x_variant":[
        "Star\u00e9 Msto"
    ],
    "qs:gn_adm0_cc":"CZ",
    "qs:gn_local":3077244,
    "qs:gn_nam_loc":"D\u011b\u010d\u00edn, D\u011b\u010d\u00edn, D\u011b\u010d\u00edn, \u00dasteck\u00fd kraj, CZ",
    "qs:gn_namadm1":"89",
    "qs:local_max":595,
    "qs:local_sum":645,
    "qs:localhoods":3,
    "qs:name":"Star\u00e9 Msto",
    "qs:name_adm0":"\u010cesk\u00e1 republika",
    "qs:name_adm1":"\u00dasteck\u00fd kraj",
    "qs:name_adm2":"D\u011b\u010d\u00edn",
    "qs:name_lau":"D\u011b\u010d\u00edn",
    "qs:name_local":"D\u011b\u010d\u00edn",
    "qs:photo_max":17,
    "qs:photo_sum":23,
    "qs:placetype":"Suburb",
    "qs:quad_count":4,
    "qs:woe_adm0":23424810,
    "qs:woe_adm1":20070499,
    "qs:woe_adm2":12582562,
    "qs:woe_lau":12606602,
    "qs:woe_local":788060,
    "qs:woe_ver":"7.10.0",
    "wof:lang":[
        "cze"
    ],
    "wof:name":"Star\u00e9 Msto",
    "wof:placetype":"neighbourhood"
},
  "geometry": {"coordinates":[14.226459,50.793176],"type":"Point"}
}