{
  "type": "Feature",
  "properties": {
    "gn:admin1_code":"89.0",
    "gn:admin2_code":"0423",
    "gn:asciiname":"Brocno",
    "gn:cc2":"CZ",
    "gn:country_code":"CZ",
    "gn:dem":315,
    "gn:feature_class":"P",
    "gn:feature_code":"PPL",
    "gn:name":"Brocno",
    "gn:population":0,
    "gn:timezone":"Europe/Prague",
    "iso:country":"CZ",
    "name:und_x_variant":[
        "Brotzen"
    ],
    "wof:name":"Brocno",
    "wof:placetype":"locality"
},
  "geometry": {"coordinates":[14.44462,50.47641],"type":"Point"}
}