{
  "type": "Feature",
  "properties": {
    "gn:admin1_code":"88.0",
    "gn:admin2_code":"0209",
    "gn:asciiname":"Nehvizdky",
    "gn:country_code":"CZ",
    "gn:dem":212,
    "gn:feature_class":"P",
    "gn:feature_code":"PPL",
    "gn:name":"Nehv\u00edzdky",
    "gn:population":0,
    "gn:timezone":"Europe/Prague",
    "iso:country":"CZ",
    "wof:name":"Nehvizdky",
    "wof:placetype":"locality"
},
  "geometry": {"coordinates":[14.7421,50.14077],"type":"Point"}
}