{
  "type": "Feature",
  "properties": {
    "gn:admin1_code":"79.0",
    "gn:admin2_code":"0317",
    "gn:asciiname":"Moravec",
    "gn:country_code":"CZ",
    "gn:dem":491,
    "gn:feature_class":"P",
    "gn:feature_code":"PPL",
    "gn:name":"Morave\u010d",
    "gn:population":0,
    "gn:timezone":"Europe/Prague",
    "iso:country":"CZ",
    "name:ceb_x_preferred":[
        "Moravec"
    ],
    "name:ces_x_preferred":[
        "Moravec"
    ],
    "name:deu_x_preferred":[
        "Moravec"
    ],
    "name:fra_x_preferred":[
        "Moravec"
    ],
    "name:jpn_x_preferred":[
        "\u30e2\u30e9\u30f4\u30a7\u30c3\u30c4"
    ],
    "name:lav_x_preferred":[
        "Moravecs"
    ],
    "name:pol_x_preferred":[
        "Moravec"
    ],
    "name:rus_x_preferred":[
        "\u041c\u043e\u0440\u0430\u0432\u0435\u0446"
    ],
    "name:slk_x_preferred":[
        "Moravec"
    ],
    "name:spa_x_preferred":[
        "Moravec"
    ],
    "name:swe_x_preferred":[
        "Moravec"
    ],
    "name:ukr_x_preferred":[
        "\u041c\u043e\u0440\u0430\u0432\u0435\u0446\u044c"
    ],
    "wof:name":"Moravec",
    "wof:placetype":"locality"
},
  "geometry": {"coordinates":[14.65294,49.48326],"type":"Point"}
}