{
  "type": "Feature",
  "properties": {
    "gn:admin1_code":"79.0",
    "gn:admin2_code":"0317",
    "gn:asciiname":"Moravec",
    "gn:country_code":"CZ",
    "gn:dem":491,
    "gn:feature_class":"P",
    "gn:feature_code":"PPL",
    "gn:name":"Morave\u010d",
    "gn:population":0,
    "gn:timezone":"Europe/Prague",
    "iso:country":"CZ",
    "wof:name":"Moravec",
    "wof:placetype":"locality"
},
  "geometry": {"coordinates":[14.65294,49.48326],"type":"Point"}
}