{
  "type": "Feature",
  "properties": {
    "gn:admin1_code":"79.0",
    "gn:admin2_code":"0315",
    "gn:asciiname":"Laz",
    "gn:country_code":"CZ",
    "gn:dem":753,
    "gn:feature_class":"P",
    "gn:feature_code":"PPL",
    "gn:name":"L\u00e1z",
    "gn:population":0,
    "gn:timezone":"Europe/Prague",
    "iso:country":"CZ",
    "name:bos_x_preferred":[
        "Laz"
    ],
    "name:ceb_x_preferred":[
        "Laz"
    ],
    "name:deu_x_preferred":[
        "Laz"
    ],
    "name:hrv_x_preferred":[
        "Laz"
    ],
    "name:hun_x_preferred":[
        "Laz"
    ],
    "name:slk_x_preferred":[
        "Laz"
    ],
    "name:slv_x_preferred":[
        "Laz"
    ],
    "name:spa_x_preferred":[
        "Laz"
    ],
    "name:srp_x_preferred":[
        "\u041b\u0430\u0437"
    ],
    "name:swe_x_preferred":[
        "Laz"
    ],
    "name:und_x_variant":[
        "Geh\u00e4ng",
        "L\u00e1z"
    ],
    "wof:name":"Laz",
    "wof:placetype":"locality"
},
  "geometry": {"coordinates":[13.94148,48.78261],"type":"Point"}
}