{
  "type": "Feature",
  "properties": {
    "gn:admin1_code":"89",
    "gn:admin2_code":"0426",
    "gn:asciiname":"Zahori",
    "gn:country_code":"CZ",
    "gn:dem":425,
    "gn:feature_class":"P",
    "gn:feature_code":"PPL",
    "gn:name":"Z\u00e1ho\u0159\u00ed",
    "gn:population":0,
    "gn:timezone":"Europe/Prague",
    "iso:country":"CZ",
    "wof:name":"Zahori",
    "wof:placetype":"locality"
},
  "geometry": {"coordinates":[13.97071,50.57653],"type":"Point"}
}