{
  "type": "Feature",
  "properties": {
    "gn:admin1_code":"87",
    "gn:admin2_code":"0325",
    "gn:asciiname":"Svetec",
    "gn:country_code":"CZ",
    "gn:dem":628,
    "gn:feature_class":"P",
    "gn:feature_code":"PPL",
    "gn:name":"Sv\u011btec",
    "gn:population":0,
    "gn:timezone":"Europe/Prague",
    "iso:country":"CZ",
    "name:und_x_variant":[
        "Schwitz",
        "Sv\u011btec"
    ],
    "wof:name":"Svetec",
    "wof:placetype":"locality"
},
  "geometry": {"coordinates":[13.03868,49.96045],"type":"Point"}
}