{
  "type": "Feature",
  "properties": {
    "gn:admin1_code":"79.0",
    "gn:admin2_code":"0312",
    "gn:asciiname":"Lipova",
    "gn:country_code":"CZ",
    "gn:dem":854,
    "gn:feature_class":"P",
    "gn:feature_code":"PPL",
    "gn:name":"Lipov\u00e1",
    "gn:population":0,
    "gn:timezone":"Europe/Prague",
    "iso:country":"CZ",
    "name:und_x_variant":[
        "Lindberg",
        "Lipov\u00e1"
    ],
    "wof:name":"Lipova",
    "wof:placetype":"locality"
},
  "geometry": {"coordinates":[14.20467,48.61498],"type":"Point"}
}