{
  "type": "Feature",
  "properties": {
    "gn:admin1_code":"87.0",
    "gn:admin2_code":"0322",
    "gn:asciiname":"Nova Studnice",
    "gn:country_code":"CZ",
    "gn:dem":1087,
    "gn:feature_class":"P",
    "gn:feature_code":"PPL",
    "gn:name":"Nov\u00e1 Studnice",
    "gn:population":0,
    "gn:timezone":"Europe/Prague",
    "iso:country":"CZ",
    "name:und_x_variant":[
        "Neubrunn",
        "Nov\u00e1 Studnice"
    ],
    "wof:name":"Nova Studnice",
    "wof:placetype":"locality"
},
  "geometry": {"coordinates":[13.43342,49.08403],"type":"Point"}
}