{
  "type": "Feature",
  "properties": {
    "gn:admin1_code":"87.0",
    "gn:admin2_code":"0322",
    "gn:asciiname":"Matejovice",
    "gn:country_code":"CZ",
    "gn:dem":651,
    "gn:feature_class":"P",
    "gn:feature_code":"PPL",
    "gn:name":"Mat\u011bjovice",
    "gn:population":0,
    "gn:timezone":"Europe/Prague",
    "iso:country":"CZ",
    "name:und_x_variant":[
        "Mottowitz",
        "Mat\u011bjovice"
    ],
    "wof:name":"Matejovice",
    "wof:placetype":"locality"
},
  "geometry": {"coordinates":[13.17691,49.25978],"type":"Point"}
}