{
  "type": "Feature",
  "properties": {
    "gn:admin1_code":"79.0",
    "gn:admin2_code":"0311",
    "gn:asciiname":"Radomilice",
    "gn:country_code":"CZ",
    "gn:dem":399,
    "gn:feature_class":"P",
    "gn:feature_code":"PPL",
    "gn:name":"Radomilice",
    "gn:population":0,
    "gn:timezone":"Europe/Prague",
    "iso:country":"CZ",
    "wof:name":"Radomilice",
    "wof:placetype":"locality"
},
  "geometry": {"coordinates":[14.25971,49.12235],"type":"Point"}
}