{
  "type": "Feature",
  "properties": {
    "gn:admin1_code":"80",
    "gn:admin2_code":"0615",
    "gn:asciiname":"Stepanov",
    "gn:country_code":"CZ",
    "gn:dem":345,
    "gn:feature_class":"P",
    "gn:feature_code":"PPL",
    "gn:name":"\u0160t\u011bp\u00e1nov",
    "gn:population":0,
    "gn:timezone":"Europe/Prague",
    "iso:country":"CZ",
    "name:und_x_variant":[
        "Sti\u011bpanau",
        "\u0160t\u011bp\u00e1nov"
    ],
    "wof:name":"Stepanov",
    "wof:placetype":"locality"
},
  "geometry": {"coordinates":[16.33922,49.50489],"type":"Point"}
}