{
  "type": "Feature",
  "properties": {
    "gn:gn_country":"CZ",
    "gn:gn_fcode":"PPL",
    "gn:gn_pop":427,
    "gn:population":427,
    "iso:country":"CZ",
    "name:cze_x_preferred":[
        "Horn\u00ed \u00dajezd"
    ],
    "name:dut_x_preferred":[
        "Horn\u00ed \u00dajezd"
    ],
    "name:eng_x_preferred":[
        "Horn\u00ed \u00dajezd"
    ],
    "name:epo_x_preferred":[
        "Horn\u00ed \u00dajezd"
    ],
    "name:fre_x_preferred":[
        "Horn\u00ed \u00dajezd"
    ],
    "name:hun_x_preferred":[
        "Horn\u00ed \u00dajezd"
    ],
    "name:ita_x_preferred":[
        "Horn\u00ed \u00dajezd"
    ],
    "name:may_x_preferred":[
        "Horn\u00ed \u00dajezd"
    ],
    "name:nan_x_preferred":[
        "Horn\u00ed \u00dajezd"
    ],
    "name:per_x_preferred":[
        "\u0647\u0648\u0631\u0646\u06cc \u0648\u06cc\u0632\u062f"
    ],
    "name:pol_x_preferred":[
        "Horn\u00ed \u00dajezd"
    ],
    "name:por_x_preferred":[
        "Horn\u00ed \u00dajezd"
    ],
    "name:rup_x_preferred":[
        "Horn\u00ed \u00dajezd"
    ],
    "name:slo_x_preferred":[
        "Horn\u00ed \u00dajezd"
    ],
    "name:srp_x_preferred":[
        "\u0425\u043e\u0440\u045a\u0438 \u0423\u0458\u0435\u0437\u0434"
    ],
    "name:unk_x_variant":[
        "Ober Aujezd"
    ],
    "name:vie_x_preferred":[
        "Horn\u00ed \u00dajezd"
    ],
    "qs_pg:aaroncc":"CZ",
    "qs_pg:gn_country":"CZ",
    "qs_pg:gn_fcode":"PPL",
    "qs_pg:gn_pop":427,
    "qs_pg:name":"Horn\u00ed \u00dajezd",
    "qs_pg:name_adm0":"\u010cesk\u00e1 republika",
    "qs_pg:name_adm1":"Pardubick\u00fd kraj",
    "qs_pg:photos_9r":0,
    "qs_pg:photos_sr":0,
    "qs_pg:pop_sr":2,
    "qs_pg:qs_pg_placetype":"locality",
    "qs_pg:qs_pg_placetype_gp":"Town",
    "qs_pg:woe_adm0":23424810,
    "woe:adm0_id":23424810,
    "woe:name_adm0":"\u010cesk\u00e1 republika",
    "woe:name_adm1":"Pardubick\u00fd kraj",
    "woe:placetype":"Town",
    "wof:name":"Horn\u00ed \u00dajezd",
    "wof:placetype":"locality",
    "wof:population":427
},
  "geometry": {"coordinates":[16.23294,49.80348],"type":"Point"}
}