{
  "type": "Feature",
  "properties": {
    "gn:admin1_code":"85.0",
    "gn:admin2_code":"0801",
    "gn:asciiname":"Jamartice",
    "gn:country_code":"CZ",
    "gn:dem":570,
    "gn:feature_class":"P",
    "gn:feature_code":"PPL",
    "gn:name":"Jamartice",
    "gn:population":0,
    "gn:timezone":"Europe/Prague",
    "iso:country":"CZ",
    "name:und_x_variant":[
        "Irmsdorf",
        "Jamartice"
    ],
    "wof:name":"Jamartice",
    "wof:placetype":"locality"
},
  "geometry": {"coordinates":[17.32084,49.93881],"type":"Point"}
}