{
  "type": "Feature",
  "properties": {
    "gn:admin1_code":"79.0",
    "gn:admin2_code":"0312",
    "gn:asciiname":"Jelm",
    "gn:country_code":"CZ",
    "gn:dem":811,
    "gn:feature_class":"P",
    "gn:feature_code":"PPL",
    "gn:name":"Jelm",
    "gn:population":0,
    "gn:timezone":"Europe/Prague",
    "iso:country":"CZ",
    "name:deu_x_preferred":[
        "Melm"
    ],
    "wof:name":"Jelm",
    "wof:placetype":"locality"
},
  "geometry": {"coordinates":[14.05881,48.76717],"type":"Point"}
}