{
  "type": "Feature",
  "properties": {
    "gn:admin1_code":"89",
    "gn:admin2_code":"0421",
    "gn:asciiname":"Stare Mesto",
    "gn:country_code":"CZ",
    "gn:dem":159,
    "gn:feature_class":"P",
    "gn:feature_code":"PPL",
    "gn:name":"Star\u00e9 M\u011bsto",
    "gn:population":0,
    "gn:timezone":"Europe/Prague",
    "iso:country":"CZ",
    "name:und_x_variant":[
        "Altstadt",
        "Star\u00e9 M\u011bsto"
    ],
    "wof:name":"Stare Mesto",
    "wof:placetype":"locality"
},
  "geometry": {"coordinates":[14.22435,50.76769],"type":"Point"}
}