{
  "type": "Feature",
  "properties": {
    "gn:admin1_code":"87.0",
    "gn:admin2_code":"0322",
    "gn:asciiname":"Hodousice",
    "gn:country_code":"CZ",
    "gn:dem":498,
    "gn:feature_class":"P",
    "gn:feature_code":"PPL",
    "gn:name":"Hodousice",
    "gn:population":0,
    "gn:timezone":"Europe/Prague",
    "iso:country":"CZ",
    "name:und_x_variant":[
        "Holletitz",
        "Hodousice"
    ],
    "wof:name":"Hodousice",
    "wof:placetype":"locality"
},
  "geometry": {"coordinates":[13.1711,49.29518],"type":"Point"}
}