{
  "type": "Feature",
  "properties": {
    "gn:gn_country":"CZ",
    "gn:gn_fcode":"PPL",
    "gn:gn_pop":93,
    "gn:population":93,
    "iso:country":"CZ",
    "name:cze_x_preferred":[
        "Zdob\u00edn"
    ],
    "name:dut_x_preferred":[
        "Zdob\u00edn"
    ],
    "name:eng_x_preferred":[
        "Zdob\u00edn"
    ],
    "name:fre_x_preferred":[
        "Zdob\u00edn"
    ],
    "name:ger_x_preferred":[
        "Zdob\u00edn"
    ],
    "name:hun_x_preferred":[
        "Zdob\u00edn"
    ],
    "name:ita_x_preferred":[
        "Zdob\u00edn"
    ],
    "name:may_x_preferred":[
        "Zdob\u00edn"
    ],
    "name:nan_x_preferred":[
        "Zdob\u00edn"
    ],
    "name:per_x_preferred":[
        "\u0632\u062f\u0648\u0628\u06cc\u0646"
    ],
    "name:pol_x_preferred":[
        "Zdob\u00edn"
    ],
    "name:por_x_preferred":[
        "Zdob\u00edn"
    ],
    "name:rup_x_preferred":[
        "Zdob\u00edn"
    ],
    "name:slo_x_preferred":[
        "Zdob\u00edn"
    ],
    "name:srp_x_preferred":[
        "\u0417\u0434\u043e\u0431\u0438\u043d"
    ],
    "name:vie_x_preferred":[
        "Zdob\u00edn"
    ],
    "qs_pg:aaroncc":"CZ",
    "qs_pg:gn_country":"CZ",
    "qs_pg:gn_fcode":"PPL",
    "qs_pg:gn_pop":93,
    "qs_pg:name":"Zdob\u00edn",
    "qs_pg:name_adm0":"\u010cesk\u00e1 republika",
    "qs_pg:name_adm1":"Kr\u00e1lov\u00e9hradeck\u00fd kraj",
    "qs_pg:photos_9r":0,
    "qs_pg:photos_sr":0,
    "qs_pg:pop_sr":1,
    "qs_pg:qs_pg_placetype":"locality",
    "qs_pg:qs_pg_placetype_gp":"Town",
    "qs_pg:woe_adm0":23424810,
    "woe:adm0_id":23424810,
    "woe:name_adm0":"\u010cesk\u00e1 republika",
    "woe:name_adm1":"Kr\u00e1lov\u00e9hradeck\u00fd kraj",
    "woe:placetype":"Town",
    "wof:name":"Zdob\u00edn",
    "wof:placetype":"locality",
    "wof:population":93
},
  "geometry": {"coordinates":[15.70495,50.4153],"type":"Point"}
}