{
  "type": "Feature",
  "properties": {
    "gn:admin1_code":"82.0",
    "gn:admin2_code":"0523",
    "gn:asciiname":"Doubravice u Ceske Skalice",
    "gn:country_code":"CZ",
    "gn:dem":283,
    "gn:feature_class":"P",
    "gn:feature_code":"PPL",
    "gn:name":"Doubravice u \u010cesk\u00e9 Skalice",
    "gn:population":0,
    "gn:timezone":"Europe/Prague",
    "iso:country":"CZ",
    "wof:name":"Doubravice u Ceske Skalice",
    "wof:placetype":"locality"
},
  "geometry": {"coordinates":[15.99637,50.379],"type":"Point"}
}