{
  "type": "Feature",
  "properties": {
    "gn:admin1_code":"90.0",
    "gn:admin2_code":"0721",
    "gn:asciiname":"Chrast'any",
    "gn:country_code":"CZ",
    "gn:dem":197,
    "gn:feature_class":"P",
    "gn:feature_code":"PPL",
    "gn:name":"Chr\u00e1\u0161\u0165any",
    "gn:population":0,
    "gn:timezone":"Europe/Prague",
    "iso:country":"CZ",
    "wof:name":"Chrast'any",
    "wof:placetype":"locality"
},
  "geometry": {"coordinates":[17.49556,49.29813],"type":"Point"}
}