{
  "type": "Feature",
  "properties": {
    "gn:admin1_code":"84.0",
    "gn:admin2_code":"0714",
    "gn:asciiname":"Lovesice",
    "gn:country_code":"CZ",
    "gn:dem":205,
    "gn:feature_class":"P",
    "gn:feature_code":"PPL",
    "gn:name":"Lov\u011b\u0161ice",
    "gn:population":0,
    "gn:timezone":"Europe/Prague",
    "iso:country":"CZ",
    "wof:name":"Lovesice",
    "wof:placetype":"locality"
},
  "geometry": {"coordinates":[17.44929,49.42691],"type":"Point"}
}