{
  "type": "Feature",
  "properties": {
    "gn:admin1_code":"81.0",
    "gn:admin2_code":"0412",
    "gn:asciiname":"Horni Lomnice",
    "gn:country_code":"CZ",
    "gn:dem":523,
    "gn:feature_class":"P",
    "gn:feature_code":"PPL",
    "gn:name":"Horn\u00ed Lomnice",
    "gn:population":0,
    "gn:timezone":"Europe/Prague",
    "iso:country":"CZ",
    "name:und_x_variant":[
        "Ober Lomitz",
        "Horn\u00ed Lomnice"
    ],
    "wof:name":"Horni Lomnice",
    "wof:placetype":"locality"
},
  "geometry": {"coordinates":[13.05,50.26667],"type":"Point"}
}