{
  "type": "Feature",
  "properties": {
    "gn:gn_country":"CZ",
    "gn:gn_fcode":"PPL",
    "gn:gn_pop":290,
    "gn:population":290,
    "iso:country":"CZ",
    "name:ceb_x_preferred":[
        "Jankovice"
    ],
    "name:ces_x_preferred":[
        "Jankovice"
    ],
    "name:deu_x_preferred":[
        "Jankovice"
    ],
    "name:epo_x_preferred":[
        "Jankovice"
    ],
    "name:fra_x_preferred":[
        "Jankovice"
    ],
    "name:ita_x_preferred":[
        "Jankovice"
    ],
    "name:nld_x_preferred":[
        "Jankovice"
    ],
    "name:pol_x_preferred":[
        "Jankovice"
    ],
    "name:slk_x_preferred":[
        "Jankovice"
    ],
    "name:srp_x_preferred":[
        "\u0408\u0430\u043d\u043a\u043e\u0432\u0438\u0446\u0435"
    ],
    "name:swe_x_preferred":[
        "Jankovice"
    ],
    "qs_pg:aaroncc":"CZ",
    "qs_pg:gn_country":"CZ",
    "qs_pg:gn_fcode":"PPL",
    "qs_pg:gn_pop":290,
    "qs_pg:name":"Jankovice",
    "qs_pg:photos_9r":0,
    "qs_pg:photos_sr":0,
    "qs_pg:pop_sr":2,
    "qs_pg:qs_pg_placetype":"locality",
    "wof:name":"Jankovice",
    "wof:placetype":"locality",
    "wof:population":290
},
  "geometry": {"coordinates":[16.45901,50.04002],"type":"Point"}
}