{
  "type": "Feature",
  "properties": {
    "gn:gn_country":"CZ",
    "gn:gn_fcode":"PPL",
    "gn:gn_pop":259,
    "gn:population":259,
    "iso:country":"CZ",
    "name:ces_x_preferred":[
        "Kon\u011btopy"
    ],
    "name:eng_x_preferred":[
        "Kon\u011btopy"
    ],
    "name:fas_x_preferred":[
        "\u06a9\u0648\u0646\u06cc\u062a\u0648\u067e\u06cc"
    ],
    "name:fra_x_preferred":[
        "Kon\u011btopy"
    ],
    "name:hun_x_preferred":[
        "Kon\u011btopy"
    ],
    "name:ita_x_preferred":[
        "Kon\u011btopy"
    ],
    "name:msa_x_preferred":[
        "Kon\u011btopy"
    ],
    "name:nan_x_preferred":[
        "Kon\u011btopy"
    ],
    "name:nld_x_preferred":[
        "Kon\u011btopy"
    ],
    "name:pol_x_preferred":[
        "Kon\u011btopy"
    ],
    "name:por_x_preferred":[
        "Kon\u011btopy"
    ],
    "name:rup_x_preferred":[
        "Kon\u011btopy"
    ],
    "name:slk_x_preferred":[
        "Kon\u011btopy"
    ],
    "name:srp_x_preferred":[
        "\u041a\u043e\u045a\u0435\u0442\u043e\u043f\u0438"
    ],
    "name:swe_x_preferred":[
        "Kon\u011btopy"
    ],
    "name:vie_x_preferred":[
        "Kon\u011btopy"
    ],
    "qs_pg:aaroncc":"CZ",
    "qs_pg:gn_country":"CZ",
    "qs_pg:gn_fcode":"PPL",
    "qs_pg:gn_pop":259,
    "qs_pg:name":"Kon\u011btopy",
    "qs_pg:name_adm0":"\u010cesk\u00e1 republika",
    "qs_pg:name_adm1":"St\u0159edo\u010desk\u00fd kraj",
    "qs_pg:photos_9r":0,
    "qs_pg:photos_sr":0,
    "qs_pg:pop_sr":2,
    "qs_pg:qs_pg_placetype":"locality",
    "qs_pg:qs_pg_placetype_gp":"Town",
    "qs_pg:woe_adm0":23424810,
    "woe:adm0_id":23424810,
    "woe:name_adm0":"\u010cesk\u00e1 republika",
    "woe:name_adm1":"St\u0159edo\u010desk\u00fd kraj",
    "woe:placetype":"Town",
    "wof:name":"Kon\u011btopy",
    "wof:placetype":"locality",
    "wof:population":259
},
  "geometry": {"coordinates":[14.65382,50.2764],"type":"Point"}
}