{
  "type": "Feature",
  "properties": {
    "gn:admin1_code":"83.0",
    "gn:admin2_code":"0512",
    "gn:asciiname":"Albrechtice",
    "gn:country_code":"CZ",
    "gn:dem":613,
    "gn:feature_class":"P",
    "gn:feature_code":"PPL",
    "gn:name":"Albrechtice",
    "gn:population":0,
    "gn:timezone":"Europe/Prague",
    "iso:country":"CZ",
    "name:und_x_variant":[
        "Albrechtsdorf",
        "Albrechtice"
    ],
    "wof:name":"Albrechtice",
    "wof:placetype":"locality"
},
  "geometry": {"coordinates":[15.28618,50.76008],"type":"Point"}
}