{
  "type": "Feature",
  "properties": {
    "gn:admin1_code":"83.0",
    "gn:admin2_code":"0512",
    "gn:asciiname":"Albrechtice",
    "gn:country_code":"CZ",
    "gn:dem":613,
    "gn:feature_class":"P",
    "gn:feature_code":"PPL",
    "gn:name":"Albrechtice",
    "gn:population":0,
    "gn:timezone":"Europe/Prague",
    "iso:country":"CZ",
    "name:ceb_x_preferred":[
        "Albrechtice"
    ],
    "name:ces_x_preferred":[
        "Albrechtice"
    ],
    "name:deu_x_preferred":[
        "Albrechtice"
    ],
    "name:epo_x_preferred":[
        "Albrechtice"
    ],
    "name:fra_x_preferred":[
        "Albrechtice"
    ],
    "name:ita_x_preferred":[
        "Albrechtice"
    ],
    "name:nld_x_preferred":[
        "Albrechtice"
    ],
    "name:pol_x_preferred":[
        "Albrechtice"
    ],
    "name:slk_x_preferred":[
        "Albrechtice"
    ],
    "name:srp_x_preferred":[
        "\u0410\u043b\u0431\u0440\u0435\u0445\u0442\u0438\u0446\u0435"
    ],
    "name:swe_x_preferred":[
        "Albrechtice"
    ],
    "name:und_x_variant":[
        "Albrechtsdorf"
    ],
    "wof:name":"Albrechtice",
    "wof:placetype":"locality"
},
  "geometry": {"coordinates":[15.28618,50.76008],"type":"Point"}
}