{
  "type": "Feature",
  "properties": {
    "gn:admin1_code":"80.0",
    "gn:admin2_code":"0615",
    "gn:asciiname":"Moravska Svratka",
    "gn:country_code":"CZ",
    "gn:dem":678,
    "gn:feature_class":"P",
    "gn:feature_code":"PPL",
    "gn:name":"Moravsk\u00e1 Svratka",
    "gn:population":0,
    "gn:timezone":"Europe/Prague",
    "iso:country":"CZ",
    "wof:name":"Moravska Svratka",
    "wof:placetype":"locality"
},
  "geometry": {"coordinates":[16.02225,49.69918],"type":"Point"}
}