{
  "type": "Feature",
  "properties": {
    "iso:country":"CZ",
    "name:ces_x_preferred":[
        "Star\u00e1 Plesn\u00e1"
    ],
    "name:cze_x_colloquial":[
        "Stara Plesna"
    ],
    "name:unk_x_variant":[
        "Star\u00e1 Plesn\u00e1"
    ],
    "qs:gn_fcode":"PPL",
    "qs:gn_local":0,
    "qs:gn_namadm1":"85",
    "qs:gn_name":"Star\u00e1 Plesn\u00e1",
    "qs:local_max":2778,
    "qs:local_sum":9373,
    "qs:localhoods":17,
    "qs:name":"Star\u00e1 Plesn\u00e1",
    "qs:name_adm0":"\u010cesk\u00e1 republika",
    "qs:name_adm1":"Moravskoslezsk\u00fd kraj",
    "qs:name_adm2":"Ostrava",
    "qs:name_lau":"Ostrava",
    "qs:name_local":"Ostrava",
    "qs:photo_max":7,
    "qs:photo_sum":18,
    "qs:placetype":"Suburb",
    "qs:quad_count":9,
    "qs:woe_adm0":23424810,
    "qs:woe_adm1":20070471,
    "qs:woe_adm2":12582577,
    "qs:woe_lau":12607114,
    "qs:woe_local":795610,
    "qs:woe_ver":"7.10.0",
    "wof:lang":[
        "cze"
    ],
    "wof:name":"Star\u00e1 Plesn\u00e1",
    "wof:placetype":"neighbourhood"
},
  "geometry": {"coordinates":[18.175049,49.886966],"type":"Point"}
}