{
  "type": "Feature",
  "properties": {
    "gn:admin1_code":"81.0",
    "gn:admin2_code":"0412",
    "gn:asciiname":"Hory",
    "gn:country_code":"CZ",
    "gn:dem":510,
    "gn:feature_class":"P",
    "gn:feature_code":"PPL",
    "gn:name":"Hory",
    "gn:population":195,
    "gn:timezone":"Europe/Prague",
    "iso:country":"CZ",
    "name:azb_x_preferred":[
        "\u0647\u0648\u0631\u06cc"
    ],
    "name:ceb_x_preferred":[
        "Hory"
    ],
    "name:ces_x_preferred":[
        "Hory"
    ],
    "name:deu_x_preferred":[
        "Hory"
    ],
    "name:eus_x_preferred":[
        "Hory"
    ],
    "name:fas_x_preferred":[
        "\u0647\u0648\u0631\u06cc"
    ],
    "name:hun_x_preferred":[
        "Hory"
    ],
    "name:ita_x_preferred":[
        "Hory"
    ],
    "name:msa_x_preferred":[
        "Hory"
    ],
    "name:nld_x_preferred":[
        "Hory"
    ],
    "name:pol_x_preferred":[
        "Hory"
    ],
    "name:por_x_preferred":[
        "Hory"
    ],
    "name:slk_x_preferred":[
        "Hory"
    ],
    "name:spa_x_preferred":[
        "Hory"
    ],
    "name:srp_x_preferred":[
        "\u0425\u043e\u0440\u0438"
    ],
    "name:swe_x_preferred":[
        "Hory"
    ],
    "name:und_x_variant":[
        "Horn"
    ],
    "name:vie_x_preferred":[
        "Hory"
    ],
    "wof:name":"Hory",
    "wof:placetype":"locality",
    "wof:population":195
},
  "geometry": {"coordinates":[12.78988,50.21374],"type":"Point"}
}