{
  "type": "Feature",
  "properties": {
    "gn:admin1_code":"81.0",
    "gn:admin2_code":"0412",
    "gn:asciiname":"Hory",
    "gn:country_code":"CZ",
    "gn:dem":510,
    "gn:feature_class":"P",
    "gn:feature_code":"PPL",
    "gn:name":"Hory",
    "gn:population":195,
    "gn:timezone":"Europe/Prague",
    "iso:country":"CZ",
    "name:und_x_variant":[
        "Horn"
    ],
    "wof:name":"Hory",
    "wof:placetype":"locality",
    "wof:population":195
},
  "geometry": {"coordinates":[12.78988,50.21374],"type":"Point"}
}