{
  "type": "Feature",
  "properties": {
    "gn:admin1_code":"81.0",
    "gn:admin2_code":"0412",
    "gn:asciiname":"Litoltov",
    "gn:country_code":"CZ",
    "gn:dem":719,
    "gn:feature_class":"P",
    "gn:feature_code":"PPL",
    "gn:name":"Litoltov",
    "gn:population":0,
    "gn:timezone":"Europe/Prague",
    "iso:country":"CZ",
    "name:und_x_variant":[
        "Liesen",
        "Litoltov"
    ],
    "wof:name":"Litoltov",
    "wof:placetype":"locality"
},
  "geometry": {"coordinates":[13.16667,50.31667],"type":"Point"}
}