{
  "type": "Feature",
  "properties": {
    "gn:admin1_code":"89",
    "gn:admin2_code":"0426",
    "gn:asciiname":"Strelna",
    "gn:country_code":"CZ",
    "gn:dem":347,
    "gn:feature_class":"P",
    "gn:feature_code":"PPL",
    "gn:name":"St\u0159eln\u00e1",
    "gn:population":0,
    "gn:timezone":"Europe/Prague",
    "iso:country":"CZ",
    "name:afr_x_preferred":[
        "Strelna"
    ],
    "name:aze_x_preferred":[
        "Strelna"
    ],
    "name:bar_x_preferred":[
        "Strelna"
    ],
    "name:bel_x_preferred":[
        "\u0421\u0442\u0440\u044d\u043b\u044c\u043d\u0430"
    ],
    "name:deu_x_preferred":[
        "Strelna"
    ],
    "name:est_x_preferred":[
        "Strelna"
    ],
    "name:fin_x_preferred":[
        "Strelna"
    ],
    "name:fra_x_preferred":[
        "Strelna"
    ],
    "name:hsb_x_preferred":[
        "Strelna"
    ],
    "name:hun_x_preferred":[
        "Sztrelna"
    ],
    "name:hye_x_preferred":[
        "\u054d\u057f\u0580\u0565\u056c\u0576\u0561"
    ],
    "name:ita_x_preferred":[
        "Strel'na"
    ],
    "name:kat_x_preferred":[
        "\u10e1\u10e2\u10e0\u10d4\u10da\u10dc\u10d0"
    ],
    "name:lat_x_preferred":[
        "Strelna"
    ],
    "name:nor_x_preferred":[
        "Strelna"
    ],
    "name:pol_x_preferred":[
        "Strielna"
    ],
    "name:rus_x_preferred":[
        "\u0421\u0442\u0440\u0435\u043b\u044c\u043d\u0430"
    ],
    "name:spa_x_preferred":[
        "Strelna"
    ],
    "name:swe_x_preferred":[
        "Strelna"
    ],
    "name:ukr_x_preferred":[
        "\u0421\u0442\u0440\u0454\u043b\u044c\u043d\u0430"
    ],
    "name:und_x_variant":[
        "Strahl",
        "St\u0159eln\u00e1"
    ],
    "name:zho_x_preferred":[
        "\u65af\u7279\u5217\u5229\u7d0d"
    ],
    "wof:name":"Strelna",
    "wof:placetype":"locality"
},
  "geometry": {"coordinates":[13.74782,50.66623],"type":"Point"}
}