{
  "type": "Feature",
  "properties": {
    "gn:admin1_code":"89",
    "gn:admin2_code":"0426",
    "gn:asciiname":"Strelna",
    "gn:country_code":"CZ",
    "gn:dem":347,
    "gn:feature_class":"P",
    "gn:feature_code":"PPL",
    "gn:name":"St\u0159eln\u00e1",
    "gn:population":0,
    "gn:timezone":"Europe/Prague",
    "iso:country":"CZ",
    "name:und_x_variant":[
        "Strahl",
        "St\u0159eln\u00e1"
    ],
    "wof:name":"Strelna",
    "wof:placetype":"locality"
},
  "geometry": {"coordinates":[13.74782,50.66623],"type":"Point"}
}