{
  "type": "Feature",
  "properties": {
    "gn:gn_country":"CZ",
    "gn:gn_fcode":"PPL",
    "gn:gn_pop":229,
    "gn:population":229,
    "iso:country":"CZ",
    "name:bul_x_preferred":[
        "\u041a\u0440\u0430\u0445\u0443\u043b\u043e\u0432"
    ],
    "name:ces_x_preferred":[
        "Krahulov"
    ],
    "name:eng_x_preferred":[
        "Krahulov"
    ],
    "name:fas_x_preferred":[
        "\u06a9\u0631\u0627\u0647\u0648\u0644\u0648\u0648"
    ],
    "name:fra_x_preferred":[
        "Krahulov"
    ],
    "name:hun_x_preferred":[
        "Krahulov"
    ],
    "name:ita_x_preferred":[
        "Krahulov"
    ],
    "name:msa_x_preferred":[
        "Krahulov"
    ],
    "name:nan_x_preferred":[
        "Krahulov"
    ],
    "name:nld_x_preferred":[
        "Krahulov"
    ],
    "name:por_x_preferred":[
        "Krahulov"
    ],
    "name:rup_x_preferred":[
        "Krahulov"
    ],
    "name:slk_x_preferred":[
        "Krahulov"
    ],
    "name:swe_x_preferred":[
        "Krahulov"
    ],
    "name:vie_x_preferred":[
        "Krahulov"
    ],
    "qs_pg:aaroncc":"CZ",
    "qs_pg:gn_country":"CZ",
    "qs_pg:gn_fcode":"PPL",
    "qs_pg:gn_pop":229,
    "qs_pg:name":"Krahulov",
    "qs_pg:name_adm0":"\u010cesk\u00e1 republika",
    "qs_pg:name_adm1":"Kraj Vyso\u010dina",
    "qs_pg:photos_9k":1,
    "qs_pg:photos_9r":1,
    "qs_pg:photos_all":1,
    "qs_pg:photos_sr":0,
    "qs_pg:pop_sr":2,
    "qs_pg:qs_pg_placetype":"locality",
    "qs_pg:qs_pg_placetype_gp":"Town",
    "qs_pg:woe_adm0":23424810,
    "woe:adm0_id":23424810,
    "woe:name_adm0":"\u010cesk\u00e1 republika",
    "woe:name_adm1":"Kraj Vyso\u010dina",
    "woe:placetype":"Town",
    "wof:name":"Krahulov",
    "wof:placetype":"locality",
    "wof:population":229
},
  "geometry": {"coordinates":[15.80814,49.22291],"type":"Point"}
}