{
  "type": "Feature",
  "properties": {
    "gn:admin1_code":"89.0",
    "gn:admin2_code":"0423",
    "gn:asciiname":"Drzovice",
    "gn:cc2":"CZ",
    "gn:country_code":"CZ",
    "gn:dem":312,
    "gn:feature_class":"P",
    "gn:feature_code":"PPL",
    "gn:name":"Dr\u017eovice",
    "gn:population":0,
    "gn:timezone":"Europe/Prague",
    "iso:country":"CZ",
    "name:und_x_variant":[
        "Tirschowitz"
    ],
    "wof:name":"Drzovice",
    "wof:placetype":"locality"
},
  "geometry": {"coordinates":[14.32617,50.61309],"type":"Point"}
}