{
  "type": "Feature",
  "properties": {
    "iso:country":"CZ",
    "name:azb_x_preferred":[
        "\u0648\u0648\u06cc\u062a\u0627\u0646\u0648\u0648"
    ],
    "name:ceb_x_preferred":[
        "Vojtanov"
    ],
    "name:ces_x_preferred":[
        "Vojtanov"
    ],
    "name:deu_x_preferred":[
        "Vojtanov"
    ],
    "name:eus_x_preferred":[
        "Vojtanov"
    ],
    "name:fas_x_preferred":[
        "\u0648\u0648\u06cc\u062a\u0627\u0646\u0648\u0648"
    ],
    "name:fra_x_preferred":[
        "Vojtanov"
    ],
    "name:hun_x_preferred":[
        "Vojtanov"
    ],
    "name:ita_x_preferred":[
        "Vojtanov"
    ],
    "name:msa_x_preferred":[
        "Vojtanov"
    ],
    "name:nld_x_preferred":[
        "Vojtanov"
    ],
    "name:pol_x_preferred":[
        "Vojtanov"
    ],
    "name:por_x_preferred":[
        "Vojtanov"
    ],
    "name:slk_x_preferred":[
        "Vojtanov"
    ],
    "name:spa_x_preferred":[
        "Vojtanov"
    ],
    "name:srp_x_preferred":[
        "\u0412\u043e\u0458\u0442\u0430\u043d\u043e\u0432"
    ],
    "name:swe_x_preferred":[
        "Vojtanov"
    ],
    "name:vie_x_preferred":[
        "Vojtanov"
    ],
    "qs_pg:aaroncc":"CZ",
    "qs_pg:name":"Vojtanov",
    "qs_pg:name_adm0":"\u010cesk\u00e1 republika",
    "qs_pg:name_adm1":"Karlovarsk\u00fd kraj",
    "qs_pg:photos":8,
    "qs_pg:photos_1k":2,
    "qs_pg:photos_9k":1,
    "qs_pg:photos_9r":1,
    "qs_pg:photos_all":8,
    "qs_pg:photos_sr":1,
    "qs_pg:pop_sr":0,
    "qs_pg:qs_pg_placetype":"localadmin",
    "qs_pg:qs_pg_placetype_gp":"LocalAdmin",
    "qs_pg:woe_adm0":23424810,
    "woe:adm0_id":23424810,
    "woe:name_adm0":"\u010cesk\u00e1 republika",
    "woe:name_adm1":"Karlovarsk\u00fd kraj",
    "woe:placetype":"LocalAdmin",
    "wof:name":"Vojtanov",
    "wof:placetype":"localadmin"
},
  "geometry": {"coordinates":[12.3169,50.16618],"type":"Point"}
}