{
  "type": "Feature",
  "properties": {
    "gn:admin1_code":"89.0",
    "gn:admin2_code":"0423",
    "gn:asciiname":"Rochov",
    "gn:cc2":"CZ",
    "gn:country_code":"CZ",
    "gn:dem":198,
    "gn:feature_class":"P",
    "gn:feature_code":"PPL",
    "gn:name":"Rochov",
    "gn:population":0,
    "gn:timezone":"Europe/Prague",
    "iso:country":"CZ",
    "name:azb_x_preferred":[
        "\u0631\u0648\u062e\u0648\u0648"
    ],
    "name:ceb_x_preferred":[
        "Rochov"
    ],
    "name:ces_x_preferred":[
        "Rochov"
    ],
    "name:deu_x_preferred":[
        "Rochov"
    ],
    "name:epo_x_preferred":[
        "Rochov"
    ],
    "name:eus_x_preferred":[
        "Rochov"
    ],
    "name:fas_x_preferred":[
        "\u0631\u0648\u062e\u0648\u0648"
    ],
    "name:fra_x_preferred":[
        "Rochov"
    ],
    "name:hun_x_preferred":[
        "Rochov"
    ],
    "name:ita_x_preferred":[
        "Rochov"
    ],
    "name:msa_x_preferred":[
        "Rochov"
    ],
    "name:nld_x_preferred":[
        "Rochov"
    ],
    "name:por_x_preferred":[
        "Rochov"
    ],
    "name:slk_x_preferred":[
        "Rochov"
    ],
    "name:spa_x_preferred":[
        "Rochov"
    ],
    "name:srp_x_preferred":[
        "\u0420\u043e\u0445\u043e\u0432"
    ],
    "name:swe_x_preferred":[
        "Rochov"
    ],
    "name:und_x_variant":[
        "Roche"
    ],
    "name:vie_x_preferred":[
        "Rochov"
    ],
    "wof:name":"Rochov",
    "wof:placetype":"locality"
},
  "geometry": {"coordinates":[14.34179,50.54769],"type":"Point"}
}