{
  "type": "Feature",
  "properties": {
    "gn:admin1_code":"78.0",
    "gn:admin2_code":"0626",
    "gn:asciiname":"Lhota",
    "gn:country_code":"CZ",
    "gn:dem":362,
    "gn:feature_class":"P",
    "gn:feature_code":"PPL",
    "gn:name":"Lhota",
    "gn:population":0,
    "gn:timezone":"Europe/Prague",
    "iso:country":"CZ",
    "wof:name":"Lhota",
    "wof:placetype":"locality"
},
  "geometry": {"coordinates":[16.9495,49.31169000000001],"type":"Point"}
}