{
  "type": "Feature",
  "properties": {
    "gn:admin1_code":"83.0",
    "gn:admin2_code":"0513",
    "gn:asciiname":"Modlibohov",
    "gn:country_code":"CZ",
    "gn:dem":360,
    "gn:feature_class":"P",
    "gn:feature_code":"PPL",
    "gn:name":"Modlibohov",
    "gn:population":0,
    "gn:timezone":"Europe/Prague",
    "iso:country":"CZ",
    "wof:name":"Modlibohov",
    "wof:placetype":"locality"
},
  "geometry": {"coordinates":[14.98191,50.68453],"type":"Point"}
}