{
  "type": "Feature",
  "properties": {
    "iso:country":"CZ",
    "wof:name":"Praha 21",
    "wof:placetype":"neighbourhood"
},
  "geometry": {"coordinates":[14.65045768817718,50.08106529410586],"type":"Point"}
}