{
  "type": "Feature",
  "properties": {
    "gn:country":"CZ",
    "gn:fcode":"PPL",
    "gn:population":732,
    "iso:country":"CZ",
    "name:azb_x_preferred":[
        "\u0632\u0627\u0645\u0631\u0633\u06a9"
    ],
    "name:ceb_x_preferred":[
        "Z\u00e1mrsk"
    ],
    "name:ces_x_preferred":[
        "Z\u00e1mrsk"
    ],
    "name:deu_x_preferred":[
        "Z\u00e1mrsk"
    ],
    "name:eng_x_preferred":[
        "Z\u00e1mrsk"
    ],
    "name:epo_x_preferred":[
        "Z\u00e1mrsk"
    ],
    "name:eus_x_preferred":[
        "Z\u00e1mrsk"
    ],
    "name:fas_x_preferred":[
        "\u0632\u0627\u0645\u0631\u0633\u06a9"
    ],
    "name:fra_x_preferred":[
        "Z\u00e1mrsk"
    ],
    "name:hun_x_preferred":[
        "Z\u00e1mrsk"
    ],
    "name:ita_x_preferred":[
        "Z\u00e1mrsk"
    ],
    "name:msa_x_preferred":[
        "Z\u00e1mrsk"
    ],
    "name:nan_x_preferred":[
        "Z\u00e1mrsk"
    ],
    "name:nld_x_preferred":[
        "Z\u00e1mrsk"
    ],
    "name:por_x_preferred":[
        "Z\u00e1mrsk"
    ],
    "name:rup_x_preferred":[
        "Z\u00e1mrsk"
    ],
    "name:slk_x_preferred":[
        "Z\u00e1mrsk"
    ],
    "name:slv_x_preferred":[
        "Z\u00e1mrsk"
    ],
    "name:spa_x_preferred":[
        "Z\u00e1mrsk"
    ],
    "name:srp_x_preferred":[
        "\u0417\u0430\u043c\u0440\u0441\u043a"
    ],
    "name:swe_x_preferred":[
        "Z\u00e1mrsk"
    ],
    "name:vie_x_preferred":[
        "Z\u00e1mrsk"
    ],
    "qs_pg:aaroncc":"CZ",
    "qs_pg:gn_country":"CZ",
    "qs_pg:gn_fcode":"PPL",
    "qs_pg:gn_pop":732,
    "qs_pg:name":"Z\u00e1mrsk",
    "qs_pg:name_adm0":"\u010cesk\u00e1 republika",
    "qs_pg:name_adm1":"Pardubick\u00fd kraj",
    "qs_pg:photos_9r":0,
    "qs_pg:photos_sr":0,
    "qs_pg:pop_sr":2,
    "qs_pg:qs_pg_placetype":"locality",
    "qs_pg:qs_pg_placetype_gp":"Town",
    "qs_pg:woe_adm0":23424810,
    "woe:adm0_id":23424810,
    "woe:name_adm0":"\u010cesk\u00e1 republika",
    "woe:name_adm1":"Pardubick\u00fd kraj",
    "woe:placetype":"Town",
    "wof:name":"Z\u00e1mrsk",
    "wof:placetype":"locality",
    "wof:population":732
},
  "geometry": {"coordinates":[16.12874,49.98618],"type":"Point"}
}