{
  "type": "Feature",
  "properties": {
    "gn:gn_country":"CZ",
    "gn:gn_fcode":"PPL",
    "gn:gn_pop":180,
    "gn:population":180,
    "iso:country":"CZ",
    "name:cze_x_preferred":[
        "Kr\u00e1sn\u00fd Les"
    ],
    "name:dut_x_preferred":[
        "Kr\u00e1sn\u00fd Les"
    ],
    "name:eng_x_preferred":[
        "Kr\u00e1sn\u00fd Les"
    ],
    "name:fre_x_preferred":[
        "Kr\u00e1sn\u00fd Les"
    ],
    "name:ger_x_preferred":[
        "Kr\u00e1sn\u00fd Les"
    ],
    "name:hun_x_preferred":[
        "Kr\u00e1sn\u00fd Les"
    ],
    "name:ita_x_preferred":[
        "Kr\u00e1sn\u00fd Les"
    ],
    "name:may_x_preferred":[
        "Kr\u00e1sn\u00fd Les"
    ],
    "name:nan_x_preferred":[
        "Kr\u00e1sn\u00fd Les"
    ],
    "name:pol_x_preferred":[
        "Kr\u00e1sn\u00fd Les"
    ],
    "name:por_x_preferred":[
        "Kr\u00e1sn\u00fd Les"
    ],
    "name:rup_x_preferred":[
        "Kr\u00e1sn\u00fd Les"
    ],
    "name:slo_x_preferred":[
        "Kr\u00e1sn\u00fd Les"
    ],
    "name:srp_x_preferred":[
        "\u041a\u0440\u0430\u0441\u043d\u0438 \u041b\u0435\u0441"
    ],
    "name:swe_x_preferred":[
        "Kr\u00e1sn\u00fd Les"
    ],
    "name:unk_x_variant":[
        "Schoenwald"
    ],
    "name:vie_x_preferred":[
        "Kr\u00e1sn\u00fd Les"
    ],
    "qs_pg:aaroncc":"CZ",
    "qs_pg:gn_country":"CZ",
    "qs_pg:gn_fcode":"PPL",
    "qs_pg:gn_pop":180,
    "qs_pg:name":"Kr\u00e1sn\u00fd Les",
    "qs_pg:name_adm0":"\u010cesk\u00e1 republika",
    "qs_pg:name_adm1":"Karlovarsk\u00fd kraj",
    "qs_pg:photos_9k":1,
    "qs_pg:photos_9r":1,
    "qs_pg:photos_all":5,
    "qs_pg:photos_sr":0,
    "qs_pg:pop_sr":1,
    "qs_pg:qs_pg_placetype":"locality",
    "qs_pg:qs_pg_placetype_gp":"Town",
    "qs_pg:woe_adm0":23424810,
    "woe:adm0_id":23424810,
    "woe:name_adm0":"\u010cesk\u00e1 republika",
    "woe:name_adm1":"Karlovarsk\u00fd kraj",
    "woe:placetype":"Town",
    "wof:name":"Kr\u00e1sn\u00fd Les",
    "wof:placetype":"locality",
    "wof:population":180
},
  "geometry": {"coordinates":[13.00274,50.34485],"type":"Point"}
}