{
  "type": "Feature",
  "properties": {
    "gn:admin1_code":"78.0",
    "gn:admin2_code":"0621",
    "gn:asciiname":"Privest'",
    "gn:country_code":"CZ",
    "gn:dem":446,
    "gn:feature_class":"P",
    "gn:feature_code":"PPL",
    "gn:name":"P\u0159\u00edv\u011bs\u0165",
    "gn:population":0,
    "gn:timezone":"Europe/Prague",
    "iso:country":"CZ",
    "wof:name":"Privest'",
    "wof:placetype":"locality"
},
  "geometry": {"coordinates":[16.72072,49.56571],"type":"Point"}
}