{
  "type": "Feature",
  "properties": {
    "gn:admin1_code":"89",
    "gn:admin2_code":"0424",
    "gn:asciiname":"Vojnice",
    "gn:country_code":"CZ",
    "gn:dem":188,
    "gn:feature_class":"P",
    "gn:feature_code":"PPL",
    "gn:name":"Vojnice",
    "gn:population":0,
    "gn:timezone":"Europe/Prague",
    "iso:country":"CZ",
    "wof:name":"Vojnice",
    "wof:placetype":"locality"
},
  "geometry": {"coordinates":[13.94236,50.42204],"type":"Point"}
}