{
  "type": "Feature",
  "properties": {
    "gn:admin1_code":"84",
    "gn:admin2_code":"0711",
    "gn:asciiname":"Starost",
    "gn:country_code":"CZ",
    "gn:dem":375,
    "gn:feature_class":"P",
    "gn:feature_code":"PPL",
    "gn:name":"Starost",
    "gn:population":0,
    "gn:timezone":"Europe/Prague",
    "iso:country":"CZ",
    "name:und_x_variant":[
        "Sorge",
        "Starost"
    ],
    "wof:name":"Starost",
    "wof:placetype":"locality"
},
  "geometry": {"coordinates":[17.10615,50.30177],"type":"Point"}
}