{
  "type": "Feature",
  "properties": {
    "gn:admin1_code":"82.0",
    "gn:admin2_code":"0525",
    "gn:asciiname":"Lipnice",
    "gn:country_code":"CZ",
    "gn:dem":337,
    "gn:feature_class":"P",
    "gn:feature_code":"PPL",
    "gn:name":"Lipnice",
    "gn:population":0,
    "gn:timezone":"Europe/Prague",
    "iso:country":"CZ",
    "name:fra_x_preferred":[
        "Lipnice"
    ],
    "name:pol_x_preferred":[
        "Lipnice"
    ],
    "name:ukr_x_preferred":[
        "\u041b\u0456\u043f\u043d\u0456\u0446\u0435"
    ],
    "wof:name":"Lipnice",
    "wof:placetype":"locality"
},
  "geometry": {"coordinates":[15.78621,50.42211],"type":"Point"}
}