{
  "type": "Feature",
  "properties": {
    "iso:country":"CZ",
    "name:azb_x_preferred":[
        "\u0627\u0648\u06a9\u0631\u06cc\u0634\u06a9\u06cc"
    ],
    "name:ceb_x_preferred":[
        "Ok\u0159\u00ed\u0161ky"
    ],
    "name:ces_x_preferred":[
        "Ok\u0159\u00ed\u0161ky"
    ],
    "name:epo_x_preferred":[
        "Ok\u0159\u00ed\u0161ky"
    ],
    "name:eus_x_preferred":[
        "Ok\u0159\u00ed\u0161ky"
    ],
    "name:fas_x_preferred":[
        "\u0627\u0648\u06a9\u0631\u06cc\u0634\u06a9\u06cc"
    ],
    "name:fra_x_preferred":[
        "Ok\u0159\u00ed\u0161ky"
    ],
    "name:hun_x_preferred":[
        "Ok\u0159\u00ed\u0161ky"
    ],
    "name:ita_x_preferred":[
        "Ok\u0159\u00ed\u0161ky"
    ],
    "name:msa_x_preferred":[
        "Ok\u0159\u00ed\u0161ky"
    ],
    "name:nld_x_preferred":[
        "Ok\u0159\u00ed\u0161ky"
    ],
    "name:por_x_preferred":[
        "Ok\u0159\u00ed\u0161ky"
    ],
    "name:slk_x_preferred":[
        "Ok\u0159\u00ed\u0161ky"
    ],
    "name:spa_x_preferred":[
        "Ok\u0159\u00ed\u0161ky"
    ],
    "name:srp_x_preferred":[
        "\u041e\u043a\u0440\u0438\u0448\u043a\u0438"
    ],
    "name:swe_x_preferred":[
        "Ok\u0159\u00ed\u0161ky"
    ],
    "name:vie_x_preferred":[
        "Ok\u0159\u00ed\u0161ky"
    ],
    "qs_pg:aaroncc":"CZ",
    "qs_pg:name":"Ok\u0159\u00ed\u0161ky",
    "qs_pg:name_adm0":"\u010cesk\u00e1 republika",
    "qs_pg:name_adm1":"Kraj Vyso\u010dina",
    "qs_pg:photos":1,
    "qs_pg:photos_1k":1,
    "qs_pg:photos_9k":1,
    "qs_pg:photos_9r":1,
    "qs_pg:photos_all":15,
    "qs_pg:photos_sr":1,
    "qs_pg:pop_sr":0,
    "qs_pg:qs_pg_placetype":"localadmin",
    "qs_pg:qs_pg_placetype_gp":"LocalAdmin",
    "qs_pg:woe_adm0":23424810,
    "woe:adm0_id":23424810,
    "woe:name_adm0":"\u010cesk\u00e1 republika",
    "woe:name_adm1":"Kraj Vyso\u010dina",
    "woe:placetype":"LocalAdmin",
    "wof:name":"Ok\u0159\u00ed\u0161ky",
    "wof:placetype":"localadmin"
},
  "geometry": {"coordinates":[15.77244,49.248058],"type":"Point"}
}