{
  "type": "Feature",
  "properties": {
    "gn:admin1_code":"79",
    "gn:admin2_code":"0317",
    "gn:asciiname":"Vsechlapy",
    "gn:country_code":"CZ",
    "gn:dem":505,
    "gn:feature_class":"P",
    "gn:feature_code":"PPL",
    "gn:name":"V\u0161echlapy",
    "gn:population":0,
    "gn:timezone":"Europe/Prague",
    "iso:country":"CZ",
    "wof:name":"Vsechlapy",
    "wof:placetype":"locality"
},
  "geometry": {"coordinates":[14.55748,49.32701],"type":"Point"}
}