{
  "type": "Feature",
  "properties": {
    "gn:admin1_code":"79.0",
    "gn:admin2_code":"0312",
    "gn:asciiname":"Kyselov",
    "gn:country_code":"CZ",
    "gn:dem":726,
    "gn:feature_class":"P",
    "gn:feature_code":"PPL",
    "gn:name":"Kyselov",
    "gn:population":0,
    "gn:timezone":"Europe/Prague",
    "iso:country":"CZ",
    "name:und_x_variant":[
        "Sarau",
        "Kyselov"
    ],
    "wof:name":"Kyselov",
    "wof:placetype":"locality"
},
  "geometry": {"coordinates":[14.06667,48.68333],"type":"Point"}
}