{
  "type": "Feature",
  "properties": {
    "gn:admin1_code":"87",
    "gn:admin2_code":"0325",
    "gn:asciiname":"Vrtba",
    "gn:country_code":"CZ",
    "gn:dem":518,
    "gn:feature_class":"P",
    "gn:feature_code":"PPL",
    "gn:name":"Vrtba",
    "gn:population":0,
    "gn:timezone":"Europe/Prague",
    "iso:country":"CZ",
    "wof:name":"Vrtba",
    "wof:placetype":"locality"
},
  "geometry": {"coordinates":[13.24918,49.88486],"type":"Point"}
}