{
  "type": "Feature",
  "properties": {
    "gn:admin1_code":"84.0",
    "gn:admin2_code":"0711",
    "gn:asciiname":"Dolni Fort Mlatci Zahradnici",
    "gn:country_code":"CZ",
    "gn:dem":282,
    "gn:feature_class":"P",
    "gn:feature_code":"PPL",
    "gn:name":"Doln\u00ed Fo\u0159t Mlatci Zahradn\u00edci",
    "gn:population":0,
    "gn:timezone":"Europe/Prague",
    "iso:country":"CZ",
    "name:und_x_variant":[
        "Niederforst-Dreschg\u00e4rtner",
        "Doln\u00ed Fo\u0159t Mlatci Zahradn\u00edci"
    ],
    "wof:name":"Dolni Fort Mlatci Zahradnici",
    "wof:placetype":"locality"
},
  "geometry": {"coordinates":[17.03622,50.37445],"type":"Point"}
}