{
  "type": "Feature",
  "properties": {
    "gn:country":"CZ",
    "gn:fcode":"PPL",
    "gn:population":54,
    "iso:country":"CZ",
    "name:azb_x_preferred":[
        "\u06a9\u0631\u0627\u062a\u0648\u0634\u06cc\u0646"
    ],
    "name:ces_x_preferred":[
        "Kratu\u0161\u00edn"
    ],
    "name:deu_x_preferred":[
        "Kratu\u0161\u00edn"
    ],
    "name:eng_x_preferred":[
        "Kratu\u0161\u00edn"
    ],
    "name:eus_x_preferred":[
        "Kratu\u0161\u00edn"
    ],
    "name:fas_x_preferred":[
        "\u06a9\u0631\u0627\u062a\u0648\u0634\u06cc\u0646"
    ],
    "name:fra_x_preferred":[
        "Kratu\u0161\u00edn"
    ],
    "name:hun_x_preferred":[
        "Kratu\u0161\u00edn"
    ],
    "name:ita_x_preferred":[
        "Kratu\u0161\u00edn"
    ],
    "name:msa_x_preferred":[
        "Kratu\u0161\u00edn"
    ],
    "name:nan_x_preferred":[
        "Kratu\u0161\u00edn"
    ],
    "name:nld_x_preferred":[
        "Kratu\u0161\u00edn"
    ],
    "name:por_x_preferred":[
        "Kratu\u0161\u00edn"
    ],
    "name:slk_x_preferred":[
        "Kratu\u0161\u00edn"
    ],
    "name:spa_x_preferred":[
        "Kratu\u0161\u00edn"
    ],
    "name:srp_x_preferred":[
        "\u041a\u0440\u0430\u0442\u0443\u0448\u0438\u043d"
    ],
    "name:vie_x_preferred":[
        "Kratu\u0161\u00edn"
    ],
    "qs_pg:aaroncc":"CZ",
    "qs_pg:gn_country":"CZ",
    "qs_pg:gn_fcode":"PPL",
    "qs_pg:gn_pop":54,
    "qs_pg:name":"Kratu\u0161\u00edn",
    "qs_pg:name_adm0":"\u010cesk\u00e1 republika",
    "qs_pg:name_adm1":"Jiho\u010desk\u00fd kraj",
    "qs_pg:photos_9r":0,
    "qs_pg:photos_sr":0,
    "qs_pg:pop_sr":1,
    "qs_pg:qs_pg_placetype":"locality",
    "qs_pg:qs_pg_placetype_gp":"Town",
    "qs_pg:woe_adm0":23424810,
    "woe:adm0_id":23424810,
    "woe:name_adm0":"\u010cesk\u00e1 republika",
    "woe:name_adm1":"Jiho\u010desk\u00fd kraj",
    "woe:placetype":"Town",
    "wof:name":"Kratu\u0161\u00edn",
    "wof:placetype":"locality",
    "wof:population":54
},
  "geometry": {"coordinates":[13.92851,49.02025],"type":"Point"}
}