{
  "type": "Feature",
  "properties": {
    "gn:admin1_code":"88.0",
    "gn:admin2_code":"0206",
    "gn:asciiname":"Horni Privory",
    "gn:country_code":"CZ",
    "gn:dem":175,
    "gn:feature_class":"P",
    "gn:feature_code":"PPL",
    "gn:name":"Horn\u00ed P\u0159\u00edvory",
    "gn:population":0,
    "gn:timezone":"Europe/Prague",
    "iso:country":"CZ",
    "wof:name":"Horni Privory",
    "wof:placetype":"locality"
},
  "geometry": {"coordinates":[14.58435,50.28693],"type":"Point"}
}