{
  "type": "Feature",
  "properties": {
    "iso:country":"CZ",
    "name:ara_x_preferred":[
        "\u062a\u0627\u062e\u0648\u0641"
    ],
    "name:bel_x_preferred":[
        "\u0422\u0430\u0445\u0430\u045e"
    ],
    "name:ceb_x_preferred":[
        "Tachov"
    ],
    "name:ces_x_preferred":[
        "Tachov"
    ],
    "name:dan_x_preferred":[
        "Tachov"
    ],
    "name:deu_x_preferred":[
        "Tachov"
    ],
    "name:epo_x_preferred":[
        "Tachov"
    ],
    "name:est_x_preferred":[
        "Tachov"
    ],
    "name:eus_x_preferred":[
        "Tachov"
    ],
    "name:fas_x_preferred":[
        "\u062a\u0627\u062e\u0648\u0648"
    ],
    "name:fin_x_preferred":[
        "Tachov"
    ],
    "name:fra_x_preferred":[
        "Tachov"
    ],
    "name:hun_x_preferred":[
        "Tachov"
    ],
    "name:ind_x_preferred":[
        "Tachov"
    ],
    "name:ita_x_preferred":[
        "Tachov"
    ],
    "name:lat_x_preferred":[
        "Tachovia"
    ],
    "name:lav_x_preferred":[
        "Tahova"
    ],
    "name:lit_x_preferred":[
        "Tachovas"
    ],
    "name:msa_x_preferred":[
        "Tachov"
    ],
    "name:nld_x_preferred":[
        "Tachov"
    ],
    "name:nno_x_preferred":[
        "Tachov"
    ],
    "name:nor_x_preferred":[
        "Tachov"
    ],
    "name:pol_x_preferred":[
        "Tachov"
    ],
    "name:por_x_preferred":[
        "Tachov"
    ],
    "name:ron_x_preferred":[
        "Tachov"
    ],
    "name:rus_x_preferred":[
        "\u0422\u0430\u0445\u043e\u0432"
    ],
    "name:slk_x_preferred":[
        "Tachov"
    ],
    "name:slv_x_preferred":[
        "Tachov"
    ],
    "name:spa_x_preferred":[
        "Tachov"
    ],
    "name:srp_x_preferred":[
        "\u0422\u0430\u0445\u043e\u0432"
    ],
    "name:swe_x_preferred":[
        "Tachov"
    ],
    "name:tur_x_preferred":[
        "Tachov"
    ],
    "name:ukr_x_preferred":[
        "\u0422\u0430\u0445\u043e\u0432"
    ],
    "name:vie_x_preferred":[
        "Tachov"
    ],
    "name:war_x_preferred":[
        "Tachov"
    ],
    "name:zho_x_preferred":[
        "\u5854\u970d\u592b"
    ],
    "qs_pg:aaroncc":"CZ",
    "qs_pg:name":"Tachov",
    "qs_pg:name_adm0":"\u010cesk\u00e1 republika",
    "qs_pg:name_adm1":"Plze\u0148sk\u00fd kraj",
    "qs_pg:photos":1,
    "qs_pg:photos_1k":1,
    "qs_pg:photos_9k":1,
    "qs_pg:photos_9r":2,
    "qs_pg:photos_all":29,
    "qs_pg:photos_sr":1,
    "qs_pg:pop_sr":0,
    "qs_pg:qs_pg_placetype":"localadmin",
    "qs_pg:qs_pg_placetype_gp":"LocalAdmin",
    "qs_pg:woe_adm0":23424810,
    "woe:adm0_id":23424810,
    "woe:name_adm0":"\u010cesk\u00e1 republika",
    "woe:name_adm1":"Plze\u0148sk\u00fd kraj",
    "woe:placetype":"LocalAdmin",
    "wof:name":"Tachov",
    "wof:placetype":"localadmin"
},
  "geometry": {"coordinates":[12.630361,49.7958385],"type":"Point"}
}