{
  "type": "Feature",
  "properties": {
    "gn:gn_country":"CZ",
    "gn:gn_fcode":"PPL",
    "gn:gn_pop":1054,
    "gn:population":1054,
    "iso:country":"CZ",
    "name:ces_x_preferred":[
        "Jakartovice"
    ],
    "name:deu_x_preferred":[
        "Jakartovice"
    ],
    "name:eng_x_preferred":[
        "Jakartovice"
    ],
    "name:epo_x_preferred":[
        "Jakartovice"
    ],
    "name:fra_x_preferred":[
        "Jakartovice"
    ],
    "name:hun_x_preferred":[
        "Jakartovice"
    ],
    "name:ita_x_preferred":[
        "Jakartovice"
    ],
    "name:msa_x_preferred":[
        "Jakartovice"
    ],
    "name:nld_x_preferred":[
        "Jakartovice"
    ],
    "name:pol_x_preferred":[
        "Jakartovice"
    ],
    "name:por_x_preferred":[
        "Jakartovice"
    ],
    "name:rup_x_preferred":[
        "Jakartovice"
    ],
    "name:slk_x_preferred":[
        "Jakartovice"
    ],
    "name:srp_x_preferred":[
        "\u0408\u0430\u043a\u0430\u0440\u0442\u043e\u0432\u0438\u0446\u0435"
    ],
    "name:swe_x_preferred":[
        "Jakartovice"
    ],
    "name:unk_x_variant":[
        "Eckersdorf"
    ],
    "name:vie_x_preferred":[
        "Jakartovice"
    ],
    "qs_pg:aaroncc":"CZ",
    "qs_pg:gn_country":"CZ",
    "qs_pg:gn_fcode":"PPL",
    "qs_pg:gn_pop":1054,
    "qs_pg:name":"Jakartovice",
    "qs_pg:photos_9r":0,
    "qs_pg:photos_sr":0,
    "qs_pg:pop_sr":3,
    "qs_pg:qs_pg_placetype":"locality",
    "wof:name":"Jakartovice",
    "wof:placetype":"locality",
    "wof:population":1054
},
  "geometry": {"coordinates":[17.684,49.9151],"type":"Point"}
}