{
  "type": "Feature",
  "properties": {
    "gn:admin1_code":"81.0",
    "gn:admin2_code":"0412",
    "gn:asciiname":"Hradiste",
    "gn:country_code":"CZ",
    "gn:dem":703,
    "gn:feature_class":"P",
    "gn:feature_code":"PPL",
    "gn:name":"Hradi\u0161t\u011b",
    "gn:population":617,
    "gn:timezone":"Europe/Prague",
    "iso:country":"CZ",
    "name:und_x_variant":[
        "H\u00f6fen"
    ],
    "wof:name":"Hradiste",
    "wof:placetype":"locality",
    "wof:population":617
},
  "geometry": {"coordinates":[13.04653,50.17485],"type":"Point"}
}