{
  "type": "Feature",
  "properties": {
    "gn:country":"CZ",
    "gn:fcode":"PPL",
    "gn:population":297,
    "iso:country":"CZ",
    "name:azb_x_preferred":[
        "\u0698\u0631\u0648\u062a\u06cc\u062a\u0633\u0647"
    ],
    "name:cat_x_preferred":[
        "\u017derotice"
    ],
    "name:ceb_x_preferred":[
        "\u017derotice"
    ],
    "name:ces_x_preferred":[
        "\u017derotice"
    ],
    "name:che_x_preferred":[
        "\u0416\u0435\u0440\u043e\u0442\u0438\u0446\u0435"
    ],
    "name:deu_x_preferred":[
        "\u017derotice"
    ],
    "name:eng_x_preferred":[
        "\u017derotice"
    ],
    "name:epo_x_preferred":[
        "\u017derotice"
    ],
    "name:eus_x_preferred":[
        "\u017derotice"
    ],
    "name:fas_x_preferred":[
        "\u0698\u0631\u0648\u062a\u06cc\u062a\u0633\u0647"
    ],
    "name:fra_x_preferred":[
        "\u017derotice"
    ],
    "name:gle_x_preferred":[
        "\u017derotice"
    ],
    "name:hun_x_preferred":[
        "\u017derotice"
    ],
    "name:ita_x_preferred":[
        "\u017derotice"
    ],
    "name:lmo_x_preferred":[
        "\u017derotice"
    ],
    "name:msa_x_preferred":[
        "\u017derotice"
    ],
    "name:nan_x_preferred":[
        "\u017derotice"
    ],
    "name:nld_x_preferred":[
        "\u017derotice"
    ],
    "name:pol_x_preferred":[
        "\u017derotice"
    ],
    "name:por_x_preferred":[
        "\u017derotice"
    ],
    "name:slk_x_preferred":[
        "\u017derotice"
    ],
    "name:spa_x_preferred":[
        "\u017derotice"
    ],
    "name:srp_x_preferred":[
        "\u0416\u0435\u0440\u043e\u0442\u0438\u0446\u0435"
    ],
    "name:swe_x_preferred":[
        "\u017derotice"
    ],
    "name:tat_x_preferred":[
        "\u0416\u0435\u0440\u043e\u0442\u0438\u0446\u0435"
    ],
    "name:vie_x_preferred":[
        "\u017derotice"
    ],
    "qs_pg:aaroncc":"CZ",
    "qs_pg:gn_country":"CZ",
    "qs_pg:gn_fcode":"PPL",
    "qs_pg:gn_pop":297,
    "qs_pg:name":"\u017derotice",
    "qs_pg:name_adm0":"\u010cesk\u00e1 republika",
    "qs_pg:name_adm1":"Jihomoravsk\u00fd kraj",
    "qs_pg:photos_9r":0,
    "qs_pg:photos_sr":0,
    "qs_pg:pop_sr":2,
    "qs_pg:qs_pg_placetype":"locality",
    "qs_pg:qs_pg_placetype_gp":"Town",
    "qs_pg:woe_adm0":23424810,
    "woe:adm0_id":23424810,
    "woe:name_adm0":"\u010cesk\u00e1 republika",
    "woe:name_adm1":"Jihomoravsk\u00fd kraj",
    "woe:placetype":"Town",
    "wof:name":"\u017derotice",
    "wof:placetype":"locality",
    "wof:population":297
},
  "geometry": {"coordinates":[16.16874,48.92671],"type":"Point"}
}