{
  "type": "Feature",
  "properties": {
    "gn:admin1_code":"82.0",
    "gn:admin2_code":"0522",
    "gn:asciiname":"Horni Rokytnany",
    "gn:country_code":"CZ",
    "gn:dem":237,
    "gn:feature_class":"P",
    "gn:feature_code":"PPL",
    "gn:name":"Horn\u00ed Rokyt\u0148any",
    "gn:population":0,
    "gn:timezone":"Europe/Prague",
    "iso:country":"CZ",
    "wof:name":"Horni Rokytnany",
    "wof:placetype":"locality"
},
  "geometry": {"coordinates":[15.12713,50.37741],"type":"Point"}
}