{
  "type": "Feature",
  "properties": {
    "gn:admin1_code":"85",
    "gn:admin2_code":"0803",
    "gn:asciiname":"Spluchov",
    "gn:country_code":"CZ",
    "gn:dem":284,
    "gn:feature_class":"P",
    "gn:feature_code":"PPL",
    "gn:name":"\u0160pluchov",
    "gn:population":0,
    "gn:timezone":"Europe/Prague",
    "iso:country":"CZ",
    "name:und_x_variant":[
        "\u0160pluckov",
        "\u0160pluchov"
    ],
    "wof:name":"Spluchov",
    "wof:placetype":"locality"
},
  "geometry": {"coordinates":[18.41667,49.75],"type":"Point"}
}