{
  "type": "Feature",
  "properties": {
    "gn:admin1_code":"83.0",
    "gn:admin2_code":"0511",
    "gn:asciiname":"Prosec",
    "gn:country_code":"CZ",
    "gn:dem":395,
    "gn:feature_class":"P",
    "gn:feature_code":"PPL",
    "gn:name":"Prose\u010d",
    "gn:population":0,
    "gn:timezone":"Europe/Prague",
    "iso:country":"CZ",
    "name:und_x_variant":[
        "Proschwitz",
        "Prose\u010d"
    ],
    "wof:name":"Prosec",
    "wof:placetype":"locality"
},
  "geometry": {"coordinates":[14.89699,50.62184],"type":"Point"}
}