{
  "type": "Feature",
  "properties": {
    "gn:admin1_code":"86",
    "gn:admin2_code":"0532",
    "gn:asciiname":"Ujezd",
    "gn:country_code":"CZ",
    "gn:dem":239,
    "gn:feature_class":"P",
    "gn:feature_code":"PPL",
    "gn:name":"\u00dajezd",
    "gn:population":0,
    "gn:timezone":"Europe/Prague",
    "iso:country":"CZ",
    "wof:name":"Ujezd",
    "wof:placetype":"locality"
},
  "geometry": {"coordinates":[15.85712,50.11387],"type":"Point"}
}