{
  "type": "Feature",
  "properties": {
    "gn:gn_country":"CZ",
    "gn:gn_fcode":"PPL",
    "gn:gn_pop":331,
    "gn:population":331,
    "iso:country":"CZ",
    "name:ces_x_preferred":[
        "Veru\u0161i\u010dky"
    ],
    "name:deu_x_preferred":[
        "Veru\u0161i\u010dky"
    ],
    "name:eng_x_preferred":[
        "Veru\u0161i\u010dky"
    ],
    "name:fas_x_preferred":[
        "\u0648\u0631\u0648\u0634\u06cc\u062a\u0634\u06a9\u06cc"
    ],
    "name:fra_x_preferred":[
        "Veru\u0161i\u010dky"
    ],
    "name:hun_x_preferred":[
        "Veru\u0161i\u010dky"
    ],
    "name:ita_x_preferred":[
        "Veru\u0161i\u010dky"
    ],
    "name:msa_x_preferred":[
        "Veru\u0161i\u010dky"
    ],
    "name:nan_x_preferred":[
        "Veru\u0161i\u010dky"
    ],
    "name:nld_x_preferred":[
        "Veru\u0161i\u010dky"
    ],
    "name:pol_x_preferred":[
        "Veru\u0161i\u010dky"
    ],
    "name:por_x_preferred":[
        "Veru\u0161i\u010dky"
    ],
    "name:rup_x_preferred":[
        "Veru\u0161i\u010dky"
    ],
    "name:slk_x_preferred":[
        "Veru\u0161i\u010dky"
    ],
    "name:srp_x_preferred":[
        "\u0412\u0435\u0440\u0443\u0448\u0438\u0447\u043a\u0438"
    ],
    "name:swe_x_preferred":[
        "Veru\u0161i\u010dky"
    ],
    "name:unk_x_variant":[
        "Klein Werscheditz"
    ],
    "name:vie_x_preferred":[
        "Veru\u0161i\u010dky"
    ],
    "qs_pg:aaroncc":"CZ",
    "qs_pg:gn_country":"CZ",
    "qs_pg:gn_fcode":"PPL",
    "qs_pg:gn_pop":331,
    "qs_pg:name":"Veru\u0161i\u010dky",
    "qs_pg:name_adm0":"\u010cesk\u00e1 republika",
    "qs_pg:name_adm1":"Karlovarsk\u00fd kraj",
    "qs_pg:photos_9r":0,
    "qs_pg:photos_sr":0,
    "qs_pg:pop_sr":2,
    "qs_pg:qs_pg_placetype":"locality",
    "qs_pg:qs_pg_placetype_gp":"Town",
    "qs_pg:woe_adm0":23424810,
    "woe:adm0_id":23424810,
    "woe:name_adm0":"\u010cesk\u00e1 republika",
    "woe:name_adm1":"Karlovarsk\u00fd kraj",
    "woe:placetype":"Town",
    "wof:name":"Veru\u0161i\u010dky",
    "wof:placetype":"locality",
    "wof:population":331
},
  "geometry": {"coordinates":[13.17428,50.14154],"type":"Point"}
}