{
  "type": "Feature",
  "properties": {
    "gn:admin1_code":"88.0",
    "gn:admin2_code":"020B",
    "gn:asciiname":"Drsnik",
    "gn:country_code":"CZ",
    "gn:dem":491,
    "gn:feature_class":"P",
    "gn:feature_code":"PPL",
    "gn:name":"Drsn\u00edk",
    "gn:population":0,
    "gn:timezone":"Europe/Prague",
    "iso:country":"CZ",
    "wof:name":"Drsnik",
    "wof:placetype":"locality"
},
  "geometry": {"coordinates":[14.10142,49.62741],"type":"Point"}
}