{
  "type": "Feature",
  "properties": {
    "iso:country":"CZ",
    "name:ceb_x_preferred":[
        "Str\u00e1\u017en\u00e9"
    ],
    "name:ces_x_preferred":[
        "Str\u00e1\u017en\u00e9"
    ],
    "name:deu_x_preferred":[
        "Str\u00e1\u017en\u00e9"
    ],
    "name:eus_x_preferred":[
        "Str\u00e1\u017en\u00e9"
    ],
    "name:fas_x_preferred":[
        "\u0633\u062a\u0631\u0627\u0698\u0646\u0647"
    ],
    "name:fra_x_preferred":[
        "Str\u00e1\u017en\u00e9"
    ],
    "name:hun_x_preferred":[
        "Str\u00e1\u017en\u00e9"
    ],
    "name:ita_x_preferred":[
        "Str\u00e1\u017en\u00e9"
    ],
    "name:msa_x_preferred":[
        "Str\u00e1\u017en\u00e9"
    ],
    "name:nld_x_preferred":[
        "Str\u00e1\u017en\u00e9"
    ],
    "name:pol_x_preferred":[
        "Str\u00e1\u017en\u00e9"
    ],
    "name:por_x_preferred":[
        "Str\u00e1\u017en\u00e9"
    ],
    "name:slk_x_preferred":[
        "Str\u00e1\u017en\u00e9"
    ],
    "name:spa_x_preferred":[
        "Str\u00e1\u017en\u00e9"
    ],
    "name:srp_x_preferred":[
        "\u0421\u0442\u0440\u0430\u0436\u043d\u0435"
    ],
    "name:swe_x_preferred":[
        "Str\u00e1\u017en\u00e9"
    ],
    "name:vie_x_preferred":[
        "Str\u00e1\u017en\u00e9"
    ],
    "qs_pg:aaroncc":"CZ",
    "qs_pg:name":"Str\u00e1\u017en\u00e9",
    "qs_pg:name_adm0":"\u010cesk\u00e1 republika",
    "qs_pg:name_adm1":"Kr\u00e1lov\u00e9hradeck\u00fd kraj",
    "qs_pg:photos":7,
    "qs_pg:photos_1k":1,
    "qs_pg:photos_9k":1,
    "qs_pg:photos_9r":3,
    "qs_pg:photos_all":118,
    "qs_pg:photos_sr":1,
    "qs_pg:pop_sr":0,
    "qs_pg:qs_pg_placetype":"localadmin",
    "qs_pg:qs_pg_placetype_gp":"LocalAdmin",
    "qs_pg:woe_adm0":23424810,
    "woe:adm0_id":23424810,
    "woe:name_adm0":"\u010cesk\u00e1 republika",
    "woe:name_adm1":"Kr\u00e1lov\u00e9hradeck\u00fd kraj",
    "woe:placetype":"LocalAdmin",
    "wof:name":"Str\u00e1\u017en\u00e9",
    "wof:placetype":"localadmin"
},
  "geometry": {"coordinates":[15.635089,50.689987],"type":"Point"}
}