{
  "type": "Feature",
  "properties": {
    "gn:admin1_code":"79.0",
    "gn:admin2_code":"0313",
    "gn:asciiname":"Hrutkov",
    "gn:country_code":"CZ",
    "gn:dem":521,
    "gn:feature_class":"P",
    "gn:feature_code":"PPL",
    "gn:name":"Hrutkov",
    "gn:population":0,
    "gn:timezone":"Europe/Prague",
    "iso:country":"CZ",
    "name:und_x_variant":[
        "Ruttenschlag",
        "Hrutkov"
    ],
    "wof:name":"Hrutkov",
    "wof:placetype":"locality"
},
  "geometry": {"coordinates":[15.05816,49.11851],"type":"Point"}
}