{
  "type": "Feature",
  "properties": {
    "gn:admin1_code":"88.0",
    "gn:admin2_code":"0204",
    "gn:asciiname":"Sedlov",
    "gn:country_code":"CZ",
    "gn:dem":338,
    "gn:feature_class":"P",
    "gn:feature_code":"PPL",
    "gn:name":"Sedlov",
    "gn:population":0,
    "gn:timezone":"Europe/Prague",
    "iso:country":"CZ",
    "wof:name":"Sedlov",
    "wof:placetype":"locality"
},
  "geometry": {"coordinates":[15.1525,49.96343],"type":"Point"}
}