{
  "type": "Feature",
  "properties": {
    "gn:country":"CZ",
    "gn:fcode":"PPL",
    "gn:population":579,
    "iso:country":"CZ",
    "name:azb_x_preferred":[
        "\u0628\u0644\u0627\u062a\u062a\u0633"
    ],
    "name:cat_x_preferred":[
        "Blatec"
    ],
    "name:ceb_x_preferred":[
        "Blatec"
    ],
    "name:ces_x_preferred":[
        "Blatec"
    ],
    "name:che_x_preferred":[
        "\u0411\u043b\u0430\u0442\u0435\u0446"
    ],
    "name:deu_x_preferred":[
        "Blatec"
    ],
    "name:eng_x_preferred":[
        "Blatec"
    ],
    "name:epo_x_preferred":[
        "Blatec"
    ],
    "name:eus_x_preferred":[
        "Blatec"
    ],
    "name:fas_x_preferred":[
        "\u0628\u0644\u0627\u062a\u062a\u0633"
    ],
    "name:fra_x_preferred":[
        "Blatec"
    ],
    "name:gle_x_preferred":[
        "Blatec"
    ],
    "name:hun_x_preferred":[
        "Blatec"
    ],
    "name:ind_x_preferred":[
        "Blatec"
    ],
    "name:ita_x_preferred":[
        "Blatec"
    ],
    "name:lmo_x_preferred":[
        "Blatec"
    ],
    "name:msa_x_preferred":[
        "Blatec"
    ],
    "name:nan_x_preferred":[
        "Blatec"
    ],
    "name:nld_x_preferred":[
        "Blatec"
    ],
    "name:pol_x_preferred":[
        "Blatec"
    ],
    "name:por_x_preferred":[
        "Blatec"
    ],
    "name:rup_x_preferred":[
        "Blatec"
    ],
    "name:slk_x_preferred":[
        "Blatec"
    ],
    "name:spa_x_preferred":[
        "Blatec"
    ],
    "name:srp_x_preferred":[
        "\u0411\u043b\u0430\u0442\u0435\u0446"
    ],
    "name:swe_x_preferred":[
        "Blatec"
    ],
    "name:tat_x_preferred":[
        "\u0411\u043b\u0430\u0442\u0435\u0446"
    ],
    "name:vie_x_preferred":[
        "Blatec"
    ],
    "qs_pg:aaroncc":"CZ",
    "qs_pg:gn_country":"CZ",
    "qs_pg:gn_fcode":"PPL",
    "qs_pg:gn_pop":579,
    "qs_pg:name":"Blatec",
    "qs_pg:name_adm0":"\u010cesk\u00e1 republika",
    "qs_pg:name_adm1":"Olomouck\u00fd kraj",
    "qs_pg:photos_9r":0,
    "qs_pg:photos_sr":0,
    "qs_pg:pop_sr":2,
    "qs_pg:qs_pg_placetype":"locality",
    "qs_pg:qs_pg_placetype_gp":"Town",
    "qs_pg:woe_adm0":23424810,
    "woe:adm0_id":23424810,
    "woe:name_adm0":"\u010cesk\u00e1 republika",
    "woe:name_adm1":"Olomouck\u00fd kraj",
    "woe:placetype":"Town",
    "wof:name":"Blatec",
    "wof:placetype":"locality",
    "wof:population":579
},
  "geometry": {"coordinates":[17.23857,49.52834],"type":"Point"}
}