{
  "type": "Feature",
  "properties": {
    "gn:admin1_code":"80.0",
    "gn:admin2_code":"0613",
    "gn:asciiname":"Novy Drahonov",
    "gn:country_code":"CZ",
    "gn:dem":656,
    "gn:feature_class":"P",
    "gn:feature_code":"PPL",
    "gn:name":"Nov\u00fd Drahonov",
    "gn:population":0,
    "gn:timezone":"Europe/Prague",
    "iso:country":"CZ",
    "wof:name":"Novy Drahonov",
    "wof:placetype":"locality"
},
  "geometry": {"coordinates":[15.0722,49.36067],"type":"Point"}
}