{
  "type": "Feature",
  "properties": {
    "gn:admin1_code":"81.0",
    "gn:admin2_code":"0411",
    "gn:asciiname":"Nebesa",
    "gn:cc2":"CZ",
    "gn:country_code":"CZ",
    "gn:dem":694,
    "gn:feature_class":"P",
    "gn:feature_code":"PPL",
    "gn:name":"Nebesa",
    "gn:population":0,
    "gn:timezone":"Europe/Prague",
    "iso:country":"CZ",
    "name:und_x_variant":[
        "Himmelreich"
    ],
    "wof:name":"Nebesa",
    "wof:placetype":"locality"
},
  "geometry": {"coordinates":[12.22658,50.19745],"type":"Point"}
}