{
  "type": "Feature",
  "properties": {
    "gn:gn_country":"CZ",
    "gn:gn_fcode":"PPL",
    "gn:gn_pop":496,
    "gn:population":496,
    "iso:country":"CZ",
    "name:ceb_x_preferred":[
        "K\u00e1ran\u00fd"
    ],
    "name:ces_x_preferred":[
        "K\u00e1ran\u00fd"
    ],
    "name:eng_x_preferred":[
        "K\u00e1ran\u00fd"
    ],
    "name:eus_x_preferred":[
        "K\u00e1ran\u00fd"
    ],
    "name:fra_x_preferred":[
        "K\u00e1ran\u00fd"
    ],
    "name:hun_x_preferred":[
        "K\u00e1ran\u00fd"
    ],
    "name:ita_x_preferred":[
        "K\u00e1ran\u00fd"
    ],
    "name:msa_x_preferred":[
        "K\u00e1ran\u00fd"
    ],
    "name:nan_x_preferred":[
        "K\u00e1ran\u00fd"
    ],
    "name:nld_x_preferred":[
        "K\u00e1ran\u00fd"
    ],
    "name:pol_x_preferred":[
        "K\u00e1ran\u00fd"
    ],
    "name:por_x_preferred":[
        "K\u00e1ran\u00fd"
    ],
    "name:rus_x_preferred":[
        "\u041a\u0430\u0440\u0430\u043d\u0438"
    ],
    "name:slk_x_preferred":[
        "K\u00e1ran\u00fd"
    ],
    "name:spa_x_preferred":[
        "K\u00e1ran\u00fd"
    ],
    "name:srp_x_preferred":[
        "\u041a\u0430\u0440\u0430\u043d\u0438"
    ],
    "name:swe_x_preferred":[
        "K\u00e1ran\u00fd"
    ],
    "name:vie_x_preferred":[
        "K\u00e1ran\u00fd"
    ],
    "qs_pg:aaroncc":"CZ",
    "qs_pg:gn_country":"CZ",
    "qs_pg:gn_fcode":"PPL",
    "qs_pg:gn_pop":496,
    "qs_pg:name":"K\u00e1ran\u00fd",
    "qs_pg:name_adm0":"\u010cesk\u00e1 republika",
    "qs_pg:name_adm1":"St\u0159edo\u010desk\u00fd kraj",
    "qs_pg:photos":10,
    "qs_pg:photos_1k":2,
    "qs_pg:photos_9k":1,
    "qs_pg:photos_9r":1,
    "qs_pg:photos_all":10,
    "qs_pg:photos_sr":1,
    "qs_pg:pop_sr":2,
    "qs_pg:qs_pg_placetype":"locality",
    "qs_pg:qs_pg_placetype_gp":"Town",
    "qs_pg:woe_adm0":23424810,
    "woe:adm0_id":23424810,
    "woe:name_adm0":"\u010cesk\u00e1 republika",
    "woe:name_adm1":"St\u0159edo\u010desk\u00fd kraj",
    "woe:placetype":"Town",
    "wof:name":"K\u00e1ran\u00fd",
    "wof:placetype":"locality",
    "wof:population":496
},
  "geometry": {"coordinates":[14.73699,50.17477],"type":"Point"}
}