{
  "type": "Feature",
  "properties": {
    "gn:admin1_code":"83",
    "gn:admin2_code":"0511",
    "gn:asciiname":"Zaksin",
    "gn:country_code":"CZ",
    "gn:dem":252,
    "gn:feature_class":"P",
    "gn:feature_code":"PPL",
    "gn:name":"Zak\u0161\u00edn",
    "gn:population":0,
    "gn:timezone":"Europe/Prague",
    "iso:country":"CZ",
    "wof:name":"Zaksin",
    "wof:placetype":"locality"
},
  "geometry": {"coordinates":[14.49206,50.52849000000001],"type":"Point"}
}