{
  "type": "Feature",
  "properties": {
    "gn:admin1_code":"87.0",
    "gn:admin2_code":"0324",
    "gn:asciiname":"Novy",
    "gn:country_code":"CZ",
    "gn:dem":379,
    "gn:feature_class":"P",
    "gn:feature_code":"PPL",
    "gn:name":"Nov\u00fd",
    "gn:population":0,
    "gn:timezone":"Europe/Prague",
    "iso:country":"CZ",
    "wof:name":"Novy",
    "wof:placetype":"locality"
},
  "geometry": {"coordinates":[13.15204,49.6814],"type":"Point"}
}