{
  "type": "Feature",
  "properties": {
    "gn:admin1_code":"87.0",
    "gn:admin2_code":"0324",
    "gn:asciiname":"Novy",
    "gn:country_code":"CZ",
    "gn:dem":379,
    "gn:feature_class":"P",
    "gn:feature_code":"PPL",
    "gn:name":"Nov\u00fd",
    "gn:population":0,
    "gn:timezone":"Europe/Prague",
    "iso:country":"CZ",
    "name:bel_x_preferred":[
        "\u041d\u043e\u0432\u044b"
    ],
    "name:ceb_x_preferred":[
        "\u041d\u043e\u0432\u044b\u0439"
    ],
    "name:deu_x_preferred":[
        "Novy"
    ],
    "name:hye_x_preferred":[
        "\u0546\u0578\u057e\u056b"
    ],
    "name:nld_x_preferred":[
        "Novy"
    ],
    "name:rus_x_preferred":[
        "\u041d\u043e\u0432\u044b\u0439"
    ],
    "name:slv_x_preferred":[
        "Novy"
    ],
    "name:ukr_x_preferred":[
        "\u041d\u043e\u0432\u0438\u0439"
    ],
    "wof:name":"Novy",
    "wof:placetype":"locality"
},
  "geometry": {"coordinates":[13.15204,49.6814],"type":"Point"}
}