{
  "type": "Feature",
  "properties": {
    "gn:admin1_code":"79.0",
    "gn:admin2_code":"0311",
    "gn:asciiname":"Lhota pod Horami",
    "gn:country_code":"CZ",
    "gn:dem":437,
    "gn:feature_class":"P",
    "gn:feature_code":"PPL",
    "gn:name":"Lhota pod Horami",
    "gn:population":0,
    "gn:timezone":"Europe/Prague",
    "iso:country":"CZ",
    "wof:name":"Lhota pod Horami",
    "wof:placetype":"locality"
},
  "geometry": {"coordinates":[14.31702,49.18203],"type":"Point"}
}