{
  "type": "Feature",
  "properties": {
    "gn:admin1_code":"86",
    "gn:admin2_code":"0533",
    "gn:asciiname":"Zalesi",
    "gn:country_code":"CZ",
    "gn:dem":447,
    "gn:feature_class":"P",
    "gn:feature_code":"PPL",
    "gn:name":"Z\u00e1les\u00ed",
    "gn:population":0,
    "gn:timezone":"Europe/Prague",
    "iso:country":"CZ",
    "name:und_x_variant":[
        "Lib\u0161tejn",
        "Z\u00e1les\u00ed"
    ],
    "wof:name":"Zalesi",
    "wof:placetype":"locality"
},
  "geometry": {"coordinates":[16.76917000000001,49.63976],"type":"Point"}
}