{
  "type": "Feature",
  "properties": {
    "gn:country":"CZ",
    "gn:fcode":"PPL",
    "gn:population":251,
    "iso:country":"CZ",
    "name:cat_x_preferred":[
        "Bud\u00edkov"
    ],
    "name:ceb_x_preferred":[
        "Bud\u00edkov"
    ],
    "name:ces_x_preferred":[
        "Bud\u00edkov"
    ],
    "name:che_x_preferred":[
        "\u0411\u0443\u0434\u0438\u043a\u043e\u0432"
    ],
    "name:deu_x_preferred":[
        "Bud\u00edkov"
    ],
    "name:eng_x_preferred":[
        "Bud\u00edkov"
    ],
    "name:epo_x_preferred":[
        "Bud\u00edkov"
    ],
    "name:eus_x_preferred":[
        "Bud\u00edkov"
    ],
    "name:fra_x_preferred":[
        "Bud\u00edkov"
    ],
    "name:gle_x_preferred":[
        "Bud\u00edkov"
    ],
    "name:hsb_x_preferred":[
        "Bud\u00edkov"
    ],
    "name:hun_x_preferred":[
        "Bud\u00edkov"
    ],
    "name:ita_x_preferred":[
        "Bud\u00edkov"
    ],
    "name:lmo_x_preferred":[
        "Bud\u00edkov"
    ],
    "name:msa_x_preferred":[
        "Bud\u00edkov"
    ],
    "name:nan_x_preferred":[
        "Bud\u00edkov"
    ],
    "name:nld_x_preferred":[
        "Bud\u00edkov"
    ],
    "name:pol_x_preferred":[
        "Bud\u00edkov"
    ],
    "name:por_x_preferred":[
        "Bud\u00edkov"
    ],
    "name:rup_x_preferred":[
        "Bud\u00edkov"
    ],
    "name:slk_x_preferred":[
        "Bud\u00edkov"
    ],
    "name:spa_x_preferred":[
        "Bud\u00edkov"
    ],
    "name:srp_x_preferred":[
        "\u0411\u0443\u0434\u0438\u043a\u043e\u0432"
    ],
    "name:swe_x_preferred":[
        "Bud\u00edkov"
    ],
    "name:tat_x_preferred":[
        "\u0411\u0443\u0434\u0438\u043a\u043e\u0432"
    ],
    "name:vie_x_preferred":[
        "Bud\u00edkov"
    ],
    "qs_pg:aaroncc":"CZ",
    "qs_pg:gn_country":"CZ",
    "qs_pg:gn_fcode":"PPL",
    "qs_pg:gn_pop":251,
    "qs_pg:name":"Bud\u00edkov",
    "qs_pg:name_adm0":"\u010cesk\u00e1 republika",
    "qs_pg:name_adm1":"Kraj Vyso\u010dina",
    "qs_pg:photos_9r":0,
    "qs_pg:photos_sr":0,
    "qs_pg:pop_sr":2,
    "qs_pg:qs_pg_placetype":"locality",
    "qs_pg:qs_pg_placetype_gp":"Town",
    "qs_pg:woe_adm0":23424810,
    "woe:adm0_id":23424810,
    "woe:name_adm0":"\u010cesk\u00e1 republika",
    "woe:name_adm1":"Kraj Vyso\u010dina",
    "woe:placetype":"Town",
    "wof:name":"Bud\u00edkov",
    "wof:placetype":"locality",
    "wof:population":251
},
  "geometry": {"coordinates":[15.3626,49.57914],"type":"Point"}
}