{
  "type": "Feature",
  "properties": {
    "gn:admin1_code":"88.0",
    "gn:admin2_code":"0209",
    "gn:asciiname":"Pakomerice",
    "gn:country_code":"CZ",
    "gn:dem":249,
    "gn:feature_class":"P",
    "gn:feature_code":"PPL",
    "gn:name":"Pakom\u011b\u0159ice",
    "gn:population":0,
    "gn:timezone":"Europe/Prague",
    "iso:country":"CZ",
    "wof:name":"Pakomerice",
    "wof:placetype":"locality"
},
  "geometry": {"coordinates":[14.48112,50.18063],"type":"Point"}
}