{
  "type": "Feature",
  "properties": {
    "gn:admin1_code":"89.0",
    "gn:admin2_code":"0426",
    "gn:asciiname":"Drahunky",
    "gn:cc2":"CZ",
    "gn:country_code":"CZ",
    "gn:dem":422,
    "gn:feature_class":"P",
    "gn:feature_code":"PPL",
    "gn:name":"Drah\u016fnky",
    "gn:population":0,
    "gn:timezone":"Europe/Prague",
    "iso:country":"CZ",
    "name:deu_x_preferred":[
        "Dreihunken"
    ],
    "wof:name":"Drahunky",
    "wof:placetype":"locality"
},
  "geometry": {"coordinates":[13.81667,50.68333],"type":"Point"}
}