{
  "type": "Feature",
  "properties": {
    "gn:country":"CZ",
    "gn:fcode":"PPL",
    "gn:population":501,
    "iso:country":"CZ",
    "name:ceb_x_preferred":[
        "Old\u0159ichov v H\u00e1j\u00edch"
    ],
    "name:ces_x_preferred":[
        "Old\u0159ichov v H\u00e1j\u00edch"
    ],
    "name:deu_x_preferred":[
        "Old\u0159ichov v H\u00e1j\u00edch"
    ],
    "name:eng_x_preferred":[
        "Old\u0159ichov v H\u00e1j\u00edch"
    ],
    "name:eus_x_preferred":[
        "Old\u0159ichov v H\u00e1j\u00edch"
    ],
    "name:fra_x_preferred":[
        "Old\u0159ichov v H\u00e1j\u00edch"
    ],
    "name:hun_x_preferred":[
        "Old\u0159ichov v H\u00e1j\u00edch"
    ],
    "name:ita_x_preferred":[
        "Old\u0159ichov v H\u00e1j\u00edch"
    ],
    "name:msa_x_preferred":[
        "Old\u0159ichov v H\u00e1j\u00edch"
    ],
    "name:nan_x_preferred":[
        "Old\u0159ichov v H\u00e1j\u00edch"
    ],
    "name:nld_x_preferred":[
        "Old\u0159ichov v H\u00e1j\u00edch"
    ],
    "name:pol_x_preferred":[
        "Old\u0159ichov v H\u00e1j\u00edch"
    ],
    "name:por_x_preferred":[
        "Old\u0159ichov v H\u00e1j\u00edch"
    ],
    "name:rup_x_preferred":[
        "Old\u0159ichov v H\u00e1j\u00edch"
    ],
    "name:slk_x_preferred":[
        "Old\u0159ichov v H\u00e1j\u00edch"
    ],
    "name:spa_x_preferred":[
        "Old\u0159ichov v H\u00e1j\u00edch"
    ],
    "name:srp_x_preferred":[
        "\u041e\u043b\u0434\u0440\u0438\u0445\u043e\u0432 \u0432 \u0425\u0430\u0458\u0438\u0445"
    ],
    "name:swe_x_preferred":[
        "Old\u0159ichov v H\u00e1j\u00edch"
    ],
    "name:und_x_variant":[
        "Buschullersdorf"
    ],
    "name:vie_x_preferred":[
        "Old\u0159ichov v H\u00e1j\u00edch"
    ],
    "qs_pg:aaroncc":"CZ",
    "qs_pg:gn_country":"CZ",
    "qs_pg:gn_fcode":"PPL",
    "qs_pg:gn_pop":501,
    "qs_pg:name":"Old\u0159ichov v H\u00e1j\u00edch",
    "qs_pg:name_adm0":"\u010cesk\u00e1 republika",
    "qs_pg:name_adm1":"Libereck\u00fd kraj",
    "qs_pg:photos_9k":1,
    "qs_pg:photos_9r":1,
    "qs_pg:photos_all":1,
    "qs_pg:photos_sr":0,
    "qs_pg:pop_sr":2,
    "qs_pg:qs_pg_placetype":"locality",
    "qs_pg:qs_pg_placetype_gp":"Town",
    "qs_pg:woe_adm0":23424810,
    "woe:adm0_id":23424810,
    "woe:name_adm0":"\u010cesk\u00e1 republika",
    "woe:name_adm1":"Libereck\u00fd kraj",
    "woe:placetype":"Town",
    "wof:name":"Old\u0159ichov v H\u00e1j\u00edch",
    "wof:placetype":"locality",
    "wof:population":501
},
  "geometry": {"coordinates":[15.08367,50.84963],"type":"Point"}
}