{
  "type": "Feature",
  "properties": {
    "gn:admin1_code":"79.0",
    "gn:admin2_code":"0312",
    "gn:asciiname":"Kladenske Rovne",
    "gn:country_code":"CZ",
    "gn:dem":602,
    "gn:feature_class":"P",
    "gn:feature_code":"PPL",
    "gn:name":"Kladensk\u00e9 Rovn\u00e9",
    "gn:population":0,
    "gn:timezone":"Europe/Prague",
    "iso:country":"CZ",
    "name:und_x_variant":[
        "Kladener Ruben",
        "Kladensk\u00e9 Rovn\u00e9"
    ],
    "wof:name":"Kladenske Rovne",
    "wof:placetype":"locality"
},
  "geometry": {"coordinates":[14.22354,48.79471],"type":"Point"}
}