{
  "type": "Feature",
  "properties": {
    "gn:country":"CZ",
    "gn:fcode":"PPL",
    "gn:population":1067,
    "iso:country":"CZ",
    "name:azb_x_preferred":[
        "\u0645\u0627\u0644\u0627 \u0633\u06a9\u0627\u0644\u0627"
    ],
    "name:ceb_x_preferred":[
        "Mal\u00e1 Sk\u00e1la"
    ],
    "name:ces_x_preferred":[
        "Mal\u00e1 Sk\u00e1la"
    ],
    "name:deu_x_preferred":[
        "Mal\u00e1 Sk\u00e1la"
    ],
    "name:eng_x_preferred":[
        "Mal\u00e1 Sk\u00e1la"
    ],
    "name:eus_x_preferred":[
        "Mal\u00e1 Sk\u00e1la"
    ],
    "name:fas_x_preferred":[
        "\u0645\u0627\u0644\u0627 \u0633\u06a9\u0627\u0644\u0627"
    ],
    "name:fra_x_preferred":[
        "Mal\u00e1 Sk\u00e1la"
    ],
    "name:hun_x_preferred":[
        "Mal\u00e1 Sk\u00e1la"
    ],
    "name:ita_x_preferred":[
        "Mal\u00e1 Sk\u00e1la"
    ],
    "name:msa_x_preferred":[
        "Mal\u00e1 Sk\u00e1la"
    ],
    "name:nan_x_preferred":[
        "Mal\u00e1 Sk\u00e1la"
    ],
    "name:nld_x_preferred":[
        "Mal\u00e1 Sk\u00e1la"
    ],
    "name:pol_x_preferred":[
        "Mal\u00e1 Sk\u00e1la"
    ],
    "name:por_x_preferred":[
        "Mal\u00e1 Sk\u00e1la"
    ],
    "name:rup_x_preferred":[
        "Mal\u00e1 Sk\u00e1la"
    ],
    "name:slk_x_preferred":[
        "Mal\u00e1 Sk\u00e1la"
    ],
    "name:spa_x_preferred":[
        "Mal\u00e1 Sk\u00e1la"
    ],
    "name:srp_x_preferred":[
        "\u041c\u0430\u043b\u0430 \u0421\u043a\u0430\u043b\u0430"
    ],
    "name:swe_x_preferred":[
        "Mal\u00e1 Sk\u00e1la"
    ],
    "name:vie_x_preferred":[
        "Mal\u00e1 Sk\u00e1la"
    ],
    "qs_pg:aaroncc":"CZ",
    "qs_pg:gn_country":"CZ",
    "qs_pg:gn_fcode":"PPL",
    "qs_pg:gn_pop":1067,
    "qs_pg:name":"Mal\u00e1 Sk\u00e1la",
    "qs_pg:photos_9r":0,
    "qs_pg:photos_sr":0,
    "qs_pg:pop_sr":3,
    "qs_pg:qs_pg_placetype":"locality",
    "wof:name":"Mal\u00e1 Sk\u00e1la",
    "wof:placetype":"locality",
    "wof:population":1067
},
  "geometry": {"coordinates":[15.19543,50.64631],"type":"Point"}
}