{
  "type": "Feature",
  "properties": {
    "gn:admin1_code":"79.0",
    "gn:admin2_code":"0315",
    "gn:asciiname":"Belec",
    "gn:country_code":"CZ",
    "gn:dem":525,
    "gn:feature_class":"P",
    "gn:feature_code":"PPL",
    "gn:name":"B\u011ble\u010d",
    "gn:population":0,
    "gn:timezone":"Europe/Prague",
    "iso:country":"CZ",
    "wof:name":"Belec",
    "wof:placetype":"locality"
},
  "geometry": {"coordinates":[14.03665,49.04882],"type":"Point"}
}