{
  "type": "Feature",
  "properties": {
    "gn:country":"CZ",
    "gn:fcode":"PPL",
    "gn:population":431,
    "iso:country":"CZ",
    "name:azb_x_preferred":[
        "\u0627\u0648\u0647\u0631\u062a\u0634\u06cc\u062a\u0633\u0647"
    ],
    "name:cat_x_preferred":[
        "Uher\u010dice"
    ],
    "name:ceb_x_preferred":[
        "Uher\u010dice"
    ],
    "name:ces_x_preferred":[
        "Uher\u010dice"
    ],
    "name:che_x_preferred":[
        "\u0423\u0433\u0435\u0440\u0447\u0438\u0446\u0435"
    ],
    "name:deu_x_preferred":[
        "Uher\u010dice u Znojma"
    ],
    "name:eng_x_preferred":[
        "Uher\u010dice"
    ],
    "name:epo_x_preferred":[
        "Uher\u010dice"
    ],
    "name:eus_x_preferred":[
        "Uher\u010dice"
    ],
    "name:fas_x_preferred":[
        "\u0627\u0648\u0647\u0631\u062a\u0634\u06cc\u062a\u0633\u0647"
    ],
    "name:fra_x_preferred":[
        "Uher\u010dice"
    ],
    "name:gle_x_preferred":[
        "Uher\u010dice"
    ],
    "name:hun_x_preferred":[
        "Uher\u010dice"
    ],
    "name:ita_x_preferred":[
        "Uher\u010dice"
    ],
    "name:lmo_x_preferred":[
        "Uher\u010dice"
    ],
    "name:msa_x_preferred":[
        "Uher\u010dice"
    ],
    "name:nan_x_preferred":[
        "Uher\u010dice"
    ],
    "name:nld_x_preferred":[
        "Uher\u010dice"
    ],
    "name:pol_x_preferred":[
        "Uher\u010dice"
    ],
    "name:por_x_preferred":[
        "Uher\u010dice"
    ],
    "name:rup_x_preferred":[
        "Uher\u010dice"
    ],
    "name:slk_x_preferred":[
        "Uher\u010dice"
    ],
    "name:spa_x_preferred":[
        "Uher\u010dice"
    ],
    "name:srp_x_preferred":[
        "\u0423\u0445\u0435\u0440\u0447\u0438\u0446\u0435"
    ],
    "name:swe_x_preferred":[
        "Uher\u010dice"
    ],
    "name:tat_x_preferred":[
        "\u0423\u0433\u0435\u0440\u0447\u0438\u0446\u0435"
    ],
    "name:vie_x_preferred":[
        "Uher\u010dice"
    ],
    "qs_pg:aaroncc":"CZ",
    "qs_pg:gn_country":"CZ",
    "qs_pg:gn_fcode":"PPL",
    "qs_pg:gn_pop":431,
    "qs_pg:name":"Uher\u010dice",
    "qs_pg:name_adm0":"\u010cesk\u00e1 republika",
    "qs_pg:name_adm1":"Jihomoravsk\u00fd kraj",
    "qs_pg:photos":11,
    "qs_pg:photos_1k":2,
    "qs_pg:photos_9k":1,
    "qs_pg:photos_9r":1,
    "qs_pg:photos_all":11,
    "qs_pg:photos_sr":1,
    "qs_pg:pop_sr":2,
    "qs_pg:qs_pg_placetype":"locality",
    "qs_pg:qs_pg_placetype_gp":"Town",
    "qs_pg:woe_adm0":23424810,
    "woe:adm0_id":23424810,
    "woe:name_adm0":"\u010cesk\u00e1 republika",
    "woe:name_adm1":"Jihomoravsk\u00fd kraj",
    "woe:placetype":"Town",
    "wof:name":"Uher\u010dice",
    "wof:placetype":"locality",
    "wof:population":431
},
  "geometry": {"coordinates":[15.63038,48.91323],"type":"Point"}
}