{
  "type": "Feature",
  "properties": {
    "gn:admin1_code":"88.0",
    "gn:admin2_code":"0206",
    "gn:asciiname":"Na Stepane",
    "gn:country_code":"CZ",
    "gn:dem":165,
    "gn:feature_class":"P",
    "gn:feature_code":"PPL",
    "gn:name":"Na \u0160t\u011bp\u00e1n\u011b",
    "gn:population":0,
    "gn:timezone":"Europe/Prague",
    "iso:country":"CZ",
    "wof:name":"Na Stepane",
    "wof:placetype":"locality"
},
  "geometry": {"coordinates":[14.49572,50.28931],"type":"Point"}
}