{
  "type": "Feature",
  "properties": {
    "gn:admin1_code":"83",
    "gn:admin2_code":"0513",
    "gn:asciiname":"Vetrov",
    "gn:country_code":"CZ",
    "gn:dem":364,
    "gn:feature_class":"P",
    "gn:feature_code":"PPL",
    "gn:name":"V\u011btrov",
    "gn:population":0,
    "gn:timezone":"Europe/Prague",
    "iso:country":"CZ",
    "name:und_x_variant":[
        "Ringenhain",
        "V\u011btrov"
    ],
    "wof:name":"Vetrov",
    "wof:placetype":"locality"
},
  "geometry": {"coordinates":[15.07068,50.90757],"type":"Point"}
}