{
  "type": "Feature",
  "properties": {
    "gn:admin1_code":"79.0",
    "gn:admin2_code":"0314",
    "gn:asciiname":"Sochovice",
    "gn:country_code":"CZ",
    "gn:dem":489,
    "gn:feature_class":"P",
    "gn:feature_code":"PPL",
    "gn:name":"Sochovice",
    "gn:population":0,
    "gn:timezone":"Europe/Prague",
    "iso:country":"CZ",
    "wof:name":"Sochovice",
    "wof:placetype":"locality"
},
  "geometry": {"coordinates":[14.00568,49.50743],"type":"Point"}
}