{
  "type": "Feature",
  "properties": {
    "gn:admin1_code":"89.0",
    "gn:admin2_code":"0427",
    "gn:asciiname":"Kninice",
    "gn:country_code":"CZ",
    "gn:dem":487,
    "gn:feature_class":"P",
    "gn:feature_code":"PPL",
    "gn:name":"Kn\u00ednice",
    "gn:population":0,
    "gn:timezone":"Europe/Prague",
    "iso:country":"CZ",
    "wof:name":"Kninice",
    "wof:placetype":"locality"
},
  "geometry": {"coordinates":[14.00036,50.73569000000001],"type":"Point"}
}