{
  "type": "Feature",
  "properties": {
    "gn:admin1_code":"90.0",
    "gn:admin2_code":"0723",
    "gn:asciiname":"Jama",
    "gn:country_code":"CZ",
    "gn:dem":568,
    "gn:feature_class":"P",
    "gn:feature_code":"PPL",
    "gn:name":"J\u00e1ma",
    "gn:population":0,
    "gn:timezone":"Europe/Prague",
    "iso:country":"CZ",
    "name:bos_x_preferred":[
        "Jama"
    ],
    "name:ceb_x_preferred":[
        "Jama"
    ],
    "name:ces_x_preferred":[
        "Jama"
    ],
    "name:deu_x_preferred":[
        "Jama"
    ],
    "name:est_x_preferred":[
        "Jama"
    ],
    "name:fra_x_preferred":[
        "Jama"
    ],
    "name:hrv_x_preferred":[
        "Jama"
    ],
    "name:ita_x_preferred":[
        "Jama"
    ],
    "name:nld_x_preferred":[
        "Jama"
    ],
    "name:nor_x_preferred":[
        "Jama"
    ],
    "name:pol_x_preferred":[
        "Jama"
    ],
    "name:slk_x_preferred":[
        "Jama"
    ],
    "name:slv_x_preferred":[
        "Jama"
    ],
    "name:spa_x_preferred":[
        "Jama"
    ],
    "name:swe_x_preferred":[
        "Jama"
    ],
    "wof:name":"Jama",
    "wof:placetype":"locality"
},
  "geometry": {"coordinates":[18.13476,49.20262],"type":"Point"}
}