{
  "type": "Feature",
  "properties": {
    "gn:admin1_code":"82.0",
    "gn:admin2_code":"0524",
    "gn:asciiname":"Polom",
    "gn:country_code":"CZ",
    "gn:dem":495,
    "gn:feature_class":"P",
    "gn:feature_code":"PPL",
    "gn:name":"Polom",
    "gn:population":120,
    "gn:timezone":"Europe/Prague",
    "iso:country":"CZ",
    "name:ces_x_preferred":[
        "Polom"
    ],
    "name:eus_x_preferred":[
        "Polom"
    ],
    "name:fas_x_preferred":[
        "\u067e\u0648\u0644\u0648\u0645"
    ],
    "name:hun_x_preferred":[
        "Polom"
    ],
    "name:ita_x_preferred":[
        "Polom"
    ],
    "name:msa_x_preferred":[
        "Polom"
    ],
    "name:nld_x_preferred":[
        "Polom"
    ],
    "name:pol_x_preferred":[
        "Polom"
    ],
    "name:por_x_preferred":[
        "Polom"
    ],
    "name:slk_x_preferred":[
        "Polom"
    ],
    "name:spa_x_preferred":[
        "Polom"
    ],
    "name:srp_x_preferred":[
        "\u041f\u043e\u043b\u043e\u043c"
    ],
    "name:vie_x_preferred":[
        "Polom"
    ],
    "wof:name":"Polom",
    "wof:placetype":"locality",
    "wof:population":120
},
  "geometry": {"coordinates":[16.30665,50.05894],"type":"Point"}
}