{
  "type": "Feature",
  "properties": {
    "gn:admin1_code":"82.0",
    "gn:admin2_code":"0524",
    "gn:asciiname":"Polom",
    "gn:country_code":"CZ",
    "gn:dem":495,
    "gn:feature_class":"P",
    "gn:feature_code":"PPL",
    "gn:name":"Polom",
    "gn:population":120,
    "gn:timezone":"Europe/Prague",
    "iso:country":"CZ",
    "wof:name":"Polom",
    "wof:placetype":"locality",
    "wof:population":120
},
  "geometry": {"coordinates":[16.30665,50.05894],"type":"Point"}
}