{
  "type": "Feature",
  "properties": {
    "gn:admin1_code":"89.0",
    "gn:admin2_code":"0424",
    "gn:asciiname":"Pribenice",
    "gn:country_code":"CZ",
    "gn:dem":335,
    "gn:feature_class":"P",
    "gn:feature_code":"PPL",
    "gn:name":"P\u0159ibenice",
    "gn:population":0,
    "gn:timezone":"Europe/Prague",
    "iso:country":"CZ",
    "wof:name":"Pribenice",
    "wof:placetype":"locality"
},
  "geometry": {"coordinates":[13.37568,50.13951],"type":"Point"}
}