{
  "type": "Feature",
  "properties": {
    "gn:admin1_code":"89.0",
    "gn:admin2_code":"0423",
    "gn:asciiname":"Sedlec",
    "gn:cc2":"CZ",
    "gn:country_code":"CZ",
    "gn:dem":232,
    "gn:feature_class":"P",
    "gn:feature_code":"PPL",
    "gn:name":"Sedlec",
    "gn:population":0,
    "gn:timezone":"Europe/Prague",
    "iso:country":"CZ",
    "name:und_x_variant":[
        "Selz"
    ],
    "wof:name":"Sedlec",
    "wof:placetype":"locality"
},
  "geometry": {"coordinates":[14.23365,50.54213],"type":"Point"}
}