{
  "type": "Feature",
  "properties": {
    "gn:gn_country":"CZ",
    "gn:gn_fcode":"PPL",
    "gn:gn_pop":216,
    "gn:population":216,
    "iso:country":"CZ",
    "name:azb_x_preferred":[
        "\u0633\u062a\u06cc\u0626\u0627"
    ],
    "name:bos_x_preferred":[
        "Slatina"
    ],
    "name:bul_x_preferred":[
        "\u0421\u043b\u0430\u0442\u0438\u043d\u0430"
    ],
    "name:ceb_x_preferred":[
        "Slatina"
    ],
    "name:ces_x_preferred":[
        "Slatina"
    ],
    "name:deu_x_preferred":[
        "Slatina"
    ],
    "name:epo_x_preferred":[
        "Slatina"
    ],
    "name:eus_x_preferred":[
        "Slatina"
    ],
    "name:fin_x_preferred":[
        "Slatina"
    ],
    "name:fra_x_preferred":[
        "Slatina"
    ],
    "name:heb_x_preferred":[
        "\u05e1\u05dc\u05d0\u05d8\u05d9\u05e0\u05d4"
    ],
    "name:hrv_x_preferred":[
        "Slatina"
    ],
    "name:hun_x_preferred":[
        "Slatina"
    ],
    "name:ita_x_preferred":[
        "Slatina"
    ],
    "name:jpn_x_preferred":[
        "\u30b9\u30e9\u30c6\u30a3\u30ca"
    ],
    "name:min_x_preferred":[
        "Slatina"
    ],
    "name:mkd_x_preferred":[
        "\u0421\u043b\u0430\u0442\u0438\u043d\u0430"
    ],
    "name:nld_x_preferred":[
        "Slatina"
    ],
    "name:pol_x_preferred":[
        "Slatina"
    ],
    "name:ron_x_preferred":[
        "Slatina"
    ],
    "name:rus_x_preferred":[
        "\u0421\u043b\u0430\u0442\u0438\u043d\u0430"
    ],
    "name:slk_x_preferred":[
        "Slatina"
    ],
    "name:slv_x_preferred":[
        "Slatina"
    ],
    "name:spa_x_preferred":[
        "Slatina"
    ],
    "name:sqi_x_preferred":[
        "Sllatina"
    ],
    "name:srp_x_preferred":[
        "\u0421\u043b\u0430\u0442\u0438\u043d\u0430"
    ],
    "name:swe_x_preferred":[
        "Slatina"
    ],
    "name:tat_x_preferred":[
        "\u0421\u043b\u0430\u0442\u0438\u043d\u0430"
    ],
    "name:ukr_x_preferred":[
        "\u0421\u043b\u0430\u0442\u0438\u043d\u0430"
    ],
    "qs_pg:aaroncc":"CZ",
    "qs_pg:gn_country":"CZ",
    "qs_pg:gn_fcode":"PPL",
    "qs_pg:gn_pop":216,
    "qs_pg:name":"Slatina",
    "qs_pg:name_adm0":"\u010cesk\u00e1 republika",
    "qs_pg:name_adm1":"\u00dasteck\u00fd kraj",
    "qs_pg:photos_9r":0,
    "qs_pg:photos_sr":0,
    "qs_pg:pop_sr":2,
    "qs_pg:qs_pg_placetype":"locality",
    "qs_pg:qs_pg_placetype_gp":"Town",
    "qs_pg:woe_adm0":23424810,
    "woe:adm0_id":23424810,
    "woe:name_adm0":"\u010cesk\u00e1 republika",
    "woe:name_adm1":"\u00dasteck\u00fd kraj",
    "woe:placetype":"Town",
    "wof:name":"Slatina",
    "wof:placetype":"locality",
    "wof:population":216
},
  "geometry": {"coordinates":[14.03804,50.43058],"type":"Point"}
}