{
  "type": "Feature",
  "properties": {
    "gn:admin1_code":"88.0",
    "gn:admin2_code":"0203",
    "gn:asciiname":"Bratkovice",
    "gn:country_code":"CZ",
    "gn:dem":200,
    "gn:feature_class":"P",
    "gn:feature_code":"PPL",
    "gn:name":"Bratkovice",
    "gn:population":0,
    "gn:timezone":"Europe/Prague",
    "iso:country":"CZ",
    "name:azb_x_preferred":[
        "\u0628\u0631\u0627\u062a\u06a9\u0648\u0648\u06cc\u062a\u0633\u0647"
    ],
    "name:ceb_x_preferred":[
        "Bratkovice"
    ],
    "name:ces_x_preferred":[
        "Bratkovice"
    ],
    "name:deu_x_preferred":[
        "Bratkovice"
    ],
    "name:eus_x_preferred":[
        "Bratkovice"
    ],
    "name:fas_x_preferred":[
        "\u0628\u0631\u0627\u062a\u06a9\u0648\u0648\u06cc\u062a\u0633\u0647"
    ],
    "name:fra_x_preferred":[
        "Bratkovice"
    ],
    "name:hun_x_preferred":[
        "Bratkovice"
    ],
    "name:ita_x_preferred":[
        "Bratkovice"
    ],
    "name:msa_x_preferred":[
        "Bratkovice"
    ],
    "name:nld_x_preferred":[
        "Bratkovice"
    ],
    "name:pol_x_preferred":[
        "Bratkovice"
    ],
    "name:por_x_preferred":[
        "Bratkovice"
    ],
    "name:slk_x_preferred":[
        "Bratkovice"
    ],
    "name:spa_x_preferred":[
        "Bratkovice"
    ],
    "name:srp_x_preferred":[
        "\u0411\u0440\u0430\u0442\u043a\u043e\u0432\u0438\u0446\u0435"
    ],
    "name:swe_x_preferred":[
        "Bratkovice"
    ],
    "name:vie_x_preferred":[
        "Bratkovice"
    ],
    "wof:name":"Bratkovice",
    "wof:placetype":"locality"
},
  "geometry": {"coordinates":[14.18879,50.28413],"type":"Point"}
}