{
  "type": "Feature",
  "properties": {
    "gn:admin1_code":"89.0",
    "gn:admin2_code":"0427",
    "gn:asciiname":"Habri",
    "gn:country_code":"CZ",
    "gn:dem":227,
    "gn:feature_class":"P",
    "gn:feature_code":"PPL",
    "gn:name":"Hab\u0159\u00ed",
    "gn:population":0,
    "gn:timezone":"Europe/Prague",
    "iso:country":"CZ",
    "name:deu_x_preferred":[
        "Haberzie"
    ],
    "wof:name":"Habri",
    "wof:placetype":"locality"
},
  "geometry": {"coordinates":[13.94388,50.6205],"type":"Point"}
}