{
  "type": "Feature",
  "properties": {
    "gn:admin1_code":"88.0",
    "gn:admin2_code":"0204",
    "gn:asciiname":"Liblice",
    "gn:country_code":"CZ",
    "gn:dem":215,
    "gn:feature_class":"P",
    "gn:feature_code":"PPL",
    "gn:name":"Liblice",
    "gn:population":0,
    "gn:timezone":"Europe/Prague",
    "iso:country":"CZ",
    "name:ceb_x_preferred":[
        "Liblice"
    ],
    "name:ces_x_preferred":[
        "Liblice"
    ],
    "name:deu_x_preferred":[
        "Liblice"
    ],
    "name:eus_x_preferred":[
        "Liblice"
    ],
    "name:fra_x_preferred":[
        "Liblice"
    ],
    "name:hun_x_preferred":[
        "Liblice"
    ],
    "name:ita_x_preferred":[
        "Liblice"
    ],
    "name:msa_x_preferred":[
        "Liblice"
    ],
    "name:nld_x_preferred":[
        "Liblice"
    ],
    "name:pol_x_preferred":[
        "Liblice"
    ],
    "name:por_x_preferred":[
        "Liblice"
    ],
    "name:ron_x_preferred":[
        "Liblice"
    ],
    "name:slk_x_preferred":[
        "Liblice"
    ],
    "name:spa_x_preferred":[
        "Liblice"
    ],
    "name:srp_x_preferred":[
        "\u041b\u0438\u0431\u043b\u0438\u0446\u0435"
    ],
    "name:swe_x_preferred":[
        "Liblice"
    ],
    "name:und_x_variant":[
        "Liblitz",
        "Liblice"
    ],
    "name:vie_x_preferred":[
        "Liblice"
    ],
    "wof:name":"Liblice",
    "wof:placetype":"locality"
},
  "geometry": {"coordinates":[14.88473,50.07458],"type":"Point"}
}