{
  "type": "Feature",
  "properties": {
    "gn:admin1_code":"88.0",
    "gn:admin2_code":"0204",
    "gn:asciiname":"Liblice",
    "gn:country_code":"CZ",
    "gn:dem":215,
    "gn:feature_class":"P",
    "gn:feature_code":"PPL",
    "gn:name":"Liblice",
    "gn:population":0,
    "gn:timezone":"Europe/Prague",
    "iso:country":"CZ",
    "name:und_x_variant":[
        "Liblitz",
        "Liblice"
    ],
    "wof:name":"Liblice",
    "wof:placetype":"locality"
},
  "geometry": {"coordinates":[14.88473,50.07458],"type":"Point"}
}