{
  "type": "Feature",
  "properties": {
    "gn:admin1_code":"81.0",
    "gn:admin2_code":"0412",
    "gn:asciiname":"Moricov",
    "gn:country_code":"CZ",
    "gn:dem":460,
    "gn:feature_class":"P",
    "gn:feature_code":"PPL",
    "gn:name":"Mo\u0159i\u010dov",
    "gn:population":0,
    "gn:timezone":"Europe/Prague",
    "iso:country":"CZ",
    "name:und_x_variant":[
        "Moritschau",
        "Mo\u0159i\u010dov"
    ],
    "wof:name":"Moricov",
    "wof:placetype":"locality"
},
  "geometry": {"coordinates":[12.98611,50.29806],"type":"Point"}
}