{
  "type": "Feature",
  "properties": {
    "gn:gn_country":"CZ",
    "gn:gn_fcode":"PPL",
    "gn:gn_pop":847,
    "gn:population":847,
    "iso:country":"CZ",
    "name:azb_x_preferred":[
        "\u0627\u0648\u0628\u0631\u0627\u062a\u0627\u0646"
    ],
    "name:ceb_x_preferred":[
        "Obrata\u0148"
    ],
    "name:ces_x_preferred":[
        "Obrata\u0148"
    ],
    "name:deu_x_preferred":[
        "Obrata\u0148"
    ],
    "name:eng_x_preferred":[
        "Obrata\u0148"
    ],
    "name:eus_x_preferred":[
        "Obrata\u0148"
    ],
    "name:fas_x_preferred":[
        "\u0627\u0648\u0628\u0631\u0627\u062a\u0627\u0646"
    ],
    "name:fra_x_preferred":[
        "Obrata\u0148"
    ],
    "name:hun_x_preferred":[
        "Obrata\u0148"
    ],
    "name:ita_x_preferred":[
        "Obrata\u0148"
    ],
    "name:msa_x_preferred":[
        "Obrata\u0148"
    ],
    "name:nan_x_preferred":[
        "Obrata\u0148"
    ],
    "name:nld_x_preferred":[
        "Obrata\u0148"
    ],
    "name:pol_x_preferred":[
        "Obrata\u0148"
    ],
    "name:por_x_preferred":[
        "Obrata\u0148"
    ],
    "name:slk_x_preferred":[
        "Obrata\u0148"
    ],
    "name:spa_x_preferred":[
        "Obrata\u0148"
    ],
    "name:srp_x_preferred":[
        "\u041e\u0431\u0440\u0430\u0442\u0430\u045a"
    ],
    "name:swe_x_preferred":[
        "Obrata\u0148"
    ],
    "name:unk_x_variant":[
        "Wobratain"
    ],
    "name:vie_x_preferred":[
        "Obrata\u0148"
    ],
    "qs_pg:aaroncc":"CZ",
    "qs_pg:gn_country":"CZ",
    "qs_pg:gn_fcode":"PPL",
    "qs_pg:gn_pop":847,
    "qs_pg:name":"Obrata\u0148",
    "qs_pg:name_adm0":"\u010cesk\u00e1 republika",
    "qs_pg:name_adm1":"Kraj Vyso\u010dina",
    "qs_pg:photos_9k":1,
    "qs_pg:photos_9r":1,
    "qs_pg:photos_all":1,
    "qs_pg:photos_sr":0,
    "qs_pg:pop_sr":2,
    "qs_pg:qs_pg_placetype":"locality",
    "qs_pg:qs_pg_placetype_gp":"Town",
    "qs_pg:woe_adm0":23424810,
    "woe:adm0_id":23424810,
    "woe:name_adm0":"\u010cesk\u00e1 republika",
    "woe:name_adm1":"Kraj Vyso\u010dina",
    "woe:placetype":"Town",
    "wof:name":"Obrata\u0148",
    "wof:placetype":"locality",
    "wof:population":847
},
  "geometry": {"coordinates":[14.94349,49.42506],"type":"Point"}
}