{
  "type": "Feature",
  "properties": {
    "gn:country":"CZ",
    "gn:fcode":"PPL",
    "gn:population":167,
    "iso:country":"CZ",
    "name:cat_x_preferred":[
        "Zachra\u0161\u0165any"
    ],
    "name:ceb_x_preferred":[
        "Zachra\u0161\u0165any"
    ],
    "name:ces_x_preferred":[
        "Zachra\u0161\u0165any"
    ],
    "name:che_x_preferred":[
        "\u0417\u0430\u0445\u0440\u0430\u0448\u0442\u044f\u043d\u0438"
    ],
    "name:deu_x_preferred":[
        "Zachra\u0161\u0165any"
    ],
    "name:eng_x_preferred":[
        "Zachra\u0161\u0165any"
    ],
    "name:eus_x_preferred":[
        "Zachra\u0161\u0165any"
    ],
    "name:fas_x_preferred":[
        "\u0632\u0627\u062e\u0631\u0627\u0634\u0633\u0627\u0646\u06cc"
    ],
    "name:fra_x_preferred":[
        "Zachra\u0161\u0165any"
    ],
    "name:gle_x_preferred":[
        "Zachra\u0161\u0165any"
    ],
    "name:hun_x_preferred":[
        "Zachra\u0161\u0165any"
    ],
    "name:ita_x_preferred":[
        "Zachra\u0161\u0165any"
    ],
    "name:lmo_x_preferred":[
        "Zachra\u0161\u0165any"
    ],
    "name:msa_x_preferred":[
        "Zachra\u0161\u0165any"
    ],
    "name:nan_x_preferred":[
        "Zachra\u0161\u0165any"
    ],
    "name:nld_x_preferred":[
        "Zachra\u0161\u0165any"
    ],
    "name:pol_x_preferred":[
        "Zachra\u0161\u0165any"
    ],
    "name:por_x_preferred":[
        "Zachra\u0161\u0165any"
    ],
    "name:rup_x_preferred":[
        "Zachra\u0161\u0165any"
    ],
    "name:slk_x_preferred":[
        "Zachra\u0161\u0165any"
    ],
    "name:spa_x_preferred":[
        "Zachra\u0161\u0165any"
    ],
    "name:srp_x_preferred":[
        "\u0417\u0430\u0445\u0440\u0430\u0448\u0442\u0458\u0430\u043d\u0438"
    ],
    "name:swe_x_preferred":[
        "Zachra\u0161\u0165any"
    ],
    "name:tat_x_preferred":[
        "\u0417\u0430\u0445\u0440\u0430\u0448\u0442\u044f\u043d\u0438"
    ],
    "name:vie_x_preferred":[
        "Zachra\u0161\u0165any"
    ],
    "qs_pg:aaroncc":"CZ",
    "qs_pg:gn_country":"CZ",
    "qs_pg:gn_fcode":"PPL",
    "qs_pg:gn_pop":167,
    "qs_pg:name":"Zachra\u0161\u0165any",
    "qs_pg:name_adm0":"\u010cesk\u00e1 republika",
    "qs_pg:name_adm1":"Kr\u00e1lov\u00e9hradeck\u00fd kraj",
    "qs_pg:photos_9r":0,
    "qs_pg:photos_sr":0,
    "qs_pg:pop_sr":1,
    "qs_pg:qs_pg_placetype":"locality",
    "qs_pg:qs_pg_placetype_gp":"Town",
    "qs_pg:woe_adm0":23424810,
    "woe:adm0_id":23424810,
    "woe:name_adm0":"\u010cesk\u00e1 republika",
    "woe:name_adm1":"Kr\u00e1lov\u00e9hradeck\u00fd kraj",
    "woe:placetype":"Town",
    "wof:name":"Zachra\u0161\u0165any",
    "wof:placetype":"locality",
    "wof:population":167
},
  "geometry": {"coordinates":[15.48298,50.21114],"type":"Point"}
}