{
  "type": "Feature",
  "properties": {
    "gn:admin1_code":"79",
    "gn:admin2_code":"0315",
    "gn:asciiname":"Trebanice",
    "gn:country_code":"CZ",
    "gn:dem":516,
    "gn:feature_class":"P",
    "gn:feature_code":"PPL",
    "gn:name":"T\u0159ebanice",
    "gn:population":0,
    "gn:timezone":"Europe/Prague",
    "iso:country":"CZ",
    "wof:name":"Trebanice",
    "wof:placetype":"locality"
},
  "geometry": {"coordinates":[14.12697,49.01465],"type":"Point"}
}