{
  "type": "Feature",
  "properties": {
    "gn:gn_country":"CZ",
    "gn:gn_fcode":"PPL",
    "gn:gn_pop":838,
    "gn:population":838,
    "iso:country":"CZ",
    "name:ces_x_preferred":[
        "Besednice"
    ],
    "name:deu_x_preferred":[
        "Besednice"
    ],
    "name:eng_x_preferred":[
        "Besednice"
    ],
    "name:fas_x_preferred":[
        "\u0628\u0633\u062f\u0646\u06cc\u062a\u0633\u0647"
    ],
    "name:fra_x_preferred":[
        "Besednice"
    ],
    "name:hun_x_preferred":[
        "Besednice"
    ],
    "name:ita_x_preferred":[
        "Besednice"
    ],
    "name:msa_x_preferred":[
        "Besednice"
    ],
    "name:nan_x_preferred":[
        "Besednice"
    ],
    "name:nld_x_preferred":[
        "Besednice"
    ],
    "name:pol_x_preferred":[
        "Besednice"
    ],
    "name:por_x_preferred":[
        "Besednice"
    ],
    "name:rup_x_preferred":[
        "Besednice"
    ],
    "name:slk_x_preferred":[
        "Besednice"
    ],
    "name:srp_x_preferred":[
        "\u0411\u0435\u0441\u0435\u0434\u045a\u0438\u0446\u0435"
    ],
    "name:swe_x_preferred":[
        "Besednice"
    ],
    "name:vie_x_preferred":[
        "Besednice"
    ],
    "qs_pg:aaroncc":"CZ",
    "qs_pg:gn_country":"CZ",
    "qs_pg:gn_fcode":"PPL",
    "qs_pg:gn_pop":838,
    "qs_pg:name":"Besednice",
    "qs_pg:name_adm0":"\u010cesk\u00e1 republika",
    "qs_pg:name_adm1":"Jiho\u010desk\u00fd kraj",
    "qs_pg:photos_9r":0,
    "qs_pg:photos_sr":0,
    "qs_pg:pop_sr":2,
    "qs_pg:qs_pg_placetype":"locality",
    "qs_pg:qs_pg_placetype_gp":"Town",
    "qs_pg:woe_adm0":23424810,
    "woe:adm0_id":23424810,
    "woe:name_adm0":"\u010cesk\u00e1 republika",
    "woe:name_adm1":"Jiho\u010desk\u00fd kraj",
    "woe:placetype":"Town",
    "wof:name":"Besednice",
    "wof:placetype":"locality",
    "wof:population":838
},
  "geometry": {"coordinates":[14.55689,48.78999],"type":"Point"}
}