{
  "type": "Feature",
  "properties": {
    "gn:admin1_code":"81",
    "gn:admin2_code":"0413",
    "gn:asciiname":"Muelln",
    "gn:country_code":"CZ",
    "gn:dem":500,
    "gn:feature_class":"P",
    "gn:feature_code":"PPL",
    "gn:name":"Muelln",
    "gn:population":0,
    "gn:timezone":"Europe/Prague",
    "iso:country":"CZ",
    "name:und_x_variant":[
        "M\u00fclln",
        "Muelln",
        "\u0160t\u011bdr\u00e1"
    ],
    "wof:name":"Muelln",
    "wof:placetype":"locality"
},
  "geometry": {"coordinates":[12.54745,50.09249000000001],"type":"Point"}
}