{
  "type": "Feature",
  "properties": {
    "gn:admin1_code":"89",
    "gn:admin2_code":"0423",
    "gn:asciiname":"Zelena Ves",
    "gn:country_code":"CZ",
    "gn:dem":233,
    "gn:feature_class":"P",
    "gn:feature_code":"PPL",
    "gn:name":"Zelen\u00e1 Ves",
    "gn:population":0,
    "gn:timezone":"Europe/Prague",
    "iso:country":"CZ",
    "name:und_x_variant":[
        "Gr\u00fcndorf",
        "Zelen\u00e1 Ves"
    ],
    "wof:name":"Zelena Ves",
    "wof:placetype":"locality"
},
  "geometry": {"coordinates":[14.33523,50.59184000000001],"type":"Point"}
}