{
  "type": "Feature",
  "properties": {
    "gn:admin1_code":"80.0",
    "gn:admin2_code":"0611",
    "gn:asciiname":"Pelestrov",
    "gn:country_code":"CZ",
    "gn:dem":498,
    "gn:feature_class":"P",
    "gn:feature_code":"PPL",
    "gn:name":"Pelestrov",
    "gn:population":0,
    "gn:timezone":"Europe/Prague",
    "iso:country":"CZ",
    "wof:name":"Pelestrov",
    "wof:placetype":"locality"
},
  "geometry": {"coordinates":[15.55992,49.64378],"type":"Point"}
}