{
  "type": "Feature",
  "properties": {
    "gn:admin1_code":"86.0",
    "gn:admin2_code":"0532",
    "gn:asciiname":"Opocinek",
    "gn:country_code":"CZ",
    "gn:dem":227,
    "gn:feature_class":"P",
    "gn:feature_code":"PPL",
    "gn:name":"Opo\u010d\u00ednek",
    "gn:population":0,
    "gn:timezone":"Europe/Prague",
    "iso:country":"CZ",
    "wof:name":"Opocinek",
    "wof:placetype":"locality"
},
  "geometry": {"coordinates":[15.65271,50.03843],"type":"Point"}
}