{
  "type": "Feature",
  "properties": {
    "iso:country":"CZ",
    "name:ces_x_preferred":[
        "De\u0161tn\u00e9 v Orlick\u00fdch hor\u00e1ch"
    ],
    "name:deu_x_preferred":[
        "De\u0161tn\u00e9 v Orlick\u00fdch hor\u00e1ch"
    ],
    "name:eus_x_preferred":[
        "De\u0161tn\u00e9 v Orlick\u00fdch hor\u00e1ch"
    ],
    "name:fas_x_preferred":[
        "\u062f\u0634\u062a\u0646\u0647 \u0641 \u0627\u0648\u0631\u0644\u06cc\u062a\u0633\u06a9\u06cc\u062e \u0647\u0648\u0631\u0627\u062e"
    ],
    "name:fra_x_preferred":[
        "De\u0161tn\u00e9 v Orlick\u00fdch hor\u00e1ch"
    ],
    "name:hun_x_preferred":[
        "De\u0161tn\u00e9 v Orlick\u00fdch hor\u00e1ch"
    ],
    "name:ita_x_preferred":[
        "De\u0161tn\u00e9 v Orlick\u00fdch hor\u00e1ch"
    ],
    "name:msa_x_preferred":[
        "De\u0161tn\u00e9 v Orlick\u00fdch hor\u00e1ch"
    ],
    "name:nld_x_preferred":[
        "De\u0161tn\u00e9 v Orlick\u00fdch hor\u00e1ch"
    ],
    "name:pol_x_preferred":[
        "De\u0161tn\u00e9 v Orlick\u00fdch hor\u00e1ch"
    ],
    "name:por_x_preferred":[
        "De\u0161tn\u00e9 v Orlick\u00fdch hor\u00e1ch"
    ],
    "name:slk_x_preferred":[
        "De\u0161tn\u00e9 v Orlick\u00fdch hor\u00e1ch"
    ],
    "name:spa_x_preferred":[
        "De\u0161tn\u00e9 v Orlick\u00fdch hor\u00e1ch"
    ],
    "name:srp_x_preferred":[
        "\u0414\u0435\u0448\u0442\u043d\u0435 \u0432 \u041e\u0440\u043b\u0438\u0446\u043a\u0438\u0445 \u0445\u043e\u0440\u0430\u0445"
    ],
    "name:vie_x_preferred":[
        "De\u0161tn\u00e9 v Orlick\u00fdch hor\u00e1ch"
    ],
    "qs_pg:aaroncc":"CZ",
    "qs_pg:name":"De\u0161tn\u00e9 v Orlick\u00fdch hor\u00e1ch",
    "qs_pg:name_adm0":"\u010cesk\u00e1 republika",
    "qs_pg:name_adm1":"Kr\u00e1lov\u00e9hradeck\u00fd kraj",
    "qs_pg:photos":3,
    "qs_pg:photos_1k":1,
    "qs_pg:photos_9k":1,
    "qs_pg:photos_9r":1,
    "qs_pg:photos_all":3,
    "qs_pg:photos_sr":1,
    "qs_pg:pop_sr":0,
    "qs_pg:qs_pg_placetype":"localadmin",
    "qs_pg:qs_pg_placetype_gp":"LocalAdmin",
    "qs_pg:woe_adm0":23424810,
    "woe:adm0_id":23424810,
    "woe:name_adm0":"\u010cesk\u00e1 republika",
    "woe:name_adm1":"Kr\u00e1lov\u00e9hradeck\u00fd kraj",
    "woe:placetype":"LocalAdmin",
    "wof:name":"De\u0161tn\u00e9 v Orlick\u00fdch hor\u00e1ch",
    "wof:placetype":"localadmin"
},
  "geometry": {"coordinates":[16.349716,50.29241],"type":"Point"}
}