{
  "type": "Feature",
  "properties": {
    "gn:gn_country":"CZ",
    "gn:gn_fcode":"PPL",
    "gn:gn_pop":216,
    "gn:population":216,
    "iso:country":"CZ",
    "name:cze_x_preferred":[
        "\u00dapohlavy"
    ],
    "name:dut_x_preferred":[
        "\u00dapohlavy"
    ],
    "name:eng_x_preferred":[
        "\u00dapohlavy"
    ],
    "name:epo_x_preferred":[
        "\u00dapohlavy"
    ],
    "name:fre_x_preferred":[
        "\u00dapohlavy"
    ],
    "name:ger_x_preferred":[
        "\u00dapohlavy"
    ],
    "name:hun_x_preferred":[
        "\u00dapohlavy"
    ],
    "name:ita_x_preferred":[
        "\u00dapohlavy"
    ],
    "name:may_x_preferred":[
        "\u00dapohlavy"
    ],
    "name:nan_x_preferred":[
        "\u00dapohlavy"
    ],
    "name:per_x_preferred":[
        "\u0627\u0648\u067e\u0648\u0647\u0644\u0627\u0648\u06cc"
    ],
    "name:por_x_preferred":[
        "\u00dapohlavy"
    ],
    "name:rup_x_preferred":[
        "\u00dapohlavy"
    ],
    "name:slo_x_preferred":[
        "\u00dapohlavy"
    ],
    "name:srp_x_preferred":[
        "\u0423\u043f\u043e\u0445\u043b\u0430\u0432\u0438"
    ],
    "name:swe_x_preferred":[
        "\u00dapohlavy"
    ],
    "name:vie_x_preferred":[
        "\u00dapohlavy"
    ],
    "qs_pg:aaroncc":"CZ",
    "qs_pg:gn_country":"CZ",
    "qs_pg:gn_fcode":"PPL",
    "qs_pg:gn_pop":216,
    "qs_pg:name":"\u00dapohlavy",
    "qs_pg:name_adm0":"\u010cesk\u00e1 republika",
    "qs_pg:name_adm1":"\u00dasteck\u00fd kraj",
    "qs_pg:photos_9r":0,
    "qs_pg:photos_sr":0,
    "qs_pg:pop_sr":2,
    "qs_pg:qs_pg_placetype":"locality",
    "qs_pg:qs_pg_placetype_gp":"Town",
    "qs_pg:woe_adm0":23424810,
    "woe:adm0_id":23424810,
    "woe:name_adm0":"\u010cesk\u00e1 republika",
    "woe:name_adm1":"\u00dasteck\u00fd kraj",
    "woe:placetype":"Town",
    "wof:name":"\u00dapohlavy",
    "wof:placetype":"locality",
    "wof:population":216
},
  "geometry": {"coordinates":[14.03553,50.4631],"type":"Point"}
}