{
  "type": "Feature",
  "properties": {
    "iso:country":"CZ",
    "name:ara_x_preferred":[
        "\u0628\u064a\u0631\u0648\u0646"
    ],
    "name:bul_x_preferred":[
        "\u0411\u0435\u0440\u043e\u0443\u043d"
    ],
    "name:cat_x_preferred":[
        "Beroun"
    ],
    "name:ceb_x_preferred":[
        "Beroun"
    ],
    "name:ces_x_preferred":[
        "Beroun"
    ],
    "name:deu_x_preferred":[
        "Beroun"
    ],
    "name:epo_x_preferred":[
        "Beroun"
    ],
    "name:eus_x_preferred":[
        "Beroun"
    ],
    "name:fas_x_preferred":[
        "\u0628\u0631\u0648\u0648\u0646"
    ],
    "name:fra_x_preferred":[
        "Beroun"
    ],
    "name:hun_x_preferred":[
        "Beroun"
    ],
    "name:ita_x_preferred":[
        "Beroun"
    ],
    "name:kor_x_preferred":[
        "\ubca0\ub85c\uc6b4"
    ],
    "name:lav_x_preferred":[
        "Berouna"
    ],
    "name:lit_x_preferred":[
        "Berounas"
    ],
    "name:msa_x_preferred":[
        "Beroun"
    ],
    "name:nld_x_preferred":[
        "Beroun"
    ],
    "name:nor_x_preferred":[
        "Beroun"
    ],
    "name:oci_x_preferred":[
        "Beroun"
    ],
    "name:pam_x_preferred":[
        "Beroun"
    ],
    "name:pol_x_preferred":[
        "Beroun"
    ],
    "name:por_x_preferred":[
        "Beroun"
    ],
    "name:rus_x_preferred":[
        "\u0411\u0435\u0440\u043e\u0443\u043d"
    ],
    "name:slk_x_preferred":[
        "Beroun"
    ],
    "name:spa_x_preferred":[
        "Beroun"
    ],
    "name:srp_x_preferred":[
        "\u0411\u0435\u0440\u043e\u0443\u043d"
    ],
    "name:swe_x_preferred":[
        "Beroun"
    ],
    "name:tur_x_preferred":[
        "Beroun"
    ],
    "name:vie_x_preferred":[
        "Beroun"
    ],
    "name:war_x_preferred":[
        "Beroun"
    ],
    "qs_pg:aaroncc":"CZ",
    "qs_pg:name":"Beroun",
    "qs_pg:name_adm0":"\u010cesk\u00e1 republika",
    "qs_pg:name_adm1":"St\u0159edo\u010desk\u00fd kraj",
    "qs_pg:photos":186,
    "qs_pg:photos_1k":38,
    "qs_pg:photos_9k":2,
    "qs_pg:photos_9r":5,
    "qs_pg:photos_all":418,
    "qs_pg:photos_sr":4,
    "qs_pg:pop_sr":0,
    "qs_pg:qs_pg_placetype":"localadmin",
    "qs_pg:qs_pg_placetype_gp":"LocalAdmin",
    "qs_pg:woe_adm0":23424810,
    "woe:adm0_id":23424810,
    "woe:name_adm0":"\u010cesk\u00e1 republika",
    "woe:name_adm1":"St\u0159edo\u010desk\u00fd kraj",
    "woe:placetype":"LocalAdmin",
    "wof:name":"Beroun",
    "wof:placetype":"localadmin"
},
  "geometry": {"coordinates":[14.073786,49.964224],"type":"Point"}
}