{
  "type": "Feature",
  "properties": {
    "gn:gn_country":"CZ",
    "gn:gn_fcode":"PPL",
    "gn:gn_pop":595,
    "gn:population":595,
    "iso:country":"CZ",
    "name:cze_x_preferred":[
        "Vlkane\u010d"
    ],
    "name:dut_x_preferred":[
        "Vlkane\u010d"
    ],
    "name:eng_x_preferred":[
        "Vlkane\u010d"
    ],
    "name:fre_x_preferred":[
        "Vlkane\u010d"
    ],
    "name:ger_x_preferred":[
        "Vlkane\u010d"
    ],
    "name:hun_x_preferred":[
        "Vlkane\u010d"
    ],
    "name:ita_x_preferred":[
        "Vlkane\u010d"
    ],
    "name:may_x_preferred":[
        "Vlkane\u010d"
    ],
    "name:per_x_preferred":[
        "\u0648\u0644\u06a9\u0627\u0646\u062a\u0634"
    ],
    "name:pol_x_preferred":[
        "Vlkane\u010d"
    ],
    "name:por_x_preferred":[
        "Vlkane\u010d"
    ],
    "name:slo_x_preferred":[
        "Vlkane\u010d"
    ],
    "name:srp_x_preferred":[
        "\u0412\u043b\u043a\u0430\u043d\u0435\u0447"
    ],
    "name:swe_x_preferred":[
        "Vlkane\u010d"
    ],
    "name:vie_x_preferred":[
        "Vlkane\u010d"
    ],
    "qs_pg:aaroncc":"CZ",
    "qs_pg:gn_country":"CZ",
    "qs_pg:gn_fcode":"PPL",
    "qs_pg:gn_pop":595,
    "qs_pg:name":"Vlkane\u010d",
    "qs_pg:name_adm0":"\u010cesk\u00e1 republika",
    "qs_pg:name_adm1":"St\u0159edo\u010desk\u00fd kraj",
    "qs_pg:photos_9k":1,
    "qs_pg:photos_9r":1,
    "qs_pg:photos_all":2,
    "qs_pg:photos_sr":0,
    "qs_pg:pop_sr":2,
    "qs_pg:qs_pg_placetype":"locality",
    "qs_pg:qs_pg_placetype_gp":"Town",
    "qs_pg:woe_adm0":23424810,
    "woe:adm0_id":23424810,
    "woe:name_adm0":"\u010cesk\u00e1 republika",
    "woe:name_adm1":"St\u0159edo\u010desk\u00fd kraj",
    "woe:placetype":"Town",
    "wof:name":"Vlkane\u010d",
    "wof:placetype":"locality",
    "wof:population":595
},
  "geometry": {"coordinates":[15.40312,49.80638],"type":"Point"}
}