{
  "type": "Feature",
  "properties": {
    "gn:admin1_code":"83.0",
    "gn:admin2_code":"0514",
    "gn:asciiname":"Bohuslav",
    "gn:country_code":"CZ",
    "gn:dem":326,
    "gn:feature_class":"P",
    "gn:feature_code":"PPL",
    "gn:name":"Bohuslav",
    "gn:population":0,
    "gn:timezone":"Europe/Prague",
    "iso:country":"CZ",
    "name:ara_x_preferred":[
        "\u0628\u0648\u0647\u0648\u0633\u0644\u0627\u0641"
    ],
    "name:azb_x_preferred":[
        "\u0628\u0648\u0647\u0648\u0633\u0644\u0627\u0648"
    ],
    "name:bel_x_preferred":[
        "\u0411\u0430\u0433\u0443\u0441\u043b\u0430\u045e"
    ],
    "name:ceb_x_preferred":[
        "Bohuslav"
    ],
    "name:ces_x_preferred":[
        "Bohuslav"
    ],
    "name:crh_x_preferred":[
        "Boguslav"
    ],
    "name:deu_x_preferred":[
        "Bohuslaw"
    ],
    "name:fas_x_preferred":[
        "\u0628\u0648\u0647\u0648\u0633\u0644\u0627\u0648"
    ],
    "name:fin_x_preferred":[
        "Bohuslav"
    ],
    "name:fra_x_preferred":[
        "Bohouslav"
    ],
    "name:hsb_x_preferred":[
        "Bohuslaw"
    ],
    "name:hye_x_preferred":[
        "\u0532\u0578\u0563\u0578\u0582\u057d\u056c\u0561\u057e"
    ],
    "name:ita_x_preferred":[
        "Bohuslav"
    ],
    "name:jpn_x_preferred":[
        "\u30dc\u30d5\u30b9\u30e9\u30fc\u30a6"
    ],
    "name:kat_x_preferred":[
        "\u10d1\u10dd\u10d2\u10e3\u10e1\u10da\u10d0\u10d5\u10d8"
    ],
    "name:lit_x_preferred":[
        "Bohuslavas"
    ],
    "name:nno_x_preferred":[
        "Bohuslav"
    ],
    "name:pol_x_preferred":[
        "Bohus\u0142aw"
    ],
    "name:ron_x_preferred":[
        "Bohuslav"
    ],
    "name:rus_x_preferred":[
        "\u0411\u043e\u0433\u0443\u0441\u043b\u0430\u0432"
    ],
    "name:sah_x_preferred":[
        "\u0411\u043e\u0433\u0443\u0441\u043b\u0430\u0432"
    ],
    "name:ukr_x_preferred":[
        "\u0411\u043e\u0433\u0443\u0441\u043b\u0430\u0432"
    ],
    "name:vie_x_preferred":[
        "Bohuslav"
    ],
    "name:zho_x_preferred":[
        "\u535a\u80e1\u65af\u62c9\u592b"
    ],
    "wof:name":"Bohuslav",
    "wof:placetype":"locality"
},
  "geometry": {"coordinates":[15.20435,50.52246],"type":"Point"}
}