{
  "type": "Feature",
  "properties": {
    "gn:gn_country":"CZ",
    "gn:gn_fcode":"PPL",
    "gn:gn_pop":1110,
    "gn:population":1110,
    "iso:country":"CZ",
    "name:cze_x_preferred":[
        "Dob\u0159\u00edv"
    ],
    "name:dut_x_preferred":[
        "Dob\u0159\u00edv"
    ],
    "name:eng_x_preferred":[
        "Dob\u0159\u00edv"
    ],
    "name:fre_x_preferred":[
        "Dob\u0159\u00edv"
    ],
    "name:ger_x_preferred":[
        "Dob\u0159\u00edv"
    ],
    "name:hun_x_preferred":[
        "Dob\u0159\u00edv"
    ],
    "name:ita_x_preferred":[
        "Dob\u0159\u00edv"
    ],
    "name:may_x_preferred":[
        "Dob\u0159\u00edv"
    ],
    "name:per_x_preferred":[
        "\u062f\u0648\u0628\u0631\u06cc\u0648"
    ],
    "name:pol_x_preferred":[
        "Dob\u0159\u00edv"
    ],
    "name:por_x_preferred":[
        "Dob\u0159\u00edv"
    ],
    "name:slo_x_preferred":[
        "Dob\u0159\u00edv"
    ],
    "name:srp_x_preferred":[
        "\u0414\u043e\u0431\u0440\u0438\u0432"
    ],
    "name:swe_x_preferred":[
        "Dob\u0159\u00edv"
    ],
    "name:unk_x_variant":[
        "Dob\u0159\u00edw"
    ],
    "name:vie_x_preferred":[
        "Dob\u0159\u00edv"
    ],
    "qs_pg:aaroncc":"CZ",
    "qs_pg:gn_country":"CZ",
    "qs_pg:gn_fcode":"PPL",
    "qs_pg:gn_pop":1110,
    "qs_pg:name":"Dob\u0159\u00edv",
    "qs_pg:name_adm0":"\u010cesk\u00e1 republika",
    "qs_pg:name_adm1":"Plze\u0148sk\u00fd kraj",
    "qs_pg:photos_9k":1,
    "qs_pg:photos_9r":1,
    "qs_pg:photos_all":2,
    "qs_pg:photos_sr":0,
    "qs_pg:pop_sr":3,
    "qs_pg:qs_pg_placetype":"locality",
    "qs_pg:qs_pg_placetype_gp":"Town",
    "qs_pg:woe_adm0":23424810,
    "woe:adm0_id":23424810,
    "woe:name_adm0":"\u010cesk\u00e1 republika",
    "woe:name_adm1":"Plze\u0148sk\u00fd kraj",
    "woe:placetype":"Town",
    "wof:name":"Dob\u0159\u00edv",
    "wof:placetype":"locality",
    "wof:population":1110
},
  "geometry": {"coordinates":[13.68681,49.71566],"type":"Point"}
}