{
  "type": "Feature",
  "properties": {
    "gn:admin1_code":"87.0",
    "gn:admin2_code":"0327",
    "gn:asciiname":"Resin",
    "gn:country_code":"CZ",
    "gn:dem":564,
    "gn:feature_class":"P",
    "gn:feature_code":"PPL",
    "gn:name":"\u0158e\u0161\u00edn",
    "gn:population":0,
    "gn:timezone":"Europe/Prague",
    "iso:country":"CZ",
    "name:deu_x_preferred":[
        "R\u00f6ssin"
    ],
    "wof:name":"Resin",
    "wof:placetype":"locality"
},
  "geometry": {"coordinates":[12.95013,49.91011],"type":"Point"}
}