{
  "type": "Feature",
  "properties": {
    "gn:admin1_code":"89.0",
    "gn:admin2_code":"0423",
    "gn:asciiname":"Kletecna",
    "gn:country_code":"CZ",
    "gn:dem":463,
    "gn:feature_class":"P",
    "gn:feature_code":"PPL",
    "gn:name":"Klete\u010dn\u00e1",
    "gn:population":0,
    "gn:timezone":"Europe/Prague",
    "iso:country":"CZ",
    "name:und_x_variant":[
        "Kletschen",
        "Klete\u010dn\u00e1"
    ],
    "wof:name":"Kletecna",
    "wof:placetype":"locality"
},
  "geometry": {"coordinates":[13.98591,50.56837],"type":"Point"}
}