{
  "type": "Feature",
  "properties": {
    "gn:admin1_code":"84",
    "gn:admin2_code":"0713",
    "gn:asciiname":"Starnov",
    "gn:country_code":"CZ",
    "gn:dem":452,
    "gn:feature_class":"P",
    "gn:feature_code":"PPL",
    "gn:name":"\u0160tarnov",
    "gn:population":0,
    "gn:timezone":"Europe/Prague",
    "iso:country":"CZ",
    "wof:name":"Starnov",
    "wof:placetype":"locality"
},
  "geometry": {"coordinates":[16.92512,49.57262],"type":"Point"}
}