{
  "type": "Feature",
  "properties": {
    "gn:gn_country":"CZ",
    "gn:gn_fcode":"PPL",
    "gn:gn_pop":396,
    "gn:population":396,
    "iso:country":"CZ",
    "name:ces_x_preferred":[
        "Mar\u0161ovice"
    ],
    "name:deu_x_preferred":[
        "Mar\u0161ovice u Jablonce nad Nisou"
    ],
    "name:eng_x_preferred":[
        "Mar\u0161ovice"
    ],
    "name:fas_x_preferred":[
        "\u0645\u0627\u0631\u0634\u0648\u0648\u06cc\u062a\u0633\u0647"
    ],
    "name:fra_x_preferred":[
        "Mar\u0161ovice"
    ],
    "name:hun_x_preferred":[
        "Mar\u0161ovice"
    ],
    "name:ita_x_preferred":[
        "Mar\u0161ovice"
    ],
    "name:msa_x_preferred":[
        "Mar\u0161ovice"
    ],
    "name:nld_x_preferred":[
        "Mar\u0161ovice"
    ],
    "name:pol_x_preferred":[
        "Mar\u0161ovice"
    ],
    "name:por_x_preferred":[
        "Mar\u0161ovice"
    ],
    "name:rup_x_preferred":[
        "Mar\u0161ovice"
    ],
    "name:slk_x_preferred":[
        "Mar\u0161ovice"
    ],
    "name:srp_x_preferred":[
        "\u041c\u0430\u0440\u0448\u043e\u0432\u0438\u0446\u0435"
    ],
    "name:swe_x_preferred":[
        "Mar\u0161ovice"
    ],
    "name:vie_x_preferred":[
        "Mar\u0161ovice"
    ],
    "qs_pg:aaroncc":"CZ",
    "qs_pg:gn_country":"CZ",
    "qs_pg:gn_fcode":"PPL",
    "qs_pg:gn_pop":396,
    "qs_pg:name":"Mar\u0161ovice",
    "qs_pg:name_adm0":"\u010cesk\u00e1 republika",
    "qs_pg:name_adm1":"Libereck\u00fd kraj",
    "qs_pg:photos_9k":1,
    "qs_pg:photos_9r":1,
    "qs_pg:photos_all":1,
    "qs_pg:photos_sr":0,
    "qs_pg:pop_sr":2,
    "qs_pg:qs_pg_placetype":"locality",
    "qs_pg:qs_pg_placetype_gp":"Town",
    "qs_pg:woe_adm0":23424810,
    "woe:adm0_id":23424810,
    "woe:name_adm0":"\u010cesk\u00e1 republika",
    "woe:name_adm1":"Libereck\u00fd kraj",
    "woe:placetype":"Town",
    "wof:name":"Mar\u0161ovice",
    "wof:placetype":"locality",
    "wof:population":396
},
  "geometry": {"coordinates":[15.19847,50.69635],"type":"Point"}
}