{
  "type": "Feature",
  "properties": {
    "gn:gn_country":"CZ",
    "gn:gn_fcode":"PPL",
    "gn:gn_pop":791,
    "gn:population":791,
    "iso:country":"CZ",
    "name:bul_x_preferred":[
        "\u0411\u0443\u043b\u0445\u0430\u0440\u0439"
    ],
    "name:cze_x_preferred":[
        "Bulhary"
    ],
    "name:dut_x_preferred":[
        "Bulhary"
    ],
    "name:eng_x_preferred":[
        "Bulhary"
    ],
    "name:fre_x_preferred":[
        "Bulhary"
    ],
    "name:ger_x_preferred":[
        "Bulhary"
    ],
    "name:hun_x_preferred":[
        "Bulhary"
    ],
    "name:ita_x_preferred":[
        "Bulhary"
    ],
    "name:may_x_preferred":[
        "Bulhary"
    ],
    "name:per_x_preferred":[
        "\u0628\u0648\u0644\u0647\u0627\u0631\u06cc"
    ],
    "name:pol_x_preferred":[
        "Bulhary"
    ],
    "name:por_x_preferred":[
        "Bulhary"
    ],
    "name:rup_x_preferred":[
        "Bulhary"
    ],
    "name:slo_x_preferred":[
        "Bulhary"
    ],
    "name:srp_x_preferred":[
        "\u0411\u0443\u043b\u0445\u0430\u0440\u0438"
    ],
    "name:swe_x_preferred":[
        "Bulhary"
    ],
    "name:unk_x_variant":[
        "Pulgram"
    ],
    "name:vie_x_preferred":[
        "Bulhary"
    ],
    "qs_pg:aaroncc":"CZ",
    "qs_pg:gn_country":"CZ",
    "qs_pg:gn_fcode":"PPL",
    "qs_pg:gn_pop":791,
    "qs_pg:name":"Bulhary",
    "qs_pg:name_adm0":"\u010cesk\u00e1 republika",
    "qs_pg:name_adm1":"Jihomoravsk\u00fd kraj",
    "qs_pg:photos_9k":1,
    "qs_pg:photos_9r":1,
    "qs_pg:photos_all":2,
    "qs_pg:photos_sr":0,
    "qs_pg:pop_sr":2,
    "qs_pg:qs_pg_placetype":"locality",
    "qs_pg:qs_pg_placetype_gp":"Town",
    "qs_pg:woe_adm0":23424810,
    "woe:adm0_id":23424810,
    "woe:name_adm0":"\u010cesk\u00e1 republika",
    "woe:name_adm1":"Jihomoravsk\u00fd kraj",
    "woe:placetype":"Town",
    "wof:name":"Bulhary",
    "wof:placetype":"locality",
    "wof:population":791
},
  "geometry": {"coordinates":[16.74874,48.83147],"type":"Point"}
}