{
  "type": "Feature",
  "properties": {
    "gn:country":"CZ",
    "gn:fcode":"PPL",
    "gn:population":282,
    "iso:country":"CZ",
    "name:azb_x_preferred":[
        "\u0627\u0648\u06a9\u0646\u0627"
    ],
    "name:ceb_x_preferred":[
        "Okna"
    ],
    "name:ces_x_preferred":[
        "Okna"
    ],
    "name:deu_x_preferred":[
        "Okna"
    ],
    "name:eng_x_preferred":[
        "Okna"
    ],
    "name:eus_x_preferred":[
        "Okna"
    ],
    "name:fas_x_preferred":[
        "\u0627\u0648\u06a9\u0646\u0627"
    ],
    "name:fra_x_preferred":[
        "Okna"
    ],
    "name:hun_x_preferred":[
        "Okna"
    ],
    "name:ita_x_preferred":[
        "Okna"
    ],
    "name:msa_x_preferred":[
        "Okna"
    ],
    "name:nan_x_preferred":[
        "Okna"
    ],
    "name:nld_x_preferred":[
        "Okna"
    ],
    "name:pol_x_preferred":[
        "Okna"
    ],
    "name:por_x_preferred":[
        "Okna"
    ],
    "name:rup_x_preferred":[
        "Okna"
    ],
    "name:slk_x_preferred":[
        "Okna"
    ],
    "name:spa_x_preferred":[
        "Okna"
    ],
    "name:srp_x_preferred":[
        "\u041e\u043a\u043d\u0430"
    ],
    "name:swe_x_preferred":[
        "Okna"
    ],
    "name:und_x_variant":[
        "Woken"
    ],
    "name:vie_x_preferred":[
        "Okna"
    ],
    "qs_pg:aaroncc":"CZ",
    "qs_pg:gn_country":"CZ",
    "qs_pg:gn_fcode":"PPL",
    "qs_pg:gn_pop":282,
    "qs_pg:name":"Okna",
    "qs_pg:photos_9r":0,
    "qs_pg:photos_sr":0,
    "qs_pg:pop_sr":2,
    "qs_pg:qs_pg_placetype":"locality",
    "wof:name":"Okna",
    "wof:placetype":"locality",
    "wof:population":282
},
  "geometry": {"coordinates":[14.67096,50.52749],"type":"Point"}
}