{
  "type": "Feature",
  "properties": {
    "gn:country":"CZ",
    "gn:fcode":"PPL",
    "gn:population":342,
    "iso:country":"CZ",
    "name:azb_x_preferred":[
        "\u0633\u0648\u0631\u0627\u062f\u06cc\u062a\u0633\u0647"
    ],
    "name:ceb_x_preferred":[
        "Sv\u00e9radice"
    ],
    "name:ces_x_preferred":[
        "Sv\u00e9radice"
    ],
    "name:eng_x_preferred":[
        "Sv\u00e9radice"
    ],
    "name:eus_x_preferred":[
        "Sv\u00e9radice"
    ],
    "name:fas_x_preferred":[
        "\u0633\u0648\u0631\u0627\u062f\u06cc\u062a\u0633\u0647"
    ],
    "name:fra_x_preferred":[
        "Sv\u00e9radice"
    ],
    "name:hun_x_preferred":[
        "Sv\u00e9radice"
    ],
    "name:ita_x_preferred":[
        "Sv\u00e9radice"
    ],
    "name:msa_x_preferred":[
        "Sv\u00e9radice"
    ],
    "name:nan_x_preferred":[
        "Sv\u00e9radice"
    ],
    "name:nld_x_preferred":[
        "Sv\u00e9radice"
    ],
    "name:por_x_preferred":[
        "Sv\u00e9radice"
    ],
    "name:slk_x_preferred":[
        "Sv\u00e9radice"
    ],
    "name:spa_x_preferred":[
        "Sv\u00e9radice"
    ],
    "name:srp_x_preferred":[
        "\u0421\u0432\u0435\u0440\u0430\u0434\u0438\u0446\u0435"
    ],
    "name:swe_x_preferred":[
        "Sv\u00e9radice"
    ],
    "name:vie_x_preferred":[
        "Sv\u00e9radice"
    ],
    "qs_pg:aaroncc":"CZ",
    "qs_pg:gn_country":"CZ",
    "qs_pg:gn_fcode":"PPL",
    "qs_pg:gn_pop":342,
    "qs_pg:name":"Sv\u00e9radice",
    "qs_pg:name_adm0":"\u010cesk\u00e1 republika",
    "qs_pg:name_adm1":"Plze\u0148sk\u00fd kraj",
    "qs_pg:photos_9r":0,
    "qs_pg:photos_sr":0,
    "qs_pg:pop_sr":2,
    "qs_pg:qs_pg_placetype":"locality",
    "qs_pg:qs_pg_placetype_gp":"Town",
    "qs_pg:woe_adm0":23424810,
    "woe:adm0_id":23424810,
    "woe:name_adm0":"\u010cesk\u00e1 republika",
    "woe:name_adm1":"Plze\u0148sk\u00fd kraj",
    "woe:placetype":"Town",
    "wof:name":"Sv\u00e9radice",
    "wof:placetype":"locality",
    "wof:population":342
},
  "geometry": {"coordinates":[13.73959,49.37134],"type":"Point"}
}