{
  "type": "Feature",
  "properties": {
    "iso:country":"CZ",
    "name:azb_x_preferred":[
        "\u0698\u06cc\u0631\u0648\u0648\u0646\u06cc\u062a\u0633\u0647"
    ],
    "name:ceb_x_preferred":[
        "\u017dirovnice"
    ],
    "name:ces_x_preferred":[
        "\u017dirovnice"
    ],
    "name:deu_x_preferred":[
        "\u017dirovnice"
    ],
    "name:epo_x_preferred":[
        "\u017dirovnice"
    ],
    "name:eus_x_preferred":[
        "\u017dirovnice"
    ],
    "name:fas_x_preferred":[
        "\u0698\u06cc\u0631\u0648\u0648\u0646\u06cc\u062a\u0633\u0647"
    ],
    "name:fra_x_preferred":[
        "\u017dirovnice"
    ],
    "name:hun_x_preferred":[
        "\u017dirovnice"
    ],
    "name:ita_x_preferred":[
        "\u017dirovnice"
    ],
    "name:lav_x_preferred":[
        "\u017dirovnice"
    ],
    "name:msa_x_preferred":[
        "\u017dirovnice"
    ],
    "name:nld_x_preferred":[
        "\u017dirovnice"
    ],
    "name:pol_x_preferred":[
        "\u017dirovnice"
    ],
    "name:por_x_preferred":[
        "\u017dirovnice"
    ],
    "name:rus_x_preferred":[
        "\u0416\u0438\u0440\u043e\u0432\u043d\u0438\u0446\u0435"
    ],
    "name:slk_x_preferred":[
        "\u017dirovnice"
    ],
    "name:spa_x_preferred":[
        "\u017dirovnice"
    ],
    "name:srp_x_preferred":[
        "\u0416\u0438\u0440\u043e\u0432\u045a\u0438\u0446\u0435"
    ],
    "name:swe_x_preferred":[
        "\u017dirovnice"
    ],
    "name:vie_x_preferred":[
        "\u017dirovnice"
    ],
    "name:zho_x_preferred":[
        "\u65e5\u7f85\u592b\u5c3c\u91c7"
    ],
    "qs_pg:aaroncc":"CZ",
    "qs_pg:name":"\u017dirovnice",
    "qs_pg:name_adm0":"\u010cesk\u00e1 republika",
    "qs_pg:name_adm1":"Kraj Vyso\u010dina",
    "qs_pg:photos":2,
    "qs_pg:photos_1k":1,
    "qs_pg:photos_9k":5,
    "qs_pg:photos_9r":7,
    "qs_pg:photos_all":1140,
    "qs_pg:photos_sr":1,
    "qs_pg:pop_sr":0,
    "qs_pg:qs_pg_placetype":"localadmin",
    "qs_pg:qs_pg_placetype_gp":"LocalAdmin",
    "qs_pg:woe_adm0":23424810,
    "woe:adm0_id":23424810,
    "woe:name_adm0":"\u010cesk\u00e1 republika",
    "woe:name_adm1":"Kraj Vyso\u010dina",
    "woe:placetype":"LocalAdmin",
    "wof:name":"\u017dirovnice",
    "wof:placetype":"localadmin"
},
  "geometry": {"coordinates":[15.17568,49.25153],"type":"Point"}
}