{
  "type": "Feature",
  "properties": {
    "gn:gn_country":"CZ",
    "gn:gn_fcode":"PPL",
    "gn:gn_pop":88,
    "gn:population":88,
    "iso:country":"CZ",
    "name:ces_x_preferred":[
        "Lu\u017ece"
    ],
    "name:deu_x_preferred":[
        "Lu\u017ece"
    ],
    "name:eng_x_preferred":[
        "Lu\u017ece"
    ],
    "name:fas_x_preferred":[
        "\u0644\u0648\u0698\u062a\u0633\u0647"
    ],
    "name:fra_x_preferred":[
        "Lu\u017ece"
    ],
    "name:hun_x_preferred":[
        "Lu\u017ece"
    ],
    "name:ita_x_preferred":[
        "Lu\u017ece"
    ],
    "name:msa_x_preferred":[
        "Lu\u017ece"
    ],
    "name:nld_x_preferred":[
        "Lu\u017ece"
    ],
    "name:pol_x_preferred":[
        "Lu\u017ece"
    ],
    "name:por_x_preferred":[
        "Lu\u017ece"
    ],
    "name:slk_x_preferred":[
        "Lu\u017ece"
    ],
    "name:srp_x_preferred":[
        "\u041b\u0443\u0436\u0446\u0435"
    ],
    "name:vie_x_preferred":[
        "Lu\u017ece"
    ],
    "qs_pg:aaroncc":"CZ",
    "qs_pg:gn_country":"CZ",
    "qs_pg:gn_fcode":"PPL",
    "qs_pg:gn_pop":88,
    "qs_pg:name":"Lu\u017ece",
    "qs_pg:name_adm0":"\u010cesk\u00e1 republika",
    "qs_pg:name_adm1":"St\u0159edo\u010desk\u00fd kraj",
    "qs_pg:photos_9r":0,
    "qs_pg:photos_sr":0,
    "qs_pg:pop_sr":1,
    "qs_pg:qs_pg_placetype":"locality",
    "qs_pg:qs_pg_placetype_gp":"Town",
    "qs_pg:woe_adm0":23424810,
    "woe:adm0_id":23424810,
    "woe:name_adm0":"\u010cesk\u00e1 republika",
    "woe:name_adm1":"St\u0159edo\u010desk\u00fd kraj",
    "woe:placetype":"Town",
    "wof:name":"Lu\u017ece",
    "wof:placetype":"locality",
    "wof:population":88
},
  "geometry": {"coordinates":[14.19672,49.98412],"type":"Point"}
}