{
  "type": "Feature",
  "properties": {
    "gn:admin1_code":"88.0",
    "gn:admin2_code":"0201",
    "gn:asciiname":"Petriny",
    "gn:country_code":"CZ",
    "gn:dem":432,
    "gn:feature_class":"P",
    "gn:feature_code":"PPL",
    "gn:name":"Pet\u0159\u00edny",
    "gn:population":0,
    "gn:timezone":"Europe/Prague",
    "iso:country":"CZ",
    "wof:name":"Petriny",
    "wof:placetype":"locality"
},
  "geometry": {"coordinates":[14.94194,49.73524000000001],"type":"Point"}
}