{
  "type": "Feature",
  "properties": {
    "gn:admin1_code":"79.0",
    "gn:admin2_code":"0311",
    "gn:asciiname":"Kaliste",
    "gn:country_code":"CZ",
    "gn:dem":515,
    "gn:feature_class":"P",
    "gn:feature_code":"PPL",
    "gn:name":"Kali\u0161t\u011b",
    "gn:population":0,
    "gn:timezone":"Europe/Prague",
    "iso:country":"CZ",
    "wof:name":"Kaliste",
    "wof:placetype":"locality"
},
  "geometry": {"coordinates":[14.57536,48.96565],"type":"Point"}
}