{
  "type": "Feature",
  "properties": {
    "gn:admin1_code":"82.0",
    "gn:admin2_code":"0521",
    "gn:asciiname":"Jericky",
    "gn:country_code":"CZ",
    "gn:dem":266,
    "gn:feature_class":"P",
    "gn:feature_code":"PPL",
    "gn:name":"Je\u0159i\u010dky",
    "gn:population":0,
    "gn:timezone":"Europe/Prague",
    "iso:country":"CZ",
    "wof:name":"Jericky",
    "wof:placetype":"locality"
},
  "geometry": {"coordinates":[15.76982,50.34418],"type":"Point"}
}