{
  "type": "Feature",
  "properties": {
    "gn:gn_country":"CZ",
    "gn:gn_fcode":"PPL",
    "gn:gn_pop":703,
    "gn:population":703,
    "iso:country":"CZ",
    "name:ces_x_preferred":[
        "Ohrobec"
    ],
    "name:eng_x_preferred":[
        "Ohrobec"
    ],
    "name:fas_x_preferred":[
        "\u0627\u0648\u0647\u0631\u0648\u0628\u062a\u0633"
    ],
    "name:fra_x_preferred":[
        "Ohrobec"
    ],
    "name:hun_x_preferred":[
        "Ohrobec"
    ],
    "name:ita_x_preferred":[
        "Ohrobec"
    ],
    "name:msa_x_preferred":[
        "Ohrobec"
    ],
    "name:nld_x_preferred":[
        "Ohrobec"
    ],
    "name:pol_x_preferred":[
        "Ohrobec"
    ],
    "name:por_x_preferred":[
        "Ohrobec"
    ],
    "name:rus_x_preferred":[
        "\u041e\u0433\u0440\u043e\u0431\u0435\u0446"
    ],
    "name:slk_x_preferred":[
        "Ohrobec"
    ],
    "name:srp_x_preferred":[
        "\u041e\u0445\u0440\u043e\u0431\u0435\u0446"
    ],
    "name:swe_x_preferred":[
        "Ohrobec"
    ],
    "name:unk_x_variant":[
        "Ochrobetz"
    ],
    "name:vie_x_preferred":[
        "Ohrobec"
    ],
    "qs_pg:aaroncc":"CZ",
    "qs_pg:gn_country":"CZ",
    "qs_pg:gn_fcode":"PPL",
    "qs_pg:gn_pop":703,
    "qs_pg:name":"Ohrobec",
    "qs_pg:name_adm0":"\u010cesk\u00e1 republika",
    "qs_pg:name_adm1":"St\u0159edo\u010desk\u00fd kraj",
    "qs_pg:photos_9k":1,
    "qs_pg:photos_9r":1,
    "qs_pg:photos_all":1,
    "qs_pg:photos_sr":0,
    "qs_pg:pop_sr":2,
    "qs_pg:qs_pg_placetype":"locality",
    "qs_pg:qs_pg_placetype_gp":"Town",
    "qs_pg:woe_adm0":23424810,
    "woe:adm0_id":23424810,
    "woe:name_adm0":"\u010cesk\u00e1 republika",
    "woe:name_adm1":"St\u0159edo\u010desk\u00fd kraj",
    "woe:placetype":"Town",
    "wof:name":"Ohrobec",
    "wof:placetype":"locality",
    "wof:population":703
},
  "geometry": {"coordinates":[14.43203,49.94172],"type":"Point"}
}