{
  "type": "Feature",
  "properties": {
    "gn:country":"CZ",
    "gn:fcode":"PPL",
    "gn:population":220,
    "iso:country":"CZ",
    "name:azb_x_preferred":[
        "\u0698\u0627\u0628\u0648\u0648\u0631\u0633\u06a9\u06cc \u0646\u0627\u062f \u0627\u0648\u0647\u0631\u06cc"
    ],
    "name:ceb_x_preferred":[
        "\u017dabov\u0159esky nad Oh\u0159\u00ed"
    ],
    "name:ces_x_preferred":[
        "\u017dabov\u0159esky nad Oh\u0159\u00ed"
    ],
    "name:deu_x_preferred":[
        "\u017dabov\u0159esky nad Oh\u0159\u00ed"
    ],
    "name:eng_x_preferred":[
        "\u017dabov\u0159esky nad Oh\u0159\u00ed"
    ],
    "name:epo_x_preferred":[
        "\u017dabov\u0159esky nad Oh\u0159\u00ed"
    ],
    "name:eus_x_preferred":[
        "\u017dabov\u0159esky nad Oh\u0159\u00ed"
    ],
    "name:fas_x_preferred":[
        "\u0698\u0627\u0628\u0648\u0648\u0631\u0633\u06a9\u06cc \u0646\u0627\u062f \u0627\u0648\u0647\u0631\u06cc"
    ],
    "name:fra_x_preferred":[
        "\u017dabov\u0159esky nad Oh\u0159\u00ed"
    ],
    "name:hun_x_preferred":[
        "\u017dabov\u0159esky nad Oh\u0159\u00ed"
    ],
    "name:ita_x_preferred":[
        "\u017dabov\u0159esky nad Oh\u0159\u00ed"
    ],
    "name:msa_x_preferred":[
        "\u017dabov\u0159esky nad Oh\u0159\u00ed"
    ],
    "name:nan_x_preferred":[
        "\u017dabov\u0159esky nad Oh\u0159\u00ed"
    ],
    "name:nld_x_preferred":[
        "\u017dabov\u0159esky nad Oh\u0159\u00ed"
    ],
    "name:por_x_preferred":[
        "\u017dabov\u0159esky nad Oh\u0159\u00ed"
    ],
    "name:rup_x_preferred":[
        "\u017dabov\u0159esky nad Oh\u0159\u00ed"
    ],
    "name:slk_x_preferred":[
        "\u017dabov\u0159esky nad Oh\u0159\u00ed"
    ],
    "name:spa_x_preferred":[
        "\u017dabov\u0159esky nad Oh\u0159\u00ed"
    ],
    "name:srp_x_preferred":[
        "\u0416\u0430\u0431\u043e\u0432\u0440\u0435\u0441\u043a\u0438 \u043d\u0430 \u041e\u0445\u0440\u0438"
    ],
    "name:swe_x_preferred":[
        "\u017dabov\u0159esky nad Oh\u0159\u00ed"
    ],
    "name:urd_x_preferred":[
        "\u0698\u0627\u0628\u0648\u0648\u0631\u06cc\u0633\u06a9\u06d2 \u0646\u0627\u062f \u0648\u06c1\u0631\u06cc"
    ],
    "name:vie_x_preferred":[
        "\u017dabov\u0159esky nad Oh\u0159\u00ed"
    ],
    "qs_pg:aaroncc":"CZ",
    "qs_pg:gn_country":"CZ",
    "qs_pg:gn_fcode":"PPL",
    "qs_pg:gn_pop":220,
    "qs_pg:name":"\u017dabov\u0159esky nad Oh\u0159\u00ed",
    "qs_pg:name_adm0":"\u010cesk\u00e1 republika",
    "qs_pg:name_adm1":"\u00dasteck\u00fd kraj",
    "qs_pg:photos_9r":0,
    "qs_pg:photos_sr":0,
    "qs_pg:pop_sr":2,
    "qs_pg:qs_pg_placetype":"locality",
    "qs_pg:qs_pg_placetype_gp":"Town",
    "qs_pg:woe_adm0":23424810,
    "woe:adm0_id":23424810,
    "woe:name_adm0":"\u010cesk\u00e1 republika",
    "woe:name_adm1":"\u00dasteck\u00fd kraj",
    "woe:placetype":"Town",
    "wof:name":"\u017dabov\u0159esky nad Oh\u0159\u00ed",
    "wof:placetype":"locality",
    "wof:population":220
},
  "geometry": {"coordinates":[14.09103,50.41316],"type":"Point"}
}