{
  "type": "Feature",
  "properties": {
    "gn:admin1_code":"86.0",
    "gn:admin2_code":"0534",
    "gn:asciiname":"Podhorany",
    "gn:country_code":"CZ",
    "gn:dem":451,
    "gn:feature_class":"P",
    "gn:feature_code":"PPL",
    "gn:name":"Podho\u0159any",
    "gn:population":0,
    "gn:timezone":"Europe/Prague",
    "iso:country":"CZ",
    "name:cat_x_preferred":[
        "Podhorany"
    ],
    "name:ces_x_preferred":[
        "Podhorany"
    ],
    "name:deu_x_preferred":[
        "Podhorany"
    ],
    "name:epo_x_preferred":[
        "Podhorany"
    ],
    "name:fra_x_preferred":[
        "Podhorany"
    ],
    "name:hun_x_preferred":[
        "Podhorany"
    ],
    "name:ita_x_preferred":[
        "Podhorany"
    ],
    "name:nld_x_preferred":[
        "Podhorany"
    ],
    "name:pol_x_preferred":[
        "Podhorany"
    ],
    "name:slk_x_preferred":[
        "Podhorany"
    ],
    "name:srp_x_preferred":[
        "\u041f\u043e\u0434\u0445\u043e\u0440\u0430\u043d\u0438"
    ],
    "name:ukr_x_preferred":[
        "\u041f\u043e\u0434\u0433\u043e\u0440\u0430\u043d\u0438"
    ],
    "wof:name":"Podhorany",
    "wof:placetype":"locality"
},
  "geometry": {"coordinates":[16.13565,49.86871],"type":"Point"}
}