{
  "type": "Feature",
  "properties": {
    "gn:admin1_code":"86.0",
    "gn:admin2_code":"0534",
    "gn:asciiname":"Podhorany",
    "gn:country_code":"CZ",
    "gn:dem":451,
    "gn:feature_class":"P",
    "gn:feature_code":"PPL",
    "gn:name":"Podho\u0159any",
    "gn:population":0,
    "gn:timezone":"Europe/Prague",
    "iso:country":"CZ",
    "wof:name":"Podhorany",
    "wof:placetype":"locality"
},
  "geometry": {"coordinates":[16.13565,49.86871],"type":"Point"}
}