{
  "type": "Feature",
  "properties": {
    "gn:admin1_code":"88.0",
    "gn:admin2_code":"0205",
    "gn:asciiname":"Mala Skalice",
    "gn:country_code":"CZ",
    "gn:dem":450,
    "gn:feature_class":"P",
    "gn:feature_code":"PPL",
    "gn:name":"Mal\u00e1 Skalice",
    "gn:population":0,
    "gn:timezone":"Europe/Prague",
    "iso:country":"CZ",
    "wof:name":"Mala Skalice",
    "wof:placetype":"locality"
},
  "geometry": {"coordinates":[15.15662,49.81946],"type":"Point"}
}