{
  "type": "Feature",
  "properties": {
    "gn:admin1_code":"82.0",
    "gn:admin2_code":"0524",
    "gn:asciiname":"Mala Cermna nad Orlici",
    "gn:country_code":"CZ",
    "gn:dem":261,
    "gn:feature_class":"P",
    "gn:feature_code":"PPL",
    "gn:name":"Mal\u00e1 \u010cermn\u00e1 nad Orlic\u00ed",
    "gn:population":0,
    "gn:timezone":"Europe/Prague",
    "iso:country":"CZ",
    "name:und_x_variant":[
        "Klein \u010cerma",
        "Mal\u00e1 \u010cermn\u00e1 nad Orlic\u00ed"
    ],
    "wof:name":"Mala Cermna nad Orlici",
    "wof:placetype":"locality"
},
  "geometry": {"coordinates":[16.13293,50.0762],"type":"Point"}
}