{
  "type": "Feature",
  "properties": {
    "gn:admin1_code":"85.0",
    "gn:admin2_code":"0801",
    "gn:asciiname":"Novy Les",
    "gn:country_code":"CZ",
    "gn:dem":355,
    "gn:feature_class":"P",
    "gn:feature_code":"PPL",
    "gn:name":"Nov\u00fd Les",
    "gn:population":0,
    "gn:timezone":"Europe/Prague",
    "iso:country":"CZ",
    "name:und_x_variant":[
        "Neuwald",
        "Nov\u00fd Les"
    ],
    "wof:name":"Novy Les",
    "wof:placetype":"locality"
},
  "geometry": {"coordinates":[17.63922999999999,50.20114],"type":"Point"}
}