{
  "type": "Feature",
  "properties": {
    "gn:admin1_code":"79.0",
    "gn:admin2_code":"0317",
    "gn:asciiname":"Lisky",
    "gn:country_code":"CZ",
    "gn:dem":616,
    "gn:feature_class":"P",
    "gn:feature_code":"PPL",
    "gn:name":"L\u00edsky",
    "gn:population":0,
    "gn:timezone":"Europe/Prague",
    "iso:country":"CZ",
    "wof:name":"Lisky",
    "wof:placetype":"locality"
},
  "geometry": {"coordinates":[14.89576,49.37049],"type":"Point"}
}