{
  "type": "Feature",
  "properties": {
    "gn:admin1_code":"87.0",
    "gn:admin2_code":"0327",
    "gn:asciiname":"Kostelec",
    "gn:country_code":"CZ",
    "gn:dem":486,
    "gn:feature_class":"P",
    "gn:feature_code":"PPL",
    "gn:name":"Kostelec",
    "gn:population":547,
    "gn:timezone":"Europe/Prague",
    "iso:country":"CZ",
    "name:ceb_x_preferred":[
        "Kostelec"
    ],
    "name:ces_x_preferred":[
        "Kostelec"
    ],
    "name:deu_x_preferred":[
        "Kostelec"
    ],
    "name:fra_x_preferred":[
        "Kostelec"
    ],
    "name:ita_x_preferred":[
        "Kostelec"
    ],
    "name:nld_x_preferred":[
        "Kostelec"
    ],
    "name:slk_x_preferred":[
        "Kostelec"
    ],
    "name:srp_x_preferred":[
        "\u041a\u043e\u0441\u0442\u0435\u043b\u0435\u0446"
    ],
    "name:swe_x_preferred":[
        "Kostelec"
    ],
    "name:ukr_x_preferred":[
        "\u041a\u043e\u0441\u0442\u0435\u043b\u0435\u0446"
    ],
    "name:und_x_variant":[
        "Kostelzen"
    ],
    "wof:name":"Kostelec",
    "wof:placetype":"locality",
    "wof:population":547
},
  "geometry": {"coordinates":[13.02638,49.6743],"type":"Point"}
}