{
  "type": "Feature",
  "properties": {
    "gn:admin1_code":"87.0",
    "gn:admin2_code":"0327",
    "gn:asciiname":"Kostelec",
    "gn:country_code":"CZ",
    "gn:dem":486,
    "gn:feature_class":"P",
    "gn:feature_code":"PPL",
    "gn:name":"Kostelec",
    "gn:population":547,
    "gn:timezone":"Europe/Prague",
    "iso:country":"CZ",
    "name:und_x_variant":[
        "Kostelzen"
    ],
    "wof:name":"Kostelec",
    "wof:placetype":"locality",
    "wof:population":547
},
  "geometry": {"coordinates":[13.02638,49.6743],"type":"Point"}
}