{
  "type": "Feature",
  "properties": {
    "gn:gn_country":"CZ",
    "gn:gn_fcode":"PPL",
    "gn:gn_pop":161,
    "gn:population":161,
    "iso:country":"CZ",
    "name:cze_x_preferred":[
        "Sob\u00ed\u0161ky"
    ],
    "name:dut_x_preferred":[
        "Sob\u00ed\u0161ky"
    ],
    "name:eng_x_preferred":[
        "Sob\u00ed\u0161ky"
    ],
    "name:fre_x_preferred":[
        "Sob\u00ed\u0161ky"
    ],
    "name:ger_x_preferred":[
        "Sob\u00ed\u0161ky"
    ],
    "name:hun_x_preferred":[
        "Sob\u00ed\u0161ky"
    ],
    "name:ita_x_preferred":[
        "Sob\u00ed\u0161ky"
    ],
    "name:may_x_preferred":[
        "Sob\u00ed\u0161ky"
    ],
    "name:per_x_preferred":[
        "\u0633\u0648\u0628\u06cc\u0634\u06a9\u06cc"
    ],
    "name:pol_x_preferred":[
        "Sob\u00ed\u0161ky"
    ],
    "name:por_x_preferred":[
        "Sob\u00ed\u0161ky"
    ],
    "name:slo_x_preferred":[
        "Sob\u00ed\u0161ky"
    ],
    "name:srp_x_preferred":[
        "\u0421\u043e\u0431\u0438\u0448\u043a\u0438"
    ],
    "name:swe_x_preferred":[
        "Sob\u00ed\u0161ky"
    ],
    "name:vie_x_preferred":[
        "Sob\u00ed\u0161ky"
    ],
    "qs_pg:aaroncc":"CZ",
    "qs_pg:gn_country":"CZ",
    "qs_pg:gn_fcode":"PPL",
    "qs_pg:gn_pop":161,
    "qs_pg:name":"Sob\u00ed\u0161ky",
    "qs_pg:name_adm0":"\u010cesk\u00e1 republika",
    "qs_pg:name_adm1":"Olomouck\u00fd kraj",
    "qs_pg:photos_9r":0,
    "qs_pg:photos_sr":0,
    "qs_pg:pop_sr":1,
    "qs_pg:qs_pg_placetype":"locality",
    "qs_pg:qs_pg_placetype_gp":"Town",
    "qs_pg:woe_adm0":23424810,
    "woe:adm0_id":23424810,
    "woe:name_adm0":"\u010cesk\u00e1 republika",
    "woe:name_adm1":"Olomouck\u00fd kraj",
    "woe:placetype":"Town",
    "wof:name":"Sob\u00ed\u0161ky",
    "wof:placetype":"locality",
    "wof:population":161
},
  "geometry": {"coordinates":[17.45077,49.50376],"type":"Point"}
}