{
  "type": "Feature",
  "properties": {
    "gn:gn_country":"CZ",
    "gn:gn_fcode":"PPL",
    "gn:gn_pop":33,
    "gn:population":33,
    "iso:country":"CZ",
    "name:cze_x_preferred":[
        "Nem\u00ed\u017e"
    ],
    "name:dut_x_preferred":[
        "Nem\u00ed\u017e"
    ],
    "name:eng_x_preferred":[
        "Nem\u00ed\u017e"
    ],
    "name:fre_x_preferred":[
        "Nem\u00ed\u017e"
    ],
    "name:hun_x_preferred":[
        "Nem\u00ed\u017e"
    ],
    "name:may_x_preferred":[
        "Nem\u00ed\u017e"
    ],
    "name:per_x_preferred":[
        "\u0646\u0645\u06cc\u0698"
    ],
    "name:slo_x_preferred":[
        "Nem\u00ed\u017e"
    ],
    "qs_pg:aaroncc":"CZ",
    "qs_pg:gn_country":"CZ",
    "qs_pg:gn_fcode":"PPL",
    "qs_pg:gn_pop":33,
    "qs_pg:name":"Nem\u00ed\u017e",
    "qs_pg:name_adm0":"\u010cesk\u00e1 republika",
    "qs_pg:name_adm1":"St\u0159edo\u010desk\u00fd kraj",
    "qs_pg:photos_9r":0,
    "qs_pg:photos_sr":0,
    "qs_pg:pop_sr":1,
    "qs_pg:qs_pg_placetype":"locality",
    "qs_pg:qs_pg_placetype_gp":"Town",
    "qs_pg:woe_adm0":23424810,
    "woe:adm0_id":23424810,
    "woe:name_adm0":"\u010cesk\u00e1 republika",
    "woe:name_adm1":"St\u0159edo\u010desk\u00fd kraj",
    "woe:placetype":"Town",
    "wof:name":"Nem\u00ed\u017e",
    "wof:placetype":"locality",
    "wof:population":33
},
  "geometry": {"coordinates":[14.93353,49.74275],"type":"Point"}
}