{
  "type": "Feature",
  "properties": {
    "gn:admin1_code":"88",
    "gn:admin2_code":"0205",
    "gn:asciiname":"Suchdol",
    "gn:country_code":"CZ",
    "gn:dem":370,
    "gn:feature_class":"P",
    "gn:feature_code":"PPL",
    "gn:name":"Suchdol",
    "gn:population":1065,
    "gn:timezone":"Europe/Prague",
    "iso:country":"CZ",
    "name:azb_x_preferred":[
        "\u0633\u0648\u062e\u062f\u0648\u0644"
    ],
    "name:ceb_x_preferred":[
        "Suchdol"
    ],
    "name:ces_x_preferred":[
        "Suchdol"
    ],
    "name:eus_x_preferred":[
        "Suchdol"
    ],
    "name:fas_x_preferred":[
        "\u0633\u0648\u062e\u062f\u0648\u0644"
    ],
    "name:hun_x_preferred":[
        "Suchdol"
    ],
    "name:ita_x_preferred":[
        "Suchdol"
    ],
    "name:msa_x_preferred":[
        "Suchdol"
    ],
    "name:nld_x_preferred":[
        "Suchdol"
    ],
    "name:pol_x_preferred":[
        "Suchdol"
    ],
    "name:por_x_preferred":[
        "Suchdol"
    ],
    "name:slk_x_preferred":[
        "Suchdol"
    ],
    "name:spa_x_preferred":[
        "Suchdol"
    ],
    "name:srp_x_preferred":[
        "\u0421\u0443\u0445\u0434\u043e\u043b"
    ],
    "name:vie_x_preferred":[
        "Suchdol"
    ],
    "wof:name":"Suchdol",
    "wof:placetype":"locality",
    "wof:population":1065
},
  "geometry": {"coordinates":[15.16651,49.95247],"type":"Point"}
}