{
  "type": "Feature",
  "properties": {
    "gn:admin1_code":"88",
    "gn:admin2_code":"0205",
    "gn:asciiname":"Suchdol",
    "gn:country_code":"CZ",
    "gn:dem":370,
    "gn:feature_class":"P",
    "gn:feature_code":"PPL",
    "gn:name":"Suchdol",
    "gn:population":1065,
    "gn:timezone":"Europe/Prague",
    "iso:country":"CZ",
    "wof:name":"Suchdol",
    "wof:placetype":"locality",
    "wof:population":1065
},
  "geometry": {"coordinates":[15.16651,49.95247],"type":"Point"}
}