{
  "type": "Feature",
  "properties": {
    "gn:admin1_code":"80.0",
    "gn:admin2_code":"0613",
    "gn:asciiname":"Bedrichov",
    "gn:country_code":"CZ",
    "gn:dem":574,
    "gn:feature_class":"P",
    "gn:feature_code":"PPL",
    "gn:name":"Bed\u0159ichov",
    "gn:population":0,
    "gn:timezone":"Europe/Prague",
    "iso:country":"CZ",
    "wof:name":"Bedrichov",
    "wof:placetype":"locality"
},
  "geometry": {"coordinates":[14.96175,49.47459],"type":"Point"}
}