{
  "type": "Feature",
  "properties": {
    "gn:admin1_code":"88.0",
    "gn:admin2_code":"0205",
    "gn:asciiname":"Horka",
    "gn:country_code":"CZ",
    "gn:dem":214,
    "gn:feature_class":"P",
    "gn:feature_code":"PPL",
    "gn:name":"Horka",
    "gn:population":0,
    "gn:timezone":"Europe/Prague",
    "iso:country":"CZ",
    "name:ceb_x_preferred":[
        "Horka"
    ],
    "name:ces_x_preferred":[
        "Horka"
    ],
    "name:deu_x_preferred":[
        "Horka"
    ],
    "name:epo_x_preferred":[
        "Horka"
    ],
    "name:fra_x_preferred":[
        "Horka"
    ],
    "name:hsb_x_preferred":[
        "Horka"
    ],
    "name:hun_x_preferred":[
        "Horka"
    ],
    "name:ita_x_preferred":[
        "Horka"
    ],
    "name:nld_x_preferred":[
        "Horka"
    ],
    "name:pol_x_preferred":[
        "Horka"
    ],
    "name:rus_x_preferred":[
        "\u0425\u043e\u0440\u043a\u0430"
    ],
    "name:slk_x_preferred":[
        "Horka"
    ],
    "name:srp_x_preferred":[
        "\u0425\u043e\u0440\u043a\u0430"
    ],
    "name:swe_x_preferred":[
        "Horka"
    ],
    "wof:name":"Horka",
    "wof:placetype":"locality"
},
  "geometry": {"coordinates":[15.43994,49.98253],"type":"Point"}
}