{
  "type": "Feature",
  "properties": {
    "gn:admin1_code":"80",
    "gn:admin2_code":"0613",
    "gn:asciiname":"Velka Ves",
    "gn:country_code":"CZ",
    "gn:dem":602,
    "gn:feature_class":"P",
    "gn:feature_code":"PPL",
    "gn:name":"Velk\u00e1 Ves",
    "gn:population":0,
    "gn:timezone":"Europe/Prague",
    "iso:country":"CZ",
    "wof:name":"Velka Ves",
    "wof:placetype":"locality"
},
  "geometry": {"coordinates":[14.95394,49.56803],"type":"Point"}
}