{
  "type": "Feature",
  "properties": {
    "gn:admin1_code":"80.0",
    "gn:admin2_code":"0611",
    "gn:asciiname":"Dlouhy",
    "gn:country_code":"CZ",
    "gn:dem":552,
    "gn:feature_class":"P",
    "gn:feature_code":"PPL",
    "gn:name":"Dlouh\u00fd",
    "gn:population":0,
    "gn:timezone":"Europe/Prague",
    "iso:country":"CZ",
    "wof:name":"Dlouhy",
    "wof:placetype":"locality"
},
  "geometry": {"coordinates":[15.81572,49.75313],"type":"Point"}
}