{
  "type": "Feature",
  "properties": {
    "gn:admin1_code":"79.0",
    "gn:admin2_code":"0312",
    "gn:asciiname":"Josefuv Dul",
    "gn:cc2":"CZ",
    "gn:country_code":"CZ",
    "gn:dem":801,
    "gn:feature_class":"P",
    "gn:feature_code":"PPL",
    "gn:name":"Josef\u016fv D\u016fl",
    "gn:population":0,
    "gn:timezone":"Europe/Prague",
    "iso:country":"CZ",
    "name:und_x_variant":[
        "Josefsthal"
    ],
    "wof:name":"Josefuv Dul",
    "wof:placetype":"locality"
},
  "geometry": {"coordinates":[13.98333,48.73333],"type":"Point"}
}