{
  "type": "Feature",
  "properties": {
    "gn:admin1_code":"88.0",
    "gn:admin2_code":"020A",
    "gn:asciiname":"Mnisek pod Brdy",
    "gn:country_code":"CZ",
    "gn:dem":384,
    "gn:feature_class":"P",
    "gn:feature_code":"PPL",
    "gn:name":"Mn\u00ed\u0161ek pod Brdy",
    "gn:population":4181,
    "gn:timezone":"Europe/Prague",
    "iso:country":"CZ",
    "name:ceb_x_preferred":[
        "Mn\u00ed\u0161ek pod Brdy"
    ],
    "name:ces_x_preferred":[
        "Mn\u00ed\u0161ek pod Brdy"
    ],
    "name:deu_x_preferred":[
        "Mn\u00ed\u0161ek pod Brdy"
    ],
    "name:eus_x_preferred":[
        "Mn\u00ed\u0161ek pod Brdy"
    ],
    "name:fas_x_preferred":[
        "\u0645\u0646\u06cc\u0634\u06a9 \u067e\u0648\u062f \u0628\u0631\u062f\u06cc"
    ],
    "name:fra_x_preferred":[
        "Mn\u00ed\u0161ek pod Brdy"
    ],
    "name:hun_x_preferred":[
        "Mn\u00ed\u0161ek pod Brdy"
    ],
    "name:ita_x_preferred":[
        "Mn\u00ed\u0161ek pod Brdy"
    ],
    "name:msa_x_preferred":[
        "Mn\u00ed\u0161ek pod Brdy"
    ],
    "name:nld_x_preferred":[
        "Mn\u00ed\u0161ek pod Brdy"
    ],
    "name:pol_x_preferred":[
        "Mn\u00ed\u0161ek pod Brdy"
    ],
    "name:por_x_preferred":[
        "Mn\u00ed\u0161ek pod Brdy"
    ],
    "name:rus_x_preferred":[
        "\u041c\u043d\u0438\u0448\u0435\u043a-\u043f\u043e\u0434-\u0411\u0440\u0434\u0438"
    ],
    "name:slk_x_preferred":[
        "Mn\u00ed\u0161ek pod Brdy"
    ],
    "name:spa_x_preferred":[
        "Mn\u00ed\u0161ek pod Brdy"
    ],
    "name:srp_x_preferred":[
        "\u041c\u045a\u0438\u0448\u0435\u043a \u043f\u043e\u0434 \u0411\u0440\u0434\u043e\u043c"
    ],
    "name:swe_x_preferred":[
        "Mn\u00ed\u0161ek pod Brdy"
    ],
    "name:und_x_variant":[
        "Mnisek",
        "Mnischek"
    ],
    "name:vie_x_preferred":[
        "Mn\u00ed\u0161ek pod Brdy"
    ],
    "wof:name":"Mnisek pod Brdy",
    "wof:placetype":"locality",
    "wof:population":4181
},
  "geometry": {"coordinates":[14.26176,49.8665],"type":"Point"}
}