{
  "type": "Feature",
  "properties": {
    "gn:gn_country":"CZ",
    "gn:gn_fcode":"PPL",
    "gn:gn_pop":84,
    "gn:population":84,
    "iso:country":"CZ",
    "name:azb_x_preferred":[
        "\u0648\u0634\u06a9\u0627\u0631\u06cc"
    ],
    "name:ces_x_preferred":[
        "V\u0161ekary"
    ],
    "name:deu_x_preferred":[
        "V\u0161ekary"
    ],
    "name:eng_x_preferred":[
        "V\u0161ekary"
    ],
    "name:eus_x_preferred":[
        "V\u0161ekary"
    ],
    "name:fas_x_preferred":[
        "\u0648\u0634\u06a9\u0627\u0631\u06cc"
    ],
    "name:fra_x_preferred":[
        "V\u0161ekary"
    ],
    "name:hun_x_preferred":[
        "V\u0161ekary"
    ],
    "name:ita_x_preferred":[
        "V\u0161ekary"
    ],
    "name:msa_x_preferred":[
        "V\u0161ekary"
    ],
    "name:nan_x_preferred":[
        "V\u0161ekary"
    ],
    "name:nld_x_preferred":[
        "V\u0161ekary"
    ],
    "name:pol_x_preferred":[
        "V\u0161ekary"
    ],
    "name:por_x_preferred":[
        "V\u0161ekary"
    ],
    "name:slk_x_preferred":[
        "V\u0161ekary"
    ],
    "name:spa_x_preferred":[
        "V\u0161ekary"
    ],
    "name:srp_x_preferred":[
        "\u0412\u0448\u0435\u043a\u0430\u0440\u0438"
    ],
    "name:vie_x_preferred":[
        "V\u0161ekary"
    ],
    "qs_pg:aaroncc":"CZ",
    "qs_pg:gn_country":"CZ",
    "qs_pg:gn_fcode":"PPL",
    "qs_pg:gn_pop":84,
    "qs_pg:name":"V\u0161ekary",
    "qs_pg:name_adm0":"\u010cesk\u00e1 republika",
    "qs_pg:name_adm1":"Plze\u0148sk\u00fd kraj",
    "qs_pg:photos_9k":1,
    "qs_pg:photos_9r":1,
    "qs_pg:photos_all":2,
    "qs_pg:photos_sr":0,
    "qs_pg:pop_sr":1,
    "qs_pg:qs_pg_placetype":"locality",
    "qs_pg:qs_pg_placetype_gp":"Town",
    "qs_pg:woe_adm0":23424810,
    "woe:adm0_id":23424810,
    "woe:name_adm0":"\u010cesk\u00e1 republika",
    "woe:name_adm1":"Plze\u0148sk\u00fd kraj",
    "woe:placetype":"Town",
    "wof:name":"V\u0161ekary",
    "wof:placetype":"locality",
    "wof:population":84
},
  "geometry": {"coordinates":[13.04245,49.6034],"type":"Point"}
}