{
  "type": "Feature",
  "properties": {
    "gn:admin1_code":"79",
    "gn:admin2_code":"0315",
    "gn:asciiname":"Stare Prachatice",
    "gn:country_code":"CZ",
    "gn:dem":630,
    "gn:feature_class":"P",
    "gn:feature_code":"PPL",
    "gn:name":"Star\u00e9 Prachatice",
    "gn:population":0,
    "gn:timezone":"Europe/Prague",
    "iso:country":"CZ",
    "wof:name":"Stare Prachatice",
    "wof:placetype":"locality"
},
  "geometry": {"coordinates":[14.02203,49.02398],"type":"Point"}
}