{
  "type": "Feature",
  "properties": {
    "gn:gn_country":"CZ",
    "gn:gn_fcode":"PPL",
    "gn:gn_pop":944,
    "gn:population":944,
    "iso:country":"CZ",
    "name:azb_x_preferred":[
        "\u062a\u0634\u0633\u062a\u06cc\u062a\u0633\u0647"
    ],
    "name:ceb_x_preferred":[
        "\u010cestice"
    ],
    "name:ces_x_preferred":[
        "\u010cestice"
    ],
    "name:deu_x_preferred":[
        "\u010cestice"
    ],
    "name:eng_x_preferred":[
        "\u010cestice"
    ],
    "name:eus_x_preferred":[
        "\u010cestice"
    ],
    "name:fas_x_preferred":[
        "\u062a\u0634\u0633\u062a\u06cc\u062a\u0633\u0647"
    ],
    "name:hun_x_preferred":[
        "\u010cestice"
    ],
    "name:ita_x_preferred":[
        "\u010cestice"
    ],
    "name:msa_x_preferred":[
        "\u010cestice"
    ],
    "name:nan_x_preferred":[
        "\u010cestice"
    ],
    "name:nld_x_preferred":[
        "\u010cestice"
    ],
    "name:por_x_preferred":[
        "\u010cestice"
    ],
    "name:rup_x_preferred":[
        "\u010cestice"
    ],
    "name:slk_x_preferred":[
        "\u010cestice"
    ],
    "name:spa_x_preferred":[
        "\u010cestice"
    ],
    "name:srp_x_preferred":[
        "\u0427\u0435\u0441\u0442\u0438\u0446\u0435"
    ],
    "name:swe_x_preferred":[
        "\u010cestice"
    ],
    "name:unk_x_variant":[
        "\u010cestitz"
    ],
    "name:vie_x_preferred":[
        "\u010cestice"
    ],
    "qs_pg:aaroncc":"CZ",
    "qs_pg:gn_country":"CZ",
    "qs_pg:gn_fcode":"PPL",
    "qs_pg:gn_pop":944,
    "qs_pg:name":"\u010cestice",
    "qs_pg:name_adm0":"\u010cesk\u00e1 republika",
    "qs_pg:name_adm1":"Jiho\u010desk\u00fd kraj",
    "qs_pg:photos_9r":0,
    "qs_pg:photos_sr":0,
    "qs_pg:pop_sr":2,
    "qs_pg:qs_pg_placetype":"locality",
    "qs_pg:qs_pg_placetype_gp":"Town",
    "qs_pg:woe_adm0":23424810,
    "woe:adm0_id":23424810,
    "woe:name_adm0":"\u010cesk\u00e1 republika",
    "woe:name_adm1":"Jiho\u010desk\u00fd kraj",
    "woe:placetype":"Town",
    "wof:name":"\u010cestice",
    "wof:placetype":"locality",
    "wof:population":944
},
  "geometry": {"coordinates":[13.8037,49.16782],"type":"Point"}
}