{
  "type": "Feature",
  "properties": {
    "gn:admin1_code":"80.0",
    "gn:admin2_code":"0613",
    "gn:asciiname":"Dekancice",
    "gn:country_code":"CZ",
    "gn:dem":462,
    "gn:feature_class":"P",
    "gn:feature_code":"PPL",
    "gn:name":"D\u011bkan\u010dice",
    "gn:population":0,
    "gn:timezone":"Europe/Prague",
    "iso:country":"CZ",
    "wof:name":"Dekancice",
    "wof:placetype":"locality"
},
  "geometry": {"coordinates":[15.19846,49.58819],"type":"Point"}
}