{
  "type": "Feature",
  "properties": {
    "gn:country":"CZ",
    "gn:fcode":"PPL",
    "gn:population":243,
    "iso:country":"CZ",
    "name:azb_x_preferred":[
        "\u0644\u06cc\u0628\u0648\u0648\u06cc\u062a\u0633\u0647"
    ],
    "name:ceb_x_preferred":[
        "Libovice"
    ],
    "name:ces_x_preferred":[
        "Libovice"
    ],
    "name:eus_x_preferred":[
        "Libovice"
    ],
    "name:fas_x_preferred":[
        "\u0644\u06cc\u0628\u0648\u0648\u06cc\u062a\u0633\u0647"
    ],
    "name:fra_x_preferred":[
        "Libovice"
    ],
    "name:hun_x_preferred":[
        "Libovice"
    ],
    "name:ita_x_preferred":[
        "Libovice"
    ],
    "name:msa_x_preferred":[
        "Libovice"
    ],
    "name:nld_x_preferred":[
        "Libovice"
    ],
    "name:pol_x_preferred":[
        "Libovice"
    ],
    "name:por_x_preferred":[
        "Libovice"
    ],
    "name:slk_x_preferred":[
        "Libovice"
    ],
    "name:spa_x_preferred":[
        "Libovice"
    ],
    "name:srp_x_preferred":[
        "\u041b\u0438\u0431\u043e\u0432\u0438\u0446\u0435"
    ],
    "name:swe_x_preferred":[
        "Libovice"
    ],
    "name:vie_x_preferred":[
        "Libovice"
    ],
    "qs_pg:aaroncc":"CZ",
    "qs_pg:gn_country":"CZ",
    "qs_pg:gn_fcode":"PPL",
    "qs_pg:gn_pop":243,
    "qs_pg:name":"Libovice",
    "qs_pg:name_adm0":"\u010cesk\u00e1 republika",
    "qs_pg:name_adm1":"St\u0159edo\u010desk\u00fd kraj",
    "qs_pg:photos_9k":1,
    "qs_pg:photos_9r":1,
    "qs_pg:photos_all":1,
    "qs_pg:photos_sr":0,
    "qs_pg:pop_sr":2,
    "qs_pg:qs_pg_placetype":"locality",
    "qs_pg:qs_pg_placetype_gp":"Town",
    "qs_pg:woe_adm0":23424810,
    "woe:adm0_id":23424810,
    "woe:name_adm0":"\u010cesk\u00e1 republika",
    "woe:name_adm1":"St\u0159edo\u010desk\u00fd kraj",
    "woe:placetype":"Town",
    "wof:name":"Libovice",
    "wof:placetype":"locality",
    "wof:population":243
},
  "geometry": {"coordinates":[14.01634,50.2356],"type":"Point"}
}