{
  "type": "Feature",
  "properties": {
    "gn:gn_country":"CZ",
    "gn:gn_fcode":"PPL",
    "gn:gn_pop":539,
    "gn:population":539,
    "iso:country":"CZ",
    "name:cze_x_preferred":[
        "St\u0159e\u0148"
    ],
    "name:dut_x_preferred":[
        "St\u0159e\u0148"
    ],
    "name:eng_x_preferred":[
        "St\u0159e\u0148"
    ],
    "name:epo_x_preferred":[
        "St\u0159e\u0148"
    ],
    "name:fre_x_preferred":[
        "St\u0159e\u0148"
    ],
    "name:ger_x_preferred":[
        "St\u0159e\u0148"
    ],
    "name:hun_x_preferred":[
        "St\u0159e\u0148"
    ],
    "name:ita_x_preferred":[
        "St\u0159e\u0148"
    ],
    "name:may_x_preferred":[
        "St\u0159e\u0148"
    ],
    "name:per_x_preferred":[
        "\u0633\u062a\u0631\u0646"
    ],
    "name:pol_x_preferred":[
        "St\u0159e\u0148"
    ],
    "name:por_x_preferred":[
        "St\u0159e\u0148"
    ],
    "name:slo_x_preferred":[
        "St\u0159e\u0148"
    ],
    "name:srp_x_preferred":[
        "\u0421\u0442\u0440\u0435\u045a"
    ],
    "name:swe_x_preferred":[
        "St\u0159e\u0148"
    ],
    "name:vie_x_preferred":[
        "St\u0159e\u0148"
    ],
    "qs_pg:aaroncc":"CZ",
    "qs_pg:gn_country":"CZ",
    "qs_pg:gn_fcode":"PPL",
    "qs_pg:gn_pop":539,
    "qs_pg:name":"St\u0159e\u0148",
    "qs_pg:name_adm0":"\u010cesk\u00e1 republika",
    "qs_pg:name_adm1":"Olomouck\u00fd kraj",
    "qs_pg:photos_9k":1,
    "qs_pg:photos_9r":1,
    "qs_pg:photos_all":1,
    "qs_pg:photos_sr":0,
    "qs_pg:pop_sr":2,
    "qs_pg:qs_pg_placetype":"locality",
    "qs_pg:qs_pg_placetype_gp":"Town",
    "qs_pg:woe_adm0":23424810,
    "woe:adm0_id":23424810,
    "woe:name_adm0":"\u010cesk\u00e1 republika",
    "woe:name_adm1":"Olomouck\u00fd kraj",
    "woe:placetype":"Town",
    "wof:name":"St\u0159e\u0148",
    "wof:placetype":"locality",
    "wof:population":539
},
  "geometry": {"coordinates":[17.15382,49.69152],"type":"Point"}
}