{
  "type": "Feature",
  "properties": {
    "gn:gn_country":"CZ",
    "gn:gn_fcode":"PPL",
    "gn:gn_pop":886,
    "gn:population":886,
    "iso:country":"CZ",
    "name:cze_x_preferred":[
        "Ka\u0161ava"
    ],
    "name:dut_x_preferred":[
        "Ka\u0161ava"
    ],
    "name:eng_x_preferred":[
        "Ka\u0161ava"
    ],
    "name:fre_x_preferred":[
        "Ka\u0161ava"
    ],
    "name:ger_x_preferred":[
        "Ka\u0161ava"
    ],
    "name:hun_x_preferred":[
        "Ka\u0161ava"
    ],
    "name:ita_x_preferred":[
        "Ka\u0161ava"
    ],
    "name:may_x_preferred":[
        "Ka\u0161ava"
    ],
    "name:per_x_preferred":[
        "\u06a9\u0627\u0634\u0627\u0648\u0627"
    ],
    "name:pol_x_preferred":[
        "Ka\u0161ava"
    ],
    "name:por_x_preferred":[
        "Ka\u0161ava"
    ],
    "name:slo_x_preferred":[
        "Ka\u0161ava"
    ],
    "name:srp_x_preferred":[
        "\u041a\u0430\u0448\u0430\u0432\u0430"
    ],
    "name:swe_x_preferred":[
        "Ka\u0161ava"
    ],
    "name:vie_x_preferred":[
        "Ka\u0161ava"
    ],
    "qs_pg:aaroncc":"CZ",
    "qs_pg:gn_country":"CZ",
    "qs_pg:gn_fcode":"PPL",
    "qs_pg:gn_pop":886,
    "qs_pg:name":"Ka\u0161ava",
    "qs_pg:name_adm0":"\u010cesk\u00e1 republika",
    "qs_pg:name_adm1":"Zl\u00ednsk\u00fd kraj",
    "qs_pg:photos_9k":1,
    "qs_pg:photos_9r":1,
    "qs_pg:photos_all":4,
    "qs_pg:photos_sr":0,
    "qs_pg:pop_sr":2,
    "qs_pg:qs_pg_placetype":"locality",
    "qs_pg:qs_pg_placetype_gp":"Town",
    "qs_pg:woe_adm0":23424810,
    "woe:adm0_id":23424810,
    "woe:name_adm0":"\u010cesk\u00e1 republika",
    "woe:name_adm1":"Zl\u00ednsk\u00fd kraj",
    "woe:placetype":"Town",
    "wof:name":"Ka\u0161ava",
    "wof:placetype":"locality",
    "wof:population":886
},
  "geometry": {"coordinates":[17.78566,49.29541],"type":"Point"}
}