{
  "type": "Feature",
  "properties": {
    "gn:country":"CZ",
    "gn:fcode":"PPL",
    "gn:population":248,
    "iso:country":"CZ",
    "name:azb_x_preferred":[
        "\u0632\u0627\u0647\u0631\u0627\u062f\u06a9\u06cc"
    ],
    "name:cat_x_preferred":[
        "Zahr\u00e1dky"
    ],
    "name:ceb_x_preferred":[
        "Zahr\u00e1dky"
    ],
    "name:ces_x_preferred":[
        "Zahr\u00e1dky"
    ],
    "name:che_x_preferred":[
        "\u0417\u0430\u0433\u0440\u0430\u0434\u043a\u0438"
    ],
    "name:deu_x_preferred":[
        "Zahr\u00e1dky"
    ],
    "name:eng_x_preferred":[
        "Zahr\u00e1dky"
    ],
    "name:epo_x_preferred":[
        "Zahr\u00e1dky"
    ],
    "name:eus_x_preferred":[
        "Zahr\u00e1dky"
    ],
    "name:fas_x_preferred":[
        "\u0632\u0627\u0647\u0631\u0627\u062f\u06a9\u06cc"
    ],
    "name:fra_x_preferred":[
        "Zahr\u00e1dky"
    ],
    "name:gle_x_preferred":[
        "Zahr\u00e1dky"
    ],
    "name:hun_x_preferred":[
        "Zahr\u00e1dky"
    ],
    "name:ita_x_preferred":[
        "Zahr\u00e1dky"
    ],
    "name:msa_x_preferred":[
        "Zahr\u00e1dky"
    ],
    "name:nan_x_preferred":[
        "Zahr\u00e1dky"
    ],
    "name:nld_x_preferred":[
        "Zahr\u00e1dky"
    ],
    "name:pol_x_preferred":[
        "Zahr\u00e1dky"
    ],
    "name:por_x_preferred":[
        "Zahr\u00e1dky"
    ],
    "name:rup_x_preferred":[
        "Zahr\u00e1dky"
    ],
    "name:slk_x_preferred":[
        "Zahr\u00e1dky"
    ],
    "name:spa_x_preferred":[
        "Zahr\u00e1dky"
    ],
    "name:srp_x_preferred":[
        "\u0417\u0430\u0445\u0440\u0430\u0442\u043a\u0438"
    ],
    "name:swe_x_preferred":[
        "Zahr\u00e1dky"
    ],
    "name:tat_x_preferred":[
        "\u0417\u0430\u0433\u0440\u0430\u0434\u043a\u0438"
    ],
    "name:urd_x_preferred":[
        "\u0632\u06c1\u0631\u0627\u062f\u06a9\u06d2"
    ],
    "name:vie_x_preferred":[
        "Zahr\u00e1dky"
    ],
    "qs_pg:aaroncc":"CZ",
    "qs_pg:gn_country":"CZ",
    "qs_pg:gn_fcode":"PPL",
    "qs_pg:gn_pop":248,
    "qs_pg:name":"Zahr\u00e1dky",
    "qs_pg:name_adm0":"\u010cesk\u00e1 republika",
    "qs_pg:name_adm1":"Jiho\u010desk\u00fd kraj",
    "qs_pg:photos_9r":0,
    "qs_pg:photos_sr":0,
    "qs_pg:pop_sr":2,
    "qs_pg:qs_pg_placetype":"locality",
    "qs_pg:qs_pg_placetype_gp":"Town",
    "qs_pg:woe_adm0":23424810,
    "woe:adm0_id":23424810,
    "woe:name_adm0":"\u010cesk\u00e1 republika",
    "woe:name_adm1":"Jiho\u010desk\u00fd kraj",
    "woe:placetype":"Town",
    "wof:name":"Zahr\u00e1dky",
    "wof:placetype":"locality",
    "wof:population":248
},
  "geometry": {"coordinates":[15.24171,49.20081],"type":"Point"}
}