{
  "type": "Feature",
  "properties": {
    "gn:admin1_code":"88.0",
    "gn:admin2_code":"0207",
    "gn:asciiname":"Reckov",
    "gn:country_code":"CZ",
    "gn:dem":245,
    "gn:feature_class":"P",
    "gn:feature_code":"PPL",
    "gn:name":"Re\u010dkov",
    "gn:population":0,
    "gn:timezone":"Europe/Prague",
    "iso:country":"CZ",
    "wof:name":"Reckov",
    "wof:placetype":"locality"
},
  "geometry": {"coordinates":[14.8906,50.4945],"type":"Point"}
}