{
  "type": "Feature",
  "properties": {
    "gn:admin1_code":"86.0",
    "gn:admin2_code":"0532",
    "gn:asciiname":"Skudly",
    "gn:country_code":"CZ",
    "gn:dem":211,
    "gn:feature_class":"P",
    "gn:feature_code":"PPL",
    "gn:name":"\u0160kudly",
    "gn:population":0,
    "gn:timezone":"Europe/Prague",
    "iso:country":"CZ",
    "wof:name":"Skudly",
    "wof:placetype":"locality"
},
  "geometry": {"coordinates":[15.52683,50.02515],"type":"Point"}
}