{
  "type": "Feature",
  "properties": {
    "gn:admin1_code":"79.0",
    "gn:admin2_code":"0312",
    "gn:asciiname":"Novosedly",
    "gn:country_code":"CZ",
    "gn:dem":571,
    "gn:feature_class":"P",
    "gn:feature_code":"PPL",
    "gn:name":"Novosedly",
    "gn:population":0,
    "gn:timezone":"Europe/Prague",
    "iso:country":"CZ",
    "name:und_x_variant":[
        "Neusiedl",
        "Novosedly"
    ],
    "wof:name":"Novosedly",
    "wof:placetype":"locality"
},
  "geometry": {"coordinates":[14.25047,48.79751],"type":"Point"}
}