{
  "type": "Feature",
  "properties": {
    "gn:country":"CZ",
    "gn:fcode":"PPL",
    "gn:population":326,
    "iso:country":"CZ",
    "name:azb_x_preferred":[
        "\u06cc\u0627\u0628\u0644\u0648\u0646\u0648\u0648"
    ],
    "name:cat_x_preferred":[
        "Jablo\u0148ov"
    ],
    "name:ceb_x_preferred":[
        "Jablo\u0148ov"
    ],
    "name:ces_x_preferred":[
        "Jablo\u0148ov"
    ],
    "name:che_x_preferred":[
        "\u042f\u0431\u043b\u043e\u043d\u0451\u0432"
    ],
    "name:deu_x_preferred":[
        "Jablo\u0148ov"
    ],
    "name:eng_x_preferred":[
        "Jablo\u0148ov"
    ],
    "name:epo_x_preferred":[
        "Jablo\u0148ov"
    ],
    "name:eus_x_preferred":[
        "Jablo\u0148ov"
    ],
    "name:fas_x_preferred":[
        "\u06cc\u0627\u0628\u0644\u0648\u0646\u0648\u0648"
    ],
    "name:fra_x_preferred":[
        "Jablo\u0148ov"
    ],
    "name:gle_x_preferred":[
        "Jablo\u0148ov"
    ],
    "name:hun_x_preferred":[
        "Jablo\u0148ov"
    ],
    "name:ita_x_preferred":[
        "Jablo\u0148ov"
    ],
    "name:lmo_x_preferred":[
        "Jablo\u0148ov"
    ],
    "name:msa_x_preferred":[
        "Jablo\u0148ov"
    ],
    "name:nan_x_preferred":[
        "Jablo\u0148ov"
    ],
    "name:nld_x_preferred":[
        "Jablo\u0148ov"
    ],
    "name:oci_x_preferred":[
        "Jablo\u0148ov"
    ],
    "name:pol_x_preferred":[
        "Jablo\u0148ov"
    ],
    "name:por_x_preferred":[
        "Jablo\u0148ov"
    ],
    "name:rup_x_preferred":[
        "Jablo\u0148ov"
    ],
    "name:slk_x_preferred":[
        "Jablo\u0148ov"
    ],
    "name:spa_x_preferred":[
        "Jablo\u0148ov"
    ],
    "name:swe_x_preferred":[
        "Jablo\u0148ov"
    ],
    "name:tat_x_preferred":[
        "\u042f\u0431\u043b\u043e\u043d\u0451\u0432"
    ],
    "name:urd_x_preferred":[
        "\u062c\u0628\u0644\u0648\u0646\u0627\u0648"
    ],
    "name:uzb_x_preferred":[
        "Jablo\u0148ov"
    ],
    "name:vie_x_preferred":[
        "Jablo\u0148ov"
    ],
    "qs_pg:aaroncc":"CZ",
    "qs_pg:gn_country":"CZ",
    "qs_pg:gn_fcode":"PPL",
    "qs_pg:gn_pop":326,
    "qs_pg:name":"Jablo\u0148ov",
    "qs_pg:photos_9r":0,
    "qs_pg:photos_sr":0,
    "qs_pg:pop_sr":2,
    "qs_pg:qs_pg_placetype":"locality",
    "wof:name":"Jablo\u0148ov",
    "wof:placetype":"locality",
    "wof:population":326
},
  "geometry": {"coordinates":[16.08966,49.32401],"type":"Point"}
}