{
  "type": "Feature",
  "properties": {
    "gn:admin1_code":"87.0",
    "gn:admin2_code":"0321",
    "gn:asciiname":"Ostromec",
    "gn:country_code":"CZ",
    "gn:dem":508,
    "gn:feature_class":"P",
    "gn:feature_code":"PPL",
    "gn:name":"Ostrome\u010d",
    "gn:population":0,
    "gn:timezone":"Europe/Prague",
    "iso:country":"CZ",
    "name:und_x_variant":[
        "Wassertrompeten",
        "Ostrome\u010d"
    ],
    "wof:name":"Ostromec",
    "wof:placetype":"locality"
},
  "geometry": {"coordinates":[12.96071,49.61208],"type":"Point"}
}