{
  "type": "Feature",
  "properties": {
    "gn:gn_country":"CZ",
    "gn:gn_fcode":"PPL",
    "gn:gn_pop":1537,
    "gn:population":1537,
    "iso:country":"CZ",
    "name:cze_x_preferred":[
        "V\u0161estary"
    ],
    "name:dut_x_preferred":[
        "V\u0161estary"
    ],
    "name:eng_x_preferred":[
        "V\u0161estary"
    ],
    "name:fre_x_preferred":[
        "V\u0161estary"
    ],
    "name:ger_x_preferred":[
        "V\u0161estary"
    ],
    "name:hun_x_preferred":[
        "V\u0161estary"
    ],
    "name:ita_x_preferred":[
        "V\u0161estary"
    ],
    "name:may_x_preferred":[
        "V\u0161estary"
    ],
    "name:nan_x_preferred":[
        "V\u0161estary"
    ],
    "name:per_x_preferred":[
        "\u0648\u0634\u0633\u062a\u0627\u0631\u06cc"
    ],
    "name:pol_x_preferred":[
        "V\u0161estary"
    ],
    "name:por_x_preferred":[
        "V\u0161estary"
    ],
    "name:rup_x_preferred":[
        "V\u0161estary"
    ],
    "name:slo_x_preferred":[
        "V\u0161estary"
    ],
    "name:srp_x_preferred":[
        "\u0412\u0448\u0435\u0441\u0442\u0430\u0440\u0438"
    ],
    "name:swe_x_preferred":[
        "V\u0161estary"
    ],
    "name:vie_x_preferred":[
        "V\u0161estary"
    ],
    "qs_pg:aaroncc":"CZ",
    "qs_pg:gn_country":"CZ",
    "qs_pg:gn_fcode":"PPL",
    "qs_pg:gn_pop":1537,
    "qs_pg:name":"V\u0161estary",
    "qs_pg:name_adm0":"\u010cesk\u00e1 republika",
    "qs_pg:name_adm1":"Kr\u00e1lov\u00e9hradeck\u00fd kraj",
    "qs_pg:photos_9k":1,
    "qs_pg:photos_9r":1,
    "qs_pg:photos_all":1,
    "qs_pg:photos_sr":0,
    "qs_pg:pop_sr":3,
    "qs_pg:qs_pg_placetype":"locality",
    "qs_pg:qs_pg_placetype_gp":"Town",
    "qs_pg:woe_adm0":23424810,
    "woe:adm0_id":23424810,
    "woe:name_adm0":"\u010cesk\u00e1 republika",
    "woe:name_adm1":"Kr\u00e1lov\u00e9hradeck\u00fd kraj",
    "woe:placetype":"Town",
    "wof:name":"V\u0161estary",
    "wof:placetype":"locality",
    "wof:population":1537
},
  "geometry": {"coordinates":[15.75983,50.2566],"type":"Point"}
}