{
  "type": "Feature",
  "properties": {
    "gn:admin1_code":"84.0",
    "gn:admin2_code":"0715",
    "gn:asciiname":"Bukova",
    "gn:cc2":"CZ",
    "gn:country_code":"CZ",
    "gn:dem":538,
    "gn:feature_class":"P",
    "gn:feature_code":"PPL",
    "gn:name":"Bukov\u00e1",
    "gn:population":0,
    "gn:timezone":"Europe/Prague",
    "iso:country":"CZ",
    "name:und_x_variant":[
        "Dreibuchen"
    ],
    "wof:name":"Bukova",
    "wof:placetype":"locality"
},
  "geometry": {"coordinates":[16.79973,49.75698],"type":"Point"}
}