{
  "type": "Feature",
  "properties": {
    "gn:gn_country":"CZ",
    "gn:gn_fcode":"PPL",
    "gn:gn_pop":241,
    "gn:population":241,
    "iso:country":"CZ",
    "name:cze_x_preferred":[
        "Vr\u00e1tkov"
    ],
    "name:dut_x_preferred":[
        "Vr\u00e1tkov"
    ],
    "name:eng_x_preferred":[
        "Vr\u00e1tkov"
    ],
    "name:fre_x_preferred":[
        "Vr\u00e1tkov"
    ],
    "name:hun_x_preferred":[
        "Vr\u00e1tkov"
    ],
    "name:ita_x_preferred":[
        "Vr\u00e1tkov"
    ],
    "name:may_x_preferred":[
        "Vr\u00e1tkov"
    ],
    "name:per_x_preferred":[
        "\u0648\u0631\u0627\u062a\u06a9\u0648\u0648"
    ],
    "name:pol_x_preferred":[
        "Vr\u00e1tkov"
    ],
    "name:por_x_preferred":[
        "Vr\u00e1tkov"
    ],
    "name:slo_x_preferred":[
        "Vr\u00e1tkov"
    ],
    "name:srp_x_preferred":[
        "\u0412\u0440\u0430\u0442\u043a\u043e\u0432"
    ],
    "name:swe_x_preferred":[
        "Vr\u00e1tkov"
    ],
    "name:vie_x_preferred":[
        "Vr\u00e1tkov"
    ],
    "qs_pg:aaroncc":"CZ",
    "qs_pg:gn_country":"CZ",
    "qs_pg:gn_fcode":"PPL",
    "qs_pg:gn_pop":241,
    "qs_pg:name":"Vratkov",
    "qs_pg:name_adm0":"\u010cesk\u00e1 republika",
    "qs_pg:name_adm1":"St\u0159edo\u010desk\u00fd kraj",
    "qs_pg:photos_9k":1,
    "qs_pg:photos_9r":1,
    "qs_pg:photos_all":1,
    "qs_pg:photos_sr":0,
    "qs_pg:pop_sr":2,
    "qs_pg:qs_pg_placetype":"locality",
    "qs_pg:qs_pg_placetype_gp":"Town",
    "qs_pg:woe_adm0":23424810,
    "woe:adm0_id":23424810,
    "woe:name_adm0":"\u010cesk\u00e1 republika",
    "woe:name_adm1":"St\u0159edo\u010desk\u00fd kraj",
    "woe:placetype":"Town",
    "wof:name":"Vratkov",
    "wof:placetype":"locality",
    "wof:population":241
},
  "geometry": {"coordinates":[14.83478,50.04695],"type":"Point"}
}