{
  "type": "Feature",
  "properties": {
    "gn:country":"CZ",
    "gn:fcode":"PPL",
    "gn:population":490,
    "iso:country":"CZ",
    "name:ceb_x_preferred":[
        "Lesonice"
    ],
    "name:ces_x_preferred":[
        "Lesonice"
    ],
    "name:fra_x_preferred":[
        "Lesonice"
    ],
    "name:ita_x_preferred":[
        "Lesonice"
    ],
    "name:nld_x_preferred":[
        "Lesonice"
    ],
    "name:slk_x_preferred":[
        "Lesonice"
    ],
    "name:srp_x_preferred":[
        "\u041b\u0435\u0441\u043e\u045a\u0438\u0446\u0435"
    ],
    "name:swe_x_preferred":[
        "Lesonice"
    ],
    "qs_pg:aaroncc":"CZ",
    "qs_pg:gn_country":"CZ",
    "qs_pg:gn_fcode":"PPL",
    "qs_pg:gn_pop":490,
    "qs_pg:name":"Lesonice",
    "qs_pg:name_adm0":"\u010cesk\u00e1 republika",
    "qs_pg:name_adm1":"Kraj Vyso\u010dina",
    "qs_pg:photos_9r":0,
    "qs_pg:photos_sr":0,
    "qs_pg:pop_sr":2,
    "qs_pg:qs_pg_placetype":"locality",
    "qs_pg:qs_pg_placetype_gp":"Town",
    "qs_pg:woe_adm0":23424810,
    "woe:adm0_id":23424810,
    "woe:name_adm0":"\u010cesk\u00e1 republika",
    "woe:name_adm1":"Kraj Vyso\u010dina",
    "woe:placetype":"Town",
    "wof:name":"Lesonice",
    "wof:placetype":"locality",
    "wof:population":490
},
  "geometry": {"coordinates":[15.75588,49.10786],"type":"Point"}
}