{
  "type": "Feature",
  "properties": {
    "gn:admin1_code":"88",
    "gn:admin2_code":"0208",
    "gn:asciiname":"Vrceni",
    "gn:country_code":"CZ",
    "gn:dem":188,
    "gn:feature_class":"P",
    "gn:feature_code":"PPL",
    "gn:name":"Vr\u010den\u00ed",
    "gn:population":0,
    "gn:timezone":"Europe/Prague",
    "iso:country":"CZ",
    "wof:name":"Vrceni",
    "wof:placetype":"locality"
},
  "geometry": {"coordinates":[15.16769,50.14511],"type":"Point"}
}