{
  "type": "Feature",
  "properties": {
    "gn:gn_country":"CZ",
    "gn:gn_fcode":"PPL",
    "gn:gn_pop":80,
    "gn:population":80,
    "iso:country":"CZ",
    "name:cze_x_preferred":[
        "Horn\u00ed Skr\u00fdchov"
    ],
    "name:dut_x_preferred":[
        "Horn\u00ed Skr\u00fdchov"
    ],
    "name:eng_x_preferred":[
        "Horn\u00ed Skr\u00fdchov"
    ],
    "name:fre_x_preferred":[
        "Horn\u00ed Skr\u00fdchov"
    ],
    "name:ger_x_preferred":[
        "Horn\u00ed Skr\u00fdchov"
    ],
    "name:hun_x_preferred":[
        "Horn\u00ed Skr\u00fdchov"
    ],
    "name:ita_x_preferred":[
        "Horn\u00ed Skr\u00fdchov"
    ],
    "name:may_x_preferred":[
        "Horn\u00ed Skr\u00fdchov"
    ],
    "name:nan_x_preferred":[
        "Horn\u00ed Skr\u00fdchov"
    ],
    "name:pol_x_preferred":[
        "Horn\u00ed Skr\u00fdchov"
    ],
    "name:por_x_preferred":[
        "Horn\u00ed Skr\u00fdchov"
    ],
    "name:rup_x_preferred":[
        "Horn\u00ed Skr\u00fdchov"
    ],
    "name:slo_x_preferred":[
        "Horn\u00ed Skr\u00fdchov"
    ],
    "name:srp_x_preferred":[
        "\u0425\u043e\u0440\u045a\u0438 \u0421\u043a\u0440\u0438\u0445\u043e\u0432"
    ],
    "name:vie_x_preferred":[
        "Horn\u00ed Skr\u00fdchov"
    ],
    "qs_pg:aaroncc":"CZ",
    "qs_pg:gn_country":"CZ",
    "qs_pg:gn_fcode":"PPL",
    "qs_pg:gn_pop":80,
    "qs_pg:name":"Horn\u00ed Skr\u00fdchov",
    "qs_pg:name_adm0":"\u010cesk\u00e1 republika",
    "qs_pg:name_adm1":"Jiho\u010desk\u00fd kraj",
    "qs_pg:photos_9r":0,
    "qs_pg:photos_sr":0,
    "qs_pg:pop_sr":1,
    "qs_pg:qs_pg_placetype":"locality",
    "qs_pg:qs_pg_placetype_gp":"Town",
    "qs_pg:woe_adm0":23424810,
    "woe:adm0_id":23424810,
    "woe:name_adm0":"\u010cesk\u00e1 republika",
    "woe:name_adm1":"Jiho\u010desk\u00fd kraj",
    "woe:placetype":"Town",
    "wof:name":"Horn\u00ed Skr\u00fdchov",
    "wof:placetype":"locality",
    "wof:population":80
},
  "geometry": {"coordinates":[15.02837,49.17278],"type":"Point"}
}