{
  "type": "Feature",
  "properties": {
    "gn:admin1_code":"90.0",
    "gn:admin2_code":"0724",
    "gn:asciiname":"Nad Brehama",
    "gn:country_code":"CZ",
    "gn:dem":484,
    "gn:feature_class":"P",
    "gn:feature_code":"PPL",
    "gn:name":"Nad B\u0159ehama",
    "gn:population":0,
    "gn:timezone":"Europe/Prague",
    "iso:country":"CZ",
    "wof:name":"Nad Brehama",
    "wof:placetype":"locality"
},
  "geometry": {"coordinates":[17.78017999999999,49.1924],"type":"Point"}
}