{
  "type": "Feature",
  "properties": {
    "gn:admin1_code":"88",
    "gn:admin2_code":"0205",
    "gn:asciiname":"Vilemovice",
    "gn:country_code":"CZ",
    "gn:dem":420,
    "gn:feature_class":"P",
    "gn:feature_code":"PPL",
    "gn:name":"Vil\u011bmovice",
    "gn:population":0,
    "gn:timezone":"Europe/Prague",
    "iso:country":"CZ",
    "wof:name":"Vilemovice",
    "wof:placetype":"locality"
},
  "geometry": {"coordinates":[15.26667,49.84605],"type":"Point"}
}