{
  "type": "Feature",
  "properties": {
    "gn:admin1_code":"80",
    "gn:admin2_code":"0615",
    "gn:asciiname":"Strzanov",
    "gn:country_code":"CZ",
    "gn:dem":609,
    "gn:feature_class":"P",
    "gn:feature_code":"PPL",
    "gn:name":"Str\u017eanov",
    "gn:population":0,
    "gn:timezone":"Europe/Prague",
    "iso:country":"CZ",
    "wof:name":"Strzanov",
    "wof:placetype":"locality"
},
  "geometry": {"coordinates":[15.93755,49.59986],"type":"Point"}
}