{
  "type": "Feature",
  "properties": {
    "gn:admin1_code":"81.0",
    "gn:admin2_code":"0413",
    "gn:asciiname":"Kremenita",
    "gn:country_code":"CZ",
    "gn:dem":592,
    "gn:feature_class":"P",
    "gn:feature_code":"PPL",
    "gn:name":"K\u0159emenit\u00e1",
    "gn:population":0,
    "gn:timezone":"Europe/Prague",
    "iso:country":"CZ",
    "name:und_x_variant":[
        "Griesbach",
        "K\u0159emenit\u00e1"
    ],
    "wof:name":"Kremenita",
    "wof:placetype":"locality"
},
  "geometry": {"coordinates":[12.68176,50.26426],"type":"Point"}
}