{
  "type": "Feature",
  "properties": {
    "gn:admin1_code":"82.0",
    "gn:admin2_code":"0523",
    "gn:asciiname":"Lhota",
    "gn:country_code":"CZ",
    "gn:dem":293,
    "gn:feature_class":"P",
    "gn:feature_code":"PPL",
    "gn:name":"Lhota",
    "gn:population":0,
    "gn:timezone":"Europe/Prague",
    "iso:country":"CZ",
    "name:ces_x_preferred":[
        "Lhota"
    ],
    "name:deu_x_preferred":[
        "Lhota"
    ],
    "wof:name":"Lhota",
    "wof:placetype":"locality"
},
  "geometry": {"coordinates":[16.08442,50.36177],"type":"Point"}
}