{
  "type": "Feature",
  "properties": {
    "gn:gn_country":"CZ",
    "gn:gn_fcode":"PPL",
    "gn:gn_pop":203,
    "gn:population":203,
    "iso:country":"CZ",
    "name:cze_x_preferred":[
        "Sto\u0161\u00edkovice na Louce"
    ],
    "name:dut_x_preferred":[
        "Sto\u0161\u00edkovice na Louce"
    ],
    "name:eng_x_preferred":[
        "Sto\u0161\u00edkovice na Louce"
    ],
    "name:fre_x_preferred":[
        "Sto\u0161\u00edkovice na Louce"
    ],
    "name:ger_x_preferred":[
        "Sto\u0161\u00edkovice na Louce"
    ],
    "name:hun_x_preferred":[
        "Sto\u0161\u00edkovice na Louce"
    ],
    "name:ita_x_preferred":[
        "Sto\u0161\u00edkovice na Louce"
    ],
    "name:may_x_preferred":[
        "Sto\u0161\u00edkovice na Louce"
    ],
    "name:per_x_preferred":[
        "\u0633\u062a\u0648\u0634\u06cc\u06a9\u0648\u0648\u06cc\u062a\u0633\u0647 \u0646\u0627 \u0644\u0648\u0648\u062a\u0633\u0647"
    ],
    "name:pol_x_preferred":[
        "Sto\u0161\u00edkovice na Louce"
    ],
    "name:por_x_preferred":[
        "Sto\u0161\u00edkovice na Louce"
    ],
    "name:rup_x_preferred":[
        "Sto\u0161\u00edkovice na Louce"
    ],
    "name:slo_x_preferred":[
        "Sto\u0161\u00edkovice na Louce"
    ],
    "name:srp_x_preferred":[
        "\u0421\u0442\u043e\u0448\u0438\u043a\u043e\u0432\u0438\u0446\u0435 \u043d\u0430 \u041b\u043e\u0443\u0446\u0438"
    ],
    "name:swe_x_preferred":[
        "Sto\u0161\u00edkovice na Louce"
    ],
    "name:unk_x_variant":[
        "Tesswitz an der Wiese"
    ],
    "name:vie_x_preferred":[
        "Sto\u0161\u00edkovice na Louce"
    ],
    "qs_pg:aaroncc":"CZ",
    "qs_pg:gn_country":"CZ",
    "qs_pg:gn_fcode":"PPL",
    "qs_pg:gn_pop":203,
    "qs_pg:name":"Sto\u0161\u00edkovice na Louce",
    "qs_pg:name_adm0":"\u010cesk\u00e1 republika",
    "qs_pg:name_adm1":"Jihomoravsk\u00fd kraj",
    "qs_pg:photos_9r":0,
    "qs_pg:photos_sr":0,
    "qs_pg:pop_sr":2,
    "qs_pg:qs_pg_placetype":"locality",
    "qs_pg:qs_pg_placetype_gp":"Town",
    "qs_pg:woe_adm0":23424810,
    "woe:adm0_id":23424810,
    "woe:name_adm0":"\u010cesk\u00e1 republika",
    "woe:name_adm1":"Jihomoravsk\u00fd kraj",
    "woe:placetype":"Town",
    "wof:name":"Sto\u0161\u00edkovice na Louce",
    "wof:placetype":"locality",
    "wof:population":203
},
  "geometry": {"coordinates":[16.21487,48.89659],"type":"Point"}
}