{
  "type": "Feature",
  "properties": {
    "gn:admin1_code":"81.0",
    "gn:admin2_code":"0412",
    "gn:asciiname":"Pastviny",
    "gn:country_code":"CZ",
    "gn:dem":569,
    "gn:feature_class":"P",
    "gn:feature_code":"PPL",
    "gn:name":"Pastviny",
    "gn:population":0,
    "gn:timezone":"Europe/Prague",
    "iso:country":"CZ",
    "name:und_x_variant":[
        "Ranzengr\u00fcn",
        "Ranzengruen",
        "Pastviny"
    ],
    "wof:name":"Pastviny",
    "wof:placetype":"locality"
},
  "geometry": {"coordinates":[13.06557,50.26918],"type":"Point"}
}