{
  "type": "Feature",
  "properties": {
    "gn:gn_country":"CZ",
    "gn:gn_fcode":"PPL",
    "gn:gn_pop":388,
    "gn:population":388,
    "iso:country":"CZ",
    "name:azb_x_preferred":[
        "\u0648\u06cc\u062a\u0631\u0648\u0634\u06cc\u062a\u0633\u0647"
    ],
    "name:ceb_x_preferred":[
        "V\u011btru\u0161ice"
    ],
    "name:ces_x_preferred":[
        "V\u011btru\u0161ice"
    ],
    "name:deu_x_preferred":[
        "V\u011btru\u0161ice"
    ],
    "name:eng_x_preferred":[
        "V\u011btru\u0161ice"
    ],
    "name:eus_x_preferred":[
        "V\u011btru\u0161ice"
    ],
    "name:fas_x_preferred":[
        "\u0648\u06cc\u062a\u0631\u0648\u0634\u06cc\u062a\u0633\u0647"
    ],
    "name:fra_x_preferred":[
        "V\u011btru\u0161ice"
    ],
    "name:hun_x_preferred":[
        "V\u011btru\u0161ice"
    ],
    "name:ita_x_preferred":[
        "V\u011btru\u0161ice"
    ],
    "name:msa_x_preferred":[
        "V\u011btru\u0161ice"
    ],
    "name:nan_x_preferred":[
        "V\u011btru\u0161ice"
    ],
    "name:nld_x_preferred":[
        "V\u011btru\u0161ice"
    ],
    "name:pol_x_preferred":[
        "V\u011btru\u0161ice"
    ],
    "name:por_x_preferred":[
        "V\u011btru\u0161ice"
    ],
    "name:rus_x_preferred":[
        "\u0412\u0435\u0442\u0440\u0443\u0448\u0438\u0446\u0435"
    ],
    "name:slk_x_preferred":[
        "V\u011btru\u0161ice"
    ],
    "name:spa_x_preferred":[
        "V\u011btru\u0161ice"
    ],
    "name:srp_x_preferred":[
        "\u0412\u0458\u0435\u0442\u0440\u0443\u0448\u0438\u0446\u0435"
    ],
    "name:swe_x_preferred":[
        "V\u011btru\u0161ice"
    ],
    "name:vie_x_preferred":[
        "V\u011btru\u0161ice"
    ],
    "qs_pg:aaroncc":"CZ",
    "qs_pg:gn_country":"CZ",
    "qs_pg:gn_fcode":"PPL",
    "qs_pg:gn_pop":388,
    "qs_pg:name":"V\u011btru\u0161ice",
    "qs_pg:name_adm0":"\u010cesk\u00e1 republika",
    "qs_pg:name_adm1":"St\u0159edo\u010desk\u00fd kraj",
    "qs_pg:photos_9r":0,
    "qs_pg:photos_sr":0,
    "qs_pg:pop_sr":2,
    "qs_pg:qs_pg_placetype":"locality",
    "qs_pg:qs_pg_placetype_gp":"Town",
    "qs_pg:woe_adm0":23424810,
    "woe:adm0_id":23424810,
    "woe:name_adm0":"\u010cesk\u00e1 republika",
    "woe:name_adm1":"St\u0159edo\u010desk\u00fd kraj",
    "woe:placetype":"Town",
    "wof:name":"V\u011btru\u0161ice",
    "wof:placetype":"locality",
    "wof:population":388
},
  "geometry": {"coordinates":[14.38341,50.1908],"type":"Point"}
}