{
  "type": "Feature",
  "properties": {
    "gn:gn_country":"CZ",
    "gn:gn_fcode":"PPL",
    "gn:gn_pop":407,
    "gn:population":407,
    "iso:country":"CZ",
    "name:azb_x_preferred":[
        "\u0647\u0644\u06cc\u0632\u0648\u0648"
    ],
    "name:ceb_x_preferred":[
        "Hl\u00edzov"
    ],
    "name:ces_x_preferred":[
        "Hl\u00edzov"
    ],
    "name:deu_x_preferred":[
        "Hl\u00edzov"
    ],
    "name:eng_x_preferred":[
        "Hl\u00edzov"
    ],
    "name:eus_x_preferred":[
        "Hl\u00edzov"
    ],
    "name:fas_x_preferred":[
        "\u0647\u0644\u06cc\u0632\u0648\u0648"
    ],
    "name:fra_x_preferred":[
        "Hl\u00edzov"
    ],
    "name:hun_x_preferred":[
        "Hl\u00edzov"
    ],
    "name:ita_x_preferred":[
        "Hl\u00edzov"
    ],
    "name:msa_x_preferred":[
        "Hl\u00edzov"
    ],
    "name:nan_x_preferred":[
        "Hl\u00edzov"
    ],
    "name:nld_x_preferred":[
        "Hl\u00edzov"
    ],
    "name:pol_x_preferred":[
        "Hl\u00edzov"
    ],
    "name:por_x_preferred":[
        "Hl\u00edzov"
    ],
    "name:slk_x_preferred":[
        "Hl\u00edzov"
    ],
    "name:spa_x_preferred":[
        "Hl\u00edzov"
    ],
    "name:srp_x_preferred":[
        "\u0425\u043b\u0438\u0437\u043e\u0432"
    ],
    "name:swe_x_preferred":[
        "Hl\u00edzov"
    ],
    "name:vie_x_preferred":[
        "Hl\u00edzov"
    ],
    "qs_pg:aaroncc":"CZ",
    "qs_pg:gn_country":"CZ",
    "qs_pg:gn_fcode":"PPL",
    "qs_pg:gn_pop":407,
    "qs_pg:name":"Hl\u00edzov",
    "qs_pg:photos_9r":0,
    "qs_pg:photos_sr":0,
    "qs_pg:pop_sr":2,
    "qs_pg:qs_pg_placetype":"locality",
    "wof:name":"Hl\u00edzov",
    "wof:placetype":"locality",
    "wof:population":407
},
  "geometry": {"coordinates":[15.2951,49.985],"type":"Point"}
}