{
  "type": "Feature",
  "properties": {
    "gn:admin1_code":"86.0",
    "gn:admin2_code":"0534",
    "gn:asciiname":"Dolni Libchavy",
    "gn:country_code":"CZ",
    "gn:dem":335,
    "gn:feature_class":"P",
    "gn:feature_code":"PPL",
    "gn:name":"Doln\u00ed Libchavy",
    "gn:population":0,
    "gn:timezone":"Europe/Prague",
    "iso:country":"CZ",
    "name:und_x_variant":[
        "Nieder Lichwe",
        "Doln\u00ed Libchavy"
    ],
    "wof:name":"Dolni Libchavy",
    "wof:placetype":"locality"
},
  "geometry": {"coordinates":[16.39233,49.99722],"type":"Point"}
}