{
  "type": "Feature",
  "properties": {
    "gn:country":"CZ",
    "gn:fcode":"PPL",
    "gn:population":252,
    "iso:country":"CZ",
    "name:azb_x_preferred":[
        "\u0631\u0646\u062f\u06cc\u06cc\u0648\u0648"
    ],
    "name:ceb_x_preferred":[
        "\u0158end\u011bjov"
    ],
    "name:ces_x_preferred":[
        "\u0158end\u011bjov"
    ],
    "name:deu_x_preferred":[
        "\u0158end\u011bjov"
    ],
    "name:eng_x_preferred":[
        "\u0158end\u011bjov"
    ],
    "name:eus_x_preferred":[
        "\u0158end\u011bjov"
    ],
    "name:fas_x_preferred":[
        "\u0631\u0646\u062f\u06cc\u06cc\u0648\u0648"
    ],
    "name:fra_x_preferred":[
        "\u0158end\u011bjov"
    ],
    "name:hun_x_preferred":[
        "\u0158end\u011bjov"
    ],
    "name:ita_x_preferred":[
        "\u0158end\u011bjov"
    ],
    "name:msa_x_preferred":[
        "\u0158end\u011bjov"
    ],
    "name:nan_x_preferred":[
        "\u0158end\u011bjov"
    ],
    "name:nld_x_preferred":[
        "\u0158end\u011bjov"
    ],
    "name:pol_x_preferred":[
        "\u0158end\u011bjov"
    ],
    "name:por_x_preferred":[
        "\u0158end\u011bjov"
    ],
    "name:slk_x_preferred":[
        "\u0158end\u011bjov"
    ],
    "name:spa_x_preferred":[
        "\u0158end\u011bjov"
    ],
    "name:srp_x_preferred":[
        "\u0420\u0435\u043d\u0434\u0458\u0435\u0458\u043e\u0432"
    ],
    "name:swe_x_preferred":[
        "\u0158end\u011bjov"
    ],
    "name:vie_x_preferred":[
        "\u0158end\u011bjov"
    ],
    "qs_pg:aaroncc":"CZ",
    "qs_pg:gn_country":"CZ",
    "qs_pg:gn_fcode":"PPL",
    "qs_pg:gn_pop":252,
    "qs_pg:name":"\u0158end\u011bjov",
    "qs_pg:name_adm0":"\u010cesk\u00e1 republika",
    "qs_pg:name_adm1":"St\u0159edo\u010desk\u00fd kraj",
    "qs_pg:photos_9r":0,
    "qs_pg:photos_sr":0,
    "qs_pg:pop_sr":2,
    "qs_pg:qs_pg_placetype":"locality",
    "qs_pg:qs_pg_placetype_gp":"Town",
    "qs_pg:woe_adm0":23424810,
    "woe:adm0_id":23424810,
    "woe:name_adm0":"\u010cesk\u00e1 republika",
    "woe:name_adm1":"St\u0159edo\u010desk\u00fd kraj",
    "woe:placetype":"Town",
    "wof:name":"\u0158end\u011bjov",
    "wof:placetype":"locality",
    "wof:population":252
},
  "geometry": {"coordinates":[15.08037,49.76784],"type":"Point"}
}