{
  "type": "Feature",
  "properties": {
    "gn:country":"CZ",
    "gn:fcode":"PPL",
    "gn:population":117,
    "iso:country":"CZ",
    "name:azb_x_preferred":[
        "\u0648\u0631\u062a\u0633\u0648\u0648\u06cc\u062a\u0633\u0647"
    ],
    "name:cat_x_preferred":[
        "Vrcovice"
    ],
    "name:ceb_x_preferred":[
        "Vrcovice"
    ],
    "name:ces_x_preferred":[
        "Vrcovice"
    ],
    "name:che_x_preferred":[
        "\u0412\u0440\u0446\u043e\u0432\u0438\u0446\u0435"
    ],
    "name:eng_x_preferred":[
        "Vrcovice"
    ],
    "name:epo_x_preferred":[
        "Vrcovice"
    ],
    "name:eus_x_preferred":[
        "Vrcovice"
    ],
    "name:fas_x_preferred":[
        "\u0648\u0631\u062a\u0633\u0648\u0648\u06cc\u062a\u0633\u0647"
    ],
    "name:fra_x_preferred":[
        "Vrcovice"
    ],
    "name:gle_x_preferred":[
        "Vrcovice"
    ],
    "name:hun_x_preferred":[
        "Vrcovice"
    ],
    "name:ita_x_preferred":[
        "Vrcovice"
    ],
    "name:lmo_x_preferred":[
        "Vrcovice"
    ],
    "name:msa_x_preferred":[
        "Vrcovice"
    ],
    "name:nan_x_preferred":[
        "Vrcovice"
    ],
    "name:nld_x_preferred":[
        "Vrcovice"
    ],
    "name:pol_x_preferred":[
        "Vrcovice"
    ],
    "name:por_x_preferred":[
        "Vrcovice"
    ],
    "name:slk_x_preferred":[
        "Vrcovice"
    ],
    "name:spa_x_preferred":[
        "Vrcovice"
    ],
    "name:srp_x_preferred":[
        "\u0412\u0440\u0446\u043e\u0432\u0438\u0446\u0435"
    ],
    "name:swe_x_preferred":[
        "Vrcovice"
    ],
    "name:tat_x_preferred":[
        "\u0412\u0440\u0446\u043e\u0432\u0438\u0446\u0435"
    ],
    "name:vie_x_preferred":[
        "Vrcovice"
    ],
    "qs_pg:aaroncc":"CZ",
    "qs_pg:gn_country":"CZ",
    "qs_pg:gn_fcode":"PPL",
    "qs_pg:gn_pop":117,
    "qs_pg:name":"Vrcovice",
    "qs_pg:name_adm0":"\u010cesk\u00e1 republika",
    "qs_pg:name_adm1":"Jiho\u010desk\u00fd kraj",
    "qs_pg:photos_9r":0,
    "qs_pg:photos_sr":0,
    "qs_pg:pop_sr":1,
    "qs_pg:qs_pg_placetype":"locality",
    "qs_pg:qs_pg_placetype_gp":"Town",
    "qs_pg:woe_adm0":23424810,
    "woe:adm0_id":23424810,
    "woe:name_adm0":"\u010cesk\u00e1 republika",
    "woe:name_adm1":"Jiho\u010desk\u00fd kraj",
    "woe:placetype":"Town",
    "wof:name":"Vrcovice",
    "wof:placetype":"locality",
    "wof:population":117
},
  "geometry": {"coordinates":[14.17443,49.34465],"type":"Point"}
}