{
  "type": "Feature",
  "properties": {
    "gn:admin1_code":"88.0",
    "gn:admin2_code":"0204",
    "gn:asciiname":"Radlice",
    "gn:country_code":"CZ",
    "gn:dem":370,
    "gn:feature_class":"P",
    "gn:feature_code":"PPL",
    "gn:name":"Radlice",
    "gn:population":0,
    "gn:timezone":"Europe/Prague",
    "iso:country":"CZ",
    "name:ces_x_preferred":[
        "Radlice"
    ],
    "name:nld_x_preferred":[
        "Radlice"
    ],
    "name:pol_x_preferred":[
        "Radlice"
    ],
    "wof:name":"Radlice",
    "wof:placetype":"locality"
},
  "geometry": {"coordinates":[14.94595,49.93525],"type":"Point"}
}