{
  "type": "Feature",
  "properties": {
    "gn:gn_country":"CZ",
    "gn:gn_fcode":"PPL",
    "gn:gn_pop":189,
    "gn:population":189,
    "iso:country":"CZ",
    "name:cze_x_preferred":[
        "\u017deraviny"
    ],
    "name:dut_x_preferred":[
        "\u017deraviny"
    ],
    "name:eng_x_preferred":[
        "\u017deraviny"
    ],
    "name:fre_x_preferred":[
        "\u017deraviny"
    ],
    "name:ger_x_preferred":[
        "\u017deraviny"
    ],
    "name:hun_x_preferred":[
        "\u017deraviny"
    ],
    "name:ita_x_preferred":[
        "\u017deraviny"
    ],
    "name:may_x_preferred":[
        "\u017deraviny"
    ],
    "name:nan_x_preferred":[
        "\u017deraviny"
    ],
    "name:per_x_preferred":[
        "\u0698\u0631\u0627\u0648\u06cc\u0646\u06cc"
    ],
    "name:pol_x_preferred":[
        "\u017deraviny"
    ],
    "name:por_x_preferred":[
        "\u017deraviny"
    ],
    "name:rup_x_preferred":[
        "\u017deraviny"
    ],
    "name:slo_x_preferred":[
        "\u017deraviny"
    ],
    "name:srp_x_preferred":[
        "\u0416\u0435\u0440\u0430\u0432\u0438\u043d\u0438"
    ],
    "name:swe_x_preferred":[
        "\u017deraviny"
    ],
    "name:vie_x_preferred":[
        "\u017deraviny"
    ],
    "qs_pg:aaroncc":"CZ",
    "qs_pg:gn_country":"CZ",
    "qs_pg:gn_fcode":"PPL",
    "qs_pg:gn_pop":189,
    "qs_pg:name":"\u017deraviny",
    "qs_pg:name_adm0":"\u010cesk\u00e1 republika",
    "qs_pg:name_adm1":"Jihomoravsk\u00fd kraj",
    "qs_pg:photos_9r":0,
    "qs_pg:photos_sr":0,
    "qs_pg:pop_sr":1,
    "qs_pg:qs_pg_placetype":"locality",
    "qs_pg:qs_pg_placetype_gp":"Town",
    "qs_pg:woe_adm0":23424810,
    "woe:adm0_id":23424810,
    "woe:name_adm0":"\u010cesk\u00e1 republika",
    "woe:name_adm1":"Jihomoravsk\u00fd kraj",
    "woe:placetype":"Town",
    "wof:name":"\u017deraviny",
    "wof:placetype":"locality",
    "wof:population":189
},
  "geometry": {"coordinates":[17.39152,48.90823],"type":"Point"}
}