{
  "type": "Feature",
  "properties": {
    "gn:admin1_code":"84",
    "gn:admin2_code":"0715",
    "gn:asciiname":"Terezin",
    "gn:country_code":"CZ",
    "gn:dem":375,
    "gn:feature_class":"P",
    "gn:feature_code":"PPL",
    "gn:name":"Terez\u00edn",
    "gn:population":0,
    "gn:timezone":"Europe/Prague",
    "iso:country":"CZ",
    "name:und_x_variant":[
        "Theresienthal",
        "Terez\u00edn"
    ],
    "wof:name":"Terezin",
    "wof:placetype":"locality"
},
  "geometry": {"coordinates":[17.03333,50.01667],"type":"Point"}
}