{
  "type": "Feature",
  "properties": {
    "gn:admin1_code":"90.0",
    "gn:admin2_code":"0721",
    "gn:asciiname":"Sobelice",
    "gn:country_code":"CZ",
    "gn:dem":235,
    "gn:feature_class":"P",
    "gn:feature_code":"PPL",
    "gn:name":"Sob\u011blice",
    "gn:population":0,
    "gn:timezone":"Europe/Prague",
    "iso:country":"CZ",
    "wof:name":"Sobelice",
    "wof:placetype":"locality"
},
  "geometry": {"coordinates":[17.3423,49.28264],"type":"Point"}
}