{
  "type": "Feature",
  "properties": {
    "gn:gn_country":"CZ",
    "gn:gn_fcode":"PPL",
    "gn:gn_pop":637,
    "gn:population":637,
    "iso:country":"CZ",
    "name:unk_x_variant":[
        "R\u00f6hrsdorf"
    ],
    "qs_pg:aaroncc":"CZ",
    "qs_pg:gn_country":"CZ",
    "qs_pg:gn_fcode":"PPL",
    "qs_pg:gn_pop":637,
    "qs_pg:name":"Svor",
    "qs_pg:photos_9r":0,
    "qs_pg:photos_sr":0,
    "qs_pg:pop_sr":2,
    "qs_pg:qs_pg_placetype":"locality",
    "wof:name":"Svor",
    "wof:placetype":"locality",
    "wof:population":637
},
  "geometry": {"coordinates":[14.59681,50.7918],"type":"Point"}
}