{
  "type": "Feature",
  "properties": {
    "iso:country":"CZ",
    "name:azb_x_preferred":[
        "\u0628\u0648\u0631\u0648\u0648\u0646\u06cc\u062a\u0634\u06a9\u0627"
    ],
    "name:ceb_x_preferred":[
        "Borovni\u010dka"
    ],
    "name:ces_x_preferred":[
        "Borovni\u010dka"
    ],
    "name:deu_x_preferred":[
        "Borovni\u010dka"
    ],
    "name:eus_x_preferred":[
        "Borovni\u010dka"
    ],
    "name:fas_x_preferred":[
        "\u0628\u0648\u0631\u0648\u0648\u0646\u06cc\u062a\u0634\u06a9\u0627"
    ],
    "name:fra_x_preferred":[
        "Borovni\u010dka"
    ],
    "name:hun_x_preferred":[
        "Borovni\u010dka"
    ],
    "name:ita_x_preferred":[
        "Borovni\u010dka"
    ],
    "name:msa_x_preferred":[
        "Borovni\u010dka"
    ],
    "name:nld_x_preferred":[
        "Borovni\u010dka"
    ],
    "name:pol_x_preferred":[
        "Borovni\u010dka"
    ],
    "name:por_x_preferred":[
        "Borovni\u010dka"
    ],
    "name:slk_x_preferred":[
        "Borovni\u010dka"
    ],
    "name:spa_x_preferred":[
        "Borovni\u010dka"
    ],
    "name:srp_x_preferred":[
        "\u0411\u043e\u0440\u043e\u0432\u045a\u0438\u0447\u043a\u0430"
    ],
    "name:swe_x_preferred":[
        "Borovni\u010dka"
    ],
    "name:vie_x_preferred":[
        "Borovni\u010dka"
    ],
    "qs_pg:aaroncc":"CZ",
    "qs_pg:name":"Borovni\u010dka",
    "qs_pg:name_adm0":"\u010cesk\u00e1 republika",
    "qs_pg:name_adm1":"Kr\u00e1lov\u00e9hradeck\u00fd kraj",
    "qs_pg:photos":13,
    "qs_pg:photos_1k":3,
    "qs_pg:photos_9k":1,
    "qs_pg:photos_9r":1,
    "qs_pg:photos_all":13,
    "qs_pg:photos_sr":1,
    "qs_pg:pop_sr":0,
    "qs_pg:qs_pg_placetype":"localadmin",
    "qs_pg:qs_pg_placetype_gp":"LocalAdmin",
    "qs_pg:woe_adm0":23424810,
    "woe:adm0_id":23424810,
    "woe:name_adm0":"\u010cesk\u00e1 republika",
    "woe:name_adm1":"Kr\u00e1lov\u00e9hradeck\u00fd kraj",
    "woe:placetype":"LocalAdmin",
    "wof:name":"Borovni\u010dka",
    "wof:placetype":"localadmin"
},
  "geometry": {"coordinates":[15.670002,50.486716],"type":"Point"}
}