{
  "type": "Feature",
  "properties": {
    "iso:country":"CZ",
    "name:ces_x_preferred":[
        "Lesn\u00e1"
    ],
    "name:cze_x_colloquial":[
        "Lesna"
    ],
    "name:eng_x_preferred":[
        "Lesn\u00e1"
    ],
    "name:fra_x_preferred":[
        "Lesn\u00e1"
    ],
    "name:hun_x_preferred":[
        "Lesn\u00e1"
    ],
    "name:ita_x_preferred":[
        "Lesn\u00e1"
    ],
    "name:msa_x_preferred":[
        "Lesn\u00e1"
    ],
    "name:nld_x_preferred":[
        "Lesn\u00e1"
    ],
    "name:pol_x_preferred":[
        "Lesn\u00e1"
    ],
    "name:por_x_preferred":[
        "Lesn\u00e1"
    ],
    "name:slk_x_preferred":[
        "Lesn\u00e1"
    ],
    "name:vie_x_preferred":[
        "Lesn\u00e1"
    ],
    "qs:gn_adm0_cc":"CZ",
    "qs:gn_fcode":"PPLX",
    "qs:gn_local":3078610,
    "qs:gn_name":"Lesn\u00e1",
    "qs:local_max":6134,
    "qs:local_sum":32721,
    "qs:localhoods":44,
    "qs:name":"Lesn\u00e1",
    "qs:name_adm0":"\u010cesk\u00e1 republika",
    "qs:name_adm1":"Jihomoravsk\u00fd kraj",
    "qs:name_adm2":"Brno-M\u011bsto",
    "qs:name_lau":"Brno",
    "qs:name_local":"Brno",
    "qs:photo_max":36,
    "qs:photo_sum":240,
    "qs:placetype":"Suburb",
    "qs:quad_count":36,
    "qs:woe_adm0":23424810,
    "qs:woe_adm1":20070503,
    "qs:woe_adm2":12582547,
    "qs:woe_lau":12605174,
    "qs:woe_local":786869,
    "qs:woe_ver":"7.10.0",
    "wof:lang":[
        "cze"
    ],
    "wof:name":"Lesn\u00e1",
    "wof:placetype":"neighbourhood"
},
  "geometry": {"coordinates":[16.626481,49.225414],"type":"Point"}
}