{
  "type": "Feature",
  "properties": {
    "gn:admin1_code":"89.0",
    "gn:admin2_code":"0426",
    "gn:asciiname":"Hlince",
    "gn:country_code":"CZ",
    "gn:dem":426,
    "gn:feature_class":"P",
    "gn:feature_code":"PPL",
    "gn:name":"Hlince",
    "gn:population":0,
    "gn:timezone":"Europe/Prague",
    "iso:country":"CZ",
    "name:und_x_variant":[
        "Linschen",
        "Hlince"
    ],
    "wof:name":"Hlince",
    "wof:placetype":"locality"
},
  "geometry": {"coordinates":[13.88578,50.5679],"type":"Point"}
}