{
  "type": "Feature",
  "properties": {
    "gn:admin1_code":"87.0",
    "gn:admin2_code":"0322",
    "gn:asciiname":"Besetin",
    "gn:country_code":"CZ",
    "gn:dem":501,
    "gn:feature_class":"P",
    "gn:feature_code":"PPL",
    "gn:name":"Be\u0161et\u00edn",
    "gn:population":0,
    "gn:timezone":"Europe/Prague",
    "iso:country":"CZ",
    "wof:name":"Besetin",
    "wof:placetype":"locality"
},
  "geometry": {"coordinates":[13.62691,49.23974000000001],"type":"Point"}
}