{
  "type": "Feature",
  "properties": {
    "gn:admin1_code":"88.0",
    "gn:admin2_code":"0204",
    "gn:asciiname":"Lzovice",
    "gn:country_code":"CZ",
    "gn:dem":234,
    "gn:feature_class":"P",
    "gn:feature_code":"PPL",
    "gn:name":"L\u017eovice",
    "gn:population":0,
    "gn:timezone":"Europe/Prague",
    "iso:country":"CZ",
    "wof:name":"Lzovice",
    "wof:placetype":"locality"
},
  "geometry": {"coordinates":[15.33977,50.03806],"type":"Point"}
}