{
  "type": "Feature",
  "properties": {
    "gn:admin1_code":"81",
    "gn:admin2_code":"0411",
    "gn:asciiname":"Vyhledy",
    "gn:cc2":"CZ",
    "gn:country_code":"CZ",
    "gn:dem":675,
    "gn:feature_class":"P",
    "gn:feature_code":"PPL",
    "gn:name":"V\u00fdhledy",
    "gn:population":0,
    "gn:timezone":"Europe/Prague",
    "iso:country":"CZ",
    "name:und_x_variant":[
        "Steingruen",
        "Steingr\u00fcn"
    ],
    "wof:name":"Vyhledy",
    "wof:placetype":"locality"
},
  "geometry": {"coordinates":[12.26898,50.1891],"type":"Point"}
}