{
  "type": "Feature",
  "properties": {
    "gn:admin1_code":"86.0",
    "gn:admin2_code":"0534",
    "gn:asciiname":"Darilek",
    "gn:country_code":"CZ",
    "gn:dem":422,
    "gn:feature_class":"P",
    "gn:feature_code":"PPL",
    "gn:name":"Da\u0159\u00edlek",
    "gn:population":0,
    "gn:timezone":"Europe/Prague",
    "iso:country":"CZ",
    "wof:name":"Darilek",
    "wof:placetype":"locality"
},
  "geometry": {"coordinates":[16.35279,50.01939],"type":"Point"}
}