{
  "type": "Feature",
  "properties": {
    "gn:admin1_code":"88",
    "gn:admin2_code":"0207",
    "gn:asciiname":"Zd'ar",
    "gn:country_code":"CZ",
    "gn:dem":239,
    "gn:feature_class":"P",
    "gn:feature_code":"PPL",
    "gn:name":"\u017d\u010f\u00e1r",
    "gn:population":1181,
    "gn:timezone":"Europe/Prague",
    "iso:country":"CZ",
    "name:azb_x_preferred":[
        "\u0698\u062f\u0627\u0631"
    ],
    "name:ceb_x_preferred":[
        "\u017d\u010f\u00e1r"
    ],
    "name:ces_x_preferred":[
        "\u017d\u010f\u00e1r"
    ],
    "name:eus_x_preferred":[
        "\u017d\u010f\u00e1r"
    ],
    "name:fas_x_preferred":[
        "\u0698\u062f\u0627\u0631"
    ],
    "name:hun_x_preferred":[
        "\u017d\u010f\u00e1r"
    ],
    "name:ita_x_preferred":[
        "\u017d\u010f\u00e1r"
    ],
    "name:msa_x_preferred":[
        "\u017d\u010f\u00e1r"
    ],
    "name:nld_x_preferred":[
        "\u017d\u010f\u00e1r"
    ],
    "name:pol_x_preferred":[
        "\u017d\u010f\u00e1r"
    ],
    "name:por_x_preferred":[
        "\u017d\u010f\u00e1r"
    ],
    "name:slk_x_preferred":[
        "\u017d\u010f\u00e1r"
    ],
    "name:spa_x_preferred":[
        "\u017d\u010f\u00e1r"
    ],
    "name:srp_x_preferred":[
        "\u0416\u0434\u0458\u0430\u0440"
    ],
    "name:vie_x_preferred":[
        "\u017d\u010f\u00e1r"
    ],
    "wof:name":"Zd'ar",
    "wof:placetype":"locality",
    "wof:population":1181
},
  "geometry": {"coordinates":[15.08034,50.54366],"type":"Point"}
}