{
  "type": "Feature",
  "properties": {
    "gn:admin1_code":"88",
    "gn:admin2_code":"0207",
    "gn:asciiname":"Zd'ar",
    "gn:country_code":"CZ",
    "gn:dem":239,
    "gn:feature_class":"P",
    "gn:feature_code":"PPL",
    "gn:name":"\u017d\u010f\u00e1r",
    "gn:population":1181,
    "gn:timezone":"Europe/Prague",
    "iso:country":"CZ",
    "wof:name":"Zd'ar",
    "wof:placetype":"locality",
    "wof:population":1181
},
  "geometry": {"coordinates":[15.08034,50.54366],"type":"Point"}
}