{
  "type": "Feature",
  "properties": {
    "iso:country":"CZ",
    "name:ces_x_preferred":[
        "Sv\u00edtkov"
    ],
    "name:cze_x_colloquial":[
        "Svitkov"
    ],
    "name:cze_x_variant":[
        "Switkow"
    ],
    "qs:gn_adm0_cc":"CZ",
    "qs:gn_fcode":"PPL",
    "qs:gn_local":3068582,
    "qs:gn_nam_loc":"Pardubice, Pardubice, Pardubice, Pardubick\u00fd kraj, CZ",
    "qs:gn_namadm1":"86",
    "qs:gn_name":"Sv\u00edtkov",
    "qs:local_max":718,
    "qs:local_sum":1556,
    "qs:localhoods":5,
    "qs:name":"Sv\u00edtkov",
    "qs:name_adm0":"\u010cesk\u00e1 republika",
    "qs:name_adm1":"Pardubick\u00fd kraj",
    "qs:name_adm2":"Pardubice",
    "qs:name_lau":"Pardubice",
    "qs:name_local":"Pardubice",
    "qs:photo_max":270,
    "qs:photo_sum":718,
    "qs:placetype":"Suburb",
    "qs:quad_count":19,
    "qs:woe_adm0":23424810,
    "qs:woe_adm1":20070465,
    "qs:woe_adm2":12582598,
    "qs:woe_lau":12608891,
    "qs:woe_local":795793,
    "qs:woe_ver":"7.10.0",
    "wof:lang":[
        "cze"
    ],
    "wof:name":"Sv\u00edtkov",
    "wof:placetype":"neighbourhood"
},
  "geometry": {"coordinates":[15.737804,50.020081],"type":"Point"}
}