{
  "type": "Feature",
  "properties": {
    "gn:admin1_code":"88.0",
    "gn:admin2_code":"020B",
    "gn:asciiname":"Kosobudy",
    "gn:country_code":"CZ",
    "gn:dem":475,
    "gn:feature_class":"P",
    "gn:feature_code":"PPL",
    "gn:name":"Kosobudy",
    "gn:population":0,
    "gn:timezone":"Europe/Prague",
    "iso:country":"CZ",
    "name:fra_x_preferred":[
        "Kosobudy"
    ],
    "name:pol_x_preferred":[
        "Kosobudy"
    ],
    "name:ukr_x_preferred":[
        "\u041a\u043e\u0441\u043e\u0431\u0443\u0434\u0438"
    ],
    "wof:name":"Kosobudy",
    "wof:placetype":"locality"
},
  "geometry": {"coordinates":[14.23606,49.57919],"type":"Point"}
}