{
  "type": "Feature",
  "properties": {
    "gn:admin1_code":"79.0",
    "gn:admin2_code":"0316",
    "gn:asciiname":"Domanice",
    "gn:country_code":"CZ",
    "gn:dem":439,
    "gn:feature_class":"P",
    "gn:feature_code":"PPL",
    "gn:name":"Domanice",
    "gn:population":0,
    "gn:timezone":"Europe/Prague",
    "iso:country":"CZ",
    "name:ceb_x_preferred":[
        "Domanice"
    ],
    "name:ces_x_preferred":[
        "Domanice"
    ],
    "name:deu_x_preferred":[
        "Domanice"
    ],
    "name:fra_x_preferred":[
        "Domanice"
    ],
    "name:nld_x_preferred":[
        "Domanice"
    ],
    "name:pol_x_preferred":[
        "Domanice"
    ],
    "name:ukr_x_preferred":[
        "\u0414\u043e\u043c\u0430\u043d\u0456\u0446\u0435"
    ],
    "wof:name":"Domanice",
    "wof:placetype":"locality"
},
  "geometry": {"coordinates":[13.92182,49.29888],"type":"Point"}
}