{
  "type": "Feature",
  "properties": {
    "gn:gn_country":"CZ",
    "gn:gn_fcode":"PPL",
    "gn:gn_pop":315,
    "gn:population":315,
    "iso:country":"CZ",
    "name:cze_x_preferred":[
        "Libl\u00edn"
    ],
    "name:dut_x_preferred":[
        "Libl\u00edn"
    ],
    "name:eng_x_preferred":[
        "Libl\u00edn"
    ],
    "name:fre_x_preferred":[
        "Libl\u00edn"
    ],
    "name:hun_x_preferred":[
        "Libl\u00edn"
    ],
    "name:ita_x_preferred":[
        "Libl\u00edn"
    ],
    "name:may_x_preferred":[
        "Libl\u00edn"
    ],
    "name:per_x_preferred":[
        "\u0644\u06cc\u0628\u0644\u06cc\u0646"
    ],
    "name:por_x_preferred":[
        "Libl\u00edn"
    ],
    "name:slo_x_preferred":[
        "Libl\u00edn"
    ],
    "name:srp_x_preferred":[
        "\u041b\u0438\u0431\u043b\u0438\u043d"
    ],
    "name:swe_x_preferred":[
        "Libl\u00edn"
    ],
    "name:vie_x_preferred":[
        "Libl\u00edn"
    ],
    "qs_pg:aaroncc":"CZ",
    "qs_pg:gn_country":"CZ",
    "qs_pg:gn_fcode":"PPL",
    "qs_pg:gn_pop":315,
    "qs_pg:name":"Libl\u00edn",
    "qs_pg:name_adm0":"\u010cesk\u00e1 republika",
    "qs_pg:name_adm1":"Plze\u0148sk\u00fd kraj",
    "qs_pg:photos_9k":1,
    "qs_pg:photos_9r":1,
    "qs_pg:photos_all":2,
    "qs_pg:photos_sr":0,
    "qs_pg:pop_sr":2,
    "qs_pg:qs_pg_placetype":"locality",
    "qs_pg:qs_pg_placetype_gp":"Town",
    "qs_pg:woe_adm0":23424810,
    "woe:adm0_id":23424810,
    "woe:name_adm0":"\u010cesk\u00e1 republika",
    "woe:name_adm1":"Plze\u0148sk\u00fd kraj",
    "woe:placetype":"Town",
    "wof:name":"Libl\u00edn",
    "wof:placetype":"locality",
    "wof:population":315
},
  "geometry": {"coordinates":[13.54424,49.91681],"type":"Point"}
}