{
  "type": "Feature",
  "properties": {
    "gn:admin1_code":"83.0",
    "gn:admin2_code":"0511",
    "gn:asciiname":"Bozikov",
    "gn:country_code":"CZ",
    "gn:dem":264,
    "gn:feature_class":"P",
    "gn:feature_code":"PPL",
    "gn:name":"Bo\u017e\u00edkov",
    "gn:population":0,
    "gn:timezone":"Europe/Prague",
    "iso:country":"CZ",
    "name:und_x_variant":[
        "G\u00f6tzdorf",
        "Bo\u017e\u00edkov"
    ],
    "wof:name":"Bozikov",
    "wof:placetype":"locality"
},
  "geometry": {"coordinates":[14.64878,50.67357],"type":"Point"}
}