{
  "type": "Feature",
  "properties": {
    "gn:country":"CZ",
    "gn:fcode":"PPL",
    "gn:population":133,
    "iso:country":"CZ",
    "name:ceb_x_preferred":[
        "Ond\u0159ejov"
    ],
    "name:ces_x_preferred":[
        "Ond\u0159ejov"
    ],
    "name:deu_x_preferred":[
        "Ond\u0159ejov"
    ],
    "name:epo_x_preferred":[
        "Ond\u0159ejov"
    ],
    "name:fra_x_preferred":[
        "Ond\u0159ejov"
    ],
    "name:ita_x_preferred":[
        "Ond\u0159ejov"
    ],
    "name:nld_x_preferred":[
        "Ond\u0159ejov"
    ],
    "name:slk_x_preferred":[
        "Ond\u0159ejov"
    ],
    "name:srp_x_preferred":[
        "\u041e\u043d\u0434\u0440\u0435\u0458\u043e\u0432"
    ],
    "name:swe_x_preferred":[
        "Ond\u0159ejov"
    ],
    "qs_pg:aaroncc":"CZ",
    "qs_pg:gn_country":"CZ",
    "qs_pg:gn_fcode":"PPL",
    "qs_pg:gn_pop":133,
    "qs_pg:name":"Ond\u0159ejov",
    "qs_pg:name_adm0":"\u010cesk\u00e1 republika",
    "qs_pg:name_adm1":"Kraj Vyso\u010dina",
    "qs_pg:photos_9r":0,
    "qs_pg:photos_sr":0,
    "qs_pg:pop_sr":1,
    "qs_pg:qs_pg_placetype":"locality",
    "qs_pg:qs_pg_placetype_gp":"Town",
    "qs_pg:woe_adm0":23424810,
    "woe:adm0_id":23424810,
    "woe:name_adm0":"\u010cesk\u00e1 republika",
    "woe:name_adm1":"Kraj Vyso\u010dina",
    "woe:placetype":"Town",
    "wof:name":"Ond\u0159ejov",
    "wof:placetype":"locality",
    "wof:population":133
},
  "geometry": {"coordinates":[15.17796,49.39294],"type":"Point"}
}