{
  "type": "Feature",
  "properties": {
    "gn:admin1_code":"87.0",
    "gn:admin2_code":"0321",
    "gn:asciiname":"Hajek",
    "gn:country_code":"CZ",
    "gn:dem":452,
    "gn:feature_class":"P",
    "gn:feature_code":"PPL",
    "gn:name":"H\u00e1jek",
    "gn:population":0,
    "gn:timezone":"Europe/Prague",
    "iso:country":"CZ",
    "name:und_x_variant":[
        "Donau",
        "H\u00e1jek"
    ],
    "wof:name":"Hajek",
    "wof:placetype":"locality"
},
  "geometry": {"coordinates":[13.00237,49.35237],"type":"Point"}
}