{
  "type": "Feature",
  "properties": {
    "gn:admin1_code":"79.0",
    "gn:admin2_code":"0312",
    "gn:asciiname":"Budakov",
    "gn:country_code":"CZ",
    "gn:dem":652,
    "gn:feature_class":"P",
    "gn:feature_code":"PPL",
    "gn:name":"Bud\u00e1kov",
    "gn:population":0,
    "gn:timezone":"Europe/Prague",
    "iso:country":"CZ",
    "name:und_x_variant":[
        "Pudageln",
        "Bud\u00e1kov"
    ],
    "wof:name":"Budakov",
    "wof:placetype":"locality"
},
  "geometry": {"coordinates":[14.50075,48.67609],"type":"Point"}
}