{
  "type": "Feature",
  "properties": {
    "gn:admin1_code":"87",
    "gn:admin2_code":"0322",
    "gn:asciiname":"Zbyslav",
    "gn:country_code":"CZ",
    "gn:dem":577,
    "gn:feature_class":"P",
    "gn:feature_code":"PPL",
    "gn:name":"Zbyslav",
    "gn:population":0,
    "gn:timezone":"Europe/Prague",
    "iso:country":"CZ",
    "wof:name":"Zbyslav",
    "wof:placetype":"locality"
},
  "geometry": {"coordinates":[13.42656,49.41728],"type":"Point"}
}