{
  "type": "Feature",
  "properties": {
    "gn:admin1_code":"89.0",
    "gn:admin2_code":"0423",
    "gn:asciiname":"Brozany",
    "gn:country_code":"CZ",
    "gn:dem":154,
    "gn:feature_class":"P",
    "gn:feature_code":"PPL",
    "gn:name":"Brozany",
    "gn:population":0,
    "gn:timezone":"Europe/Prague",
    "iso:country":"CZ",
    "name:und_x_variant":[
        "Brozan",
        "Brozany"
    ],
    "wof:name":"Brozany",
    "wof:placetype":"locality"
},
  "geometry": {"coordinates":[14.14525,50.45423],"type":"Point"}
}