{
  "type": "Feature",
  "properties": {
    "iso:country":"CZ",
    "name:ceb_x_preferred":[
        "T\u0159e\u0161\u0165"
    ],
    "name:ces_x_preferred":[
        "T\u0159e\u0161\u0165"
    ],
    "name:deu_x_preferred":[
        "T\u0159e\u0161\u0165"
    ],
    "name:epo_x_preferred":[
        "T\u0159e\u0161\u0165"
    ],
    "name:eus_x_preferred":[
        "T\u0159e\u0161\u0165"
    ],
    "name:fas_x_preferred":[
        "\u062a\u0631\u0634\u0633"
    ],
    "name:fra_x_preferred":[
        "T\u0159e\u0161\u0165"
    ],
    "name:hun_x_preferred":[
        "T\u0159e\u0161\u0165"
    ],
    "name:ita_x_preferred":[
        "T\u0159e\u0161\u0165"
    ],
    "name:lav_x_preferred":[
        "Tr\u0161e\u0161tja"
    ],
    "name:msa_x_preferred":[
        "T\u0159e\u0161\u0165"
    ],
    "name:nld_x_preferred":[
        "T\u0159e\u0161\u0165"
    ],
    "name:pol_x_preferred":[
        "T\u0159e\u0161\u0165"
    ],
    "name:por_x_preferred":[
        "T\u0159e\u0161\u0165"
    ],
    "name:ron_x_preferred":[
        "T\u0159e\u0161\u0165"
    ],
    "name:rus_x_preferred":[
        "\u0422\u0440\u0448\u0435\u0448\u0442\u044c"
    ],
    "name:slk_x_preferred":[
        "T\u0159e\u0161\u0165"
    ],
    "name:spa_x_preferred":[
        "T\u0159e\u0161\u0165"
    ],
    "name:srp_x_preferred":[
        "\u0422\u0440\u0435\u0448\u0442"
    ],
    "name:swe_x_preferred":[
        "T\u0159e\u0161\u0165"
    ],
    "name:vie_x_preferred":[
        "T\u0159e\u0161\u0165"
    ],
    "name:zho_x_preferred":[
        "\u7279\u71b1\u4ec0\u5b63"
    ],
    "qs_pg:aaroncc":"CZ",
    "qs_pg:name":"T\u0159e\u0161\u0165",
    "qs_pg:name_adm0":"\u010cesk\u00e1 republika",
    "qs_pg:name_adm1":"Kraj Vyso\u010dina",
    "qs_pg:photos":1,
    "qs_pg:photos_1k":1,
    "qs_pg:photos_9k":2,
    "qs_pg:photos_9r":5,
    "qs_pg:photos_all":544,
    "qs_pg:photos_sr":1,
    "qs_pg:pop_sr":0,
    "qs_pg:qs_pg_placetype":"localadmin",
    "qs_pg:qs_pg_placetype_gp":"LocalAdmin",
    "qs_pg:woe_adm0":23424810,
    "woe:adm0_id":23424810,
    "woe:name_adm0":"\u010cesk\u00e1 republika",
    "woe:name_adm1":"Kraj Vyso\u010dina",
    "woe:placetype":"LocalAdmin",
    "wof:name":"T\u0159e\u0161\u0165",
    "wof:placetype":"localadmin"
},
  "geometry": {"coordinates":[15.487336,49.289347],"type":"Point"}
}