{
  "type": "Feature",
  "properties": {
    "gn:gn_country":"CZ",
    "gn:gn_fcode":"PPL",
    "gn:gn_pop":212,
    "gn:population":212,
    "iso:country":"CZ",
    "name:ces_x_preferred":[
        "Odrava"
    ],
    "name:deu_x_preferred":[
        "Odrava"
    ],
    "name:eng_x_preferred":[
        "Odrava"
    ],
    "name:fas_x_preferred":[
        "\u0627\u0648\u062f\u0631\u0627\u0648\u0627"
    ],
    "name:fra_x_preferred":[
        "Odrava"
    ],
    "name:hun_x_preferred":[
        "Odrava"
    ],
    "name:ita_x_preferred":[
        "Odrava"
    ],
    "name:msa_x_preferred":[
        "Odrava"
    ],
    "name:nld_x_preferred":[
        "Odrava"
    ],
    "name:pol_x_preferred":[
        "Odrava"
    ],
    "name:por_x_preferred":[
        "Odrava"
    ],
    "name:rup_x_preferred":[
        "Odrava"
    ],
    "name:slk_x_preferred":[
        "Odrava"
    ],
    "name:srp_x_preferred":[
        "\u041e\u0434\u0440\u0430\u0432\u0430"
    ],
    "name:swe_x_preferred":[
        "Odrava"
    ],
    "name:unk_x_variant":[
        "Kulsam"
    ],
    "name:vie_x_preferred":[
        "Odrava"
    ],
    "qs_pg:aaroncc":"CZ",
    "qs_pg:gn_country":"CZ",
    "qs_pg:gn_fcode":"PPL",
    "qs_pg:gn_pop":212,
    "qs_pg:name":"Odrava",
    "qs_pg:name_adm0":"\u010cesk\u00e1 republika",
    "qs_pg:name_adm1":"Karlovarsk\u00fd kraj",
    "qs_pg:photos_9k":1,
    "qs_pg:photos_9r":1,
    "qs_pg:photos_all":2,
    "qs_pg:photos_sr":0,
    "qs_pg:pop_sr":2,
    "qs_pg:qs_pg_placetype":"locality",
    "qs_pg:qs_pg_placetype_gp":"Town",
    "qs_pg:woe_adm0":23424810,
    "woe:adm0_id":23424810,
    "woe:name_adm0":"\u010cesk\u00e1 republika",
    "woe:name_adm1":"Karlovarsk\u00fd kraj",
    "woe:placetype":"Town",
    "wof:name":"Odrava",
    "wof:placetype":"locality",
    "wof:population":212
},
  "geometry": {"coordinates":[12.48413,50.10306],"type":"Point"}
}