{
  "type": "Feature",
  "properties": {
    "gn:admin1_code":"89.0",
    "gn:admin2_code":"0423",
    "gn:asciiname":"Malesov",
    "gn:cc2":"CZ",
    "gn:country_code":"CZ",
    "gn:dem":243,
    "gn:feature_class":"P",
    "gn:feature_code":"PPL",
    "gn:name":"Male\u0161ov",
    "gn:population":0,
    "gn:timezone":"Europe/Prague",
    "iso:country":"CZ",
    "name:und_x_variant":[
        "Malschen"
    ],
    "wof:name":"Malesov",
    "wof:placetype":"locality"
},
  "geometry": {"coordinates":[14.32188,50.5107],"type":"Point"}
}