{
  "type": "Feature",
  "properties": {
    "iso:country":"CZ",
    "name:ces_x_preferred":[
        "Leti\u0161t\u011b Jihlava"
    ],
    "name:eng_x_preferred":[
        "Jihlava Airport"
    ],
    "name:msa_x_preferred":[
        "Lapangan Terbang Jihlava"
    ],
    "name:ron_x_preferred":[
        "Aeroportul Jihlava"
    ],
    "oa:elevation_ft":"1821",
    "oa:type":"small_airport",
    "woe:hierarchy":{
        "country_id":23424810,
        "county_id":12582550,
        "localadmin_id":12605925,
        "planet_id":1,
        "state_id":20070467
    },
    "wof:name":"Letiste Jihlava",
    "wof:placetype":"campus"
},
  "geometry": {"coordinates":[15.6353,49.4194],"type":"Point"}
}