{
  "type": "Feature",
  "properties": {
    "gn:admin1_code":"78",
    "gn:admin2_code":"0623",
    "gn:asciiname":"Vinohradky",
    "gn:country_code":"CZ",
    "gn:dem":202,
    "gn:feature_class":"P",
    "gn:feature_code":"PPL",
    "gn:name":"Vinohr\u00e1dky",
    "gn:population":0,
    "gn:timezone":"Europe/Prague",
    "iso:country":"CZ",
    "name:und_x_variant":[
        "Weinberg",
        "Vinohr\u00e1dky"
    ],
    "wof:name":"Vinohradky",
    "wof:placetype":"locality"
},
  "geometry": {"coordinates":[16.41667,48.96667],"type":"Point"}
}