{
  "type": "Feature",
  "properties": {
    "gn:admin1_code":"88.0",
    "gn:admin2_code":"0206",
    "gn:asciiname":"Pribohy",
    "gn:country_code":"CZ",
    "gn:dem":332,
    "gn:feature_class":"P",
    "gn:feature_code":"PPL",
    "gn:name":"P\u0159\u00edbohy",
    "gn:population":0,
    "gn:timezone":"Europe/Prague",
    "iso:country":"CZ",
    "name:und_x_variant":[
        "Riboch",
        "P\u0159\u00edbohy"
    ],
    "wof:name":"Pribohy",
    "wof:placetype":"locality"
},
  "geometry": {"coordinates":[14.63857,50.46724],"type":"Point"}
}