{
  "type": "Feature",
  "properties": {
    "gn:admin1_code":"82",
    "gn:admin2_code":"0524",
    "gn:asciiname":"Vojenice",
    "gn:country_code":"CZ",
    "gn:dem":384,
    "gn:feature_class":"P",
    "gn:feature_code":"PPL",
    "gn:name":"Vojenice",
    "gn:population":0,
    "gn:timezone":"Europe/Prague",
    "iso:country":"CZ",
    "wof:name":"Vojenice",
    "wof:placetype":"locality"
},
  "geometry": {"coordinates":[16.1336,50.21748],"type":"Point"}
}