{
  "type": "Feature",
  "properties": {
    "gn:admin1_code":"81.0",
    "gn:admin2_code":"0412",
    "gn:asciiname":"Luby",
    "gn:country_code":"CZ",
    "gn:dem":491,
    "gn:feature_class":"P",
    "gn:feature_code":"PPL",
    "gn:name":"Luby",
    "gn:population":0,
    "gn:timezone":"Europe/Prague",
    "iso:country":"CZ",
    "wof:name":"Luby",
    "wof:placetype":"locality"
},
  "geometry": {"coordinates":[13.2687,50.08102],"type":"Point"}
}