{
  "type": "Feature",
  "properties": {
    "gn:gn_country":"CZ",
    "gn:gn_fcode":"PPL",
    "gn:gn_pop":398,
    "gn:population":398,
    "iso:country":"CZ",
    "name:bul_x_preferred":[
        "\u0411\u0430\u0432\u043e\u0440\u0439"
    ],
    "name:cze_x_preferred":[
        "Bavory"
    ],
    "name:dut_x_preferred":[
        "Bavory"
    ],
    "name:eng_x_preferred":[
        "Bavory"
    ],
    "name:epo_x_preferred":[
        "Bavory"
    ],
    "name:fre_x_preferred":[
        "Bavory"
    ],
    "name:ger_x_preferred":[
        "Bavory"
    ],
    "name:hun_x_preferred":[
        "Bavory"
    ],
    "name:ita_x_preferred":[
        "Bavory"
    ],
    "name:may_x_preferred":[
        "Bavory"
    ],
    "name:nan_x_preferred":[
        "Bavory"
    ],
    "name:per_x_preferred":[
        "\u0628\u0627\u0648\u0648\u0631\u06cc"
    ],
    "name:pol_x_preferred":[
        "Bavory"
    ],
    "name:por_x_preferred":[
        "Bavory"
    ],
    "name:rup_x_preferred":[
        "Bavory"
    ],
    "name:slo_x_preferred":[
        "Bavory"
    ],
    "name:srp_x_preferred":[
        "\u0411\u0430\u0432\u043e\u0440\u0438"
    ],
    "name:swe_x_preferred":[
        "Bavory"
    ],
    "name:unk_x_variant":[
        "Pardorf"
    ],
    "name:vie_x_preferred":[
        "Bavory"
    ],
    "qs_pg:aaroncc":"CZ",
    "qs_pg:gn_country":"CZ",
    "qs_pg:gn_fcode":"PPL",
    "qs_pg:gn_pop":398,
    "qs_pg:name":"Bavory",
    "qs_pg:name_adm0":"\u010cesk\u00e1 republika",
    "qs_pg:name_adm1":"Jihomoravsk\u00fd kraj",
    "qs_pg:photos_9k":1,
    "qs_pg:photos_9r":1,
    "qs_pg:photos_all":2,
    "qs_pg:photos_sr":0,
    "qs_pg:pop_sr":2,
    "qs_pg:qs_pg_placetype":"locality",
    "qs_pg:qs_pg_placetype_gp":"Town",
    "qs_pg:woe_adm0":23424810,
    "woe:adm0_id":23424810,
    "woe:name_adm0":"\u010cesk\u00e1 republika",
    "woe:name_adm1":"Jihomoravsk\u00fd kraj",
    "woe:placetype":"Town",
    "wof:name":"Bavory",
    "wof:placetype":"locality",
    "wof:population":398
},
  "geometry": {"coordinates":[16.62225,48.83469],"type":"Point"}
}