{
  "type": "Feature",
  "properties": {
    "gn:gn_country":"CZ",
    "gn:gn_fcode":"PPL",
    "gn:gn_pop":438,
    "gn:population":438,
    "iso:country":"CZ",
    "name:cze_x_preferred":[
        "Prosenick\u00e1 Lhota"
    ],
    "name:dut_x_preferred":[
        "Prosenick\u00e1 Lhota"
    ],
    "name:eng_x_preferred":[
        "Prosenick\u00e1 Lhota"
    ],
    "name:fre_x_preferred":[
        "Prosenick\u00e1 Lhota"
    ],
    "name:hun_x_preferred":[
        "Prosenick\u00e1 Lhota"
    ],
    "name:ita_x_preferred":[
        "Prosenick\u00e1 Lhota"
    ],
    "name:may_x_preferred":[
        "Prosenick\u00e1 Lhota"
    ],
    "name:per_x_preferred":[
        "\u067e\u0631\u0648\u0633\u0646\u06cc\u062a\u0633\u06a9\u0627 \u0644\u0647\u0648\u062a\u0627"
    ],
    "name:por_x_preferred":[
        "Prosenick\u00e1 Lhota"
    ],
    "name:rup_x_preferred":[
        "Prosenick\u00e1 Lhota"
    ],
    "name:slo_x_preferred":[
        "Prosenick\u00e1 Lhota"
    ],
    "name:srp_x_preferred":[
        "\u041f\u0440\u043e\u0441\u0435\u045a\u0438\u0446\u043a\u0430 \u041b\u0445\u043e\u0442\u0430"
    ],
    "name:swe_x_preferred":[
        "Prosenick\u00e1 Lhota"
    ],
    "name:vie_x_preferred":[
        "Prosenick\u00e1 Lhota"
    ],
    "qs_pg:aaroncc":"CZ",
    "qs_pg:gn_country":"CZ",
    "qs_pg:gn_fcode":"PPL",
    "qs_pg:gn_pop":438,
    "qs_pg:name":"Prosenick\u00e1 Lhota",
    "qs_pg:name_adm0":"\u010cesk\u00e1 republika",
    "qs_pg:name_adm1":"St\u0159edo\u010desk\u00fd kraj",
    "qs_pg:photos_9r":0,
    "qs_pg:photos_sr":0,
    "qs_pg:pop_sr":2,
    "qs_pg:qs_pg_placetype":"locality",
    "qs_pg:qs_pg_placetype_gp":"Town",
    "qs_pg:woe_adm0":23424810,
    "woe:adm0_id":23424810,
    "woe:name_adm0":"\u010cesk\u00e1 republika",
    "woe:name_adm1":"St\u0159edo\u010desk\u00fd kraj",
    "woe:placetype":"Town",
    "wof:name":"Prosenick\u00e1 Lhota",
    "wof:placetype":"locality",
    "wof:population":438
},
  "geometry": {"coordinates":[14.48269,49.68963],"type":"Point"}
}