{
  "type": "Feature",
  "properties": {
    "gn:admin1_code":"89",
    "gn:admin2_code":"0424",
    "gn:asciiname":"Vrbicka",
    "gn:cc2":"CZ",
    "gn:country_code":"CZ",
    "gn:dem":438,
    "gn:feature_class":"P",
    "gn:feature_code":"PPL",
    "gn:name":"Vrbi\u010dka",
    "gn:population":0,
    "gn:timezone":"Europe/Prague",
    "iso:country":"CZ",
    "name:und_x_variant":[
        "Klein F\u00fcrwitz"
    ],
    "wof:name":"Vrbicka",
    "wof:placetype":"locality"
},
  "geometry": {"coordinates":[13.29329,50.17679],"type":"Point"}
}