{
  "type": "Feature",
  "properties": {
    "gn:gn_country":"CZ",
    "gn:gn_fcode":"PPL",
    "gn:gn_pop":579,
    "gn:population":579,
    "iso:country":"CZ",
    "name:ceb_x_preferred":[
        "Ky\u0161ice"
    ],
    "name:ces_x_preferred":[
        "Ky\u0161ice"
    ],
    "name:epo_x_preferred":[
        "Ky\u0161ice"
    ],
    "name:fra_x_preferred":[
        "Ky\u0161ice"
    ],
    "name:ita_x_preferred":[
        "Ky\u0161ice"
    ],
    "name:nld_x_preferred":[
        "Ky\u0161ice"
    ],
    "name:slk_x_preferred":[
        "Ky\u0161ice"
    ],
    "name:srp_x_preferred":[
        "\u041a\u0438\u0448\u0438\u0446\u0435"
    ],
    "name:swe_x_preferred":[
        "Ky\u0161ice"
    ],
    "qs_pg:aaroncc":"CZ",
    "qs_pg:gn_country":"CZ",
    "qs_pg:gn_fcode":"PPL",
    "qs_pg:gn_pop":579,
    "qs_pg:name":"Ky\u0161ice",
    "qs_pg:name_adm0":"\u010cesk\u00e1 republika",
    "qs_pg:name_adm1":"St\u0159edo\u010desk\u00fd kraj",
    "qs_pg:photos_9r":0,
    "qs_pg:photos_sr":0,
    "qs_pg:pop_sr":2,
    "qs_pg:qs_pg_placetype":"locality",
    "qs_pg:qs_pg_placetype_gp":"Town",
    "qs_pg:woe_adm0":23424810,
    "woe:adm0_id":23424810,
    "woe:name_adm0":"\u010cesk\u00e1 republika",
    "woe:name_adm1":"St\u0159edo\u010desk\u00fd kraj",
    "woe:placetype":"Town",
    "wof:name":"Ky\u0161ice",
    "wof:placetype":"locality",
    "wof:population":579
},
  "geometry": {"coordinates":[14.10623,50.09119],"type":"Point"}
}