{
  "type": "Feature",
  "properties": {
    "gn:admin1_code":"79.0",
    "gn:admin2_code":"0315",
    "gn:asciiname":"Nespice",
    "gn:country_code":"CZ",
    "gn:dem":685,
    "gn:feature_class":"P",
    "gn:feature_code":"PPL",
    "gn:name":"Nespice",
    "gn:population":0,
    "gn:timezone":"Europe/Prague",
    "iso:country":"CZ",
    "wof:name":"Nespice",
    "wof:placetype":"locality"
},
  "geometry": {"coordinates":[13.74549,49.11682],"type":"Point"}
}