{
  "type": "Feature",
  "properties": {
    "gn:gn_country":"CZ",
    "gn:gn_fcode":"PPL",
    "gn:gn_pop":80,
    "gn:population":80,
    "iso:country":"CZ",
    "name:cze_x_preferred":[
        "Vratisl\u00e1vka"
    ],
    "name:dut_x_preferred":[
        "Vratisl\u00e1vka"
    ],
    "name:eng_x_preferred":[
        "Vratisl\u00e1vka"
    ],
    "name:fre_x_preferred":[
        "Vratisl\u00e1vka"
    ],
    "name:ger_x_preferred":[
        "Vratisl\u00e1vka"
    ],
    "name:gre_x_preferred":[
        "\u0392\u03c1\u03b1\u03c4\u03b9\u03c3\u03bb\u03ac\u03b2\u03ba\u03b1"
    ],
    "name:hun_x_preferred":[
        "Vratisl\u00e1vka"
    ],
    "name:ita_x_preferred":[
        "Vratisl\u00e1vka"
    ],
    "name:may_x_preferred":[
        "Vratisl\u00e1vka"
    ],
    "name:nan_x_preferred":[
        "Vratisl\u00e1vka"
    ],
    "name:per_x_preferred":[
        "\u0648\u0631\u0627\u062a\u06cc\u0633\u0644\u0627\u0648\u06a9\u0627"
    ],
    "name:pol_x_preferred":[
        "Vratisl\u00e1vka"
    ],
    "name:por_x_preferred":[
        "Vratisl\u00e1vka"
    ],
    "name:rup_x_preferred":[
        "Vratisl\u00e1vka"
    ],
    "name:slo_x_preferred":[
        "Vratisl\u00e1vka"
    ],
    "name:vie_x_preferred":[
        "Vratisl\u00e1vka"
    ],
    "qs_pg:aaroncc":"CZ",
    "qs_pg:gn_country":"CZ",
    "qs_pg:gn_fcode":"PPL",
    "qs_pg:gn_pop":80,
    "qs_pg:name":"Vratisl\u00e1vka",
    "qs_pg:name_adm0":"\u010cesk\u00e1 republika",
    "qs_pg:name_adm1":"Kraj Vyso\u010dina",
    "qs_pg:photos_9r":0,
    "qs_pg:photos_sr":0,
    "qs_pg:pop_sr":1,
    "qs_pg:qs_pg_placetype":"locality",
    "qs_pg:qs_pg_placetype_gp":"Town",
    "qs_pg:woe_adm0":23424810,
    "woe:adm0_id":23424810,
    "woe:name_adm0":"\u010cesk\u00e1 republika",
    "woe:name_adm1":"Kraj Vyso\u010dina",
    "woe:placetype":"Town",
    "wof:name":"Vratisl\u00e1vka",
    "wof:placetype":"locality",
    "wof:population":80
},
  "geometry": {"coordinates":[16.24403,49.38641],"type":"Point"}
}