{
  "type": "Feature",
  "properties": {
    "gn:gn_country":"CZ",
    "gn:gn_fcode":"PPL",
    "gn:gn_pop":589,
    "gn:population":589,
    "iso:country":"CZ",
    "name:cze_x_preferred":[
        "Daskab\u00e1t"
    ],
    "name:dut_x_preferred":[
        "Daskab\u00e1t"
    ],
    "name:eng_x_preferred":[
        "Daskab\u00e1t"
    ],
    "name:epo_x_preferred":[
        "Daskab\u00e1t"
    ],
    "name:fre_x_preferred":[
        "Daskab\u00e1t"
    ],
    "name:ger_x_preferred":[
        "Daskab\u00e1t"
    ],
    "name:hun_x_preferred":[
        "Daskab\u00e1t"
    ],
    "name:ita_x_preferred":[
        "Daskab\u00e1t"
    ],
    "name:may_x_preferred":[
        "Daskab\u00e1t"
    ],
    "name:per_x_preferred":[
        "\u062f\u0627\u0633\u06a9\u0627\u0628\u0627\u062a"
    ],
    "name:pol_x_preferred":[
        "Daskab\u00e1t"
    ],
    "name:por_x_preferred":[
        "Daskab\u00e1t"
    ],
    "name:rup_x_preferred":[
        "Daskab\u00e1t"
    ],
    "name:slo_x_preferred":[
        "Daskab\u00e1t"
    ],
    "name:srp_x_preferred":[
        "\u0414\u0430\u0441\u043a\u0430\u0431\u0430\u0442"
    ],
    "name:swe_x_preferred":[
        "Daskab\u00e1t"
    ],
    "name:vie_x_preferred":[
        "Daskab\u00e1t"
    ],
    "qs_pg:aaroncc":"CZ",
    "qs_pg:gn_country":"CZ",
    "qs_pg:gn_fcode":"PPL",
    "qs_pg:gn_pop":589,
    "qs_pg:name":"Daskab\u00e1t",
    "qs_pg:name_adm0":"\u010cesk\u00e1 republika",
    "qs_pg:name_adm1":"Olomouck\u00fd kraj",
    "qs_pg:photos_9r":0,
    "qs_pg:photos_sr":0,
    "qs_pg:pop_sr":2,
    "qs_pg:qs_pg_placetype":"locality",
    "qs_pg:qs_pg_placetype_gp":"Town",
    "qs_pg:woe_adm0":23424810,
    "woe:adm0_id":23424810,
    "woe:name_adm0":"\u010cesk\u00e1 republika",
    "woe:name_adm1":"Olomouck\u00fd kraj",
    "woe:placetype":"Town",
    "wof:name":"Daskab\u00e1t",
    "wof:placetype":"locality",
    "wof:population":589
},
  "geometry": {"coordinates":[17.44724,49.57854],"type":"Point"}
}