{
  "type": "Feature",
  "properties": {
    "gn:admin1_code":"86.0",
    "gn:admin2_code":"0532",
    "gn:asciiname":"Mnetice",
    "gn:country_code":"CZ",
    "gn:dem":227,
    "gn:feature_class":"P",
    "gn:feature_code":"PPL",
    "gn:name":"Mn\u00e9tice",
    "gn:population":0,
    "gn:timezone":"Europe/Prague",
    "iso:country":"CZ",
    "wof:name":"Mnetice",
    "wof:placetype":"locality"
},
  "geometry": {"coordinates":[15.83497,50.01381],"type":"Point"}
}