{
  "type": "Feature",
  "properties": {
    "gn:admin1_code":"80.0",
    "gn:admin2_code":"0614",
    "gn:asciiname":"Ohrazenice",
    "gn:country_code":"CZ",
    "gn:dem":414,
    "gn:feature_class":"P",
    "gn:feature_code":"PPL",
    "gn:name":"Ohrazenice",
    "gn:population":0,
    "gn:timezone":"Europe/Prague",
    "iso:country":"CZ",
    "name:ceb_x_preferred":[
        "Ohrazenice"
    ],
    "name:ces_x_preferred":[
        "Ohrazenice"
    ],
    "name:deu_x_preferred":[
        "Ohrazenice"
    ],
    "name:fra_x_preferred":[
        "Ohrazenice"
    ],
    "name:ita_x_preferred":[
        "Ohrazenice"
    ],
    "name:nld_x_preferred":[
        "Ohrazenice"
    ],
    "name:slk_x_preferred":[
        "Ohrazenice"
    ],
    "name:srp_x_preferred":[
        "\u041e\u0445\u0440\u0430\u0437\u0435\u045a\u0438\u0446\u0435"
    ],
    "name:swe_x_preferred":[
        "Ohrazenice"
    ],
    "wof:name":"Ohrazenice",
    "wof:placetype":"locality"
},
  "geometry": {"coordinates":[15.89083,49.05526],"type":"Point"}
}