{
  "type": "Feature",
  "properties": {
    "gn:admin1_code":"83.0",
    "gn:admin2_code":"0513",
    "gn:asciiname":"Knezice",
    "gn:country_code":"CZ",
    "gn:dem":343,
    "gn:feature_class":"P",
    "gn:feature_code":"PPL",
    "gn:name":"Kn\u011b\u017eice",
    "gn:population":0,
    "gn:timezone":"Europe/Prague",
    "iso:country":"CZ",
    "name:und_x_variant":[
        "Gross Herrndorf",
        "Kn\u011b\u017eice"
    ],
    "wof:name":"Knezice",
    "wof:placetype":"locality"
},
  "geometry": {"coordinates":[14.77238,50.7919],"type":"Point"}
}