{
  "type": "Feature",
  "properties": {
    "gn:gn_country":"CZ",
    "gn:gn_fcode":"PPL",
    "gn:gn_pop":0,
    "iso:country":"CZ",
    "name:unk_x_variant":[
        "Doln\u00ed Brand"
    ],
    "qs_pg:aaroncc":"CZ",
    "qs_pg:gn_country":"CZ",
    "qs_pg:gn_fcode":"PPL",
    "qs_pg:gn_pop":0,
    "qs_pg:name":"Doln\u00ed \u017d\u010f\u00e1r",
    "qs_pg:name_adm0":"\u010cesk\u00e1 republika",
    "qs_pg:name_adm1":"Karlovarsk\u00fd kraj",
    "qs_pg:photos_9r":0,
    "qs_pg:photos_sr":0,
    "qs_pg:pop_sr":0,
    "qs_pg:qs_pg_placetype":"locality",
    "qs_pg:qs_pg_placetype_gp":"Town",
    "qs_pg:woe_adm0":23424810,
    "woe:adm0_id":23424810,
    "woe:name_adm0":"\u010cesk\u00e1 republika",
    "woe:name_adm1":"Karlovarsk\u00fd kraj",
    "woe:placetype":"Town",
    "wof:name":"Doln\u00ed \u017d\u010f\u00e1r",
    "wof:placetype":"locality"
},
  "geometry": {"coordinates":[12.9479,50.32574],"type":"Point"}
}