{
  "type": "Feature",
  "properties": {
    "gn:country":"CZ",
    "gn:fcode":"PPL",
    "gn:population":0,
    "iso:country":"CZ",
    "name:azb_x_preferred":[
        "\u062f\u0648\u0644\u0646\u06cc \u0698\u062f\u0627\u0631"
    ],
    "name:ceb_x_preferred":[
        "Doln\u00ed \u017d\u010f\u00e1r"
    ],
    "name:ces_x_preferred":[
        "Doln\u00ed \u017d\u010f\u00e1r"
    ],
    "name:deu_x_preferred":[
        "Doln\u00ed \u017d\u010f\u00e1r"
    ],
    "name:eus_x_preferred":[
        "Doln\u00ed \u017d\u010f\u00e1r"
    ],
    "name:fas_x_preferred":[
        "\u062f\u0648\u0644\u0646\u06cc \u0698\u062f\u0627\u0631"
    ],
    "name:fra_x_preferred":[
        "Doln\u00ed \u017d\u010f\u00e1r"
    ],
    "name:hun_x_preferred":[
        "Doln\u00ed \u017d\u010f\u00e1r"
    ],
    "name:ita_x_preferred":[
        "Doln\u00ed \u017d\u010f\u00e1r"
    ],
    "name:msa_x_preferred":[
        "Doln\u00ed \u017d\u010f\u00e1r"
    ],
    "name:nld_x_preferred":[
        "Doln\u00ed \u017d\u010f\u00e1r"
    ],
    "name:pol_x_preferred":[
        "Doln\u00ed \u017d\u010f\u00e1r"
    ],
    "name:por_x_preferred":[
        "Doln\u00ed \u017d\u010f\u00e1r"
    ],
    "name:slk_x_preferred":[
        "Doln\u00ed \u017d\u010f\u00e1r"
    ],
    "name:spa_x_preferred":[
        "Doln\u00ed \u017d\u010f\u00e1r"
    ],
    "name:srp_x_preferred":[
        "\u0414\u043e\u043b\u045a\u0438 \u0416\u0434\u0458\u0430\u0440"
    ],
    "name:swe_x_preferred":[
        "Doln\u00ed \u017d\u010f\u00e1r"
    ],
    "name:und_x_variant":[
        "Doln\u00ed Brand"
    ],
    "name:vie_x_preferred":[
        "Doln\u00ed \u017d\u010f\u00e1r"
    ],
    "qs_pg:aaroncc":"CZ",
    "qs_pg:gn_country":"CZ",
    "qs_pg:gn_fcode":"PPL",
    "qs_pg:gn_pop":0,
    "qs_pg:name":"Doln\u00ed \u017d\u010f\u00e1r",
    "qs_pg:name_adm0":"\u010cesk\u00e1 republika",
    "qs_pg:name_adm1":"Karlovarsk\u00fd kraj",
    "qs_pg:photos_9r":0,
    "qs_pg:photos_sr":0,
    "qs_pg:pop_sr":0,
    "qs_pg:qs_pg_placetype":"locality",
    "qs_pg:qs_pg_placetype_gp":"Town",
    "qs_pg:woe_adm0":23424810,
    "woe:adm0_id":23424810,
    "woe:name_adm0":"\u010cesk\u00e1 republika",
    "woe:name_adm1":"Karlovarsk\u00fd kraj",
    "woe:placetype":"Town",
    "wof:name":"Doln\u00ed \u017d\u010f\u00e1r",
    "wof:placetype":"locality"
},
  "geometry": {"coordinates":[12.9479,50.32574],"type":"Point"}
}