{
  "type": "Feature",
  "properties": {
    "gn:gn_country":"CZ",
    "gn:gn_fcode":"PPL",
    "gn:gn_pop":103,
    "gn:population":103,
    "iso:country":"CZ",
    "name:ces_x_preferred":[
        "Kornatice"
    ],
    "name:eng_x_preferred":[
        "Kornatice"
    ],
    "name:fas_x_preferred":[
        "\u06a9\u0648\u0631\u0646\u0627\u062a\u06cc\u062a\u0633\u0647"
    ],
    "name:fra_x_preferred":[
        "Kornatice"
    ],
    "name:hun_x_preferred":[
        "Kornatice"
    ],
    "name:ita_x_preferred":[
        "Kornatice"
    ],
    "name:msa_x_preferred":[
        "Kornatice"
    ],
    "name:nan_x_preferred":[
        "Kornatice"
    ],
    "name:nld_x_preferred":[
        "Kornatice"
    ],
    "name:por_x_preferred":[
        "Kornatice"
    ],
    "name:rup_x_preferred":[
        "Kornatice"
    ],
    "name:slk_x_preferred":[
        "Kornatice"
    ],
    "name:srp_x_preferred":[
        "\u041a\u043e\u0440\u043d\u0430\u0442\u0438\u0446\u0435"
    ],
    "name:swe_x_preferred":[
        "Kornatice"
    ],
    "name:unk_x_variant":[
        "Kornatitz"
    ],
    "name:vie_x_preferred":[
        "Kornatice"
    ],
    "qs_pg:aaroncc":"CZ",
    "qs_pg:gn_country":"CZ",
    "qs_pg:gn_fcode":"PPL",
    "qs_pg:gn_pop":103,
    "qs_pg:name":"Kornatice",
    "qs_pg:name_adm0":"\u010cesk\u00e1 republika",
    "qs_pg:name_adm1":"Plze\u0148sk\u00fd kraj",
    "qs_pg:photos_9r":0,
    "qs_pg:photos_sr":0,
    "qs_pg:pop_sr":1,
    "qs_pg:qs_pg_placetype":"locality",
    "qs_pg:qs_pg_placetype_gp":"Town",
    "qs_pg:woe_adm0":23424810,
    "woe:adm0_id":23424810,
    "woe:name_adm0":"\u010cesk\u00e1 republika",
    "woe:name_adm1":"Plze\u0148sk\u00fd kraj",
    "woe:placetype":"Town",
    "wof:name":"Kornatice",
    "wof:placetype":"locality",
    "wof:population":103
},
  "geometry": {"coordinates":[13.59222,49.65893],"type":"Point"}
}