{
  "type": "Feature",
  "properties": {
    "iso:country":"CZ",
    "name:azb_x_preferred":[
        "\u067e\u0631\u0648\u0634\u0627\u0646\u06a9\u06cc"
    ],
    "name:ceb_x_preferred":[
        "Pru\u0161\u00e1nky"
    ],
    "name:ces_x_preferred":[
        "Pru\u0161\u00e1nky"
    ],
    "name:eus_x_preferred":[
        "Pru\u0161\u00e1nky"
    ],
    "name:fas_x_preferred":[
        "\u067e\u0631\u0648\u0634\u0627\u0646\u06a9\u06cc"
    ],
    "name:fra_x_preferred":[
        "Pru\u0161\u00e1nky"
    ],
    "name:hun_x_preferred":[
        "Pru\u0161\u00e1nky"
    ],
    "name:ita_x_preferred":[
        "Pru\u0161\u00e1nky"
    ],
    "name:msa_x_preferred":[
        "Pru\u0161\u00e1nky"
    ],
    "name:nld_x_preferred":[
        "Pru\u0161\u00e1nky"
    ],
    "name:pol_x_preferred":[
        "Pru\u0161\u00e1nky"
    ],
    "name:por_x_preferred":[
        "Pru\u0161\u00e1nky"
    ],
    "name:slk_x_preferred":[
        "Pru\u0161\u00e1nky"
    ],
    "name:spa_x_preferred":[
        "Pru\u0161\u00e1nky"
    ],
    "name:srp_x_preferred":[
        "\u041f\u0440\u0443\u0448\u0430\u043d\u043a\u0438"
    ],
    "name:swe_x_preferred":[
        "Pru\u0161\u00e1nky"
    ],
    "name:vie_x_preferred":[
        "Pru\u0161\u00e1nky"
    ],
    "qs_pg:aaroncc":"CZ",
    "qs_pg:name":"Pru\u0161\u00e1nky",
    "qs_pg:name_adm0":"\u010cesk\u00e1 republika",
    "qs_pg:name_adm1":"Jihomoravsk\u00fd kraj",
    "qs_pg:photos":1,
    "qs_pg:photos_1k":1,
    "qs_pg:photos_9k":1,
    "qs_pg:photos_9r":1,
    "qs_pg:photos_all":8,
    "qs_pg:photos_sr":1,
    "qs_pg:pop_sr":0,
    "qs_pg:qs_pg_placetype":"localadmin",
    "qs_pg:qs_pg_placetype_gp":"LocalAdmin",
    "qs_pg:woe_adm0":23424810,
    "woe:adm0_id":23424810,
    "woe:name_adm0":"\u010cesk\u00e1 republika",
    "woe:name_adm1":"Jihomoravsk\u00fd kraj",
    "woe:placetype":"LocalAdmin",
    "wof:name":"Pru\u0161\u00e1nky",
    "wof:placetype":"localadmin"
},
  "geometry": {"coordinates":[16.986161,48.826704],"type":"Point"}
}