{
  "type": "Feature",
  "properties": {
    "gn:gn_country":"CZ",
    "gn:gn_fcode":"PPL",
    "gn:gn_pop":172,
    "gn:population":172,
    "iso:country":"CZ",
    "name:azb_x_preferred":[
        "\u0648\u06cc\u062f\u0648\u0646\u06cc\u0646"
    ],
    "name:cat_x_preferred":[
        "Vidon\u00edn"
    ],
    "name:ceb_x_preferred":[
        "Vidon\u00edn"
    ],
    "name:ces_x_preferred":[
        "Vidon\u00edn"
    ],
    "name:deu_x_preferred":[
        "Vidon\u00edn"
    ],
    "name:eng_x_preferred":[
        "Vidon\u00edn"
    ],
    "name:eus_x_preferred":[
        "Vidon\u00edn"
    ],
    "name:fas_x_preferred":[
        "\u0648\u06cc\u062f\u0648\u0646\u06cc\u0646"
    ],
    "name:fra_x_preferred":[
        "Vidon\u00edn"
    ],
    "name:hun_x_preferred":[
        "Vidon\u00edn"
    ],
    "name:ita_x_preferred":[
        "Vidon\u00edn"
    ],
    "name:msa_x_preferred":[
        "Vidon\u00edn"
    ],
    "name:nan_x_preferred":[
        "Vidon\u00edn"
    ],
    "name:nld_x_preferred":[
        "Vidon\u00edn"
    ],
    "name:oci_x_preferred":[
        "Vidon\u00edn"
    ],
    "name:por_x_preferred":[
        "Vidon\u00edn"
    ],
    "name:rup_x_preferred":[
        "Vidon\u00edn"
    ],
    "name:slk_x_preferred":[
        "Vidon\u00edn"
    ],
    "name:spa_x_preferred":[
        "Vidon\u00edn"
    ],
    "name:swe_x_preferred":[
        "Vidon\u00edn"
    ],
    "name:vie_x_preferred":[
        "Vidon\u00edn"
    ],
    "qs_pg:aaroncc":"CZ",
    "qs_pg:gn_country":"CZ",
    "qs_pg:gn_fcode":"PPL",
    "qs_pg:gn_pop":172,
    "qs_pg:name":"Vidon\u00edn",
    "qs_pg:name_adm0":"\u010cesk\u00e1 republika",
    "qs_pg:name_adm1":"Kraj Vyso\u010dina",
    "qs_pg:photos_9r":0,
    "qs_pg:photos_sr":0,
    "qs_pg:pop_sr":1,
    "qs_pg:qs_pg_placetype":"locality",
    "qs_pg:qs_pg_placetype_gp":"Town",
    "qs_pg:woe_adm0":23424810,
    "woe:adm0_id":23424810,
    "woe:name_adm0":"\u010cesk\u00e1 republika",
    "woe:name_adm1":"Kraj Vyso\u010dina",
    "woe:placetype":"Town",
    "wof:name":"Vidon\u00edn",
    "wof:placetype":"locality",
    "wof:population":172
},
  "geometry": {"coordinates":[16.22244,49.37974],"type":"Point"}
}