{
  "type": "Feature",
  "properties": {
    "gn:country":"CZ",
    "gn:fcode":"PPL",
    "gn:population":571,
    "iso:country":"CZ",
    "name:azb_x_preferred":[
        "\u0628\u0631\u0627\u062a\u0631\u0648\u0634\u0648\u0648"
    ],
    "name:ceb_x_preferred":[
        "Bratru\u0161ov"
    ],
    "name:ces_x_preferred":[
        "Bratru\u0161ov"
    ],
    "name:deu_x_preferred":[
        "Bratru\u0161ov"
    ],
    "name:eng_x_preferred":[
        "Bratru\u0161ov"
    ],
    "name:eus_x_preferred":[
        "Bratru\u0161ov"
    ],
    "name:fas_x_preferred":[
        "\u0628\u0631\u0627\u062a\u0631\u0648\u0634\u0648\u0648"
    ],
    "name:fra_x_preferred":[
        "Bratru\u0161ov"
    ],
    "name:hun_x_preferred":[
        "Bratru\u0161ov"
    ],
    "name:ita_x_preferred":[
        "Bratru\u0161ov"
    ],
    "name:msa_x_preferred":[
        "Bratru\u0161ov"
    ],
    "name:nan_x_preferred":[
        "Bratru\u0161ov"
    ],
    "name:nld_x_preferred":[
        "Bratru\u0161ov"
    ],
    "name:pol_x_preferred":[
        "Bratru\u0161ov"
    ],
    "name:por_x_preferred":[
        "Bratru\u0161ov"
    ],
    "name:rup_x_preferred":[
        "Bratru\u0161ov"
    ],
    "name:slk_x_preferred":[
        "Bratru\u0161ov"
    ],
    "name:spa_x_preferred":[
        "Bratru\u0161ov"
    ],
    "name:srp_x_preferred":[
        "\u0411\u0440\u0430\u0442\u0440\u0443\u0448\u043e\u0432"
    ],
    "name:swe_x_preferred":[
        "Bratru\u0161ov"
    ],
    "name:und_x_variant":[
        "Brattersdorf"
    ],
    "name:vie_x_preferred":[
        "Bratru\u0161ov"
    ],
    "qs_pg:aaroncc":"CZ",
    "qs_pg:gn_country":"CZ",
    "qs_pg:gn_fcode":"PPL",
    "qs_pg:gn_pop":571,
    "qs_pg:name":"Bratru\u0161ov",
    "qs_pg:name_adm0":"\u010cesk\u00e1 republika",
    "qs_pg:name_adm1":"Olomouck\u00fd kraj",
    "qs_pg:photos_9r":0,
    "qs_pg:photos_sr":0,
    "qs_pg:pop_sr":2,
    "qs_pg:qs_pg_placetype":"locality",
    "qs_pg:qs_pg_placetype_gp":"Town",
    "qs_pg:woe_adm0":23424810,
    "woe:adm0_id":23424810,
    "woe:name_adm0":"\u010cesk\u00e1 republika",
    "woe:name_adm1":"Olomouck\u00fd kraj",
    "woe:placetype":"Town",
    "wof:name":"Bratru\u0161ov",
    "wof:placetype":"locality",
    "wof:population":571
},
  "geometry": {"coordinates":[16.94962,50.00935],"type":"Point"}
}