{
  "type": "Feature",
  "properties": {
    "gn:country":"CZ",
    "gn:fcode":"PPL",
    "gn:population":1114,
    "iso:country":"CZ",
    "name:bel_x_preferred":[
        "\u041c\u0456\u0440\u0430\u0446\u0456\u0446\u044b"
    ],
    "name:ceb_x_preferred":[
        "Mirotice"
    ],
    "name:ces_x_preferred":[
        "Mirotice"
    ],
    "name:deu_x_preferred":[
        "Mirotitz"
    ],
    "name:deu_x_variant":[
        "Mirotice"
    ],
    "name:eng_x_preferred":[
        "Mirotice"
    ],
    "name:epo_x_preferred":[
        "Mirotice"
    ],
    "name:eus_x_preferred":[
        "Mirotice"
    ],
    "name:fas_x_preferred":[
        "\u0645\u06cc\u0631\u0648\u062a\u06cc\u062a\u0633\u0647"
    ],
    "name:fra_x_preferred":[
        "Mirotice"
    ],
    "name:hun_x_preferred":[
        "Mirotice"
    ],
    "name:hye_x_preferred":[
        "\u0544\u056b\u0580\u0578\u057f\u056b\u0581\u0565"
    ],
    "name:ita_x_preferred":[
        "Mirotice"
    ],
    "name:msa_x_preferred":[
        "Mirotice"
    ],
    "name:nan_x_preferred":[
        "Mirotice"
    ],
    "name:nld_x_preferred":[
        "Mirotice"
    ],
    "name:pol_x_preferred":[
        "Mirotice"
    ],
    "name:por_x_preferred":[
        "Mirotice"
    ],
    "name:rup_x_preferred":[
        "Mirotice"
    ],
    "name:rus_x_preferred":[
        "\u041c\u0438\u0440\u043e\u0442\u0438\u0446\u0435"
    ],
    "name:slk_x_preferred":[
        "Mirotice"
    ],
    "name:slv_x_preferred":[
        "Mirotice"
    ],
    "name:spa_x_preferred":[
        "Mirotice"
    ],
    "name:srp_x_preferred":[
        "\u041c\u0438\u0440\u043e\u0442\u0438\u0446\u0435"
    ],
    "name:swe_x_preferred":[
        "Mirotice"
    ],
    "name:tat_x_preferred":[
        "\u041c\u0438\u0440\u043e\u0442\u0438\u0442\u0441\u0435"
    ],
    "name:vie_x_preferred":[
        "Mirotice"
    ],
    "name:zho_x_preferred":[
        "\u7c73\u7f85\u5b63\u91c7"
    ],
    "qs_pg:aaroncc":"CZ",
    "qs_pg:gn_country":"CZ",
    "qs_pg:gn_fcode":"PPL",
    "qs_pg:gn_pop":1114,
    "qs_pg:name":"Mirotice",
    "qs_pg:name_adm0":"\u010cesk\u00e1 republika",
    "qs_pg:name_adm1":"Jiho\u010desk\u00fd kraj",
    "qs_pg:photos_9k":1,
    "qs_pg:photos_9r":4,
    "qs_pg:photos_all":176,
    "qs_pg:photos_sr":0,
    "qs_pg:pop_sr":3,
    "qs_pg:qs_pg_placetype":"locality",
    "qs_pg:qs_pg_placetype_gp":"Town",
    "qs_pg:woe_adm0":23424810,
    "woe:adm0_id":23424810,
    "woe:name_adm0":"\u010cesk\u00e1 republika",
    "woe:name_adm1":"Jiho\u010desk\u00fd kraj",
    "woe:placetype":"Town",
    "wof:name":"Mirotice",
    "wof:placetype":"locality",
    "wof:population":1114
},
  "geometry": {"coordinates":[14.03697,49.42908],"type":"Point"}
}