{
  "type": "Feature",
  "properties": {
    "gn:admin1_code":"81.0",
    "gn:admin2_code":"0412",
    "gn:asciiname":"Nezichov",
    "gn:country_code":"CZ",
    "gn:dem":660,
    "gn:feature_class":"P",
    "gn:feature_code":"PPL",
    "gn:name":"Ne\u017eichov",
    "gn:population":0,
    "gn:timezone":"Europe/Prague",
    "iso:country":"CZ",
    "name:und_x_variant":[
        "Neschikau",
        "Ne\u017eichov"
    ],
    "wof:name":"Nezichov",
    "wof:placetype":"locality"
},
  "geometry": {"coordinates":[13.01697,50.00973],"type":"Point"}
}