{
  "type": "Feature",
  "properties": {
    "gn:admin1_code":"89",
    "gn:admin2_code":"0423",
    "gn:asciiname":"Vetla",
    "gn:country_code":"CZ",
    "gn:dem":186,
    "gn:feature_class":"P",
    "gn:feature_code":"PPL",
    "gn:name":"Vetl\u00e1",
    "gn:population":0,
    "gn:timezone":"Europe/Prague",
    "iso:country":"CZ",
    "name:est_x_preferred":[
        "Vetla"
    ],
    "name:fra_x_preferred":[
        "Vetla"
    ],
    "name:hye_x_preferred":[
        "\u054e\u0565\u057f\u056c\u0561"
    ],
    "name:nld_x_preferred":[
        "Vetla"
    ],
    "name:pol_x_preferred":[
        "Vetla"
    ],
    "name:sco_x_preferred":[
        "Vetla"
    ],
    "name:spa_x_preferred":[
        "Vetla"
    ],
    "name:vol_x_preferred":[
        "Vetla"
    ],
    "wof:name":"Vetla",
    "wof:placetype":"locality"
},
  "geometry": {"coordinates":[14.28909,50.47193],"type":"Point"}
}