{
  "type": "Feature",
  "properties": {
    "gn:admin1_code":"87",
    "gn:admin2_code":"0327",
    "gn:asciiname":"Strachovice",
    "gn:country_code":"CZ",
    "gn:dem":512,
    "gn:feature_class":"P",
    "gn:feature_code":"PPL",
    "gn:name":"Strachovice",
    "gn:population":0,
    "gn:timezone":"Europe/Prague",
    "iso:country":"CZ",
    "wof:name":"Strachovice",
    "wof:placetype":"locality"
},
  "geometry": {"coordinates":[12.81952,49.63435],"type":"Point"}
}