{
  "type": "Feature",
  "properties": {
    "gn:admin1_code":"79.0",
    "gn:admin2_code":"0317",
    "gn:asciiname":"Novy Kostelec",
    "gn:country_code":"CZ",
    "gn:dem":542,
    "gn:feature_class":"P",
    "gn:feature_code":"PPL",
    "gn:name":"Nov\u00fd Kostelec",
    "gn:population":0,
    "gn:timezone":"Europe/Prague",
    "iso:country":"CZ",
    "wof:name":"Novy Kostelec",
    "wof:placetype":"locality"
},
  "geometry": {"coordinates":[14.61005,49.48804000000001],"type":"Point"}
}