{
  "type": "Feature",
  "properties": {
    "gn:admin1_code":"86.0",
    "gn:admin2_code":"0534",
    "gn:asciiname":"Marianska Hora",
    "gn:country_code":"CZ",
    "gn:dem":503,
    "gn:feature_class":"P",
    "gn:feature_code":"PPL",
    "gn:name":"Mariansk\u00e1 Hora",
    "gn:population":0,
    "gn:timezone":"Europe/Prague",
    "iso:country":"CZ",
    "wof:name":"Marianska Hora",
    "wof:placetype":"locality"
},
  "geometry": {"coordinates":[16.58983,49.96044000000001],"type":"Point"}
}