{
  "type": "Feature",
  "properties": {
    "gn:gn_country":"CZ",
    "gn:gn_fcode":"PPL",
    "gn:gn_pop":252,
    "gn:population":252,
    "iso:country":"CZ",
    "name:ces_x_preferred":[
        "Chvalkovice"
    ],
    "name:deu_x_preferred":[
        "Chvalkovice"
    ],
    "name:eng_x_preferred":[
        "Chvalkovice"
    ],
    "name:fas_x_preferred":[
        "\u062e\u0648\u0627\u0644\u06a9\u0648\u0648\u06cc\u062a\u0633\u0647"
    ],
    "name:fra_x_preferred":[
        "Chvalkovice"
    ],
    "name:hun_x_preferred":[
        "Chvalkovice"
    ],
    "name:ita_x_preferred":[
        "Chvalkovice"
    ],
    "name:msa_x_preferred":[
        "Chvalkovice"
    ],
    "name:nan_x_preferred":[
        "Chvalkovice"
    ],
    "name:nld_x_preferred":[
        "Chvalkovice"
    ],
    "name:por_x_preferred":[
        "Chvalkovice"
    ],
    "name:rup_x_preferred":[
        "Chvalkovice"
    ],
    "name:slk_x_preferred":[
        "Chvalkovice"
    ],
    "name:srp_x_preferred":[
        "\u0425\u0432\u0430\u043b\u043a\u043e\u0432\u0438\u0446\u0435"
    ],
    "name:swe_x_preferred":[
        "Chvalkovice"
    ],
    "name:vie_x_preferred":[
        "Chvalkovice"
    ],
    "qs_pg:aaroncc":"CZ",
    "qs_pg:gn_country":"CZ",
    "qs_pg:gn_fcode":"PPL",
    "qs_pg:gn_pop":252,
    "qs_pg:name":"Chvalkovice",
    "qs_pg:photos_9r":0,
    "qs_pg:photos_sr":0,
    "qs_pg:pop_sr":2,
    "qs_pg:qs_pg_placetype":"locality",
    "wof:name":"Chvalkovice",
    "wof:placetype":"locality",
    "wof:population":252
},
  "geometry": {"coordinates":[17.11011,49.18703],"type":"Point"}
}