{
  "type": "Feature",
  "properties": {
    "gn:gn_country":"CZ",
    "gn:gn_fcode":"PPL",
    "gn:gn_pop":135,
    "gn:population":135,
    "iso:country":"CZ",
    "name:ces_x_preferred":[
        "Dra\u017ee\u0148"
    ],
    "name:eng_x_preferred":[
        "Dra\u017ee\u0148"
    ],
    "name:fas_x_preferred":[
        "\u062f\u0631\u0627\u0698\u0646"
    ],
    "name:fra_x_preferred":[
        "Dra\u017ee\u0148"
    ],
    "name:hun_x_preferred":[
        "Dra\u017ee\u0148"
    ],
    "name:ita_x_preferred":[
        "Dra\u017ee\u0148"
    ],
    "name:msa_x_preferred":[
        "Dra\u017ee\u0148"
    ],
    "name:nld_x_preferred":[
        "Dra\u017ee\u0148"
    ],
    "name:por_x_preferred":[
        "Dra\u017ee\u0148"
    ],
    "name:slk_x_preferred":[
        "Dra\u017ee\u0148"
    ],
    "name:srp_x_preferred":[
        "\u0414\u0440\u0430\u0436\u0435\u045a"
    ],
    "name:swe_x_preferred":[
        "Dra\u017ee\u0148"
    ],
    "name:vie_x_preferred":[
        "Dra\u017ee\u0148"
    ],
    "qs_pg:aaroncc":"CZ",
    "qs_pg:gn_country":"CZ",
    "qs_pg:gn_fcode":"PPL",
    "qs_pg:gn_pop":135,
    "qs_pg:name":"Dra\u017ee\u0148",
    "qs_pg:name_adm0":"\u010cesk\u00e1 republika",
    "qs_pg:name_adm1":"Plze\u0148sk\u00fd kraj",
    "qs_pg:photos_9r":0,
    "qs_pg:photos_sr":0,
    "qs_pg:pop_sr":1,
    "qs_pg:qs_pg_placetype":"locality",
    "qs_pg:qs_pg_placetype_gp":"Town",
    "qs_pg:woe_adm0":23424810,
    "woe:adm0_id":23424810,
    "woe:name_adm0":"\u010cesk\u00e1 republika",
    "woe:name_adm1":"Plze\u0148sk\u00fd kraj",
    "woe:placetype":"Town",
    "wof:name":"Dra\u017ee\u0148",
    "wof:placetype":"locality",
    "wof:population":135
},
  "geometry": {"coordinates":[13.28787,49.92684],"type":"Point"}
}