{
  "type": "Feature",
  "properties": {
    "gn:admin1_code":"82.0",
    "gn:admin2_code":"0522",
    "gn:asciiname":"Dobsice",
    "gn:country_code":"CZ",
    "gn:dem":332,
    "gn:feature_class":"P",
    "gn:feature_code":"PPL",
    "gn:name":"Dob\u0161ice",
    "gn:population":0,
    "gn:timezone":"Europe/Prague",
    "iso:country":"CZ",
    "wof:name":"Dobsice",
    "wof:placetype":"locality"
},
  "geometry": {"coordinates":[15.1424,50.50913],"type":"Point"}
}