{
  "type": "Feature",
  "properties": {
    "gn:admin1_code":"87",
    "gn:admin2_code":"0325",
    "gn:asciiname":"Stipoklasy",
    "gn:country_code":"CZ",
    "gn:dem":604,
    "gn:feature_class":"P",
    "gn:feature_code":"PPL",
    "gn:name":"\u0160tipoklasy",
    "gn:population":0,
    "gn:timezone":"Europe/Prague",
    "iso:country":"CZ",
    "name:und_x_variant":[
        "Stipokl",
        "\u0160tipoklasy"
    ],
    "wof:name":"Stipoklasy",
    "wof:placetype":"locality"
},
  "geometry": {"coordinates":[13.09358,49.91432],"type":"Point"}
}