{
  "type": "Feature",
  "properties": {
    "gn:gn_country":"CZ",
    "gn:gn_fcode":"PPL",
    "gn:gn_pop":344,
    "gn:population":344,
    "iso:country":"CZ",
    "name:ces_x_preferred":[
        "Hlohovice"
    ],
    "name:eng_x_preferred":[
        "Hlohovice"
    ],
    "name:fas_x_preferred":[
        "\u0647\u0644\u0648\u0647\u0648\u0648\u06cc\u062a\u0633\u0647"
    ],
    "name:fra_x_preferred":[
        "Hlohovice"
    ],
    "name:hun_x_preferred":[
        "Hlohovice"
    ],
    "name:ita_x_preferred":[
        "Hlohovice"
    ],
    "name:msa_x_preferred":[
        "Hlohovice"
    ],
    "name:nan_x_preferred":[
        "Hlohovice"
    ],
    "name:nld_x_preferred":[
        "Hlohovice"
    ],
    "name:pol_x_preferred":[
        "Hlohovice"
    ],
    "name:por_x_preferred":[
        "Hlohovice"
    ],
    "name:rup_x_preferred":[
        "Hlohovice"
    ],
    "name:slk_x_preferred":[
        "Hlohovice"
    ],
    "name:srp_x_preferred":[
        "\u0425\u043b\u043e\u0445\u043e\u0432\u0438\u0446\u0435"
    ],
    "name:swe_x_preferred":[
        "Hlohovice"
    ],
    "name:vie_x_preferred":[
        "Hlohovice"
    ],
    "qs_pg:aaroncc":"CZ",
    "qs_pg:gn_country":"CZ",
    "qs_pg:gn_fcode":"PPL",
    "qs_pg:gn_pop":344,
    "qs_pg:name":"Hlohovice",
    "qs_pg:name_adm0":"\u010cesk\u00e1 republika",
    "qs_pg:name_adm1":"Plze\u0148sk\u00fd kraj",
    "qs_pg:photos_9r":0,
    "qs_pg:photos_sr":0,
    "qs_pg:pop_sr":2,
    "qs_pg:qs_pg_placetype":"locality",
    "qs_pg:qs_pg_placetype_gp":"Town",
    "qs_pg:woe_adm0":23424810,
    "woe:adm0_id":23424810,
    "woe:name_adm0":"\u010cesk\u00e1 republika",
    "woe:name_adm1":"Plze\u0148sk\u00fd kraj",
    "woe:placetype":"Town",
    "wof:name":"Hlohovice",
    "wof:placetype":"locality",
    "wof:population":344
},
  "geometry": {"coordinates":[13.64334,49.88947],"type":"Point"}
}