{
  "type": "Feature",
  "properties": {
    "gn:gn_country":"CZ",
    "gn:gn_fcode":"PPL",
    "gn:gn_pop":138,
    "gn:population":138,
    "iso:country":"CZ",
    "name:ceb_x_preferred":[
        "Mal\u00e9 V\u00fdkleky"
    ],
    "name:ces_x_preferred":[
        "Mal\u00e9 V\u00fdkleky"
    ],
    "name:deu_x_preferred":[
        "Mal\u00e9 V\u00fdkleky"
    ],
    "name:eng_x_preferred":[
        "Mal\u00e9 V\u00fdkleky"
    ],
    "name:epo_x_preferred":[
        "Mal\u00e9 V\u00fdkleky"
    ],
    "name:eus_x_preferred":[
        "Mal\u00e9 V\u00fdkleky"
    ],
    "name:fra_x_preferred":[
        "Mal\u00e9 V\u00fdkleky"
    ],
    "name:hun_x_preferred":[
        "Mal\u00e9 V\u00fdkleky"
    ],
    "name:ita_x_preferred":[
        "Mal\u00e9 V\u00fdkleky"
    ],
    "name:msa_x_preferred":[
        "Mal\u00e9 V\u00fdkleky"
    ],
    "name:nan_x_preferred":[
        "Mal\u00e9 V\u00fdkleky"
    ],
    "name:nld_x_preferred":[
        "Mal\u00e9 V\u00fdkleky"
    ],
    "name:pol_x_preferred":[
        "Mal\u00e9 V\u00fdkleky"
    ],
    "name:por_x_preferred":[
        "Mal\u00e9 V\u00fdkleky"
    ],
    "name:rup_x_preferred":[
        "Mal\u00e9 V\u00fdkleky"
    ],
    "name:slk_x_preferred":[
        "Mal\u00e9 V\u00fdkleky"
    ],
    "name:spa_x_preferred":[
        "Mal\u00e9 V\u00fdkleky"
    ],
    "name:srp_x_preferred":[
        "\u041c\u0430\u043b\u0435 \u0412\u0438\u043a\u043b\u0435\u043a\u0438"
    ],
    "name:swe_x_preferred":[
        "Mal\u00e9 V\u00fdkleky"
    ],
    "name:vie_x_preferred":[
        "Mal\u00e9 V\u00fdkleky"
    ],
    "qs_pg:aaroncc":"CZ",
    "qs_pg:gn_country":"CZ",
    "qs_pg:gn_fcode":"PPL",
    "qs_pg:gn_pop":138,
    "qs_pg:name":"Mal\u00e9 V\u00fdkleky",
    "qs_pg:name_adm0":"\u010cesk\u00e1 republika",
    "qs_pg:name_adm1":"Pardubick\u00fd kraj",
    "qs_pg:photos_9r":0,
    "qs_pg:photos_sr":0,
    "qs_pg:pop_sr":1,
    "qs_pg:qs_pg_placetype":"locality",
    "qs_pg:qs_pg_placetype_gp":"Town",
    "qs_pg:woe_adm0":23424810,
    "woe:adm0_id":23424810,
    "woe:name_adm0":"\u010cesk\u00e1 republika",
    "woe:name_adm1":"Pardubick\u00fd kraj",
    "woe:placetype":"Town",
    "wof:name":"Mal\u00e9 V\u00fdkleky",
    "wof:placetype":"locality",
    "wof:population":138
},
  "geometry": {"coordinates":[15.53851,50.11934],"type":"Point"}
}