{
  "type": "Feature",
  "properties": {
    "gn:admin1_code":"82.0",
    "gn:admin2_code":"0523",
    "gn:asciiname":"Roztoky",
    "gn:country_code":"CZ",
    "gn:dem":270,
    "gn:feature_class":"P",
    "gn:feature_code":"PPL",
    "gn:name":"Roztoky",
    "gn:population":0,
    "gn:timezone":"Europe/Prague",
    "iso:country":"CZ",
    "name:ces_x_preferred":[
        "Roztoky"
    ],
    "name:eus_x_preferred":[
        "Roztoky"
    ],
    "name:fas_x_preferred":[
        "\u0631\u0648\u0632\u062a\u0648\u06a9\u06cc"
    ],
    "name:hun_x_preferred":[
        "Roztoky"
    ],
    "name:ita_x_preferred":[
        "Roztoky"
    ],
    "name:msa_x_preferred":[
        "Roztoky"
    ],
    "name:nld_x_preferred":[
        "Roztoky"
    ],
    "name:pol_x_preferred":[
        "Roztoky"
    ],
    "name:por_x_preferred":[
        "Roztoky"
    ],
    "name:rus_x_preferred":[
        "\u0420\u043e\u0437\u0442\u043e\u043a\u0438"
    ],
    "name:slk_x_preferred":[
        "Roztoky"
    ],
    "name:spa_x_preferred":[
        "Roztoky"
    ],
    "name:srp_x_preferred":[
        "\u0420\u043e\u0441\u0442\u043e\u043a\u0438"
    ],
    "name:vie_x_preferred":[
        "Roztoky"
    ],
    "name:zho_x_preferred":[
        "\u7f85\u8332\u6258\u57fa"
    ],
    "wof:name":"Roztoky",
    "wof:placetype":"locality"
},
  "geometry": {"coordinates":[16.03804,50.33696],"type":"Point"}
}