{
  "type": "Feature",
  "properties": {
    "gn:admin1_code":"82.0",
    "gn:admin2_code":"0523",
    "gn:asciiname":"Roztoky",
    "gn:country_code":"CZ",
    "gn:dem":270,
    "gn:feature_class":"P",
    "gn:feature_code":"PPL",
    "gn:name":"Roztoky",
    "gn:population":0,
    "gn:timezone":"Europe/Prague",
    "iso:country":"CZ",
    "wof:name":"Roztoky",
    "wof:placetype":"locality"
},
  "geometry": {"coordinates":[16.03804,50.33696],"type":"Point"}
}