{
  "type": "Feature",
  "properties": {
    "gn:gn_country":"CZ",
    "gn:gn_fcode":"PPL",
    "gn:gn_pop":468,
    "gn:population":468,
    "iso:country":"CZ",
    "name:bul_x_preferred":[
        "\u0421\u0443\u0447\u043e\u043c\u0430\u0441\u0442\u0439"
    ],
    "name:cze_x_preferred":[
        "Suchomasty"
    ],
    "name:dut_x_preferred":[
        "Suchomasty"
    ],
    "name:eng_x_preferred":[
        "Suchomasty"
    ],
    "name:fre_x_preferred":[
        "Suchomasty"
    ],
    "name:hun_x_preferred":[
        "Suchomasty"
    ],
    "name:ita_x_preferred":[
        "Suchomasty"
    ],
    "name:may_x_preferred":[
        "Suchomasty"
    ],
    "name:per_x_preferred":[
        "\u0633\u0648\u062e\u0648\u0645\u0627\u0633\u062a\u06cc"
    ],
    "name:pol_x_preferred":[
        "Suchomasty"
    ],
    "name:por_x_preferred":[
        "Suchomasty"
    ],
    "name:slo_x_preferred":[
        "Suchomasty"
    ],
    "name:srp_x_preferred":[
        "\u0421\u0443\u0445\u043e\u043c\u0430\u0441\u0442\u0438"
    ],
    "name:swe_x_preferred":[
        "Suchomasty"
    ],
    "name:vie_x_preferred":[
        "Suchomasty"
    ],
    "qs_pg:aaroncc":"CZ",
    "qs_pg:gn_country":"CZ",
    "qs_pg:gn_fcode":"PPL",
    "qs_pg:gn_pop":468,
    "qs_pg:name":"Suchomasty",
    "qs_pg:name_adm0":"\u010cesk\u00e1 republika",
    "qs_pg:name_adm1":"St\u0159edo\u010desk\u00fd kraj",
    "qs_pg:photos_9r":0,
    "qs_pg:photos_sr":0,
    "qs_pg:pop_sr":2,
    "qs_pg:qs_pg_placetype":"locality",
    "qs_pg:qs_pg_placetype_gp":"Town",
    "qs_pg:woe_adm0":23424810,
    "woe:adm0_id":23424810,
    "woe:name_adm0":"\u010cesk\u00e1 republika",
    "woe:name_adm1":"St\u0159edo\u010desk\u00fd kraj",
    "woe:placetype":"Town",
    "wof:name":"Suchomasty",
    "wof:placetype":"locality",
    "wof:population":468
},
  "geometry": {"coordinates":[14.05661,49.89535],"type":"Point"}
}