{
  "type": "Feature",
  "properties": {
    "gn:gn_country":"CZ",
    "gn:gn_fcode":"PPL",
    "gn:gn_pop":25,
    "gn:population":25,
    "iso:country":"CZ",
    "name:ces_x_preferred":[
        "Ku\u0159imany"
    ],
    "name:deu_x_preferred":[
        "Ku\u0159imany"
    ],
    "name:eng_x_preferred":[
        "Ku\u0159imany"
    ],
    "name:fas_x_preferred":[
        "\u06a9\u0648\u0631\u06cc\u0645\u0627\u0646\u06cc"
    ],
    "name:fra_x_preferred":[
        "Ku\u0159imany"
    ],
    "name:hun_x_preferred":[
        "Ku\u0159imany"
    ],
    "name:ita_x_preferred":[
        "Ku\u0159imany"
    ],
    "name:msa_x_preferred":[
        "Ku\u0159imany"
    ],
    "name:nld_x_preferred":[
        "Ku\u0159imany"
    ],
    "name:por_x_preferred":[
        "Ku\u0159imany"
    ],
    "name:rup_x_preferred":[
        "Ku\u0159imany"
    ],
    "name:slk_x_preferred":[
        "Ku\u0159imany"
    ],
    "name:srp_x_preferred":[
        "\u041a\u0443\u0440\u0436\u0438\u043c\u0430\u043d\u0438"
    ],
    "name:vie_x_preferred":[
        "Ku\u0159imany"
    ],
    "qs_pg:aaroncc":"CZ",
    "qs_pg:gn_country":"CZ",
    "qs_pg:gn_fcode":"PPL",
    "qs_pg:gn_pop":25,
    "qs_pg:name":"Ku\u0159imany",
    "qs_pg:name_adm0":"\u010cesk\u00e1 republika",
    "qs_pg:name_adm1":"Jiho\u010desk\u00fd kraj",
    "qs_pg:photos_9r":0,
    "qs_pg:photos_sr":0,
    "qs_pg:pop_sr":1,
    "qs_pg:qs_pg_placetype":"locality",
    "qs_pg:qs_pg_placetype_gp":"Town",
    "qs_pg:woe_adm0":23424810,
    "woe:adm0_id":23424810,
    "woe:name_adm0":"\u010cesk\u00e1 republika",
    "woe:name_adm1":"Jiho\u010desk\u00fd kraj",
    "woe:placetype":"Town",
    "wof:name":"Ku\u0159imany",
    "wof:placetype":"locality",
    "wof:population":25
},
  "geometry": {"coordinates":[13.96813,49.2039],"type":"Point"}
}