{
  "type": "Feature",
  "properties": {
    "gn:admin1_code":"86.0",
    "gn:admin2_code":"0531",
    "gn:asciiname":"Hnevetice",
    "gn:country_code":"CZ",
    "gn:dem":447,
    "gn:feature_class":"P",
    "gn:feature_code":"PPL",
    "gn:name":"Hn\u011bv\u011btice",
    "gn:population":0,
    "gn:timezone":"Europe/Prague",
    "iso:country":"CZ",
    "wof:name":"Hnevetice",
    "wof:placetype":"locality"
},
  "geometry": {"coordinates":[16.05275,49.83289],"type":"Point"}
}