{
  "type": "Feature",
  "properties": {
    "gn:country":"CZ",
    "gn:fcode":"PPL",
    "gn:population":48,
    "iso:country":"CZ",
    "name:azb_x_preferred":[
        "\u0627\u0648\u0633\u0648\u0648\u0647"
    ],
    "name:cat_x_preferred":[
        "Osov\u00e9"
    ],
    "name:ces_x_preferred":[
        "Osov\u00e9"
    ],
    "name:che_x_preferred":[
        "\u041e\u0441\u043e\u0432\u0435"
    ],
    "name:deu_x_preferred":[
        "Osov\u00e9"
    ],
    "name:eng_x_preferred":[
        "Osov\u00e9"
    ],
    "name:epo_x_preferred":[
        "Osov\u00e9"
    ],
    "name:eus_x_preferred":[
        "Osov\u00e9"
    ],
    "name:fas_x_preferred":[
        "\u0627\u0648\u0633\u0648\u0648\u0647"
    ],
    "name:fra_x_preferred":[
        "Osov\u00e9"
    ],
    "name:gle_x_preferred":[
        "Osov\u00e9"
    ],
    "name:hun_x_preferred":[
        "Osov\u00e9"
    ],
    "name:ita_x_preferred":[
        "Osov\u00e9"
    ],
    "name:lmo_x_preferred":[
        "Osov\u00e9"
    ],
    "name:msa_x_preferred":[
        "Osov\u00e9"
    ],
    "name:nan_x_preferred":[
        "Osov\u00e9"
    ],
    "name:nld_x_preferred":[
        "Osov\u00e9"
    ],
    "name:pol_x_preferred":[
        "Osov\u00e9"
    ],
    "name:por_x_preferred":[
        "Osov\u00e9"
    ],
    "name:slk_x_preferred":[
        "Osov\u00e9"
    ],
    "name:spa_x_preferred":[
        "Osov\u00e9"
    ],
    "name:tat_x_preferred":[
        "\u041e\u0441\u043e\u0432\u0435"
    ],
    "name:vie_x_preferred":[
        "Osov\u00e9"
    ],
    "qs_pg:aaroncc":"CZ",
    "qs_pg:gn_country":"CZ",
    "qs_pg:gn_fcode":"PPL",
    "qs_pg:gn_pop":48,
    "qs_pg:name":"Osov\u00e9",
    "qs_pg:name_adm0":"\u010cesk\u00e1 republika",
    "qs_pg:name_adm1":"Kraj Vyso\u010dina",
    "qs_pg:photos_9r":0,
    "qs_pg:photos_sr":0,
    "qs_pg:pop_sr":1,
    "qs_pg:qs_pg_placetype":"locality",
    "qs_pg:qs_pg_placetype_gp":"Town",
    "qs_pg:woe_adm0":23424810,
    "woe:adm0_id":23424810,
    "woe:name_adm0":"\u010cesk\u00e1 republika",
    "woe:name_adm1":"Kraj Vyso\u010dina",
    "woe:placetype":"Town",
    "wof:name":"Osov\u00e9",
    "wof:placetype":"locality",
    "wof:population":48
},
  "geometry": {"coordinates":[16.01542,49.32522],"type":"Point"}
}