{
  "type": "Feature",
  "properties": {
    "gn:admin1_code":"79.0",
    "gn:admin2_code":"0312",
    "gn:asciiname":"Drochov",
    "gn:country_code":"CZ",
    "gn:dem":639,
    "gn:feature_class":"P",
    "gn:feature_code":"PPL",
    "gn:name":"Drochov",
    "gn:population":0,
    "gn:timezone":"Europe/Prague",
    "iso:country":"CZ",
    "name:und_x_variant":[
        "Droschersdorf",
        "Drochov"
    ],
    "wof:name":"Drochov",
    "wof:placetype":"locality"
},
  "geometry": {"coordinates":[14.49361,48.69803],"type":"Point"}
}