{
  "type": "Feature",
  "properties": {
    "gn:admin1_code":"89.0",
    "gn:admin2_code":"0424",
    "gn:asciiname":"Kruzin",
    "gn:country_code":"CZ",
    "gn:dem":375,
    "gn:feature_class":"P",
    "gn:feature_code":"PPL",
    "gn:name":"Kru\u017e\u00edn",
    "gn:population":0,
    "gn:timezone":"Europe/Prague",
    "iso:country":"CZ",
    "wof:name":"Kruzin",
    "wof:placetype":"locality"
},
  "geometry": {"coordinates":[13.33808,50.19858],"type":"Point"}
}