{
  "type": "Feature",
  "properties": {
    "gn:admin1_code":"80.0",
    "gn:admin2_code":"0614",
    "gn:asciiname":"Ostry",
    "gn:country_code":"CZ",
    "gn:dem":502,
    "gn:feature_class":"P",
    "gn:feature_code":"PPL",
    "gn:name":"Ostr\u00fd",
    "gn:population":0,
    "gn:timezone":"Europe/Prague",
    "iso:country":"CZ",
    "name:fas_x_preferred":[
        "\u0627\u0648\u0633\u062a\u0631\u06cc"
    ],
    "name:fra_x_preferred":[
        "Ostry"
    ],
    "name:nno_x_preferred":[
        "Ostryj"
    ],
    "name:rus_x_preferred":[
        "\u041e\u0441\u0442\u0440\u0430\u044f"
    ],
    "name:slk_x_preferred":[
        "Ostryj"
    ],
    "name:und_x_variant":[
        "Dv\u016dr Ostr\u00fd",
        "Ostr\u00fd"
    ],
    "name:zho_x_preferred":[
        "\u5967\u65af\u7279\u62c9\u4e9e\u706b\u5c71"
    ],
    "wof:name":"Ostry",
    "wof:placetype":"locality"
},
  "geometry": {"coordinates":[15.95178,49.12022],"type":"Point"}
}