{
  "type": "Feature",
  "properties": {
    "gn:admin1_code":"80.0",
    "gn:admin2_code":"0614",
    "gn:asciiname":"Ostry",
    "gn:country_code":"CZ",
    "gn:dem":502,
    "gn:feature_class":"P",
    "gn:feature_code":"PPL",
    "gn:name":"Ostr\u00fd",
    "gn:population":0,
    "gn:timezone":"Europe/Prague",
    "iso:country":"CZ",
    "name:und_x_variant":[
        "Dv\u016dr Ostr\u00fd",
        "Ostr\u00fd"
    ],
    "wof:name":"Ostry",
    "wof:placetype":"locality"
},
  "geometry": {"coordinates":[15.95178,49.12022],"type":"Point"}
}