{
  "type": "Feature",
  "properties": {
    "gn:admin1_code":"87.0",
    "gn:admin2_code":"0323",
    "gn:asciiname":"Chrast",
    "gn:country_code":"CZ",
    "gn:dem":340,
    "gn:feature_class":"P",
    "gn:feature_code":"PPL",
    "gn:name":"Chr\u00e1st",
    "gn:population":1700,
    "gn:timezone":"Europe/Prague",
    "iso:country":"CZ",
    "name:azb_x_preferred":[
        "\u062e\u0631\u0627\u0633\u062a"
    ],
    "name:ceb_x_preferred":[
        "Chr\u00e1st"
    ],
    "name:ces_x_preferred":[
        "Chr\u00e1st"
    ],
    "name:eus_x_preferred":[
        "Chr\u00e1st"
    ],
    "name:fas_x_preferred":[
        "\u062e\u0631\u0627\u0633\u062a"
    ],
    "name:hun_x_preferred":[
        "Chr\u00e1st"
    ],
    "name:ita_x_preferred":[
        "Chr\u00e1st"
    ],
    "name:msa_x_preferred":[
        "Chr\u00e1st"
    ],
    "name:nld_x_preferred":[
        "Chr\u00e1st"
    ],
    "name:por_x_preferred":[
        "Chr\u00e1st"
    ],
    "name:slk_x_preferred":[
        "Chr\u00e1st"
    ],
    "name:spa_x_preferred":[
        "Chr\u00e1st"
    ],
    "name:srp_x_preferred":[
        "\u0425\u0440\u0430\u0441\u0442"
    ],
    "name:vie_x_preferred":[
        "Chr\u00e1st"
    ],
    "wof:name":"Chrast",
    "wof:placetype":"locality",
    "wof:population":1700
},
  "geometry": {"coordinates":[13.49358,49.7932],"type":"Point"}
}