{
  "type": "Feature",
  "properties": {
    "gn:admin1_code":"87.0",
    "gn:admin2_code":"0323",
    "gn:asciiname":"Chrast",
    "gn:country_code":"CZ",
    "gn:dem":340,
    "gn:feature_class":"P",
    "gn:feature_code":"PPL",
    "gn:name":"Chr\u00e1st",
    "gn:population":1700,
    "gn:timezone":"Europe/Prague",
    "iso:country":"CZ",
    "wof:name":"Chrast",
    "wof:placetype":"locality",
    "wof:population":1700
},
  "geometry": {"coordinates":[13.49358,49.7932],"type":"Point"}
}