{
  "type": "Feature",
  "properties": {
    "gn:admin1_code":"90",
    "gn:admin2_code":"0724",
    "gn:asciiname":"Vlachovice",
    "gn:country_code":"CZ",
    "gn:dem":345,
    "gn:feature_class":"P",
    "gn:feature_code":"PPL",
    "gn:name":"Vlachovice",
    "gn:population":1532,
    "gn:timezone":"Europe/Prague",
    "iso:country":"CZ",
    "name:und_x_variant":[
        "Vlahovice",
        "Wlachowitz"
    ],
    "wof:name":"Vlachovice",
    "wof:placetype":"locality",
    "wof:population":1532
},
  "geometry": {"coordinates":[17.94001,49.12377],"type":"Point"}
}