{
  "type": "Feature",
  "properties": {
    "gn:admin1_code":"90",
    "gn:admin2_code":"0724",
    "gn:asciiname":"Vlachovice",
    "gn:country_code":"CZ",
    "gn:dem":345,
    "gn:feature_class":"P",
    "gn:feature_code":"PPL",
    "gn:name":"Vlachovice",
    "gn:population":1532,
    "gn:timezone":"Europe/Prague",
    "iso:country":"CZ",
    "name:azb_x_preferred":[
        "\u0648\u0644\u0627\u062e\u0648\u0648\u06cc\u062a\u0633\u0647"
    ],
    "name:ceb_x_preferred":[
        "Vlachovice"
    ],
    "name:ces_x_preferred":[
        "Vlachovice"
    ],
    "name:deu_x_preferred":[
        "Vlachovice"
    ],
    "name:eus_x_preferred":[
        "Vlachovice"
    ],
    "name:fas_x_preferred":[
        "\u0648\u0644\u0627\u062e\u0648\u0648\u06cc\u062a\u0633\u0647"
    ],
    "name:hun_x_preferred":[
        "Vlachovice"
    ],
    "name:ita_x_preferred":[
        "Vlachovice"
    ],
    "name:msa_x_preferred":[
        "Vlachovice"
    ],
    "name:nld_x_preferred":[
        "Vlachovice"
    ],
    "name:pol_x_preferred":[
        "Vlachovice"
    ],
    "name:por_x_preferred":[
        "Vlachovice"
    ],
    "name:slk_x_preferred":[
        "Vlachovice"
    ],
    "name:spa_x_preferred":[
        "Vlachovice"
    ],
    "name:srp_x_preferred":[
        "\u0412\u043b\u0430\u0445\u043e\u0432\u0438\u0446\u0435"
    ],
    "name:und_x_variant":[
        "Vlahovice",
        "Wlachowitz"
    ],
    "name:vie_x_preferred":[
        "Vlachovice"
    ],
    "wof:name":"Vlachovice",
    "wof:placetype":"locality",
    "wof:population":1532
},
  "geometry": {"coordinates":[17.94001,49.12377],"type":"Point"}
}