{
  "type": "Feature",
  "properties": {
    "gn:admin1_code":"85.0",
    "gn:admin2_code":"0802",
    "gn:asciiname":"Slavic",
    "gn:country_code":"CZ",
    "gn:dem":847,
    "gn:feature_class":"P",
    "gn:feature_code":"PPL",
    "gn:name":"Slav\u00ed\u010d",
    "gn:population":0,
    "gn:timezone":"Europe/Prague",
    "iso:country":"CZ",
    "wof:name":"Slavic",
    "wof:placetype":"locality"
},
  "geometry": {"coordinates":[18.61667000000001,49.55],"type":"Point"}
}