{
  "type": "Feature",
  "properties": {
    "gn:admin1_code":"85.0",
    "gn:admin2_code":"0802",
    "gn:asciiname":"Slavic",
    "gn:country_code":"CZ",
    "gn:dem":847,
    "gn:feature_class":"P",
    "gn:feature_code":"PPL",
    "gn:name":"Slav\u00ed\u010d",
    "gn:population":0,
    "gn:timezone":"Europe/Prague",
    "iso:country":"CZ",
    "name:bar_x_preferred":[
        "Slawisch"
    ],
    "name:cat_x_preferred":[
        "Eslau"
    ],
    "name:ceb_x_preferred":[
        "Slavic"
    ],
    "name:dan_x_preferred":[
        "Slavisk"
    ],
    "name:deu_x_preferred":[
        "Slawisch"
    ],
    "name:fra_x_preferred":[
        "Slavon"
    ],
    "name:heb_x_preferred":[
        "\u05e1\u05dc\u05d0\u05d1\u05d9"
    ],
    "name:hun_x_preferred":[
        "Szl\u00e1vok"
    ],
    "name:ita_x_preferred":[
        "Slavo"
    ],
    "name:nld_x_preferred":[
        "Slavisch"
    ],
    "name:nor_x_preferred":[
        "Slavisk"
    ],
    "name:spa_x_preferred":[
        "Eslavo"
    ],
    "name:srp_x_preferred":[
        "\u0421\u043b\u043e\u0432\u0435\u043d\u0441\u043a\u0438"
    ],
    "name:swe_x_preferred":[
        "Slavic"
    ],
    "name:tgl_x_preferred":[
        "Eslabo"
    ],
    "wof:name":"Slavic",
    "wof:placetype":"locality"
},
  "geometry": {"coordinates":[18.61667000000001,49.55],"type":"Point"}
}