{
  "type": "Feature",
  "properties": {
    "gn:admin1_code":"79.0",
    "gn:admin2_code":"0317",
    "gn:asciiname":"Javori",
    "gn:country_code":"CZ",
    "gn:dem":657,
    "gn:feature_class":"P",
    "gn:feature_code":"PPL",
    "gn:name":"Javo\u0159\u00ed",
    "gn:population":0,
    "gn:timezone":"Europe/Prague",
    "iso:country":"CZ",
    "wof:name":"Javori",
    "wof:placetype":"locality"
},
  "geometry": {"coordinates":[14.53139,49.52883],"type":"Point"}
}