{
  "type": "Feature",
  "properties": {
    "gn:gn_country":"CZ",
    "gn:gn_fcode":"PPL",
    "gn:gn_pop":234,
    "gn:population":234,
    "iso:country":"CZ",
    "name:bul_x_preferred":[
        "\u0420\u043e\u043a\u043b\u0435"
    ],
    "name:ces_x_preferred":[
        "Rokle"
    ],
    "name:deu_x_preferred":[
        "Rokle"
    ],
    "name:eng_x_preferred":[
        "Rokle"
    ],
    "name:fas_x_preferred":[
        "\u0631\u0648\u06a9\u0644\u0647"
    ],
    "name:fra_x_preferred":[
        "Rokle"
    ],
    "name:hun_x_preferred":[
        "Rokle"
    ],
    "name:ita_x_preferred":[
        "Rokle"
    ],
    "name:msa_x_preferred":[
        "Rokle"
    ],
    "name:nld_x_preferred":[
        "Rokle"
    ],
    "name:por_x_preferred":[
        "Rokle"
    ],
    "name:slk_x_preferred":[
        "Rokle"
    ],
    "name:srp_x_preferred":[
        "\u0420\u043e\u043a\u043b\u0435"
    ],
    "name:swe_x_preferred":[
        "Rokle"
    ],
    "name:unk_x_variant":[
        "Rachel"
    ],
    "name:vie_x_preferred":[
        "Rokle"
    ],
    "qs_pg:aaroncc":"CZ",
    "qs_pg:gn_country":"CZ",
    "qs_pg:gn_fcode":"PPL",
    "qs_pg:gn_pop":234,
    "qs_pg:name":"Rokle",
    "qs_pg:name_adm0":"\u010cesk\u00e1 republika",
    "qs_pg:name_adm1":"\u00dasteck\u00fd kraj",
    "qs_pg:photos_9r":0,
    "qs_pg:photos_sr":0,
    "qs_pg:pop_sr":2,
    "qs_pg:qs_pg_placetype":"locality",
    "qs_pg:qs_pg_placetype_gp":"Town",
    "qs_pg:woe_adm0":23424810,
    "woe:adm0_id":23424810,
    "woe:name_adm0":"\u010cesk\u00e1 republika",
    "woe:name_adm1":"\u00dasteck\u00fd kraj",
    "woe:placetype":"Town",
    "wof:name":"Rokle",
    "wof:placetype":"locality",
    "wof:population":234
},
  "geometry": {"coordinates":[13.2987,50.35317],"type":"Point"}
}