{
  "type": "Feature",
  "properties": {
    "gn:admin1_code":"87.0",
    "gn:admin2_code":"0327",
    "gn:asciiname":"Leiter",
    "gn:country_code":"CZ",
    "gn:dem":461,
    "gn:feature_class":"P",
    "gn:feature_code":"PPL",
    "gn:name":"Leiter",
    "gn:population":0,
    "gn:timezone":"Europe/Prague",
    "iso:country":"CZ",
    "name:und_x_variant":[
        "\u0158eb\u0159\u00ed"
    ],
    "wof:name":"Leiter",
    "wof:placetype":"locality"
},
  "geometry": {"coordinates":[12.88129,49.76279],"type":"Point"}
}