{
  "type": "Feature",
  "properties": {
    "gn:admin1_code":"79.0",
    "gn:admin2_code":"0315",
    "gn:asciiname":"Cudrovice",
    "gn:country_code":"CZ",
    "gn:dem":832,
    "gn:feature_class":"P",
    "gn:feature_code":"PPL",
    "gn:name":"Cudrovice",
    "gn:population":0,
    "gn:timezone":"Europe/Prague",
    "iso:country":"CZ",
    "name:und_x_variant":[
        "Zuderschlag",
        "Cudrovice"
    ],
    "wof:name":"Cudrovice",
    "wof:placetype":"locality"
},
  "geometry": {"coordinates":[13.91826,48.95189],"type":"Point"}
}