{
  "type": "Feature",
  "properties": {
    "gn:admin1_code":"79",
    "gn:admin2_code":"0317",
    "gn:asciiname":"Zaluzi u Budislave",
    "gn:country_code":"CZ",
    "gn:dem":521,
    "gn:feature_class":"P",
    "gn:feature_code":"PPL",
    "gn:name":"Z\u00e1lu\u017e\u00ed u Budislav\u011b",
    "gn:population":0,
    "gn:timezone":"Europe/Prague",
    "iso:country":"CZ",
    "wof:name":"Zaluzi u Budislave",
    "wof:placetype":"locality"
},
  "geometry": {"coordinates":[14.8539,49.28216],"type":"Point"}
}