{
  "type": "Feature",
  "properties": {
    "gn:gn_country":"CZ",
    "gn:gn_fcode":"PPL",
    "gn:gn_pop":112,
    "gn:population":112,
    "iso:country":"CZ",
    "name:ces_x_preferred":[
        "Klenov\u00e1"
    ],
    "name:deu_x_preferred":[
        "Klenov\u00e1"
    ],
    "name:eng_x_preferred":[
        "Klenov\u00e1"
    ],
    "name:fas_x_preferred":[
        "\u06a9\u0644\u0646\u0648\u0648\u0627"
    ],
    "name:fra_x_preferred":[
        "Klenov\u00e1"
    ],
    "name:hun_x_preferred":[
        "Klenov\u00e1"
    ],
    "name:ita_x_preferred":[
        "Klenov\u00e1"
    ],
    "name:msa_x_preferred":[
        "Klenov\u00e1"
    ],
    "name:nld_x_preferred":[
        "Klenov\u00e1"
    ],
    "name:pol_x_preferred":[
        "Klenov\u00e1"
    ],
    "name:por_x_preferred":[
        "Klenov\u00e1"
    ],
    "name:rup_x_preferred":[
        "Klenov\u00e1"
    ],
    "name:slk_x_preferred":[
        "Klenov\u00e1"
    ],
    "name:srp_x_preferred":[
        "\u041a\u043b\u0435\u043d\u043e\u0432\u0430"
    ],
    "name:swe_x_preferred":[
        "Klenov\u00e1"
    ],
    "name:vie_x_preferred":[
        "Klenov\u00e1"
    ],
    "qs_pg:aaroncc":"CZ",
    "qs_pg:gn_country":"CZ",
    "qs_pg:gn_fcode":"PPL",
    "qs_pg:gn_pop":112,
    "qs_pg:name":"Klenov\u00e1",
    "qs_pg:name_adm0":"\u010cesk\u00e1 republika",
    "qs_pg:name_adm1":"Plze\u0148sk\u00fd kraj",
    "qs_pg:photos_9k":1,
    "qs_pg:photos_9r":4,
    "qs_pg:photos_all":186,
    "qs_pg:photos_sr":0,
    "qs_pg:pop_sr":1,
    "qs_pg:qs_pg_placetype":"locality",
    "qs_pg:qs_pg_placetype_gp":"Town",
    "qs_pg:woe_adm0":23424810,
    "woe:adm0_id":23424810,
    "woe:name_adm0":"\u010cesk\u00e1 republika",
    "woe:name_adm1":"Plze\u0148sk\u00fd kraj",
    "woe:placetype":"Town",
    "wof:name":"Klenov\u00e1",
    "wof:placetype":"locality",
    "wof:population":112
},
  "geometry": {"coordinates":[13.23318,49.33343],"type":"Point"}
}