{
  "type": "Feature",
  "properties": {
    "gn:gn_country":"CZ",
    "gn:gn_fcode":"PPL",
    "gn:gn_pop":0,
    "iso:country":"CZ",
    "name:cze_x_preferred":[
        "Tou\u017e\u00edn"
    ],
    "name:eng_x_preferred":[
        "Tou\u017e\u00edn"
    ],
    "name:fre_x_preferred":[
        "Tou\u017e\u00edn"
    ],
    "name:rus_x_preferred":[
        "\u0422\u0443\u0436\u0438\u043d"
    ],
    "qs_pg:aaroncc":"CZ",
    "qs_pg:gn_country":"CZ",
    "qs_pg:gn_fcode":"PPL",
    "qs_pg:gn_pop":0,
    "qs_pg:name":"Tou\u017e\u00edn",
    "qs_pg:name_adm0":"\u010cesk\u00e1 republika",
    "qs_pg:name_adm1":"Jiho\u010desk\u00fd kraj",
    "qs_pg:photos_9r":0,
    "qs_pg:photos_sr":0,
    "qs_pg:pop_sr":0,
    "qs_pg:qs_pg_placetype":"locality",
    "qs_pg:qs_pg_placetype_gp":"Town",
    "qs_pg:woe_adm0":23424810,
    "woe:adm0_id":23424810,
    "woe:name_adm0":"\u010cesk\u00e1 republika",
    "woe:name_adm1":"Jiho\u010desk\u00fd kraj",
    "woe:placetype":"Town",
    "wof:name":"Tou\u017e\u00edn",
    "wof:placetype":"locality"
},
  "geometry": {"coordinates":[15.41904,49.07416],"type":"Point"}
}