{
  "type": "Feature",
  "properties": {
    "gn:admin1_code":"88",
    "gn:admin2_code":"020B",
    "gn:asciiname":"Stary Rozmital",
    "gn:country_code":"CZ",
    "gn:dem":525,
    "gn:feature_class":"P",
    "gn:feature_code":"PPL",
    "gn:name":"Star\u00fd Ro\u017emit\u00e1l",
    "gn:population":0,
    "gn:timezone":"Europe/Prague",
    "iso:country":"CZ",
    "wof:name":"Stary Rozmital",
    "wof:placetype":"locality"
},
  "geometry": {"coordinates":[13.85229,49.60592000000001],"type":"Point"}
}