{
  "type": "Feature",
  "properties": {
    "gn:admin1_code":"79.0",
    "gn:admin2_code":"0311",
    "gn:asciiname":"Horni Bukovsko",
    "gn:country_code":"CZ",
    "gn:dem":489,
    "gn:feature_class":"P",
    "gn:feature_code":"PPL",
    "gn:name":"Horn\u00ed Bukovsko",
    "gn:population":0,
    "gn:timezone":"Europe/Prague",
    "iso:country":"CZ",
    "wof:name":"Horni Bukovsko",
    "wof:placetype":"locality"
},
  "geometry": {"coordinates":[14.5713,49.18819000000001],"type":"Point"}
}