{
  "type": "Feature",
  "properties": {
    "gn:admin1_code":"85",
    "gn:admin2_code":"0803",
    "gn:asciiname":"Zavada",
    "gn:country_code":"CZ",
    "gn:dem":210,
    "gn:feature_class":"P",
    "gn:feature_code":"PPL",
    "gn:name":"Z\u00e1vada",
    "gn:population":0,
    "gn:timezone":"Europe/Prague",
    "iso:country":"CZ",
    "name:ces_x_preferred":[
        "Z\u00e1vada"
    ],
    "name:epo_x_preferred":[
        "Z\u00e1vada"
    ],
    "name:pol_x_preferred":[
        "Zawada"
    ],
    "name:slk_x_preferred":[
        "Z\u00e1vada"
    ],
    "wof:name":"Zavada",
    "wof:placetype":"locality"
},
  "geometry": {"coordinates":[18.49001,49.89941],"type":"Point"}
}