{
  "type": "Feature",
  "properties": {
    "gn:admin1_code":"87.0",
    "gn:admin2_code":"0321",
    "gn:asciiname":"Cermna",
    "gn:country_code":"CZ",
    "gn:dem":438,
    "gn:feature_class":"P",
    "gn:feature_code":"PPL",
    "gn:name":"\u010cermn\u00e1",
    "gn:population":221,
    "gn:timezone":"Europe/Prague",
    "iso:country":"CZ",
    "wof:name":"Cermna",
    "wof:placetype":"locality",
    "wof:population":221
},
  "geometry": {"coordinates":[13.1166,49.53159],"type":"Point"}
}