{
  "type": "Feature",
  "properties": {
    "gn:gn_country":"CZ",
    "gn:gn_fcode":"PPL",
    "gn:gn_pop":53,
    "gn:population":53,
    "iso:country":"CZ",
    "name:azb_x_preferred":[
        "\u0628\u0631\u0627\u062a\u0631\u0648\u0646\u06cc\u062a\u0633\u0647"
    ],
    "name:ces_x_preferred":[
        "Bratronice"
    ],
    "name:deu_x_preferred":[
        "Bratronice"
    ],
    "name:eng_x_preferred":[
        "Bratronice"
    ],
    "name:eus_x_preferred":[
        "Bratronice"
    ],
    "name:fas_x_preferred":[
        "\u0628\u0631\u0627\u062a\u0631\u0648\u0646\u06cc\u062a\u0633\u0647"
    ],
    "name:fra_x_preferred":[
        "Bratronice"
    ],
    "name:hun_x_preferred":[
        "Bratronice"
    ],
    "name:ita_x_preferred":[
        "Bratronice"
    ],
    "name:msa_x_preferred":[
        "Bratronice"
    ],
    "name:nan_x_preferred":[
        "Bratronice"
    ],
    "name:nld_x_preferred":[
        "Bratronice"
    ],
    "name:por_x_preferred":[
        "Bratronice"
    ],
    "name:rup_x_preferred":[
        "Bratronice"
    ],
    "name:slk_x_preferred":[
        "Bratronice"
    ],
    "name:spa_x_preferred":[
        "Bratronice"
    ],
    "name:srp_x_preferred":[
        "\u0411\u0440\u0430\u0442\u0440\u043e\u045a\u0438\u0446\u0435"
    ],
    "name:vie_x_preferred":[
        "Bratronice"
    ],
    "qs_pg:aaroncc":"CZ",
    "qs_pg:gn_country":"CZ",
    "qs_pg:gn_fcode":"PPL",
    "qs_pg:gn_pop":53,
    "qs_pg:name":"Bratronice",
    "qs_pg:name_adm0":"\u010cesk\u00e1 republika",
    "qs_pg:name_adm1":"Jiho\u010desk\u00fd kraj",
    "qs_pg:photos_9r":0,
    "qs_pg:photos_sr":0,
    "qs_pg:pop_sr":1,
    "qs_pg:qs_pg_placetype":"locality",
    "qs_pg:qs_pg_placetype_gp":"Town",
    "qs_pg:woe_adm0":23424810,
    "woe:adm0_id":23424810,
    "woe:name_adm0":"\u010cesk\u00e1 republika",
    "woe:name_adm1":"Jiho\u010desk\u00fd kraj",
    "woe:placetype":"Town",
    "wof:name":"Bratronice",
    "wof:placetype":"locality",
    "wof:population":53
},
  "geometry": {"coordinates":[13.84235,49.36525],"type":"Point"}
}