{
  "type": "Feature",
  "properties": {
    "gn:admin1_code":"82.0",
    "gn:admin2_code":"0522",
    "gn:asciiname":"Dolni Javori",
    "gn:country_code":"CZ",
    "gn:dem":362,
    "gn:feature_class":"P",
    "gn:feature_code":"PPL",
    "gn:name":"Doln\u00ed Javo\u0159\u00ed",
    "gn:population":0,
    "gn:timezone":"Europe/Prague",
    "iso:country":"CZ",
    "wof:name":"Dolni Javori",
    "wof:placetype":"locality"
},
  "geometry": {"coordinates":[15.58092,50.4625],"type":"Point"}
}