{
  "type": "Feature",
  "properties": {
    "gn:gn_country":"CZ",
    "gn:gn_fcode":"PPL",
    "gn:gn_pop":574,
    "gn:population":574,
    "iso:country":"CZ",
    "name:ces_x_preferred":[
        "Pozd\u011bchov"
    ],
    "name:deu_x_preferred":[
        "Pozd\u011bchov"
    ],
    "name:eng_x_preferred":[
        "Pozd\u011bchov"
    ],
    "name:epo_x_preferred":[
        "Pozd\u011bchov"
    ],
    "name:fas_x_preferred":[
        "\u067e\u0648\u0632\u062f\u06cc\u062e\u0648\u0648"
    ],
    "name:fra_x_preferred":[
        "Pozd\u011bchov"
    ],
    "name:hun_x_preferred":[
        "Pozd\u011bchov"
    ],
    "name:ita_x_preferred":[
        "Pozd\u011bchov"
    ],
    "name:msa_x_preferred":[
        "Pozd\u011bchov"
    ],
    "name:nld_x_preferred":[
        "Pozd\u011bchov"
    ],
    "name:pol_x_preferred":[
        "Pozd\u011bchov"
    ],
    "name:por_x_preferred":[
        "Pozd\u011bchov"
    ],
    "name:rup_x_preferred":[
        "Pozd\u011bchov"
    ],
    "name:slk_x_preferred":[
        "Pozd\u011bchov"
    ],
    "name:srp_x_preferred":[
        "\u041f\u043e\u0437\u0434\u0458\u0435\u0445\u043e\u0432"
    ],
    "name:swe_x_preferred":[
        "Pozd\u011bchov"
    ],
    "name:unk_x_variant":[
        "Pozdiechow"
    ],
    "name:vie_x_preferred":[
        "Pozd\u011bchov"
    ],
    "qs_pg:aaroncc":"CZ",
    "qs_pg:gn_country":"CZ",
    "qs_pg:gn_fcode":"PPL",
    "qs_pg:gn_pop":574,
    "qs_pg:name":"Pozd\u011bchov",
    "qs_pg:name_adm0":"\u010cesk\u00e1 republika",
    "qs_pg:name_adm1":"Zl\u00ednsk\u00fd kraj",
    "qs_pg:photos_9k":1,
    "qs_pg:photos_9r":1,
    "qs_pg:photos_all":1,
    "qs_pg:photos_sr":0,
    "qs_pg:pop_sr":2,
    "qs_pg:qs_pg_placetype":"locality",
    "qs_pg:qs_pg_placetype_gp":"Town",
    "qs_pg:woe_adm0":23424810,
    "woe:adm0_id":23424810,
    "woe:name_adm0":"\u010cesk\u00e1 republika",
    "woe:name_adm1":"Zl\u00ednsk\u00fd kraj",
    "woe:placetype":"Town",
    "wof:name":"Pozd\u011bchov",
    "wof:placetype":"locality",
    "wof:population":574
},
  "geometry": {"coordinates":[17.95543,49.23323],"type":"Point"}
}