{
  "type": "Feature",
  "properties": {
    "gn:country":"CZ",
    "gn:fcode":"PPL",
    "gn:population":42,
    "iso:country":"CZ",
    "name:azb_x_preferred":[
        "\u0632\u0627\u062f\u0646\u06cc \u0633\u062a\u0631\u06cc\u062a\u0698"
    ],
    "name:ces_x_preferred":[
        "Zadn\u00ed St\u0159\u00edte\u017e"
    ],
    "name:deu_x_preferred":[
        "Zadn\u00ed St\u0159\u00edte\u017e"
    ],
    "name:eng_x_preferred":[
        "Zadn\u00ed St\u0159\u00edte\u017e"
    ],
    "name:eus_x_preferred":[
        "Zadn\u00ed St\u0159\u00edte\u017e"
    ],
    "name:fas_x_preferred":[
        "\u0632\u0627\u062f\u0646\u06cc \u0633\u062a\u0631\u06cc\u062a\u0698"
    ],
    "name:fra_x_preferred":[
        "Zadn\u00ed St\u0159\u00edte\u017e"
    ],
    "name:hun_x_preferred":[
        "Zadn\u00ed St\u0159\u00edte\u017e"
    ],
    "name:ita_x_preferred":[
        "Zadn\u00ed St\u0159\u00edte\u017e"
    ],
    "name:msa_x_preferred":[
        "Zadn\u00ed St\u0159\u00edte\u017e"
    ],
    "name:nan_x_preferred":[
        "Zadn\u00ed St\u0159\u00edte\u017e"
    ],
    "name:nld_x_preferred":[
        "Zadn\u00ed St\u0159\u00edte\u017e"
    ],
    "name:pol_x_preferred":[
        "Zadn\u00ed St\u0159\u00edte\u017e"
    ],
    "name:por_x_preferred":[
        "Zadn\u00ed St\u0159\u00edte\u017e"
    ],
    "name:rup_x_preferred":[
        "Zadn\u00ed St\u0159\u00edte\u017e"
    ],
    "name:rus_x_preferred":[
        "\u0417\u0430\u0434\u043d\u0438-\u0421\u0442\u0440\u0448\u0438\u0442\u0435\u0436"
    ],
    "name:slk_x_preferred":[
        "Zadn\u00ed St\u0159\u00edte\u017e"
    ],
    "name:spa_x_preferred":[
        "Zadn\u00ed St\u0159\u00edte\u017e"
    ],
    "name:srp_x_preferred":[
        "\u0417\u0430\u0434\u045a\u0438 \u0421\u0442\u0440\u0438\u0442\u0435\u0436"
    ],
    "name:urd_x_preferred":[
        "\u0632\u062f\u0646\u06cc \u0633\u062a\u06cc\u06cc\u062a\u06d2\u0698"
    ],
    "name:vie_x_preferred":[
        "Zadn\u00ed St\u0159\u00edte\u017e"
    ],
    "qs_pg:aaroncc":"CZ",
    "qs_pg:gn_country":"CZ",
    "qs_pg:gn_fcode":"PPL",
    "qs_pg:gn_pop":42,
    "qs_pg:name":"Zadn\u00ed St\u0159\u00edte\u017e",
    "qs_pg:name_adm0":"\u010cesk\u00e1 republika",
    "qs_pg:name_adm1":"Jiho\u010desk\u00fd kraj",
    "qs_pg:photos_9k":1,
    "qs_pg:photos_9r":1,
    "qs_pg:photos_all":1,
    "qs_pg:photos_sr":0,
    "qs_pg:pop_sr":1,
    "qs_pg:qs_pg_placetype":"locality",
    "qs_pg:qs_pg_placetype_gp":"Town",
    "qs_pg:woe_adm0":23424810,
    "woe:adm0_id":23424810,
    "woe:name_adm0":"\u010cesk\u00e1 republika",
    "woe:name_adm1":"Jiho\u010desk\u00fd kraj",
    "woe:placetype":"Town",
    "wof:name":"Zadn\u00ed St\u0159\u00edte\u017e",
    "wof:placetype":"locality",
    "wof:population":42
},
  "geometry": {"coordinates":[14.91671,49.49408],"type":"Point"}
}