{
  "type": "Feature",
  "properties": {
    "gn:country":"CZ",
    "gn:fcode":"PPL",
    "gn:population":323,
    "iso:country":"CZ",
    "name:azb_x_preferred":[
        "\u0648\u0644\u06cc\u0634"
    ],
    "name:ceb_x_preferred":[
        "Veli\u0161"
    ],
    "name:ces_x_preferred":[
        "Veli\u0161"
    ],
    "name:eng_x_preferred":[
        "Veli\u0161"
    ],
    "name:eus_x_preferred":[
        "Veli\u0161"
    ],
    "name:fas_x_preferred":[
        "\u0648\u0644\u06cc\u0634"
    ],
    "name:fra_x_preferred":[
        "Veli\u0161"
    ],
    "name:hun_x_preferred":[
        "Veli\u0161"
    ],
    "name:ita_x_preferred":[
        "Veli\u0161"
    ],
    "name:msa_x_preferred":[
        "Veli\u0161"
    ],
    "name:nan_x_preferred":[
        "Veli\u0161"
    ],
    "name:nld_x_preferred":[
        "Veli\u0161"
    ],
    "name:pol_x_preferred":[
        "Veli\u0161"
    ],
    "name:por_x_preferred":[
        "Veli\u0161"
    ],
    "name:rup_x_preferred":[
        "Veli\u0161"
    ],
    "name:slk_x_preferred":[
        "Veli\u0161"
    ],
    "name:spa_x_preferred":[
        "Veli\u0161"
    ],
    "name:srp_x_preferred":[
        "\u0412\u0435\u043b\u0438\u0448"
    ],
    "name:swe_x_preferred":[
        "Veli\u0161"
    ],
    "name:und_x_variant":[
        "Welisch"
    ],
    "name:vie_x_preferred":[
        "Veli\u0161"
    ],
    "qs_pg:aaroncc":"CZ",
    "qs_pg:gn_country":"CZ",
    "qs_pg:gn_fcode":"PPL",
    "qs_pg:gn_pop":323,
    "qs_pg:name":"Veli\u0161",
    "qs_pg:name_adm0":"\u010cesk\u00e1 republika",
    "qs_pg:name_adm1":"St\u0159edo\u010desk\u00fd kraj",
    "qs_pg:photos_9k":1,
    "qs_pg:photos_9r":1,
    "qs_pg:photos_all":6,
    "qs_pg:photos_sr":0,
    "qs_pg:pop_sr":2,
    "qs_pg:qs_pg_placetype":"locality",
    "qs_pg:qs_pg_placetype_gp":"Town",
    "qs_pg:woe_adm0":23424810,
    "woe:adm0_id":23424810,
    "woe:name_adm0":"\u010cesk\u00e1 republika",
    "woe:name_adm1":"St\u0159edo\u010desk\u00fd kraj",
    "woe:placetype":"Town",
    "wof:name":"Veli\u0161",
    "wof:placetype":"locality",
    "wof:population":323
},
  "geometry": {"coordinates":[14.82314,49.66856],"type":"Point"}
}