{
  "type": "Feature",
  "properties": {
    "gn:admin1_code":"90.0",
    "gn:admin2_code":"0722",
    "gn:asciiname":"Olsovec",
    "gn:country_code":"CZ",
    "gn:dem":728,
    "gn:feature_class":"P",
    "gn:feature_code":"PPL",
    "gn:name":"Ol\u0161ovec",
    "gn:population":0,
    "gn:timezone":"Europe/Prague",
    "iso:country":"CZ",
    "name:und_x_variant":[
        "Ol\u0161ovec"
    ],
    "wof:name":"Olsovec",
    "wof:placetype":"locality"
},
  "geometry": {"coordinates":[17.76667,48.93333],"type":"Point"}
}