{
  "type": "Feature",
  "properties": {
    "gn:gn_country":"CZ",
    "gn:gn_fcode":"PPL",
    "gn:gn_pop":122,
    "gn:population":122,
    "iso:country":"CZ",
    "name:azb_x_preferred":[
        "\u0628\u0627\u0644\u06a9\u0648\u0648\u0627 \u0644\u0647\u0648\u062a\u0627"
    ],
    "name:ceb_x_preferred":[
        "Balkova Lhota"
    ],
    "name:ces_x_preferred":[
        "Balkova Lhota"
    ],
    "name:deu_x_preferred":[
        "Balkova Lhota"
    ],
    "name:eng_x_preferred":[
        "Balkova Lhota"
    ],
    "name:eus_x_preferred":[
        "Balkova Lhota"
    ],
    "name:fas_x_preferred":[
        "\u0628\u0627\u0644\u06a9\u0648\u0648\u0627 \u0644\u0647\u0648\u062a\u0627"
    ],
    "name:fra_x_preferred":[
        "Balkova Lhota"
    ],
    "name:hun_x_preferred":[
        "Balkova Lhota"
    ],
    "name:ita_x_preferred":[
        "Balkova Lhota"
    ],
    "name:msa_x_preferred":[
        "Balkova Lhota"
    ],
    "name:nan_x_preferred":[
        "Balkova Lhota"
    ],
    "name:nld_x_preferred":[
        "Balkova Lhota"
    ],
    "name:nob_x_preferred":[
        "Balkova Lhota"
    ],
    "name:pol_x_preferred":[
        "Balkova Lhota"
    ],
    "name:por_x_preferred":[
        "Balkova Lhota"
    ],
    "name:rup_x_preferred":[
        "Balkova Lhota"
    ],
    "name:slk_x_preferred":[
        "Balkova Lhota"
    ],
    "name:spa_x_preferred":[
        "Balkova Lhota"
    ],
    "name:srp_x_preferred":[
        "\u0411\u0430\u043b\u043a\u043e\u0432\u0430 \u041b\u0445\u043e\u0442\u0430"
    ],
    "name:swe_x_preferred":[
        "Balkova Lhota"
    ],
    "name:vie_x_preferred":[
        "Balkova Lhota"
    ],
    "qs_pg:aaroncc":"CZ",
    "qs_pg:gn_country":"CZ",
    "qs_pg:gn_fcode":"PPL",
    "qs_pg:gn_pop":122,
    "qs_pg:name":"Balkova Lhota",
    "qs_pg:name_adm0":"\u010cesk\u00e1 republika",
    "qs_pg:name_adm1":"Jiho\u010desk\u00fd kraj",
    "qs_pg:photos_9r":0,
    "qs_pg:photos_sr":0,
    "qs_pg:pop_sr":1,
    "qs_pg:qs_pg_placetype":"locality",
    "qs_pg:qs_pg_placetype_gp":"Town",
    "qs_pg:woe_adm0":23424810,
    "woe:adm0_id":23424810,
    "woe:name_adm0":"\u010cesk\u00e1 republika",
    "woe:name_adm1":"Jiho\u010desk\u00fd kraj",
    "woe:placetype":"Town",
    "wof:name":"Balkova Lhota",
    "wof:placetype":"locality",
    "wof:population":122
},
  "geometry": {"coordinates":[14.60822,49.45202],"type":"Point"}
}