{
  "type": "Feature",
  "properties": {
    "gn:admin1_code":"87.0",
    "gn:admin2_code":"0327",
    "gn:asciiname":"Nynkov",
    "gn:country_code":"CZ",
    "gn:dem":484,
    "gn:feature_class":"P",
    "gn:feature_code":"PPL",
    "gn:name":"Nynkov",
    "gn:population":0,
    "gn:timezone":"Europe/Prague",
    "iso:country":"CZ",
    "name:und_x_variant":[
        "Linkau",
        "Nynkov"
    ],
    "wof:name":"Nynkov",
    "wof:placetype":"locality"
},
  "geometry": {"coordinates":[12.89602,49.75984],"type":"Point"}
}