{
  "type": "Feature",
  "properties": {
    "gn:admin1_code":"79.0",
    "gn:admin2_code":"0313",
    "gn:asciiname":"Domasin",
    "gn:country_code":"CZ",
    "gn:dem":642,
    "gn:feature_class":"P",
    "gn:feature_code":"PPL",
    "gn:name":"Doma\u0161\u00edn",
    "gn:population":0,
    "gn:timezone":"Europe/Prague",
    "iso:country":"CZ",
    "wof:name":"Domasin",
    "wof:placetype":"locality"
},
  "geometry": {"coordinates":[15.27347,49.20454],"type":"Point"}
}