{
  "type": "Feature",
  "properties": {
    "gn:admin1_code":"79.0",
    "gn:admin2_code":"0317",
    "gn:asciiname":"Hlasivko",
    "gn:country_code":"CZ",
    "gn:dem":543,
    "gn:feature_class":"P",
    "gn:feature_code":"PPL",
    "gn:name":"Hlas\u00edvko",
    "gn:population":0,
    "gn:timezone":"Europe/Prague",
    "iso:country":"CZ",
    "wof:name":"Hlasivko",
    "wof:placetype":"locality"
},
  "geometry": {"coordinates":[14.76137,49.48591],"type":"Point"}
}