{
  "type": "Feature",
  "properties": {
    "gn:gn_country":"CZ",
    "gn:gn_fcode":"PPL",
    "gn:gn_pop":709,
    "gn:population":709,
    "iso:country":"CZ",
    "name:cze_x_preferred":[
        "\u010cerven\u00e9 Janovice"
    ],
    "name:dut_x_preferred":[
        "\u010cerven\u00e9 Janovice"
    ],
    "name:eng_x_preferred":[
        "\u010cerven\u00e9 Janovice"
    ],
    "name:fre_x_preferred":[
        "\u010cerven\u00e9 Janovice"
    ],
    "name:hun_x_preferred":[
        "\u010cerven\u00e9 Janovice"
    ],
    "name:ita_x_preferred":[
        "\u010cerven\u00e9 Janovice"
    ],
    "name:may_x_preferred":[
        "\u010cerven\u00e9 Janovice"
    ],
    "name:per_x_preferred":[
        "\u062a\u0634\u0631\u0648\u0646\u0647 \u06cc\u0627\u0646\u0648\u0648\u06cc\u062a\u0633\u0647"
    ],
    "name:pol_x_preferred":[
        "\u010cerven\u00e9 Janovice"
    ],
    "name:por_x_preferred":[
        "\u010cerven\u00e9 Janovice"
    ],
    "name:rup_x_preferred":[
        "\u010cerven\u00e9 Janovice"
    ],
    "name:slo_x_preferred":[
        "\u010cerven\u00e9 Janovice"
    ],
    "name:srp_x_preferred":[
        "\u0427\u0435\u0440\u0432\u0435\u043d\u0435 \u0408\u0430\u043d\u043e\u0432\u0438\u0446\u0435"
    ],
    "name:swe_x_preferred":[
        "\u010cerven\u00e9 Janovice"
    ],
    "name:unk_x_variant":[
        "Roth Janowitz"
    ],
    "name:vie_x_preferred":[
        "\u010cerven\u00e9 Janovice"
    ],
    "qs_pg:aaroncc":"CZ",
    "qs_pg:gn_country":"CZ",
    "qs_pg:gn_fcode":"PPL",
    "qs_pg:gn_pop":709,
    "qs_pg:name":"\u010cerven\u00e9 Janovice",
    "qs_pg:name_adm0":"\u010cesk\u00e1 republika",
    "qs_pg:name_adm1":"St\u0159edo\u010desk\u00fd kraj",
    "qs_pg:photos_9r":0,
    "qs_pg:photos_sr":0,
    "qs_pg:pop_sr":2,
    "qs_pg:qs_pg_placetype":"locality",
    "qs_pg:qs_pg_placetype_gp":"Town",
    "qs_pg:woe_adm0":23424810,
    "woe:adm0_id":23424810,
    "woe:name_adm0":"\u010cesk\u00e1 republika",
    "woe:name_adm1":"St\u0159edo\u010desk\u00fd kraj",
    "woe:placetype":"Town",
    "wof:name":"\u010cerven\u00e9 Janovice",
    "wof:placetype":"locality",
    "wof:population":709
},
  "geometry": {"coordinates":[15.25333,49.83461],"type":"Point"}
}