{
  "type": "Feature",
  "properties": {
    "gn:gn_country":"CZ",
    "gn:gn_fcode":"PPL",
    "gn:gn_pop":443,
    "gn:population":443,
    "iso:country":"CZ",
    "name:ceb_x_preferred":[
        "Put\u00edm"
    ],
    "name:ces_x_preferred":[
        "Putim"
    ],
    "name:deu_x_preferred":[
        "Putim"
    ],
    "name:eng_x_preferred":[
        "Putim"
    ],
    "name:epo_x_preferred":[
        "Putim"
    ],
    "name:eus_x_preferred":[
        "Putim"
    ],
    "name:fra_x_preferred":[
        "Putim"
    ],
    "name:hun_x_preferred":[
        "Putim"
    ],
    "name:ita_x_preferred":[
        "Putim"
    ],
    "name:msa_x_preferred":[
        "Putim"
    ],
    "name:nan_x_preferred":[
        "Putim"
    ],
    "name:nld_x_preferred":[
        "Putim"
    ],
    "name:por_x_preferred":[
        "Putim"
    ],
    "name:slk_x_preferred":[
        "Putim"
    ],
    "name:spa_x_preferred":[
        "Putim"
    ],
    "name:srp_x_preferred":[
        "\u041f\u0443\u0442\u0438\u043c"
    ],
    "name:swe_x_preferred":[
        "Put\u00edm"
    ],
    "name:vie_x_preferred":[
        "Putim"
    ],
    "qs_pg:aaroncc":"CZ",
    "qs_pg:gn_country":"CZ",
    "qs_pg:gn_fcode":"PPL",
    "qs_pg:gn_pop":443,
    "qs_pg:name":"Putim",
    "qs_pg:name_adm0":"\u010cesk\u00e1 republika",
    "qs_pg:name_adm1":"Jiho\u010desk\u00fd kraj",
    "qs_pg:photos_9r":0,
    "qs_pg:photos_sr":0,
    "qs_pg:pop_sr":2,
    "qs_pg:qs_pg_placetype":"locality",
    "qs_pg:qs_pg_placetype_gp":"Town",
    "qs_pg:woe_adm0":23424810,
    "woe:adm0_id":23424810,
    "woe:name_adm0":"\u010cesk\u00e1 republika",
    "woe:name_adm1":"Jiho\u010desk\u00fd kraj",
    "woe:placetype":"Town",
    "wof:name":"Putim",
    "wof:placetype":"locality",
    "wof:population":443
},
  "geometry": {"coordinates":[14.11903,49.26452],"type":"Point"}
}