{
  "type": "Feature",
  "properties": {
    "gn:gn_country":"CZ",
    "gn:gn_fcode":"PPL",
    "gn:gn_pop":135,
    "gn:population":135,
    "iso:country":"CZ",
    "name:ces_x_preferred":[
        "Pr\u00e1\u0161ily"
    ],
    "name:deu_x_preferred":[
        "Pr\u00e1\u0161ily"
    ],
    "name:eng_x_preferred":[
        "Pr\u00e1\u0161ily"
    ],
    "name:epo_x_preferred":[
        "Pr\u00e1\u0161ily"
    ],
    "name:fas_x_preferred":[
        "\u067e\u0631\u0627\u0634\u06cc\u0644\u06cc"
    ],
    "name:fra_x_preferred":[
        "Pr\u00e1\u0161ily"
    ],
    "name:hun_x_preferred":[
        "Pr\u00e1\u0161ily"
    ],
    "name:ita_x_preferred":[
        "Pr\u00e1\u0161ily"
    ],
    "name:msa_x_preferred":[
        "Pr\u00e1\u0161ily"
    ],
    "name:nld_x_preferred":[
        "Pr\u00e1\u0161ily"
    ],
    "name:pol_x_preferred":[
        "Pr\u00e1\u0161ily"
    ],
    "name:por_x_preferred":[
        "Pr\u00e1\u0161ily"
    ],
    "name:slk_x_preferred":[
        "Pr\u00e1\u0161ily"
    ],
    "name:srp_x_preferred":[
        "\u041f\u0440\u0430\u0448\u0438\u043b\u0438"
    ],
    "name:swe_x_preferred":[
        "Pr\u00e1\u0161ily"
    ],
    "name:unk_x_variant":[
        "Stubenbach"
    ],
    "name:vie_x_preferred":[
        "Pr\u00e1\u0161ily"
    ],
    "qs_pg:aaroncc":"CZ",
    "qs_pg:gn_country":"CZ",
    "qs_pg:gn_fcode":"PPL",
    "qs_pg:gn_pop":135,
    "qs_pg:name":"Pr\u00e1\u0161ily",
    "qs_pg:name_adm0":"\u010cesk\u00e1 republika",
    "qs_pg:name_adm1":"Plze\u0148sk\u00fd kraj",
    "qs_pg:photos_9k":2,
    "qs_pg:photos_9r":5,
    "qs_pg:photos_all":384,
    "qs_pg:photos_sr":0,
    "qs_pg:pop_sr":1,
    "qs_pg:qs_pg_placetype":"locality",
    "qs_pg:qs_pg_placetype_gp":"Town",
    "qs_pg:woe_adm0":23424810,
    "woe:adm0_id":23424810,
    "woe:name_adm0":"\u010cesk\u00e1 republika",
    "woe:name_adm1":"Plze\u0148sk\u00fd kraj",
    "woe:placetype":"Town",
    "wof:name":"Pr\u00e1\u0161ily",
    "wof:placetype":"locality",
    "wof:population":135
},
  "geometry": {"coordinates":[13.37794,49.10513],"type":"Point"}
}