{
  "type": "Feature",
  "properties": {
    "gn:admin1_code":"79.0",
    "gn:admin2_code":"0312",
    "gn:asciiname":"Herbertov",
    "gn:cc2":"CZ",
    "gn:country_code":"CZ",
    "gn:dem":541,
    "gn:feature_class":"P",
    "gn:feature_code":"PPL",
    "gn:name":"Herbertov",
    "gn:population":0,
    "gn:timezone":"Europe/Prague",
    "iso:country":"CZ",
    "name:und_x_variant":[
        "Gerbetschlag"
    ],
    "wof:name":"Herbertov",
    "wof:placetype":"locality"
},
  "geometry": {"coordinates":[14.35098,48.6206],"type":"Point"}
}