{
  "type": "Feature",
  "properties": {
    "gn:country":"CZ",
    "gn:fcode":"PPL",
    "gn:population":169,
    "iso:country":"CZ",
    "name:azb_x_preferred":[
        "\u067e\u0631\u062f\u0646\u06cc\u062a\u0633\u0647"
    ],
    "name:ceb_x_preferred":[
        "P\u0159edenice"
    ],
    "name:ces_x_preferred":[
        "P\u0159edenice"
    ],
    "name:deu_x_preferred":[
        "P\u0159edenice"
    ],
    "name:eng_x_preferred":[
        "P\u0159edenice"
    ],
    "name:eus_x_preferred":[
        "P\u0159edenice"
    ],
    "name:fas_x_preferred":[
        "\u067e\u0631\u062f\u0646\u06cc\u062a\u0633\u0647"
    ],
    "name:fra_x_preferred":[
        "P\u0159edenice"
    ],
    "name:hun_x_preferred":[
        "P\u0159edenice"
    ],
    "name:ita_x_preferred":[
        "P\u0159edenice"
    ],
    "name:msa_x_preferred":[
        "P\u0159edenice"
    ],
    "name:nan_x_preferred":[
        "P\u0159edenice"
    ],
    "name:nld_x_preferred":[
        "P\u0159edenice"
    ],
    "name:pol_x_preferred":[
        "P\u0159edenice"
    ],
    "name:por_x_preferred":[
        "P\u0159edenice"
    ],
    "name:slk_x_preferred":[
        "P\u0159edenice"
    ],
    "name:spa_x_preferred":[
        "P\u0159edenice"
    ],
    "name:srp_x_preferred":[
        "\u041f\u0440\u0435\u0434\u0435\u045a\u0438\u0446\u0435"
    ],
    "name:swe_x_preferred":[
        "P\u0159edenice"
    ],
    "name:vie_x_preferred":[
        "P\u0159edenice"
    ],
    "qs_pg:aaroncc":"CZ",
    "qs_pg:gn_country":"CZ",
    "qs_pg:gn_fcode":"PPL",
    "qs_pg:gn_pop":169,
    "qs_pg:name":"P\u0159edenice",
    "qs_pg:name_adm0":"\u010cesk\u00e1 republika",
    "qs_pg:name_adm1":"Plze\u0148sk\u00fd kraj",
    "qs_pg:photos_9r":0,
    "qs_pg:photos_sr":0,
    "qs_pg:pop_sr":1,
    "qs_pg:qs_pg_placetype":"locality",
    "qs_pg:qs_pg_placetype_gp":"Town",
    "qs_pg:woe_adm0":23424810,
    "woe:adm0_id":23424810,
    "woe:name_adm0":"\u010cesk\u00e1 republika",
    "woe:name_adm1":"Plze\u0148sk\u00fd kraj",
    "woe:placetype":"Town",
    "wof:name":"P\u0159edenice",
    "wof:placetype":"locality",
    "wof:population":169
},
  "geometry": {"coordinates":[13.39656,49.62439],"type":"Point"}
}