{
  "type": "Feature",
  "properties": {
    "gn:country":"CZ",
    "gn:fcode":"PPL",
    "gn:population":1425,
    "iso:country":"CZ",
    "name:azb_x_preferred":[
        "\u0646\u0627\u06a9\u0644\u0648"
    ],
    "name:cat_x_preferred":[
        "N\u00e1klo"
    ],
    "name:ceb_x_preferred":[
        "N\u00e1klo"
    ],
    "name:ces_x_preferred":[
        "N\u00e1klo"
    ],
    "name:che_x_preferred":[
        "\u041d\u0430\u043a\u043b\u043e"
    ],
    "name:deu_x_preferred":[
        "N\u00e1klo"
    ],
    "name:eng_x_preferred":[
        "N\u00e1klo"
    ],
    "name:epo_x_preferred":[
        "N\u00e1klo"
    ],
    "name:eus_x_preferred":[
        "N\u00e1klo"
    ],
    "name:fas_x_preferred":[
        "\u0646\u0627\u06a9\u0644\u0648"
    ],
    "name:fra_x_preferred":[
        "N\u00e1klo"
    ],
    "name:gle_x_preferred":[
        "N\u00e1klo"
    ],
    "name:hun_x_preferred":[
        "N\u00e1klo"
    ],
    "name:ita_x_preferred":[
        "N\u00e1klo"
    ],
    "name:jpn_x_preferred":[
        "\u30ca\u30fc\u30af\u30ed"
    ],
    "name:lmo_x_preferred":[
        "N\u00e1klo"
    ],
    "name:msa_x_preferred":[
        "N\u00e1klo"
    ],
    "name:nan_x_preferred":[
        "N\u00e1klo"
    ],
    "name:nld_x_preferred":[
        "N\u00e1klo"
    ],
    "name:pol_x_preferred":[
        "N\u00e1klo"
    ],
    "name:por_x_preferred":[
        "N\u00e1klo"
    ],
    "name:rup_x_preferred":[
        "N\u00e1klo"
    ],
    "name:rus_x_preferred":[
        "\u041d\u0430\u043a\u043b\u043e"
    ],
    "name:slk_x_preferred":[
        "N\u00e1klo"
    ],
    "name:spa_x_preferred":[
        "N\u00e1klo"
    ],
    "name:srp_x_preferred":[
        "\u041d\u0430\u043a\u043b\u043e"
    ],
    "name:swe_x_preferred":[
        "N\u00e1klo"
    ],
    "name:tat_x_preferred":[
        "\u041d\u0430\u043a\u043b\u043e"
    ],
    "name:vie_x_preferred":[
        "N\u00e1klo"
    ],
    "qs_pg:aaroncc":"CZ",
    "qs_pg:gn_country":"CZ",
    "qs_pg:gn_fcode":"PPL",
    "qs_pg:gn_pop":1425,
    "qs_pg:name":"N\u00e1klo",
    "qs_pg:name_adm0":"\u010cesk\u00e1 republika",
    "qs_pg:name_adm1":"Olomouck\u00fd kraj",
    "qs_pg:photos_9k":1,
    "qs_pg:photos_9r":1,
    "qs_pg:photos_all":1,
    "qs_pg:photos_sr":0,
    "qs_pg:pop_sr":3,
    "qs_pg:qs_pg_placetype":"locality",
    "qs_pg:qs_pg_placetype_gp":"Town",
    "qs_pg:woe_adm0":23424810,
    "woe:adm0_id":23424810,
    "woe:name_adm0":"\u010cesk\u00e1 republika",
    "woe:name_adm1":"Olomouck\u00fd kraj",
    "woe:placetype":"Town",
    "wof:name":"N\u00e1klo",
    "wof:placetype":"locality",
    "wof:population":1425
},
  "geometry": {"coordinates":[17.12969,49.65462],"type":"Point"}
}