{
  "type": "Feature",
  "properties": {
    "gn:admin1_code":"87",
    "gn:admin2_code":"0325",
    "gn:asciiname":"Trhomne",
    "gn:country_code":"CZ",
    "gn:dem":644,
    "gn:feature_class":"P",
    "gn:feature_code":"PPL",
    "gn:name":"Trhomn\u00e9",
    "gn:population":0,
    "gn:timezone":"Europe/Prague",
    "iso:country":"CZ",
    "name:und_x_variant":[
        "Trahona",
        "Trhomn\u00e9"
    ],
    "wof:name":"Trhomne",
    "wof:placetype":"locality"
},
  "geometry": {"coordinates":[13.08405,49.94929000000001],"type":"Point"}
}