{
  "type": "Feature",
  "properties": {
    "gn:country":"CZ",
    "gn:fcode":"PPL",
    "gn:population":342,
    "iso:country":"CZ",
    "name:azb_x_preferred":[
        "\u06a9\u0648\u06cc\u0627\u062a\u06cc\u062a\u0633\u0647"
    ],
    "name:ceb_x_preferred":[
        "Kojatice"
    ],
    "name:ces_x_preferred":[
        "Kojatice"
    ],
    "name:eng_x_preferred":[
        "Kojatice"
    ],
    "name:eus_x_preferred":[
        "Kojatice"
    ],
    "name:fas_x_preferred":[
        "\u06a9\u0648\u06cc\u0627\u062a\u06cc\u062a\u0633\u0647"
    ],
    "name:fra_x_preferred":[
        "Kojatice"
    ],
    "name:hun_x_preferred":[
        "Kojatice"
    ],
    "name:ita_x_preferred":[
        "Kojatice"
    ],
    "name:msa_x_preferred":[
        "Kojatice"
    ],
    "name:nan_x_preferred":[
        "Kojatice"
    ],
    "name:nld_x_preferred":[
        "Kojatice"
    ],
    "name:pol_x_preferred":[
        "Kojatice"
    ],
    "name:por_x_preferred":[
        "Kojatice"
    ],
    "name:rup_x_preferred":[
        "Kojatice"
    ],
    "name:slk_x_preferred":[
        "Kojatice"
    ],
    "name:spa_x_preferred":[
        "Kojatice"
    ],
    "name:swe_x_preferred":[
        "Kojatice"
    ],
    "name:vie_x_preferred":[
        "Kojatice"
    ],
    "qs_pg:aaroncc":"CZ",
    "qs_pg:gn_country":"CZ",
    "qs_pg:gn_fcode":"PPL",
    "qs_pg:gn_pop":342,
    "qs_pg:name":"Kojatice",
    "qs_pg:name_adm0":"\u010cesk\u00e1 republika",
    "qs_pg:name_adm1":"Kraj Vyso\u010dina",
    "qs_pg:photos_9r":0,
    "qs_pg:photos_sr":0,
    "qs_pg:pop_sr":2,
    "qs_pg:qs_pg_placetype":"locality",
    "qs_pg:qs_pg_placetype_gp":"Town",
    "qs_pg:woe_adm0":23424810,
    "woe:adm0_id":23424810,
    "woe:name_adm0":"\u010cesk\u00e1 republika",
    "woe:name_adm1":"Kraj Vyso\u010dina",
    "woe:placetype":"Town",
    "wof:name":"Kojatice",
    "wof:placetype":"locality",
    "wof:population":342
},
  "geometry": {"coordinates":[15.70312,48.99885],"type":"Point"}
}