{
  "type": "Feature",
  "properties": {
    "gn:admin1_code":"88.0",
    "gn:admin2_code":"0203",
    "gn:asciiname":"Rozdelov",
    "gn:country_code":"CZ",
    "gn:dem":425,
    "gn:feature_class":"P",
    "gn:feature_code":"PPL",
    "gn:name":"Rozd\u011blov",
    "gn:population":0,
    "gn:timezone":"Europe/Prague",
    "iso:country":"CZ",
    "name:und_x_variant":[
        "Rozd\u011blow",
        "Rozd\u011blov"
    ],
    "wof:name":"Rozdelov",
    "wof:placetype":"locality"
},
  "geometry": {"coordinates":[14.06834,50.14043],"type":"Point"}
}