{
  "type": "Feature",
  "properties": {
    "gn:country":"CZ",
    "gn:fcode":"PPL",
    "gn:population":1314,
    "iso:country":"CZ",
    "name:bul_x_preferred":[
        "\u0417\u0434\u0438\u0431\u0439"
    ],
    "name:cat_x_preferred":[
        "Zdiby"
    ],
    "name:ceb_x_preferred":[
        "Zdiby"
    ],
    "name:ces_x_preferred":[
        "Zdiby"
    ],
    "name:che_x_preferred":[
        "\u0417\u0434\u0438\u0431\u0438"
    ],
    "name:deu_x_preferred":[
        "Zdiby"
    ],
    "name:eng_x_preferred":[
        "Zdiby"
    ],
    "name:eus_x_preferred":[
        "Zdiby"
    ],
    "name:fra_x_preferred":[
        "Zdiby"
    ],
    "name:gle_x_preferred":[
        "Zdiby"
    ],
    "name:hun_x_preferred":[
        "Zdiby"
    ],
    "name:ita_x_preferred":[
        "Zdiby"
    ],
    "name:lmo_x_preferred":[
        "Zdiby"
    ],
    "name:msa_x_preferred":[
        "Zdiby"
    ],
    "name:nan_x_preferred":[
        "Zdiby"
    ],
    "name:nld_x_preferred":[
        "Zdiby"
    ],
    "name:pol_x_preferred":[
        "Zdiby"
    ],
    "name:por_x_preferred":[
        "Zdiby"
    ],
    "name:rup_x_preferred":[
        "Zdiby"
    ],
    "name:rus_x_preferred":[
        "\u0417\u0434\u0438\u0431\u0438"
    ],
    "name:slk_x_preferred":[
        "Zdiby"
    ],
    "name:spa_x_preferred":[
        "Zdiby"
    ],
    "name:srp_x_preferred":[
        "\u0417\u0434\u0438\u0431\u0438"
    ],
    "name:swe_x_preferred":[
        "Zdiby"
    ],
    "name:tat_x_preferred":[
        "\u0417\u0434\u0438\u0431\u0438"
    ],
    "name:vie_x_preferred":[
        "Zdiby"
    ],
    "qs_pg:aaroncc":"CZ",
    "qs_pg:gn_country":"CZ",
    "qs_pg:gn_fcode":"PPL",
    "qs_pg:gn_pop":1314,
    "qs_pg:name":"Zdiby",
    "qs_pg:name_adm0":"\u010cesk\u00e1 republika",
    "qs_pg:name_adm1":"St\u0159edo\u010desk\u00fd kraj",
    "qs_pg:photos_9k":1,
    "qs_pg:photos_9r":2,
    "qs_pg:photos_all":73,
    "qs_pg:photos_sr":0,
    "qs_pg:pop_sr":3,
    "qs_pg:qs_pg_placetype":"locality",
    "qs_pg:qs_pg_placetype_gp":"Town",
    "qs_pg:woe_adm0":23424810,
    "woe:adm0_id":23424810,
    "woe:name_adm0":"\u010cesk\u00e1 republika",
    "woe:name_adm1":"St\u0159edo\u010desk\u00fd kraj",
    "woe:placetype":"Town",
    "wof:name":"Zdiby",
    "wof:placetype":"locality",
    "wof:population":1314
},
  "geometry": {"coordinates":[14.45118,50.16799],"type":"Point"}
}