{
  "type": "Feature",
  "properties": {
    "gn:gn_country":"CZ",
    "gn:gn_fcode":"PPL",
    "gn:gn_pop":139,
    "gn:population":139,
    "iso:country":"CZ",
    "name:cze_x_preferred":[
        "Podhrad\u00ed"
    ],
    "name:dut_x_preferred":[
        "Podhrad\u00ed"
    ],
    "name:eng_x_preferred":[
        "Podhrad\u00ed"
    ],
    "name:fre_x_preferred":[
        "Podhrad\u00ed"
    ],
    "name:ger_x_preferred":[
        "Podhrad\u00ed u A\u0161e"
    ],
    "name:hun_x_preferred":[
        "Podhrad\u00ed"
    ],
    "name:ita_x_preferred":[
        "Podhrad\u00ed"
    ],
    "name:may_x_preferred":[
        "Podhrad\u00ed"
    ],
    "name:per_x_preferred":[
        "\u067e\u0648\u062f\u0647\u0631\u0627\u062f\u06cc"
    ],
    "name:pol_x_preferred":[
        "Podhrad\u00ed"
    ],
    "name:por_x_preferred":[
        "Podhrad\u00ed"
    ],
    "name:rup_x_preferred":[
        "Podhrad\u00ed"
    ],
    "name:slo_x_preferred":[
        "Podhrad\u00ed"
    ],
    "name:srp_x_preferred":[
        "\u041f\u043e\u0434\u0445\u0440\u0430\u0434\u0438"
    ],
    "name:unk_x_variant":[
        "Neuberg"
    ],
    "name:vie_x_preferred":[
        "Podhrad\u00ed"
    ],
    "qs_pg:aaroncc":"CZ",
    "qs_pg:gn_country":"CZ",
    "qs_pg:gn_fcode":"PPL",
    "qs_pg:gn_pop":139,
    "qs_pg:name":"Podhrad\u00ed",
    "qs_pg:name_adm0":"\u010cesk\u00e1 republika",
    "qs_pg:name_adm1":"Karlovarsk\u00fd kraj",
    "qs_pg:photos_9r":0,
    "qs_pg:photos_sr":0,
    "qs_pg:pop_sr":1,
    "qs_pg:qs_pg_placetype":"locality",
    "qs_pg:qs_pg_placetype_gp":"Town",
    "qs_pg:woe_adm0":23424810,
    "woe:adm0_id":23424810,
    "woe:name_adm0":"\u010cesk\u00e1 republika",
    "woe:name_adm1":"Karlovarsk\u00fd kraj",
    "woe:placetype":"Town",
    "wof:name":"Podhrad\u00ed",
    "wof:placetype":"locality",
    "wof:population":139
},
  "geometry": {"coordinates":[12.20174,50.25535],"type":"Point"}
}