{
  "type": "Feature",
  "properties": {
    "gn:admin1_code":"86.0",
    "gn:admin2_code":"0534",
    "gn:asciiname":"Pesice",
    "gn:country_code":"CZ",
    "gn:dem":398,
    "gn:feature_class":"P",
    "gn:feature_code":"PPL",
    "gn:name":"P\u011b\u0161ice",
    "gn:population":0,
    "gn:timezone":"Europe/Prague",
    "iso:country":"CZ",
    "wof:name":"Pesice",
    "wof:placetype":"locality"
},
  "geometry": {"coordinates":[16.06993,49.91898],"type":"Point"}
}