{
  "type": "Feature",
  "properties": {
    "gn:country":"CZ",
    "gn:fcode":"PPL",
    "gn:population":779,
    "iso:country":"CZ",
    "name:azb_x_preferred":[
        "\u0645\u0648\u062a\u06cc\u06cc\u0648\u0648\u06cc\u062a\u0633\u0647"
    ],
    "name:cat_x_preferred":[
        "Mut\u011bjovice"
    ],
    "name:ceb_x_preferred":[
        "Mut\u011bjovice"
    ],
    "name:ces_x_preferred":[
        "Mut\u011bjovice"
    ],
    "name:che_x_preferred":[
        "\u041c\u0443\u0442\u0435\u0439\u043e\u0432\u0438\u0446\u0435"
    ],
    "name:deu_x_preferred":[
        "Mut\u011bjovice"
    ],
    "name:eng_x_preferred":[
        "Mut\u011bjovice"
    ],
    "name:epo_x_preferred":[
        "Mut\u011bjovice"
    ],
    "name:eus_x_preferred":[
        "Mut\u011bjovice"
    ],
    "name:fas_x_preferred":[
        "\u0645\u0648\u062a\u06cc\u06cc\u0648\u0648\u06cc\u062a\u0633\u0647"
    ],
    "name:fra_x_preferred":[
        "Mut\u011bjovice"
    ],
    "name:gle_x_preferred":[
        "Mut\u011bjovice"
    ],
    "name:hun_x_preferred":[
        "Mut\u011bjovice"
    ],
    "name:ita_x_preferred":[
        "Mut\u011bjovice"
    ],
    "name:lmo_x_preferred":[
        "Mut\u011bjovice"
    ],
    "name:msa_x_preferred":[
        "Mut\u011bjovice"
    ],
    "name:nan_x_preferred":[
        "Mut\u011bjovice"
    ],
    "name:nld_x_preferred":[
        "Mut\u011bjovice"
    ],
    "name:pol_x_preferred":[
        "Mut\u011bjovice"
    ],
    "name:por_x_preferred":[
        "Mut\u011bjovice"
    ],
    "name:slk_x_preferred":[
        "Mut\u011bjovice"
    ],
    "name:spa_x_preferred":[
        "Mut\u011bjovice"
    ],
    "name:srp_x_preferred":[
        "\u041c\u0443\u0442\u0458\u0435\u0458\u043e\u0432\u0438\u0446\u0435"
    ],
    "name:swe_x_preferred":[
        "Mut\u011bjovice"
    ],
    "name:tat_x_preferred":[
        "\u041c\u0443\u0442\u0435\u0439\u043e\u0432\u0438\u0446\u0435"
    ],
    "name:und_x_variant":[
        "Mutowitz"
    ],
    "name:vie_x_preferred":[
        "Mut\u011bjovice"
    ],
    "qs_pg:aaroncc":"CZ",
    "qs_pg:gn_country":"CZ",
    "qs_pg:gn_fcode":"PPL",
    "qs_pg:gn_pop":779,
    "qs_pg:name":"Mut\u011bjovice",
    "qs_pg:name_adm0":"\u010cesk\u00e1 republika",
    "qs_pg:name_adm1":"St\u0159edo\u010desk\u00fd kraj",
    "qs_pg:photos_9k":1,
    "qs_pg:photos_9r":1,
    "qs_pg:photos_all":2,
    "qs_pg:photos_sr":0,
    "qs_pg:pop_sr":2,
    "qs_pg:qs_pg_placetype":"locality",
    "qs_pg:qs_pg_placetype_gp":"Town",
    "qs_pg:woe_adm0":23424810,
    "woe:adm0_id":23424810,
    "woe:name_adm0":"\u010cesk\u00e1 republika",
    "woe:name_adm1":"St\u0159edo\u010desk\u00fd kraj",
    "woe:placetype":"Town",
    "wof:name":"Mut\u011bjovice",
    "wof:placetype":"locality",
    "wof:population":779
},
  "geometry": {"coordinates":[13.70951,50.19425],"type":"Point"}
}