{
  "type": "Feature",
  "properties": {
    "gn:admin1_code":"80",
    "gn:admin2_code":"0612",
    "gn:asciiname":"Sucha",
    "gn:cc2":"CZ",
    "gn:country_code":"CZ",
    "gn:dem":567,
    "gn:feature_class":"P",
    "gn:feature_code":"PPL",
    "gn:name":"Such\u00e1",
    "gn:population":240,
    "gn:timezone":"Europe/Prague",
    "iso:country":"CZ",
    "name:und_x_variant":[
        "D\u00fcrre"
    ],
    "wof:name":"Sucha",
    "wof:placetype":"locality",
    "wof:population":240
},
  "geometry": {"coordinates":[15.57744,49.30101],"type":"Point"}
}