{
  "type": "Feature",
  "properties": {
    "gn:admin1_code":"80",
    "gn:admin2_code":"0612",
    "gn:asciiname":"Sucha",
    "gn:cc2":"CZ",
    "gn:country_code":"CZ",
    "gn:dem":567,
    "gn:feature_class":"P",
    "gn:feature_code":"PPL",
    "gn:name":"Such\u00e1",
    "gn:population":240,
    "gn:timezone":"Europe/Prague",
    "iso:country":"CZ",
    "name:azb_x_preferred":[
        "\u0633\u0648\u062e\u0627"
    ],
    "name:ceb_x_preferred":[
        "Such\u00e1"
    ],
    "name:ces_x_preferred":[
        "Such\u00e1"
    ],
    "name:deu_x_preferred":[
        "Such\u00e1"
    ],
    "name:eus_x_preferred":[
        "Such\u00e1"
    ],
    "name:fas_x_preferred":[
        "\u0633\u0648\u062e\u0627"
    ],
    "name:ita_x_preferred":[
        "Such\u00e1"
    ],
    "name:msa_x_preferred":[
        "Such\u00e1"
    ],
    "name:nld_x_preferred":[
        "Such\u00e1"
    ],
    "name:pol_x_preferred":[
        "Such\u00e1"
    ],
    "name:por_x_preferred":[
        "Such\u00e1"
    ],
    "name:slk_x_preferred":[
        "Such\u00e1"
    ],
    "name:spa_x_preferred":[
        "Such\u00e1"
    ],
    "name:srp_x_preferred":[
        "\u0421\u0443\u0445\u0430"
    ],
    "name:swe_x_preferred":[
        "Such\u00e1"
    ],
    "name:und_x_variant":[
        "D\u00fcrre"
    ],
    "name:vie_x_preferred":[
        "Such\u00e1"
    ],
    "wof:name":"Sucha",
    "wof:placetype":"locality",
    "wof:population":240
},
  "geometry": {"coordinates":[15.57744,49.30101],"type":"Point"}
}