{
  "type": "Feature",
  "properties": {
    "gn:admin1_code":"79",
    "gn:admin2_code":"0316",
    "gn:asciiname":"Stridka",
    "gn:country_code":"CZ",
    "gn:dem":508,
    "gn:feature_class":"P",
    "gn:feature_code":"PPL",
    "gn:name":"St\u0159\u00eddka",
    "gn:population":0,
    "gn:timezone":"Europe/Prague",
    "iso:country":"CZ",
    "wof:name":"Stridka",
    "wof:placetype":"locality"
},
  "geometry": {"coordinates":[13.80935,49.17925],"type":"Point"}
}