{
  "type": "Feature",
  "properties": {
    "gn:admin1_code":"86",
    "gn:admin2_code":"0532",
    "gn:asciiname":"Zika",
    "gn:country_code":"CZ",
    "gn:dem":261,
    "gn:feature_class":"P",
    "gn:feature_code":"PPL",
    "gn:name":"\u017d\u00edka",
    "gn:population":0,
    "gn:timezone":"Europe/Prague",
    "iso:country":"CZ",
    "wof:name":"Zika",
    "wof:placetype":"locality"
},
  "geometry": {"coordinates":[16.06418,49.99773],"type":"Point"}
}