{
  "type": "Feature",
  "properties": {
    "gn:admin1_code":"81.0",
    "gn:admin2_code":"0411",
    "gn:asciiname":"Milikov",
    "gn:country_code":"CZ",
    "gn:dem":465,
    "gn:feature_class":"P",
    "gn:feature_code":"PPL",
    "gn:name":"Mil\u00edkov",
    "gn:population":216,
    "gn:timezone":"Europe/Prague",
    "iso:country":"CZ",
    "name:azb_x_preferred":[
        "\u0645\u06cc\u0644\u06cc\u06a9\u0648\u0641"
    ],
    "name:ceb_x_preferred":[
        "Mil\u00edkov"
    ],
    "name:ces_x_preferred":[
        "Mil\u00edkov"
    ],
    "name:eus_x_preferred":[
        "Mil\u00edkov"
    ],
    "name:fas_x_preferred":[
        "\u0645\u06cc\u0644\u06cc\u06a9\u0648\u0641"
    ],
    "name:hun_x_preferred":[
        "Mil\u00edkov"
    ],
    "name:ita_x_preferred":[
        "Mil\u00edkov"
    ],
    "name:msa_x_preferred":[
        "Mil\u00edkov"
    ],
    "name:nld_x_preferred":[
        "Mil\u00edkov"
    ],
    "name:pol_x_preferred":[
        "Mil\u00edkov"
    ],
    "name:por_x_preferred":[
        "Mil\u00edkov"
    ],
    "name:slk_x_preferred":[
        "Mil\u00edkov"
    ],
    "name:spa_x_preferred":[
        "Mil\u00edkov"
    ],
    "name:srp_x_preferred":[
        "\u041c\u0438\u043b\u0438\u043a\u043e\u0432"
    ],
    "name:und_x_variant":[
        "Miltigau"
    ],
    "name:vie_x_preferred":[
        "Mil\u00edkov"
    ],
    "wof:name":"Milikov",
    "wof:placetype":"locality",
    "wof:population":216
},
  "geometry": {"coordinates":[12.5476,50.05577],"type":"Point"}
}