{
  "type": "Feature",
  "properties": {
    "gn:admin1_code":"81.0",
    "gn:admin2_code":"0411",
    "gn:asciiname":"Milikov",
    "gn:country_code":"CZ",
    "gn:dem":465,
    "gn:feature_class":"P",
    "gn:feature_code":"PPL",
    "gn:name":"Mil\u00edkov",
    "gn:population":216,
    "gn:timezone":"Europe/Prague",
    "iso:country":"CZ",
    "name:und_x_variant":[
        "Miltigau"
    ],
    "wof:name":"Milikov",
    "wof:placetype":"locality",
    "wof:population":216
},
  "geometry": {"coordinates":[12.5476,50.05577],"type":"Point"}
}