{
  "type": "Feature",
  "properties": {
    "gn:admin1_code":"79.0",
    "gn:admin2_code":"0312",
    "gn:asciiname":"Ondrejov",
    "gn:country_code":"CZ",
    "gn:dem":1005,
    "gn:feature_class":"P",
    "gn:feature_code":"PPL",
    "gn:name":"Ond\u0159ejov",
    "gn:population":0,
    "gn:timezone":"Europe/Prague",
    "iso:country":"CZ",
    "name:und_x_variant":[
        "Andreasberg",
        "Ond\u0159ejov"
    ],
    "wof:name":"Ondrejov",
    "wof:placetype":"locality"
},
  "geometry": {"coordinates":[14.0889,48.86667],"type":"Point"}
}