{
  "type": "Feature",
  "properties": {
    "gn:gn_country":"CZ",
    "gn:gn_fcode":"PPL",
    "gn:gn_pop":306,
    "gn:population":306,
    "iso:country":"CZ",
    "name:azb_x_preferred":[
        "\u067e\u06cc\u06a9\u0627\u0631\u062a\u0633"
    ],
    "name:cat_x_preferred":[
        "Pik\u00e1rec"
    ],
    "name:ceb_x_preferred":[
        "Pikarec"
    ],
    "name:ces_x_preferred":[
        "Pik\u00e1rec"
    ],
    "name:deu_x_preferred":[
        "Pik\u00e1rec"
    ],
    "name:eng_x_preferred":[
        "Pik\u00e1rec"
    ],
    "name:eus_x_preferred":[
        "Pik\u00e1rec"
    ],
    "name:fas_x_preferred":[
        "\u067e\u06cc\u06a9\u0627\u0631\u062a\u0633"
    ],
    "name:fra_x_preferred":[
        "Pik\u00e1rec"
    ],
    "name:hun_x_preferred":[
        "Pik\u00e1rec"
    ],
    "name:ita_x_preferred":[
        "Pik\u00e1rec"
    ],
    "name:msa_x_preferred":[
        "Pik\u00e1rec"
    ],
    "name:nan_x_preferred":[
        "Pik\u00e1rec"
    ],
    "name:nld_x_preferred":[
        "Pik\u00e1rec"
    ],
    "name:oci_x_preferred":[
        "Pik\u00e1rec"
    ],
    "name:por_x_preferred":[
        "Pik\u00e1rec"
    ],
    "name:rup_x_preferred":[
        "Pik\u00e1rec"
    ],
    "name:slk_x_preferred":[
        "Pik\u00e1rec"
    ],
    "name:spa_x_preferred":[
        "Pik\u00e1rec"
    ],
    "name:swe_x_preferred":[
        "Pikarec"
    ],
    "name:vie_x_preferred":[
        "Pik\u00e1rec"
    ],
    "qs_pg:aaroncc":"CZ",
    "qs_pg:gn_country":"CZ",
    "qs_pg:gn_fcode":"PPL",
    "qs_pg:gn_pop":306,
    "qs_pg:name":"Pik\u00e1rec",
    "qs_pg:name_adm0":"\u010cesk\u00e1 republika",
    "qs_pg:name_adm1":"Kraj Vyso\u010dina",
    "qs_pg:photos_9r":0,
    "qs_pg:photos_sr":0,
    "qs_pg:pop_sr":2,
    "qs_pg:qs_pg_placetype":"locality",
    "qs_pg:qs_pg_placetype_gp":"Town",
    "qs_pg:woe_adm0":23424810,
    "woe:adm0_id":23424810,
    "woe:name_adm0":"\u010cesk\u00e1 republika",
    "woe:name_adm1":"Kraj Vyso\u010dina",
    "woe:placetype":"Town",
    "wof:name":"Pik\u00e1rec",
    "wof:placetype":"locality",
    "wof:population":306
},
  "geometry": {"coordinates":[16.12239,49.43241],"type":"Point"}
}