{
  "type": "Feature",
  "properties": {
    "gn:admin1_code":"89.0",
    "gn:admin2_code":"0423",
    "gn:asciiname":"Mukarov",
    "gn:cc2":"CZ",
    "gn:country_code":"CZ",
    "gn:dem":564,
    "gn:feature_class":"P",
    "gn:feature_code":"PPL",
    "gn:name":"Muka\u0159ov",
    "gn:population":0,
    "gn:timezone":"Europe/Prague",
    "iso:country":"CZ",
    "name:und_x_variant":[
        "Munker"
    ],
    "wof:name":"Mukarov",
    "wof:placetype":"locality"
},
  "geometry": {"coordinates":[14.29682,50.64696],"type":"Point"}
}