{
  "type": "Feature",
  "properties": {
    "gn:country":"CZ",
    "gn:fcode":"PPL",
    "gn:population":685,
    "iso:country":"CZ",
    "name:azb_x_preferred":[
        "\u062f\u0648\u0644\u0646\u06cc \u0631\u0627\u062f\u062e\u0648\u0648\u0627"
    ],
    "name:ceb_x_preferred":[
        "Doln\u00ed Radechov\u00e1"
    ],
    "name:ces_x_preferred":[
        "Doln\u00ed Radechov\u00e1"
    ],
    "name:deu_x_preferred":[
        "Doln\u00ed Radechov\u00e1"
    ],
    "name:eng_x_preferred":[
        "Doln\u00ed Radechov\u00e1"
    ],
    "name:eus_x_preferred":[
        "Doln\u00ed Radechov\u00e1"
    ],
    "name:fas_x_preferred":[
        "\u062f\u0648\u0644\u0646\u06cc \u0631\u0627\u062f\u062e\u0648\u0648\u0627"
    ],
    "name:fra_x_preferred":[
        "Doln\u00ed Radechov\u00e1"
    ],
    "name:hun_x_preferred":[
        "Doln\u00ed Radechov\u00e1"
    ],
    "name:ita_x_preferred":[
        "Doln\u00ed Radechov\u00e1"
    ],
    "name:msa_x_preferred":[
        "Doln\u00ed Radechov\u00e1"
    ],
    "name:nan_x_preferred":[
        "Doln\u00ed Radechov\u00e1"
    ],
    "name:nld_x_preferred":[
        "Doln\u00ed Radechov\u00e1"
    ],
    "name:pol_x_preferred":[
        "Doln\u00ed Radechov\u00e1"
    ],
    "name:por_x_preferred":[
        "Doln\u00ed Radechov\u00e1"
    ],
    "name:rup_x_preferred":[
        "Doln\u00ed Radechov\u00e1"
    ],
    "name:slk_x_preferred":[
        "Doln\u00ed Radechov\u00e1"
    ],
    "name:spa_x_preferred":[
        "Doln\u00ed Radechov\u00e1"
    ],
    "name:srp_x_preferred":[
        "\u0414\u043e\u043b\u045a\u0438 \u0420\u0430\u0434\u0435\u0445\u043e\u0432\u0430"
    ],
    "name:swe_x_preferred":[
        "Doln\u00ed Radechov\u00e1"
    ],
    "name:vie_x_preferred":[
        "Doln\u00ed Radechov\u00e1"
    ],
    "qs_pg:aaroncc":"CZ",
    "qs_pg:gn_country":"CZ",
    "qs_pg:gn_fcode":"PPL",
    "qs_pg:gn_pop":685,
    "qs_pg:name":"Doln\u00ed Radechov\u00e1",
    "qs_pg:name_adm0":"\u010cesk\u00e1 republika",
    "qs_pg:name_adm1":"Kr\u00e1lov\u00e9hradeck\u00fd kraj",
    "qs_pg:photos_9r":0,
    "qs_pg:photos_sr":0,
    "qs_pg:pop_sr":2,
    "qs_pg:qs_pg_placetype":"locality",
    "qs_pg:qs_pg_placetype_gp":"Town",
    "qs_pg:woe_adm0":23424810,
    "woe:adm0_id":23424810,
    "woe:name_adm0":"\u010cesk\u00e1 republika",
    "woe:name_adm1":"Kr\u00e1lov\u00e9hradeck\u00fd kraj",
    "woe:placetype":"Town",
    "wof:name":"Doln\u00ed Radechov\u00e1",
    "wof:placetype":"locality",
    "wof:population":685
},
  "geometry": {"coordinates":[16.15123,50.43834],"type":"Point"}
}