{
  "type": "Feature",
  "properties": {
    "gn:admin1_code":"79.0",
    "gn:admin2_code":"0314",
    "gn:asciiname":"Mlaky",
    "gn:country_code":"CZ",
    "gn:dem":435,
    "gn:feature_class":"P",
    "gn:feature_code":"PPL",
    "gn:name":"Mlaky",
    "gn:population":0,
    "gn:timezone":"Europe/Prague",
    "iso:country":"CZ",
    "wof:name":"Mlaky",
    "wof:placetype":"locality"
},
  "geometry": {"coordinates":[14.25213,49.2955],"type":"Point"}
}