{
  "type": "Feature",
  "properties": {
    "gn:admin1_code":"89.0",
    "gn:admin2_code":"0421",
    "gn:asciiname":"Novina",
    "gn:cc2":"CZ",
    "gn:country_code":"CZ",
    "gn:dem":297,
    "gn:feature_class":"P",
    "gn:feature_code":"PPL",
    "gn:name":"Novina",
    "gn:population":0,
    "gn:timezone":"Europe/Prague",
    "iso:country":"CZ",
    "name:und_x_variant":[
        "Neuland",
        "Novina"
    ],
    "wof:name":"Novina",
    "wof:placetype":"locality"
},
  "geometry": {"coordinates":[14.31667,50.73333],"type":"Point"}
}