{
  "type": "Feature",
  "properties": {
    "gn:admin1_code":"82.0",
    "gn:admin2_code":"0522",
    "gn:asciiname":"Mlynec",
    "gn:country_code":"CZ",
    "gn:dem":211,
    "gn:feature_class":"P",
    "gn:feature_code":"PPL",
    "gn:name":"Ml\u00fdnec",
    "gn:population":0,
    "gn:timezone":"Europe/Prague",
    "iso:country":"CZ",
    "wof:name":"Mlynec",
    "wof:placetype":"locality"
},
  "geometry": {"coordinates":[15.22645,50.31471],"type":"Point"}
}