{
  "type": "Feature",
  "properties": {
    "gn:admin1_code":"79",
    "gn:admin2_code":"0311",
    "gn:asciiname":"Vranov",
    "gn:country_code":"CZ",
    "gn:dem":422,
    "gn:feature_class":"P",
    "gn:feature_code":"PPL",
    "gn:name":"Vranov",
    "gn:population":0,
    "gn:timezone":"Europe/Prague",
    "iso:country":"CZ",
    "wof:name":"Vranov",
    "wof:placetype":"locality"
},
  "geometry": {"coordinates":[14.35055,49.30375],"type":"Point"}
}