{
  "type": "Feature",
  "properties": {
    "gn:admin1_code":"79",
    "gn:admin2_code":"0311",
    "gn:asciiname":"Vranov",
    "gn:country_code":"CZ",
    "gn:dem":422,
    "gn:feature_class":"P",
    "gn:feature_code":"PPL",
    "gn:name":"Vranov",
    "gn:population":0,
    "gn:timezone":"Europe/Prague",
    "iso:country":"CZ",
    "name:ceb_x_preferred":[
        "Vranov"
    ],
    "name:ces_x_preferred":[
        "Vranov"
    ],
    "name:deu_x_preferred":[
        "Vranov"
    ],
    "name:epo_x_preferred":[
        "Vranov"
    ],
    "name:fra_x_preferred":[
        "Vranov"
    ],
    "name:ita_x_preferred":[
        "Vranov"
    ],
    "name:nld_x_preferred":[
        "Vranov"
    ],
    "name:oci_x_preferred":[
        "Vranov"
    ],
    "name:pol_x_preferred":[
        "Vranov"
    ],
    "name:rus_x_preferred":[
        "\u0412\u0440\u0430\u043d\u043e\u0432"
    ],
    "name:slk_x_preferred":[
        "Vranov"
    ],
    "name:srp_x_preferred":[
        "\u0412\u0440\u0430\u043d\u043e\u0432"
    ],
    "name:swe_x_preferred":[
        "Vranov"
    ],
    "wof:name":"Vranov",
    "wof:placetype":"locality"
},
  "geometry": {"coordinates":[14.35055,49.30375],"type":"Point"}
}