{
  "type": "Feature",
  "properties": {
    "gn:gn_country":"CZ",
    "gn:gn_fcode":"PPL",
    "gn:gn_pop":648,
    "gn:population":648,
    "iso:country":"CZ",
    "name:cze_x_preferred":[
        "Vojkovice"
    ],
    "name:dut_x_preferred":[
        "Vojkovice"
    ],
    "name:eng_x_preferred":[
        "Vojkovice"
    ],
    "name:fre_x_preferred":[
        "Vojkovice"
    ],
    "name:hun_x_preferred":[
        "Vojkovice"
    ],
    "name:ita_x_preferred":[
        "Vojkovice"
    ],
    "name:may_x_preferred":[
        "Vojkovice"
    ],
    "name:nan_x_preferred":[
        "Vojkovice"
    ],
    "name:per_x_preferred":[
        "\u0648\u0648\u06cc\u06a9\u0648\u0648\u06cc\u062a\u0633\u0647"
    ],
    "name:pol_x_preferred":[
        "Vojkovice"
    ],
    "name:por_x_preferred":[
        "Vojkovice"
    ],
    "name:rup_x_preferred":[
        "Vojkovice"
    ],
    "name:slo_x_preferred":[
        "Vojkovice"
    ],
    "name:srp_x_preferred":[
        "\u0412\u043e\u0458\u043a\u043e\u0432\u0438\u0446\u0435"
    ],
    "name:swe_x_preferred":[
        "Vojkovice"
    ],
    "name:vie_x_preferred":[
        "Vojkovice"
    ],
    "qs_pg:aaroncc":"CZ",
    "qs_pg:gn_country":"CZ",
    "qs_pg:gn_fcode":"PPL",
    "qs_pg:gn_pop":648,
    "qs_pg:name":"Vojkovice",
    "qs_pg:name_adm0":"\u010cesk\u00e1 republika",
    "qs_pg:name_adm1":"St\u0159edo\u010desk\u00fd kraj",
    "qs_pg:photos_9r":0,
    "qs_pg:photos_sr":0,
    "qs_pg:pop_sr":2,
    "qs_pg:qs_pg_placetype":"locality",
    "qs_pg:qs_pg_placetype_gp":"Town",
    "qs_pg:woe_adm0":23424810,
    "woe:adm0_id":23424810,
    "woe:name_adm0":"\u010cesk\u00e1 republika",
    "woe:name_adm1":"St\u0159edo\u010desk\u00fd kraj",
    "woe:placetype":"Town",
    "wof:name":"Vojkovice",
    "wof:placetype":"locality",
    "wof:population":648
},
  "geometry": {"coordinates":[14.37522,50.29613],"type":"Point"}
}