{
  "type": "Feature",
  "properties": {
    "gn:admin1_code":"88.0",
    "gn:admin2_code":"020B",
    "gn:asciiname":"Boudy",
    "gn:country_code":"CZ",
    "gn:dem":411,
    "gn:feature_class":"P",
    "gn:feature_code":"PPL",
    "gn:name":"Boudy",
    "gn:population":0,
    "gn:timezone":"Europe/Prague",
    "iso:country":"CZ",
    "name:azb_x_preferred":[
        "\u0628\u0648\u0648\u062f\u06cc"
    ],
    "name:ceb_x_preferred":[
        "Boudy"
    ],
    "name:ces_x_preferred":[
        "Boudy"
    ],
    "name:epo_x_preferred":[
        "Boudy"
    ],
    "name:eus_x_preferred":[
        "Boudy"
    ],
    "name:fas_x_preferred":[
        "\u0628\u0648\u0648\u062f\u06cc"
    ],
    "name:fra_x_preferred":[
        "Boudy"
    ],
    "name:hun_x_preferred":[
        "Boudy"
    ],
    "name:ita_x_preferred":[
        "Boudy"
    ],
    "name:msa_x_preferred":[
        "Boudy"
    ],
    "name:nld_x_preferred":[
        "Boudy"
    ],
    "name:por_x_preferred":[
        "Boudy"
    ],
    "name:slk_x_preferred":[
        "Boudy"
    ],
    "name:spa_x_preferred":[
        "Boudy"
    ],
    "name:srp_x_preferred":[
        "\u0411\u043e\u0443\u0434\u0438"
    ],
    "name:swe_x_preferred":[
        "Boudy"
    ],
    "name:vie_x_preferred":[
        "Boudy"
    ],
    "wof:name":"Boudy",
    "wof:placetype":"locality"
},
  "geometry": {"coordinates":[14.46855,49.59179],"type":"Point"}
}