{
  "type": "Feature",
  "properties": {
    "gn:admin1_code":"87",
    "gn:admin2_code":"0324",
    "gn:asciiname":"Vodni Ujezd",
    "gn:country_code":"CZ",
    "gn:dem":326,
    "gn:feature_class":"P",
    "gn:feature_code":"PPL",
    "gn:name":"Vodn\u00ed \u00dajezd",
    "gn:population":0,
    "gn:timezone":"Europe/Prague",
    "iso:country":"CZ",
    "name:und_x_variant":[
        "Wasser-Aujezd",
        "Vodn\u00ed \u00dajezd"
    ],
    "wof:name":"Vodni Ujezd",
    "wof:placetype":"locality"
},
  "geometry": {"coordinates":[13.25755,49.65749],"type":"Point"}
}