{
  "type": "Feature",
  "properties": {
    "gn:admin1_code":"89.0",
    "gn:admin2_code":"0424",
    "gn:asciiname":"Detan",
    "gn:country_code":"CZ",
    "gn:dem":428,
    "gn:feature_class":"P",
    "gn:feature_code":"PPL",
    "gn:name":"D\u011bta\u0148",
    "gn:population":0,
    "gn:timezone":"Europe/Prague",
    "iso:country":"CZ",
    "name:und_x_variant":[
        "G\u00f6desin",
        "D\u011bta\u0148"
    ],
    "wof:name":"Detan",
    "wof:placetype":"locality"
},
  "geometry": {"coordinates":[13.30857,50.19443],"type":"Point"}
}