{
  "type": "Feature",
  "properties": {
    "gn:admin1_code":"81.0",
    "gn:admin2_code":"0412",
    "gn:asciiname":"Cihana",
    "gn:country_code":"CZ",
    "gn:dem":662,
    "gn:feature_class":"P",
    "gn:feature_code":"PPL",
    "gn:name":"\u010c\u00edhan\u00e1",
    "gn:population":0,
    "gn:timezone":"Europe/Prague",
    "iso:country":"CZ",
    "wof:name":"Cihana",
    "wof:placetype":"locality"
},
  "geometry": {"coordinates":[12.98426,50.12342],"type":"Point"}
}