{
  "type": "Feature",
  "properties": {
    "gn:gn_country":"CZ",
    "gn:gn_fcode":"PPL",
    "gn:gn_pop":125,
    "gn:population":125,
    "iso:country":"CZ",
    "name:ces_x_preferred":[
        "Slan\u00edk"
    ],
    "name:deu_x_preferred":[
        "Slan\u00edk"
    ],
    "name:eng_x_preferred":[
        "Slan\u00edk"
    ],
    "name:fra_x_preferred":[
        "Slan\u00edk"
    ],
    "name:hun_x_preferred":[
        "Slan\u00edk"
    ],
    "name:ita_x_preferred":[
        "Slan\u00edk"
    ],
    "name:msa_x_preferred":[
        "Slan\u00edk"
    ],
    "name:nld_x_preferred":[
        "Slan\u00edk"
    ],
    "name:por_x_preferred":[
        "Slan\u00edk"
    ],
    "name:slk_x_preferred":[
        "Slan\u00edk"
    ],
    "name:srp_x_preferred":[
        "\u0421\u043b\u0430\u045a\u0438\u043a"
    ],
    "name:swe_x_preferred":[
        "Slan\u00edk"
    ],
    "name:vie_x_preferred":[
        "Slan\u00edk"
    ],
    "qs_pg:aaroncc":"CZ",
    "qs_pg:gn_country":"CZ",
    "qs_pg:gn_fcode":"PPL",
    "qs_pg:gn_pop":125,
    "qs_pg:name":"Slan\u00edk",
    "qs_pg:name_adm0":"\u010cesk\u00e1 republika",
    "qs_pg:name_adm1":"Jiho\u010desk\u00fd kraj",
    "qs_pg:photos_9r":0,
    "qs_pg:photos_sr":0,
    "qs_pg:pop_sr":1,
    "qs_pg:qs_pg_placetype":"locality",
    "qs_pg:qs_pg_placetype_gp":"Town",
    "qs_pg:woe_adm0":23424810,
    "woe:adm0_id":23424810,
    "woe:name_adm0":"\u010cesk\u00e1 republika",
    "woe:name_adm1":"Jiho\u010desk\u00fd kraj",
    "woe:placetype":"Town",
    "wof:name":"Slan\u00edk",
    "wof:placetype":"locality",
    "wof:population":125
},
  "geometry": {"coordinates":[13.95157,49.26828],"type":"Point"}
}