{
  "type": "Feature",
  "properties": {
    "gn:admin1_code":"89.0",
    "gn:admin2_code":"0423",
    "gn:asciiname":"Dolni Nezly",
    "gn:country_code":"CZ",
    "gn:dem":274,
    "gn:feature_class":"P",
    "gn:feature_code":"PPL",
    "gn:name":"Doln\u00ed Nezly",
    "gn:population":0,
    "gn:timezone":"Europe/Prague",
    "iso:country":"CZ",
    "wof:name":"Dolni Nezly",
    "wof:placetype":"locality"
},
  "geometry": {"coordinates":[14.22695,50.56863],"type":"Point"}
}