{
  "type": "Feature",
  "properties": {
    "gn:admin1_code":"90.0",
    "gn:admin2_code":"0724",
    "gn:asciiname":"Paseky",
    "gn:country_code":"CZ",
    "gn:dem":470,
    "gn:feature_class":"P",
    "gn:feature_code":"PPL",
    "gn:name":"Paseky",
    "gn:population":0,
    "gn:timezone":"Europe/Prague",
    "iso:country":"CZ",
    "wof:name":"Paseky",
    "wof:placetype":"locality"
},
  "geometry": {"coordinates":[18.09393,49.12744],"type":"Point"}
}