{
  "type": "Feature",
  "properties": {
    "gn:gn_country":"CZ",
    "gn:gn_fcode":"PPL",
    "gn:gn_pop":318,
    "gn:population":318,
    "iso:country":"CZ",
    "name:bul_x_preferred":[
        "\u0417\u0431\u0439\u0442\u0438\u043d\u0439"
    ],
    "name:ces_x_preferred":[
        "Zbytiny"
    ],
    "name:deu_x_preferred":[
        "Oberhaid"
    ],
    "name:deu_x_variant":[
        "Zbytiny"
    ],
    "name:eng_x_preferred":[
        "Zbytiny"
    ],
    "name:fas_x_preferred":[
        "\u0632\u0628\u06cc\u062a\u06cc\u0646\u06cc"
    ],
    "name:fra_x_preferred":[
        "Zbytiny"
    ],
    "name:hun_x_preferred":[
        "Zbytiny"
    ],
    "name:ita_x_preferred":[
        "Zbytiny"
    ],
    "name:msa_x_preferred":[
        "Zbytiny"
    ],
    "name:nan_x_preferred":[
        "Zbytiny"
    ],
    "name:nld_x_preferred":[
        "Zbytiny"
    ],
    "name:por_x_preferred":[
        "Zbytiny"
    ],
    "name:rup_x_preferred":[
        "Zbytiny"
    ],
    "name:slk_x_preferred":[
        "Zbytiny"
    ],
    "name:srp_x_preferred":[
        "\u0417\u0431\u0438\u0442\u0438\u043d\u0438"
    ],
    "name:swe_x_preferred":[
        "Zbytiny"
    ],
    "name:vie_x_preferred":[
        "Zbytiny"
    ],
    "qs_pg:aaroncc":"CZ",
    "qs_pg:gn_country":"CZ",
    "qs_pg:gn_fcode":"PPL",
    "qs_pg:gn_pop":318,
    "qs_pg:name":"Zbytiny",
    "qs_pg:name_adm0":"\u010cesk\u00e1 republika",
    "qs_pg:name_adm1":"Jiho\u010desk\u00fd kraj",
    "qs_pg:photos_9k":1,
    "qs_pg:photos_9r":1,
    "qs_pg:photos_all":1,
    "qs_pg:photos_sr":0,
    "qs_pg:pop_sr":2,
    "qs_pg:qs_pg_placetype":"locality",
    "qs_pg:qs_pg_placetype_gp":"Town",
    "qs_pg:woe_adm0":23424810,
    "woe:adm0_id":23424810,
    "woe:name_adm0":"\u010cesk\u00e1 republika",
    "woe:name_adm1":"Jiho\u010desk\u00fd kraj",
    "woe:placetype":"Town",
    "wof:name":"Zbytiny",
    "wof:placetype":"locality",
    "wof:population":318
},
  "geometry": {"coordinates":[13.97805,48.94262],"type":"Point"}
}