{
  "type": "Feature",
  "properties": {
    "gn:gn_country":"CZ",
    "gn:gn_fcode":"PPL",
    "gn:gn_pop":243,
    "gn:population":243,
    "iso:country":"CZ",
    "name:cze_x_preferred":[
        "Rovn\u00e1"
    ],
    "name:dut_x_preferred":[
        "Rovn\u00e1"
    ],
    "name:eng_x_preferred":[
        "Rovn\u00e1"
    ],
    "name:fre_x_preferred":[
        "Rovn\u00e1"
    ],
    "name:ger_x_preferred":[
        "Rovn\u00e1 u Strakonic"
    ],
    "name:hun_x_preferred":[
        "Rovn\u00e1"
    ],
    "name:ita_x_preferred":[
        "Rovn\u00e1"
    ],
    "name:may_x_preferred":[
        "Rovn\u00e1"
    ],
    "name:per_x_preferred":[
        "\u0631\u0648\u0648\u0646\u0627"
    ],
    "name:por_x_preferred":[
        "Rovn\u00e1"
    ],
    "name:rup_x_preferred":[
        "Rovn\u00e1"
    ],
    "name:slo_x_preferred":[
        "Rovn\u00e1"
    ],
    "name:srp_x_preferred":[
        "\u0420\u043e\u0432\u043d\u0430"
    ],
    "name:vie_x_preferred":[
        "Rovn\u00e1"
    ],
    "qs_pg:aaroncc":"CZ",
    "qs_pg:gn_country":"CZ",
    "qs_pg:gn_fcode":"PPL",
    "qs_pg:gn_pop":243,
    "qs_pg:name":"Rovn\u00e1",
    "qs_pg:name_adm0":"\u010cesk\u00e1 republika",
    "qs_pg:name_adm1":"Jiho\u010desk\u00fd kraj",
    "qs_pg:photos_9r":0,
    "qs_pg:photos_sr":0,
    "qs_pg:pop_sr":2,
    "qs_pg:qs_pg_placetype":"locality",
    "qs_pg:qs_pg_placetype_gp":"Town",
    "qs_pg:woe_adm0":23424810,
    "woe:adm0_id":23424810,
    "woe:name_adm0":"\u010cesk\u00e1 republika",
    "woe:name_adm1":"Jiho\u010desk\u00fd kraj",
    "woe:placetype":"Town",
    "wof:name":"Rovn\u00e1",
    "wof:placetype":"locality",
    "wof:population":243
},
  "geometry": {"coordinates":[13.95395,49.28634],"type":"Point"}
}