{
  "type": "Feature",
  "properties": {
    "gn:country":"CZ",
    "gn:fcode":"PPL",
    "gn:population":781,
    "iso:country":"CZ",
    "name:azb_x_preferred":[
        "\u062f\u0648\u06a9\u0648\u0648\u0627\u0646\u06cc"
    ],
    "name:bul_x_preferred":[
        "\u0414\u0443\u043a\u043e\u0432\u0430\u043d\u0439"
    ],
    "name:ceb_x_preferred":[
        "Dukovany"
    ],
    "name:ces_x_preferred":[
        "Dukovany"
    ],
    "name:deu_x_preferred":[
        "Dukovany"
    ],
    "name:eng_x_preferred":[
        "Dukovany"
    ],
    "name:epo_x_preferred":[
        "Dukovany"
    ],
    "name:eus_x_preferred":[
        "Dukovany"
    ],
    "name:fas_x_preferred":[
        "\u062f\u0648\u06a9\u0648\u0648\u0627\u0646\u06cc"
    ],
    "name:fra_x_preferred":[
        "Dukovany"
    ],
    "name:hun_x_preferred":[
        "Dukovany"
    ],
    "name:ita_x_preferred":[
        "Dukovany"
    ],
    "name:kor_x_preferred":[
        "\ub450\ucf54\ubc14\ub2c8"
    ],
    "name:msa_x_preferred":[
        "Dukovany"
    ],
    "name:nan_x_preferred":[
        "Dukovany"
    ],
    "name:nld_x_preferred":[
        "Dukovany"
    ],
    "name:pol_x_preferred":[
        "Dukovany"
    ],
    "name:por_x_preferred":[
        "Dukovany"
    ],
    "name:slk_x_preferred":[
        "Dukovany"
    ],
    "name:spa_x_preferred":[
        "Dukovany"
    ],
    "name:swe_x_preferred":[
        "Dukovany"
    ],
    "name:und_x_variant":[
        "Dukowan"
    ],
    "name:vie_x_preferred":[
        "Dukovany"
    ],
    "qs_pg:aaroncc":"CZ",
    "qs_pg:gn_country":"CZ",
    "qs_pg:gn_fcode":"PPL",
    "qs_pg:gn_pop":781,
    "qs_pg:name":"Dukovany",
    "qs_pg:name_adm0":"\u010cesk\u00e1 republika",
    "qs_pg:name_adm1":"Kraj Vyso\u010dina",
    "qs_pg:photos_9k":1,
    "qs_pg:photos_9r":1,
    "qs_pg:photos_all":2,
    "qs_pg:photos_sr":0,
    "qs_pg:pop_sr":2,
    "qs_pg:qs_pg_placetype":"locality",
    "qs_pg:qs_pg_placetype_gp":"Town",
    "qs_pg:woe_adm0":23424810,
    "woe:adm0_id":23424810,
    "woe:name_adm0":"\u010cesk\u00e1 republika",
    "woe:name_adm1":"Kraj Vyso\u010dina",
    "woe:placetype":"Town",
    "wof:name":"Dukovany",
    "wof:placetype":"locality",
    "wof:population":781
},
  "geometry": {"coordinates":[16.19218,49.08125],"type":"Point"}
}