{
  "type": "Feature",
  "properties": {
    "gn:admin1_code":"89.0",
    "gn:admin2_code":"0423",
    "gn:asciiname":"Hnevice",
    "gn:country_code":"CZ",
    "gn:dem":159,
    "gn:feature_class":"P",
    "gn:feature_code":"PPL",
    "gn:name":"Hn\u011bvice",
    "gn:population":0,
    "gn:timezone":"Europe/Prague",
    "iso:country":"CZ",
    "name:und_x_variant":[
        "Hn\u011bwitz",
        "Hn\u011bvice"
    ],
    "wof:name":"Hnevice",
    "wof:placetype":"locality"
},
  "geometry": {"coordinates":[14.36781,50.44619],"type":"Point"}
}