{
  "type": "Feature",
  "properties": {
    "gn:country":"CZ",
    "gn:fcode":"PPL",
    "gn:population":180,
    "iso:country":"CZ",
    "name:azb_x_preferred":[
        "\u0644\u06cc\u067e\u0648\u0648\u06cc\u062a\u0633\u0647"
    ],
    "name:ceb_x_preferred":[
        "Lipovice"
    ],
    "name:ces_x_preferred":[
        "Lipovice"
    ],
    "name:deu_x_preferred":[
        "Lipovice"
    ],
    "name:eng_x_preferred":[
        "Lipovice"
    ],
    "name:eus_x_preferred":[
        "Lipovice"
    ],
    "name:fas_x_preferred":[
        "\u0644\u06cc\u067e\u0648\u0648\u06cc\u062a\u0633\u0647"
    ],
    "name:fra_x_preferred":[
        "Lipovice"
    ],
    "name:hun_x_preferred":[
        "Lipovice"
    ],
    "name:ita_x_preferred":[
        "Lipovice"
    ],
    "name:msa_x_preferred":[
        "Lipovice"
    ],
    "name:nan_x_preferred":[
        "Lipovice"
    ],
    "name:nld_x_preferred":[
        "Lipovice"
    ],
    "name:por_x_preferred":[
        "Lipovice"
    ],
    "name:rup_x_preferred":[
        "Lipovice"
    ],
    "name:slk_x_preferred":[
        "Lipovice"
    ],
    "name:spa_x_preferred":[
        "Lipovice"
    ],
    "name:srp_x_preferred":[
        "\u041b\u0438\u043f\u043e\u0432\u0438\u0446\u0435"
    ],
    "name:swe_x_preferred":[
        "Lipovice"
    ],
    "name:vie_x_preferred":[
        "Lipovice"
    ],
    "qs_pg:aaroncc":"CZ",
    "qs_pg:gn_country":"CZ",
    "qs_pg:gn_fcode":"PPL",
    "qs_pg:gn_pop":180,
    "qs_pg:name":"Lipovice",
    "qs_pg:name_adm0":"\u010cesk\u00e1 republika",
    "qs_pg:name_adm1":"Jiho\u010desk\u00fd kraj",
    "qs_pg:photos_9r":0,
    "qs_pg:photos_sr":0,
    "qs_pg:pop_sr":1,
    "qs_pg:qs_pg_placetype":"locality",
    "qs_pg:qs_pg_placetype_gp":"Town",
    "qs_pg:woe_adm0":23424810,
    "woe:adm0_id":23424810,
    "woe:name_adm0":"\u010cesk\u00e1 republika",
    "woe:name_adm1":"Jiho\u010desk\u00fd kraj",
    "woe:placetype":"Town",
    "wof:name":"Lipovice",
    "wof:placetype":"locality",
    "wof:population":180
},
  "geometry": {"coordinates":[13.99388,49.10053],"type":"Point"}
}