{
  "type": "Feature",
  "properties": {
    "gn:admin1_code":"79",
    "gn:admin2_code":"0317",
    "gn:asciiname":"Veselka",
    "gn:country_code":"CZ",
    "gn:dem":424,
    "gn:feature_class":"P",
    "gn:feature_code":"PPL",
    "gn:name":"Veselka",
    "gn:population":0,
    "gn:timezone":"Europe/Prague",
    "iso:country":"CZ",
    "name:fra_x_preferred":[
        "Veselka"
    ],
    "name:ukr_x_preferred":[
        "\u0412\u0435\u0441\u0435\u043b\u043a\u0430"
    ],
    "wof:name":"Veselka",
    "wof:placetype":"locality"
},
  "geometry": {"coordinates":[14.6911,49.28017],"type":"Point"}
}