{
  "type": "Feature",
  "properties": {
    "gn:admin1_code":"79",
    "gn:admin2_code":"0314",
    "gn:asciiname":"Zahradka",
    "gn:country_code":"CZ",
    "gn:dem":454,
    "gn:feature_class":"P",
    "gn:feature_code":"PPL",
    "gn:name":"Zahr\u00e1dka",
    "gn:population":0,
    "gn:timezone":"Europe/Prague",
    "iso:country":"CZ",
    "wof:name":"Zahradka",
    "wof:placetype":"locality"
},
  "geometry": {"coordinates":[14.22682,49.49266],"type":"Point"}
}