{
  "type": "Feature",
  "properties": {
    "gn:admin1_code":"81.0",
    "gn:admin2_code":"0412",
    "gn:asciiname":"Poritsch",
    "gn:country_code":"CZ",
    "gn:dem":440,
    "gn:feature_class":"P",
    "gn:feature_code":"PPL",
    "gn:name":"Poritsch",
    "gn:population":0,
    "gn:timezone":"Europe/Prague",
    "iso:country":"CZ",
    "name:und_x_variant":[
        "Po\u0159\u00ed\u010d\u00ed"
    ],
    "wof:name":"Poritsch",
    "wof:placetype":"locality"
},
  "geometry": {"coordinates":[13.2763,50.08884000000001],"type":"Point"}
}