{
  "type": "Feature",
  "properties": {
    "gn:admin1_code":"87.0",
    "gn:admin2_code":"0322",
    "gn:asciiname":"Paseka",
    "gn:country_code":"CZ",
    "gn:dem":880,
    "gn:feature_class":"P",
    "gn:feature_code":"PPL",
    "gn:name":"Paseka",
    "gn:population":0,
    "gn:timezone":"Europe/Prague",
    "iso:country":"CZ",
    "name:und_x_variant":[
        "Holzschlag",
        "Paseka"
    ],
    "wof:name":"Paseka",
    "wof:placetype":"locality"
},
  "geometry": {"coordinates":[13.33577,49.14803],"type":"Point"}
}