{
  "type": "Feature",
  "properties": {
    "gn:admin1_code":"81.0",
    "gn:admin2_code":"0411",
    "gn:asciiname":"Horni Ves",
    "gn:country_code":"CZ",
    "gn:dem":448,
    "gn:feature_class":"P",
    "gn:feature_code":"PPL",
    "gn:name":"Horn\u00ed Ves",
    "gn:population":0,
    "gn:timezone":"Europe/Prague",
    "iso:country":"CZ",
    "name:und_x_variant":[
        "Oberndorf"
    ],
    "wof:name":"Horni Ves",
    "wof:placetype":"locality"
},
  "geometry": {"coordinates":[12.37627,50.12619],"type":"Point"}
}