{
  "type": "Feature",
  "properties": {
    "gn:admin1_code":"87.0",
    "gn:admin2_code":"0322",
    "gn:asciiname":"Frauenthal",
    "gn:country_code":"CZ",
    "gn:dem":801,
    "gn:feature_class":"P",
    "gn:feature_code":"PPL",
    "gn:name":"Frauenthal",
    "gn:population":0,
    "gn:timezone":"Europe/Prague",
    "iso:country":"CZ",
    "wof:name":"Frauenthal",
    "wof:placetype":"locality"
},
  "geometry": {"coordinates":[13.39556,49.14335],"type":"Point"}
}