{
  "type": "Feature",
  "properties": {
    "gn:admin1_code":"81.0",
    "gn:admin2_code":"0412",
    "gn:asciiname":"Kozlov",
    "gn:country_code":"CZ",
    "gn:dem":564,
    "gn:feature_class":"P",
    "gn:feature_code":"PPL",
    "gn:name":"Kozlov",
    "gn:population":0,
    "gn:timezone":"Europe/Prague",
    "iso:country":"CZ",
    "name:rus_x_preferred":[
        "\u041a\u043e\u0437\u043b\u043e\u0432"
    ],
    "name:und_x_variant":[
        "Koslau",
        "Kozlov"
    ],
    "wof:name":"Kozlov",
    "wof:placetype":"locality"
},
  "geometry": {"coordinates":[13.13484,50.28994],"type":"Point"}
}