{
  "type": "Feature",
  "properties": {
    "gn:admin1_code":"84.0",
    "gn:admin2_code":"0713",
    "gn:asciiname":"Lutotin",
    "gn:country_code":"CZ",
    "gn:dem":257,
    "gn:feature_class":"P",
    "gn:feature_code":"PPL",
    "gn:name":"Lutot\u00edn",
    "gn:population":0,
    "gn:timezone":"Europe/Prague",
    "iso:country":"CZ",
    "wof:name":"Lutotin",
    "wof:placetype":"locality"
},
  "geometry": {"coordinates":[17.03143,49.52],"type":"Point"}
}