{
  "type": "Feature",
  "properties": {
    "gn:admin1_code":"88.0",
    "gn:admin2_code":"020C",
    "gn:asciiname":"Maxovna",
    "gn:country_code":"CZ",
    "gn:dem":464,
    "gn:feature_class":"P",
    "gn:feature_code":"PPL",
    "gn:name":"Maxovna",
    "gn:population":0,
    "gn:timezone":"Europe/Prague",
    "iso:country":"CZ",
    "wof:name":"Maxovna",
    "wof:placetype":"locality"
},
  "geometry": {"coordinates":[13.83112,50.11617],"type":"Point"}
}