{
  "type": "Feature",
  "properties": {
    "gn:country":"CZ",
    "gn:fcode":"PPL",
    "gn:population":158,
    "iso:country":"CZ",
    "name:ceb_x_preferred":[
        "Hn\u011bv\u010deves"
    ],
    "name:ces_x_preferred":[
        "Hn\u011bv\u010deves"
    ],
    "name:deu_x_preferred":[
        "Hn\u011bv\u010deves"
    ],
    "name:eng_x_preferred":[
        "Hn\u011bv\u010deves"
    ],
    "name:eus_x_preferred":[
        "Hn\u011bv\u010deves"
    ],
    "name:fas_x_preferred":[
        "\u0647\u0646\u06cc\u0648\u062a\u0634\u0648\u0633"
    ],
    "name:fra_x_preferred":[
        "Hn\u011bv\u010deves"
    ],
    "name:hun_x_preferred":[
        "Hn\u011bv\u010deves"
    ],
    "name:ita_x_preferred":[
        "Hn\u011bv\u010deves"
    ],
    "name:msa_x_preferred":[
        "Hn\u011bv\u010deves"
    ],
    "name:nan_x_preferred":[
        "Hn\u011bv\u010deves"
    ],
    "name:nld_x_preferred":[
        "Hn\u011bv\u010deves"
    ],
    "name:pol_x_preferred":[
        "Hn\u011bv\u010deves"
    ],
    "name:por_x_preferred":[
        "Hn\u011bv\u010deves"
    ],
    "name:slk_x_preferred":[
        "Hn\u011bv\u010deves"
    ],
    "name:spa_x_preferred":[
        "Hn\u011bv\u010deves"
    ],
    "name:srp_x_preferred":[
        "\u0425\u045a\u0435\u0432\u0447\u0435\u0432\u0435\u0441"
    ],
    "name:swe_x_preferred":[
        "Hn\u011bv\u010deves"
    ],
    "name:vie_x_preferred":[
        "Hn\u011bv\u010deves"
    ],
    "qs_pg:aaroncc":"CZ",
    "qs_pg:gn_country":"CZ",
    "qs_pg:gn_fcode":"PPL",
    "qs_pg:gn_pop":158,
    "qs_pg:name":"Hn\u011bv\u010deves",
    "qs_pg:name_adm0":"\u010cesk\u00e1 republika",
    "qs_pg:name_adm1":"Kr\u00e1lov\u00e9hradeck\u00fd kraj",
    "qs_pg:photos_9r":0,
    "qs_pg:photos_sr":0,
    "qs_pg:pop_sr":1,
    "qs_pg:qs_pg_placetype":"locality",
    "qs_pg:qs_pg_placetype_gp":"Town",
    "qs_pg:woe_adm0":23424810,
    "woe:adm0_id":23424810,
    "woe:name_adm0":"\u010cesk\u00e1 republika",
    "woe:name_adm1":"Kr\u00e1lov\u00e9hradeck\u00fd kraj",
    "woe:placetype":"Town",
    "wof:name":"Hn\u011bv\u010deves",
    "wof:placetype":"locality",
    "wof:population":158
},
  "geometry": {"coordinates":[15.71612,50.31487],"type":"Point"}
}