{
  "type": "Feature",
  "properties": {
    "gn:gn_country":"CZ",
    "gn:gn_fcode":"PPL",
    "gn:gn_pop":0,
    "iso:country":"CZ",
    "name:ceb_x_preferred":[
        "Podhrad\u00ed"
    ],
    "name:ces_x_preferred":[
        "Podhrad\u00ed"
    ],
    "name:deu_x_preferred":[
        "Podhrad\u00ed"
    ],
    "name:epo_x_preferred":[
        "Podhrad\u00ed"
    ],
    "name:fra_x_preferred":[
        "Podhrad\u00ed"
    ],
    "name:hun_x_preferred":[
        "Podhrad\u00ed"
    ],
    "name:ita_x_preferred":[
        "Podhrad\u00ed"
    ],
    "name:nld_x_preferred":[
        "Podhrad\u00ed"
    ],
    "name:pol_x_preferred":[
        "Podhrad\u00ed"
    ],
    "name:slk_x_preferred":[
        "Podhrad\u00ed"
    ],
    "name:srp_x_preferred":[
        "\u041f\u043e\u0434\u0445\u0440\u0430\u0434\u0438"
    ],
    "name:swe_x_preferred":[
        "Podhrad\u00ed"
    ],
    "qs_pg:aaroncc":"CZ",
    "qs_pg:gn_country":"CZ",
    "qs_pg:gn_fcode":"PPL",
    "qs_pg:gn_pop":0,
    "qs_pg:name":"Podhrad\u00ed",
    "qs_pg:name_adm0":"\u010cesk\u00e1 republika",
    "qs_pg:name_adm1":"Pardubick\u00fd kraj",
    "qs_pg:photos_9r":0,
    "qs_pg:photos_sr":0,
    "qs_pg:pop_sr":0,
    "qs_pg:qs_pg_placetype":"locality",
    "qs_pg:qs_pg_placetype_gp":"Town",
    "qs_pg:woe_adm0":23424810,
    "woe:adm0_id":23424810,
    "woe:name_adm0":"\u010cesk\u00e1 republika",
    "woe:name_adm1":"Pardubick\u00fd kraj",
    "woe:placetype":"Town",
    "wof:name":"Podhrad\u00ed",
    "wof:placetype":"locality"
},
  "geometry": {"coordinates":[15.58779,49.87897],"type":"Point"}
}