{
  "type": "Feature",
  "properties": {
    "gn:admin1_code":"88.0",
    "gn:admin2_code":"0209",
    "gn:asciiname":"Otice",
    "gn:country_code":"CZ",
    "gn:dem":358,
    "gn:feature_class":"P",
    "gn:feature_code":"PPL",
    "gn:name":"Otice",
    "gn:population":0,
    "gn:timezone":"Europe/Prague",
    "iso:country":"CZ",
    "name:ceb_x_preferred":[
        "Otice"
    ],
    "name:ces_x_preferred":[
        "Otice"
    ],
    "name:deu_x_preferred":[
        "Otice"
    ],
    "name:epo_x_preferred":[
        "Otice"
    ],
    "name:eus_x_preferred":[
        "Otice"
    ],
    "name:fra_x_preferred":[
        "Otice"
    ],
    "name:hun_x_preferred":[
        "Otice"
    ],
    "name:ita_x_preferred":[
        "Otice"
    ],
    "name:msa_x_preferred":[
        "Otice"
    ],
    "name:nld_x_preferred":[
        "Otice"
    ],
    "name:pol_x_preferred":[
        "Otice"
    ],
    "name:por_x_preferred":[
        "Otice"
    ],
    "name:slk_x_preferred":[
        "Otice"
    ],
    "name:spa_x_preferred":[
        "Otice"
    ],
    "name:srp_x_preferred":[
        "\u041e\u0442\u0438\u0446\u0435"
    ],
    "name:swe_x_preferred":[
        "Otice"
    ],
    "name:und_x_variant":[
        "Wotitz"
    ],
    "name:vie_x_preferred":[
        "Otice"
    ],
    "wof:name":"Otice",
    "wof:placetype":"locality"
},
  "geometry": {"coordinates":[14.64529,49.9635],"type":"Point"}
}