{
  "type": "Feature",
  "properties": {
    "gn:country":"CZ",
    "gn:fcode":"PPL",
    "gn:population":118,
    "iso:country":"CZ",
    "name:azb_x_preferred":[
        "\u062a\u0633\u06a9\u0648\u0648"
    ],
    "name:cat_x_preferred":[
        "Cekov"
    ],
    "name:ceb_x_preferred":[
        "Cekov"
    ],
    "name:ces_x_preferred":[
        "Cekov"
    ],
    "name:che_x_preferred":[
        "\u0426\u0435\u043a\u043e\u0432"
    ],
    "name:deu_x_preferred":[
        "Cekov"
    ],
    "name:eng_x_preferred":[
        "Cekov"
    ],
    "name:epo_x_preferred":[
        "Cekov"
    ],
    "name:eus_x_preferred":[
        "Cekov"
    ],
    "name:fas_x_preferred":[
        "\u062a\u0633\u06a9\u0648\u0648"
    ],
    "name:fra_x_preferred":[
        "Cekov"
    ],
    "name:gle_x_preferred":[
        "Cekov"
    ],
    "name:hun_x_preferred":[
        "Cekov"
    ],
    "name:ita_x_preferred":[
        "Cekov"
    ],
    "name:lmo_x_preferred":[
        "Cekov"
    ],
    "name:msa_x_preferred":[
        "Cekov"
    ],
    "name:nan_x_preferred":[
        "Cekov"
    ],
    "name:nld_x_preferred":[
        "Cekov"
    ],
    "name:pol_x_preferred":[
        "Cekov"
    ],
    "name:por_x_preferred":[
        "Cekov"
    ],
    "name:slk_x_preferred":[
        "Cekov"
    ],
    "name:spa_x_preferred":[
        "Cekov"
    ],
    "name:srp_x_preferred":[
        "\u0426\u0435\u043a\u043e\u0432"
    ],
    "name:swe_x_preferred":[
        "Cekov"
    ],
    "name:tat_x_preferred":[
        "\u0426\u0435\u043a\u043e\u0432"
    ],
    "name:vie_x_preferred":[
        "Cekov"
    ],
    "qs_pg:aaroncc":"CZ",
    "qs_pg:gn_country":"CZ",
    "qs_pg:gn_fcode":"PPL",
    "qs_pg:gn_pop":118,
    "qs_pg:name":"Cekov",
    "qs_pg:name_adm0":"\u010cesk\u00e1 republika",
    "qs_pg:name_adm1":"Plze\u0148sk\u00fd kraj",
    "qs_pg:photos_9r":0,
    "qs_pg:photos_sr":0,
    "qs_pg:pop_sr":1,
    "qs_pg:qs_pg_placetype":"locality",
    "qs_pg:qs_pg_placetype_gp":"Town",
    "qs_pg:woe_adm0":23424810,
    "woe:adm0_id":23424810,
    "woe:name_adm0":"\u010cesk\u00e1 republika",
    "woe:name_adm1":"Plze\u0148sk\u00fd kraj",
    "woe:placetype":"Town",
    "wof:name":"Cekov",
    "wof:placetype":"locality",
    "wof:population":118
},
  "geometry": {"coordinates":[13.76379,49.82186],"type":"Point"}
}