{
  "type": "Feature",
  "properties": {
    "gn:admin1_code":"80",
    "gn:admin2_code":"0613",
    "gn:asciiname":"Vitovice",
    "gn:country_code":"CZ",
    "gn:dem":455,
    "gn:feature_class":"P",
    "gn:feature_code":"PPL",
    "gn:name":"V\u00edtovice",
    "gn:population":0,
    "gn:timezone":"Europe/Prague",
    "iso:country":"CZ",
    "wof:name":"Vitovice",
    "wof:placetype":"locality"
},
  "geometry": {"coordinates":[15.11075,49.51122],"type":"Point"}
}