{
  "type": "Feature",
  "properties": {
    "gn:admin1_code":"79",
    "gn:admin2_code":"0313",
    "gn:asciiname":"Vlazinka",
    "gn:country_code":"CZ",
    "gn:dem":519,
    "gn:feature_class":"P",
    "gn:feature_code":"PPL",
    "gn:name":"Vla\u017einka",
    "gn:population":0,
    "gn:timezone":"Europe/Prague",
    "iso:country":"CZ",
    "wof:name":"Vlazinka",
    "wof:placetype":"locality"
},
  "geometry": {"coordinates":[15.48629,49.05276],"type":"Point"}
}