{
  "type": "Feature",
  "properties": {
    "gn:country":"CZ",
    "gn:fcode":"PPL",
    "gn:population":508,
    "iso:country":"CZ",
    "name:bel_x_preferred":[
        "\u0411\u0435\u0448\u0442\u0432\u0456\u043d\u0430"
    ],
    "name:cat_x_preferred":[
        "B\u011bstvina"
    ],
    "name:ceb_x_preferred":[
        "B\u011bstvina"
    ],
    "name:ces_x_preferred":[
        "B\u011bstvina"
    ],
    "name:che_x_preferred":[
        "\u0411\u0435\u0441\u0442\u0432\u0438\u043d\u0430"
    ],
    "name:deu_x_preferred":[
        "B\u011bstvina"
    ],
    "name:eng_x_preferred":[
        "B\u011bstvina"
    ],
    "name:epo_x_preferred":[
        "B\u011bstvina"
    ],
    "name:eus_x_preferred":[
        "B\u011bstvina"
    ],
    "name:fra_x_preferred":[
        "B\u011bstvina"
    ],
    "name:gle_x_preferred":[
        "B\u011bstvina"
    ],
    "name:hun_x_preferred":[
        "B\u011bstvina"
    ],
    "name:ita_x_preferred":[
        "B\u011bstvina"
    ],
    "name:lmo_x_preferred":[
        "B\u011bstvina"
    ],
    "name:msa_x_preferred":[
        "B\u011bstvina"
    ],
    "name:nan_x_preferred":[
        "B\u011bstvina"
    ],
    "name:nld_x_preferred":[
        "B\u011bstvina"
    ],
    "name:pol_x_preferred":[
        "B\u011bstvina"
    ],
    "name:por_x_preferred":[
        "B\u011bstvina"
    ],
    "name:rup_x_preferred":[
        "B\u011bstvina"
    ],
    "name:rus_x_preferred":[
        "\u0411\u0435\u0448\u0442\u0432\u0438\u043d\u0430"
    ],
    "name:slk_x_preferred":[
        "B\u011bstvina"
    ],
    "name:spa_x_preferred":[
        "B\u011bstvina"
    ],
    "name:srp_x_preferred":[
        "\u0411\u0458\u0435\u0441\u0442\u0432\u0438\u043d\u0430"
    ],
    "name:swe_x_preferred":[
        "B\u011bstvina"
    ],
    "name:tat_x_preferred":[
        "\u0411\u0435\u0441\u0442\u0432\u0438\u043d\u0430"
    ],
    "name:und_x_variant":[
        "Bestwin"
    ],
    "name:vie_x_preferred":[
        "B\u011bstvina"
    ],
    "qs_pg:aaroncc":"CZ",
    "qs_pg:gn_country":"CZ",
    "qs_pg:gn_fcode":"PPL",
    "qs_pg:gn_pop":508,
    "qs_pg:name":"B\u011bstvina",
    "qs_pg:name_adm0":"\u010cesk\u00e1 republika",
    "qs_pg:name_adm1":"Pardubick\u00fd kraj",
    "qs_pg:photos_9k":1,
    "qs_pg:photos_9r":1,
    "qs_pg:photos_all":20,
    "qs_pg:photos_sr":0,
    "qs_pg:pop_sr":2,
    "qs_pg:qs_pg_placetype":"locality",
    "qs_pg:qs_pg_placetype_gp":"Town",
    "qs_pg:woe_adm0":23424810,
    "woe:adm0_id":23424810,
    "woe:name_adm0":"\u010cesk\u00e1 republika",
    "woe:name_adm1":"Pardubick\u00fd kraj",
    "woe:placetype":"Town",
    "wof:name":"B\u011bstvina",
    "wof:placetype":"locality",
    "wof:population":508
},
  "geometry": {"coordinates":[15.59576,49.83703],"type":"Point"}
}