{
  "type": "Feature",
  "properties": {
    "gn:admin1_code":"89.0",
    "gn:admin2_code":"0426",
    "gn:asciiname":"Dlouha Louka",
    "gn:country_code":"CZ",
    "gn:dem":812,
    "gn:feature_class":"P",
    "gn:feature_code":"PPL",
    "gn:name":"Dlouh\u00e1 Louka",
    "gn:population":0,
    "gn:timezone":"Europe/Prague",
    "iso:country":"CZ",
    "name:und_x_variant":[
        "Louka",
        "Langewiese",
        "Dlouh\u00e1 Louka"
    ],
    "wof:name":"Dlouha Louka",
    "wof:placetype":"locality"
},
  "geometry": {"coordinates":[13.64977,50.64469],"type":"Point"}
}