{
  "type": "Feature",
  "properties": {
    "gn:gn_country":"CZ",
    "gn:gn_fcode":"PPL",
    "gn:gn_pop":804,
    "gn:population":804,
    "iso:country":"CZ",
    "name:ces_x_preferred":[
        "Lov\u010dice"
    ],
    "name:deu_x_preferred":[
        "Lov\u010dice u Kyjova"
    ],
    "name:eng_x_preferred":[
        "Lov\u010dice"
    ],
    "name:fas_x_preferred":[
        "\u0644\u0648\u0648\u062a\u0634\u06cc\u062a\u0633\u0647"
    ],
    "name:fra_x_preferred":[
        "Lov\u010dice"
    ],
    "name:hun_x_preferred":[
        "Lov\u010dice"
    ],
    "name:ita_x_preferred":[
        "Lov\u010dice"
    ],
    "name:msa_x_preferred":[
        "Lov\u010dice"
    ],
    "name:nld_x_preferred":[
        "Lov\u010dice"
    ],
    "name:pol_x_preferred":[
        "Lov\u010dice"
    ],
    "name:por_x_preferred":[
        "Lov\u010dice"
    ],
    "name:rup_x_preferred":[
        "Lov\u010dice"
    ],
    "name:slk_x_preferred":[
        "Lov\u010dice"
    ],
    "name:srp_x_preferred":[
        "\u041b\u043e\u0432\u0447\u0438\u0446\u0435"
    ],
    "name:swe_x_preferred":[
        "Lovcice"
    ],
    "name:unk_x_variant":[
        "Gross Lowtschitz"
    ],
    "name:vie_x_preferred":[
        "Lov\u010dice"
    ],
    "qs_pg:aaroncc":"CZ",
    "qs_pg:gn_country":"CZ",
    "qs_pg:gn_fcode":"PPL",
    "qs_pg:gn_pop":804,
    "qs_pg:name":"Lov\u010dice",
    "qs_pg:name_adm0":"\u010cesk\u00e1 republika",
    "qs_pg:name_adm1":"Jihomoravsk\u00fd kraj",
    "qs_pg:photos_9r":0,
    "qs_pg:photos_sr":0,
    "qs_pg:pop_sr":2,
    "qs_pg:qs_pg_placetype":"locality",
    "qs_pg:qs_pg_placetype_gp":"Town",
    "qs_pg:woe_adm0":23424810,
    "woe:adm0_id":23424810,
    "woe:name_adm0":"\u010cesk\u00e1 republika",
    "woe:name_adm1":"Jihomoravsk\u00fd kraj",
    "woe:placetype":"Town",
    "wof:name":"Lov\u010dice",
    "wof:placetype":"locality",
    "wof:population":804
},
  "geometry": {"coordinates":[17.05428,49.06358],"type":"Point"}
}