{
  "type": "Feature",
  "properties": {
    "gn:admin1_code":"88.0",
    "gn:admin2_code":"0201",
    "gn:asciiname":"Maskovice",
    "gn:country_code":"CZ",
    "gn:dem":377,
    "gn:feature_class":"P",
    "gn:feature_code":"PPL",
    "gn:name":"Maskovice",
    "gn:population":0,
    "gn:timezone":"Europe/Prague",
    "iso:country":"CZ",
    "name:und_x_variant":[
        "Maskowitz",
        "Maskovice"
    ],
    "wof:name":"Maskovice",
    "wof:placetype":"locality"
},
  "geometry": {"coordinates":[14.50081,49.82468],"type":"Point"}
}