{
  "type": "Feature",
  "properties": {
    "gn:gn_country":"CZ",
    "gn:gn_fcode":"PPL",
    "gn:gn_pop":909,
    "gn:population":909,
    "iso:country":"CZ",
    "name:azb_x_preferred":[
        "\u0698\u06cc\u0646\u06a9\u0648\u0648\u06cc"
    ],
    "name:ceb_x_preferred":[
        "\u017dinkovy"
    ],
    "name:ces_x_preferred":[
        "\u017dinkovy"
    ],
    "name:deu_x_preferred":[
        "\u017dinkovy"
    ],
    "name:eng_x_preferred":[
        "\u017dinkovy"
    ],
    "name:eus_x_preferred":[
        "\u017dinkovy"
    ],
    "name:fas_x_preferred":[
        "\u0698\u06cc\u0646\u06a9\u0648\u0648\u06cc"
    ],
    "name:fra_x_preferred":[
        "\u017dinkovy"
    ],
    "name:hun_x_preferred":[
        "\u017dinkovy"
    ],
    "name:ita_x_preferred":[
        "\u017dinkovy"
    ],
    "name:msa_x_preferred":[
        "\u017dinkovy"
    ],
    "name:nan_x_preferred":[
        "\u017dinkovy"
    ],
    "name:nld_x_preferred":[
        "\u017dinkovy"
    ],
    "name:pol_x_preferred":[
        "\u017dinkovy"
    ],
    "name:por_x_preferred":[
        "\u017dinkovy"
    ],
    "name:rup_x_preferred":[
        "\u017dinkovy"
    ],
    "name:slk_x_preferred":[
        "\u017dinkovy"
    ],
    "name:spa_x_preferred":[
        "\u017dinkovy"
    ],
    "name:srp_x_preferred":[
        "\u0416\u0438\u043d\u043a\u043e\u0432\u0438"
    ],
    "name:swe_x_preferred":[
        "\u017dinkovy"
    ],
    "name:unk_x_variant":[
        "\u017dinkau"
    ],
    "name:vie_x_preferred":[
        "\u017dinkovy"
    ],
    "qs_pg:aaroncc":"CZ",
    "qs_pg:gn_country":"CZ",
    "qs_pg:gn_fcode":"PPL",
    "qs_pg:gn_pop":909,
    "qs_pg:name":"\u017dinkovy",
    "qs_pg:name_adm0":"\u010cesk\u00e1 republika",
    "qs_pg:name_adm1":"Plze\u0148sk\u00fd kraj",
    "qs_pg:photos_9k":1,
    "qs_pg:photos_9r":3,
    "qs_pg:photos_all":82,
    "qs_pg:photos_sr":0,
    "qs_pg:pop_sr":2,
    "qs_pg:qs_pg_placetype":"locality",
    "qs_pg:qs_pg_placetype_gp":"Town",
    "qs_pg:woe_adm0":23424810,
    "woe:adm0_id":23424810,
    "woe:name_adm0":"\u010cesk\u00e1 republika",
    "woe:name_adm1":"Plze\u0148sk\u00fd kraj",
    "woe:placetype":"Town",
    "wof:name":"\u017dinkovy",
    "wof:placetype":"locality",
    "wof:population":909
},
  "geometry": {"coordinates":[13.48944,49.4834],"type":"Point"}
}