{
  "type": "Feature",
  "properties": {
    "gn:admin1_code":"84.0",
    "gn:admin2_code":"0715",
    "gn:asciiname":"Mirovicek",
    "gn:country_code":"CZ",
    "gn:dem":379,
    "gn:feature_class":"P",
    "gn:feature_code":"PPL",
    "gn:name":"M\u00edrov\u00ed\u010dek",
    "gn:population":0,
    "gn:timezone":"Europe/Prague",
    "iso:country":"CZ",
    "wof:name":"Mirovicek",
    "wof:placetype":"locality"
},
  "geometry": {"coordinates":[16.83844,49.79606],"type":"Point"}
}