{
  "type": "Feature",
  "properties": {
    "gn:country":"CZ",
    "gn:fcode":"PPL",
    "gn:population":355,
    "iso:country":"CZ",
    "name:azb_x_preferred":[
        "\u062f\u0648\u0648\u062f\u0644\u0628\u06cc"
    ],
    "name:cat_x_preferred":[
        "Doudleby"
    ],
    "name:ceb_x_preferred":[
        "Doudleby"
    ],
    "name:ces_x_preferred":[
        "Doudleby"
    ],
    "name:deu_x_preferred":[
        "Doudleby"
    ],
    "name:eus_x_preferred":[
        "Doudleby"
    ],
    "name:fas_x_preferred":[
        "\u062f\u0648\u0648\u062f\u0644\u0628\u06cc"
    ],
    "name:fra_x_preferred":[
        "Doudleby"
    ],
    "name:hun_x_preferred":[
        "Doudleby"
    ],
    "name:ita_x_preferred":[
        "Doudleby"
    ],
    "name:msa_x_preferred":[
        "Doudleby"
    ],
    "name:nld_x_preferred":[
        "Doudleby"
    ],
    "name:pol_x_preferred":[
        "Doudleby"
    ],
    "name:por_x_preferred":[
        "Doudleby"
    ],
    "name:slk_x_preferred":[
        "Doudleby"
    ],
    "name:spa_x_preferred":[
        "Doudleby"
    ],
    "name:srp_x_preferred":[
        "\u0414\u043e\u0443\u0434\u043b\u0435\u0431\u0438"
    ],
    "name:swe_x_preferred":[
        "Doudleby"
    ],
    "name:vie_x_preferred":[
        "Doudleby"
    ],
    "qs_pg:aaroncc":"CZ",
    "qs_pg:gn_country":"CZ",
    "qs_pg:gn_fcode":"PPL",
    "qs_pg:gn_pop":355,
    "qs_pg:name":"Doudleby",
    "qs_pg:name_adm0":"\u010cesk\u00e1 republika",
    "qs_pg:name_adm1":"Jiho\u010desk\u00fd kraj",
    "qs_pg:photos_9k":1,
    "qs_pg:photos_9r":1,
    "qs_pg:photos_all":1,
    "qs_pg:photos_sr":0,
    "qs_pg:pop_sr":2,
    "qs_pg:qs_pg_placetype":"localadmin",
    "qs_pg:qs_pg_placetype_gp":"LocalAdmin",
    "qs_pg:woe_adm0":23424810,
    "woe:adm0_id":23424810,
    "woe:name_adm0":"\u010cesk\u00e1 republika",
    "woe:name_adm1":"Jiho\u010desk\u00fd kraj",
    "woe:placetype":"LocalAdmin",
    "wof:name":"Doudleby",
    "wof:placetype":"localadmin",
    "wof:population":355
},
  "geometry": {"coordinates":[14.50149,48.89353],"type":"Point"}
}