{
  "type": "Feature",
  "properties": {
    "gn:admin1_code":"85",
    "gn:admin2_code":"0804",
    "gn:asciiname":"Stranik",
    "gn:country_code":"CZ",
    "gn:dem":332,
    "gn:feature_class":"P",
    "gn:feature_code":"PPL",
    "gn:name":"Stran\u00edk",
    "gn:population":0,
    "gn:timezone":"Europe/Prague",
    "iso:country":"CZ",
    "wof:name":"Stranik",
    "wof:placetype":"locality"
},
  "geometry": {"coordinates":[18.00222999999999,49.545],"type":"Point"}
}