{
  "type": "Feature",
  "properties": {
    "gn:gn_country":"CZ",
    "gn:gn_fcode":"PPL",
    "gn:gn_pop":250,
    "gn:population":250,
    "iso:country":"CZ",
    "name:cze_x_preferred":[
        "Hru\u0161ka"
    ],
    "name:dut_x_preferred":[
        "Hru\u0161ka"
    ],
    "name:eng_x_preferred":[
        "Hru\u0161ka"
    ],
    "name:fre_x_preferred":[
        "Hru\u0161ka"
    ],
    "name:ger_x_preferred":[
        "Hru\u0161ka"
    ],
    "name:hun_x_preferred":[
        "Hru\u0161ka"
    ],
    "name:ita_x_preferred":[
        "Hru\u0161ka"
    ],
    "name:may_x_preferred":[
        "Hru\u0161ka"
    ],
    "name:per_x_preferred":[
        "\u0647\u0631\u0648\u0634\u06a9\u0627"
    ],
    "name:pol_x_preferred":[
        "Hru\u0161ka"
    ],
    "name:por_x_preferred":[
        "Hru\u0161ka"
    ],
    "name:rup_x_preferred":[
        "Hru\u0161ka"
    ],
    "name:slo_x_preferred":[
        "Hru\u0161ka"
    ],
    "name:srp_x_preferred":[
        "\u0425\u0440\u0443\u0448\u043a\u0430"
    ],
    "name:swe_x_preferred":[
        "Hru\u0161ka"
    ],
    "name:vie_x_preferred":[
        "Hru\u0161ka"
    ],
    "qs_pg:aaroncc":"CZ",
    "qs_pg:gn_country":"CZ",
    "qs_pg:gn_fcode":"PPL",
    "qs_pg:gn_pop":250,
    "qs_pg:name":"Hru\u0161ka",
    "qs_pg:name_adm0":"\u010cesk\u00e1 republika",
    "qs_pg:name_adm1":"Olomouck\u00fd kraj",
    "qs_pg:photos_9r":0,
    "qs_pg:photos_sr":0,
    "qs_pg:pop_sr":2,
    "qs_pg:qs_pg_placetype":"locality",
    "qs_pg:qs_pg_placetype_gp":"Town",
    "qs_pg:woe_adm0":23424810,
    "woe:adm0_id":23424810,
    "woe:name_adm0":"\u010cesk\u00e1 republika",
    "woe:name_adm1":"Olomouck\u00fd kraj",
    "woe:placetype":"Town",
    "wof:name":"Hru\u0161ka",
    "wof:placetype":"locality",
    "wof:population":250
},
  "geometry": {"coordinates":[17.22666,49.35878],"type":"Point"}
}