{
  "type": "Feature",
  "properties": {
    "gn:gn_country":"CZ",
    "gn:gn_fcode":"PPL",
    "gn:gn_pop":319,
    "gn:population":319,
    "iso:country":"CZ",
    "name:cze_x_preferred":[
        "Hv\u011bzdonice"
    ],
    "name:dut_x_preferred":[
        "Hv\u011bzdonice"
    ],
    "name:eng_x_preferred":[
        "Hv\u011bzdonice"
    ],
    "name:fre_x_preferred":[
        "Hv\u011bzdonice"
    ],
    "name:hun_x_preferred":[
        "Hv\u011bzdonice"
    ],
    "name:ita_x_preferred":[
        "Hv\u011bzdonice"
    ],
    "name:may_x_preferred":[
        "Hv\u011bzdonice"
    ],
    "name:per_x_preferred":[
        "\u0647\u0648\u06cc\u0632\u062f\u0648\u0646\u06cc\u062a\u0633\u0647"
    ],
    "name:pol_x_preferred":[
        "Hv\u011bzdonice"
    ],
    "name:por_x_preferred":[
        "Hv\u011bzdonice"
    ],
    "name:slo_x_preferred":[
        "Hv\u011bzdonice"
    ],
    "name:srp_x_preferred":[
        "\u0425\u0432\u0458\u0435\u0437\u0434\u043e\u045a\u0438\u0446\u0435"
    ],
    "name:swe_x_preferred":[
        "Hv\u011bzdonice"
    ],
    "name:unk_x_variant":[
        "Hwiesdonitz"
    ],
    "name:vie_x_preferred":[
        "Hv\u011bzdonice"
    ],
    "qs_pg:aaroncc":"CZ",
    "qs_pg:gn_country":"CZ",
    "qs_pg:gn_fcode":"PPL",
    "qs_pg:gn_pop":319,
    "qs_pg:name":"Hv\u011bzdonice",
    "qs_pg:name_adm0":"\u010cesk\u00e1 republika",
    "qs_pg:name_adm1":"St\u0159edo\u010desk\u00fd kraj",
    "qs_pg:photos_9k":1,
    "qs_pg:photos_9r":1,
    "qs_pg:photos_all":6,
    "qs_pg:photos_sr":0,
    "qs_pg:pop_sr":2,
    "qs_pg:qs_pg_placetype":"locality",
    "qs_pg:qs_pg_placetype_gp":"Town",
    "qs_pg:woe_adm0":23424810,
    "woe:adm0_id":23424810,
    "woe:name_adm0":"\u010cesk\u00e1 republika",
    "woe:name_adm1":"St\u0159edo\u010desk\u00fd kraj",
    "woe:placetype":"Town",
    "wof:name":"Hv\u011bzdonice",
    "wof:placetype":"locality",
    "wof:population":319
},
  "geometry": {"coordinates":[14.77727,49.87282],"type":"Point"}
}