{
  "type": "Feature",
  "properties": {
    "gn:country":"CZ",
    "gn:fcode":"PPL",
    "gn:population":455,
    "iso:country":"CZ",
    "name:azb_x_preferred":[
        "\u062e\u0631\u0648\u0628\u0648\u0644\u06cc"
    ],
    "name:bul_x_preferred":[
        "\u0427\u0440\u043e\u0431\u043e\u043b\u0439"
    ],
    "name:ceb_x_preferred":[
        "Chroboly"
    ],
    "name:ces_x_preferred":[
        "Chroboly"
    ],
    "name:deu_x_preferred":[
        "Chroboly"
    ],
    "name:eng_x_preferred":[
        "Chroboly"
    ],
    "name:eus_x_preferred":[
        "Chroboly"
    ],
    "name:fas_x_preferred":[
        "\u062e\u0631\u0648\u0628\u0648\u0644\u06cc"
    ],
    "name:fra_x_preferred":[
        "Chroboly"
    ],
    "name:hun_x_preferred":[
        "Chroboly"
    ],
    "name:ita_x_preferred":[
        "Chroboly"
    ],
    "name:msa_x_preferred":[
        "Chroboly"
    ],
    "name:nan_x_preferred":[
        "Chroboly"
    ],
    "name:nld_x_preferred":[
        "Chroboly"
    ],
    "name:por_x_preferred":[
        "Chroboly"
    ],
    "name:slk_x_preferred":[
        "Chroboly"
    ],
    "name:spa_x_preferred":[
        "Chroboly"
    ],
    "name:srp_x_preferred":[
        "\u0425\u0440\u043e\u0431\u043e\u043b\u0438"
    ],
    "name:swe_x_preferred":[
        "Chroboly"
    ],
    "name:und_x_variant":[
        "Chrobold"
    ],
    "name:vie_x_preferred":[
        "Chroboly"
    ],
    "qs_pg:aaroncc":"CZ",
    "qs_pg:gn_country":"CZ",
    "qs_pg:gn_fcode":"PPL",
    "qs_pg:gn_pop":455,
    "qs_pg:name":"Chroboly",
    "qs_pg:name_adm0":"\u010cesk\u00e1 republika",
    "qs_pg:name_adm1":"Jiho\u010desk\u00fd kraj",
    "qs_pg:photos_9k":1,
    "qs_pg:photos_9r":1,
    "qs_pg:photos_all":2,
    "qs_pg:photos_sr":0,
    "qs_pg:pop_sr":2,
    "qs_pg:qs_pg_placetype":"locality",
    "qs_pg:qs_pg_placetype_gp":"Town",
    "qs_pg:woe_adm0":23424810,
    "woe:adm0_id":23424810,
    "woe:name_adm0":"\u010cesk\u00e1 republika",
    "woe:name_adm1":"Jiho\u010desk\u00fd kraj",
    "woe:placetype":"Town",
    "wof:name":"Chroboly",
    "wof:placetype":"locality",
    "wof:population":455
},
  "geometry": {"coordinates":[14.06698,48.95653],"type":"Point"}
}