{
  "type": "Feature",
  "properties": {
    "gn:admin1_code":"80.0",
    "gn:admin2_code":"0612",
    "gn:asciiname":"Handlovy Dvory",
    "gn:country_code":"CZ",
    "gn:dem":522,
    "gn:feature_class":"P",
    "gn:feature_code":"PPL",
    "gn:name":"Handlovy Dvory",
    "gn:population":0,
    "gn:timezone":"Europe/Prague",
    "iso:country":"CZ",
    "name:und_x_variant":[
        "Handelsdorf",
        "Handlovy Dvory"
    ],
    "wof:name":"Handlovy Dvory",
    "wof:placetype":"locality"
},
  "geometry": {"coordinates":[15.60866,49.3972],"type":"Point"}
}