{
  "type": "Feature",
  "properties": {
    "gn:admin1_code":"80.0",
    "gn:admin2_code":"0611",
    "gn:asciiname":"Pozovice",
    "gn:country_code":"CZ",
    "gn:dem":480,
    "gn:feature_class":"P",
    "gn:feature_code":"PPL",
    "gn:name":"Pozovice",
    "gn:population":0,
    "gn:timezone":"Europe/Prague",
    "iso:country":"CZ",
    "name:und_x_variant":[
        "Bosowitz",
        "Pozovice"
    ],
    "wof:name":"Pozovice",
    "wof:placetype":"locality"
},
  "geometry": {"coordinates":[15.61957,49.51648],"type":"Point"}
}