{
  "type": "Feature",
  "properties": {
    "gn:country":"CZ",
    "gn:fcode":"PPL",
    "gn:population":647,
    "iso:country":"CZ",
    "name:ceb_x_preferred":[
        "Chvalkovice"
    ],
    "name:ces_x_preferred":[
        "Chvalkovice"
    ],
    "name:deu_x_preferred":[
        "Chvalkovice v \u010cech\u00e1ch"
    ],
    "name:eng_x_preferred":[
        "Chvalkovice"
    ],
    "name:eus_x_preferred":[
        "Chvalkovice"
    ],
    "name:fas_x_preferred":[
        "\u062e\u0648\u0627\u0644\u06a9\u0648\u0648\u06cc\u062a\u0633\u0647"
    ],
    "name:fra_x_preferred":[
        "Chvalkovice"
    ],
    "name:hun_x_preferred":[
        "Chvalkovice"
    ],
    "name:ita_x_preferred":[
        "Chvalkovice"
    ],
    "name:msa_x_preferred":[
        "Chvalkovice"
    ],
    "name:nan_x_preferred":[
        "Chvalkovice"
    ],
    "name:nld_x_preferred":[
        "Chvalkovice"
    ],
    "name:pol_x_preferred":[
        "Chvalkovice"
    ],
    "name:por_x_preferred":[
        "Chvalkovice"
    ],
    "name:rup_x_preferred":[
        "Chvalkovice"
    ],
    "name:slk_x_preferred":[
        "Chvalkovice"
    ],
    "name:spa_x_preferred":[
        "Chvalkovice"
    ],
    "name:srp_x_preferred":[
        "\u0425\u0432\u0430\u043b\u043a\u043e\u0432\u0438\u0446\u0435"
    ],
    "name:swe_x_preferred":[
        "Chvalkovice"
    ],
    "name:vie_x_preferred":[
        "Chvalkovice"
    ],
    "qs_pg:aaroncc":"CZ",
    "qs_pg:gn_country":"CZ",
    "qs_pg:gn_fcode":"PPL",
    "qs_pg:gn_pop":647,
    "qs_pg:name":"Chvalkovice",
    "qs_pg:name_adm0":"\u010cesk\u00e1 republika",
    "qs_pg:name_adm1":"Kr\u00e1lov\u00e9hradeck\u00fd kraj",
    "qs_pg:photos_9k":1,
    "qs_pg:photos_9r":1,
    "qs_pg:photos_all":5,
    "qs_pg:photos_sr":0,
    "qs_pg:pop_sr":2,
    "qs_pg:qs_pg_placetype":"locality",
    "qs_pg:qs_pg_placetype_gp":"Town",
    "qs_pg:woe_adm0":23424810,
    "woe:adm0_id":23424810,
    "woe:name_adm0":"\u010cesk\u00e1 republika",
    "woe:name_adm1":"Kr\u00e1lov\u00e9hradeck\u00fd kraj",
    "woe:placetype":"Town",
    "wof:name":"Chvalkovice",
    "wof:placetype":"locality",
    "wof:population":647
},
  "geometry": {"coordinates":[15.97829,50.41434],"type":"Point"}
}