{
  "type": "Feature",
  "properties": {
    "gn:admin1_code":"86.0",
    "gn:admin2_code":"0531",
    "gn:asciiname":"Hrbokov",
    "gn:country_code":"CZ",
    "gn:dem":529,
    "gn:feature_class":"P",
    "gn:feature_code":"PPL",
    "gn:name":"Hrbokov",
    "gn:population":0,
    "gn:timezone":"Europe/Prague",
    "iso:country":"CZ",
    "wof:name":"Hrbokov",
    "wof:placetype":"locality"
},
  "geometry": {"coordinates":[15.69088,49.86735],"type":"Point"}
}