{
  "type": "Feature",
  "properties": {
    "gn:gn_country":"CZ",
    "gn:gn_fcode":"PPL",
    "gn:gn_pop":288,
    "gn:population":288,
    "iso:country":"CZ",
    "name:ceb_x_preferred":[
        "Chlumany"
    ],
    "name:ces_x_preferred":[
        "Chlumany"
    ],
    "name:deu_x_preferred":[
        "Chlumany"
    ],
    "name:eng_x_preferred":[
        "Chlumany"
    ],
    "name:eus_x_preferred":[
        "Chlumany"
    ],
    "name:fas_x_preferred":[
        "\u062e\u0644\u0648\u0645\u0627\u0646\u06cc"
    ],
    "name:fra_x_preferred":[
        "Chlumany"
    ],
    "name:hun_x_preferred":[
        "Chlumany"
    ],
    "name:ita_x_preferred":[
        "Chlumany"
    ],
    "name:msa_x_preferred":[
        "Chlumany"
    ],
    "name:nan_x_preferred":[
        "Chlumany"
    ],
    "name:nld_x_preferred":[
        "Chlumany"
    ],
    "name:por_x_preferred":[
        "Chlumany"
    ],
    "name:slk_x_preferred":[
        "Chlumany"
    ],
    "name:spa_x_preferred":[
        "Chlumany"
    ],
    "name:srp_x_preferred":[
        "\u0425\u043b\u0443\u043c\u0430\u043d\u0438"
    ],
    "name:swe_x_preferred":[
        "Chlumany"
    ],
    "name:unk_x_variant":[
        "Chumau"
    ],
    "name:vie_x_preferred":[
        "Chlumany"
    ],
    "qs_pg:aaroncc":"CZ",
    "qs_pg:gn_country":"CZ",
    "qs_pg:gn_fcode":"PPL",
    "qs_pg:gn_pop":288,
    "qs_pg:name":"Chlumany",
    "qs_pg:photos_9r":0,
    "qs_pg:photos_sr":0,
    "qs_pg:pop_sr":2,
    "qs_pg:qs_pg_placetype":"locality",
    "wof:name":"Chlumany",
    "wof:placetype":"locality",
    "wof:population":288
},
  "geometry": {"coordinates":[14.06667,48.88333],"type":"Point"}
}