{
  "type": "Feature",
  "properties": {
    "gn:admin1_code":"89.0",
    "gn:admin2_code":"0425",
    "gn:asciiname":"Dolni Litvinov",
    "gn:cc2":"CZ",
    "gn:country_code":"CZ",
    "gn:dem":312,
    "gn:feature_class":"P",
    "gn:feature_code":"PPL",
    "gn:name":"Doln\u00ed Litv\u00ednov",
    "gn:population":0,
    "gn:timezone":"Europe/Prague",
    "iso:country":"CZ",
    "name:und_x_variant":[
        "Nieder-Leutensdorf"
    ],
    "wof:name":"Dolni Litvinov",
    "wof:placetype":"locality"
},
  "geometry": {"coordinates":[13.61172,50.5974],"type":"Point"}
}