{
  "type": "Feature",
  "properties": {
    "gn:admin1_code":"88.0",
    "gn:admin2_code":"0207",
    "gn:asciiname":"Male Vselisy",
    "gn:country_code":"CZ",
    "gn:dem":282,
    "gn:feature_class":"P",
    "gn:feature_code":"PPL",
    "gn:name":"Mal\u00e9 V\u0161elisy",
    "gn:population":0,
    "gn:timezone":"Europe/Prague",
    "iso:country":"CZ",
    "wof:name":"Male Vselisy",
    "wof:placetype":"locality"
},
  "geometry": {"coordinates":[14.7485,50.38423],"type":"Point"}
}