{
  "type": "Feature",
  "properties": {
    "gn:gn_country":"CZ",
    "gn:gn_fcode":"PPL",
    "gn:gn_pop":193,
    "gn:population":193,
    "iso:country":"CZ",
    "name:azb_x_preferred":[
        "\u0627\u0648\u0628\u0631\u0648\u0628\u06cc"
    ],
    "name:bul_x_preferred":[
        "\u041e\u0431\u0440\u0443\u0431\u0439"
    ],
    "name:ceb_x_preferred":[
        "Obruby"
    ],
    "name:ces_x_preferred":[
        "Obruby"
    ],
    "name:eng_x_preferred":[
        "Obruby"
    ],
    "name:eus_x_preferred":[
        "Obruby"
    ],
    "name:fas_x_preferred":[
        "\u0627\u0648\u0628\u0631\u0648\u0628\u06cc"
    ],
    "name:fra_x_preferred":[
        "Obruby"
    ],
    "name:hun_x_preferred":[
        "Obruby"
    ],
    "name:ita_x_preferred":[
        "Obruby"
    ],
    "name:msa_x_preferred":[
        "Obruby"
    ],
    "name:nan_x_preferred":[
        "Obruby"
    ],
    "name:nld_x_preferred":[
        "Obruby"
    ],
    "name:pol_x_preferred":[
        "Obruby"
    ],
    "name:por_x_preferred":[
        "Obruby"
    ],
    "name:rus_x_preferred":[
        "\u041e\u0431\u0440\u0443\u0431\u0438"
    ],
    "name:slk_x_preferred":[
        "Obruby"
    ],
    "name:spa_x_preferred":[
        "Obruby"
    ],
    "name:srp_x_preferred":[
        "\u041e\u0431\u0440\u0443\u0431\u0438"
    ],
    "name:swe_x_preferred":[
        "Obruby"
    ],
    "name:vie_x_preferred":[
        "Obruby"
    ],
    "qs_pg:aaroncc":"CZ",
    "qs_pg:gn_country":"CZ",
    "qs_pg:gn_fcode":"PPL",
    "qs_pg:gn_pop":193,
    "qs_pg:name":"Obruby",
    "qs_pg:name_adm0":"\u010cesk\u00e1 republika",
    "qs_pg:name_adm1":"St\u0159edo\u010desk\u00fd kraj",
    "qs_pg:photos_9r":0,
    "qs_pg:photos_sr":0,
    "qs_pg:pop_sr":1,
    "qs_pg:qs_pg_placetype":"locality",
    "qs_pg:qs_pg_placetype_gp":"Town",
    "qs_pg:woe_adm0":23424810,
    "woe:adm0_id":23424810,
    "woe:name_adm0":"\u010cesk\u00e1 republika",
    "woe:name_adm1":"St\u0159edo\u010desk\u00fd kraj",
    "woe:placetype":"Town",
    "wof:name":"Obruby",
    "wof:placetype":"locality",
    "wof:population":193
},
  "geometry": {"coordinates":[15.08231,50.46013],"type":"Point"}
}