{
  "type": "Feature",
  "properties": {
    "gn:admin1_code":"79.0",
    "gn:admin2_code":"0311",
    "gn:asciiname":"Popovice",
    "gn:country_code":"CZ",
    "gn:dem":481,
    "gn:feature_class":"P",
    "gn:feature_code":"PPL",
    "gn:name":"Popovice",
    "gn:population":0,
    "gn:timezone":"Europe/Prague",
    "iso:country":"CZ",
    "name:ceb_x_preferred":[
        "Popovice"
    ],
    "name:ces_x_preferred":[
        "Popovice"
    ],
    "name:deu_x_preferred":[
        "Popovice"
    ],
    "name:fra_x_preferred":[
        "Popovice"
    ],
    "name:ita_x_preferred":[
        "Popovice"
    ],
    "name:nld_x_preferred":[
        "Popovice"
    ],
    "name:oci_x_preferred":[
        "Popovice"
    ],
    "name:pol_x_preferred":[
        "Popovice"
    ],
    "name:slk_x_preferred":[
        "Popovice"
    ],
    "name:srp_x_preferred":[
        "\u041f\u043e\u043f\u043e\u0432\u0438\u0446\u0435"
    ],
    "name:swe_x_preferred":[
        "Popovice"
    ],
    "wof:name":"Popovice",
    "wof:placetype":"locality"
},
  "geometry": {"coordinates":[14.56325,49.16082],"type":"Point"}
}