{
  "type": "Feature",
  "properties": {
    "gn:admin1_code":"79",
    "gn:admin2_code":"0314",
    "gn:asciiname":"Zd'arske Chalupy",
    "gn:country_code":"CZ",
    "gn:dem":413,
    "gn:feature_class":"P",
    "gn:feature_code":"PPL",
    "gn:name":"\u017d\u010f\u00e1rsk\u00e9 Chalupy",
    "gn:population":0,
    "gn:timezone":"Europe/Prague",
    "iso:country":"CZ",
    "wof:name":"Zd'arske Chalupy",
    "wof:placetype":"locality"
},
  "geometry": {"coordinates":[14.2434,49.22623],"type":"Point"}
}