{
  "type": "Feature",
  "properties": {
    "gn:gn_country":"CZ",
    "gn:gn_fcode":"PPL",
    "gn:gn_pop":181,
    "gn:population":181,
    "iso:country":"CZ",
    "name:ces_x_preferred":[
        "B\u011blu\u0161ice"
    ],
    "name:deu_x_preferred":[
        "B\u011blu\u0161ice"
    ],
    "name:eng_x_preferred":[
        "B\u011blu\u0161ice"
    ],
    "name:fas_x_preferred":[
        "\u0628\u06cc\u0644\u0648\u0634\u06cc\u062a\u0633\u0647"
    ],
    "name:fra_x_preferred":[
        "B\u011blu\u0161ice"
    ],
    "name:hun_x_preferred":[
        "B\u011blu\u0161ice"
    ],
    "name:ita_x_preferred":[
        "B\u011blu\u0161ice"
    ],
    "name:msa_x_preferred":[
        "B\u011blu\u0161ice"
    ],
    "name:nan_x_preferred":[
        "B\u011blu\u0161ice"
    ],
    "name:nld_x_preferred":[
        "B\u011blu\u0161ice"
    ],
    "name:por_x_preferred":[
        "B\u011blu\u0161ice"
    ],
    "name:rup_x_preferred":[
        "B\u011blu\u0161ice"
    ],
    "name:slk_x_preferred":[
        "B\u011blu\u0161ice"
    ],
    "name:srp_x_preferred":[
        "\u0411\u0458\u0435\u043b\u0443\u0448\u0438\u0446\u0435"
    ],
    "name:swe_x_preferred":[
        "B\u011blu\u0161ice"
    ],
    "name:vie_x_preferred":[
        "B\u011blu\u0161ice"
    ],
    "qs_pg:aaroncc":"CZ",
    "qs_pg:gn_country":"CZ",
    "qs_pg:gn_fcode":"PPL",
    "qs_pg:gn_pop":181,
    "qs_pg:name":"B\u011blu\u0161ice",
    "qs_pg:name_adm0":"\u010cesk\u00e1 republika",
    "qs_pg:name_adm1":"\u00dasteck\u00fd kraj",
    "qs_pg:photos_9r":0,
    "qs_pg:photos_sr":0,
    "qs_pg:pop_sr":1,
    "qs_pg:qs_pg_placetype":"locality",
    "qs_pg:qs_pg_placetype_gp":"Town",
    "qs_pg:woe_adm0":23424810,
    "woe:adm0_id":23424810,
    "woe:name_adm0":"\u010cesk\u00e1 republika",
    "woe:name_adm1":"\u00dasteck\u00fd kraj",
    "woe:placetype":"Town",
    "wof:name":"B\u011blu\u0161ice",
    "wof:placetype":"locality",
    "wof:population":181
},
  "geometry": {"coordinates":[13.76282,50.44916],"type":"Point"}
}