{
  "type": "Feature",
  "properties": {
    "gn:admin1_code":"89.0",
    "gn:admin2_code":"0421",
    "gn:asciiname":"Soutesky",
    "gn:country_code":"CZ",
    "gn:dem":169,
    "gn:feature_class":"P",
    "gn:feature_code":"PPL",
    "gn:name":"Sout\u011bsky",
    "gn:population":0,
    "gn:timezone":"Europe/Prague",
    "iso:country":"CZ",
    "name:und_x_variant":[
        "Zautig",
        "Sout\u011bsky"
    ],
    "wof:name":"Soutesky",
    "wof:placetype":"locality"
},
  "geometry": {"coordinates":[14.25973,50.75034],"type":"Point"}
}