{
  "type": "Feature",
  "properties": {
    "gn:admin1_code":"87.0",
    "gn:admin2_code":"0322",
    "gn:asciiname":"Ostruzno",
    "gn:country_code":"CZ",
    "gn:dem":742,
    "gn:feature_class":"P",
    "gn:feature_code":"PPL",
    "gn:name":"Ostru\u017eno",
    "gn:population":0,
    "gn:timezone":"Europe/Prague",
    "iso:country":"CZ",
    "wof:name":"Ostruzno",
    "wof:placetype":"locality"
},
  "geometry": {"coordinates":[13.59138,49.17744],"type":"Point"}
}