{
  "type": "Feature",
  "properties": {
    "gn:admin1_code":"80.0",
    "gn:admin2_code":"0614",
    "gn:asciiname":"Bitovanky",
    "gn:country_code":"CZ",
    "gn:dem":593,
    "gn:feature_class":"P",
    "gn:feature_code":"PPL",
    "gn:name":"B\u00edtov\u00e1nky",
    "gn:population":0,
    "gn:timezone":"Europe/Prague",
    "iso:country":"CZ",
    "wof:name":"Bitovanky",
    "wof:placetype":"locality"
},
  "geometry": {"coordinates":[15.69096,49.14513],"type":"Point"}
}