{
  "type": "Feature",
  "properties": {
    "gn:admin1_code":"82.0",
    "gn:admin2_code":"0523",
    "gn:asciiname":"Mala Bukovina",
    "gn:country_code":"CZ",
    "gn:dem":364,
    "gn:feature_class":"P",
    "gn:feature_code":"PPL",
    "gn:name":"Mal\u00e1 Bukovina",
    "gn:population":0,
    "gn:timezone":"Europe/Prague",
    "iso:country":"CZ",
    "name:und_x_variant":[
        "Klein Bukovina",
        "Mal\u00e1 Bukovina"
    ],
    "wof:name":"Mala Bukovina",
    "wof:placetype":"locality"
},
  "geometry": {"coordinates":[15.96122,50.42014],"type":"Point"}
}