{
  "type": "Feature",
  "properties": {
    "gn:country":"CZ",
    "gn:fcode":"PPL",
    "gn:population":759,
    "iso:country":"CZ",
    "name:azb_x_preferred":[
        "\u067e\u0648\u062a\u062a\u0634"
    ],
    "name:cat_x_preferred":[
        "Pote\u010d"
    ],
    "name:ceb_x_preferred":[
        "Pote\u010d"
    ],
    "name:ces_x_preferred":[
        "Pote\u010d"
    ],
    "name:che_x_preferred":[
        "\u041f\u043e\u0442\u0435\u0447"
    ],
    "name:deu_x_preferred":[
        "Pote\u010d"
    ],
    "name:eng_x_preferred":[
        "Pote\u010d"
    ],
    "name:epo_x_preferred":[
        "Pote\u010d"
    ],
    "name:eus_x_preferred":[
        "Pote\u010d"
    ],
    "name:fas_x_preferred":[
        "\u067e\u0648\u062a\u062a\u0634"
    ],
    "name:fra_x_preferred":[
        "Pote\u010d"
    ],
    "name:gle_x_preferred":[
        "Pote\u010d"
    ],
    "name:hun_x_preferred":[
        "Pote\u010d"
    ],
    "name:ita_x_preferred":[
        "Pote\u010d"
    ],
    "name:lmo_x_preferred":[
        "Pote\u010d"
    ],
    "name:msa_x_preferred":[
        "Pote\u010d"
    ],
    "name:nan_x_preferred":[
        "Pote\u010d"
    ],
    "name:nld_x_preferred":[
        "Pote\u010d"
    ],
    "name:pol_x_preferred":[
        "Pote\u010d"
    ],
    "name:por_x_preferred":[
        "Pote\u010d"
    ],
    "name:rup_x_preferred":[
        "Pote\u010d"
    ],
    "name:slk_x_preferred":[
        "Pote\u010d"
    ],
    "name:spa_x_preferred":[
        "Pote\u010d"
    ],
    "name:srp_x_preferred":[
        "\u041f\u043e\u0442\u0435\u0447"
    ],
    "name:swe_x_preferred":[
        "Pote\u010d"
    ],
    "name:tat_x_preferred":[
        "\u041f\u043e\u0442\u0435\u0447"
    ],
    "name:vie_x_preferred":[
        "Pote\u010d"
    ],
    "qs_pg:aaroncc":"CZ",
    "qs_pg:gn_country":"CZ",
    "qs_pg:gn_fcode":"PPL",
    "qs_pg:gn_pop":759,
    "qs_pg:name":"Potec",
    "qs_pg:name_adm0":"\u010cesk\u00e1 republika",
    "qs_pg:name_adm1":"Zl\u00ednsk\u00fd kraj",
    "qs_pg:photos_9r":0,
    "qs_pg:photos_sr":0,
    "qs_pg:pop_sr":2,
    "qs_pg:qs_pg_placetype":"locality",
    "qs_pg:qs_pg_placetype_gp":"Town",
    "qs_pg:woe_adm0":23424810,
    "woe:adm0_id":23424810,
    "woe:name_adm0":"\u010cesk\u00e1 republika",
    "woe:name_adm1":"Zl\u00ednsk\u00fd kraj",
    "woe:placetype":"Town",
    "wof:name":"Potec",
    "wof:placetype":"locality",
    "wof:population":759
},
  "geometry": {"coordinates":[18.03543,49.15438],"type":"Point"}
}