{
  "type": "Feature",
  "properties": {
    "gn:admin1_code":"87.0",
    "gn:admin2_code":"0327",
    "gn:asciiname":"Nova Ves",
    "gn:country_code":"CZ",
    "gn:dem":592,
    "gn:feature_class":"P",
    "gn:feature_code":"PPL",
    "gn:name":"Nov\u00e1 Ves",
    "gn:population":0,
    "gn:timezone":"Europe/Prague",
    "iso:country":"CZ",
    "name:und_x_variant":[
        "Neudorf",
        "Nov\u00e1 Ves"
    ],
    "wof:name":"Nova Ves",
    "wof:placetype":"locality"
},
  "geometry": {"coordinates":[12.64888,49.62866],"type":"Point"}
}