{
  "type": "Feature",
  "properties": {
    "iso:country":"CZ",
    "name:ceb_x_preferred":[
        "Slati\u0148any"
    ],
    "name:ces_x_preferred":[
        "Slati\u0148any"
    ],
    "name:deu_x_preferred":[
        "Slati\u0148any"
    ],
    "name:epo_x_preferred":[
        "Slati\u0148any"
    ],
    "name:eus_x_preferred":[
        "Slati\u0148any"
    ],
    "name:fas_x_preferred":[
        "\u0633\u0644\u0627\u062a\u06cc\u0646\u0627\u0646\u06cc"
    ],
    "name:fra_x_preferred":[
        "Slati\u0148any"
    ],
    "name:hun_x_preferred":[
        "Slati\u0148any"
    ],
    "name:ita_x_preferred":[
        "Slati\u0148any"
    ],
    "name:lav_x_preferred":[
        "Slati\u0146ani"
    ],
    "name:msa_x_preferred":[
        "Slati\u0148any"
    ],
    "name:nld_x_preferred":[
        "Slati\u0148any"
    ],
    "name:pol_x_preferred":[
        "Slati\u0148any"
    ],
    "name:por_x_preferred":[
        "Slati\u0148any"
    ],
    "name:rus_x_preferred":[
        "\u0421\u043b\u0430\u0442\u0438\u043d\u044f\u043d\u0438"
    ],
    "name:slk_x_preferred":[
        "Slati\u0148any"
    ],
    "name:spa_x_preferred":[
        "Slati\u0148any"
    ],
    "name:srp_x_preferred":[
        "\u0421\u043b\u0430\u0442\u0438\u045a\u0430\u043d\u0438"
    ],
    "name:swe_x_preferred":[
        "Slati\u0148any"
    ],
    "name:vie_x_preferred":[
        "Slati\u0148any"
    ],
    "name:zho_x_preferred":[
        "\u65af\u62c9\u5b63\u5c3c\u4e9e\u5c3c"
    ],
    "qs_pg:aaroncc":"CZ",
    "qs_pg:name":"Slati\u0148any",
    "qs_pg:name_adm0":"\u010cesk\u00e1 republika",
    "qs_pg:name_adm1":"Pardubick\u00fd kraj",
    "qs_pg:photos":5,
    "qs_pg:photos_1k":1,
    "qs_pg:photos_9k":1,
    "qs_pg:photos_9r":2,
    "qs_pg:photos_all":48,
    "qs_pg:photos_sr":1,
    "qs_pg:pop_sr":0,
    "qs_pg:qs_pg_placetype":"localadmin",
    "qs_pg:qs_pg_placetype_gp":"LocalAdmin",
    "qs_pg:woe_adm0":23424810,
    "woe:adm0_id":23424810,
    "woe:name_adm0":"\u010cesk\u00e1 republika",
    "woe:name_adm1":"Pardubick\u00fd kraj",
    "woe:placetype":"LocalAdmin",
    "wof:name":"Slati\u0148any",
    "wof:placetype":"localadmin"
},
  "geometry": {"coordinates":[15.810356,49.918403],"type":"Point"}
}