{
  "type": "Feature",
  "properties": {
    "gn:admin1_code":"80.0",
    "gn:admin2_code":"0615",
    "gn:asciiname":"Na Place",
    "gn:country_code":"CZ",
    "gn:dem":659,
    "gn:feature_class":"P",
    "gn:feature_code":"PPL",
    "gn:name":"Na Place",
    "gn:population":0,
    "gn:timezone":"Europe/Prague",
    "iso:country":"CZ",
    "wof:name":"Na Place",
    "wof:placetype":"locality"
},
  "geometry": {"coordinates":[15.98899,49.67471],"type":"Point"}
}