{
  "type": "Feature",
  "properties": {
    "gn:admin1_code":"89",
    "gn:admin2_code":"0423",
    "gn:asciiname":"Stary Tyn",
    "gn:cc2":"CZ",
    "gn:country_code":"CZ",
    "gn:dem":313,
    "gn:feature_class":"P",
    "gn:feature_code":"PPL",
    "gn:name":"Star\u00fd T\u00fdn",
    "gn:population":0,
    "gn:timezone":"Europe/Prague",
    "iso:country":"CZ",
    "name:und_x_variant":[
        "Alt Thein"
    ],
    "wof:name":"Stary Tyn",
    "wof:placetype":"locality"
},
  "geometry": {"coordinates":[14.32806,50.60634],"type":"Point"}
}