{
  "type": "Feature",
  "properties": {
    "gn:admin1_code":"89.0",
    "gn:admin2_code":"0422",
    "gn:asciiname":"Orasin",
    "gn:country_code":"CZ",
    "gn:dem":571,
    "gn:feature_class":"P",
    "gn:feature_code":"PPL",
    "gn:name":"Oras\u00edn",
    "gn:population":0,
    "gn:timezone":"Europe/Prague",
    "iso:country":"CZ",
    "name:und_x_variant":[
        "Uhrissen",
        "Oras\u00edn"
    ],
    "wof:name":"Orasin",
    "wof:placetype":"locality"
},
  "geometry": {"coordinates":[13.39933,50.53468],"type":"Point"}
}