{
  "type": "Feature",
  "properties": {
    "gn:country":"CZ",
    "gn:fcode":"PPL",
    "gn:population":84,
    "iso:country":"CZ",
    "name:azb_x_preferred":[
        "\u0627\u0648\u06cc\u0632\u062f\u062a\u0633"
    ],
    "name:ces_x_preferred":[
        "\u00dajezdec"
    ],
    "name:eng_x_preferred":[
        "\u00dajezdec"
    ],
    "name:epo_x_preferred":[
        "\u00dajezdec"
    ],
    "name:eus_x_preferred":[
        "\u00dajezdec"
    ],
    "name:fas_x_preferred":[
        "\u0627\u0648\u06cc\u0632\u062f\u062a\u0633"
    ],
    "name:fra_x_preferred":[
        "\u00dajezdec"
    ],
    "name:hun_x_preferred":[
        "\u00dajezdec"
    ],
    "name:ita_x_preferred":[
        "\u00dajezdec"
    ],
    "name:msa_x_preferred":[
        "\u00dajezdec"
    ],
    "name:nan_x_preferred":[
        "\u00dajezdec"
    ],
    "name:nld_x_preferred":[
        "\u00dajezdec"
    ],
    "name:por_x_preferred":[
        "\u00dajezdec"
    ],
    "name:rup_x_preferred":[
        "\u00dajezdec"
    ],
    "name:slk_x_preferred":[
        "\u00dajezdec"
    ],
    "name:spa_x_preferred":[
        "\u00dajezdec"
    ],
    "name:srp_x_preferred":[
        "\u0423\u0458\u0435\u0437\u0434\u0435\u0446"
    ],
    "name:vie_x_preferred":[
        "\u00dajezdec"
    ],
    "qs_pg:aaroncc":"CZ",
    "qs_pg:gn_country":"CZ",
    "qs_pg:gn_fcode":"PPL",
    "qs_pg:gn_pop":84,
    "qs_pg:name":"\u00dajezdec",
    "qs_pg:name_adm0":"\u010cesk\u00e1 republika",
    "qs_pg:name_adm1":"Pardubick\u00fd kraj",
    "qs_pg:photos_9r":0,
    "qs_pg:photos_sr":0,
    "qs_pg:pop_sr":1,
    "qs_pg:qs_pg_placetype":"locality",
    "qs_pg:qs_pg_placetype_gp":"Town",
    "qs_pg:woe_adm0":23424810,
    "woe:adm0_id":23424810,
    "woe:name_adm0":"\u010cesk\u00e1 republika",
    "woe:name_adm1":"Pardubick\u00fd kraj",
    "woe:placetype":"Town",
    "wof:name":"\u00dajezdec",
    "wof:placetype":"locality",
    "wof:population":84
},
  "geometry": {"coordinates":[16.20593,49.87776],"type":"Point"}
}