{
  "type": "Feature",
  "properties": {
    "gn:gn_country":"CZ",
    "gn:gn_fcode":"PPL",
    "gn:gn_pop":75,
    "gn:population":75,
    "iso:country":"CZ",
    "name:ces_x_preferred":[
        "Zde\u0148kov"
    ],
    "name:eng_x_preferred":[
        "Zde\u0148kov"
    ],
    "name:fas_x_preferred":[
        "\u0632\u062f\u0646\u06a9\u0648\u0648"
    ],
    "name:fra_x_preferred":[
        "Zde\u0148kov"
    ],
    "name:hun_x_preferred":[
        "Zde\u0148kov"
    ],
    "name:ita_x_preferred":[
        "Zde\u0148kov"
    ],
    "name:msa_x_preferred":[
        "Zde\u0148kov"
    ],
    "name:nan_x_preferred":[
        "Zde\u0148kov"
    ],
    "name:nld_x_preferred":[
        "Zde\u0148kov"
    ],
    "name:pol_x_preferred":[
        "Zde\u0148kov"
    ],
    "name:por_x_preferred":[
        "Zde\u0148kov"
    ],
    "name:rup_x_preferred":[
        "Zde\u0148kov"
    ],
    "name:slk_x_preferred":[
        "Zde\u0148kov"
    ],
    "name:srp_x_preferred":[
        "\u0417\u0434\u0435\u045a\u043a\u043e\u0432"
    ],
    "name:vie_x_preferred":[
        "Zde\u0148kov"
    ],
    "qs_pg:aaroncc":"CZ",
    "qs_pg:gn_country":"CZ",
    "qs_pg:gn_fcode":"PPL",
    "qs_pg:gn_pop":75,
    "qs_pg:name":"Zde\u0148kov",
    "qs_pg:name_adm0":"\u010cesk\u00e1 republika",
    "qs_pg:name_adm1":"Kraj Vyso\u010dina",
    "qs_pg:photos_9r":0,
    "qs_pg:photos_sr":0,
    "qs_pg:pop_sr":1,
    "qs_pg:qs_pg_placetype":"locality",
    "qs_pg:qs_pg_placetype_gp":"Town",
    "qs_pg:woe_adm0":23424810,
    "woe:adm0_id":23424810,
    "woe:name_adm0":"\u010cesk\u00e1 republika",
    "woe:name_adm1":"Kraj Vyso\u010dina",
    "woe:placetype":"Town",
    "wof:name":"Zde\u0148kov",
    "wof:placetype":"locality",
    "wof:population":75
},
  "geometry": {"coordinates":[15.61997,49.13993],"type":"Point"}
}