{
  "type": "Feature",
  "properties": {
    "gn:admin1_code":"88",
    "gn:admin2_code":"0207",
    "gn:asciiname":"Zehrov",
    "gn:country_code":"CZ",
    "gn:dem":253,
    "gn:feature_class":"P",
    "gn:feature_code":"PPL",
    "gn:name":"\u017dehrov",
    "gn:population":0,
    "gn:timezone":"Europe/Prague",
    "iso:country":"CZ",
    "wof:name":"Zehrov",
    "wof:placetype":"locality"
},
  "geometry": {"coordinates":[15.10019,50.53111],"type":"Point"}
}