{
  "type": "Feature",
  "properties": {
    "gn:admin1_code":"80.0",
    "gn:admin2_code":"0612",
    "gn:asciiname":"Slavibor",
    "gn:country_code":"CZ",
    "gn:dem":487,
    "gn:feature_class":"P",
    "gn:feature_code":"PPL",
    "gn:name":"Slavibo\u0159",
    "gn:population":0,
    "gn:timezone":"Europe/Prague",
    "iso:country":"CZ",
    "name:ces_x_preferred":[
        "Slavibor"
    ],
    "name:deu_x_preferred":[
        "Slavibor"
    ],
    "name:pol_x_preferred":[
        "S\u0142awibor"
    ],
    "name:srp_x_preferred":[
        "\u0421\u043b\u0430\u0432\u0438\u0431\u043e\u0440"
    ],
    "name:ukr_x_preferred":[
        "\u0421\u043b\u0430\u0432\u0456\u0431\u043e\u0440"
    ],
    "wof:name":"Slavibor",
    "wof:placetype":"locality"
},
  "geometry": {"coordinates":[15.46443,49.13465],"type":"Point"}
}