{
  "type": "Feature",
  "properties": {
    "gn:gn_country":"CZ",
    "gn:gn_fcode":"PPL",
    "gn:gn_pop":124,
    "gn:population":124,
    "iso:country":"CZ",
    "name:ces_x_preferred":[
        "Ta\u0161ov"
    ],
    "name:deu_x_preferred":[
        "Ta\u0161ov"
    ],
    "name:eng_x_preferred":[
        "Ta\u0161ov"
    ],
    "name:fas_x_preferred":[
        "\u062a\u0627\u0634\u0648\u0648"
    ],
    "name:fra_x_preferred":[
        "Ta\u0161ov"
    ],
    "name:hun_x_preferred":[
        "Ta\u0161ov"
    ],
    "name:ita_x_preferred":[
        "Ta\u0161ov"
    ],
    "name:msa_x_preferred":[
        "Ta\u0161ov"
    ],
    "name:nan_x_preferred":[
        "Ta\u0161ov"
    ],
    "name:nld_x_preferred":[
        "Ta\u0161ov"
    ],
    "name:pol_x_preferred":[
        "Ta\u0161ov"
    ],
    "name:por_x_preferred":[
        "Ta\u0161ov"
    ],
    "name:rup_x_preferred":[
        "Ta\u0161ov"
    ],
    "name:slk_x_preferred":[
        "Ta\u0161ov"
    ],
    "name:srp_x_preferred":[
        "\u0422\u0430\u0448\u043e\u0432"
    ],
    "name:swe_x_preferred":[
        "Ta\u0161ov"
    ],
    "name:vie_x_preferred":[
        "Ta\u0161ov"
    ],
    "qs_pg:aaroncc":"CZ",
    "qs_pg:gn_country":"CZ",
    "qs_pg:gn_fcode":"PPL",
    "qs_pg:gn_pop":124,
    "qs_pg:name":"Ta\u0161ov",
    "qs_pg:name_adm0":"\u010cesk\u00e1 republika",
    "qs_pg:name_adm1":"\u00dasteck\u00fd kraj",
    "qs_pg:photos_9k":1,
    "qs_pg:photos_9r":1,
    "qs_pg:photos_all":1,
    "qs_pg:photos_sr":0,
    "qs_pg:pop_sr":1,
    "qs_pg:qs_pg_placetype":"locality",
    "qs_pg:qs_pg_placetype_gp":"Town",
    "qs_pg:woe_adm0":23424810,
    "woe:adm0_id":23424810,
    "woe:name_adm0":"\u010cesk\u00e1 republika",
    "woe:name_adm1":"\u00dasteck\u00fd kraj",
    "woe:placetype":"Town",
    "wof:name":"Ta\u0161ov",
    "wof:placetype":"locality",
    "wof:population":124
},
  "geometry": {"coordinates":[14.13579,50.61452],"type":"Point"}
}