{
  "type": "Feature",
  "properties": {
    "gn:country":"CZ",
    "gn:fcode":"PPL",
    "gn:population":569,
    "iso:country":"CZ",
    "name:ceb_x_preferred":[
        "Trst\u011bnice"
    ],
    "name:ces_x_preferred":[
        "Trst\u011bnice"
    ],
    "name:deu_x_preferred":[
        "Trst\u011bnice u Moravsk\u00e9ho Krumlova"
    ],
    "name:eng_x_preferred":[
        "Trst\u011bnice"
    ],
    "name:eus_x_preferred":[
        "Trst\u011bnice"
    ],
    "name:fas_x_preferred":[
        "\u062a\u0631\u0633\u062a\u06cc\u0646\u06cc\u062a\u0633\u0647"
    ],
    "name:fra_x_preferred":[
        "Trst\u011bnice"
    ],
    "name:hun_x_preferred":[
        "Trst\u011bnice"
    ],
    "name:ita_x_preferred":[
        "Trst\u011bnice"
    ],
    "name:msa_x_preferred":[
        "Trst\u011bnice"
    ],
    "name:nan_x_preferred":[
        "Trst\u011bnice"
    ],
    "name:nld_x_preferred":[
        "Trst\u011bnice"
    ],
    "name:pol_x_preferred":[
        "Trst\u011bnice"
    ],
    "name:por_x_preferred":[
        "Trst\u011bnice"
    ],
    "name:rup_x_preferred":[
        "Trst\u011bnice"
    ],
    "name:slk_x_preferred":[
        "Trst\u011bnice"
    ],
    "name:spa_x_preferred":[
        "Trst\u011bnice"
    ],
    "name:srp_x_preferred":[
        "\u0422\u0440\u0441\u0442\u0458\u0435\u045a\u0438\u0446\u0435"
    ],
    "name:swe_x_preferred":[
        "Trst\u011bnice"
    ],
    "name:und_x_variant":[
        "K\u0159t\u011bnice"
    ],
    "name:vie_x_preferred":[
        "Trst\u011bnice"
    ],
    "qs_pg:aaroncc":"CZ",
    "qs_pg:gn_country":"CZ",
    "qs_pg:gn_fcode":"PPL",
    "qs_pg:gn_pop":569,
    "qs_pg:name":"Trst\u011bnice",
    "qs_pg:name_adm0":"\u010cesk\u00e1 republika",
    "qs_pg:name_adm1":"Jihomoravsk\u00fd kraj",
    "qs_pg:photos_9r":0,
    "qs_pg:photos_sr":0,
    "qs_pg:pop_sr":2,
    "qs_pg:qs_pg_placetype":"locality",
    "qs_pg:qs_pg_placetype_gp":"Town",
    "qs_pg:woe_adm0":23424810,
    "woe:adm0_id":23424810,
    "woe:name_adm0":"\u010cesk\u00e1 republika",
    "woe:name_adm1":"Jihomoravsk\u00fd kraj",
    "woe:placetype":"Town",
    "wof:name":"Trst\u011bnice",
    "wof:placetype":"locality",
    "wof:population":569
},
  "geometry": {"coordinates":[16.19542,48.98676],"type":"Point"}
}