{
  "type": "Feature",
  "properties": {
    "gn:admin1_code":"82.0",
    "gn:admin2_code":"0521",
    "gn:asciiname":"Klaster nad Dedinou",
    "gn:country_code":"CZ",
    "gn:dem":250,
    "gn:feature_class":"P",
    "gn:feature_code":"PPL",
    "gn:name":"Kl\u00e1\u0161ter nad D\u011bdinou",
    "gn:population":0,
    "gn:timezone":"Europe/Prague",
    "iso:country":"CZ",
    "wof:name":"Klaster nad Dedinou",
    "wof:placetype":"locality"
},
  "geometry": {"coordinates":[16.03817,50.23501],"type":"Point"}
}