{
  "type": "Feature",
  "properties": {
    "gn:admin1_code":"81.0",
    "gn:admin2_code":"0412",
    "gn:asciiname":"Maly Hrzin",
    "gn:country_code":"CZ",
    "gn:dem":554,
    "gn:feature_class":"P",
    "gn:feature_code":"PPL",
    "gn:name":"Mal\u00fd Hrz\u00edn",
    "gn:population":0,
    "gn:timezone":"Europe/Prague",
    "iso:country":"CZ",
    "name:und_x_variant":[
        "Kleingr\u00fcn",
        "Mal\u00fd Hrz\u00edn"
    ],
    "wof:name":"Maly Hrzin",
    "wof:placetype":"locality"
},
  "geometry": {"coordinates":[13.07438,50.37562],"type":"Point"}
}