{
  "type": "Feature",
  "properties": {
    "gn:country":"CZ",
    "gn:fcode":"PPL",
    "gn:population":470,
    "iso:country":"CZ",
    "name:cat_x_preferred":[
        "\u00dasobrno"
    ],
    "name:ceb_x_preferred":[
        "\u00dasobrno"
    ],
    "name:ces_x_preferred":[
        "\u00dasobrno"
    ],
    "name:che_x_preferred":[
        "\u0423\u0441\u043e\u0431\u0440\u043d\u043e"
    ],
    "name:deu_x_preferred":[
        "\u00dasobrno"
    ],
    "name:eng_x_preferred":[
        "\u00dasobrno"
    ],
    "name:epo_x_preferred":[
        "\u00dasobrno"
    ],
    "name:eus_x_preferred":[
        "\u00dasobrno"
    ],
    "name:fas_x_preferred":[
        "\u0627\u0648\u0633\u0648\u0628\u0631\u0646\u0648"
    ],
    "name:fra_x_preferred":[
        "\u00dasobrno"
    ],
    "name:gle_x_preferred":[
        "\u00dasobrno"
    ],
    "name:hun_x_preferred":[
        "\u00dasobrno"
    ],
    "name:ita_x_preferred":[
        "\u00dasobrno"
    ],
    "name:lmo_x_preferred":[
        "\u00dasobrno"
    ],
    "name:msa_x_preferred":[
        "\u00dasobrno"
    ],
    "name:nan_x_preferred":[
        "\u00dasobrno"
    ],
    "name:nld_x_preferred":[
        "\u00dasobrno"
    ],
    "name:oci_x_preferred":[
        "\u00dasobrno"
    ],
    "name:pol_x_preferred":[
        "\u00dasobrno"
    ],
    "name:por_x_preferred":[
        "\u00dasobrno"
    ],
    "name:rup_x_preferred":[
        "\u00dasobrno"
    ],
    "name:slk_x_preferred":[
        "\u00dasobrno"
    ],
    "name:spa_x_preferred":[
        "\u00dasobrno"
    ],
    "name:srp_x_preferred":[
        "\u0423\u0441\u043e\u0431\u0440\u043d\u043e"
    ],
    "name:swe_x_preferred":[
        "\u00dasobrno"
    ],
    "name:tat_x_preferred":[
        "\u0423\u0441\u043e\u0431\u0440\u043d\u043e"
    ],
    "name:und_x_variant":[
        "Hausbr\u00fcnn"
    ],
    "name:vie_x_preferred":[
        "\u00dasobrno"
    ],
    "qs_pg:aaroncc":"CZ",
    "qs_pg:gn_country":"CZ",
    "qs_pg:gn_fcode":"PPL",
    "qs_pg:gn_pop":470,
    "qs_pg:name":"\u00dasobrno",
    "qs_pg:name_adm0":"\u010cesk\u00e1 republika",
    "qs_pg:name_adm1":"Jihomoravsk\u00fd kraj",
    "qs_pg:photos_9r":0,
    "qs_pg:photos_sr":0,
    "qs_pg:pop_sr":2,
    "qs_pg:qs_pg_placetype":"locality",
    "qs_pg:qs_pg_placetype_gp":"Town",
    "qs_pg:woe_adm0":23424810,
    "woe:adm0_id":23424810,
    "woe:name_adm0":"\u010cesk\u00e1 republika",
    "woe:name_adm1":"Jihomoravsk\u00fd kraj",
    "woe:placetype":"Town",
    "wof:name":"\u00dasobrno",
    "wof:placetype":"locality",
    "wof:population":470
},
  "geometry": {"coordinates":[16.76288,49.58892],"type":"Point"}
}