{
  "type": "Feature",
  "properties": {
    "gn:admin1_code":"79.0",
    "gn:admin2_code":"0312",
    "gn:asciiname":"Nussdoerfl",
    "gn:country_code":"CZ",
    "gn:dem":797,
    "gn:feature_class":"P",
    "gn:feature_code":"PPL",
    "gn:name":"Nussd\u00f6rfl",
    "gn:population":0,
    "gn:timezone":"Europe/Prague",
    "iso:country":"CZ",
    "wof:name":"Nussdoerfl",
    "wof:placetype":"locality"
},
  "geometry": {"coordinates":[14.11391,48.77062],"type":"Point"}
}