{
  "type": "Feature",
  "properties": {
    "gn:admin1_code":"87.0",
    "gn:admin2_code":"0321",
    "gn:asciiname":"Nacetin",
    "gn:country_code":"CZ",
    "gn:dem":545,
    "gn:feature_class":"P",
    "gn:feature_code":"PPL",
    "gn:name":"Na\u010det\u00edn",
    "gn:population":0,
    "gn:timezone":"Europe/Prague",
    "iso:country":"CZ",
    "wof:name":"Nacetin",
    "wof:placetype":"locality"
},
  "geometry": {"coordinates":[12.7486,49.51217000000001],"type":"Point"}
}