{
  "type": "Feature",
  "properties": {
    "gn:admin1_code":"84",
    "gn:admin2_code":"0712",
    "gn:asciiname":"Svaty Kopecek",
    "gn:country_code":"CZ",
    "gn:dem":373,
    "gn:feature_class":"P",
    "gn:feature_code":"PPL",
    "gn:name":"Svat\u00fd Kope\u010dek",
    "gn:population":0,
    "gn:timezone":"Europe/Prague",
    "iso:country":"CZ",
    "name:und_x_variant":[
        "Heiligberg",
        "Svat\u00fd Kope\u010dek"
    ],
    "wof:name":"Svaty Kopecek",
    "wof:placetype":"locality"
},
  "geometry": {"coordinates":[17.34428,49.63036],"type":"Point"}
}