{
  "type": "Feature",
  "properties": {
    "gn:admin1_code":"86.0",
    "gn:admin2_code":"0532",
    "gn:asciiname":"Klenovka",
    "gn:country_code":"CZ",
    "gn:dem":233,
    "gn:feature_class":"P",
    "gn:feature_code":"PPL",
    "gn:name":"Klenovka",
    "gn:population":0,
    "gn:timezone":"Europe/Prague",
    "iso:country":"CZ",
    "name:che_x_preferred":[
        "\u041a\u043b\u0435\u043d\u043e\u0432\u043a\u0430"
    ],
    "name:rus_x_preferred":[
        "\u041a\u043b\u0435\u043d\u043e\u0432\u043a\u0430"
    ],
    "wof:name":"Klenovka",
    "wof:placetype":"locality"
},
  "geometry": {"coordinates":[15.59939,50.02466],"type":"Point"}
}