{
  "type": "Feature",
  "properties": {
    "gn:admin1_code":"89.0",
    "gn:admin2_code":"0421",
    "gn:asciiname":"Rozany",
    "gn:country_code":"CZ",
    "gn:dem":322,
    "gn:feature_class":"P",
    "gn:feature_code":"PPL",
    "gn:name":"Ro\u017eany",
    "gn:population":0,
    "gn:timezone":"Europe/Prague",
    "iso:country":"CZ",
    "name:und_x_variant":[
        "Rosenhain",
        "Ro\u017eany"
    ],
    "wof:name":"Rozany",
    "wof:placetype":"locality"
},
  "geometry": {"coordinates":[14.45055,51.02843],"type":"Point"}
}