{
  "type": "Feature",
  "properties": {
    "iso:country":"CZ",
    "name:ceb_x_preferred":[
        "Humpolec"
    ],
    "name:ces_x_preferred":[
        "Humpolec"
    ],
    "name:deu_x_preferred":[
        "Humpolec"
    ],
    "name:epo_x_preferred":[
        "Humpolec"
    ],
    "name:eus_x_preferred":[
        "Humpolec"
    ],
    "name:fas_x_preferred":[
        "\u0647\u0648\u0645\u067e\u0648\u0644\u062a\u0633"
    ],
    "name:fra_x_preferred":[
        "Humpolec"
    ],
    "name:hun_x_preferred":[
        "Humpolec"
    ],
    "name:ita_x_preferred":[
        "Humpolec"
    ],
    "name:lav_x_preferred":[
        "Humpoleca"
    ],
    "name:msa_x_preferred":[
        "Humpolec"
    ],
    "name:nld_x_preferred":[
        "Humpolec"
    ],
    "name:pol_x_preferred":[
        "Humpolec"
    ],
    "name:por_x_preferred":[
        "Humpolec"
    ],
    "name:rus_x_preferred":[
        "\u0413\u0443\u043c\u043f\u043e\u043b\u0435\u0446"
    ],
    "name:slk_x_preferred":[
        "Humpolec"
    ],
    "name:spa_x_preferred":[
        "Humpolec"
    ],
    "name:srp_x_preferred":[
        "\u0425\u0443\u043c\u043f\u043e\u043b\u0435\u0446"
    ],
    "name:swe_x_preferred":[
        "Humpolec"
    ],
    "name:ukr_x_preferred":[
        "\u0413\u0443\u043c\u043f\u043e\u043b\u0435\u0446"
    ],
    "name:vie_x_preferred":[
        "Humpolec"
    ],
    "name:zho_x_preferred":[
        "\u6d2a\u6ce2\u840a\u8328"
    ],
    "qs_pg:aaroncc":"CZ",
    "qs_pg:name":"Humpolec",
    "qs_pg:name_adm0":"\u010cesk\u00e1 republika",
    "qs_pg:name_adm1":"Kraj Vyso\u010dina",
    "qs_pg:photos":9,
    "qs_pg:photos_1k":2,
    "qs_pg:photos_9k":1,
    "qs_pg:photos_9r":1,
    "qs_pg:photos_all":9,
    "qs_pg:photos_sr":1,
    "qs_pg:pop_sr":0,
    "qs_pg:qs_pg_placetype":"localadmin",
    "qs_pg:qs_pg_placetype_gp":"LocalAdmin",
    "qs_pg:woe_adm0":23424810,
    "woe:adm0_id":23424810,
    "woe:name_adm0":"\u010cesk\u00e1 republika",
    "woe:name_adm1":"Kraj Vyso\u010dina",
    "woe:placetype":"LocalAdmin",
    "wof:name":"Humpolec",
    "wof:placetype":"localadmin"
},
  "geometry": {"coordinates":[15.35932,49.54152],"type":"Point"}
}