{
  "type": "Feature",
  "properties": {
    "gn:gn_country":"CZ",
    "gn:gn_fcode":"PPL",
    "gn:gn_pop":465,
    "gn:population":465,
    "iso:country":"CZ",
    "name:azb_x_preferred":[
        "\u0648\u06cc\u062a\u0648\u0646\u06cc\u062a\u0633\u0647"
    ],
    "name:ceb_x_preferred":[
        "V\u00edtonice"
    ],
    "name:ces_x_preferred":[
        "V\u00edtonice"
    ],
    "name:deu_x_preferred":[
        "V\u00edtonice"
    ],
    "name:eng_x_preferred":[
        "V\u00edtonice"
    ],
    "name:eus_x_preferred":[
        "V\u00edtonice"
    ],
    "name:fas_x_preferred":[
        "\u0648\u06cc\u062a\u0648\u0646\u06cc\u062a\u0633\u0647"
    ],
    "name:fra_x_preferred":[
        "V\u00edtonice"
    ],
    "name:hun_x_preferred":[
        "V\u00edtonice"
    ],
    "name:ita_x_preferred":[
        "V\u00edtonice"
    ],
    "name:msa_x_preferred":[
        "V\u00edtonice"
    ],
    "name:nan_x_preferred":[
        "V\u00edtonice"
    ],
    "name:nld_x_preferred":[
        "V\u00edtonice"
    ],
    "name:pol_x_preferred":[
        "V\u00edtonice"
    ],
    "name:por_x_preferred":[
        "V\u00edtonice"
    ],
    "name:rup_x_preferred":[
        "V\u00edtonice"
    ],
    "name:slk_x_preferred":[
        "V\u00edtonice"
    ],
    "name:spa_x_preferred":[
        "V\u00edtonice"
    ],
    "name:srp_x_preferred":[
        "\u0412\u0438\u0442\u043e\u045a\u0438\u0446\u0435"
    ],
    "name:swe_x_preferred":[
        "V\u00edtonice"
    ],
    "name:vie_x_preferred":[
        "V\u00edtonice"
    ],
    "qs_pg:aaroncc":"CZ",
    "qs_pg:gn_country":"CZ",
    "qs_pg:gn_fcode":"PPL",
    "qs_pg:gn_pop":465,
    "qs_pg:name":"V\u00edtonice",
    "qs_pg:photos_9r":0,
    "qs_pg:photos_sr":0,
    "qs_pg:pop_sr":2,
    "qs_pg:qs_pg_placetype":"locality",
    "wof:name":"V\u00edtonice",
    "wof:placetype":"locality",
    "wof:population":465
},
  "geometry": {"coordinates":[17.69296,49.44713],"type":"Point"}
}