{
  "type": "Feature",
  "properties": {
    "gn:gn_country":"CZ",
    "gn:gn_fcode":"PPL",
    "gn:gn_pop":1853,
    "gn:population":1853,
    "iso:country":"CZ",
    "name:ceb_x_preferred":[
        "Krmel\u00edn"
    ],
    "name:ces_x_preferred":[
        "Krmel\u00edn"
    ],
    "name:deu_x_preferred":[
        "Krmel\u00edn"
    ],
    "name:eng_x_preferred":[
        "Krmel\u00edn"
    ],
    "name:eus_x_preferred":[
        "Krmel\u00edn"
    ],
    "name:fra_x_preferred":[
        "Krmel\u00edn"
    ],
    "name:hun_x_preferred":[
        "Krmel\u00edn"
    ],
    "name:ita_x_preferred":[
        "Krmel\u00edn"
    ],
    "name:msa_x_preferred":[
        "Krmel\u00edn"
    ],
    "name:nan_x_preferred":[
        "Krmel\u00edn"
    ],
    "name:nld_x_preferred":[
        "Krmel\u00edn"
    ],
    "name:pol_x_preferred":[
        "Krmel\u00edn"
    ],
    "name:por_x_preferred":[
        "Krmel\u00edn"
    ],
    "name:slk_x_preferred":[
        "Krmel\u00edn"
    ],
    "name:spa_x_preferred":[
        "Krmel\u00edn"
    ],
    "name:srp_x_preferred":[
        "\u041a\u0440\u043c\u0435\u043b\u0438\u043d"
    ],
    "name:swe_x_preferred":[
        "Krmel\u00edn"
    ],
    "name:vie_x_preferred":[
        "Krmel\u00edn"
    ],
    "qs_pg:aaroncc":"CZ",
    "qs_pg:gn_country":"CZ",
    "qs_pg:gn_fcode":"PPL",
    "qs_pg:gn_pop":1853,
    "qs_pg:name":"Krmelin",
    "qs_pg:name_adm0":"\u010cesk\u00e1 republika",
    "qs_pg:name_adm1":"Moravskoslezsk\u00fd kraj",
    "qs_pg:photos_9r":0,
    "qs_pg:photos_sr":0,
    "qs_pg:pop_sr":3,
    "qs_pg:qs_pg_placetype":"locality",
    "qs_pg:qs_pg_placetype_gp":"Town",
    "qs_pg:woe_adm0":23424810,
    "woe:adm0_id":23424810,
    "woe:name_adm0":"\u010cesk\u00e1 republika",
    "woe:name_adm1":"Moravskoslezsk\u00fd kraj",
    "woe:placetype":"Town",
    "wof:name":"Krmelin",
    "wof:placetype":"locality",
    "wof:population":1853
},
  "geometry": {"coordinates":[18.23541,49.72914],"type":"Point"}
}