{
  "type": "Feature",
  "properties": {
    "gn:admin1_code":"87.0",
    "gn:admin2_code":"0322",
    "gn:asciiname":"Habartice",
    "gn:country_code":"CZ",
    "gn:dem":624,
    "gn:feature_class":"P",
    "gn:feature_code":"PPL",
    "gn:name":"Habartice",
    "gn:population":0,
    "gn:timezone":"Europe/Prague",
    "iso:country":"CZ",
    "name:ceb_x_preferred":[
        "Habartice"
    ],
    "name:ces_x_preferred":[
        "Habartice"
    ],
    "name:deu_x_preferred":[
        "Habartice"
    ],
    "name:swe_x_preferred":[
        "Habartice"
    ],
    "wof:name":"Habartice",
    "wof:placetype":"locality"
},
  "geometry": {"coordinates":[13.40564,49.39026],"type":"Point"}
}