{
  "type": "Feature",
  "properties": {
    "gn:country":"CZ",
    "gn:fcode":"PPL",
    "gn:population":44,
    "iso:country":"CZ",
    "name:azb_x_preferred":[
        "\u0628\u0648\u0647\u0648\u0646\u06cc\u062a\u0633\u0647"
    ],
    "name:ces_x_preferred":[
        "Bohunice"
    ],
    "name:deu_x_preferred":[
        "Bohunice u Tvrzic"
    ],
    "name:eng_x_preferred":[
        "Bohunice"
    ],
    "name:eus_x_preferred":[
        "Bohunice"
    ],
    "name:fas_x_preferred":[
        "\u0628\u0648\u0647\u0648\u0646\u06cc\u062a\u0633\u0647"
    ],
    "name:fra_x_preferred":[
        "Bohunice"
    ],
    "name:hun_x_preferred":[
        "Bohunice"
    ],
    "name:ita_x_preferred":[
        "Bohunice"
    ],
    "name:msa_x_preferred":[
        "Bohunice"
    ],
    "name:nan_x_preferred":[
        "Bohunice"
    ],
    "name:nld_x_preferred":[
        "Bohunice"
    ],
    "name:por_x_preferred":[
        "Bohunice"
    ],
    "name:rup_x_preferred":[
        "Bohunice"
    ],
    "name:slk_x_preferred":[
        "Bohunice"
    ],
    "name:spa_x_preferred":[
        "Bohunice"
    ],
    "name:srp_x_preferred":[
        "\u0411\u043e\u0445\u0443\u045a\u0438\u0446\u0435"
    ],
    "name:vie_x_preferred":[
        "Bohunice"
    ],
    "qs_pg:aaroncc":"CZ",
    "qs_pg:gn_country":"CZ",
    "qs_pg:gn_fcode":"PPL",
    "qs_pg:gn_pop":44,
    "qs_pg:name":"Bohunice",
    "qs_pg:name_adm0":"\u010cesk\u00e1 republika",
    "qs_pg:name_adm1":"Jiho\u010desk\u00fd kraj",
    "qs_pg:photos_9k":1,
    "qs_pg:photos_9r":1,
    "qs_pg:photos_all":1,
    "qs_pg:photos_sr":0,
    "qs_pg:pop_sr":1,
    "qs_pg:qs_pg_placetype":"locality",
    "qs_pg:qs_pg_placetype_gp":"Town",
    "qs_pg:woe_adm0":23424810,
    "woe:adm0_id":23424810,
    "woe:name_adm0":"\u010cesk\u00e1 republika",
    "woe:name_adm1":"Jiho\u010desk\u00fd kraj",
    "woe:placetype":"Town",
    "wof:name":"Bohunice",
    "wof:placetype":"locality",
    "wof:population":44
},
  "geometry": {"coordinates":[14.38093,49.21087],"type":"Point"}
}