{
  "type": "Feature",
  "properties": {
    "gn:gn_country":"CZ",
    "gn:gn_fcode":"PPL",
    "gn:gn_pop":177,
    "gn:population":177,
    "iso:country":"CZ",
    "name:azb_x_preferred":[
        "\u0648\u0644\u06a9\u0627 \u0644\u0686\u06cc\u06a9"
    ],
    "name:ceb_x_preferred":[
        "Velk\u00e1 Le\u010dice"
    ],
    "name:ces_x_preferred":[
        "Velk\u00e1 Le\u010dice"
    ],
    "name:deu_x_preferred":[
        "Velk\u00e1 Le\u010dice"
    ],
    "name:eng_x_preferred":[
        "Velk\u00e1 Le\u010dice"
    ],
    "name:eus_x_preferred":[
        "Velk\u00e1 Le\u010dice"
    ],
    "name:fas_x_preferred":[
        "\u0648\u0644\u06a9\u0627 \u0644\u0686\u06cc\u06a9"
    ],
    "name:fra_x_preferred":[
        "Velk\u00e1 Le\u010dice"
    ],
    "name:hun_x_preferred":[
        "Velk\u00e1 Le\u010dice"
    ],
    "name:ita_x_preferred":[
        "Velk\u00e1 Le\u010dice"
    ],
    "name:msa_x_preferred":[
        "Velk\u00e1 Le\u010dice"
    ],
    "name:nan_x_preferred":[
        "Velk\u00e1 Le\u010dice"
    ],
    "name:nld_x_preferred":[
        "Velk\u00e1 Le\u010dice"
    ],
    "name:por_x_preferred":[
        "Velk\u00e1 Le\u010dice"
    ],
    "name:slk_x_preferred":[
        "Velk\u00e1 Le\u010dice"
    ],
    "name:spa_x_preferred":[
        "Velk\u00e1 Le\u010dice"
    ],
    "name:srp_x_preferred":[
        "\u0412\u0435\u043b\u043a\u0430 \u041b\u0435\u0447\u0438\u0446\u0430"
    ],
    "name:swe_x_preferred":[
        "Velk\u00e1 Le\u010dice"
    ],
    "name:vie_x_preferred":[
        "Velk\u00e1 Le\u010dice"
    ],
    "qs_pg:aaroncc":"CZ",
    "qs_pg:gn_country":"CZ",
    "qs_pg:gn_fcode":"PPL",
    "qs_pg:gn_pop":177,
    "qs_pg:name":"Velk\u00e1 Le\u010dice",
    "qs_pg:name_adm0":"\u010cesk\u00e1 republika",
    "qs_pg:name_adm1":"St\u0159edo\u010desk\u00fd kraj",
    "qs_pg:photos_9r":0,
    "qs_pg:photos_sr":0,
    "qs_pg:pop_sr":1,
    "qs_pg:qs_pg_placetype":"locality",
    "qs_pg:qs_pg_placetype_gp":"Town",
    "qs_pg:woe_adm0":23424810,
    "woe:adm0_id":23424810,
    "woe:name_adm0":"\u010cesk\u00e1 republika",
    "woe:name_adm1":"St\u0159edo\u010desk\u00fd kraj",
    "woe:placetype":"Town",
    "wof:name":"Velk\u00e1 Le\u010dice",
    "wof:placetype":"locality",
    "wof:population":177
},
  "geometry": {"coordinates":[14.32348,49.81471],"type":"Point"}
}