{
  "type": "Feature",
  "properties": {
    "gn:admin1_code":"85.0",
    "gn:admin2_code":"0805",
    "gn:asciiname":"Lipina",
    "gn:country_code":"CZ",
    "gn:dem":469,
    "gn:feature_class":"P",
    "gn:feature_code":"PPL",
    "gn:name":"Lipina",
    "gn:population":0,
    "gn:timezone":"Europe/Prague",
    "iso:country":"CZ",
    "name:ceb_x_preferred":[
        "Lipina"
    ],
    "name:ces_x_preferred":[
        "Lipina"
    ],
    "name:deu_x_preferred":[
        "Lipina"
    ],
    "name:fra_x_preferred":[
        "Lipina"
    ],
    "name:lit_x_preferred":[
        "Lipina"
    ],
    "name:pol_x_preferred":[
        "Lipina"
    ],
    "name:rus_x_preferred":[
        "\u041b\u0438\u043f\u0438\u043d\u0430"
    ],
    "name:slk_x_preferred":[
        "Lipina"
    ],
    "name:srp_x_preferred":[
        "\u041b\u0438\u043f\u0438\u043d\u0430"
    ],
    "name:swe_x_preferred":[
        "Lipina"
    ],
    "name:ukr_x_preferred":[
        "\u041b\u0456\u043f\u0456\u043d\u0430"
    ],
    "name:und_x_variant":[
        "Lippin"
    ],
    "wof:name":"Lipina",
    "wof:placetype":"locality"
},
  "geometry": {"coordinates":[17.79667000000001,49.86048],"type":"Point"}
}