{
  "type": "Feature",
  "properties": {
    "gn:admin1_code":"85.0",
    "gn:admin2_code":"0805",
    "gn:asciiname":"Lipina",
    "gn:country_code":"CZ",
    "gn:dem":469,
    "gn:feature_class":"P",
    "gn:feature_code":"PPL",
    "gn:name":"Lipina",
    "gn:population":0,
    "gn:timezone":"Europe/Prague",
    "iso:country":"CZ",
    "name:und_x_variant":[
        "Lippin",
        "Lipina"
    ],
    "wof:name":"Lipina",
    "wof:placetype":"locality"
},
  "geometry": {"coordinates":[17.79667000000001,49.86048],"type":"Point"}
}