{
  "type": "Feature",
  "properties": {
    "gn:admin1_code":"84",
    "gn:admin2_code":"0715",
    "gn:asciiname":"Stepanov",
    "gn:country_code":"CZ",
    "gn:dem":598,
    "gn:feature_class":"P",
    "gn:feature_code":"PPL",
    "gn:name":"\u0160t\u011bp\u00e1nov",
    "gn:population":3306,
    "gn:timezone":"Europe/Prague",
    "iso:country":"CZ",
    "name:ces_x_preferred":[
        "\u0160t\u011bp\u00e1nov"
    ],
    "name:deu_x_preferred":[
        "Stiepanau"
    ],
    "name:und_x_variant":[
        "\u0160t\u011bp\u00e1nov",
        "Stiepanau"
    ],
    "wof:name":"Stepanov",
    "wof:placetype":"locality",
    "wof:population":3306
},
  "geometry": {"coordinates":[16.91702,50.16238],"type":"Point"}
}