{
  "type": "Feature",
  "properties": {
    "gn:admin1_code":"79.0",
    "gn:admin2_code":"0313",
    "gn:asciiname":"Poldovka",
    "gn:country_code":"CZ",
    "gn:dem":702,
    "gn:feature_class":"P",
    "gn:feature_code":"PPL",
    "gn:name":"Poldovka",
    "gn:population":0,
    "gn:timezone":"Europe/Prague",
    "iso:country":"CZ",
    "wof:name":"Poldovka",
    "wof:placetype":"locality"
},
  "geometry": {"coordinates":[15.33195,49.15427],"type":"Point"}
}