{
  "type": "Feature",
  "properties": {
    "gn:admin1_code":"79.0",
    "gn:admin2_code":"0312",
    "gn:asciiname":"Sedlice",
    "gn:country_code":"CZ",
    "gn:dem":656,
    "gn:feature_class":"P",
    "gn:feature_code":"PPL",
    "gn:name":"Sedlice",
    "gn:population":1220,
    "gn:timezone":"Europe/Prague",
    "iso:country":"CZ",
    "name:ceb_x_preferred":[
        "Sedlice"
    ],
    "name:ces_x_preferred":[
        "Sedlice"
    ],
    "name:deu_x_preferred":[
        "Sedlice"
    ],
    "name:epo_x_preferred":[
        "Sedlice"
    ],
    "name:eus_x_preferred":[
        "Sedlice"
    ],
    "name:fra_x_preferred":[
        "Sedlice"
    ],
    "name:ita_x_preferred":[
        "Sedlice"
    ],
    "name:nld_x_preferred":[
        "Sedlice"
    ],
    "name:pol_x_preferred":[
        "Sedlice"
    ],
    "name:slk_x_preferred":[
        "Sedlice"
    ],
    "name:srp_x_preferred":[
        "\u0421\u0435\u0434\u043b\u0438\u0446\u0435"
    ],
    "name:swe_x_preferred":[
        "Sedlice"
    ],
    "name:ukr_x_preferred":[
        "\u0421\u0435\u0434\u043b\u0438\u0446\u0435"
    ],
    "wof:name":"Sedlice",
    "wof:placetype":"locality",
    "wof:population":1220
},
  "geometry": {"coordinates":[14.39115,48.77401],"type":"Point"}
}