{
  "type": "Feature",
  "properties": {
    "iso:country":"CZ",
    "name:bul_x_preferred":[
        "\u041a\u0430\u043d\u0438\u0446\u0435"
    ],
    "name:ceb_x_preferred":[
        "Kanice"
    ],
    "name:ces_x_preferred":[
        "Kanice"
    ],
    "name:deu_x_preferred":[
        "Kanice"
    ],
    "name:fra_x_preferred":[
        "Kanice"
    ],
    "name:ita_x_preferred":[
        "Kanice"
    ],
    "name:nld_x_preferred":[
        "Kanice"
    ],
    "name:pol_x_preferred":[
        "Kanice"
    ],
    "name:slk_x_preferred":[
        "Kanice"
    ],
    "name:srp_x_preferred":[
        "\u041a\u0430\u045a\u0438\u0446\u0435"
    ],
    "name:swe_x_preferred":[
        "Kanice"
    ],
    "qs_pg:aaroncc":"CZ",
    "qs_pg:name":"Kanice",
    "qs_pg:name_adm0":"\u010cesk\u00e1 republika",
    "qs_pg:name_adm1":"Jihomoravsk\u00fd kraj",
    "qs_pg:photos":59,
    "qs_pg:photos_1k":12,
    "qs_pg:photos_9k":1,
    "qs_pg:photos_9r":2,
    "qs_pg:photos_all":59,
    "qs_pg:photos_sr":2,
    "qs_pg:pop_sr":0,
    "qs_pg:qs_pg_placetype":"localadmin",
    "qs_pg:qs_pg_placetype_gp":"LocalAdmin",
    "qs_pg:woe_adm0":23424810,
    "woe:adm0_id":23424810,
    "woe:name_adm0":"\u010cesk\u00e1 republika",
    "woe:name_adm1":"Jihomoravsk\u00fd kraj",
    "woe:placetype":"LocalAdmin",
    "wof:name":"Kanice",
    "wof:placetype":"localadmin"
},
  "geometry": {"coordinates":[16.696144,49.237381],"type":"Point"}
}