{
  "type": "Feature",
  "properties": {
    "gn:admin1_code":"88.0",
    "gn:admin2_code":"020B",
    "gn:asciiname":"Kletice",
    "gn:country_code":"CZ",
    "gn:dem":490,
    "gn:feature_class":"P",
    "gn:feature_code":"PPL",
    "gn:name":"Kletice",
    "gn:population":0,
    "gn:timezone":"Europe/Prague",
    "iso:country":"CZ",
    "wof:name":"Kletice",
    "wof:placetype":"locality"
},
  "geometry": {"coordinates":[14.04775,49.57966],"type":"Point"}
}