{
  "type": "Feature",
  "properties": {
    "gn:admin1_code":"79.0",
    "gn:admin2_code":"0315",
    "gn:asciiname":"Petruv Dvur",
    "gn:country_code":"CZ",
    "gn:dem":489,
    "gn:feature_class":"P",
    "gn:feature_code":"PPL",
    "gn:name":"Petr\u016fv Dv\u016fr",
    "gn:population":0,
    "gn:timezone":"Europe/Prague",
    "iso:country":"CZ",
    "wof:name":"Petruv Dvur",
    "wof:placetype":"locality"
},
  "geometry": {"coordinates":[14.16667,49.05],"type":"Point"}
}