{
  "type": "Feature",
  "properties": {
    "gn:admin1_code":"87.0",
    "gn:admin2_code":"0322",
    "gn:asciiname":"Kozi",
    "gn:country_code":"CZ",
    "gn:dem":492,
    "gn:feature_class":"P",
    "gn:feature_code":"PPL",
    "gn:name":"Koz\u00ed",
    "gn:population":0,
    "gn:timezone":"Europe/Prague",
    "iso:country":"CZ",
    "wof:name":"Kozi",
    "wof:placetype":"locality"
},
  "geometry": {"coordinates":[13.29312,49.30673],"type":"Point"}
}