{
  "type": "Feature",
  "properties": {
    "gn:admin1_code":"83.0",
    "gn:admin2_code":"0511",
    "gn:asciiname":"Litice",
    "gn:country_code":"CZ",
    "gn:dem":304,
    "gn:feature_class":"P",
    "gn:feature_code":"PPL",
    "gn:name":"Litice",
    "gn:population":0,
    "gn:timezone":"Europe/Prague",
    "iso:country":"CZ",
    "name:und_x_variant":[
        "Litnitz",
        "Litice"
    ],
    "wof:name":"Litice",
    "wof:placetype":"locality"
},
  "geometry": {"coordinates":[14.43896,50.61313],"type":"Point"}
}