{
  "type": "Feature",
  "properties": {
    "gn:admin1_code":"79.0",
    "gn:admin2_code":"0317",
    "gn:asciiname":"Chabrovice",
    "gn:country_code":"CZ",
    "gn:dem":481,
    "gn:feature_class":"P",
    "gn:feature_code":"PPL",
    "gn:name":"Chabrovice",
    "gn:population":0,
    "gn:timezone":"Europe/Prague",
    "iso:country":"CZ",
    "wof:name":"Chabrovice",
    "wof:placetype":"locality"
},
  "geometry": {"coordinates":[14.78495,49.33054],"type":"Point"}
}