{
  "type": "Feature",
  "properties": {
    "gn:gn_country":"CZ",
    "gn:gn_fcode":"PPL",
    "gn:gn_pop":260,
    "gn:population":260,
    "iso:country":"CZ",
    "name:ces_x_preferred":[
        "Bu\u0161anovice"
    ],
    "name:deu_x_preferred":[
        "Bu\u0161anovice"
    ],
    "name:eng_x_preferred":[
        "Bu\u0161anovice"
    ],
    "name:fas_x_preferred":[
        "\u0628\u0648\u0634\u0627\u0646\u0648\u0648\u06cc\u062a\u0633\u0647"
    ],
    "name:fra_x_preferred":[
        "Bu\u0161anovice"
    ],
    "name:hun_x_preferred":[
        "Bu\u0161anovice"
    ],
    "name:ita_x_preferred":[
        "Bu\u0161anovice"
    ],
    "name:msa_x_preferred":[
        "Bu\u0161anovice"
    ],
    "name:nan_x_preferred":[
        "Bu\u0161anovice"
    ],
    "name:nld_x_preferred":[
        "Bu\u0161anovice"
    ],
    "name:por_x_preferred":[
        "Bu\u0161anovice"
    ],
    "name:rup_x_preferred":[
        "Bu\u0161anovice"
    ],
    "name:slk_x_preferred":[
        "Bu\u0161anovice"
    ],
    "name:srp_x_preferred":[
        "\u0411\u0443\u0448\u0430\u043d\u043e\u0432\u0438\u0446\u0435"
    ],
    "name:swe_x_preferred":[
        "Bu\u0161anovice"
    ],
    "name:vie_x_preferred":[
        "Bu\u0161anovice"
    ],
    "qs_pg:aaroncc":"CZ",
    "qs_pg:gn_country":"CZ",
    "qs_pg:gn_fcode":"PPL",
    "qs_pg:gn_pop":260,
    "qs_pg:name":"Bu\u0161anovice",
    "qs_pg:name_adm0":"\u010cesk\u00e1 republika",
    "qs_pg:name_adm1":"Jiho\u010desk\u00fd kraj",
    "qs_pg:photos_9r":0,
    "qs_pg:photos_sr":0,
    "qs_pg:pop_sr":2,
    "qs_pg:qs_pg_placetype":"locality",
    "qs_pg:qs_pg_placetype_gp":"Town",
    "qs_pg:woe_adm0":23424810,
    "woe:adm0_id":23424810,
    "woe:name_adm0":"\u010cesk\u00e1 republika",
    "woe:name_adm1":"Jiho\u010desk\u00fd kraj",
    "woe:placetype":"Town",
    "wof:name":"Bu\u0161anovice",
    "wof:placetype":"locality",
    "wof:population":260
},
  "geometry": {"coordinates":[13.93469,49.11543],"type":"Point"}
}