{
  "type": "Feature",
  "properties": {
    "gn:admin1_code":"84.0",
    "gn:admin2_code":"0712",
    "gn:asciiname":"Kralova",
    "gn:country_code":"CZ",
    "gn:dem":252,
    "gn:feature_class":"P",
    "gn:feature_code":"PPL",
    "gn:name":"Kr\u00e1lov\u00e1",
    "gn:population":0,
    "gn:timezone":"Europe/Prague",
    "iso:country":"CZ",
    "name:und_x_variant":[
        "K\u00f6niglosen",
        "Kr\u00e1lov\u00e1"
    ],
    "wof:name":"Kralova",
    "wof:placetype":"locality"
},
  "geometry": {"coordinates":[17.0344,49.76905],"type":"Point"}
}