{
  "type": "Feature",
  "properties": {
    "gn:admin1_code":"80.0",
    "gn:admin2_code":"0612",
    "gn:asciiname":"Na Nemecku",
    "gn:country_code":"CZ",
    "gn:dem":558,
    "gn:feature_class":"P",
    "gn:feature_code":"PPL",
    "gn:name":"Na N\u011bme\u010dku",
    "gn:population":0,
    "gn:timezone":"Europe/Prague",
    "iso:country":"CZ",
    "wof:name":"Na Nemecku",
    "wof:placetype":"locality"
},
  "geometry": {"coordinates":[15.40387,49.48936],"type":"Point"}
}