{
  "type": "Feature",
  "properties": {
    "gn:admin1_code":"86.0",
    "gn:admin2_code":"0531",
    "gn:asciiname":"Pist'ovy",
    "gn:country_code":"CZ",
    "gn:dem":263,
    "gn:feature_class":"P",
    "gn:feature_code":"PPL",
    "gn:name":"Pi\u0161\u0165ovy",
    "gn:population":0,
    "gn:timezone":"Europe/Prague",
    "iso:country":"CZ",
    "wof:name":"Pist'ovy",
    "wof:placetype":"locality"
},
  "geometry": {"coordinates":[15.81727,49.93048],"type":"Point"}
}