{
  "type": "Feature",
  "properties": {
    "gn:admin1_code":"89.0",
    "gn:admin2_code":"0422",
    "gn:asciiname":"Brany",
    "gn:cc2":"CZ",
    "gn:country_code":"CZ",
    "gn:dem":309,
    "gn:feature_class":"P",
    "gn:feature_code":"PPL",
    "gn:name":"Brany",
    "gn:population":0,
    "gn:timezone":"Europe/Prague",
    "iso:country":"CZ",
    "name:ces_x_historical":[
        "Brany"
    ],
    "name:ces_x_preferred":[
        "Brany"
    ],
    "name:deu_x_historical":[
        "Prahn"
    ],
    "name:deu_x_preferred":[
        "Prahn"
    ],
    "wof:name":"Brany",
    "wof:placetype":"locality"
},
  "geometry": {"coordinates":[13.38333,50.41667],"type":"Point"}
}