{
  "type": "Feature",
  "properties": {
    "gn:admin1_code":"81.0",
    "gn:admin2_code":"0411",
    "gn:asciiname":"Dolni Paseky",
    "gn:country_code":"CZ",
    "gn:dem":564,
    "gn:feature_class":"P",
    "gn:feature_code":"PPL",
    "gn:name":"Doln\u00ed Paseky",
    "gn:population":0,
    "gn:timezone":"Europe/Prague",
    "iso:country":"CZ",
    "name:deu_x_preferred":[
        "Niederreuth"
    ],
    "name:und_x_variant":[
        "Doln\u00ed Reuth"
    ],
    "wof:name":"Dolni Paseky",
    "wof:placetype":"locality"
},
  "geometry": {"coordinates":[12.23516,50.23403],"type":"Point"}
}