{
  "type": "Feature",
  "properties": {
    "gn:admin1_code":"87.0",
    "gn:admin2_code":"0324",
    "gn:asciiname":"Dubec",
    "gn:cc2":"CZ",
    "gn:country_code":"CZ",
    "gn:dem":525,
    "gn:feature_class":"P",
    "gn:feature_code":"PPL",
    "gn:name":"Dube\u010d",
    "gn:population":0,
    "gn:timezone":"Europe/Prague",
    "iso:country":"CZ",
    "name:und_x_variant":[
        "Dv\u016dr Dube\u010d"
    ],
    "wof:name":"Dubec",
    "wof:placetype":"locality"
},
  "geometry": {"coordinates":[13.56073,49.51373],"type":"Point"}
}