{
  "type": "Feature",
  "properties": {
    "gn:country":"CZ",
    "gn:fcode":"PPL",
    "gn:population":59,
    "iso:country":"CZ",
    "name:azb_x_preferred":[
        "\u062e\u0648\u0631\u0627\u062a\u06cc\u062a\u0633\u0647"
    ],
    "name:cat_x_preferred":[
        "Choratice"
    ],
    "name:ces_x_preferred":[
        "Choratice"
    ],
    "name:che_x_preferred":[
        "\u0425\u043e\u0440\u0430\u0442\u0438\u0446\u0435"
    ],
    "name:deu_x_preferred":[
        "Choratice"
    ],
    "name:eng_x_preferred":[
        "Choratice"
    ],
    "name:epo_x_preferred":[
        "Choratice"
    ],
    "name:eus_x_preferred":[
        "Choratice"
    ],
    "name:fas_x_preferred":[
        "\u062e\u0648\u0631\u0627\u062a\u06cc\u062a\u0633\u0647"
    ],
    "name:fra_x_preferred":[
        "Choratice"
    ],
    "name:gle_x_preferred":[
        "Choratice"
    ],
    "name:hun_x_preferred":[
        "Choratice"
    ],
    "name:ita_x_preferred":[
        "Choratice"
    ],
    "name:lmo_x_preferred":[
        "Choratice"
    ],
    "name:msa_x_preferred":[
        "Choratice"
    ],
    "name:nan_x_preferred":[
        "Choratice"
    ],
    "name:nld_x_preferred":[
        "Choratice"
    ],
    "name:oci_x_preferred":[
        "Choratice"
    ],
    "name:pol_x_preferred":[
        "Choratice"
    ],
    "name:por_x_preferred":[
        "Choratice"
    ],
    "name:slk_x_preferred":[
        "Choratice"
    ],
    "name:spa_x_preferred":[
        "Choratice"
    ],
    "name:srp_x_preferred":[
        "\u0425\u043e\u0440\u0430\u0442\u0438\u0446\u0435"
    ],
    "name:tat_x_preferred":[
        "\u0425\u043e\u0440\u0430\u0442\u0438\u0446\u0435"
    ],
    "name:uzb_x_preferred":[
        "Choratice"
    ],
    "name:vie_x_preferred":[
        "Choratice"
    ],
    "qs_pg:aaroncc":"CZ",
    "qs_pg:gn_country":"CZ",
    "qs_pg:gn_fcode":"PPL",
    "qs_pg:gn_pop":59,
    "qs_pg:name":"Choratice",
    "qs_pg:name_adm0":"\u010cesk\u00e1 republika",
    "qs_pg:name_adm1":"St\u0159edo\u010desk\u00fd kraj",
    "qs_pg:photos_9r":0,
    "qs_pg:photos_sr":0,
    "qs_pg:pop_sr":1,
    "qs_pg:qs_pg_placetype":"locality",
    "qs_pg:qs_pg_placetype_gp":"Town",
    "qs_pg:woe_adm0":23424810,
    "woe:adm0_id":23424810,
    "woe:name_adm0":"\u010cesk\u00e1 republika",
    "woe:name_adm1":"St\u0159edo\u010desk\u00fd kraj",
    "woe:placetype":"Town",
    "wof:name":"Choratice",
    "wof:placetype":"locality",
    "wof:population":59
},
  "geometry": {"coordinates":[14.87469,49.83933],"type":"Point"}
}