{
  "type": "Feature",
  "properties": {
    "gn:admin1_code":"79.0",
    "gn:admin2_code":"0315",
    "gn:asciiname":"Babice",
    "gn:country_code":"CZ",
    "gn:dem":442,
    "gn:feature_class":"P",
    "gn:feature_code":"PPL",
    "gn:name":"Babice",
    "gn:population":71,
    "gn:timezone":"Europe/Prague",
    "iso:country":"CZ",
    "name:und_x_variant":[
        "Bowitz"
    ],
    "wof:name":"Babice",
    "wof:placetype":"locality",
    "wof:population":71
},
  "geometry": {"coordinates":[14.23758,49.02476],"type":"Point"}
}