{
  "type": "Feature",
  "properties": {
    "gn:admin1_code":"79.0",
    "gn:admin2_code":"0315",
    "gn:asciiname":"Babice",
    "gn:country_code":"CZ",
    "gn:dem":442,
    "gn:feature_class":"P",
    "gn:feature_code":"PPL",
    "gn:name":"Babice",
    "gn:population":71,
    "gn:timezone":"Europe/Prague",
    "iso:country":"CZ",
    "name:azb_x_preferred":[
        "\u0628\u0627\u0628\u06cc\u062a\u0633\u0647"
    ],
    "name:ces_x_preferred":[
        "Babice"
    ],
    "name:eus_x_preferred":[
        "Babice"
    ],
    "name:fas_x_preferred":[
        "\u0628\u0627\u0628\u06cc\u062a\u0633\u0647"
    ],
    "name:hun_x_preferred":[
        "Babice"
    ],
    "name:ita_x_preferred":[
        "Babice"
    ],
    "name:msa_x_preferred":[
        "Babice"
    ],
    "name:nld_x_preferred":[
        "Babice"
    ],
    "name:slk_x_preferred":[
        "Babice"
    ],
    "name:spa_x_preferred":[
        "Babice"
    ],
    "name:srp_x_preferred":[
        "\u0411\u0430\u0431\u0438\u0446\u0435"
    ],
    "name:und_x_variant":[
        "Bowitz"
    ],
    "name:vie_x_preferred":[
        "Babice"
    ],
    "wof:name":"Babice",
    "wof:placetype":"locality",
    "wof:population":71
},
  "geometry": {"coordinates":[14.23758,49.02476],"type":"Point"}
}