{
  "type": "Feature",
  "properties": {
    "gn:admin1_code":"87.0",
    "gn:admin2_code":"0325",
    "gn:asciiname":"Balkova",
    "gn:country_code":"CZ",
    "gn:dem":496,
    "gn:feature_class":"P",
    "gn:feature_code":"PPL",
    "gn:name":"Balkov\u00e1",
    "gn:population":0,
    "gn:timezone":"Europe/Prague",
    "iso:country":"CZ",
    "name:und_x_variant":[
        "Walkowa",
        "Balkov\u00e1"
    ],
    "wof:name":"Balkova",
    "wof:placetype":"locality"
},
  "geometry": {"coordinates":[13.29969,50.08435],"type":"Point"}
}