{
  "type": "Feature",
  "properties": {
    "gn:country":"CZ",
    "gn:fcode":"PPL",
    "gn:population":135,
    "iso:country":"CZ",
    "name:azb_x_preferred":[
        "\u062f\u0648\u0644\u0646\u06cc \u0647\u0631\u0627\u062e\u0648\u0648\u06cc\u062a\u0633\u0647"
    ],
    "name:ceb_x_preferred":[
        "Doln\u00ed Hrachovice"
    ],
    "name:ces_x_preferred":[
        "Doln\u00ed Hrachovice"
    ],
    "name:deu_x_preferred":[
        "Doln\u00ed Hrachovice"
    ],
    "name:eng_x_preferred":[
        "Doln\u00ed Hrachovice"
    ],
    "name:eus_x_preferred":[
        "Doln\u00ed Hrachovice"
    ],
    "name:fas_x_preferred":[
        "\u062f\u0648\u0644\u0646\u06cc \u0647\u0631\u0627\u062e\u0648\u0648\u06cc\u062a\u0633\u0647"
    ],
    "name:fra_x_preferred":[
        "Doln\u00ed Hrachovice"
    ],
    "name:hun_x_preferred":[
        "Doln\u00ed Hrachovice"
    ],
    "name:ita_x_preferred":[
        "Doln\u00ed Hrachovice"
    ],
    "name:msa_x_preferred":[
        "Doln\u00ed Hrachovice"
    ],
    "name:nan_x_preferred":[
        "Doln\u00ed Hrachovice"
    ],
    "name:nld_x_preferred":[
        "Doln\u00ed Hrachovice"
    ],
    "name:pol_x_preferred":[
        "Doln\u00ed Hrachovice"
    ],
    "name:por_x_preferred":[
        "Doln\u00ed Hrachovice"
    ],
    "name:rup_x_preferred":[
        "Doln\u00ed Hrachovice"
    ],
    "name:slk_x_preferred":[
        "Doln\u00ed Hrachovice"
    ],
    "name:spa_x_preferred":[
        "Doln\u00ed Hrachovice"
    ],
    "name:srp_x_preferred":[
        "\u0414\u043e\u043b\u045a\u0438 \u0425\u0440\u0430\u0445\u043e\u0432\u0438\u0446\u0435"
    ],
    "name:swe_x_preferred":[
        "Doln\u00ed Hrachovice"
    ],
    "name:vie_x_preferred":[
        "Doln\u00ed Hrachovice"
    ],
    "qs_pg:aaroncc":"CZ",
    "qs_pg:gn_country":"CZ",
    "qs_pg:gn_fcode":"PPL",
    "qs_pg:gn_pop":135,
    "qs_pg:name":"Doln\u00ed Hrachovice",
    "qs_pg:name_adm0":"\u010cesk\u00e1 republika",
    "qs_pg:name_adm1":"Jiho\u010desk\u00fd kraj",
    "qs_pg:photos_9r":0,
    "qs_pg:photos_sr":0,
    "qs_pg:pop_sr":1,
    "qs_pg:qs_pg_placetype":"locality",
    "qs_pg:qs_pg_placetype_gp":"Town",
    "qs_pg:woe_adm0":23424810,
    "woe:adm0_id":23424810,
    "woe:name_adm0":"\u010cesk\u00e1 republika",
    "woe:name_adm1":"Jiho\u010desk\u00fd kraj",
    "woe:placetype":"Town",
    "wof:name":"Doln\u00ed Hrachovice",
    "wof:placetype":"locality",
    "wof:population":135
},
  "geometry": {"coordinates":[14.7971,49.48608],"type":"Point"}
}