{
  "type": "Feature",
  "properties": {
    "gn:gn_country":"CZ",
    "gn:gn_fcode":"PPL",
    "gn:gn_pop":390,
    "gn:population":390,
    "iso:country":"CZ",
    "name:ceb_x_preferred":[
        "Star\u00fd Byd\u017eov"
    ],
    "name:ces_x_preferred":[
        "Star\u00fd Byd\u017eov"
    ],
    "name:deu_x_preferred":[
        "Star\u00fd Byd\u017eov"
    ],
    "name:eng_x_preferred":[
        "Star\u00fd Byd\u017eov"
    ],
    "name:eus_x_preferred":[
        "Star\u00fd Byd\u017eov"
    ],
    "name:fas_x_preferred":[
        "\u0633\u062a\u0627\u0631\u06cc \u0628\u06cc\u062c\u0648\u0648"
    ],
    "name:fra_x_preferred":[
        "Star\u00fd Byd\u017eov"
    ],
    "name:hun_x_preferred":[
        "Star\u00fd Byd\u017eov"
    ],
    "name:ita_x_preferred":[
        "Star\u00fd Byd\u017eov"
    ],
    "name:msa_x_preferred":[
        "Star\u00fd Byd\u017eov"
    ],
    "name:nan_x_preferred":[
        "Star\u00fd Byd\u017eov"
    ],
    "name:nld_x_preferred":[
        "Star\u00fd Byd\u017eov"
    ],
    "name:pol_x_preferred":[
        "Star\u00fd Byd\u017eov"
    ],
    "name:por_x_preferred":[
        "Star\u00fd Byd\u017eov"
    ],
    "name:rup_x_preferred":[
        "Star\u00fd Byd\u017eov"
    ],
    "name:slk_x_preferred":[
        "Star\u00fd Byd\u017eov"
    ],
    "name:spa_x_preferred":[
        "Star\u00fd Byd\u017eov"
    ],
    "name:srp_x_preferred":[
        "\u0421\u0442\u0430\u0440\u0438 \u0411\u0438\u045f\u043e\u0432"
    ],
    "name:swe_x_preferred":[
        "Star\u00fd Byd\u017eov"
    ],
    "name:unk_x_variant":[
        "Alt Bidschow"
    ],
    "name:vie_x_preferred":[
        "Star\u00fd Byd\u017eov"
    ],
    "qs_pg:aaroncc":"CZ",
    "qs_pg:gn_country":"CZ",
    "qs_pg:gn_fcode":"PPL",
    "qs_pg:gn_pop":390,
    "qs_pg:name":"Star\u00fd Byd\u017eov",
    "qs_pg:name_adm0":"\u010cesk\u00e1 republika",
    "qs_pg:name_adm1":"Kr\u00e1lov\u00e9hradeck\u00fd kraj",
    "qs_pg:photos_9r":0,
    "qs_pg:photos_sr":0,
    "qs_pg:pop_sr":2,
    "qs_pg:qs_pg_placetype":"locality",
    "qs_pg:qs_pg_placetype_gp":"Town",
    "qs_pg:woe_adm0":23424810,
    "woe:adm0_id":23424810,
    "woe:name_adm0":"\u010cesk\u00e1 republika",
    "woe:name_adm1":"Kr\u00e1lov\u00e9hradeck\u00fd kraj",
    "woe:placetype":"Town",
    "wof:name":"Star\u00fd Byd\u017eov",
    "wof:placetype":"locality",
    "wof:population":390
},
  "geometry": {"coordinates":[15.45233,50.25844],"type":"Point"}
}