{
  "type": "Feature",
  "properties": {
    "gn:admin1_code":"79.0",
    "gn:admin2_code":"0313",
    "gn:asciiname":"Hurky",
    "gn:cc2":"CZ",
    "gn:country_code":"CZ",
    "gn:dem":653,
    "gn:feature_class":"P",
    "gn:feature_code":"PPL",
    "gn:name":"H\u016frky",
    "gn:population":0,
    "gn:timezone":"Europe/Prague",
    "iso:country":"CZ",
    "name:und_x_variant":[
        "Adamsfreiheit"
    ],
    "wof:name":"Hurky",
    "wof:placetype":"locality"
},
  "geometry": {"coordinates":[15.15,49.05],"type":"Point"}
}