{
  "type": "Feature",
  "properties": {
    "gn:admin1_code":"81",
    "gn:admin2_code":"0412",
    "gn:asciiname":"Telcov",
    "gn:country_code":"CZ",
    "gn:dem":723,
    "gn:feature_class":"P",
    "gn:feature_code":"PPL",
    "gn:name":"Telcov",
    "gn:population":0,
    "gn:timezone":"Europe/Prague",
    "iso:country":"CZ",
    "name:und_x_variant":[
        "Teltsch",
        "Telcov"
    ],
    "wof:name":"Telcov",
    "wof:placetype":"locality"
},
  "geometry": {"coordinates":[13.11667,50.33333],"type":"Point"}
}