{
  "type": "Feature",
  "properties": {
    "gn:gn_country":"CZ",
    "gn:gn_fcode":"PPL",
    "gn:gn_pop":859,
    "gn:population":859,
    "iso:country":"CZ",
    "name:azb_x_preferred":[
        "\u0628\u0648\u0647\u0648\u062a\u06cc\u0646"
    ],
    "name:ceb_x_preferred":[
        "Bohut\u00edn"
    ],
    "name:ces_x_preferred":[
        "Bohut\u00edn"
    ],
    "name:deu_x_preferred":[
        "Bohut\u00edn nad Moravou"
    ],
    "name:eng_x_preferred":[
        "Bohut\u00edn"
    ],
    "name:eus_x_preferred":[
        "Bohut\u00edn"
    ],
    "name:fas_x_preferred":[
        "\u0628\u0648\u0647\u0648\u062a\u06cc\u0646"
    ],
    "name:fra_x_preferred":[
        "Bohut\u00edn"
    ],
    "name:hun_x_preferred":[
        "Bohut\u00edn"
    ],
    "name:ita_x_preferred":[
        "Bohut\u00edn"
    ],
    "name:msa_x_preferred":[
        "Bohut\u00edn"
    ],
    "name:nan_x_preferred":[
        "Bohut\u00edn"
    ],
    "name:nld_x_preferred":[
        "Bohut\u00edn"
    ],
    "name:pol_x_preferred":[
        "Bohut\u00edn"
    ],
    "name:por_x_preferred":[
        "Bohut\u00edn"
    ],
    "name:rup_x_preferred":[
        "Bohut\u00edn"
    ],
    "name:slk_x_preferred":[
        "Bohut\u00edn"
    ],
    "name:spa_x_preferred":[
        "Bohut\u00edn"
    ],
    "name:srp_x_preferred":[
        "\u0411\u043e\u0445\u0443\u0442\u0438\u043d"
    ],
    "name:swe_x_preferred":[
        "Bohut\u00edn"
    ],
    "name:vie_x_preferred":[
        "Bohut\u00edn"
    ],
    "qs_pg:aaroncc":"CZ",
    "qs_pg:gn_country":"CZ",
    "qs_pg:gn_fcode":"PPL",
    "qs_pg:gn_pop":859,
    "qs_pg:name":"Bohut\u00edn",
    "qs_pg:name_adm0":"\u010cesk\u00e1 republika",
    "qs_pg:name_adm1":"Olomouck\u00fd kraj",
    "qs_pg:photos_9k":1,
    "qs_pg:photos_9r":1,
    "qs_pg:photos_all":1,
    "qs_pg:photos_sr":0,
    "qs_pg:pop_sr":2,
    "qs_pg:qs_pg_placetype":"locality",
    "qs_pg:qs_pg_placetype_gp":"Town",
    "qs_pg:woe_adm0":23424810,
    "woe:adm0_id":23424810,
    "woe:name_adm0":"\u010cesk\u00e1 republika",
    "woe:name_adm1":"Olomouck\u00fd kraj",
    "woe:placetype":"Town",
    "wof:name":"Bohut\u00edn",
    "wof:placetype":"locality",
    "wof:population":859
},
  "geometry": {"coordinates":[16.88193,49.95351],"type":"Point"}
}