{
  "type": "Feature",
  "properties": {
    "gn:gn_country":"CZ",
    "gn:gn_fcode":"PPL",
    "gn:gn_pop":301,
    "gn:population":301,
    "iso:country":"CZ",
    "name:bul_x_preferred":[
        "\u041e\u0442\u0440\u0430\u0434\u043e\u0432"
    ],
    "name:cze_x_preferred":[
        "Otradov"
    ],
    "name:dut_x_preferred":[
        "Otradov"
    ],
    "name:eng_x_preferred":[
        "Otradov"
    ],
    "name:epo_x_preferred":[
        "Otradov"
    ],
    "name:fre_x_preferred":[
        "Otradov"
    ],
    "name:hun_x_preferred":[
        "Otradov"
    ],
    "name:ita_x_preferred":[
        "Otradov"
    ],
    "name:may_x_preferred":[
        "Otradov"
    ],
    "name:nan_x_preferred":[
        "Otradov"
    ],
    "name:pol_x_preferred":[
        "Otradov"
    ],
    "name:por_x_preferred":[
        "Otradov"
    ],
    "name:rup_x_preferred":[
        "Otradov"
    ],
    "name:slo_x_preferred":[
        "Otradov"
    ],
    "name:srp_x_preferred":[
        "\u041e\u0442\u0440\u0430\u0434\u043e\u0432"
    ],
    "name:swe_x_preferred":[
        "Otradov"
    ],
    "name:vie_x_preferred":[
        "Otradov"
    ],
    "qs_pg:aaroncc":"CZ",
    "qs_pg:gn_country":"CZ",
    "qs_pg:gn_fcode":"PPL",
    "qs_pg:gn_pop":301,
    "qs_pg:name":"Otradov",
    "qs_pg:name_adm0":"\u010cesk\u00e1 republika",
    "qs_pg:name_adm1":"Pardubick\u00fd kraj",
    "qs_pg:photos_9r":0,
    "qs_pg:photos_sr":0,
    "qs_pg:pop_sr":2,
    "qs_pg:qs_pg_placetype":"locality",
    "qs_pg:qs_pg_placetype_gp":"Town",
    "qs_pg:woe_adm0":23424810,
    "woe:adm0_id":23424810,
    "woe:name_adm0":"\u010cesk\u00e1 republika",
    "woe:name_adm1":"Pardubick\u00fd kraj",
    "woe:placetype":"Town",
    "wof:name":"Otradov",
    "wof:placetype":"locality",
    "wof:population":301
},
  "geometry": {"coordinates":[16.0435,49.79334],"type":"Point"}
}