{
  "type": "Feature",
  "properties": {
    "gn:admin1_code":"83.0",
    "gn:admin2_code":"0511",
    "gn:asciiname":"Borek",
    "gn:country_code":"CZ",
    "gn:dem":258,
    "gn:feature_class":"P",
    "gn:feature_code":"PPL",
    "gn:name":"Borek",
    "gn:population":0,
    "gn:timezone":"Europe/Prague",
    "iso:country":"CZ",
    "name:und_x_variant":[
        "Regersdorf",
        "Borek"
    ],
    "wof:name":"Borek",
    "wof:placetype":"locality"
},
  "geometry": {"coordinates":[14.53114,50.61795],"type":"Point"}
}