{
  "type": "Feature",
  "properties": {
    "gn:admin1_code":"89.0",
    "gn:admin2_code":"0422",
    "gn:asciiname":"Cerny Potok",
    "gn:country_code":"CZ",
    "gn:dem":718,
    "gn:feature_class":"P",
    "gn:feature_code":"PPL",
    "gn:name":"\u010cern\u00fd Potok",
    "gn:population":0,
    "gn:timezone":"Europe/Prague",
    "iso:country":"CZ",
    "name:und_x_variant":[
        "Pleil",
        "\u010cern\u00fd Potok"
    ],
    "wof:name":"Cerny Potok",
    "wof:placetype":"locality"
},
  "geometry": {"coordinates":[13.07799,50.49013],"type":"Point"}
}