{
  "type": "Feature",
  "properties": {
    "gn:admin1_code":"89",
    "gn:admin2_code":"0424",
    "gn:asciiname":"Stranky",
    "gn:country_code":"CZ",
    "gn:dem":246,
    "gn:feature_class":"P",
    "gn:feature_code":"PPL",
    "gn:name":"Str\u00e1nky",
    "gn:population":0,
    "gn:timezone":"Europe/Prague",
    "iso:country":"CZ",
    "wof:name":"Stranky",
    "wof:placetype":"locality"
},
  "geometry": {"coordinates":[13.57672,50.28919000000001],"type":"Point"}
}