{
  "type": "Feature",
  "properties": {
    "gn:admin1_code":"80.0",
    "gn:admin2_code":"0614",
    "gn:asciiname":"Kracovice",
    "gn:country_code":"CZ",
    "gn:dem":474,
    "gn:feature_class":"P",
    "gn:feature_code":"PPL",
    "gn:name":"Kracovice",
    "gn:population":0,
    "gn:timezone":"Europe/Prague",
    "iso:country":"CZ",
    "wof:name":"Kracovice",
    "wof:placetype":"locality"
},
  "geometry": {"coordinates":[15.84025,49.1942],"type":"Point"}
}