{
  "type": "Feature",
  "properties": {
    "gn:admin1_code":"88.0",
    "gn:admin2_code":"0205",
    "gn:asciiname":"Silvanka",
    "gn:country_code":"CZ",
    "gn:dem":450,
    "gn:feature_class":"P",
    "gn:feature_code":"PPL",
    "gn:name":"Silv\u00e1nka",
    "gn:population":0,
    "gn:timezone":"Europe/Prague",
    "iso:country":"CZ",
    "wof:name":"Silvanka",
    "wof:placetype":"locality"
},
  "geometry": {"coordinates":[15.0472,49.86431],"type":"Point"}
}