{
  "type": "Feature",
  "properties": {
    "gn:admin1_code":"82.0",
    "gn:admin2_code":"0524",
    "gn:asciiname":"Mokre",
    "gn:country_code":"CZ",
    "gn:dem":260,
    "gn:feature_class":"P",
    "gn:feature_code":"PPL",
    "gn:name":"Mokr\u00e9",
    "gn:population":154,
    "gn:timezone":"Europe/Prague",
    "iso:country":"CZ",
    "wof:name":"Mokre",
    "wof:placetype":"locality",
    "wof:population":154
},
  "geometry": {"coordinates":[16.06642,50.2592],"type":"Point"}
}