{
  "type": "Feature",
  "properties": {
    "gn:admin1_code":"82.0",
    "gn:admin2_code":"0524",
    "gn:asciiname":"Mokre",
    "gn:country_code":"CZ",
    "gn:dem":260,
    "gn:feature_class":"P",
    "gn:feature_code":"PPL",
    "gn:name":"Mokr\u00e9",
    "gn:population":154,
    "gn:timezone":"Europe/Prague",
    "iso:country":"CZ",
    "name:azb_x_preferred":[
        "\u0645\u0648\u06a9\u0631\u0647"
    ],
    "name:ceb_x_preferred":[
        "Mokr\u00e9"
    ],
    "name:ces_x_preferred":[
        "Mokr\u00e9"
    ],
    "name:deu_x_preferred":[
        "Mokr\u00e9"
    ],
    "name:eus_x_preferred":[
        "Mokr\u00e9"
    ],
    "name:fas_x_preferred":[
        "\u0645\u0648\u06a9\u0631\u0647"
    ],
    "name:fra_x_preferred":[
        "Mokr\u00e9"
    ],
    "name:hun_x_preferred":[
        "Mokr\u00e9"
    ],
    "name:ita_x_preferred":[
        "Mokr\u00e9"
    ],
    "name:msa_x_preferred":[
        "Mokr\u00e9"
    ],
    "name:nld_x_preferred":[
        "Mokr\u00e9"
    ],
    "name:pol_x_preferred":[
        "Mokr\u00e9"
    ],
    "name:por_x_preferred":[
        "Mokr\u00e9"
    ],
    "name:slk_x_preferred":[
        "Mokr\u00e9"
    ],
    "name:spa_x_preferred":[
        "Mokr\u00e9"
    ],
    "name:srp_x_preferred":[
        "\u041c\u043e\u043a\u0440\u0435"
    ],
    "name:swe_x_preferred":[
        "Mokr\u00e9"
    ],
    "name:vie_x_preferred":[
        "Mokr\u00e9"
    ],
    "wof:name":"Mokre",
    "wof:placetype":"locality",
    "wof:population":154
},
  "geometry": {"coordinates":[16.06642,50.2592],"type":"Point"}
}