{
  "type": "Feature",
  "properties": {
    "gn:admin1_code":"88.0",
    "gn:admin2_code":"020B",
    "gn:asciiname":"Janov",
    "gn:country_code":"CZ",
    "gn:dem":403,
    "gn:feature_class":"P",
    "gn:feature_code":"PPL",
    "gn:name":"Janov",
    "gn:population":0,
    "gn:timezone":"Europe/Prague",
    "iso:country":"CZ",
    "name:ceb_x_preferred":[
        "Janov"
    ],
    "name:ces_x_preferred":[
        "Janov"
    ],
    "name:deu_x_preferred":[
        "Janov"
    ],
    "name:epo_x_preferred":[
        "Janov"
    ],
    "name:fra_x_preferred":[
        "Janov"
    ],
    "name:hun_x_preferred":[
        "Janov"
    ],
    "name:ita_x_preferred":[
        "Janov"
    ],
    "name:nld_x_preferred":[
        "Janov"
    ],
    "name:pol_x_preferred":[
        "Janov"
    ],
    "name:slk_x_preferred":[
        "Janov"
    ],
    "name:srp_x_preferred":[
        "\u0408\u0430\u043d\u043e\u0432"
    ],
    "name:swe_x_preferred":[
        "Janov"
    ],
    "wof:name":"Janov",
    "wof:placetype":"locality"
},
  "geometry": {"coordinates":[14.45673,49.64502],"type":"Point"}
}