{
  "type": "Feature",
  "properties": {
    "gn:gn_country":"CZ",
    "gn:gn_fcode":"PPL",
    "gn:gn_pop":365,
    "gn:population":365,
    "iso:country":"CZ",
    "name:ces_x_preferred":[
        "Lev\u00ednsk\u00e1 Ole\u0161nice"
    ],
    "name:deu_x_preferred":[
        "Lev\u00ednsk\u00e1 Ole\u0161nice"
    ],
    "name:eng_x_preferred":[
        "Lev\u00ednsk\u00e1 Ole\u0161nice"
    ],
    "name:fas_x_preferred":[
        "\u0644\u0648\u06cc\u0646\u0633\u06a9\u0627 \u0627\u0648\u0644\u0634\u0646\u06cc\u062a\u0633\u0647"
    ],
    "name:fra_x_preferred":[
        "Lev\u00ednsk\u00e1 Ole\u0161nice"
    ],
    "name:hun_x_preferred":[
        "Lev\u00ednsk\u00e1 Ole\u0161nice"
    ],
    "name:ita_x_preferred":[
        "Lev\u00ednsk\u00e1 Ole\u0161nice"
    ],
    "name:msa_x_preferred":[
        "Lev\u00ednsk\u00e1 Ole\u0161nice"
    ],
    "name:nan_x_preferred":[
        "Lev\u00ednsk\u00e1 Ole\u0161nice"
    ],
    "name:nld_x_preferred":[
        "Lev\u00ednsk\u00e1 Ole\u0161nice"
    ],
    "name:pol_x_preferred":[
        "Lev\u00ednsk\u00e1 Ole\u0161nice"
    ],
    "name:por_x_preferred":[
        "Lev\u00ednsk\u00e1 Ole\u0161nice"
    ],
    "name:rup_x_preferred":[
        "Lev\u00ednsk\u00e1 Ole\u0161nice"
    ],
    "name:slk_x_preferred":[
        "Lev\u00ednsk\u00e1 Ole\u0161nice"
    ],
    "name:srp_x_preferred":[
        "\u041b\u0435\u0432\u0438\u043d\u0441\u043a\u0430 \u041e\u043b\u0435\u0448\u045a\u0438\u0446\u0430"
    ],
    "name:swe_x_preferred":[
        "Lev\u00ednsk\u00e1 Ole\u0161nice"
    ],
    "name:vie_x_preferred":[
        "Lev\u00ednsk\u00e1 Ole\u0161nice"
    ],
    "qs_pg:aaroncc":"CZ",
    "qs_pg:gn_country":"CZ",
    "qs_pg:gn_fcode":"PPL",
    "qs_pg:gn_pop":365,
    "qs_pg:name":"Lev\u00ednsk\u00e1 Ole\u0161nice",
    "qs_pg:name_adm0":"\u010cesk\u00e1 republika",
    "qs_pg:name_adm1":"Libereck\u00fd kraj",
    "qs_pg:photos_9k":1,
    "qs_pg:photos_9r":1,
    "qs_pg:photos_all":17,
    "qs_pg:photos_sr":0,
    "qs_pg:pop_sr":2,
    "qs_pg:qs_pg_placetype":"locality",
    "qs_pg:qs_pg_placetype_gp":"Town",
    "qs_pg:woe_adm0":23424810,
    "woe:adm0_id":23424810,
    "woe:name_adm0":"\u010cesk\u00e1 republika",
    "woe:name_adm1":"Libereck\u00fd kraj",
    "woe:placetype":"Town",
    "wof:name":"Lev\u00ednsk\u00e1 Ole\u0161nice",
    "wof:placetype":"locality",
    "wof:population":365
},
  "geometry": {"coordinates":[15.54071,50.52821],"type":"Point"}
}