{
  "type": "Feature",
  "properties": {
    "gn:admin1_code":"79.0",
    "gn:admin2_code":"0314",
    "gn:asciiname":"Hnevanice",
    "gn:country_code":"CZ",
    "gn:dem":562,
    "gn:feature_class":"P",
    "gn:feature_code":"PPL",
    "gn:name":"Hn\u011bvanice",
    "gn:population":0,
    "gn:timezone":"Europe/Prague",
    "iso:country":"CZ",
    "wof:name":"Hnevanice",
    "wof:placetype":"locality"
},
  "geometry": {"coordinates":[14.36667,49.51608],"type":"Point"}
}