{
  "type": "Feature",
  "properties": {
    "gn:admin1_code":"81.0",
    "gn:admin2_code":"0413",
    "gn:asciiname":"Chranisov",
    "gn:country_code":"CZ",
    "gn:dem":433,
    "gn:feature_class":"P",
    "gn:feature_code":"PPL",
    "gn:name":"Chrani\u0161ov",
    "gn:population":0,
    "gn:timezone":"Europe/Prague",
    "iso:country":"CZ",
    "name:und_x_variant":[
        "Granesau",
        "Chrani\u0161ov"
    ],
    "wof:name":"Chranisov",
    "wof:placetype":"locality"
},
  "geometry": {"coordinates":[12.74233,50.22101],"type":"Point"}
}