{
  "type": "Feature",
  "properties": {
    "gn:admin1_code":"88.0",
    "gn:admin2_code":"0201",
    "gn:asciiname":"Nahoruby",
    "gn:country_code":"CZ",
    "gn:dem":381,
    "gn:feature_class":"P",
    "gn:feature_code":"PPL",
    "gn:name":"Nahoruby",
    "gn:population":0,
    "gn:timezone":"Europe/Prague",
    "iso:country":"CZ",
    "wof:name":"Nahoruby",
    "wof:placetype":"locality"
},
  "geometry": {"coordinates":[14.44384,49.74044],"type":"Point"}
}