{
  "type": "Feature",
  "properties": {
    "gn:gn_country":"CZ",
    "gn:gn_fcode":"PPL",
    "gn:gn_pop":639,
    "gn:population":639,
    "iso:country":"CZ",
    "name:ceb_x_preferred":[
        "Chomutice"
    ],
    "name:ces_x_preferred":[
        "Chomutice"
    ],
    "name:eng_x_preferred":[
        "Chomutice"
    ],
    "name:eus_x_preferred":[
        "Chomutice"
    ],
    "name:fas_x_preferred":[
        "\u062e\u0648\u0645\u0648\u062a\u06cc\u062a\u0633\u0647"
    ],
    "name:fra_x_preferred":[
        "Chomutice"
    ],
    "name:hun_x_preferred":[
        "Chomutice"
    ],
    "name:ita_x_preferred":[
        "Chomutice"
    ],
    "name:msa_x_preferred":[
        "Chomutice"
    ],
    "name:nan_x_preferred":[
        "Chomutice"
    ],
    "name:nld_x_preferred":[
        "Chomutice"
    ],
    "name:pol_x_preferred":[
        "Chomutice"
    ],
    "name:por_x_preferred":[
        "Chomutice"
    ],
    "name:slk_x_preferred":[
        "Chomutice"
    ],
    "name:spa_x_preferred":[
        "Chomutice"
    ],
    "name:srp_x_preferred":[
        "\u0425\u043e\u043c\u0443\u0442\u0438\u0446\u0435"
    ],
    "name:swe_x_preferred":[
        "Chomutice"
    ],
    "name:unk_x_variant":[
        "Chomutitz"
    ],
    "name:vie_x_preferred":[
        "Chomutice"
    ],
    "qs_pg:aaroncc":"CZ",
    "qs_pg:gn_country":"CZ",
    "qs_pg:gn_fcode":"PPL",
    "qs_pg:gn_pop":639,
    "qs_pg:name":"Chomutice",
    "qs_pg:name_adm0":"\u010cesk\u00e1 republika",
    "qs_pg:name_adm1":"Kr\u00e1lov\u00e9hradeck\u00fd kraj",
    "qs_pg:photos_9r":0,
    "qs_pg:photos_sr":0,
    "qs_pg:pop_sr":2,
    "qs_pg:qs_pg_placetype":"locality",
    "qs_pg:qs_pg_placetype_gp":"Town",
    "qs_pg:woe_adm0":23424810,
    "woe:adm0_id":23424810,
    "woe:name_adm0":"\u010cesk\u00e1 republika",
    "woe:name_adm1":"Kr\u00e1lov\u00e9hradeck\u00fd kraj",
    "woe:placetype":"Town",
    "wof:name":"Chomutice",
    "wof:placetype":"locality",
    "wof:population":639
},
  "geometry": {"coordinates":[15.49618,50.35927],"type":"Point"}
}