{
  "type": "Feature",
  "properties": {
    "gn:gn_country":"CZ",
    "gn:gn_fcode":"PPL",
    "gn:gn_pop":209,
    "gn:population":209,
    "iso:country":"CZ",
    "name:cze_x_preferred":[
        "P\u0159\u00edse\u010dn\u00e1"
    ],
    "name:dut_x_preferred":[
        "P\u0159\u00edse\u010dn\u00e1"
    ],
    "name:eng_x_preferred":[
        "P\u0159\u00edse\u010dn\u00e1"
    ],
    "name:fre_x_preferred":[
        "P\u0159\u00edse\u010dn\u00e1"
    ],
    "name:ger_x_preferred":[
        "P\u0159\u00edse\u010dn\u00e1"
    ],
    "name:hun_x_preferred":[
        "P\u0159\u00edse\u010dn\u00e1"
    ],
    "name:ita_x_preferred":[
        "P\u0159\u00edse\u010dn\u00e1"
    ],
    "name:may_x_preferred":[
        "P\u0159\u00edse\u010dn\u00e1"
    ],
    "name:nan_x_preferred":[
        "P\u0159\u00edse\u010dn\u00e1"
    ],
    "name:per_x_preferred":[
        "\u067e\u0631\u06cc\u0633\u062a\u0634\u0646\u0627"
    ],
    "name:pol_x_preferred":[
        "P\u0159\u00edse\u010dn\u00e1"
    ],
    "name:por_x_preferred":[
        "P\u0159\u00edse\u010dn\u00e1"
    ],
    "name:rup_x_preferred":[
        "P\u0159\u00edse\u010dn\u00e1"
    ],
    "name:slo_x_preferred":[
        "P\u0159\u00edse\u010dn\u00e1"
    ],
    "name:srp_x_preferred":[
        "\u041f\u0440\u0438\u0441\u0435\u0447\u043d\u0430"
    ],
    "name:swe_x_preferred":[
        "P\u0159\u00edse\u010dn\u00e1"
    ],
    "name:vie_x_preferred":[
        "P\u0159\u00edse\u010dn\u00e1"
    ],
    "qs_pg:aaroncc":"CZ",
    "qs_pg:gn_country":"CZ",
    "qs_pg:gn_fcode":"PPL",
    "qs_pg:gn_pop":209,
    "qs_pg:name":"P\u0159\u00edse\u010dn\u00e1",
    "qs_pg:name_adm0":"\u010cesk\u00e1 republika",
    "qs_pg:name_adm1":"Jiho\u010desk\u00fd kraj",
    "qs_pg:photos_9r":0,
    "qs_pg:photos_sr":0,
    "qs_pg:pop_sr":2,
    "qs_pg:qs_pg_placetype":"locality",
    "qs_pg:qs_pg_placetype_gp":"Town",
    "qs_pg:woe_adm0":23424810,
    "woe:adm0_id":23424810,
    "woe:name_adm0":"\u010cesk\u00e1 republika",
    "woe:name_adm1":"Jiho\u010desk\u00fd kraj",
    "woe:placetype":"Town",
    "wof:name":"P\u0159\u00edse\u010dn\u00e1",
    "wof:placetype":"locality",
    "wof:population":209
},
  "geometry": {"coordinates":[14.34523,48.83309],"type":"Point"}
}