{
  "type": "Feature",
  "properties": {
    "gn:admin1_code":"87",
    "gn:admin2_code":"0327",
    "gn:asciiname":"Zliv",
    "gn:country_code":"CZ",
    "gn:dem":534,
    "gn:feature_class":"P",
    "gn:feature_code":"PPL",
    "gn:name":"Zliv",
    "gn:population":0,
    "gn:timezone":"Europe/Prague",
    "iso:country":"CZ",
    "name:und_x_variant":[
        "Schlief",
        "Zliv"
    ],
    "wof:name":"Zliv",
    "wof:placetype":"locality"
},
  "geometry": {"coordinates":[12.80347,49.82956],"type":"Point"}
}