{
  "type": "Feature",
  "properties": {
    "gn:admin1_code":"87",
    "gn:admin2_code":"0327",
    "gn:asciiname":"Zliv",
    "gn:country_code":"CZ",
    "gn:dem":534,
    "gn:feature_class":"P",
    "gn:feature_code":"PPL",
    "gn:name":"Zliv",
    "gn:population":0,
    "gn:timezone":"Europe/Prague",
    "iso:country":"CZ",
    "name:ceb_x_preferred":[
        "Zliv"
    ],
    "name:ces_x_preferred":[
        "Zliv"
    ],
    "name:deu_x_preferred":[
        "Zliv"
    ],
    "name:eus_x_preferred":[
        "Zliv"
    ],
    "name:fra_x_preferred":[
        "Zliv"
    ],
    "name:hun_x_preferred":[
        "Zliv"
    ],
    "name:ita_x_preferred":[
        "Zliv"
    ],
    "name:msa_x_preferred":[
        "Zliv"
    ],
    "name:nld_x_preferred":[
        "Zliv"
    ],
    "name:pol_x_preferred":[
        "Zliv"
    ],
    "name:por_x_preferred":[
        "Zliv"
    ],
    "name:slk_x_preferred":[
        "Zliv"
    ],
    "name:spa_x_preferred":[
        "Zliv"
    ],
    "name:srp_x_preferred":[
        "\u0417\u043b\u0438\u0432"
    ],
    "name:swe_x_preferred":[
        "Zliv"
    ],
    "name:und_x_variant":[
        "Schlief",
        "Zliv"
    ],
    "name:vie_x_preferred":[
        "Zliv"
    ],
    "name:zho_x_preferred":[
        "\u8332\u5229\u592b"
    ],
    "wof:name":"Zliv",
    "wof:placetype":"locality"
},
  "geometry": {"coordinates":[12.80347,49.82956],"type":"Point"}
}