{
  "type": "Feature",
  "properties": {
    "gn:gn_country":"CZ",
    "gn:gn_fcode":"PPL",
    "gn:gn_pop":934,
    "gn:population":934,
    "iso:country":"CZ",
    "name:ces_x_preferred":[
        "\u010cernuc"
    ],
    "name:eng_x_preferred":[
        "\u010cernuc"
    ],
    "name:fas_x_preferred":[
        "\u062a\u0634\u0631\u0646\u0648\u062a\u0633"
    ],
    "name:fra_x_preferred":[
        "\u010cernuc"
    ],
    "name:hun_x_preferred":[
        "\u010cernuc"
    ],
    "name:ita_x_preferred":[
        "\u010cernuc"
    ],
    "name:msa_x_preferred":[
        "\u010cernuc"
    ],
    "name:nld_x_preferred":[
        "\u010cernuc"
    ],
    "name:pol_x_preferred":[
        "\u010cernuc"
    ],
    "name:por_x_preferred":[
        "\u010cernuc"
    ],
    "name:rus_x_preferred":[
        "\u0427\u0435\u0440\u043d\u0443\u0446"
    ],
    "name:slk_x_preferred":[
        "\u010cernuc"
    ],
    "name:srp_x_preferred":[
        "\u0427\u0435\u0440\u043d\u0443\u0446"
    ],
    "name:swe_x_preferred":[
        "\u010cernuc"
    ],
    "name:unk_x_variant":[
        "Cernutz"
    ],
    "name:vie_x_preferred":[
        "\u010cernuc"
    ],
    "qs_pg:aaroncc":"CZ",
    "qs_pg:gn_country":"CZ",
    "qs_pg:gn_fcode":"PPL",
    "qs_pg:gn_pop":934,
    "qs_pg:name":"\u010cernuc",
    "qs_pg:name_adm0":"\u010cesk\u00e1 republika",
    "qs_pg:name_adm1":"St\u0159edo\u010desk\u00fd kraj",
    "qs_pg:photos_9k":1,
    "qs_pg:photos_9r":1,
    "qs_pg:photos_all":1,
    "qs_pg:photos_sr":0,
    "qs_pg:pop_sr":2,
    "qs_pg:qs_pg_placetype":"locality",
    "qs_pg:qs_pg_placetype_gp":"Town",
    "qs_pg:woe_adm0":23424810,
    "woe:adm0_id":23424810,
    "woe:name_adm0":"\u010cesk\u00e1 republika",
    "woe:name_adm1":"St\u0159edo\u010desk\u00fd kraj",
    "woe:placetype":"Town",
    "wof:name":"\u010cernuc",
    "wof:placetype":"locality",
    "wof:population":934
},
  "geometry": {"coordinates":[14.20249,50.30114],"type":"Point"}
}