{
  "type": "Feature",
  "properties": {
    "gn:admin1_code":"86",
    "gn:admin2_code":"0531",
    "gn:asciiname":"Srbce",
    "gn:country_code":"CZ",
    "gn:dem":339,
    "gn:feature_class":"P",
    "gn:feature_code":"PPL",
    "gn:name":"Srbce",
    "gn:population":0,
    "gn:timezone":"Europe/Prague",
    "iso:country":"CZ",
    "name:azb_x_preferred":[
        "\u0633\u0631\u0628\u062a\u0633\u0647"
    ],
    "name:ces_x_preferred":[
        "Srbce"
    ],
    "name:deu_x_preferred":[
        "Srbce"
    ],
    "name:eus_x_preferred":[
        "Srbce"
    ],
    "name:fas_x_preferred":[
        "\u0633\u0631\u0628\u062a\u0633\u0647"
    ],
    "name:fra_x_preferred":[
        "Srbce"
    ],
    "name:hun_x_preferred":[
        "Srbce"
    ],
    "name:ita_x_preferred":[
        "Srbce"
    ],
    "name:msa_x_preferred":[
        "Srbce"
    ],
    "name:nld_x_preferred":[
        "Srbce"
    ],
    "name:pol_x_preferred":[
        "Srbce"
    ],
    "name:por_x_preferred":[
        "Srbce"
    ],
    "name:slk_x_preferred":[
        "Srbce"
    ],
    "name:srp_x_preferred":[
        "\u0421\u0440\u0431\u0446\u0435"
    ],
    "name:vie_x_preferred":[
        "Srbce"
    ],
    "wof:name":"Srbce",
    "wof:placetype":"locality"
},
  "geometry": {"coordinates":[16.05536,49.91424],"type":"Point"}
}