{
  "type": "Feature",
  "properties": {
    "gn:admin1_code":"86",
    "gn:admin2_code":"0531",
    "gn:asciiname":"Srbce",
    "gn:country_code":"CZ",
    "gn:dem":339,
    "gn:feature_class":"P",
    "gn:feature_code":"PPL",
    "gn:name":"Srbce",
    "gn:population":0,
    "gn:timezone":"Europe/Prague",
    "iso:country":"CZ",
    "wof:name":"Srbce",
    "wof:placetype":"locality"
},
  "geometry": {"coordinates":[16.05536,49.91424],"type":"Point"}
}