{
  "type": "Feature",
  "properties": {
    "gn:gn_country":"CZ",
    "gn:gn_fcode":"PPL",
    "gn:gn_pop":794,
    "gn:population":794,
    "iso:country":"CZ",
    "name:cze_x_preferred":[
        "Nezdenice"
    ],
    "name:dut_x_preferred":[
        "Nezdenice"
    ],
    "name:eng_x_preferred":[
        "Nezdenice"
    ],
    "name:fre_x_preferred":[
        "Nezdenice"
    ],
    "name:hun_x_preferred":[
        "Nezdenice"
    ],
    "name:ita_x_preferred":[
        "Nezdenice"
    ],
    "name:may_x_preferred":[
        "Nezdenice"
    ],
    "name:per_x_preferred":[
        "\u0646\u0632\u062f\u0646\u06cc\u062a\u0633\u0647"
    ],
    "name:pol_x_preferred":[
        "Nezdenice"
    ],
    "name:por_x_preferred":[
        "Nezdenice"
    ],
    "name:slo_x_preferred":[
        "Nezdenice"
    ],
    "name:srp_x_preferred":[
        "\u041d\u0435\u0437\u0434\u0435\u045a\u0438\u0446\u0435"
    ],
    "name:swe_x_preferred":[
        "Nezdenice"
    ],
    "name:vie_x_preferred":[
        "Nezdenice"
    ],
    "qs_pg:aaroncc":"CZ",
    "qs_pg:gn_country":"CZ",
    "qs_pg:gn_fcode":"PPL",
    "qs_pg:gn_pop":794,
    "qs_pg:name":"Nezdenice",
    "qs_pg:name_adm0":"\u010cesk\u00e1 republika",
    "qs_pg:name_adm1":"Zl\u00ednsk\u00fd kraj",
    "qs_pg:photos_9k":1,
    "qs_pg:photos_9r":1,
    "qs_pg:photos_all":2,
    "qs_pg:photos_sr":0,
    "qs_pg:pop_sr":2,
    "qs_pg:qs_pg_placetype":"locality",
    "qs_pg:qs_pg_placetype_gp":"Town",
    "qs_pg:woe_adm0":23424810,
    "woe:adm0_id":23424810,
    "woe:name_adm0":"\u010cesk\u00e1 republika",
    "woe:name_adm1":"Zl\u00ednsk\u00fd kraj",
    "woe:placetype":"Town",
    "wof:name":"Nezdenice",
    "wof:placetype":"locality",
    "wof:population":794
},
  "geometry": {"coordinates":[17.7522,49.01668],"type":"Point"}
}