{
  "type": "Feature",
  "properties": {
    "gn:admin1_code":"88",
    "gn:admin2_code":"020C",
    "gn:asciiname":"Tlestky",
    "gn:country_code":"CZ",
    "gn:dem":528,
    "gn:feature_class":"P",
    "gn:feature_code":"PPL",
    "gn:name":"Tlestky",
    "gn:population":0,
    "gn:timezone":"Europe/Prague",
    "iso:country":"CZ",
    "wof:name":"Tlestky",
    "wof:placetype":"locality"
},
  "geometry": {"coordinates":[13.46493,50.07487],"type":"Point"}
}