{
  "type": "Feature",
  "properties": {
    "gn:admin1_code":"80",
    "gn:admin2_code":"0611",
    "gn:asciiname":"Spytice",
    "gn:country_code":"CZ",
    "gn:dem":314,
    "gn:feature_class":"P",
    "gn:feature_code":"PPL",
    "gn:name":"Spytice",
    "gn:population":0,
    "gn:timezone":"Europe/Prague",
    "iso:country":"CZ",
    "wof:name":"Spytice",
    "wof:placetype":"locality"
},
  "geometry": {"coordinates":[15.52306,49.83728],"type":"Point"}
}