{
  "type": "Feature",
  "properties": {
    "gn:gn_country":"CZ",
    "gn:gn_fcode":"PPL",
    "gn:gn_pop":220,
    "gn:population":220,
    "iso:country":"CZ",
    "name:azb_x_preferred":[
        "\u0648\u06cc\u0644\u0648\u067e\u0648\u0644\u06cc"
    ],
    "name:ceb_x_preferred":[
        "V\u011blopol\u00ed"
    ],
    "name:ces_x_preferred":[
        "V\u011blopol\u00ed"
    ],
    "name:deu_x_preferred":[
        "V\u011blopol\u00ed"
    ],
    "name:eng_x_preferred":[
        "V\u011blopol\u00ed"
    ],
    "name:eus_x_preferred":[
        "V\u011blopol\u00ed"
    ],
    "name:fas_x_preferred":[
        "\u0648\u06cc\u0644\u0648\u067e\u0648\u0644\u06cc"
    ],
    "name:fra_x_preferred":[
        "V\u011blopol\u00ed"
    ],
    "name:hun_x_preferred":[
        "V\u011blopol\u00ed"
    ],
    "name:ita_x_preferred":[
        "V\u011blopol\u00ed"
    ],
    "name:msa_x_preferred":[
        "V\u011blopol\u00ed"
    ],
    "name:nan_x_preferred":[
        "V\u011blopol\u00ed"
    ],
    "name:nld_x_preferred":[
        "V\u011blopol\u00ed"
    ],
    "name:pol_x_preferred":[
        "Wielopole"
    ],
    "name:por_x_preferred":[
        "V\u011blopol\u00ed"
    ],
    "name:rup_x_preferred":[
        "V\u011blopol\u00ed"
    ],
    "name:slk_x_preferred":[
        "V\u011blopol\u00ed"
    ],
    "name:spa_x_preferred":[
        "V\u011blopol\u00ed"
    ],
    "name:srp_x_preferred":[
        "\u0412\u0458\u0435\u043b\u043e\u043f\u043e\u043b\u0438"
    ],
    "name:swe_x_preferred":[
        "V\u011blopol\u00ed"
    ],
    "name:vie_x_preferred":[
        "V\u011blopol\u00ed"
    ],
    "qs_pg:aaroncc":"CZ",
    "qs_pg:gn_country":"CZ",
    "qs_pg:gn_fcode":"PPL",
    "qs_pg:gn_pop":220,
    "qs_pg:name":"V\u011blopol\u00ed",
    "qs_pg:name_adm0":"\u010cesk\u00e1 republika",
    "qs_pg:name_adm1":"Moravskoslezsk\u00fd kraj",
    "qs_pg:photos_9r":0,
    "qs_pg:photos_sr":0,
    "qs_pg:pop_sr":2,
    "qs_pg:qs_pg_placetype":"locality",
    "qs_pg:qs_pg_placetype_gp":"Town",
    "qs_pg:woe_adm0":23424810,
    "woe:adm0_id":23424810,
    "woe:name_adm0":"\u010cesk\u00e1 republika",
    "woe:name_adm1":"Moravskoslezsk\u00fd kraj",
    "woe:placetype":"Town",
    "wof:name":"V\u011blopol\u00ed",
    "wof:placetype":"locality",
    "wof:population":220
},
  "geometry": {"coordinates":[18.5709,49.70043],"type":"Point"}
}