{
  "type": "Feature",
  "properties": {
    "gn:admin1_code":"88",
    "gn:asciiname":"Zhor",
    "gn:country_code":"CZ",
    "gn:dem":605,
    "gn:feature_class":"P",
    "gn:feature_code":"PPL",
    "gn:name":"Zho\u0159",
    "gn:population":0,
    "gn:timezone":"Europe/Prague",
    "iso:country":"CZ",
    "wof:name":"Zhor",
    "wof:placetype":"locality"
},
  "geometry": {"coordinates":[14.98956,49.61689000000001],"type":"Point"}
}