{
  "type": "Feature",
  "properties": {
    "gn:admin1_code":"87",
    "gn:admin2_code":"0322",
    "gn:asciiname":"Spaleniste",
    "gn:country_code":"CZ",
    "gn:dem":962,
    "gn:feature_class":"P",
    "gn:feature_code":"PPL",
    "gn:name":"Sp\u00e1leni\u0161t\u011b",
    "gn:population":0,
    "gn:timezone":"Europe/Prague",
    "iso:country":"CZ",
    "name:und_x_variant":[
        "Brandstaff",
        "Sp\u00e1leni\u0161t\u011b"
    ],
    "wof:name":"Spaleniste",
    "wof:placetype":"locality"
},
  "geometry": {"coordinates":[13.35246,49.20868],"type":"Point"}
}