{
  "type": "Feature",
  "properties": {
    "gn:admin1_code":"83.0",
    "gn:admin2_code":"0513",
    "gn:asciiname":"Markvartice",
    "gn:country_code":"CZ",
    "gn:dem":310,
    "gn:feature_class":"P",
    "gn:feature_code":"PPL",
    "gn:name":"Markvartice",
    "gn:population":0,
    "gn:timezone":"Europe/Prague",
    "iso:country":"CZ",
    "name:und_x_variant":[
        "Markersdorf",
        "Markvartice"
    ],
    "wof:name":"Markvartice",
    "wof:placetype":"locality"
},
  "geometry": {"coordinates":[14.7724,50.76813],"type":"Point"}
}