{
  "type": "Feature",
  "properties": {
    "gn:admin1_code":"88.0",
    "gn:admin2_code":"0207",
    "gn:asciiname":"Bozi Voda",
    "gn:country_code":"CZ",
    "gn:dem":298,
    "gn:feature_class":"P",
    "gn:feature_code":"PPL",
    "gn:name":"Bo\u017e\u00ed Voda",
    "gn:population":0,
    "gn:timezone":"Europe/Prague",
    "iso:country":"CZ",
    "wof:name":"Bozi Voda",
    "wof:placetype":"locality"
},
  "geometry": {"coordinates":[14.94965,50.39399],"type":"Point"}
}