{
  "type": "Feature",
  "properties": {
    "gn:gn_country":"CZ",
    "gn:gn_fcode":"PPL",
    "gn:gn_pop":247,
    "gn:population":247,
    "iso:country":"CZ",
    "name:cze_x_preferred":[
        "Pec"
    ],
    "name:dut_x_preferred":[
        "Pec"
    ],
    "name:eng_x_preferred":[
        "Pec"
    ],
    "name:epo_x_preferred":[
        "Pec"
    ],
    "name:fre_x_preferred":[
        "Pec"
    ],
    "name:ger_x_preferred":[
        "Pec pod \u010cerchovem"
    ],
    "name:hun_x_preferred":[
        "Pec"
    ],
    "name:ita_x_preferred":[
        "Pec"
    ],
    "name:may_x_preferred":[
        "Pec"
    ],
    "name:per_x_preferred":[
        "\u067e\u062a\u0633"
    ],
    "name:pol_x_preferred":[
        "Pec"
    ],
    "name:por_x_preferred":[
        "Pec"
    ],
    "name:rup_x_preferred":[
        "Pec"
    ],
    "name:slo_x_preferred":[
        "Pec"
    ],
    "name:srp_x_preferred":[
        "\u041f\u0435\u0446"
    ],
    "name:swe_x_preferred":[
        "Pec"
    ],
    "name:vie_x_preferred":[
        "Pec"
    ],
    "qs_pg:aaroncc":"CZ",
    "qs_pg:gn_country":"CZ",
    "qs_pg:gn_fcode":"PPL",
    "qs_pg:gn_pop":247,
    "qs_pg:name":"Pec",
    "qs_pg:name_adm0":"\u010cesk\u00e1 republika",
    "qs_pg:name_adm1":"Plze\u0148sk\u00fd kraj",
    "qs_pg:photos_9r":0,
    "qs_pg:photos_sr":0,
    "qs_pg:pop_sr":2,
    "qs_pg:qs_pg_placetype":"locality",
    "qs_pg:qs_pg_placetype_gp":"Town",
    "qs_pg:woe_adm0":23424810,
    "woe:adm0_id":23424810,
    "woe:name_adm0":"\u010cesk\u00e1 republika",
    "woe:name_adm1":"Plze\u0148sk\u00fd kraj",
    "woe:placetype":"Town",
    "wof:name":"Pec",
    "wof:placetype":"locality",
    "wof:population":247
},
  "geometry": {"coordinates":[12.83118,49.39857],"type":"Point"}
}