{
  "type": "Feature",
  "properties": {
    "gn:admin1_code":"88.0",
    "gn:admin2_code":"0201",
    "gn:asciiname":"Bozejny",
    "gn:country_code":"CZ",
    "gn:dem":521,
    "gn:feature_class":"P",
    "gn:feature_code":"PPL",
    "gn:name":"Bozejny",
    "gn:population":0,
    "gn:timezone":"Europe/Prague",
    "iso:country":"CZ",
    "wof:name":"Bozejny",
    "wof:placetype":"locality"
},
  "geometry": {"coordinates":[14.88355,49.56851],"type":"Point"}
}