{
  "type": "Feature",
  "properties": {
    "gn:admin1_code":"88.0",
    "gn:admin2_code":"020B",
    "gn:asciiname":"Horni Laz",
    "gn:country_code":"CZ",
    "gn:dem":594,
    "gn:feature_class":"P",
    "gn:feature_code":"PPL",
    "gn:name":"Horn\u00ed L\u00e1z",
    "gn:population":0,
    "gn:timezone":"Europe/Prague",
    "iso:country":"CZ",
    "wof:name":"Horni Laz",
    "wof:placetype":"locality"
},
  "geometry": {"coordinates":[13.91667,49.65],"type":"Point"}
}