{
  "type": "Feature",
  "properties": {
    "gn:gn_country":"CZ",
    "gn:gn_fcode":"PPL",
    "gn:gn_pop":707,
    "gn:population":707,
    "iso:country":"CZ",
    "name:cze_x_preferred":[
        "Kyselka"
    ],
    "name:dut_x_preferred":[
        "Kyselka"
    ],
    "name:eng_x_preferred":[
        "Kyselka"
    ],
    "name:epo_x_preferred":[
        "Kyselka"
    ],
    "name:fre_x_preferred":[
        "Kyselka"
    ],
    "name:ger_x_preferred":[
        "Kyselka"
    ],
    "name:hun_x_preferred":[
        "Kyselka"
    ],
    "name:ita_x_preferred":[
        "Kyselka"
    ],
    "name:may_x_preferred":[
        "Kyselka"
    ],
    "name:per_x_preferred":[
        "\u06a9\u06cc\u0633\u0644\u06a9\u0627"
    ],
    "name:pol_x_preferred":[
        "Kyselka"
    ],
    "name:por_x_preferred":[
        "Kyselka"
    ],
    "name:rup_x_preferred":[
        "Kyselka"
    ],
    "name:slo_x_preferred":[
        "Kyselka"
    ],
    "name:srp_x_preferred":[
        "\u041a\u0438\u0441\u0435\u043b\u043a\u0430"
    ],
    "name:swe_x_preferred":[
        "Kyselka"
    ],
    "name:unk_x_variant":[
        "S\u00e4uerlingh\u00e4usel"
    ],
    "name:vie_x_preferred":[
        "Kyselka"
    ],
    "qs_pg:aaroncc":"CZ",
    "qs_pg:gn_country":"CZ",
    "qs_pg:gn_fcode":"PPL",
    "qs_pg:gn_pop":707,
    "qs_pg:name":"Kyselka",
    "qs_pg:name_adm0":"\u010cesk\u00e1 republika",
    "qs_pg:name_adm1":"Karlovarsk\u00fd kraj",
    "qs_pg:photos_9k":1,
    "qs_pg:photos_9r":1,
    "qs_pg:photos_all":5,
    "qs_pg:photos_sr":0,
    "qs_pg:pop_sr":2,
    "qs_pg:qs_pg_placetype":"locality",
    "qs_pg:qs_pg_placetype_gp":"Town",
    "qs_pg:woe_adm0":23424810,
    "woe:adm0_id":23424810,
    "woe:name_adm0":"\u010cesk\u00e1 republika",
    "woe:name_adm1":"Karlovarsk\u00fd kraj",
    "woe:placetype":"Town",
    "wof:name":"Kyselka",
    "wof:placetype":"locality",
    "wof:population":707
},
  "geometry": {"coordinates":[12.78639,50.06799],"type":"Point"}
}