{
  "type": "Feature",
  "properties": {
    "gn:admin1_code":"79.0",
    "gn:admin2_code":"0313",
    "gn:asciiname":"Kruplov",
    "gn:country_code":"CZ",
    "gn:dem":482,
    "gn:feature_class":"P",
    "gn:feature_code":"PPL",
    "gn:name":"Kruplov",
    "gn:population":0,
    "gn:timezone":"Europe/Prague",
    "iso:country":"CZ",
    "wof:name":"Kruplov",
    "wof:placetype":"locality"
},
  "geometry": {"coordinates":[15.06556,49.18208],"type":"Point"}
}