{
  "type": "Feature",
  "properties": {
    "gn:admin1_code":"88.0",
    "gn:admin2_code":"020B",
    "gn:asciiname":"Dolni Trti",
    "gn:country_code":"CZ",
    "gn:dem":356,
    "gn:feature_class":"P",
    "gn:feature_code":"PPL",
    "gn:name":"Doln\u00ed T\u0159t\u00ed",
    "gn:population":0,
    "gn:timezone":"Europe/Prague",
    "iso:country":"CZ",
    "wof:name":"Dolni Trti",
    "wof:placetype":"locality"
},
  "geometry": {"coordinates":[14.22489,49.65518],"type":"Point"}
}