{
  "type": "Feature",
  "properties": {
    "gn:admin1_code":"79.0",
    "gn:admin2_code":"0317",
    "gn:asciiname":"Radostovice",
    "gn:country_code":"CZ",
    "gn:dem":638,
    "gn:feature_class":"P",
    "gn:feature_code":"PPL",
    "gn:name":"Radostovice",
    "gn:population":0,
    "gn:timezone":"Europe/Prague",
    "iso:country":"CZ",
    "wof:name":"Radostovice",
    "wof:placetype":"locality"
},
  "geometry": {"coordinates":[14.86828,49.51412],"type":"Point"}
}