{
  "type": "Feature",
  "properties": {
    "gn:admin1_code":"79.0",
    "gn:admin2_code":"0312",
    "gn:asciiname":"Dobrkovice",
    "gn:country_code":"CZ",
    "gn:dem":509,
    "gn:feature_class":"P",
    "gn:feature_code":"PPL",
    "gn:name":"Dobrkovice",
    "gn:population":0,
    "gn:timezone":"Europe/Prague",
    "iso:country":"CZ",
    "name:azb_x_preferred":[
        "\u062f\u0648\u0628\u0631\u06a9\u0648\u0648\u06cc\u062a\u0633\u0647"
    ],
    "name:ceb_x_preferred":[
        "Dobrkovice"
    ],
    "name:ces_x_preferred":[
        "Dobrkovice"
    ],
    "name:deu_x_preferred":[
        "Dobrkovice"
    ],
    "name:eus_x_preferred":[
        "Dobrkovice"
    ],
    "name:fas_x_preferred":[
        "\u062f\u0648\u0628\u0631\u06a9\u0648\u0648\u06cc\u062a\u0633\u0647"
    ],
    "name:fra_x_preferred":[
        "Dobrkovice"
    ],
    "name:hun_x_preferred":[
        "Dobrkovice"
    ],
    "name:ita_x_preferred":[
        "Dobrkovice"
    ],
    "name:msa_x_preferred":[
        "Dobrkovice"
    ],
    "name:nld_x_preferred":[
        "Dobrkovice"
    ],
    "name:pol_x_preferred":[
        "Dobrkovice"
    ],
    "name:por_x_preferred":[
        "Dobrkovice"
    ],
    "name:slk_x_preferred":[
        "Dobrkovice"
    ],
    "name:spa_x_preferred":[
        "Dobrkovice"
    ],
    "name:srp_x_preferred":[
        "\u0414\u043e\u0431\u0440\u043a\u043e\u0432\u0438\u0446\u0435"
    ],
    "name:swe_x_preferred":[
        "Dobrkovice"
    ],
    "name:und_x_variant":[
        "Turkowitz",
        "Dobrkovice"
    ],
    "name:vie_x_preferred":[
        "Dobrkovice"
    ],
    "wof:name":"Dobrkovice",
    "wof:placetype":"locality"
},
  "geometry": {"coordinates":[14.28333,48.81667],"type":"Point"}
}