{
  "type": "Feature",
  "properties": {
    "gn:gn_country":"CZ",
    "gn:gn_fcode":"PPL",
    "gn:gn_pop":587,
    "gn:population":587,
    "iso:country":"CZ",
    "name:ces_x_preferred":[
        "V\u0161echlapy"
    ],
    "name:deu_x_preferred":[
        "V\u0161echlapy"
    ],
    "name:fra_x_preferred":[
        "V\u0161echlapy"
    ],
    "name:ita_x_preferred":[
        "V\u0161echlapy"
    ],
    "name:nld_x_preferred":[
        "V\u0161echlapy"
    ],
    "name:oci_x_preferred":[
        "V\u0161echlapy"
    ],
    "name:pol_x_preferred":[
        "V\u0161echlapy"
    ],
    "name:slk_x_preferred":[
        "V\u0161echlapy"
    ],
    "name:srp_x_preferred":[
        "\u0412\u0448\u0435\u0445\u043b\u0430\u043f\u0438"
    ],
    "qs_pg:aaroncc":"CZ",
    "qs_pg:gn_country":"CZ",
    "qs_pg:gn_fcode":"PPL",
    "qs_pg:gn_pop":587,
    "qs_pg:name":"V\u0161echlapy",
    "qs_pg:name_adm0":"\u010cesk\u00e1 republika",
    "qs_pg:name_adm1":"St\u0159edo\u010desk\u00fd kraj",
    "qs_pg:photos_9r":0,
    "qs_pg:photos_sr":0,
    "qs_pg:pop_sr":2,
    "qs_pg:qs_pg_placetype":"locality",
    "qs_pg:qs_pg_placetype_gp":"Town",
    "qs_pg:woe_adm0":23424810,
    "woe:adm0_id":23424810,
    "woe:name_adm0":"\u010cesk\u00e1 republika",
    "woe:name_adm1":"St\u0159edo\u010desk\u00fd kraj",
    "woe:placetype":"Town",
    "wof:name":"V\u0161echlapy",
    "wof:placetype":"locality",
    "wof:population":587
},
  "geometry": {"coordinates":[15.0284,50.22108],"type":"Point"}
}