{
  "type": "Feature",
  "properties": {
    "gn:admin1_code":"79.0",
    "gn:admin2_code":"0312",
    "gn:asciiname":"Hodonice",
    "gn:country_code":"CZ",
    "gn:dem":661,
    "gn:feature_class":"P",
    "gn:feature_code":"PPL",
    "gn:name":"Hodonice",
    "gn:population":0,
    "gn:timezone":"Europe/Prague",
    "iso:country":"CZ",
    "name:ceb_x_preferred":[
        "Hodonice"
    ],
    "name:ces_x_preferred":[
        "Hodonice"
    ],
    "name:deu_x_preferred":[
        "Hodonice"
    ],
    "name:fra_x_preferred":[
        "Hodonice"
    ],
    "name:ita_x_preferred":[
        "Hodonice"
    ],
    "name:nld_x_preferred":[
        "Hodonice"
    ],
    "name:pol_x_preferred":[
        "Hodonice"
    ],
    "name:slk_x_preferred":[
        "Hodonice"
    ],
    "name:srp_x_preferred":[
        "\u0425\u043e\u0434\u043e\u045a\u0438\u0446\u0435"
    ],
    "name:swe_x_preferred":[
        "Hodonice"
    ],
    "name:und_x_variant":[
        "Hodenitz"
    ],
    "wof:name":"Hodonice",
    "wof:placetype":"locality"
},
  "geometry": {"coordinates":[14.54904,48.71667],"type":"Point"}
}