{
  "type": "Feature",
  "properties": {
    "gn:admin1_code":"79",
    "gn:admin2_code":"0311",
    "gn:asciiname":"Veselka",
    "gn:country_code":"CZ",
    "gn:dem":473,
    "gn:feature_class":"P",
    "gn:feature_code":"PPL",
    "gn:name":"Veselka",
    "gn:population":0,
    "gn:timezone":"Europe/Prague",
    "iso:country":"CZ",
    "wof:name":"Veselka",
    "wof:placetype":"locality"
},
  "geometry": {"coordinates":[14.58327,48.88053],"type":"Point"}
}