{
  "type": "Feature",
  "properties": {
    "gn:admin1_code":"79.0",
    "gn:admin2_code":"0315",
    "gn:asciiname":"Jodlovy Chalupy",
    "gn:country_code":"CZ",
    "gn:dem":897,
    "gn:feature_class":"P",
    "gn:feature_code":"PPL",
    "gn:name":"Jodlovy Chalupy",
    "gn:population":0,
    "gn:timezone":"Europe/Prague",
    "iso:country":"CZ",
    "name:und_x_variant":[
        "Jodh\u00e4user",
        "Jodlovy Chalupy"
    ],
    "wof:name":"Jodlovy Chalupy",
    "wof:placetype":"locality"
},
  "geometry": {"coordinates":[13.95,48.86667],"type":"Point"}
}