{
  "type": "Feature",
  "properties": {
    "gn:admin1_code":"78.0",
    "gn:admin2_code":"0623",
    "gn:asciiname":"Karlov",
    "gn:country_code":"CZ",
    "gn:dem":294,
    "gn:feature_class":"P",
    "gn:feature_code":"PPL",
    "gn:name":"Karlov",
    "gn:population":0,
    "gn:timezone":"Europe/Prague",
    "iso:country":"CZ",
    "wof:name":"Karlov",
    "wof:placetype":"locality"
},
  "geometry": {"coordinates":[16.45,49.08333],"type":"Point"}
}