{
  "type": "Feature",
  "properties": {
    "gn:gn_country":"CZ",
    "gn:gn_fcode":"PPL",
    "gn:gn_pop":1365,
    "gn:population":1365,
    "iso:country":"CZ",
    "name:ces_x_preferred":[
        "Opa\u0159any"
    ],
    "name:deu_x_preferred":[
        "Opa\u0159any"
    ],
    "name:eng_x_preferred":[
        "Opa\u0159any"
    ],
    "name:epo_x_preferred":[
        "Opa\u0159any"
    ],
    "name:fas_x_preferred":[
        "\u0627\u0648\u067e\u0627\u0631\u0627\u0646\u06cc"
    ],
    "name:fra_x_preferred":[
        "Opa\u0159any"
    ],
    "name:hun_x_preferred":[
        "Opa\u0159any"
    ],
    "name:ita_x_preferred":[
        "Opa\u0159any"
    ],
    "name:msa_x_preferred":[
        "Opa\u0159any"
    ],
    "name:nld_x_preferred":[
        "Opa\u0159any"
    ],
    "name:pol_x_preferred":[
        "Opa\u0159any"
    ],
    "name:por_x_preferred":[
        "Opa\u0159any"
    ],
    "name:slk_x_preferred":[
        "Opa\u0159any"
    ],
    "name:srp_x_preferred":[
        "\u041e\u043f\u0430\u0440\u0436\u0430\u043d\u0438"
    ],
    "name:swe_x_preferred":[
        "Opa\u0159any"
    ],
    "name:unk_x_variant":[
        "Wopo\u0159an"
    ],
    "name:vie_x_preferred":[
        "Opa\u0159any"
    ],
    "qs_pg:aaroncc":"CZ",
    "qs_pg:gn_country":"CZ",
    "qs_pg:gn_fcode":"PPL",
    "qs_pg:gn_pop":1365,
    "qs_pg:name":"Opa\u0159any",
    "qs_pg:name_adm0":"\u010cesk\u00e1 republika",
    "qs_pg:name_adm1":"Jiho\u010desk\u00fd kraj",
    "qs_pg:photos_9k":1,
    "qs_pg:photos_9r":1,
    "qs_pg:photos_all":4,
    "qs_pg:photos_sr":0,
    "qs_pg:pop_sr":3,
    "qs_pg:qs_pg_placetype":"locality",
    "qs_pg:qs_pg_placetype_gp":"Town",
    "qs_pg:woe_adm0":23424810,
    "woe:adm0_id":23424810,
    "woe:name_adm0":"\u010cesk\u00e1 republika",
    "woe:name_adm1":"Jiho\u010desk\u00fd kraj",
    "woe:placetype":"Town",
    "wof:name":"Opa\u0159any",
    "wof:placetype":"locality",
    "wof:population":1365
},
  "geometry": {"coordinates":[14.48137,49.39678],"type":"Point"}
}