{
  "type": "Feature",
  "properties": {
    "gn:admin1_code":"52.0",
    "gn:asciiname":"Lipany",
    "gn:cc2":"CZ",
    "gn:country_code":"CZ",
    "gn:dem":205,
    "gn:feature_class":"P",
    "gn:feature_code":"PPL",
    "gn:name":"Lipany",
    "gn:population":0,
    "gn:timezone":"Europe/Prague",
    "iso:country":"CZ",
    "name:ara_x_preferred":[
        "\u0644\u064a\u0628\u0627\u0646\u064a"
    ],
    "name:cat_x_preferred":[
        "Lipany"
    ],
    "name:ceb_x_preferred":[
        "Lipany"
    ],
    "name:ces_x_preferred":[
        "Lipany"
    ],
    "name:deu_x_preferred":[
        "Lipany"
    ],
    "name:epo_x_preferred":[
        "Lipany"
    ],
    "name:eus_x_preferred":[
        "Lipany"
    ],
    "name:fas_x_preferred":[
        "\u0644\u06cc\u067e\u0627\u0646\u06cc"
    ],
    "name:fra_x_preferred":[
        "Lipany"
    ],
    "name:hrv_x_preferred":[
        "Lipany"
    ],
    "name:hun_x_preferred":[
        "H\u00e9th\u00e1rs"
    ],
    "name:ita_x_preferred":[
        "Lipany"
    ],
    "name:lav_x_preferred":[
        "Lipani"
    ],
    "name:lit_x_preferred":[
        "Lipanai"
    ],
    "name:msa_x_preferred":[
        "Lipany"
    ],
    "name:nld_x_preferred":[
        "Lipany"
    ],
    "name:pol_x_preferred":[
        "Lipany"
    ],
    "name:ron_x_preferred":[
        "Lipany"
    ],
    "name:rus_x_preferred":[
        "\u041b\u0438\u043f\u0430\u043d\u044b"
    ],
    "name:slk_x_preferred":[
        "Lipany"
    ],
    "name:spa_x_preferred":[
        "Lipany"
    ],
    "name:srp_x_preferred":[
        "\u041b\u0438\u043f\u0430\u043d\u0438"
    ],
    "name:tur_x_preferred":[
        "Lipany"
    ],
    "name:ukr_x_preferred":[
        "\u041b\u0438\u043f\u0430\u043d\u0438"
    ],
    "name:und_x_variant":[
        "Lipan"
    ],
    "name:urd_x_preferred":[
        "\u0644\u06cc\u067e\u0627\u0646\u06cc"
    ],
    "name:war_x_preferred":[
        "Lipany"
    ],
    "name:zho_x_preferred":[
        "\u5229\u5e15\u5c3c"
    ],
    "wof:name":"Lipany",
    "wof:placetype":"locality"
},
  "geometry": {"coordinates":[14.34008,49.95387],"type":"Point"}
}