{
  "type": "Feature",
  "properties": {
    "gn:admin1_code":"80.0",
    "gn:admin2_code":"0615",
    "gn:asciiname":"Hrda Ves",
    "gn:country_code":"CZ",
    "gn:dem":401,
    "gn:feature_class":"P",
    "gn:feature_code":"PPL",
    "gn:name":"Hrd\u00e1 Ves",
    "gn:population":0,
    "gn:timezone":"Europe/Prague",
    "iso:country":"CZ",
    "wof:name":"Hrda Ves",
    "wof:placetype":"locality"
},
  "geometry": {"coordinates":[16.31071,49.55464],"type":"Point"}
}