{
  "type": "Feature",
  "properties": {
    "gn:admin1_code":"83.0",
    "gn:admin2_code":"0514",
    "gn:asciiname":"Kotelsko",
    "gn:country_code":"CZ",
    "gn:dem":352,
    "gn:feature_class":"P",
    "gn:feature_code":"PPL",
    "gn:name":"Kotelsko",
    "gn:population":0,
    "gn:timezone":"Europe/Prague",
    "iso:country":"CZ",
    "wof:name":"Kotelsko",
    "wof:placetype":"locality"
},
  "geometry": {"coordinates":[15.29382,50.55193],"type":"Point"}
}