{
  "type": "Feature",
  "properties": {
    "gn:admin1_code":"78.0",
    "gn:admin2_code":"0627",
    "gn:asciiname":"Mesovice",
    "gn:country_code":"CZ",
    "gn:dem":451,
    "gn:feature_class":"P",
    "gn:feature_code":"PPL",
    "gn:name":"Me\u0161ovice",
    "gn:population":0,
    "gn:timezone":"Europe/Prague",
    "iso:country":"CZ",
    "name:und_x_variant":[
        "Nespitz",
        "Me\u0161ovice"
    ],
    "wof:name":"Mesovice",
    "wof:placetype":"locality"
},
  "geometry": {"coordinates":[15.75,48.91667],"type":"Point"}
}