{
  "type": "Feature",
  "properties": {
    "gn:admin1_code":"89.0",
    "gn:admin2_code":"0423",
    "gn:asciiname":"Hrusovany",
    "gn:country_code":"CZ",
    "gn:dem":198,
    "gn:feature_class":"P",
    "gn:feature_code":"PPL",
    "gn:name":"Hru\u0161ovany",
    "gn:population":0,
    "gn:timezone":"Europe/Prague",
    "iso:country":"CZ",
    "wof:name":"Hrusovany",
    "wof:placetype":"locality"
},
  "geometry": {"coordinates":[14.27811,50.52052],"type":"Point"}
}