{
  "type": "Feature",
  "properties": {
    "gn:gn_country":"CZ",
    "gn:gn_fcode":"PPL",
    "gn:gn_pop":561,
    "gn:population":561,
    "iso:country":"CZ",
    "name:ceb_x_preferred":[
        "Struha\u0159ov"
    ],
    "name:ces_x_preferred":[
        "Struha\u0159ov"
    ],
    "name:deu_x_preferred":[
        "Struha\u0159ov"
    ],
    "name:fra_x_preferred":[
        "Struha\u0159ov"
    ],
    "name:ita_x_preferred":[
        "Struha\u0159ov"
    ],
    "name:nld_x_preferred":[
        "Struha\u0159ov"
    ],
    "name:pol_x_preferred":[
        "Struha\u0159ov"
    ],
    "name:slk_x_preferred":[
        "Struha\u0159ov"
    ],
    "name:srp_x_preferred":[
        "\u0421\u0442\u0440\u0443\u0445\u0430\u0440\u0436\u043e\u0432"
    ],
    "name:swe_x_preferred":[
        "Struha\u0159ov"
    ],
    "name:unk_x_variant":[
        "Struharschow"
    ],
    "qs_pg:aaroncc":"CZ",
    "qs_pg:gn_country":"CZ",
    "qs_pg:gn_fcode":"PPL",
    "qs_pg:gn_pop":561,
    "qs_pg:name":"Struha\u0159ov",
    "qs_pg:name_adm0":"\u010cesk\u00e1 republika",
    "qs_pg:name_adm1":"St\u0159edo\u010desk\u00fd kraj",
    "qs_pg:photos_9r":0,
    "qs_pg:photos_sr":0,
    "qs_pg:pop_sr":2,
    "qs_pg:qs_pg_placetype":"locality",
    "qs_pg:qs_pg_placetype_gp":"Town",
    "qs_pg:woe_adm0":23424810,
    "woe:adm0_id":23424810,
    "woe:name_adm0":"\u010cesk\u00e1 republika",
    "woe:name_adm1":"St\u0159edo\u010desk\u00fd kraj",
    "woe:placetype":"Town",
    "wof:name":"Struha\u0159ov",
    "wof:placetype":"locality",
    "wof:population":561
},
  "geometry": {"coordinates":[14.74443,49.95192],"type":"Point"}
}