{
  "type": "Feature",
  "properties": {
    "gn:admin1_code":"88.0",
    "gn:admin2_code":"0205",
    "gn:asciiname":"Malin",
    "gn:country_code":"CZ",
    "gn:dem":210,
    "gn:feature_class":"P",
    "gn:feature_code":"PPL",
    "gn:name":"Mal\u00edn",
    "gn:population":0,
    "gn:timezone":"Europe/Prague",
    "iso:country":"CZ",
    "name:bel_x_preferred":[
        "\u041c\u0430\u043b\u0456\u043d"
    ],
    "name:ceb_x_preferred":[
        "Malin"
    ],
    "name:ces_x_preferred":[
        "Mal\u00edn"
    ],
    "name:deu_x_preferred":[
        "Malin"
    ],
    "name:fas_x_preferred":[
        "\u0645\u0627\u0644\u06cc\u0646"
    ],
    "name:heb_x_preferred":[
        "\u05de\u05d0\u05dc\u05d9\u05df"
    ],
    "name:hun_x_preferred":[
        "Malin"
    ],
    "name:ita_x_preferred":[
        "Malin"
    ],
    "name:nld_x_preferred":[
        "Malin"
    ],
    "name:pol_x_preferred":[
        "Malin"
    ],
    "name:rus_x_preferred":[
        "\u041c\u0430\u043b\u0438\u043d"
    ],
    "name:swe_x_preferred":[
        "Malin"
    ],
    "name:ukr_x_preferred":[
        "\u041c\u0430\u043b\u0438\u043d"
    ],
    "wof:name":"Malin",
    "wof:placetype":"locality"
},
  "geometry": {"coordinates":[15.30163,49.9683],"type":"Point"}
}