{
  "type": "Feature",
  "properties": {
    "gn:gn_country":"CZ",
    "gn:gn_fcode":"PPL",
    "gn:gn_pop":217,
    "gn:population":217,
    "iso:country":"CZ",
    "name:azb_x_preferred":[
        "\u06a9\u0648\u0644\u06cc\u0631\u0648\u0648"
    ],
    "name:ceb_x_preferred":[
        "Kul\u00ed\u0159ov"
    ],
    "name:ces_x_preferred":[
        "Kul\u00ed\u0159ov"
    ],
    "name:deu_x_preferred":[
        "Kul\u00ed\u0159ov"
    ],
    "name:eng_x_preferred":[
        "Kul\u00ed\u0159ov"
    ],
    "name:eus_x_preferred":[
        "Kul\u00ed\u0159ov"
    ],
    "name:fas_x_preferred":[
        "\u06a9\u0648\u0644\u06cc\u0631\u0648\u0648"
    ],
    "name:fra_x_preferred":[
        "Kul\u00ed\u0159ov"
    ],
    "name:hun_x_preferred":[
        "Kul\u00ed\u0159ov"
    ],
    "name:ita_x_preferred":[
        "Kul\u00ed\u0159ov"
    ],
    "name:msa_x_preferred":[
        "Kul\u00ed\u0159ov"
    ],
    "name:nan_x_preferred":[
        "Kul\u00ed\u0159ov"
    ],
    "name:nld_x_preferred":[
        "Kul\u00ed\u0159ov"
    ],
    "name:por_x_preferred":[
        "Kul\u00ed\u0159ov"
    ],
    "name:slk_x_preferred":[
        "Kul\u00ed\u0159ov"
    ],
    "name:spa_x_preferred":[
        "Kul\u00ed\u0159ov"
    ],
    "name:srp_x_preferred":[
        "\u041a\u0443\u043b\u0438\u0440\u0436\u043e\u0432"
    ],
    "name:swe_x_preferred":[
        "Kul\u00ed\u0159ov"
    ],
    "name:vie_x_preferred":[
        "Kul\u00ed\u0159ov"
    ],
    "qs_pg:aaroncc":"CZ",
    "qs_pg:gn_country":"CZ",
    "qs_pg:gn_fcode":"PPL",
    "qs_pg:gn_pop":217,
    "qs_pg:name":"Kul\u00ed\u0159ov",
    "qs_pg:name_adm0":"\u010cesk\u00e1 republika",
    "qs_pg:name_adm1":"Jihomoravsk\u00fd kraj",
    "qs_pg:photos_9r":0,
    "qs_pg:photos_sr":0,
    "qs_pg:pop_sr":2,
    "qs_pg:qs_pg_placetype":"locality",
    "qs_pg:qs_pg_placetype_gp":"Town",
    "qs_pg:woe_adm0":23424810,
    "woe:adm0_id":23424810,
    "woe:name_adm0":"\u010cesk\u00e1 republika",
    "woe:name_adm1":"Jihomoravsk\u00fd kraj",
    "woe:placetype":"Town",
    "wof:name":"Kul\u00ed\u0159ov",
    "wof:placetype":"locality",
    "wof:population":217
},
  "geometry": {"coordinates":[16.84681,49.37932],"type":"Point"}
}