{
  "type": "Feature",
  "properties": {
    "gn:admin1_code":"84.0",
    "gn:admin2_code":"0711",
    "gn:asciiname":"Dolni Lipova",
    "gn:country_code":"CZ",
    "gn:dem":492,
    "gn:feature_class":"P",
    "gn:feature_code":"PPL",
    "gn:name":"Doln\u00ed Lipov\u00e1",
    "gn:population":0,
    "gn:timezone":"Europe/Prague",
    "iso:country":"CZ",
    "name:und_x_variant":[
        "Nieder Lundewiese",
        "Nieder-Lindewiese",
        "Doln\u00ed Lipov\u00e1"
    ],
    "wof:name":"Dolni Lipova",
    "wof:placetype":"locality"
},
  "geometry": {"coordinates":[17.14561,50.2283],"type":"Point"}
}