{
  "type": "Feature",
  "properties": {
    "gn:gn_country":"CZ",
    "gn:gn_fcode":"PPL",
    "gn:gn_pop":91,
    "gn:population":91,
    "iso:country":"CZ",
    "name:azb_x_preferred":[
        "\u0647\u0627\u0628\u0631\u06cc"
    ],
    "name:ces_x_preferred":[
        "Hab\u0159\u00ed"
    ],
    "name:deu_x_preferred":[
        "Hab\u0159\u00ed"
    ],
    "name:eng_x_preferred":[
        "Hab\u0159\u00ed"
    ],
    "name:eus_x_preferred":[
        "Hab\u0159\u00ed"
    ],
    "name:fas_x_preferred":[
        "\u0647\u0627\u0628\u0631\u06cc"
    ],
    "name:fra_x_preferred":[
        "Hab\u0159\u00ed"
    ],
    "name:hun_x_preferred":[
        "Hab\u0159\u00ed"
    ],
    "name:ita_x_preferred":[
        "Hab\u0159\u00ed"
    ],
    "name:msa_x_preferred":[
        "Hab\u0159\u00ed"
    ],
    "name:nan_x_preferred":[
        "Hab\u0159\u00ed"
    ],
    "name:nld_x_preferred":[
        "Hab\u0159\u00ed"
    ],
    "name:pol_x_preferred":[
        "Hab\u0159\u00ed"
    ],
    "name:por_x_preferred":[
        "Hab\u0159\u00ed"
    ],
    "name:rup_x_preferred":[
        "Hab\u0159\u00ed"
    ],
    "name:slk_x_preferred":[
        "Hab\u0159\u00ed"
    ],
    "name:spa_x_preferred":[
        "Hab\u0159\u00ed"
    ],
    "name:srp_x_preferred":[
        "\u0425\u0430\u0431\u0440\u0438"
    ],
    "name:vie_x_preferred":[
        "Hab\u0159\u00ed"
    ],
    "qs_pg:aaroncc":"CZ",
    "qs_pg:gn_country":"CZ",
    "qs_pg:gn_fcode":"PPL",
    "qs_pg:gn_pop":91,
    "qs_pg:name":"Hab\u0159\u00ed",
    "qs_pg:name_adm0":"\u010cesk\u00e1 republika",
    "qs_pg:name_adm1":"Jiho\u010desk\u00fd kraj",
    "qs_pg:photos_9r":0,
    "qs_pg:photos_sr":0,
    "qs_pg:pop_sr":1,
    "qs_pg:qs_pg_placetype":"locality",
    "qs_pg:qs_pg_placetype_gp":"Town",
    "qs_pg:woe_adm0":23424810,
    "woe:adm0_id":23424810,
    "woe:name_adm0":"\u010cesk\u00e1 republika",
    "woe:name_adm1":"Jiho\u010desk\u00fd kraj",
    "woe:placetype":"Town",
    "wof:name":"Hab\u0159\u00ed",
    "wof:placetype":"locality",
    "wof:population":91
},
  "geometry": {"coordinates":[14.33485,48.94814],"type":"Point"}
}