{
  "type": "Feature",
  "properties": {
    "gn:admin1_code":"79.0",
    "gn:admin2_code":"0317",
    "gn:asciiname":"Mezimosti nad Nezarkou",
    "gn:country_code":"CZ",
    "gn:dem":410,
    "gn:feature_class":"P",
    "gn:feature_code":"PPL",
    "gn:name":"Mezimost\u00ed nad Ne\u017e\u00e1rkou",
    "gn:population":0,
    "gn:timezone":"Europe/Prague",
    "iso:country":"CZ",
    "wof:name":"Mezimosti nad Nezarkou",
    "wof:placetype":"locality"
},
  "geometry": {"coordinates":[14.704,49.18294],"type":"Point"}
}