{
  "type": "Feature",
  "properties": {
    "gn:country":"CZ",
    "gn:fcode":"PPL",
    "gn:population":215,
    "iso:country":"CZ",
    "name:azb_x_preferred":[
        "\u0647\u0648\u0631\u0646\u06cc \u0646\u06cc\u062a\u062a\u0634\u06cc\u062a\u0633\u0647"
    ],
    "name:ceb_x_preferred":[
        "Horn\u00ed N\u011bt\u010dice"
    ],
    "name:ces_x_preferred":[
        "Horn\u00ed N\u011bt\u010dice"
    ],
    "name:deu_x_preferred":[
        "Horn\u00ed N\u011bt\u010dice"
    ],
    "name:eng_x_preferred":[
        "Horn\u00ed N\u011bt\u010dice"
    ],
    "name:epo_x_preferred":[
        "Horn\u00ed N\u011bt\u010dice"
    ],
    "name:eus_x_preferred":[
        "Horn\u00ed N\u011bt\u010dice"
    ],
    "name:fas_x_preferred":[
        "\u0647\u0648\u0631\u0646\u06cc \u0646\u06cc\u062a\u062a\u0634\u06cc\u062a\u0633\u0647"
    ],
    "name:fra_x_preferred":[
        "Horn\u00ed N\u011bt\u010dice"
    ],
    "name:hun_x_preferred":[
        "Horn\u00ed N\u011bt\u010dice"
    ],
    "name:ita_x_preferred":[
        "Horn\u00ed N\u011bt\u010dice"
    ],
    "name:msa_x_preferred":[
        "Horn\u00ed N\u011bt\u010dice"
    ],
    "name:nan_x_preferred":[
        "Horn\u00ed N\u011bt\u010dice"
    ],
    "name:nld_x_preferred":[
        "Horn\u00ed N\u011bt\u010dice"
    ],
    "name:pol_x_preferred":[
        "Horn\u00ed N\u011bt\u010dice"
    ],
    "name:por_x_preferred":[
        "Horn\u00ed N\u011bt\u010dice"
    ],
    "name:rup_x_preferred":[
        "Horn\u00ed N\u011bt\u010dice"
    ],
    "name:slk_x_preferred":[
        "Horn\u00ed N\u011bt\u010dice"
    ],
    "name:spa_x_preferred":[
        "Horn\u00ed N\u011bt\u010dice"
    ],
    "name:srp_x_preferred":[
        "\u0425\u043e\u0440\u045a\u0438 \u040a\u0435\u0442\u0447\u0438\u0446\u0435"
    ],
    "name:swe_x_preferred":[
        "Horn\u00ed N\u011bt\u010dice"
    ],
    "name:vie_x_preferred":[
        "Horn\u00ed N\u011bt\u010dice"
    ],
    "qs_pg:aaroncc":"CZ",
    "qs_pg:gn_country":"CZ",
    "qs_pg:gn_fcode":"PPL",
    "qs_pg:gn_pop":215,
    "qs_pg:name":"Horn\u00ed N\u011bt\u010dice",
    "qs_pg:name_adm0":"\u010cesk\u00e1 republika",
    "qs_pg:name_adm1":"Olomouck\u00fd kraj",
    "qs_pg:photos_9r":0,
    "qs_pg:photos_sr":0,
    "qs_pg:pop_sr":2,
    "qs_pg:qs_pg_placetype":"locality",
    "qs_pg:qs_pg_placetype_gp":"Town",
    "qs_pg:woe_adm0":23424810,
    "woe:adm0_id":23424810,
    "woe:name_adm0":"\u010cesk\u00e1 republika",
    "woe:name_adm1":"Olomouck\u00fd kraj",
    "woe:placetype":"Town",
    "wof:name":"Horn\u00ed N\u011bt\u010dice",
    "wof:placetype":"locality",
    "wof:population":215
},
  "geometry": {"coordinates":[17.68439,49.47015],"type":"Point"}
}