{
  "type": "Feature",
  "properties": {
    "gn:country":"CZ",
    "gn:fcode":"PPL",
    "gn:population":62,
    "iso:country":"CZ",
    "name:azb_x_preferred":[
        "\u0628\u062f\u06cc\u0646"
    ],
    "name:ces_x_preferred":[
        "Bd\u00edn"
    ],
    "name:deu_x_preferred":[
        "Bd\u00edn"
    ],
    "name:eng_x_preferred":[
        "Bd\u00edn"
    ],
    "name:eus_x_preferred":[
        "Bd\u00edn"
    ],
    "name:fas_x_preferred":[
        "\u0628\u062f\u06cc\u0646"
    ],
    "name:fra_x_preferred":[
        "Bd\u00edn"
    ],
    "name:hun_x_preferred":[
        "Bd\u00edn"
    ],
    "name:ita_x_preferred":[
        "Bd\u00edn"
    ],
    "name:msa_x_preferred":[
        "Bd\u00edn"
    ],
    "name:nan_x_preferred":[
        "Bd\u00edn"
    ],
    "name:nld_x_preferred":[
        "Bd\u00edn"
    ],
    "name:por_x_preferred":[
        "Bd\u00edn"
    ],
    "name:rup_x_preferred":[
        "Bd\u00edn"
    ],
    "name:slk_x_preferred":[
        "Bd\u00edn"
    ],
    "name:spa_x_preferred":[
        "Bd\u00edn"
    ],
    "name:srp_x_preferred":[
        "\u0411\u0434\u0438\u043d"
    ],
    "name:vie_x_preferred":[
        "Bd\u00edn"
    ],
    "qs_pg:aaroncc":"CZ",
    "qs_pg:gn_country":"CZ",
    "qs_pg:gn_fcode":"PPL",
    "qs_pg:gn_pop":62,
    "qs_pg:name":"Bd\u00edn",
    "qs_pg:name_adm0":"\u010cesk\u00e1 republika",
    "qs_pg:name_adm1":"St\u0159edo\u010desk\u00fd kraj",
    "qs_pg:photos_9r":0,
    "qs_pg:photos_sr":0,
    "qs_pg:pop_sr":1,
    "qs_pg:qs_pg_placetype":"locality",
    "qs_pg:qs_pg_placetype_gp":"Town",
    "qs_pg:woe_adm0":23424810,
    "woe:adm0_id":23424810,
    "woe:name_adm0":"\u010cesk\u00e1 republika",
    "woe:name_adm1":"St\u0159edo\u010desk\u00fd kraj",
    "woe:placetype":"Town",
    "wof:name":"Bd\u00edn",
    "wof:placetype":"locality",
    "wof:population":62
},
  "geometry": {"coordinates":[13.85874,50.21414],"type":"Point"}
}