{
  "type": "Feature",
  "properties": {
    "gn:admin1_code":"78.0",
    "gn:admin2_code":"0627",
    "gn:asciiname":"Filipovice",
    "gn:country_code":"CZ",
    "gn:dem":215,
    "gn:feature_class":"P",
    "gn:feature_code":"PPL",
    "gn:name":"Filipovice",
    "gn:population":0,
    "gn:timezone":"Europe/Prague",
    "iso:country":"CZ",
    "name:und_x_variant":[
        "Philippsdorf",
        "Filipovice"
    ],
    "wof:name":"Filipovice",
    "wof:placetype":"locality"
},
  "geometry": {"coordinates":[16.25,48.85],"type":"Point"}
}