{
  "type": "Feature",
  "properties": {
    "gn:gn_country":"CZ",
    "gn:gn_fcode":"PPL",
    "gn:gn_pop":590,
    "gn:population":590,
    "iso:country":"CZ",
    "name:ces_x_preferred":[
        "Libavsk\u00e9 \u00dadol\u00ed"
    ],
    "name:deu_x_preferred":[
        "Libavsk\u00e9 \u00dadol\u00ed"
    ],
    "name:eng_x_preferred":[
        "Libavsk\u00e9 \u00dadol\u00ed"
    ],
    "name:fas_x_preferred":[
        "\u0644\u06cc\u0628\u0627\u0648\u0633\u06a9\u0647 \u0648\u062f\u0648\u0644\u06cc"
    ],
    "name:fra_x_preferred":[
        "Libavsk\u00e9 \u00dadol\u00ed"
    ],
    "name:hun_x_preferred":[
        "Libavsk\u00e9 \u00dadol\u00ed"
    ],
    "name:ita_x_preferred":[
        "Libavsk\u00e9 \u00dadol\u00ed"
    ],
    "name:msa_x_preferred":[
        "Libavsk\u00e9 \u00dadol\u00ed"
    ],
    "name:nan_x_preferred":[
        "Libavsk\u00e9 \u00dadol\u00ed"
    ],
    "name:nld_x_preferred":[
        "Libavsk\u00e9 \u00dadol\u00ed"
    ],
    "name:pol_x_preferred":[
        "Libavsk\u00e9 \u00dadol\u00ed"
    ],
    "name:por_x_preferred":[
        "Libavsk\u00e9 \u00dadol\u00ed"
    ],
    "name:rup_x_preferred":[
        "Libavsk\u00e9 \u00dadol\u00ed"
    ],
    "name:slk_x_preferred":[
        "Libavsk\u00e9 \u00dadol\u00ed"
    ],
    "name:srp_x_preferred":[
        "\u041b\u0438\u0431\u0430\u0432\u0441\u043a\u0435 \u0423\u0434\u043e\u043b\u0438"
    ],
    "name:swe_x_preferred":[
        "Libavsk\u00e9 \u00dadol\u00ed"
    ],
    "name:unk_x_variant":[
        "Kagerava"
    ],
    "name:vie_x_preferred":[
        "Libavsk\u00e9 \u00dadol\u00ed"
    ],
    "qs_pg:aaroncc":"CZ",
    "qs_pg:gn_country":"CZ",
    "qs_pg:gn_fcode":"PPL",
    "qs_pg:gn_pop":590,
    "qs_pg:name":"Libavsk\u00e9 \u00dadol\u00ed",
    "qs_pg:name_adm0":"\u010cesk\u00e1 republika",
    "qs_pg:name_adm1":"Karlovarsk\u00fd kraj",
    "qs_pg:photos_9r":0,
    "qs_pg:photos_sr":0,
    "qs_pg:pop_sr":2,
    "qs_pg:qs_pg_placetype":"locality",
    "qs_pg:qs_pg_placetype_gp":"Town",
    "qs_pg:woe_adm0":23424810,
    "woe:adm0_id":23424810,
    "woe:name_adm0":"\u010cesk\u00e1 republika",
    "woe:name_adm1":"Karlovarsk\u00fd kraj",
    "woe:placetype":"Town",
    "wof:name":"Libavsk\u00e9 \u00dadol\u00ed",
    "wof:placetype":"locality",
    "wof:population":590
},
  "geometry": {"coordinates":[12.55249,50.12887],"type":"Point"}
}