{
  "type": "Feature",
  "properties": {
    "gn:admin1_code":"88.0",
    "gn:admin2_code":"020B",
    "gn:asciiname":"Libice",
    "gn:country_code":"CZ",
    "gn:dem":423,
    "gn:feature_class":"P",
    "gn:feature_code":"PPL",
    "gn:name":"Libice",
    "gn:population":0,
    "gn:timezone":"Europe/Prague",
    "iso:country":"CZ",
    "name:ceb_x_preferred":[
        "Libice"
    ],
    "name:ces_x_preferred":[
        "Libice"
    ],
    "name:deu_x_preferred":[
        "Libice"
    ],
    "name:ita_x_preferred":[
        "Libice"
    ],
    "name:pol_x_preferred":[
        "Libice"
    ],
    "name:swe_x_preferred":[
        "Libice"
    ],
    "wof:name":"Libice",
    "wof:placetype":"locality"
},
  "geometry": {"coordinates":[14.20672,49.73783],"type":"Point"}
}