{
  "type": "Feature",
  "properties": {
    "iso:country":"CZ",
    "qs_pg:aaroncc":"CZ",
    "qs_pg:name":"Desn\u00e1",
    "qs_pg:name_adm0":"\u010cesk\u00e1 republika",
    "qs_pg:name_adm1":"Libereck\u00fd kraj",
    "qs_pg:photos":56,
    "qs_pg:photos_1k":11,
    "qs_pg:photos_9k":6,
    "qs_pg:photos_9r":7,
    "qs_pg:photos_all":1286,
    "qs_pg:photos_sr":2,
    "qs_pg:pop_sr":0,
    "qs_pg:qs_pg_placetype":"localadmin",
    "qs_pg:qs_pg_placetype_gp":"LocalAdmin",
    "qs_pg:woe_adm0":23424810,
    "woe:adm0_id":23424810,
    "woe:name_adm0":"\u010cesk\u00e1 republika",
    "woe:name_adm1":"Libereck\u00fd kraj",
    "woe:placetype":"LocalAdmin",
    "wof:name":"Desn\u00e1",
    "wof:placetype":"localadmin"
},
  "geometry": {"coordinates":[15.318379,50.755551],"type":"Point"}
}