{
  "type": "Feature",
  "properties": {
    "gn:gn_country":"CZ",
    "gn:gn_fcode":"PPL",
    "gn:gn_pop":297,
    "gn:population":297,
    "iso:country":"CZ",
    "name:bul_x_preferred":[
        "\u0417\u0434\u0435\u0440\u0430\u0437"
    ],
    "name:cze_x_preferred":[
        "Zderaz"
    ],
    "name:dut_x_preferred":[
        "Zderaz"
    ],
    "name:eng_x_preferred":[
        "Zderaz"
    ],
    "name:epo_x_preferred":[
        "Zderaz"
    ],
    "name:fre_x_preferred":[
        "Zderaz"
    ],
    "name:hun_x_preferred":[
        "Zderaz"
    ],
    "name:ita_x_preferred":[
        "Zderaz"
    ],
    "name:may_x_preferred":[
        "Zderaz"
    ],
    "name:pol_x_preferred":[
        "Zderaz"
    ],
    "name:por_x_preferred":[
        "Zderaz"
    ],
    "name:rup_x_preferred":[
        "Zderaz"
    ],
    "name:slo_x_preferred":[
        "Zderaz"
    ],
    "name:srp_x_preferred":[
        "\u0417\u0434\u0435\u0440\u0430\u0437"
    ],
    "name:swe_x_preferred":[
        "Zderaz"
    ],
    "name:vie_x_preferred":[
        "Zderaz"
    ],
    "qs_pg:aaroncc":"CZ",
    "qs_pg:gn_country":"CZ",
    "qs_pg:gn_fcode":"PPL",
    "qs_pg:gn_pop":297,
    "qs_pg:name":"Zderaz",
    "qs_pg:name_adm0":"\u010cesk\u00e1 republika",
    "qs_pg:name_adm1":"Pardubick\u00fd kraj",
    "qs_pg:photos_9k":1,
    "qs_pg:photos_9r":1,
    "qs_pg:photos_all":1,
    "qs_pg:photos_sr":0,
    "qs_pg:pop_sr":2,
    "qs_pg:qs_pg_placetype":"locality",
    "qs_pg:qs_pg_placetype_gp":"Town",
    "qs_pg:woe_adm0":23424810,
    "woe:adm0_id":23424810,
    "woe:name_adm0":"\u010cesk\u00e1 republika",
    "woe:name_adm1":"Pardubick\u00fd kraj",
    "woe:placetype":"Town",
    "wof:name":"Zderaz",
    "wof:placetype":"locality",
    "wof:population":297
},
  "geometry": {"coordinates":[16.10009,49.82855],"type":"Point"}
}