{
  "type": "Feature",
  "properties": {
    "gn:admin1_code":"84.0",
    "gn:admin2_code":"0711",
    "gn:asciiname":"Dolni Fort Domkari",
    "gn:country_code":"CZ",
    "gn:dem":298,
    "gn:feature_class":"P",
    "gn:feature_code":"PPL",
    "gn:name":"Doln\u00ed Fo\u0159t Domk\u00e1\u0159i",
    "gn:population":0,
    "gn:timezone":"Europe/Prague",
    "iso:country":"CZ",
    "name:und_x_variant":[
        "Niederforst-Priebnerleuten",
        "Doln\u00ed Fo\u0159t Domk\u00e1\u0159i"
    ],
    "wof:name":"Dolni Fort Domkari",
    "wof:placetype":"locality"
},
  "geometry": {"coordinates":[17.03333,50.36667],"type":"Point"}
}