{
  "type": "Feature",
  "properties": {
    "gn:gn_country":"CZ",
    "gn:gn_fcode":"PPL",
    "gn:gn_pop":632,
    "gn:population":632,
    "iso:country":"CZ",
    "name:bul_x_preferred":[
        "\u0422\u0440\u043d\u043e\u0432"
    ],
    "name:ces_x_preferred":[
        "Trnov"
    ],
    "name:eng_x_preferred":[
        "Trnov"
    ],
    "name:fas_x_preferred":[
        "\u062a\u0631\u0646\u0648\u0648"
    ],
    "name:fra_x_preferred":[
        "Trnov"
    ],
    "name:hun_x_preferred":[
        "Trnov"
    ],
    "name:ita_x_preferred":[
        "Trnov"
    ],
    "name:msa_x_preferred":[
        "Trnov"
    ],
    "name:nld_x_preferred":[
        "Trnov"
    ],
    "name:pol_x_preferred":[
        "Trnov"
    ],
    "name:por_x_preferred":[
        "Trnov"
    ],
    "name:slk_x_preferred":[
        "Trnov"
    ],
    "name:srp_x_preferred":[
        "\u0422\u0440\u043d\u043e\u0432"
    ],
    "name:swe_x_preferred":[
        "Trnov"
    ],
    "name:vie_x_preferred":[
        "Trnov"
    ],
    "qs_pg:aaroncc":"CZ",
    "qs_pg:gn_country":"CZ",
    "qs_pg:gn_fcode":"PPL",
    "qs_pg:gn_pop":632,
    "qs_pg:name":"Trnov",
    "qs_pg:name_adm0":"\u010cesk\u00e1 republika",
    "qs_pg:name_adm1":"Kr\u00e1lov\u00e9hradeck\u00fd kraj",
    "qs_pg:photos_9r":0,
    "qs_pg:photos_sr":0,
    "qs_pg:pop_sr":2,
    "qs_pg:qs_pg_placetype":"locality",
    "qs_pg:qs_pg_placetype_gp":"Town",
    "qs_pg:woe_adm0":23424810,
    "woe:adm0_id":23424810,
    "woe:name_adm0":"\u010cesk\u00e1 republika",
    "woe:name_adm1":"Kr\u00e1lov\u00e9hradeck\u00fd kraj",
    "woe:placetype":"Town",
    "wof:name":"Trnov",
    "wof:placetype":"locality",
    "wof:population":632
},
  "geometry": {"coordinates":[16.16441,50.24468],"type":"Point"}
}