{
  "type": "Feature",
  "properties": {
    "gn:gn_country":"CZ",
    "gn:gn_fcode":"PPL",
    "gn:gn_pop":70,
    "gn:population":70,
    "iso:country":"CZ",
    "name:ces_x_preferred":[
        "Koryta"
    ],
    "name:eng_x_preferred":[
        "Koryta"
    ],
    "name:fas_x_preferred":[
        "\u06a9\u0648\u0631\u06cc\u062a\u0627"
    ],
    "name:fra_x_preferred":[
        "Koryta"
    ],
    "name:hun_x_preferred":[
        "Koryta"
    ],
    "name:ita_x_preferred":[
        "Koryta"
    ],
    "name:msa_x_preferred":[
        "Koryta"
    ],
    "name:nld_x_preferred":[
        "Koryta"
    ],
    "name:pol_x_preferred":[
        "Koryta"
    ],
    "name:por_x_preferred":[
        "Koryta"
    ],
    "name:rup_x_preferred":[
        "Koryta"
    ],
    "name:slk_x_preferred":[
        "Koryta"
    ],
    "name:srp_x_preferred":[
        "\u041a\u043e\u0440\u0438\u0442\u0430"
    ],
    "name:vie_x_preferred":[
        "Koryta"
    ],
    "qs_pg:aaroncc":"CZ",
    "qs_pg:gn_country":"CZ",
    "qs_pg:gn_fcode":"PPL",
    "qs_pg:gn_pop":70,
    "qs_pg:name":"Koryta",
    "qs_pg:name_adm0":"\u010cesk\u00e1 republika",
    "qs_pg:name_adm1":"St\u0159edo\u010desk\u00fd kraj",
    "qs_pg:photos_9r":0,
    "qs_pg:photos_sr":0,
    "qs_pg:pop_sr":1,
    "qs_pg:qs_pg_placetype":"locality",
    "qs_pg:qs_pg_placetype_gp":"Town",
    "qs_pg:woe_adm0":23424810,
    "woe:adm0_id":23424810,
    "woe:name_adm0":"\u010cesk\u00e1 republika",
    "woe:name_adm1":"St\u0159edo\u010desk\u00fd kraj",
    "woe:placetype":"Town",
    "wof:name":"Koryta",
    "wof:placetype":"locality",
    "wof:population":70
},
  "geometry": {"coordinates":[15.01172,50.57195],"type":"Point"}
}