{
  "type": "Feature",
  "properties": {
    "gn:admin1_code":"88.0",
    "gn:admin2_code":"0206",
    "gn:asciiname":"Nova Ves",
    "gn:country_code":"CZ",
    "gn:dem":190,
    "gn:feature_class":"P",
    "gn:feature_code":"PPL",
    "gn:name":"Nov\u00e1 Ves",
    "gn:population":827,
    "gn:timezone":"Europe/Prague",
    "iso:country":"CZ",
    "name:azb_x_preferred":[
        "\u0646\u0648\u0648\u0627 \u0648\u0633"
    ],
    "name:ces_x_preferred":[
        "Nov\u00e1 Ves"
    ],
    "name:deu_x_preferred":[
        "Nov\u00e1 Ves u Nelahozevsi"
    ],
    "name:epo_x_preferred":[
        "Nov\u00e1 Ves"
    ],
    "name:eus_x_preferred":[
        "Nov\u00e1 Ves"
    ],
    "name:fas_x_preferred":[
        "\u0646\u0648\u0648\u0627 \u0648\u0633"
    ],
    "name:hun_x_preferred":[
        "Nov\u00e1 Ves"
    ],
    "name:ita_x_preferred":[
        "Nov\u00e1 Ves"
    ],
    "name:msa_x_preferred":[
        "Nov\u00e1 Ves"
    ],
    "name:nld_x_preferred":[
        "Nov\u00e1 Ves"
    ],
    "name:pol_x_preferred":[
        "Nov\u00e1 Ves"
    ],
    "name:por_x_preferred":[
        "Nov\u00e1 Ves"
    ],
    "name:slk_x_preferred":[
        "Nov\u00e1 Ves"
    ],
    "name:spa_x_preferred":[
        "Nov\u00e1 Ves"
    ],
    "name:srp_x_preferred":[
        "\u041d\u043e\u0432\u0430 \u0412\u0435\u0441"
    ],
    "name:vie_x_preferred":[
        "Nov\u00e1 Ves"
    ],
    "wof:name":"Nova Ves",
    "wof:placetype":"locality",
    "wof:population":827
},
  "geometry": {"coordinates":[14.30818,50.31279],"type":"Point"}
}