{
  "type": "Feature",
  "properties": {
    "gn:admin1_code":"88.0",
    "gn:admin2_code":"0206",
    "gn:asciiname":"Nova Ves",
    "gn:country_code":"CZ",
    "gn:dem":190,
    "gn:feature_class":"P",
    "gn:feature_code":"PPL",
    "gn:name":"Nov\u00e1 Ves",
    "gn:population":827,
    "gn:timezone":"Europe/Prague",
    "iso:country":"CZ",
    "wof:name":"Nova Ves",
    "wof:placetype":"locality",
    "wof:population":827
},
  "geometry": {"coordinates":[14.30818,50.31279],"type":"Point"}
}