{
  "type": "Feature",
  "properties": {
    "gn:admin1_code":"89.0",
    "gn:admin2_code":"0426",
    "gn:asciiname":"Kladruby",
    "gn:country_code":"CZ",
    "gn:dem":288,
    "gn:feature_class":"P",
    "gn:feature_code":"PPL",
    "gn:name":"Kladruby",
    "gn:population":262,
    "gn:timezone":"Europe/Prague",
    "iso:country":"CZ",
    "name:azb_x_preferred":[
        "\u06a9\u0644\u0627\u062f\u0631\u0648\u0628\u06cc"
    ],
    "name:ceb_x_preferred":[
        "Kladruby"
    ],
    "name:ces_x_preferred":[
        "Kladruby"
    ],
    "name:eus_x_preferred":[
        "Kladruby"
    ],
    "name:fas_x_preferred":[
        "\u06a9\u0644\u0627\u062f\u0631\u0648\u0628\u06cc"
    ],
    "name:hun_x_preferred":[
        "Kladruby"
    ],
    "name:ita_x_preferred":[
        "Kladruby"
    ],
    "name:msa_x_preferred":[
        "Kladruby"
    ],
    "name:nld_x_preferred":[
        "Kladruby"
    ],
    "name:pol_x_preferred":[
        "Kladruby"
    ],
    "name:por_x_preferred":[
        "Kladruby"
    ],
    "name:slk_x_preferred":[
        "Kladruby"
    ],
    "name:spa_x_preferred":[
        "Kladruby"
    ],
    "name:srp_x_preferred":[
        "\u041a\u043b\u0430\u0434\u0440\u0443\u0431\u0438"
    ],
    "name:und_x_variant":[
        "Kradrob"
    ],
    "name:vie_x_preferred":[
        "Kladruby"
    ],
    "wof:name":"Kladruby",
    "wof:placetype":"locality",
    "wof:population":262
},
  "geometry": {"coordinates":[13.8255,50.61492],"type":"Point"}
}