{
  "type": "Feature",
  "properties": {
    "gn:admin1_code":"89.0",
    "gn:admin2_code":"0426",
    "gn:asciiname":"Kladruby",
    "gn:country_code":"CZ",
    "gn:dem":288,
    "gn:feature_class":"P",
    "gn:feature_code":"PPL",
    "gn:name":"Kladruby",
    "gn:population":262,
    "gn:timezone":"Europe/Prague",
    "iso:country":"CZ",
    "name:und_x_variant":[
        "Kradrob"
    ],
    "wof:name":"Kladruby",
    "wof:placetype":"locality",
    "wof:population":262
},
  "geometry": {"coordinates":[13.8255,50.61492],"type":"Point"}
}