{
  "type": "Feature",
  "properties": {
    "gn:admin1_code":"79.0",
    "gn:admin2_code":"0313",
    "gn:asciiname":"Hluboka",
    "gn:country_code":"CZ",
    "gn:dem":483,
    "gn:feature_class":"P",
    "gn:feature_code":"PPL",
    "gn:name":"Hlubok\u00e1",
    "gn:population":0,
    "gn:timezone":"Europe/Prague",
    "iso:country":"CZ",
    "name:und_x_variant":[
        "Tiefenbach",
        "Hlubok\u00e1"
    ],
    "wof:name":"Hluboka",
    "wof:placetype":"locality"
},
  "geometry": {"coordinates":[15.52259,48.92219],"type":"Point"}
}