{
  "type": "Feature",
  "properties": {
    "gn:gn_country":"CZ",
    "gn:gn_fcode":"PPL",
    "gn:gn_pop":280,
    "gn:population":280,
    "iso:country":"CZ",
    "name:cze_x_preferred":[
        "P\u0159\u00ed\u0161tpo"
    ],
    "name:dut_x_preferred":[
        "P\u0159\u00ed\u0161tpo"
    ],
    "name:eng_x_preferred":[
        "P\u0159\u00ed\u0161tpo"
    ],
    "name:fre_x_preferred":[
        "P\u0159\u00ed\u0161tpo"
    ],
    "name:ger_x_preferred":[
        "P\u0159\u00ed\u0161tpo"
    ],
    "name:hun_x_preferred":[
        "P\u0159\u00ed\u0161tpo"
    ],
    "name:ita_x_preferred":[
        "P\u0159\u00ed\u0161tpo"
    ],
    "name:may_x_preferred":[
        "P\u0159\u00ed\u0161tpo"
    ],
    "name:nan_x_preferred":[
        "P\u0159\u00ed\u0161tpo"
    ],
    "name:per_x_preferred":[
        "\u067e\u0631\u06cc\u0634\u062a\u067e\u0648"
    ],
    "name:por_x_preferred":[
        "P\u0159\u00ed\u0161tpo"
    ],
    "name:rup_x_preferred":[
        "P\u0159\u00ed\u0161tpo"
    ],
    "name:slo_x_preferred":[
        "P\u0159\u00ed\u0161tpo"
    ],
    "name:swe_x_preferred":[
        "P\u0159\u00ed\u0161tpo"
    ],
    "name:unk_x_variant":[
        "Przispach"
    ],
    "name:vie_x_preferred":[
        "P\u0159\u00ed\u0161tpo"
    ],
    "qs_pg:aaroncc":"CZ",
    "qs_pg:gn_country":"CZ",
    "qs_pg:gn_fcode":"PPL",
    "qs_pg:gn_pop":280,
    "qs_pg:name":"P\u0159\u00ed\u0161tpo",
    "qs_pg:name_adm0":"\u010cesk\u00e1 republika",
    "qs_pg:name_adm1":"Kraj Vyso\u010dina",
    "qs_pg:photos_9r":0,
    "qs_pg:photos_sr":0,
    "qs_pg:pop_sr":2,
    "qs_pg:qs_pg_placetype":"locality",
    "qs_pg:qs_pg_placetype_gp":"Town",
    "qs_pg:woe_adm0":23424810,
    "woe:adm0_id":23424810,
    "woe:name_adm0":"\u010cesk\u00e1 republika",
    "woe:name_adm1":"Kraj Vyso\u010dina",
    "woe:placetype":"Town",
    "wof:name":"P\u0159\u00ed\u0161tpo",
    "wof:placetype":"locality",
    "wof:population":280
},
  "geometry": {"coordinates":[15.9349,49.07384],"type":"Point"}
}