{
  "type": "Feature",
  "properties": {
    "gn:gn_country":"CZ",
    "gn:gn_fcode":"PPL",
    "gn:gn_pop":386,
    "gn:population":386,
    "iso:country":"CZ",
    "name:cze_x_preferred":[
        "Bose\u0148"
    ],
    "name:dut_x_preferred":[
        "Bose\u0148"
    ],
    "name:eng_x_preferred":[
        "Bose\u0148"
    ],
    "name:fre_x_preferred":[
        "Bose\u0148"
    ],
    "name:ger_x_preferred":[
        "Bose\u0148"
    ],
    "name:hun_x_preferred":[
        "Bose\u0148"
    ],
    "name:ita_x_preferred":[
        "Bose\u0148"
    ],
    "name:may_x_preferred":[
        "Bose\u0148"
    ],
    "name:nan_x_preferred":[
        "Bose\u0148"
    ],
    "name:per_x_preferred":[
        "\u0628\u0648\u0633\u0646"
    ],
    "name:pol_x_preferred":[
        "Bose\u0148"
    ],
    "name:por_x_preferred":[
        "Bose\u0148"
    ],
    "name:rup_x_preferred":[
        "Bose\u0148"
    ],
    "name:rus_x_preferred":[
        "\u0411\u043e\u0441\u0435\u043d\u044c"
    ],
    "name:slo_x_preferred":[
        "Bose\u0148"
    ],
    "name:srp_x_preferred":[
        "\u0411\u043e\u0441\u0435\u045a"
    ],
    "name:swe_x_preferred":[
        "Bose\u0148"
    ],
    "name:vie_x_preferred":[
        "Bose\u0148"
    ],
    "qs_pg:aaroncc":"CZ",
    "qs_pg:gn_country":"CZ",
    "qs_pg:gn_fcode":"PPL",
    "qs_pg:gn_pop":386,
    "qs_pg:name":"Bose\u0148",
    "qs_pg:name_adm0":"\u010cesk\u00e1 republika",
    "qs_pg:name_adm1":"St\u0159edo\u010desk\u00fd kraj",
    "qs_pg:photos_9r":0,
    "qs_pg:photos_sr":0,
    "qs_pg:pop_sr":2,
    "qs_pg:qs_pg_placetype":"locality",
    "qs_pg:qs_pg_placetype_gp":"Town",
    "qs_pg:woe_adm0":23424810,
    "woe:adm0_id":23424810,
    "woe:name_adm0":"\u010cesk\u00e1 republika",
    "woe:name_adm1":"St\u0159edo\u010desk\u00fd kraj",
    "woe:placetype":"Town",
    "wof:name":"Bose\u0148",
    "wof:placetype":"locality",
    "wof:population":386
},
  "geometry": {"coordinates":[15.0228,50.5041],"type":"Point"}
}