{
  "type": "Feature",
  "properties": {
    "gn:admin1_code":"80.0",
    "gn:admin2_code":"0611",
    "gn:asciiname":"Ceska Jablonna",
    "gn:country_code":"CZ",
    "gn:dem":512,
    "gn:feature_class":"P",
    "gn:feature_code":"PPL",
    "gn:name":"\u010cesk\u00e1 Jablonn\u00e1",
    "gn:population":0,
    "gn:timezone":"Europe/Prague",
    "iso:country":"CZ",
    "wof:name":"Ceska Jablonna",
    "wof:placetype":"locality"
},
  "geometry": {"coordinates":[15.74408,49.54473],"type":"Point"}
}