{
  "type": "Feature",
  "properties": {
    "gn:gn_country":"CZ",
    "gn:gn_fcode":"PPL",
    "gn:gn_pop":95,
    "gn:population":95,
    "iso:country":"CZ",
    "name:cze_x_preferred":[
        "Vrchovany"
    ],
    "name:dut_x_preferred":[
        "Vrchovany"
    ],
    "name:eng_x_preferred":[
        "Vrchovany"
    ],
    "name:fre_x_preferred":[
        "Vrchovany"
    ],
    "name:ger_x_preferred":[
        "Vrchovany"
    ],
    "name:hun_x_preferred":[
        "Vrchovany"
    ],
    "name:ita_x_preferred":[
        "Vrchovany"
    ],
    "name:may_x_preferred":[
        "Vrchovany"
    ],
    "name:per_x_preferred":[
        "\u0648\u0631\u062e\u0648\u0648\u0627\u0646\u06cc"
    ],
    "name:por_x_preferred":[
        "Vrchovany"
    ],
    "name:slo_x_preferred":[
        "Vrchovany"
    ],
    "name:srp_x_preferred":[
        "\u0412\u0440\u0445\u043e\u0432\u0430\u043d\u0438"
    ],
    "name:vie_x_preferred":[
        "Vrchovany"
    ],
    "qs_pg:aaroncc":"CZ",
    "qs_pg:gn_country":"CZ",
    "qs_pg:gn_fcode":"PPL",
    "qs_pg:gn_pop":95,
    "qs_pg:name":"Vrchovany",
    "qs_pg:name_adm0":"\u010cesk\u00e1 republika",
    "qs_pg:name_adm1":"Libereck\u00fd kraj",
    "qs_pg:photos_9k":1,
    "qs_pg:photos_9r":1,
    "qs_pg:photos_all":1,
    "qs_pg:photos_sr":0,
    "qs_pg:pop_sr":1,
    "qs_pg:qs_pg_placetype":"locality",
    "qs_pg:qs_pg_placetype_gp":"Town",
    "qs_pg:woe_adm0":23424810,
    "woe:adm0_id":23424810,
    "woe:name_adm0":"\u010cesk\u00e1 republika",
    "woe:name_adm1":"Libereck\u00fd kraj",
    "woe:placetype":"Town",
    "wof:name":"Vrchovany",
    "wof:placetype":"locality",
    "wof:population":95
},
  "geometry": {"coordinates":[14.57111,50.55314],"type":"Point"}
}