{
  "type": "Feature",
  "properties": {
    "gn:admin1_code":"81.0",
    "gn:admin2_code":"0412",
    "gn:asciiname":"Popov",
    "gn:country_code":"CZ",
    "gn:dem":638,
    "gn:feature_class":"P",
    "gn:feature_code":"PPL",
    "gn:name":"Popov",
    "gn:population":0,
    "gn:timezone":"Europe/Prague",
    "iso:country":"CZ",
    "name:est_x_preferred":[
        "Popov"
    ],
    "name:lav_x_preferred":[
        "Popovs"
    ],
    "name:rus_x_preferred":[
        "\u041f\u043e\u043f\u043e\u0432"
    ],
    "name:slv_x_preferred":[
        "Popov"
    ],
    "name:und_x_variant":[
        "Pfaffengr\u00fcn",
        "Pfaffengruen"
    ],
    "wof:name":"Popov",
    "wof:placetype":"locality"
},
  "geometry": {"coordinates":[12.9204,50.33608],"type":"Point"}
}