{
  "type": "Feature",
  "properties": {
    "gn:country":"CZ",
    "gn:fcode":"PPL",
    "gn:population":322,
    "iso:country":"CZ",
    "name:ceb_x_preferred":[
        "Vod\u011brady"
    ],
    "name:ces_x_preferred":[
        "Vod\u011brady"
    ],
    "name:deu_x_preferred":[
        "Vod\u011brady"
    ],
    "name:epo_x_preferred":[
        "Vod\u011brady"
    ],
    "name:fra_x_preferred":[
        "Voderady"
    ],
    "name:ita_x_preferred":[
        "Vod\u011brady"
    ],
    "name:nld_x_preferred":[
        "Vod\u011brady"
    ],
    "name:slk_x_preferred":[
        "Vod\u011brady"
    ],
    "name:srp_x_preferred":[
        "\u0412\u043e\u0434\u0458\u0435\u0440\u0430\u0434\u0438"
    ],
    "name:swe_x_preferred":[
        "Vod\u011brady"
    ],
    "qs_pg:aaroncc":"CZ",
    "qs_pg:gn_country":"CZ",
    "qs_pg:gn_fcode":"PPL",
    "qs_pg:gn_pop":322,
    "qs_pg:name":"Vod\u011brady",
    "qs_pg:name_adm0":"\u010cesk\u00e1 republika",
    "qs_pg:name_adm1":"Pardubick\u00fd kraj",
    "qs_pg:photos_9k":1,
    "qs_pg:photos_9r":3,
    "qs_pg:photos_all":113,
    "qs_pg:photos_sr":0,
    "qs_pg:pop_sr":2,
    "qs_pg:qs_pg_placetype":"locality",
    "qs_pg:qs_pg_placetype_gp":"Town",
    "qs_pg:woe_adm0":23424810,
    "woe:adm0_id":23424810,
    "woe:name_adm0":"\u010cesk\u00e1 republika",
    "woe:name_adm1":"Pardubick\u00fd kraj",
    "woe:placetype":"Town",
    "wof:name":"Vod\u011brady",
    "wof:placetype":"locality",
    "wof:population":322
},
  "geometry": {"coordinates":[16.28506,49.9496],"type":"Point"}
}