{
  "type": "Feature",
  "properties": {
    "gn:gn_country":"CZ",
    "gn:gn_fcode":"PPL",
    "gn:gn_pop":396,
    "gn:population":396,
    "iso:country":"CZ",
    "name:cze_x_preferred":[
        "V\u0161eradice"
    ],
    "name:dut_x_preferred":[
        "V\u0161eradice"
    ],
    "name:eng_x_preferred":[
        "V\u0161eradice"
    ],
    "name:fre_x_preferred":[
        "V\u0161eradice"
    ],
    "name:ger_x_preferred":[
        "V\u0161eradice"
    ],
    "name:hun_x_preferred":[
        "V\u0161eradice"
    ],
    "name:ita_x_preferred":[
        "V\u0161eradice"
    ],
    "name:may_x_preferred":[
        "V\u0161eradice"
    ],
    "name:nan_x_preferred":[
        "V\u0161eradice"
    ],
    "name:per_x_preferred":[
        "\u0648\u0634\u0631\u0627\u062f\u06cc\u062a\u0633\u0647"
    ],
    "name:pol_x_preferred":[
        "V\u0161eradice"
    ],
    "name:por_x_preferred":[
        "V\u0161eradice"
    ],
    "name:rup_x_preferred":[
        "V\u0161eradice"
    ],
    "name:rus_x_preferred":[
        "\u0412\u0448\u0435\u0440\u0430\u0434\u0438\u0446\u0435"
    ],
    "name:slo_x_preferred":[
        "V\u0161eradice"
    ],
    "name:srp_x_preferred":[
        "\u0412\u0448\u0435\u0440\u0430\u0434\u0438\u0446\u0435"
    ],
    "name:swe_x_preferred":[
        "V\u0161eradice"
    ],
    "name:unk_x_variant":[
        "W\u0161eraditz"
    ],
    "name:vie_x_preferred":[
        "V\u0161eradice"
    ],
    "qs_pg:aaroncc":"CZ",
    "qs_pg:gn_country":"CZ",
    "qs_pg:gn_fcode":"PPL",
    "qs_pg:gn_pop":396,
    "qs_pg:name":"V\u0161eradice",
    "qs_pg:name_adm0":"\u010cesk\u00e1 republika",
    "qs_pg:name_adm1":"St\u0159edo\u010desk\u00fd kraj",
    "qs_pg:photos_9k":1,
    "qs_pg:photos_9r":1,
    "qs_pg:photos_all":1,
    "qs_pg:photos_sr":0,
    "qs_pg:pop_sr":2,
    "qs_pg:qs_pg_placetype":"locality",
    "qs_pg:qs_pg_placetype_gp":"Town",
    "qs_pg:woe_adm0":23424810,
    "woe:adm0_id":23424810,
    "woe:name_adm0":"\u010cesk\u00e1 republika",
    "woe:name_adm1":"St\u0159edo\u010desk\u00fd kraj",
    "woe:placetype":"Town",
    "wof:name":"V\u0161eradice",
    "wof:placetype":"locality",
    "wof:population":396
},
  "geometry": {"coordinates":[14.10476,49.87365],"type":"Point"}
}