{
  "type": "Feature",
  "properties": {
    "gn:admin1_code":"80.0",
    "gn:admin2_code":"0613",
    "gn:asciiname":"Caslavko",
    "gn:country_code":"CZ",
    "gn:dem":578,
    "gn:feature_class":"P",
    "gn:feature_code":"PPL",
    "gn:name":"\u010c\u00e1slavko",
    "gn:population":0,
    "gn:timezone":"Europe/Prague",
    "iso:country":"CZ",
    "wof:name":"Caslavko",
    "wof:placetype":"locality"
},
  "geometry": {"coordinates":[15.00363,49.59235],"type":"Point"}
}