{
  "type": "Feature",
  "properties": {
    "gn:admin1_code":"82.0",
    "gn:admin2_code":"0523",
    "gn:asciiname":"Rerisny",
    "gn:country_code":"CZ",
    "gn:dem":500,
    "gn:feature_class":"P",
    "gn:feature_code":"PPL",
    "gn:name":"\u0158e\u0159i\u0161n\u00fd",
    "gn:population":0,
    "gn:timezone":"Europe/Prague",
    "iso:country":"CZ",
    "wof:name":"Rerisny",
    "wof:placetype":"locality"
},
  "geometry": {"coordinates":[16.2934,50.50448],"type":"Point"}
}