{
  "type": "Feature",
  "properties": {
    "gn:gn_country":"CZ",
    "gn:gn_fcode":"PPL",
    "gn:gn_pop":468,
    "gn:population":468,
    "iso:country":"CZ",
    "name:cze_x_preferred":[
        "Div\u00e1ky"
    ],
    "name:dut_x_preferred":[
        "Div\u00e1ky"
    ],
    "name:eng_x_preferred":[
        "Div\u00e1ky"
    ],
    "name:fre_x_preferred":[
        "Div\u00e1ky"
    ],
    "name:ger_x_preferred":[
        "Div\u00e1ky"
    ],
    "name:hun_x_preferred":[
        "Div\u00e1ky"
    ],
    "name:ita_x_preferred":[
        "Div\u00e1ky"
    ],
    "name:may_x_preferred":[
        "Div\u00e1ky"
    ],
    "name:per_x_preferred":[
        "\u062f\u06cc\u0648\u0627\u06a9\u06cc"
    ],
    "name:pol_x_preferred":[
        "Div\u00e1ky"
    ],
    "name:por_x_preferred":[
        "Div\u00e1ky"
    ],
    "name:rup_x_preferred":[
        "Div\u00e1ky"
    ],
    "name:sgs_x_preferred":[
        "D\u0117vak\u0113"
    ],
    "name:slo_x_preferred":[
        "Div\u00e1ky"
    ],
    "name:srp_x_preferred":[
        "\u0414\u0438\u0432\u0430\u043a\u0438"
    ],
    "name:swe_x_preferred":[
        "Div\u00e1ky"
    ],
    "name:vie_x_preferred":[
        "Div\u00e1ky"
    ],
    "qs_pg:aaroncc":"CZ",
    "qs_pg:gn_country":"CZ",
    "qs_pg:gn_fcode":"PPL",
    "qs_pg:gn_pop":468,
    "qs_pg:name":"Div\u00e1ky",
    "qs_pg:name_adm0":"\u010cesk\u00e1 republika",
    "qs_pg:name_adm1":"Jihomoravsk\u00fd kraj",
    "qs_pg:photos":27,
    "qs_pg:photos_1k":5,
    "qs_pg:photos_9k":1,
    "qs_pg:photos_9r":2,
    "qs_pg:photos_all":27,
    "qs_pg:photos_sr":2,
    "qs_pg:pop_sr":2,
    "qs_pg:qs_pg_placetype":"locality",
    "qs_pg:qs_pg_placetype_gp":"Town",
    "qs_pg:woe_adm0":23424810,
    "woe:adm0_id":23424810,
    "woe:name_adm0":"\u010cesk\u00e1 republika",
    "woe:name_adm1":"Jihomoravsk\u00fd kraj",
    "woe:placetype":"Town",
    "wof:name":"Div\u00e1ky",
    "wof:placetype":"locality",
    "wof:population":468
},
  "geometry": {"coordinates":[16.79176,48.98869],"type":"Point"}
}