{
  "type": "Feature",
  "properties": {
    "iso:country":"CZ",
    "qs_pg:aaroncc":"CZ",
    "qs_pg:name":"Ko\u0159enov",
    "qs_pg:name_adm0":"\u010cesk\u00e1 republika",
    "qs_pg:name_adm1":"Libereck\u00fd kraj",
    "qs_pg:photos":278,
    "qs_pg:photos_1k":56,
    "qs_pg:photos_9k":4,
    "qs_pg:photos_9r":6,
    "qs_pg:photos_all":882,
    "qs_pg:photos_sr":5,
    "qs_pg:pop_sr":0,
    "qs_pg:qs_pg_placetype":"localadmin",
    "qs_pg:qs_pg_placetype_gp":"LocalAdmin",
    "qs_pg:woe_adm0":23424810,
    "woe:adm0_id":23424810,
    "woe:name_adm0":"\u010cesk\u00e1 republika",
    "woe:name_adm1":"Libereck\u00fd kraj",
    "woe:placetype":"LocalAdmin",
    "wof:name":"Ko\u0159enov",
    "wof:placetype":"localadmin"
},
  "geometry": {"coordinates":[15.362663,50.77023],"type":"Point"}
}