{
  "type": "Feature",
  "properties": {
    "gn:admin1_code":"79.0",
    "gn:admin2_code":"0312",
    "gn:asciiname":"Osek",
    "gn:country_code":"CZ",
    "gn:dem":716,
    "gn:feature_class":"P",
    "gn:feature_code":"PPL",
    "gn:name":"Osek",
    "gn:population":0,
    "gn:timezone":"Europe/Prague",
    "iso:country":"CZ",
    "wof:name":"Osek",
    "wof:placetype":"locality"
},
  "geometry": {"coordinates":[14.39097,48.76241],"type":"Point"}
}