{
  "type": "Feature",
  "properties": {
    "gn:admin1_code":"79.0",
    "gn:admin2_code":"0312",
    "gn:asciiname":"Osek",
    "gn:country_code":"CZ",
    "gn:dem":716,
    "gn:feature_class":"P",
    "gn:feature_code":"PPL",
    "gn:name":"Osek",
    "gn:population":0,
    "gn:timezone":"Europe/Prague",
    "iso:country":"CZ",
    "name:ceb_x_preferred":[
        "Osek"
    ],
    "name:ces_x_preferred":[
        "Osek"
    ],
    "name:deu_x_preferred":[
        "Osek"
    ],
    "name:fra_x_preferred":[
        "Osek"
    ],
    "name:hun_x_preferred":[
        "Osek"
    ],
    "name:ita_x_preferred":[
        "Osek"
    ],
    "name:nld_x_preferred":[
        "Osek"
    ],
    "name:oci_x_preferred":[
        "Osek"
    ],
    "name:pol_x_preferred":[
        "Osek"
    ],
    "name:ron_x_preferred":[
        "Osek"
    ],
    "name:slk_x_preferred":[
        "Osek"
    ],
    "name:slv_x_preferred":[
        "Osek"
    ],
    "name:srp_x_preferred":[
        "\u041e\u0441\u0435\u043a"
    ],
    "name:swe_x_preferred":[
        "Osek"
    ],
    "wof:name":"Osek",
    "wof:placetype":"locality"
},
  "geometry": {"coordinates":[14.39097,48.76241],"type":"Point"}
}