{
  "type": "Feature",
  "properties": {
    "iso:country":"CZ",
    "name:ceb_x_preferred":[
        "Hlinsko"
    ],
    "name:ces_x_preferred":[
        "Hlinsko"
    ],
    "name:epo_x_preferred":[
        "Hlinsko"
    ],
    "name:eus_x_preferred":[
        "Hlinsko"
    ],
    "name:fas_x_preferred":[
        "\u0647\u0644\u06cc\u0646\u0633\u06a9\u0648"
    ],
    "name:fra_x_preferred":[
        "Hlinsko"
    ],
    "name:hun_x_preferred":[
        "Hlinsko"
    ],
    "name:ita_x_preferred":[
        "Hlinsko"
    ],
    "name:lav_x_preferred":[
        "Hlinsko"
    ],
    "name:msa_x_preferred":[
        "Hlinsko"
    ],
    "name:nld_x_preferred":[
        "Hlinsko"
    ],
    "name:pol_x_preferred":[
        "Hlinsko"
    ],
    "name:por_x_preferred":[
        "Hlinsko"
    ],
    "name:rus_x_preferred":[
        "\u0413\u043b\u0438\u043d\u0441\u043a\u043e"
    ],
    "name:slk_x_preferred":[
        "Hlinsko"
    ],
    "name:spa_x_preferred":[
        "Hlinsko"
    ],
    "name:srp_x_preferred":[
        "\u0425\u043b\u0438\u043d\u0441\u043a\u043e"
    ],
    "name:vie_x_preferred":[
        "Hlinsko"
    ],
    "name:zho_x_preferred":[
        "\u8d6b\u6797\u65af\u79d1"
    ],
    "qs_pg:aaroncc":"CZ",
    "qs_pg:name":"Hlinsko",
    "qs_pg:name_adm0":"\u010cesk\u00e1 republika",
    "qs_pg:name_adm1":"Pardubick\u00fd kraj",
    "qs_pg:photos":45,
    "qs_pg:photos_1k":9,
    "qs_pg:photos_9k":1,
    "qs_pg:photos_9r":2,
    "qs_pg:photos_all":45,
    "qs_pg:photos_sr":2,
    "qs_pg:pop_sr":0,
    "qs_pg:qs_pg_placetype":"localadmin",
    "qs_pg:qs_pg_placetype_gp":"LocalAdmin",
    "qs_pg:woe_adm0":23424810,
    "woe:adm0_id":23424810,
    "woe:name_adm0":"\u010cesk\u00e1 republika",
    "woe:name_adm1":"Pardubick\u00fd kraj",
    "woe:placetype":"LocalAdmin",
    "wof:name":"Hlinsko",
    "wof:placetype":"localadmin"
},
  "geometry": {"coordinates":[15.90756,49.76213],"type":"Point"}
}