{
  "type": "Feature",
  "properties": {
    "gn:admin1_code":"89.0",
    "gn:admin2_code":"0422",
    "gn:asciiname":"Hradecna",
    "gn:country_code":"CZ",
    "gn:dem":552,
    "gn:feature_class":"P",
    "gn:feature_code":"PPL",
    "gn:name":"Hrade\u010dn\u00e1",
    "gn:population":0,
    "gn:timezone":"Europe/Prague",
    "iso:country":"CZ",
    "name:und_x_variant":[
        "Sperbersdorf",
        "Hrade\u010dn\u00e1"
    ],
    "wof:name":"Hradecna",
    "wof:placetype":"locality"
},
  "geometry": {"coordinates":[13.38456,50.49899],"type":"Point"}
}