{
  "type": "Feature",
  "properties": {
    "gn:admin1_code":"80",
    "gn:admin2_code":"0614",
    "gn:asciiname":"Tyn",
    "gn:country_code":"CZ",
    "gn:dem":456,
    "gn:feature_class":"P",
    "gn:feature_code":"PPL",
    "gn:name":"T\u00fdn",
    "gn:population":0,
    "gn:timezone":"Europe/Prague",
    "iso:country":"CZ",
    "wof:name":"Tyn",
    "wof:placetype":"locality"
},
  "geometry": {"coordinates":[15.87301,49.22444],"type":"Point"}
}