{
  "type": "Feature",
  "properties": {
    "gn:gn_country":"CZ",
    "gn:gn_fcode":"PPL",
    "gn:gn_pop":1004,
    "gn:population":1004,
    "iso:country":"CZ",
    "name:bul_x_preferred":[
        "\u0411\u0435\u0437\u0434\u0440\u0443\u0436\u0438\u0446\u0435"
    ],
    "name:chi_x_preferred":[
        "\u8c9d\u8332\u5fb7\u9b6f\u65e5\u91c7"
    ],
    "name:cze_x_preferred":[
        "Bezdru\u017eice"
    ],
    "name:dut_x_preferred":[
        "Bezdru\u017eice"
    ],
    "name:eng_x_preferred":[
        "Bezdru\u017eice"
    ],
    "name:fre_x_preferred":[
        "Bezdru\u017eice"
    ],
    "name:ger_x_preferred":[
        "Bezdru\u017eice"
    ],
    "name:hun_x_preferred":[
        "Bezdru\u017eice"
    ],
    "name:ita_x_preferred":[
        "Bezdru\u017eice"
    ],
    "name:may_x_preferred":[
        "Bezdru\u017eice"
    ],
    "name:nan_x_preferred":[
        "Bezdru\u017eice"
    ],
    "name:per_x_preferred":[
        "\u0628\u0632\u062f\u0631\u0648\u0698\u06cc\u062a\u0633\u0647"
    ],
    "name:pol_x_preferred":[
        "Bezdru\u017eice"
    ],
    "name:por_x_preferred":[
        "Bezdru\u017eice"
    ],
    "name:rup_x_preferred":[
        "Bezdru\u017eice"
    ],
    "name:rus_x_preferred":[
        "\u0411\u0435\u0437\u0434\u0440\u0443\u0436\u0438\u0446\u0435"
    ],
    "name:slo_x_preferred":[
        "Bezdru\u017eice"
    ],
    "name:srp_x_preferred":[
        "\u0411\u0435\u0437\u0434\u0440\u0443\u0436\u0438\u0446\u0435"
    ],
    "name:swe_x_preferred":[
        "Bezdru\u017eice"
    ],
    "name:tat_x_preferred":[
        "\u0411\u0435\u0437\u0434\u0440\u0443\u0436\u0438\u0442\u0441\u0435"
    ],
    "name:unk_x_variant":[
        "Weseritz"
    ],
    "name:vie_x_preferred":[
        "Bezdru\u017eice"
    ],
    "qs_pg:aaroncc":"CZ",
    "qs_pg:gn_country":"CZ",
    "qs_pg:gn_fcode":"PPL",
    "qs_pg:gn_pop":1004,
    "qs_pg:name":"Bezdru\u017eice",
    "qs_pg:name_adm0":"\u010cesk\u00e1 republika",
    "qs_pg:name_adm1":"Plze\u0148sk\u00fd kraj",
    "qs_pg:photos_9k":1,
    "qs_pg:photos_9r":1,
    "qs_pg:photos_all":6,
    "qs_pg:photos_sr":0,
    "qs_pg:pop_sr":3,
    "qs_pg:qs_pg_placetype":"locality",
    "qs_pg:qs_pg_placetype_gp":"Town",
    "qs_pg:woe_adm0":23424810,
    "woe:adm0_id":23424810,
    "woe:name_adm0":"\u010cesk\u00e1 republika",
    "woe:name_adm1":"Plze\u0148sk\u00fd kraj",
    "woe:placetype":"Town",
    "wof:name":"Bezdru\u017eice",
    "wof:placetype":"locality",
    "wof:population":1004
},
  "geometry": {"coordinates":[12.9711,49.90724],"type":"Point"}
}