{
  "type": "Feature",
  "properties": {
    "gn:country":"CZ",
    "gn:fcode":"PPL",
    "gn:population":1004,
    "iso:country":"CZ",
    "name:bul_x_preferred":[
        "\u0411\u0435\u0437\u0434\u0440\u0443\u0436\u0438\u0446\u0435"
    ],
    "name:cat_x_preferred":[
        "Bezdru\u017eice"
    ],
    "name:ceb_x_preferred":[
        "Bezdru\u017eice"
    ],
    "name:ces_x_preferred":[
        "Bezdru\u017eice"
    ],
    "name:deu_x_preferred":[
        "Bezdru\u017eice"
    ],
    "name:eng_x_preferred":[
        "Bezdru\u017eice"
    ],
    "name:epo_x_preferred":[
        "Bezdru\u017eice"
    ],
    "name:est_x_preferred":[
        "Bezdru\u017eice"
    ],
    "name:eus_x_preferred":[
        "Bezdru\u017eice"
    ],
    "name:fas_x_preferred":[
        "\u0628\u0632\u062f\u0631\u0648\u0698\u06cc\u062a\u0633\u0647"
    ],
    "name:fra_x_preferred":[
        "Bezdru\u017eice"
    ],
    "name:gle_x_preferred":[
        "Bezdru\u017eice"
    ],
    "name:hun_x_preferred":[
        "Bezdru\u017eice"
    ],
    "name:ita_x_preferred":[
        "Bezdru\u017eice"
    ],
    "name:lmo_x_preferred":[
        "Bezdru\u017eice"
    ],
    "name:msa_x_preferred":[
        "Bezdru\u017eice"
    ],
    "name:nan_x_preferred":[
        "Bezdru\u017eice"
    ],
    "name:nld_x_preferred":[
        "Bezdru\u017eice"
    ],
    "name:pol_x_preferred":[
        "Bezdru\u017eice"
    ],
    "name:por_x_preferred":[
        "Bezdru\u017eice"
    ],
    "name:rup_x_preferred":[
        "Bezdru\u017eice"
    ],
    "name:rus_x_preferred":[
        "\u0411\u0435\u0437\u0434\u0440\u0443\u0436\u0438\u0446\u0435"
    ],
    "name:slk_x_preferred":[
        "Bezdru\u017eice"
    ],
    "name:spa_x_preferred":[
        "Bezdru\u017eice"
    ],
    "name:srp_x_preferred":[
        "\u0411\u0435\u0437\u0434\u0440\u0443\u0436\u0438\u0446\u0435"
    ],
    "name:swe_x_preferred":[
        "Bezdru\u017eice"
    ],
    "name:tat_x_preferred":[
        "\u0411\u0435\u0437\u0434\u0440\u0443\u0436\u0438\u0442\u0441\u0435"
    ],
    "name:und_x_variant":[
        "Weseritz"
    ],
    "name:uzb_x_preferred":[
        "Bezdru\u017eice"
    ],
    "name:vie_x_preferred":[
        "Bezdru\u017eice"
    ],
    "name:zho_x_preferred":[
        "\u8c9d\u8332\u5fb7\u9b6f\u65e5\u91c7"
    ],
    "qs_pg:aaroncc":"CZ",
    "qs_pg:gn_country":"CZ",
    "qs_pg:gn_fcode":"PPL",
    "qs_pg:gn_pop":1004,
    "qs_pg:name":"Bezdru\u017eice",
    "qs_pg:name_adm0":"\u010cesk\u00e1 republika",
    "qs_pg:name_adm1":"Plze\u0148sk\u00fd kraj",
    "qs_pg:photos_9k":1,
    "qs_pg:photos_9r":1,
    "qs_pg:photos_all":6,
    "qs_pg:photos_sr":0,
    "qs_pg:pop_sr":3,
    "qs_pg:qs_pg_placetype":"locality",
    "qs_pg:qs_pg_placetype_gp":"Town",
    "qs_pg:woe_adm0":23424810,
    "woe:adm0_id":23424810,
    "woe:name_adm0":"\u010cesk\u00e1 republika",
    "woe:name_adm1":"Plze\u0148sk\u00fd kraj",
    "woe:placetype":"Town",
    "wof:name":"Bezdru\u017eice",
    "wof:placetype":"locality",
    "wof:population":1004
},
  "geometry": {"coordinates":[12.9711,49.90724],"type":"Point"}
}