{
  "type": "Feature",
  "properties": {
    "gn:admin1_code":"79.0",
    "gn:admin2_code":"0311",
    "gn:asciiname":"Hlinov",
    "gn:country_code":"CZ",
    "gn:dem":524,
    "gn:feature_class":"P",
    "gn:feature_code":"PPL",
    "gn:name":"Hl\u00ednov",
    "gn:population":0,
    "gn:timezone":"Europe/Prague",
    "iso:country":"CZ",
    "name:und_x_variant":[
        "Tonberg",
        "Hl\u00ednov"
    ],
    "wof:name":"Hlinov",
    "wof:placetype":"locality"
},
  "geometry": {"coordinates":[14.75088,48.7939],"type":"Point"}
}