{
  "type": "Feature",
  "properties": {
    "gn:admin1_code":"84.0",
    "gn:admin2_code":"0715",
    "gn:asciiname":"Klasterec",
    "gn:country_code":"CZ",
    "gn:dem":322,
    "gn:feature_class":"P",
    "gn:feature_code":"PPL",
    "gn:name":"Kl\u00e1\u0161terec",
    "gn:population":0,
    "gn:timezone":"Europe/Prague",
    "iso:country":"CZ",
    "wof:name":"Klasterec",
    "wof:placetype":"locality"
},
  "geometry": {"coordinates":[16.86547,49.95409],"type":"Point"}
}