{
  "type": "Feature",
  "properties": {
    "gn:gn_country":"CZ",
    "gn:gn_fcode":"PPL",
    "gn:gn_pop":417,
    "gn:population":417,
    "iso:country":"CZ",
    "name:ces_x_preferred":[
        "\u0160imonovice"
    ],
    "name:deu_x_preferred":[
        "\u0160imonovice"
    ],
    "name:eng_x_preferred":[
        "\u0160imonovice"
    ],
    "name:fas_x_preferred":[
        "\u0634\u06cc\u0645\u0648\u0646\u0648\u0648\u06cc\u062a\u0633\u0647"
    ],
    "name:fra_x_preferred":[
        "\u0160imonovice"
    ],
    "name:hun_x_preferred":[
        "\u0160imonovice"
    ],
    "name:ita_x_preferred":[
        "\u0160imonovice"
    ],
    "name:msa_x_preferred":[
        "\u0160imonovice"
    ],
    "name:nan_x_preferred":[
        "\u0160imonovice"
    ],
    "name:nld_x_preferred":[
        "\u0160imonovice"
    ],
    "name:pol_x_preferred":[
        "\u0160imonovice"
    ],
    "name:por_x_preferred":[
        "\u0160imonovice"
    ],
    "name:rup_x_preferred":[
        "\u0160imonovice"
    ],
    "name:slk_x_preferred":[
        "\u0160imonovice"
    ],
    "name:srp_x_preferred":[
        "\u0428\u0438\u043c\u043e\u043d\u043e\u0432\u0438\u0446\u0435"
    ],
    "name:swe_x_preferred":[
        "\u0160imonovice"
    ],
    "name:vie_x_preferred":[
        "\u0160imonovice"
    ],
    "qs_pg:aaroncc":"CZ",
    "qs_pg:gn_country":"CZ",
    "qs_pg:gn_fcode":"PPL",
    "qs_pg:gn_pop":417,
    "qs_pg:name":"\u00c5 imonovice",
    "qs_pg:name_adm0":"\u010cesk\u00e1 republika",
    "qs_pg:name_adm1":"Libereck\u00fd kraj",
    "qs_pg:photos_9r":0,
    "qs_pg:photos_sr":0,
    "qs_pg:pop_sr":2,
    "qs_pg:qs_pg_placetype":"locality",
    "qs_pg:qs_pg_placetype_gp":"Town",
    "qs_pg:woe_adm0":23424810,
    "woe:adm0_id":23424810,
    "woe:name_adm0":"\u010cesk\u00e1 republika",
    "woe:name_adm1":"Libereck\u00fd kraj",
    "woe:placetype":"Town",
    "wof:name":"\u00c5 imonovice",
    "wof:placetype":"locality",
    "wof:population":417
},
  "geometry": {"coordinates":[15.05262,50.70638],"type":"Point"}
}