{
  "type": "Feature",
  "properties": {
    "gn:admin1_code":"81.0",
    "gn:admin2_code":"0412",
    "gn:asciiname":"Pulovice",
    "gn:country_code":"CZ",
    "gn:dem":439,
    "gn:feature_class":"P",
    "gn:feature_code":"PPL",
    "gn:name":"Pulovice",
    "gn:population":0,
    "gn:timezone":"Europe/Prague",
    "iso:country":"CZ",
    "name:und_x_variant":[
        "Pullwitz",
        "Pulovice"
    ],
    "wof:name":"Pulovice",
    "wof:placetype":"locality"
},
  "geometry": {"coordinates":[12.9626,50.25287],"type":"Point"}
}