{
  "type": "Feature",
  "properties": {
    "gn:admin1_code":"88.0",
    "gn:admin2_code":"0204",
    "gn:asciiname":"Labut'",
    "gn:country_code":"CZ",
    "gn:dem":198,
    "gn:feature_class":"P",
    "gn:feature_code":"PPL",
    "gn:name":"Labu\u0165",
    "gn:population":0,
    "gn:timezone":"Europe/Prague",
    "iso:country":"CZ",
    "wof:name":"Labut'",
    "wof:placetype":"locality"
},
  "geometry": {"coordinates":[15.28037,50.03245],"type":"Point"}
}