{
  "type": "Feature",
  "properties": {
    "gn:gn_country":"CZ",
    "gn:gn_fcode":"PPL",
    "gn:gn_pop":307,
    "gn:population":307,
    "iso:country":"CZ",
    "name:ces_x_preferred":[
        "Dubi\u010dn\u00e9"
    ],
    "name:eng_x_preferred":[
        "Dubi\u010dn\u00e9"
    ],
    "name:fas_x_preferred":[
        "\u062f\u0648\u0628\u06cc\u062a\u0634\u0646\u0647"
    ],
    "name:fra_x_preferred":[
        "Dubi\u010dn\u00e9"
    ],
    "name:hun_x_preferred":[
        "Dubi\u010dn\u00e9"
    ],
    "name:ita_x_preferred":[
        "Dubi\u010dn\u00e9"
    ],
    "name:msa_x_preferred":[
        "Dubi\u010dn\u00e9"
    ],
    "name:nld_x_preferred":[
        "Dubi\u010dn\u00e9"
    ],
    "name:pol_x_preferred":[
        "Dubi\u010dn\u00e9"
    ],
    "name:por_x_preferred":[
        "Dubi\u010dn\u00e9"
    ],
    "name:slk_x_preferred":[
        "Dubi\u010dn\u00e9"
    ],
    "name:srp_x_preferred":[
        "\u0414\u0443\u0431\u0438\u0447\u043d\u0435"
    ],
    "name:swe_x_preferred":[
        "Dubi\u010dn\u00e9"
    ],
    "name:unk_x_variant":[
        "Dubiken"
    ],
    "name:vie_x_preferred":[
        "Dubi\u010dn\u00e9"
    ],
    "qs_pg:aaroncc":"CZ",
    "qs_pg:gn_country":"CZ",
    "qs_pg:gn_fcode":"PPL",
    "qs_pg:gn_pop":307,
    "qs_pg:name":"Dubi\u010dn\u00e9",
    "qs_pg:name_adm0":"\u010cesk\u00e1 republika",
    "qs_pg:name_adm1":"Jiho\u010desk\u00fd kraj",
    "qs_pg:photos_9r":0,
    "qs_pg:photos_sr":0,
    "qs_pg:pop_sr":2,
    "qs_pg:qs_pg_placetype":"locality",
    "qs_pg:qs_pg_placetype_gp":"Town",
    "qs_pg:woe_adm0":23424810,
    "woe:adm0_id":23424810,
    "woe:name_adm0":"\u010cesk\u00e1 republika",
    "woe:name_adm1":"Jiho\u010desk\u00fd kraj",
    "woe:placetype":"Town",
    "wof:name":"Dubi\u010dn\u00e9",
    "wof:placetype":"locality",
    "wof:population":307
},
  "geometry": {"coordinates":[14.53876,48.98107],"type":"Point"}
}