{
  "type": "Feature",
  "properties": {
    "gn:admin1_code":"79.0",
    "gn:admin2_code":"0312",
    "gn:asciiname":"Pihlov",
    "gn:country_code":"CZ",
    "gn:dem":750,
    "gn:feature_class":"P",
    "gn:feature_code":"PPL",
    "gn:name":"Pihlov",
    "gn:population":0,
    "gn:timezone":"Europe/Prague",
    "iso:country":"CZ",
    "name:und_x_variant":[
        "Pichlern",
        "Pihlov"
    ],
    "wof:name":"Pihlov",
    "wof:placetype":"locality"
},
  "geometry": {"coordinates":[14.01655,48.7786],"type":"Point"}
}