{
  "type": "Feature",
  "properties": {
    "gn:admin1_code":"87",
    "gn:admin2_code":"0325",
    "gn:asciiname":"Vrazne",
    "gn:country_code":"CZ",
    "gn:dem":474,
    "gn:feature_class":"P",
    "gn:feature_code":"PPL",
    "gn:name":"Vr\u00e1\u017en\u00e9",
    "gn:population":0,
    "gn:timezone":"Europe/Prague",
    "iso:country":"CZ",
    "wof:name":"Vrazne",
    "wof:placetype":"locality"
},
  "geometry": {"coordinates":[13.33188,49.94962],"type":"Point"}
}