{
  "type": "Feature",
  "properties": {
    "gn:admin1_code":"85.0",
    "gn:admin2_code":"0805",
    "gn:asciiname":"Destne",
    "gn:country_code":"CZ",
    "gn:dem":392,
    "gn:feature_class":"P",
    "gn:feature_code":"PPL",
    "gn:name":"De\u0161tn\u00e9",
    "gn:population":0,
    "gn:timezone":"Europe/Prague",
    "iso:country":"CZ",
    "name:und_x_variant":[
        "Dorfteschen",
        "De\u0161tn\u00e9"
    ],
    "wof:name":"Destne",
    "wof:placetype":"locality"
},
  "geometry": {"coordinates":[17.67987999999999,49.89548],"type":"Point"}
}