{
  "type": "Feature",
  "properties": {
    "gn:admin1_code":"89",
    "gn:admin2_code":"0423",
    "gn:asciiname":"Tetcineves",
    "gn:cc2":"CZ",
    "gn:country_code":"CZ",
    "gn:dem":207,
    "gn:feature_class":"P",
    "gn:feature_code":"PPL",
    "gn:name":"Tet\u010din\u011bves",
    "gn:population":0,
    "gn:timezone":"Europe/Prague",
    "iso:country":"CZ",
    "name:und_x_variant":[
        "Tetschendorf"
    ],
    "wof:name":"Tetcineves",
    "wof:placetype":"locality"
},
  "geometry": {"coordinates":[14.34677,50.56132],"type":"Point"}
}