{
  "type": "Feature",
  "properties": {
    "gn:admin1_code":"79",
    "gn:admin2_code":"0316",
    "gn:asciiname":"Vodnanske Svobodne Hory",
    "gn:country_code":"CZ",
    "gn:dem":518,
    "gn:feature_class":"P",
    "gn:feature_code":"PPL",
    "gn:name":"Vod\u0148ansk\u00e9 Svobodn\u00e9 Hory",
    "gn:population":0,
    "gn:timezone":"Europe/Prague",
    "iso:country":"CZ",
    "wof:name":"Vodnanske Svobodne Hory",
    "wof:placetype":"locality"
},
  "geometry": {"coordinates":[14.1233,49.1312],"type":"Point"}
}