{
  "type": "Feature",
  "properties": {
    "gn:admin1_code":"78",
    "gn:admin2_code":"0621",
    "gn:asciiname":"Vlkov",
    "gn:country_code":"CZ",
    "gn:dem":397,
    "gn:feature_class":"P",
    "gn:feature_code":"PPL",
    "gn:name":"Vlkov",
    "gn:population":0,
    "gn:timezone":"Europe/Prague",
    "iso:country":"CZ",
    "name:ceb_x_preferred":[
        "Vlkov"
    ],
    "name:ces_x_preferred":[
        "Vlkov"
    ],
    "name:deu_x_preferred":[
        "Vlkov"
    ],
    "name:fra_x_preferred":[
        "Vlkov"
    ],
    "name:ita_x_preferred":[
        "Vlkov"
    ],
    "name:nld_x_preferred":[
        "Vlkov"
    ],
    "name:pol_x_preferred":[
        "Vlkov"
    ],
    "name:slk_x_preferred":[
        "Vlkov"
    ],
    "name:srp_x_preferred":[
        "\u0412\u043b\u043a\u043e\u0432"
    ],
    "name:swe_x_preferred":[
        "Vlkov"
    ],
    "wof:name":"Vlkov",
    "wof:placetype":"locality"
},
  "geometry": {"coordinates":[16.52953,49.5849],"type":"Point"}
}