{
  "type": "Feature",
  "properties": {
    "gn:admin1_code":"78",
    "gn:admin2_code":"0621",
    "gn:asciiname":"Vlkov",
    "gn:country_code":"CZ",
    "gn:dem":397,
    "gn:feature_class":"P",
    "gn:feature_code":"PPL",
    "gn:name":"Vlkov",
    "gn:population":0,
    "gn:timezone":"Europe/Prague",
    "iso:country":"CZ",
    "wof:name":"Vlkov",
    "wof:placetype":"locality"
},
  "geometry": {"coordinates":[16.52953,49.5849],"type":"Point"}
}