{
  "type": "Feature",
  "properties": {
    "gn:gn_country":"CZ",
    "gn:gn_fcode":"PPL",
    "gn:gn_pop":268,
    "gn:population":268,
    "iso:country":"CZ",
    "name:ces_x_preferred":[
        "Libod\u0159ice"
    ],
    "name:eng_x_preferred":[
        "Libod\u0159ice"
    ],
    "name:fas_x_preferred":[
        "\u0644\u06cc\u0628\u0648\u062f\u0631\u06cc\u062a\u0633\u0647"
    ],
    "name:fra_x_preferred":[
        "Libod\u0159ice"
    ],
    "name:hun_x_preferred":[
        "Libod\u0159ice"
    ],
    "name:ita_x_preferred":[
        "Libod\u0159ice"
    ],
    "name:msa_x_preferred":[
        "Libod\u0159ice"
    ],
    "name:nld_x_preferred":[
        "Libod\u0159ice"
    ],
    "name:pol_x_preferred":[
        "Libod\u0159ice"
    ],
    "name:por_x_preferred":[
        "Libod\u0159ice"
    ],
    "name:slk_x_preferred":[
        "Libod\u0159ice"
    ],
    "name:srp_x_preferred":[
        "\u041b\u0438\u0431\u043e\u0434\u0440\u0438\u0446\u0435"
    ],
    "name:swe_x_preferred":[
        "Libod\u0159ice"
    ],
    "name:vie_x_preferred":[
        "Libod\u0159ice"
    ],
    "qs_pg:aaroncc":"CZ",
    "qs_pg:gn_country":"CZ",
    "qs_pg:gn_fcode":"PPL",
    "qs_pg:gn_pop":268,
    "qs_pg:name":"Libod\u0159ice",
    "qs_pg:name_adm0":"\u010cesk\u00e1 republika",
    "qs_pg:name_adm1":"St\u0159edo\u010desk\u00fd kraj",
    "qs_pg:photos_9k":1,
    "qs_pg:photos_9r":1,
    "qs_pg:photos_all":1,
    "qs_pg:photos_sr":0,
    "qs_pg:pop_sr":2,
    "qs_pg:qs_pg_placetype":"locality",
    "qs_pg:qs_pg_placetype_gp":"Town",
    "qs_pg:woe_adm0":23424810,
    "woe:adm0_id":23424810,
    "woe:name_adm0":"\u010cesk\u00e1 republika",
    "woe:name_adm1":"St\u0159edo\u010desk\u00fd kraj",
    "woe:placetype":"Town",
    "wof:name":"Libod\u0159ice",
    "wof:placetype":"locality",
    "wof:population":268
},
  "geometry": {"coordinates":[15.08828,50.00431],"type":"Point"}
}