{
  "type": "Feature",
  "properties": {
    "gn:admin1_code":"89",
    "gn:admin2_code":"0426",
    "gn:asciiname":"Tvrdin",
    "gn:cc2":"CZ",
    "gn:country_code":"CZ",
    "gn:dem":372,
    "gn:feature_class":"P",
    "gn:feature_code":"PPL",
    "gn:name":"Tvrd\u00edn",
    "gn:population":0,
    "gn:timezone":"Europe/Prague",
    "iso:country":"CZ",
    "name:und_x_variant":[
        "Twrdina"
    ],
    "wof:name":"Tvrdin",
    "wof:placetype":"locality"
},
  "geometry": {"coordinates":[13.80278,50.50251],"type":"Point"}
}