{
  "type": "Feature",
  "properties": {
    "iso:country":"CZ",
    "name:ceb_x_preferred":[
        "Milovice"
    ],
    "name:ces_x_preferred":[
        "Milovice"
    ],
    "name:deu_x_preferred":[
        "Milovice"
    ],
    "name:fra_x_preferred":[
        "Milovice"
    ],
    "name:ita_x_preferred":[
        "Milovice"
    ],
    "name:nld_x_preferred":[
        "Milovice"
    ],
    "name:slk_x_preferred":[
        "Milovice"
    ],
    "name:srp_x_preferred":[
        "\u041c\u0438\u043b\u043e\u0432\u0438\u0446\u0435"
    ],
    "name:swe_x_preferred":[
        "Milovice"
    ],
    "qs_pg:aaroncc":"CZ",
    "qs_pg:name":"Milovice",
    "qs_pg:name_adm0":"\u010cesk\u00e1 republika",
    "qs_pg:name_adm1":"St\u0159edo\u010desk\u00fd kraj",
    "qs_pg:photos":1,
    "qs_pg:photos_1k":1,
    "qs_pg:photos_9k":1,
    "qs_pg:photos_9r":4,
    "qs_pg:photos_all":202,
    "qs_pg:photos_sr":1,
    "qs_pg:pop_sr":0,
    "qs_pg:qs_pg_placetype":"localadmin",
    "qs_pg:qs_pg_placetype_gp":"LocalAdmin",
    "qs_pg:woe_adm0":23424810,
    "woe:adm0_id":23424810,
    "woe:name_adm0":"\u010cesk\u00e1 republika",
    "woe:name_adm1":"St\u0159edo\u010desk\u00fd kraj",
    "woe:placetype":"LocalAdmin",
    "wof:name":"Milovice",
    "wof:placetype":"localadmin"
},
  "geometry": {"coordinates":[14.908962,50.2416605],"type":"Point"}
}