{
  "type": "Feature",
  "properties": {
    "gn:admin1_code":"88",
    "gn:admin2_code":"0205",
    "gn:asciiname":"Svabinov",
    "gn:country_code":"CZ",
    "gn:dem":459,
    "gn:feature_class":"P",
    "gn:feature_code":"PPL",
    "gn:name":"\u0160v\u00e1b\u00ednov",
    "gn:population":0,
    "gn:timezone":"Europe/Prague",
    "iso:country":"CZ",
    "wof:name":"Svabinov",
    "wof:placetype":"locality"
},
  "geometry": {"coordinates":[15.18032,49.84654000000001],"type":"Point"}
}