{
  "type": "Feature",
  "properties": {
    "gn:gn_country":"CZ",
    "gn:gn_fcode":"PPL",
    "gn:gn_pop":167,
    "gn:population":167,
    "iso:country":"CZ",
    "name:ces_x_preferred":[
        "Libe\u017e"
    ],
    "name:eng_x_preferred":[
        "Libe\u017e"
    ],
    "name:fas_x_preferred":[
        "\u0644\u06cc\u0628\u0698"
    ],
    "name:fra_x_preferred":[
        "Libe\u017e"
    ],
    "name:hun_x_preferred":[
        "Libe\u017e"
    ],
    "name:ita_x_preferred":[
        "Libe\u017e"
    ],
    "name:msa_x_preferred":[
        "Libe\u017e"
    ],
    "name:nld_x_preferred":[
        "Libe\u017e"
    ],
    "name:pol_x_preferred":[
        "Libe\u017e"
    ],
    "name:por_x_preferred":[
        "Libe\u017e"
    ],
    "name:slk_x_preferred":[
        "Libe\u017e"
    ],
    "name:srp_x_preferred":[
        "\u041b\u0438\u0431\u0435\u0436"
    ],
    "name:swe_x_preferred":[
        "Libe\u017e"
    ],
    "name:vie_x_preferred":[
        "Libe\u017e"
    ],
    "qs_pg:aaroncc":"CZ",
    "qs_pg:gn_country":"CZ",
    "qs_pg:gn_fcode":"PPL",
    "qs_pg:gn_pop":167,
    "qs_pg:name":"Libe\u017e",
    "qs_pg:name_adm0":"\u010cesk\u00e1 republika",
    "qs_pg:name_adm1":"St\u0159edo\u010desk\u00fd kraj",
    "qs_pg:photos_9r":0,
    "qs_pg:photos_sr":0,
    "qs_pg:pop_sr":1,
    "qs_pg:qs_pg_placetype":"locality",
    "qs_pg:qs_pg_placetype_gp":"Town",
    "qs_pg:woe_adm0":23424810,
    "woe:adm0_id":23424810,
    "woe:name_adm0":"\u010cesk\u00e1 republika",
    "woe:name_adm1":"St\u0159edo\u010desk\u00fd kraj",
    "woe:placetype":"Town",
    "wof:name":"Libe\u017e",
    "wof:placetype":"locality",
    "wof:population":167
},
  "geometry": {"coordinates":[14.91677,49.75742],"type":"Point"}
}