{
  "type": "Feature",
  "properties": {
    "gn:country":"CZ",
    "gn:fcode":"PPL",
    "gn:population":123,
    "iso:country":"CZ",
    "name:azb_x_preferred":[
        "\u0633\u062a\u0631\u0627\u0646\u0646\u06cc"
    ],
    "name:ceb_x_preferred":[
        "Strann\u00fd"
    ],
    "name:ces_x_preferred":[
        "Strann\u00fd"
    ],
    "name:deu_x_preferred":[
        "Strann\u00fd"
    ],
    "name:eng_x_preferred":[
        "Strann\u00fd"
    ],
    "name:eus_x_preferred":[
        "Strann\u00fd"
    ],
    "name:fas_x_preferred":[
        "\u0633\u062a\u0631\u0627\u0646\u0646\u06cc"
    ],
    "name:fra_x_preferred":[
        "Strann\u00fd"
    ],
    "name:hun_x_preferred":[
        "Strann\u00fd"
    ],
    "name:ita_x_preferred":[
        "Strann\u00fd"
    ],
    "name:msa_x_preferred":[
        "Strann\u00fd"
    ],
    "name:nan_x_preferred":[
        "Strann\u00fd"
    ],
    "name:nld_x_preferred":[
        "Strann\u00fd"
    ],
    "name:oci_x_preferred":[
        "Strann\u00fd"
    ],
    "name:pol_x_preferred":[
        "Strann\u00fd"
    ],
    "name:por_x_preferred":[
        "Strann\u00fd"
    ],
    "name:slk_x_preferred":[
        "Strann\u00fd"
    ],
    "name:spa_x_preferred":[
        "Strann\u00fd"
    ],
    "name:srp_x_preferred":[
        "\u0421\u0442\u0440\u0430\u043d\u0438"
    ],
    "name:swe_x_preferred":[
        "Strann\u00fd"
    ],
    "name:vie_x_preferred":[
        "Strann\u00fd"
    ],
    "qs_pg:aaroncc":"CZ",
    "qs_pg:gn_country":"CZ",
    "qs_pg:gn_fcode":"PPL",
    "qs_pg:gn_pop":123,
    "qs_pg:name":"Strann\u00fd",
    "qs_pg:name_adm0":"\u010cesk\u00e1 republika",
    "qs_pg:name_adm1":"St\u0159edo\u010desk\u00fd kraj",
    "qs_pg:photos_9r":0,
    "qs_pg:photos_sr":0,
    "qs_pg:pop_sr":1,
    "qs_pg:qs_pg_placetype":"locality",
    "qs_pg:qs_pg_placetype_gp":"Town",
    "qs_pg:woe_adm0":23424810,
    "woe:adm0_id":23424810,
    "woe:name_adm0":"\u010cesk\u00e1 republika",
    "woe:name_adm1":"St\u0159edo\u010desk\u00fd kraj",
    "woe:placetype":"Town",
    "wof:name":"Strann\u00fd",
    "wof:placetype":"locality",
    "wof:population":123
},
  "geometry": {"coordinates":[14.49398,49.75375],"type":"Point"}
}