{
  "type": "Feature",
  "properties": {
    "gn:country":"CZ",
    "gn:fcode":"PPL",
    "gn:population":515,
    "iso:country":"CZ",
    "name:azb_x_preferred":[
        "\u0634\u0627\u0646\u0648\u0641"
    ],
    "name:cat_x_preferred":[
        "\u0160anov"
    ],
    "name:ceb_x_preferred":[
        "\u0160anov"
    ],
    "name:ces_x_preferred":[
        "\u0160anov"
    ],
    "name:che_x_preferred":[
        "\u0428\u0430\u043d\u043e\u0432"
    ],
    "name:deu_x_preferred":[
        "\u0160anov"
    ],
    "name:eng_x_preferred":[
        "\u0160anov"
    ],
    "name:epo_x_preferred":[
        "\u0160anov"
    ],
    "name:eus_x_preferred":[
        "\u0160anov"
    ],
    "name:fas_x_preferred":[
        "\u0634\u0627\u0646\u0648\u0641"
    ],
    "name:fra_x_preferred":[
        "\u0160anov"
    ],
    "name:gle_x_preferred":[
        "\u0160anov"
    ],
    "name:hun_x_preferred":[
        "\u0160anov"
    ],
    "name:ita_x_preferred":[
        "\u0160anov"
    ],
    "name:lmo_x_preferred":[
        "\u0160anov"
    ],
    "name:msa_x_preferred":[
        "\u0160anov"
    ],
    "name:nld_x_preferred":[
        "\u0160anov"
    ],
    "name:pol_x_preferred":[
        "\u0160anov"
    ],
    "name:por_x_preferred":[
        "\u0160anov"
    ],
    "name:rup_x_preferred":[
        "\u0160anov"
    ],
    "name:slk_x_preferred":[
        "\u0160anov"
    ],
    "name:spa_x_preferred":[
        "\u0160anov"
    ],
    "name:srp_x_preferred":[
        "\u0428\u0430\u043d\u043e\u0432"
    ],
    "name:swe_x_preferred":[
        "\u0160anov"
    ],
    "name:tat_x_preferred":[
        "\u0428\u0430\u043d\u043e\u0432"
    ],
    "name:vie_x_preferred":[
        "\u0160anov"
    ],
    "qs_pg:aaroncc":"CZ",
    "qs_pg:gn_country":"CZ",
    "qs_pg:gn_fcode":"PPL",
    "qs_pg:gn_pop":515,
    "qs_pg:name":"\u0160anov",
    "qs_pg:photos_9r":0,
    "qs_pg:photos_sr":0,
    "qs_pg:pop_sr":2,
    "qs_pg:qs_pg_placetype":"locality",
    "wof:name":"\u0160anov",
    "wof:placetype":"locality",
    "wof:population":515
},
  "geometry": {"coordinates":[17.8984,49.04546],"type":"Point"}
}