{
  "type": "Feature",
  "properties": {
    "gn:gn_country":"CZ",
    "gn:gn_fcode":"PPL",
    "gn:gn_pop":973,
    "gn:population":973,
    "iso:country":"CZ",
    "name:ces_x_preferred":[
        "Lib\u011bchov"
    ],
    "name:deu_x_preferred":[
        "Lib\u011bchov"
    ],
    "name:eng_x_preferred":[
        "Lib\u011bchov"
    ],
    "name:fas_x_preferred":[
        "\u0644\u06cc\u0628\u06cc\u062e\u0648\u0648"
    ],
    "name:fra_x_preferred":[
        "Lib\u011bchov"
    ],
    "name:hun_x_preferred":[
        "Lib\u011bchov"
    ],
    "name:ita_x_preferred":[
        "Lib\u011bchov"
    ],
    "name:msa_x_preferred":[
        "Lib\u011bchov"
    ],
    "name:nld_x_preferred":[
        "Lib\u011bchov"
    ],
    "name:pol_x_preferred":[
        "Lib\u011bchov"
    ],
    "name:por_x_preferred":[
        "Lib\u011bchov"
    ],
    "name:rup_x_preferred":[
        "Lib\u011bchov"
    ],
    "name:slk_x_preferred":[
        "Lib\u011bchov"
    ],
    "name:srp_x_preferred":[
        "\u041b\u0438\u0431\u0458\u0435\u0445\u043e\u0432"
    ],
    "name:swe_x_preferred":[
        "Lib\u011bchov"
    ],
    "name:tat_x_preferred":[
        "\u041b\u0438\u0431\u0435\u0445\u043e\u0432"
    ],
    "name:unk_x_variant":[
        "Liboch"
    ],
    "name:vie_x_preferred":[
        "Lib\u011bchov"
    ],
    "name:zho_x_preferred":[
        "\u5229\u5225\u970d\u592b"
    ],
    "qs_pg:aaroncc":"CZ",
    "qs_pg:gn_country":"CZ",
    "qs_pg:gn_fcode":"PPL",
    "qs_pg:gn_pop":973,
    "qs_pg:name":"Lib\u011bchov",
    "qs_pg:name_adm0":"\u010cesk\u00e1 republika",
    "qs_pg:name_adm1":"St\u0159edo\u010desk\u00fd kraj",
    "qs_pg:photos":14,
    "qs_pg:photos_1k":3,
    "qs_pg:photos_9k":1,
    "qs_pg:photos_9r":1,
    "qs_pg:photos_all":14,
    "qs_pg:photos_sr":1,
    "qs_pg:pop_sr":2,
    "qs_pg:qs_pg_placetype":"locality",
    "qs_pg:qs_pg_placetype_gp":"Town",
    "qs_pg:woe_adm0":23424810,
    "woe:adm0_id":23424810,
    "woe:name_adm0":"\u010cesk\u00e1 republika",
    "woe:name_adm1":"St\u0159edo\u010desk\u00fd kraj",
    "woe:placetype":"Town",
    "wof:name":"Lib\u011bchov",
    "wof:placetype":"locality",
    "wof:population":973
},
  "geometry": {"coordinates":[14.44675,50.40784],"type":"Point"}
}