{
  "type": "Feature",
  "properties": {
    "gn:admin1_code":"82.0",
    "gn:admin2_code":"0523",
    "gn:asciiname":"Janovicky",
    "gn:country_code":"CZ",
    "gn:dem":611,
    "gn:feature_class":"P",
    "gn:feature_code":"PPL",
    "gn:name":"Janovi\u010dky",
    "gn:population":0,
    "gn:timezone":"Europe/Prague",
    "iso:country":"CZ",
    "name:und_x_variant":[
        "Janovice",
        "Johannesberg",
        "Janovi\u010dky"
    ],
    "wof:name":"Janovicky",
    "wof:placetype":"locality"
},
  "geometry": {"coordinates":[16.36034,50.64054],"type":"Point"}
}