{
  "type": "Feature",
  "properties": {
    "gn:admin1_code":"88.0",
    "gn:admin2_code":"0205",
    "gn:asciiname":"Koukalka",
    "gn:country_code":"CZ",
    "gn:dem":230,
    "gn:feature_class":"P",
    "gn:feature_code":"PPL",
    "gn:name":"Koukalka",
    "gn:population":0,
    "gn:timezone":"Europe/Prague",
    "iso:country":"CZ",
    "wof:name":"Koukalka",
    "wof:placetype":"locality"
},
  "geometry": {"coordinates":[15.47336,49.97613],"type":"Point"}
}