{
  "type": "Feature",
  "properties": {
    "gn:admin1_code":"85.0",
    "gn:admin2_code":"0804",
    "gn:asciiname":"Pozaha",
    "gn:country_code":"CZ",
    "gn:dem":487,
    "gn:feature_class":"P",
    "gn:feature_code":"PPL",
    "gn:name":"Po\u017eaha",
    "gn:population":0,
    "gn:timezone":"Europe/Prague",
    "iso:country":"CZ",
    "wof:name":"Pozaha",
    "wof:placetype":"locality"
},
  "geometry": {"coordinates":[17.92441,49.7831],"type":"Point"}
}