{
  "type": "Feature",
  "properties": {
    "gn:country":"CZ",
    "gn:fcode":"PPL",
    "gn:population":190,
    "iso:country":"CZ",
    "name:azb_x_preferred":[
        "\u06a9\u0628\u0644\u0648\u0641"
    ],
    "name:bul_x_preferred":[
        "\u041a\u0435\u0431\u043b\u043e\u0432"
    ],
    "name:ceb_x_preferred":[
        "Keblov"
    ],
    "name:ces_x_preferred":[
        "Keblov"
    ],
    "name:eng_x_preferred":[
        "Keblov"
    ],
    "name:eus_x_preferred":[
        "Keblov"
    ],
    "name:fas_x_preferred":[
        "\u06a9\u0628\u0644\u0648\u0641"
    ],
    "name:fra_x_preferred":[
        "Keblov"
    ],
    "name:hun_x_preferred":[
        "Keblov"
    ],
    "name:ita_x_preferred":[
        "Keblov"
    ],
    "name:msa_x_preferred":[
        "Keblov"
    ],
    "name:nan_x_preferred":[
        "Keblov"
    ],
    "name:nld_x_preferred":[
        "Keblov"
    ],
    "name:oci_x_preferred":[
        "Keblov"
    ],
    "name:pol_x_preferred":[
        "Keblov"
    ],
    "name:por_x_preferred":[
        "Keblov"
    ],
    "name:rup_x_preferred":[
        "Keblov"
    ],
    "name:slk_x_preferred":[
        "Keblov"
    ],
    "name:spa_x_preferred":[
        "Keblov"
    ],
    "name:srp_x_preferred":[
        "\u041a\u0435\u0431\u043b\u043e\u0432"
    ],
    "name:swe_x_preferred":[
        "Keblov"
    ],
    "name:vie_x_preferred":[
        "Keblov"
    ],
    "qs_pg:aaroncc":"CZ",
    "qs_pg:gn_country":"CZ",
    "qs_pg:gn_fcode":"PPL",
    "qs_pg:gn_pop":190,
    "qs_pg:name":"Keblov",
    "qs_pg:name_adm0":"\u010cesk\u00e1 republika",
    "qs_pg:name_adm1":"St\u0159edo\u010desk\u00fd kraj",
    "qs_pg:photos_9r":0,
    "qs_pg:photos_sr":0,
    "qs_pg:pop_sr":1,
    "qs_pg:qs_pg_placetype":"locality",
    "qs_pg:qs_pg_placetype_gp":"Town",
    "qs_pg:woe_adm0":23424810,
    "woe:adm0_id":23424810,
    "woe:name_adm0":"\u010cesk\u00e1 republika",
    "woe:name_adm1":"St\u0159edo\u010desk\u00fd kraj",
    "woe:placetype":"Town",
    "wof:name":"Keblov",
    "wof:placetype":"locality",
    "wof:population":190
},
  "geometry": {"coordinates":[15.07189,49.67765],"type":"Point"}
}