{
  "type": "Feature",
  "properties": {
    "gn:country":"CZ",
    "gn:fcode":"PPL",
    "gn:population":78,
    "iso:country":"CZ",
    "name:azb_x_preferred":[
        "\u0646\u0647\u0648\u062f\u06cc\u0648"
    ],
    "name:ces_x_preferred":[
        "Nehodiv"
    ],
    "name:deu_x_preferred":[
        "Nehodiv"
    ],
    "name:eng_x_preferred":[
        "Nehodiv"
    ],
    "name:eus_x_preferred":[
        "Nehodiv"
    ],
    "name:fas_x_preferred":[
        "\u0646\u0647\u0648\u062f\u06cc\u0648"
    ],
    "name:fra_x_preferred":[
        "Nehodiv"
    ],
    "name:hun_x_preferred":[
        "Nehodiv"
    ],
    "name:ita_x_preferred":[
        "Nehodiv"
    ],
    "name:msa_x_preferred":[
        "Nehodiv"
    ],
    "name:nan_x_preferred":[
        "Nehodiv"
    ],
    "name:nld_x_preferred":[
        "Nehodiv"
    ],
    "name:pol_x_preferred":[
        "Nehodiv"
    ],
    "name:por_x_preferred":[
        "Nehodiv"
    ],
    "name:slk_x_preferred":[
        "Nehodiv"
    ],
    "name:spa_x_preferred":[
        "Nehodiv"
    ],
    "name:srp_x_preferred":[
        "\u041d\u0435\u0445\u043e\u0434\u0438\u0432"
    ],
    "name:vie_x_preferred":[
        "Nehodiv"
    ],
    "qs_pg:aaroncc":"CZ",
    "qs_pg:gn_country":"CZ",
    "qs_pg:gn_fcode":"PPL",
    "qs_pg:gn_pop":78,
    "qs_pg:name":"Nehodiv",
    "qs_pg:name_adm0":"\u010cesk\u00e1 republika",
    "qs_pg:name_adm1":"Plze\u0148sk\u00fd kraj",
    "qs_pg:photos_9r":0,
    "qs_pg:photos_sr":0,
    "qs_pg:pop_sr":1,
    "qs_pg:qs_pg_placetype":"locality",
    "qs_pg:qs_pg_placetype_gp":"Town",
    "qs_pg:woe_adm0":23424810,
    "woe:adm0_id":23424810,
    "woe:name_adm0":"\u010cesk\u00e1 republika",
    "woe:name_adm1":"Plze\u0148sk\u00fd kraj",
    "woe:placetype":"Town",
    "wof:name":"Nehodiv",
    "wof:placetype":"locality",
    "wof:population":78
},
  "geometry": {"coordinates":[13.55636,49.41075],"type":"Point"}
}