{
  "type": "Feature",
  "properties": {
    "gn:country":"CZ",
    "gn:fcode":"PPL",
    "gn:population":189,
    "iso:country":"CZ",
    "name:azb_x_preferred":[
        "\u06a9\u0631\u06cc\u0645\u0648\u0648"
    ],
    "name:cat_x_preferred":[
        "K\u0159imov"
    ],
    "name:ceb_x_preferred":[
        "K\u0159imov"
    ],
    "name:ces_x_preferred":[
        "K\u0159imov"
    ],
    "name:che_x_preferred":[
        "\u041a\u0440\u0436\u0438\u043c\u043e\u0432"
    ],
    "name:deu_x_preferred":[
        "K\u0159imov"
    ],
    "name:eng_x_preferred":[
        "K\u0159imov"
    ],
    "name:epo_x_preferred":[
        "K\u0159imov"
    ],
    "name:eus_x_preferred":[
        "K\u0159imov"
    ],
    "name:fas_x_preferred":[
        "\u06a9\u0631\u06cc\u0645\u0648\u0648"
    ],
    "name:fra_x_preferred":[
        "K\u0159imov"
    ],
    "name:gle_x_preferred":[
        "K\u0159imov"
    ],
    "name:hun_x_preferred":[
        "K\u0159imov"
    ],
    "name:ita_x_preferred":[
        "K\u0159imov"
    ],
    "name:lmo_x_preferred":[
        "K\u0159imov"
    ],
    "name:msa_x_preferred":[
        "K\u0159imov"
    ],
    "name:nan_x_preferred":[
        "K\u0159imov"
    ],
    "name:nld_x_preferred":[
        "K\u0159imov"
    ],
    "name:pol_x_preferred":[
        "K\u0159imov"
    ],
    "name:por_x_preferred":[
        "K\u0159imov"
    ],
    "name:slk_x_preferred":[
        "K\u0159imov"
    ],
    "name:spa_x_preferred":[
        "K\u0159imov"
    ],
    "name:srp_x_preferred":[
        "\u041a\u0440\u0438\u043c\u043e\u0432"
    ],
    "name:swe_x_preferred":[
        "K\u0159imov"
    ],
    "name:tat_x_preferred":[
        "\u041a\u0440\u0436\u0438\u043c\u043e\u0432"
    ],
    "name:und_x_variant":[
        "Krima"
    ],
    "name:vie_x_preferred":[
        "K\u0159imov"
    ],
    "qs_pg:aaroncc":"CZ",
    "qs_pg:gn_country":"CZ",
    "qs_pg:gn_fcode":"PPL",
    "qs_pg:gn_pop":189,
    "qs_pg:name":"K\u0159imov",
    "qs_pg:name_adm0":"\u010cesk\u00e1 republika",
    "qs_pg:name_adm1":"\u00dasteck\u00fd kraj",
    "qs_pg:photos_9k":1,
    "qs_pg:photos_9r":1,
    "qs_pg:photos_all":1,
    "qs_pg:photos_sr":0,
    "qs_pg:pop_sr":1,
    "qs_pg:qs_pg_placetype":"locality",
    "qs_pg:qs_pg_placetype_gp":"Town",
    "qs_pg:woe_adm0":23424810,
    "woe:adm0_id":23424810,
    "woe:name_adm0":"\u010cesk\u00e1 republika",
    "woe:name_adm1":"\u00dasteck\u00fd kraj",
    "woe:placetype":"Town",
    "wof:name":"K\u0159imov",
    "wof:placetype":"locality",
    "wof:population":189
},
  "geometry": {"coordinates":[13.30147,50.48602],"type":"Point"}
}