{
  "type": "Feature",
  "properties": {
    "iso:country":"CZ",
    "name:azb_x_preferred":[
        "\u062f\u0648\u0628\u0631\u0648\u0648\u06cc\u0632"
    ],
    "name:ceb_x_preferred":[
        "Dobrov\u00edz"
    ],
    "name:ces_x_preferred":[
        "Dobrov\u00edz"
    ],
    "name:ell_x_preferred":[
        "\u039d\u03c4\u03bf\u03bc\u03c0\u03c1\u03bf\u03b2\u03af\u03b6"
    ],
    "name:eus_x_preferred":[
        "Dobrov\u00edz"
    ],
    "name:fas_x_preferred":[
        "\u062f\u0648\u0628\u0631\u0648\u0648\u06cc\u0632"
    ],
    "name:fra_x_preferred":[
        "Dobrov\u00edz"
    ],
    "name:hun_x_preferred":[
        "Dobrov\u00edz"
    ],
    "name:ita_x_preferred":[
        "Dobrov\u00edz"
    ],
    "name:msa_x_preferred":[
        "Dobrov\u00edz"
    ],
    "name:nld_x_preferred":[
        "Dobrov\u00edz"
    ],
    "name:pol_x_preferred":[
        "Dobrov\u00edz"
    ],
    "name:por_x_preferred":[
        "Dobrov\u00edz"
    ],
    "name:rus_x_preferred":[
        "\u0414\u043e\u0431\u0440\u043e\u0432\u0438\u0437"
    ],
    "name:slk_x_preferred":[
        "Dobrov\u00edz"
    ],
    "name:spa_x_preferred":[
        "Dobrov\u00edz"
    ],
    "name:srp_x_preferred":[
        "\u0414\u043e\u0431\u0440\u043e\u0432\u0438\u0437"
    ],
    "name:swe_x_preferred":[
        "Dobrov\u00edz"
    ],
    "name:vie_x_preferred":[
        "Dobrov\u00edz"
    ],
    "qs_pg:aaroncc":"CZ",
    "qs_pg:name":"Dobrov\u00edz",
    "qs_pg:name_adm0":"\u010cesk\u00e1 republika",
    "qs_pg:name_adm1":"St\u0159edo\u010desk\u00fd kraj",
    "qs_pg:photos":1,
    "qs_pg:photos_1k":1,
    "qs_pg:photos_9k":1,
    "qs_pg:photos_9r":1,
    "qs_pg:photos_all":1,
    "qs_pg:photos_sr":1,
    "qs_pg:pop_sr":0,
    "qs_pg:qs_pg_placetype":"localadmin",
    "qs_pg:qs_pg_placetype_gp":"LocalAdmin",
    "qs_pg:woe_adm0":23424810,
    "woe:adm0_id":23424810,
    "woe:name_adm0":"\u010cesk\u00e1 republika",
    "woe:name_adm1":"St\u0159edo\u010desk\u00fd kraj",
    "woe:placetype":"LocalAdmin",
    "wof:name":"Dobrov\u00edz",
    "wof:placetype":"localadmin"
},
  "geometry": {"coordinates":[14.222016,50.106838],"type":"Point"}
}