{
  "type": "Feature",
  "properties": {
    "gn:country":"CZ",
    "gn:fcode":"PPL",
    "gn:population":156,
    "iso:country":"CZ",
    "name:azb_x_preferred":[
        "\u0628\u06cc\u0647\u0627\u0631\u0648\u0648"
    ],
    "name:ceb_x_preferred":[
        "B\u011bha\u0159ov"
    ],
    "name:ces_x_preferred":[
        "B\u011bha\u0159ov"
    ],
    "name:deu_x_preferred":[
        "B\u011bha\u0159ov"
    ],
    "name:eng_x_preferred":[
        "B\u011bha\u0159ov"
    ],
    "name:eus_x_preferred":[
        "B\u011bha\u0159ov"
    ],
    "name:fas_x_preferred":[
        "\u0628\u06cc\u0647\u0627\u0631\u0648\u0648"
    ],
    "name:fra_x_preferred":[
        "B\u011bha\u0159ov"
    ],
    "name:hun_x_preferred":[
        "B\u011bha\u0159ov"
    ],
    "name:ita_x_preferred":[
        "B\u011bha\u0159ov"
    ],
    "name:msa_x_preferred":[
        "B\u011bha\u0159ov"
    ],
    "name:nan_x_preferred":[
        "B\u011bha\u0159ov"
    ],
    "name:nld_x_preferred":[
        "B\u011bha\u0159ov"
    ],
    "name:pol_x_preferred":[
        "B\u011bha\u0159ov"
    ],
    "name:por_x_preferred":[
        "B\u011bha\u0159ov"
    ],
    "name:rus_x_preferred":[
        "\u0411\u0435\u0433\u0430\u0440\u0436\u043e\u0432"
    ],
    "name:slk_x_preferred":[
        "B\u011bha\u0159ov"
    ],
    "name:spa_x_preferred":[
        "B\u011bha\u0159ov"
    ],
    "name:srp_x_preferred":[
        "\u0411\u0458\u0435\u0445\u0430\u0440\u0436\u043e\u0432"
    ],
    "name:swe_x_preferred":[
        "B\u011bha\u0159ov"
    ],
    "name:vie_x_preferred":[
        "B\u011bha\u0159ov"
    ],
    "qs_pg:aaroncc":"CZ",
    "qs_pg:gn_country":"CZ",
    "qs_pg:gn_fcode":"PPL",
    "qs_pg:gn_pop":156,
    "qs_pg:name":"B\u011bha\u0159ov",
    "qs_pg:name_adm0":"\u010cesk\u00e1 republika",
    "qs_pg:name_adm1":"Plze\u0148sk\u00fd kraj",
    "qs_pg:photos_9k":1,
    "qs_pg:photos_9r":1,
    "qs_pg:photos_all":2,
    "qs_pg:photos_sr":0,
    "qs_pg:pop_sr":1,
    "qs_pg:qs_pg_placetype":"locality",
    "qs_pg:qs_pg_placetype_gp":"Town",
    "qs_pg:woe_adm0":23424810,
    "woe:adm0_id":23424810,
    "woe:name_adm0":"\u010cesk\u00e1 republika",
    "woe:name_adm1":"Plze\u0148sk\u00fd kraj",
    "woe:placetype":"Town",
    "wof:name":"B\u011bha\u0159ov",
    "wof:placetype":"locality",
    "wof:population":156
},
  "geometry": {"coordinates":[13.16018,49.34477],"type":"Point"}
}