{
  "type": "Feature",
  "properties": {
    "gn:admin1_code":"81.0",
    "gn:admin2_code":"0412",
    "gn:asciiname":"Doupovske Mezilesi",
    "gn:country_code":"CZ",
    "gn:dem":865,
    "gn:feature_class":"P",
    "gn:feature_code":"PPL",
    "gn:name":"Doupovsk\u00e9 Meziles\u00ed",
    "gn:population":0,
    "gn:timezone":"Europe/Prague",
    "iso:country":"CZ",
    "name:und_x_variant":[
        "Olitzhaus",
        "Doupovsk\u00e9 Meziles\u00ed"
    ],
    "wof:name":"Doupovske Mezilesi",
    "wof:placetype":"locality"
},
  "geometry": {"coordinates":[13.08333,50.21667],"type":"Point"}
}