{
  "type": "Feature",
  "properties": {
    "gn:country":"CZ",
    "gn:fcode":"PPL",
    "gn:population":648,
    "iso:country":"CZ",
    "name:ceb_x_preferred":[
        "Slapy"
    ],
    "name:ces_x_preferred":[
        "Slapy"
    ],
    "name:deu_x_preferred":[
        "Slapy nad Vltavou"
    ],
    "name:deu_x_variant":[
        "Slapy"
    ],
    "name:epo_x_preferred":[
        "Slapy"
    ],
    "name:fra_x_preferred":[
        "Slapy"
    ],
    "name:hun_x_preferred":[
        "Slapy"
    ],
    "name:ita_x_preferred":[
        "Slapy"
    ],
    "name:nld_x_preferred":[
        "Slapy"
    ],
    "name:slk_x_preferred":[
        "Slapy"
    ],
    "name:srp_x_preferred":[
        "\u0421\u043b\u0430\u043f\u0438"
    ],
    "name:swe_x_preferred":[
        "Slapy"
    ],
    "name:und_x_variant":[
        "Slap"
    ],
    "qs_pg:aaroncc":"CZ",
    "qs_pg:gn_country":"CZ",
    "qs_pg:gn_fcode":"PPL",
    "qs_pg:gn_pop":648,
    "qs_pg:name":"Slapy",
    "qs_pg:name_adm0":"\u010cesk\u00e1 republika",
    "qs_pg:name_adm1":"St\u0159edo\u010desk\u00fd kraj",
    "qs_pg:photos":40,
    "qs_pg:photos_1k":8,
    "qs_pg:photos_9k":1,
    "qs_pg:photos_9r":2,
    "qs_pg:photos_all":40,
    "qs_pg:photos_sr":2,
    "qs_pg:pop_sr":2,
    "qs_pg:qs_pg_placetype":"locality",
    "qs_pg:qs_pg_placetype_gp":"Town",
    "qs_pg:woe_adm0":23424810,
    "woe:adm0_id":23424810,
    "woe:name_adm0":"\u010cesk\u00e1 republika",
    "woe:name_adm1":"St\u0159edo\u010desk\u00fd kraj",
    "woe:placetype":"Town",
    "wof:name":"Slapy",
    "wof:placetype":"locality",
    "wof:population":648
},
  "geometry": {"coordinates":[14.39612,49.81531],"type":"Point"}
}