{
  "type": "Feature",
  "properties": {
    "gn:admin1_code":"84.0",
    "gn:admin2_code":"0712",
    "gn:asciiname":"Karlov",
    "gn:country_code":"CZ",
    "gn:dem":576,
    "gn:feature_class":"P",
    "gn:feature_code":"PPL",
    "gn:name":"Karlov",
    "gn:population":0,
    "gn:timezone":"Europe/Prague",
    "iso:country":"CZ",
    "name:und_x_variant":[
        "Karle"
    ],
    "wof:name":"Karlov",
    "wof:placetype":"locality"
},
  "geometry": {"coordinates":[17.24459,49.81561],"type":"Point"}
}