{
  "type": "Feature",
  "properties": {
    "gn:admin1_code":"84.0",
    "gn:admin2_code":"0712",
    "gn:asciiname":"Karlov",
    "gn:country_code":"CZ",
    "gn:dem":576,
    "gn:feature_class":"P",
    "gn:feature_code":"PPL",
    "gn:name":"Karlov",
    "gn:population":0,
    "gn:timezone":"Europe/Prague",
    "iso:country":"CZ",
    "name:ces_x_preferred":[
        "Karlov"
    ],
    "name:deu_x_preferred":[
        "Karlov"
    ],
    "name:fra_x_preferred":[
        "Karlov"
    ],
    "name:nld_x_preferred":[
        "Karlov"
    ],
    "name:rus_x_preferred":[
        "\u041a\u0430\u0440\u043b\u043e\u0432"
    ],
    "name:slk_x_preferred":[
        "Karlov"
    ],
    "name:slv_x_preferred":[
        "Karlov"
    ],
    "name:ukr_x_preferred":[
        "\u041a\u0430\u0440\u043b\u043e\u0432"
    ],
    "name:und_x_variant":[
        "Karle"
    ],
    "wof:name":"Karlov",
    "wof:placetype":"locality"
},
  "geometry": {"coordinates":[17.24459,49.81561],"type":"Point"}
}