{
  "type": "Feature",
  "properties": {
    "gn:gn_country":"CZ",
    "gn:gn_fcode":"PPL",
    "gn:gn_pop":425,
    "gn:population":425,
    "iso:country":"CZ",
    "name:ceb_x_preferred":[
        "V\u00edtanov"
    ],
    "name:ces_x_preferred":[
        "V\u00edtanov"
    ],
    "name:eng_x_preferred":[
        "V\u00edtanov"
    ],
    "name:epo_x_preferred":[
        "V\u00edtanov"
    ],
    "name:eus_x_preferred":[
        "V\u00edtanov"
    ],
    "name:fra_x_preferred":[
        "V\u00edtanov"
    ],
    "name:hun_x_preferred":[
        "V\u00edtanov"
    ],
    "name:ita_x_preferred":[
        "V\u00edtanov"
    ],
    "name:msa_x_preferred":[
        "V\u00edtanov"
    ],
    "name:nan_x_preferred":[
        "V\u00edtanov"
    ],
    "name:nld_x_preferred":[
        "V\u00edtanov"
    ],
    "name:pol_x_preferred":[
        "V\u00edtanov"
    ],
    "name:por_x_preferred":[
        "V\u00edtanov"
    ],
    "name:rup_x_preferred":[
        "V\u00edtanov"
    ],
    "name:slk_x_preferred":[
        "V\u00edtanov"
    ],
    "name:spa_x_preferred":[
        "V\u00edtanov"
    ],
    "name:srp_x_preferred":[
        "\u0412\u0438\u0442\u0430\u043d\u043e\u0432"
    ],
    "name:swe_x_preferred":[
        "V\u00edtanov"
    ],
    "name:vie_x_preferred":[
        "V\u00edtanov"
    ],
    "qs_pg:aaroncc":"CZ",
    "qs_pg:gn_country":"CZ",
    "qs_pg:gn_fcode":"PPL",
    "qs_pg:gn_pop":425,
    "qs_pg:name":"V\u00edtanov",
    "qs_pg:name_adm0":"\u010cesk\u00e1 republika",
    "qs_pg:name_adm1":"Pardubick\u00fd kraj",
    "qs_pg:photos_9r":0,
    "qs_pg:photos_sr":0,
    "qs_pg:pop_sr":2,
    "qs_pg:qs_pg_placetype":"locality",
    "qs_pg:qs_pg_placetype_gp":"Town",
    "qs_pg:woe_adm0":23424810,
    "woe:adm0_id":23424810,
    "woe:name_adm0":"\u010cesk\u00e1 republika",
    "woe:name_adm1":"Pardubick\u00fd kraj",
    "woe:placetype":"Town",
    "wof:name":"V\u00edtanov",
    "wof:placetype":"locality",
    "wof:population":425
},
  "geometry": {"coordinates":[15.88172,49.74909],"type":"Point"}
}