{
  "type": "Feature",
  "properties": {
    "gn:country":"CZ",
    "gn:fcode":"PPL",
    "gn:population":187,
    "iso:country":"CZ",
    "name:azb_x_preferred":[
        "\u0631\u0627\u06a9\u0648\u0648\u0627 \u0648 \u06a9\u0648\u0646\u06cc\u062a\u0633\u0647"
    ],
    "name:ceb_x_preferred":[
        "Rakov\u00e1 u Konice"
    ],
    "name:ces_x_preferred":[
        "Rakov\u00e1 u Konice"
    ],
    "name:deu_x_preferred":[
        "Rakov\u00e1 u Konice"
    ],
    "name:eng_x_preferred":[
        "Rakov\u00e1 u Konice"
    ],
    "name:eus_x_preferred":[
        "Rakov\u00e1 u Konice"
    ],
    "name:fas_x_preferred":[
        "\u0631\u0627\u06a9\u0648\u0648\u0627 \u0648 \u06a9\u0648\u0646\u06cc\u062a\u0633\u0647"
    ],
    "name:fra_x_preferred":[
        "Rakov\u00e1 u Konice"
    ],
    "name:hun_x_preferred":[
        "Rakov\u00e1 u Konice"
    ],
    "name:ita_x_preferred":[
        "Rakov\u00e1 u Konice"
    ],
    "name:msa_x_preferred":[
        "Rakov\u00e1 u Konice"
    ],
    "name:nan_x_preferred":[
        "Rakov\u00e1 u Konice"
    ],
    "name:nld_x_preferred":[
        "Rakov\u00e1 u Konice"
    ],
    "name:pol_x_preferred":[
        "Rakov\u00e1 u Konice"
    ],
    "name:por_x_preferred":[
        "Rakov\u00e1 u Konice"
    ],
    "name:rup_x_preferred":[
        "Rakov\u00e1 u Konice"
    ],
    "name:slk_x_preferred":[
        "Rakov\u00e1 u Konice"
    ],
    "name:spa_x_preferred":[
        "Rakov\u00e1 u Konice"
    ],
    "name:srp_x_preferred":[
        "\u0420\u0430\u043a\u043e\u0432\u0430 \u0443 \u041a\u043e\u045a\u0438\u0446\u0438"
    ],
    "name:swe_x_preferred":[
        "Rakov\u00e1 u Konice"
    ],
    "name:vie_x_preferred":[
        "Rakov\u00e1 u Konice"
    ],
    "qs_pg:aaroncc":"CZ",
    "qs_pg:gn_country":"CZ",
    "qs_pg:gn_fcode":"PPL",
    "qs_pg:gn_pop":187,
    "qs_pg:name":"Rakov\u00e1 u Konice",
    "qs_pg:name_adm0":"\u010cesk\u00e1 republika",
    "qs_pg:name_adm1":"Olomouck\u00fd kraj",
    "qs_pg:photos_9r":0,
    "qs_pg:photos_sr":0,
    "qs_pg:pop_sr":1,
    "qs_pg:qs_pg_placetype":"locality",
    "qs_pg:qs_pg_placetype_gp":"Town",
    "qs_pg:woe_adm0":23424810,
    "woe:adm0_id":23424810,
    "woe:name_adm0":"\u010cesk\u00e1 republika",
    "woe:name_adm1":"Olomouck\u00fd kraj",
    "woe:placetype":"Town",
    "wof:name":"Rakov\u00e1 u Konice",
    "wof:placetype":"locality",
    "wof:population":187
},
  "geometry": {"coordinates":[16.95082,49.60725],"type":"Point"}
}