{
  "type": "Feature",
  "properties": {
    "gn:country":"CZ",
    "gn:fcode":"PPL",
    "gn:population":274,
    "iso:country":"CZ",
    "name:azb_x_preferred":[
        "\u062f\u0644\u0648\u0648\u0647\u0647"
    ],
    "name:cat_x_preferred":[
        "Dlouh\u00e9"
    ],
    "name:ceb_x_preferred":[
        "Dlouh\u00e9"
    ],
    "name:ces_x_preferred":[
        "Dlouh\u00e9"
    ],
    "name:che_x_preferred":[
        "\u0414\u043b\u043e\u0443\u0433\u0435"
    ],
    "name:deu_x_preferred":[
        "Dlouh\u00e9"
    ],
    "name:eng_x_preferred":[
        "Dlouh\u00e9"
    ],
    "name:epo_x_preferred":[
        "Dlouh\u00e9"
    ],
    "name:eus_x_preferred":[
        "Dlouh\u00e9"
    ],
    "name:fas_x_preferred":[
        "\u062f\u0644\u0648\u0648\u0647\u0647"
    ],
    "name:fra_x_preferred":[
        "Dlouh\u00e9"
    ],
    "name:gle_x_preferred":[
        "Dlouh\u00e9"
    ],
    "name:hun_x_preferred":[
        "Dlouh\u00e9"
    ],
    "name:ita_x_preferred":[
        "Dlouh\u00e9"
    ],
    "name:lmo_x_preferred":[
        "Dlouh\u00e9"
    ],
    "name:msa_x_preferred":[
        "Dlouh\u00e9"
    ],
    "name:nan_x_preferred":[
        "Dlouh\u00e9"
    ],
    "name:nld_x_preferred":[
        "Dlouh\u00e9"
    ],
    "name:pol_x_preferred":[
        "Dlouh\u00e9"
    ],
    "name:por_x_preferred":[
        "Dlouh\u00e9"
    ],
    "name:slk_x_preferred":[
        "Dlouh\u00e9"
    ],
    "name:spa_x_preferred":[
        "Dlouh\u00e9"
    ],
    "name:swe_x_preferred":[
        "Dlouh\u00e9"
    ],
    "name:tat_x_preferred":[
        "\u0414\u043b\u043e\u0443\u0433\u0435"
    ],
    "name:vie_x_preferred":[
        "Dlouh\u00e9"
    ],
    "qs_pg:aaroncc":"CZ",
    "qs_pg:gn_country":"CZ",
    "qs_pg:gn_fcode":"PPL",
    "qs_pg:gn_pop":274,
    "qs_pg:name":"Dlouh\u00e9",
    "qs_pg:name_adm0":"\u010cesk\u00e1 republika",
    "qs_pg:name_adm1":"Kraj Vyso\u010dina",
    "qs_pg:photos_9r":0,
    "qs_pg:photos_sr":0,
    "qs_pg:pop_sr":2,
    "qs_pg:qs_pg_placetype":"locality",
    "qs_pg:qs_pg_placetype_gp":"Town",
    "qs_pg:woe_adm0":23424810,
    "woe:adm0_id":23424810,
    "woe:name_adm0":"\u010cesk\u00e1 republika",
    "woe:name_adm1":"Kraj Vyso\u010dina",
    "woe:placetype":"Town",
    "wof:name":"Dlouh\u00e9",
    "wof:placetype":"locality",
    "wof:population":274
},
  "geometry": {"coordinates":[16.12304,49.50898],"type":"Point"}
}