{
  "type": "Feature",
  "properties": {
    "gn:country":"CZ",
    "gn:fcode":"PPL",
    "gn:population":1050,
    "iso:country":"CZ",
    "name:azb_x_preferred":[
        "\u062e\u0648\u062a\u06cc\u0628\u0648\u0632"
    ],
    "name:cat_x_preferred":[
        "Chot\u011bbuz"
    ],
    "name:ceb_x_preferred":[
        "Chot\u011bbuz"
    ],
    "name:ces_x_preferred":[
        "Chot\u011bbuz"
    ],
    "name:che_x_preferred":[
        "\u0425\u043e\u0442\u0435\u0431\u0443\u0437"
    ],
    "name:deu_x_preferred":[
        "Kozobentz"
    ],
    "name:deu_x_variant":[
        "Kotzobenz",
        "Chot\u011bbuz"
    ],
    "name:eng_x_preferred":[
        "Chot\u011bbuz"
    ],
    "name:epo_x_preferred":[
        "Chot\u011bbuz"
    ],
    "name:eus_x_preferred":[
        "Chot\u011bbuz"
    ],
    "name:fas_x_preferred":[
        "\u062e\u0648\u062a\u06cc\u0628\u0648\u0632"
    ],
    "name:fra_x_preferred":[
        "Chot\u011bbuz"
    ],
    "name:gle_x_preferred":[
        "Chot\u011bbuz"
    ],
    "name:hun_x_preferred":[
        "Chot\u011bbuz"
    ],
    "name:ita_x_preferred":[
        "Chot\u011bbuz"
    ],
    "name:lmo_x_preferred":[
        "Chot\u011bbuz"
    ],
    "name:msa_x_preferred":[
        "Chot\u011bbuz"
    ],
    "name:nan_x_preferred":[
        "Chot\u011bbuz"
    ],
    "name:nld_x_preferred":[
        "Chot\u011bbuz"
    ],
    "name:pol_x_preferred":[
        "Kocob\u0119dz"
    ],
    "name:por_x_preferred":[
        "Chot\u011bbuz"
    ],
    "name:rup_x_preferred":[
        "Chot\u011bbuz"
    ],
    "name:slk_x_preferred":[
        "Chot\u011bbuz"
    ],
    "name:spa_x_preferred":[
        "Chot\u011bbuz"
    ],
    "name:srp_x_preferred":[
        "\u0425\u043e\u0442\u0458\u0435\u0431\u0443\u0437"
    ],
    "name:swe_x_preferred":[
        "Chot\u011bbuz"
    ],
    "name:tat_x_preferred":[
        "\u0425\u043e\u0442\u0435\u0431\u0443\u0437"
    ],
    "name:vie_x_preferred":[
        "Chot\u011bbuz"
    ],
    "qs_pg:aaroncc":"CZ",
    "qs_pg:gn_country":"CZ",
    "qs_pg:gn_fcode":"PPL",
    "qs_pg:gn_pop":1050,
    "qs_pg:name":"Chotbuz",
    "qs_pg:name_adm0":"\u010cesk\u00e1 republika",
    "qs_pg:name_adm1":"Moravskoslezsk\u00fd kraj",
    "qs_pg:photos_9k":1,
    "qs_pg:photos_9r":1,
    "qs_pg:photos_all":1,
    "qs_pg:photos_sr":0,
    "qs_pg:pop_sr":3,
    "qs_pg:qs_pg_placetype":"locality",
    "qs_pg:qs_pg_placetype_gp":"Town",
    "qs_pg:woe_adm0":23424810,
    "woe:adm0_id":23424810,
    "woe:name_adm0":"\u010cesk\u00e1 republika",
    "woe:name_adm1":"Moravskoslezsk\u00fd kraj",
    "woe:placetype":"Town",
    "wof:name":"Chotbuz",
    "wof:placetype":"locality",
    "wof:population":1050
},
  "geometry": {"coordinates":[18.56912,49.76849],"type":"Point"}
}