{
  "type": "Feature",
  "properties": {
    "gn:country":"CZ",
    "gn:fcode":"PPL",
    "gn:population":530,
    "iso:country":"CZ",
    "name:azb_x_preferred":[
        "\u0632\u0628\u06cc\u0633\u0644\u0627\u0648\u06cc\u062a\u0633\u0647"
    ],
    "name:cat_x_preferred":[
        "Zbyslavice"
    ],
    "name:ceb_x_preferred":[
        "Zbyslavice"
    ],
    "name:ces_x_preferred":[
        "Zbyslavice"
    ],
    "name:che_x_preferred":[
        "\u0417\u0431\u0438\u0441\u043b\u0430\u0432\u0438\u0446\u0435"
    ],
    "name:eng_x_preferred":[
        "Zbyslavice"
    ],
    "name:epo_x_preferred":[
        "Zbyslavice"
    ],
    "name:eus_x_preferred":[
        "Zbyslavice"
    ],
    "name:fas_x_preferred":[
        "\u0632\u0628\u06cc\u0633\u0644\u0627\u0648\u06cc\u062a\u0633\u0647"
    ],
    "name:fra_x_preferred":[
        "Zbyslavice"
    ],
    "name:gle_x_preferred":[
        "Zbyslavice"
    ],
    "name:hun_x_preferred":[
        "Zbyslavice"
    ],
    "name:ita_x_preferred":[
        "Zbyslavice"
    ],
    "name:lmo_x_preferred":[
        "Zbyslavice"
    ],
    "name:msa_x_preferred":[
        "Zbyslavice"
    ],
    "name:nan_x_preferred":[
        "Zbyslavice"
    ],
    "name:nld_x_preferred":[
        "Zbyslavice"
    ],
    "name:pol_x_preferred":[
        "Zbyslavice"
    ],
    "name:por_x_preferred":[
        "Zbyslavice"
    ],
    "name:rus_x_preferred":[
        "\u0417\u0431\u0438\u0441\u043b\u0430\u0432\u0438\u0446\u0435"
    ],
    "name:slk_x_preferred":[
        "Zbyslavice"
    ],
    "name:spa_x_preferred":[
        "Zbyslavice"
    ],
    "name:srp_x_preferred":[
        "\u0417\u0431\u0438\u0441\u043b\u0430\u0432\u0438\u0446\u0435"
    ],
    "name:swe_x_preferred":[
        "Zbyslavice"
    ],
    "name:tat_x_preferred":[
        "\u0417\u0431\u0438\u0441\u043b\u0430\u0432\u0438\u0446\u0435"
    ],
    "name:vie_x_preferred":[
        "Zbyslavice"
    ],
    "qs_pg:aaroncc":"CZ",
    "qs_pg:gn_country":"CZ",
    "qs_pg:gn_fcode":"PPL",
    "qs_pg:gn_pop":530,
    "qs_pg:name":"Zbyslavice",
    "qs_pg:name_adm0":"\u010cesk\u00e1 republika",
    "qs_pg:name_adm1":"Moravskoslezsk\u00fd kraj",
    "qs_pg:photos_9r":0,
    "qs_pg:photos_sr":0,
    "qs_pg:pop_sr":2,
    "qs_pg:qs_pg_placetype":"locality",
    "qs_pg:qs_pg_placetype_gp":"Town",
    "qs_pg:woe_adm0":23424810,
    "woe:adm0_id":23424810,
    "woe:name_adm0":"\u010cesk\u00e1 republika",
    "woe:name_adm1":"Moravskoslezsk\u00fd kraj",
    "woe:placetype":"Town",
    "wof:name":"Zbyslavice",
    "wof:placetype":"locality",
    "wof:population":530
},
  "geometry": {"coordinates":[18.07547,49.80534],"type":"Point"}
}