{
  "type": "Feature",
  "properties": {
    "gn:admin1_code":"85.0",
    "gn:admin2_code":"0804",
    "gn:asciiname":"Klokocov",
    "gn:country_code":"CZ",
    "gn:dem":276,
    "gn:feature_class":"P",
    "gn:feature_code":"PPL",
    "gn:name":"Kloko\u010dov",
    "gn:population":0,
    "gn:timezone":"Europe/Prague",
    "iso:country":"CZ",
    "name:und_x_variant":[
        "Klogsdorf"
    ],
    "wof:name":"Klokocov",
    "wof:placetype":"locality"
},
  "geometry": {"coordinates":[18.15491,49.64951],"type":"Point"}
}