{
  "type": "Feature",
  "properties": {
    "gn:gn_country":"CZ",
    "gn:gn_fcode":"PPL",
    "gn:gn_pop":341,
    "gn:population":341,
    "iso:country":"CZ",
    "name:ces_x_preferred":[
        "St\u0159\u00ed\u017eovice"
    ],
    "name:eng_x_preferred":[
        "St\u0159\u00ed\u017eovice"
    ],
    "name:fas_x_preferred":[
        "\u0633\u062a\u0631\u06cc\u0698\u0648\u0648\u06cc\u062a\u0633\u0647"
    ],
    "name:hun_x_preferred":[
        "St\u0159\u00ed\u017eovice"
    ],
    "name:ita_x_preferred":[
        "St\u0159\u00ed\u017eovice"
    ],
    "name:msa_x_preferred":[
        "St\u0159\u00ed\u017eovice"
    ],
    "name:nld_x_preferred":[
        "St\u0159\u00ed\u017eovice"
    ],
    "name:pol_x_preferred":[
        "St\u0159\u00ed\u017eovice"
    ],
    "name:por_x_preferred":[
        "St\u0159\u00ed\u017eovice"
    ],
    "name:rup_x_preferred":[
        "St\u0159\u00ed\u017eovice"
    ],
    "name:slk_x_preferred":[
        "St\u0159\u00ed\u017eovice"
    ],
    "name:srp_x_preferred":[
        "\u0421\u0442\u0440\u0438\u0436\u043e\u0432\u0438\u0446\u0435"
    ],
    "name:swe_x_preferred":[
        "St\u0159\u00ed\u017eovice"
    ],
    "name:vie_x_preferred":[
        "St\u0159\u00ed\u017eovice"
    ],
    "qs_pg:aaroncc":"CZ",
    "qs_pg:gn_country":"CZ",
    "qs_pg:gn_fcode":"PPL",
    "qs_pg:gn_pop":341,
    "qs_pg:name":"St\u0159\u00ed\u017eovice",
    "qs_pg:name_adm0":"\u010cesk\u00e1 republika",
    "qs_pg:name_adm1":"Plze\u0148sk\u00fd kraj",
    "qs_pg:photos_9r":0,
    "qs_pg:photos_sr":0,
    "qs_pg:pop_sr":2,
    "qs_pg:qs_pg_placetype":"locality",
    "qs_pg:qs_pg_placetype_gp":"Town",
    "qs_pg:woe_adm0":23424810,
    "woe:adm0_id":23424810,
    "woe:name_adm0":"\u010cesk\u00e1 republika",
    "woe:name_adm1":"Plze\u0148sk\u00fd kraj",
    "woe:placetype":"Town",
    "wof:name":"St\u0159\u00ed\u017eovice",
    "wof:placetype":"locality",
    "wof:population":341
},
  "geometry": {"coordinates":[13.45839,49.61178],"type":"Point"}
}