{
  "type": "Feature",
  "properties": {
    "gn:gn_country":"CZ",
    "gn:gn_fcode":"PPL",
    "gn:gn_pop":620,
    "gn:population":620,
    "iso:country":"CZ",
    "name:cze_x_preferred":[
        "Kojetice"
    ],
    "name:dut_x_preferred":[
        "Kojetice"
    ],
    "name:eng_x_preferred":[
        "Kojetice"
    ],
    "name:fre_x_preferred":[
        "Kojetice"
    ],
    "name:ger_x_preferred":[
        "Kojetice"
    ],
    "name:hun_x_preferred":[
        "Kojetice"
    ],
    "name:ita_x_preferred":[
        "Kojetice"
    ],
    "name:may_x_preferred":[
        "Kojetice"
    ],
    "name:nan_x_preferred":[
        "Kojetice"
    ],
    "name:per_x_preferred":[
        "\u06a9\u0648\u06cc\u062a\u06cc\u062a\u0633\u0647"
    ],
    "name:pol_x_preferred":[
        "Kojetice"
    ],
    "name:por_x_preferred":[
        "Kojetice"
    ],
    "name:rup_x_preferred":[
        "Kojetice"
    ],
    "name:slo_x_preferred":[
        "Kojetice"
    ],
    "name:srp_x_preferred":[
        "\u041a\u043e\u0458\u0435\u0442\u0438\u0446\u0435"
    ],
    "name:swe_x_preferred":[
        "Kojetice"
    ],
    "name:unk_x_variant":[
        "Kojetitz"
    ],
    "name:vie_x_preferred":[
        "Kojetice"
    ],
    "qs_pg:aaroncc":"CZ",
    "qs_pg:gn_country":"CZ",
    "qs_pg:gn_fcode":"PPL",
    "qs_pg:gn_pop":620,
    "qs_pg:name":"Kojetice",
    "qs_pg:name_adm0":"\u010cesk\u00e1 republika",
    "qs_pg:name_adm1":"St\u0159edo\u010desk\u00fd kraj",
    "qs_pg:photos_9k":1,
    "qs_pg:photos_9r":1,
    "qs_pg:photos_all":1,
    "qs_pg:photos_sr":0,
    "qs_pg:pop_sr":2,
    "qs_pg:qs_pg_placetype":"locality",
    "qs_pg:qs_pg_placetype_gp":"Town",
    "qs_pg:woe_adm0":23424810,
    "woe:adm0_id":23424810,
    "woe:name_adm0":"\u010cesk\u00e1 republika",
    "woe:name_adm1":"St\u0159edo\u010desk\u00fd kraj",
    "woe:placetype":"Town",
    "wof:name":"Kojetice",
    "wof:placetype":"locality",
    "wof:population":620
},
  "geometry": {"coordinates":[14.50848,50.2381],"type":"Point"}
}