{
  "type": "Feature",
  "properties": {
    "gn:admin1_code":"82.0",
    "gn:admin2_code":"0521",
    "gn:asciiname":"Budin",
    "gn:country_code":"CZ",
    "gn:dem":252,
    "gn:feature_class":"P",
    "gn:feature_code":"PPL",
    "gn:name":"Bud\u00edn",
    "gn:population":0,
    "gn:timezone":"Europe/Prague",
    "iso:country":"CZ",
    "wof:name":"Budin",
    "wof:placetype":"locality"
},
  "geometry": {"coordinates":[15.59975,50.21362],"type":"Point"}
}