{
  "type": "Feature",
  "properties": {
    "gn:admin1_code":"80.0",
    "gn:admin2_code":"0615",
    "gn:asciiname":"Podlesi",
    "gn:country_code":"CZ",
    "gn:dem":611,
    "gn:feature_class":"P",
    "gn:feature_code":"PPL",
    "gn:name":"Podles\u00ed",
    "gn:population":0,
    "gn:timezone":"Europe/Prague",
    "iso:country":"CZ",
    "name:und_x_variant":[
        "Valdorf",
        "Podles\u00ed"
    ],
    "wof:name":"Podlesi",
    "wof:placetype":"locality"
},
  "geometry": {"coordinates":[16.10068,49.67701],"type":"Point"}
}