{
  "type": "Feature",
  "properties": {
    "gn:country":"CZ",
    "gn:fcode":"PPL",
    "gn:population":327,
    "iso:country":"CZ",
    "name:azb_x_preferred":[
        "\u067e\u062a\u0631\u0648\u0648\u06a9\u0627"
    ],
    "name:cat_x_preferred":[
        "Petr\u016fvka"
    ],
    "name:ceb_x_preferred":[
        "Petr\u016fvka"
    ],
    "name:ces_x_preferred":[
        "Petr\u016fvka"
    ],
    "name:che_x_preferred":[
        "\u041f\u0435\u0442\u0440\u0443\u0432\u043a\u0430"
    ],
    "name:deu_x_preferred":[
        "Petr\u016fvka"
    ],
    "name:eng_x_preferred":[
        "Petr\u016fvka"
    ],
    "name:epo_x_preferred":[
        "Petr\u016fvka"
    ],
    "name:est_x_preferred":[
        "Obec Petr\u016fvka"
    ],
    "name:eus_x_preferred":[
        "Petr\u016fvka"
    ],
    "name:fas_x_preferred":[
        "\u067e\u062a\u0631\u0648\u0648\u06a9\u0627"
    ],
    "name:fra_x_preferred":[
        "Petr\u016fvka"
    ],
    "name:gle_x_preferred":[
        "Petr\u016fvka"
    ],
    "name:hrv_x_preferred":[
        "Obec Petr\u016fvka"
    ],
    "name:hun_x_preferred":[
        "Petr\u016fvka"
    ],
    "name:ita_x_preferred":[
        "Petr\u016fvka"
    ],
    "name:lmo_x_preferred":[
        "Petr\u016fvka"
    ],
    "name:msa_x_preferred":[
        "Petr\u016fvka"
    ],
    "name:nan_x_preferred":[
        "Petr\u016fvka"
    ],
    "name:nld_x_preferred":[
        "Petr\u016fvka"
    ],
    "name:pol_x_preferred":[
        "Petr\u016fvka"
    ],
    "name:por_x_preferred":[
        "Petr\u016fvka"
    ],
    "name:rup_x_preferred":[
        "Petr\u016fvka"
    ],
    "name:slk_x_preferred":[
        "Petr\u016fvka"
    ],
    "name:slv_x_preferred":[
        "Obec Petr\u016fvka"
    ],
    "name:spa_x_preferred":[
        "Petr\u016fvka"
    ],
    "name:srp_x_preferred":[
        "\u041f\u0435\u0442\u0440\u0443\u0432\u043a\u0430"
    ],
    "name:swe_x_preferred":[
        "Petr\u016fvka"
    ],
    "name:tat_x_preferred":[
        "\u041f\u0435\u0442\u0440\u0443\u0432\u043a\u0430"
    ],
    "name:vie_x_preferred":[
        "Petr\u016fvka"
    ],
    "qs_pg:aaroncc":"CZ",
    "qs_pg:gn_country":"CZ",
    "qs_pg:gn_fcode":"PPL",
    "qs_pg:gn_pop":327,
    "qs_pg:name":"Petr\u016fvka",
    "qs_pg:name_adm0":"\u010cesk\u00e1 republika",
    "qs_pg:name_adm1":"Zl\u00ednsk\u00fd kraj",
    "qs_pg:photos_9r":0,
    "qs_pg:photos_sr":0,
    "qs_pg:pop_sr":2,
    "qs_pg:qs_pg_placetype":"locality",
    "qs_pg:qs_pg_placetype_gp":"Town",
    "qs_pg:woe_adm0":23424810,
    "woe:adm0_id":23424810,
    "woe:name_adm0":"\u010cesk\u00e1 republika",
    "woe:name_adm1":"Zl\u00ednsk\u00fd kraj",
    "woe:placetype":"Town",
    "wof:name":"Petr\u016fvka",
    "wof:placetype":"locality",
    "wof:population":327
},
  "geometry": {"coordinates":[17.80997,49.10491],"type":"Point"}
}