{
  "type": "Feature",
  "properties": {
    "gn:gn_country":"CZ",
    "gn:gn_fcode":"PPL",
    "gn:gn_pop":327,
    "gn:population":327,
    "iso:country":"CZ",
    "name:cze_x_preferred":[
        "Petr\u016fvka"
    ],
    "name:dut_x_preferred":[
        "Petr\u016fvka"
    ],
    "name:eng_x_preferred":[
        "Petr\u016fvka"
    ],
    "name:fre_x_preferred":[
        "Petr\u016fvka"
    ],
    "name:ger_x_preferred":[
        "Petr\u016fvka"
    ],
    "name:hun_x_preferred":[
        "Petr\u016fvka"
    ],
    "name:ita_x_preferred":[
        "Petr\u016fvka"
    ],
    "name:may_x_preferred":[
        "Petr\u016fvka"
    ],
    "name:per_x_preferred":[
        "\u067e\u062a\u0631\u0648\u0648\u06a9\u0627"
    ],
    "name:pol_x_preferred":[
        "Petr\u016fvka"
    ],
    "name:por_x_preferred":[
        "Petr\u016fvka"
    ],
    "name:rup_x_preferred":[
        "Petr\u016fvka"
    ],
    "name:slo_x_preferred":[
        "Petr\u016fvka"
    ],
    "name:srp_x_preferred":[
        "\u041f\u0435\u0442\u0440\u0443\u0432\u043a\u0430"
    ],
    "name:swe_x_preferred":[
        "Petr\u016fvka"
    ],
    "name:vie_x_preferred":[
        "Petr\u016fvka"
    ],
    "qs_pg:aaroncc":"CZ",
    "qs_pg:gn_country":"CZ",
    "qs_pg:gn_fcode":"PPL",
    "qs_pg:gn_pop":327,
    "qs_pg:name":"Petr\u016fvka",
    "qs_pg:name_adm0":"\u010cesk\u00e1 republika",
    "qs_pg:name_adm1":"Zl\u00ednsk\u00fd kraj",
    "qs_pg:photos_9r":0,
    "qs_pg:photos_sr":0,
    "qs_pg:pop_sr":2,
    "qs_pg:qs_pg_placetype":"locality",
    "qs_pg:qs_pg_placetype_gp":"Town",
    "qs_pg:woe_adm0":23424810,
    "woe:adm0_id":23424810,
    "woe:name_adm0":"\u010cesk\u00e1 republika",
    "woe:name_adm1":"Zl\u00ednsk\u00fd kraj",
    "woe:placetype":"Town",
    "wof:name":"Petr\u016fvka",
    "wof:placetype":"locality",
    "wof:population":327
},
  "geometry": {"coordinates":[17.80997,49.10491],"type":"Point"}
}