{
  "type": "Feature",
  "properties": {
    "gn:admin1_code":"87.0",
    "gn:admin2_code":"0324",
    "gn:asciiname":"Resanice",
    "gn:country_code":"CZ",
    "gn:dem":565,
    "gn:feature_class":"P",
    "gn:feature_code":"PPL",
    "gn:name":"\u0158esanice",
    "gn:population":0,
    "gn:timezone":"Europe/Prague",
    "iso:country":"CZ",
    "wof:name":"Resanice",
    "wof:placetype":"locality"
},
  "geometry": {"coordinates":[13.71116,49.44057],"type":"Point"}
}