{
  "type": "Feature",
  "properties": {
    "gn:gn_country":"CZ",
    "gn:gn_fcode":"PPL",
    "gn:gn_pop":1297,
    "gn:population":1297,
    "iso:country":"CZ",
    "name:ces_x_preferred":[
        "Muka\u0159ov"
    ],
    "name:eng_x_preferred":[
        "Muka\u0159ov"
    ],
    "name:fas_x_preferred":[
        "\u0645\u0648\u06a9\u0627\u0631\u0648\u0641"
    ],
    "name:fra_x_preferred":[
        "Muka\u0159ov"
    ],
    "name:hun_x_preferred":[
        "Muka\u0159ov"
    ],
    "name:ita_x_preferred":[
        "Muka\u0159ov"
    ],
    "name:msa_x_preferred":[
        "Muka\u0159ov"
    ],
    "name:nld_x_preferred":[
        "Muka\u0159ov"
    ],
    "name:pol_x_preferred":[
        "Muka\u0159ov"
    ],
    "name:por_x_preferred":[
        "Muka\u0159ov"
    ],
    "name:rup_x_preferred":[
        "Muka\u0159ov"
    ],
    "name:slk_x_preferred":[
        "Muka\u0159ov"
    ],
    "name:srp_x_preferred":[
        "\u041c\u0443\u043a\u0430\u0440\u0436\u043e\u0432"
    ],
    "name:swe_x_preferred":[
        "Muka\u0159ov"
    ],
    "name:unk_x_variant":[
        "Mukarschow"
    ],
    "name:vie_x_preferred":[
        "Muka\u0159ov"
    ],
    "qs_pg:aaroncc":"CZ",
    "qs_pg:gn_country":"CZ",
    "qs_pg:gn_fcode":"PPL",
    "qs_pg:gn_pop":1297,
    "qs_pg:name":"Muka\u0159ov",
    "qs_pg:name_adm0":"\u010cesk\u00e1 republika",
    "qs_pg:name_adm1":"St\u0159edo\u010desk\u00fd kraj",
    "qs_pg:photos":13,
    "qs_pg:photos_1k":3,
    "qs_pg:photos_9k":1,
    "qs_pg:photos_9r":1,
    "qs_pg:photos_all":13,
    "qs_pg:photos_sr":1,
    "qs_pg:pop_sr":3,
    "qs_pg:qs_pg_placetype":"locality",
    "qs_pg:qs_pg_placetype_gp":"Town",
    "qs_pg:woe_adm0":23424810,
    "woe:adm0_id":23424810,
    "woe:name_adm0":"\u010cesk\u00e1 republika",
    "woe:name_adm1":"St\u0159edo\u010desk\u00fd kraj",
    "woe:placetype":"Town",
    "wof:name":"Muka\u0159ov",
    "wof:placetype":"locality",
    "wof:population":1297
},
  "geometry": {"coordinates":[14.74155,49.99115],"type":"Point"}
}