{
  "type": "Feature",
  "properties": {
    "gn:gn_country":"CZ",
    "gn:gn_fcode":"PPL",
    "gn:gn_pop":415,
    "gn:population":415,
    "iso:country":"CZ",
    "name:cze_x_preferred":[
        "Such\u00fd D\u016fl"
    ],
    "name:dut_x_preferred":[
        "Such\u00fd D\u016fl"
    ],
    "name:eng_x_preferred":[
        "Such\u00fd D\u016fl"
    ],
    "name:fre_x_preferred":[
        "Such\u00fd D\u016fl"
    ],
    "name:ger_x_preferred":[
        "Such\u00fd D\u016fl"
    ],
    "name:hun_x_preferred":[
        "Such\u00fd D\u016fl"
    ],
    "name:ita_x_preferred":[
        "Such\u00fd D\u016fl"
    ],
    "name:may_x_preferred":[
        "Such\u00fd D\u016fl"
    ],
    "name:per_x_preferred":[
        "\u0633\u0648\u062e\u06cc \u062f\u0648\u0644"
    ],
    "name:pol_x_preferred":[
        "Such\u00fd D\u016fl"
    ],
    "name:por_x_preferred":[
        "Such\u00fd D\u016fl"
    ],
    "name:slo_x_preferred":[
        "Such\u00fd D\u016fl"
    ],
    "name:srp_x_preferred":[
        "\u0421\u0443\u0445\u0438 \u0414\u0443\u043b"
    ],
    "name:swe_x_preferred":[
        "Such\u00fd D\u016fl"
    ],
    "name:vie_x_preferred":[
        "Such\u00fd D\u016fl"
    ],
    "qs_pg:aaroncc":"CZ",
    "qs_pg:gn_country":"CZ",
    "qs_pg:gn_fcode":"PPL",
    "qs_pg:gn_pop":415,
    "qs_pg:name":"Such\u00fd D\u016fl",
    "qs_pg:name_adm0":"\u010cesk\u00e1 republika",
    "qs_pg:name_adm1":"Kr\u00e1lov\u00e9hradeck\u00fd kraj",
    "qs_pg:photos_9k":1,
    "qs_pg:photos_9r":4,
    "qs_pg:photos_all":184,
    "qs_pg:photos_sr":0,
    "qs_pg:pop_sr":2,
    "qs_pg:qs_pg_placetype":"locality",
    "qs_pg:qs_pg_placetype_gp":"Town",
    "qs_pg:woe_adm0":23424810,
    "woe:adm0_id":23424810,
    "woe:name_adm0":"\u010cesk\u00e1 republika",
    "woe:name_adm1":"Kr\u00e1lov\u00e9hradeck\u00fd kraj",
    "woe:placetype":"Town",
    "wof:name":"Such\u00fd D\u016fl",
    "wof:placetype":"locality",
    "wof:population":415
},
  "geometry": {"coordinates":[16.26537,50.54008],"type":"Point"}
}