{
  "type": "Feature",
  "properties": {
    "gn:country":"CZ",
    "gn:fcode":"PPL",
    "gn:population":327,
    "iso:country":"CZ",
    "name:azb_x_preferred":[
        "\u0633\u0648\u0644\u0646\u06cc\u062a\u0633\u0647"
    ],
    "name:ceb_x_preferred":[
        "Solenice"
    ],
    "name:ces_x_preferred":[
        "Solenice"
    ],
    "name:deu_x_preferred":[
        "Solenice"
    ],
    "name:eng_x_preferred":[
        "Solenice"
    ],
    "name:eus_x_preferred":[
        "Solenice"
    ],
    "name:fas_x_preferred":[
        "\u0633\u0648\u0644\u0646\u06cc\u062a\u0633\u0647"
    ],
    "name:fra_x_preferred":[
        "Solenice"
    ],
    "name:hun_x_preferred":[
        "Solenice"
    ],
    "name:ita_x_preferred":[
        "Solenice"
    ],
    "name:msa_x_preferred":[
        "Solenice"
    ],
    "name:nan_x_preferred":[
        "Solenice"
    ],
    "name:nld_x_preferred":[
        "Solenice"
    ],
    "name:por_x_preferred":[
        "Solenice"
    ],
    "name:rup_x_preferred":[
        "Solenice"
    ],
    "name:slk_x_preferred":[
        "Solenice"
    ],
    "name:spa_x_preferred":[
        "Solenice"
    ],
    "name:srp_x_preferred":[
        "\u0421\u043e\u043b\u0435\u045a\u0438\u0446\u0435"
    ],
    "name:swe_x_preferred":[
        "Solenice"
    ],
    "name:vie_x_preferred":[
        "Solenice"
    ],
    "qs_pg:aaroncc":"CZ",
    "qs_pg:gn_country":"CZ",
    "qs_pg:gn_fcode":"PPL",
    "qs_pg:gn_pop":327,
    "qs_pg:name":"Solenice",
    "qs_pg:name_adm0":"\u010cesk\u00e1 republika",
    "qs_pg:name_adm1":"St\u0159edo\u010desk\u00fd kraj",
    "qs_pg:photos_9r":0,
    "qs_pg:photos_sr":0,
    "qs_pg:pop_sr":2,
    "qs_pg:qs_pg_placetype":"locality",
    "qs_pg:qs_pg_placetype_gp":"Town",
    "qs_pg:woe_adm0":23424810,
    "woe:adm0_id":23424810,
    "woe:name_adm0":"\u010cesk\u00e1 republika",
    "woe:name_adm1":"St\u0159edo\u010desk\u00fd kraj",
    "woe:placetype":"Town",
    "wof:name":"Solenice",
    "wof:placetype":"locality",
    "wof:population":327
},
  "geometry": {"coordinates":[14.19578,49.61757],"type":"Point"}
}