{
  "type": "Feature",
  "properties": {
    "gn:admin1_code":"90.0",
    "gn:admin2_code":"0723",
    "gn:asciiname":"Planisko",
    "gn:country_code":"CZ",
    "gn:dem":553,
    "gn:feature_class":"P",
    "gn:feature_code":"PPL",
    "gn:name":"Pl\u00e1nisko",
    "gn:population":0,
    "gn:timezone":"Europe/Prague",
    "iso:country":"CZ",
    "wof:name":"Planisko",
    "wof:placetype":"locality"
},
  "geometry": {"coordinates":[18.20179,49.30977],"type":"Point"}
}