{
  "type": "Feature",
  "properties": {
    "gn:admin1_code":"88.0",
    "gn:admin2_code":"0208",
    "gn:asciiname":"Patrin",
    "gn:country_code":"CZ",
    "gn:dem":254,
    "gn:feature_class":"P",
    "gn:feature_code":"PPL",
    "gn:name":"Pat\u0159\u00edn",
    "gn:population":0,
    "gn:timezone":"Europe/Prague",
    "iso:country":"CZ",
    "wof:name":"Patrin",
    "wof:placetype":"locality"
},
  "geometry": {"coordinates":[15.01359,50.2786],"type":"Point"}
}