{
  "type": "Feature",
  "properties": {
    "gn:admin1_code":"88.0",
    "gn:admin2_code":"020B",
    "gn:asciiname":"Divisovice",
    "gn:country_code":"CZ",
    "gn:dem":406,
    "gn:feature_class":"P",
    "gn:feature_code":"PPL",
    "gn:name":"Divi\u0161ovice",
    "gn:population":0,
    "gn:timezone":"Europe/Prague",
    "iso:country":"CZ",
    "wof:name":"Divisovice",
    "wof:placetype":"locality"
},
  "geometry": {"coordinates":[14.53105,49.60066],"type":"Point"}
}