{
  "type": "Feature",
  "properties": {
    "gn:admin1_code":"82.0",
    "gn:admin2_code":"0524",
    "gn:asciiname":"Dolni Dvur",
    "gn:cc2":"CZ",
    "gn:country_code":"CZ",
    "gn:dem":520,
    "gn:feature_class":"P",
    "gn:feature_code":"PPL",
    "gn:name":"Doln\u00ed Dv\u016fr",
    "gn:population":0,
    "gn:timezone":"Europe/Prague",
    "iso:country":"CZ",
    "name:und_x_variant":[
        "Niederhof"
    ],
    "wof:name":"Dolni Dvur",
    "wof:placetype":"locality"
},
  "geometry": {"coordinates":[16.46667,50.15],"type":"Point"}
}