{
  "type": "Feature",
  "properties": {
    "gn:country":"CZ",
    "gn:fcode":"PPL",
    "gn:population":671,
    "iso:country":"CZ",
    "name:azb_x_preferred":[
        "\u0631\u0627\u062f\u0648\u0633\u062a\u06cc\u062a\u0633\u0647"
    ],
    "name:cat_x_preferred":[
        "Radostice"
    ],
    "name:ceb_x_preferred":[
        "Radostice"
    ],
    "name:ces_x_preferred":[
        "Radostice"
    ],
    "name:che_x_preferred":[
        "\u0420\u0436\u0430\u0434\u043e\u0441\u0442\u0438\u0446\u0435"
    ],
    "name:deu_x_preferred":[
        "Radostice"
    ],
    "name:eng_x_preferred":[
        "Radostice"
    ],
    "name:epo_x_preferred":[
        "Radostice"
    ],
    "name:est_x_preferred":[
        "Obec Radostice"
    ],
    "name:eus_x_preferred":[
        "Radostice"
    ],
    "name:fas_x_preferred":[
        "\u0631\u0627\u062f\u0648\u0633\u062a\u06cc\u062a\u0633\u0647"
    ],
    "name:fra_x_preferred":[
        "Radostice"
    ],
    "name:gle_x_preferred":[
        "Radostice"
    ],
    "name:hrv_x_preferred":[
        "Obec Radostice"
    ],
    "name:hun_x_preferred":[
        "Radostice"
    ],
    "name:ita_x_preferred":[
        "Radostice"
    ],
    "name:kat_x_preferred":[
        "\u10e0\u10d0\u10d3\u10dd\u10e1\u10e2\u10d8\u10ea\u10d4"
    ],
    "name:lmo_x_preferred":[
        "Radostice"
    ],
    "name:msa_x_preferred":[
        "Radostice"
    ],
    "name:nan_x_preferred":[
        "Radostice"
    ],
    "name:nld_x_preferred":[
        "Radostice"
    ],
    "name:pol_x_preferred":[
        "Radostice"
    ],
    "name:por_x_preferred":[
        "Radostice"
    ],
    "name:slk_x_preferred":[
        "Radostice"
    ],
    "name:slv_x_preferred":[
        "Obec Radostice"
    ],
    "name:spa_x_preferred":[
        "Radostice"
    ],
    "name:swe_x_preferred":[
        "Radostice"
    ],
    "name:tat_x_preferred":[
        "\u0420\u0436\u0430\u0434\u043e\u0441\u0442\u0438\u0446\u0435"
    ],
    "name:vie_x_preferred":[
        "Radostice"
    ],
    "qs_pg:aaroncc":"CZ",
    "qs_pg:gn_country":"CZ",
    "qs_pg:gn_fcode":"PPL",
    "qs_pg:gn_pop":671,
    "qs_pg:name":"Radostice",
    "qs_pg:name_adm0":"\u010cesk\u00e1 republika",
    "qs_pg:name_adm1":"Jihomoravsk\u00fd kraj",
    "qs_pg:photos_9r":0,
    "qs_pg:photos_sr":0,
    "qs_pg:pop_sr":2,
    "qs_pg:qs_pg_placetype":"locality",
    "qs_pg:qs_pg_placetype_gp":"Town",
    "qs_pg:woe_adm0":23424810,
    "woe:adm0_id":23424810,
    "woe:name_adm0":"\u010cesk\u00e1 republika",
    "woe:name_adm1":"Jihomoravsk\u00fd kraj",
    "woe:placetype":"Town",
    "wof:name":"Radostice",
    "wof:placetype":"locality",
    "wof:population":671
},
  "geometry": {"coordinates":[16.47701,49.13361],"type":"Point"}
}