{
  "type": "Feature",
  "properties": {
    "gn:admin1_code":"79.0",
    "gn:admin2_code":"0312",
    "gn:asciiname":"Jenin",
    "gn:country_code":"CZ",
    "gn:dem":665,
    "gn:feature_class":"P",
    "gn:feature_code":"PPL",
    "gn:name":"Jen\u00edn",
    "gn:population":0,
    "gn:timezone":"Europe/Prague",
    "iso:country":"CZ",
    "name:und_x_variant":[
        "Kodetschlag",
        "Jen\u00edn"
    ],
    "wof:name":"Jenin",
    "wof:placetype":"locality"
},
  "geometry": {"coordinates":[14.40743,48.63898],"type":"Point"}
}