{
  "type": "Feature",
  "properties": {
    "gn:admin1_code":"79.0",
    "gn:admin2_code":"0312",
    "gn:asciiname":"Jenin",
    "gn:country_code":"CZ",
    "gn:dem":665,
    "gn:feature_class":"P",
    "gn:feature_code":"PPL",
    "gn:name":"Jen\u00edn",
    "gn:population":0,
    "gn:timezone":"Europe/Prague",
    "iso:country":"CZ",
    "name:ara_x_preferred":[
        "\u062c\u0646\u064a\u0646"
    ],
    "name:bul_x_preferred":[
        "\u0414\u0436\u0435\u043d\u0438\u043d"
    ],
    "name:cat_x_preferred":[
        "Jenin"
    ],
    "name:ceb_x_preferred":[
        "Jan\u012bn"
    ],
    "name:ces_x_preferred":[
        "D\u017een\u00edn"
    ],
    "name:cym_x_preferred":[
        "Jenin"
    ],
    "name:deu_x_preferred":[
        "Dschenin"
    ],
    "name:epo_x_preferred":[
        "Jenin"
    ],
    "name:eus_x_preferred":[
        "Jenin"
    ],
    "name:fas_x_preferred":[
        "\u062c\u0646\u06cc\u0646"
    ],
    "name:fin_x_preferred":[
        "Jenin"
    ],
    "name:fra_x_preferred":[
        "J\u00e9nine"
    ],
    "name:glg_x_preferred":[
        "Xinin"
    ],
    "name:heb_x_preferred":[
        "\u05d2'\u05e0\u05d9\u05df"
    ],
    "name:hin_x_preferred":[
        "\u091c\u0947\u0928\u093f\u0928"
    ],
    "name:ind_x_preferred":[
        "Jenin"
    ],
    "name:ita_x_preferred":[
        "Jenin"
    ],
    "name:lit_x_preferred":[
        "D\u017eeninas"
    ],
    "name:mal_x_preferred":[
        "\u0d1c\u0d46\u0d28\u0d3f\u0d7b"
    ],
    "name:mkd_x_preferred":[
        "\u040f\u0435\u043d\u0438\u043d"
    ],
    "name:nld_x_preferred":[
        "Jenin"
    ],
    "name:nno_x_preferred":[
        "Jenin"
    ],
    "name:nor_x_preferred":[
        "Jenin"
    ],
    "name:pnb_x_preferred":[
        "\u062c\u0646\u06cc\u0646"
    ],
    "name:pol_x_preferred":[
        "D\u017canin"
    ],
    "name:por_x_preferred":[
        "Jenin"
    ],
    "name:rus_x_preferred":[
        "\u0414\u0436\u0435\u043d\u0438\u043d"
    ],
    "name:sco_x_preferred":[
        "Jenin"
    ],
    "name:spa_x_preferred":[
        "Yen\u00edn"
    ],
    "name:swe_x_preferred":[
        "Jenin"
    ],
    "name:tur_x_preferred":[
        "Cenin"
    ],
    "name:ukr_x_preferred":[
        "\u0414\u0436\u0430\u043d\u0456\u043d"
    ],
    "name:und_x_variant":[
        "Kodetschlag",
        "Jen\u00edn"
    ],
    "name:urd_x_preferred":[
        "\u062c\u0646\u06cc\u0646"
    ],
    "wof:name":"Jenin",
    "wof:placetype":"locality"
},
  "geometry": {"coordinates":[14.40743,48.63898],"type":"Point"}
}