{
  "type": "Feature",
  "properties": {
    "gn:admin1_code":"78.0",
    "gn:admin2_code":"0627",
    "gn:asciiname":"Hnizdo",
    "gn:country_code":"CZ",
    "gn:dem":247,
    "gn:feature_class":"P",
    "gn:feature_code":"PPL",
    "gn:name":"Hn\u00edzdo",
    "gn:population":0,
    "gn:timezone":"Europe/Prague",
    "iso:country":"CZ",
    "name:und_x_variant":[
        "Knast",
        "Hn\u00edzdo"
    ],
    "wof:name":"Hnizdo",
    "wof:placetype":"locality"
},
  "geometry": {"coordinates":[16.13332999999999,48.76667],"type":"Point"}
}