{
  "type": "Feature",
  "properties": {
    "gn:admin1_code":"79.0",
    "gn:admin2_code":"0315",
    "gn:asciiname":"Mosna",
    "gn:country_code":"CZ",
    "gn:dem":856,
    "gn:feature_class":"P",
    "gn:feature_code":"PPL",
    "gn:name":"Mo\u0161na",
    "gn:population":0,
    "gn:timezone":"Europe/Prague",
    "iso:country":"CZ",
    "name:ceb_x_preferred":[
        "Mosna"
    ],
    "name:deu_x_preferred":[
        "Mosna"
    ],
    "name:nld_x_preferred":[
        "Mosna"
    ],
    "name:und_x_variant":[
        "Jandles",
        "Mo\u0161na"
    ],
    "wof:name":"Mosna",
    "wof:placetype":"locality"
},
  "geometry": {"coordinates":[13.98993,48.93523],"type":"Point"}
}