{
  "type": "Feature",
  "properties": {
    "gn:admin1_code":"86.0",
    "gn:admin2_code":"0531",
    "gn:asciiname":"Jasne Pole",
    "gn:country_code":"CZ",
    "gn:dem":558,
    "gn:feature_class":"P",
    "gn:feature_code":"PPL",
    "gn:name":"Jasn\u00e9 Pole",
    "gn:population":0,
    "gn:timezone":"Europe/Prague",
    "iso:country":"CZ",
    "wof:name":"Jasne Pole",
    "wof:placetype":"locality"
},
  "geometry": {"coordinates":[15.85667,49.74755],"type":"Point"}
}