{
  "type": "Feature",
  "properties": {
    "gn:gn_country":"CZ",
    "gn:gn_fcode":"PPL",
    "gn:gn_pop":404,
    "gn:population":404,
    "iso:country":"CZ",
    "name:bul_x_preferred":[
        "\u0412\u0439\u0441\u043e\u043a\u043e\u0432"
    ],
    "name:ces_x_preferred":[
        "Vysokov"
    ],
    "name:deu_x_preferred":[
        "Vysokov"
    ],
    "name:eng_x_preferred":[
        "Vysokov"
    ],
    "name:fas_x_preferred":[
        "\u0648\u06cc\u0633\u0648\u06a9\u0648\u0648"
    ],
    "name:fra_x_preferred":[
        "Vysokov"
    ],
    "name:hun_x_preferred":[
        "Vysokov"
    ],
    "name:ita_x_preferred":[
        "Vysokov"
    ],
    "name:msa_x_preferred":[
        "Vysokov"
    ],
    "name:nld_x_preferred":[
        "Vysokov"
    ],
    "name:pol_x_preferred":[
        "Vysokov"
    ],
    "name:por_x_preferred":[
        "Vysokov"
    ],
    "name:slk_x_preferred":[
        "Vysokov"
    ],
    "name:srp_x_preferred":[
        "\u0412\u0438\u0441\u043e\u043a\u043e\u0432"
    ],
    "name:swe_x_preferred":[
        "Vysokov"
    ],
    "name:vie_x_preferred":[
        "Vysokov"
    ],
    "qs_pg:aaroncc":"CZ",
    "qs_pg:gn_country":"CZ",
    "qs_pg:gn_fcode":"PPL",
    "qs_pg:gn_pop":404,
    "qs_pg:name":"Vysokov",
    "qs_pg:name_adm0":"\u010cesk\u00e1 republika",
    "qs_pg:name_adm1":"Kr\u00e1lov\u00e9hradeck\u00fd kraj",
    "qs_pg:photos_9k":1,
    "qs_pg:photos_9r":3,
    "qs_pg:photos_all":84,
    "qs_pg:photos_sr":0,
    "qs_pg:pop_sr":2,
    "qs_pg:qs_pg_placetype":"locality",
    "qs_pg:qs_pg_placetype_gp":"Town",
    "qs_pg:woe_adm0":23424810,
    "woe:adm0_id":23424810,
    "woe:name_adm0":"\u010cesk\u00e1 republika",
    "woe:name_adm1":"Kr\u00e1lov\u00e9hradeck\u00fd kraj",
    "woe:placetype":"Town",
    "wof:name":"Vysokov",
    "wof:placetype":"locality",
    "wof:population":404
},
  "geometry": {"coordinates":[16.11664,50.40377],"type":"Point"}
}