{
  "type": "Feature",
  "properties": {
    "gn:admin1_code":"81",
    "gn:admin2_code":"0413",
    "gn:asciiname":"Tridomi",
    "gn:country_code":"CZ",
    "gn:dem":616,
    "gn:feature_class":"P",
    "gn:feature_code":"PPL",
    "gn:name":"T\u0159\u00eddom\u00ed",
    "gn:population":0,
    "gn:timezone":"Europe/Prague",
    "iso:country":"CZ",
    "name:und_x_variant":[
        "Dreih\u00e4user",
        "T\u0159\u00eddom\u00ed"
    ],
    "wof:name":"Tridomi",
    "wof:placetype":"locality"
},
  "geometry": {"coordinates":[12.75056,50.14575],"type":"Point"}
}