{
  "type": "Feature",
  "properties": {
    "gn:gn_country":"CZ",
    "gn:gn_fcode":"PPL",
    "gn:gn_pop":90,
    "gn:population":90,
    "iso:country":"CZ",
    "name:azb_x_preferred":[
        "\u0644\u0634\u06a9\u0648\u0648\u06cc\u062a\u0633\u0647"
    ],
    "name:ces_x_preferred":[
        "Le\u0161kovice"
    ],
    "name:deu_x_preferred":[
        "Le\u0161kovice"
    ],
    "name:eus_x_preferred":[
        "Le\u0161kovice"
    ],
    "name:fas_x_preferred":[
        "\u0644\u0634\u06a9\u0648\u0648\u06cc\u062a\u0633\u0647"
    ],
    "name:fra_x_preferred":[
        "Le\u0161kovice"
    ],
    "name:hun_x_preferred":[
        "Le\u0161kovice"
    ],
    "name:ita_x_preferred":[
        "Le\u0161kovice"
    ],
    "name:msa_x_preferred":[
        "Le\u0161kovice"
    ],
    "name:nld_x_preferred":[
        "Le\u0161kovice"
    ],
    "name:pol_x_preferred":[
        "Le\u0161kovice"
    ],
    "name:por_x_preferred":[
        "Le\u0161kovice"
    ],
    "name:slk_x_preferred":[
        "Le\u0161kovice"
    ],
    "name:spa_x_preferred":[
        "Le\u0161kovice"
    ],
    "name:srp_x_preferred":[
        "\u041b\u0435\u0448\u043a\u043e\u0432\u0438\u0446\u0435"
    ],
    "name:vie_x_preferred":[
        "Le\u0161kovice"
    ],
    "qs_pg:aaroncc":"CZ",
    "qs_pg:gn_country":"CZ",
    "qs_pg:gn_fcode":"PPL",
    "qs_pg:gn_pop":90,
    "qs_pg:name":"Le\u0161kovice",
    "qs_pg:name_adm0":"\u010cesk\u00e1 republika",
    "qs_pg:name_adm1":"Kraj Vyso\u010dina",
    "qs_pg:photos_9r":0,
    "qs_pg:photos_sr":0,
    "qs_pg:pop_sr":1,
    "qs_pg:qs_pg_placetype":"locality",
    "qs_pg:qs_pg_placetype_gp":"Town",
    "qs_pg:woe_adm0":23424810,
    "woe:adm0_id":23424810,
    "woe:name_adm0":"\u010cesk\u00e1 republika",
    "woe:name_adm1":"Kraj Vyso\u010dina",
    "woe:placetype":"Town",
    "wof:name":"Le\u0161kovice",
    "wof:placetype":"locality",
    "wof:population":90
},
  "geometry": {"coordinates":[15.537,49.76289],"type":"Point"}
}