{
  "type": "Feature",
  "properties": {
    "gn:admin1_code":"82",
    "gn:admin2_code":"0523",
    "gn:asciiname":"Zvole",
    "gn:country_code":"CZ",
    "gn:dem":271,
    "gn:feature_class":"P",
    "gn:feature_code":"PPL",
    "gn:name":"Zvole",
    "gn:population":0,
    "gn:timezone":"Europe/Prague",
    "iso:country":"CZ",
    "name:ceb_x_preferred":[
        "Zvole"
    ],
    "name:ces_x_preferred":[
        "Zvole"
    ],
    "name:deu_x_preferred":[
        "Zvole"
    ],
    "name:epo_x_preferred":[
        "Zvole"
    ],
    "name:fra_x_preferred":[
        "Zvole"
    ],
    "name:ita_x_preferred":[
        "Zvole"
    ],
    "name:nld_x_preferred":[
        "Zvole"
    ],
    "name:pol_x_preferred":[
        "Zvole"
    ],
    "name:slk_x_preferred":[
        "Zvole"
    ],
    "name:srp_x_preferred":[
        "\u0417\u0432\u043e\u043b\u0435"
    ],
    "name:swe_x_preferred":[
        "Zvole"
    ],
    "wof:name":"Zvole",
    "wof:placetype":"locality"
},
  "geometry": {"coordinates":[15.97839,50.36458],"type":"Point"}
}