{
  "type": "Feature",
  "properties": {
    "gn:admin1_code":"79",
    "gn:admin2_code":"0311",
    "gn:asciiname":"Svetvi",
    "gn:country_code":"CZ",
    "gn:dem":559,
    "gn:feature_class":"P",
    "gn:feature_code":"PPL",
    "gn:name":"Sv\u011btv\u00ed",
    "gn:population":0,
    "gn:timezone":"Europe/Prague",
    "iso:country":"CZ",
    "name:und_x_variant":[
        "Gschwendt",
        "Sv\u011btv\u00ed"
    ],
    "wof:name":"Svetvi",
    "wof:placetype":"locality"
},
  "geometry": {"coordinates":[14.75713,48.77005],"type":"Point"}
}