{
  "type": "Feature",
  "properties": {
    "gn:admin1_code":"83.0",
    "gn:admin2_code":"0514",
    "gn:asciiname":"Rovnacov",
    "gn:country_code":"CZ",
    "gn:dem":531,
    "gn:feature_class":"P",
    "gn:feature_code":"PPL",
    "gn:name":"Rovn\u00e1\u010dov",
    "gn:population":0,
    "gn:timezone":"Europe/Prague",
    "iso:country":"CZ",
    "wof:name":"Rovnacov",
    "wof:placetype":"locality"
},
  "geometry": {"coordinates":[15.54394,50.56623],"type":"Point"}
}