{
  "type": "Feature",
  "properties": {
    "gn:admin1_code":"78.0",
    "gn:admin2_code":"0627",
    "gn:asciiname":"Budkovice",
    "gn:country_code":"CZ",
    "gn:dem":259,
    "gn:feature_class":"P",
    "gn:feature_code":"PPL",
    "gn:name":"Budkovice",
    "gn:population":0,
    "gn:timezone":"Europe/Prague",
    "iso:country":"CZ",
    "wof:name":"Budkovice",
    "wof:placetype":"locality"
},
  "geometry": {"coordinates":[16.34776,49.07206],"type":"Point"}
}