{
  "type": "Feature",
  "properties": {
    "gn:admin1_code":"81.0",
    "gn:admin2_code":"0413",
    "gn:asciiname":"Davidov",
    "gn:country_code":"CZ",
    "gn:dem":408,
    "gn:feature_class":"P",
    "gn:feature_code":"PPL",
    "gn:name":"Davidov",
    "gn:population":0,
    "gn:timezone":"Europe/Prague",
    "iso:country":"CZ",
    "name:deu_x_preferred":[
        "Davidov"
    ],
    "name:fra_x_preferred":[
        "Davidov"
    ],
    "name:heb_x_preferred":[
        "\u05d3\u05d5\u05d9\u05d3\u05d5\u05d1"
    ],
    "name:ita_x_preferred":[
        "Davidov"
    ],
    "name:srp_x_preferred":[
        "\u0414\u0430\u0432\u0438\u0434\u043e\u0432"
    ],
    "name:und_x_variant":[
        "Davidsthal"
    ],
    "wof:name":"Davidov",
    "wof:placetype":"locality"
},
  "geometry": {"coordinates":[12.61244,50.19127],"type":"Point"}
}