{
  "type": "Feature",
  "properties": {
    "gn:gn_country":"CZ",
    "gn:gn_fcode":"PPL",
    "gn:gn_pop":133,
    "gn:population":133,
    "iso:country":"CZ",
    "name:ceb_x_preferred":[
        "C\u00edrkvice"
    ],
    "name:ces_x_preferred":[
        "C\u00edrkvice"
    ],
    "name:deu_x_preferred":[
        "C\u00edrkvice"
    ],
    "name:fra_x_preferred":[
        "C\u00edrkvice"
    ],
    "name:ita_x_preferred":[
        "C\u00edrkvice"
    ],
    "name:nld_x_preferred":[
        "C\u00edrkvice"
    ],
    "name:pol_x_preferred":[
        "C\u00edrkvice"
    ],
    "name:slk_x_preferred":[
        "C\u00edrkvice"
    ],
    "name:srp_x_preferred":[
        "\u0426\u0438\u0440\u043a\u0432\u0438\u0446\u0435"
    ],
    "name:swe_x_preferred":[
        "C\u00edrkvice"
    ],
    "name:unk_x_variant":[
        "Cirkwitz"
    ],
    "qs_pg:aaroncc":"CZ",
    "qs_pg:gn_country":"CZ",
    "qs_pg:gn_fcode":"PPL",
    "qs_pg:gn_pop":133,
    "qs_pg:name":"C\u00edrkvice",
    "qs_pg:photos_9r":0,
    "qs_pg:photos_sr":0,
    "qs_pg:pop_sr":1,
    "qs_pg:qs_pg_placetype":"locality",
    "wof:name":"C\u00edrkvice",
    "wof:placetype":"locality",
    "wof:population":133
},
  "geometry": {"coordinates":[15.01571,49.90935],"type":"Point"}
}