{
  "type": "Feature",
  "properties": {
    "gn:admin1_code":"80.0",
    "gn:admin2_code":"0614",
    "gn:asciiname":"Jejkov",
    "gn:country_code":"CZ",
    "gn:dem":399,
    "gn:feature_class":"P",
    "gn:feature_code":"PPL",
    "gn:name":"Jejkov",
    "gn:population":0,
    "gn:timezone":"Europe/Prague",
    "iso:country":"CZ",
    "name:ceb_x_preferred":[
        "Jejkov"
    ],
    "name:ces_x_preferred":[
        "Jejkov"
    ],
    "name:pol_x_preferred":[
        "Jejkov"
    ],
    "name:sqi_x_preferred":[
        "Jejkov"
    ],
    "name:swe_x_preferred":[
        "Jejkov"
    ],
    "wof:name":"Jejkov",
    "wof:placetype":"locality"
},
  "geometry": {"coordinates":[15.8864,49.21429000000001],"type":"Point"}
}