{
  "type": "Feature",
  "properties": {
    "gn:admin1_code":"79.0",
    "gn:admin2_code":"0314",
    "gn:asciiname":"Brezi",
    "gn:country_code":"CZ",
    "gn:dem":517,
    "gn:feature_class":"P",
    "gn:feature_code":"PPL",
    "gn:name":"B\u0159ez\u00ed",
    "gn:population":68,
    "gn:timezone":"Europe/Prague",
    "iso:country":"CZ",
    "wof:name":"Brezi",
    "wof:placetype":"locality",
    "wof:population":68
},
  "geometry": {"coordinates":[14.359,49.50024000000001],"type":"Point"}
}