{
  "type": "Feature",
  "properties": {
    "gn:admin1_code":"83.0",
    "gn:admin2_code":"0513",
    "gn:asciiname":"Javornik",
    "gn:country_code":"CZ",
    "gn:dem":409,
    "gn:feature_class":"P",
    "gn:feature_code":"PPL",
    "gn:name":"Javorn\u00edk",
    "gn:population":0,
    "gn:timezone":"Europe/Prague",
    "iso:country":"CZ",
    "name:bos_x_preferred":[
        "Javornik"
    ],
    "name:ceb_x_preferred":[
        "Javornik"
    ],
    "name:deu_x_preferred":[
        "Javornik"
    ],
    "name:fra_x_preferred":[
        "Javornik"
    ],
    "name:hrv_x_preferred":[
        "Javornik"
    ],
    "name:hun_x_preferred":[
        "Javornik"
    ],
    "name:slv_x_preferred":[
        "Javornik"
    ],
    "name:srp_x_preferred":[
        "\u0408\u0430\u0432\u043e\u0440\u043d\u0438\u043a"
    ],
    "name:swe_x_preferred":[
        "Javornik"
    ],
    "wof:name":"Javornik",
    "wof:placetype":"locality"
},
  "geometry": {"coordinates":[14.99289,50.69502],"type":"Point"}
}