{
  "type": "Feature",
  "properties": {
    "gn:admin1_code":"82.0",
    "gn:admin2_code":"0523",
    "gn:asciiname":"Mestec",
    "gn:country_code":"CZ",
    "gn:dem":285,
    "gn:feature_class":"P",
    "gn:feature_code":"PPL",
    "gn:name":"M\u011bstec",
    "gn:population":0,
    "gn:timezone":"Europe/Prague",
    "iso:country":"CZ",
    "wof:name":"Mestec",
    "wof:placetype":"locality"
},
  "geometry": {"coordinates":[16.0534,50.35204],"type":"Point"}
}