{
  "type": "Feature",
  "properties": {
    "gn:admin1_code":"85.0",
    "gn:admin2_code":"0802",
    "gn:asciiname":"Kamenity",
    "gn:country_code":"CZ",
    "gn:dem":771,
    "gn:feature_class":"P",
    "gn:feature_code":"PPL",
    "gn:name":"Kamenit\u00fd",
    "gn:population":0,
    "gn:timezone":"Europe/Prague",
    "iso:country":"CZ",
    "wof:name":"Kamenity",
    "wof:placetype":"locality"
},
  "geometry": {"coordinates":[18.64774,49.56203],"type":"Point"}
}