{
  "type": "Feature",
  "properties": {
    "gn:admin1_code":"79",
    "gn:admin2_code":"0316",
    "gn:asciiname":"Zalesi",
    "gn:country_code":"CZ",
    "gn:dem":726,
    "gn:feature_class":"P",
    "gn:feature_code":"PPL",
    "gn:name":"Z\u00e1les\u00ed",
    "gn:population":0,
    "gn:timezone":"Europe/Prague",
    "iso:country":"CZ",
    "wof:name":"Zalesi",
    "wof:placetype":"locality"
},
  "geometry": {"coordinates":[13.7251,49.16403],"type":"Point"}
}