{
  "type": "Feature",
  "properties": {
    "gn:admin1_code":"88",
    "gn:admin2_code":"0206",
    "gn:asciiname":"Strezivojice",
    "gn:country_code":"CZ",
    "gn:dem":385,
    "gn:feature_class":"P",
    "gn:feature_code":"PPL",
    "gn:name":"St\u0159ezivojice",
    "gn:population":0,
    "gn:timezone":"Europe/Prague",
    "iso:country":"CZ",
    "name:und_x_variant":[
        "Schedoweitz",
        "St\u0159ezivojice"
    ],
    "wof:name":"Strezivojice",
    "wof:placetype":"locality"
},
  "geometry": {"coordinates":[14.55778,50.49126],"type":"Point"}
}