{
  "type": "Feature",
  "properties": {
    "gn:admin1_code":"83.0",
    "gn:admin2_code":"0514",
    "gn:asciiname":"Drahonovice",
    "gn:country_code":"CZ",
    "gn:dem":402,
    "gn:feature_class":"P",
    "gn:feature_code":"PPL",
    "gn:name":"Draho\u0148ovice",
    "gn:population":0,
    "gn:timezone":"Europe/Prague",
    "iso:country":"CZ",
    "wof:name":"Drahonovice",
    "wof:placetype":"locality"
},
  "geometry": {"coordinates":[15.17517,50.53706],"type":"Point"}
}