{
  "type": "Feature",
  "properties": {
    "gn:admin1_code":"88.0",
    "gn:admin2_code":"020B",
    "gn:asciiname":"Radava",
    "gn:country_code":"CZ",
    "gn:dem":352,
    "gn:feature_class":"P",
    "gn:feature_code":"PPL",
    "gn:name":"Radava",
    "gn:population":0,
    "gn:timezone":"Europe/Prague",
    "iso:country":"CZ",
    "wof:name":"Radava",
    "wof:placetype":"locality"
},
  "geometry": {"coordinates":[14.16667,49.53333],"type":"Point"}
}