{
  "type": "Feature",
  "properties": {
    "gn:admin1_code":"82.0",
    "gn:admin2_code":"0525",
    "gn:asciiname":"Prkenny Dul",
    "gn:country_code":"CZ",
    "gn:dem":567,
    "gn:feature_class":"P",
    "gn:feature_code":"PPL",
    "gn:name":"Prkenn\u00fd D\u016fl",
    "gn:population":0,
    "gn:timezone":"Europe/Prague",
    "iso:country":"CZ",
    "wof:name":"Prkenny Dul",
    "wof:placetype":"locality"
},
  "geometry": {"coordinates":[15.91667,50.65],"type":"Point"}
}