{
  "type": "Feature",
  "properties": {
    "gn:admin1_code":"88.0",
    "gn:admin2_code":"0205",
    "gn:asciiname":"Cizov",
    "gn:country_code":"CZ",
    "gn:dem":337,
    "gn:feature_class":"P",
    "gn:feature_code":"PPL",
    "gn:name":"\u010c\u00ed\u017eov",
    "gn:population":0,
    "gn:timezone":"Europe/Prague",
    "iso:country":"CZ",
    "wof:name":"Cizov",
    "wof:placetype":"locality"
},
  "geometry": {"coordinates":[15.04853,49.75125],"type":"Point"}
}