{
  "type": "Feature",
  "properties": {
    "gn:admin1_code":"80",
    "gn:admin2_code":"0612",
    "gn:asciiname":"Zvolenovice",
    "gn:country_code":"CZ",
    "gn:dem":563,
    "gn:feature_class":"P",
    "gn:feature_code":"PPL",
    "gn:name":"Zvolenovice",
    "gn:population":70,
    "gn:timezone":"Europe/Prague",
    "iso:country":"CZ",
    "name:azb_x_preferred":[
        "\u0632\u0648\u0648\u0644\u0646\u0648\u0648\u06cc\u062a\u0633\u0647"
    ],
    "name:ces_x_preferred":[
        "Zvolenovice"
    ],
    "name:eus_x_preferred":[
        "Zvolenovice"
    ],
    "name:fas_x_preferred":[
        "\u0632\u0648\u0648\u0644\u0646\u0648\u0648\u06cc\u062a\u0633\u0647"
    ],
    "name:fra_x_preferred":[
        "Zvolenovice"
    ],
    "name:hun_x_preferred":[
        "Zvolenovice"
    ],
    "name:ita_x_preferred":[
        "Zvolenovice"
    ],
    "name:msa_x_preferred":[
        "Zvolenovice"
    ],
    "name:nld_x_preferred":[
        "Zvolenovice"
    ],
    "name:pol_x_preferred":[
        "Zvolenovice"
    ],
    "name:por_x_preferred":[
        "Zvolenovice"
    ],
    "name:slk_x_preferred":[
        "Zvolenovice"
    ],
    "name:spa_x_preferred":[
        "Zvolenovice"
    ],
    "name:srp_x_preferred":[
        "\u0417\u0432\u043e\u043b\u0435\u043d\u043e\u0432\u0438\u0446\u0435"
    ],
    "name:vie_x_preferred":[
        "Zvolenovice"
    ],
    "wof:name":"Zvolenovice",
    "wof:placetype":"locality",
    "wof:population":70
},
  "geometry": {"coordinates":[15.50557,49.16328],"type":"Point"}
}