{
  "type": "Feature",
  "properties": {
    "gn:admin1_code":"80",
    "gn:admin2_code":"0612",
    "gn:asciiname":"Zvolenovice",
    "gn:country_code":"CZ",
    "gn:dem":563,
    "gn:feature_class":"P",
    "gn:feature_code":"PPL",
    "gn:name":"Zvolenovice",
    "gn:population":70,
    "gn:timezone":"Europe/Prague",
    "iso:country":"CZ",
    "wof:name":"Zvolenovice",
    "wof:placetype":"locality",
    "wof:population":70
},
  "geometry": {"coordinates":[15.50557,49.16328],"type":"Point"}
}