{
  "type": "Feature",
  "properties": {
    "gn:admin1_code":"87",
    "gn:admin2_code":"0321",
    "gn:asciiname":"Stitary",
    "gn:country_code":"CZ",
    "gn:dem":416,
    "gn:feature_class":"P",
    "gn:feature_code":"PPL",
    "gn:name":"\u0160t\u00edtary",
    "gn:population":0,
    "gn:timezone":"Europe/Prague",
    "iso:country":"CZ",
    "name:und_x_variant":[
        "Schitarschen",
        "\u0160t\u00edtary"
    ],
    "wof:name":"Stitary",
    "wof:placetype":"locality"
},
  "geometry": {"coordinates":[12.81646,49.56504],"type":"Point"}
}