{
  "type": "Feature",
  "properties": {
    "gn:admin1_code":"87.0",
    "gn:admin2_code":"0326",
    "gn:asciiname":"Sklena Hut'",
    "gn:country_code":"CZ",
    "gn:dem":509,
    "gn:feature_class":"P",
    "gn:feature_code":"PPL",
    "gn:name":"Sklen\u00e1 Hut\u2019",
    "gn:population":0,
    "gn:timezone":"Europe/Prague",
    "iso:country":"CZ",
    "wof:name":"Sklena Hut'",
    "wof:placetype":"locality"
},
  "geometry": {"coordinates":[13.63379,49.82064],"type":"Point"}
}