{
  "type": "Feature",
  "properties": {
    "gn:gn_country":"CZ",
    "gn:gn_fcode":"PPL",
    "gn:gn_pop":205,
    "gn:population":205,
    "iso:country":"CZ",
    "name:ceb_x_preferred":[
        "Krhov"
    ],
    "name:ces_x_preferred":[
        "Krhov"
    ],
    "name:deu_x_preferred":[
        "Krhov"
    ],
    "name:epo_x_preferred":[
        "Krhov"
    ],
    "name:fra_x_preferred":[
        "Krhov"
    ],
    "name:ita_x_preferred":[
        "Krhov"
    ],
    "name:nld_x_preferred":[
        "Krhov"
    ],
    "name:slk_x_preferred":[
        "Krhov"
    ],
    "name:srp_x_preferred":[
        "\u041a\u0440\u0445\u043e\u0432"
    ],
    "name:swe_x_preferred":[
        "Krhov"
    ],
    "qs_pg:aaroncc":"CZ",
    "qs_pg:gn_country":"CZ",
    "qs_pg:gn_fcode":"PPL",
    "qs_pg:gn_pop":205,
    "qs_pg:name":"Krhov",
    "qs_pg:name_adm0":"\u010cesk\u00e1 republika",
    "qs_pg:name_adm1":"Kraj Vyso\u010dina",
    "qs_pg:photos_9r":0,
    "qs_pg:photos_sr":0,
    "qs_pg:pop_sr":2,
    "qs_pg:qs_pg_placetype":"locality",
    "qs_pg:qs_pg_placetype_gp":"Town",
    "qs_pg:woe_adm0":23424810,
    "woe:adm0_id":23424810,
    "woe:name_adm0":"\u010cesk\u00e1 republika",
    "woe:name_adm1":"Kraj Vyso\u010dina",
    "woe:placetype":"Town",
    "wof:name":"Krhov",
    "wof:placetype":"locality",
    "wof:population":205
},
  "geometry": {"coordinates":[16.01941,49.10034],"type":"Point"}
}