{
  "type": "Feature",
  "properties": {
    "gn:gn_country":"CZ",
    "gn:gn_fcode":"PPL",
    "gn:gn_pop":402,
    "gn:population":402,
    "iso:country":"CZ",
    "name:azb_x_preferred":[
        "\u0633\u062a\u0648\u062f\u0627\u0646\u06a9\u0627"
    ],
    "name:ceb_x_preferred":[
        "Stud\u00e1nka"
    ],
    "name:ces_x_preferred":[
        "Stud\u00e1nka"
    ],
    "name:deu_x_preferred":[
        "Stud\u00e1nka"
    ],
    "name:eng_x_preferred":[
        "Stud\u00e1nka"
    ],
    "name:eus_x_preferred":[
        "Stud\u00e1nka"
    ],
    "name:fas_x_preferred":[
        "\u0633\u062a\u0648\u062f\u0627\u0646\u06a9\u0627"
    ],
    "name:fra_x_preferred":[
        "Stud\u00e1nka"
    ],
    "name:hun_x_preferred":[
        "Stud\u00e1nka"
    ],
    "name:ita_x_preferred":[
        "Stud\u00e1nka"
    ],
    "name:msa_x_preferred":[
        "Stud\u00e1nka"
    ],
    "name:nan_x_preferred":[
        "Stud\u00e1nka"
    ],
    "name:nld_x_preferred":[
        "Stud\u00e1nka"
    ],
    "name:por_x_preferred":[
        "Stud\u00e1nka"
    ],
    "name:rup_x_preferred":[
        "Stud\u00e1nka"
    ],
    "name:slk_x_preferred":[
        "Stud\u00e1nka"
    ],
    "name:spa_x_preferred":[
        "Stud\u00e1nka"
    ],
    "name:srp_x_preferred":[
        "\u0421\u0442\u0443\u0434\u0430\u043d\u043a\u0430"
    ],
    "name:swe_x_preferred":[
        "Stud\u00e1nka"
    ],
    "name:unk_x_variant":[
        "Schoenbrunn"
    ],
    "name:vie_x_preferred":[
        "Stud\u00e1nka"
    ],
    "qs_pg:aaroncc":"CZ",
    "qs_pg:gn_country":"CZ",
    "qs_pg:gn_fcode":"PPL",
    "qs_pg:gn_pop":402,
    "qs_pg:name":"Stud\u00e1nka",
    "qs_pg:name_adm0":"\u010cesk\u00e1 republika",
    "qs_pg:name_adm1":"Plze\u0148sk\u00fd kraj",
    "qs_pg:photos_9r":0,
    "qs_pg:photos_sr":0,
    "qs_pg:pop_sr":2,
    "qs_pg:qs_pg_placetype":"locality",
    "qs_pg:qs_pg_placetype_gp":"Town",
    "qs_pg:woe_adm0":23424810,
    "woe:adm0_id":23424810,
    "woe:name_adm0":"\u010cesk\u00e1 republika",
    "woe:name_adm1":"Plze\u0148sk\u00fd kraj",
    "woe:placetype":"Town",
    "wof:name":"Stud\u00e1nka",
    "wof:placetype":"locality",
    "wof:population":402
},
  "geometry": {"coordinates":[12.60367,49.78057],"type":"Point"}
}