{
  "type": "Feature",
  "properties": {
    "iso:country":"CZ",
    "name:ceb_x_preferred":[
        "Opo\u010dno"
    ],
    "name:ces_x_preferred":[
        "Opo\u010dno"
    ],
    "name:deu_x_preferred":[
        "Opo\u010dno"
    ],
    "name:epo_x_preferred":[
        "Opo\u010dno"
    ],
    "name:eus_x_preferred":[
        "Opo\u010dno"
    ],
    "name:fas_x_preferred":[
        "\u0627\u0648\u067e\u0648\u062a\u0634\u0646\u0648"
    ],
    "name:fra_x_preferred":[
        "Opo\u010dno"
    ],
    "name:hun_x_preferred":[
        "Opo\u010dno"
    ],
    "name:ita_x_preferred":[
        "Opo\u010dno"
    ],
    "name:kor_x_preferred":[
        "\uc624\ud3ec\uce58\ub178"
    ],
    "name:msa_x_preferred":[
        "Opo\u010dno"
    ],
    "name:nld_x_preferred":[
        "Opo\u010dno"
    ],
    "name:pol_x_preferred":[
        "Opo\u010dno"
    ],
    "name:por_x_preferred":[
        "Opo\u010dno"
    ],
    "name:rus_x_preferred":[
        "\u041e\u043f\u043e\u0447\u043d\u043e"
    ],
    "name:slk_x_preferred":[
        "Opo\u010dno"
    ],
    "name:spa_x_preferred":[
        "Opo\u010dno"
    ],
    "name:srp_x_preferred":[
        "\u041e\u043f\u043e\u0447\u043d\u043e"
    ],
    "name:urd_x_preferred":[
        "\u0627\u0648\u067e\u0648\u0686\u0646\u0648"
    ],
    "name:vie_x_preferred":[
        "Opo\u010dno"
    ],
    "name:zho_x_preferred":[
        "\u5967\u6ce2\u5947\u8afe"
    ],
    "qs_pg:aaroncc":"CZ",
    "qs_pg:name":"Opo\u010dno",
    "qs_pg:name_adm0":"\u010cesk\u00e1 republika",
    "qs_pg:name_adm1":"Kr\u00e1lov\u00e9hradeck\u00fd kraj",
    "qs_pg:photos":8,
    "qs_pg:photos_1k":2,
    "qs_pg:photos_9k":1,
    "qs_pg:photos_9r":2,
    "qs_pg:photos_all":57,
    "qs_pg:photos_sr":1,
    "qs_pg:pop_sr":0,
    "qs_pg:qs_pg_placetype":"localadmin",
    "qs_pg:qs_pg_placetype_gp":"LocalAdmin",
    "qs_pg:woe_adm0":23424810,
    "woe:adm0_id":23424810,
    "woe:name_adm0":"\u010cesk\u00e1 republika",
    "woe:name_adm1":"Kr\u00e1lov\u00e9hradeck\u00fd kraj",
    "woe:placetype":"LocalAdmin",
    "wof:name":"Opo\u010dno",
    "wof:placetype":"localadmin"
},
  "geometry": {"coordinates":[16.113166,50.267124],"type":"Point"}
}