{
  "type": "Feature",
  "properties": {
    "gn:admin1_code":"88.0",
    "gn:admin2_code":"0204",
    "gn:asciiname":"Pobori",
    "gn:country_code":"CZ",
    "gn:dem":253,
    "gn:feature_class":"P",
    "gn:feature_code":"PPL",
    "gn:name":"Pobo\u0159\u00ed",
    "gn:population":0,
    "gn:timezone":"Europe/Prague",
    "iso:country":"CZ",
    "wof:name":"Pobori",
    "wof:placetype":"locality"
},
  "geometry": {"coordinates":[15.04882,50.02451],"type":"Point"}
}