{
  "type": "Feature",
  "properties": {
    "gn:gn_country":"CZ",
    "gn:gn_fcode":"PPLX",
    "gn:gn_pop":23034,
    "gn:population":23034,
    "iso:country":"CZ",
    "name:cze_x_preferred":[
        "Star\u00fd Bohum\u00edn"
    ],
    "name:deu_x_preferred":[
        "Oderberg"
    ],
    "name:dut_x_preferred":[
        "Star\u00fd Bohum\u00edn"
    ],
    "name:eng_x_preferred":[
        "Star\u00fd Bohum\u00edn"
    ],
    "name:epo_x_preferred":[
        "Star\u00fd Bohum\u00edn"
    ],
    "name:fre_x_preferred":[
        "Star\u00fd Bohum\u00edn"
    ],
    "name:pol_x_preferred":[
        "Stary Bogumin"
    ],
    "name:swe_x_preferred":[
        "Star\u00fd Bohum\u00edn"
    ],
    "name:unk_x_variant":[
        "Bogumin"
    ],
    "qs_pg:aaroncc":"CZ",
    "qs_pg:gn_country":"CZ",
    "qs_pg:gn_fcode":"PPLX",
    "qs_pg:gn_pop":23034,
    "qs_pg:name":"Star\u00fd Bohum\u00edn",
    "qs_pg:photos_9r":0,
    "qs_pg:photos_sr":0,
    "qs_pg:pop_sr":7,
    "qs_pg:qs_pg_placetype":"neighbourhood",
    "wof:name":"Star\u00fd Bohum\u00edn",
    "wof:placetype":"neighbourhood",
    "wof:population":23034
},
  "geometry": {"coordinates":[18.33619,49.9169],"type":"Point"}
}