{
  "type": "Feature",
  "properties": {
    "iso:country":"CZ",
    "name:azb_x_preferred":[
        "\u0632\u062f\u0645\u06cc\u0633\u0644\u06cc\u062a\u0633\u0647"
    ],
    "name:ceb_x_preferred":[
        "Zdemyslice"
    ],
    "name:ces_x_preferred":[
        "Zdemyslice"
    ],
    "name:eus_x_preferred":[
        "Zdemyslice"
    ],
    "name:fas_x_preferred":[
        "\u0632\u062f\u0645\u06cc\u0633\u0644\u06cc\u062a\u0633\u0647"
    ],
    "name:fra_x_preferred":[
        "Zdemyslice"
    ],
    "name:hun_x_preferred":[
        "Zdemyslice"
    ],
    "name:ita_x_preferred":[
        "Zdemyslice"
    ],
    "name:msa_x_preferred":[
        "Zdemyslice"
    ],
    "name:nld_x_preferred":[
        "Zdemyslice"
    ],
    "name:pol_x_preferred":[
        "Zdemyslice"
    ],
    "name:por_x_preferred":[
        "Zdemyslice"
    ],
    "name:slk_x_preferred":[
        "Zdemyslice"
    ],
    "name:spa_x_preferred":[
        "Zdemyslice"
    ],
    "name:srp_x_preferred":[
        "\u0417\u0434\u0435\u043c\u0438\u0441\u043b\u0438\u0446\u0435"
    ],
    "name:swe_x_preferred":[
        "Zdemyslice"
    ],
    "name:vie_x_preferred":[
        "Zdemyslice"
    ],
    "qs_pg:aaroncc":"CZ",
    "qs_pg:name":"Zdemyslice",
    "qs_pg:name_adm0":"\u010cesk\u00e1 republika",
    "qs_pg:name_adm1":"Plze\u0148sk\u00fd kraj",
    "qs_pg:photos":80,
    "qs_pg:photos_1k":16,
    "qs_pg:photos_9k":1,
    "qs_pg:photos_9r":3,
    "qs_pg:photos_all":80,
    "qs_pg:photos_sr":3,
    "qs_pg:pop_sr":0,
    "qs_pg:qs_pg_placetype":"localadmin",
    "qs_pg:qs_pg_placetype_gp":"LocalAdmin",
    "qs_pg:woe_adm0":23424810,
    "woe:adm0_id":23424810,
    "woe:name_adm0":"\u010cesk\u00e1 republika",
    "woe:name_adm1":"Plze\u0148sk\u00fd kraj",
    "woe:placetype":"LocalAdmin",
    "wof:name":"Zdemyslice",
    "wof:placetype":"localadmin"
},
  "geometry": {"coordinates":[13.521015,49.601421],"type":"Point"}
}