{
  "type": "Feature",
  "properties": {
    "gn:gn_country":"CZ",
    "gn:gn_fcode":"PPL",
    "gn:gn_pop":291,
    "gn:population":291,
    "iso:country":"CZ",
    "name:ces_x_preferred":[
        "Nebanice"
    ],
    "name:deu_x_preferred":[
        "Nebanice"
    ],
    "name:eng_x_preferred":[
        "Nebanice"
    ],
    "name:fas_x_preferred":[
        "\u0646\u0628\u0627\u0646\u06cc\u062a\u0633\u0647"
    ],
    "name:fra_x_preferred":[
        "Nebanice"
    ],
    "name:hun_x_preferred":[
        "Nebanice"
    ],
    "name:ita_x_preferred":[
        "Nebanice"
    ],
    "name:msa_x_preferred":[
        "Nebanice"
    ],
    "name:nld_x_preferred":[
        "Nebanice"
    ],
    "name:pol_x_preferred":[
        "Nebanice"
    ],
    "name:por_x_preferred":[
        "Nebanice"
    ],
    "name:slk_x_preferred":[
        "Nebanice"
    ],
    "name:srp_x_preferred":[
        "\u041d\u0435\u0431\u0430\u045a\u0438\u0446\u0435"
    ],
    "name:swe_x_preferred":[
        "Nebanice"
    ],
    "name:vie_x_preferred":[
        "Nebanice"
    ],
    "qs_pg:aaroncc":"CZ",
    "qs_pg:gn_country":"CZ",
    "qs_pg:gn_fcode":"PPL",
    "qs_pg:gn_pop":291,
    "qs_pg:name":"Nebanice",
    "qs_pg:name_adm0":"\u010cesk\u00e1 republika",
    "qs_pg:name_adm1":"Karlovarsk\u00fd kraj",
    "qs_pg:photos_9k":1,
    "qs_pg:photos_9r":1,
    "qs_pg:photos_all":1,
    "qs_pg:photos_sr":0,
    "qs_pg:pop_sr":2,
    "qs_pg:qs_pg_placetype":"locality",
    "qs_pg:qs_pg_placetype_gp":"Town",
    "qs_pg:woe_adm0":23424810,
    "woe:adm0_id":23424810,
    "woe:name_adm0":"\u010cesk\u00e1 republika",
    "woe:name_adm1":"Karlovarsk\u00fd kraj",
    "woe:placetype":"Town",
    "wof:name":"Nebanice",
    "wof:placetype":"locality",
    "wof:population":291
},
  "geometry": {"coordinates":[12.47197,50.11524],"type":"Point"}
}