{
  "type": "Feature",
  "properties": {
    "gn:gn_country":"CZ",
    "gn:gn_fcode":"PPL",
    "gn:gn_pop":144,
    "gn:population":144,
    "iso:country":"CZ",
    "name:cze_x_preferred":[
        "Dob\u0159e\u0148"
    ],
    "name:dut_x_preferred":[
        "Dob\u0159e\u0148"
    ],
    "name:eng_x_preferred":[
        "Dob\u0159e\u0148"
    ],
    "name:fre_x_preferred":[
        "Dob\u0159e\u0148"
    ],
    "name:hun_x_preferred":[
        "Dob\u0159e\u0148"
    ],
    "name:ita_x_preferred":[
        "Dob\u0159e\u0148"
    ],
    "name:may_x_preferred":[
        "Dob\u0159e\u0148"
    ],
    "name:pol_x_preferred":[
        "Dob\u0159e\u0148"
    ],
    "name:por_x_preferred":[
        "Dob\u0159e\u0148"
    ],
    "name:slo_x_preferred":[
        "Dob\u0159e\u0148"
    ],
    "name:srp_x_preferred":[
        "\u0414\u043e\u0431\u0440\u0435\u045a"
    ],
    "name:swe_x_preferred":[
        "Dob\u0159e\u0148"
    ],
    "name:vie_x_preferred":[
        "Dob\u0159e\u0148"
    ],
    "qs_pg:aaroncc":"CZ",
    "qs_pg:gn_country":"CZ",
    "qs_pg:gn_fcode":"PPL",
    "qs_pg:gn_pop":144,
    "qs_pg:name":"Dob\u0159e\u0148",
    "qs_pg:name_adm0":"\u010cesk\u00e1 republika",
    "qs_pg:name_adm1":"St\u0159edo\u010desk\u00fd kraj",
    "qs_pg:photos_9k":1,
    "qs_pg:photos_9r":1,
    "qs_pg:photos_all":5,
    "qs_pg:photos_sr":0,
    "qs_pg:pop_sr":1,
    "qs_pg:qs_pg_placetype":"locality",
    "qs_pg:qs_pg_placetype_gp":"Town",
    "qs_pg:woe_adm0":23424810,
    "woe:adm0_id":23424810,
    "woe:name_adm0":"\u010cesk\u00e1 republika",
    "woe:name_adm1":"St\u0159edo\u010desk\u00fd kraj",
    "woe:placetype":"Town",
    "wof:name":"Dob\u0159e\u0148",
    "wof:placetype":"locality",
    "wof:population":144
},
  "geometry": {"coordinates":[14.5567,50.4794],"type":"Point"}
}