{
  "type": "Feature",
  "properties": {
    "gn:admin1_code":"82",
    "gn:admin2_code":"0522",
    "gn:asciiname":"Udrnicka Lhota",
    "gn:country_code":"CZ",
    "gn:dem":280,
    "gn:feature_class":"P",
    "gn:feature_code":"PPL",
    "gn:name":"\u00dadrnick\u00e1 Lhota",
    "gn:population":0,
    "gn:timezone":"Europe/Prague",
    "iso:country":"CZ",
    "wof:name":"Udrnicka Lhota",
    "wof:placetype":"locality"
},
  "geometry": {"coordinates":[15.27043,50.37022],"type":"Point"}
}