{
  "type": "Feature",
  "properties": {
    "gn:admin1_code":"79",
    "gn:admin2_code":"0312",
    "gn:asciiname":"Velke Strazne",
    "gn:country_code":"CZ",
    "gn:dem":678,
    "gn:feature_class":"P",
    "gn:feature_code":"PPL",
    "gn:name":"Velk\u00e9 Str\u00e1\u017en\u00e9",
    "gn:population":0,
    "gn:timezone":"Europe/Prague",
    "iso:country":"CZ",
    "name:und_x_variant":[
        "Gross Drossen",
        "Velk\u00e9 Str\u00e1\u017en\u00e9"
    ],
    "wof:name":"Velke Strazne",
    "wof:placetype":"locality"
},
  "geometry": {"coordinates":[14.24586,48.74079],"type":"Point"}
}