{
  "type": "Feature",
  "properties": {
    "iso:country":"CZ",
    "name:arm_x_preferred":[
        "\u053c\u056b\u057a\u0565\u0576\u0581\u0565"
    ],
    "name:cze_x_preferred":[
        "Lipence"
    ],
    "name:dut_x_preferred":[
        "Praag-Lipence"
    ],
    "name:eng_x_preferred":[
        "Lipence"
    ],
    "name:fre_x_preferred":[
        "Lipence"
    ],
    "name:pol_x_preferred":[
        "Lipence"
    ],
    "name:slo_x_preferred":[
        "Lipence"
    ],
    "wof:name":"Lipence",
    "wof:placetype":"neighbourhood"
},
  "geometry": {"coordinates":[14.35356918735674,49.96051388462363],"type":"Point"}
}