{
  "type": "Feature",
  "properties": {
    "gn:admin1_code":"79.0",
    "gn:admin2_code":"0314",
    "gn:asciiname":"Mirec",
    "gn:country_code":"CZ",
    "gn:dem":421,
    "gn:feature_class":"P",
    "gn:feature_code":"PPL",
    "gn:name":"M\u00edre\u010d",
    "gn:population":0,
    "gn:timezone":"Europe/Prague",
    "iso:country":"CZ",
    "wof:name":"Mirec",
    "wof:placetype":"locality"
},
  "geometry": {"coordinates":[13.98499,49.43203],"type":"Point"}
}