{
  "type": "Feature",
  "properties": {
    "gn:gn_country":"CZ",
    "gn:gn_fcode":"PPL",
    "gn:gn_pop":940,
    "gn:population":940,
    "iso:country":"CZ",
    "name:ces_x_preferred":[
        "Prak\u0161ice"
    ],
    "name:deu_x_preferred":[
        "Prak\u0161ice"
    ],
    "name:eng_x_preferred":[
        "Prak\u0161ice"
    ],
    "name:fas_x_preferred":[
        "\u067e\u0631\u0627\u06a9\u0634\u06cc\u062a\u0633\u0647"
    ],
    "name:fra_x_preferred":[
        "Prak\u0161ice"
    ],
    "name:hun_x_preferred":[
        "Prak\u0161ice"
    ],
    "name:ita_x_preferred":[
        "Prak\u0161ice"
    ],
    "name:msa_x_preferred":[
        "Prak\u0161ice"
    ],
    "name:nld_x_preferred":[
        "Prak\u0161ice"
    ],
    "name:pol_x_preferred":[
        "Prak\u0161ice"
    ],
    "name:por_x_preferred":[
        "Prak\u0161ice"
    ],
    "name:rup_x_preferred":[
        "Prak\u0161ice"
    ],
    "name:slk_x_preferred":[
        "Prak\u0161ice"
    ],
    "name:srp_x_preferred":[
        "\u041f\u0440\u0430\u043a\u0448\u0438\u0446\u0435"
    ],
    "name:swe_x_preferred":[
        "Prak\u0161ice"
    ],
    "name:vie_x_preferred":[
        "Prak\u0161ice"
    ],
    "qs_pg:aaroncc":"CZ",
    "qs_pg:gn_country":"CZ",
    "qs_pg:gn_fcode":"PPL",
    "qs_pg:gn_pop":940,
    "qs_pg:name":"Prak\u0161ice",
    "qs_pg:name_adm0":"\u010cesk\u00e1 republika",
    "qs_pg:name_adm1":"Zl\u00ednsk\u00fd kraj",
    "qs_pg:photos_9r":0,
    "qs_pg:photos_sr":0,
    "qs_pg:pop_sr":2,
    "qs_pg:qs_pg_placetype":"locality",
    "qs_pg:qs_pg_placetype_gp":"Town",
    "qs_pg:woe_adm0":23424810,
    "woe:adm0_id":23424810,
    "woe:name_adm0":"\u010cesk\u00e1 republika",
    "woe:name_adm1":"Zl\u00ednsk\u00fd kraj",
    "woe:placetype":"Town",
    "wof:name":"Prak\u0161ice",
    "wof:placetype":"locality",
    "wof:population":940
},
  "geometry": {"coordinates":[17.63303,49.0689],"type":"Point"}
}