{
  "type": "Feature",
  "properties": {
    "gn:admin1_code":"80.0",
    "gn:admin2_code":"0613",
    "gn:asciiname":"Chlovy",
    "gn:country_code":"CZ",
    "gn:dem":506,
    "gn:feature_class":"P",
    "gn:feature_code":"PPL",
    "gn:name":"Chlovy",
    "gn:population":0,
    "gn:timezone":"Europe/Prague",
    "iso:country":"CZ",
    "wof:name":"Chlovy",
    "wof:placetype":"locality"
},
  "geometry": {"coordinates":[15.14325,49.59036],"type":"Point"}
}