{
  "type": "Feature",
  "properties": {
    "gn:admin1_code":"87.0",
    "gn:admin2_code":"0321",
    "gn:asciiname":"Ohnist'ovice",
    "gn:cc2":"CZ",
    "gn:country_code":"CZ",
    "gn:dem":400,
    "gn:feature_class":"P",
    "gn:feature_code":"PPL",
    "gn:name":"Ohni\u0161\u0165ovice",
    "gn:population":0,
    "gn:timezone":"Europe/Prague",
    "iso:country":"CZ",
    "name:und_x_variant":[
        "Wonischen"
    ],
    "wof:name":"Ohnist'ovice",
    "wof:placetype":"locality"
},
  "geometry": {"coordinates":[12.84422,49.50314],"type":"Point"}
}