{
  "type": "Feature",
  "properties": {
    "gn:admin1_code":"87.0",
    "gn:admin2_code":"0321",
    "gn:asciiname":"Mlynec",
    "gn:cc2":"CZ",
    "gn:country_code":"CZ",
    "gn:dem":463,
    "gn:feature_class":"P",
    "gn:feature_code":"PPL",
    "gn:name":"Ml\u00fdnec",
    "gn:population":0,
    "gn:timezone":"Europe/Prague",
    "iso:country":"CZ",
    "name:und_x_variant":[
        "Linz"
    ],
    "wof:name":"Mlynec",
    "wof:placetype":"locality"
},
  "geometry": {"coordinates":[12.80302,49.46087],"type":"Point"}
}