{
  "type": "Feature",
  "properties": {
    "gn:admin1_code":"80.0",
    "gn:admin2_code":"0614",
    "gn:asciiname":"Biskupice",
    "gn:country_code":"CZ",
    "gn:dem":378,
    "gn:feature_class":"P",
    "gn:feature_code":"PPL",
    "gn:name":"Biskupice",
    "gn:population":0,
    "gn:timezone":"Europe/Prague",
    "iso:country":"CZ",
    "name:und_x_variant":[
        "Biskupitz",
        "Biskupice"
    ],
    "wof:name":"Biskupice",
    "wof:placetype":"locality"
},
  "geometry": {"coordinates":[16.01006,49.03748],"type":"Point"}
}