{
  "type": "Feature",
  "properties": {
    "gn:admin1_code":"80.0",
    "gn:admin2_code":"0614",
    "gn:asciiname":"Biskupice",
    "gn:country_code":"CZ",
    "gn:dem":378,
    "gn:feature_class":"P",
    "gn:feature_code":"PPL",
    "gn:name":"Biskupice",
    "gn:population":0,
    "gn:timezone":"Europe/Prague",
    "iso:country":"CZ",
    "name:ceb_x_preferred":[
        "Biskupice"
    ],
    "name:ces_x_preferred":[
        "Biskupice"
    ],
    "name:deu_x_preferred":[
        "Biskupice"
    ],
    "name:epo_x_preferred":[
        "Biskupice"
    ],
    "name:fra_x_preferred":[
        "Biskupice"
    ],
    "name:hun_x_preferred":[
        "Biskupice"
    ],
    "name:ita_x_preferred":[
        "Biskupice"
    ],
    "name:nld_x_preferred":[
        "Biskupice"
    ],
    "name:pol_x_preferred":[
        "Biskupice"
    ],
    "name:rus_x_preferred":[
        "\u0411\u0438\u0441\u043a\u0443\u043f\u0438\u0446\u0435"
    ],
    "name:slk_x_preferred":[
        "Biskupice"
    ],
    "name:spa_x_preferred":[
        "Biskupice"
    ],
    "name:srp_x_preferred":[
        "\u0411\u0438\u0441\u043a\u0443\u043f\u0438\u0446\u0435"
    ],
    "name:swe_x_preferred":[
        "Biskupice"
    ],
    "name:ukr_x_preferred":[
        "\u0411\u0456\u0441\u043a\u0443\u043f\u0456\u0446\u0435"
    ],
    "name:und_x_variant":[
        "Biskupitz"
    ],
    "wof:name":"Biskupice",
    "wof:placetype":"locality"
},
  "geometry": {"coordinates":[16.01006,49.03748],"type":"Point"}
}