{
  "type": "Feature",
  "properties": {
    "iso:country":"CZ",
    "name:azb_x_preferred":[
        "\u06a9\u0648\u0646\u0648\u0627\u0644\u062f"
    ],
    "name:ceb_x_preferred":[
        "Kunvald"
    ],
    "name:ces_x_preferred":[
        "Kunvald"
    ],
    "name:deu_x_preferred":[
        "Kunvald"
    ],
    "name:epo_x_preferred":[
        "Kunvald"
    ],
    "name:eus_x_preferred":[
        "Kunvald"
    ],
    "name:fas_x_preferred":[
        "\u06a9\u0648\u0646\u0648\u0627\u0644\u062f"
    ],
    "name:fra_x_preferred":[
        "Kunvald"
    ],
    "name:hun_x_preferred":[
        "Kunvald"
    ],
    "name:ita_x_preferred":[
        "Kunvald"
    ],
    "name:msa_x_preferred":[
        "Kunvald"
    ],
    "name:nld_x_preferred":[
        "Kunvald"
    ],
    "name:nor_x_preferred":[
        "Kunvald"
    ],
    "name:pol_x_preferred":[
        "Kunvald"
    ],
    "name:por_x_preferred":[
        "Kunvald"
    ],
    "name:slk_x_preferred":[
        "Kunvald"
    ],
    "name:spa_x_preferred":[
        "Kunvald"
    ],
    "name:srp_x_preferred":[
        "\u041a\u0443\u043d\u0432\u0430\u043b\u0434"
    ],
    "name:vie_x_preferred":[
        "Kunvald"
    ],
    "qs_pg:aaroncc":"CZ",
    "qs_pg:name":"Kunvald",
    "qs_pg:name_adm0":"\u010cesk\u00e1 republika",
    "qs_pg:name_adm1":"Pardubick\u00fd kraj",
    "qs_pg:photos":1,
    "qs_pg:photos_1k":1,
    "qs_pg:photos_9k":1,
    "qs_pg:photos_9r":1,
    "qs_pg:photos_all":1,
    "qs_pg:photos_sr":1,
    "qs_pg:pop_sr":0,
    "qs_pg:qs_pg_placetype":"localadmin",
    "qs_pg:qs_pg_placetype_gp":"LocalAdmin",
    "qs_pg:woe_adm0":23424810,
    "woe:adm0_id":23424810,
    "woe:name_adm0":"\u010cesk\u00e1 republika",
    "woe:name_adm1":"Pardubick\u00fd kraj",
    "woe:placetype":"LocalAdmin",
    "wof:name":"Kunvald",
    "wof:placetype":"localadmin"
},
  "geometry": {"coordinates":[16.49996,50.12927],"type":"Point"}
}