{
  "type": "Feature",
  "properties": {
    "gn:admin1_code":"79.0",
    "gn:admin2_code":"0313",
    "gn:asciiname":"Kolence",
    "gn:country_code":"CZ",
    "gn:dem":432,
    "gn:feature_class":"P",
    "gn:feature_code":"PPL",
    "gn:name":"Kolence",
    "gn:population":0,
    "gn:timezone":"Europe/Prague",
    "iso:country":"CZ",
    "name:und_x_variant":[
        "Kolenetz"
    ],
    "wof:name":"Kolence",
    "wof:placetype":"locality"
},
  "geometry": {"coordinates":[14.78949,49.09107],"type":"Point"}
}