{
  "type": "Feature",
  "properties": {
    "gn:admin1_code":"87.0",
    "gn:admin2_code":"0327",
    "gn:asciiname":"Girnberg",
    "gn:country_code":"CZ",
    "gn:dem":636,
    "gn:feature_class":"P",
    "gn:feature_code":"PPL",
    "gn:name":"Girnberg",
    "gn:population":0,
    "gn:timezone":"Europe/Prague",
    "iso:country":"CZ",
    "wof:name":"Girnberg",
    "wof:placetype":"locality"
},
  "geometry": {"coordinates":[12.53537,49.78069],"type":"Point"}
}