{
  "type": "Feature",
  "properties": {
    "gn:admin1_code":"88.0",
    "gn:admin2_code":"0205",
    "gn:asciiname":"Cenovice",
    "gn:country_code":"CZ",
    "gn:dem":463,
    "gn:feature_class":"P",
    "gn:feature_code":"PPL",
    "gn:name":"\u010cenovice",
    "gn:population":0,
    "gn:timezone":"Europe/Prague",
    "iso:country":"CZ",
    "wof:name":"Cenovice",
    "wof:placetype":"locality"
},
  "geometry": {"coordinates":[15.11476,49.79507],"type":"Point"}
}