{
  "type": "Feature",
  "properties": {
    "iso:country":"CZ",
    "name:ceb_x_preferred":[
        "Senec"
    ],
    "name:ces_x_preferred":[
        "Senec"
    ],
    "name:fra_x_preferred":[
        "Senec"
    ],
    "name:nld_x_preferred":[
        "Senec"
    ],
    "name:rus_x_preferred":[
        "\u0421\u0435\u043d\u0435\u0446"
    ],
    "name:swe_x_preferred":[
        "Senec"
    ],
    "name:ukr_x_preferred":[
        "\u0421\u0435\u043d\u0435\u0446\u044c"
    ],
    "name:unk_x_variant":[
        "Senec"
    ],
    "qs:gn_fcode":"PPL",
    "qs:gn_local":0,
    "qs:gn_namadm1":"87",
    "qs:gn_name":"Senec",
    "qs:local_max":1309,
    "qs:local_sum":4721,
    "qs:localhoods":13,
    "qs:name":"Senec",
    "qs:name_adm0":"\u010cesk\u00e1 republika",
    "qs:name_adm1":"Plze\u0148sk\u00fd kraj",
    "qs:name_adm2":"Plze\u0148-M\u011bsto",
    "qs:name_lau":"Plze\u0148",
    "qs:name_local":"Plze\u0148",
    "qs:photo_max":175,
    "qs:photo_sum":228,
    "qs:placetype":"Suburb",
    "qs:quad_count":14,
    "qs:woe_adm0":23424810,
    "qs:woe_adm1":20070501,
    "qs:woe_adm2":12582609,
    "qs:woe_lau":12610042,
    "qs:woe_local":12610042,
    "qs:woe_ver":"7.10.0",
    "wof:lang":[
        "cze"
    ],
    "wof:name":"Senec",
    "wof:placetype":"neighbourhood"
},
  "geometry": {"coordinates":[13.411519,49.804553],"type":"Point"}
}