{
  "type": "Feature",
  "properties": {
    "gn:admin1_code":"87.0",
    "gn:admin2_code":"0325",
    "gn:asciiname":"Dolni Sekyrany",
    "gn:country_code":"CZ",
    "gn:dem":363,
    "gn:feature_class":"P",
    "gn:feature_code":"PPL",
    "gn:name":"Doln\u00ed Seky\u0159any",
    "gn:population":0,
    "gn:timezone":"Europe/Prague",
    "iso:country":"CZ",
    "name:und_x_variant":[
        "Unter-Sekeran"
    ],
    "wof:name":"Dolni Sekyrany",
    "wof:placetype":"locality"
},
  "geometry": {"coordinates":[13.10429,49.70472],"type":"Point"}
}