{
  "type": "Feature",
  "properties": {
    "gn:gn_country":"CZ",
    "gn:gn_fcode":"PPL",
    "gn:gn_pop":306,
    "gn:population":306,
    "iso:country":"CZ",
    "name:ces_x_preferred":[
        "Vyk\u00e1\u0148"
    ],
    "name:deu_x_preferred":[
        "Vyk\u00e1\u0148"
    ],
    "name:eng_x_preferred":[
        "Vyk\u00e1\u0148"
    ],
    "name:fra_x_preferred":[
        "Vyk\u00e1\u0148"
    ],
    "name:hun_x_preferred":[
        "Vyk\u00e1\u0148"
    ],
    "name:ita_x_preferred":[
        "Vyk\u00e1\u0148"
    ],
    "name:msa_x_preferred":[
        "Vyk\u00e1\u0148"
    ],
    "name:nan_x_preferred":[
        "Vyk\u00e1\u0148"
    ],
    "name:nld_x_preferred":[
        "Vyk\u00e1\u0148"
    ],
    "name:pol_x_preferred":[
        "Vyk\u00e1\u0148"
    ],
    "name:por_x_preferred":[
        "Vyk\u00e1\u0148"
    ],
    "name:rup_x_preferred":[
        "Vyk\u00e1\u0148"
    ],
    "name:slk_x_preferred":[
        "Vyk\u00e1\u0148"
    ],
    "name:srp_x_preferred":[
        "\u0412\u0438\u043a\u0430\u045a"
    ],
    "name:swe_x_preferred":[
        "Vyk\u00e1\u0148"
    ],
    "name:vie_x_preferred":[
        "Vyk\u00e1\u0148"
    ],
    "qs_pg:aaroncc":"CZ",
    "qs_pg:gn_country":"CZ",
    "qs_pg:gn_fcode":"PPL",
    "qs_pg:gn_pop":306,
    "qs_pg:name":"Vyk\u00e1\u0148",
    "qs_pg:name_adm0":"\u010cesk\u00e1 republika",
    "qs_pg:name_adm1":"St\u0159edo\u010desk\u00fd kraj",
    "qs_pg:photos_9r":0,
    "qs_pg:photos_sr":0,
    "qs_pg:pop_sr":2,
    "qs_pg:qs_pg_placetype":"locality",
    "qs_pg:qs_pg_placetype_gp":"Town",
    "qs_pg:woe_adm0":23424810,
    "woe:adm0_id":23424810,
    "woe:name_adm0":"\u010cesk\u00e1 republika",
    "woe:name_adm1":"St\u0159edo\u010desk\u00fd kraj",
    "woe:placetype":"Town",
    "wof:name":"Vyk\u00e1\u0148",
    "wof:placetype":"locality",
    "wof:population":306
},
  "geometry": {"coordinates":[14.81668,50.11986],"type":"Point"}
}