{
  "type": "Feature",
  "properties": {
    "gn:admin1_code":"79.0",
    "gn:admin2_code":"0311",
    "gn:asciiname":"Shon",
    "gn:country_code":"CZ",
    "gn:dem":525,
    "gn:feature_class":"P",
    "gn:feature_code":"PPL",
    "gn:name":"Shon",
    "gn:population":0,
    "gn:timezone":"Europe/Prague",
    "iso:country":"CZ",
    "name:tat_x_preferred":[
        "\u0428\u043e\u043d"
    ],
    "wof:name":"Shon",
    "wof:placetype":"locality"
},
  "geometry": {"coordinates":[14.32765,49.20817],"type":"Point"}
}