{
  "type": "Feature",
  "properties": {
    "gn:admin1_code":"89.0",
    "gn:admin2_code":"0427",
    "gn:asciiname":"Lysa",
    "gn:country_code":"CZ",
    "gn:dem":436,
    "gn:feature_class":"P",
    "gn:feature_code":"PPL",
    "gn:name":"Lys\u00e1",
    "gn:population":0,
    "gn:timezone":"Europe/Prague",
    "iso:country":"CZ",
    "name:und_x_variant":[
        "Leissen",
        "Lys\u00e1"
    ],
    "wof:name":"Lysa",
    "wof:placetype":"locality"
},
  "geometry": {"coordinates":[14.1255,50.70334],"type":"Point"}
}