{
  "type": "Feature",
  "properties": {
    "gn:admin1_code":"89.0",
    "gn:admin2_code":"0422",
    "gn:asciiname":"Mytinka",
    "gn:country_code":"CZ",
    "gn:dem":787,
    "gn:feature_class":"P",
    "gn:feature_code":"PPL",
    "gn:name":"M\u00fdtinka",
    "gn:population":0,
    "gn:timezone":"Europe/Prague",
    "iso:country":"CZ",
    "name:und_x_variant":[
        "Roedling",
        "R\u00f6dling",
        "M\u00fdtinka"
    ],
    "wof:name":"Mytinka",
    "wof:placetype":"locality"
},
  "geometry": {"coordinates":[13.08038,50.40516],"type":"Point"}
}