{
  "type": "Feature",
  "properties": {
    "gn:admin1_code":"88.0",
    "gn:admin2_code":"0204",
    "gn:asciiname":"Brezany",
    "gn:country_code":"CZ",
    "gn:dem":243,
    "gn:feature_class":"P",
    "gn:feature_code":"PPL",
    "gn:name":"B\u0159e\u017eany",
    "gn:population":0,
    "gn:timezone":"Europe/Prague",
    "iso:country":"CZ",
    "name:und_x_variant":[
        "B\u0159e\u017eany"
    ],
    "wof:name":"Brezany",
    "wof:placetype":"locality"
},
  "geometry": {"coordinates":[14.8072,50.09144000000001],"type":"Point"}
}