{
  "type": "Feature",
  "properties": {
    "gn:admin1_code":"80.0",
    "gn:admin2_code":"0614",
    "gn:asciiname":"Dobra Voda",
    "gn:country_code":"CZ",
    "gn:dem":466,
    "gn:feature_class":"P",
    "gn:feature_code":"PPL",
    "gn:name":"Dobr\u00e1 Voda",
    "gn:population":0,
    "gn:timezone":"Europe/Prague",
    "iso:country":"CZ",
    "wof:name":"Dobra Voda",
    "wof:placetype":"locality"
},
  "geometry": {"coordinates":[15.95612,49.20158],"type":"Point"}
}