{
  "type": "Feature",
  "properties": {
    "gn:gn_country":"CZ",
    "gn:gn_fcode":"PPL",
    "gn:gn_pop":164,
    "gn:population":164,
    "iso:country":"CZ",
    "name:cze_x_preferred":[
        "Ok\u0159e\u0161ice"
    ],
    "name:dut_x_preferred":[
        "Ok\u0159e\u0161ice"
    ],
    "name:eng_x_preferred":[
        "Ok\u0159e\u0161ice"
    ],
    "name:fre_x_preferred":[
        "Ok\u0159e\u0161ice"
    ],
    "name:hun_x_preferred":[
        "Ok\u0159e\u0161ice"
    ],
    "name:ita_x_preferred":[
        "Ok\u0159e\u0161ice"
    ],
    "name:may_x_preferred":[
        "Ok\u0159e\u0161ice"
    ],
    "name:nan_x_preferred":[
        "Ok\u0159e\u0161ice"
    ],
    "name:per_x_preferred":[
        "\u0627\u0648\u06a9\u0631\u0634\u06cc\u062a\u0633\u0647"
    ],
    "name:por_x_preferred":[
        "Ok\u0159e\u0161ice"
    ],
    "name:rup_x_preferred":[
        "Ok\u0159e\u0161ice"
    ],
    "name:slo_x_preferred":[
        "Ok\u0159e\u0161ice"
    ],
    "name:swe_x_preferred":[
        "Ok\u0159e\u0161ice"
    ],
    "name:vie_x_preferred":[
        "Ok\u0159e\u0161ice"
    ],
    "qs_pg:aaroncc":"CZ",
    "qs_pg:gn_country":"CZ",
    "qs_pg:gn_fcode":"PPL",
    "qs_pg:gn_pop":164,
    "qs_pg:name":"Ok\u0159e\u0161ice",
    "qs_pg:name_adm0":"\u010cesk\u00e1 republika",
    "qs_pg:name_adm1":"Kraj Vyso\u010dina",
    "qs_pg:photos_9r":0,
    "qs_pg:photos_sr":0,
    "qs_pg:pop_sr":1,
    "qs_pg:qs_pg_placetype":"locality",
    "qs_pg:qs_pg_placetype_gp":"Town",
    "qs_pg:woe_adm0":23424810,
    "woe:adm0_id":23424810,
    "woe:name_adm0":"\u010cesk\u00e1 republika",
    "woe:name_adm1":"Kraj Vyso\u010dina",
    "woe:placetype":"Town",
    "wof:name":"Ok\u0159e\u0161ice",
    "wof:placetype":"locality",
    "wof:population":164
},
  "geometry": {"coordinates":[15.85197,49.25938],"type":"Point"}
}