{
  "type": "Feature",
  "properties": {
    "gn:country":"CZ",
    "gn:fcode":"PPL",
    "gn:population":164,
    "iso:country":"CZ",
    "name:azb_x_preferred":[
        "\u0627\u0648\u06a9\u0631\u0634\u06cc\u062a\u0633\u0647"
    ],
    "name:cat_x_preferred":[
        "Ok\u0159e\u0161ice"
    ],
    "name:ceb_x_preferred":[
        "Ok\u0159e\u0161ice"
    ],
    "name:ces_x_preferred":[
        "Ok\u0159e\u0161ice"
    ],
    "name:che_x_preferred":[
        "\u041e\u043a\u0440\u0436\u0435\u0448\u0438\u0446\u0435"
    ],
    "name:deu_x_preferred":[
        "Ok\u0159e\u0161ice"
    ],
    "name:eng_x_preferred":[
        "Ok\u0159e\u0161ice"
    ],
    "name:eus_x_preferred":[
        "Ok\u0159e\u0161ice"
    ],
    "name:fas_x_preferred":[
        "\u0627\u0648\u06a9\u0631\u0634\u06cc\u062a\u0633\u0647"
    ],
    "name:fra_x_preferred":[
        "Ok\u0159e\u0161ice"
    ],
    "name:gle_x_preferred":[
        "Ok\u0159e\u0161ice"
    ],
    "name:hun_x_preferred":[
        "Ok\u0159e\u0161ice"
    ],
    "name:ita_x_preferred":[
        "Ok\u0159e\u0161ice"
    ],
    "name:lmo_x_preferred":[
        "Ok\u0159e\u0161ice"
    ],
    "name:msa_x_preferred":[
        "Ok\u0159e\u0161ice"
    ],
    "name:nan_x_preferred":[
        "Ok\u0159e\u0161ice"
    ],
    "name:nld_x_preferred":[
        "Ok\u0159e\u0161ice"
    ],
    "name:pol_x_preferred":[
        "Ok\u0159e\u0161ice"
    ],
    "name:por_x_preferred":[
        "Ok\u0159e\u0161ice"
    ],
    "name:rup_x_preferred":[
        "Ok\u0159e\u0161ice"
    ],
    "name:slk_x_preferred":[
        "Ok\u0159e\u0161ice"
    ],
    "name:spa_x_preferred":[
        "Ok\u0159e\u0161ice"
    ],
    "name:swe_x_preferred":[
        "Ok\u0159e\u0161ice"
    ],
    "name:tat_x_preferred":[
        "\u041e\u043a\u0440\u0436\u0435\u0448\u0438\u0446\u0435"
    ],
    "name:vie_x_preferred":[
        "Ok\u0159e\u0161ice"
    ],
    "qs_pg:aaroncc":"CZ",
    "qs_pg:gn_country":"CZ",
    "qs_pg:gn_fcode":"PPL",
    "qs_pg:gn_pop":164,
    "qs_pg:name":"Ok\u0159e\u0161ice",
    "qs_pg:name_adm0":"\u010cesk\u00e1 republika",
    "qs_pg:name_adm1":"Kraj Vyso\u010dina",
    "qs_pg:photos_9r":0,
    "qs_pg:photos_sr":0,
    "qs_pg:pop_sr":1,
    "qs_pg:qs_pg_placetype":"locality",
    "qs_pg:qs_pg_placetype_gp":"Town",
    "qs_pg:woe_adm0":23424810,
    "woe:adm0_id":23424810,
    "woe:name_adm0":"\u010cesk\u00e1 republika",
    "woe:name_adm1":"Kraj Vyso\u010dina",
    "woe:placetype":"Town",
    "wof:name":"Ok\u0159e\u0161ice",
    "wof:placetype":"locality",
    "wof:population":164
},
  "geometry": {"coordinates":[15.85197,49.25938],"type":"Point"}
}