{
  "type": "Feature",
  "properties": {
    "gn:admin1_code":"87.0",
    "gn:admin2_code":"0327",
    "gn:asciiname":"Bezdekov",
    "gn:country_code":"CZ",
    "gn:dem":485,
    "gn:feature_class":"P",
    "gn:feature_code":"PPL",
    "gn:name":"Bezd\u011bkov",
    "gn:population":0,
    "gn:timezone":"Europe/Prague",
    "iso:country":"CZ",
    "name:und_x_variant":[
        "P\u00f6ssigkau",
        "Bezd\u011bkov"
    ],
    "wof:name":"Bezdekov",
    "wof:placetype":"locality"
},
  "geometry": {"coordinates":[12.69137,49.62185],"type":"Point"}
}