{
  "type": "Feature",
  "properties": {
    "gn:admin1_code":"79.0",
    "gn:admin2_code":"0316",
    "gn:asciiname":"Mladotice",
    "gn:country_code":"CZ",
    "gn:dem":641,
    "gn:feature_class":"P",
    "gn:feature_code":"PPL",
    "gn:name":"Mladotice",
    "gn:population":0,
    "gn:timezone":"Europe/Prague",
    "iso:country":"CZ",
    "name:azb_x_preferred":[
        "\u0645\u0644\u0627\u062f\u0648\u062a\u06cc\u062a\u0633\u0647"
    ],
    "name:ceb_x_preferred":[
        "Mladotice"
    ],
    "name:ces_x_preferred":[
        "Mladotice"
    ],
    "name:deu_x_preferred":[
        "Mladotice"
    ],
    "name:eus_x_preferred":[
        "Mladotice"
    ],
    "name:fas_x_preferred":[
        "\u0645\u0644\u0627\u062f\u0648\u062a\u06cc\u062a\u0633\u0647"
    ],
    "name:fra_x_preferred":[
        "Mladotice"
    ],
    "name:hun_x_preferred":[
        "Mladotice"
    ],
    "name:ita_x_preferred":[
        "Mladotice"
    ],
    "name:msa_x_preferred":[
        "Mladotice"
    ],
    "name:nld_x_preferred":[
        "Mladotice"
    ],
    "name:por_x_preferred":[
        "Mladotice"
    ],
    "name:slk_x_preferred":[
        "Mladotice"
    ],
    "name:spa_x_preferred":[
        "Mladotice"
    ],
    "name:srp_x_preferred":[
        "\u041c\u043b\u0430\u0434\u043e\u0442\u0438\u0446\u0435"
    ],
    "name:swe_x_preferred":[
        "Mladotice"
    ],
    "name:vie_x_preferred":[
        "Mladotice"
    ],
    "wof:name":"Mladotice",
    "wof:placetype":"locality"
},
  "geometry": {"coordinates":[13.78999,49.21681],"type":"Point"}
}