{
  "type": "Feature",
  "properties": {
    "gn:admin1_code":"79.0",
    "gn:admin2_code":"0316",
    "gn:asciiname":"Mladotice",
    "gn:country_code":"CZ",
    "gn:dem":641,
    "gn:feature_class":"P",
    "gn:feature_code":"PPL",
    "gn:name":"Mladotice",
    "gn:population":0,
    "gn:timezone":"Europe/Prague",
    "iso:country":"CZ",
    "wof:name":"Mladotice",
    "wof:placetype":"locality"
},
  "geometry": {"coordinates":[13.78999,49.21681],"type":"Point"}
}