{
  "type": "Feature",
  "properties": {
    "gn:gn_country":"CZ",
    "gn:gn_fcode":"PPL",
    "gn:gn_pop":76,
    "gn:population":76,
    "iso:country":"CZ",
    "name:ces_x_preferred":[
        "Modr\u00e1 H\u016frka"
    ],
    "name:deu_x_preferred":[
        "Modr\u00e1 H\u016frka"
    ],
    "name:eng_x_preferred":[
        "Modr\u00e1 H\u016frka"
    ],
    "name:fas_x_preferred":[
        "\u0645\u0648\u062f\u0631\u0627 \u0647\u0648\u0631\u06a9\u0627"
    ],
    "name:fra_x_preferred":[
        "Modr\u00e1 H\u016frka"
    ],
    "name:hun_x_preferred":[
        "Modr\u00e1 H\u016frka"
    ],
    "name:ita_x_preferred":[
        "Modr\u00e1 H\u016frka"
    ],
    "name:msa_x_preferred":[
        "Modr\u00e1 H\u016frka"
    ],
    "name:nan_x_preferred":[
        "Modr\u00e1 H\u016frka"
    ],
    "name:nld_x_preferred":[
        "Modr\u00e1 H\u016frka"
    ],
    "name:pol_x_preferred":[
        "Modr\u00e1 H\u016frka"
    ],
    "name:por_x_preferred":[
        "Modr\u00e1 H\u016frka"
    ],
    "name:rup_x_preferred":[
        "Modr\u00e1 H\u016frka"
    ],
    "name:slk_x_preferred":[
        "Modr\u00e1 H\u016frka"
    ],
    "name:srp_x_preferred":[
        "\u041c\u043e\u0434\u0440\u0430 \u0425\u0443\u0440\u043a\u0430"
    ],
    "name:vie_x_preferred":[
        "Modr\u00e1 H\u016frka"
    ],
    "qs_pg:aaroncc":"CZ",
    "qs_pg:gn_country":"CZ",
    "qs_pg:gn_fcode":"PPL",
    "qs_pg:gn_pop":76,
    "qs_pg:name":"Modr\u00e1 H\u016frka",
    "qs_pg:name_adm0":"\u010cesk\u00e1 republika",
    "qs_pg:name_adm1":"Jiho\u010desk\u00fd kraj",
    "qs_pg:photos_9r":0,
    "qs_pg:photos_sr":0,
    "qs_pg:pop_sr":1,
    "qs_pg:qs_pg_placetype":"locality",
    "qs_pg:qs_pg_placetype_gp":"Town",
    "qs_pg:woe_adm0":23424810,
    "woe:adm0_id":23424810,
    "woe:name_adm0":"\u010cesk\u00e1 republika",
    "woe:name_adm1":"Jiho\u010desk\u00fd kraj",
    "woe:placetype":"Town",
    "wof:name":"Modr\u00e1 H\u016frka",
    "wof:placetype":"locality",
    "wof:population":76
},
  "geometry": {"coordinates":[14.52566,49.18004],"type":"Point"}
}