{
  "type": "Feature",
  "properties": {
    "gn:admin1_code":"88.0",
    "gn:admin2_code":"0205",
    "gn:asciiname":"Malovidy",
    "gn:country_code":"CZ",
    "gn:dem":352,
    "gn:feature_class":"P",
    "gn:feature_code":"PPL",
    "gn:name":"Malovidy",
    "gn:population":0,
    "gn:timezone":"Europe/Prague",
    "iso:country":"CZ",
    "name:ces_x_preferred":[
        "Malovidy"
    ],
    "name:msa_x_preferred":[
        "Malovidy"
    ],
    "wof:name":"Malovidy",
    "wof:placetype":"locality"
},
  "geometry": {"coordinates":[14.94478,49.83032],"type":"Point"}
}