{
  "type": "Feature",
  "properties": {
    "iso:country":"CZ",
    "name:ara_x_preferred":[
        "\u0641\u064a\u0634\u0643\u0648\u0641"
    ],
    "name:bel_x_preferred":[
        "\u0412\u044b\u0448\u043a\u0430\u045e"
    ],
    "name:bul_x_preferred":[
        "\u0412\u0438\u0448\u043a\u043e\u0432"
    ],
    "name:ceb_x_preferred":[
        "Vy\u0161kov"
    ],
    "name:ces_x_preferred":[
        "Vy\u0161kov"
    ],
    "name:deu_x_preferred":[
        "Vy\u0161kov"
    ],
    "name:epo_x_preferred":[
        "Vy\u0161kov"
    ],
    "name:eus_x_preferred":[
        "Vy\u0161kov"
    ],
    "name:fas_x_preferred":[
        "\u0648\u06cc\u0634\u06a9\u0648"
    ],
    "name:fra_x_preferred":[
        "Vy\u0161kov"
    ],
    "name:hun_x_preferred":[
        "Vy\u0161kov"
    ],
    "name:ita_x_preferred":[
        "Vy\u0161kov"
    ],
    "name:kor_x_preferred":[
        "\ube44\uc288\ucf54\ud504"
    ],
    "name:lav_x_preferred":[
        "Vi\u0161kova"
    ],
    "name:lit_x_preferred":[
        "Vi\u0161kovas"
    ],
    "name:msa_x_preferred":[
        "Vy\u0161kov"
    ],
    "name:nld_x_preferred":[
        "Vy\u0161kov"
    ],
    "name:pol_x_preferred":[
        "Vy\u0161kov"
    ],
    "name:por_x_preferred":[
        "Vy\u0161kov"
    ],
    "name:rus_x_preferred":[
        "\u0412\u0438\u0448\u043a\u043e\u0432"
    ],
    "name:slk_x_preferred":[
        "Vy\u0161kov"
    ],
    "name:spa_x_preferred":[
        "Vy\u0161kov"
    ],
    "name:srp_x_preferred":[
        "\u0412\u0438\u0448\u043a\u043e\u0432"
    ],
    "name:swe_x_preferred":[
        "Vy\u0161kov"
    ],
    "name:tur_x_preferred":[
        "Vy\u0161kov"
    ],
    "name:ukr_x_preferred":[
        "\u0412\u0438\u0448\u043a\u043e\u0432"
    ],
    "name:urd_x_preferred":[
        "\u0648\u06cc\u0634\u06a9\u0648\u0641"
    ],
    "name:vie_x_preferred":[
        "Vy\u0161kov"
    ],
    "name:war_x_preferred":[
        "Vy\u0161kov"
    ],
    "name:zho_x_preferred":[
        "\u7ef4\u4ec0\u79d1\u592b"
    ],
    "qs_pg:aaroncc":"CZ",
    "qs_pg:name":"Vy\u0161kov",
    "qs_pg:name_adm0":"\u010cesk\u00e1 republika",
    "qs_pg:name_adm1":"Jihomoravsk\u00fd kraj",
    "qs_pg:photos":6,
    "qs_pg:photos_1k":1,
    "qs_pg:photos_9k":1,
    "qs_pg:photos_9r":4,
    "qs_pg:photos_all":166,
    "qs_pg:photos_sr":1,
    "qs_pg:pop_sr":0,
    "qs_pg:qs_pg_placetype":"localadmin",
    "qs_pg:qs_pg_placetype_gp":"LocalAdmin",
    "qs_pg:woe_adm0":23424810,
    "woe:adm0_id":23424810,
    "woe:name_adm0":"\u010cesk\u00e1 republika",
    "woe:name_adm1":"Jihomoravsk\u00fd kraj",
    "woe:placetype":"LocalAdmin",
    "wof:name":"Vy\u0161kov",
    "wof:placetype":"localadmin"
},
  "geometry": {"coordinates":[16.9990525,49.279375],"type":"Point"}
}