{
  "type": "Feature",
  "properties": {
    "gn:admin1_code":"82.0",
    "gn:admin2_code":"0524",
    "gn:asciiname":"Bela",
    "gn:country_code":"CZ",
    "gn:dem":516,
    "gn:feature_class":"P",
    "gn:feature_code":"PPL",
    "gn:name":"B\u011bl\u00e1",
    "gn:population":0,
    "gn:timezone":"Europe/Prague",
    "iso:country":"CZ",
    "name:und_x_variant":[
        "Bielai"
    ],
    "wof:name":"Bela",
    "wof:placetype":"locality"
},
  "geometry": {"coordinates":[16.3783,50.18498],"type":"Point"}
}