{
  "type": "Feature",
  "properties": {
    "gn:admin1_code":"88.0",
    "gn:admin2_code":"0205",
    "gn:asciiname":"Chmeliste",
    "gn:country_code":"CZ",
    "gn:dem":401,
    "gn:feature_class":"P",
    "gn:feature_code":"PPL",
    "gn:name":"Chmeli\u0161t\u011b",
    "gn:population":0,
    "gn:timezone":"Europe/Prague",
    "iso:country":"CZ",
    "wof:name":"Chmeliste",
    "wof:placetype":"locality"
},
  "geometry": {"coordinates":[15.05257,49.89779],"type":"Point"}
}