{
  "type": "Feature",
  "properties": {
    "gn:admin1_code":"88.0",
    "gn:admin2_code":"0207",
    "gn:asciiname":"Neuberk",
    "gn:country_code":"CZ",
    "gn:dem":238,
    "gn:feature_class":"P",
    "gn:feature_code":"PPL",
    "gn:name":"Neuberk",
    "gn:population":0,
    "gn:timezone":"Europe/Prague",
    "iso:country":"CZ",
    "wof:name":"Neuberk",
    "wof:placetype":"locality"
},
  "geometry": {"coordinates":[14.88412,50.40122],"type":"Point"}
}