{
  "type": "Feature",
  "properties": {
    "gn:admin1_code":"80.0",
    "gn:admin2_code":"0613",
    "gn:asciiname":"Drahonov",
    "gn:country_code":"CZ",
    "gn:dem":659,
    "gn:feature_class":"P",
    "gn:feature_code":"PPL",
    "gn:name":"Draho\u0148ov",
    "gn:population":0,
    "gn:timezone":"Europe/Prague",
    "iso:country":"CZ",
    "wof:name":"Drahonov",
    "wof:placetype":"locality"
},
  "geometry": {"coordinates":[15.08436,49.35902],"type":"Point"}
}