{
  "type": "Feature",
  "properties": {
    "gn:admin1_code":"86",
    "gn:admin2_code":"0531",
    "gn:asciiname":"Zd'arec",
    "gn:country_code":"CZ",
    "gn:dem":416,
    "gn:feature_class":"P",
    "gn:feature_code":"PPL",
    "gn:name":"\u017d\u010f\u00e1rec",
    "gn:population":0,
    "gn:timezone":"Europe/Prague",
    "iso:country":"CZ",
    "wof:name":"Zd'arec",
    "wof:placetype":"locality"
},
  "geometry": {"coordinates":[15.98931,49.82675],"type":"Point"}
}