{
  "type": "Feature",
  "properties": {
    "gn:country":"CZ",
    "gn:fcode":"PPL",
    "gn:population":1173,
    "iso:country":"CZ",
    "name:azb_x_preferred":[
        "\u062f\u0648\u0644\u0646\u06cc \u062a\u0633\u0631\u06a9\u0648"
    ],
    "name:ceb_x_preferred":[
        "Doln\u00ed Cerekev"
    ],
    "name:ces_x_preferred":[
        "Doln\u00ed Cerekev"
    ],
    "name:deu_x_preferred":[
        "Doln\u00ed Cerekev"
    ],
    "name:eng_x_preferred":[
        "Doln\u00ed Cerekev"
    ],
    "name:epo_x_preferred":[
        "Doln\u00ed Cerekev"
    ],
    "name:eus_x_preferred":[
        "Doln\u00ed Cerekev"
    ],
    "name:fas_x_preferred":[
        "\u062f\u0648\u0644\u0646\u06cc \u062a\u0633\u0631\u06a9\u0648"
    ],
    "name:fra_x_preferred":[
        "Doln\u00ed Cerekev"
    ],
    "name:hun_x_preferred":[
        "Doln\u00ed Cerekev"
    ],
    "name:ita_x_preferred":[
        "Doln\u00ed Cerekev"
    ],
    "name:msa_x_preferred":[
        "Doln\u00ed Cerekev"
    ],
    "name:nan_x_preferred":[
        "Doln\u00ed Cerekev"
    ],
    "name:nld_x_preferred":[
        "Doln\u00ed Cerekev"
    ],
    "name:pol_x_preferred":[
        "Doln\u00ed Cerekev"
    ],
    "name:por_x_preferred":[
        "Lukavec"
    ],
    "name:rup_x_preferred":[
        "Doln\u00ed Cerekev"
    ],
    "name:slk_x_preferred":[
        "Doln\u00ed Cerekev"
    ],
    "name:spa_x_preferred":[
        "Doln\u00ed Cerekev"
    ],
    "name:srp_x_preferred":[
        "\u0414\u043e\u043b\u045a\u0438 \u0426\u0435\u0440\u0435\u043a\u0435\u0432"
    ],
    "name:swe_x_preferred":[
        "Doln\u00ed Cerekev"
    ],
    "name:und_x_variant":[
        "Unter Cerekwe"
    ],
    "name:vie_x_preferred":[
        "Doln\u00ed Cerekev"
    ],
    "qs_pg:aaroncc":"CZ",
    "qs_pg:gn_country":"CZ",
    "qs_pg:gn_fcode":"PPL",
    "qs_pg:gn_pop":1173,
    "qs_pg:name":"Doln\u00ed Cerekev",
    "qs_pg:name_adm0":"\u010cesk\u00e1 republika",
    "qs_pg:name_adm1":"Kraj Vyso\u010dina",
    "qs_pg:photos_9r":0,
    "qs_pg:photos_sr":0,
    "qs_pg:pop_sr":3,
    "qs_pg:qs_pg_placetype":"locality",
    "qs_pg:qs_pg_placetype_gp":"Town",
    "qs_pg:woe_adm0":23424810,
    "woe:adm0_id":23424810,
    "woe:name_adm0":"\u010cesk\u00e1 republika",
    "woe:name_adm1":"Kraj Vyso\u010dina",
    "woe:placetype":"Town",
    "wof:name":"Doln\u00ed Cerekev",
    "wof:placetype":"locality",
    "wof:population":1173
},
  "geometry": {"coordinates":[15.45655,49.34449],"type":"Point"}
}