{
  "type": "Feature",
  "properties": {
    "gn:admin1_code":"81",
    "gn:admin2_code":"0412",
    "gn:asciiname":"Stran",
    "gn:cc2":"CZ",
    "gn:country_code":"CZ",
    "gn:dem":458,
    "gn:feature_class":"P",
    "gn:feature_code":"PPL",
    "gn:name":"Str\u00e1\u0148",
    "gn:population":0,
    "gn:timezone":"Europe/Prague",
    "iso:country":"CZ",
    "name:und_x_variant":[
        "Elm"
    ],
    "wof:name":"Stran",
    "wof:placetype":"locality"
},
  "geometry": {"coordinates":[12.96146,50.27047],"type":"Point"}
}