{
  "type": "Feature",
  "properties": {
    "iso:country":"CZ",
    "name:azb_x_preferred":[
        "\u0631\u0627\u062a\u0634\u06cc\u062a\u0633-\u067e\u06cc\u0633\u062a\u0648\u0648\u06cc\u062a\u0633\u0647"
    ],
    "name:ces_x_preferred":[
        "Ra\u010dice-P\u00edstovice"
    ],
    "name:deu_x_preferred":[
        "Ra\u010dice-P\u00edstovice"
    ],
    "name:eus_x_preferred":[
        "Ra\u010dice-P\u00edstovice"
    ],
    "name:fas_x_preferred":[
        "\u0631\u0627\u062a\u0634\u06cc\u062a\u0633-\u067e\u06cc\u0633\u062a\u0648\u0648\u06cc\u062a\u0633\u0647"
    ],
    "name:fra_x_preferred":[
        "Ra\u010dice-P\u00edstovice"
    ],
    "name:hun_x_preferred":[
        "Ra\u010dice-P\u00edstovice"
    ],
    "name:ita_x_preferred":[
        "Ra\u010dice-P\u00edstovice"
    ],
    "name:msa_x_preferred":[
        "Ra\u010dice-P\u00edstovice"
    ],
    "name:nld_x_preferred":[
        "Ra\u010dice-P\u00edstovice"
    ],
    "name:por_x_preferred":[
        "Ra\u010dice-P\u00edstovice"
    ],
    "name:slk_x_preferred":[
        "Ra\u010dice-P\u00edstovice"
    ],
    "name:spa_x_preferred":[
        "Ra\u010dice-P\u00edstovice"
    ],
    "name:srp_x_preferred":[
        "\u0420\u0430\u0447\u0438\u0446\u0435-\u041f\u0438\u0441\u0442\u043e\u0432\u0438\u0446\u0435"
    ],
    "name:vie_x_preferred":[
        "Ra\u010dice-P\u00edstovice"
    ],
    "qs_pg:aaroncc":"CZ",
    "qs_pg:name":"Ra\u010dice-P\u00edstovice",
    "qs_pg:name_adm0":"\u010cesk\u00e1 republika",
    "qs_pg:name_adm1":"Jihomoravsk\u00fd kraj",
    "qs_pg:photos":16,
    "qs_pg:photos_1k":3,
    "qs_pg:photos_9k":1,
    "qs_pg:photos_9r":1,
    "qs_pg:photos_all":18,
    "qs_pg:photos_sr":1,
    "qs_pg:pop_sr":0,
    "qs_pg:qs_pg_placetype":"localadmin",
    "qs_pg:qs_pg_placetype_gp":"LocalAdmin",
    "qs_pg:woe_adm0":23424810,
    "woe:adm0_id":23424810,
    "woe:name_adm0":"\u010cesk\u00e1 republika",
    "woe:name_adm1":"Jihomoravsk\u00fd kraj",
    "woe:placetype":"LocalAdmin",
    "wof:name":"Ra\u010dice-P\u00edstovice",
    "wof:placetype":"localadmin"
},
  "geometry": {"coordinates":[16.872253,49.277044],"type":"Point"}
}