{
  "type": "Feature",
  "properties": {
    "gn:country":"CZ",
    "gn:fcode":"PPL",
    "gn:population":282,
    "iso:country":"CZ",
    "name:azb_x_preferred":[
        "\u0646\u06cc\u0645\u06cc\u0631\u06cc\u062a\u0633\u0647"
    ],
    "name:ceb_x_preferred":[
        "Nim\u011b\u0159ice"
    ],
    "name:ces_x_preferred":[
        "Nim\u011b\u0159ice"
    ],
    "name:eng_x_preferred":[
        "Nim\u011b\u0159ice"
    ],
    "name:eus_x_preferred":[
        "Nim\u011b\u0159ice"
    ],
    "name:fas_x_preferred":[
        "\u0646\u06cc\u0645\u06cc\u0631\u06cc\u062a\u0633\u0647"
    ],
    "name:fra_x_preferred":[
        "Nim\u011b\u0159ice"
    ],
    "name:hun_x_preferred":[
        "Nim\u011b\u0159ice"
    ],
    "name:ita_x_preferred":[
        "Nim\u011b\u0159ice"
    ],
    "name:msa_x_preferred":[
        "Nim\u011b\u0159ice"
    ],
    "name:nan_x_preferred":[
        "Nim\u011b\u0159ice"
    ],
    "name:nld_x_preferred":[
        "Nim\u011b\u0159ice"
    ],
    "name:pol_x_preferred":[
        "Nim\u011b\u0159ice"
    ],
    "name:por_x_preferred":[
        "Nim\u011b\u0159ice"
    ],
    "name:rus_x_preferred":[
        "\u041d\u0438\u043c\u0435\u0440\u0436\u0438\u0446\u0435"
    ],
    "name:slk_x_preferred":[
        "Nim\u011b\u0159ice"
    ],
    "name:spa_x_preferred":[
        "Nim\u011b\u0159ice"
    ],
    "name:srp_x_preferred":[
        "\u040a\u0438\u043c\u0458\u0435\u0440\u0436\u0438\u0446\u0435"
    ],
    "name:swe_x_preferred":[
        "Nim\u011b\u0159ice"
    ],
    "name:vie_x_preferred":[
        "Nim\u011b\u0159ice"
    ],
    "qs_pg:aaroncc":"CZ",
    "qs_pg:gn_country":"CZ",
    "qs_pg:gn_fcode":"PPL",
    "qs_pg:gn_pop":282,
    "qs_pg:name":"Nim\u011b\u0159ice",
    "qs_pg:name_adm0":"\u010cesk\u00e1 republika",
    "qs_pg:name_adm1":"St\u0159edo\u010desk\u00fd kraj",
    "qs_pg:photos_9r":0,
    "qs_pg:photos_sr":0,
    "qs_pg:pop_sr":2,
    "qs_pg:qs_pg_placetype":"locality",
    "qs_pg:qs_pg_placetype_gp":"Town",
    "qs_pg:woe_adm0":23424810,
    "woe:adm0_id":23424810,
    "woe:name_adm0":"\u010cesk\u00e1 republika",
    "woe:name_adm1":"St\u0159edo\u010desk\u00fd kraj",
    "woe:placetype":"Town",
    "wof:name":"Nim\u011b\u0159ice",
    "wof:placetype":"locality",
    "wof:population":282
},
  "geometry": {"coordinates":[14.80844,50.39578],"type":"Point"}
}