{
  "type": "Feature",
  "properties": {
    "gn:gn_country":"CZ",
    "gn:gn_fcode":"PPL",
    "gn:gn_pop":118,
    "gn:population":118,
    "iso:country":"CZ",
    "name:cze_x_preferred":[
        "Mal\u0161\u00edn"
    ],
    "name:dut_x_preferred":[
        "Mal\u0161\u00edn"
    ],
    "name:eng_x_preferred":[
        "Mal\u0161\u00edn"
    ],
    "name:fre_x_preferred":[
        "Mal\u0161\u00edn"
    ],
    "name:ger_x_preferred":[
        "Mal\u0161\u00edn"
    ],
    "name:hun_x_preferred":[
        "Mal\u0161\u00edn"
    ],
    "name:ita_x_preferred":[
        "Mal\u0161\u00edn"
    ],
    "name:may_x_preferred":[
        "Mal\u0161\u00edn"
    ],
    "name:nan_x_preferred":[
        "Mal\u0161\u00edn"
    ],
    "name:pol_x_preferred":[
        "Mal\u0161\u00edn"
    ],
    "name:por_x_preferred":[
        "Mal\u0161\u00edn"
    ],
    "name:rup_x_preferred":[
        "Mal\u0161\u00edn"
    ],
    "name:slo_x_preferred":[
        "Mal\u0161\u00edn"
    ],
    "name:srp_x_preferred":[
        "\u041c\u0430\u043b\u0448\u0438\u043d"
    ],
    "name:swe_x_preferred":[
        "Mal\u0161\u00edn"
    ],
    "name:vie_x_preferred":[
        "Mal\u0161\u00edn"
    ],
    "qs_pg:aaroncc":"CZ",
    "qs_pg:gn_country":"CZ",
    "qs_pg:gn_fcode":"PPL",
    "qs_pg:gn_pop":118,
    "qs_pg:name":"Mal\u0161\u00edn",
    "qs_pg:name_adm0":"\u010cesk\u00e1 republika",
    "qs_pg:name_adm1":"Jiho\u010desk\u00fd kraj",
    "qs_pg:photos_9r":0,
    "qs_pg:photos_sr":0,
    "qs_pg:pop_sr":1,
    "qs_pg:qs_pg_placetype":"locality",
    "qs_pg:qs_pg_placetype_gp":"Town",
    "qs_pg:woe_adm0":23424810,
    "woe:adm0_id":23424810,
    "woe:name_adm0":"\u010cesk\u00e1 republika",
    "woe:name_adm1":"Jiho\u010desk\u00fd kraj",
    "woe:placetype":"Town",
    "wof:name":"Mal\u0161\u00edn",
    "wof:placetype":"locality",
    "wof:population":118
},
  "geometry": {"coordinates":[14.28934,48.6732],"type":"Point"}
}