{
  "type": "Feature",
  "properties": {
    "gn:gn_country":"CZ",
    "gn:gn_fcode":"PPL",
    "gn:gn_pop":1950,
    "gn:population":1950,
    "iso:country":"CZ",
    "name:ceb_x_preferred":[
        "Skaln\u00e1"
    ],
    "name:ces_x_preferred":[
        "Vild\u0161tejn"
    ],
    "name:ces_x_variant":[
        "Skaln\u00e1"
    ],
    "name:deu_x_preferred":[
        "Wildstein"
    ],
    "name:deu_x_variant":[
        "Skaln\u00e1"
    ],
    "name:eus_x_preferred":[
        "Skaln\u00e1"
    ],
    "name:fas_x_preferred":[
        "\u0633\u06a9\u0627\u0644\u0646\u0627"
    ],
    "name:fra_x_preferred":[
        "Skaln\u00e1"
    ],
    "name:hun_x_preferred":[
        "Skaln\u00e1"
    ],
    "name:ita_x_preferred":[
        "Skaln\u00e1"
    ],
    "name:msa_x_preferred":[
        "Skaln\u00e1"
    ],
    "name:nld_x_preferred":[
        "Skaln\u00e1"
    ],
    "name:pol_x_preferred":[
        "Skaln\u00e1"
    ],
    "name:por_x_preferred":[
        "Skaln\u00e1"
    ],
    "name:rus_x_preferred":[
        "\u0421\u043a\u0430\u043b\u044c\u043d\u0430"
    ],
    "name:slk_x_preferred":[
        "Skaln\u00e1"
    ],
    "name:spa_x_preferred":[
        "Skaln\u00e1"
    ],
    "name:srp_x_preferred":[
        "\u0421\u043a\u0430\u043b\u043d\u0430"
    ],
    "name:swe_x_preferred":[
        "Skaln\u00e1"
    ],
    "name:vie_x_preferred":[
        "Skaln\u00e1"
    ],
    "name:zho_x_preferred":[
        "\u65af\u5361\u723e\u7d0d"
    ],
    "qs_pg:aaroncc":"CZ",
    "qs_pg:gn_country":"CZ",
    "qs_pg:gn_fcode":"PPL",
    "qs_pg:gn_pop":1950,
    "qs_pg:name":"Skaln\u00e1",
    "qs_pg:name_adm0":"\u010cesk\u00e1 republika",
    "qs_pg:name_adm1":"Karlovarsk\u00fd kraj",
    "qs_pg:photos":1,
    "qs_pg:photos_1k":1,
    "qs_pg:photos_9k":1,
    "qs_pg:photos_9r":3,
    "qs_pg:photos_all":79,
    "qs_pg:photos_sr":1,
    "qs_pg:pop_sr":3,
    "qs_pg:qs_pg_placetype":"localadmin",
    "qs_pg:qs_pg_placetype_gp":"LocalAdmin",
    "qs_pg:woe_adm0":23424810,
    "woe:adm0_id":23424810,
    "woe:name_adm0":"\u010cesk\u00e1 republika",
    "woe:name_adm1":"Karlovarsk\u00fd kraj",
    "woe:placetype":"LocalAdmin",
    "wof:name":"Skaln\u00e1",
    "wof:placetype":"localadmin",
    "wof:population":1950
},
  "geometry": {"coordinates":[12.36144,50.1703],"type":"Point"}
}