{
  "type": "Feature",
  "properties": {
    "iso:country":"CZ",
    "name:azb_x_preferred":[
        "\u067e\u0631\u0646\u0627"
    ],
    "name:ceb_x_preferred":[
        "Pern\u00e1"
    ],
    "name:ces_x_preferred":[
        "Pern\u00e1"
    ],
    "name:deu_x_preferred":[
        "Pern\u00e1"
    ],
    "name:eus_x_preferred":[
        "Pern\u00e1"
    ],
    "name:fas_x_preferred":[
        "\u067e\u0631\u0646\u0627"
    ],
    "name:fra_x_preferred":[
        "Pern\u00e1"
    ],
    "name:hun_x_preferred":[
        "Pern\u00e1"
    ],
    "name:ita_x_preferred":[
        "Pern\u00e1"
    ],
    "name:msa_x_preferred":[
        "Pern\u00e1"
    ],
    "name:nld_x_preferred":[
        "Pern\u00e1"
    ],
    "name:pol_x_preferred":[
        "Pern\u00e1"
    ],
    "name:por_x_preferred":[
        "Pern\u00e1"
    ],
    "name:slk_x_preferred":[
        "Pern\u00e1"
    ],
    "name:spa_x_preferred":[
        "Pern\u00e1"
    ],
    "name:srp_x_preferred":[
        "\u041f\u0435\u0440\u043d\u0430"
    ],
    "name:swe_x_preferred":[
        "Pern\u00e1"
    ],
    "name:vie_x_preferred":[
        "Pern\u00e1"
    ],
    "qs_pg:aaroncc":"CZ",
    "qs_pg:name":"Pern\u00e1",
    "qs_pg:name_adm0":"\u010cesk\u00e1 republika",
    "qs_pg:name_adm1":"Jihomoravsk\u00fd kraj",
    "qs_pg:photos":1,
    "qs_pg:photos_1k":1,
    "qs_pg:photos_9k":1,
    "qs_pg:photos_9r":2,
    "qs_pg:photos_all":47,
    "qs_pg:photos_sr":1,
    "qs_pg:pop_sr":0,
    "qs_pg:qs_pg_placetype":"localadmin",
    "qs_pg:qs_pg_placetype_gp":"LocalAdmin",
    "qs_pg:woe_adm0":23424810,
    "woe:adm0_id":23424810,
    "woe:name_adm0":"\u010cesk\u00e1 republika",
    "woe:name_adm1":"Jihomoravsk\u00fd kraj",
    "woe:placetype":"LocalAdmin",
    "wof:name":"Pern\u00e1",
    "wof:placetype":"localadmin"
},
  "geometry": {"coordinates":[16.629016,48.855849],"type":"Point"}
}