{
  "type": "Feature",
  "properties": {
    "gn:gn_country":"CZ",
    "gn:gn_fcode":"PPL",
    "gn:gn_pop":191,
    "gn:population":191,
    "iso:country":"CZ",
    "name:cze_x_preferred":[
        "V\u00e1penice"
    ],
    "name:dut_x_preferred":[
        "V\u00e1penice"
    ],
    "name:eng_x_preferred":[
        "V\u00e1penice"
    ],
    "name:fre_x_preferred":[
        "V\u00e1penice"
    ],
    "name:ger_x_preferred":[
        "V\u00e1penice"
    ],
    "name:hun_x_preferred":[
        "V\u00e1penice"
    ],
    "name:ita_x_preferred":[
        "V\u00e1penice"
    ],
    "name:may_x_preferred":[
        "V\u00e1penice"
    ],
    "name:nan_x_preferred":[
        "V\u00e1penice"
    ],
    "name:per_x_preferred":[
        "\u0648\u0627\u067e\u0646\u06cc\u062a\u0633\u0647"
    ],
    "name:pol_x_preferred":[
        "V\u00e1penice"
    ],
    "name:por_x_preferred":[
        "V\u00e1penice"
    ],
    "name:rup_x_preferred":[
        "V\u00e1penice"
    ],
    "name:slo_x_preferred":[
        "V\u00e1penice"
    ],
    "name:srp_x_preferred":[
        "\u0412\u0430\u043f\u0435\u045a\u0438\u0446\u0435"
    ],
    "name:swe_x_preferred":[
        "V\u00e1penice"
    ],
    "name:vie_x_preferred":[
        "V\u00e1penice"
    ],
    "qs_pg:aaroncc":"CZ",
    "qs_pg:gn_country":"CZ",
    "qs_pg:gn_fcode":"PPL",
    "qs_pg:gn_pop":191,
    "qs_pg:name":"V\u00e1penice",
    "qs_pg:name_adm0":"\u010cesk\u00e1 republika",
    "qs_pg:name_adm1":"Zl\u00ednsk\u00fd kraj",
    "qs_pg:photos_9r":0,
    "qs_pg:photos_sr":0,
    "qs_pg:pop_sr":1,
    "qs_pg:qs_pg_placetype":"locality",
    "qs_pg:qs_pg_placetype_gp":"Town",
    "qs_pg:woe_adm0":23424810,
    "woe:adm0_id":23424810,
    "woe:name_adm0":"\u010cesk\u00e1 republika",
    "woe:name_adm1":"Zl\u00ednsk\u00fd kraj",
    "woe:placetype":"Town",
    "wof:name":"V\u00e1penice",
    "wof:placetype":"locality",
    "wof:population":191
},
  "geometry": {"coordinates":[17.84121,48.96781],"type":"Point"}
}