{
  "type": "Feature",
  "properties": {
    "gn:admin1_code":"80.0",
    "gn:admin2_code":"0613",
    "gn:asciiname":"Mohelnice",
    "gn:country_code":"CZ",
    "gn:dem":518,
    "gn:feature_class":"P",
    "gn:feature_code":"PPL",
    "gn:name":"Mohelnice",
    "gn:population":0,
    "gn:timezone":"Europe/Prague",
    "iso:country":"CZ",
    "name:ceb_x_preferred":[
        "Mohelnice"
    ],
    "name:ces_x_preferred":[
        "Mohelnice"
    ],
    "name:deu_x_preferred":[
        "Mohelnice"
    ],
    "name:epo_x_preferred":[
        "Mohelnice"
    ],
    "name:fra_x_preferred":[
        "Mohelnice"
    ],
    "name:hun_x_preferred":[
        "Mohelnice"
    ],
    "name:ita_x_preferred":[
        "Mohelnice"
    ],
    "name:nld_x_preferred":[
        "Mohelnice"
    ],
    "name:slk_x_preferred":[
        "Mohelnice"
    ],
    "name:srp_x_preferred":[
        "\u041c\u043e\u0445\u0435\u043b\u045a\u0438\u0446\u0435"
    ],
    "name:swe_x_preferred":[
        "Mohelnice"
    ],
    "wof:name":"Mohelnice",
    "wof:placetype":"locality"
},
  "geometry": {"coordinates":[15.03479,49.58863],"type":"Point"}
}