{
  "type": "Feature",
  "properties": {
    "gn:admin1_code":"84.0",
    "gn:admin2_code":"0713",
    "gn:asciiname":"Pohora",
    "gn:country_code":"CZ",
    "gn:dem":572,
    "gn:feature_class":"P",
    "gn:feature_code":"PPL",
    "gn:name":"Pohora",
    "gn:population":0,
    "gn:timezone":"Europe/Prague",
    "iso:country":"CZ",
    "wof:name":"Pohora",
    "wof:placetype":"locality"
},
  "geometry": {"coordinates":[16.75552,49.56096],"type":"Point"}
}