{
  "type": "Feature",
  "properties": {
    "gn:admin1_code":"88.0",
    "gn:admin2_code":"020A",
    "gn:asciiname":"Kuchar",
    "gn:country_code":"CZ",
    "gn:dem":378,
    "gn:feature_class":"P",
    "gn:feature_code":"PPL",
    "gn:name":"Kucha\u0159",
    "gn:population":0,
    "gn:timezone":"Europe/Prague",
    "iso:country":"CZ",
    "name:ara_x_preferred":[
        "\u0643\u0648\u062a\u0634\u0627\u0631"
    ],
    "name:ceb_x_preferred":[
        "K\u016bch\u0101r-e Kalt\u016bn\u0101b\u0101d"
    ],
    "name:fas_x_preferred":[
        "\u06a9\u0648\u0686\u0627\u0631"
    ],
    "name:swe_x_preferred":[
        "K\u016bch\u0101r-e Kalt\u016bn\u0101b\u0101d"
    ],
    "wof:name":"Kuchar",
    "wof:placetype":"locality"
},
  "geometry": {"coordinates":[14.23588,49.98192],"type":"Point"}
}