{
  "type": "Feature",
  "properties": {
    "gn:admin1_code":"85.0",
    "gn:admin2_code":"0802",
    "gn:asciiname":"Nemcanka",
    "gn:country_code":"CZ",
    "gn:dem":714,
    "gn:feature_class":"P",
    "gn:feature_code":"PPL",
    "gn:name":"N\u011bm\u010danka",
    "gn:population":0,
    "gn:timezone":"Europe/Prague",
    "iso:country":"CZ",
    "wof:name":"Nemcanka",
    "wof:placetype":"locality"
},
  "geometry": {"coordinates":[18.41369,49.45012],"type":"Point"}
}