{
  "type": "Feature",
  "properties": {
    "gn:admin1_code":"83.0",
    "gn:admin2_code":"0513",
    "gn:asciiname":"Kohoutovice",
    "gn:country_code":"CZ",
    "gn:dem":329,
    "gn:feature_class":"P",
    "gn:feature_code":"PPL",
    "gn:name":"Kohoutovice",
    "gn:population":0,
    "gn:timezone":"Europe/Prague",
    "iso:country":"CZ",
    "wof:name":"Kohoutovice",
    "wof:placetype":"locality"
},
  "geometry": {"coordinates":[15.05271,50.65679],"type":"Point"}
}