{
  "type": "Feature",
  "properties": {
    "gn:country":"CZ",
    "gn:fcode":"PPL",
    "gn:population":951,
    "iso:country":"CZ",
    "name:azb_x_preferred":[
        "\u0648\u0644\u0634\u0648\u06cc\u06a9"
    ],
    "name:ceb_x_preferred":[
        "Vele\u0161ovice"
    ],
    "name:ces_x_preferred":[
        "Vele\u0161ovice"
    ],
    "name:deu_x_preferred":[
        "Vele\u0161ovice"
    ],
    "name:eng_x_preferred":[
        "Vele\u0161ovice"
    ],
    "name:eus_x_preferred":[
        "Vele\u0161ovice"
    ],
    "name:fas_x_preferred":[
        "\u0648\u0644\u0634\u0648\u06cc\u06a9"
    ],
    "name:fra_x_preferred":[
        "Vele\u0161ovice"
    ],
    "name:hun_x_preferred":[
        "Vele\u0161ovice"
    ],
    "name:ita_x_preferred":[
        "Vele\u0161ovice"
    ],
    "name:msa_x_preferred":[
        "Vele\u0161ovice"
    ],
    "name:nan_x_preferred":[
        "Vele\u0161ovice"
    ],
    "name:nld_x_preferred":[
        "Vele\u0161ovice"
    ],
    "name:pol_x_preferred":[
        "Vele\u0161ovice"
    ],
    "name:por_x_preferred":[
        "Vele\u0161ovice"
    ],
    "name:rup_x_preferred":[
        "Vele\u0161ovice"
    ],
    "name:slk_x_preferred":[
        "Vele\u0161ovice"
    ],
    "name:spa_x_preferred":[
        "Vele\u0161ovice"
    ],
    "name:srp_x_preferred":[
        "\u0412\u0435\u043b\u0435\u0448\u043e\u0432\u0438\u0446\u0435"
    ],
    "name:swe_x_preferred":[
        "Vele\u0161ovice"
    ],
    "name:und_x_variant":[
        "Welspitz"
    ],
    "name:vie_x_preferred":[
        "Vele\u0161ovice"
    ],
    "qs_pg:aaroncc":"CZ",
    "qs_pg:gn_country":"CZ",
    "qs_pg:gn_fcode":"PPL",
    "qs_pg:gn_pop":951,
    "qs_pg:name":"Vele\u0161ovice",
    "qs_pg:name_adm0":"\u010cesk\u00e1 republika",
    "qs_pg:name_adm1":"Jihomoravsk\u00fd kraj",
    "qs_pg:photos_9r":0,
    "qs_pg:photos_sr":0,
    "qs_pg:pop_sr":2,
    "qs_pg:qs_pg_placetype":"locality",
    "qs_pg:qs_pg_placetype_gp":"Town",
    "qs_pg:woe_adm0":23424810,
    "woe:adm0_id":23424810,
    "woe:name_adm0":"\u010cesk\u00e1 republika",
    "woe:name_adm1":"Jihomoravsk\u00fd kraj",
    "woe:placetype":"Town",
    "wof:name":"Vele\u0161ovice",
    "wof:placetype":"locality",
    "wof:population":951
},
  "geometry": {"coordinates":[16.84914,49.17916],"type":"Point"}
}