{
  "type": "Feature",
  "properties": {
    "gn:gn_country":"CZ",
    "gn:gn_fcode":"PPL",
    "gn:gn_pop":1305,
    "gn:population":1305,
    "iso:country":"CZ",
    "name:bul_x_preferred":[
        "\u0425\u0430\u0431\u0440\u0439"
    ],
    "name:ceb_x_preferred":[
        "Habry"
    ],
    "name:ces_x_preferred":[
        "Habry"
    ],
    "name:deu_x_preferred":[
        "Habry"
    ],
    "name:eng_x_preferred":[
        "Habry"
    ],
    "name:eus_x_preferred":[
        "Habry"
    ],
    "name:fas_x_preferred":[
        "\u0647\u0627\u0628\u0631\u06cc"
    ],
    "name:fra_x_preferred":[
        "Habry"
    ],
    "name:hun_x_preferred":[
        "Habry"
    ],
    "name:ita_x_preferred":[
        "Habry"
    ],
    "name:lav_x_preferred":[
        "Habri"
    ],
    "name:msa_x_preferred":[
        "Habry"
    ],
    "name:nan_x_preferred":[
        "Habry"
    ],
    "name:nld_x_preferred":[
        "Habry"
    ],
    "name:pol_x_preferred":[
        "Habry"
    ],
    "name:por_x_preferred":[
        "Habry"
    ],
    "name:rus_x_preferred":[
        "\u0413\u0430\u0431\u0440\u044b"
    ],
    "name:slk_x_preferred":[
        "Habry"
    ],
    "name:spa_x_preferred":[
        "Habry"
    ],
    "name:srp_x_preferred":[
        "\u0425\u0430\u0431\u0440\u0438"
    ],
    "name:swe_x_preferred":[
        "Habry"
    ],
    "name:tat_x_preferred":[
        "\u04ba\u0430\u0431\u0440\u0438"
    ],
    "name:unk_x_variant":[
        "Habern"
    ],
    "name:vie_x_preferred":[
        "Habry"
    ],
    "name:zho_x_preferred":[
        "\u54c8\u5e03\u91cc"
    ],
    "qs_pg:aaroncc":"CZ",
    "qs_pg:gn_country":"CZ",
    "qs_pg:gn_fcode":"PPL",
    "qs_pg:gn_pop":1305,
    "qs_pg:name":"Habry",
    "qs_pg:name_adm0":"\u010cesk\u00e1 republika",
    "qs_pg:name_adm1":"Kraj Vyso\u010dina",
    "qs_pg:photos_9k":1,
    "qs_pg:photos_9r":1,
    "qs_pg:photos_all":2,
    "qs_pg:photos_sr":0,
    "qs_pg:pop_sr":3,
    "qs_pg:qs_pg_placetype":"locality",
    "qs_pg:qs_pg_placetype_gp":"Town",
    "qs_pg:woe_adm0":23424810,
    "woe:adm0_id":23424810,
    "woe:name_adm0":"\u010cesk\u00e1 republika",
    "woe:name_adm1":"Kraj Vyso\u010dina",
    "woe:placetype":"Town",
    "wof:name":"Habry",
    "wof:placetype":"locality",
    "wof:population":1305
},
  "geometry": {"coordinates":[15.48486,49.75603],"type":"Point"}
}