{
  "type": "Feature",
  "properties": {
    "gn:gn_country":"CZ",
    "gn:gn_fcode":"PPL",
    "gn:gn_pop":153,
    "gn:population":153,
    "iso:country":"CZ",
    "name:ceb_x_preferred":[
        "Li\u0161any"
    ],
    "name:ces_x_preferred":[
        "Li\u0161any"
    ],
    "name:fra_x_preferred":[
        "Li\u0161any"
    ],
    "name:ita_x_preferred":[
        "Li\u0161any"
    ],
    "name:nld_x_preferred":[
        "Li\u0161any"
    ],
    "name:slk_x_preferred":[
        "Li\u0161any"
    ],
    "name:srp_x_preferred":[
        "\u041b\u0438\u0448\u0430\u043d\u0438"
    ],
    "name:swe_x_preferred":[
        "Li\u0161any"
    ],
    "qs_pg:aaroncc":"CZ",
    "qs_pg:gn_country":"CZ",
    "qs_pg:gn_fcode":"PPL",
    "qs_pg:gn_pop":153,
    "qs_pg:name":"Li\u0161any",
    "qs_pg:name_adm0":"\u010cesk\u00e1 republika",
    "qs_pg:name_adm1":"\u00dasteck\u00fd kraj",
    "qs_pg:photos_9r":0,
    "qs_pg:photos_sr":0,
    "qs_pg:pop_sr":1,
    "qs_pg:qs_pg_placetype":"locality",
    "qs_pg:qs_pg_placetype_gp":"Town",
    "qs_pg:woe_adm0":23424810,
    "woe:adm0_id":23424810,
    "woe:name_adm0":"\u010cesk\u00e1 republika",
    "woe:name_adm1":"\u00dasteck\u00fd kraj",
    "woe:placetype":"Town",
    "wof:name":"Li\u0161any",
    "wof:placetype":"locality",
    "wof:population":153
},
  "geometry": {"coordinates":[13.64191,50.34436],"type":"Point"}
}