{
  "type": "Feature",
  "properties": {
    "gn:gn_country":"CZ",
    "gn:gn_fcode":"PPL",
    "gn:gn_pop":271,
    "gn:population":271,
    "iso:country":"CZ",
    "name:cze_x_preferred":[
        "Nemy\u010deves"
    ],
    "name:dut_x_preferred":[
        "Nemy\u010deves"
    ],
    "name:eng_x_preferred":[
        "Nemy\u010deves"
    ],
    "name:fre_x_preferred":[
        "Nemy\u010deves"
    ],
    "name:hun_x_preferred":[
        "Nemy\u010deves"
    ],
    "name:ita_x_preferred":[
        "Nemy\u010deves"
    ],
    "name:may_x_preferred":[
        "Nemy\u010deves"
    ],
    "name:per_x_preferred":[
        "\u0646\u0645\u06cc\u062a\u0634\u0648\u0633"
    ],
    "name:pol_x_preferred":[
        "Nemy\u010deves"
    ],
    "name:por_x_preferred":[
        "Nemy\u010deves"
    ],
    "name:slo_x_preferred":[
        "Nemy\u010deves"
    ],
    "name:srp_x_preferred":[
        "\u041d\u0435\u043c\u0438\u0447\u0435\u0432\u0435\u0441"
    ],
    "name:swe_x_preferred":[
        "Nemy\u010deves"
    ],
    "name:vie_x_preferred":[
        "Nemy\u010deves"
    ],
    "qs_pg:aaroncc":"CZ",
    "qs_pg:gn_country":"CZ",
    "qs_pg:gn_fcode":"PPL",
    "qs_pg:gn_pop":271,
    "qs_pg:name":"Nemy\u010deves",
    "qs_pg:name_adm0":"\u010cesk\u00e1 republika",
    "qs_pg:name_adm1":"Kr\u00e1lov\u00e9hradeck\u00fd kraj",
    "qs_pg:photos_9r":0,
    "qs_pg:photos_sr":0,
    "qs_pg:pop_sr":2,
    "qs_pg:qs_pg_placetype":"locality",
    "qs_pg:qs_pg_placetype_gp":"Town",
    "qs_pg:woe_adm0":23424810,
    "woe:adm0_id":23424810,
    "woe:name_adm0":"\u010cesk\u00e1 republika",
    "woe:name_adm1":"Kr\u00e1lov\u00e9hradeck\u00fd kraj",
    "woe:placetype":"Town",
    "wof:name":"Nemy\u010deves",
    "wof:placetype":"locality",
    "wof:population":271
},
  "geometry": {"coordinates":[15.37002,50.38443],"type":"Point"}
}