{
  "type": "Feature",
  "properties": {
    "gn:admin1_code":"82.0",
    "gn:admin2_code":"0524",
    "gn:asciiname":"Horni Rokytnice",
    "gn:country_code":"CZ",
    "gn:dem":649,
    "gn:feature_class":"P",
    "gn:feature_code":"PPL",
    "gn:name":"Horn\u00ed Rokytnice",
    "gn:population":0,
    "gn:timezone":"Europe/Prague",
    "iso:country":"CZ",
    "name:und_x_variant":[
        "Oberdorf"
    ],
    "wof:name":"Horni Rokytnice",
    "wof:placetype":"locality"
},
  "geometry": {"coordinates":[16.47407999999999,50.18657],"type":"Point"}
}