{
  "type": "Feature",
  "properties": {
    "gn:admin1_code":"88.0",
    "gn:admin2_code":"0204",
    "gn:asciiname":"Horni Jelcany",
    "gn:country_code":"CZ",
    "gn:dem":382,
    "gn:elevation":"400.0",
    "gn:feature_class":"P",
    "gn:feature_code":"PPL",
    "gn:name":"Horn\u00ed Jel\u010dany",
    "gn:population":1,
    "gn:timezone":"Europe/Prague",
    "iso:country":"CZ",
    "wof:name":"Horni Jelcany",
    "wof:placetype":"locality",
    "wof:population":1
},
  "geometry": {"coordinates":[15.05059,49.9301],"type":"Point"}
}