{
  "type": "Feature",
  "properties": {
    "gn:admin1_code":"89.0",
    "gn:admin2_code":"0426",
    "gn:asciiname":"Nemecky",
    "gn:country_code":"CZ",
    "gn:dem":197,
    "gn:feature_class":"P",
    "gn:feature_code":"PPL",
    "gn:name":"N\u011bme\u010dky",
    "gn:population":0,
    "gn:timezone":"Europe/Prague",
    "iso:country":"CZ",
    "wof:name":"Nemecky",
    "wof:placetype":"locality"
},
  "geometry": {"coordinates":[13.84367,50.58598],"type":"Point"}
}