{
  "type": "Feature",
  "properties": {
    "gn:admin1_code":"82.0",
    "gn:admin2_code":"0524",
    "gn:asciiname":"Nove Dvory",
    "gn:country_code":"CZ",
    "gn:dem":326,
    "gn:feature_class":"P",
    "gn:feature_code":"PPL",
    "gn:name":"Nov\u00e9 Dvory",
    "gn:population":0,
    "gn:timezone":"Europe/Prague",
    "iso:country":"CZ",
    "wof:name":"Nove Dvory",
    "wof:placetype":"locality"
},
  "geometry": {"coordinates":[16.23947,50.22187],"type":"Point"}
}