{
  "type": "Feature",
  "properties": {
    "gn:admin1_code":"88.0",
    "gn:admin2_code":"020B",
    "gn:asciiname":"Chlum",
    "gn:country_code":"CZ",
    "gn:dem":337,
    "gn:feature_class":"P",
    "gn:feature_code":"PPL",
    "gn:name":"Chlum",
    "gn:population":0,
    "gn:timezone":"Europe/Prague",
    "iso:country":"CZ",
    "name:ceb_x_preferred":[
        "Chlum"
    ],
    "name:ces_x_preferred":[
        "Chlum"
    ],
    "name:deu_x_preferred":[
        "Chlum"
    ],
    "name:epo_x_preferred":[
        "Chlum"
    ],
    "name:fra_x_preferred":[
        "Chlum"
    ],
    "name:hun_x_preferred":[
        "Chlum"
    ],
    "name:ita_x_preferred":[
        "Chlum"
    ],
    "name:nld_x_preferred":[
        "Chlum"
    ],
    "name:oci_x_preferred":[
        "Chlum"
    ],
    "name:pol_x_preferred":[
        "Chlum"
    ],
    "name:slk_x_preferred":[
        "Chlum"
    ],
    "name:srp_x_preferred":[
        "\u0425\u043b\u0443\u043c"
    ],
    "name:swe_x_preferred":[
        "Chlum"
    ],
    "name:ukr_x_preferred":[
        "\u0425\u043b\u0443\u043c"
    ],
    "wof:name":"Chlum",
    "wof:placetype":"locality"
},
  "geometry": {"coordinates":[14.38058,49.69976],"type":"Point"}
}