{
  "type": "Feature",
  "properties": {
    "gn:gn_country":"CZ",
    "gn:gn_fcode":"PPL",
    "gn:gn_pop":0,
    "iso:country":"CZ",
    "name:ces_x_preferred":[
        "Svat\u00e1 Kate\u0159ina"
    ],
    "name:deu_x_preferred":[
        "Svat\u00e1 Kate\u0159ina"
    ],
    "name:eng_x_preferred":[
        "Svat\u00e1 Kate\u0159ina"
    ],
    "name:fra_x_preferred":[
        "Svat\u00e1 Kate\u0159ina"
    ],
    "name:ita_x_preferred":[
        "Svat\u00e1 Kate\u0159ina"
    ],
    "name:por_x_preferred":[
        "Svat\u00e1 Kate\u0159ina"
    ],
    "name:spa_x_preferred":[
        "Svat\u00e1 Kate\u0159ina"
    ],
    "qs_pg:aaroncc":"CZ",
    "qs_pg:gn_country":"CZ",
    "qs_pg:gn_fcode":"PPL",
    "qs_pg:gn_pop":0,
    "qs_pg:name":"Svat\u00e1 Kate\u0159ina",
    "qs_pg:name_adm0":"\u010cesk\u00e1 republika",
    "qs_pg:name_adm1":"Kraj Vyso\u010dina",
    "qs_pg:photos":16,
    "qs_pg:photos_1k":3,
    "qs_pg:photos_9k":1,
    "qs_pg:photos_9r":1,
    "qs_pg:photos_all":16,
    "qs_pg:photos_sr":1,
    "qs_pg:pop_sr":0,
    "qs_pg:qs_pg_placetype":"locality",
    "qs_pg:qs_pg_placetype_gp":"Town",
    "qs_pg:woe_adm0":23424810,
    "woe:adm0_id":23424810,
    "woe:name_adm0":"\u010cesk\u00e1 republika",
    "woe:name_adm1":"Kraj Vyso\u010dina",
    "woe:placetype":"Town",
    "wof:name":"Svat\u00e1 Kate\u0159ina",
    "wof:placetype":"locality"
},
  "geometry": {"coordinates":[15.33721,50.00348],"type":"Point"}
}