{
  "type": "Feature",
  "properties": {
    "gn:gn_country":"CZ",
    "gn:gn_fcode":"PPL",
    "gn:gn_pop":974,
    "gn:population":974,
    "iso:country":"CZ",
    "name:azb_x_preferred":[
        "\u0633\u062a\u0631\u0627\u062e\u0648\u062a\u06cc\u062a\u0633\u0647"
    ],
    "name:ceb_x_preferred":[
        "Strachotice"
    ],
    "name:ces_x_preferred":[
        "Strachotice"
    ],
    "name:deu_x_preferred":[
        "Strachotice"
    ],
    "name:eng_x_preferred":[
        "Strachotice"
    ],
    "name:eus_x_preferred":[
        "Strachotice"
    ],
    "name:fas_x_preferred":[
        "\u0633\u062a\u0631\u0627\u062e\u0648\u062a\u06cc\u062a\u0633\u0647"
    ],
    "name:fra_x_preferred":[
        "Strachotice"
    ],
    "name:hun_x_preferred":[
        "Strachotice"
    ],
    "name:ita_x_preferred":[
        "Strachotice"
    ],
    "name:msa_x_preferred":[
        "Strachotice"
    ],
    "name:nan_x_preferred":[
        "Strachotice"
    ],
    "name:nld_x_preferred":[
        "Strachotice"
    ],
    "name:pol_x_preferred":[
        "Strachotice"
    ],
    "name:por_x_preferred":[
        "Strachotice"
    ],
    "name:rup_x_preferred":[
        "Strachotice"
    ],
    "name:slk_x_preferred":[
        "Strachotice"
    ],
    "name:spa_x_preferred":[
        "Strachotice"
    ],
    "name:srp_x_preferred":[
        "\u0421\u0442\u0440\u0430\u0445\u043e\u0442\u0438\u0446\u0435"
    ],
    "name:swe_x_preferred":[
        "Strachotice"
    ],
    "name:unk_x_variant":[
        "Rausenbruck"
    ],
    "name:vie_x_preferred":[
        "Strachotice"
    ],
    "qs_pg:aaroncc":"CZ",
    "qs_pg:gn_country":"CZ",
    "qs_pg:gn_fcode":"PPL",
    "qs_pg:gn_pop":974,
    "qs_pg:name":"Strachotice",
    "qs_pg:name_adm0":"\u010cesk\u00e1 republika",
    "qs_pg:name_adm1":"Jihomoravsk\u00fd kraj",
    "qs_pg:photos":13,
    "qs_pg:photos_1k":3,
    "qs_pg:photos_9k":1,
    "qs_pg:photos_9r":1,
    "qs_pg:photos_all":13,
    "qs_pg:photos_sr":1,
    "qs_pg:pop_sr":2,
    "qs_pg:qs_pg_placetype":"locality",
    "qs_pg:qs_pg_placetype_gp":"Town",
    "qs_pg:woe_adm0":23424810,
    "woe:adm0_id":23424810,
    "woe:name_adm0":"\u010cesk\u00e1 republika",
    "woe:name_adm1":"Jihomoravsk\u00fd kraj",
    "woe:placetype":"Town",
    "wof:name":"Strachotice",
    "wof:placetype":"locality",
    "wof:population":974
},
  "geometry": {"coordinates":[16.1723,48.79614],"type":"Point"}
}