{
  "type": "Feature",
  "properties": {
    "gn:admin1_code":"84.0",
    "gn:admin2_code":"0712",
    "gn:asciiname":"Hablov",
    "gn:country_code":"CZ",
    "gn:dem":213,
    "gn:feature_class":"P",
    "gn:feature_code":"PPL",
    "gn:name":"Hablov",
    "gn:population":0,
    "gn:timezone":"Europe/Prague",
    "iso:country":"CZ",
    "wof:name":"Hablov",
    "wof:placetype":"locality"
},
  "geometry": {"coordinates":[17.18004,49.53045],"type":"Point"}
}