{
  "type": "Feature",
  "properties": {
    "gn:admin1_code":"84.0",
    "gn:admin2_code":"0715",
    "gn:asciiname":"Labe",
    "gn:country_code":"CZ",
    "gn:dem":643,
    "gn:feature_class":"P",
    "gn:feature_code":"PPL",
    "gn:name":"Labe",
    "gn:population":0,
    "gn:timezone":"Europe/Prague",
    "iso:country":"CZ",
    "name:und_x_variant":[
        "Elba",
        "Labe"
    ],
    "wof:name":"Labe",
    "wof:placetype":"locality"
},
  "geometry": {"coordinates":[17.02071,50.10666],"type":"Point"}
}