{
  "type": "Feature",
  "properties": {
    "gn:country":"CZ",
    "gn:fcode":"PPL",
    "gn:population":461,
    "iso:country":"CZ",
    "name:azb_x_preferred":[
        "\u0698\u0627\u0644\u0627\u0646\u06cc"
    ],
    "name:cat_x_preferred":[
        "\u017dalany"
    ],
    "name:ceb_x_preferred":[
        "\u017dalany"
    ],
    "name:ces_x_preferred":[
        "\u017dalany"
    ],
    "name:che_x_preferred":[
        "\u0416\u0430\u043b\u0430\u043d\u0438"
    ],
    "name:deu_x_historical":[
        "Schallan"
    ],
    "name:deu_x_preferred":[
        "Schallan"
    ],
    "name:deu_x_variant":[
        "\u017dalany"
    ],
    "name:eng_x_preferred":[
        "\u017dalany"
    ],
    "name:epo_x_preferred":[
        "\u017dalany"
    ],
    "name:eus_x_preferred":[
        "\u017dalany"
    ],
    "name:fas_x_preferred":[
        "\u0698\u0627\u0644\u0627\u0646\u06cc"
    ],
    "name:fra_x_preferred":[
        "\u017dalany"
    ],
    "name:gle_x_preferred":[
        "\u017dalany"
    ],
    "name:hun_x_preferred":[
        "\u017dalany"
    ],
    "name:ita_x_preferred":[
        "\u017dalany"
    ],
    "name:lmo_x_preferred":[
        "\u017dalany"
    ],
    "name:msa_x_preferred":[
        "\u017dalany"
    ],
    "name:nan_x_preferred":[
        "\u017dalany"
    ],
    "name:nld_x_preferred":[
        "\u017dalany"
    ],
    "name:pol_x_preferred":[
        "\u017dalany"
    ],
    "name:por_x_preferred":[
        "\u017dalany"
    ],
    "name:rup_x_preferred":[
        "\u017dalany"
    ],
    "name:slk_x_preferred":[
        "\u017dalany"
    ],
    "name:spa_x_preferred":[
        "\u017dalany"
    ],
    "name:srp_x_preferred":[
        "\u0416\u0430\u043b\u0430\u043d\u0438"
    ],
    "name:swe_x_preferred":[
        "\u017dalany"
    ],
    "name:tat_x_preferred":[
        "\u0416\u0430\u043b\u0430\u043d\u0438"
    ],
    "name:uzb_x_preferred":[
        "\u017dalany"
    ],
    "name:vec_x_preferred":[
        "\u017dalany"
    ],
    "name:vie_x_preferred":[
        "\u017dalany"
    ],
    "qs_pg:aaroncc":"CZ",
    "qs_pg:gn_country":"CZ",
    "qs_pg:gn_fcode":"PPL",
    "qs_pg:gn_pop":461,
    "qs_pg:name":"\u017dalany",
    "qs_pg:name_adm0":"\u010cesk\u00e1 republika",
    "qs_pg:name_adm1":"\u00dasteck\u00fd kraj",
    "qs_pg:photos_9k":1,
    "qs_pg:photos_9r":1,
    "qs_pg:photos_all":3,
    "qs_pg:photos_sr":0,
    "qs_pg:pop_sr":2,
    "qs_pg:qs_pg_placetype":"locality",
    "qs_pg:qs_pg_placetype_gp":"Town",
    "qs_pg:woe_adm0":23424810,
    "woe:adm0_id":23424810,
    "woe:name_adm0":"\u010cesk\u00e1 republika",
    "woe:name_adm1":"\u00dasteck\u00fd kraj",
    "woe:placetype":"Town",
    "wof:name":"\u017dalany",
    "wof:placetype":"locality",
    "wof:population":461
},
  "geometry": {"coordinates":[13.90633,50.59002],"type":"Point"}
}