{
  "type": "Feature",
  "properties": {
    "gn:gn_country":"CZ",
    "gn:gn_fcode":"PPL",
    "gn:gn_pop":461,
    "gn:population":461,
    "iso:country":"CZ",
    "name:cze_x_preferred":[
        "\u017dalany"
    ],
    "name:deu_x_historical":[
        "Schallan"
    ],
    "name:deu_x_preferred":[
        "Schallan"
    ],
    "name:dut_x_preferred":[
        "\u017dalany"
    ],
    "name:eng_x_preferred":[
        "\u017dalany"
    ],
    "name:fre_x_preferred":[
        "\u017dalany"
    ],
    "name:ger_x_preferred":[
        "\u017dalany"
    ],
    "name:hun_x_preferred":[
        "\u017dalany"
    ],
    "name:ita_x_preferred":[
        "\u017dalany"
    ],
    "name:may_x_preferred":[
        "\u017dalany"
    ],
    "name:nan_x_preferred":[
        "\u017dalany"
    ],
    "name:per_x_preferred":[
        "\u0698\u0627\u0644\u0627\u0646\u06cc"
    ],
    "name:pol_x_preferred":[
        "\u017dalany"
    ],
    "name:por_x_preferred":[
        "\u017dalany"
    ],
    "name:rup_x_preferred":[
        "\u017dalany"
    ],
    "name:slo_x_preferred":[
        "\u017dalany"
    ],
    "name:srp_x_preferred":[
        "\u0416\u0430\u043b\u0430\u043d\u0438"
    ],
    "name:swe_x_preferred":[
        "\u017dalany"
    ],
    "name:vie_x_preferred":[
        "\u017dalany"
    ],
    "qs_pg:aaroncc":"CZ",
    "qs_pg:gn_country":"CZ",
    "qs_pg:gn_fcode":"PPL",
    "qs_pg:gn_pop":461,
    "qs_pg:name":"\u017dalany",
    "qs_pg:name_adm0":"\u010cesk\u00e1 republika",
    "qs_pg:name_adm1":"\u00dasteck\u00fd kraj",
    "qs_pg:photos_9k":1,
    "qs_pg:photos_9r":1,
    "qs_pg:photos_all":3,
    "qs_pg:photos_sr":0,
    "qs_pg:pop_sr":2,
    "qs_pg:qs_pg_placetype":"locality",
    "qs_pg:qs_pg_placetype_gp":"Town",
    "qs_pg:woe_adm0":23424810,
    "woe:adm0_id":23424810,
    "woe:name_adm0":"\u010cesk\u00e1 republika",
    "woe:name_adm1":"\u00dasteck\u00fd kraj",
    "woe:placetype":"Town",
    "wof:name":"\u017dalany",
    "wof:placetype":"locality",
    "wof:population":461
},
  "geometry": {"coordinates":[13.90633,50.59002],"type":"Point"}
}