{
  "type": "Feature",
  "properties": {
    "gn:admin1_code":"86",
    "gn:admin2_code":"0532",
    "gn:asciiname":"Telcice",
    "gn:country_code":"CZ",
    "gn:dem":223,
    "gn:feature_class":"P",
    "gn:feature_code":"PPL",
    "gn:name":"Tel\u010dice",
    "gn:population":0,
    "gn:timezone":"Europe/Prague",
    "iso:country":"CZ",
    "wof:name":"Telcice",
    "wof:placetype":"locality"
},
  "geometry": {"coordinates":[15.41528,50.03428],"type":"Point"}
}