{
  "type": "Feature",
  "properties": {
    "gn:admin1_code":"88",
    "gn:admin2_code":"0201",
    "gn:asciiname":"Volavka",
    "gn:country_code":"CZ",
    "gn:dem":473,
    "gn:feature_class":"P",
    "gn:feature_code":"PPL",
    "gn:name":"Volavka",
    "gn:population":0,
    "gn:timezone":"Europe/Prague",
    "iso:country":"CZ",
    "wof:name":"Volavka",
    "wof:placetype":"locality"
},
  "geometry": {"coordinates":[14.91424,49.63319],"type":"Point"}
}