{
  "type": "Feature",
  "properties": {
    "gn:admin1_code":"86.0",
    "gn:admin2_code":"0531",
    "gn:asciiname":"Bily Kamen",
    "gn:country_code":"CZ",
    "gn:dem":394,
    "gn:feature_class":"P",
    "gn:feature_code":"PPL",
    "gn:name":"B\u00edl\u00fd K\u00e1men",
    "gn:population":0,
    "gn:timezone":"Europe/Prague",
    "iso:country":"CZ",
    "wof:name":"Bily Kamen",
    "wof:placetype":"locality"
},
  "geometry": {"coordinates":[15.5519,49.93102],"type":"Point"}
}