{
  "type": "Feature",
  "properties": {
    "gn:gn_country":"CZ",
    "gn:gn_fcode":"PPL",
    "gn:gn_pop":259,
    "gn:population":259,
    "iso:country":"CZ",
    "name:ceb_x_preferred":[
        "Turkovice"
    ],
    "name:ces_x_preferred":[
        "Turkovice"
    ],
    "name:deu_x_preferred":[
        "Turkovice"
    ],
    "name:eng_x_preferred":[
        "Turkovice"
    ],
    "name:epo_x_preferred":[
        "Turkovice"
    ],
    "name:eus_x_preferred":[
        "Turkovice"
    ],
    "name:fra_x_preferred":[
        "Turkovice"
    ],
    "name:hun_x_preferred":[
        "Turkovice"
    ],
    "name:ita_x_preferred":[
        "Turkovice"
    ],
    "name:msa_x_preferred":[
        "Turkovice"
    ],
    "name:nan_x_preferred":[
        "Turkovice"
    ],
    "name:nld_x_preferred":[
        "Turkovice"
    ],
    "name:pol_x_preferred":[
        "Turkovice"
    ],
    "name:por_x_preferred":[
        "Turkovice"
    ],
    "name:rup_x_preferred":[
        "Turkovice"
    ],
    "name:slk_x_preferred":[
        "Turkovice"
    ],
    "name:spa_x_preferred":[
        "Turkovice"
    ],
    "name:srp_x_preferred":[
        "\u0422\u0443\u0440\u043a\u043e\u0432\u0438\u0446\u0435"
    ],
    "name:swe_x_preferred":[
        "Turkovice"
    ],
    "name:vie_x_preferred":[
        "Turkovice"
    ],
    "qs_pg:aaroncc":"CZ",
    "qs_pg:gn_country":"CZ",
    "qs_pg:gn_fcode":"PPL",
    "qs_pg:gn_pop":259,
    "qs_pg:name":"Turkovice",
    "qs_pg:name_adm0":"\u010cesk\u00e1 republika",
    "qs_pg:name_adm1":"Pardubick\u00fd kraj",
    "qs_pg:photos_9k":1,
    "qs_pg:photos_9r":1,
    "qs_pg:photos_all":2,
    "qs_pg:photos_sr":0,
    "qs_pg:pop_sr":2,
    "qs_pg:qs_pg_placetype":"locality",
    "qs_pg:qs_pg_placetype_gp":"Town",
    "qs_pg:woe_adm0":23424810,
    "woe:adm0_id":23424810,
    "woe:name_adm0":"\u010cesk\u00e1 republika",
    "woe:name_adm1":"Pardubick\u00fd kraj",
    "woe:placetype":"Town",
    "wof:name":"Turkovice",
    "wof:placetype":"locality",
    "wof:population":259
},
  "geometry": {"coordinates":[15.54875,49.95245],"type":"Point"}
}