{
  "type": "Feature",
  "properties": {
    "gn:gn_country":"CZ",
    "gn:gn_fcode":"PPL",
    "gn:gn_pop":180,
    "gn:population":180,
    "iso:country":"CZ",
    "name:ces_x_preferred":[
        "Zbo\u017e\u00ed\u010dko"
    ],
    "name:deu_x_preferred":[
        "Zbo\u017e\u00ed\u010dko"
    ],
    "name:eng_x_preferred":[
        "Zbo\u017e\u00ed\u010dko"
    ],
    "name:fas_x_preferred":[
        "\u0632\u0628\u0648\u0698\u06cc\u062a\u0634\u06a9\u0648"
    ],
    "name:fra_x_preferred":[
        "Zbo\u017e\u00ed\u010dko"
    ],
    "name:hun_x_preferred":[
        "Zbo\u017e\u00ed\u010dko"
    ],
    "name:ita_x_preferred":[
        "Zbo\u017e\u00ed\u010dko"
    ],
    "name:msa_x_preferred":[
        "Zbo\u017e\u00ed\u010dko"
    ],
    "name:nan_x_preferred":[
        "Zbo\u017e\u00ed\u010dko"
    ],
    "name:nld_x_preferred":[
        "Zbo\u017e\u00ed\u010dko"
    ],
    "name:pol_x_preferred":[
        "Zbo\u017e\u00ed\u010dko"
    ],
    "name:por_x_preferred":[
        "Zbo\u017e\u00ed\u010dko"
    ],
    "name:rup_x_preferred":[
        "Zbo\u017e\u00ed\u010dko"
    ],
    "name:slk_x_preferred":[
        "Zbo\u017e\u00ed\u010dko"
    ],
    "name:srp_x_preferred":[
        "\u0417\u0431\u043e\u0436\u0438\u0447\u043a\u043e"
    ],
    "name:swe_x_preferred":[
        "Zbo\u017e\u00ed\u010dko"
    ],
    "name:vie_x_preferred":[
        "Zbo\u017e\u00ed\u010dko"
    ],
    "qs_pg:aaroncc":"CZ",
    "qs_pg:gn_country":"CZ",
    "qs_pg:gn_fcode":"PPL",
    "qs_pg:gn_pop":180,
    "qs_pg:name":"Zbo\u017e\u00ed\u010dko",
    "qs_pg:name_adm0":"\u010cesk\u00e1 republika",
    "qs_pg:name_adm1":"St\u0159edo\u010desk\u00fd kraj",
    "qs_pg:photos_9k":1,
    "qs_pg:photos_9r":1,
    "qs_pg:photos_all":1,
    "qs_pg:photos_sr":0,
    "qs_pg:pop_sr":1,
    "qs_pg:qs_pg_placetype":"locality",
    "qs_pg:qs_pg_placetype_gp":"Town",
    "qs_pg:woe_adm0":23424810,
    "woe:adm0_id":23424810,
    "woe:name_adm0":"\u010cesk\u00e1 republika",
    "woe:name_adm1":"St\u0159edo\u010desk\u00fd kraj",
    "woe:placetype":"Town",
    "wof:name":"Zbo\u017e\u00ed\u010dko",
    "wof:placetype":"locality",
    "wof:population":180
},
  "geometry": {"coordinates":[14.93982,50.22573],"type":"Point"}
}