{
  "type": "Feature",
  "properties": {
    "gn:admin1_code":"88.0",
    "gn:admin2_code":"0201",
    "gn:asciiname":"Beztahov",
    "gn:country_code":"CZ",
    "gn:dem":537,
    "gn:feature_class":"P",
    "gn:feature_code":"PPL",
    "gn:name":"Beztahov",
    "gn:population":0,
    "gn:timezone":"Europe/Prague",
    "iso:country":"CZ",
    "wof:name":"Beztahov",
    "wof:placetype":"locality"
},
  "geometry": {"coordinates":[14.61093,49.6401],"type":"Point"}
}