{
  "type": "Feature",
  "properties": {
    "gn:admin1_code":"88.0",
    "gn:admin2_code":"0208",
    "gn:asciiname":"Drahelice",
    "gn:country_code":"CZ",
    "gn:dem":185,
    "gn:feature_class":"P",
    "gn:feature_code":"PPL",
    "gn:name":"Drahelice",
    "gn:population":0,
    "gn:timezone":"Europe/Prague",
    "iso:country":"CZ",
    "wof:name":"Drahelice",
    "wof:placetype":"locality"
},
  "geometry": {"coordinates":[15.01404,50.17623],"type":"Point"}
}