{
  "type": "Feature",
  "properties": {
    "gn:gn_country":"CZ",
    "gn:gn_fcode":"PPL",
    "gn:gn_pop":287,
    "gn:population":287,
    "iso:country":"CZ",
    "name:bul_x_preferred":[
        "\u041e\u043a\u043e\u0443\u043d\u043e\u0432"
    ],
    "name:cze_x_preferred":[
        "Okounov"
    ],
    "name:dut_x_preferred":[
        "Okounov"
    ],
    "name:eng_x_preferred":[
        "Okounov"
    ],
    "name:fre_x_preferred":[
        "Okounov"
    ],
    "name:ger_x_preferred":[
        "Okounov"
    ],
    "name:hun_x_preferred":[
        "Okounov"
    ],
    "name:ita_x_preferred":[
        "Okounov"
    ],
    "name:may_x_preferred":[
        "Okounov"
    ],
    "name:per_x_preferred":[
        "\u0627\u0648\u06a9\u0648\u0648\u0646\u0648\u0648"
    ],
    "name:pol_x_preferred":[
        "Okounov"
    ],
    "name:por_x_preferred":[
        "Okounov"
    ],
    "name:slo_x_preferred":[
        "Okounov"
    ],
    "name:srp_x_preferred":[
        "\u041e\u043a\u043e\u0443\u043d\u043e\u0432"
    ],
    "name:swe_x_preferred":[
        "Okounov"
    ],
    "name:unk_x_variant":[
        "Okenau"
    ],
    "name:vie_x_preferred":[
        "Okounov"
    ],
    "qs_pg:aaroncc":"CZ",
    "qs_pg:gn_country":"CZ",
    "qs_pg:gn_fcode":"PPL",
    "qs_pg:gn_pop":287,
    "qs_pg:name":"Okounov",
    "qs_pg:name_adm0":"\u010cesk\u00e1 republika",
    "qs_pg:name_adm1":"\u00dasteck\u00fd kraj",
    "qs_pg:photos_9k":1,
    "qs_pg:photos_9r":1,
    "qs_pg:photos_all":2,
    "qs_pg:photos_sr":0,
    "qs_pg:pop_sr":2,
    "qs_pg:qs_pg_placetype":"locality",
    "qs_pg:qs_pg_placetype_gp":"Town",
    "qs_pg:woe_adm0":23424810,
    "woe:adm0_id":23424810,
    "woe:name_adm0":"\u010cesk\u00e1 republika",
    "woe:name_adm1":"\u00dasteck\u00fd kraj",
    "woe:placetype":"Town",
    "wof:name":"Okounov",
    "wof:placetype":"locality",
    "wof:population":287
},
  "geometry": {"coordinates":[13.10656,50.36222],"type":"Point"}
}