{
  "type": "Feature",
  "properties": {
    "gn:admin1_code":"88.0",
    "gn:admin2_code":"0201",
    "gn:asciiname":"Mysletice",
    "gn:country_code":"CZ",
    "gn:dem":630,
    "gn:feature_class":"P",
    "gn:feature_code":"PPL",
    "gn:name":"Mysletice",
    "gn:population":0,
    "gn:timezone":"Europe/Prague",
    "iso:country":"CZ",
    "name:azb_x_preferred":[
        "\u0645\u06cc\u0633\u0644\u062a\u06cc\u062a\u0633\u0647"
    ],
    "name:ceb_x_preferred":[
        "Mysletice"
    ],
    "name:ces_x_preferred":[
        "Mysletice"
    ],
    "name:eus_x_preferred":[
        "Mysletice"
    ],
    "name:fas_x_preferred":[
        "\u0645\u06cc\u0633\u0644\u062a\u06cc\u062a\u0633\u0647"
    ],
    "name:fra_x_preferred":[
        "Mysletice"
    ],
    "name:hun_x_preferred":[
        "Mysletice"
    ],
    "name:ita_x_preferred":[
        "Mysletice"
    ],
    "name:msa_x_preferred":[
        "Mysletice"
    ],
    "name:nld_x_preferred":[
        "Mysletice"
    ],
    "name:pol_x_preferred":[
        "Mysletice"
    ],
    "name:por_x_preferred":[
        "Mysletice"
    ],
    "name:slk_x_preferred":[
        "Mysletice"
    ],
    "name:spa_x_preferred":[
        "Mysletice"
    ],
    "name:srp_x_preferred":[
        "\u041c\u0438\u0441\u043b\u0435\u0442\u0438\u0446\u0435"
    ],
    "name:swe_x_preferred":[
        "Mysletice"
    ],
    "name:vie_x_preferred":[
        "Mysletice"
    ],
    "wof:name":"Mysletice",
    "wof:placetype":"locality"
},
  "geometry": {"coordinates":[14.66512,49.62248],"type":"Point"}
}