{
  "type": "Feature",
  "properties": {
    "gn:admin1_code":"88.0",
    "gn:admin2_code":"0201",
    "gn:asciiname":"Mysletice",
    "gn:country_code":"CZ",
    "gn:dem":630,
    "gn:feature_class":"P",
    "gn:feature_code":"PPL",
    "gn:name":"Mysletice",
    "gn:population":0,
    "gn:timezone":"Europe/Prague",
    "iso:country":"CZ",
    "wof:name":"Mysletice",
    "wof:placetype":"locality"
},
  "geometry": {"coordinates":[14.66512,49.62248],"type":"Point"}
}