{
  "type": "Feature",
  "properties": {
    "gn:admin1_code":"79.0",
    "gn:admin2_code":"0312",
    "gn:asciiname":"Dolni Svince",
    "gn:country_code":"CZ",
    "gn:dem":519,
    "gn:feature_class":"P",
    "gn:feature_code":"PPL",
    "gn:name":"Doln\u00ed Svince",
    "gn:population":0,
    "gn:timezone":"Europe/Prague",
    "iso:country":"CZ",
    "wof:name":"Dolni Svince",
    "wof:placetype":"locality"
},
  "geometry": {"coordinates":[14.43186,48.85685],"type":"Point"}
}