{
  "type": "Feature",
  "properties": {
    "gn:admin1_code":"79.0",
    "gn:admin2_code":"0315",
    "gn:asciiname":"Brixuv Dvur",
    "gn:country_code":"CZ",
    "gn:dem":885,
    "gn:feature_class":"P",
    "gn:feature_code":"PPL",
    "gn:name":"Brix\u016fv Dv\u016fr",
    "gn:population":0,
    "gn:timezone":"Europe/Prague",
    "iso:country":"CZ",
    "wof:name":"Brixuv Dvur",
    "wof:placetype":"locality"
},
  "geometry": {"coordinates":[13.86667,48.91667],"type":"Point"}
}