{
  "type": "Feature",
  "properties": {
    "gn:admin1_code":"83",
    "gn:admin2_code":"0511",
    "gn:asciiname":"Svaby",
    "gn:country_code":"CZ",
    "gn:dem":285,
    "gn:feature_class":"P",
    "gn:feature_code":"PPL",
    "gn:name":"\u0160v\u00e1by",
    "gn:population":0,
    "gn:timezone":"Europe/Prague",
    "iso:country":"CZ",
    "wof:name":"Svaby",
    "wof:placetype":"locality"
},
  "geometry": {"coordinates":[14.52431,50.60507],"type":"Point"}
}