{
  "type": "Feature",
  "properties": {
    "gn:admin1_code":"90.0",
    "gn:admin2_code":"0722",
    "gn:asciiname":"Ordejov",
    "gn:country_code":"CZ",
    "gn:dem":331,
    "gn:feature_class":"P",
    "gn:feature_code":"PPL",
    "gn:name":"Ord\u011bjov",
    "gn:population":0,
    "gn:timezone":"Europe/Prague",
    "iso:country":"CZ",
    "name:und_x_variant":[
        "Dv\u016dr Ord\u011bjov",
        "Ord\u011bjov"
    ],
    "wof:name":"Ordejov",
    "wof:placetype":"locality"
},
  "geometry": {"coordinates":[17.74862000000001,48.9719],"type":"Point"}
}