{
  "type": "Feature",
  "properties": {
    "iso:country":"CZ",
    "name:bul_x_preferred":[
        "\u0422\u0443\u0440\u043d\u043e\u0432"
    ],
    "name:ceb_x_preferred":[
        "Turnov"
    ],
    "name:ces_x_preferred":[
        "Turnov"
    ],
    "name:deu_x_preferred":[
        "Turnov"
    ],
    "name:dsb_x_preferred":[
        "Turnow"
    ],
    "name:epo_x_preferred":[
        "Turnov"
    ],
    "name:eus_x_preferred":[
        "Turnov"
    ],
    "name:fas_x_preferred":[
        "\u062a\u0648\u0631\u0646\u0648\u0648"
    ],
    "name:fra_x_preferred":[
        "Turnov"
    ],
    "name:heb_x_preferred":[
        "\u05d8\u05d5\u05e8\u05e0\u05d5\u05d1"
    ],
    "name:hun_x_preferred":[
        "Turnov"
    ],
    "name:ita_x_preferred":[
        "Turnov"
    ],
    "name:kor_x_preferred":[
        "\ud22c\ub974\ub178\ud504"
    ],
    "name:lit_x_preferred":[
        "Turnovas"
    ],
    "name:msa_x_preferred":[
        "Turnov"
    ],
    "name:nld_x_preferred":[
        "Turnov"
    ],
    "name:nor_x_preferred":[
        "Turnov"
    ],
    "name:pol_x_preferred":[
        "Turnov"
    ],
    "name:por_x_preferred":[
        "Turnov"
    ],
    "name:rus_x_preferred":[
        "\u0422\u0443\u0440\u043d\u043e\u0432"
    ],
    "name:slk_x_preferred":[
        "Turnov"
    ],
    "name:spa_x_preferred":[
        "Turnov"
    ],
    "name:srp_x_preferred":[
        "\u0422\u0443\u0440\u043d\u043e\u0432"
    ],
    "name:swe_x_preferred":[
        "Turnov"
    ],
    "name:tur_x_preferred":[
        "Turnov"
    ],
    "name:ukr_x_preferred":[
        "\u0422\u0443\u0440\u043d\u043e\u0432"
    ],
    "name:vie_x_preferred":[
        "Turnov"
    ],
    "name:zho_x_preferred":[
        "\u56fe\u5c14\u8bfa\u592b"
    ],
    "qs_pg:aaroncc":"CZ",
    "qs_pg:name":"Turnov",
    "qs_pg:name_adm0":"\u010cesk\u00e1 republika",
    "qs_pg:name_adm1":"Libereck\u00fd kraj",
    "qs_pg:photos":228,
    "qs_pg:photos_1k":46,
    "qs_pg:photos_9k":4,
    "qs_pg:photos_9r":6,
    "qs_pg:photos_all":858,
    "qs_pg:photos_sr":4,
    "qs_pg:pop_sr":0,
    "qs_pg:qs_pg_placetype":"localadmin",
    "qs_pg:qs_pg_placetype_gp":"LocalAdmin",
    "qs_pg:woe_adm0":23424810,
    "woe:adm0_id":23424810,
    "woe:name_adm0":"\u010cesk\u00e1 republika",
    "woe:name_adm1":"Libereck\u00fd kraj",
    "woe:placetype":"LocalAdmin",
    "wof:name":"Turnov",
    "wof:placetype":"localadmin"
},
  "geometry": {"coordinates":[15.156583,50.588907],"type":"Point"}
}