{
  "type": "Feature",
  "properties": {
    "gn:country":"CZ",
    "gn:fcode":"PPL",
    "gn:population":66,
    "iso:country":"CZ",
    "name:azb_x_preferred":[
        "\u0632\u0627\u0644\u0648\u0698\u06cc\u062a\u0633\u0647"
    ],
    "name:ces_x_preferred":[
        "Z\u00e1lu\u017eice"
    ],
    "name:deu_x_preferred":[
        "Z\u00e1lu\u017eice"
    ],
    "name:eng_x_preferred":[
        "Z\u00e1lu\u017eice"
    ],
    "name:eus_x_preferred":[
        "Z\u00e1lu\u017eice"
    ],
    "name:fas_x_preferred":[
        "\u0632\u0627\u0644\u0648\u0698\u06cc\u062a\u0633\u0647"
    ],
    "name:fra_x_preferred":[
        "Z\u00e1lu\u017eice"
    ],
    "name:hun_x_preferred":[
        "Z\u00e1lu\u017eice"
    ],
    "name:ita_x_preferred":[
        "Z\u00e1lu\u017eice"
    ],
    "name:msa_x_preferred":[
        "Z\u00e1lu\u017eice"
    ],
    "name:nan_x_preferred":[
        "Z\u00e1lu\u017eice"
    ],
    "name:nld_x_preferred":[
        "Z\u00e1lu\u017eice"
    ],
    "name:por_x_preferred":[
        "Z\u00e1lu\u017eice"
    ],
    "name:rup_x_preferred":[
        "Z\u00e1lu\u017eice"
    ],
    "name:slk_x_preferred":[
        "Z\u00e1lu\u017eice"
    ],
    "name:spa_x_preferred":[
        "Z\u00e1lu\u017eice"
    ],
    "name:srp_x_preferred":[
        "\u0417\u0430\u043b\u0443\u0436\u0438\u0446\u0435"
    ],
    "name:vie_x_preferred":[
        "Z\u00e1lu\u017eice"
    ],
    "qs_pg:aaroncc":"CZ",
    "qs_pg:gn_country":"CZ",
    "qs_pg:gn_fcode":"PPL",
    "qs_pg:gn_pop":66,
    "qs_pg:name":"Z\u00e1lu\u017eice",
    "qs_pg:name_adm0":"\u010cesk\u00e1 republika",
    "qs_pg:name_adm1":"\u00dasteck\u00fd kraj",
    "qs_pg:photos_9r":0,
    "qs_pg:photos_sr":0,
    "qs_pg:pop_sr":1,
    "qs_pg:qs_pg_placetype":"locality",
    "qs_pg:qs_pg_placetype_gp":"Town",
    "qs_pg:woe_adm0":23424810,
    "woe:adm0_id":23424810,
    "woe:name_adm0":"\u010cesk\u00e1 republika",
    "woe:name_adm1":"\u00dasteck\u00fd kraj",
    "woe:placetype":"Town",
    "wof:name":"Z\u00e1lu\u017eice",
    "wof:placetype":"locality",
    "wof:population":66
},
  "geometry": {"coordinates":[13.60416,50.3212],"type":"Point"}
}