{
  "type": "Feature",
  "properties": {
    "iso:country":"CZ",
    "name:unk_x_variant":[
        "Altbiela"
    ],
    "qs:a0":"Cesk\u00e1 republika",
    "qs:a1":"*Moravskoslezsk\u00fd",
    "qs:a1r":"0",
    "qs:adm0":"Cesk\u00e1 republika",
    "qs:la_lc":"*",
    "qs:level":"locality",
    "qs:loc":"Star\u00e1 B\u011bl\u00e1",
    "qs:loc_alt":"Stara Bela",
    "qs:pop":0,
    "qs:type":"buffered point",
    "wof:name":"Star\u00e1 B\u011bl\u00e1",
    "wof:placetype":"locality"
},
  "geometry": {"coordinates":[18.229604,49.770844],"type":"Point"}
}