{
  "type": "Feature",
  "properties": {
    "gn:admin1_code":"88.0",
    "gn:admin2_code":"0201",
    "gn:asciiname":"Kresice",
    "gn:country_code":"CZ",
    "gn:dem":407,
    "gn:feature_class":"P",
    "gn:feature_code":"PPL",
    "gn:name":"K\u0159e\u0161ice",
    "gn:population":0,
    "gn:timezone":"Europe/Prague",
    "iso:country":"CZ",
    "wof:name":"Kresice",
    "wof:placetype":"locality"
},
  "geometry": {"coordinates":[14.84654,49.81086],"type":"Point"}
}