{
  "type": "Feature",
  "properties": {
    "gn:country":"CZ",
    "gn:fcode":"PPL",
    "gn:population":121,
    "iso:country":"CZ",
    "name:azb_x_preferred":[
        "\u067e\u0648\u062a\u0633\u0648\u0641"
    ],
    "name:cat_x_preferred":[
        "Pucov"
    ],
    "name:ceb_x_preferred":[
        "Pucov"
    ],
    "name:ces_x_preferred":[
        "Pucov"
    ],
    "name:che_x_preferred":[
        "\u041f\u0443\u0446\u043e\u0432"
    ],
    "name:deu_x_preferred":[
        "Pucov"
    ],
    "name:eng_x_preferred":[
        "Pucov"
    ],
    "name:eus_x_preferred":[
        "Pucov"
    ],
    "name:fas_x_preferred":[
        "\u067e\u0648\u062a\u0633\u0648\u0641"
    ],
    "name:fra_x_preferred":[
        "Pucov"
    ],
    "name:gle_x_preferred":[
        "Pucov"
    ],
    "name:hun_x_preferred":[
        "Pucov"
    ],
    "name:ita_x_preferred":[
        "Pucov"
    ],
    "name:lmo_x_preferred":[
        "Pucov"
    ],
    "name:msa_x_preferred":[
        "Pucov"
    ],
    "name:nan_x_preferred":[
        "Pucov"
    ],
    "name:nld_x_preferred":[
        "Pucov"
    ],
    "name:pol_x_preferred":[
        "Pucov"
    ],
    "name:por_x_preferred":[
        "Pucov"
    ],
    "name:rup_x_preferred":[
        "Pucov"
    ],
    "name:slk_x_preferred":[
        "Pucov"
    ],
    "name:spa_x_preferred":[
        "Pucov"
    ],
    "name:swe_x_preferred":[
        "Pucov"
    ],
    "name:tat_x_preferred":[
        "\u041f\u0443\u0446\u043e\u0432"
    ],
    "name:vie_x_preferred":[
        "Pucov"
    ],
    "qs_pg:aaroncc":"CZ",
    "qs_pg:gn_country":"CZ",
    "qs_pg:gn_fcode":"PPL",
    "qs_pg:gn_pop":121,
    "qs_pg:name":"Pucov",
    "qs_pg:name_adm0":"\u010cesk\u00e1 republika",
    "qs_pg:name_adm1":"Kraj Vyso\u010dina",
    "qs_pg:photos_9r":0,
    "qs_pg:photos_sr":0,
    "qs_pg:pop_sr":1,
    "qs_pg:qs_pg_placetype":"locality",
    "qs_pg:qs_pg_placetype_gp":"Town",
    "qs_pg:woe_adm0":23424810,
    "woe:adm0_id":23424810,
    "woe:name_adm0":"\u010cesk\u00e1 republika",
    "woe:name_adm1":"Kraj Vyso\u010dina",
    "woe:placetype":"Town",
    "wof:name":"Pucov",
    "wof:placetype":"locality",
    "wof:population":121
},
  "geometry": {"coordinates":[16.17407,49.24705],"type":"Point"}
}