{
  "type": "Feature",
  "properties": {
    "gn:admin1_code":"86",
    "gn:admin2_code":"0531",
    "gn:asciiname":"Vranov",
    "gn:country_code":"CZ",
    "gn:dem":565,
    "gn:feature_class":"P",
    "gn:feature_code":"PPL",
    "gn:name":"Vranov",
    "gn:population":0,
    "gn:timezone":"Europe/Prague",
    "iso:country":"CZ",
    "wof:name":"Vranov",
    "wof:placetype":"locality"
},
  "geometry": {"coordinates":[15.84034,49.81871],"type":"Point"}
}