{
  "type": "Feature",
  "properties": {
    "gn:admin1_code":"79.0",
    "gn:admin2_code":"0311",
    "gn:asciiname":"Pohurka",
    "gn:cc2":"CZ",
    "gn:country_code":"CZ",
    "gn:dem":460,
    "gn:feature_class":"P",
    "gn:feature_code":"PPL",
    "gn:name":"Poh\u016frka",
    "gn:population":0,
    "gn:timezone":"Europe/Prague",
    "iso:country":"CZ",
    "name:und_x_variant":[
        "Bucharten"
    ],
    "wof:name":"Pohurka",
    "wof:placetype":"locality"
},
  "geometry": {"coordinates":[14.53333,48.96667],"type":"Point"}
}