{
  "type": "Feature",
  "properties": {
    "gn:gn_country":"CZ",
    "gn:gn_fcode":"PPL",
    "gn:gn_pop":191,
    "gn:population":191,
    "iso:country":"CZ",
    "name:ces_x_preferred":[
        "\u0160\u00e1rovcova Lhota"
    ],
    "name:eng_x_preferred":[
        "\u0160\u00e1rovcova Lhota"
    ],
    "name:fas_x_preferred":[
        "\u0634\u0627\u0631\u0648\u0648\u062a\u0633\u0648\u0648\u0627 \u0644\u0647\u0648\u062a\u0627"
    ],
    "name:fra_x_preferred":[
        "\u0160\u00e1rovcova Lhota"
    ],
    "name:hun_x_preferred":[
        "\u0160\u00e1rovcova Lhota"
    ],
    "name:ita_x_preferred":[
        "\u0160\u00e1rovcova Lhota"
    ],
    "name:msa_x_preferred":[
        "\u0160\u00e1rovcova Lhota"
    ],
    "name:nan_x_preferred":[
        "\u0160\u00e1rovcova Lhota"
    ],
    "name:nld_x_preferred":[
        "\u0160\u00e1rovcova Lhota"
    ],
    "name:pol_x_preferred":[
        "\u0160\u00e1rovcova Lhota"
    ],
    "name:por_x_preferred":[
        "\u0160\u00e1rovcova Lhota"
    ],
    "name:rup_x_preferred":[
        "\u0160\u00e1rovcova Lhota"
    ],
    "name:slk_x_preferred":[
        "\u0160\u00e1rovcova Lhota"
    ],
    "name:srp_x_preferred":[
        "\u0428\u0430\u0440\u043e\u0432\u0446\u043e\u0432\u0430 \u041b\u0445\u043e\u0442\u0430"
    ],
    "name:swe_x_preferred":[
        "\u0160\u00e1rovcova Lhota"
    ],
    "name:vie_x_preferred":[
        "\u0160\u00e1rovcova Lhota"
    ],
    "qs_pg:aaroncc":"CZ",
    "qs_pg:gn_country":"CZ",
    "qs_pg:gn_fcode":"PPL",
    "qs_pg:gn_pop":191,
    "qs_pg:name":"\u0160\u00e1rovcova Lhota",
    "qs_pg:photos_9r":0,
    "qs_pg:photos_sr":0,
    "qs_pg:pop_sr":1,
    "qs_pg:qs_pg_placetype":"locality",
    "wof:name":"\u0160\u00e1rovcova Lhota",
    "wof:placetype":"locality",
    "wof:population":191
},
  "geometry": {"coordinates":[15.56228,50.40751],"type":"Point"}
}