{
  "type": "Feature",
  "properties": {
    "gn:admin1_code":"80.0",
    "gn:admin2_code":"0614",
    "gn:asciiname":"Nove Dvory",
    "gn:country_code":"CZ",
    "gn:dem":383,
    "gn:feature_class":"P",
    "gn:feature_code":"PPL",
    "gn:name":"Nov\u00e9 Dvory",
    "gn:population":0,
    "gn:timezone":"Europe/Prague",
    "iso:country":"CZ",
    "wof:name":"Nove Dvory",
    "wof:placetype":"locality"
},
  "geometry": {"coordinates":[16.08478,49.07899000000001],"type":"Point"}
}