{
  "type": "Feature",
  "properties": {
    "gn:admin1_code":"87",
    "gn:admin2_code":"0326",
    "gn:asciiname":"Vitinka",
    "gn:country_code":"CZ",
    "gn:dem":456,
    "gn:feature_class":"P",
    "gn:feature_code":"PPL",
    "gn:name":"Vitinka",
    "gn:population":0,
    "gn:timezone":"Europe/Prague",
    "iso:country":"CZ",
    "wof:name":"Vitinka",
    "wof:placetype":"locality"
},
  "geometry": {"coordinates":[13.56646,49.78711],"type":"Point"}
}