{
  "type": "Feature",
  "properties": {
    "gn:admin1_code":"81.0",
    "gn:admin2_code":"0412",
    "gn:asciiname":"Hrivinov",
    "gn:cc2":"CZ",
    "gn:country_code":"CZ",
    "gn:dem":618,
    "gn:feature_class":"P",
    "gn:feature_code":"PPL",
    "gn:name":"H\u0159ivinov",
    "gn:population":0,
    "gn:timezone":"Europe/Prague",
    "iso:country":"CZ",
    "name:und_x_variant":[
        "Mokowitz"
    ],
    "wof:name":"Hrivinov",
    "wof:placetype":"locality"
},
  "geometry": {"coordinates":[13.1151,50.15546],"type":"Point"}
}