{
  "type": "Feature",
  "properties": {
    "gn:admin1_code":"78.0",
    "gn:admin2_code":"0621",
    "gn:asciiname":"Sasina",
    "gn:country_code":"CZ",
    "gn:dem":336,
    "gn:feature_class":"P",
    "gn:feature_code":"PPL",
    "gn:name":"Sasina",
    "gn:population":0,
    "gn:timezone":"Europe/Prague",
    "iso:country":"CZ",
    "name:bos_x_preferred":[
        "Sasina"
    ],
    "name:ceb_x_preferred":[
        "Sasina"
    ],
    "name:fra_x_preferred":[
        "Sasina"
    ],
    "name:hrv_x_preferred":[
        "Sasina"
    ],
    "name:nau_x_preferred":[
        "Sasina"
    ],
    "name:srp_x_preferred":[
        "\u0421\u0430\u0441\u0438\u043d\u0430"
    ],
    "name:swe_x_preferred":[
        "Sasina"
    ],
    "wof:name":"Sasina",
    "wof:placetype":"locality"
},
  "geometry": {"coordinates":[16.58412,49.51434],"type":"Point"}
}