{
  "type": "Feature",
  "properties": {
    "gn:admin1_code":"87",
    "gn:admin2_code":"0324",
    "gn:asciiname":"Ujezdec",
    "gn:country_code":"CZ",
    "gn:dem":409,
    "gn:feature_class":"P",
    "gn:feature_code":"PPL",
    "gn:name":"\u00dajezdec",
    "gn:population":0,
    "gn:timezone":"Europe/Prague",
    "iso:country":"CZ",
    "wof:name":"Ujezdec",
    "wof:placetype":"locality"
},
  "geometry": {"coordinates":[13.19836,49.51657],"type":"Point"}
}