{
  "type": "Feature",
  "properties": {
    "gn:admin1_code":"88.0",
    "gn:admin2_code":"0201",
    "gn:asciiname":"Babice",
    "gn:country_code":"CZ",
    "gn:dem":354,
    "gn:feature_class":"P",
    "gn:feature_code":"PPL",
    "gn:name":"Babice",
    "gn:population":0,
    "gn:timezone":"Europe/Prague",
    "iso:country":"CZ",
    "name:und_x_variant":[
        "Babitz",
        "Babice"
    ],
    "wof:name":"Babice",
    "wof:placetype":"locality"
},
  "geometry": {"coordinates":[14.6248,49.87863],"type":"Point"}
}