{
  "type": "Feature",
  "properties": {
    "gn:admin1_code":"88.0",
    "gn:admin2_code":"0201",
    "gn:asciiname":"Babice",
    "gn:country_code":"CZ",
    "gn:dem":354,
    "gn:feature_class":"P",
    "gn:feature_code":"PPL",
    "gn:name":"Babice",
    "gn:population":0,
    "gn:timezone":"Europe/Prague",
    "iso:country":"CZ",
    "name:ceb_x_preferred":[
        "Babice"
    ],
    "name:ces_x_preferred":[
        "Babice"
    ],
    "name:deu_x_preferred":[
        "Babice"
    ],
    "name:epo_x_preferred":[
        "Babice"
    ],
    "name:fra_x_preferred":[
        "Babice"
    ],
    "name:hun_x_preferred":[
        "Babice"
    ],
    "name:ita_x_preferred":[
        "Babice"
    ],
    "name:nld_x_preferred":[
        "Babice"
    ],
    "name:pol_x_preferred":[
        "Babice"
    ],
    "name:rus_x_preferred":[
        "\u0411\u0430\u0431\u0438\u0446\u0435"
    ],
    "name:slk_x_preferred":[
        "Babice"
    ],
    "name:srp_x_preferred":[
        "\u0411\u0430\u0431\u0438\u0446\u0435"
    ],
    "name:swe_x_preferred":[
        "Babice"
    ],
    "name:und_x_variant":[
        "Babitz",
        "Babice"
    ],
    "wof:name":"Babice",
    "wof:placetype":"locality"
},
  "geometry": {"coordinates":[14.6248,49.87863],"type":"Point"}
}