{
  "type": "Feature",
  "properties": {
    "gn:admin1_code":"89.0",
    "gn:admin2_code":"0421",
    "gn:asciiname":"Nova Bohyne",
    "gn:cc2":"CZ",
    "gn:country_code":"CZ",
    "gn:dem":297,
    "gn:feature_class":"P",
    "gn:feature_code":"PPL",
    "gn:name":"Nov\u00e1 Bohyn\u011b",
    "gn:population":0,
    "gn:timezone":"Europe/Prague",
    "iso:country":"CZ",
    "name:und_x_variant":[
        "Neu-Bohmen"
    ],
    "wof:name":"Nova Bohyne",
    "wof:placetype":"locality"
},
  "geometry": {"coordinates":[14.13923,50.74395],"type":"Point"}
}