{
  "type": "Feature",
  "properties": {
    "iso:country":"CZ",
    "name:ces_x_preferred":[
        "Mich\u00e1lkovice"
    ],
    "name:cze_x_colloquial":[
        "Michalkovice"
    ],
    "name:cze_x_variant":[
        "Michalkowitz"
    ],
    "name:eng_x_preferred":[
        "Mich\u00e1lkovice"
    ],
    "name:epo_x_preferred":[
        "Mich\u00e1lkovice"
    ],
    "name:fra_x_preferred":[
        "Mich\u00e1lkovice"
    ],
    "name:pol_x_preferred":[
        "Micha\u0142kowice"
    ],
    "name:slk_x_preferred":[
        "Mich\u00e1lkovice"
    ],
    "qs:local_max":2778,
    "qs:local_sum":9373,
    "qs:localhoods":17,
    "qs:name":"Mich\u00e1lkovice",
    "qs:name_adm0":"\u010cesk\u00e1 republika",
    "qs:name_adm1":"Moravskoslezsk\u00fd kraj",
    "qs:name_adm2":"Ostrava",
    "qs:name_lau":"Ostrava",
    "qs:name_local":"Ostrava",
    "qs:photo_max":9,
    "qs:photo_sum":21,
    "qs:placetype":"Suburb",
    "qs:quad_count":6,
    "qs:woe_adm0":23424810,
    "qs:woe_adm1":20070471,
    "qs:woe_adm2":12582577,
    "qs:woe_lau":12607114,
    "qs:woe_local":795610,
    "qs:woe_ver":"7.10.0",
    "wd:wordcount":203,
    "wof:lang":[
        "cze"
    ],
    "wof:name":"Mich\u00e1lkovice",
    "wof:placetype":"neighbourhood"
},
  "geometry": {"coordinates":[18.356454,49.827944],"type":"Point"}
}