{
  "type": "Feature",
  "properties": {
    "gn:admin1_code":"85.0",
    "gn:admin2_code":"0805",
    "gn:asciiname":"Lesni Albrechtice",
    "gn:country_code":"CZ",
    "gn:dem":503,
    "gn:feature_class":"P",
    "gn:feature_code":"PPL",
    "gn:name":"Lesn\u00ed Albrechtice",
    "gn:population":0,
    "gn:timezone":"Europe/Prague",
    "iso:country":"CZ",
    "name:deu_x_preferred":[
        "Waldolbersdorf"
    ],
    "wof:name":"Lesni Albrechtice",
    "wof:placetype":"locality"
},
  "geometry": {"coordinates":[17.8636,49.80664],"type":"Point"}
}