{
  "type": "Feature",
  "properties": {
    "gn:admin1_code":"90.0",
    "gn:admin2_code":"0724",
    "gn:asciiname":"Nevsova",
    "gn:country_code":"CZ",
    "gn:dem":407,
    "gn:feature_class":"P",
    "gn:feature_code":"PPL",
    "gn:name":"Nev\u0161ov\u00e1",
    "gn:population":0,
    "gn:timezone":"Europe/Prague",
    "iso:country":"CZ",
    "wof:name":"Nevsova",
    "wof:placetype":"locality"
},
  "geometry": {"coordinates":[17.84339,49.1069],"type":"Point"}
}