{
  "type": "Feature",
  "properties": {
    "gn:admin1_code":"88.0",
    "gn:admin2_code":"020B",
    "gn:asciiname":"Dvorce",
    "gn:country_code":"CZ",
    "gn:dem":488,
    "gn:feature_class":"P",
    "gn:feature_code":"PPL",
    "gn:name":"Dvorce",
    "gn:population":0,
    "gn:timezone":"Europe/Prague",
    "iso:country":"CZ",
    "name:bos_x_preferred":[
        "Dvorce"
    ],
    "name:ceb_x_preferred":[
        "Dvorce"
    ],
    "name:ces_x_preferred":[
        "Dvorce"
    ],
    "name:deu_x_preferred":[
        "Dvorce"
    ],
    "name:epo_x_preferred":[
        "Dvorce"
    ],
    "name:fra_x_preferred":[
        "Dvorce"
    ],
    "name:ita_x_preferred":[
        "Dvorce"
    ],
    "name:nld_x_preferred":[
        "Dvorce"
    ],
    "name:pol_x_preferred":[
        "Dvorce"
    ],
    "name:slk_x_preferred":[
        "Dvorce"
    ],
    "name:srp_x_preferred":[
        "\u0414\u0432\u043e\u0440\u0446\u0435"
    ],
    "name:swe_x_preferred":[
        "Dvorce"
    ],
    "name:ukr_x_preferred":[
        "\u0414\u0432\u043e\u0440\u0446\u0435"
    ],
    "wof:name":"Dvorce",
    "wof:placetype":"locality"
},
  "geometry": {"coordinates":[14.58517,49.55998],"type":"Point"}
}