{
  "type": "Feature",
  "properties": {
    "gn:admin1_code":"82.0",
    "gn:admin2_code":"0525",
    "gn:asciiname":"Nove Zamky",
    "gn:country_code":"CZ",
    "gn:dem":367,
    "gn:feature_class":"P",
    "gn:feature_code":"PPL",
    "gn:name":"Nov\u00e9 Z\u00e1mky",
    "gn:population":0,
    "gn:timezone":"Europe/Prague",
    "iso:country":"CZ",
    "name:und_x_variant":[
        "Neuschloss",
        "Nov\u00e9 Z\u00e1mky"
    ],
    "wof:name":"Nove Zamky",
    "wof:placetype":"locality"
},
  "geometry": {"coordinates":[15.73758,50.51495],"type":"Point"}
}