{
  "type": "Feature",
  "properties": {
    "gn:admin1_code":"89.0",
    "gn:admin2_code":"0424",
    "gn:asciiname":"Mala Cernoc",
    "gn:cc2":"CZ",
    "gn:country_code":"CZ",
    "gn:dem":307,
    "gn:feature_class":"P",
    "gn:feature_code":"PPL",
    "gn:name":"Mal\u00e1 \u010cernoc",
    "gn:population":0,
    "gn:timezone":"Europe/Prague",
    "iso:country":"CZ",
    "name:und_x_variant":[
        "Klein-Tschernitz"
    ],
    "wof:name":"Mala Cernoc",
    "wof:placetype":"locality"
},
  "geometry": {"coordinates":[13.54923,50.2058],"type":"Point"}
}