{
  "type": "Feature",
  "properties": {
    "gn:admin1_code":"88.0",
    "gn:admin2_code":"0209",
    "gn:asciiname":"Rovna",
    "gn:country_code":"CZ",
    "gn:dem":296,
    "gn:feature_class":"P",
    "gn:feature_code":"PPL",
    "gn:name":"Rovn\u00e1",
    "gn:population":0,
    "gn:timezone":"Europe/Prague",
    "iso:country":"CZ",
    "name:ceb_x_preferred":[
        "Rovna"
    ],
    "name:swe_x_preferred":[
        "Rovna"
    ],
    "wof:name":"Rovna",
    "wof:placetype":"locality"
},
  "geometry": {"coordinates":[14.85743,49.89699],"type":"Point"}
}