{
  "type": "Feature",
  "properties": {
    "gn:admin1_code":"79.0",
    "gn:admin2_code":"0315",
    "gn:asciiname":"Dubska Lhota",
    "gn:country_code":"CZ",
    "gn:dem":469,
    "gn:feature_class":"P",
    "gn:feature_code":"PPL",
    "gn:name":"Dubsk\u00e1 Lhota",
    "gn:population":0,
    "gn:timezone":"Europe/Prague",
    "iso:country":"CZ",
    "wof:name":"Dubska Lhota",
    "wof:placetype":"locality"
},
  "geometry": {"coordinates":[14.02812,49.10083],"type":"Point"}
}