{
  "type": "Feature",
  "properties": {
    "gn:country":"CZ",
    "gn:fcode":"PPL",
    "gn:population":374,
    "iso:country":"CZ",
    "name:azb_x_preferred":[
        "\u0633\u06a9\u0627\u0634\u062a\u06cc\u062a\u0633\u0647"
    ],
    "name:cat_x_preferred":[
        "Ska\u0161tice"
    ],
    "name:ceb_x_preferred":[
        "Ska\u0161tice"
    ],
    "name:ces_x_preferred":[
        "Ska\u0161tice"
    ],
    "name:che_x_preferred":[
        "\u0421\u043a\u0430\u0448\u0442\u0438\u0446\u0435"
    ],
    "name:deu_x_preferred":[
        "Ska\u0161tice"
    ],
    "name:eng_x_preferred":[
        "Ska\u0161tice"
    ],
    "name:epo_x_preferred":[
        "Ska\u0161tice"
    ],
    "name:eus_x_preferred":[
        "Ska\u0161tice"
    ],
    "name:fas_x_preferred":[
        "\u0633\u06a9\u0627\u0634\u062a\u06cc\u062a\u0633\u0647"
    ],
    "name:fra_x_preferred":[
        "Ska\u0161tice"
    ],
    "name:gle_x_preferred":[
        "Ska\u0161tice"
    ],
    "name:hun_x_preferred":[
        "Ska\u0161tice"
    ],
    "name:ita_x_preferred":[
        "Ska\u0161tice"
    ],
    "name:jpn_x_preferred":[
        "\u30b9\u30ab\u30b7\u30e5\u30c6\u30a3\u30c4\u30a7"
    ],
    "name:lmo_x_preferred":[
        "Ska\u0161tice"
    ],
    "name:msa_x_preferred":[
        "Ska\u0161tice"
    ],
    "name:nan_x_preferred":[
        "Ska\u0161tice"
    ],
    "name:nld_x_preferred":[
        "Ska\u0161tice"
    ],
    "name:pol_x_preferred":[
        "Ska\u0161tice"
    ],
    "name:por_x_preferred":[
        "Ska\u0161tice"
    ],
    "name:rup_x_preferred":[
        "Ska\u0161tice"
    ],
    "name:slk_x_preferred":[
        "Ska\u0161tice"
    ],
    "name:spa_x_preferred":[
        "Ska\u0161tice"
    ],
    "name:srp_x_preferred":[
        "\u0421\u043a\u0430\u0448\u0442\u0438\u0446\u0435"
    ],
    "name:swe_x_preferred":[
        "Ska\u0161tice"
    ],
    "name:tat_x_preferred":[
        "\u0421\u043a\u0430\u0448\u0442\u0438\u0446\u0435"
    ],
    "name:vie_x_preferred":[
        "Ska\u0161tice"
    ],
    "qs_pg:aaroncc":"CZ",
    "qs_pg:gn_country":"CZ",
    "qs_pg:gn_fcode":"PPL",
    "qs_pg:gn_pop":374,
    "qs_pg:name":"Ska\u0161tice",
    "qs_pg:name_adm0":"\u010cesk\u00e1 republika",
    "qs_pg:name_adm1":"Zl\u00ednsk\u00fd kraj",
    "qs_pg:photos_9r":0,
    "qs_pg:photos_sr":0,
    "qs_pg:pop_sr":2,
    "qs_pg:qs_pg_placetype":"locality",
    "qs_pg:qs_pg_placetype_gp":"Town",
    "qs_pg:woe_adm0":23424810,
    "woe:adm0_id":23424810,
    "woe:name_adm0":"\u010cesk\u00e1 republika",
    "woe:name_adm1":"Zl\u00ednsk\u00fd kraj",
    "woe:placetype":"Town",
    "wof:name":"Ska\u0161tice",
    "wof:placetype":"locality",
    "wof:population":374
},
  "geometry": {"coordinates":[17.41739,49.33231],"type":"Point"}
}