{
  "type": "Feature",
  "properties": {
    "gn:admin1_code":"86.0",
    "gn:admin2_code":"0534",
    "gn:asciiname":"Dolni Orlice",
    "gn:country_code":"CZ",
    "gn:dem":573,
    "gn:feature_class":"P",
    "gn:feature_code":"PPL",
    "gn:name":"Doln\u00ed Orlice",
    "gn:population":0,
    "gn:timezone":"Europe/Prague",
    "iso:country":"CZ",
    "name:und_x_variant":[
        "Nieder Erlitz"
    ],
    "wof:name":"Dolni Orlice",
    "wof:placetype":"locality"
},
  "geometry": {"coordinates":[16.75329,50.06331],"type":"Point"}
}