{
  "type": "Feature",
  "properties": {
    "gn:country":"CZ",
    "gn:fcode":"PPL",
    "gn:population":182,
    "iso:country":"CZ",
    "name:azb_x_preferred":[
        "\u06a9\u0648\u0631\u0648\u0633\u0644\u067e\u06cc"
    ],
    "name:bul_x_preferred":[
        "\u041a\u0443\u0440\u043e\u0441\u043b\u0435\u043f\u0439"
    ],
    "name:ceb_x_preferred":[
        "Kuroslepy"
    ],
    "name:ces_x_preferred":[
        "Kuroslepy"
    ],
    "name:deu_x_preferred":[
        "Kuroslepy"
    ],
    "name:eng_x_preferred":[
        "Kuroslepy"
    ],
    "name:eus_x_preferred":[
        "Kuroslepy"
    ],
    "name:fas_x_preferred":[
        "\u06a9\u0648\u0631\u0648\u0633\u0644\u067e\u06cc"
    ],
    "name:fra_x_preferred":[
        "Kuroslepy"
    ],
    "name:hun_x_preferred":[
        "Kuroslepy"
    ],
    "name:ita_x_preferred":[
        "Kuroslepy"
    ],
    "name:msa_x_preferred":[
        "Kuroslepy"
    ],
    "name:nan_x_preferred":[
        "Kuroslepy"
    ],
    "name:nld_x_preferred":[
        "Kuroslepy"
    ],
    "name:por_x_preferred":[
        "Kuroslepy"
    ],
    "name:rup_x_preferred":[
        "Kuroslepy"
    ],
    "name:slk_x_preferred":[
        "Kuroslepy"
    ],
    "name:spa_x_preferred":[
        "Kuroslepy"
    ],
    "name:swe_x_preferred":[
        "Kuroslepy"
    ],
    "name:vie_x_preferred":[
        "Kuroslepy"
    ],
    "qs_pg:aaroncc":"CZ",
    "qs_pg:gn_country":"CZ",
    "qs_pg:gn_fcode":"PPL",
    "qs_pg:gn_pop":182,
    "qs_pg:name":"Kuroslepy",
    "qs_pg:name_adm0":"\u010cesk\u00e1 republika",
    "qs_pg:name_adm1":"Kraj Vyso\u010dina",
    "qs_pg:photos_9r":0,
    "qs_pg:photos_sr":0,
    "qs_pg:pop_sr":1,
    "qs_pg:qs_pg_placetype":"locality",
    "qs_pg:qs_pg_placetype_gp":"Town",
    "qs_pg:woe_adm0":23424810,
    "woe:adm0_id":23424810,
    "woe:name_adm0":"\u010cesk\u00e1 republika",
    "woe:name_adm1":"Kraj Vyso\u010dina",
    "woe:placetype":"Town",
    "wof:name":"Kuroslepy",
    "wof:placetype":"locality",
    "wof:population":182
},
  "geometry": {"coordinates":[16.21011,49.15433],"type":"Point"}
}