{
  "type": "Feature",
  "properties": {
    "gn:admin1_code":"84.0",
    "gn:admin2_code":"0714",
    "gn:asciiname":"Kozi Loucky",
    "gn:country_code":"CZ",
    "gn:dem":321,
    "gn:feature_class":"P",
    "gn:feature_code":"PPL",
    "gn:name":"Koz\u00ed Lou\u010dky",
    "gn:population":0,
    "gn:timezone":"Europe/Prague",
    "iso:country":"CZ",
    "name:und_x_variant":[
        "Lifschel",
        "Koz\u00ed Lou\u010dky"
    ],
    "wof:name":"Kozi Loucky",
    "wof:placetype":"locality"
},
  "geometry": {"coordinates":[17.85,49.55],"type":"Point"}
}