{
  "type": "Feature",
  "properties": {
    "gn:admin1_code":"79.0",
    "gn:admin2_code":"0313",
    "gn:asciiname":"Mutyneves",
    "gn:country_code":"CZ",
    "gn:dem":535,
    "gn:feature_class":"P",
    "gn:feature_code":"PPL",
    "gn:name":"Mutyn\u011bves",
    "gn:population":0,
    "gn:timezone":"Europe/Prague",
    "iso:country":"CZ",
    "name:und_x_variant":[
        "Muttaschlag",
        "Mutyn\u011bves"
    ],
    "wof:name":"Mutyneves",
    "wof:placetype":"locality"
},
  "geometry": {"coordinates":[15.12483,49.16395],"type":"Point"}
}