{
  "type": "Feature",
  "properties": {
    "gn:admin1_code":"88.0",
    "gn:admin2_code":"0201",
    "gn:asciiname":"Nove Dvory",
    "gn:country_code":"CZ",
    "gn:dem":531,
    "gn:feature_class":"P",
    "gn:feature_code":"PPL",
    "gn:name":"Nov\u00e9 Dvory",
    "gn:population":0,
    "gn:timezone":"Europe/Prague",
    "iso:country":"CZ",
    "wof:name":"Nove Dvory",
    "wof:placetype":"locality"
},
  "geometry": {"coordinates":[14.70743,49.54765],"type":"Point"}
}