{
  "type": "Feature",
  "properties": {
    "gn:admin1_code":"83.0",
    "gn:admin2_code":"0511",
    "gn:asciiname":"Juliovka",
    "gn:country_code":"CZ",
    "gn:dem":432,
    "gn:feature_class":"P",
    "gn:feature_code":"PPL",
    "gn:name":"Juliovka",
    "gn:population":0,
    "gn:timezone":"Europe/Prague",
    "iso:country":"CZ",
    "name:und_x_variant":[
        "Juliusthal",
        "Juliovka"
    ],
    "wof:name":"Juliovka",
    "wof:placetype":"locality"
},
  "geometry": {"coordinates":[14.67067,50.82297],"type":"Point"}
}