{
  "type": "Feature",
  "properties": {
    "gn:country":"CZ",
    "gn:fcode":"PPL",
    "gn:population":33,
    "iso:country":"CZ",
    "name:azb_x_preferred":[
        "\u0646\u0648\u0648\u0627 \u067e\u0644\u0627\u0646"
    ],
    "name:cat_x_preferred":[
        "Nov\u00e1 Pl\u00e1\u0148"
    ],
    "name:ces_x_preferred":[
        "Nov\u00e1 Pl\u00e1\u0148"
    ],
    "name:che_x_preferred":[
        "\u041d\u043e\u0432\u0430 \u041f\u043b\u0430\u043d\u044c"
    ],
    "name:deu_x_preferred":[
        "Nov\u00e1 Pl\u00e1\u0148"
    ],
    "name:eng_x_preferred":[
        "Nov\u00e1 Pl\u00e1\u0148"
    ],
    "name:epo_x_preferred":[
        "Nov\u00e1 Pl\u00e1\u0148"
    ],
    "name:eus_x_preferred":[
        "Nov\u00e1 Pl\u00e1\u0148"
    ],
    "name:fas_x_preferred":[
        "\u0646\u0648\u0648\u0627 \u067e\u0644\u0627\u0646"
    ],
    "name:fra_x_preferred":[
        "Nov\u00e1 Pl\u00e1\u0148"
    ],
    "name:gle_x_preferred":[
        "Nov\u00e1 Pl\u00e1\u0148"
    ],
    "name:glg_x_preferred":[
        "Nov\u00e1 Pl\u00e1\u0148"
    ],
    "name:hun_x_preferred":[
        "Nov\u00e1 Pl\u00e1\u0148"
    ],
    "name:ita_x_preferred":[
        "Nov\u00e1 Pl\u00e1\u0148"
    ],
    "name:lmo_x_preferred":[
        "Nov\u00e1 Pl\u00e1\u0148"
    ],
    "name:msa_x_preferred":[
        "Nov\u00e1 Pl\u00e1\u0148"
    ],
    "name:nan_x_preferred":[
        "Nov\u00e1 Pl\u00e1\u0148"
    ],
    "name:nld_x_preferred":[
        "Nov\u00e1 Pl\u00e1\u0148"
    ],
    "name:pol_x_preferred":[
        "Nov\u00e1 Pl\u00e1\u0148"
    ],
    "name:por_x_preferred":[
        "Nov\u00e1 Pl\u00e1\u0148"
    ],
    "name:rup_x_preferred":[
        "Nov\u00e1 Pl\u00e1\u0148"
    ],
    "name:slk_x_preferred":[
        "Nov\u00e1 Pl\u00e1\u0148"
    ],
    "name:spa_x_preferred":[
        "Nov\u00e1 Pl\u00e1\u0148"
    ],
    "name:srp_x_preferred":[
        "\u041d\u043e\u0432\u0430 \u041f\u043b\u0430\u045a"
    ],
    "name:tat_x_preferred":[
        "\u041d\u043e\u0432\u0430 \u041f\u043b\u0430\u043d\u044c"
    ],
    "name:und_x_variant":[
        "Neurode"
    ],
    "name:uzb_x_preferred":[
        "Nov\u00e1 Pl\u00e1\u0148"
    ],
    "name:vie_x_preferred":[
        "Nov\u00e1 Pl\u00e1\u0148"
    ],
    "qs_pg:aaroncc":"CZ",
    "qs_pg:gn_country":"CZ",
    "qs_pg:gn_fcode":"PPL",
    "qs_pg:gn_pop":33,
    "qs_pg:name":"Nov\u00e1 Pl\u00e1\u0148",
    "qs_pg:name_adm0":"\u010cesk\u00e1 republika",
    "qs_pg:name_adm1":"Moravskoslezsk\u00fd kraj",
    "qs_pg:photos_9k":1,
    "qs_pg:photos_9r":3,
    "qs_pg:photos_all":106,
    "qs_pg:photos_sr":0,
    "qs_pg:pop_sr":1,
    "qs_pg:qs_pg_placetype":"locality",
    "qs_pg:qs_pg_placetype_gp":"Town",
    "qs_pg:woe_adm0":23424810,
    "woe:adm0_id":23424810,
    "woe:name_adm0":"\u010cesk\u00e1 republika",
    "woe:name_adm1":"Moravskoslezsk\u00fd kraj",
    "woe:placetype":"Town",
    "wof:name":"Nov\u00e1 Pl\u00e1\u0148",
    "wof:placetype":"locality",
    "wof:population":33
},
  "geometry": {"coordinates":[17.4751,49.92191],"type":"Point"}
}