{
  "type": "Feature",
  "properties": {
    "gn:admin1_code":"81.0",
    "gn:admin2_code":"0412",
    "gn:asciiname":"Jablonna",
    "gn:country_code":"CZ",
    "gn:dem":448,
    "gn:feature_class":"P",
    "gn:feature_code":"PPL",
    "gn:name":"Jablonn\u00e1",
    "gn:population":0,
    "gn:timezone":"Europe/Prague",
    "iso:country":"CZ",
    "wof:name":"Jablonna",
    "wof:placetype":"locality"
},
  "geometry": {"coordinates":[13.28772,50.06922],"type":"Point"}
}