{
  "type": "Feature",
  "properties": {
    "gn:gn_country":"CZ",
    "gn:gn_fcode":"PPL",
    "gn:gn_pop":562,
    "gn:population":562,
    "iso:country":"CZ",
    "name:ces_x_preferred":[
        "Star\u00e9 Hobz\u00ed"
    ],
    "name:deu_x_preferred":[
        "Star\u00e9 Hobz\u00ed"
    ],
    "name:eng_x_preferred":[
        "Star\u00e9 Hobz\u00ed"
    ],
    "name:fas_x_preferred":[
        "\u0633\u062a\u0627\u0631\u0647 \u0647\u0648\u0628\u0632\u06cc"
    ],
    "name:fra_x_preferred":[
        "Star\u00e9 Hobz\u00ed"
    ],
    "name:hun_x_preferred":[
        "Star\u00e9 Hobz\u00ed"
    ],
    "name:ita_x_preferred":[
        "Star\u00e9 Hobz\u00ed"
    ],
    "name:msa_x_preferred":[
        "Star\u00e9 Hobz\u00ed"
    ],
    "name:nld_x_preferred":[
        "Star\u00e9 Hobz\u00ed"
    ],
    "name:pol_x_preferred":[
        "Star\u00e9 Hobz\u00ed"
    ],
    "name:por_x_preferred":[
        "Star\u00e9 Hobz\u00ed"
    ],
    "name:rup_x_preferred":[
        "Star\u00e9 Hobz\u00ed"
    ],
    "name:slk_x_preferred":[
        "Star\u00e9 Hobz\u00ed"
    ],
    "name:srp_x_preferred":[
        "\u0421\u0442\u0430\u0440\u0435 \u0425\u043e\u0431\u0441\u0438"
    ],
    "name:swe_x_preferred":[
        "Star\u00e9 Hobz\u00ed"
    ],
    "name:unk_x_variant":[
        "Alt-Hart"
    ],
    "name:vie_x_preferred":[
        "Star\u00e9 Hobz\u00ed"
    ],
    "qs_pg:aaroncc":"CZ",
    "qs_pg:gn_country":"CZ",
    "qs_pg:gn_fcode":"PPL",
    "qs_pg:gn_pop":562,
    "qs_pg:name":"Star\u00e9 Hobz\u00ed",
    "qs_pg:name_adm0":"\u010cesk\u00e1 republika",
    "qs_pg:name_adm1":"Jiho\u010desk\u00fd kraj",
    "qs_pg:photos_9r":0,
    "qs_pg:photos_sr":0,
    "qs_pg:pop_sr":2,
    "qs_pg:qs_pg_placetype":"locality",
    "qs_pg:qs_pg_placetype_gp":"Town",
    "qs_pg:woe_adm0":23424810,
    "woe:adm0_id":23424810,
    "woe:name_adm0":"\u010cesk\u00e1 republika",
    "woe:name_adm1":"Jiho\u010desk\u00fd kraj",
    "woe:placetype":"Town",
    "wof:name":"Star\u00e9 Hobz\u00ed",
    "wof:placetype":"locality",
    "wof:population":562
},
  "geometry": {"coordinates":[15.45321,49.0104],"type":"Point"}
}