{
  "type": "Feature",
  "properties": {
    "gn:admin1_code":"88.0",
    "gn:admin2_code":"0202",
    "gn:asciiname":"Hodyne",
    "gn:country_code":"CZ",
    "gn:dem":315,
    "gn:feature_class":"P",
    "gn:feature_code":"PPL",
    "gn:name":"Hodyn\u011b",
    "gn:population":0,
    "gn:timezone":"Europe/Prague",
    "iso:country":"CZ",
    "wof:name":"Hodyne",
    "wof:placetype":"locality"
},
  "geometry": {"coordinates":[14.17481,49.8844],"type":"Point"}
}