{
  "type": "Feature",
  "properties": {
    "gn:admin1_code":"90.0",
    "gn:admin2_code":"0722",
    "gn:asciiname":"Kvacice",
    "gn:country_code":"CZ",
    "gn:dem":181,
    "gn:feature_class":"P",
    "gn:feature_code":"PPL",
    "gn:name":"Kva\u010dice",
    "gn:population":0,
    "gn:timezone":"Europe/Prague",
    "iso:country":"CZ",
    "wof:name":"Kvacice",
    "wof:placetype":"locality"
},
  "geometry": {"coordinates":[17.41025,48.98984],"type":"Point"}
}