{
  "type": "Feature",
  "properties": {
    "gn:country":"CZ",
    "gn:fcode":"PPL",
    "gn:population":335,
    "iso:country":"CZ",
    "name:azb_x_preferred":[
        "\u0627\u0648\u067e\u0644\u0648\u062a"
    ],
    "name:bul_x_preferred":[
        "\u041e\u043f\u043b\u043e\u0442"
    ],
    "name:ceb_x_preferred":[
        "Oplot"
    ],
    "name:ces_x_preferred":[
        "Oplot"
    ],
    "name:deu_x_preferred":[
        "Oplot"
    ],
    "name:eng_x_preferred":[
        "Oplot"
    ],
    "name:eus_x_preferred":[
        "Oplot"
    ],
    "name:fas_x_preferred":[
        "\u0627\u0648\u067e\u0644\u0648\u062a"
    ],
    "name:fra_x_preferred":[
        "Oplot"
    ],
    "name:hun_x_preferred":[
        "Oplot"
    ],
    "name:ita_x_preferred":[
        "Oplot"
    ],
    "name:msa_x_preferred":[
        "Oplot"
    ],
    "name:nan_x_preferred":[
        "Oplot"
    ],
    "name:nld_x_preferred":[
        "Oplot"
    ],
    "name:pol_x_preferred":[
        "Oplot"
    ],
    "name:por_x_preferred":[
        "Oplot"
    ],
    "name:rup_x_preferred":[
        "Oplot"
    ],
    "name:slk_x_preferred":[
        "Oplot"
    ],
    "name:spa_x_preferred":[
        "Oplot"
    ],
    "name:srp_x_preferred":[
        "\u041e\u043f\u043b\u043e\u0442"
    ],
    "name:swe_x_preferred":[
        "Oplot"
    ],
    "name:vie_x_preferred":[
        "Oplot"
    ],
    "qs_pg:aaroncc":"CZ",
    "qs_pg:gn_country":"CZ",
    "qs_pg:gn_fcode":"PPL",
    "qs_pg:gn_pop":335,
    "qs_pg:name":"Oplot",
    "qs_pg:name_adm0":"\u010cesk\u00e1 republika",
    "qs_pg:name_adm1":"Plze\u0148sk\u00fd kraj",
    "qs_pg:photos_9k":1,
    "qs_pg:photos_9r":2,
    "qs_pg:photos_all":46,
    "qs_pg:photos_sr":0,
    "qs_pg:pop_sr":2,
    "qs_pg:qs_pg_placetype":"locality",
    "qs_pg:qs_pg_placetype_gp":"Town",
    "qs_pg:woe_adm0":23424810,
    "woe:adm0_id":23424810,
    "woe:name_adm0":"\u010cesk\u00e1 republika",
    "woe:name_adm1":"Plze\u0148sk\u00fd kraj",
    "woe:placetype":"Town",
    "wof:name":"Oplot",
    "wof:placetype":"locality",
    "wof:population":335
},
  "geometry": {"coordinates":[13.27423,49.57985],"type":"Point"}
}