{
  "type": "Feature",
  "properties": {
    "iso:country":"CZ",
    "name:ara_x_preferred":[
        "\u0641\u0633\u064a\u062a\u064a\u0646"
    ],
    "name:azb_x_preferred":[
        "\u0648\u0633\u062a\u06cc\u0646"
    ],
    "name:ceb_x_preferred":[
        "Vset\u00edn"
    ],
    "name:ces_x_preferred":[
        "Vset\u00edn"
    ],
    "name:deu_x_preferred":[
        "Vset\u00edn"
    ],
    "name:epo_x_preferred":[
        "Vset\u00edn"
    ],
    "name:eus_x_preferred":[
        "Vset\u00edn"
    ],
    "name:fas_x_preferred":[
        "\u0648\u0633\u062a\u06cc\u0646"
    ],
    "name:fra_x_preferred":[
        "Vset\u00edn"
    ],
    "name:hun_x_preferred":[
        "Vset\u00edn"
    ],
    "name:ita_x_preferred":[
        "Vset\u00edn"
    ],
    "name:kor_x_preferred":[
        "\ud504\uc138\ud2f4"
    ],
    "name:lav_x_preferred":[
        "Vset\u012bna"
    ],
    "name:lit_x_preferred":[
        "Vsetynas"
    ],
    "name:msa_x_preferred":[
        "Vset\u00edn"
    ],
    "name:nld_x_preferred":[
        "Vset\u00edn"
    ],
    "name:oci_x_preferred":[
        "Vset\u00edn"
    ],
    "name:pol_x_preferred":[
        "Vset\u00edn"
    ],
    "name:por_x_preferred":[
        "Vset\u00edn"
    ],
    "name:ron_x_preferred":[
        "Vset\u00edn"
    ],
    "name:rus_x_preferred":[
        "\u0412\u0441\u0435\u0442\u0438\u043d"
    ],
    "name:slk_x_preferred":[
        "Vset\u00edn"
    ],
    "name:spa_x_preferred":[
        "Vset\u00edn"
    ],
    "name:srp_x_preferred":[
        "\u0412\u0441\u0435\u0442\u0438\u043d"
    ],
    "name:swe_x_preferred":[
        "Vset\u00edn"
    ],
    "name:tgk_x_preferred":[
        "\u0412\u0441\u0435\u0442\u0438\u043d"
    ],
    "name:tur_x_preferred":[
        "Vset\u00edn"
    ],
    "name:ukr_x_preferred":[
        "\u0412\u0441\u0435\u0442\u0456\u043d"
    ],
    "name:vie_x_preferred":[
        "Vset\u00edn"
    ],
    "name:war_x_preferred":[
        "Vset\u00edn"
    ],
    "name:zho_x_preferred":[
        "\u5f17\u585e\u5ef7"
    ],
    "qs_pg:aaroncc":"CZ",
    "qs_pg:name":"Vset\u00edn",
    "qs_pg:name_adm0":"\u010cesk\u00e1 republika",
    "qs_pg:name_adm1":"Zl\u00ednsk\u00fd kraj",
    "qs_pg:photos":7,
    "qs_pg:photos_1k":1,
    "qs_pg:photos_9k":2,
    "qs_pg:photos_9r":5,
    "qs_pg:photos_all":468,
    "qs_pg:photos_sr":1,
    "qs_pg:pop_sr":0,
    "qs_pg:qs_pg_placetype":"localadmin",
    "qs_pg:qs_pg_placetype_gp":"LocalAdmin",
    "qs_pg:woe_adm0":23424810,
    "woe:adm0_id":23424810,
    "woe:name_adm0":"\u010cesk\u00e1 republika",
    "woe:name_adm1":"Zl\u00ednsk\u00fd kraj",
    "woe:placetype":"LocalAdmin",
    "wof:name":"Vset\u00edn",
    "wof:placetype":"localadmin"
},
  "geometry": {"coordinates":[17.995176,49.340601],"type":"Point"}
}