{
  "type": "Feature",
  "properties": {
    "iso:country":"CZ",
    "name:azb_x_preferred":[
        "\u0644\u06cc\u0628\u0646\u06cc\u062a\u0633\u0647"
    ],
    "name:ceb_x_preferred":[
        "Libenice"
    ],
    "name:ces_x_preferred":[
        "Libenice"
    ],
    "name:deu_x_preferred":[
        "Libenice"
    ],
    "name:eus_x_preferred":[
        "Libenice"
    ],
    "name:fas_x_preferred":[
        "\u0644\u06cc\u0628\u0646\u06cc\u062a\u0633\u0647"
    ],
    "name:fra_x_preferred":[
        "Libenice"
    ],
    "name:hun_x_preferred":[
        "Libenice"
    ],
    "name:ita_x_preferred":[
        "Libenice"
    ],
    "name:msa_x_preferred":[
        "Libenice"
    ],
    "name:nld_x_preferred":[
        "Libenice"
    ],
    "name:pol_x_preferred":[
        "Libenice"
    ],
    "name:por_x_preferred":[
        "Libenice"
    ],
    "name:slk_x_preferred":[
        "Libenice"
    ],
    "name:spa_x_preferred":[
        "Libenice"
    ],
    "name:srp_x_preferred":[
        "\u041b\u0438\u0431\u0435\u045a\u0438\u0446\u0435"
    ],
    "name:swe_x_preferred":[
        "Libenice"
    ],
    "name:vie_x_preferred":[
        "Libenice"
    ],
    "qs_pg:aaroncc":"CZ",
    "qs_pg:name":"Libenice",
    "qs_pg:name_adm0":"\u010cesk\u00e1 republika",
    "qs_pg:name_adm1":"St\u0159edo\u010desk\u00fd kraj",
    "qs_pg:photos":183,
    "qs_pg:photos_1k":37,
    "qs_pg:photos_9k":1,
    "qs_pg:photos_9r":4,
    "qs_pg:photos_all":210,
    "qs_pg:photos_sr":4,
    "qs_pg:pop_sr":0,
    "qs_pg:qs_pg_placetype":"localadmin",
    "qs_pg:qs_pg_placetype_gp":"LocalAdmin",
    "qs_pg:woe_adm0":23424810,
    "woe:adm0_id":23424810,
    "woe:name_adm0":"\u010cesk\u00e1 republika",
    "woe:name_adm1":"St\u0159edo\u010desk\u00fd kraj",
    "woe:placetype":"LocalAdmin",
    "wof:name":"Libenice",
    "wof:placetype":"localadmin"
},
  "geometry": {"coordinates":[15.280753,49.975692],"type":"Point"}
}