{
  "type": "Feature",
  "properties": {
    "gn:gn_country":"CZ",
    "gn:gn_fcode":"PPL",
    "gn:gn_pop":674,
    "gn:population":674,
    "iso:country":"CZ",
    "name:azb_x_preferred":[
        "\u0631\u0648\u062f\u06cc\u06a9\u0648\u0648"
    ],
    "name:ceb_x_preferred":[
        "Rud\u00edkov"
    ],
    "name:ces_x_preferred":[
        "Rud\u00edkov"
    ],
    "name:eng_x_preferred":[
        "Rud\u00edkov"
    ],
    "name:eus_x_preferred":[
        "Rud\u00edkov"
    ],
    "name:fas_x_preferred":[
        "\u0631\u0648\u062f\u06cc\u06a9\u0648\u0648"
    ],
    "name:fra_x_preferred":[
        "Rud\u00edkov"
    ],
    "name:hun_x_preferred":[
        "Rud\u00edkov"
    ],
    "name:ita_x_preferred":[
        "Rud\u00edkov"
    ],
    "name:msa_x_preferred":[
        "Rud\u00edkov"
    ],
    "name:nan_x_preferred":[
        "Rud\u00edkov"
    ],
    "name:nld_x_preferred":[
        "Rud\u00edkov"
    ],
    "name:por_x_preferred":[
        "Rud\u00edkov"
    ],
    "name:rup_x_preferred":[
        "Rud\u00edkov"
    ],
    "name:slk_x_preferred":[
        "Rud\u00edkov"
    ],
    "name:spa_x_preferred":[
        "Rud\u00edkov"
    ],
    "name:swe_x_preferred":[
        "Rud\u00edkov"
    ],
    "name:unk_x_variant":[
        "Rudikau"
    ],
    "name:vie_x_preferred":[
        "Rud\u00edkov"
    ],
    "qs_pg:aaroncc":"CZ",
    "qs_pg:gn_country":"CZ",
    "qs_pg:gn_fcode":"PPL",
    "qs_pg:gn_pop":674,
    "qs_pg:name":"Rud\u00edkov",
    "qs_pg:name_adm0":"\u010cesk\u00e1 republika",
    "qs_pg:name_adm1":"Kraj Vyso\u010dina",
    "qs_pg:photos_9r":0,
    "qs_pg:photos_sr":0,
    "qs_pg:pop_sr":2,
    "qs_pg:qs_pg_placetype":"locality",
    "qs_pg:qs_pg_placetype_gp":"Town",
    "qs_pg:woe_adm0":23424810,
    "woe:adm0_id":23424810,
    "woe:name_adm0":"\u010cesk\u00e1 republika",
    "woe:name_adm1":"Kraj Vyso\u010dina",
    "woe:placetype":"Town",
    "wof:name":"Rud\u00edkov",
    "wof:placetype":"locality",
    "wof:population":674
},
  "geometry": {"coordinates":[15.94595,49.28802],"type":"Point"}
}