{
  "type": "Feature",
  "properties": {
    "gn:admin1_code":"88",
    "gn:admin2_code":"0205",
    "gn:asciiname":"Vsesoky",
    "gn:country_code":"CZ",
    "gn:dem":456,
    "gn:feature_class":"P",
    "gn:feature_code":"PPL",
    "gn:name":"V\u0161esoky",
    "gn:population":0,
    "gn:timezone":"Europe/Prague",
    "iso:country":"CZ",
    "wof:name":"Vsesoky",
    "wof:placetype":"locality"
},
  "geometry": {"coordinates":[15.16976,49.85828],"type":"Point"}
}