{
  "type": "Feature",
  "properties": {
    "gn:admin1_code":"86",
    "gn:admin2_code":"0531",
    "gn:asciiname":"Vysonin",
    "gn:country_code":"CZ",
    "gn:dem":335,
    "gn:feature_class":"P",
    "gn:feature_code":"PPL",
    "gn:name":"V\u00fdson\u00edn",
    "gn:population":0,
    "gn:timezone":"Europe/Prague",
    "iso:country":"CZ",
    "wof:name":"Vysonin",
    "wof:placetype":"locality"
},
  "geometry": {"coordinates":[15.82422,49.88075],"type":"Point"}
}