{
  "type": "Feature",
  "properties": {
    "gn:admin1_code":"89.0",
    "gn:admin2_code":"0423",
    "gn:asciiname":"Bukovina",
    "gn:cc2":"CZ",
    "gn:country_code":"CZ",
    "gn:dem":476,
    "gn:feature_class":"P",
    "gn:feature_code":"PPL",
    "gn:name":"Bukovina",
    "gn:population":0,
    "gn:timezone":"Europe/Prague",
    "iso:country":"CZ",
    "name:und_x_variant":[
        "G\u00fcgel"
    ],
    "wof:name":"Bukovina",
    "wof:placetype":"locality"
},
  "geometry": {"coordinates":[14.3042,50.61843],"type":"Point"}
}