{
  "type": "Feature",
  "properties": {
    "gn:admin1_code":"84.0",
    "gn:admin2_code":"0715",
    "gn:asciiname":"Adamov",
    "gn:country_code":"CZ",
    "gn:dem":883,
    "gn:feature_class":"P",
    "gn:feature_code":"PPL",
    "gn:name":"Adamov",
    "gn:population":0,
    "gn:timezone":"Europe/Prague",
    "iso:country":"CZ",
    "name:bel_x_preferred":[
        "\u0410\u0434\u0430\u043c\u0430\u045e"
    ],
    "name:ceb_x_preferred":[
        "Adamov"
    ],
    "name:ces_x_preferred":[
        "Adamov"
    ],
    "name:deu_x_preferred":[
        "Adamov"
    ],
    "name:epo_x_preferred":[
        "Adamov"
    ],
    "name:fra_x_preferred":[
        "Adamov"
    ],
    "name:heb_x_preferred":[
        "\u05d0\u05d3\u05de\u05d5\u05d1"
    ],
    "name:hsb_x_preferred":[
        "Adamov"
    ],
    "name:ita_x_preferred":[
        "Adamov"
    ],
    "name:jpn_x_preferred":[
        "\u30a2\u30c0\u30e2\u30d5"
    ],
    "name:nld_x_preferred":[
        "Adamov"
    ],
    "name:rus_x_preferred":[
        "\u0410\u0434\u0430\u043c\u043e\u0432"
    ],
    "name:slk_x_preferred":[
        "Adamov"
    ],
    "name:srp_x_preferred":[
        "\u0410\u0434\u0430\u043c\u043e\u0432"
    ],
    "name:swe_x_preferred":[
        "Adamov"
    ],
    "name:und_x_variant":[
        "Adamsthal"
    ],
    "wof:name":"Adamov",
    "wof:placetype":"locality"
},
  "geometry": {"coordinates":[17.02317,50.19615],"type":"Point"}
}