{
  "type": "Feature",
  "properties": {
    "gn:admin1_code":"84.0",
    "gn:admin2_code":"0715",
    "gn:asciiname":"Adamov",
    "gn:country_code":"CZ",
    "gn:dem":883,
    "gn:feature_class":"P",
    "gn:feature_code":"PPL",
    "gn:name":"Adamov",
    "gn:population":0,
    "gn:timezone":"Europe/Prague",
    "iso:country":"CZ",
    "name:und_x_variant":[
        "Adamsthal",
        "Adamov"
    ],
    "wof:name":"Adamov",
    "wof:placetype":"locality"
},
  "geometry": {"coordinates":[17.02317,50.19615],"type":"Point"}
}