{
  "type": "Feature",
  "properties": {
    "gn:admin1_code":"87.0",
    "gn:admin2_code":"0322",
    "gn:asciiname":"Defurovy Lazany",
    "gn:country_code":"CZ",
    "gn:dem":540,
    "gn:feature_class":"P",
    "gn:feature_code":"PPL",
    "gn:name":"Defurovy La\u017eany",
    "gn:population":0,
    "gn:timezone":"Europe/Prague",
    "iso:country":"CZ",
    "name:und_x_variant":[
        "La\u017ean Desfours",
        "Desfours La\u017ean",
        "Defurovy La\u017eany"
    ],
    "wof:name":"Defurovy Lazany",
    "wof:placetype":"locality"
},
  "geometry": {"coordinates":[13.67732,49.408],"type":"Point"}
}