{
  "type": "Feature",
  "properties": {
    "gn:admin1_code":"87",
    "gn:admin2_code":"0327",
    "gn:asciiname":"Vyrov",
    "gn:country_code":"CZ",
    "gn:dem":431,
    "gn:feature_class":"P",
    "gn:feature_code":"PPL",
    "gn:name":"V\u00fdrov",
    "gn:population":0,
    "gn:timezone":"Europe/Prague",
    "iso:country":"CZ",
    "name:und_x_variant":[
        "Wierau",
        "V\u00fdrov"
    ],
    "wof:name":"Vyrov",
    "wof:placetype":"locality"
},
  "geometry": {"coordinates":[12.8921,49.70143],"type":"Point"}
}