{
  "type": "Feature",
  "properties": {
    "gn:gn_country":"CZ",
    "gn:gn_fcode":"PPL",
    "gn:gn_pop":367,
    "gn:population":367,
    "iso:country":"CZ",
    "name:ces_x_preferred":[
        "Hora Svat\u00e9 Kate\u0159iny"
    ],
    "name:deu_x_preferred":[
        "Hora Svat\u00e9 Kate\u0159iny"
    ],
    "name:eng_x_preferred":[
        "Hora Svat\u00e9 Kate\u0159iny"
    ],
    "name:fas_x_preferred":[
        "\u0647\u0648\u0631\u0627 \u0633\u0648\u0627\u062a\u0647 \u06a9\u0627\u062a\u0631\u06cc\u0646\u06cc"
    ],
    "name:fra_x_preferred":[
        "Hora Svat\u00e9 Kate\u0159iny"
    ],
    "name:hun_x_preferred":[
        "Hora Svat\u00e9 Kate\u0159iny"
    ],
    "name:ita_x_preferred":[
        "Hora Svat\u00e9 Kate\u0159iny"
    ],
    "name:msa_x_preferred":[
        "Hora Svat\u00e9 Kate\u0159iny"
    ],
    "name:nld_x_preferred":[
        "Hora Svat\u00e9 Kate\u0159iny"
    ],
    "name:nob_x_preferred":[
        "Hora Svat\u00e9 Kate\u0159iny"
    ],
    "name:por_x_preferred":[
        "Hora Svat\u00e9 Kate\u0159iny"
    ],
    "name:rup_x_preferred":[
        "Hora Svat\u00e9 Kate\u0159iny"
    ],
    "name:rus_x_preferred":[
        "\u0413\u043e\u0440\u0430-\u0421\u0432\u0430\u0442\u0435-\u041a\u0430\u0442\u0435\u0440\u0436\u0438\u043d\u0438"
    ],
    "name:slk_x_preferred":[
        "Hora Svat\u00e9 Kate\u0159iny"
    ],
    "name:srp_x_preferred":[
        "\u0425\u043e\u0440\u0430 \u0421\u0432\u0430\u0442\u0435 \u041a\u0430\u0442\u0435\u0440\u0436\u0438\u043d\u0438"
    ],
    "name:swe_x_preferred":[
        "Hora Svat\u00e9 Kate\u0159iny"
    ],
    "name:tat_x_preferred":[
        "\u04ba\u043e\u0440\u0430-\u0421\u0432\u0430\u0442\u0435-\u041a\u0430\u0442\u0435\u0440\u0436\u0438\u043d\u044b"
    ],
    "name:unk_x_variant":[
        "Katharinaberg"
    ],
    "name:vie_x_preferred":[
        "Hora Svat\u00e9 Kate\u0159iny"
    ],
    "qs_pg:aaroncc":"CZ",
    "qs_pg:gn_country":"CZ",
    "qs_pg:gn_fcode":"PPL",
    "qs_pg:gn_pop":367,
    "qs_pg:name":"Hora Svat\u00e9 Kate\u0159iny",
    "qs_pg:name_adm0":"\u010cesk\u00e1 republika",
    "qs_pg:name_adm1":"\u00dasteck\u00fd kraj",
    "qs_pg:photos_9k":1,
    "qs_pg:photos_9r":1,
    "qs_pg:photos_all":3,
    "qs_pg:photos_sr":0,
    "qs_pg:pop_sr":2,
    "qs_pg:qs_pg_placetype":"locality",
    "qs_pg:qs_pg_placetype_gp":"Town",
    "qs_pg:woe_adm0":23424810,
    "woe:adm0_id":23424810,
    "woe:name_adm0":"\u010cesk\u00e1 republika",
    "woe:name_adm1":"\u00dasteck\u00fd kraj",
    "woe:placetype":"Town",
    "wof:name":"Hora Svat\u00e9 Kate\u0159iny",
    "wof:placetype":"locality",
    "wof:population":367
},
  "geometry": {"coordinates":[13.43672,50.60631],"type":"Point"}
}