{
  "type": "Feature",
  "properties": {
    "gn:admin1_code":"79.0",
    "gn:admin2_code":"0313",
    "gn:asciiname":"Otin",
    "gn:country_code":"CZ",
    "gn:dem":481,
    "gn:feature_class":"P",
    "gn:feature_code":"PPL",
    "gn:name":"Ot\u00edn",
    "gn:population":0,
    "gn:timezone":"Europe/Prague",
    "iso:country":"CZ",
    "name:und_x_variant":[
        "Ottenschlag"
    ],
    "wof:name":"Otin",
    "wof:placetype":"locality"
},
  "geometry": {"coordinates":[15.04282,49.1366],"type":"Point"}
}