{
  "type": "Feature",
  "properties": {
    "gn:country":"CZ",
    "gn:fcode":"PPL",
    "gn:population":484,
    "iso:country":"CZ",
    "name:azb_x_preferred":[
        "\u0646\u0633\u067e\u06a9\u06cc"
    ],
    "name:bul_x_preferred":[
        "\u041d\u0435\u0441\u043f\u0435\u043a\u0439"
    ],
    "name:cat_x_preferred":[
        "Nespeky"
    ],
    "name:ceb_x_preferred":[
        "Nespeky"
    ],
    "name:ces_x_preferred":[
        "Nespeky"
    ],
    "name:che_x_preferred":[
        "\u041d\u0435\u0441\u043f\u0435\u043a\u0438"
    ],
    "name:deu_x_preferred":[
        "Nespeky"
    ],
    "name:eng_x_preferred":[
        "Nespeky"
    ],
    "name:eus_x_preferred":[
        "Nespeky"
    ],
    "name:fas_x_preferred":[
        "\u0646\u0633\u067e\u06a9\u06cc"
    ],
    "name:fra_x_preferred":[
        "Nespeky"
    ],
    "name:gle_x_preferred":[
        "Nespeky"
    ],
    "name:hun_x_preferred":[
        "Nespeky"
    ],
    "name:ita_x_preferred":[
        "Nespeky"
    ],
    "name:lmo_x_preferred":[
        "Nespeky"
    ],
    "name:msa_x_preferred":[
        "Nespeky"
    ],
    "name:nan_x_preferred":[
        "Nespeky"
    ],
    "name:nld_x_preferred":[
        "Nespeky"
    ],
    "name:oci_x_preferred":[
        "Nespeky"
    ],
    "name:pol_x_preferred":[
        "Nespeky"
    ],
    "name:por_x_preferred":[
        "Nespeky"
    ],
    "name:rup_x_preferred":[
        "Nespeky"
    ],
    "name:slk_x_preferred":[
        "Nespeky"
    ],
    "name:spa_x_preferred":[
        "Nespeky"
    ],
    "name:srp_x_preferred":[
        "\u041d\u0435\u0441\u043f\u0435\u043a\u0438"
    ],
    "name:swe_x_preferred":[
        "Nespeky"
    ],
    "name:tat_x_preferred":[
        "\u041d\u0435\u0441\u043f\u0435\u043a\u0438"
    ],
    "name:und_x_variant":[
        "Dnespek"
    ],
    "name:uzb_x_preferred":[
        "Nespeky"
    ],
    "name:vie_x_preferred":[
        "Nespeky"
    ],
    "qs_pg:aaroncc":"CZ",
    "qs_pg:gn_country":"CZ",
    "qs_pg:gn_fcode":"PPL",
    "qs_pg:gn_pop":484,
    "qs_pg:name":"Nespeky",
    "qs_pg:name_adm0":"\u010cesk\u00e1 republika",
    "qs_pg:name_adm1":"St\u0159edo\u010desk\u00fd kraj",
    "qs_pg:photos_9k":1,
    "qs_pg:photos_9r":1,
    "qs_pg:photos_all":8,
    "qs_pg:photos_sr":0,
    "qs_pg:pop_sr":2,
    "qs_pg:qs_pg_placetype":"locality",
    "qs_pg:qs_pg_placetype_gp":"Town",
    "qs_pg:woe_adm0":23424810,
    "woe:adm0_id":23424810,
    "woe:name_adm0":"\u010cesk\u00e1 republika",
    "woe:name_adm1":"St\u0159edo\u010desk\u00fd kraj",
    "woe:placetype":"Town",
    "wof:name":"Nespeky",
    "wof:placetype":"locality",
    "wof:population":484
},
  "geometry": {"coordinates":[14.65936,49.85931],"type":"Point"}
}