{
  "type": "Feature",
  "properties": {
    "gn:admin1_code":"86",
    "gn:admin2_code":"0534",
    "gn:asciiname":"Vanice",
    "gn:country_code":"CZ",
    "gn:dem":329,
    "gn:feature_class":"P",
    "gn:feature_code":"PPL",
    "gn:name":"Vanice",
    "gn:population":0,
    "gn:timezone":"Europe/Prague",
    "iso:country":"CZ",
    "wof:name":"Vanice",
    "wof:placetype":"locality"
},
  "geometry": {"coordinates":[16.13172,49.93612],"type":"Point"}
}