{
  "type": "Feature",
  "properties": {
    "gn:admin1_code":"87.0",
    "gn:admin2_code":"0327",
    "gn:asciiname":"Prazka",
    "gn:country_code":"CZ",
    "gn:dem":450,
    "gn:feature_class":"P",
    "gn:feature_code":"PPL",
    "gn:name":"Pra\u017eka",
    "gn:population":0,
    "gn:timezone":"Europe/Prague",
    "iso:country":"CZ",
    "wof:name":"Prazka",
    "wof:placetype":"locality"
},
  "geometry": {"coordinates":[12.90561,49.74006],"type":"Point"}
}