{
  "type": "Feature",
  "properties": {
    "gn:gn_country":"CZ",
    "gn:gn_fcode":"PPL",
    "gn:gn_pop":0,
    "iso:country":"CZ",
    "name:azb_x_preferred":[
        "\u0645\u0644\u06a9\u0648\u06cc\u062f\u06cc"
    ],
    "name:ceb_x_preferred":[
        "Ml\u00e9kojedy"
    ],
    "name:ces_x_preferred":[
        "Ml\u00e9kojedy"
    ],
    "name:deu_x_preferred":[
        "Ml\u00e9kojedy"
    ],
    "name:epo_x_preferred":[
        "Ml\u00e9kojedy"
    ],
    "name:eus_x_preferred":[
        "Ml\u00e9kojedy"
    ],
    "name:fas_x_preferred":[
        "\u0645\u0644\u06a9\u0648\u06cc\u062f\u06cc"
    ],
    "name:fra_x_preferred":[
        "Ml\u00e9kojedy"
    ],
    "name:hun_x_preferred":[
        "Ml\u00e9kojedy"
    ],
    "name:ita_x_preferred":[
        "Ml\u00e9kojedy"
    ],
    "name:msa_x_preferred":[
        "Ml\u00e9kojedy"
    ],
    "name:nld_x_preferred":[
        "Ml\u00e9kojedy"
    ],
    "name:por_x_preferred":[
        "Ml\u00e9kojedy"
    ],
    "name:slk_x_preferred":[
        "Ml\u00e9kojedy"
    ],
    "name:spa_x_preferred":[
        "Ml\u00e9kojedy"
    ],
    "name:srp_x_preferred":[
        "\u041c\u043b\u0435\u043a\u043e\u0458\u0435\u0434\u0438"
    ],
    "name:swe_x_preferred":[
        "Ml\u00e9kojedy"
    ],
    "name:unk_x_variant":[
        "Mlikojed"
    ],
    "name:vie_x_preferred":[
        "Ml\u00e9kojedy"
    ],
    "qs_pg:aaroncc":"CZ",
    "qs_pg:gn_country":"CZ",
    "qs_pg:gn_fcode":"PPL",
    "qs_pg:gn_pop":0,
    "qs_pg:name":"Ml\u00e9kojedy",
    "qs_pg:name_adm0":"\u010cesk\u00e1 republika",
    "qs_pg:name_adm1":"St\u0159edo\u010desk\u00fd kraj",
    "qs_pg:photos_9k":1,
    "qs_pg:photos_9r":1,
    "qs_pg:photos_all":12,
    "qs_pg:photos_sr":0,
    "qs_pg:pop_sr":0,
    "qs_pg:qs_pg_placetype":"locality",
    "qs_pg:qs_pg_placetype_gp":"Town",
    "qs_pg:woe_adm0":23424810,
    "woe:adm0_id":23424810,
    "woe:name_adm0":"\u010cesk\u00e1 republika",
    "woe:name_adm1":"St\u0159edo\u010desk\u00fd kraj",
    "woe:placetype":"Town",
    "wof:name":"Ml\u00e9kojedy",
    "wof:placetype":"locality"
},
  "geometry": {"coordinates":[14.53244,50.25941],"type":"Point"}
}