{
  "type": "Feature",
  "properties": {
    "gn:admin1_code":"85.0",
    "gn:admin2_code":"0801",
    "gn:asciiname":"Dlouha Ves",
    "gn:country_code":"CZ",
    "gn:dem":670,
    "gn:feature_class":"P",
    "gn:feature_code":"PPL",
    "gn:name":"Dlouh\u00e1 Ves",
    "gn:population":0,
    "gn:timezone":"Europe/Prague",
    "iso:country":"CZ",
    "name:und_x_variant":[
        "Langendorf"
    ],
    "wof:name":"Dlouha Ves",
    "wof:placetype":"locality"
},
  "geometry": {"coordinates":[17.49075,50.13609],"type":"Point"}
}