{
  "type": "Feature",
  "properties": {
    "gn:admin1_code":"85.0",
    "gn:admin2_code":"0801",
    "gn:asciiname":"Milotice",
    "gn:country_code":"CZ",
    "gn:dem":506,
    "gn:feature_class":"P",
    "gn:feature_code":"PPL",
    "gn:name":"Milotice",
    "gn:population":0,
    "gn:timezone":"Europe/Prague",
    "iso:country":"CZ",
    "name:azb_x_preferred":[
        "\u0645\u06cc\u0644\u0648\u062a\u06cc\u062a\u0633\u0647"
    ],
    "name:ceb_x_preferred":[
        "Milotice"
    ],
    "name:ces_x_preferred":[
        "Milotice"
    ],
    "name:eus_x_preferred":[
        "Milotice"
    ],
    "name:fas_x_preferred":[
        "\u0645\u06cc\u0644\u0648\u062a\u06cc\u062a\u0633\u0647"
    ],
    "name:fra_x_preferred":[
        "Milotice"
    ],
    "name:hun_x_preferred":[
        "Milotice"
    ],
    "name:ita_x_preferred":[
        "Milotice"
    ],
    "name:msa_x_preferred":[
        "Milotice"
    ],
    "name:nld_x_preferred":[
        "Milotice"
    ],
    "name:pol_x_preferred":[
        "Milotice"
    ],
    "name:por_x_preferred":[
        "Milotice"
    ],
    "name:rus_x_preferred":[
        "\u041c\u0438\u043b\u043e\u0442\u0438\u0446\u0435"
    ],
    "name:slk_x_preferred":[
        "Milotice"
    ],
    "name:spa_x_preferred":[
        "Milotice"
    ],
    "name:srp_x_preferred":[
        "\u041c\u0438\u043b\u043e\u0442\u0438\u0446\u0435"
    ],
    "name:swe_x_preferred":[
        "Milotice"
    ],
    "name:und_x_variant":[
        "Milkendorf"
    ],
    "name:vie_x_preferred":[
        "Milotice"
    ],
    "wof:name":"Milotice",
    "wof:placetype":"locality"
},
  "geometry": {"coordinates":[17.54143,49.99548],"type":"Point"}
}