{
  "type": "Feature",
  "properties": {
    "gn:admin1_code":"82",
    "gn:admin2_code":"0523",
    "gn:asciiname":"Strezimerice",
    "gn:country_code":"CZ",
    "gn:dem":336,
    "gn:feature_class":"P",
    "gn:feature_code":"PPL",
    "gn:name":"St\u0159ezim\u011b\u0159ice",
    "gn:population":0,
    "gn:timezone":"Europe/Prague",
    "iso:country":"CZ",
    "name:und_x_variant":[
        "Ziesmitz",
        "St\u0159ezim\u011b\u0159ice"
    ],
    "wof:name":"Strezimerice",
    "wof:placetype":"locality"
},
  "geometry": {"coordinates":[15.95666,50.40875],"type":"Point"}
}