{
  "type": "Feature",
  "properties": {
    "gn:admin1_code":"79.0",
    "gn:admin2_code":"0315",
    "gn:asciiname":"Horosedly",
    "gn:country_code":"CZ",
    "gn:dem":688,
    "gn:feature_class":"P",
    "gn:feature_code":"PPL",
    "gn:name":"Horosedly",
    "gn:population":0,
    "gn:timezone":"Europe/Prague",
    "iso:country":"CZ",
    "name:azb_x_preferred":[
        "\u0647\u0648\u0631\u0648\u0633\u062f\u0644\u06cc"
    ],
    "name:ceb_x_preferred":[
        "Horosedly"
    ],
    "name:ces_x_preferred":[
        "Horosedly"
    ],
    "name:deu_x_preferred":[
        "Horosedly"
    ],
    "name:epo_x_preferred":[
        "Horosedly"
    ],
    "name:eus_x_preferred":[
        "Horosedly"
    ],
    "name:fas_x_preferred":[
        "\u0647\u0648\u0631\u0648\u0633\u062f\u0644\u06cc"
    ],
    "name:fra_x_preferred":[
        "Horosedly"
    ],
    "name:hun_x_preferred":[
        "Horosedly"
    ],
    "name:ita_x_preferred":[
        "Horosedly"
    ],
    "name:msa_x_preferred":[
        "Horosedly"
    ],
    "name:nld_x_preferred":[
        "Horosedly"
    ],
    "name:por_x_preferred":[
        "Horosedly"
    ],
    "name:slk_x_preferred":[
        "Horosedly"
    ],
    "name:spa_x_preferred":[
        "Horosedly"
    ],
    "name:srp_x_preferred":[
        "\u0425\u043e\u0440\u043e\u0441\u0435\u0434\u043b\u0438"
    ],
    "name:swe_x_preferred":[
        "Horosedly"
    ],
    "name:vie_x_preferred":[
        "Horosedly"
    ],
    "wof:name":"Horosedly",
    "wof:placetype":"locality"
},
  "geometry": {"coordinates":[13.79052,49.12469],"type":"Point"}
}