{
  "type": "Feature",
  "properties": {
    "gn:admin1_code":"79.0",
    "gn:admin2_code":"0312",
    "gn:asciiname":"Kokotin",
    "gn:country_code":"CZ",
    "gn:dem":645,
    "gn:feature_class":"P",
    "gn:feature_code":"PPL",
    "gn:name":"Kokot\u00edn",
    "gn:population":0,
    "gn:timezone":"Europe/Prague",
    "iso:country":"CZ",
    "wof:name":"Kokotin",
    "wof:placetype":"locality"
},
  "geometry": {"coordinates":[14.33333,48.85],"type":"Point"}
}