{
  "type": "Feature",
  "properties": {
    "gn:admin1_code":"87.0",
    "gn:admin2_code":"0322",
    "gn:asciiname":"Depoltice",
    "gn:country_code":"CZ",
    "gn:dem":635,
    "gn:feature_class":"P",
    "gn:feature_code":"PPL",
    "gn:name":"D\u011bpoltice",
    "gn:population":0,
    "gn:timezone":"Europe/Prague",
    "iso:country":"CZ",
    "wof:name":"Depoltice",
    "wof:placetype":"locality"
},
  "geometry": {"coordinates":[13.21721,49.26346],"type":"Point"}
}