{
  "type": "Feature",
  "properties": {
    "gn:admin1_code":"82.0",
    "gn:admin2_code":"0523",
    "gn:asciiname":"Lhotky",
    "gn:country_code":"CZ",
    "gn:dem":396,
    "gn:feature_class":"P",
    "gn:feature_code":"PPL",
    "gn:name":"Lhotky",
    "gn:population":0,
    "gn:timezone":"Europe/Prague",
    "iso:country":"CZ",
    "name:azb_x_preferred":[
        "\u0644\u0647\u0648\u062a\u06a9\u06cc"
    ],
    "name:ceb_x_preferred":[
        "Lhotky"
    ],
    "name:ces_x_preferred":[
        "Lhotky"
    ],
    "name:eus_x_preferred":[
        "Lhotky"
    ],
    "name:fas_x_preferred":[
        "\u0644\u0647\u0648\u062a\u06a9\u06cc"
    ],
    "name:fra_x_preferred":[
        "Lhotky"
    ],
    "name:hun_x_preferred":[
        "Lhotky"
    ],
    "name:ita_x_preferred":[
        "Lhotky"
    ],
    "name:msa_x_preferred":[
        "Lhotky"
    ],
    "name:nld_x_preferred":[
        "Lhotky"
    ],
    "name:pol_x_preferred":[
        "Lhotky"
    ],
    "name:por_x_preferred":[
        "Lhotky"
    ],
    "name:slk_x_preferred":[
        "Lhotky"
    ],
    "name:spa_x_preferred":[
        "Lhotky"
    ],
    "name:srp_x_preferred":[
        "\u041b\u0445\u043e\u0442\u043a\u0438"
    ],
    "name:swe_x_preferred":[
        "Lhotky"
    ],
    "name:vie_x_preferred":[
        "Lhotky"
    ],
    "wof:name":"Lhotky",
    "wof:placetype":"locality"
},
  "geometry": {"coordinates":[16.11411,50.42454],"type":"Point"}
}