{
  "type": "Feature",
  "properties": {
    "gn:admin1_code":"79",
    "gn:admin2_code":"0315",
    "gn:asciiname":"Zahradky - Borova Lada",
    "gn:country_code":"CZ",
    "gn:dem":873,
    "gn:feature_class":"P",
    "gn:feature_code":"PPL",
    "gn:name":"Zahr\u00e1dky - Borov\u00e1 Lada",
    "gn:population":0,
    "gn:timezone":"Europe/Prague",
    "iso:country":"CZ",
    "name:und_x_variant":[
        "Mergart",
        "Zahr\u00e1dky"
    ],
    "wof:name":"Zahradky - Borova Lada",
    "wof:placetype":"locality"
},
  "geometry": {"coordinates":[13.67515,48.97209],"type":"Point"}
}