{
  "type": "Feature",
  "properties": {
    "gn:admin1_code":"82.0",
    "gn:admin2_code":"0524",
    "gn:asciiname":"Popelov",
    "gn:country_code":"CZ",
    "gn:dem":544,
    "gn:feature_class":"P",
    "gn:feature_code":"PPL",
    "gn:name":"Popelov",
    "gn:population":0,
    "gn:timezone":"Europe/Prague",
    "iso:country":"CZ",
    "wof:name":"Popelov",
    "wof:placetype":"locality"
},
  "geometry": {"coordinates":[16.40718,50.17974],"type":"Point"}
}