{
  "type": "Feature",
  "properties": {
    "gn:admin1_code":"86",
    "gn:admin2_code":"0531",
    "gn:asciiname":"Ustupky",
    "gn:country_code":"CZ",
    "gn:dem":509,
    "gn:feature_class":"P",
    "gn:feature_code":"PPL",
    "gn:name":"\u00dastupky",
    "gn:population":0,
    "gn:timezone":"Europe/Prague",
    "iso:country":"CZ",
    "wof:name":"Ustupky",
    "wof:placetype":"locality"
},
  "geometry": {"coordinates":[15.65337,49.82463],"type":"Point"}
}