{
  "type": "Feature",
  "properties": {
    "gn:admin1_code":"87.0",
    "gn:admin2_code":"0322",
    "gn:asciiname":"Mestiste",
    "gn:country_code":"CZ",
    "gn:dem":612,
    "gn:feature_class":"P",
    "gn:feature_code":"PPL",
    "gn:name":"M\u011bsti\u0161t\u011b",
    "gn:population":0,
    "gn:timezone":"Europe/Prague",
    "iso:country":"CZ",
    "name:und_x_variant":[
        "Dorrstadt",
        "M\u011bsti\u0161t\u011b"
    ],
    "wof:name":"Mestiste",
    "wof:placetype":"locality"
},
  "geometry": {"coordinates":[13.23746,49.24572],"type":"Point"}
}