{
  "type": "Feature",
  "properties": {
    "gn:admin1_code":"84.0",
    "gn:admin2_code":"0713",
    "gn:asciiname":"Dubany",
    "gn:country_code":"CZ",
    "gn:dem":212,
    "gn:feature_class":"P",
    "gn:feature_code":"PPL",
    "gn:name":"Dubany",
    "gn:population":0,
    "gn:timezone":"Europe/Prague",
    "iso:country":"CZ",
    "name:ceb_x_preferred":[
        "Dubany"
    ],
    "name:ces_x_preferred":[
        "Dubany"
    ],
    "name:deu_x_preferred":[
        "Dubany"
    ],
    "name:epo_x_preferred":[
        "Dubany"
    ],
    "name:eus_x_preferred":[
        "Dubany"
    ],
    "name:fra_x_preferred":[
        "Dubany"
    ],
    "name:hun_x_preferred":[
        "Dubany"
    ],
    "name:ita_x_preferred":[
        "Dubany"
    ],
    "name:msa_x_preferred":[
        "Dubany"
    ],
    "name:nld_x_preferred":[
        "Dubany"
    ],
    "name:pol_x_preferred":[
        "Dubany"
    ],
    "name:por_x_preferred":[
        "Dubany"
    ],
    "name:slk_x_preferred":[
        "Dubany"
    ],
    "name:spa_x_preferred":[
        "Dubany"
    ],
    "name:srp_x_preferred":[
        "\u0414\u0443\u0431\u0430\u043d\u0438"
    ],
    "name:swe_x_preferred":[
        "Dubany"
    ],
    "name:vie_x_preferred":[
        "Dubany"
    ],
    "wof:name":"Dubany",
    "wof:placetype":"locality"
},
  "geometry": {"coordinates":[17.19163,49.51579],"type":"Point"}
}