{
  "type": "Feature",
  "properties": {
    "gn:admin1_code":"84.0",
    "gn:admin2_code":"0713",
    "gn:asciiname":"Dubany",
    "gn:country_code":"CZ",
    "gn:dem":212,
    "gn:feature_class":"P",
    "gn:feature_code":"PPL",
    "gn:name":"Dubany",
    "gn:population":0,
    "gn:timezone":"Europe/Prague",
    "iso:country":"CZ",
    "wof:name":"Dubany",
    "wof:placetype":"locality"
},
  "geometry": {"coordinates":[17.19163,49.51579],"type":"Point"}
}