{
  "type": "Feature",
  "properties": {
    "gn:admin1_code":"89.0",
    "gn:admin2_code":"0425",
    "gn:asciiname":"Flaje",
    "gn:country_code":"CZ",
    "gn:dem":722,
    "gn:feature_class":"P",
    "gn:feature_code":"PPL",
    "gn:name":"Fl\u00e1je",
    "gn:population":0,
    "gn:timezone":"Europe/Prague",
    "iso:country":"CZ",
    "name:und_x_variant":[
        "Fleyh",
        "Fl\u00e1je"
    ],
    "wof:name":"Flaje",
    "wof:placetype":"locality"
},
  "geometry": {"coordinates":[13.58417,50.68865],"type":"Point"}
}