{
  "type": "Feature",
  "properties": {
    "gn:admin1_code":"88.0",
    "gn:admin2_code":"0201",
    "gn:asciiname":"Podelusy",
    "gn:country_code":"CZ",
    "gn:dem":261,
    "gn:feature_class":"P",
    "gn:feature_code":"PPL",
    "gn:name":"Pod\u011blusy",
    "gn:population":0,
    "gn:timezone":"Europe/Prague",
    "iso:country":"CZ",
    "name:und_x_variant":[
        "Podielus",
        "Pod\u011blusy"
    ],
    "wof:name":"Podelusy",
    "wof:placetype":"locality"
},
  "geometry": {"coordinates":[14.57708,49.83738],"type":"Point"}
}