{
  "type": "Feature",
  "properties": {
    "gn:admin1_code":"78.0",
    "gn:admin2_code":"0623",
    "gn:asciiname":"Smolin",
    "gn:cc2":"CZ",
    "gn:country_code":"CZ",
    "gn:dem":185,
    "gn:feature_class":"P",
    "gn:feature_code":"PPL",
    "gn:name":"Smol\u00edn",
    "gn:population":0,
    "gn:timezone":"Europe/Prague",
    "iso:country":"CZ",
    "name:und_x_variant":[
        "Mohleis"
    ],
    "wof:name":"Smolin",
    "wof:placetype":"locality"
},
  "geometry": {"coordinates":[16.53837,49.00792],"type":"Point"}
}