{
  "type": "Feature",
  "properties": {
    "gn:admin1_code":"79.0",
    "gn:admin2_code":"0315",
    "gn:asciiname":"Skarez",
    "gn:country_code":"CZ",
    "gn:dem":819,
    "gn:feature_class":"P",
    "gn:feature_code":"PPL",
    "gn:name":"Skarez",
    "gn:population":0,
    "gn:timezone":"Europe/Prague",
    "iso:country":"CZ",
    "wof:name":"Skarez",
    "wof:placetype":"locality"
},
  "geometry": {"coordinates":[13.88592,49.03294],"type":"Point"}
}