{
  "type": "Feature",
  "properties": {
    "gn:admin1_code":"90.0",
    "gn:admin2_code":"0722",
    "gn:asciiname":"Mikovice",
    "gn:country_code":"CZ",
    "gn:dem":190,
    "gn:feature_class":"P",
    "gn:feature_code":"PPL",
    "gn:name":"M\u00edkovice",
    "gn:population":0,
    "gn:timezone":"Europe/Prague",
    "iso:country":"CZ",
    "wof:name":"Mikovice",
    "wof:placetype":"locality"
},
  "geometry": {"coordinates":[17.50447,49.03715],"type":"Point"}
}