{
  "type": "Feature",
  "properties": {
    "gn:admin1_code":"82.0",
    "gn:admin2_code":"0525",
    "gn:asciiname":"Rudolfov",
    "gn:country_code":"CZ",
    "gn:dem":669,
    "gn:feature_class":"P",
    "gn:feature_code":"PPL",
    "gn:name":"Rudolfov",
    "gn:population":0,
    "gn:timezone":"Europe/Prague",
    "iso:country":"CZ",
    "name:und_x_variant":[
        "Rudolfsthal",
        "Rudolfov"
    ],
    "wof:name":"Rudolfov",
    "wof:placetype":"locality"
},
  "geometry": {"coordinates":[15.66455,50.66942],"type":"Point"}
}