{
  "type": "Feature",
  "properties": {
    "gn:admin1_code":"82.0",
    "gn:admin2_code":"0525",
    "gn:asciiname":"Rudolfov",
    "gn:country_code":"CZ",
    "gn:dem":669,
    "gn:feature_class":"P",
    "gn:feature_code":"PPL",
    "gn:name":"Rudolfov",
    "gn:population":0,
    "gn:timezone":"Europe/Prague",
    "iso:country":"CZ",
    "name:ceb_x_preferred":[
        "Rudolfov"
    ],
    "name:ces_x_preferred":[
        "Rudolfov"
    ],
    "name:deu_x_preferred":[
        "Rudolfov"
    ],
    "name:eus_x_preferred":[
        "Rudolfov"
    ],
    "name:fas_x_preferred":[
        "\u0631\u0648\u062f\u0648\u0644\u0641\u0648\u0648"
    ],
    "name:fra_x_preferred":[
        "Rudolfov"
    ],
    "name:hun_x_preferred":[
        "Rudolfov"
    ],
    "name:ita_x_preferred":[
        "Rudolfov"
    ],
    "name:msa_x_preferred":[
        "Rudolfov"
    ],
    "name:nld_x_preferred":[
        "Rudolfov"
    ],
    "name:pol_x_preferred":[
        "Rudolfov"
    ],
    "name:por_x_preferred":[
        "Rudolfov"
    ],
    "name:slk_x_preferred":[
        "Rudolfov"
    ],
    "name:spa_x_preferred":[
        "Rudolfov"
    ],
    "name:srp_x_preferred":[
        "\u0420\u0443\u0434\u043e\u043b\u0444\u043e\u0432"
    ],
    "name:swe_x_preferred":[
        "Rudolfov"
    ],
    "name:und_x_variant":[
        "Rudolfsthal"
    ],
    "name:vie_x_preferred":[
        "Rudolfov"
    ],
    "name:zho_x_preferred":[
        "\u9b6f\u591a\u723e\u798f\u592b"
    ],
    "wof:name":"Rudolfov",
    "wof:placetype":"locality"
},
  "geometry": {"coordinates":[15.66455,50.66942],"type":"Point"}
}