{
  "type": "Feature",
  "properties": {
    "gn:admin1_code":"79.0",
    "gn:admin2_code":"0312",
    "gn:asciiname":"Poresinec",
    "gn:country_code":"CZ",
    "gn:dem":570,
    "gn:feature_class":"P",
    "gn:feature_code":"PPL",
    "gn:name":"Po\u0159e\u0161inec",
    "gn:population":0,
    "gn:timezone":"Europe/Prague",
    "iso:country":"CZ",
    "wof:name":"Poresinec",
    "wof:placetype":"locality"
},
  "geometry": {"coordinates":[14.49866,48.76466],"type":"Point"}
}