{
  "type": "Feature",
  "properties": {
    "gn:gn_country":"CZ",
    "gn:gn_fcode":"PPL",
    "gn:gn_pop":938,
    "gn:population":938,
    "iso:country":"CZ",
    "name:bel_x_preferred":[
        "\u0423\u0432\u0430\u043b\u044c\u043d\u0430"
    ],
    "name:ces_x_preferred":[
        "\u00davalno"
    ],
    "name:cym_x_preferred":[
        "Uvalno"
    ],
    "name:deu_x_preferred":[
        "\u00davalno"
    ],
    "name:eng_x_preferred":[
        "\u00davalno"
    ],
    "name:epo_x_preferred":[
        "\u00davalno"
    ],
    "name:fas_x_preferred":[
        "\u0627\u0648\u0648\u0627\u0644\u0646\u0648"
    ],
    "name:fra_x_preferred":[
        "\u00davalno"
    ],
    "name:hun_x_preferred":[
        "\u00davalno"
    ],
    "name:ita_x_preferred":[
        "\u00davalno"
    ],
    "name:msa_x_preferred":[
        "\u00davalno"
    ],
    "name:nan_x_preferred":[
        "\u00davalno"
    ],
    "name:nld_x_preferred":[
        "\u00davalno"
    ],
    "name:pol_x_preferred":[
        "\u00davalno"
    ],
    "name:por_x_preferred":[
        "\u00davalno"
    ],
    "name:rup_x_preferred":[
        "\u00davalno"
    ],
    "name:rus_x_preferred":[
        "\u0423\u0432\u0430\u043b\u044c\u043d\u043e"
    ],
    "name:slk_x_preferred":[
        "\u00davalno"
    ],
    "name:srp_x_preferred":[
        "\u0423\u0432\u0430\u043b\u043d\u043e"
    ],
    "name:swe_x_preferred":[
        "\u00davalno"
    ],
    "name:unk_x_variant":[
        "Lobenstein"
    ],
    "name:vie_x_preferred":[
        "\u00davalno"
    ],
    "qs_pg:aaroncc":"CZ",
    "qs_pg:gn_country":"CZ",
    "qs_pg:gn_fcode":"PPL",
    "qs_pg:gn_pop":938,
    "qs_pg:name":"\u00davalno",
    "qs_pg:name_adm0":"\u010cesk\u00e1 republika",
    "qs_pg:name_adm1":"Moravskoslezsk\u00fd kraj",
    "qs_pg:photos_9k":1,
    "qs_pg:photos_9r":1,
    "qs_pg:photos_all":2,
    "qs_pg:photos_sr":0,
    "qs_pg:pop_sr":2,
    "qs_pg:qs_pg_placetype":"locality",
    "qs_pg:qs_pg_placetype_gp":"Town",
    "qs_pg:woe_adm0":23424810,
    "woe:adm0_id":23424810,
    "woe:name_adm0":"\u010cesk\u00e1 republika",
    "woe:name_adm1":"Moravskoslezsk\u00fd kraj",
    "woe:placetype":"Town",
    "wof:name":"\u00davalno",
    "wof:placetype":"locality",
    "wof:population":938
},
  "geometry": {"coordinates":[17.74473,50.04716],"type":"Point"}
}