{
  "type": "Feature",
  "properties": {
    "gn:admin1_code":"89",
    "gn:admin2_code":"0422",
    "gn:asciiname":"Zasada",
    "gn:cc2":"CZ",
    "gn:country_code":"CZ",
    "gn:dem":334,
    "gn:feature_class":"P",
    "gn:feature_code":"PPL",
    "gn:name":"Z\u00e1sada",
    "gn:population":0,
    "gn:timezone":"Europe/Prague",
    "iso:country":"CZ",
    "name:und_x_variant":[
        "Sosau",
        "Z\u00e1sada"
    ],
    "wof:name":"Zasada",
    "wof:placetype":"locality"
},
  "geometry": {"coordinates":[13.33333,50.43333],"type":"Point"}
}