{
  "type": "Feature",
  "properties": {
    "gn:gn_country":"CZ",
    "gn:gn_fcode":"PPL",
    "gn:gn_pop":92,
    "gn:population":92,
    "iso:country":"CZ",
    "name:azb_x_preferred":[
        "\u067e\u0648\u0644\u0634\u062a\u06cc"
    ],
    "name:ces_x_preferred":[
        "Pol\u0161t\u011b"
    ],
    "name:deu_x_preferred":[
        "Pol\u0161t\u011b"
    ],
    "name:eng_x_preferred":[
        "Pol\u0161t\u011b"
    ],
    "name:eus_x_preferred":[
        "Pol\u0161t\u011b"
    ],
    "name:fas_x_preferred":[
        "\u067e\u0648\u0644\u0634\u062a\u06cc"
    ],
    "name:fra_x_preferred":[
        "Pol\u0161t\u011b"
    ],
    "name:hun_x_preferred":[
        "Pol\u0161t\u011b"
    ],
    "name:ita_x_preferred":[
        "Pol\u0161t\u011b"
    ],
    "name:msa_x_preferred":[
        "Pol\u0161t\u011b"
    ],
    "name:nan_x_preferred":[
        "Pol\u0161t\u011b"
    ],
    "name:nld_x_preferred":[
        "Pol\u0161t\u011b"
    ],
    "name:pol_x_preferred":[
        "Pol\u0161t\u011b"
    ],
    "name:por_x_preferred":[
        "Pol\u0161t\u011b"
    ],
    "name:slk_x_preferred":[
        "Pol\u0161t\u011b"
    ],
    "name:spa_x_preferred":[
        "Pol\u0161t\u011b"
    ],
    "name:srp_x_preferred":[
        "\u041f\u043e\u043b\u0448\u0442\u0435"
    ],
    "name:vie_x_preferred":[
        "Pol\u0161t\u011b"
    ],
    "qs_pg:aaroncc":"CZ",
    "qs_pg:gn_country":"CZ",
    "qs_pg:gn_fcode":"PPL",
    "qs_pg:gn_pop":92,
    "qs_pg:name":"Pol\u0161t\u011b",
    "qs_pg:name_adm0":"\u010cesk\u00e1 republika",
    "qs_pg:name_adm1":"Jiho\u010desk\u00fd kraj",
    "qs_pg:photos_9r":0,
    "qs_pg:photos_sr":0,
    "qs_pg:pop_sr":1,
    "qs_pg:qs_pg_placetype":"locality",
    "qs_pg:qs_pg_placetype_gp":"Town",
    "qs_pg:woe_adm0":23424810,
    "woe:adm0_id":23424810,
    "woe:name_adm0":"\u010cesk\u00e1 republika",
    "woe:name_adm1":"Jiho\u010desk\u00fd kraj",
    "woe:placetype":"Town",
    "wof:name":"Pol\u0161t\u011b",
    "wof:placetype":"locality",
    "wof:population":92
},
  "geometry": {"coordinates":[14.92785,49.10638],"type":"Point"}
}