{
  "type": "Feature",
  "properties": {
    "gn:country":"CZ",
    "gn:fcode":"PPL",
    "gn:population":203,
    "iso:country":"CZ",
    "name:azb_x_preferred":[
        "\u0627\u0646\u062f\u06cc\u0644\u0633\u06a9\u0627 \u0647\u0648\u0631\u0627"
    ],
    "name:ceb_x_preferred":[
        "And\u011blska Hor\u00e1"
    ],
    "name:ces_x_preferred":[
        "And\u011blsk\u00e1 Hora"
    ],
    "name:deu_x_preferred":[
        "And\u011blsk\u00e1 Hora"
    ],
    "name:eng_x_preferred":[
        "And\u011blsk\u00e1 Hora"
    ],
    "name:epo_x_preferred":[
        "And\u011blsk\u00e1 Hora"
    ],
    "name:eus_x_preferred":[
        "And\u011blsk\u00e1 Hora"
    ],
    "name:fas_x_preferred":[
        "\u0627\u0646\u062f\u06cc\u0644\u0633\u06a9\u0627 \u0647\u0648\u0631\u0627"
    ],
    "name:fra_x_preferred":[
        "And\u011blsk\u00e1 Hora"
    ],
    "name:hun_x_preferred":[
        "And\u011blsk\u00e1 Hora"
    ],
    "name:ita_x_preferred":[
        "And\u011blsk\u00e1 Hora"
    ],
    "name:msa_x_preferred":[
        "And\u011blsk\u00e1 Hora"
    ],
    "name:nan_x_preferred":[
        "And\u011blsk\u00e1 Hora"
    ],
    "name:nld_x_preferred":[
        "And\u011blsk\u00e1 Hora"
    ],
    "name:oci_x_preferred":[
        "And\u011blsk\u00e1 Hora"
    ],
    "name:pol_x_preferred":[
        "And\u011blsk\u00e1 Hora"
    ],
    "name:por_x_preferred":[
        "And\u011blsk\u00e1 Hora"
    ],
    "name:rup_x_preferred":[
        "And\u011blsk\u00e1 Hora"
    ],
    "name:slk_x_preferred":[
        "And\u011blsk\u00e1 Hora"
    ],
    "name:spa_x_preferred":[
        "And\u011blsk\u00e1 Hora"
    ],
    "name:srp_x_preferred":[
        "\u0410\u043d\u0434\u0458\u0435\u043b\u0441\u043a\u0430 \u0425\u043e\u0440\u0430"
    ],
    "name:swe_x_preferred":[
        "And\u011blska Hor\u00e1"
    ],
    "name:und_x_variant":[
        "Engelhaus"
    ],
    "name:vie_x_preferred":[
        "And\u011blsk\u00e1 Hora"
    ],
    "qs_pg:aaroncc":"CZ",
    "qs_pg:gn_country":"CZ",
    "qs_pg:gn_fcode":"PPL",
    "qs_pg:gn_pop":203,
    "qs_pg:name":"And\u011blsk\u00e1 Hora",
    "qs_pg:name_adm0":"\u010cesk\u00e1 republika",
    "qs_pg:name_adm1":"Karlovarsk\u00fd kraj",
    "qs_pg:photos":25,
    "qs_pg:photos_1k":5,
    "qs_pg:photos_9k":1,
    "qs_pg:photos_9r":1,
    "qs_pg:photos_all":25,
    "qs_pg:photos_sr":1,
    "qs_pg:pop_sr":2,
    "qs_pg:qs_pg_placetype":"locality",
    "qs_pg:qs_pg_placetype_gp":"Town",
    "qs_pg:woe_adm0":23424810,
    "woe:adm0_id":23424810,
    "woe:name_adm0":"\u010cesk\u00e1 republika",
    "woe:name_adm1":"Karlovarsk\u00fd kraj",
    "woe:placetype":"Town",
    "wof:name":"And\u011blsk\u00e1 Hora",
    "wof:placetype":"locality",
    "wof:population":203
},
  "geometry": {"coordinates":[12.9628,50.20438],"type":"Point"}
}