{
  "type": "Feature",
  "properties": {
    "gn:country":"CZ",
    "gn:fcode":"PPL",
    "gn:population":489,
    "iso:country":"CZ",
    "name:azb_x_preferred":[
        "\u062a\u0686\u0627\u0644\u0648\u06cc\u06a9"
    ],
    "name:cat_x_preferred":[
        "T\u011bchlovice"
    ],
    "name:ceb_x_preferred":[
        "T\u011bchlovice"
    ],
    "name:ces_x_preferred":[
        "T\u011bchlovice"
    ],
    "name:che_x_preferred":[
        "\u0422\u0435\u0445\u043b\u043e\u0432\u0438\u0446\u0435"
    ],
    "name:deu_x_preferred":[
        "T\u011bchlovice nad Labem"
    ],
    "name:eng_x_preferred":[
        "T\u011bchlovice"
    ],
    "name:epo_x_preferred":[
        "T\u011bchlovice"
    ],
    "name:eus_x_preferred":[
        "T\u011bchlovice"
    ],
    "name:fas_x_preferred":[
        "\u062a\u0686\u0627\u0644\u0648\u06cc\u06a9"
    ],
    "name:fra_x_preferred":[
        "T\u011bchlovice"
    ],
    "name:gle_x_preferred":[
        "T\u011bchlovice"
    ],
    "name:hun_x_preferred":[
        "T\u011bchlovice"
    ],
    "name:ita_x_preferred":[
        "T\u011bchlovice"
    ],
    "name:lmo_x_preferred":[
        "T\u011bchlovice"
    ],
    "name:msa_x_preferred":[
        "T\u011bchlovice"
    ],
    "name:nan_x_preferred":[
        "T\u011bchlovice"
    ],
    "name:nld_x_preferred":[
        "T\u011bchlovice"
    ],
    "name:pol_x_preferred":[
        "T\u011bchlovice"
    ],
    "name:por_x_preferred":[
        "T\u011bchlovice"
    ],
    "name:rup_x_preferred":[
        "T\u011bchlovice"
    ],
    "name:rus_x_preferred":[
        "\u0422\u0435\u0445\u043b\u043e\u0432\u0438\u0446\u0435"
    ],
    "name:slk_x_preferred":[
        "T\u011bchlovice"
    ],
    "name:spa_x_preferred":[
        "T\u011bchlovice"
    ],
    "name:srp_x_preferred":[
        "\u0422\u0458\u0435\u0445\u043b\u043e\u0432\u0438\u0446\u0435"
    ],
    "name:swe_x_preferred":[
        "T\u011bchlovice"
    ],
    "name:tat_x_preferred":[
        "\u0422\u0435\u0445\u043b\u043e\u0432\u0438\u0446\u0435"
    ],
    "name:und_x_variant":[
        "Tichlowitz"
    ],
    "name:vie_x_preferred":[
        "T\u011bchlovice"
    ],
    "qs_pg:aaroncc":"CZ",
    "qs_pg:gn_country":"CZ",
    "qs_pg:gn_fcode":"PPL",
    "qs_pg:gn_pop":489,
    "qs_pg:name":"T\u011bchlovice",
    "qs_pg:name_adm0":"\u010cesk\u00e1 republika",
    "qs_pg:name_adm1":"\u00dasteck\u00fd kraj",
    "qs_pg:photos_9k":1,
    "qs_pg:photos_9r":1,
    "qs_pg:photos_all":1,
    "qs_pg:photos_sr":0,
    "qs_pg:pop_sr":2,
    "qs_pg:qs_pg_placetype":"locality",
    "qs_pg:qs_pg_placetype_gp":"Town",
    "qs_pg:woe_adm0":23424810,
    "woe:adm0_id":23424810,
    "woe:name_adm0":"\u010cesk\u00e1 republika",
    "woe:name_adm1":"\u00dasteck\u00fd kraj",
    "woe:placetype":"Town",
    "wof:name":"T\u011bchlovice",
    "wof:placetype":"locality",
    "wof:population":489
},
  "geometry": {"coordinates":[14.20492,50.69632],"type":"Point"}
}