{
  "type": "Feature",
  "properties": {
    "gn:admin1_code":"88.0",
    "gn:admin2_code":"020A",
    "gn:asciiname":"Solopysky",
    "gn:country_code":"CZ",
    "gn:dem":271,
    "gn:feature_class":"P",
    "gn:feature_code":"PPL",
    "gn:name":"Solopysky",
    "gn:population":0,
    "gn:timezone":"Europe/Prague",
    "iso:country":"CZ",
    "wof:name":"Solopysky",
    "wof:placetype":"locality"
},
  "geometry": {"coordinates":[14.29115,49.96237],"type":"Point"}
}