{
  "type": "Feature",
  "properties": {
    "gn:admin1_code":"81.0",
    "gn:admin2_code":"0412",
    "gn:asciiname":"Leno",
    "gn:country_code":"CZ",
    "gn:dem":779,
    "gn:feature_class":"P",
    "gn:feature_code":"PPL",
    "gn:name":"L\u00e9no",
    "gn:population":0,
    "gn:timezone":"Europe/Prague",
    "iso:country":"CZ",
    "name:und_x_variant":[
        "Holzbachlehen",
        "L\u00e9no"
    ],
    "wof:name":"Leno",
    "wof:placetype":"locality"
},
  "geometry": {"coordinates":[12.95507,50.36865],"type":"Point"}
}