{
  "type": "Feature",
  "properties": {
    "gn:admin1_code":"80.0",
    "gn:admin2_code":"0613",
    "gn:asciiname":"Krasolesi",
    "gn:country_code":"CZ",
    "gn:dem":531,
    "gn:feature_class":"P",
    "gn:feature_code":"PPL",
    "gn:name":"Krasoles\u00ed",
    "gn:population":0,
    "gn:timezone":"Europe/Prague",
    "iso:country":"CZ",
    "wof:name":"Krasolesi",
    "wof:placetype":"locality"
},
  "geometry": {"coordinates":[15.09788,49.54749],"type":"Point"}
}