{
  "type": "Feature",
  "properties": {
    "gn:admin1_code":"81.0",
    "gn:admin2_code":"0412",
    "gn:asciiname":"Maly Hlavakov",
    "gn:country_code":"CZ",
    "gn:dem":660,
    "gn:feature_class":"P",
    "gn:feature_code":"PPL",
    "gn:name":"Mal\u00fd Hlav\u00e1kov",
    "gn:population":0,
    "gn:timezone":"Europe/Prague",
    "iso:country":"CZ",
    "name:und_x_variant":[
        "Klein Lubigau",
        "Mal\u00fd Hlav\u00e1kov"
    ],
    "wof:name":"Maly Hlavakov",
    "wof:placetype":"locality"
},
  "geometry": {"coordinates":[13.20161,50.17369],"type":"Point"}
}