{
  "type": "Feature",
  "properties": {
    "gn:admin1_code":"79.0",
    "gn:admin2_code":"0315",
    "gn:asciiname":"Smedecek",
    "gn:country_code":"CZ",
    "gn:dem":642,
    "gn:feature_class":"P",
    "gn:feature_code":"PPL",
    "gn:name":"Sm\u011bde\u010dek",
    "gn:population":0,
    "gn:timezone":"Europe/Prague",
    "iso:country":"CZ",
    "name:und_x_variant":[
        "Klein Zmietsch",
        "Sm\u011bde\u010dek"
    ],
    "wof:name":"Smedecek",
    "wof:placetype":"locality"
},
  "geometry": {"coordinates":[14.1688,48.95201],"type":"Point"}
}