{
  "type": "Feature",
  "properties": {
    "gn:admin1_code":"87",
    "gn:admin2_code":"0322",
    "gn:asciiname":"Svihov",
    "gn:country_code":"CZ",
    "gn:dem":375,
    "gn:feature_class":"P",
    "gn:feature_code":"PPL",
    "gn:name":"\u0160vihov",
    "gn:population":1582,
    "gn:timezone":"Europe/Prague",
    "iso:country":"CZ",
    "name:cat_x_preferred":[
        "\u0160vihov"
    ],
    "name:ceb_x_preferred":[
        "\u0160vihov"
    ],
    "name:ces_x_preferred":[
        "\u0160vihov"
    ],
    "name:deu_x_preferred":[
        "Schwihau"
    ],
    "name:deu_x_variant":[
        "\u0160vihov u Klatov"
    ],
    "name:eus_x_preferred":[
        "\u0160vihov"
    ],
    "name:fas_x_preferred":[
        "\u0634\u0648\u06cc\u0647\u0648\u0641"
    ],
    "name:hun_x_preferred":[
        "\u0160vihov"
    ],
    "name:ita_x_preferred":[
        "\u0160vihov"
    ],
    "name:msa_x_preferred":[
        "\u0160vihov"
    ],
    "name:nld_x_preferred":[
        "\u0160vihov"
    ],
    "name:pol_x_preferred":[
        "\u0160vihov"
    ],
    "name:por_x_preferred":[
        "\u0160vihov"
    ],
    "name:rus_x_preferred":[
        "\u0428\u0432\u0438\u0433\u043e\u0432"
    ],
    "name:slk_x_preferred":[
        "\u0160vihov"
    ],
    "name:spa_x_preferred":[
        "\u0160vihov"
    ],
    "name:srp_x_preferred":[
        "\u0428\u0432\u0438\u0445\u043e\u0432"
    ],
    "name:swe_x_preferred":[
        "\u0160vihov"
    ],
    "name:vie_x_preferred":[
        "\u0160vihov"
    ],
    "name:zho_x_preferred":[
        "\u4ec0\u7dad\u970d\u592b"
    ],
    "wof:name":"Svihov",
    "wof:placetype":"locality",
    "wof:population":1582
},
  "geometry": {"coordinates":[13.28417,49.48136],"type":"Point"}
}