{
  "type": "Feature",
  "properties": {
    "gn:admin1_code":"84.0",
    "gn:admin2_code":"0715",
    "gn:asciiname":"Rejhotice",
    "gn:cc2":"CZ",
    "gn:country_code":"CZ",
    "gn:dem":516,
    "gn:feature_class":"P",
    "gn:feature_code":"PPL",
    "gn:name":"Rejhotice",
    "gn:population":0,
    "gn:timezone":"Europe/Prague",
    "iso:country":"CZ",
    "name:und_x_variant":[
        "Reutenhau"
    ],
    "wof:name":"Rejhotice",
    "wof:placetype":"locality"
},
  "geometry": {"coordinates":[17.09164,50.08832],"type":"Point"}
}