{
  "type": "Feature",
  "properties": {
    "gn:admin1_code":"79.0",
    "gn:admin2_code":"0315",
    "gn:asciiname":"Malovicky",
    "gn:country_code":"CZ",
    "gn:dem":412,
    "gn:feature_class":"P",
    "gn:feature_code":"PPL",
    "gn:name":"Malovi\u010dky",
    "gn:population":0,
    "gn:timezone":"Europe/Prague",
    "iso:country":"CZ",
    "wof:name":"Malovicky",
    "wof:placetype":"locality"
},
  "geometry": {"coordinates":[14.23321,49.09574],"type":"Point"}
}