{
  "type": "Feature",
  "properties": {
    "iso:country":"CZ",
    "name:ceb_x_preferred":[
        "\u010cesk\u00fd Brod"
    ],
    "name:ces_x_preferred":[
        "\u010cesk\u00fd Brod"
    ],
    "name:deu_x_preferred":[
        "\u010cesk\u00fd Brod"
    ],
    "name:epo_x_preferred":[
        "\u010cesk\u00fd Brod"
    ],
    "name:eus_x_preferred":[
        "\u010cesk\u00fd Brod"
    ],
    "name:fas_x_preferred":[
        "\u062a\u0634\u0633\u06a9\u06cc \u0628\u0631\u0648\u062f"
    ],
    "name:fra_x_preferred":[
        "\u010cesk\u00fd Brod"
    ],
    "name:hun_x_preferred":[
        "\u010cesk\u00fd Brod"
    ],
    "name:ita_x_preferred":[
        "\u010cesk\u00fd Brod"
    ],
    "name:lav_x_preferred":[
        "\u010ceski Broda"
    ],
    "name:msa_x_preferred":[
        "\u010cesk\u00fd Brod"
    ],
    "name:nld_x_preferred":[
        "\u010cesk\u00fd Brod"
    ],
    "name:pol_x_preferred":[
        "\u010cesk\u00fd Brod"
    ],
    "name:por_x_preferred":[
        "\u010cesk\u00fd Brod"
    ],
    "name:slk_x_preferred":[
        "\u010cesk\u00fd Brod"
    ],
    "name:spa_x_preferred":[
        "\u010cesk\u00fd Brod"
    ],
    "name:srp_x_preferred":[
        "\u0427\u0435\u0448\u043a\u0438 \u0411\u0440\u043e\u0434"
    ],
    "name:swe_x_preferred":[
        "\u010cesk\u00fd Brod"
    ],
    "name:szl_x_preferred":[
        "\u010cesk\u00fd Brod"
    ],
    "name:vie_x_preferred":[
        "\u010cesk\u00fd Brod"
    ],
    "name:zho_x_preferred":[
        "\u6377\u514b\u5e03\u7f85\u5fb7"
    ],
    "qs_pg:aaroncc":"CZ",
    "qs_pg:name":"\u010cesk\u00fd Brod",
    "qs_pg:name_adm0":"\u010cesk\u00e1 republika",
    "qs_pg:name_adm1":"St\u0159edo\u010desk\u00fd kraj",
    "qs_pg:photos":2,
    "qs_pg:photos_1k":1,
    "qs_pg:photos_9k":1,
    "qs_pg:photos_9r":4,
    "qs_pg:photos_all":221,
    "qs_pg:photos_sr":1,
    "qs_pg:pop_sr":0,
    "qs_pg:qs_pg_placetype":"localadmin",
    "qs_pg:qs_pg_placetype_gp":"LocalAdmin",
    "qs_pg:woe_adm0":23424810,
    "woe:adm0_id":23424810,
    "woe:name_adm0":"\u010cesk\u00e1 republika",
    "woe:name_adm1":"St\u0159edo\u010desk\u00fd kraj",
    "woe:placetype":"LocalAdmin",
    "wof:name":"\u010cesk\u00fd Brod",
    "wof:placetype":"localadmin"
},
  "geometry": {"coordinates":[14.857667,50.072619],"type":"Point"}
}