{
  "type": "Feature",
  "properties": {
    "iso:country":"CZ",
    "name:azb_x_preferred":[
        "\u062a\u06cc\u0633\u0627"
    ],
    "name:ceb_x_preferred":[
        "Tis\u00e1"
    ],
    "name:ces_x_preferred":[
        "Tis\u00e1"
    ],
    "name:deu_x_preferred":[
        "Tis\u00e1"
    ],
    "name:epo_x_preferred":[
        "Tis\u00e1"
    ],
    "name:eus_x_preferred":[
        "Tis\u00e1"
    ],
    "name:fas_x_preferred":[
        "\u062a\u06cc\u0633\u0627"
    ],
    "name:fra_x_preferred":[
        "Tis\u00e1"
    ],
    "name:hun_x_preferred":[
        "Tis\u00e1"
    ],
    "name:ita_x_preferred":[
        "Tis\u00e1"
    ],
    "name:msa_x_preferred":[
        "Tis\u00e1"
    ],
    "name:nld_x_preferred":[
        "Tis\u00e1"
    ],
    "name:pol_x_preferred":[
        "Tis\u00e1"
    ],
    "name:por_x_preferred":[
        "Velk\u00e9 B\u0159ezno"
    ],
    "name:slk_x_preferred":[
        "Tis\u00e1"
    ],
    "name:spa_x_preferred":[
        "Tis\u00e1"
    ],
    "name:srp_x_preferred":[
        "\u0422\u0438\u0441\u0430"
    ],
    "name:swe_x_preferred":[
        "Tis\u00e1"
    ],
    "name:vie_x_preferred":[
        "Tis\u00e1"
    ],
    "qs_pg:aaroncc":"CZ",
    "qs_pg:name":"Tis\u00e1",
    "qs_pg:name_adm0":"\u010cesk\u00e1 republika",
    "qs_pg:name_adm1":"\u00dasteck\u00fd kraj",
    "qs_pg:photos":87,
    "qs_pg:photos_1k":18,
    "qs_pg:photos_9k":2,
    "qs_pg:photos_9r":5,
    "qs_pg:photos_all":346,
    "qs_pg:photos_sr":3,
    "qs_pg:pop_sr":0,
    "qs_pg:qs_pg_placetype":"localadmin",
    "qs_pg:qs_pg_placetype_gp":"LocalAdmin",
    "qs_pg:woe_adm0":23424810,
    "woe:adm0_id":23424810,
    "woe:name_adm0":"\u010cesk\u00e1 republika",
    "woe:name_adm1":"\u00dasteck\u00fd kraj",
    "woe:placetype":"LocalAdmin",
    "wof:name":"Tis\u00e1",
    "wof:placetype":"localadmin"
},
  "geometry": {"coordinates":[14.034261,50.789117],"type":"Point"}
}