{
  "type": "Feature",
  "properties": {
    "gn:admin1_code":"86.0",
    "gn:admin2_code":"0531",
    "gn:asciiname":"Skuticko",
    "gn:country_code":"CZ",
    "gn:dem":365,
    "gn:feature_class":"P",
    "gn:feature_code":"PPL",
    "gn:name":"Skut\u00ed\u010dko",
    "gn:population":0,
    "gn:timezone":"Europe/Prague",
    "iso:country":"CZ",
    "wof:name":"Skuticko",
    "wof:placetype":"locality"
},
  "geometry": {"coordinates":[15.97299,49.85231],"type":"Point"}
}