{
  "type": "Feature",
  "properties": {
    "gn:admin1_code":"79.0",
    "gn:admin2_code":"0312",
    "gn:asciiname":"Slupenec",
    "gn:country_code":"CZ",
    "gn:dem":595,
    "gn:feature_class":"P",
    "gn:feature_code":"PPL",
    "gn:name":"Slupenec",
    "gn:population":0,
    "gn:timezone":"Europe/Prague",
    "iso:country":"CZ",
    "name:und_x_variant":[
        "Lupenz",
        "Slupenec"
    ],
    "wof:name":"Slupenec",
    "wof:placetype":"locality"
},
  "geometry": {"coordinates":[14.322,48.79372],"type":"Point"}
}