{
  "type": "Feature",
  "properties": {
    "gn:admin1_code":"86.0",
    "gn:admin2_code":"0532",
    "gn:asciiname":"Kladina",
    "gn:country_code":"CZ",
    "gn:dem":226,
    "gn:feature_class":"P",
    "gn:feature_code":"PPL",
    "gn:name":"Kladina",
    "gn:population":0,
    "gn:timezone":"Europe/Prague",
    "iso:country":"CZ",
    "wof:name":"Kladina",
    "wof:placetype":"locality"
},
  "geometry": {"coordinates":[15.87626,50.06177],"type":"Point"}
}