{
  "type": "Feature",
  "properties": {
    "gn:admin1_code":"84.0",
    "gn:admin2_code":"0714",
    "gn:asciiname":"Lazniky",
    "gn:country_code":"CZ",
    "gn:dem":296,
    "gn:feature_class":"P",
    "gn:feature_code":"PPL",
    "gn:name":"Lazn\u00edky",
    "gn:population":0,
    "gn:timezone":"Europe/Prague",
    "iso:country":"CZ",
    "wof:name":"Lazniky",
    "wof:placetype":"locality"
},
  "geometry": {"coordinates":[17.46483,49.52382],"type":"Point"}
}