{
  "type": "Feature",
  "properties": {
    "gn:admin1_code":"84.0",
    "gn:admin2_code":"0714",
    "gn:asciiname":"Lazniky",
    "gn:country_code":"CZ",
    "gn:dem":296,
    "gn:feature_class":"P",
    "gn:feature_code":"PPL",
    "gn:name":"Lazn\u00edky",
    "gn:population":0,
    "gn:timezone":"Europe/Prague",
    "iso:country":"CZ",
    "name:azb_x_preferred":[
        "\u0644\u0627\u0632\u0646\u06cc\u06a9\u06cc"
    ],
    "name:ces_x_preferred":[
        "Lazn\u00edky"
    ],
    "name:deu_x_preferred":[
        "Lazn\u00edky"
    ],
    "name:epo_x_preferred":[
        "Lazn\u00edky"
    ],
    "name:eus_x_preferred":[
        "Lazn\u00edky"
    ],
    "name:fas_x_preferred":[
        "\u0644\u0627\u0632\u0646\u06cc\u06a9\u06cc"
    ],
    "name:fra_x_preferred":[
        "Lazn\u00edky"
    ],
    "name:hun_x_preferred":[
        "Lazn\u00edky"
    ],
    "name:ita_x_preferred":[
        "Lazn\u00edky"
    ],
    "name:msa_x_preferred":[
        "Lazn\u00edky"
    ],
    "name:nld_x_preferred":[
        "Lazn\u00edky"
    ],
    "name:pol_x_preferred":[
        "Lazn\u00edky"
    ],
    "name:por_x_preferred":[
        "Lazn\u00edky"
    ],
    "name:slk_x_preferred":[
        "Lazn\u00edky"
    ],
    "name:spa_x_preferred":[
        "Lazn\u00edky"
    ],
    "name:srp_x_preferred":[
        "\u041b\u0430\u0437\u045a\u0438\u043a\u0438"
    ],
    "name:vie_x_preferred":[
        "Lazn\u00edky"
    ],
    "wof:name":"Lazniky",
    "wof:placetype":"locality"
},
  "geometry": {"coordinates":[17.46483,49.52382],"type":"Point"}
}