{
  "type": "Feature",
  "properties": {
    "gn:admin1_code":"85.0",
    "gn:admin2_code":"0801",
    "gn:asciiname":"Markvartice",
    "gn:country_code":"CZ",
    "gn:dem":478,
    "gn:feature_class":"P",
    "gn:feature_code":"PPL",
    "gn:name":"Markvartice",
    "gn:population":0,
    "gn:timezone":"Europe/Prague",
    "iso:country":"CZ",
    "name:und_x_variant":[
        "Markersdorf"
    ],
    "wof:name":"Markvartice",
    "wof:placetype":"locality"
},
  "geometry": {"coordinates":[17.47187000000001,50.05703],"type":"Point"}
}