{
  "type": "Feature",
  "properties": {
    "gn:admin1_code":"85.0",
    "gn:admin2_code":"0801",
    "gn:asciiname":"Markvartice",
    "gn:country_code":"CZ",
    "gn:dem":478,
    "gn:feature_class":"P",
    "gn:feature_code":"PPL",
    "gn:name":"Markvartice",
    "gn:population":0,
    "gn:timezone":"Europe/Prague",
    "iso:country":"CZ",
    "name:ceb_x_preferred":[
        "Markvartice"
    ],
    "name:ces_x_preferred":[
        "Markvartice"
    ],
    "name:deu_x_preferred":[
        "Markvartice"
    ],
    "name:epo_x_preferred":[
        "Markvartice"
    ],
    "name:fra_x_preferred":[
        "Markvartice"
    ],
    "name:ita_x_preferred":[
        "Markvartice"
    ],
    "name:nld_x_preferred":[
        "Markvartice"
    ],
    "name:pol_x_preferred":[
        "Markvartice"
    ],
    "name:slk_x_preferred":[
        "Markvartice"
    ],
    "name:srp_x_preferred":[
        "\u041c\u0430\u0440\u043a\u0432\u0430\u0440\u0442\u0438\u0446\u0435"
    ],
    "name:swe_x_preferred":[
        "Markvartice"
    ],
    "name:und_x_variant":[
        "Markersdorf"
    ],
    "wof:name":"Markvartice",
    "wof:placetype":"locality"
},
  "geometry": {"coordinates":[17.47187000000001,50.05703],"type":"Point"}
}