{
  "type": "Feature",
  "properties": {
    "gn:admin1_code":"83.0",
    "gn:admin2_code":"0513",
    "gn:asciiname":"Predlance",
    "gn:country_code":"CZ",
    "gn:dem":231,
    "gn:feature_class":"P",
    "gn:feature_code":"PPL",
    "gn:name":"P\u0159edl\u00e1nce",
    "gn:population":0,
    "gn:timezone":"Europe/Prague",
    "iso:country":"CZ",
    "name:und_x_variant":[
        "Priedlanz",
        "P\u0159edl\u00e1nce"
    ],
    "wof:name":"Predlance",
    "wof:placetype":"locality"
},
  "geometry": {"coordinates":[15.03555,50.97727],"type":"Point"}
}