{
  "type": "Feature",
  "properties": {
    "iso:country":"CZ",
    "wof:name":"Praha 15",
    "wof:placetype":"neighbourhood"
},
  "geometry": {"coordinates":[14.55661608822622,50.05667796615921],"type":"Point"}
}