{
  "type": "Feature",
  "properties": {
    "gn:gn_country":"CZ",
    "gn:gn_fcode":"PPL",
    "gn:gn_pop":457,
    "gn:population":457,
    "iso:country":"CZ",
    "name:bul_x_preferred":[
        "\u0412\u0430\u043b\u0447\u043e\u0432"
    ],
    "name:ces_x_preferred":[
        "Valchov"
    ],
    "name:deu_x_preferred":[
        "Valchov"
    ],
    "name:eng_x_preferred":[
        "Valchov"
    ],
    "name:fas_x_preferred":[
        "\u0648\u0627\u0644\u062e\u0648\u0648"
    ],
    "name:fra_x_preferred":[
        "Valchov"
    ],
    "name:hun_x_preferred":[
        "Valchov"
    ],
    "name:ita_x_preferred":[
        "Valchov"
    ],
    "name:msa_x_preferred":[
        "Valchov"
    ],
    "name:nld_x_preferred":[
        "Valchov"
    ],
    "name:por_x_preferred":[
        "Valchov"
    ],
    "name:slk_x_preferred":[
        "Valchov"
    ],
    "name:srp_x_preferred":[
        "\u0412\u0430\u043b\u0445\u043e\u0432"
    ],
    "name:swe_x_preferred":[
        "Valchov"
    ],
    "name:vie_x_preferred":[
        "Valchov"
    ],
    "qs_pg:aaroncc":"CZ",
    "qs_pg:gn_country":"CZ",
    "qs_pg:gn_fcode":"PPL",
    "qs_pg:gn_pop":457,
    "qs_pg:name":"Valchov",
    "qs_pg:name_adm0":"\u010cesk\u00e1 republika",
    "qs_pg:name_adm1":"Jihomoravsk\u00fd kraj",
    "qs_pg:photos_9k":1,
    "qs_pg:photos_9r":1,
    "qs_pg:photos_all":7,
    "qs_pg:photos_sr":0,
    "qs_pg:pop_sr":2,
    "qs_pg:qs_pg_placetype":"locality",
    "qs_pg:qs_pg_placetype_gp":"Town",
    "qs_pg:woe_adm0":23424810,
    "woe:adm0_id":23424810,
    "woe:name_adm0":"\u010cesk\u00e1 republika",
    "woe:name_adm1":"Jihomoravsk\u00fd kraj",
    "woe:placetype":"Town",
    "wof:name":"Valchov",
    "wof:placetype":"locality",
    "wof:population":457
},
  "geometry": {"coordinates":[16.71987,49.47018],"type":"Point"}
}