{
  "type": "Feature",
  "properties": {
    "gn:gn_country":"CZ",
    "gn:gn_fcode":"PPL",
    "gn:gn_pop":289,
    "gn:population":289,
    "iso:country":"CZ",
    "name:ces_x_preferred":[
        "Jet\u011btice"
    ],
    "name:deu_x_preferred":[
        "Jet\u011btice"
    ],
    "name:eng_x_preferred":[
        "Jet\u011btice"
    ],
    "name:epo_x_preferred":[
        "Jet\u011btice"
    ],
    "name:fas_x_preferred":[
        "\u06cc\u062a\u06cc\u062a\u06cc\u062a\u0633\u0647"
    ],
    "name:fra_x_preferred":[
        "Jet\u011btice"
    ],
    "name:hun_x_preferred":[
        "Jet\u011btice"
    ],
    "name:ita_x_preferred":[
        "Jet\u011btice"
    ],
    "name:msa_x_preferred":[
        "Jet\u011btice"
    ],
    "name:nan_x_preferred":[
        "Jet\u011btice"
    ],
    "name:nld_x_preferred":[
        "Jet\u011btice"
    ],
    "name:por_x_preferred":[
        "Jet\u011btice"
    ],
    "name:rup_x_preferred":[
        "Jet\u011btice"
    ],
    "name:slk_x_preferred":[
        "Jet\u011btice"
    ],
    "name:srp_x_preferred":[
        "\u0408\u0435\u0442\u0458\u0435\u0442\u0438\u0446\u0435"
    ],
    "name:swe_x_preferred":[
        "Jet\u011btice"
    ],
    "name:unk_x_variant":[
        "Jet\u011btitz"
    ],
    "name:vie_x_preferred":[
        "Jet\u011btice"
    ],
    "qs_pg:aaroncc":"CZ",
    "qs_pg:gn_country":"CZ",
    "qs_pg:gn_fcode":"PPL",
    "qs_pg:gn_pop":289,
    "qs_pg:name":"Jet\u011btice",
    "qs_pg:name_adm0":"\u010cesk\u00e1 republika",
    "qs_pg:name_adm1":"Jiho\u010desk\u00fd kraj",
    "qs_pg:photos_9r":0,
    "qs_pg:photos_sr":0,
    "qs_pg:pop_sr":2,
    "qs_pg:qs_pg_placetype":"locality",
    "qs_pg:qs_pg_placetype_gp":"Town",
    "qs_pg:woe_adm0":23424810,
    "woe:adm0_id":23424810,
    "woe:name_adm0":"\u010cesk\u00e1 republika",
    "woe:name_adm1":"Jiho\u010desk\u00fd kraj",
    "woe:placetype":"Town",
    "wof:name":"Jet\u011btice",
    "wof:placetype":"locality",
    "wof:population":289
},
  "geometry": {"coordinates":[14.29261,49.38595],"type":"Point"}
}