{
  "type": "Feature",
  "properties": {
    "iso:country":"CZ",
    "name:cze_x_preferred":[
        "\u0158epy"
    ],
    "name:dut_x_preferred":[
        "Praag 17-\u0158epy"
    ],
    "name:eng_x_preferred":[
        "\u0158epy"
    ],
    "name:fre_x_preferred":[
        "\u0158epy"
    ],
    "name:ger_x_preferred":[
        "Prag 17"
    ],
    "name:pol_x_preferred":[
        "\u0158epy"
    ],
    "name:slo_x_preferred":[
        "\u0158epy"
    ],
    "wof:name":"Repy",
    "wof:placetype":"neighbourhood"
},
  "geometry": {"coordinates":[14.30754873423992,50.06976476054985],"type":"Point"}
}