{
  "type": "Feature",
  "properties": {
    "iso:country":"CZ",
    "name:ces_x_preferred":[
        "\u0158epy"
    ],
    "name:deu_x_preferred":[
        "Prag 17"
    ],
    "name:deu_x_variant":[
        "\u0158epy"
    ],
    "name:eng_x_preferred":[
        "\u0158epy"
    ],
    "name:fra_x_preferred":[
        "\u0158epy"
    ],
    "name:nld_x_preferred":[
        "Praag 17-\u0158epy"
    ],
    "name:nld_x_variant":[
        "\u0158epy"
    ],
    "name:pol_x_preferred":[
        "\u0158epy"
    ],
    "name:slk_x_preferred":[
        "\u0158epy"
    ],
    "wof:name":"Repy",
    "wof:placetype":"neighbourhood"
},
  "geometry": {"coordinates":[14.307549,50.069765],"type":"Point"}
}