{
  "type": "Feature",
  "properties": {
    "gn:admin1_code":"87.0",
    "gn:admin2_code":"0325",
    "gn:asciiname":"Skupec",
    "gn:country_code":"CZ",
    "gn:dem":511,
    "gn:feature_class":"P",
    "gn:feature_code":"PPL",
    "gn:name":"Skupe\u010d",
    "gn:population":0,
    "gn:timezone":"Europe/Prague",
    "iso:country":"CZ",
    "name:und_x_variant":[
        "Skupsch"
    ],
    "wof:name":"Skupec",
    "wof:placetype":"locality"
},
  "geometry": {"coordinates":[13.10944,49.87119000000001],"type":"Point"}
}