{
  "type": "Feature",
  "properties": {
    "gn:gn_country":"CZ",
    "gn:gn_fcode":"PPL",
    "gn:gn_pop":230,
    "gn:population":230,
    "iso:country":"CZ",
    "name:cze_x_preferred":[
        "Vr\u0161ce"
    ],
    "name:dut_x_preferred":[
        "Vr\u0161ce"
    ],
    "name:eng_x_preferred":[
        "Vr\u0161ce"
    ],
    "name:fre_x_preferred":[
        "Vr\u0161ce"
    ],
    "name:hun_x_preferred":[
        "Vr\u0161ce"
    ],
    "name:ita_x_preferred":[
        "Vr\u0161ce"
    ],
    "name:may_x_preferred":[
        "Vr\u0161ce"
    ],
    "name:per_x_preferred":[
        "\u0648\u0631\u0634\u062a\u0633\u0647"
    ],
    "name:pol_x_preferred":[
        "Vr\u0161ce"
    ],
    "name:por_x_preferred":[
        "Vr\u0161ce"
    ],
    "name:slo_x_preferred":[
        "Vr\u0161ce"
    ],
    "name:srp_x_preferred":[
        "\u0412\u0440\u0448\u0446\u0435"
    ],
    "name:swe_x_preferred":[
        "Vr\u0161ce"
    ],
    "name:vie_x_preferred":[
        "Vr\u0161ce"
    ],
    "qs_pg:aaroncc":"CZ",
    "qs_pg:gn_country":"CZ",
    "qs_pg:gn_fcode":"PPL",
    "qs_pg:gn_pop":230,
    "qs_pg:name":"Vr\u0161ce",
    "qs_pg:name_adm0":"\u010cesk\u00e1 republika",
    "qs_pg:name_adm1":"Kr\u00e1lov\u00e9hradeck\u00fd kraj",
    "qs_pg:photos_9r":0,
    "qs_pg:photos_sr":0,
    "qs_pg:pop_sr":2,
    "qs_pg:qs_pg_placetype":"locality",
    "qs_pg:qs_pg_placetype_gp":"Town",
    "qs_pg:woe_adm0":23424810,
    "woe:adm0_id":23424810,
    "woe:name_adm0":"\u010cesk\u00e1 republika",
    "woe:name_adm1":"Kr\u00e1lov\u00e9hradeck\u00fd kraj",
    "woe:placetype":"Town",
    "wof:name":"Vr\u0161ce",
    "wof:placetype":"locality",
    "wof:population":230
},
  "geometry": {"coordinates":[15.32305,50.32385],"type":"Point"}
}