{
  "type": "Feature",
  "properties": {
    "gn:admin1_code":"81.0",
    "gn:admin2_code":"0412",
    "gn:asciiname":"Cesky Chloumek",
    "gn:country_code":"CZ",
    "gn:dem":707,
    "gn:feature_class":"P",
    "gn:feature_code":"PPL",
    "gn:name":"\u010cesk\u00fd Chloumek",
    "gn:population":0,
    "gn:timezone":"Europe/Prague",
    "iso:country":"CZ",
    "name:und_x_variant":[
        "B\u00f6hmisch Kilmes",
        "\u010cesk\u00fd Chloumek"
    ],
    "wof:name":"Cesky Chloumek",
    "wof:placetype":"locality"
},
  "geometry": {"coordinates":[12.94972,50.11417],"type":"Point"}
}