{
  "type": "Feature",
  "properties": {
    "gn:admin1_code":"78.0",
    "gn:admin2_code":"0625",
    "gn:asciiname":"Silnicna",
    "gn:country_code":"CZ",
    "gn:dem":248,
    "gn:feature_class":"P",
    "gn:feature_code":"PPL",
    "gn:name":"Silni\u010dn\u00e1",
    "gn:population":0,
    "gn:timezone":"Europe/Prague",
    "iso:country":"CZ",
    "wof:name":"Silnicna",
    "wof:placetype":"locality"
},
  "geometry": {"coordinates":[16.95404,49.05579],"type":"Point"}
}