{
  "type": "Feature",
  "properties": {
    "gn:gn_country":"CZ",
    "gn:gn_fcode":"PPL",
    "gn:gn_pop":423,
    "gn:population":423,
    "iso:country":"CZ",
    "name:ces_x_preferred":[
        "Kace\u0159ov"
    ],
    "name:deu_x_preferred":[
        "Kace\u0159ov u Kyn\u0161perka nad Oh\u0159\u00ed"
    ],
    "name:eng_x_preferred":[
        "Kace\u0159ov"
    ],
    "name:fas_x_preferred":[
        "\u06a9\u0627\u062a\u0633\u0631\u0648\u0641"
    ],
    "name:fra_x_preferred":[
        "Kace\u0159ov"
    ],
    "name:hun_x_preferred":[
        "Kace\u0159ov"
    ],
    "name:ita_x_preferred":[
        "Kace\u0159ov"
    ],
    "name:msa_x_preferred":[
        "Kace\u0159ov"
    ],
    "name:nld_x_preferred":[
        "Kace\u0159ov"
    ],
    "name:pol_x_preferred":[
        "Kace\u0159ov"
    ],
    "name:por_x_preferred":[
        "Kace\u0159ov"
    ],
    "name:rup_x_preferred":[
        "Kace\u0159ov"
    ],
    "name:slk_x_preferred":[
        "Kace\u0159ov"
    ],
    "name:srp_x_preferred":[
        "\u041a\u0430\u0446\u0435\u0440\u0436\u043e\u0432"
    ],
    "name:swe_x_preferred":[
        "Kace\u0159ov"
    ],
    "name:unk_x_variant":[
        "Katzengr\u00fcn"
    ],
    "name:vie_x_preferred":[
        "Kace\u0159ov"
    ],
    "qs_pg:aaroncc":"CZ",
    "qs_pg:gn_country":"CZ",
    "qs_pg:gn_fcode":"PPL",
    "qs_pg:gn_pop":423,
    "qs_pg:name":"Kace\u0159ov",
    "qs_pg:name_adm0":"\u010cesk\u00e1 republika",
    "qs_pg:name_adm1":"Karlovarsk\u00fd kraj",
    "qs_pg:photos_9r":0,
    "qs_pg:photos_sr":0,
    "qs_pg:pop_sr":2,
    "qs_pg:qs_pg_placetype":"locality",
    "qs_pg:qs_pg_placetype_gp":"Town",
    "qs_pg:woe_adm0":23424810,
    "woe:adm0_id":23424810,
    "woe:name_adm0":"\u010cesk\u00e1 republika",
    "woe:name_adm1":"Karlovarsk\u00fd kraj",
    "woe:placetype":"Town",
    "wof:name":"Kace\u0159ov",
    "wof:placetype":"locality",
    "wof:population":423
},
  "geometry": {"coordinates":[12.50429,50.14893],"type":"Point"}
}