{
  "type": "Feature",
  "properties": {
    "gn:gn_country":"CZ",
    "gn:gn_fcode":"PPL",
    "gn:gn_pop":441,
    "gn:population":441,
    "iso:country":"CZ",
    "name:azb_x_preferred":[
        "\u0633\u0648\u06cc\u0648\u0648\u06cc\u062a\u0633\u0647"
    ],
    "name:ceb_x_preferred":[
        "Sojovice"
    ],
    "name:ces_x_preferred":[
        "Sojovice"
    ],
    "name:eng_x_preferred":[
        "Sojovice"
    ],
    "name:eus_x_preferred":[
        "Sojovice"
    ],
    "name:fas_x_preferred":[
        "\u0633\u0648\u06cc\u0648\u0648\u06cc\u062a\u0633\u0647"
    ],
    "name:fra_x_preferred":[
        "Sojovice"
    ],
    "name:hun_x_preferred":[
        "Sojovice"
    ],
    "name:ita_x_preferred":[
        "Sojovice"
    ],
    "name:msa_x_preferred":[
        "Sojovice"
    ],
    "name:nan_x_preferred":[
        "Sojovice"
    ],
    "name:nld_x_preferred":[
        "Sojovice"
    ],
    "name:pol_x_preferred":[
        "Sojovice"
    ],
    "name:por_x_preferred":[
        "Sojovice"
    ],
    "name:slk_x_preferred":[
        "Sojovice"
    ],
    "name:spa_x_preferred":[
        "Sojovice"
    ],
    "name:srp_x_preferred":[
        "\u0421\u043e\u0458\u043e\u0432\u0438\u0446\u0435"
    ],
    "name:swe_x_preferred":[
        "Sojovice"
    ],
    "name:vie_x_preferred":[
        "Sojovice"
    ],
    "qs_pg:aaroncc":"CZ",
    "qs_pg:gn_country":"CZ",
    "qs_pg:gn_fcode":"PPL",
    "qs_pg:gn_pop":441,
    "qs_pg:name":"Sojovice",
    "qs_pg:name_adm0":"\u010cesk\u00e1 republika",
    "qs_pg:name_adm1":"St\u0159edo\u010desk\u00fd kraj",
    "qs_pg:photos_9r":0,
    "qs_pg:photos_sr":0,
    "qs_pg:pop_sr":2,
    "qs_pg:qs_pg_placetype":"locality",
    "qs_pg:qs_pg_placetype_gp":"Town",
    "qs_pg:woe_adm0":23424810,
    "woe:adm0_id":23424810,
    "woe:name_adm0":"\u010cesk\u00e1 republika",
    "woe:name_adm1":"St\u0159edo\u010desk\u00fd kraj",
    "woe:placetype":"Town",
    "wof:name":"Sojovice",
    "wof:placetype":"locality",
    "wof:population":441
},
  "geometry": {"coordinates":[14.76199,50.22226],"type":"Point"}
}