{
  "type": "Feature",
  "properties": {
    "gn:admin1_code":"87.0",
    "gn:admin2_code":"0325",
    "gn:asciiname":"Budec",
    "gn:country_code":"CZ",
    "gn:dem":575,
    "gn:feature_class":"P",
    "gn:feature_code":"PPL",
    "gn:name":"Bude\u010d",
    "gn:population":0,
    "gn:timezone":"Europe/Prague",
    "iso:country":"CZ",
    "name:und_x_variant":[
        "Wutsch",
        "Bude\u010d"
    ],
    "wof:name":"Budec",
    "wof:placetype":"locality"
},
  "geometry": {"coordinates":[13.09235,49.90204],"type":"Point"}
}