{
  "type": "Feature",
  "properties": {
    "gn:gn_country":"CZ",
    "gn:gn_fcode":"PPL",
    "gn:gn_pop":308,
    "gn:population":308,
    "iso:country":"CZ",
    "name:cze_x_preferred":[
        "\u0160ele\u0161ovice"
    ],
    "name:dut_x_preferred":[
        "\u0160ele\u0161ovice"
    ],
    "name:eng_x_preferred":[
        "\u0160ele\u0161ovice"
    ],
    "name:fre_x_preferred":[
        "\u0160ele\u0161ovice"
    ],
    "name:ger_x_preferred":[
        "\u0160ele\u0161ovice"
    ],
    "name:hun_x_preferred":[
        "\u0160ele\u0161ovice"
    ],
    "name:ita_x_preferred":[
        "\u0160ele\u0161ovice"
    ],
    "name:may_x_preferred":[
        "\u0160ele\u0161ovice"
    ],
    "name:nan_x_preferred":[
        "\u0160ele\u0161ovice"
    ],
    "name:per_x_preferred":[
        "\u0634\u0644\u0634\u0648\u0648\u06cc\u062a\u0633\u0647"
    ],
    "name:pol_x_preferred":[
        "\u0160ele\u0161ovice"
    ],
    "name:por_x_preferred":[
        "\u0160ele\u0161ovice"
    ],
    "name:rup_x_preferred":[
        "\u0160ele\u0161ovice"
    ],
    "name:slo_x_preferred":[
        "\u0160ele\u0161ovice"
    ],
    "name:srp_x_preferred":[
        "\u0428\u0435\u043b\u0435\u0448\u043e\u0432\u0438\u0446\u0435"
    ],
    "name:swe_x_preferred":[
        "\u0160ele\u0161ovice"
    ],
    "name:vie_x_preferred":[
        "\u0160ele\u0161ovice"
    ],
    "qs_pg:aaroncc":"CZ",
    "qs_pg:gn_country":"CZ",
    "qs_pg:gn_fcode":"PPL",
    "qs_pg:gn_pop":308,
    "qs_pg:name":"\u0160ele\u0161ovice",
    "qs_pg:name_adm0":"\u010cesk\u00e1 republika",
    "qs_pg:name_adm1":"Zl\u00ednsk\u00fd kraj",
    "qs_pg:photos_9r":0,
    "qs_pg:photos_sr":0,
    "qs_pg:pop_sr":2,
    "qs_pg:qs_pg_placetype":"locality",
    "qs_pg:qs_pg_placetype_gp":"Town",
    "qs_pg:woe_adm0":23424810,
    "woe:adm0_id":23424810,
    "woe:name_adm0":"\u010cesk\u00e1 republika",
    "woe:name_adm1":"Zl\u00ednsk\u00fd kraj",
    "woe:placetype":"Town",
    "wof:name":"\u0160ele\u0161ovice",
    "wof:placetype":"locality",
    "wof:population":308
},
  "geometry": {"coordinates":[17.36002,49.25478],"type":"Point"}
}