{
  "type": "Feature",
  "properties": {
    "iso:country":"CZ",
    "name:ceb_x_preferred":[
        "Vr\u00e1\u017e"
    ],
    "name:ces_x_preferred":[
        "Vr\u00e1\u017e"
    ],
    "name:deu_x_preferred":[
        "Vr\u00e1\u017e"
    ],
    "name:epo_x_preferred":[
        "Vr\u00e1\u017e"
    ],
    "name:fra_x_preferred":[
        "Vr\u00e1\u017e"
    ],
    "name:ita_x_preferred":[
        "Vr\u00e1\u017e"
    ],
    "name:nld_x_preferred":[
        "Vraz"
    ],
    "name:oci_x_preferred":[
        "Vr\u00e1\u017e"
    ],
    "name:slk_x_preferred":[
        "Vr\u00e1\u017e"
    ],
    "name:srp_x_preferred":[
        "\u0412\u0440\u0430\u0436"
    ],
    "name:swe_x_preferred":[
        "Vr\u00e1\u017e"
    ],
    "qs_pg:aaroncc":"CZ",
    "qs_pg:name":"Vr\u00e1\u017e",
    "qs_pg:name_adm0":"\u010cesk\u00e1 republika",
    "qs_pg:name_adm1":"St\u0159edo\u010desk\u00fd kraj",
    "qs_pg:photos":1,
    "qs_pg:photos_1k":1,
    "qs_pg:photos_9k":1,
    "qs_pg:photos_9r":1,
    "qs_pg:photos_all":10,
    "qs_pg:photos_sr":1,
    "qs_pg:pop_sr":0,
    "qs_pg:qs_pg_placetype":"localadmin",
    "qs_pg:qs_pg_placetype_gp":"LocalAdmin",
    "qs_pg:woe_adm0":23424810,
    "woe:adm0_id":23424810,
    "woe:name_adm0":"\u010cesk\u00e1 republika",
    "woe:name_adm1":"St\u0159edo\u010desk\u00fd kraj",
    "woe:placetype":"LocalAdmin",
    "wof:name":"Vr\u00e1\u017e",
    "wof:placetype":"localadmin"
},
  "geometry": {"coordinates":[14.137065,49.971511],"type":"Point"}
}