{
  "type": "Feature",
  "properties": {
    "gn:country":"CZ",
    "gn:fcode":"PPL",
    "gn:population":1578,
    "iso:country":"CZ",
    "name:bul_x_preferred":[
        "\u0427\u043e\u0442\u043e\u0432\u0438\u043d\u0439"
    ],
    "name:cat_x_preferred":[
        "Chotoviny"
    ],
    "name:ceb_x_preferred":[
        "Chotoviny"
    ],
    "name:ces_x_preferred":[
        "Chotoviny"
    ],
    "name:che_x_preferred":[
        "\u0425\u043e\u0442\u043e\u0432\u0438\u043d\u0438"
    ],
    "name:deu_x_preferred":[
        "Chotoviny"
    ],
    "name:eng_x_preferred":[
        "Chotoviny"
    ],
    "name:epo_x_preferred":[
        "Chotoviny"
    ],
    "name:eus_x_preferred":[
        "Chotoviny"
    ],
    "name:fas_x_preferred":[
        "\u062e\u0648\u062a\u0648\u0648\u06cc\u0646\u06cc"
    ],
    "name:fra_x_preferred":[
        "Chotoviny"
    ],
    "name:gle_x_preferred":[
        "Chotoviny"
    ],
    "name:hun_x_preferred":[
        "Chotoviny"
    ],
    "name:ind_x_preferred":[
        "Chotoviny"
    ],
    "name:ita_x_preferred":[
        "Chotoviny"
    ],
    "name:lmo_x_preferred":[
        "Chotoviny"
    ],
    "name:msa_x_preferred":[
        "Chotoviny"
    ],
    "name:nan_x_preferred":[
        "Chotoviny"
    ],
    "name:nld_x_preferred":[
        "Chotoviny"
    ],
    "name:pol_x_preferred":[
        "Chotoviny"
    ],
    "name:por_x_preferred":[
        "Chotoviny"
    ],
    "name:slk_x_preferred":[
        "Chotoviny"
    ],
    "name:spa_x_preferred":[
        "Chotoviny"
    ],
    "name:srp_x_preferred":[
        "\u0425\u043e\u0442\u043e\u0432\u0438\u043d\u0438"
    ],
    "name:swe_x_preferred":[
        "Chotoviny"
    ],
    "name:tat_x_preferred":[
        "\u0425\u043e\u0442\u043e\u0432\u0438\u043d\u0438"
    ],
    "name:uzb_x_preferred":[
        "Chotoviny"
    ],
    "name:vie_x_preferred":[
        "Chotoviny"
    ],
    "qs_pg:aaroncc":"CZ",
    "qs_pg:gn_country":"CZ",
    "qs_pg:gn_fcode":"PPL",
    "qs_pg:gn_pop":1578,
    "qs_pg:name":"Chotoviny",
    "qs_pg:name_adm0":"\u010cesk\u00e1 republika",
    "qs_pg:name_adm1":"Jiho\u010desk\u00fd kraj",
    "qs_pg:photos_9k":1,
    "qs_pg:photos_9r":1,
    "qs_pg:photos_all":1,
    "qs_pg:photos_sr":0,
    "qs_pg:pop_sr":3,
    "qs_pg:qs_pg_placetype":"locality",
    "qs_pg:qs_pg_placetype_gp":"Town",
    "qs_pg:woe_adm0":23424810,
    "woe:adm0_id":23424810,
    "woe:name_adm0":"\u010cesk\u00e1 republika",
    "woe:name_adm1":"Jiho\u010desk\u00fd kraj",
    "woe:placetype":"Town",
    "wof:name":"Chotoviny",
    "wof:placetype":"locality",
    "wof:population":1578
},
  "geometry": {"coordinates":[14.67695,49.47803],"type":"Point"}
}