{
  "type": "Feature",
  "properties": {
    "gn:admin1_code":"80.0",
    "gn:admin2_code":"0614",
    "gn:asciiname":"Lipnik",
    "gn:country_code":"CZ",
    "gn:dem":480,
    "gn:feature_class":"P",
    "gn:feature_code":"PPL",
    "gn:name":"Lipn\u00edk",
    "gn:population":332,
    "gn:timezone":"Europe/Prague",
    "iso:country":"CZ",
    "wof:name":"Lipnik",
    "wof:placetype":"locality",
    "wof:population":332
},
  "geometry": {"coordinates":[15.95062,49.14426],"type":"Point"}
}