{
  "type": "Feature",
  "properties": {
    "gn:admin1_code":"80.0",
    "gn:admin2_code":"0614",
    "gn:asciiname":"Lipnik",
    "gn:country_code":"CZ",
    "gn:dem":480,
    "gn:feature_class":"P",
    "gn:feature_code":"PPL",
    "gn:name":"Lipn\u00edk",
    "gn:population":332,
    "gn:timezone":"Europe/Prague",
    "iso:country":"CZ",
    "name:azb_x_preferred":[
        "\u0644\u06cc\u067e\u0646\u06cc\u06a9"
    ],
    "name:ceb_x_preferred":[
        "Lipn\u00edk"
    ],
    "name:ces_x_preferred":[
        "Lipn\u00edk"
    ],
    "name:eus_x_preferred":[
        "Lipn\u00edk"
    ],
    "name:fas_x_preferred":[
        "\u0644\u06cc\u067e\u0646\u06cc\u06a9"
    ],
    "name:hun_x_preferred":[
        "Lipn\u00edk"
    ],
    "name:ita_x_preferred":[
        "Lipn\u00edk"
    ],
    "name:msa_x_preferred":[
        "Lipn\u00edk"
    ],
    "name:nld_x_preferred":[
        "Lipn\u00edk"
    ],
    "name:por_x_preferred":[
        "Lipn\u00edk"
    ],
    "name:slk_x_preferred":[
        "Lipn\u00edk"
    ],
    "name:spa_x_preferred":[
        "Lipn\u00edk"
    ],
    "name:vie_x_preferred":[
        "Lipn\u00edk"
    ],
    "wof:name":"Lipnik",
    "wof:placetype":"locality",
    "wof:population":332
},
  "geometry": {"coordinates":[15.95062,49.14426],"type":"Point"}
}