{
  "type": "Feature",
  "properties": {
    "gn:admin1_code":"84",
    "gn:admin2_code":"0712",
    "gn:asciiname":"Uncovice",
    "gn:country_code":"CZ",
    "gn:dem":234,
    "gn:feature_class":"P",
    "gn:feature_code":"PPL",
    "gn:name":"Un\u010dovice",
    "gn:population":0,
    "gn:timezone":"Europe/Prague",
    "iso:country":"CZ",
    "wof:name":"Uncovice",
    "wof:placetype":"locality"
},
  "geometry": {"coordinates":[17.10607000000001,49.66631],"type":"Point"}
}