{
  "type": "Feature",
  "properties": {
    "gn:admin1_code":"79.0",
    "gn:admin2_code":"0317",
    "gn:asciiname":"Padarov",
    "gn:country_code":"CZ",
    "gn:dem":513,
    "gn:feature_class":"P",
    "gn:feature_code":"PPL",
    "gn:name":"Pada\u0159ov",
    "gn:population":0,
    "gn:timezone":"Europe/Prague",
    "iso:country":"CZ",
    "wof:name":"Padarov",
    "wof:placetype":"locality"
},
  "geometry": {"coordinates":[14.52556,49.4525],"type":"Point"}
}