{
  "type": "Feature",
  "properties": {
    "gn:admin1_code":"82",
    "gn:admin2_code":"0525",
    "gn:asciiname":"Sylvarov",
    "gn:country_code":"CZ",
    "gn:dem":305,
    "gn:feature_class":"P",
    "gn:feature_code":"PPL",
    "gn:name":"Sylv\u00e1rov",
    "gn:population":0,
    "gn:timezone":"Europe/Prague",
    "iso:country":"CZ",
    "name:und_x_variant":[
        "Silwarleut",
        "Sylv\u00e1rov"
    ],
    "wof:name":"Sylvarov",
    "wof:placetype":"locality"
},
  "geometry": {"coordinates":[15.80922,50.4122],"type":"Point"}
}