{
  "type": "Feature",
  "properties": {
    "gn:gn_country":"CZ",
    "gn:gn_fcode":"PPL",
    "gn:gn_pop":1278,
    "gn:population":1278,
    "iso:country":"CZ",
    "name:ces_x_preferred":[
        "Doln\u00ed Stud\u00e9nky"
    ],
    "name:deu_x_preferred":[
        "Doln\u00ed Stud\u00e9nky"
    ],
    "name:eng_x_preferred":[
        "Doln\u00ed Stud\u00e9nky"
    ],
    "name:fas_x_preferred":[
        "\u062f\u0648\u0644\u0646\u06cc \u0633\u062a\u0648\u062f\u0646\u06a9\u06cc"
    ],
    "name:fra_x_preferred":[
        "Doln\u00ed Stud\u00e9nky"
    ],
    "name:hun_x_preferred":[
        "Doln\u00ed Stud\u00e9nky"
    ],
    "name:ita_x_preferred":[
        "Doln\u00ed Stud\u00e9nky"
    ],
    "name:msa_x_preferred":[
        "Doln\u00ed Stud\u00e9nky"
    ],
    "name:nld_x_preferred":[
        "Doln\u00ed Stud\u00e9nky"
    ],
    "name:pol_x_preferred":[
        "Doln\u00ed Stud\u00e9nky"
    ],
    "name:por_x_preferred":[
        "Doln\u00ed Stud\u00e9nky"
    ],
    "name:rup_x_preferred":[
        "Doln\u00ed Stud\u00e9nky"
    ],
    "name:slk_x_preferred":[
        "Doln\u00ed Stud\u00e9nky"
    ],
    "name:slv_x_preferred":[
        "Doln\u00ed Stud\u00e9nky"
    ],
    "name:srp_x_preferred":[
        "\u0414\u043e\u043b\u045a\u0438 \u0421\u0442\u0443\u0434\u0435\u043d\u043a\u0438"
    ],
    "name:swe_x_preferred":[
        "Doln\u00ed Stud\u00e9nky"
    ],
    "name:unk_x_variant":[
        "Sch\u00f6nbrunn"
    ],
    "name:vie_x_preferred":[
        "Doln\u00ed Stud\u00e9nky"
    ],
    "qs_pg:aaroncc":"CZ",
    "qs_pg:gn_country":"CZ",
    "qs_pg:gn_fcode":"PPL",
    "qs_pg:gn_pop":1278,
    "qs_pg:name":"Doln\u00ed Stud\u00e9nky",
    "qs_pg:name_adm0":"\u010cesk\u00e1 republika",
    "qs_pg:name_adm1":"Olomouck\u00fd kraj",
    "qs_pg:photos_9r":0,
    "qs_pg:photos_sr":0,
    "qs_pg:pop_sr":3,
    "qs_pg:qs_pg_placetype":"locality",
    "qs_pg:qs_pg_placetype_gp":"Town",
    "qs_pg:woe_adm0":23424810,
    "woe:adm0_id":23424810,
    "woe:name_adm0":"\u010cesk\u00e1 republika",
    "woe:name_adm1":"Olomouck\u00fd kraj",
    "woe:placetype":"Town",
    "wof:name":"Doln\u00ed Stud\u00e9nky",
    "wof:placetype":"locality",
    "wof:population":1278
},
  "geometry": {"coordinates":[16.97107,49.93506],"type":"Point"}
}