{
  "type": "Feature",
  "properties": {
    "gn:admin1_code":"89.0",
    "gn:admin2_code":"0423",
    "gn:asciiname":"Hostenice",
    "gn:country_code":"CZ",
    "gn:dem":158,
    "gn:feature_class":"P",
    "gn:feature_code":"PPL",
    "gn:name":"Host\u011bnice",
    "gn:population":0,
    "gn:timezone":"Europe/Prague",
    "iso:country":"CZ",
    "name:und_x_variant":[
        "Hostenitz",
        "Host\u011bnice"
    ],
    "wof:name":"Hostenice",
    "wof:placetype":"locality"
},
  "geometry": {"coordinates":[14.14886,50.43271],"type":"Point"}
}