{
  "type": "Feature",
  "properties": {
    "gn:admin1_code":"83.0",
    "gn:admin2_code":"0514",
    "gn:asciiname":"Frantiskov",
    "gn:country_code":"CZ",
    "gn:dem":669,
    "gn:feature_class":"P",
    "gn:feature_code":"PPL",
    "gn:name":"Franti\u0161kov",
    "gn:population":0,
    "gn:timezone":"Europe/Prague",
    "iso:country":"CZ",
    "name:und_x_variant":[
        "Franzenthal",
        "Franti\u0161kov"
    ],
    "wof:name":"Frantiskov",
    "wof:placetype":"locality"
},
  "geometry": {"coordinates":[15.48071,50.7161],"type":"Point"}
}