{
  "type": "Feature",
  "properties": {
    "gn:gn_country":"CZ",
    "gn:gn_fcode":"PPL",
    "gn:gn_pop":821,
    "gn:population":821,
    "iso:country":"CZ",
    "name:cze_x_preferred":[
        "Vesel\u00ed\u010dko"
    ],
    "name:deu_x_preferred":[
        "Vesel\u00ed\u010dko u Lipn\u00edka nad Be\u010dvou"
    ],
    "name:dut_x_preferred":[
        "Vesel\u00ed\u010dko"
    ],
    "name:eng_x_preferred":[
        "Vesel\u00ed\u010dko"
    ],
    "name:fre_x_preferred":[
        "Vesel\u00ed\u010dko"
    ],
    "name:ger_x_preferred":[
        "Vesel\u00ed\u010dko u Lipn\u00edka nad Be\u010dvou"
    ],
    "name:hun_x_preferred":[
        "Vesel\u00ed\u010dko"
    ],
    "name:ita_x_preferred":[
        "Vesel\u00ed\u010dko"
    ],
    "name:may_x_preferred":[
        "Vesel\u00ed\u010dko"
    ],
    "name:per_x_preferred":[
        "\u0648\u0633\u0644\u06cc\u062a\u0634\u06a9\u0648"
    ],
    "name:pol_x_preferred":[
        "Vesel\u00ed\u010dko"
    ],
    "name:por_x_preferred":[
        "Vesel\u00ed\u010dko"
    ],
    "name:rup_x_preferred":[
        "Vesel\u00ed\u010dko"
    ],
    "name:slo_x_preferred":[
        "Vesel\u00ed\u010dko"
    ],
    "name:srp_x_preferred":[
        "\u0412\u0435\u0441\u0435\u043b\u0438\u0447\u043a\u043e"
    ],
    "name:swe_x_preferred":[
        "Vesel\u00edcko"
    ],
    "name:unk_x_variant":[
        "Weselitschko"
    ],
    "name:vie_x_preferred":[
        "Vesel\u00ed\u010dko"
    ],
    "qs_pg:aaroncc":"CZ",
    "qs_pg:gn_country":"CZ",
    "qs_pg:gn_fcode":"PPL",
    "qs_pg:gn_pop":821,
    "qs_pg:name":"Vesel\u00ed\u010dko",
    "qs_pg:name_adm0":"\u010cesk\u00e1 republika",
    "qs_pg:name_adm1":"Olomouck\u00fd kraj",
    "qs_pg:photos_9r":0,
    "qs_pg:photos_sr":0,
    "qs_pg:pop_sr":2,
    "qs_pg:qs_pg_placetype":"locality",
    "qs_pg:qs_pg_placetype_gp":"Town",
    "qs_pg:woe_adm0":23424810,
    "woe:adm0_id":23424810,
    "woe:name_adm0":"\u010cesk\u00e1 republika",
    "woe:name_adm1":"Olomouck\u00fd kraj",
    "woe:placetype":"Town",
    "wof:name":"Vesel\u00ed\u010dko",
    "wof:placetype":"locality",
    "wof:population":821
},
  "geometry": {"coordinates":[17.50302,49.52961],"type":"Point"}
}