{
  "type": "Feature",
  "properties": {
    "gn:admin1_code":"85.0",
    "gn:admin2_code":"0802",
    "gn:asciiname":"Oldrichovice",
    "gn:country_code":"CZ",
    "gn:dem":387,
    "gn:feature_class":"P",
    "gn:feature_code":"PPL",
    "gn:name":"Old\u0159ichovice",
    "gn:population":0,
    "gn:timezone":"Europe/Prague",
    "iso:country":"CZ",
    "name:ces_x_preferred":[
        "Old\u0159ichovice"
    ],
    "name:deu_x_preferred":[
        "Old\u0159ichovice"
    ],
    "name:pol_x_preferred":[
        "Oldrzychowice"
    ],
    "name:und_x_variant":[
        "Old\u0159ichovice"
    ],
    "wof:name":"Oldrichovice",
    "wof:placetype":"locality"
},
  "geometry": {"coordinates":[18.63751,49.64739],"type":"Point"}
}