{
  "type": "Feature",
  "properties": {
    "gn:admin1_code":"86.0",
    "gn:admin2_code":"0531",
    "gn:asciiname":"Lhotka",
    "gn:country_code":"CZ",
    "gn:dem":412,
    "gn:feature_class":"P",
    "gn:feature_code":"PPL",
    "gn:name":"Lhotka",
    "gn:population":0,
    "gn:timezone":"Europe/Prague",
    "iso:country":"CZ",
    "name:und_x_variant":[
        "Dv\u016dr Lhotka",
        "Lhotka"
    ],
    "wof:name":"Lhotka",
    "wof:placetype":"locality"
},
  "geometry": {"coordinates":[15.59333,49.85354],"type":"Point"}
}