{
  "type": "Feature",
  "properties": {
    "gn:gn_country":"CZ",
    "gn:gn_fcode":"PPL",
    "gn:gn_pop":318,
    "gn:population":318,
    "iso:country":"CZ",
    "name:cze_x_preferred":[
        "\u010c\u00e1stkov"
    ],
    "name:dut_x_preferred":[
        "\u010c\u00e1stkov"
    ],
    "name:eng_x_preferred":[
        "\u010c\u00e1stkov"
    ],
    "name:fre_x_preferred":[
        "\u010c\u00e1stkov"
    ],
    "name:ger_x_preferred":[
        "\u010c\u00e1stkov u Tachova"
    ],
    "name:hun_x_preferred":[
        "\u010c\u00e1stkov"
    ],
    "name:ita_x_preferred":[
        "\u010c\u00e1stkov"
    ],
    "name:may_x_preferred":[
        "\u010c\u00e1stkov"
    ],
    "name:nan_x_preferred":[
        "\u010c\u00e1stkov"
    ],
    "name:per_x_preferred":[
        "\u062a\u0634\u0627\u0633\u062a\u06a9\u0648\u0641"
    ],
    "name:pol_x_preferred":[
        "\u010c\u00e1stkov"
    ],
    "name:por_x_preferred":[
        "\u010c\u00e1stkov"
    ],
    "name:rup_x_preferred":[
        "\u010c\u00e1stkov"
    ],
    "name:slo_x_preferred":[
        "\u010c\u00e1stkov"
    ],
    "name:srp_x_preferred":[
        "\u0427\u0430\u0441\u0442\u043a\u043e\u0432"
    ],
    "name:unk_x_variant":[
        "Schossenreith"
    ],
    "name:vie_x_preferred":[
        "\u010c\u00e1stkov"
    ],
    "qs_pg:aaroncc":"CZ",
    "qs_pg:gn_country":"CZ",
    "qs_pg:gn_fcode":"PPL",
    "qs_pg:gn_pop":318,
    "qs_pg:name":"\u010c\u00e1stkov",
    "qs_pg:name_adm0":"\u010cesk\u00e1 republika",
    "qs_pg:name_adm1":"Plze\u0148sk\u00fd kraj",
    "qs_pg:photos_9r":0,
    "qs_pg:photos_sr":0,
    "qs_pg:pop_sr":2,
    "qs_pg:qs_pg_placetype":"locality",
    "qs_pg:qs_pg_placetype_gp":"Town",
    "qs_pg:woe_adm0":23424810,
    "woe:adm0_id":23424810,
    "woe:name_adm0":"\u010cesk\u00e1 republika",
    "woe:name_adm1":"Plze\u0148sk\u00fd kraj",
    "woe:placetype":"Town",
    "wof:name":"\u010c\u00e1stkov",
    "wof:placetype":"locality",
    "wof:population":318
},
  "geometry": {"coordinates":[12.67369,49.75596],"type":"Point"}
}