{
  "type": "Feature",
  "properties": {
    "gn:admin1_code":"87.0",
    "gn:admin2_code":"0322",
    "gn:asciiname":"Oldrichovice",
    "gn:country_code":"CZ",
    "gn:dem":661,
    "gn:feature_class":"P",
    "gn:feature_code":"PPL",
    "gn:name":"Old\u0159ichovice",
    "gn:population":0,
    "gn:timezone":"Europe/Prague",
    "iso:country":"CZ",
    "name:und_x_variant":[
        "Olchowitz",
        "Old\u0159ichovice"
    ],
    "wof:name":"Oldrichovice",
    "wof:placetype":"locality"
},
  "geometry": {"coordinates":[13.21667,49.26667],"type":"Point"}
}