{
  "type": "Feature",
  "properties": {
    "gn:admin1_code":"80.0",
    "gn:admin2_code":"0611",
    "gn:asciiname":"Modletin",
    "gn:country_code":"CZ",
    "gn:dem":598,
    "gn:feature_class":"P",
    "gn:feature_code":"PPL",
    "gn:name":"Modlet\u00edn",
    "gn:population":0,
    "gn:timezone":"Europe/Prague",
    "iso:country":"CZ",
    "wof:name":"Modletin",
    "wof:placetype":"locality"
},
  "geometry": {"coordinates":[15.71259,49.79184],"type":"Point"}
}