{
  "type": "Feature",
  "properties": {
    "gn:admin1_code":"85.0",
    "gn:admin2_code":"0803",
    "gn:asciiname":"Prostredni Bludovice",
    "gn:country_code":"CZ",
    "gn:dem":334,
    "gn:feature_class":"P",
    "gn:feature_code":"PPL",
    "gn:name":"Prost\u0159edn\u00ed Bludovice",
    "gn:population":0,
    "gn:timezone":"Europe/Prague",
    "iso:country":"CZ",
    "name:und_x_variant":[
        "Mittel-Bludowitz",
        "Prost\u0159edn\u00ed Bludovice"
    ],
    "wof:name":"Prostredni Bludovice",
    "wof:placetype":"locality"
},
  "geometry": {"coordinates":[18.46408,49.75901],"type":"Point"}
}