{
  "type": "Feature",
  "properties": {
    "gn:gn_country":"CZ",
    "gn:gn_fcode":"PPL",
    "gn:gn_pop":274,
    "gn:population":274,
    "iso:country":"CZ",
    "name:cze_x_preferred":[
        "Ctin\u011bves"
    ],
    "name:dut_x_preferred":[
        "Ctin\u011bves"
    ],
    "name:eng_x_preferred":[
        "Ctin\u011bves"
    ],
    "name:epo_x_preferred":[
        "Ctin\u011bves"
    ],
    "name:fre_x_preferred":[
        "Ctin\u011bves"
    ],
    "name:hun_x_preferred":[
        "Ctin\u011bves"
    ],
    "name:ita_x_preferred":[
        "Ctin\u011bves"
    ],
    "name:may_x_preferred":[
        "Ctin\u011bves"
    ],
    "name:per_x_preferred":[
        "\u062a\u0633\u062a\u06cc\u0646\u06cc\u0648\u0633"
    ],
    "name:pol_x_preferred":[
        "Ctin\u011bves"
    ],
    "name:por_x_preferred":[
        "Ctin\u011bves"
    ],
    "name:rup_x_preferred":[
        "Ctin\u011bves"
    ],
    "name:slo_x_preferred":[
        "Ctin\u011bves"
    ],
    "name:srp_x_preferred":[
        "\u0426\u0442\u0438\u045a\u0435\u0432\u0435\u0441"
    ],
    "name:swe_x_preferred":[
        "Ctin\u011bves"
    ],
    "name:vie_x_preferred":[
        "Ctin\u011bves"
    ],
    "qs_pg:aaroncc":"CZ",
    "qs_pg:gn_country":"CZ",
    "qs_pg:gn_fcode":"PPL",
    "qs_pg:gn_pop":274,
    "qs_pg:name":"Ctin\u011bves",
    "qs_pg:name_adm0":"\u010cesk\u00e1 republika",
    "qs_pg:name_adm1":"\u00dasteck\u00fd kraj",
    "qs_pg:photos_9k":1,
    "qs_pg:photos_9r":1,
    "qs_pg:photos_all":2,
    "qs_pg:photos_sr":0,
    "qs_pg:pop_sr":2,
    "qs_pg:qs_pg_placetype":"locality",
    "qs_pg:qs_pg_placetype_gp":"Town",
    "qs_pg:woe_adm0":23424810,
    "woe:adm0_id":23424810,
    "woe:name_adm0":"\u010cesk\u00e1 republika",
    "woe:name_adm1":"\u00dasteck\u00fd kraj",
    "woe:placetype":"Town",
    "wof:name":"Ctin\u011bves",
    "wof:placetype":"locality",
    "wof:population":274
},
  "geometry": {"coordinates":[14.30711,50.3747],"type":"Point"}
}