{
  "type": "Feature",
  "properties": {
    "gn:admin1_code":"87.0",
    "gn:admin2_code":"0327",
    "gn:asciiname":"Polesi",
    "gn:country_code":"CZ",
    "gn:dem":586,
    "gn:feature_class":"P",
    "gn:feature_code":"PPL",
    "gn:name":"Poles\u00ed",
    "gn:population":0,
    "gn:timezone":"Europe/Prague",
    "iso:country":"CZ",
    "name:und_x_variant":[
        "Cirk",
        "Poles\u00ed"
    ],
    "wof:name":"Polesi",
    "wof:placetype":"locality"
},
  "geometry": {"coordinates":[12.55008,49.66758],"type":"Point"}
}