{
  "type": "Feature",
  "properties": {
    "gn:gn_country":"CZ",
    "gn:gn_fcode":"PPL",
    "gn:gn_pop":361,
    "gn:population":361,
    "iso:country":"CZ",
    "name:azb_x_preferred":[
        "\u062a\u0634\u0646\u06a9\u0648\u0648"
    ],
    "name:ceb_x_preferred":[
        "\u010cenkov"
    ],
    "name:ces_x_preferred":[
        "\u010cenkov"
    ],
    "name:eng_x_preferred":[
        "\u010cenkov"
    ],
    "name:eus_x_preferred":[
        "\u010cenkov"
    ],
    "name:fas_x_preferred":[
        "\u062a\u0634\u0646\u06a9\u0648\u0648"
    ],
    "name:fra_x_preferred":[
        "\u010cenkov"
    ],
    "name:hrv_x_preferred":[
        "\u010cenkov"
    ],
    "name:hun_x_preferred":[
        "\u010cenkov"
    ],
    "name:ita_x_preferred":[
        "\u010cenkov"
    ],
    "name:msa_x_preferred":[
        "\u010cenkov"
    ],
    "name:nan_x_preferred":[
        "\u010cenkov"
    ],
    "name:nld_x_preferred":[
        "\u010cenkov"
    ],
    "name:pol_x_preferred":[
        "\u010cenkov"
    ],
    "name:por_x_preferred":[
        "\u010cenkov"
    ],
    "name:slk_x_preferred":[
        "\u010cenkov"
    ],
    "name:spa_x_preferred":[
        "\u010cenkov"
    ],
    "name:srp_x_preferred":[
        "\u0427\u0435\u043d\u043a\u043e\u0432"
    ],
    "name:swe_x_preferred":[
        "\u010cenkov"
    ],
    "name:vie_x_preferred":[
        "\u010cenkov"
    ],
    "qs_pg:aaroncc":"CZ",
    "qs_pg:gn_country":"CZ",
    "qs_pg:gn_fcode":"PPL",
    "qs_pg:gn_pop":361,
    "qs_pg:name":"\u010cenkov",
    "qs_pg:photos_9r":0,
    "qs_pg:photos_sr":0,
    "qs_pg:pop_sr":2,
    "qs_pg:qs_pg_placetype":"locality",
    "wof:name":"\u010cenkov",
    "wof:placetype":"locality",
    "wof:population":361
},
  "geometry": {"coordinates":[14.00075,49.7777],"type":"Point"}
}