{
  "type": "Feature",
  "properties": {
    "gn:gn_country":"CZ",
    "gn:gn_fcode":"PPL",
    "gn:gn_pop":193,
    "gn:population":193,
    "iso:country":"CZ",
    "name:ces_x_preferred":[
        "B\u00edl\u00fd K\u00e1men"
    ],
    "name:deu_x_preferred":[
        "B\u00edl\u00fd K\u00e1men"
    ],
    "name:eng_x_preferred":[
        "B\u00edl\u00fd K\u00e1men"
    ],
    "name:epo_x_preferred":[
        "B\u00edl\u00fd K\u00e1men"
    ],
    "name:fas_x_preferred":[
        "\u0628\u06cc\u0644\u06cc \u06a9\u0627\u0645\u0646"
    ],
    "name:fra_x_preferred":[
        "B\u00edl\u00fd K\u00e1men"
    ],
    "name:hun_x_preferred":[
        "B\u00edl\u00fd K\u00e1men"
    ],
    "name:ita_x_preferred":[
        "B\u00edl\u00fd K\u00e1men"
    ],
    "name:msa_x_preferred":[
        "B\u00edl\u00fd K\u00e1men"
    ],
    "name:nan_x_preferred":[
        "B\u00edl\u00fd K\u00e1men"
    ],
    "name:nld_x_preferred":[
        "B\u00edl\u00fd K\u00e1men"
    ],
    "name:pol_x_preferred":[
        "B\u00edl\u00fd K\u00e1men"
    ],
    "name:por_x_preferred":[
        "B\u00edl\u00fd K\u00e1men"
    ],
    "name:rup_x_preferred":[
        "B\u00edl\u00fd K\u00e1men"
    ],
    "name:slk_x_preferred":[
        "B\u00edl\u00fd K\u00e1men"
    ],
    "name:srp_x_preferred":[
        "\u0411\u0438\u043b\u0438 \u041a\u0430\u043c\u0435\u043d"
    ],
    "name:swe_x_preferred":[
        "B\u00edl\u00fd K\u00e1men"
    ],
    "name:unk_x_variant":[
        "Weissenstein"
    ],
    "name:vie_x_preferred":[
        "B\u00edl\u00fd K\u00e1men"
    ],
    "qs_pg:aaroncc":"CZ",
    "qs_pg:gn_country":"CZ",
    "qs_pg:gn_fcode":"PPL",
    "qs_pg:gn_pop":193,
    "qs_pg:name":"B\u00edl\u00fd K\u00e1men",
    "qs_pg:name_adm0":"\u010cesk\u00e1 republika",
    "qs_pg:name_adm1":"Kraj Vyso\u010dina",
    "qs_pg:photos_9r":0,
    "qs_pg:photos_sr":0,
    "qs_pg:pop_sr":1,
    "qs_pg:qs_pg_placetype":"locality",
    "qs_pg:qs_pg_placetype_gp":"Town",
    "qs_pg:woe_adm0":23424810,
    "woe:adm0_id":23424810,
    "woe:name_adm0":"\u010cesk\u00e1 republika",
    "woe:name_adm1":"Kraj Vyso\u010dina",
    "woe:placetype":"Town",
    "wof:name":"B\u00edl\u00fd K\u00e1men",
    "wof:placetype":"locality",
    "wof:population":193
},
  "geometry": {"coordinates":[15.50883,49.43624],"type":"Point"}
}