{
  "type": "Feature",
  "properties": {
    "gn:admin1_code":"87.0",
    "gn:admin2_code":"0327",
    "gn:asciiname":"Kosov",
    "gn:country_code":"CZ",
    "gn:dem":526,
    "gn:feature_class":"P",
    "gn:feature_code":"PPL",
    "gn:name":"Kosov",
    "gn:population":0,
    "gn:timezone":"Europe/Prague",
    "iso:country":"CZ",
    "name:und_x_variant":[
        "Gossau",
        "Kosov"
    ],
    "wof:name":"Kosov",
    "wof:placetype":"locality"
},
  "geometry": {"coordinates":[12.83201,49.70316],"type":"Point"}
}