{
  "type": "Feature",
  "properties": {
    "gn:admin1_code":"87.0",
    "gn:admin2_code":"0327",
    "gn:asciiname":"Kosov",
    "gn:country_code":"CZ",
    "gn:dem":526,
    "gn:feature_class":"P",
    "gn:feature_code":"PPL",
    "gn:name":"Kosov",
    "gn:population":0,
    "gn:timezone":"Europe/Prague",
    "iso:country":"CZ",
    "name:ceb_x_preferred":[
        "Kosov"
    ],
    "name:ces_x_preferred":[
        "Kosov"
    ],
    "name:deu_x_preferred":[
        "Kosov"
    ],
    "name:rus_x_preferred":[
        "\u041a\u043e\u0441\u043e\u0432"
    ],
    "name:srp_x_preferred":[
        "\u041a\u043e\u0441\u043e\u0432"
    ],
    "name:swe_x_preferred":[
        "Kosov"
    ],
    "name:und_x_variant":[
        "Gossau"
    ],
    "name:vep_x_preferred":[
        "Kosov"
    ],
    "wof:name":"Kosov",
    "wof:placetype":"locality"
},
  "geometry": {"coordinates":[12.83201,49.70316],"type":"Point"}
}