{
  "type": "Feature",
  "properties": {
    "gn:admin1_code":"85",
    "gn:admin2_code":"0803",
    "gn:asciiname":"Zablati",
    "gn:country_code":"CZ",
    "gn:dem":241,
    "gn:feature_class":"P",
    "gn:feature_code":"PPL",
    "gn:name":"Z\u00e1blat\u00ed",
    "gn:population":0,
    "gn:timezone":"Europe/Prague",
    "iso:country":"CZ",
    "name:und_x_variant":[
        "Z\u00e1blat\u00ed"
    ],
    "wof:name":"Zablati",
    "wof:placetype":"locality"
},
  "geometry": {"coordinates":[18.37096,49.88321],"type":"Point"}
}