{
  "type": "Feature",
  "properties": {
    "gn:admin1_code":"87",
    "gn:admin2_code":"0327",
    "gn:asciiname":"Stan",
    "gn:country_code":"CZ",
    "gn:dem":573,
    "gn:feature_class":"P",
    "gn:feature_code":"PPL",
    "gn:name":"Stan",
    "gn:population":0,
    "gn:timezone":"Europe/Prague",
    "iso:country":"CZ",
    "name:und_x_variant":[
        "Gstom"
    ],
    "wof:name":"Stan",
    "wof:placetype":"locality"
},
  "geometry": {"coordinates":[12.84525,49.86621],"type":"Point"}
}