{
  "type": "Feature",
  "properties": {
    "iso:country":"CZ",
    "name:ceb_x_preferred":[
        "Bakov nad Jizerou"
    ],
    "name:ces_x_preferred":[
        "Bakov nad Jizerou"
    ],
    "name:deu_x_preferred":[
        "Bakov nad Jizerou"
    ],
    "name:eus_x_preferred":[
        "Bakov nad Jizerou"
    ],
    "name:fas_x_preferred":[
        "\u0628\u0627\u06a9\u0648\u0641 \u0646\u0627\u062f \u06cc\u06cc\u0632\u0631\u0648\u0648"
    ],
    "name:fra_x_preferred":[
        "Bakov nad Jizerou"
    ],
    "name:hun_x_preferred":[
        "Bakov nad Jizerou"
    ],
    "name:ita_x_preferred":[
        "Bakov nad Jizerou"
    ],
    "name:lav_x_preferred":[
        "Bakova pie Jizeras"
    ],
    "name:msa_x_preferred":[
        "Bakov nad Jizerou"
    ],
    "name:nld_x_preferred":[
        "Bakov nad Jizerou"
    ],
    "name:pol_x_preferred":[
        "Bakov nad Jizerou"
    ],
    "name:por_x_preferred":[
        "Bakov nad Jizerou"
    ],
    "name:rus_x_preferred":[
        "\u0411\u0430\u043a\u043e\u0432-\u043d\u0430\u0434-\u0419\u0438\u0437\u0435\u0440\u043e\u0443"
    ],
    "name:slk_x_preferred":[
        "Bakov nad Jizerou"
    ],
    "name:spa_x_preferred":[
        "Bakov nad Jizerou"
    ],
    "name:srp_x_preferred":[
        "\u0411\u0430\u043a\u043e\u0432 \u043d\u0430 \u0408\u0438\u0437\u0435\u0440\u0438"
    ],
    "name:swe_x_preferred":[
        "Bakov nad Jizerou"
    ],
    "name:vie_x_preferred":[
        "Bakov nad Jizerou"
    ],
    "name:zho_x_preferred":[
        "\u4f0a\u6fa4\u62c9\u6cb3\u7554\u5df4\u79d1\u592b"
    ],
    "qs_pg:aaroncc":"CZ",
    "qs_pg:name":"Bakov nad Jizerou",
    "qs_pg:name_adm0":"\u010cesk\u00e1 republika",
    "qs_pg:name_adm1":"St\u0159edo\u010desk\u00fd kraj",
    "qs_pg:photos":1,
    "qs_pg:photos_1k":1,
    "qs_pg:photos_9k":1,
    "qs_pg:photos_9r":3,
    "qs_pg:photos_all":106,
    "qs_pg:photos_sr":1,
    "qs_pg:pop_sr":0,
    "qs_pg:qs_pg_placetype":"localadmin",
    "qs_pg:qs_pg_placetype_gp":"LocalAdmin",
    "qs_pg:woe_adm0":23424810,
    "woe:adm0_id":23424810,
    "woe:name_adm0":"\u010cesk\u00e1 republika",
    "woe:name_adm1":"St\u0159edo\u010desk\u00fd kraj",
    "woe:placetype":"LocalAdmin",
    "wof:name":"Bakov nad Jizerou",
    "wof:placetype":"localadmin"
},
  "geometry": {"coordinates":[14.919948,50.484954],"type":"Point"}
}