{
  "type": "Feature",
  "properties": {
    "gn:admin1_code":"88.0",
    "gn:admin2_code":"020B",
    "gn:asciiname":"Leletice",
    "gn:country_code":"CZ",
    "gn:dem":579,
    "gn:feature_class":"P",
    "gn:feature_code":"PPL",
    "gn:name":"Leletice",
    "gn:population":0,
    "gn:timezone":"Europe/Prague",
    "iso:country":"CZ",
    "wof:name":"Leletice",
    "wof:placetype":"locality"
},
  "geometry": {"coordinates":[13.84154,49.52518],"type":"Point"}
}