{
  "type": "Feature",
  "properties": {
    "gn:country":"CZ",
    "gn:fcode":"PPL",
    "gn:population":604,
    "iso:country":"CZ",
    "name:azb_x_preferred":[
        "\u0645\u0627\u0646\u06a9\u0648\u0648\u06cc\u062a\u0633\u0647"
    ],
    "name:ceb_x_preferred":[
        "Mankovice"
    ],
    "name:ces_x_preferred":[
        "Mankovice"
    ],
    "name:deu_x_preferred":[
        "Mankovice"
    ],
    "name:eng_x_preferred":[
        "Mankovice"
    ],
    "name:eus_x_preferred":[
        "Mankovice"
    ],
    "name:fas_x_preferred":[
        "\u0645\u0627\u0646\u06a9\u0648\u0648\u06cc\u062a\u0633\u0647"
    ],
    "name:fra_x_preferred":[
        "Mankovice"
    ],
    "name:hun_x_preferred":[
        "Mankovice"
    ],
    "name:ita_x_preferred":[
        "Mankovice"
    ],
    "name:jpn_x_preferred":[
        "\u30de\u30f3\u30b3\u30f4\u30a3\u30c4\u30a7"
    ],
    "name:msa_x_preferred":[
        "Mankovice"
    ],
    "name:nan_x_preferred":[
        "Mankovice"
    ],
    "name:nld_x_preferred":[
        "Mankovice"
    ],
    "name:pol_x_preferred":[
        "Mankovice"
    ],
    "name:por_x_preferred":[
        "Mankovice"
    ],
    "name:slk_x_preferred":[
        "Mankovice"
    ],
    "name:spa_x_preferred":[
        "Mankovice"
    ],
    "name:srp_x_preferred":[
        "\u041c\u0430\u043d\u043a\u043e\u0432\u0438\u0446\u0435"
    ],
    "name:swe_x_preferred":[
        "Mankovice"
    ],
    "name:und_x_variant":[
        "Mankendorf"
    ],
    "name:vie_x_preferred":[
        "Mankovice"
    ],
    "qs_pg:aaroncc":"CZ",
    "qs_pg:gn_country":"CZ",
    "qs_pg:gn_fcode":"PPL",
    "qs_pg:gn_pop":604,
    "qs_pg:name":"Mankovice",
    "qs_pg:name_adm0":"\u010cesk\u00e1 republika",
    "qs_pg:name_adm1":"Moravskoslezsk\u00fd kraj",
    "qs_pg:photos_9k":1,
    "qs_pg:photos_9r":1,
    "qs_pg:photos_all":2,
    "qs_pg:photos_sr":0,
    "qs_pg:pop_sr":2,
    "qs_pg:qs_pg_placetype":"locality",
    "qs_pg:qs_pg_placetype_gp":"Town",
    "qs_pg:woe_adm0":23424810,
    "woe:adm0_id":23424810,
    "woe:name_adm0":"\u010cesk\u00e1 republika",
    "woe:name_adm1":"Moravskoslezsk\u00fd kraj",
    "woe:placetype":"Town",
    "wof:name":"Mankovice",
    "wof:placetype":"locality",
    "wof:population":604
},
  "geometry": {"coordinates":[17.88014,49.63746],"type":"Point"}
}