{
  "type": "Feature",
  "properties": {
    "gn:gn_country":"CZ",
    "gn:gn_fcode":"PPL",
    "gn:gn_pop":953,
    "gn:population":953,
    "iso:country":"CZ",
    "name:cze_x_preferred":[
        "C\u00edtoliby"
    ],
    "name:dut_x_preferred":[
        "C\u00edtoliby"
    ],
    "name:eng_x_preferred":[
        "C\u00edtoliby"
    ],
    "name:fre_x_preferred":[
        "C\u00edtoliby"
    ],
    "name:ger_x_preferred":[
        "C\u00edtoliby"
    ],
    "name:hun_x_preferred":[
        "C\u00edtoliby"
    ],
    "name:ita_x_preferred":[
        "C\u00edtoliby"
    ],
    "name:may_x_preferred":[
        "C\u00edtoliby"
    ],
    "name:per_x_preferred":[
        "\u062a\u0633\u06cc\u062a\u0648\u0644\u06cc\u0628\u06cc"
    ],
    "name:por_x_preferred":[
        "C\u00edtoliby"
    ],
    "name:rup_x_preferred":[
        "C\u00edtoliby"
    ],
    "name:slo_x_preferred":[
        "C\u00edtoliby"
    ],
    "name:srp_x_preferred":[
        "\u0426\u0438\u0442\u043e\u043b\u0438\u0431\u0438"
    ],
    "name:swe_x_preferred":[
        "C\u00edtoliby"
    ],
    "name:unk_x_variant":[
        "Zittolib"
    ],
    "name:vie_x_preferred":[
        "C\u00edtoliby"
    ],
    "qs_pg:aaroncc":"CZ",
    "qs_pg:gn_country":"CZ",
    "qs_pg:gn_fcode":"PPL",
    "qs_pg:gn_pop":953,
    "qs_pg:name":"C\u00edtoliby",
    "qs_pg:name_adm0":"\u010cesk\u00e1 republika",
    "qs_pg:name_adm1":"\u00dasteck\u00fd kraj",
    "qs_pg:photos_9k":1,
    "qs_pg:photos_9r":1,
    "qs_pg:photos_all":1,
    "qs_pg:photos_sr":0,
    "qs_pg:pop_sr":2,
    "qs_pg:qs_pg_placetype":"locality",
    "qs_pg:qs_pg_placetype_gp":"Town",
    "qs_pg:woe_adm0":23424810,
    "woe:adm0_id":23424810,
    "woe:name_adm0":"\u010cesk\u00e1 republika",
    "woe:name_adm1":"\u00dasteck\u00fd kraj",
    "woe:placetype":"Town",
    "wof:name":"C\u00edtoliby",
    "wof:placetype":"locality",
    "wof:population":953
},
  "geometry": {"coordinates":[13.81214,50.33273],"type":"Point"}
}