{
  "type": "Feature",
  "properties": {
    "gn:country":"CZ",
    "gn:fcode":"PPL",
    "gn:population":953,
    "iso:country":"CZ",
    "name:azb_x_preferred":[
        "\u062a\u0633\u06cc\u062a\u0648\u0644\u06cc\u0628\u06cc"
    ],
    "name:bul_x_preferred":[
        "\u0426\u0438\u0442\u043e\u043b\u0438\u0431\u0438"
    ],
    "name:cat_x_preferred":[
        "C\u00edtoliby"
    ],
    "name:ceb_x_preferred":[
        "C\u00edtoliby"
    ],
    "name:ces_x_preferred":[
        "C\u00edtoliby"
    ],
    "name:dan_x_preferred":[
        "C\u00edtoliby"
    ],
    "name:deu_x_preferred":[
        "C\u00edtoliby"
    ],
    "name:eng_x_preferred":[
        "C\u00edtoliby"
    ],
    "name:epo_x_preferred":[
        "C\u00edtoliby"
    ],
    "name:est_x_preferred":[
        "M\u011bstys C\u00edtoliby"
    ],
    "name:eus_x_preferred":[
        "C\u00edtoliby"
    ],
    "name:fas_x_preferred":[
        "\u062a\u0633\u06cc\u062a\u0648\u0644\u06cc\u0628\u06cc"
    ],
    "name:fra_x_preferred":[
        "C\u00edtoliby"
    ],
    "name:gle_x_preferred":[
        "C\u00edtoliby"
    ],
    "name:hrv_x_preferred":[
        "M\u011bstys C\u00edtoliby"
    ],
    "name:hun_x_preferred":[
        "C\u00edtoliby"
    ],
    "name:ita_x_preferred":[
        "C\u00edtoliby"
    ],
    "name:jpn_x_preferred":[
        "\u30c1\u30fc\u30c8\u30ea\u30d3\u30fc"
    ],
    "name:lav_x_preferred":[
        "C\u00edtolibi"
    ],
    "name:lmo_x_preferred":[
        "C\u00edtoliby"
    ],
    "name:msa_x_preferred":[
        "C\u00edtoliby"
    ],
    "name:nan_x_preferred":[
        "C\u00edtoliby"
    ],
    "name:nld_x_preferred":[
        "C\u00edtoliby"
    ],
    "name:pol_x_preferred":[
        "C\u00edtoliby"
    ],
    "name:por_x_preferred":[
        "C\u00edtoliby"
    ],
    "name:rup_x_preferred":[
        "C\u00edtoliby"
    ],
    "name:rus_x_preferred":[
        "\u0426\u0438\u0442\u043e\u043b\u0438\u0431\u0438"
    ],
    "name:slk_x_preferred":[
        "C\u00edtoliby"
    ],
    "name:slv_x_preferred":[
        "M\u011bstys C\u00edtoliby"
    ],
    "name:spa_x_preferred":[
        "C\u00edtoliby"
    ],
    "name:srp_x_preferred":[
        "\u0426\u0438\u0442\u043e\u043b\u0438\u0431\u0438"
    ],
    "name:swe_x_preferred":[
        "C\u00edtoliby"
    ],
    "name:und_x_variant":[
        "Zittolib"
    ],
    "name:vie_x_preferred":[
        "C\u00edtoliby"
    ],
    "qs_pg:aaroncc":"CZ",
    "qs_pg:gn_country":"CZ",
    "qs_pg:gn_fcode":"PPL",
    "qs_pg:gn_pop":953,
    "qs_pg:name":"C\u00edtoliby",
    "qs_pg:name_adm0":"\u010cesk\u00e1 republika",
    "qs_pg:name_adm1":"\u00dasteck\u00fd kraj",
    "qs_pg:photos_9k":1,
    "qs_pg:photos_9r":1,
    "qs_pg:photos_all":1,
    "qs_pg:photos_sr":0,
    "qs_pg:pop_sr":2,
    "qs_pg:qs_pg_placetype":"locality",
    "qs_pg:qs_pg_placetype_gp":"Town",
    "qs_pg:woe_adm0":23424810,
    "woe:adm0_id":23424810,
    "woe:name_adm0":"\u010cesk\u00e1 republika",
    "woe:name_adm1":"\u00dasteck\u00fd kraj",
    "woe:placetype":"Town",
    "wof:name":"C\u00edtoliby",
    "wof:placetype":"locality",
    "wof:population":953
},
  "geometry": {"coordinates":[13.81214,50.33273],"type":"Point"}
}