{
  "type": "Feature",
  "properties": {
    "gn:country":"CZ",
    "gn:fcode":"PPL",
    "gn:population":30,
    "iso:country":"CZ",
    "name:ceb_x_preferred":[
        "Sta\u0148kovice"
    ],
    "name:ces_x_preferred":[
        "Sta\u0148kovice"
    ],
    "name:deu_x_preferred":[
        "Sta\u0148kovice"
    ],
    "name:epo_x_preferred":[
        "Sta\u0148kovice"
    ],
    "name:fra_x_preferred":[
        "Sta\u0148kovice"
    ],
    "name:ita_x_preferred":[
        "Sta\u0148kovice"
    ],
    "name:nld_x_preferred":[
        "Sta\u0148kovice"
    ],
    "name:slk_x_preferred":[
        "Sta\u0148kovice"
    ],
    "name:srp_x_preferred":[
        "\u0421\u0442\u0430\u045a\u043a\u043e\u0432\u0438\u0446\u0435"
    ],
    "name:swe_x_preferred":[
        "Sta\u0148kovice"
    ],
    "qs_pg:aaroncc":"CZ",
    "qs_pg:gn_country":"CZ",
    "qs_pg:gn_fcode":"PPL",
    "qs_pg:gn_pop":30,
    "qs_pg:name":"Sta\u0148kovice",
    "qs_pg:name_adm0":"\u010cesk\u00e1 republika",
    "qs_pg:name_adm1":"\u00dasteck\u00fd kraj",
    "qs_pg:photos_9r":0,
    "qs_pg:photos_sr":0,
    "qs_pg:pop_sr":1,
    "qs_pg:qs_pg_placetype":"locality",
    "qs_pg:qs_pg_placetype_gp":"Town",
    "qs_pg:woe_adm0":23424810,
    "woe:adm0_id":23424810,
    "woe:name_adm0":"\u010cesk\u00e1 republika",
    "woe:name_adm1":"\u00dasteck\u00fd kraj",
    "woe:placetype":"Town",
    "wof:name":"Sta\u0148kovice",
    "wof:placetype":"locality",
    "wof:population":30
},
  "geometry": {"coordinates":[14.16702,50.5894],"type":"Point"}
}