{
  "type": "Feature",
  "properties": {
    "gn:admin1_code":"90.0",
    "gn:admin2_code":"0723",
    "gn:asciiname":"Rokytnice",
    "gn:country_code":"CZ",
    "gn:dem":354,
    "gn:feature_class":"P",
    "gn:feature_code":"PPL",
    "gn:name":"Rokytnice",
    "gn:population":0,
    "gn:timezone":"Europe/Prague",
    "iso:country":"CZ",
    "name:und_x_variant":[
        "Roketnice",
        "Roketnitz",
        "Rokytnice"
    ],
    "wof:name":"Rokytnice",
    "wof:placetype":"locality"
},
  "geometry": {"coordinates":[17.98357,49.32572],"type":"Point"}
}