{
  "type": "Feature",
  "properties": {
    "gn:admin1_code":"78",
    "gn:admin2_code":"0621",
    "gn:asciiname":"Veselka",
    "gn:country_code":"CZ",
    "gn:dem":629,
    "gn:feature_class":"P",
    "gn:feature_code":"PPL",
    "gn:name":"Veselka",
    "gn:population":0,
    "gn:timezone":"Europe/Prague",
    "iso:country":"CZ",
    "wof:name":"Veselka",
    "wof:placetype":"locality"
},
  "geometry": {"coordinates":[16.45036,49.57917],"type":"Point"}
}