{
  "type": "Feature",
  "properties": {
    "gn:country":"CZ",
    "gn:fcode":"PPL",
    "gn:population":91,
    "iso:country":"CZ",
    "name:cat_x_preferred":[
        "Chl\u00edstov"
    ],
    "name:ces_x_preferred":[
        "Chl\u00edstov"
    ],
    "name:che_x_preferred":[
        "\u0425\u043b\u0438\u0441\u0442\u043e\u0432"
    ],
    "name:deu_x_preferred":[
        "Chl\u00edstov u Dobru\u0161ky"
    ],
    "name:deu_x_variant":[
        "Chl\u00edstov"
    ],
    "name:eng_x_preferred":[
        "Chl\u00edstov"
    ],
    "name:epo_x_preferred":[
        "Chl\u00edstov"
    ],
    "name:eus_x_preferred":[
        "Chl\u00edstov"
    ],
    "name:fas_x_preferred":[
        "\u062e\u0644\u06cc\u0633\u062a\u0648\u0641"
    ],
    "name:fra_x_preferred":[
        "Chl\u00edstov"
    ],
    "name:gle_x_preferred":[
        "Chl\u00edstov"
    ],
    "name:hun_x_preferred":[
        "Chl\u00edstov"
    ],
    "name:ita_x_preferred":[
        "Chl\u00edstov"
    ],
    "name:lmo_x_preferred":[
        "Chl\u00edstov"
    ],
    "name:msa_x_preferred":[
        "Chl\u00edstov"
    ],
    "name:nan_x_preferred":[
        "Chl\u00edstov"
    ],
    "name:nld_x_preferred":[
        "Chl\u00edstov"
    ],
    "name:pol_x_preferred":[
        "Chl\u00edstov"
    ],
    "name:por_x_preferred":[
        "Chl\u00edstov"
    ],
    "name:rup_x_preferred":[
        "Chl\u00edstov"
    ],
    "name:slk_x_preferred":[
        "Chl\u00edstov"
    ],
    "name:spa_x_preferred":[
        "Chl\u00edstov"
    ],
    "name:srp_x_preferred":[
        "\u0425\u043b\u0438\u0441\u0442\u043e\u0432"
    ],
    "name:tat_x_preferred":[
        "\u0425\u043b\u0438\u0441\u0442\u043e\u0432"
    ],
    "name:vie_x_preferred":[
        "Chl\u00edstov"
    ],
    "qs_pg:aaroncc":"CZ",
    "qs_pg:gn_country":"CZ",
    "qs_pg:gn_fcode":"PPL",
    "qs_pg:gn_pop":91,
    "qs_pg:name":"Chl\u00edstov",
    "qs_pg:name_adm0":"\u010cesk\u00e1 republika",
    "qs_pg:name_adm1":"Kr\u00e1lov\u00e9hradeck\u00fd kraj",
    "qs_pg:photos_9r":0,
    "qs_pg:photos_sr":0,
    "qs_pg:pop_sr":1,
    "qs_pg:qs_pg_placetype":"locality",
    "qs_pg:qs_pg_placetype_gp":"Town",
    "qs_pg:woe_adm0":23424810,
    "woe:adm0_id":23424810,
    "woe:name_adm0":"\u010cesk\u00e1 republika",
    "woe:name_adm1":"Kr\u00e1lov\u00e9hradeck\u00fd kraj",
    "woe:placetype":"Town",
    "wof:name":"Chl\u00edstov",
    "wof:placetype":"locality",
    "wof:population":91
},
  "geometry": {"coordinates":[16.16946,50.32237],"type":"Point"}
}