{
  "type": "Feature",
  "properties": {
    "gn:admin1_code":"79.0",
    "gn:admin2_code":"0315",
    "gn:asciiname":"Schlag",
    "gn:country_code":"CZ",
    "gn:dem":772,
    "gn:feature_class":"P",
    "gn:feature_code":"PPL",
    "gn:name":"Schlag",
    "gn:population":0,
    "gn:timezone":"Europe/Prague",
    "iso:country":"CZ",
    "name:und_x_variant":[
        "La\u017e\u00ed\u0161\u0165ko"
    ],
    "wof:name":"Schlag",
    "wof:placetype":"locality"
},
  "geometry": {"coordinates":[14.06311,48.97883],"type":"Point"}
}