{
  "type": "Feature",
  "properties": {
    "gn:admin1_code":"85.0",
    "gn:admin2_code":"0801",
    "gn:asciiname":"Maly Valstejn",
    "gn:country_code":"CZ",
    "gn:dem":636,
    "gn:feature_class":"P",
    "gn:feature_code":"PPL",
    "gn:name":"Mal\u00fd Val\u0161tejn",
    "gn:population":0,
    "gn:timezone":"Europe/Prague",
    "iso:country":"CZ",
    "name:und_x_variant":[
        "Klein Wallstein",
        "Mal\u00fd Val\u0161tejn"
    ],
    "wof:name":"Maly Valstejn",
    "wof:placetype":"locality"
},
  "geometry": {"coordinates":[17.50286,50.20896],"type":"Point"}
}