{
  "type": "Feature",
  "properties": {
    "gn:admin1_code":"79.0",
    "gn:admin2_code":"0313",
    "gn:asciiname":"Konrac",
    "gn:country_code":"CZ",
    "gn:dem":673,
    "gn:feature_class":"P",
    "gn:feature_code":"PPL",
    "gn:name":"Konrac",
    "gn:population":0,
    "gn:timezone":"Europe/Prague",
    "iso:country":"CZ",
    "wof:name":"Konrac",
    "wof:placetype":"locality"
},
  "geometry": {"coordinates":[15.16667,49.01667],"type":"Point"}
}