{
  "type": "Feature",
  "properties": {
    "iso:country":"CZ",
    "name:azb_x_preferred":[
        "\u067e\u0648\u062f\u0648\u0645\u06cc"
    ],
    "name:ceb_x_preferred":[
        "Podom\u00ed"
    ],
    "name:ces_x_preferred":[
        "Podom\u00ed"
    ],
    "name:deu_x_preferred":[
        "Podom\u00ed"
    ],
    "name:eus_x_preferred":[
        "Podom\u00ed"
    ],
    "name:fas_x_preferred":[
        "\u067e\u0648\u062f\u0648\u0645\u06cc"
    ],
    "name:fra_x_preferred":[
        "Podom\u00ed"
    ],
    "name:hun_x_preferred":[
        "Podom\u00ed"
    ],
    "name:ita_x_preferred":[
        "Podom\u00ed"
    ],
    "name:msa_x_preferred":[
        "Podom\u00ed"
    ],
    "name:nld_x_preferred":[
        "Podom\u00ed"
    ],
    "name:por_x_preferred":[
        "Podom\u00ed"
    ],
    "name:slk_x_preferred":[
        "Podom\u00ed"
    ],
    "name:spa_x_preferred":[
        "Podom\u00ed"
    ],
    "name:srp_x_preferred":[
        "\u041f\u043e\u0434\u043e\u043c\u0438"
    ],
    "name:swe_x_preferred":[
        "Podom\u00ed"
    ],
    "name:vie_x_preferred":[
        "Podom\u00ed"
    ],
    "qs_pg:aaroncc":"CZ",
    "qs_pg:name":"Podom\u00ed",
    "qs_pg:name_adm0":"\u010cesk\u00e1 republika",
    "qs_pg:name_adm1":"Jihomoravsk\u00fd kraj",
    "qs_pg:photos":2,
    "qs_pg:photos_1k":1,
    "qs_pg:photos_9k":1,
    "qs_pg:photos_9r":1,
    "qs_pg:photos_all":2,
    "qs_pg:photos_sr":1,
    "qs_pg:pop_sr":0,
    "qs_pg:qs_pg_placetype":"localadmin",
    "qs_pg:qs_pg_placetype_gp":"LocalAdmin",
    "qs_pg:woe_adm0":23424810,
    "woe:adm0_id":23424810,
    "woe:name_adm0":"\u010cesk\u00e1 republika",
    "woe:name_adm1":"Jihomoravsk\u00fd kraj",
    "woe:placetype":"LocalAdmin",
    "wof:name":"Podom\u00ed",
    "wof:placetype":"localadmin"
},
  "geometry": {"coordinates":[16.984863,49.312589],"type":"Point"}
}