{
  "type": "Feature",
  "properties": {
    "gn:admin1_code":"88.0",
    "gn:admin2_code":"020B",
    "gn:asciiname":"Blahova Lhota",
    "gn:country_code":"CZ",
    "gn:dem":460,
    "gn:feature_class":"P",
    "gn:feature_code":"PPL",
    "gn:name":"Bl\u00e1hova Lhota",
    "gn:population":0,
    "gn:timezone":"Europe/Prague",
    "iso:country":"CZ",
    "wof:name":"Blahova Lhota",
    "wof:placetype":"locality"
},
  "geometry": {"coordinates":[14.34042,49.6101],"type":"Point"}
}