{
  "type": "Feature",
  "properties": {
    "gn:admin1_code":"82.0",
    "gn:admin2_code":"0525",
    "gn:asciiname":"Olesna",
    "gn:country_code":"CZ",
    "gn:dem":409,
    "gn:feature_class":"P",
    "gn:feature_code":"PPL",
    "gn:name":"Ole\u0161n\u00e1",
    "gn:population":0,
    "gn:timezone":"Europe/Prague",
    "iso:country":"CZ",
    "name:und_x_variant":[
        "Dv\u016dr Ole\u0161n\u00e1",
        "Ole\u0161n\u00e1"
    ],
    "wof:name":"Olesna",
    "wof:placetype":"locality"
},
  "geometry": {"coordinates":[16.29619,50.01748],"type":"Point"}
}