{
  "type": "Feature",
  "properties": {
    "gn:admin1_code":"80.0",
    "gn:admin2_code":"0613",
    "gn:asciiname":"Dobromerice",
    "gn:country_code":"CZ",
    "gn:dem":535,
    "gn:feature_class":"P",
    "gn:feature_code":"PPL",
    "gn:name":"Dobrom\u011b\u0159ice",
    "gn:population":0,
    "gn:timezone":"Europe/Prague",
    "iso:country":"CZ",
    "wof:name":"Dobromerice",
    "wof:placetype":"locality"
},
  "geometry": {"coordinates":[15.07144,49.53178],"type":"Point"}
}