{
  "type": "Feature",
  "properties": {
    "gn:country":"CZ",
    "gn:fcode":"PPL",
    "gn:population":787,
    "iso:country":"CZ",
    "name:azb_x_preferred":[
        "\u0627\u0648\u067e\u0648\u0644\u0627\u0646\u06cc"
    ],
    "name:bul_x_preferred":[
        "\u041e\u043f\u043e\u043b\u0430\u043d\u0439"
    ],
    "name:cat_x_preferred":[
        "Opolany"
    ],
    "name:ceb_x_preferred":[
        "Opolany"
    ],
    "name:ces_x_preferred":[
        "Opolany"
    ],
    "name:che_x_preferred":[
        "\u041e\u043f\u043e\u043b\u0430\u043d\u0438"
    ],
    "name:deu_x_preferred":[
        "Opolany"
    ],
    "name:eng_x_preferred":[
        "Opolany"
    ],
    "name:eus_x_preferred":[
        "Opolany"
    ],
    "name:fas_x_preferred":[
        "\u0627\u0648\u067e\u0648\u0644\u0627\u0646\u06cc"
    ],
    "name:fra_x_preferred":[
        "Opolany"
    ],
    "name:gle_x_preferred":[
        "Opolany"
    ],
    "name:hun_x_preferred":[
        "Opolany"
    ],
    "name:ita_x_preferred":[
        "Opolany"
    ],
    "name:lmo_x_preferred":[
        "Opolany"
    ],
    "name:msa_x_preferred":[
        "Opolany"
    ],
    "name:nan_x_preferred":[
        "Opolany"
    ],
    "name:nld_x_preferred":[
        "Opolany"
    ],
    "name:pol_x_preferred":[
        "Opolany"
    ],
    "name:por_x_preferred":[
        "Opolany"
    ],
    "name:slk_x_preferred":[
        "Opolany"
    ],
    "name:spa_x_preferred":[
        "Opolany"
    ],
    "name:srp_x_preferred":[
        "\u041e\u043f\u043e\u043b\u0430\u043d\u0438"
    ],
    "name:swe_x_preferred":[
        "Opolany"
    ],
    "name:tat_x_preferred":[
        "\u041e\u043f\u043e\u043b\u0430\u043d\u0438"
    ],
    "name:vie_x_preferred":[
        "Opolany"
    ],
    "qs_pg:aaroncc":"CZ",
    "qs_pg:gn_country":"CZ",
    "qs_pg:gn_fcode":"PPL",
    "qs_pg:gn_pop":787,
    "qs_pg:name":"Opolany",
    "qs_pg:name_adm0":"\u010cesk\u00e1 republika",
    "qs_pg:name_adm1":"St\u0159edo\u010desk\u00fd kraj",
    "qs_pg:photos_9r":0,
    "qs_pg:photos_sr":0,
    "qs_pg:pop_sr":2,
    "qs_pg:qs_pg_placetype":"locality",
    "qs_pg:qs_pg_placetype_gp":"Town",
    "qs_pg:woe_adm0":23424810,
    "woe:adm0_id":23424810,
    "woe:name_adm0":"\u010cesk\u00e1 republika",
    "woe:name_adm1":"St\u0159edo\u010desk\u00fd kraj",
    "woe:placetype":"Town",
    "wof:name":"Opolany",
    "wof:placetype":"locality",
    "wof:population":787
},
  "geometry": {"coordinates":[15.217,50.13071],"type":"Point"}
}