{
  "type": "Feature",
  "properties": {
    "iso:country":"CZ",
    "name:ceb_x_preferred":[
        "\u010cern\u00e1 v Po\u0161umav\u00ed"
    ],
    "name:ces_x_preferred":[
        "\u010cern\u00e1 v Po\u0161umav\u00ed"
    ],
    "name:deu_x_preferred":[
        "\u010cern\u00e1 v Po\u0161umav\u00ed"
    ],
    "name:eus_x_preferred":[
        "\u010cern\u00e1 v Po\u0161umav\u00ed"
    ],
    "name:fas_x_preferred":[
        "\u062a\u0634\u0631\u0646\u0627 \u0641 \u067e\u0648\u0634\u0648\u0645\u0627\u0648\u06cc"
    ],
    "name:fra_x_preferred":[
        "\u010cern\u00e1 v Po\u0161umav\u00ed"
    ],
    "name:hun_x_preferred":[
        "\u010cern\u00e1 v Po\u0161umav\u00ed"
    ],
    "name:ita_x_preferred":[
        "\u010cern\u00e1 v Po\u0161umav\u00ed"
    ],
    "name:msa_x_preferred":[
        "\u010cern\u00e1 v Po\u0161umav\u00ed"
    ],
    "name:nld_x_preferred":[
        "\u010cern\u00e1 v Po\u0161umav\u00ed"
    ],
    "name:pol_x_preferred":[
        "\u010cern\u00e1 v Po\u0161umav\u00ed"
    ],
    "name:por_x_preferred":[
        "\u010cern\u00e1 v Po\u0161umav\u00ed"
    ],
    "name:slk_x_preferred":[
        "\u010cern\u00e1 v Po\u0161umav\u00ed"
    ],
    "name:spa_x_preferred":[
        "\u010cern\u00e1 v Po\u0161umav\u00ed"
    ],
    "name:srp_x_preferred":[
        "\u0427\u0435\u0440\u043d\u0430 \u0432 \u041f\u043e\u0448\u0443\u043c\u0430\u0432\u0438"
    ],
    "name:swe_x_preferred":[
        "\u010cern\u00e1 v Po\u0161umav\u00ed"
    ],
    "name:vie_x_preferred":[
        "\u010cern\u00e1 v Po\u0161umav\u00ed"
    ],
    "qs_pg:aaroncc":"CZ",
    "qs_pg:name":"\u010cern\u00e1 v Po\u0161umav\u00ed",
    "qs_pg:name_adm0":"\u010cesk\u00e1 republika",
    "qs_pg:name_adm1":"Jiho\u010desk\u00fd kraj",
    "qs_pg:photos":188,
    "qs_pg:photos_1k":38,
    "qs_pg:photos_9k":2,
    "qs_pg:photos_9r":5,
    "qs_pg:photos_all":421,
    "qs_pg:photos_sr":4,
    "qs_pg:pop_sr":0,
    "qs_pg:qs_pg_placetype":"localadmin",
    "qs_pg:qs_pg_placetype_gp":"LocalAdmin",
    "qs_pg:woe_adm0":23424810,
    "woe:adm0_id":23424810,
    "woe:name_adm0":"\u010cesk\u00e1 republika",
    "woe:name_adm1":"Jiho\u010desk\u00fd kraj",
    "woe:placetype":"LocalAdmin",
    "wof:name":"\u010cern\u00e1 v Po\u0161umav\u00ed",
    "wof:placetype":"localadmin"
},
  "geometry": {"coordinates":[14.09945,48.737822],"type":"Point"}
}