{
  "type": "Feature",
  "properties": {
    "gn:admin1_code":"79.0",
    "gn:admin2_code":"0313",
    "gn:asciiname":"Dolni Radikov",
    "gn:country_code":"CZ",
    "gn:dem":577,
    "gn:feature_class":"P",
    "gn:feature_code":"PPL",
    "gn:name":"Doln\u00ed Rad\u00edkov",
    "gn:population":0,
    "gn:timezone":"Europe/Prague",
    "iso:country":"CZ",
    "name:und_x_variant":[
        "Unter Radisch",
        "Doln\u00ed Rad\u00edkov"
    ],
    "wof:name":"Dolni Radikov",
    "wof:placetype":"locality"
},
  "geometry": {"coordinates":[15.28639,49.07633],"type":"Point"}
}