{
  "type": "Feature",
  "properties": {
    "gn:admin1_code":"90.0",
    "gn:admin2_code":"0724",
    "gn:asciiname":"Kostelec u Zlina",
    "gn:country_code":"CZ",
    "gn:dem":244,
    "gn:feature_class":"P",
    "gn:feature_code":"PPL",
    "gn:name":"Kostelec u Zlina",
    "gn:population":0,
    "gn:timezone":"Europe/Prague",
    "iso:country":"CZ",
    "name:und_x_variant":[
        "Kosteletz",
        "Kostelec u Zl\u00edna",
        "Kostelec u \u0160t\u00edpy",
        "Kostelec u Gottwaldova"
    ],
    "wof:name":"Kostelec u Zlina",
    "wof:placetype":"locality"
},
  "geometry": {"coordinates":[17.69966,49.25627],"type":"Point"}
}