{
  "type": "Feature",
  "properties": {
    "iso:country":"CZ",
    "name:azb_x_preferred":[
        "\u0647\u0648\u0631\u0648\u0645\u06cc\u0631\u06cc\u062a\u0633\u0647"
    ],
    "name:ceb_x_preferred":[
        "Horom\u011b\u0159ice"
    ],
    "name:ces_x_preferred":[
        "Horom\u011b\u0159ice"
    ],
    "name:eus_x_preferred":[
        "Horom\u011b\u0159ice"
    ],
    "name:fas_x_preferred":[
        "\u0647\u0648\u0631\u0648\u0645\u06cc\u0631\u06cc\u062a\u0633\u0647"
    ],
    "name:fra_x_preferred":[
        "Horom\u011b\u0159ice"
    ],
    "name:hun_x_preferred":[
        "Horom\u011b\u0159ice"
    ],
    "name:ita_x_preferred":[
        "Horom\u011b\u0159ice"
    ],
    "name:msa_x_preferred":[
        "Horom\u011b\u0159ice"
    ],
    "name:nld_x_preferred":[
        "Horom\u011b\u0159ice"
    ],
    "name:pol_x_preferred":[
        "Horom\u011b\u0159ice"
    ],
    "name:por_x_preferred":[
        "Horom\u011b\u0159ice"
    ],
    "name:rus_x_preferred":[
        "\u0413\u043e\u0440\u043e\u043c\u0435\u0440\u0436\u0438\u0446\u0435"
    ],
    "name:slk_x_preferred":[
        "Horom\u011b\u0159ice"
    ],
    "name:spa_x_preferred":[
        "Horom\u011b\u0159ice"
    ],
    "name:srp_x_preferred":[
        "\u0425\u043e\u0440\u043e\u043c\u0458\u0435\u0440\u0436\u0438\u0446\u0435"
    ],
    "name:swe_x_preferred":[
        "Horom\u011b\u0159ice"
    ],
    "name:vie_x_preferred":[
        "Horom\u011b\u0159ice"
    ],
    "qs_pg:aaroncc":"CZ",
    "qs_pg:name":"Horom\u011b\u0159ice",
    "qs_pg:name_adm0":"\u010cesk\u00e1 republika",
    "qs_pg:name_adm1":"St\u0159edo\u010desk\u00fd kraj",
    "qs_pg:photos":4,
    "qs_pg:photos_1k":1,
    "qs_pg:photos_9k":1,
    "qs_pg:photos_9r":2,
    "qs_pg:photos_all":28,
    "qs_pg:photos_sr":1,
    "qs_pg:pop_sr":0,
    "qs_pg:qs_pg_placetype":"localadmin",
    "qs_pg:qs_pg_placetype_gp":"LocalAdmin",
    "qs_pg:woe_adm0":23424810,
    "woe:adm0_id":23424810,
    "woe:name_adm0":"\u010cesk\u00e1 republika",
    "woe:name_adm1":"St\u0159edo\u010desk\u00fd kraj",
    "woe:placetype":"LocalAdmin",
    "wof:name":"Horom\u011b\u0159ice",
    "wof:placetype":"localadmin"
},
  "geometry": {"coordinates":[14.3474785,50.1308835],"type":"Point"}
}