{
  "type": "Feature",
  "properties": {
    "gn:gn_country":"CZ",
    "gn:gn_fcode":"PPL",
    "gn:gn_pop":558,
    "gn:population":558,
    "iso:country":"CZ",
    "name:cze_x_preferred":[
        "Jina\u010dovice"
    ],
    "name:dut_x_preferred":[
        "Jina\u010dovice"
    ],
    "name:eng_x_preferred":[
        "Jina\u010dovice"
    ],
    "name:fre_x_preferred":[
        "Jina\u010dovice"
    ],
    "name:ger_x_preferred":[
        "Jina\u010dovice"
    ],
    "name:hun_x_preferred":[
        "Jina\u010dovice"
    ],
    "name:ita_x_preferred":[
        "Jina\u010dovice"
    ],
    "name:may_x_preferred":[
        "Jina\u010dovice"
    ],
    "name:per_x_preferred":[
        "\u06cc\u06cc\u0646\u0627\u062a\u0634\u0648\u0648\u06cc\u062a\u0633\u0647"
    ],
    "name:pol_x_preferred":[
        "Jina\u010dovice"
    ],
    "name:por_x_preferred":[
        "Jina\u010dovice"
    ],
    "name:rup_x_preferred":[
        "Jina\u010dovice"
    ],
    "name:slo_x_preferred":[
        "Jina\u010dovice"
    ],
    "name:swe_x_preferred":[
        "Jina\u010dovice"
    ],
    "name:vie_x_preferred":[
        "Jina\u010dovice"
    ],
    "qs_pg:aaroncc":"CZ",
    "qs_pg:gn_country":"CZ",
    "qs_pg:gn_fcode":"PPL",
    "qs_pg:gn_pop":558,
    "qs_pg:name":"Jina\u010dovice",
    "qs_pg:name_adm0":"\u010cesk\u00e1 republika",
    "qs_pg:name_adm1":"Jihomoravsk\u00fd kraj",
    "qs_pg:photos_9r":0,
    "qs_pg:photos_sr":0,
    "qs_pg:pop_sr":2,
    "qs_pg:qs_pg_placetype":"locality",
    "qs_pg:qs_pg_placetype_gp":"Town",
    "qs_pg:woe_adm0":23424810,
    "woe:adm0_id":23424810,
    "woe:name_adm0":"\u010cesk\u00e1 republika",
    "woe:name_adm1":"Jihomoravsk\u00fd kraj",
    "woe:placetype":"Town",
    "wof:name":"Jina\u010dovice",
    "wof:placetype":"locality",
    "wof:population":558
},
  "geometry": {"coordinates":[16.52756,49.26792],"type":"Point"}
}