{
  "type": "Feature",
  "properties": {
    "gn:admin1_code":"82.0",
    "gn:admin2_code":"0524",
    "gn:asciiname":"Polom",
    "gn:country_code":"CZ",
    "gn:dem":750,
    "gn:feature_class":"P",
    "gn:feature_code":"PPL",
    "gn:name":"Polom",
    "gn:population":0,
    "gn:timezone":"Europe/Prague",
    "iso:country":"CZ",
    "name:bos_x_preferred":[
        "Polom"
    ],
    "name:ceb_x_preferred":[
        "Polom"
    ],
    "name:ces_x_preferred":[
        "Polom"
    ],
    "name:deu_x_preferred":[
        "Polom"
    ],
    "name:fra_x_preferred":[
        "Polom"
    ],
    "name:ita_x_preferred":[
        "Polom"
    ],
    "name:nld_x_preferred":[
        "Polom"
    ],
    "name:pol_x_preferred":[
        "Polom"
    ],
    "name:rus_x_preferred":[
        "\u041f\u043e\u043b\u043e\u043c"
    ],
    "name:slk_x_preferred":[
        "Polom"
    ],
    "name:slv_x_preferred":[
        "Polom"
    ],
    "name:srp_x_preferred":[
        "\u041f\u043e\u043b\u043e\u043c"
    ],
    "name:swe_x_preferred":[
        "Polom"
    ],
    "name:ukr_x_preferred":[
        "\u041f\u043e\u043b\u043e\u043c"
    ],
    "wof:name":"Polom",
    "wof:placetype":"locality"
},
  "geometry": {"coordinates":[16.32397000000001,50.35755],"type":"Point"}
}