{
  "type": "Feature",
  "properties": {
    "gn:admin1_code":"87.0",
    "gn:admin2_code":"0321",
    "gn:asciiname":"Chalupy",
    "gn:country_code":"CZ",
    "gn:dem":465,
    "gn:feature_class":"P",
    "gn:feature_code":"PPL",
    "gn:name":"Chalupy",
    "gn:population":0,
    "gn:timezone":"Europe/Prague",
    "iso:country":"CZ",
    "name:und_x_variant":[
        "Friedrichsthal",
        "Chalupy"
    ],
    "wof:name":"Chalupy",
    "wof:placetype":"locality"
},
  "geometry": {"coordinates":[13.04006,49.33525],"type":"Point"}
}