{
  "type": "Feature",
  "properties": {
    "gn:gn_country":"CZ",
    "gn:gn_fcode":"PPL",
    "gn:gn_pop":585,
    "gn:population":585,
    "iso:country":"CZ",
    "name:ceb_x_preferred":[
        "\u0160t\u00e1blovice"
    ],
    "name:ces_x_preferred":[
        "\u0160t\u00e1blovice"
    ],
    "name:deu_x_preferred":[
        "\u0160t\u00e1blovice"
    ],
    "name:eng_x_preferred":[
        "\u0160t\u00e1blovice"
    ],
    "name:epo_x_preferred":[
        "\u0160t\u00e1blovice"
    ],
    "name:eus_x_preferred":[
        "\u0160t\u00e1blovice"
    ],
    "name:fra_x_preferred":[
        "\u0160t\u00e1blovice"
    ],
    "name:hun_x_preferred":[
        "\u0160t\u00e1blovice"
    ],
    "name:ita_x_preferred":[
        "\u0160t\u00e1blovice"
    ],
    "name:msa_x_preferred":[
        "\u0160t\u00e1blovice"
    ],
    "name:nan_x_preferred":[
        "\u0160t\u00e1blovice"
    ],
    "name:nld_x_preferred":[
        "\u0160t\u00e1blovice"
    ],
    "name:pol_x_preferred":[
        "\u0160t\u00e1blovice"
    ],
    "name:por_x_preferred":[
        "\u0160t\u00e1blovice"
    ],
    "name:rup_x_preferred":[
        "\u0160t\u00e1blovice"
    ],
    "name:slk_x_preferred":[
        "\u0160t\u00e1blovice"
    ],
    "name:spa_x_preferred":[
        "\u0160t\u00e1blovice"
    ],
    "name:srp_x_preferred":[
        "\u0428\u0442\u0430\u0431\u043b\u043e\u0432\u0438\u0446\u0435"
    ],
    "name:swe_x_preferred":[
        "\u0160t\u00e1blovice"
    ],
    "name:vie_x_preferred":[
        "\u0160t\u00e1blovice"
    ],
    "qs_pg:aaroncc":"CZ",
    "qs_pg:gn_country":"CZ",
    "qs_pg:gn_fcode":"PPL",
    "qs_pg:gn_pop":585,
    "qs_pg:name":"\u0160t\u00e1blovice",
    "qs_pg:photos_9r":0,
    "qs_pg:photos_sr":0,
    "qs_pg:pop_sr":2,
    "qs_pg:qs_pg_placetype":"locality",
    "wof:name":"\u0160t\u00e1blovice",
    "wof:placetype":"locality",
    "wof:population":585
},
  "geometry": {"coordinates":[17.81853,49.88003],"type":"Point"}
}