{
  "type": "Feature",
  "properties": {
    "iso:country":"CZ",
    "name:bul_x_preferred":[
        "\u041e\u0441\u043b\u0430\u0432\u0430\u043d\u0438"
    ],
    "name:ceb_x_preferred":[
        "Oslavany"
    ],
    "name:ces_x_preferred":[
        "Oslavany"
    ],
    "name:deu_x_preferred":[
        "Oslavany"
    ],
    "name:eus_x_preferred":[
        "Oslavany"
    ],
    "name:fas_x_preferred":[
        "\u0627\u0648\u0633\u0644\u0627\u0648\u0627\u0646\u06cc"
    ],
    "name:fra_x_preferred":[
        "Oslavany"
    ],
    "name:hun_x_preferred":[
        "Oslavany"
    ],
    "name:ita_x_preferred":[
        "Oslavany"
    ],
    "name:lav_x_preferred":[
        "Oslavani"
    ],
    "name:msa_x_preferred":[
        "Oslavany"
    ],
    "name:nld_x_preferred":[
        "Oslavany"
    ],
    "name:pol_x_preferred":[
        "Oslavany"
    ],
    "name:por_x_preferred":[
        "Oslavany"
    ],
    "name:slk_x_preferred":[
        "Oslavany"
    ],
    "name:spa_x_preferred":[
        "Oslavany"
    ],
    "name:srp_x_preferred":[
        "\u041e\u0441\u043b\u0430\u0432\u0430\u043d\u0438"
    ],
    "name:swe_x_preferred":[
        "Oslavany"
    ],
    "name:vie_x_preferred":[
        "Oslavany"
    ],
    "name:zho_x_preferred":[
        "\u5967\u65af\u62c9\u74e6\u5c3c"
    ],
    "qs_pg:aaroncc":"CZ",
    "qs_pg:name":"Oslavany",
    "qs_pg:name_adm0":"\u010cesk\u00e1 republika",
    "qs_pg:name_adm1":"Jihomoravsk\u00fd kraj",
    "qs_pg:photos":185,
    "qs_pg:photos_1k":37,
    "qs_pg:photos_9k":2,
    "qs_pg:photos_9r":5,
    "qs_pg:photos_all":343,
    "qs_pg:photos_sr":4,
    "qs_pg:pop_sr":0,
    "qs_pg:qs_pg_placetype":"localadmin",
    "qs_pg:qs_pg_placetype_gp":"LocalAdmin",
    "qs_pg:woe_adm0":23424810,
    "woe:adm0_id":23424810,
    "woe:name_adm0":"\u010cesk\u00e1 republika",
    "woe:name_adm1":"Jihomoravsk\u00fd kraj",
    "woe:placetype":"LocalAdmin",
    "wof:name":"Oslavany",
    "wof:placetype":"localadmin"
},
  "geometry": {"coordinates":[16.334695,49.126718],"type":"Point"}
}