{
  "type": "Feature",
  "properties": {
    "iso:country":"CZ",
    "name:azb_x_preferred":[
        "\u0647\u0648\u0631\u0646\u06cc \u0648\u06cc\u0633\u062a\u0648\u0646\u06cc\u062a\u0633\u0647"
    ],
    "name:ceb_x_preferred":[
        "Horn\u00ed V\u011bstonice"
    ],
    "name:ces_x_preferred":[
        "Horn\u00ed V\u011bstonice"
    ],
    "name:deu_x_preferred":[
        "Horn\u00ed V\u011bstonice"
    ],
    "name:eus_x_preferred":[
        "Horn\u00ed V\u011bstonice"
    ],
    "name:fas_x_preferred":[
        "\u0647\u0648\u0631\u0646\u06cc \u0648\u06cc\u0633\u062a\u0648\u0646\u06cc\u062a\u0633\u0647"
    ],
    "name:fra_x_preferred":[
        "Horn\u00ed V\u011bstonice"
    ],
    "name:hun_x_preferred":[
        "Horn\u00ed V\u011bstonice"
    ],
    "name:ita_x_preferred":[
        "Horn\u00ed V\u011bstonice"
    ],
    "name:msa_x_preferred":[
        "Horn\u00ed V\u011bstonice"
    ],
    "name:nld_x_preferred":[
        "Horn\u00ed V\u011bstonice"
    ],
    "name:pol_x_preferred":[
        "Horn\u00ed V\u011bstonice"
    ],
    "name:por_x_preferred":[
        "Horn\u00ed V\u011bstonice"
    ],
    "name:slk_x_preferred":[
        "Horn\u00ed V\u011bstonice"
    ],
    "name:spa_x_preferred":[
        "Horn\u00ed V\u011bstonice"
    ],
    "name:srp_x_preferred":[
        "\u0425\u043e\u0440\u045a\u0438 \u0412\u0458\u0435\u0441\u0442\u043e\u045a\u0438\u0446\u0435"
    ],
    "name:swe_x_preferred":[
        "Horn\u00ed V\u011bstonice"
    ],
    "name:vie_x_preferred":[
        "Horn\u00ed V\u011bstonice"
    ],
    "qs_pg:aaroncc":"CZ",
    "qs_pg:name":"Horn\u00ed V\u011bstonice",
    "qs_pg:name_adm0":"\u010cesk\u00e1 republika",
    "qs_pg:name_adm1":"Jihomoravsk\u00fd kraj",
    "qs_pg:photos":50,
    "qs_pg:photos_1k":10,
    "qs_pg:photos_9k":1,
    "qs_pg:photos_9r":3,
    "qs_pg:photos_all":77,
    "qs_pg:photos_sr":2,
    "qs_pg:pop_sr":0,
    "qs_pg:qs_pg_placetype":"localadmin",
    "qs_pg:qs_pg_placetype_gp":"LocalAdmin",
    "qs_pg:woe_adm0":23424810,
    "woe:adm0_id":23424810,
    "woe:name_adm0":"\u010cesk\u00e1 republika",
    "woe:name_adm1":"Jihomoravsk\u00fd kraj",
    "woe:placetype":"LocalAdmin",
    "wof:name":"Horn\u00ed V\u011bstonice",
    "wof:placetype":"localadmin"
},
  "geometry": {"coordinates":[16.633086,48.87053],"type":"Point"}
}