{
  "type": "Feature",
  "properties": {
    "gn:admin1_code":"79.0",
    "gn:admin2_code":"0317",
    "gn:asciiname":"Bitov",
    "gn:country_code":"CZ",
    "gn:dem":490,
    "gn:feature_class":"P",
    "gn:feature_code":"PPL",
    "gn:name":"B\u00edtov",
    "gn:population":0,
    "gn:timezone":"Europe/Prague",
    "iso:country":"CZ",
    "wof:name":"Bitov",
    "wof:placetype":"locality"
},
  "geometry": {"coordinates":[14.81902,49.37899],"type":"Point"}
}