{
  "type": "Feature",
  "properties": {
    "gn:admin1_code":"85",
    "gn:admin2_code":"0804",
    "gn:asciiname":"Stikovec",
    "gn:country_code":"CZ",
    "gn:dem":271,
    "gn:feature_class":"P",
    "gn:feature_code":"PPL",
    "gn:name":"Stikovec",
    "gn:population":0,
    "gn:timezone":"Europe/Prague",
    "iso:country":"CZ",
    "wof:name":"Stikovec",
    "wof:placetype":"locality"
},
  "geometry": {"coordinates":[18.1525,49.64954],"type":"Point"}
}