{
  "type": "Feature",
  "properties": {
    "gn:gn_country":"CZ",
    "gn:gn_fcode":"PPL",
    "gn:gn_pop":140,
    "gn:population":140,
    "iso:country":"CZ",
    "name:ces_x_preferred":[
        "Bi\u0159kov"
    ],
    "name:deu_x_preferred":[
        "Bi\u0159kov"
    ],
    "name:eng_x_preferred":[
        "Bi\u0159kov"
    ],
    "name:fas_x_preferred":[
        "\u0628\u06cc\u0631\u06a9\u0648\u0648"
    ],
    "name:fra_x_preferred":[
        "Bi\u0159kov"
    ],
    "name:hun_x_preferred":[
        "Bi\u0159kov"
    ],
    "name:ita_x_preferred":[
        "Bi\u0159kov"
    ],
    "name:msa_x_preferred":[
        "Bi\u0159kov"
    ],
    "name:nld_x_preferred":[
        "Bi\u0159kov"
    ],
    "name:pol_x_preferred":[
        "Bi\u0159kov"
    ],
    "name:por_x_preferred":[
        "Bi\u0159kov"
    ],
    "name:rup_x_preferred":[
        "Bi\u0159kov"
    ],
    "name:slk_x_preferred":[
        "Bi\u0159kov"
    ],
    "name:srp_x_preferred":[
        "\u0411\u0438\u0440\u043a\u043e\u0432"
    ],
    "name:swe_x_preferred":[
        "Bi\u0159kov"
    ],
    "name:vie_x_preferred":[
        "Bi\u0159kov"
    ],
    "qs_pg:aaroncc":"CZ",
    "qs_pg:gn_country":"CZ",
    "qs_pg:gn_fcode":"PPL",
    "qs_pg:gn_pop":140,
    "qs_pg:name":"Bi\u0159kov",
    "qs_pg:name_adm0":"\u010cesk\u00e1 republika",
    "qs_pg:name_adm1":"Plze\u0148sk\u00fd kraj",
    "qs_pg:photos_9r":0,
    "qs_pg:photos_sr":0,
    "qs_pg:pop_sr":1,
    "qs_pg:qs_pg_placetype":"locality",
    "qs_pg:qs_pg_placetype_gp":"Town",
    "qs_pg:woe_adm0":23424810,
    "woe:adm0_id":23424810,
    "woe:name_adm0":"\u010cesk\u00e1 republika",
    "woe:name_adm1":"Plze\u0148sk\u00fd kraj",
    "woe:placetype":"Town",
    "wof:name":"Bi\u0159kov",
    "wof:placetype":"locality",
    "wof:population":140
},
  "geometry": {"coordinates":[13.23015,49.51805],"type":"Point"}
}