{
  "type": "Feature",
  "properties": {
    "gn:admin1_code":"81",
    "gn:admin2_code":"0412",
    "gn:asciiname":"Srni",
    "gn:country_code":"CZ",
    "gn:dem":698,
    "gn:feature_class":"P",
    "gn:feature_code":"PPL",
    "gn:name":"Srn\u00ed",
    "gn:population":0,
    "gn:timezone":"Europe/Prague",
    "iso:country":"CZ",
    "name:und_x_variant":[
        "Boksgr\u00fcn",
        "Boksgruen",
        "Srn\u00ed"
    ],
    "wof:name":"Srni",
    "wof:placetype":"locality"
},
  "geometry": {"coordinates":[13.05414,50.37584],"type":"Point"}
}