{
  "type": "Feature",
  "properties": {
    "gn:admin1_code":"87.0",
    "gn:admin2_code":"0322",
    "gn:asciiname":"Loucany",
    "gn:country_code":"CZ",
    "gn:dem":595,
    "gn:feature_class":"P",
    "gn:feature_code":"PPL",
    "gn:name":"Lou\u010dany",
    "gn:population":0,
    "gn:timezone":"Europe/Prague",
    "iso:country":"CZ",
    "wof:name":"Loucany",
    "wof:placetype":"locality"
},
  "geometry": {"coordinates":[13.2721,49.3302],"type":"Point"}
}