{
  "type": "Feature",
  "properties": {
    "gn:gn_country":"CZ",
    "gn:gn_fcode":"PPL",
    "gn:gn_pop":449,
    "gn:population":449,
    "iso:country":"CZ",
    "name:ceb_x_preferred":[
        "H\u016fry"
    ],
    "name:ces_x_preferred":[
        "H\u016fry"
    ],
    "name:deu_x_preferred":[
        "H\u016fry"
    ],
    "name:eng_x_preferred":[
        "H\u016fry"
    ],
    "name:eus_x_preferred":[
        "H\u016fry"
    ],
    "name:fra_x_preferred":[
        "H\u016fry"
    ],
    "name:hun_x_preferred":[
        "H\u016fry"
    ],
    "name:ita_x_preferred":[
        "H\u016fry"
    ],
    "name:msa_x_preferred":[
        "H\u016fry"
    ],
    "name:nan_x_preferred":[
        "H\u016fry"
    ],
    "name:nld_x_preferred":[
        "H\u016fry"
    ],
    "name:pol_x_preferred":[
        "H\u016fry"
    ],
    "name:por_x_preferred":[
        "H\u016fry"
    ],
    "name:rup_x_preferred":[
        "H\u016fry"
    ],
    "name:slk_x_preferred":[
        "H\u016fry"
    ],
    "name:spa_x_preferred":[
        "H\u016fry"
    ],
    "name:srp_x_preferred":[
        "\u0425\u0443\u0440\u0438"
    ],
    "name:swe_x_preferred":[
        "H\u016fry"
    ],
    "name:vie_x_preferred":[
        "H\u016fry"
    ],
    "qs_pg:aaroncc":"CZ",
    "qs_pg:gn_country":"CZ",
    "qs_pg:gn_fcode":"PPL",
    "qs_pg:gn_pop":449,
    "qs_pg:name":"H\u016fry",
    "qs_pg:name_adm0":"\u010cesk\u00e1 republika",
    "qs_pg:name_adm1":"Jiho\u010desk\u00fd kraj",
    "qs_pg:photos_9r":0,
    "qs_pg:photos_sr":0,
    "qs_pg:pop_sr":2,
    "qs_pg:qs_pg_placetype":"locality",
    "qs_pg:qs_pg_placetype_gp":"Town",
    "qs_pg:woe_adm0":23424810,
    "woe:adm0_id":23424810,
    "woe:name_adm0":"\u010cesk\u00e1 republika",
    "woe:name_adm1":"Jiho\u010desk\u00fd kraj",
    "woe:placetype":"Town",
    "wof:name":"H\u016fry",
    "wof:placetype":"locality",
    "wof:population":449
},
  "geometry": {"coordinates":[14.54108,49.00649],"type":"Point"}
}