{
  "type": "Feature",
  "properties": {
    "iso:country":"CZ",
    "name:azb_x_preferred":[
        "\u0698\u0627\u0644\u0647\u0648\u0633\u062a\u06cc\u062a\u0633\u0647"
    ],
    "name:ceb_x_preferred":[
        "\u017dalhostice"
    ],
    "name:ces_x_preferred":[
        "\u017dalhostice"
    ],
    "name:deu_x_preferred":[
        "\u017dalhostice"
    ],
    "name:epo_x_preferred":[
        "\u017dalhostice"
    ],
    "name:eus_x_preferred":[
        "\u017dalhostice"
    ],
    "name:fas_x_preferred":[
        "\u0698\u0627\u0644\u0647\u0648\u0633\u062a\u06cc\u062a\u0633\u0647"
    ],
    "name:fra_x_preferred":[
        "\u017dalhostice"
    ],
    "name:hun_x_preferred":[
        "\u017dalhostice"
    ],
    "name:ita_x_preferred":[
        "\u017dalhostice"
    ],
    "name:msa_x_preferred":[
        "\u017dalhostice"
    ],
    "name:nld_x_preferred":[
        "\u017dalhostice"
    ],
    "name:por_x_preferred":[
        "\u017dalhostice"
    ],
    "name:slk_x_preferred":[
        "\u017dalhostice"
    ],
    "name:spa_x_preferred":[
        "\u017dalhostice"
    ],
    "name:srp_x_preferred":[
        "\u0416\u0430\u043b\u0445\u043e\u0441\u0442\u0438\u0446\u0435"
    ],
    "name:swe_x_preferred":[
        "\u017dalhostice"
    ],
    "name:vie_x_preferred":[
        "\u017dalhostice"
    ],
    "qs_pg:aaroncc":"CZ",
    "qs_pg:name":"\u017dalhostice",
    "qs_pg:name_adm0":"\u010cesk\u00e1 republika",
    "qs_pg:name_adm1":"\u00dasteck\u00fd kraj",
    "qs_pg:photos":4,
    "qs_pg:photos_1k":1,
    "qs_pg:photos_9k":1,
    "qs_pg:photos_9r":1,
    "qs_pg:photos_all":4,
    "qs_pg:photos_sr":1,
    "qs_pg:pop_sr":0,
    "qs_pg:qs_pg_placetype":"localadmin",
    "qs_pg:qs_pg_placetype_gp":"LocalAdmin",
    "qs_pg:woe_adm0":23424810,
    "woe:adm0_id":23424810,
    "woe:name_adm0":"\u010cesk\u00e1 republika",
    "woe:name_adm1":"\u00dasteck\u00fd kraj",
    "woe:placetype":"LocalAdmin",
    "wof:name":"\u017dalhostice",
    "wof:placetype":"localadmin"
},
  "geometry": {"coordinates":[14.0911065,50.5300895],"type":"Point"}
}