{
  "type": "Feature",
  "properties": {
    "gn:admin1_code":"79.0",
    "gn:admin2_code":"0313",
    "gn:asciiname":"Hostkovice",
    "gn:country_code":"CZ",
    "gn:dem":492,
    "gn:feature_class":"P",
    "gn:feature_code":"PPL",
    "gn:name":"Hostkovice",
    "gn:population":0,
    "gn:timezone":"Europe/Prague",
    "iso:country":"CZ",
    "name:und_x_variant":[
        "Hostes",
        "Hostkovice"
    ],
    "wof:name":"Hostkovice",
    "wof:placetype":"locality"
},
  "geometry": {"coordinates":[15.38254,49.08205],"type":"Point"}
}