{
  "type": "Feature",
  "properties": {
    "gn:admin1_code":"78.0",
    "gn:admin2_code":"0626",
    "gn:asciiname":"Pazderna",
    "gn:country_code":"CZ",
    "gn:dem":254,
    "gn:feature_class":"P",
    "gn:feature_code":"PPL",
    "gn:name":"Pazderna",
    "gn:population":0,
    "gn:timezone":"Europe/Prague",
    "iso:country":"CZ",
    "wof:name":"Pazderna",
    "wof:placetype":"locality"
},
  "geometry": {"coordinates":[16.99231,49.28254],"type":"Point"}
}