{
  "type": "Feature",
  "properties": {
    "gn:admin1_code":"78.0",
    "gn:admin2_code":"0626",
    "gn:asciiname":"Pazderna",
    "gn:country_code":"CZ",
    "gn:dem":254,
    "gn:feature_class":"P",
    "gn:feature_code":"PPL",
    "gn:name":"Pazderna",
    "gn:population":0,
    "gn:timezone":"Europe/Prague",
    "iso:country":"CZ",
    "name:azb_x_preferred":[
        "\u067e\u0627\u0632\u062f\u0631\u0646\u0627"
    ],
    "name:ceb_x_preferred":[
        "Pazderna"
    ],
    "name:ces_x_preferred":[
        "Pazderna"
    ],
    "name:deu_x_preferred":[
        "Pazderna"
    ],
    "name:eus_x_preferred":[
        "Pazderna"
    ],
    "name:fas_x_preferred":[
        "\u067e\u0627\u0632\u062f\u0631\u0646\u0627"
    ],
    "name:fra_x_preferred":[
        "Pazderna"
    ],
    "name:hun_x_preferred":[
        "Pazderna"
    ],
    "name:ita_x_preferred":[
        "Pazderna"
    ],
    "name:msa_x_preferred":[
        "Pazderna"
    ],
    "name:nld_x_preferred":[
        "Pazderna"
    ],
    "name:pol_x_preferred":[
        "Pa\u017adzierna"
    ],
    "name:por_x_preferred":[
        "Pazderna"
    ],
    "name:slk_x_preferred":[
        "Pazderna"
    ],
    "name:spa_x_preferred":[
        "Pazderna"
    ],
    "name:srp_x_preferred":[
        "\u041f\u0430\u0437\u0434\u0435\u0440\u043d\u0430"
    ],
    "name:swe_x_preferred":[
        "Pazderna"
    ],
    "name:vie_x_preferred":[
        "Pazderna"
    ],
    "wof:name":"Pazderna",
    "wof:placetype":"locality"
},
  "geometry": {"coordinates":[16.99231,49.28254],"type":"Point"}
}