{
  "type": "Feature",
  "properties": {
    "gn:gn_country":"CZ",
    "gn:gn_fcode":"PPL",
    "gn:gn_pop":261,
    "gn:population":261,
    "iso:country":"CZ",
    "name:ceb_x_preferred":[
        "Chotim\u011b\u0159"
    ],
    "name:ces_x_preferred":[
        "Chotim\u011b\u0159"
    ],
    "name:deu_x_preferred":[
        "Chotim\u011b\u0159"
    ],
    "name:eng_x_preferred":[
        "Chotim\u011b\u0159"
    ],
    "name:epo_x_preferred":[
        "Chotim\u011b\u0159"
    ],
    "name:eus_x_preferred":[
        "Chotim\u011b\u0159"
    ],
    "name:fas_x_preferred":[
        "\u062e\u0648\u062a\u06cc\u0645\u06cc\u0631"
    ],
    "name:fra_x_preferred":[
        "Chotim\u011b\u0159"
    ],
    "name:hun_x_preferred":[
        "Chotim\u011b\u0159"
    ],
    "name:ita_x_preferred":[
        "Chotim\u011b\u0159"
    ],
    "name:msa_x_preferred":[
        "Chotim\u011b\u0159"
    ],
    "name:nan_x_preferred":[
        "Chotim\u011b\u0159"
    ],
    "name:nld_x_preferred":[
        "Chotim\u011b\u0159"
    ],
    "name:pol_x_preferred":[
        "Chotim\u011b\u0159"
    ],
    "name:por_x_preferred":[
        "Chotim\u011b\u0159"
    ],
    "name:slk_x_preferred":[
        "Chotim\u011b\u0159"
    ],
    "name:spa_x_preferred":[
        "Chotim\u011b\u0159"
    ],
    "name:srp_x_preferred":[
        "\u0425\u043e\u0442\u0438\u043c\u0458\u0435\u0440\u0436"
    ],
    "name:swe_x_preferred":[
        "Chotim\u011b\u0159"
    ],
    "name:vie_x_preferred":[
        "Chotim\u011b\u0159"
    ],
    "qs_pg:aaroncc":"CZ",
    "qs_pg:gn_country":"CZ",
    "qs_pg:gn_fcode":"PPL",
    "qs_pg:gn_pop":261,
    "qs_pg:name":"Chotim\u011b\u0159",
    "qs_pg:name_adm0":"\u010cesk\u00e1 republika",
    "qs_pg:name_adm1":"\u00dasteck\u00fd kraj",
    "qs_pg:photos_9k":1,
    "qs_pg:photos_9r":1,
    "qs_pg:photos_all":1,
    "qs_pg:photos_sr":0,
    "qs_pg:pop_sr":2,
    "qs_pg:qs_pg_placetype":"locality",
    "qs_pg:qs_pg_placetype_gp":"Town",
    "qs_pg:woe_adm0":23424810,
    "woe:adm0_id":23424810,
    "woe:name_adm0":"\u010cesk\u00e1 republika",
    "woe:name_adm1":"\u00dasteck\u00fd kraj",
    "woe:placetype":"Town",
    "wof:name":"Chotim\u011b\u0159",
    "wof:placetype":"locality",
    "wof:population":261
},
  "geometry": {"coordinates":[14.00088,50.54822],"type":"Point"}
}