{
  "type": "Feature",
  "properties": {
    "gn:gn_country":"CZ",
    "gn:gn_fcode":"PPL",
    "gn:gn_pop":308,
    "gn:population":308,
    "iso:country":"CZ",
    "name:ces_x_preferred":[
        "Slu\u0161tice"
    ],
    "name:deu_x_preferred":[
        "Slu\u0161tice"
    ],
    "name:eng_x_preferred":[
        "Slu\u0161tice"
    ],
    "name:fra_x_preferred":[
        "Slu\u0161tice"
    ],
    "name:hun_x_preferred":[
        "Slu\u0161tice"
    ],
    "name:ita_x_preferred":[
        "Slu\u0161tice"
    ],
    "name:msa_x_preferred":[
        "Slu\u0161tice"
    ],
    "name:nld_x_preferred":[
        "Slu\u0161tice"
    ],
    "name:pol_x_preferred":[
        "Slu\u0161tice"
    ],
    "name:por_x_preferred":[
        "Slu\u0161tice"
    ],
    "name:rus_x_preferred":[
        "\u0421\u043b\u0443\u0448\u0442\u0438\u0446\u0435"
    ],
    "name:slk_x_preferred":[
        "Slu\u0161tice"
    ],
    "name:srp_x_preferred":[
        "\u0421\u043b\u0443\u0448\u0442\u0438\u0446\u0435"
    ],
    "name:swe_x_preferred":[
        "Slu\u0161tice"
    ],
    "name:vie_x_preferred":[
        "Slu\u0161tice"
    ],
    "qs_pg:aaroncc":"CZ",
    "qs_pg:gn_country":"CZ",
    "qs_pg:gn_fcode":"PPL",
    "qs_pg:gn_pop":308,
    "qs_pg:name":"Slu\u0161tice",
    "qs_pg:name_adm0":"\u010cesk\u00e1 republika",
    "qs_pg:name_adm1":"St\u0159edo\u010desk\u00fd kraj",
    "qs_pg:photos_9r":0,
    "qs_pg:photos_sr":0,
    "qs_pg:pop_sr":2,
    "qs_pg:qs_pg_placetype":"locality",
    "qs_pg:qs_pg_placetype_gp":"Town",
    "qs_pg:woe_adm0":23424810,
    "woe:adm0_id":23424810,
    "woe:name_adm0":"\u010cesk\u00e1 republika",
    "woe:name_adm1":"St\u0159edo\u010desk\u00fd kraj",
    "woe:placetype":"Town",
    "wof:name":"Slu\u0161tice",
    "wof:placetype":"locality",
    "wof:population":308
},
  "geometry": {"coordinates":[14.6854,50.03904],"type":"Point"}
}