{
  "type": "Feature",
  "properties": {
    "gn:gn_country":"CZ",
    "gn:gn_fcode":"PPL",
    "gn:gn_pop":484,
    "gn:population":484,
    "iso:country":"CZ",
    "name:cze_x_preferred":[
        "Kyselovice"
    ],
    "name:dut_x_preferred":[
        "Kyselovice"
    ],
    "name:eng_x_preferred":[
        "Kyselovice"
    ],
    "name:fre_x_preferred":[
        "Kyselovice"
    ],
    "name:ger_x_preferred":[
        "Kyselovice"
    ],
    "name:hun_x_preferred":[
        "Kyselovice"
    ],
    "name:ita_x_preferred":[
        "Kyselovice"
    ],
    "name:may_x_preferred":[
        "Kyselovice"
    ],
    "name:per_x_preferred":[
        "\u06a9\u06cc\u0633\u0644\u0648\u0648\u06cc\u062a\u0633\u0647"
    ],
    "name:pol_x_preferred":[
        "Kyselovice"
    ],
    "name:por_x_preferred":[
        "Kyselovice"
    ],
    "name:rup_x_preferred":[
        "Kyselovice"
    ],
    "name:slo_x_preferred":[
        "Kyselovice"
    ],
    "name:srp_x_preferred":[
        "\u041a\u0438\u0441\u0435\u043b\u043e\u0432\u0438\u0446\u0435"
    ],
    "name:swe_x_preferred":[
        "Kyselovice"
    ],
    "name:unk_x_variant":[
        "Kyselowitz"
    ],
    "name:vie_x_preferred":[
        "Kyselovice"
    ],
    "qs_pg:aaroncc":"CZ",
    "qs_pg:gn_country":"CZ",
    "qs_pg:gn_fcode":"PPL",
    "qs_pg:gn_pop":484,
    "qs_pg:name":"Kyselovice",
    "qs_pg:name_adm0":"\u010cesk\u00e1 republika",
    "qs_pg:name_adm1":"Zl\u00ednsk\u00fd kraj",
    "qs_pg:photos_9r":0,
    "qs_pg:photos_sr":0,
    "qs_pg:pop_sr":2,
    "qs_pg:qs_pg_placetype":"locality",
    "qs_pg:qs_pg_placetype_gp":"Town",
    "qs_pg:woe_adm0":23424810,
    "woe:adm0_id":23424810,
    "woe:name_adm0":"\u010cesk\u00e1 republika",
    "woe:name_adm1":"Zl\u00ednsk\u00fd kraj",
    "woe:placetype":"Town",
    "wof:name":"Kyselovice",
    "wof:placetype":"locality",
    "wof:population":484
},
  "geometry": {"coordinates":[17.40206,49.37715],"type":"Point"}
}