{
  "type": "Feature",
  "properties": {
    "gn:gn_country":"CZ",
    "gn:gn_fcode":"PPL",
    "gn:gn_pop":429,
    "gn:population":429,
    "iso:country":"CZ",
    "name:ces_x_preferred":[
        "Kosteln\u00ed Hlavno"
    ],
    "name:eng_x_preferred":[
        "Kosteln\u00ed Hlavno"
    ],
    "name:fas_x_preferred":[
        "\u06a9\u0648\u0633\u062a\u0644\u0646\u06cc \u0647\u0644\u0627\u0648\u0646\u0648"
    ],
    "name:fra_x_preferred":[
        "Kosteln\u00ed Hlavno"
    ],
    "name:hun_x_preferred":[
        "Kosteln\u00ed Hlavno"
    ],
    "name:ita_x_preferred":[
        "Kosteln\u00ed Hlavno"
    ],
    "name:msa_x_preferred":[
        "Kosteln\u00ed Hlavno"
    ],
    "name:nan_x_preferred":[
        "Kosteln\u00ed Hlavno"
    ],
    "name:nld_x_preferred":[
        "Kosteln\u00ed Hlavno"
    ],
    "name:pol_x_preferred":[
        "Kosteln\u00ed Hlavno"
    ],
    "name:por_x_preferred":[
        "Kosteln\u00ed Hlavno"
    ],
    "name:rup_x_preferred":[
        "Kosteln\u00ed Hlavno"
    ],
    "name:rus_x_preferred":[
        "\u041a\u043e\u0441\u0442\u0435\u043b\u044c\u043d\u0438-\u0413\u043b\u0430\u0432\u043d\u043e"
    ],
    "name:slk_x_preferred":[
        "Kosteln\u00ed Hlavno"
    ],
    "name:srp_x_preferred":[
        "\u041a\u043e\u0441\u0442\u0435\u043b\u045a\u0438 \u0425\u043b\u0430\u0432\u043d\u043e"
    ],
    "name:swe_x_preferred":[
        "Kosteln\u00ed Hlavno"
    ],
    "name:vie_x_preferred":[
        "Kosteln\u00ed Hlavno"
    ],
    "qs_pg:aaroncc":"CZ",
    "qs_pg:gn_country":"CZ",
    "qs_pg:gn_fcode":"PPL",
    "qs_pg:gn_pop":429,
    "qs_pg:name":"Kosteln\u00ed Hlavno",
    "qs_pg:name_adm0":"\u010cesk\u00e1 republika",
    "qs_pg:name_adm1":"St\u0159edo\u010desk\u00fd kraj",
    "qs_pg:photos_9r":0,
    "qs_pg:photos_sr":0,
    "qs_pg:pop_sr":2,
    "qs_pg:qs_pg_placetype":"locality",
    "qs_pg:qs_pg_placetype_gp":"Town",
    "qs_pg:woe_adm0":23424810,
    "woe:adm0_id":23424810,
    "woe:name_adm0":"\u010cesk\u00e1 republika",
    "woe:name_adm1":"St\u0159edo\u010desk\u00fd kraj",
    "woe:placetype":"Town",
    "wof:name":"Kosteln\u00ed Hlavno",
    "wof:placetype":"locality",
    "wof:population":429
},
  "geometry": {"coordinates":[14.69898,50.25743],"type":"Point"}
}