{
  "type": "Feature",
  "properties": {
    "gn:country":"CZ",
    "gn:fcode":"PPL",
    "gn:population":1001,
    "iso:country":"CZ",
    "name:bul_x_preferred":[
        "\u041a\u043b\u043e\u0431\u0443\u043a\u0439"
    ],
    "name:cat_x_preferred":[
        "Klobuky"
    ],
    "name:ceb_x_preferred":[
        "Klobuky"
    ],
    "name:ces_x_preferred":[
        "Klobuky"
    ],
    "name:che_x_preferred":[
        "\u041a\u043b\u043e\u0431\u0443\u043a\u0438"
    ],
    "name:deu_x_preferred":[
        "Klobuky"
    ],
    "name:eng_x_preferred":[
        "Klobuky"
    ],
    "name:eus_x_preferred":[
        "Klobuky"
    ],
    "name:fas_x_preferred":[
        "\u06a9\u0644\u0648\u0628\u0648\u06a9\u06cc"
    ],
    "name:fra_x_preferred":[
        "Klobuky"
    ],
    "name:gle_x_preferred":[
        "Klobuky"
    ],
    "name:hun_x_preferred":[
        "Klobuky"
    ],
    "name:hye_x_preferred":[
        "\u053f\u056c\u0578\u0562\u0578\u0582\u056f\u056b"
    ],
    "name:ita_x_preferred":[
        "Klobuky"
    ],
    "name:lmo_x_preferred":[
        "Klobuky"
    ],
    "name:msa_x_preferred":[
        "Klobuky"
    ],
    "name:nan_x_preferred":[
        "Klobuky"
    ],
    "name:nld_x_preferred":[
        "Klobuky"
    ],
    "name:nob_x_preferred":[
        "Klobuky"
    ],
    "name:pol_x_preferred":[
        "Klobuky"
    ],
    "name:por_x_preferred":[
        "Klobuky"
    ],
    "name:rup_x_preferred":[
        "Klobuky"
    ],
    "name:rus_x_preferred":[
        "\u041a\u043b\u043e\u0431\u0443\u043a\u0438"
    ],
    "name:slk_x_preferred":[
        "Klobuky"
    ],
    "name:spa_x_preferred":[
        "Klobuky"
    ],
    "name:srp_x_preferred":[
        "\u041a\u043b\u043e\u0431\u0443\u043a\u0438"
    ],
    "name:swe_x_preferred":[
        "Klobuky"
    ],
    "name:tat_x_preferred":[
        "\u041a\u043b\u043e\u0431\u0443\u043a\u0438"
    ],
    "name:vie_x_preferred":[
        "Klobuky"
    ],
    "qs_pg:aaroncc":"CZ",
    "qs_pg:gn_country":"CZ",
    "qs_pg:gn_fcode":"PPL",
    "qs_pg:gn_pop":1001,
    "qs_pg:name":"Klobuky",
    "qs_pg:name_adm0":"\u010cesk\u00e1 republika",
    "qs_pg:name_adm1":"St\u0159edo\u010desk\u00fd kraj",
    "qs_pg:photos_9k":1,
    "qs_pg:photos_9r":1,
    "qs_pg:photos_all":13,
    "qs_pg:photos_sr":0,
    "qs_pg:pop_sr":3,
    "qs_pg:qs_pg_placetype":"locality",
    "qs_pg:qs_pg_placetype_gp":"Town",
    "qs_pg:woe_adm0":23424810,
    "woe:adm0_id":23424810,
    "woe:name_adm0":"\u010cesk\u00e1 republika",
    "woe:name_adm1":"St\u0159edo\u010desk\u00fd kraj",
    "woe:placetype":"Town",
    "wof:name":"Klobuky",
    "wof:placetype":"locality",
    "wof:population":1001
},
  "geometry": {"coordinates":[13.98748,50.29401],"type":"Point"}
}