{
  "type": "Feature",
  "properties": {
    "gn:country":"CZ",
    "gn:fcode":"PPL",
    "gn:population":311,
    "iso:country":"CZ",
    "name:ceb_x_preferred":[
        "Stra\u0161ov"
    ],
    "name:ces_x_preferred":[
        "Stra\u0161ov"
    ],
    "name:deu_x_preferred":[
        "Stra\u0161ov"
    ],
    "name:epo_x_preferred":[
        "Stra\u0161ov"
    ],
    "name:eus_x_preferred":[
        "Stra\u0161ov"
    ],
    "name:fra_x_preferred":[
        "Stra\u0161ov"
    ],
    "name:hun_x_preferred":[
        "Stra\u0161ov"
    ],
    "name:ita_x_preferred":[
        "Stra\u0161ov"
    ],
    "name:lfn_x_preferred":[
        "Stra\u0161ov"
    ],
    "name:msa_x_preferred":[
        "Stra\u0161ov"
    ],
    "name:nld_x_preferred":[
        "Stra\u0161ov"
    ],
    "name:pol_x_preferred":[
        "Stra\u0161ov"
    ],
    "name:por_x_preferred":[
        "Stra\u0161ov"
    ],
    "name:slk_x_preferred":[
        "Stra\u0161ov"
    ],
    "name:spa_x_preferred":[
        "Stra\u0161ov"
    ],
    "name:srp_x_preferred":[
        "\u0421\u0442\u0440\u0430\u0448\u043e\u0432"
    ],
    "name:swe_x_preferred":[
        "Stra\u0161ov"
    ],
    "name:vie_x_preferred":[
        "Stra\u0161ov"
    ],
    "qs_pg:aaroncc":"CZ",
    "qs_pg:gn_country":"CZ",
    "qs_pg:gn_fcode":"PPL",
    "qs_pg:gn_pop":311,
    "qs_pg:name":"Stra\u0161ov",
    "qs_pg:name_adm0":"\u010cesk\u00e1 republika",
    "qs_pg:name_adm1":"Pardubick\u00fd kraj",
    "qs_pg:photos_9r":0,
    "qs_pg:photos_sr":0,
    "qs_pg:pop_sr":2,
    "qs_pg:qs_pg_placetype":"locality",
    "qs_pg:qs_pg_placetype_gp":"Town",
    "qs_pg:woe_adm0":23424810,
    "woe:adm0_id":23424810,
    "woe:name_adm0":"\u010cesk\u00e1 republika",
    "woe:name_adm1":"Pardubick\u00fd kraj",
    "woe:placetype":"Town",
    "wof:name":"Stra\u0161ov",
    "wof:placetype":"locality",
    "wof:population":311
},
  "geometry": {"coordinates":[15.5227,50.08746],"type":"Point"}
}