{
  "type": "Feature",
  "properties": {
    "gn:country":"CZ",
    "gn:fcode":"PPL",
    "gn:population":710,
    "iso:country":"CZ",
    "name:azb_x_preferred":[
        "\u0633\u062a\u0627\u062a\u0646\u06cc\u062a\u0633\u0647"
    ],
    "name:cat_x_preferred":[
        "Statenice"
    ],
    "name:ceb_x_preferred":[
        "Statenice"
    ],
    "name:ces_x_preferred":[
        "Statenice"
    ],
    "name:che_x_preferred":[
        "\u0421\u0442\u0430\u0442\u0435\u043d\u0438\u0446\u0435"
    ],
    "name:deu_x_preferred":[
        "Statenice"
    ],
    "name:eng_x_preferred":[
        "Statenice"
    ],
    "name:eus_x_preferred":[
        "Statenice"
    ],
    "name:fas_x_preferred":[
        "\u0633\u062a\u0627\u062a\u0646\u06cc\u062a\u0633\u0647"
    ],
    "name:fra_x_preferred":[
        "Statenice"
    ],
    "name:gle_x_preferred":[
        "Statenice"
    ],
    "name:hun_x_preferred":[
        "Statenice"
    ],
    "name:ita_x_preferred":[
        "Statenice"
    ],
    "name:lmo_x_preferred":[
        "Statenice"
    ],
    "name:msa_x_preferred":[
        "Statenice"
    ],
    "name:nan_x_preferred":[
        "Statenice"
    ],
    "name:nld_x_preferred":[
        "Statenice"
    ],
    "name:pol_x_preferred":[
        "Statenice"
    ],
    "name:por_x_preferred":[
        "Statenice"
    ],
    "name:rus_x_preferred":[
        "\u0421\u0442\u0430\u0442\u0435\u043d\u0438\u0446\u0435"
    ],
    "name:slk_x_preferred":[
        "Statenice"
    ],
    "name:spa_x_preferred":[
        "Statenice"
    ],
    "name:srp_x_preferred":[
        "\u0421\u0442\u0430\u0442\u0435\u045a\u0438\u0446\u0435"
    ],
    "name:swe_x_preferred":[
        "Statenice"
    ],
    "name:tat_x_preferred":[
        "\u0421\u0442\u0430\u0442\u0435\u043d\u0438\u0446\u0435"
    ],
    "name:vie_x_preferred":[
        "Statenice"
    ],
    "qs_pg:aaroncc":"CZ",
    "qs_pg:gn_country":"CZ",
    "qs_pg:gn_fcode":"PPL",
    "qs_pg:gn_pop":710,
    "qs_pg:name":"Statenice",
    "qs_pg:name_adm0":"\u010cesk\u00e1 republika",
    "qs_pg:name_adm1":"St\u0159edo\u010desk\u00fd kraj",
    "qs_pg:photos_9k":1,
    "qs_pg:photos_9r":1,
    "qs_pg:photos_all":1,
    "qs_pg:photos_sr":0,
    "qs_pg:pop_sr":2,
    "qs_pg:qs_pg_placetype":"locality",
    "qs_pg:qs_pg_placetype_gp":"Town",
    "qs_pg:woe_adm0":23424810,
    "woe:adm0_id":23424810,
    "woe:name_adm0":"\u010cesk\u00e1 republika",
    "woe:name_adm1":"St\u0159edo\u010desk\u00fd kraj",
    "woe:placetype":"Town",
    "wof:name":"Statenice",
    "wof:placetype":"locality",
    "wof:population":710
},
  "geometry": {"coordinates":[14.31853,50.14257],"type":"Point"}
}