{
  "type": "Feature",
  "properties": {
    "gn:admin1_code":"85.0",
    "gn:admin2_code":"0801",
    "gn:asciiname":"Kostelec",
    "gn:country_code":"CZ",
    "gn:dem":342,
    "gn:feature_class":"P",
    "gn:feature_code":"PPL",
    "gn:name":"Kostelec",
    "gn:population":0,
    "gn:timezone":"Europe/Prague",
    "iso:country":"CZ",
    "name:und_x_variant":[
        "Weisskirch",
        "Kostelec"
    ],
    "wof:name":"Kostelec",
    "wof:placetype":"locality"
},
  "geometry": {"coordinates":[17.67485,50.088],"type":"Point"}
}