{
  "type": "Feature",
  "properties": {
    "gn:country":"CZ",
    "gn:fcode":"PPL",
    "gn:population":478,
    "iso:country":"CZ",
    "name:azb_x_preferred":[
        "\u0647\u0648\u0631\u0648\u0648\u0634\u0627\u0646\u06cc"
    ],
    "name:ceb_x_preferred":[
        "Horou\u0161any"
    ],
    "name:ces_x_preferred":[
        "Horou\u0161any"
    ],
    "name:eng_x_preferred":[
        "Horou\u0161any"
    ],
    "name:eus_x_preferred":[
        "Horou\u0161any"
    ],
    "name:fas_x_preferred":[
        "\u0647\u0648\u0631\u0648\u0648\u0634\u0627\u0646\u06cc"
    ],
    "name:fra_x_preferred":[
        "Horou\u0161any"
    ],
    "name:hun_x_preferred":[
        "Horou\u0161any"
    ],
    "name:ita_x_preferred":[
        "Horou\u0161any"
    ],
    "name:msa_x_preferred":[
        "Horou\u0161any"
    ],
    "name:nan_x_preferred":[
        "Horou\u0161any"
    ],
    "name:nld_x_preferred":[
        "Horou\u0161any"
    ],
    "name:pol_x_preferred":[
        "Horou\u0161any"
    ],
    "name:por_x_preferred":[
        "Horou\u0161any"
    ],
    "name:rus_x_preferred":[
        "\u0413\u043e\u0440\u043e\u0443\u0448\u0430\u043d\u0438"
    ],
    "name:slk_x_preferred":[
        "Horou\u0161any"
    ],
    "name:spa_x_preferred":[
        "Horou\u0161any"
    ],
    "name:srp_x_preferred":[
        "\u0425\u043e\u0440\u043e\u0443\u0448\u0430\u043d\u0438"
    ],
    "name:swe_x_preferred":[
        "Horou\u0161any"
    ],
    "name:vie_x_preferred":[
        "Horou\u0161any"
    ],
    "qs_pg:aaroncc":"CZ",
    "qs_pg:gn_country":"CZ",
    "qs_pg:gn_fcode":"PPL",
    "qs_pg:gn_pop":478,
    "qs_pg:name":"Horou\u0161any",
    "qs_pg:name_adm0":"\u010cesk\u00e1 republika",
    "qs_pg:name_adm1":"St\u0159edo\u010desk\u00fd kraj",
    "qs_pg:photos_9r":0,
    "qs_pg:photos_sr":0,
    "qs_pg:pop_sr":2,
    "qs_pg:qs_pg_placetype":"locality",
    "qs_pg:qs_pg_placetype_gp":"Town",
    "qs_pg:woe_adm0":23424810,
    "woe:adm0_id":23424810,
    "woe:name_adm0":"\u010cesk\u00e1 republika",
    "woe:name_adm1":"St\u0159edo\u010desk\u00fd kraj",
    "woe:placetype":"Town",
    "wof:name":"Horou\u0161any",
    "wof:placetype":"locality",
    "wof:population":478
},
  "geometry": {"coordinates":[14.74057,50.1064],"type":"Point"}
}