{
  "type": "Feature",
  "properties": {
    "gn:gn_country":"CZ",
    "gn:gn_fcode":"PPL",
    "gn:gn_pop":1002,
    "gn:population":1002,
    "iso:country":"CZ",
    "name:azb_x_preferred":[
        "\u06a9\u0631\u0627\u0633\u0646\u0627 \u0647\u0648\u0631\u0627 \u0646\u0627\u062f \u0648\u0644\u062a\u0627\u0648\u0648\u0648"
    ],
    "name:ceb_x_preferred":[
        "Kr\u00e1sn\u00e1 Hora nad Vltavou"
    ],
    "name:ces_x_preferred":[
        "Kr\u00e1sn\u00e1 Hora nad Vltavou"
    ],
    "name:deu_x_preferred":[
        "Kr\u00e1sn\u00e1 Hora nad Vltavou"
    ],
    "name:eng_x_preferred":[
        "Kr\u00e1sn\u00e1 Hora nad Vltavou"
    ],
    "name:eus_x_preferred":[
        "Kr\u00e1sn\u00e1 Hora nad Vltavou"
    ],
    "name:fas_x_preferred":[
        "\u06a9\u0631\u0627\u0633\u0646\u0627 \u0647\u0648\u0631\u0627 \u0646\u0627\u062f \u0648\u0644\u062a\u0627\u0648\u0648\u0648"
    ],
    "name:fra_x_preferred":[
        "Kr\u00e1sn\u00e1 Hora nad Vltavou"
    ],
    "name:hun_x_preferred":[
        "Kr\u00e1sn\u00e1 Hora nad Vltavou"
    ],
    "name:ita_x_preferred":[
        "Kr\u00e1sn\u00e1 Hora nad Vltavou"
    ],
    "name:msa_x_preferred":[
        "Kr\u00e1sn\u00e1 Hora nad Vltavou"
    ],
    "name:nan_x_preferred":[
        "Kr\u00e1sn\u00e1 Hora nad Vltavou"
    ],
    "name:nld_x_preferred":[
        "Kr\u00e1sn\u00e1 Hora nad Vltavou"
    ],
    "name:por_x_preferred":[
        "Kr\u00e1sn\u00e1 Hora nad Vltavou"
    ],
    "name:rup_x_preferred":[
        "Kr\u00e1sn\u00e1 Hora nad Vltavou"
    ],
    "name:slk_x_preferred":[
        "Kr\u00e1sn\u00e1 Hora nad Vltavou"
    ],
    "name:spa_x_preferred":[
        "Kr\u00e1sn\u00e1 Hora nad Vltavou"
    ],
    "name:srp_x_preferred":[
        "\u041a\u0440\u0430\u0441\u043d\u0430 \u0425\u043e\u0440\u0430 \u043d\u0430 \u0412\u043b\u0442\u0430\u0432\u0438"
    ],
    "name:swe_x_preferred":[
        "Kr\u00e1sn\u00e1 Hora nad Vltavou"
    ],
    "name:tat_x_preferred":[
        "\u041a\u0440\u0430\u0441\u043d\u0430-\u04ba\u043e\u0440\u0430-\u043d\u0430\u0434-\u0412\u043b\u0442\u0430\u0432\u043e\u0443"
    ],
    "name:unk_x_variant":[
        "Sch\u00f6nberg"
    ],
    "name:vie_x_preferred":[
        "Kr\u00e1sn\u00e1 Hora nad Vltavou"
    ],
    "qs_pg:aaroncc":"CZ",
    "qs_pg:gn_country":"CZ",
    "qs_pg:gn_fcode":"PPL",
    "qs_pg:gn_pop":1002,
    "qs_pg:name":"Kr\u00e1sn\u00e1 Hora nad Vltavou",
    "qs_pg:name_adm0":"\u010cesk\u00e1 republika",
    "qs_pg:name_adm1":"St\u0159edo\u010desk\u00fd kraj",
    "qs_pg:photos_9k":1,
    "qs_pg:photos_9r":1,
    "qs_pg:photos_all":1,
    "qs_pg:photos_sr":0,
    "qs_pg:pop_sr":3,
    "qs_pg:qs_pg_placetype":"locality",
    "qs_pg:qs_pg_placetype_gp":"Town",
    "qs_pg:woe_adm0":23424810,
    "woe:adm0_id":23424810,
    "woe:name_adm0":"\u010cesk\u00e1 republika",
    "woe:name_adm1":"St\u0159edo\u010desk\u00fd kraj",
    "woe:placetype":"Town",
    "wof:name":"Kr\u00e1sn\u00e1 Hora nad Vltavou",
    "wof:placetype":"locality",
    "wof:population":1002
},
  "geometry": {"coordinates":[14.27742,49.60461],"type":"Point"}
}