{
  "type": "Feature",
  "properties": {
    "gn:country":"CZ",
    "gn:fcode":"PPL",
    "gn:population":586,
    "iso:country":"CZ",
    "name:azb_x_preferred":[
        "\u0632\u0627\u0645\u06cc\u0644"
    ],
    "name:ceb_x_preferred":[
        "Z\u00e1m\u011bl"
    ],
    "name:ces_x_preferred":[
        "Z\u00e1m\u011bl"
    ],
    "name:deu_x_preferred":[
        "Z\u00e1m\u011bl"
    ],
    "name:eng_x_preferred":[
        "Z\u00e1m\u011bl"
    ],
    "name:eus_x_preferred":[
        "Z\u00e1m\u011bl"
    ],
    "name:fas_x_preferred":[
        "\u0632\u0627\u0645\u06cc\u0644"
    ],
    "name:fra_x_preferred":[
        "Z\u00e1m\u011bl"
    ],
    "name:hun_x_preferred":[
        "Z\u00e1m\u011bl"
    ],
    "name:ita_x_preferred":[
        "Z\u00e1m\u011bl"
    ],
    "name:msa_x_preferred":[
        "Z\u00e1m\u011bl"
    ],
    "name:nan_x_preferred":[
        "Z\u00e1m\u011bl"
    ],
    "name:nld_x_preferred":[
        "Z\u00e1m\u011bl"
    ],
    "name:pol_x_preferred":[
        "Z\u00e1m\u011bl"
    ],
    "name:por_x_preferred":[
        "Z\u00e1m\u011bl"
    ],
    "name:slk_x_preferred":[
        "Z\u00e1m\u011bl"
    ],
    "name:spa_x_preferred":[
        "Z\u00e1m\u011bl"
    ],
    "name:srp_x_preferred":[
        "\u0417\u0430\u043c\u0458\u0435\u043b"
    ],
    "name:swe_x_preferred":[
        "Z\u00e1m\u011bl"
    ],
    "name:vie_x_preferred":[
        "Z\u00e1m\u011bl"
    ],
    "qs_pg:aaroncc":"CZ",
    "qs_pg:gn_country":"CZ",
    "qs_pg:gn_fcode":"PPL",
    "qs_pg:gn_pop":586,
    "qs_pg:name":"Z\u00e1m\u011bl",
    "qs_pg:name_adm0":"\u010cesk\u00e1 republika",
    "qs_pg:name_adm1":"Kr\u00e1lov\u00e9hradeck\u00fd kraj",
    "qs_pg:photos_9k":1,
    "qs_pg:photos_9r":1,
    "qs_pg:photos_all":1,
    "qs_pg:photos_sr":0,
    "qs_pg:pop_sr":2,
    "qs_pg:qs_pg_placetype":"locality",
    "qs_pg:qs_pg_placetype_gp":"Town",
    "qs_pg:woe_adm0":23424810,
    "woe:adm0_id":23424810,
    "woe:name_adm0":"\u010cesk\u00e1 republika",
    "woe:name_adm1":"Kr\u00e1lov\u00e9hradeck\u00fd kraj",
    "woe:placetype":"Town",
    "wof:name":"Z\u00e1m\u011bl",
    "wof:placetype":"locality",
    "wof:population":586
},
  "geometry": {"coordinates":[16.2988,50.09655],"type":"Point"}
}