{
  "type": "Feature",
  "properties": {
    "gn:admin1_code":"88.0",
    "gn:admin2_code":"020B",
    "gn:asciiname":"Knovicky",
    "gn:country_code":"CZ",
    "gn:dem":341,
    "gn:feature_class":"P",
    "gn:feature_code":"PPL",
    "gn:name":"K\u0148ovi\u010dky",
    "gn:population":0,
    "gn:timezone":"Europe/Prague",
    "iso:country":"CZ",
    "wof:name":"Knovicky",
    "wof:placetype":"locality"
},
  "geometry": {"coordinates":[14.40391,49.6825],"type":"Point"}
}