{
  "type": "Feature",
  "properties": {
    "iso:country":"CZ",
    "name:ceb_x_preferred":[
        "Jablonn\u00e9 nad Orlic\u00ed"
    ],
    "name:ces_x_preferred":[
        "Jablonn\u00e9 nad Orlic\u00ed"
    ],
    "name:deu_x_preferred":[
        "Jablonn\u00e9 nad Orlic\u00ed"
    ],
    "name:epo_x_preferred":[
        "Jablonn\u00e9 nad Orlic\u00ed"
    ],
    "name:eus_x_preferred":[
        "Jablonn\u00e9 nad Orlic\u00ed"
    ],
    "name:fas_x_preferred":[
        "\u06cc\u0627\u0628\u0644\u0648\u0646\u0646\u0647 \u0646\u0627\u062f \u0627\u0648\u0631\u0644\u06cc\u062a\u0633\u06cc"
    ],
    "name:fra_x_preferred":[
        "Jablonn\u00e9 nad Orlic\u00ed"
    ],
    "name:hun_x_preferred":[
        "Jablonn\u00e9 nad Orlic\u00ed"
    ],
    "name:ita_x_preferred":[
        "Jablonn\u00e9 nad Orlic\u00ed"
    ],
    "name:lav_x_preferred":[
        "Jablonne pie Orlices"
    ],
    "name:msa_x_preferred":[
        "Jablonn\u00e9 nad Orlic\u00ed"
    ],
    "name:nld_x_preferred":[
        "Jablonn\u00e9 nad Orlic\u00ed"
    ],
    "name:pol_x_preferred":[
        "Jablonn\u00e9 nad Orlic\u00ed"
    ],
    "name:por_x_preferred":[
        "Jablonn\u00e9 nad Orlic\u00ed"
    ],
    "name:slk_x_preferred":[
        "Jablonn\u00e9 nad Orlic\u00ed"
    ],
    "name:spa_x_preferred":[
        "Jablonn\u00e9 nad Orlic\u00ed"
    ],
    "name:srp_x_preferred":[
        "\u0408\u0430\u0431\u043b\u043e\u043d\u0435 \u043d\u0430 \u041e\u0440\u043b\u0438\u0446\u0438"
    ],
    "name:swe_x_preferred":[
        "Jablonn\u00e9 nad Orlic\u00ed"
    ],
    "name:vie_x_preferred":[
        "Jablonn\u00e9 nad Orlic\u00ed"
    ],
    "qs_pg:aaroncc":"CZ",
    "qs_pg:name":"Jablonn\u00e9 nad Orlic\u00ed",
    "qs_pg:name_adm0":"\u010cesk\u00e1 republika",
    "qs_pg:name_adm1":"Pardubick\u00fd kraj",
    "qs_pg:photos":1,
    "qs_pg:photos_1k":1,
    "qs_pg:photos_9k":1,
    "qs_pg:photos_9r":2,
    "qs_pg:photos_all":71,
    "qs_pg:photos_sr":1,
    "qs_pg:pop_sr":0,
    "qs_pg:qs_pg_placetype":"localadmin",
    "qs_pg:qs_pg_placetype_gp":"LocalAdmin",
    "qs_pg:woe_adm0":23424810,
    "woe:adm0_id":23424810,
    "woe:name_adm0":"\u010cesk\u00e1 republika",
    "woe:name_adm1":"Pardubick\u00fd kraj",
    "woe:placetype":"LocalAdmin",
    "wof:name":"Jablonn\u00e9 nad Orlic\u00ed",
    "wof:placetype":"localadmin"
},
  "geometry": {"coordinates":[16.594263,50.029943],"type":"Point"}
}