{
  "type": "Feature",
  "properties": {
    "gn:admin1_code":"88.0",
    "gn:admin2_code":"020C",
    "gn:asciiname":"Pohorelec",
    "gn:country_code":"CZ",
    "gn:dem":250,
    "gn:feature_class":"P",
    "gn:feature_code":"PPL",
    "gn:name":"Poho\u0159elec",
    "gn:population":0,
    "gn:timezone":"Europe/Prague",
    "iso:country":"CZ",
    "wof:name":"Pohorelec",
    "wof:placetype":"locality"
},
  "geometry": {"coordinates":[13.90097,50.04799000000001],"type":"Point"}
}