{
  "type": "Feature",
  "properties": {
    "gn:gn_country":"CZ",
    "gn:gn_fcode":"PPL",
    "gn:gn_pop":408,
    "gn:population":408,
    "iso:country":"CZ",
    "name:ces_x_preferred":[
        "\u0158epn\u00edky"
    ],
    "name:eng_x_preferred":[
        "\u0158epn\u00edky"
    ],
    "name:epo_x_preferred":[
        "\u0158epn\u00edky"
    ],
    "name:fra_x_preferred":[
        "\u0158epn\u00edky"
    ],
    "name:hun_x_preferred":[
        "\u0158epn\u00edky"
    ],
    "name:ita_x_preferred":[
        "\u0158epn\u00edky"
    ],
    "name:msa_x_preferred":[
        "\u0158epn\u00edky"
    ],
    "name:nld_x_preferred":[
        "\u0158epn\u00edky"
    ],
    "name:por_x_preferred":[
        "\u0158epn\u00edky"
    ],
    "name:slk_x_preferred":[
        "\u0158epn\u00edky"
    ],
    "name:srp_x_preferred":[
        "\u0420\u0435\u043f\u045a\u0438\u043a\u0438"
    ],
    "name:swe_x_preferred":[
        "\u0158epn\u00edky"
    ],
    "name:unk_x_variant":[
        "\u0158epnik"
    ],
    "name:vie_x_preferred":[
        "\u0158epn\u00edky"
    ],
    "qs_pg:aaroncc":"CZ",
    "qs_pg:gn_country":"CZ",
    "qs_pg:gn_fcode":"PPL",
    "qs_pg:gn_pop":408,
    "qs_pg:name":"\u0158epn\u00edky",
    "qs_pg:name_adm0":"\u010cesk\u00e1 republika",
    "qs_pg:name_adm1":"Pardubick\u00fd kraj",
    "qs_pg:photos_9r":0,
    "qs_pg:photos_sr":0,
    "qs_pg:pop_sr":2,
    "qs_pg:qs_pg_placetype":"locality",
    "qs_pg:qs_pg_placetype_gp":"Town",
    "qs_pg:woe_adm0":23424810,
    "woe:adm0_id":23424810,
    "woe:name_adm0":"\u010cesk\u00e1 republika",
    "woe:name_adm1":"Pardubick\u00fd kraj",
    "woe:placetype":"Town",
    "wof:name":"\u0158epn\u00edky",
    "wof:placetype":"locality",
    "wof:population":408
},
  "geometry": {"coordinates":[16.0796,49.90147],"type":"Point"}
}