{
  "type": "Feature",
  "properties": {
    "gn:admin1_code":"87.0",
    "gn:admin2_code":"0322",
    "gn:asciiname":"Ferdinandov",
    "gn:country_code":"CZ",
    "gn:dem":766,
    "gn:feature_class":"P",
    "gn:feature_code":"PPL",
    "gn:name":"Ferdinandov",
    "gn:population":0,
    "gn:timezone":"Europe/Prague",
    "iso:country":"CZ",
    "name:und_x_variant":[
        "Ferdinandsthal",
        "Ferdinandov"
    ],
    "wof:name":"Ferdinandov",
    "wof:placetype":"locality"
},
  "geometry": {"coordinates":[13.23333,49.11667],"type":"Point"}
}