{
  "type": "Feature",
  "properties": {
    "gn:admin1_code":"80.0",
    "gn:admin2_code":"0611",
    "gn:asciiname":"Novy Studenec",
    "gn:country_code":"CZ",
    "gn:dem":495,
    "gn:feature_class":"P",
    "gn:feature_code":"PPL",
    "gn:name":"Nov\u00fd Studenec",
    "gn:population":0,
    "gn:timezone":"Europe/Prague",
    "iso:country":"CZ",
    "name:und_x_variant":[
        "Neu Studenetz",
        "Nov\u00fd Studenec"
    ],
    "wof:name":"Novy Studenec",
    "wof:placetype":"locality"
},
  "geometry": {"coordinates":[15.78493,49.72028],"type":"Point"}
}