{
  "type": "Feature",
  "properties": {
    "gn:gn_country":"CZ",
    "gn:gn_fcode":"PPL",
    "gn:gn_pop":291,
    "gn:population":291,
    "iso:country":"CZ",
    "name:cze_x_preferred":[
        "\u00dajezd pod Troskami"
    ],
    "name:dut_x_preferred":[
        "\u00dajezd pod Troskami"
    ],
    "name:eng_x_preferred":[
        "\u00dajezd pod Troskami"
    ],
    "name:fre_x_preferred":[
        "\u00dajezd pod Troskami"
    ],
    "name:hun_x_preferred":[
        "\u00dajezd pod Troskami"
    ],
    "name:ita_x_preferred":[
        "\u00dajezd pod Troskami"
    ],
    "name:may_x_preferred":[
        "\u00dajezd pod Troskami"
    ],
    "name:nan_x_preferred":[
        "\u00dajezd pod Troskami"
    ],
    "name:per_x_preferred":[
        "\u0627\u0648\u06cc\u0632\u062f \u067e\u0648\u062f \u062a\u0631\u0648\u0633\u06a9\u0627\u0645\u06cc"
    ],
    "name:pol_x_preferred":[
        "\u00dajezd pod Troskami"
    ],
    "name:por_x_preferred":[
        "\u00dajezd pod Troskami"
    ],
    "name:rup_x_preferred":[
        "\u00dajezd pod Troskami"
    ],
    "name:slo_x_preferred":[
        "\u00dajezd pod Troskami"
    ],
    "name:srp_x_preferred":[
        "\u0423\u0458\u0435\u0437\u0434 \u043f\u043e\u0434 \u0422\u0440\u043e\u0441\u043a\u0430\u043c\u0438"
    ],
    "name:swe_x_preferred":[
        "\u00dajezd pod Troskami"
    ],
    "name:unk_x_variant":[
        "Ujezd"
    ],
    "name:vie_x_preferred":[
        "\u00dajezd pod Troskami"
    ],
    "qs_pg:aaroncc":"CZ",
    "qs_pg:gn_country":"CZ",
    "qs_pg:gn_fcode":"PPL",
    "qs_pg:gn_pop":291,
    "qs_pg:name":"\u00dajezd pod Troskami",
    "qs_pg:name_adm0":"\u010cesk\u00e1 republika",
    "qs_pg:name_adm1":"Kr\u00e1lov\u00e9hradeck\u00fd kraj",
    "qs_pg:photos_9k":1,
    "qs_pg:photos_9r":1,
    "qs_pg:photos_all":2,
    "qs_pg:photos_sr":0,
    "qs_pg:pop_sr":2,
    "qs_pg:qs_pg_placetype":"locality",
    "qs_pg:qs_pg_placetype_gp":"Town",
    "qs_pg:woe_adm0":23424810,
    "woe:adm0_id":23424810,
    "woe:name_adm0":"\u010cesk\u00e1 republika",
    "woe:name_adm1":"Kr\u00e1lov\u00e9hradeck\u00fd kraj",
    "woe:placetype":"Town",
    "wof:name":"\u00dajezd pod Troskami",
    "wof:placetype":"locality",
    "wof:population":291
},
  "geometry": {"coordinates":[15.26255,50.50653],"type":"Point"}
}