{
  "type": "Feature",
  "properties": {
    "gn:admin1_code":"88.0",
    "gn:admin2_code":"0202",
    "gn:asciiname":"Poucnik",
    "gn:country_code":"CZ",
    "gn:dem":214,
    "gn:feature_class":"P",
    "gn:feature_code":"PPL",
    "gn:name":"Pou\u010dn\u00edk",
    "gn:population":0,
    "gn:timezone":"Europe/Prague",
    "iso:country":"CZ",
    "wof:name":"Poucnik",
    "wof:placetype":"locality"
},
  "geometry": {"coordinates":[14.18049,49.93108],"type":"Point"}
}