{
  "type": "Feature",
  "properties": {
    "gn:admin1_code":"86.0",
    "gn:admin2_code":"0534",
    "gn:asciiname":"Horni Lipka",
    "gn:country_code":"CZ",
    "gn:dem":613,
    "gn:feature_class":"P",
    "gn:feature_code":"PPL",
    "gn:name":"Horn\u00ed Lipka",
    "gn:population":0,
    "gn:timezone":"Europe/Prague",
    "iso:country":"CZ",
    "name:und_x_variant":[
        "Lipka",
        "Ober-Lipka"
    ],
    "wof:name":"Horni Lipka",
    "wof:placetype":"locality"
},
  "geometry": {"coordinates":[16.77046,50.11788],"type":"Point"}
}