{
  "type": "Feature",
  "properties": {
    "gn:gn_country":"CZ",
    "gn:gn_fcode":"PPL",
    "gn:gn_pop":188,
    "gn:population":188,
    "iso:country":"CZ",
    "name:ceb_x_preferred":[
        "Nov\u00e9 Dvory"
    ],
    "name:ces_x_preferred":[
        "Nov\u00e9 Dvory"
    ],
    "name:deu_x_preferred":[
        "Nov\u00e9 Dvory"
    ],
    "name:epo_x_preferred":[
        "Nov\u00e9 Dvory"
    ],
    "name:fra_x_preferred":[
        "Nov\u00e9 Dvory"
    ],
    "name:ita_x_preferred":[
        "Nov\u00e9 Dvory"
    ],
    "name:nld_x_preferred":[
        "Nov\u00e9 Dvory"
    ],
    "name:slk_x_preferred":[
        "Nov\u00e9 Dvory"
    ],
    "name:srp_x_preferred":[
        "\u041d\u043e\u0432\u0435 \u0414\u0432\u043e\u0440\u0438"
    ],
    "name:swe_x_preferred":[
        "Nov\u00e9 Dvory"
    ],
    "name:unk_x_variant":[
        "Nenhof"
    ],
    "qs_pg:aaroncc":"CZ",
    "qs_pg:gn_country":"CZ",
    "qs_pg:gn_fcode":"PPL",
    "qs_pg:gn_pop":188,
    "qs_pg:name":"Nov\u00e9 Dvory",
    "qs_pg:photos_9r":0,
    "qs_pg:photos_sr":0,
    "qs_pg:pop_sr":1,
    "qs_pg:qs_pg_placetype":"locality",
    "wof:name":"Nov\u00e9 Dvory",
    "wof:placetype":"locality",
    "wof:population":188
},
  "geometry": {"coordinates":[14.35692,49.80322],"type":"Point"}
}