{
  "type": "Feature",
  "properties": {
    "gn:admin1_code":"87.0",
    "gn:admin2_code":"0327",
    "gn:asciiname":"Lazany",
    "gn:country_code":"CZ",
    "gn:dem":499,
    "gn:feature_class":"P",
    "gn:feature_code":"PPL",
    "gn:name":"La\u017eany",
    "gn:population":0,
    "gn:timezone":"Europe/Prague",
    "iso:country":"CZ",
    "name:deu_x_preferred":[
        "Lazany"
    ],
    "name:epo_x_preferred":[
        "Lazany"
    ],
    "name:eus_x_preferred":[
        "Lazany"
    ],
    "name:hun_x_preferred":[
        "Lazany"
    ],
    "name:slk_x_preferred":[
        "Lazany"
    ],
    "name:und_x_variant":[
        "Losau",
        "La\u017eany"
    ],
    "wof:name":"Lazany",
    "wof:placetype":"locality"
},
  "geometry": {"coordinates":[12.88089,49.79908],"type":"Point"}
}