{
  "type": "Feature",
  "properties": {
    "gn:gn_country":"CZ",
    "gn:gn_fcode":"PPL",
    "gn:gn_pop":83,
    "gn:population":83,
    "iso:country":"CZ",
    "name:ces_x_preferred":[
        "Chrtn\u00edky"
    ],
    "name:deu_x_preferred":[
        "Chrtn\u00edky"
    ],
    "name:eng_x_preferred":[
        "Chrtn\u00edky"
    ],
    "name:epo_x_preferred":[
        "Chrtn\u00edky"
    ],
    "name:eus_x_preferred":[
        "Chrtn\u00edky"
    ],
    "name:fra_x_preferred":[
        "Chrtn\u00edky"
    ],
    "name:hun_x_preferred":[
        "Chrtn\u00edky"
    ],
    "name:ita_x_preferred":[
        "Chrtn\u00edky"
    ],
    "name:msa_x_preferred":[
        "Chrtn\u00edky"
    ],
    "name:nan_x_preferred":[
        "Chrtn\u00edky"
    ],
    "name:nld_x_preferred":[
        "Chrtn\u00edky"
    ],
    "name:pol_x_preferred":[
        "Chrtn\u00edky"
    ],
    "name:por_x_preferred":[
        "Chrtn\u00edky"
    ],
    "name:slk_x_preferred":[
        "Chrtn\u00edky"
    ],
    "name:spa_x_preferred":[
        "Chrtn\u00edky"
    ],
    "name:srp_x_preferred":[
        "\u0425\u0440\u0442\u045a\u0438\u043a\u0438"
    ],
    "name:vie_x_preferred":[
        "Chrtn\u00edky"
    ],
    "qs_pg:aaroncc":"CZ",
    "qs_pg:gn_country":"CZ",
    "qs_pg:gn_fcode":"PPL",
    "qs_pg:gn_pop":83,
    "qs_pg:name":"Chrtn\u00edky",
    "qs_pg:name_adm0":"\u010cesk\u00e1 republika",
    "qs_pg:name_adm1":"Pardubick\u00fd kraj",
    "qs_pg:photos_9r":0,
    "qs_pg:photos_sr":0,
    "qs_pg:pop_sr":1,
    "qs_pg:qs_pg_placetype":"locality",
    "qs_pg:qs_pg_placetype_gp":"Town",
    "qs_pg:woe_adm0":23424810,
    "woe:adm0_id":23424810,
    "woe:name_adm0":"\u010cesk\u00e1 republika",
    "woe:name_adm1":"Pardubick\u00fd kraj",
    "woe:placetype":"Town",
    "wof:name":"Chrtn\u00edky",
    "wof:placetype":"locality",
    "wof:population":83
},
  "geometry": {"coordinates":[15.60485,49.9818],"type":"Point"}
}