{
  "type": "Feature",
  "properties": {
    "gn:admin1_code":"80",
    "gn:admin2_code":"0615",
    "gn:asciiname":"Vojtechov",
    "gn:country_code":"CZ",
    "gn:dem":637,
    "gn:feature_class":"P",
    "gn:feature_code":"PPL",
    "gn:name":"Vojt\u011bchov",
    "gn:population":0,
    "gn:timezone":"Europe/Prague",
    "iso:country":"CZ",
    "wof:name":"Vojtechov",
    "wof:placetype":"locality"
},
  "geometry": {"coordinates":[16.16167,49.56798],"type":"Point"}
}