{
  "type": "Feature",
  "properties": {
    "gn:country":"CZ",
    "gn:fcode":"PPL",
    "gn:population":202,
    "iso:country":"CZ",
    "name:azb_x_preferred":[
        "\u0634\u0631\u06a9\u0648\u0648\u06cc\u062a\u0633\u0647"
    ],
    "name:cat_x_preferred":[
        "\u0160erkovice"
    ],
    "name:ceb_x_preferred":[
        "\u0160erkovice"
    ],
    "name:ces_x_preferred":[
        "\u0160erkovice"
    ],
    "name:che_x_preferred":[
        "\u0428\u0435\u0440\u043a\u043e\u0432\u0438\u0446\u0435"
    ],
    "name:deu_x_preferred":[
        "\u0160erkovice"
    ],
    "name:eng_x_preferred":[
        "\u0160erkovice"
    ],
    "name:epo_x_preferred":[
        "\u0160erkovice"
    ],
    "name:eus_x_preferred":[
        "\u0160erkovice"
    ],
    "name:fas_x_preferred":[
        "\u0634\u0631\u06a9\u0648\u0648\u06cc\u062a\u0633\u0647"
    ],
    "name:fra_x_preferred":[
        "\u0160erkovice"
    ],
    "name:gle_x_preferred":[
        "\u0160erkovice"
    ],
    "name:hun_x_preferred":[
        "\u0160erkovice"
    ],
    "name:ita_x_preferred":[
        "\u0160erkovice"
    ],
    "name:lmo_x_preferred":[
        "\u0160erkovice"
    ],
    "name:msa_x_preferred":[
        "\u0160erkovice"
    ],
    "name:nan_x_preferred":[
        "\u0160erkovice"
    ],
    "name:nld_x_preferred":[
        "\u0160erkovice"
    ],
    "name:pol_x_preferred":[
        "\u0160erkovice"
    ],
    "name:por_x_preferred":[
        "\u0160erkovice"
    ],
    "name:rup_x_preferred":[
        "\u0160erkovice"
    ],
    "name:slk_x_preferred":[
        "\u0160erkovice"
    ],
    "name:spa_x_preferred":[
        "\u0160erkovice"
    ],
    "name:swe_x_preferred":[
        "\u0160erkovice"
    ],
    "name:tat_x_preferred":[
        "\u0428\u0435\u0440\u043a\u043e\u0432\u0438\u0446\u0435"
    ],
    "name:vie_x_preferred":[
        "\u0160erkovice"
    ],
    "qs_pg:aaroncc":"CZ",
    "qs_pg:gn_country":"CZ",
    "qs_pg:gn_fcode":"PPL",
    "qs_pg:gn_pop":202,
    "qs_pg:name":"\u0160erkovice",
    "qs_pg:photos_9r":0,
    "qs_pg:photos_sr":0,
    "qs_pg:pop_sr":2,
    "qs_pg:qs_pg_placetype":"locality",
    "wof:name":"\u0160erkovice",
    "wof:placetype":"locality",
    "wof:population":202
},
  "geometry": {"coordinates":[16.42996,49.38558],"type":"Point"}
}