{
  "type": "Feature",
  "properties": {
    "gn:admin1_code":"88.0",
    "gn:admin2_code":"0205",
    "gn:asciiname":"Kamenne Mosty",
    "gn:country_code":"CZ",
    "gn:dem":259,
    "gn:feature_class":"P",
    "gn:feature_code":"PPL",
    "gn:name":"Kamenn\u00e9 Mosty",
    "gn:population":0,
    "gn:timezone":"Europe/Prague",
    "iso:country":"CZ",
    "wof:name":"Kamenne Mosty",
    "wof:placetype":"locality"
},
  "geometry": {"coordinates":[15.49483,49.86313],"type":"Point"}
}