{
  "type": "Feature",
  "properties": {
    "gn:gn_country":"CZ",
    "gn:gn_fcode":"PPL",
    "gn:gn_pop":522,
    "gn:population":522,
    "iso:country":"CZ",
    "name:cze_x_preferred":[
        "V\u0161elibice"
    ],
    "name:dut_x_preferred":[
        "V\u0161elibice"
    ],
    "name:eng_x_preferred":[
        "V\u0161elibice"
    ],
    "name:fre_x_preferred":[
        "V\u0161elibice"
    ],
    "name:ger_x_preferred":[
        "V\u0161elibice"
    ],
    "name:hun_x_preferred":[
        "V\u0161elibice"
    ],
    "name:ita_x_preferred":[
        "V\u0161elibice"
    ],
    "name:may_x_preferred":[
        "V\u0161elibice"
    ],
    "name:pol_x_preferred":[
        "V\u0161elibice"
    ],
    "name:por_x_preferred":[
        "V\u0161elibice"
    ],
    "name:slo_x_preferred":[
        "V\u0161elibice"
    ],
    "name:srp_x_preferred":[
        "\u0412\u0448\u0435\u043b\u0438\u0431\u0438\u0446\u0435"
    ],
    "name:swe_x_preferred":[
        "V\u0161elibice"
    ],
    "name:vie_x_preferred":[
        "V\u0161elibice"
    ],
    "qs_pg:aaroncc":"CZ",
    "qs_pg:gn_country":"CZ",
    "qs_pg:gn_fcode":"PPL",
    "qs_pg:gn_pop":522,
    "qs_pg:name":"V\u0161elibice",
    "qs_pg:name_adm0":"\u010cesk\u00e1 republika",
    "qs_pg:name_adm1":"Libereck\u00fd kraj",
    "qs_pg:photos_9r":0,
    "qs_pg:photos_sr":0,
    "qs_pg:pop_sr":2,
    "qs_pg:qs_pg_placetype":"locality",
    "qs_pg:qs_pg_placetype_gp":"Town",
    "qs_pg:woe_adm0":23424810,
    "woe:adm0_id":23424810,
    "woe:name_adm0":"\u010cesk\u00e1 republika",
    "woe:name_adm1":"Libereck\u00fd kraj",
    "woe:placetype":"Town",
    "wof:name":"V\u0161elibice",
    "wof:placetype":"locality",
    "wof:population":522
},
  "geometry": {"coordinates":[14.95138,50.64605],"type":"Point"}
}