{
  "type": "Feature",
  "properties": {
    "gn:admin1_code":"81.0",
    "gn:admin2_code":"0412",
    "gn:asciiname":"Semtes",
    "gn:country_code":"CZ",
    "gn:dem":576,
    "gn:feature_class":"P",
    "gn:feature_code":"PPL",
    "gn:name":"Semt\u011b\u0161",
    "gn:population":0,
    "gn:timezone":"Europe/Prague",
    "iso:country":"CZ",
    "wof:name":"Semtes",
    "wof:placetype":"locality"
},
  "geometry": {"coordinates":[13.1449,50.07115],"type":"Point"}
}