{
  "type": "Feature",
  "properties": {
    "gn:admin1_code":"82.0",
    "gn:admin2_code":"0524",
    "gn:asciiname":"Nemanice",
    "gn:country_code":"CZ",
    "gn:dem":554,
    "gn:feature_class":"P",
    "gn:feature_code":"PPL",
    "gn:name":"Nemanice",
    "gn:population":0,
    "gn:timezone":"Europe/Prague",
    "iso:country":"CZ",
    "name:azb_x_preferred":[
        "\u0646\u0645\u0627\u0646\u06cc\u062a\u0633\u0647"
    ],
    "name:ceb_x_preferred":[
        "Nemanice"
    ],
    "name:ces_x_preferred":[
        "Nemanice"
    ],
    "name:deu_x_preferred":[
        "Nemanice"
    ],
    "name:eus_x_preferred":[
        "Nemanice"
    ],
    "name:fas_x_preferred":[
        "\u0646\u0645\u0627\u0646\u06cc\u062a\u0633\u0647"
    ],
    "name:fra_x_preferred":[
        "Nemanice"
    ],
    "name:hun_x_preferred":[
        "Nemanice"
    ],
    "name:ita_x_preferred":[
        "Nemanice"
    ],
    "name:msa_x_preferred":[
        "Nemanice"
    ],
    "name:nld_x_preferred":[
        "Nemanice"
    ],
    "name:pol_x_preferred":[
        "Nemanice"
    ],
    "name:por_x_preferred":[
        "Nemanice"
    ],
    "name:slk_x_preferred":[
        "Nemanice"
    ],
    "name:spa_x_preferred":[
        "Nemanice"
    ],
    "name:srp_x_preferred":[
        "\u041d\u0435\u043c\u0430\u045a\u0438\u0446\u0435"
    ],
    "name:swe_x_preferred":[
        "Nemanice"
    ],
    "name:vie_x_preferred":[
        "Nemanice"
    ],
    "wof:name":"Nemanice",
    "wof:placetype":"locality"
},
  "geometry": {"coordinates":[16.35571,50.20717],"type":"Point"}
}