{
  "type": "Feature",
  "properties": {
    "gn:admin1_code":"79.0",
    "gn:admin2_code":"0314",
    "gn:asciiname":"Predborice",
    "gn:country_code":"CZ",
    "gn:dem":510,
    "gn:feature_class":"P",
    "gn:feature_code":"PPL",
    "gn:name":"P\u0159edbo\u0159ice",
    "gn:population":0,
    "gn:timezone":"Europe/Prague",
    "iso:country":"CZ",
    "wof:name":"Predborice",
    "wof:placetype":"locality"
},
  "geometry": {"coordinates":[14.27401,49.54763],"type":"Point"}
}