{
  "type": "Feature",
  "properties": {
    "gn:admin1_code":"84.0",
    "gn:admin2_code":"0713",
    "gn:asciiname":"Snehotice",
    "gn:country_code":"CZ",
    "gn:dem":266,
    "gn:feature_class":"P",
    "gn:feature_code":"PPL",
    "gn:name":"Sn\u011bhotice",
    "gn:population":0,
    "gn:timezone":"Europe/Prague",
    "iso:country":"CZ",
    "wof:name":"Snehotice",
    "wof:placetype":"locality"
},
  "geometry": {"coordinates":[17.06667,49.36667],"type":"Point"}
}