{
  "type": "Feature",
  "properties": {
    "iso:country":"CZ",
    "name:ceb_x_preferred":[
        "\u00da\u0161t\u011bk"
    ],
    "name:ces_x_preferred":[
        "\u00da\u0161t\u011bk"
    ],
    "name:deu_x_preferred":[
        "\u00da\u0161t\u011bk"
    ],
    "name:epo_x_preferred":[
        "\u00da\u0161t\u011bk"
    ],
    "name:eus_x_preferred":[
        "\u00da\u0161t\u011bk"
    ],
    "name:fas_x_preferred":[
        "\u0627\u0648\u0634\u062a\u06cc\u06a9"
    ],
    "name:fra_x_preferred":[
        "\u00da\u0161t\u011bk"
    ],
    "name:hun_x_preferred":[
        "\u00da\u0161t\u011bk"
    ],
    "name:ita_x_preferred":[
        "\u00da\u0161t\u011bk"
    ],
    "name:msa_x_preferred":[
        "\u00da\u0161t\u011bk"
    ],
    "name:nld_x_preferred":[
        "\u00da\u0161t\u011bk"
    ],
    "name:pol_x_preferred":[
        "\u00da\u0161t\u011bk"
    ],
    "name:por_x_preferred":[
        "\u00da\u0161t\u011bk"
    ],
    "name:ron_x_preferred":[
        "\u00da\u0161t\u011bk"
    ],
    "name:rus_x_preferred":[
        "\u0423\u0448\u0442\u0435\u043a"
    ],
    "name:slk_x_preferred":[
        "\u00da\u0161t\u011bk"
    ],
    "name:spa_x_preferred":[
        "\u00da\u0161t\u011bk"
    ],
    "name:srp_x_preferred":[
        "\u0423\u0448\u0442\u0458\u0435\u043a"
    ],
    "name:swe_x_preferred":[
        "\u00da\u0161t\u011bk"
    ],
    "name:vie_x_preferred":[
        "\u00da\u0161t\u011bk"
    ],
    "name:zho_x_preferred":[
        "\u70cf\u4ec0\u6377\u514b"
    ],
    "qs_pg:aaroncc":"CZ",
    "qs_pg:name":"\u00da\u0161t\u011bk",
    "qs_pg:name_adm0":"\u010cesk\u00e1 republika",
    "qs_pg:name_adm1":"\u00dasteck\u00fd kraj",
    "qs_pg:photos":2,
    "qs_pg:photos_1k":1,
    "qs_pg:photos_9k":1,
    "qs_pg:photos_9r":3,
    "qs_pg:photos_all":131,
    "qs_pg:photos_sr":1,
    "qs_pg:pop_sr":0,
    "qs_pg:qs_pg_placetype":"localadmin",
    "qs_pg:qs_pg_placetype_gp":"LocalAdmin",
    "qs_pg:woe_adm0":23424810,
    "woe:adm0_id":23424810,
    "woe:name_adm0":"\u010cesk\u00e1 republika",
    "woe:name_adm1":"\u00dasteck\u00fd kraj",
    "woe:placetype":"LocalAdmin",
    "wof:name":"\u00da\u0161t\u011bk",
    "wof:placetype":"localadmin"
},
  "geometry": {"coordinates":[14.344689,50.585144],"type":"Point"}
}