{
  "type": "Feature",
  "properties": {
    "gn:gn_country":"CZ",
    "gn:gn_fcode":"PPL",
    "gn:gn_pop":341,
    "gn:population":341,
    "iso:country":"CZ",
    "name:azb_x_preferred":[
        "\u06a9\u0631\u0646\u0627\u0646\u06cc"
    ],
    "name:ceb_x_preferred":[
        "Kr\u0148any"
    ],
    "name:ces_x_preferred":[
        "Kr\u0148any"
    ],
    "name:deu_x_preferred":[
        "Kr\u0148any"
    ],
    "name:eng_x_preferred":[
        "Kr\u0148any"
    ],
    "name:eus_x_preferred":[
        "Kr\u0148any"
    ],
    "name:fas_x_preferred":[
        "\u06a9\u0631\u0646\u0627\u0646\u06cc"
    ],
    "name:fra_x_preferred":[
        "Kr\u0148any"
    ],
    "name:hun_x_preferred":[
        "Kr\u0148any"
    ],
    "name:ita_x_preferred":[
        "Kr\u0148any"
    ],
    "name:msa_x_preferred":[
        "Kr\u0148any"
    ],
    "name:nan_x_preferred":[
        "Kr\u0148any"
    ],
    "name:nld_x_preferred":[
        "Kr\u0148any"
    ],
    "name:oci_x_preferred":[
        "Kr\u0148any"
    ],
    "name:pol_x_preferred":[
        "Kr\u0148any"
    ],
    "name:por_x_preferred":[
        "Kr\u0148any"
    ],
    "name:slk_x_preferred":[
        "Kr\u0148any"
    ],
    "name:spa_x_preferred":[
        "Kr\u0148any"
    ],
    "name:srp_x_preferred":[
        "\u041a\u0440\u045a\u0430\u043d\u0438"
    ],
    "name:swe_x_preferred":[
        "Kr\u0148any"
    ],
    "name:unk_x_variant":[
        "Krinian"
    ],
    "name:vie_x_preferred":[
        "Kr\u0148any"
    ],
    "qs_pg:aaroncc":"CZ",
    "qs_pg:gn_country":"CZ",
    "qs_pg:gn_fcode":"PPL",
    "qs_pg:gn_pop":341,
    "qs_pg:name":"Kr\u0148any",
    "qs_pg:name_adm0":"\u010cesk\u00e1 republika",
    "qs_pg:name_adm1":"St\u0159edo\u010desk\u00fd kraj",
    "qs_pg:photos":4,
    "qs_pg:photos_1k":1,
    "qs_pg:photos_9k":1,
    "qs_pg:photos_9r":1,
    "qs_pg:photos_all":4,
    "qs_pg:photos_sr":1,
    "qs_pg:pop_sr":2,
    "qs_pg:qs_pg_placetype":"locality",
    "qs_pg:qs_pg_placetype_gp":"Town",
    "qs_pg:woe_adm0":23424810,
    "woe:adm0_id":23424810,
    "woe:name_adm0":"\u010cesk\u00e1 republika",
    "woe:name_adm1":"St\u0159edo\u010desk\u00fd kraj",
    "woe:placetype":"Town",
    "wof:name":"Kr\u0148any",
    "wof:placetype":"locality",
    "wof:population":341
},
  "geometry": {"coordinates":[14.47745,49.84481],"type":"Point"}
}