{
  "type": "Feature",
  "properties": {
    "gn:admin1_code":"79.0",
    "gn:admin2_code":"0312",
    "gn:asciiname":"Podoli",
    "gn:country_code":"CZ",
    "gn:dem":683,
    "gn:feature_class":"P",
    "gn:feature_code":"PPL",
    "gn:name":"Podol\u00ed",
    "gn:population":0,
    "gn:timezone":"Europe/Prague",
    "iso:country":"CZ",
    "name:und_x_variant":[
        "Unter Heiming",
        "Podol\u00ed"
    ],
    "wof:name":"Podoli",
    "wof:placetype":"locality"
},
  "geometry": {"coordinates":[14.26667,48.71667],"type":"Point"}
}