{
  "type": "Feature",
  "properties": {
    "gn:gn_country":"CZ",
    "gn:gn_fcode":"PPL",
    "gn:gn_pop":269,
    "gn:population":269,
    "iso:country":"CZ",
    "name:cze_x_preferred":[
        "Uh\u0159\u00ednov"
    ],
    "name:dut_x_preferred":[
        "Uh\u0159\u00ednov"
    ],
    "name:eng_x_preferred":[
        "Uh\u0159\u00ednov"
    ],
    "name:fre_x_preferred":[
        "Uh\u0159\u00ednov"
    ],
    "name:ger_x_preferred":[
        "Uh\u0159\u00ednov"
    ],
    "name:hun_x_preferred":[
        "Uh\u0159\u00ednov"
    ],
    "name:ita_x_preferred":[
        "Uh\u0159\u00ednov"
    ],
    "name:may_x_preferred":[
        "Uh\u0159\u00ednov"
    ],
    "name:per_x_preferred":[
        "\u0627\u0648\u0647\u0631\u06cc\u0646\u0648\u0648"
    ],
    "name:por_x_preferred":[
        "Uh\u0159\u00ednov"
    ],
    "name:slo_x_preferred":[
        "Uh\u0159\u00ednov"
    ],
    "name:swe_x_preferred":[
        "Uh\u0159\u00ednov"
    ],
    "name:vie_x_preferred":[
        "Uh\u0159\u00ednov"
    ],
    "qs_pg:aaroncc":"CZ",
    "qs_pg:gn_country":"CZ",
    "qs_pg:gn_fcode":"PPL",
    "qs_pg:gn_pop":269,
    "qs_pg:name":"Uh\u0159\u00ednov",
    "qs_pg:name_adm0":"\u010cesk\u00e1 republika",
    "qs_pg:name_adm1":"Kraj Vyso\u010dina",
    "qs_pg:photos_9r":0,
    "qs_pg:photos_sr":0,
    "qs_pg:pop_sr":2,
    "qs_pg:qs_pg_placetype":"locality",
    "qs_pg:qs_pg_placetype_gp":"Town",
    "qs_pg:woe_adm0":23424810,
    "woe:adm0_id":23424810,
    "woe:name_adm0":"\u010cesk\u00e1 republika",
    "woe:name_adm1":"Kraj Vyso\u010dina",
    "woe:placetype":"Town",
    "wof:name":"Uh\u0159\u00ednov",
    "wof:placetype":"locality",
    "wof:population":269
},
  "geometry": {"coordinates":[15.93795,49.34983],"type":"Point"}
}