{
  "type": "Feature",
  "properties": {
    "gn:country":"CZ",
    "gn:fcode":"PPL",
    "gn:population":1805,
    "iso:country":"CZ",
    "name:cat_x_preferred":[
        "Teplice nad Metuj\u00ed"
    ],
    "name:ceb_x_preferred":[
        "Teplice nad Metuj\u00ed"
    ],
    "name:ces_x_preferred":[
        "Teplice nad Metuj\u00ed"
    ],
    "name:dan_x_preferred":[
        "Teplice nad Metuj\u00ed"
    ],
    "name:deu_x_preferred":[
        "Teplice nad Metuj\u00ed"
    ],
    "name:eng_x_preferred":[
        "Teplice nad Metuj\u00ed"
    ],
    "name:est_x_preferred":[
        "Teplice nad Metuj\u00ed"
    ],
    "name:eus_x_preferred":[
        "Teplice nad Metuj\u00ed"
    ],
    "name:fas_x_preferred":[
        "\u062a\u067e\u0644\u06cc\u062a\u0633\u0647 \u0646\u0627\u062f \u0645\u062a\u0648\u06cc\u06cc"
    ],
    "name:fra_x_preferred":[
        "Teplice nad Metuj\u00ed"
    ],
    "name:gle_x_preferred":[
        "Teplice nad Metuj\u00ed"
    ],
    "name:hun_x_preferred":[
        "Teplice nad Metuj\u00ed"
    ],
    "name:ita_x_preferred":[
        "Teplice nad Metuj\u00ed"
    ],
    "name:lmo_x_preferred":[
        "Teplice nad Metuj\u00ed"
    ],
    "name:msa_x_preferred":[
        "Teplice nad Metuj\u00ed"
    ],
    "name:nan_x_preferred":[
        "Teplice nad Metuj\u00ed"
    ],
    "name:nld_x_preferred":[
        "Teplice nad Metuj\u00ed"
    ],
    "name:nob_x_preferred":[
        "Teplice nad Metuj\u00ed"
    ],
    "name:pol_x_preferred":[
        "Teplice nad Metuj\u00ed"
    ],
    "name:por_x_preferred":[
        "Teplice nad Metuj\u00ed"
    ],
    "name:ron_x_preferred":[
        "Teplice nad Metuj\u00ed"
    ],
    "name:rup_x_preferred":[
        "Teplice nad Metuj\u00ed"
    ],
    "name:slk_x_preferred":[
        "Teplice nad Metuj\u00ed"
    ],
    "name:spa_x_preferred":[
        "Teplice nad Metuj\u00ed"
    ],
    "name:srp_x_preferred":[
        "\u0422\u0435\u043f\u043b\u0438\u0446\u0435 \u043d\u0430 \u041c\u0435\u0442\u0443\u0458\u0438"
    ],
    "name:swe_x_preferred":[
        "Teplice nad Metuj\u00ed"
    ],
    "name:tat_x_preferred":[
        "\u0422\u0435\u043f\u043b\u0438\u0442\u0441\u0435-\u043d\u0430\u0434-\u041c\u0435\u0442\u0443\u0438"
    ],
    "name:und_x_variant":[
        "Wekelsdorf"
    ],
    "name:vie_x_preferred":[
        "Teplice nad Metuj\u00ed"
    ],
    "name:zho_x_preferred":[
        "\u6885\u5716\u8036\u6cb3\u7554\u7279\u666e\u5229\u91c7"
    ],
    "qs_pg:aaroncc":"CZ",
    "qs_pg:gn_country":"CZ",
    "qs_pg:gn_fcode":"PPL",
    "qs_pg:gn_pop":1805,
    "qs_pg:name":"Teplice nad Metuj\u00ed",
    "qs_pg:name_adm0":"\u010cesk\u00e1 republika",
    "qs_pg:name_adm1":"Kr\u00e1lov\u00e9hradeck\u00fd kraj",
    "qs_pg:photos":124,
    "qs_pg:photos_1k":25,
    "qs_pg:photos_9k":1,
    "qs_pg:photos_9r":3,
    "qs_pg:photos_all":124,
    "qs_pg:photos_sr":3,
    "qs_pg:pop_sr":3,
    "qs_pg:qs_pg_placetype":"locality",
    "qs_pg:qs_pg_placetype_gp":"Town",
    "qs_pg:woe_adm0":23424810,
    "woe:adm0_id":23424810,
    "woe:name_adm0":"\u010cesk\u00e1 republika",
    "woe:name_adm1":"Kr\u00e1lov\u00e9hradeck\u00fd kraj",
    "woe:placetype":"Town",
    "wof:name":"Teplice nad Metuj\u00ed",
    "wof:placetype":"locality",
    "wof:population":1805
},
  "geometry": {"coordinates":[16.17026,50.59332],"type":"Point"}
}