{
  "type": "Feature",
  "properties": {
    "iso:country":"CZ",
    "name:ceb_x_preferred":[
        "Ku\u0159im"
    ],
    "name:ces_x_preferred":[
        "Ku\u0159im"
    ],
    "name:deu_x_preferred":[
        "Ku\u0159im"
    ],
    "name:epo_x_preferred":[
        "Ku\u0159im"
    ],
    "name:eus_x_preferred":[
        "Ku\u0159im"
    ],
    "name:fra_x_preferred":[
        "Ku\u0159im"
    ],
    "name:hun_x_preferred":[
        "Ku\u0159im"
    ],
    "name:ita_x_preferred":[
        "Ku\u0159im"
    ],
    "name:lav_x_preferred":[
        "Kur\u017eima"
    ],
    "name:msa_x_preferred":[
        "Ku\u0159im"
    ],
    "name:nld_x_preferred":[
        "Ku\u0159im"
    ],
    "name:pol_x_preferred":[
        "Ku\u0159im"
    ],
    "name:por_x_preferred":[
        "Ku\u0159im"
    ],
    "name:slk_x_preferred":[
        "Ku\u0159im"
    ],
    "name:spa_x_preferred":[
        "Ku\u0159im"
    ],
    "name:srp_x_preferred":[
        "\u041a\u0443\u0440\u0436\u0438\u043c"
    ],
    "name:swe_x_preferred":[
        "Ku\u0159im"
    ],
    "name:vie_x_preferred":[
        "Ku\u0159im"
    ],
    "name:zho_x_preferred":[
        "\u5eab\u65e5\u59c6"
    ],
    "qs_pg:aaroncc":"CZ",
    "qs_pg:name":"Ku\u0159im",
    "qs_pg:name_adm0":"\u010cesk\u00e1 republika",
    "qs_pg:name_adm1":"Jihomoravsk\u00fd kraj",
    "qs_pg:photos":1,
    "qs_pg:photos_1k":1,
    "qs_pg:photos_9k":1,
    "qs_pg:photos_9r":2,
    "qs_pg:photos_all":58,
    "qs_pg:photos_sr":1,
    "qs_pg:pop_sr":0,
    "qs_pg:qs_pg_placetype":"localadmin",
    "qs_pg:qs_pg_placetype_gp":"LocalAdmin",
    "qs_pg:woe_adm0":23424810,
    "woe:adm0_id":23424810,
    "woe:name_adm0":"\u010cesk\u00e1 republika",
    "woe:name_adm1":"Jihomoravsk\u00fd kraj",
    "woe:placetype":"LocalAdmin",
    "wof:name":"Ku\u0159im",
    "wof:placetype":"localadmin"
},
  "geometry": {"coordinates":[16.535389,49.295135],"type":"Point"}
}