{
  "type": "Feature",
  "properties": {
    "gn:admin1_code":"87.0",
    "gn:admin2_code":"0327",
    "gn:asciiname":"Ceckovice",
    "gn:country_code":"CZ",
    "gn:dem":477,
    "gn:feature_class":"P",
    "gn:feature_code":"PPL",
    "gn:name":"\u010ce\u010dkovice",
    "gn:population":0,
    "gn:timezone":"Europe/Prague",
    "iso:country":"CZ",
    "name:und_x_variant":[
        "Eschowitz",
        "\u010ce\u010dkovice"
    ],
    "wof:name":"Ceckovice",
    "wof:placetype":"locality"
},
  "geometry": {"coordinates":[12.78293,49.73139000000001],"type":"Point"}
}