{
  "type": "Feature",
  "properties": {
    "gn:admin1_code":"80.0",
    "gn:admin2_code":"0615",
    "gn:asciiname":"Horni Cepi",
    "gn:country_code":"CZ",
    "gn:dem":485,
    "gn:feature_class":"P",
    "gn:feature_code":"PPL",
    "gn:name":"Horn\u00ed \u010cep\u00ed",
    "gn:population":0,
    "gn:timezone":"Europe/Prague",
    "iso:country":"CZ",
    "wof:name":"Horni Cepi",
    "wof:placetype":"locality"
},
  "geometry": {"coordinates":[16.3569,49.48678],"type":"Point"}
}