{
  "type": "Feature",
  "properties": {
    "gn:admin1_code":"83",
    "gn:admin2_code":"0511",
    "gn:asciiname":"Straz u Ceske Lipy",
    "gn:country_code":"CZ",
    "gn:dem":287,
    "gn:feature_class":"P",
    "gn:feature_code":"PPL",
    "gn:name":"Str\u00e1\u017e u \u010cesk\u00e9 L\u00edpy",
    "gn:population":0,
    "gn:timezone":"Europe/Prague",
    "iso:country":"CZ",
    "name:und_x_variant":[
        "Sch\u00f6nborn",
        "Str\u00e1\u017e u \u010cesk\u00e9 L\u00edpy"
    ],
    "wof:name":"Straz u Ceske Lipy",
    "wof:placetype":"locality"
},
  "geometry": {"coordinates":[14.46931,50.6822],"type":"Point"}
}