{
  "type": "Feature",
  "properties": {
    "gn:gn_country":"CZ",
    "gn:gn_fcode":"PPL",
    "gn:gn_pop":245,
    "gn:population":245,
    "iso:country":"CZ",
    "name:bul_x_preferred":[
        "\u0411\u0440\u0437\u043a\u043e\u0432"
    ],
    "name:cze_x_preferred":[
        "Brzkov"
    ],
    "name:dut_x_preferred":[
        "Brzkov"
    ],
    "name:eng_x_preferred":[
        "Brzkov"
    ],
    "name:fre_x_preferred":[
        "Brzkov"
    ],
    "name:hun_x_preferred":[
        "Brzkov"
    ],
    "name:ita_x_preferred":[
        "Brzkov"
    ],
    "name:may_x_preferred":[
        "Brzkov"
    ],
    "name:per_x_preferred":[
        "\u0628\u0631\u0632\u06a9\u0648\u0648"
    ],
    "name:pol_x_preferred":[
        "Brzkov"
    ],
    "name:por_x_preferred":[
        "Brzkov"
    ],
    "name:rup_x_preferred":[
        "Brzkov"
    ],
    "name:slo_x_preferred":[
        "Brzkov"
    ],
    "name:srp_x_preferred":[
        "\u0411\u0440\u0441\u043a\u043e\u0432"
    ],
    "name:swe_x_preferred":[
        "Brzkov"
    ],
    "name:urd_x_preferred":[
        "\u0628\u0631\u0632\u06a9\u0648\u0648"
    ],
    "name:vie_x_preferred":[
        "Brzkov"
    ],
    "qs_pg:aaroncc":"CZ",
    "qs_pg:gn_country":"CZ",
    "qs_pg:gn_fcode":"PPL",
    "qs_pg:gn_pop":245,
    "qs_pg:name":"Brzkov",
    "qs_pg:name_adm0":"\u010cesk\u00e1 republika",
    "qs_pg:name_adm1":"Kraj Vyso\u010dina",
    "qs_pg:photos_9r":0,
    "qs_pg:photos_sr":0,
    "qs_pg:pop_sr":2,
    "qs_pg:qs_pg_placetype":"locality",
    "qs_pg:qs_pg_placetype_gp":"Town",
    "qs_pg:woe_adm0":23424810,
    "woe:adm0_id":23424810,
    "woe:name_adm0":"\u010cesk\u00e1 republika",
    "woe:name_adm1":"Kraj Vyso\u010dina",
    "woe:placetype":"Town",
    "wof:name":"Brzkov",
    "wof:placetype":"locality",
    "wof:population":245
},
  "geometry": {"coordinates":[15.72714,49.52597],"type":"Point"}
}