{
  "type": "Feature",
  "properties": {
    "gn:admin1_code":"89.0",
    "gn:admin2_code":"0422",
    "gn:asciiname":"Petlery",
    "gn:country_code":"CZ",
    "gn:dem":534,
    "gn:feature_class":"P",
    "gn:feature_code":"PPL",
    "gn:name":"Petlery",
    "gn:population":36,
    "gn:timezone":"Europe/Prague",
    "iso:country":"CZ",
    "name:deu_x_preferred":[
        "Bettlern"
    ],
    "wof:name":"Petlery",
    "wof:placetype":"locality",
    "wof:population":36
},
  "geometry": {"coordinates":[13.16105,50.41306],"type":"Point"}
}