{
  "type": "Feature",
  "properties": {
    "gn:admin1_code":"90",
    "gn:admin2_code":"0723",
    "gn:asciiname":"U Vrbu",
    "gn:country_code":"CZ",
    "gn:dem":436,
    "gn:feature_class":"P",
    "gn:feature_code":"PPL",
    "gn:name":"U Vrb\u016f",
    "gn:population":0,
    "gn:timezone":"Europe/Prague",
    "iso:country":"CZ",
    "wof:name":"U Vrbu",
    "wof:placetype":"locality"
},
  "geometry": {"coordinates":[17.85,49.35],"type":"Point"}
}