{
  "type": "Feature",
  "properties": {
    "gn:admin1_code":"85",
    "gn:admin2_code":"0804",
    "gn:asciiname":"Vitovka",
    "gn:country_code":"CZ",
    "gn:dem":342,
    "gn:feature_class":"P",
    "gn:feature_code":"PPL",
    "gn:name":"V\u00edtovka",
    "gn:population":0,
    "gn:timezone":"Europe/Prague",
    "iso:country":"CZ",
    "name:und_x_variant":[
        "Werdenberg",
        "V\u00edtberk"
    ],
    "wof:name":"Vitovka",
    "wof:placetype":"locality"
},
  "geometry": {"coordinates":[17.82755,49.69051],"type":"Point"}
}