{
  "type": "Feature",
  "properties": {
    "gn:admin1_code":"79.0",
    "gn:admin2_code":"0315",
    "gn:asciiname":"Doubrava",
    "gn:country_code":"CZ",
    "gn:dem":676,
    "gn:feature_class":"P",
    "gn:feature_code":"PPL",
    "gn:name":"Doubrava",
    "gn:population":0,
    "gn:timezone":"Europe/Prague",
    "iso:country":"CZ",
    "name:ceb_x_preferred":[
        "Doubrava"
    ],
    "name:ces_x_preferred":[
        "Doubrava"
    ],
    "name:deu_x_preferred":[
        "Doubrava"
    ],
    "name:hun_x_preferred":[
        "Doubrava"
    ],
    "name:slk_x_preferred":[
        "Doubrava"
    ],
    "name:swe_x_preferred":[
        "Doubrava"
    ],
    "wof:name":"Doubrava",
    "wof:placetype":"locality"
},
  "geometry": {"coordinates":[13.93215,49.07895],"type":"Point"}
}