{
  "type": "Feature",
  "properties": {
    "gn:country":"CZ",
    "gn:fcode":"PPL",
    "gn:population":448,
    "iso:country":"CZ",
    "name:ceb_x_preferred":[
        "T\u0159tice"
    ],
    "name:ces_x_preferred":[
        "T\u0159tice"
    ],
    "name:eng_x_preferred":[
        "T\u0159tice"
    ],
    "name:eus_x_preferred":[
        "T\u0159tice"
    ],
    "name:fas_x_preferred":[
        "\u062a\u0631\u062a\u06cc\u06a9"
    ],
    "name:fra_x_preferred":[
        "T\u0159tice"
    ],
    "name:hun_x_preferred":[
        "T\u0159tice"
    ],
    "name:ita_x_preferred":[
        "T\u0159tice"
    ],
    "name:msa_x_preferred":[
        "T\u0159tice"
    ],
    "name:nan_x_preferred":[
        "T\u0159tice"
    ],
    "name:nld_x_preferred":[
        "T\u0159tice"
    ],
    "name:por_x_preferred":[
        "T\u0159tice"
    ],
    "name:slk_x_preferred":[
        "T\u0159tice"
    ],
    "name:spa_x_preferred":[
        "T\u0159tice"
    ],
    "name:srp_x_preferred":[
        "\u0422\u0440\u0442\u0438\u0446\u0435"
    ],
    "name:swe_x_preferred":[
        "T\u0159tice"
    ],
    "name:vie_x_preferred":[
        "T\u0159tice"
    ],
    "qs_pg:aaroncc":"CZ",
    "qs_pg:gn_country":"CZ",
    "qs_pg:gn_fcode":"PPL",
    "qs_pg:gn_pop":448,
    "qs_pg:name":"T\u0159tice",
    "qs_pg:name_adm0":"\u010cesk\u00e1 republika",
    "qs_pg:name_adm1":"St\u0159edo\u010desk\u00fd kraj",
    "qs_pg:photos_9r":0,
    "qs_pg:photos_sr":0,
    "qs_pg:pop_sr":2,
    "qs_pg:qs_pg_placetype":"locality",
    "qs_pg:qs_pg_placetype_gp":"Town",
    "qs_pg:woe_adm0":23424810,
    "woe:adm0_id":23424810,
    "woe:name_adm0":"\u010cesk\u00e1 republika",
    "woe:name_adm1":"St\u0159edo\u010desk\u00fd kraj",
    "woe:placetype":"Town",
    "wof:name":"T\u0159tice",
    "wof:placetype":"locality",
    "wof:population":448
},
  "geometry": {"coordinates":[13.86348,50.185],"type":"Point"}
}