{
  "type": "Feature",
  "properties": {
    "gn:country":"CZ",
    "gn:fcode":"PPL",
    "gn:population":397,
    "iso:country":"CZ",
    "name:azb_x_preferred":[
        "\u0633\u0645\u0631\u0698\u0648\u0641"
    ],
    "name:cat_x_preferred":[
        "Smr\u017eov"
    ],
    "name:ceb_x_preferred":[
        "Smr\u017eov"
    ],
    "name:ces_x_preferred":[
        "Smr\u017eov"
    ],
    "name:che_x_preferred":[
        "\u0421\u043c\u0440\u0436\u043e\u0432"
    ],
    "name:deu_x_preferred":[
        "Smr\u017eov u Smi\u0159ic"
    ],
    "name:eng_x_preferred":[
        "Smr\u017eov"
    ],
    "name:eus_x_preferred":[
        "Smr\u017eov"
    ],
    "name:fas_x_preferred":[
        "\u0633\u0645\u0631\u0698\u0648\u0641"
    ],
    "name:fra_x_preferred":[
        "Smr\u017eov"
    ],
    "name:gle_x_preferred":[
        "Smr\u017eov"
    ],
    "name:hun_x_preferred":[
        "Smr\u017eov"
    ],
    "name:ita_x_preferred":[
        "Smr\u017eov"
    ],
    "name:lmo_x_preferred":[
        "Smr\u017eov"
    ],
    "name:msa_x_preferred":[
        "Smr\u017eov"
    ],
    "name:nan_x_preferred":[
        "Smr\u017eov"
    ],
    "name:nld_x_preferred":[
        "Smr\u017eov"
    ],
    "name:pol_x_preferred":[
        "Smr\u017eov"
    ],
    "name:por_x_preferred":[
        "Smr\u017eov"
    ],
    "name:rup_x_preferred":[
        "Smr\u017eov"
    ],
    "name:slk_x_preferred":[
        "Smr\u017eov"
    ],
    "name:spa_x_preferred":[
        "Smr\u017eov"
    ],
    "name:srp_x_preferred":[
        "\u0421\u043c\u0440\u0436\u043e\u0432"
    ],
    "name:swe_x_preferred":[
        "Smr\u017eov"
    ],
    "name:tat_x_preferred":[
        "\u0421\u043c\u0440\u0436\u043e\u0432"
    ],
    "name:vie_x_preferred":[
        "Smr\u017eov"
    ],
    "qs_pg:aaroncc":"CZ",
    "qs_pg:gn_country":"CZ",
    "qs_pg:gn_fcode":"PPL",
    "qs_pg:gn_pop":397,
    "qs_pg:name":"Smr\u017eov",
    "qs_pg:name_adm0":"\u010cesk\u00e1 republika",
    "qs_pg:name_adm1":"Kr\u00e1lov\u00e9hradeck\u00fd kraj",
    "qs_pg:photos_9r":0,
    "qs_pg:photos_sr":0,
    "qs_pg:pop_sr":2,
    "qs_pg:qs_pg_placetype":"locality",
    "qs_pg:qs_pg_placetype_gp":"Town",
    "qs_pg:woe_adm0":23424810,
    "woe:adm0_id":23424810,
    "woe:name_adm0":"\u010cesk\u00e1 republika",
    "woe:name_adm1":"Kr\u00e1lov\u00e9hradeck\u00fd kraj",
    "woe:placetype":"Town",
    "wof:name":"Smr\u017eov",
    "wof:placetype":"locality",
    "wof:population":397
},
  "geometry": {"coordinates":[15.91784,50.29975],"type":"Point"}
}