{
  "type": "Feature",
  "properties": {
    "gn:admin1_code":"84.0",
    "gn:admin2_code":"0712",
    "gn:asciiname":"Cabova",
    "gn:country_code":"CZ",
    "gn:dem":590,
    "gn:feature_class":"P",
    "gn:feature_code":"PPL",
    "gn:name":"\u010cabov\u00e1",
    "gn:population":0,
    "gn:timezone":"Europe/Prague",
    "iso:country":"CZ",
    "name:und_x_variant":[
        "Brockersdorf",
        "\u010cabov\u00e1"
    ],
    "wof:name":"Cabova",
    "wof:placetype":"locality"
},
  "geometry": {"coordinates":[17.46726,49.80642],"type":"Point"}
}