{
  "type": "Feature",
  "properties": {
    "gn:admin1_code":"81.0",
    "gn:admin2_code":"0412",
    "gn:asciiname":"Jimlikov",
    "gn:country_code":"CZ",
    "gn:dem":417,
    "gn:feature_class":"P",
    "gn:feature_code":"PPL",
    "gn:name":"Jiml\u00edkov",
    "gn:population":0,
    "gn:timezone":"Europe/Prague",
    "iso:country":"CZ",
    "name:und_x_variant":[
        "Imlikau",
        "Jiml\u00edkov"
    ],
    "wof:name":"Jimlikov",
    "wof:placetype":"locality"
},
  "geometry": {"coordinates":[12.78691,50.25346],"type":"Point"}
}