{
  "type": "Feature",
  "properties": {
    "gn:country":"CZ",
    "gn:fcode":"PPL",
    "gn:population":40,
    "iso:country":"CZ",
    "name:azb_x_preferred":[
        "\u0647\u0627\u06cc\u06a9"
    ],
    "name:cat_x_preferred":[
        "H\u00e1jek"
    ],
    "name:ces_x_preferred":[
        "H\u00e1jek"
    ],
    "name:che_x_preferred":[
        "\u0413\u0430\u0435\u043a"
    ],
    "name:deu_x_preferred":[
        "H\u00e1jek u Bavorova"
    ],
    "name:eng_x_preferred":[
        "H\u00e1jek"
    ],
    "name:epo_x_preferred":[
        "H\u00e1jek"
    ],
    "name:eus_x_preferred":[
        "H\u00e1jek"
    ],
    "name:fas_x_preferred":[
        "\u0647\u0627\u06cc\u06a9"
    ],
    "name:fra_x_preferred":[
        "H\u00e1jek"
    ],
    "name:gle_x_preferred":[
        "H\u00e1jek"
    ],
    "name:hun_x_preferred":[
        "H\u00e1jek"
    ],
    "name:ita_x_preferred":[
        "H\u00e1jek"
    ],
    "name:msa_x_preferred":[
        "H\u00e1jek"
    ],
    "name:nan_x_preferred":[
        "H\u00e1jek"
    ],
    "name:nld_x_preferred":[
        "H\u00e1jek"
    ],
    "name:pol_x_preferred":[
        "H\u00e1jek"
    ],
    "name:por_x_preferred":[
        "H\u00e1jek"
    ],
    "name:rup_x_preferred":[
        "H\u00e1jek"
    ],
    "name:rus_x_preferred":[
        "\u0413\u0430\u0435\u043a"
    ],
    "name:slk_x_preferred":[
        "H\u00e1jek"
    ],
    "name:spa_x_preferred":[
        "H\u00e1jek"
    ],
    "name:srp_x_preferred":[
        "\u0425\u0430\u0458\u0435\u043a"
    ],
    "name:tat_x_preferred":[
        "\u0413\u0430\u0435\u043a"
    ],
    "name:vie_x_preferred":[
        "H\u00e1jek"
    ],
    "qs_pg:aaroncc":"CZ",
    "qs_pg:gn_country":"CZ",
    "qs_pg:gn_fcode":"PPL",
    "qs_pg:gn_pop":40,
    "qs_pg:name":"H\u00e1jek",
    "qs_pg:name_adm0":"\u010cesk\u00e1 republika",
    "qs_pg:name_adm1":"Jiho\u010desk\u00fd kraj",
    "qs_pg:photos_9r":0,
    "qs_pg:photos_sr":0,
    "qs_pg:pop_sr":1,
    "qs_pg:qs_pg_placetype":"locality",
    "qs_pg:qs_pg_placetype_gp":"Town",
    "qs_pg:woe_adm0":23424810,
    "woe:adm0_id":23424810,
    "woe:name_adm0":"\u010cesk\u00e1 republika",
    "woe:name_adm1":"Jiho\u010desk\u00fd kraj",
    "woe:placetype":"Town",
    "wof:name":"H\u00e1jek",
    "wof:placetype":"locality",
    "wof:population":40
},
  "geometry": {"coordinates":[14.06116,49.11108],"type":"Point"}
}