{
  "type": "Feature",
  "properties": {
    "gn:admin1_code":"88.0",
    "gn:admin2_code":"0201",
    "gn:asciiname":"Jivi",
    "gn:country_code":"CZ",
    "gn:dem":505,
    "gn:feature_class":"P",
    "gn:feature_code":"PPL",
    "gn:name":"J\u00edv\u00ed",
    "gn:population":0,
    "gn:timezone":"Europe/Prague",
    "iso:country":"CZ",
    "wof:name":"Jivi",
    "wof:placetype":"locality"
},
  "geometry": {"coordinates":[14.595,49.59076],"type":"Point"}
}