{
  "type": "Feature",
  "properties": {
    "gn:gn_country":"CZ",
    "gn:gn_fcode":"PPL",
    "gn:gn_pop":556,
    "gn:population":556,
    "iso:country":"CZ",
    "name:ces_x_preferred":[
        "Nemojany"
    ],
    "name:deu_x_preferred":[
        "Nemojany"
    ],
    "name:eng_x_preferred":[
        "Nemojany"
    ],
    "name:fas_x_preferred":[
        "\u0646\u0645\u0648\u06cc\u0627\u0646\u06cc"
    ],
    "name:fra_x_preferred":[
        "Nemojany"
    ],
    "name:hun_x_preferred":[
        "Nemojany"
    ],
    "name:ita_x_preferred":[
        "Nemojany"
    ],
    "name:msa_x_preferred":[
        "Nemojany"
    ],
    "name:nan_x_preferred":[
        "Nemojany"
    ],
    "name:nld_x_preferred":[
        "Nemojany"
    ],
    "name:por_x_preferred":[
        "Nemojany"
    ],
    "name:rup_x_preferred":[
        "Nemojany"
    ],
    "name:slk_x_preferred":[
        "Nemojany"
    ],
    "name:srp_x_preferred":[
        "\u041d\u0435\u043c\u043e\u0458\u0430\u043d\u0438"
    ],
    "name:swe_x_preferred":[
        "Nemojany"
    ],
    "name:vie_x_preferred":[
        "Nemojany"
    ],
    "qs_pg:aaroncc":"CZ",
    "qs_pg:gn_country":"CZ",
    "qs_pg:gn_fcode":"PPL",
    "qs_pg:gn_pop":556,
    "qs_pg:name":"Nemojany",
    "qs_pg:name_adm0":"\u010cesk\u00e1 republika",
    "qs_pg:name_adm1":"Jihomoravsk\u00fd kraj",
    "qs_pg:photos_9k":1,
    "qs_pg:photos_9r":1,
    "qs_pg:photos_all":2,
    "qs_pg:photos_sr":0,
    "qs_pg:pop_sr":2,
    "qs_pg:qs_pg_placetype":"locality",
    "qs_pg:qs_pg_placetype_gp":"Town",
    "qs_pg:woe_adm0":23424810,
    "woe:adm0_id":23424810,
    "woe:name_adm0":"\u010cesk\u00e1 republika",
    "woe:name_adm1":"Jihomoravsk\u00fd kraj",
    "woe:placetype":"Town",
    "wof:name":"Nemojany",
    "wof:placetype":"locality",
    "wof:population":556
},
  "geometry": {"coordinates":[16.91351,49.24671],"type":"Point"}
}