{
  "type": "Feature",
  "properties": {
    "gn:admin1_code":"86.0",
    "gn:admin2_code":"0532",
    "gn:asciiname":"Nove Civice",
    "gn:country_code":"CZ",
    "gn:dem":225,
    "gn:feature_class":"P",
    "gn:feature_code":"PPL",
    "gn:name":"Nov\u00e9 \u010c\u00edvice",
    "gn:population":0,
    "gn:timezone":"Europe/Prague",
    "iso:country":"CZ",
    "wof:name":"Nove Civice",
    "wof:placetype":"locality"
},
  "geometry": {"coordinates":[15.68333,50.01667],"type":"Point"}
}