{
  "type": "Feature",
  "properties": {
    "gn:admin1_code":"83",
    "gn:admin2_code":"0513",
    "gn:asciiname":"Svarov",
    "gn:country_code":"CZ",
    "gn:dem":333,
    "gn:feature_class":"P",
    "gn:feature_code":"PPL",
    "gn:name":"Sv\u00e1rov",
    "gn:population":0,
    "gn:timezone":"Europe/Prague",
    "iso:country":"CZ",
    "name:und_x_variant":[
        "Schwarau",
        "Sv\u00e1rov"
    ],
    "wof:name":"Svarov",
    "wof:placetype":"locality"
},
  "geometry": {"coordinates":[15.00738,50.79207],"type":"Point"}
}