{
  "type": "Feature",
  "properties": {
    "gn:country":"CZ",
    "gn:fcode":"PPL",
    "gn:population":927,
    "iso:country":"CZ",
    "name:azb_x_preferred":[
        "\u0633\u062a\u0631\u0627\u0698\u06a9"
    ],
    "name:ceb_x_preferred":[
        "Str\u00e1\u017eek"
    ],
    "name:ces_x_preferred":[
        "Str\u00e1\u017eek"
    ],
    "name:deu_x_preferred":[
        "Str\u00e1\u017eek"
    ],
    "name:eng_x_preferred":[
        "Str\u00e1\u017eek"
    ],
    "name:eus_x_preferred":[
        "Str\u00e1\u017eek"
    ],
    "name:fas_x_preferred":[
        "\u0633\u062a\u0631\u0627\u0698\u06a9"
    ],
    "name:fra_x_preferred":[
        "Str\u00e1\u017eek"
    ],
    "name:hun_x_preferred":[
        "Str\u00e1\u017eek"
    ],
    "name:ita_x_preferred":[
        "Str\u00e1\u017eek"
    ],
    "name:msa_x_preferred":[
        "Str\u00e1\u017eek"
    ],
    "name:nan_x_preferred":[
        "Str\u00e1\u017eek"
    ],
    "name:nld_x_preferred":[
        "Str\u00e1\u017eek"
    ],
    "name:por_x_preferred":[
        "Str\u00e1\u017eek"
    ],
    "name:slk_x_preferred":[
        "Str\u00e1\u017eek"
    ],
    "name:spa_x_preferred":[
        "Str\u00e1\u017eek"
    ],
    "name:srp_x_preferred":[
        "\u0421\u0442\u0440\u0430\u0436\u0435\u043a"
    ],
    "name:swe_x_preferred":[
        "Str\u00e1\u017eek"
    ],
    "name:und_x_variant":[
        "Straschkau"
    ],
    "name:vie_x_preferred":[
        "Str\u00e1\u017eek"
    ],
    "qs_pg:aaroncc":"CZ",
    "qs_pg:gn_country":"CZ",
    "qs_pg:gn_fcode":"PPL",
    "qs_pg:gn_pop":927,
    "qs_pg:name":"Str\u00e1\u017eek",
    "qs_pg:name_adm0":"\u010cesk\u00e1 republika",
    "qs_pg:name_adm1":"Kraj Vyso\u010dina",
    "qs_pg:photos_9r":0,
    "qs_pg:photos_sr":0,
    "qs_pg:pop_sr":2,
    "qs_pg:qs_pg_placetype":"locality",
    "qs_pg:qs_pg_placetype_gp":"Town",
    "qs_pg:woe_adm0":23424810,
    "woe:adm0_id":23424810,
    "woe:name_adm0":"\u010cesk\u00e1 republika",
    "woe:name_adm1":"Kraj Vyso\u010dina",
    "woe:placetype":"Town",
    "wof:name":"Str\u00e1\u017eek",
    "wof:placetype":"locality",
    "wof:population":927
},
  "geometry": {"coordinates":[16.19332,49.44074],"type":"Point"}
}