{
  "type": "Feature",
  "properties": {
    "gn:gn_country":"CZ",
    "gn:gn_fcode":"PPL",
    "gn:gn_pop":379,
    "gn:population":379,
    "iso:country":"CZ",
    "name:azb_x_preferred":[
        "\u062f\u0648\u0644\u0646\u06cc \u0645\u0648\u0631\u0627\u0648\u06cc\u062a\u0633\u0647"
    ],
    "name:ceb_x_preferred":[
        "Doln\u00ed Moravice"
    ],
    "name:ces_x_preferred":[
        "Doln\u00ed Moravice"
    ],
    "name:deu_x_preferred":[
        "Doln\u00ed Moravice"
    ],
    "name:epo_x_preferred":[
        "Doln\u00ed Moravice"
    ],
    "name:eus_x_preferred":[
        "Doln\u00ed Moravice"
    ],
    "name:fas_x_preferred":[
        "\u062f\u0648\u0644\u0646\u06cc \u0645\u0648\u0631\u0627\u0648\u06cc\u062a\u0633\u0647"
    ],
    "name:fra_x_preferred":[
        "Doln\u00ed Moravice"
    ],
    "name:hun_x_preferred":[
        "Doln\u00ed Moravice"
    ],
    "name:ita_x_preferred":[
        "Doln\u00ed Moravice"
    ],
    "name:msa_x_preferred":[
        "Doln\u00ed Moravice"
    ],
    "name:nld_x_preferred":[
        "Doln\u00ed Moravice"
    ],
    "name:pol_x_preferred":[
        "Doln\u00ed Moravice"
    ],
    "name:por_x_preferred":[
        "Doln\u00ed Moravice"
    ],
    "name:slk_x_preferred":[
        "Doln\u00ed Moravice"
    ],
    "name:spa_x_preferred":[
        "Doln\u00ed Moravice"
    ],
    "name:srp_x_preferred":[
        "\u0414\u043e\u043b\u045a\u0438 \u041c\u043e\u0440\u0430\u0432\u0438\u0446\u0435"
    ],
    "name:swe_x_preferred":[
        "Doln\u00ed Moravice"
    ],
    "name:unk_x_variant":[
        "Moravice"
    ],
    "name:vie_x_preferred":[
        "Doln\u00ed Moravice"
    ],
    "qs_pg:aaroncc":"CZ",
    "qs_pg:gn_country":"CZ",
    "qs_pg:gn_fcode":"PPL",
    "qs_pg:gn_pop":379,
    "qs_pg:name":"Doln\u00ed Moravice",
    "qs_pg:name_adm0":"\u010cesk\u00e1 republika",
    "qs_pg:name_adm1":"Moravskoslezsk\u00fd kraj",
    "qs_pg:photos_9k":1,
    "qs_pg:photos_9r":3,
    "qs_pg:photos_all":119,
    "qs_pg:photos_sr":0,
    "qs_pg:pop_sr":2,
    "qs_pg:qs_pg_placetype":"locality",
    "qs_pg:qs_pg_placetype_gp":"Town",
    "qs_pg:woe_adm0":23424810,
    "woe:adm0_id":23424810,
    "woe:name_adm0":"\u010cesk\u00e1 republika",
    "woe:name_adm1":"Moravskoslezsk\u00fd kraj",
    "woe:placetype":"Town",
    "wof:name":"Doln\u00ed Moravice",
    "wof:placetype":"locality",
    "wof:population":379
},
  "geometry": {"coordinates":[17.32165,49.97711],"type":"Point"}
}