{
  "type": "Feature",
  "properties": {
    "iso:country":"CZ",
    "name:azb_x_preferred":[
        "\u06a9\u0648\u0633\u062a\u0648\u0645\u0644\u0627\u062a\u06cc \u067e\u0648\u062f \u0645\u06cc\u0644\u0634\u0648\u0648\u06a9\u0648\u0648"
    ],
    "name:ceb_x_preferred":[
        "Kostomlaty pod Mile\u0161ovkou"
    ],
    "name:ces_x_preferred":[
        "Kostomlaty pod Mile\u0161ovkou"
    ],
    "name:deu_x_preferred":[
        "Kostomlaty pod Mile\u0161ovkou"
    ],
    "name:eus_x_preferred":[
        "Kostomlaty pod Mile\u0161ovkou"
    ],
    "name:fas_x_preferred":[
        "\u06a9\u0648\u0633\u062a\u0648\u0645\u0644\u0627\u062a\u06cc \u067e\u0648\u062f \u0645\u06cc\u0644\u0634\u0648\u0648\u06a9\u0648\u0648"
    ],
    "name:fra_x_preferred":[
        "Kostomlaty pod Mile\u0161ovkou"
    ],
    "name:hun_x_preferred":[
        "Kostomlaty pod Mile\u0161ovkou"
    ],
    "name:ita_x_preferred":[
        "Kostomlaty pod Mile\u0161ovkou"
    ],
    "name:msa_x_preferred":[
        "Kostomlaty pod Mile\u0161ovkou"
    ],
    "name:nld_x_preferred":[
        "Kostomlaty pod Mile\u0161ovkou"
    ],
    "name:pol_x_preferred":[
        "Kostomlaty pod Mile\u0161ovkou"
    ],
    "name:por_x_preferred":[
        "Kostomlaty pod Mile\u0161ovkou"
    ],
    "name:slk_x_preferred":[
        "Kostomlaty pod Mile\u0161ovkou"
    ],
    "name:srp_x_preferred":[
        "\u041a\u043e\u0441\u0442\u043e\u043c\u043b\u0430\u0442\u0438 \u043f\u043e\u0434 \u041c\u0438\u043b\u0435\u0448\u043e\u0432\u043a\u043e\u043c"
    ],
    "name:swe_x_preferred":[
        "Kostomlaty pod Mile\u0161ovkou"
    ],
    "name:vie_x_preferred":[
        "Kostomlaty pod Mile\u0161ovkou"
    ],
    "qs_pg:aaroncc":"CZ",
    "qs_pg:name":"Kostomlaty pod Mile\u0161ovkou",
    "qs_pg:name_adm0":"\u010cesk\u00e1 republika",
    "qs_pg:name_adm1":"\u00dasteck\u00fd kraj",
    "qs_pg:photos":3,
    "qs_pg:photos_1k":1,
    "qs_pg:photos_9k":1,
    "qs_pg:photos_9r":1,
    "qs_pg:photos_all":8,
    "qs_pg:photos_sr":1,
    "qs_pg:pop_sr":0,
    "qs_pg:qs_pg_placetype":"localadmin",
    "qs_pg:qs_pg_placetype_gp":"LocalAdmin",
    "qs_pg:woe_adm0":23424810,
    "woe:adm0_id":23424810,
    "woe:name_adm0":"\u010cesk\u00e1 republika",
    "woe:name_adm1":"\u00dasteck\u00fd kraj",
    "woe:placetype":"LocalAdmin",
    "wof:name":"Kostomlaty pod Mile\u0161ovkou",
    "wof:placetype":"localadmin"
},
  "geometry": {"coordinates":[13.89543,50.5542605],"type":"Point"}
}