{
  "type": "Feature",
  "properties": {
    "gn:admin1_code":"87.0",
    "gn:admin2_code":"0323",
    "gn:asciiname":"Chouzovy",
    "gn:country_code":"CZ",
    "gn:dem":433,
    "gn:feature_class":"P",
    "gn:feature_code":"PPL",
    "gn:name":"Chouzovy",
    "gn:population":0,
    "gn:timezone":"Europe/Prague",
    "iso:country":"CZ",
    "wof:name":"Chouzovy",
    "wof:placetype":"locality"
},
  "geometry": {"coordinates":[13.47516,49.62506],"type":"Point"}
}