{
  "type": "Feature",
  "properties": {
    "gn:admin1_code":"88.0",
    "gn:admin2_code":"0201",
    "gn:asciiname":"Palcice",
    "gn:country_code":"CZ",
    "gn:dem":598,
    "gn:feature_class":"P",
    "gn:feature_code":"PPL",
    "gn:name":"Pal\u010dice",
    "gn:population":0,
    "gn:timezone":"Europe/Prague",
    "iso:country":"CZ",
    "wof:name":"Palcice",
    "wof:placetype":"locality"
},
  "geometry": {"coordinates":[14.96946,49.61424],"type":"Point"}
}