{
  "type": "Feature",
  "properties": {
    "gn:admin1_code":"80.0",
    "gn:admin2_code":"0613",
    "gn:asciiname":"Kocourovy Lhotky",
    "gn:country_code":"CZ",
    "gn:dem":581,
    "gn:feature_class":"P",
    "gn:feature_code":"PPL",
    "gn:name":"Kocourovy Lhotky",
    "gn:population":0,
    "gn:timezone":"Europe/Prague",
    "iso:country":"CZ",
    "wof:name":"Kocourovy Lhotky",
    "wof:placetype":"locality"
},
  "geometry": {"coordinates":[15.31912,49.45571],"type":"Point"}
}