{
  "type": "Feature",
  "properties": {
    "iso:country":"CZ",
    "name:ara_x_preferred":[
        "\u0645\u0646\u064a\u0644\u0646\u064a\u0643"
    ],
    "name:bel_x_preferred":[
        "\u041c\u0435\u043b\u044c\u043d\u0456\u043a"
    ],
    "name:bul_x_preferred":[
        "\u041c\u0435\u043b\u043d\u0438\u043a"
    ],
    "name:ceb_x_preferred":[
        "M\u011bln\u00edk"
    ],
    "name:ces_x_preferred":[
        "M\u011bln\u00edk"
    ],
    "name:cym_x_preferred":[
        "M\u011bln\u00edk"
    ],
    "name:dan_x_preferred":[
        "M\u011bln\u00edk"
    ],
    "name:deu_x_preferred":[
        "M\u011bln\u00edk"
    ],
    "name:epo_x_preferred":[
        "M\u011bln\u00edk"
    ],
    "name:eus_x_preferred":[
        "M\u011bln\u00edk"
    ],
    "name:fas_x_preferred":[
        "\u0645\u0644\u0646\u06cc\u06a9"
    ],
    "name:fra_x_preferred":[
        "M\u011bln\u00edk"
    ],
    "name:hsb_x_preferred":[
        "M\u011bln\u00edk"
    ],
    "name:hun_x_preferred":[
        "M\u011bln\u00edk"
    ],
    "name:ita_x_preferred":[
        "M\u011bln\u00edk"
    ],
    "name:jpn_x_preferred":[
        "\u30e0\u30cb\u30a7\u30eb\u30cb\u30fc\u30af"
    ],
    "name:kat_x_preferred":[
        "\u10db\u10dc\u10d4\u10da\u10dc\u10d8\u10d9\u10d8"
    ],
    "name:kor_x_preferred":[
        "\uba5c\ub2c8\ud06c"
    ],
    "name:lat_x_preferred":[
        "Melnica"
    ],
    "name:lav_x_preferred":[
        "Meln\u012bka"
    ],
    "name:lit_x_preferred":[
        "Melnykas"
    ],
    "name:msa_x_preferred":[
        "M\u011bln\u00edk"
    ],
    "name:nld_x_preferred":[
        "M\u011bln\u00edk"
    ],
    "name:nor_x_preferred":[
        "M\u011bln\u00edk"
    ],
    "name:pms_x_preferred":[
        "M\u011bln\u00edk"
    ],
    "name:pol_x_preferred":[
        "Mielnik"
    ],
    "name:por_x_preferred":[
        "M\u011bln\u00edk"
    ],
    "name:ron_x_preferred":[
        "M\u011bln\u00edk"
    ],
    "name:rus_x_preferred":[
        "\u041c\u0435\u043b\u044c\u043d\u0438\u043a"
    ],
    "name:slk_x_preferred":[
        "M\u011bln\u00edk"
    ],
    "name:spa_x_preferred":[
        "M\u011bln\u00edk"
    ],
    "name:srp_x_preferred":[
        "\u041c\u0458\u0435\u043b\u045a\u0438\u043a"
    ],
    "name:swe_x_preferred":[
        "M\u011bln\u00edk"
    ],
    "name:tgk_x_preferred":[
        "\u041c\u0435\u043b\u043d\u0438\u043a"
    ],
    "name:tur_x_preferred":[
        "M\u011bln\u00edk"
    ],
    "name:vie_x_preferred":[
        "M\u011bln\u00edk"
    ],
    "name:war_x_preferred":[
        "M\u011bln\u00edk"
    ],
    "name:zho_x_preferred":[
        "\u6885\u723e\u5c3c\u514b"
    ],
    "qs_pg:aaroncc":"CZ",
    "qs_pg:name":"M\u011bln\u00edk",
    "qs_pg:name_adm0":"\u010cesk\u00e1 republika",
    "qs_pg:name_adm1":"St\u0159edo\u010desk\u00fd kraj",
    "qs_pg:photos":1,
    "qs_pg:photos_1k":1,
    "qs_pg:photos_9k":2,
    "qs_pg:photos_9r":5,
    "qs_pg:photos_all":367,
    "qs_pg:photos_sr":1,
    "qs_pg:pop_sr":0,
    "qs_pg:qs_pg_placetype":"localadmin",
    "qs_pg:qs_pg_placetype_gp":"LocalAdmin",
    "qs_pg:woe_adm0":23424810,
    "woe:adm0_id":23424810,
    "woe:name_adm0":"\u010cesk\u00e1 republika",
    "woe:name_adm1":"St\u0159edo\u010desk\u00fd kraj",
    "woe:placetype":"LocalAdmin",
    "wof:name":"M\u011bln\u00edk",
    "wof:placetype":"localadmin"
},
  "geometry": {"coordinates":[14.475038,50.3541],"type":"Point"}
}