{
  "type": "Feature",
  "properties": {
    "gn:admin1_code":"80.0",
    "gn:admin2_code":"0612",
    "gn:asciiname":"Skrysov",
    "gn:country_code":"CZ",
    "gn:dem":546,
    "gn:feature_class":"P",
    "gn:feature_code":"PPL",
    "gn:name":"Skr\u00fd\u0161ov",
    "gn:population":0,
    "gn:timezone":"Europe/Prague",
    "iso:country":"CZ",
    "wof:name":"Skrysov",
    "wof:placetype":"locality"
},
  "geometry": {"coordinates":[15.77211,49.49211],"type":"Point"}
}