{
  "type": "Feature",
  "properties": {
    "gn:gn_country":"CZ",
    "gn:gn_fcode":"PPL",
    "gn:gn_pop":96,
    "gn:population":96,
    "iso:country":"CZ",
    "name:ceb_x_preferred":[
        "N\u011bm\u010di\u010dky"
    ],
    "name:ces_x_preferred":[
        "N\u011bm\u010di\u010dky"
    ],
    "name:deu_x_preferred":[
        "N\u011bm\u010di\u010dky"
    ],
    "name:fra_x_preferred":[
        "N\u011bm\u010di\u010dky"
    ],
    "name:ita_x_preferred":[
        "N\u011bm\u010di\u010dky"
    ],
    "name:nld_x_preferred":[
        "N\u011bm\u010di\u010dky"
    ],
    "name:pol_x_preferred":[
        "N\u011bm\u010di\u010dky"
    ],
    "name:slk_x_preferred":[
        "N\u011bm\u010di\u010dky"
    ],
    "name:srp_x_preferred":[
        "\u040a\u0435\u043c\u0447\u0438\u0447\u043a\u0438"
    ],
    "name:swe_x_preferred":[
        "N\u011bm\u010di\u010dky"
    ],
    "qs_pg:aaroncc":"CZ",
    "qs_pg:gn_country":"CZ",
    "qs_pg:gn_fcode":"PPL",
    "qs_pg:gn_pop":96,
    "qs_pg:name":"N\u011bm\u010di\u010dky",
    "qs_pg:name_adm0":"\u010cesk\u00e1 republika",
    "qs_pg:name_adm1":"Jihomoravsk\u00fd kraj",
    "qs_pg:photos_9r":0,
    "qs_pg:photos_sr":0,
    "qs_pg:pop_sr":1,
    "qs_pg:qs_pg_placetype":"locality",
    "qs_pg:qs_pg_placetype_gp":"Town",
    "qs_pg:woe_adm0":23424810,
    "woe:adm0_id":23424810,
    "woe:name_adm0":"\u010cesk\u00e1 republika",
    "woe:name_adm1":"Jihomoravsk\u00fd kraj",
    "woe:placetype":"Town",
    "wof:name":"N\u011bm\u010di\u010dky",
    "wof:placetype":"locality",
    "wof:population":96
},
  "geometry": {"coordinates":[16.08841,48.94224],"type":"Point"}
}