{
  "type": "Feature",
  "properties": {
    "gn:admin1_code":"80",
    "gn:admin2_code":"0611",
    "gn:asciiname":"Stikov",
    "gn:country_code":"CZ",
    "gn:dem":607,
    "gn:feature_class":"P",
    "gn:feature_code":"PPL",
    "gn:name":"\u0160tikov",
    "gn:population":0,
    "gn:timezone":"Europe/Prague",
    "iso:country":"CZ",
    "wof:name":"Stikov",
    "wof:placetype":"locality"
},
  "geometry": {"coordinates":[15.76544,49.73333],"type":"Point"}
}