{
  "type": "Feature",
  "properties": {
    "gn:admin1_code":"86",
    "gn:admin2_code":"0533",
    "gn:asciiname":"Vysoke Pole",
    "gn:country_code":"CZ",
    "gn:dem":554,
    "gn:feature_class":"P",
    "gn:feature_code":"PPL",
    "gn:name":"Vysok\u00e9 Pole",
    "gn:population":0,
    "gn:timezone":"Europe/Prague",
    "iso:country":"CZ",
    "name:und_x_variant":[
        "Hohenfeld",
        "Vysok\u00e9 Pole"
    ],
    "wof:name":"Vysoke Pole",
    "wof:placetype":"locality"
},
  "geometry": {"coordinates":[16.55322,49.78846],"type":"Point"}
}