{
  "type": "Feature",
  "properties": {
    "gn:admin1_code":"81.0",
    "gn:admin2_code":"0413",
    "gn:asciiname":"Mlynska",
    "gn:country_code":"CZ",
    "gn:dem":623,
    "gn:feature_class":"P",
    "gn:feature_code":"PPL",
    "gn:name":"Ml\u00fdnsk\u00e1",
    "gn:population":0,
    "gn:timezone":"Europe/Prague",
    "iso:country":"CZ",
    "name:und_x_variant":[
        "Kun\u0161t\u00e1t",
        "Konstadt",
        "Ml\u00fdnsk\u00e1"
    ],
    "wof:name":"Mlynska",
    "wof:placetype":"locality"
},
  "geometry": {"coordinates":[12.48271,50.28791],"type":"Point"}
}