{
  "type": "Feature",
  "properties": {
    "gn:admin1_code":"89.0",
    "gn:admin2_code":"0424",
    "gn:asciiname":"Cerncice",
    "gn:country_code":"CZ",
    "gn:dem":337,
    "gn:feature_class":"P",
    "gn:feature_code":"PPL",
    "gn:name":"\u010cern\u010dice",
    "gn:population":0,
    "gn:timezone":"Europe/Prague",
    "iso:country":"CZ",
    "wof:name":"Cerncice",
    "wof:placetype":"locality"
},
  "geometry": {"coordinates":[13.43662,50.13885],"type":"Point"}
}