{
  "type": "Feature",
  "properties": {
    "gn:admin1_code":"89.0",
    "gn:admin2_code":"0421",
    "gn:asciiname":"Slukova",
    "gn:country_code":"CZ",
    "gn:dem":530,
    "gn:feature_class":"P",
    "gn:feature_code":"PPL",
    "gn:name":"Slukov\u00e1",
    "gn:population":0,
    "gn:timezone":"Europe/Prague",
    "iso:country":"CZ",
    "name:und_x_variant":[
        "Schneppendorf",
        "Slukov\u00e1"
    ],
    "wof:name":"Slukova",
    "wof:placetype":"locality"
},
  "geometry": {"coordinates":[14.28379,50.68494000000001],"type":"Point"}
}