{
  "type": "Feature",
  "properties": {
    "gn:gn_country":"CZ",
    "gn:gn_fcode":"PPL",
    "gn:gn_pop":56,
    "gn:population":56,
    "iso:country":"CZ",
    "name:azb_x_preferred":[
        "\u0645\u0627\u0631\u062a\u06cc\u0646\u06cc\u062a\u0633\u0647 \u0648 \u0627\u0648\u0646\u0634\u0648\u0648\u0627"
    ],
    "name:ces_x_preferred":[
        "Martinice u On\u0161ova"
    ],
    "name:deu_x_preferred":[
        "Martinice u On\u0161ova"
    ],
    "name:eng_x_preferred":[
        "Martinice u On\u0161ova"
    ],
    "name:eus_x_preferred":[
        "Martinice u On\u0161ova"
    ],
    "name:fas_x_preferred":[
        "\u0645\u0627\u0631\u062a\u06cc\u0646\u06cc\u062a\u0633\u0647 \u0648 \u0627\u0648\u0646\u0634\u0648\u0648\u0627"
    ],
    "name:fra_x_preferred":[
        "Martinice u On\u0161ova"
    ],
    "name:hun_x_preferred":[
        "Martinice u On\u0161ova"
    ],
    "name:ita_x_preferred":[
        "Martinice u On\u0161ova"
    ],
    "name:msa_x_preferred":[
        "Martinice u On\u0161ova"
    ],
    "name:nan_x_preferred":[
        "Martinice u On\u0161ova"
    ],
    "name:nld_x_preferred":[
        "Martinice u On\u0161ova"
    ],
    "name:pol_x_preferred":[
        "Martinice u On\u0161ova"
    ],
    "name:por_x_preferred":[
        "Martinice u On\u0161ova"
    ],
    "name:rup_x_preferred":[
        "Martinice u On\u0161ova"
    ],
    "name:slk_x_preferred":[
        "Martinice u On\u0161ova"
    ],
    "name:spa_x_preferred":[
        "Martinice u On\u0161ova"
    ],
    "name:srp_x_preferred":[
        "\u041c\u0430\u0440\u0442\u0438\u045a\u0438\u0446\u0435 \u0443 \u041e\u043d\u0448\u043e\u0432\u0443"
    ],
    "name:vie_x_preferred":[
        "Martinice u On\u0161ova"
    ],
    "qs_pg:aaroncc":"CZ",
    "qs_pg:gn_country":"CZ",
    "qs_pg:gn_fcode":"PPL",
    "qs_pg:gn_pop":56,
    "qs_pg:name":"Martinice u On\u0161ova",
    "qs_pg:name_adm0":"\u010cesk\u00e1 republika",
    "qs_pg:name_adm1":"Kraj Vyso\u010dina",
    "qs_pg:photos_9r":0,
    "qs_pg:photos_sr":0,
    "qs_pg:pop_sr":1,
    "qs_pg:qs_pg_placetype":"locality",
    "qs_pg:qs_pg_placetype_gp":"Town",
    "qs_pg:woe_adm0":23424810,
    "woe:adm0_id":23424810,
    "woe:name_adm0":"\u010cesk\u00e1 republika",
    "woe:name_adm1":"Kraj Vyso\u010dina",
    "woe:placetype":"Town",
    "wof:name":"Martinice u On\u0161ova",
    "wof:placetype":"locality",
    "wof:population":56
},
  "geometry": {"coordinates":[15.11538,49.57985],"type":"Point"}
}