{
  "type": "Feature",
  "properties": {
    "gn:admin1_code":"88.0",
    "gn:admin2_code":"0206",
    "gn:asciiname":"Jestrebice",
    "gn:country_code":"CZ",
    "gn:dem":340,
    "gn:feature_class":"P",
    "gn:feature_code":"PPL",
    "gn:name":"Jest\u0159ebice",
    "gn:population":0,
    "gn:timezone":"Europe/Prague",
    "iso:country":"CZ",
    "name:und_x_variant":[
        "Baudenm\u00fchle",
        "Jest\u0159ebice"
    ],
    "wof:name":"Jestrebice",
    "wof:placetype":"locality"
},
  "geometry": {"coordinates":[14.57088,50.46274],"type":"Point"}
}