{
  "type": "Feature",
  "properties": {
    "gn:admin1_code":"87.0",
    "gn:admin2_code":"0322",
    "gn:asciiname":"Horni Nemcice",
    "gn:country_code":"CZ",
    "gn:dem":586,
    "gn:feature_class":"P",
    "gn:feature_code":"PPL",
    "gn:name":"Horn\u00ed N\u011bm\u010dice",
    "gn:population":0,
    "gn:timezone":"Europe/Prague",
    "iso:country":"CZ",
    "name:und_x_variant":[
        "N\u011bm\u010dice",
        "Horn\u00ed N\u011bm\u010dice"
    ],
    "wof:name":"Horni Nemcice",
    "wof:placetype":"locality"
},
  "geometry": {"coordinates":[13.2698,49.27462],"type":"Point"}
}