{
  "type": "Feature",
  "properties": {
    "gn:admin1_code":"88.0",
    "gn:admin2_code":"020B",
    "gn:asciiname":"Skoupy",
    "gn:country_code":"CZ",
    "gn:dem":492,
    "gn:feature_class":"P",
    "gn:feature_code":"PPL",
    "gn:name":"Skoup\u00fd",
    "gn:population":0,
    "gn:timezone":"Europe/Prague",
    "iso:country":"CZ",
    "wof:name":"Skoupy",
    "wof:placetype":"locality"
},
  "geometry": {"coordinates":[14.34787,49.57966],"type":"Point"}
}