{
  "type": "Feature",
  "properties": {
    "gn:country":"CZ",
    "gn:fcode":"PPL",
    "gn:population":83,
    "iso:country":"CZ",
    "name:azb_x_preferred":[
        "\u062a\u0634\u0631\u0646\u06cc\u0634\u0648\u0648\u06cc\u062a\u0633\u0647"
    ],
    "name:ces_x_preferred":[
        "\u010cern\u00fd\u0161ovice"
    ],
    "name:deu_x_preferred":[
        "\u010cern\u00fd\u0161ovice"
    ],
    "name:eng_x_preferred":[
        "\u010cern\u00fd\u0161ovice"
    ],
    "name:eus_x_preferred":[
        "\u010cern\u00fd\u0161ovice"
    ],
    "name:fas_x_preferred":[
        "\u062a\u0634\u0631\u0646\u06cc\u0634\u0648\u0648\u06cc\u062a\u0633\u0647"
    ],
    "name:fra_x_preferred":[
        "\u010cern\u00fd\u0161ovice"
    ],
    "name:hun_x_preferred":[
        "\u010cern\u00fd\u0161ovice"
    ],
    "name:ita_x_preferred":[
        "\u010cern\u00fd\u0161ovice"
    ],
    "name:msa_x_preferred":[
        "\u010cern\u00fd\u0161ovice"
    ],
    "name:nan_x_preferred":[
        "\u010cern\u00fd\u0161ovice"
    ],
    "name:nld_x_preferred":[
        "\u010cern\u00fd\u0161ovice"
    ],
    "name:pol_x_preferred":[
        "\u010cern\u00fd\u0161ovice"
    ],
    "name:por_x_preferred":[
        "\u010cern\u00fd\u0161ovice"
    ],
    "name:rup_x_preferred":[
        "\u010cern\u00fd\u0161ovice"
    ],
    "name:slk_x_preferred":[
        "\u010cern\u00fd\u0161ovice"
    ],
    "name:spa_x_preferred":[
        "\u010cern\u00fd\u0161ovice"
    ],
    "name:srp_x_preferred":[
        "\u0427\u0435\u0440\u043d\u0438\u0448\u043e\u0432\u0438\u0446\u0435"
    ],
    "name:vie_x_preferred":[
        "\u010cern\u00fd\u0161ovice"
    ],
    "qs_pg:aaroncc":"CZ",
    "qs_pg:gn_country":"CZ",
    "qs_pg:gn_fcode":"PPL",
    "qs_pg:gn_pop":83,
    "qs_pg:name":"\u010cern\u00fd\u0161ovice",
    "qs_pg:name_adm0":"\u010cesk\u00e1 republika",
    "qs_pg:name_adm1":"Jiho\u010desk\u00fd kraj",
    "qs_pg:photos_9r":0,
    "qs_pg:photos_sr":0,
    "qs_pg:pop_sr":1,
    "qs_pg:qs_pg_placetype":"locality",
    "qs_pg:qs_pg_placetype_gp":"Town",
    "qs_pg:woe_adm0":23424810,
    "woe:adm0_id":23424810,
    "woe:name_adm0":"\u010cesk\u00e1 republika",
    "woe:name_adm1":"Jiho\u010desk\u00fd kraj",
    "woe:placetype":"Town",
    "wof:name":"\u010cern\u00fd\u0161ovice",
    "wof:placetype":"locality",
    "wof:population":83
},
  "geometry": {"coordinates":[14.52044,49.32513],"type":"Point"}
}