{
  "type": "Feature",
  "properties": {
    "gn:admin1_code":"52",
    "gn:asciiname":"Svepravice",
    "gn:country_code":"CZ",
    "gn:dem":263,
    "gn:feature_class":"P",
    "gn:feature_code":"PPL",
    "gn:name":"Sv\u00e9pravice",
    "gn:population":0,
    "gn:timezone":"Europe/Prague",
    "iso:country":"CZ",
    "wof:name":"Svepravice",
    "wof:placetype":"locality"
},
  "geometry": {"coordinates":[14.6131,50.10071],"type":"Point"}
}