{
  "type": "Feature",
  "properties": {
    "gn:country":"CZ",
    "gn:fcode":"PPL",
    "gn:population":147,
    "iso:country":"CZ",
    "name:azb_x_preferred":[
        "\u06a9\u0631\u0634\u06cc\u0646"
    ],
    "name:cat_x_preferred":[
        "K\u0159e\u0161\u00edn"
    ],
    "name:ceb_x_preferred":[
        "K\u0159e\u0161\u00edn"
    ],
    "name:ces_x_preferred":[
        "K\u0159e\u0161\u00edn"
    ],
    "name:che_x_preferred":[
        "\u041a\u0440\u0436\u0435\u0448\u0438\u043d"
    ],
    "name:deu_x_preferred":[
        "K\u0159e\u0161\u00edn u Pacova"
    ],
    "name:eng_x_preferred":[
        "K\u0159e\u0161\u00edn"
    ],
    "name:epo_x_preferred":[
        "K\u0159e\u0161\u00edn"
    ],
    "name:eus_x_preferred":[
        "K\u0159e\u0161\u00edn"
    ],
    "name:fas_x_preferred":[
        "\u06a9\u0631\u0634\u06cc\u0646"
    ],
    "name:fra_x_preferred":[
        "K\u0159e\u0161\u00edn"
    ],
    "name:gle_x_preferred":[
        "K\u0159e\u0161\u00edn"
    ],
    "name:hun_x_preferred":[
        "K\u0159e\u0161\u00edn"
    ],
    "name:ita_x_preferred":[
        "K\u0159e\u0161\u00edn"
    ],
    "name:lmo_x_preferred":[
        "K\u0159e\u0161\u00edn"
    ],
    "name:msa_x_preferred":[
        "K\u0159e\u0161\u00edn"
    ],
    "name:nan_x_preferred":[
        "K\u0159e\u0161\u00edn"
    ],
    "name:nld_x_preferred":[
        "K\u0159e\u0161\u00edn"
    ],
    "name:pol_x_preferred":[
        "K\u0159e\u0161\u00edn"
    ],
    "name:por_x_preferred":[
        "K\u0159e\u0161\u00edn"
    ],
    "name:rup_x_preferred":[
        "K\u0159e\u0161\u00edn"
    ],
    "name:slk_x_preferred":[
        "K\u0159e\u0161\u00edn"
    ],
    "name:spa_x_preferred":[
        "K\u0159e\u0161\u00edn"
    ],
    "name:srp_x_preferred":[
        "\u041a\u0440\u0435\u0448\u0438\u043d"
    ],
    "name:swe_x_preferred":[
        "K\u0159e\u0161\u00edn"
    ],
    "name:tat_x_preferred":[
        "\u041a\u0440\u0436\u0435\u0448\u0438\u043d"
    ],
    "name:vie_x_preferred":[
        "K\u0159e\u0161\u00edn"
    ],
    "qs_pg:aaroncc":"CZ",
    "qs_pg:gn_country":"CZ",
    "qs_pg:gn_fcode":"PPL",
    "qs_pg:gn_pop":147,
    "qs_pg:name":"K\u0159e\u0161\u00edn",
    "qs_pg:name_adm0":"\u010cesk\u00e1 republika",
    "qs_pg:name_adm1":"Kraj Vyso\u010dina",
    "qs_pg:photos_9r":0,
    "qs_pg:photos_sr":0,
    "qs_pg:pop_sr":1,
    "qs_pg:qs_pg_placetype":"locality",
    "qs_pg:qs_pg_placetype_gp":"Town",
    "qs_pg:woe_adm0":23424810,
    "woe:adm0_id":23424810,
    "woe:name_adm0":"\u010cesk\u00e1 republika",
    "woe:name_adm1":"Kraj Vyso\u010dina",
    "woe:placetype":"Town",
    "wof:name":"K\u0159e\u0161\u00edn",
    "wof:placetype":"locality",
    "wof:population":147
},
  "geometry": {"coordinates":[15.04371,49.58172],"type":"Point"}
}