{
  "type": "Feature",
  "properties": {
    "iso:country":"CZ",
    "name:ces_x_preferred":[
        "Leti\u0161t\u011b Jind\u0159ich\u016fv Hradec"
    ],
    "name:deu_x_preferred":[
        "Flughafen Jind\u0159ich\u016fv Hradec"
    ],
    "name:eng_x_preferred":[
        "Jindrichuv Hradec Airport"
    ],
    "name:eng_x_variant":[
        "LKJH",
        "Jind\u0159ich\u016fv Hradec Airport"
    ],
    "name:fra_x_preferred":[
        "Jind\u0159ich\u016fv Hradec"
    ],
    "name:fra_x_variant":[
        "A\u00e9roport Jind\u0159ich\u016fv Hradec"
    ],
    "name:msa_x_preferred":[
        "Lapangan Terbang Jindrichuv Hradec"
    ],
    "name:msa_x_variant":[
        "Lapangan Terbang Jind\u0159ich\u016fv Hradec"
    ],
    "name:slk_x_preferred":[
        "Letisko Jind\u0159ich\u016fv Hradec"
    ],
    "oa:elevation_ft":"1667",
    "oa:type":"small_airport",
    "woe:hierarchy":{
        "country_id":23424810,
        "county_id":12582539,
        "localadmin_id":12604526,
        "planet_id":1,
        "state_id":20070502
    },
    "wof:name":"Letiste Jindrichuv Hradec",
    "wof:placetype":"campus"
},
  "geometry": {"coordinates":[14.971664,49.150831],"type":"Point"}
}