{
  "type": "Feature",
  "properties": {
    "iso:country":"CZ",
    "oa:elevation_ft":"1667",
    "oa:type":"small_airport",
    "woe:hierarchy":{
        "country_id":23424810,
        "county_id":12582539,
        "localadmin_id":12604526,
        "planet_id":1,
        "state_id":20070502
    },
    "wof:name":"Letiste Jindrichuv Hradec",
    "wof:placetype":"campus"
},
  "geometry": {"coordinates":[14.9716639,49.1508306],"type":"Point"}
}