{
  "type": "Feature",
  "properties": {
    "gn:gn_country":"CZ",
    "gn:gn_fcode":"PPL",
    "gn:gn_pop":618,
    "gn:population":618,
    "iso:country":"CZ",
    "name:azb_x_preferred":[
        "\u067e\u0648\u0644\u0646\u06cc\u062a\u0634\u06a9\u0627"
    ],
    "name:ceb_x_preferred":[
        "Polni\u010dka"
    ],
    "name:ces_x_preferred":[
        "Polni\u010dka"
    ],
    "name:deu_x_preferred":[
        "Polni\u010dka"
    ],
    "name:eng_x_preferred":[
        "Polni\u010dka"
    ],
    "name:eus_x_preferred":[
        "Polni\u010dka"
    ],
    "name:fas_x_preferred":[
        "\u067e\u0648\u0644\u0646\u06cc\u062a\u0634\u06a9\u0627"
    ],
    "name:fra_x_preferred":[
        "Polni\u010dka"
    ],
    "name:hun_x_preferred":[
        "Polni\u010dka"
    ],
    "name:ita_x_preferred":[
        "Polni\u010dka"
    ],
    "name:msa_x_preferred":[
        "Polni\u010dka"
    ],
    "name:nan_x_preferred":[
        "Polni\u010dka"
    ],
    "name:nld_x_preferred":[
        "Polni\u010dka"
    ],
    "name:por_x_preferred":[
        "Polni\u010dka"
    ],
    "name:rup_x_preferred":[
        "Polni\u010dka"
    ],
    "name:slk_x_preferred":[
        "Polni\u010dka"
    ],
    "name:spa_x_preferred":[
        "Polni\u010dka"
    ],
    "name:swe_x_preferred":[
        "Polni\u010dka"
    ],
    "name:unk_x_variant":[
        "Pelles"
    ],
    "name:vie_x_preferred":[
        "Polni\u010dka"
    ],
    "qs_pg:aaroncc":"CZ",
    "qs_pg:gn_country":"CZ",
    "qs_pg:gn_fcode":"PPL",
    "qs_pg:gn_pop":618,
    "qs_pg:name":"Polni\u010dka",
    "qs_pg:name_adm0":"\u010cesk\u00e1 republika",
    "qs_pg:name_adm1":"Kraj Vyso\u010dina",
    "qs_pg:photos_9k":1,
    "qs_pg:photos_9r":1,
    "qs_pg:photos_all":1,
    "qs_pg:photos_sr":0,
    "qs_pg:pop_sr":2,
    "qs_pg:qs_pg_placetype":"locality",
    "qs_pg:qs_pg_placetype_gp":"Town",
    "qs_pg:woe_adm0":23424810,
    "woe:adm0_id":23424810,
    "woe:name_adm0":"\u010cesk\u00e1 republika",
    "woe:name_adm1":"Kraj Vyso\u010dina",
    "woe:placetype":"Town",
    "wof:name":"Polni\u010dka",
    "wof:placetype":"locality",
    "wof:population":618
},
  "geometry": {"coordinates":[15.91633,49.6075],"type":"Point"}
}