{
  "type": "Feature",
  "properties": {
    "gn:admin1_code":"89",
    "gn:admin2_code":"0424",
    "gn:asciiname":"Strkovice",
    "gn:cc2":"CZ",
    "gn:country_code":"CZ",
    "gn:dem":194,
    "gn:feature_class":"P",
    "gn:feature_code":"PPL",
    "gn:name":"Strkovice",
    "gn:population":0,
    "gn:timezone":"Europe/Prague",
    "iso:country":"CZ",
    "name:und_x_variant":[
        "Sterkowitz"
    ],
    "wof:name":"Strkovice",
    "wof:placetype":"locality"
},
  "geometry": {"coordinates":[13.65154,50.32552],"type":"Point"}
}