{
  "type": "Feature",
  "properties": {
    "gn:admin1_code":"89.0",
    "gn:admin2_code":"0426",
    "gn:asciiname":"Lhenice",
    "gn:cc2":"CZ",
    "gn:country_code":"CZ",
    "gn:dem":302,
    "gn:feature_class":"P",
    "gn:feature_code":"PPL",
    "gn:name":"Lhenice",
    "gn:population":0,
    "gn:timezone":"Europe/Prague",
    "iso:country":"CZ",
    "name:azb_x_preferred":[
        "\u0644\u0647\u0646\u06cc\u062a\u0633\u0647"
    ],
    "name:ceb_x_preferred":[
        "Lhenice"
    ],
    "name:ces_x_preferred":[
        "Lhenice"
    ],
    "name:deu_x_preferred":[
        "Lhenice"
    ],
    "name:eus_x_preferred":[
        "Lhenice"
    ],
    "name:fas_x_preferred":[
        "\u0644\u0647\u0646\u06cc\u062a\u0633\u0647"
    ],
    "name:fra_x_preferred":[
        "Lhenice"
    ],
    "name:hun_x_preferred":[
        "Lhenice"
    ],
    "name:ita_x_preferred":[
        "Lhenice"
    ],
    "name:msa_x_preferred":[
        "Lhenice"
    ],
    "name:nld_x_preferred":[
        "Lhenice"
    ],
    "name:por_x_preferred":[
        "Lhenice"
    ],
    "name:slk_x_preferred":[
        "Lhenice"
    ],
    "name:spa_x_preferred":[
        "Lhenice"
    ],
    "name:srp_x_preferred":[
        "\u041b\u0445\u0435\u045a\u0438\u0446\u0435"
    ],
    "name:swe_x_preferred":[
        "Lhenice"
    ],
    "name:und_x_variant":[
        "Welhenitz"
    ],
    "name:vie_x_preferred":[
        "Lhenice"
    ],
    "wof:name":"Lhenice",
    "wof:placetype":"locality"
},
  "geometry": {"coordinates":[13.8656,50.57539000000001],"type":"Point"}
}