{
  "type": "Feature",
  "properties": {
    "iso:country":"CZ",
    "qs_pg:aaroncc":"CZ",
    "qs_pg:name":"Pasohl\u00e1vky",
    "qs_pg:name_adm0":"\u010cesk\u00e1 republika",
    "qs_pg:name_adm1":"Jihomoravsk\u00fd kraj",
    "qs_pg:photos":35,
    "qs_pg:photos_1k":7,
    "qs_pg:photos_9k":1,
    "qs_pg:photos_9r":2,
    "qs_pg:photos_all":62,
    "qs_pg:photos_sr":2,
    "qs_pg:pop_sr":0,
    "qs_pg:qs_pg_placetype":"localadmin",
    "qs_pg:qs_pg_placetype_gp":"LocalAdmin",
    "qs_pg:woe_adm0":23424810,
    "woe:adm0_id":23424810,
    "woe:name_adm0":"\u010cesk\u00e1 republika",
    "woe:name_adm1":"Jihomoravsk\u00fd kraj",
    "woe:placetype":"LocalAdmin",
    "wof:name":"Pasohl\u00e1vky",
    "wof:placetype":"localadmin"
},
  "geometry": {"coordinates":[16.543916,48.899878],"type":"Point"}
}