{
  "type": "Feature",
  "properties": {
    "gn:admin1_code":"85",
    "gn:admin2_code":"0801",
    "gn:asciiname":"Vraclavek",
    "gn:country_code":"CZ",
    "gn:dem":458,
    "gn:feature_class":"P",
    "gn:feature_code":"PPL",
    "gn:name":"Vracl\u00e1vek",
    "gn:population":0,
    "gn:timezone":"Europe/Prague",
    "iso:country":"CZ",
    "name:und_x_variant":[
        "Klein-Bressel",
        "Vracl\u00e1vek"
    ],
    "wof:name":"Vraclavek",
    "wof:placetype":"locality"
},
  "geometry": {"coordinates":[17.56486,50.12553],"type":"Point"}
}