{
  "type": "Feature",
  "properties": {
    "gn:admin1_code":"78.0",
    "gn:admin2_code":"0621",
    "gn:asciiname":"Olesna",
    "gn:country_code":"CZ",
    "gn:dem":412,
    "gn:feature_class":"P",
    "gn:feature_code":"PPL",
    "gn:name":"Ole\u0161n\u00e1",
    "gn:population":0,
    "gn:timezone":"Europe/Prague",
    "iso:country":"CZ",
    "wof:name":"Olesna",
    "wof:placetype":"locality"
},
  "geometry": {"coordinates":[16.63691,49.34022],"type":"Point"}
}