{
  "type": "Feature",
  "properties": {
    "gn:admin1_code":"79.0",
    "gn:admin2_code":"0314",
    "gn:asciiname":"Nova Ves",
    "gn:country_code":"CZ",
    "gn:dem":443,
    "gn:feature_class":"P",
    "gn:feature_code":"PPL",
    "gn:name":"Nov\u00e1 Ves",
    "gn:population":0,
    "gn:timezone":"Europe/Prague",
    "iso:country":"CZ",
    "wof:name":"Nova Ves",
    "wof:placetype":"locality"
},
  "geometry": {"coordinates":[14.25616,49.2233],"type":"Point"}
}