{
  "type": "Feature",
  "properties": {
    "gn:country":"CZ",
    "gn:fcode":"PPL",
    "gn:population":250,
    "iso:country":"CZ",
    "name:azb_x_preferred":[
        "\u0646\u0648\u062a\u0633\u0647\u0644\u0647"
    ],
    "name:ceb_x_preferred":[
        "Nevcehle"
    ],
    "name:ces_x_preferred":[
        "Nevcehle"
    ],
    "name:deu_x_preferred":[
        "Nevcehle"
    ],
    "name:eng_x_preferred":[
        "Nevcehle"
    ],
    "name:eus_x_preferred":[
        "Nevcehle"
    ],
    "name:fas_x_preferred":[
        "\u0646\u0648\u062a\u0633\u0647\u0644\u0647"
    ],
    "name:fra_x_preferred":[
        "Nevcehle"
    ],
    "name:hun_x_preferred":[
        "Nevcehle"
    ],
    "name:ita_x_preferred":[
        "Nevcehle"
    ],
    "name:msa_x_preferred":[
        "Nevcehle"
    ],
    "name:nan_x_preferred":[
        "Nevcehle"
    ],
    "name:nld_x_preferred":[
        "Nevcehle"
    ],
    "name:pol_x_preferred":[
        "Nevcehle"
    ],
    "name:por_x_preferred":[
        "Nevcehle"
    ],
    "name:slk_x_preferred":[
        "Nevcehle"
    ],
    "name:spa_x_preferred":[
        "Nevcehle"
    ],
    "name:srp_x_preferred":[
        "\u041d\u0435\u0432\u0446\u0435\u0445\u043b\u0435"
    ],
    "name:swe_x_preferred":[
        "Nevcehle"
    ],
    "name:vie_x_preferred":[
        "Nevcehle"
    ],
    "qs_pg:aaroncc":"CZ",
    "qs_pg:gn_country":"CZ",
    "qs_pg:gn_fcode":"PPL",
    "qs_pg:gn_pop":250,
    "qs_pg:name":"Nevcehle",
    "qs_pg:name_adm0":"\u010cesk\u00e1 republika",
    "qs_pg:name_adm1":"Kraj Vyso\u010dina",
    "qs_pg:photos_9r":0,
    "qs_pg:photos_sr":0,
    "qs_pg:pop_sr":2,
    "qs_pg:qs_pg_placetype":"locality",
    "qs_pg:qs_pg_placetype_gp":"Town",
    "qs_pg:woe_adm0":23424810,
    "woe:adm0_id":23424810,
    "woe:name_adm0":"\u010cesk\u00e1 republika",
    "woe:name_adm1":"Kraj Vyso\u010dina",
    "woe:placetype":"Town",
    "wof:name":"Nevcehle",
    "wof:placetype":"locality",
    "wof:population":250
},
  "geometry": {"coordinates":[15.53442,49.22573],"type":"Point"}
}