{
  "type": "Feature",
  "properties": {
    "gn:gn_country":"CZ",
    "gn:gn_fcode":"PPL",
    "gn:gn_pop":247,
    "gn:population":247,
    "iso:country":"CZ",
    "name:ces_x_preferred":[
        "Petrovice"
    ],
    "name:deu_x_preferred":[
        "Petrovice u Rakovn\u00edka"
    ],
    "name:eng_x_preferred":[
        "Petrovice"
    ],
    "name:epo_x_preferred":[
        "Petrovice"
    ],
    "name:fas_x_preferred":[
        "\u067e\u062a\u0631\u0648\u0648\u06cc\u062a\u0633\u0647"
    ],
    "name:hun_x_preferred":[
        "Petrovice"
    ],
    "name:ita_x_preferred":[
        "Petrovice"
    ],
    "name:msa_x_preferred":[
        "Petrovice"
    ],
    "name:nld_x_preferred":[
        "Petrovice"
    ],
    "name:por_x_preferred":[
        "Petrovice"
    ],
    "name:rup_x_preferred":[
        "Petrovice"
    ],
    "name:slk_x_preferred":[
        "Petrovice"
    ],
    "name:srp_x_preferred":[
        "\u041f\u0435\u0442\u0440\u043e\u0432\u0438\u0446\u0435"
    ],
    "name:swe_x_preferred":[
        "Petrovice"
    ],
    "name:unk_x_variant":[
        "Petrowitz"
    ],
    "name:vie_x_preferred":[
        "Petrovice"
    ],
    "qs_pg:aaroncc":"CZ",
    "qs_pg:gn_country":"CZ",
    "qs_pg:gn_fcode":"PPL",
    "qs_pg:gn_pop":247,
    "qs_pg:name":"Petrovice",
    "qs_pg:name_adm0":"\u010cesk\u00e1 republika",
    "qs_pg:name_adm1":"St\u0159edo\u010desk\u00fd kraj",
    "qs_pg:photos_9k":1,
    "qs_pg:photos_9r":1,
    "qs_pg:photos_all":1,
    "qs_pg:photos_sr":0,
    "qs_pg:pop_sr":2,
    "qs_pg:qs_pg_placetype":"locality",
    "qs_pg:qs_pg_placetype_gp":"Town",
    "qs_pg:woe_adm0":23424810,
    "woe:adm0_id":23424810,
    "woe:name_adm0":"\u010cesk\u00e1 republika",
    "woe:name_adm1":"St\u0159edo\u010desk\u00fd kraj",
    "woe:placetype":"Town",
    "wof:name":"Petrovice",
    "wof:placetype":"locality",
    "wof:population":247
},
  "geometry": {"coordinates":[13.63917,50.06726],"type":"Point"}
}