{
  "type": "Feature",
  "properties": {
    "gn:gn_country":"CZ",
    "gn:gn_fcode":"PPL",
    "gn:gn_pop":341,
    "gn:population":341,
    "iso:country":"CZ",
    "name:azb_x_preferred":[
        "\u0698\u06cc\u0698\u06a9\u0648\u0648 \u067e\u0648\u0644\u0647"
    ],
    "name:ceb_x_preferred":[
        "\u017di\u017ekovo Pole"
    ],
    "name:ces_x_preferred":[
        "\u017di\u017ekovo Pole"
    ],
    "name:deu_x_preferred":[
        "\u017di\u017ekovo Pole"
    ],
    "name:eng_x_preferred":[
        "\u017di\u017ekovo Pole"
    ],
    "name:eus_x_preferred":[
        "\u017di\u017ekovo Pole"
    ],
    "name:fas_x_preferred":[
        "\u0698\u06cc\u0698\u06a9\u0648\u0648 \u067e\u0648\u0644\u0647"
    ],
    "name:fra_x_preferred":[
        "\u017di\u017ekovo Pole"
    ],
    "name:hun_x_preferred":[
        "\u017di\u017ekovo Pole"
    ],
    "name:ita_x_preferred":[
        "\u017di\u017ekovo Pole"
    ],
    "name:msa_x_preferred":[
        "\u017di\u017ekovo Pole"
    ],
    "name:nan_x_preferred":[
        "\u017di\u017ekovo Pole"
    ],
    "name:nld_x_preferred":[
        "\u017di\u017ekovo Pole"
    ],
    "name:por_x_preferred":[
        "\u017di\u017ekovo Pole"
    ],
    "name:rup_x_preferred":[
        "\u017di\u017ekovo Pole"
    ],
    "name:slk_x_preferred":[
        "\u017di\u017ekovo Pole"
    ],
    "name:spa_x_preferred":[
        "\u017di\u017ekovo Pole"
    ],
    "name:srp_x_preferred":[
        "\u0416\u0438\u0448\u043a\u043e\u0432\u043e \u041f\u043e\u043b\u0435"
    ],
    "name:swe_x_preferred":[
        "\u017di\u017ekovo Pole"
    ],
    "name:unk_x_variant":[
        "Sch\u00f6nfeld"
    ],
    "name:vie_x_preferred":[
        "\u017di\u017ekovo Pole"
    ],
    "qs_pg:aaroncc":"CZ",
    "qs_pg:gn_country":"CZ",
    "qs_pg:gn_fcode":"PPL",
    "qs_pg:gn_pop":341,
    "qs_pg:name":"\u017di\u017ekovo Pole",
    "qs_pg:name_adm0":"\u010cesk\u00e1 republika",
    "qs_pg:name_adm1":"Kraj Vyso\u010dina",
    "qs_pg:photos_9r":0,
    "qs_pg:photos_sr":0,
    "qs_pg:pop_sr":2,
    "qs_pg:qs_pg_placetype":"locality",
    "qs_pg:qs_pg_placetype_gp":"Town",
    "qs_pg:woe_adm0":23424810,
    "woe:adm0_id":23424810,
    "woe:name_adm0":"\u010cesk\u00e1 republika",
    "woe:name_adm1":"Kraj Vyso\u010dina",
    "woe:placetype":"Town",
    "wof:name":"\u017di\u017ekovo Pole",
    "wof:placetype":"locality",
    "wof:population":341
},
  "geometry": {"coordinates":[15.73513,49.61063],"type":"Point"}
}