{
  "type": "Feature",
  "properties": {
    "iso:country":"CZ",
    "name:ara_x_preferred":[
        "\u062c\u062f\u064a\u0627\u0631 \u0646\u0627\u062f \u0633\u0627\u0632\u0627\u0641\u0648"
    ],
    "name:ceb_x_preferred":[
        "\u017d\u010f\u00e1r nad S\u00e1zavou"
    ],
    "name:ces_x_preferred":[
        "\u017d\u010f\u00e1r nad S\u00e1zavou"
    ],
    "name:deu_x_preferred":[
        "\u017d\u010f\u00e1r nad S\u00e1zavou"
    ],
    "name:epo_x_preferred":[
        "\u017d\u010f\u00e1r nad S\u00e1zavou"
    ],
    "name:eus_x_preferred":[
        "\u017d\u010f\u00e1r nad S\u00e1zavou"
    ],
    "name:fas_x_preferred":[
        "\u0698\u062f\u0627\u0631 \u0646\u0627\u062f \u0633\u0627\u0632\u0627\u0648\u0648"
    ],
    "name:fra_x_preferred":[
        "\u017d\u010f\u00e1r nad S\u00e1zavou"
    ],
    "name:hun_x_preferred":[
        "\u017d\u010f\u00e1r nad S\u00e1zavou"
    ],
    "name:ita_x_preferred":[
        "\u017d\u010f\u00e1r nad S\u00e1zavou"
    ],
    "name:lat_x_preferred":[
        "Sar"
    ],
    "name:lav_x_preferred":[
        "\u017ddj\u0101ra pie S\u0101zavas"
    ],
    "name:lit_x_preferred":[
        "\u017ddiaras prie Sazavos"
    ],
    "name:msa_x_preferred":[
        "\u017d\u010f\u00e1r nad S\u00e1zavou"
    ],
    "name:nld_x_preferred":[
        "\u017d\u010f\u00e1r nad S\u00e1zavou"
    ],
    "name:nor_x_preferred":[
        "\u017d\u010f\u00e1r nad S\u00e1zavou"
    ],
    "name:pol_x_preferred":[
        "Zdziar nad Sazaw\u0105"
    ],
    "name:por_x_preferred":[
        "\u017d\u010f\u00e1r nad S\u00e1zavou"
    ],
    "name:rus_x_preferred":[
        "\u0416\u0434\u044f\u0440-\u043d\u0430\u0434-\u0421\u0430\u0437\u0430\u0432\u043e\u0443"
    ],
    "name:slk_x_preferred":[
        "\u017d\u010f\u00e1r nad S\u00e1zavou"
    ],
    "name:slv_x_preferred":[
        "\u017d\u010f\u00e1r nad S\u00e1zavou"
    ],
    "name:spa_x_preferred":[
        "\u017d\u010f\u00e1r nad S\u00e1zavou"
    ],
    "name:srp_x_preferred":[
        "\u0416\u0434\u0458\u0430\u0440 \u043d\u0430 \u0421\u0430\u0437\u0430\u0432\u0438"
    ],
    "name:swe_x_preferred":[
        "\u017d\u010f\u00e1r nad S\u00e1zavou"
    ],
    "name:szl_x_preferred":[
        "\u017d\u010f\u00e1r nad S\u00e1zavou"
    ],
    "name:tur_x_preferred":[
        "\u017d\u010f\u00e1r nad S\u00e1zavou"
    ],
    "name:ukr_x_preferred":[
        "\u0416\u0434\u044f\u0440-\u043d\u0430\u0434-\u0421\u0430\u0437\u0430\u0432\u043e\u044e"
    ],
    "name:vie_x_preferred":[
        "\u017d\u010f\u00e1r nad S\u00e1zavou"
    ],
    "name:war_x_preferred":[
        "\u017d\u010f\u00e1r nad S\u00e1zavou"
    ],
    "name:zho_x_preferred":[
        "\u85a9\u624e\u74e6\u6cb3\u7554\u65e5\u8cc8\u723e"
    ],
    "qs_pg:aaroncc":"CZ",
    "qs_pg:name":"\u017d\u010f\u00e1r nad S\u00e1zavou",
    "qs_pg:name_adm0":"\u010cesk\u00e1 republika",
    "qs_pg:name_adm1":"Kraj Vyso\u010dina",
    "qs_pg:photos":2,
    "qs_pg:photos_1k":1,
    "qs_pg:photos_9k":3,
    "qs_pg:photos_9r":5,
    "qs_pg:photos_all":589,
    "qs_pg:photos_sr":1,
    "qs_pg:pop_sr":0,
    "qs_pg:qs_pg_placetype":"localadmin",
    "qs_pg:qs_pg_placetype_gp":"LocalAdmin",
    "qs_pg:woe_adm0":23424810,
    "woe:adm0_id":23424810,
    "woe:name_adm0":"\u010cesk\u00e1 republika",
    "woe:name_adm1":"Kraj Vyso\u010dina",
    "woe:placetype":"LocalAdmin",
    "wof:name":"\u017d\u010f\u00e1r nad S\u00e1zavou",
    "wof:placetype":"localadmin"
},
  "geometry": {"coordinates":[15.938082,49.581989],"type":"Point"}
}