{
  "type": "Feature",
  "properties": {
    "gn:admin1_code":"88.0",
    "gn:admin2_code":"0203",
    "gn:asciiname":"Motycin",
    "gn:country_code":"CZ",
    "gn:dem":359,
    "gn:feature_class":"P",
    "gn:feature_code":"PPL",
    "gn:name":"Moty\u010d\u00edn",
    "gn:population":0,
    "gn:timezone":"Europe/Prague",
    "iso:country":"CZ",
    "name:und_x_variant":[
        "Motitschin",
        "Moty\u010d\u00edn"
    ],
    "wof:name":"Motycin",
    "wof:placetype":"locality"
},
  "geometry": {"coordinates":[14.11667,50.16667],"type":"Point"}
}