{
  "type": "Feature",
  "properties": {
    "gn:gn_country":"CZ",
    "gn:gn_fcode":"PPL",
    "gn:gn_pop":1290,
    "gn:population":1290,
    "iso:country":"CZ",
    "name:cze_x_preferred":[
        "K\u00e1jov"
    ],
    "name:dut_x_preferred":[
        "K\u00e1jov"
    ],
    "name:eng_x_preferred":[
        "K\u00e1jov"
    ],
    "name:fre_x_preferred":[
        "K\u00e1jov"
    ],
    "name:ger_x_preferred":[
        "K\u00e1jov"
    ],
    "name:hun_x_preferred":[
        "K\u00e1jov"
    ],
    "name:ita_x_preferred":[
        "K\u00e1jov"
    ],
    "name:may_x_preferred":[
        "K\u00e1jov"
    ],
    "name:per_x_preferred":[
        "\u06a9\u0627\u06cc\u0648\u0648"
    ],
    "name:pol_x_preferred":[
        "K\u00e1jov"
    ],
    "name:por_x_preferred":[
        "K\u00e1jov"
    ],
    "name:slo_x_preferred":[
        "K\u00e1jov"
    ],
    "name:srp_x_preferred":[
        "\u041a\u0430\u0458\u043e\u0432"
    ],
    "name:swe_x_preferred":[
        "K\u00e1jov"
    ],
    "name:unk_x_variant":[
        "Gojau"
    ],
    "name:vie_x_preferred":[
        "K\u00e1jov"
    ],
    "qs_pg:aaroncc":"CZ",
    "qs_pg:gn_country":"CZ",
    "qs_pg:gn_fcode":"PPL",
    "qs_pg:gn_pop":1290,
    "qs_pg:name":"K\u00e1jov",
    "qs_pg:name_adm0":"\u010cesk\u00e1 republika",
    "qs_pg:name_adm1":"Jiho\u010desk\u00fd kraj",
    "qs_pg:photos":34,
    "qs_pg:photos_1k":7,
    "qs_pg:photos_9k":1,
    "qs_pg:photos_9r":2,
    "qs_pg:photos_all":34,
    "qs_pg:photos_sr":2,
    "qs_pg:pop_sr":3,
    "qs_pg:qs_pg_placetype":"locality",
    "qs_pg:qs_pg_placetype_gp":"Town",
    "qs_pg:woe_adm0":23424810,
    "woe:adm0_id":23424810,
    "woe:name_adm0":"\u010cesk\u00e1 republika",
    "woe:name_adm1":"Jiho\u010desk\u00fd kraj",
    "woe:placetype":"Town",
    "wof:name":"K\u00e1jov",
    "wof:placetype":"locality",
    "wof:population":1290
},
  "geometry": {"coordinates":[14.25859,48.81082],"type":"Point"}
}