{
  "type": "Feature",
  "properties": {
    "gn:admin1_code":"89.0",
    "gn:admin2_code":"0426",
    "gn:asciiname":"Oldrichov",
    "gn:country_code":"CZ",
    "gn:dem":249,
    "gn:feature_class":"P",
    "gn:feature_code":"PPL",
    "gn:name":"Old\u0159ichov",
    "gn:population":0,
    "gn:timezone":"Europe/Prague",
    "iso:country":"CZ",
    "name:und_x_variant":[
        "Ullersdorf",
        "Old\u0159ichov"
    ],
    "wof:name":"Oldrichov",
    "wof:placetype":"locality"
},
  "geometry": {"coordinates":[13.75506,50.63577],"type":"Point"}
}