{
  "type": "Feature",
  "properties": {
    "gn:admin1_code":"88.0",
    "gn:admin2_code":"0201",
    "gn:asciiname":"Nesvacily",
    "gn:country_code":"CZ",
    "gn:dem":377,
    "gn:feature_class":"P",
    "gn:feature_code":"PPL",
    "gn:name":"Nesva\u010dily",
    "gn:population":0,
    "gn:timezone":"Europe/Prague",
    "iso:country":"CZ",
    "wof:name":"Nesvacily",
    "wof:placetype":"locality"
},
  "geometry": {"coordinates":[14.63701,49.73297],"type":"Point"}
}