{
  "type": "Feature",
  "properties": {
    "gn:admin1_code":"88",
    "gn:admin2_code":"0208",
    "gn:asciiname":"Sovolusky",
    "gn:country_code":"CZ",
    "gn:dem":248,
    "gn:feature_class":"P",
    "gn:feature_code":"PPL",
    "gn:name":"Sovolusky",
    "gn:population":0,
    "gn:timezone":"Europe/Prague",
    "iso:country":"CZ",
    "name:ces_x_preferred":[
        "Sovolusky"
    ],
    "name:deu_x_preferred":[
        "Sovolusky"
    ],
    "wof:name":"Sovolusky",
    "wof:placetype":"locality"
},
  "geometry": {"coordinates":[15.11305,50.32843],"type":"Point"}
}