{
  "type": "Feature",
  "properties": {
    "iso:country":"CZ",
    "name:ces_x_preferred":[
        "V\u00edtkovice"
    ],
    "name:cze_x_colloquial":[
        "Vitkovice"
    ],
    "name:cze_x_variant":[
        "Witkowitz"
    ],
    "name:deu_x_historical":[
        "Witkowitz"
    ],
    "name:deu_x_preferred":[
        "V\u00edtkovice"
    ],
    "name:deu_x_variant":[
        "Witkowitz"
    ],
    "name:eng_x_preferred":[
        "V\u00edtkovice"
    ],
    "name:epo_x_preferred":[
        "V\u00edtkovice"
    ],
    "name:fra_x_preferred":[
        "V\u00edtkovice"
    ],
    "name:heb_x_preferred":[
        "\u05d5\u05d9\u05d8\u05e7\u05d5\u05d1\u05d9\u05e6\u05d4"
    ],
    "name:jpn_x_preferred":[
        "\u30f4\u30a3\u30c8\u30b3\u30f4\u30a3\u30c3\u30c4"
    ],
    "name:nld_x_preferred":[
        "V\u00edtkovice"
    ],
    "name:pol_x_preferred":[
        "Witkowice"
    ],
    "name:slk_x_preferred":[
        "V\u00edtkovice"
    ],
    "name:ukr_x_preferred":[
        "\u0412\u0456\u0442\u043a\u043e\u0432\u0456\u0446\u0435"
    ],
    "qs:gn_fcode":"PPLX",
    "qs:gn_local":0,
    "qs:gn_namadm1":"85",
    "qs:gn_name":"V\u00edtkovice",
    "qs:local_max":2778,
    "qs:local_sum":9373,
    "qs:localhoods":17,
    "qs:name":"V\u00edtkovice",
    "qs:name_adm0":"\u010cesk\u00e1 republika",
    "qs:name_adm1":"Moravskoslezsk\u00fd kraj",
    "qs:name_adm2":"Ostrava",
    "qs:name_lau":"Ostrava",
    "qs:name_local":"Ostrava",
    "qs:photo_max":2276,
    "qs:photo_sum":2778,
    "qs:placetype":"Suburb",
    "qs:quad_count":41,
    "qs:woe_adm0":23424810,
    "qs:woe_adm1":20070471,
    "qs:woe_adm2":12582577,
    "qs:woe_lau":12607114,
    "qs:woe_local":795610,
    "qs:woe_ver":"7.10.0",
    "wof:lang":[
        "cze"
    ],
    "wof:name":"V\u00edtkovice",
    "wof:placetype":"neighbourhood"
},
  "geometry": {"coordinates":[18.258445,49.807675],"type":"Point"}
}