{
  "type": "Feature",
  "properties": {
    "gn:gn_country":"CZ",
    "gn:gn_fcode":"PPL",
    "gn:gn_pop":650,
    "gn:population":650,
    "iso:country":"CZ",
    "name:azb_x_preferred":[
        "\u0633\u0644\u0648\u0647\u06cc"
    ],
    "name:bul_x_preferred":[
        "\u0421\u043b\u0443\u0445\u0439"
    ],
    "name:ceb_x_preferred":[
        "Sluhy"
    ],
    "name:ces_x_preferred":[
        "Sluhy"
    ],
    "name:deu_x_preferred":[
        "Sluhy"
    ],
    "name:eng_x_preferred":[
        "Sluhy"
    ],
    "name:eus_x_preferred":[
        "Sluhy"
    ],
    "name:fas_x_preferred":[
        "\u0633\u0644\u0648\u0647\u06cc"
    ],
    "name:fra_x_preferred":[
        "Sluhy"
    ],
    "name:hun_x_preferred":[
        "Sluhy"
    ],
    "name:ita_x_preferred":[
        "Sluhy"
    ],
    "name:msa_x_preferred":[
        "Sluhy"
    ],
    "name:nan_x_preferred":[
        "Sluhy"
    ],
    "name:nld_x_preferred":[
        "Sluhy"
    ],
    "name:pol_x_preferred":[
        "Sluhy"
    ],
    "name:por_x_preferred":[
        "Sluhy"
    ],
    "name:slk_x_preferred":[
        "Sluhy"
    ],
    "name:spa_x_preferred":[
        "Sluhy"
    ],
    "name:srp_x_preferred":[
        "\u0421\u043b\u0443\u0445\u0438"
    ],
    "name:swe_x_preferred":[
        "Sluhy"
    ],
    "name:vie_x_preferred":[
        "Sluhy"
    ],
    "qs_pg:aaroncc":"CZ",
    "qs_pg:gn_country":"CZ",
    "qs_pg:gn_fcode":"PPL",
    "qs_pg:gn_pop":650,
    "qs_pg:name":"Sluhy",
    "qs_pg:name_adm0":"\u010cesk\u00e1 republika",
    "qs_pg:name_adm1":"St\u0159edo\u010desk\u00fd kraj",
    "qs_pg:photos_9r":0,
    "qs_pg:photos_sr":0,
    "qs_pg:pop_sr":2,
    "qs_pg:qs_pg_placetype":"locality",
    "qs_pg:qs_pg_placetype_gp":"Town",
    "qs_pg:woe_adm0":23424810,
    "woe:adm0_id":23424810,
    "woe:name_adm0":"\u010cesk\u00e1 republika",
    "woe:name_adm1":"St\u0159edo\u010desk\u00fd kraj",
    "woe:placetype":"Town",
    "wof:name":"Sluhy",
    "wof:placetype":"locality",
    "wof:population":650
},
  "geometry": {"coordinates":[14.55767,50.19244],"type":"Point"}
}