{
  "type": "Feature",
  "properties": {
    "gn:gn_country":"CZ",
    "gn:gn_fcode":"PPL",
    "gn:gn_pop":0,
    "iso:country":"CZ",
    "name:ces_x_preferred":[
        "P\u00edsnice"
    ],
    "name:eng_x_preferred":[
        "P\u00edsnice"
    ],
    "name:fas_x_preferred":[
        "\u067e\u06cc\u0633\u0646\u06cc\u062a\u0633\u0647"
    ],
    "name:fra_x_preferred":[
        "P\u00edsnice"
    ],
    "name:pol_x_preferred":[
        "P\u00edsnice"
    ],
    "name:slk_x_preferred":[
        "P\u00edsnice"
    ],
    "name:unk_x_variant":[
        "Piesnitz"
    ],
    "qs_pg:aaroncc":"CZ",
    "qs_pg:gn_country":"CZ",
    "qs_pg:gn_fcode":"PPL",
    "qs_pg:gn_pop":0,
    "qs_pg:name":"P\u00edsnice",
    "qs_pg:name_adm0":"\u010cesk\u00e1 republika",
    "qs_pg:name_adm1":"Hlavn\u00ed m\u011bsto Praha",
    "qs_pg:photos_9r":0,
    "qs_pg:photos_sr":0,
    "qs_pg:pop_sr":0,
    "qs_pg:qs_pg_placetype":"neighbourhood",
    "qs_pg:qs_pg_placetype_gp":"Suburb",
    "qs_pg:woe_adm0":23424810,
    "woe:adm0_id":23424810,
    "woe:name_adm0":"\u010cesk\u00e1 republika",
    "woe:name_adm1":"Hlavn\u00ed m\u011bsto Praha",
    "woe:placetype":"Suburb",
    "wof:name":"P\u00edsnice",
    "wof:placetype":"neighbourhood"
},
  "geometry": {"coordinates":[14.46693,49.99328],"type":"Point"}
}