{
  "type": "Feature",
  "properties": {
    "gn:admin1_code":"89.0",
    "gn:admin2_code":"0422",
    "gn:asciiname":"Mezilesi u Prisecnice",
    "gn:country_code":"CZ",
    "gn:dem":782,
    "gn:feature_class":"P",
    "gn:feature_code":"PPL",
    "gn:name":"Meziles\u00ed u P\u0159\u00edse\u010dnice",
    "gn:population":0,
    "gn:timezone":"Europe/Prague",
    "iso:country":"CZ",
    "name:und_x_variant":[
        "Orpus",
        "Meziles\u00ed u P\u0159\u00edse\u010dnice"
    ],
    "wof:name":"Mezilesi u Prisecnice",
    "wof:placetype":"locality"
},
  "geometry": {"coordinates":[13.10541,50.44201],"type":"Point"}
}