{
  "type": "Feature",
  "properties": {
    "gn:admin1_code":"81.0",
    "gn:admin2_code":"0412",
    "gn:asciiname":"Horni Valov",
    "gn:country_code":"CZ",
    "gn:dem":733,
    "gn:feature_class":"P",
    "gn:feature_code":"PPL",
    "gn:name":"Horn\u00ed Valov",
    "gn:population":0,
    "gn:timezone":"Europe/Prague",
    "iso:country":"CZ",
    "name:und_x_variant":[
        "Ober Wohlau",
        "Horn\u00ed Valov"
    ],
    "wof:name":"Horni Valov",
    "wof:placetype":"locality"
},
  "geometry": {"coordinates":[13.06667,50.16667],"type":"Point"}
}