{
  "type": "Feature",
  "properties": {
    "gn:admin1_code":"90",
    "gn:admin2_code":"0724",
    "gn:asciiname":"Zelechovice nad Drevnici",
    "gn:country_code":"CZ",
    "gn:dem":244,
    "gn:feature_class":"P",
    "gn:feature_code":"PPL",
    "gn:name":"\u017delechovice nad D\u0159evnic\u00ed",
    "gn:population":0,
    "gn:timezone":"Europe/Prague",
    "iso:country":"CZ",
    "name:azb_x_preferred":[
        "\u0698\u0644\u062e\u0648\u0648\u06cc\u062a\u0633\u0647 \u0646\u0627\u062f \u062f\u0631\u0648\u0646\u06cc\u062a\u0633\u06cc"
    ],
    "name:ces_x_preferred":[
        "\u017delechovice nad D\u0159evnic\u00ed"
    ],
    "name:deu_x_preferred":[
        "\u017delechovice nad D\u0159evnic\u00ed"
    ],
    "name:eus_x_preferred":[
        "\u017delechovice nad D\u0159evnic\u00ed"
    ],
    "name:fas_x_preferred":[
        "\u0698\u0644\u062e\u0648\u0648\u06cc\u062a\u0633\u0647 \u0646\u0627\u062f \u062f\u0631\u0648\u0646\u06cc\u062a\u0633\u06cc"
    ],
    "name:fra_x_preferred":[
        "\u017delechovice nad D\u0159evnic\u00ed"
    ],
    "name:hun_x_preferred":[
        "\u017delechovice nad D\u0159evnic\u00ed"
    ],
    "name:ita_x_preferred":[
        "\u017delechovice nad D\u0159evnic\u00ed"
    ],
    "name:msa_x_preferred":[
        "\u017delechovice nad D\u0159evnic\u00ed"
    ],
    "name:nld_x_preferred":[
        "\u017delechovice nad D\u0159evnic\u00ed"
    ],
    "name:pol_x_preferred":[
        "\u017delechovice nad D\u0159evnic\u00ed"
    ],
    "name:por_x_preferred":[
        "\u017delechovice nad D\u0159evnic\u00ed"
    ],
    "name:slk_x_preferred":[
        "\u017delechovice nad D\u0159evnic\u00ed"
    ],
    "name:spa_x_preferred":[
        "\u017delechovice nad D\u0159evnic\u00ed"
    ],
    "name:srp_x_preferred":[
        "\u0416\u0435\u043b\u0435\u0445\u043e\u0432\u0438\u0446\u0435 \u043d\u0430 \u0414\u0440\u0435\u0432\u045a\u0438\u0446\u0438"
    ],
    "name:und_x_variant":[
        "Zelechowitz",
        "\u017delechovice nad D\u0159evnic\u00ed"
    ],
    "name:vie_x_preferred":[
        "\u017delechovice nad D\u0159evnic\u00ed"
    ],
    "wof:name":"Zelechovice nad Drevnici",
    "wof:placetype":"locality"
},
  "geometry": {"coordinates":[17.74477000000001,49.21736],"type":"Point"}
}