{
  "type": "Feature",
  "properties": {
    "gn:admin1_code":"90",
    "gn:admin2_code":"0724",
    "gn:asciiname":"Zelechovice nad Drevnici",
    "gn:country_code":"CZ",
    "gn:dem":244,
    "gn:feature_class":"P",
    "gn:feature_code":"PPL",
    "gn:name":"\u017delechovice nad D\u0159evnic\u00ed",
    "gn:population":0,
    "gn:timezone":"Europe/Prague",
    "iso:country":"CZ",
    "name:und_x_variant":[
        "Zelechowitz",
        "\u017delechovice nad D\u0159evnic\u00ed"
    ],
    "wof:name":"Zelechovice nad Drevnici",
    "wof:placetype":"locality"
},
  "geometry": {"coordinates":[17.74477000000001,49.21736],"type":"Point"}
}