{
  "type": "Feature",
  "properties": {
    "gn:country":"CZ",
    "gn:fcode":"PPL",
    "gn:population":220,
    "iso:country":"CZ",
    "name:azb_x_preferred":[
        "\u0648\u0644\u062a\u0648"
    ],
    "name:bul_x_preferred":[
        "\u0412\u0435\u043b\u0435\u0442\u043e\u0432"
    ],
    "name:ceb_x_preferred":[
        "Veletov"
    ],
    "name:ces_x_preferred":[
        "Veletov"
    ],
    "name:eng_x_preferred":[
        "Veletov"
    ],
    "name:eus_x_preferred":[
        "Veletov"
    ],
    "name:fas_x_preferred":[
        "\u0648\u0644\u062a\u0648"
    ],
    "name:fra_x_preferred":[
        "Veletov"
    ],
    "name:hun_x_preferred":[
        "Veletov"
    ],
    "name:ita_x_preferred":[
        "Veletov"
    ],
    "name:msa_x_preferred":[
        "Veletov"
    ],
    "name:nan_x_preferred":[
        "Veletov"
    ],
    "name:nld_x_preferred":[
        "Veletov"
    ],
    "name:pol_x_preferred":[
        "Veletov"
    ],
    "name:por_x_preferred":[
        "Veletov"
    ],
    "name:rup_x_preferred":[
        "Veletov"
    ],
    "name:slk_x_preferred":[
        "Veletov"
    ],
    "name:spa_x_preferred":[
        "Veletov"
    ],
    "name:srp_x_preferred":[
        "\u0412\u0435\u043b\u0435\u0442\u043e\u0432"
    ],
    "name:swe_x_preferred":[
        "Veletov"
    ],
    "name:vie_x_preferred":[
        "Veletov"
    ],
    "qs_pg:aaroncc":"CZ",
    "qs_pg:gn_country":"CZ",
    "qs_pg:gn_fcode":"PPL",
    "qs_pg:gn_pop":220,
    "qs_pg:name":"Veletov",
    "qs_pg:name_adm0":"\u010cesk\u00e1 republika",
    "qs_pg:name_adm1":"St\u0159edo\u010desk\u00fd kraj",
    "qs_pg:photos_9k":1,
    "qs_pg:photos_9r":1,
    "qs_pg:photos_all":2,
    "qs_pg:photos_sr":0,
    "qs_pg:pop_sr":2,
    "qs_pg:qs_pg_placetype":"locality",
    "qs_pg:qs_pg_placetype_gp":"Town",
    "qs_pg:woe_adm0":23424810,
    "woe:adm0_id":23424810,
    "woe:name_adm0":"\u010cesk\u00e1 republika",
    "woe:name_adm1":"St\u0159edo\u010desk\u00fd kraj",
    "woe:placetype":"Town",
    "wof:name":"Veletov",
    "wof:placetype":"locality",
    "wof:population":220
},
  "geometry": {"coordinates":[15.30508,50.0282],"type":"Point"}
}