{
  "type": "Feature",
  "properties": {
    "gn:admin1_code":"84.0",
    "gn:admin2_code":"0715",
    "gn:asciiname":"Kvetin",
    "gn:cc2":"CZ",
    "gn:country_code":"CZ",
    "gn:dem":288,
    "gn:feature_class":"P",
    "gn:feature_code":"PPL",
    "gn:name":"Kv\u011bt\u00edn",
    "gn:population":0,
    "gn:timezone":"Europe/Prague",
    "iso:country":"CZ",
    "name:und_x_variant":[
        "Kwitten"
    ],
    "wof:name":"Kvetin",
    "wof:placetype":"locality"
},
  "geometry": {"coordinates":[16.89577,49.80681],"type":"Point"}
}