{
  "type": "Feature",
  "properties": {
    "gn:country":"CZ",
    "gn:fcode":"PPL",
    "gn:population":2851,
    "iso:country":"CZ",
    "name:ceb_x_preferred":[
        "Kostelec na Han\u00e9"
    ],
    "name:ces_x_preferred":[
        "Kostelec na Han\u00e9"
    ],
    "name:deu_x_preferred":[
        "Kostelec na Han\u00e9"
    ],
    "name:eus_x_preferred":[
        "Kostelec na Han\u00e9"
    ],
    "name:fas_x_preferred":[
        "\u06a9\u0648\u0633\u062a\u0644\u062a\u0633 \u0646\u0627 \u0647\u0627\u0646\u0647"
    ],
    "name:fra_x_preferred":[
        "Kostelec na Han\u00e9"
    ],
    "name:hun_x_preferred":[
        "Kostelec na Han\u00e9"
    ],
    "name:ita_x_preferred":[
        "Kostelec na Han\u00e9"
    ],
    "name:lav_x_preferred":[
        "Kosteleca Han\u0101"
    ],
    "name:msa_x_preferred":[
        "Kostelec na Han\u00e9"
    ],
    "name:nld_x_preferred":[
        "Kostelec na Han\u00e9"
    ],
    "name:pol_x_preferred":[
        "Kostelec na Han\u00e9"
    ],
    "name:por_x_preferred":[
        "Kostelec na Han\u00e9"
    ],
    "name:slk_x_preferred":[
        "Kostelec na Han\u00e9"
    ],
    "name:spa_x_preferred":[
        "Kostelec na Han\u00e9"
    ],
    "name:srp_x_preferred":[
        "\u041a\u043e\u0441\u0442\u0435\u043b\u0435\u0446 \u043d\u0430 \u0425\u0430\u043d\u0438"
    ],
    "name:swe_x_preferred":[
        "Kostelec na Han\u00e9"
    ],
    "name:und_x_variant":[
        "Kostelec"
    ],
    "name:vie_x_preferred":[
        "Kostelec na Han\u00e9"
    ],
    "qs_pg:aaroncc":"CZ",
    "qs_pg:gn_country":"CZ",
    "qs_pg:gn_fcode":"PPL",
    "qs_pg:gn_pop":2851,
    "qs_pg:name":"Kostelec na Han\u00e9",
    "qs_pg:name_adm0":"\u010cesk\u00e1 republika",
    "qs_pg:name_adm1":"Olomouck\u00fd kraj",
    "qs_pg:photos_9k":1,
    "qs_pg:photos_9r":1,
    "qs_pg:photos_all":1,
    "qs_pg:photos_sr":0,
    "qs_pg:pop_sr":4,
    "qs_pg:qs_pg_placetype":"localadmin",
    "qs_pg:qs_pg_placetype_gp":"LocalAdmin",
    "qs_pg:woe_adm0":23424810,
    "woe:adm0_id":23424810,
    "woe:name_adm0":"\u010cesk\u00e1 republika",
    "woe:name_adm1":"Olomouck\u00fd kraj",
    "woe:placetype":"LocalAdmin",
    "wof:name":"Kostelec na Han\u00e9",
    "wof:placetype":"localadmin",
    "wof:population":2851
},
  "geometry": {"coordinates":[17.05824,49.51398],"type":"Point"}
}