{
  "type": "Feature",
  "properties": {
    "gn:gn_country":"CZ",
    "gn:gn_fcode":"PPL",
    "gn:gn_pop":0,
    "iso:country":"CZ",
    "name:azb_x_preferred":[
        "\u062f\u0631\u0698\u0648\u0648\u06cc\u062a\u0633\u0647"
    ],
    "name:ces_x_preferred":[
        "Dr\u017eovice"
    ],
    "name:deu_x_preferred":[
        "Dr\u017eovice"
    ],
    "name:eng_x_preferred":[
        "Dr\u017eovice"
    ],
    "name:eus_x_preferred":[
        "Dr\u017eovice"
    ],
    "name:fas_x_preferred":[
        "\u062f\u0631\u0698\u0648\u0648\u06cc\u062a\u0633\u0647"
    ],
    "name:fra_x_preferred":[
        "Dr\u017eovice"
    ],
    "name:hun_x_preferred":[
        "Dr\u017eovice"
    ],
    "name:ita_x_preferred":[
        "Dr\u017eovice"
    ],
    "name:msa_x_preferred":[
        "Dr\u017eovice"
    ],
    "name:nan_x_preferred":[
        "Dr\u017eovice"
    ],
    "name:nld_x_preferred":[
        "Dr\u017eovice"
    ],
    "name:pol_x_preferred":[
        "Dr\u017eovice"
    ],
    "name:por_x_preferred":[
        "Dr\u017eovice"
    ],
    "name:slk_x_preferred":[
        "Dr\u017eovice"
    ],
    "name:spa_x_preferred":[
        "Dr\u017eovice"
    ],
    "name:srp_x_preferred":[
        "\u0414\u0440\u0436\u043e\u0432\u0438\u0446\u0435"
    ],
    "name:unk_x_variant":[
        "Dr\u017eowitz"
    ],
    "name:vie_x_preferred":[
        "Dr\u017eovice"
    ],
    "qs_pg:aaroncc":"CZ",
    "qs_pg:gn_country":"CZ",
    "qs_pg:gn_fcode":"PPL",
    "qs_pg:gn_pop":0,
    "qs_pg:name":"Drzovice",
    "qs_pg:name_adm0":"\u010cesk\u00e1 republika",
    "qs_pg:name_adm1":"Olomouck\u00fd kraj",
    "qs_pg:photos_9r":0,
    "qs_pg:photos_sr":0,
    "qs_pg:pop_sr":0,
    "qs_pg:qs_pg_placetype":"locality",
    "qs_pg:qs_pg_placetype_gp":"Town",
    "qs_pg:woe_adm0":23424810,
    "woe:adm0_id":23424810,
    "woe:name_adm0":"\u010cesk\u00e1 republika",
    "woe:name_adm1":"Olomouck\u00fd kraj",
    "woe:placetype":"Town",
    "wof:name":"Drzovice",
    "wof:placetype":"locality"
},
  "geometry": {"coordinates":[17.13404,49.49104],"type":"Point"}
}