{
  "type": "Feature",
  "properties": {
    "gn:admin1_code":"81",
    "gn:admin2_code":"0412",
    "gn:asciiname":"Viska",
    "gn:country_code":"CZ",
    "gn:dem":639,
    "gn:feature_class":"P",
    "gn:feature_code":"PPL",
    "gn:name":"V\u00edska",
    "gn:population":0,
    "gn:timezone":"Europe/Prague",
    "iso:country":"CZ",
    "name:ceb_x_preferred":[
        "Viska"
    ],
    "name:ces_x_preferred":[
        "V\u00edska"
    ],
    "name:deu_x_preferred":[
        "V\u00edska"
    ],
    "name:fra_x_preferred":[
        "V\u00edska"
    ],
    "name:nld_x_preferred":[
        "V\u00edska"
    ],
    "name:und_x_variant":[
        "D\u00f6rfles",
        "V\u00edska"
    ],
    "wof:name":"Viska",
    "wof:placetype":"locality"
},
  "geometry": {"coordinates":[13.10188,50.26842],"type":"Point"}
}