{
  "type": "Feature",
  "properties": {
    "gn:admin1_code":"88",
    "gn:admin2_code":"0207",
    "gn:asciiname":"Susno",
    "gn:country_code":"CZ",
    "gn:dem":219,
    "gn:feature_class":"P",
    "gn:feature_code":"PPL",
    "gn:name":"Su\u0161no",
    "gn:population":0,
    "gn:timezone":"Europe/Prague",
    "iso:country":"CZ",
    "wof:name":"Susno",
    "wof:placetype":"locality"
},
  "geometry": {"coordinates":[14.7483,50.33413],"type":"Point"}
}