{
  "type": "Feature",
  "properties": {
    "gn:admin1_code":"89.0",
    "gn:admin2_code":"0421",
    "gn:asciiname":"Kunratice",
    "gn:country_code":"CZ",
    "gn:dem":436,
    "gn:feature_class":"P",
    "gn:feature_code":"PPL",
    "gn:name":"Kunratice",
    "gn:population":0,
    "gn:timezone":"Europe/Prague",
    "iso:country":"CZ",
    "name:ceb_x_preferred":[
        "Kunratice"
    ],
    "name:ces_x_preferred":[
        "Kunratice"
    ],
    "name:deu_x_preferred":[
        "Kunratice"
    ],
    "name:fra_x_preferred":[
        "Kunratice"
    ],
    "name:hsb_x_preferred":[
        "Kunratice"
    ],
    "name:ita_x_preferred":[
        "Kunratice"
    ],
    "name:nld_x_preferred":[
        "Kunratice"
    ],
    "name:rus_x_preferred":[
        "\u041a\u0443\u043d\u0440\u0430\u0442\u0438\u0446\u0435"
    ],
    "name:slk_x_preferred":[
        "Kunratice"
    ],
    "name:spa_x_preferred":[
        "Kunratice"
    ],
    "name:srp_x_preferred":[
        "\u041a\u0443\u043d\u0440\u0430\u0442\u0438\u0446\u0435"
    ],
    "name:swe_x_preferred":[
        "Kunratice"
    ],
    "name:und_x_variant":[
        "Kunnersdorf"
    ],
    "wof:name":"Kunratice",
    "wof:placetype":"locality"
},
  "geometry": {"coordinates":[14.44316,50.98055],"type":"Point"}
}