{
  "type": "Feature",
  "properties": {
    "gn:admin1_code":"89.0",
    "gn:admin2_code":"0421",
    "gn:asciiname":"Kunratice",
    "gn:country_code":"CZ",
    "gn:dem":436,
    "gn:feature_class":"P",
    "gn:feature_code":"PPL",
    "gn:name":"Kunratice",
    "gn:population":0,
    "gn:timezone":"Europe/Prague",
    "iso:country":"CZ",
    "name:und_x_variant":[
        "Kunnersdorf",
        "Kunratice"
    ],
    "wof:name":"Kunratice",
    "wof:placetype":"locality"
},
  "geometry": {"coordinates":[14.44316,50.98055],"type":"Point"}
}