{
  "type": "Feature",
  "properties": {
    "gn:admin1_code":"81",
    "gn:admin2_code":"0411",
    "gn:asciiname":"Tachovska Hut'",
    "gn:country_code":"CZ",
    "gn:dem":621,
    "gn:feature_class":"P",
    "gn:feature_code":"PPL",
    "gn:name":"Tachovsk\u00e1 Hu\u0165",
    "gn:population":0,
    "gn:timezone":"Europe/Prague",
    "iso:country":"CZ",
    "name:und_x_variant":[
        "Tachovsk\u00fd \u0160melctal",
        "Tachovsk\u00e1 Hu\u0165"
    ],
    "wof:name":"Tachovska Hut'",
    "wof:placetype":"locality"
},
  "geometry": {"coordinates":[12.60389,49.93486],"type":"Point"}
}