{
  "type": "Feature",
  "properties": {
    "gn:admin1_code":"87.0",
    "gn:admin2_code":"0323",
    "gn:asciiname":"Nova Hut'",
    "gn:country_code":"CZ",
    "gn:dem":329,
    "gn:feature_class":"P",
    "gn:feature_code":"PPL",
    "gn:name":"Nov\u00e1 Hu\u0165",
    "gn:population":0,
    "gn:timezone":"Europe/Prague",
    "iso:country":"CZ",
    "wof:name":"Nova Hut'",
    "wof:placetype":"locality"
},
  "geometry": {"coordinates":[13.5076,49.78088],"type":"Point"}
}