{
  "type": "Feature",
  "properties": {
    "gn:admin1_code":"88.0",
    "gn:admin2_code":"0208",
    "gn:asciiname":"Hronetice",
    "gn:country_code":"CZ",
    "gn:dem":190,
    "gn:feature_class":"P",
    "gn:feature_code":"PPL",
    "gn:name":"Hron\u011btice",
    "gn:population":0,
    "gn:timezone":"Europe/Prague",
    "iso:country":"CZ",
    "wof:name":"Hronetice",
    "wof:placetype":"locality"
},
  "geometry": {"coordinates":[14.94972,50.20236],"type":"Point"}
}