{
  "type": "Feature",
  "properties": {
    "gn:gn_country":"CZ",
    "gn:gn_fcode":"PPL",
    "gn:gn_pop":285,
    "gn:population":285,
    "iso:country":"CZ",
    "name:azb_x_preferred":[
        "\u0631\u06cc\u0628\u0646\u06cc\u062a\u0634\u06a9"
    ],
    "name:ceb_x_preferred":[
        "Rybn\u00ed\u010dek"
    ],
    "name:ces_x_preferred":[
        "Rybn\u00ed\u010dek"
    ],
    "name:deu_x_preferred":[
        "Rybn\u00ed\u010dek"
    ],
    "name:eng_x_preferred":[
        "Rybn\u00ed\u010dek"
    ],
    "name:eus_x_preferred":[
        "Rybn\u00ed\u010dek"
    ],
    "name:fas_x_preferred":[
        "\u0631\u06cc\u0628\u0646\u06cc\u062a\u0634\u06a9"
    ],
    "name:fra_x_preferred":[
        "Rybn\u00ed\u010dek"
    ],
    "name:hun_x_preferred":[
        "Rybn\u00ed\u010dek"
    ],
    "name:ita_x_preferred":[
        "Rybn\u00ed\u010dek"
    ],
    "name:msa_x_preferred":[
        "Rybn\u00ed\u010dek"
    ],
    "name:nan_x_preferred":[
        "Rybn\u00ed\u010dek"
    ],
    "name:nld_x_preferred":[
        "Rybn\u00ed\u010dek"
    ],
    "name:por_x_preferred":[
        "Rybn\u00ed\u010dek"
    ],
    "name:rup_x_preferred":[
        "Rybn\u00ed\u010dek"
    ],
    "name:slk_x_preferred":[
        "Rybn\u00ed\u010dek"
    ],
    "name:spa_x_preferred":[
        "Rybn\u00ed\u010dek"
    ],
    "name:srp_x_preferred":[
        "\u0420\u0438\u0431\u045a\u0438\u0447\u0435\u043a"
    ],
    "name:swe_x_preferred":[
        "Rybn\u00ed\u010dek"
    ],
    "name:vie_x_preferred":[
        "Rybn\u00ed\u010dek"
    ],
    "qs_pg:aaroncc":"CZ",
    "qs_pg:gn_country":"CZ",
    "qs_pg:gn_fcode":"PPL",
    "qs_pg:gn_pop":285,
    "qs_pg:name":"Rybn\u00ed\u010dek",
    "qs_pg:name_adm0":"\u010cesk\u00e1 republika",
    "qs_pg:name_adm1":"Jihomoravsk\u00fd kraj",
    "qs_pg:photos_9r":0,
    "qs_pg:photos_sr":0,
    "qs_pg:pop_sr":2,
    "qs_pg:qs_pg_placetype":"locality",
    "qs_pg:qs_pg_placetype_gp":"Town",
    "qs_pg:woe_adm0":23424810,
    "woe:adm0_id":23424810,
    "woe:name_adm0":"\u010cesk\u00e1 republika",
    "woe:name_adm1":"Jihomoravsk\u00fd kraj",
    "woe:placetype":"Town",
    "wof:name":"Rybn\u00ed\u010dek",
    "wof:placetype":"locality",
    "wof:population":285
},
  "geometry": {"coordinates":[17.0738,49.27388],"type":"Point"}
}