{
  "type": "Feature",
  "properties": {
    "iso:country":"CZ",
    "name:ceb_x_preferred":[
        "Kralupy nad Vltavou"
    ],
    "name:ces_x_preferred":[
        "Kralupy nad Vltavou"
    ],
    "name:deu_x_preferred":[
        "Kralupy nad Vltavou"
    ],
    "name:epo_x_preferred":[
        "Kralupy nad Vltavou"
    ],
    "name:eus_x_preferred":[
        "Kralupy nad Vltavou"
    ],
    "name:fas_x_preferred":[
        "\u06a9\u0631\u0627\u0644\u0648\u067e\u06cc \u0646\u0627\u062f \u0648\u0644\u062a\u0627\u0648\u0648\u0648"
    ],
    "name:fra_x_preferred":[
        "Kralupy nad Vltavou"
    ],
    "name:hun_x_preferred":[
        "Kralupy nad Vltavou"
    ],
    "name:ita_x_preferred":[
        "Kralupy nad Vltavou"
    ],
    "name:kor_x_preferred":[
        "\ud06c\ub784\ub8e8\ud53c\ub098\ud2b8\ube14\ud0c0\ubcf4\uc6b0"
    ],
    "name:lav_x_preferred":[
        "Kralupi pie Vltavas"
    ],
    "name:msa_x_preferred":[
        "Kralupy nad Vltavou"
    ],
    "name:nld_x_preferred":[
        "Kralupy nad Vltavou"
    ],
    "name:pol_x_preferred":[
        "Kralupy nad Vltavou"
    ],
    "name:por_x_preferred":[
        "Kralupy nad Vltavou"
    ],
    "name:rus_x_preferred":[
        "\u041a\u0440\u0430\u043b\u0443\u043f\u0438-\u043d\u0430\u0434-\u0412\u043b\u0442\u0430\u0432\u043e\u0443"
    ],
    "name:slk_x_preferred":[
        "Kralupy nad Vltavou"
    ],
    "name:spa_x_preferred":[
        "Kralupy nad Vltavou"
    ],
    "name:srp_x_preferred":[
        "\u041a\u0440\u0430\u043b\u0443\u043f\u0438 \u043d\u0430 \u0412\u043b\u0442\u0430\u0432\u0438"
    ],
    "name:swe_x_preferred":[
        "Kralupy nad Vltavou"
    ],
    "name:ukr_x_preferred":[
        "\u041a\u0440\u0430\u043b\u0443\u043f\u0438-\u043d\u0430-\u0412\u043b\u0442\u0430\u0432\u0456"
    ],
    "name:vie_x_preferred":[
        "Kralupy nad Vltavou"
    ],
    "qs_pg:aaroncc":"CZ",
    "qs_pg:name":"Kralupy nad Vltavou",
    "qs_pg:name_adm0":"\u010cesk\u00e1 republika",
    "qs_pg:name_adm1":"St\u0159edo\u010desk\u00fd kraj",
    "qs_pg:photos":43,
    "qs_pg:photos_1k":9,
    "qs_pg:photos_9k":1,
    "qs_pg:photos_9r":4,
    "qs_pg:photos_all":191,
    "qs_pg:photos_sr":2,
    "qs_pg:pop_sr":0,
    "qs_pg:qs_pg_placetype":"localadmin",
    "qs_pg:qs_pg_placetype_gp":"LocalAdmin",
    "qs_pg:woe_adm0":23424810,
    "woe:adm0_id":23424810,
    "woe:name_adm0":"\u010cesk\u00e1 republika",
    "woe:name_adm1":"St\u0159edo\u010desk\u00fd kraj",
    "woe:placetype":"LocalAdmin",
    "wof:name":"Kralupy nad Vltavou",
    "wof:placetype":"localadmin"
},
  "geometry": {"coordinates":[14.3105935,50.2390465],"type":"Point"}
}