{
  "type": "Feature",
  "properties": {
    "gn:admin1_code":"81.0",
    "gn:admin2_code":"0411",
    "gn:asciiname":"Jesenice",
    "gn:country_code":"CZ",
    "gn:dem":441,
    "gn:feature_class":"P",
    "gn:feature_code":"PPL",
    "gn:name":"Jesenice",
    "gn:population":0,
    "gn:timezone":"Europe/Prague",
    "iso:country":"CZ",
    "name:ara_x_preferred":[
        "\u062c\u064a\u0633\u064a\u0646\u062a\u0633\u064a"
    ],
    "name:bel_x_preferred":[
        "\u0415\u0441\u0435\u043d\u0456\u0446\u044b"
    ],
    "name:bos_x_preferred":[
        "Jesenice"
    ],
    "name:bul_x_preferred":[
        "\u0419\u0435\u0441\u0435\u043d\u0438\u0446\u0435"
    ],
    "name:ceb_x_preferred":[
        "Jesenice"
    ],
    "name:ces_x_preferred":[
        "Jesenice"
    ],
    "name:dan_x_preferred":[
        "Jesenice"
    ],
    "name:deu_x_preferred":[
        "Jesenice"
    ],
    "name:est_x_preferred":[
        "Jesenice"
    ],
    "name:eus_x_preferred":[
        "Jesenice"
    ],
    "name:fas_x_preferred":[
        "\u06cc\u0633\u0646\u06cc\u062a\u0633\u0647"
    ],
    "name:fra_x_preferred":[
        "Jesenice"
    ],
    "name:hrv_x_preferred":[
        "Jesenice"
    ],
    "name:hun_x_preferred":[
        "Jesenice"
    ],
    "name:ind_x_preferred":[
        "Jesenice"
    ],
    "name:kat_x_preferred":[
        "\u10d4\u10e1\u10d4\u10dc\u10d8\u10ea\u10d4"
    ],
    "name:lit_x_preferred":[
        "Jesenic\u0117s"
    ],
    "name:mkd_x_preferred":[
        "\u0408\u0435\u0441\u0435\u043d\u0438\u0446\u0435"
    ],
    "name:nld_x_preferred":[
        "Jesenice"
    ],
    "name:pol_x_preferred":[
        "Jesenice"
    ],
    "name:por_x_preferred":[
        "Jesenice"
    ],
    "name:ron_x_preferred":[
        "Jesenice"
    ],
    "name:rus_x_preferred":[
        "\u0415\u0441\u0435\u043d\u0438\u0446\u0435"
    ],
    "name:slk_x_preferred":[
        "Jesenice"
    ],
    "name:slv_x_preferred":[
        "Jesenice"
    ],
    "name:spa_x_preferred":[
        "Jesenice"
    ],
    "name:sqi_x_preferred":[
        "Jesenice"
    ],
    "name:srp_x_preferred":[
        "\u0408\u0435\u0441\u0435\u043d\u0438\u0446\u0435"
    ],
    "name:swe_x_preferred":[
        "Jesenice"
    ],
    "name:ukr_x_preferred":[
        "\u0404\u0441\u0435\u043d\u0438\u0446\u0435"
    ],
    "name:und_x_variant":[
        "Gassnitz",
        "Jesenice"
    ],
    "name:urd_x_preferred":[
        "\u06cc\u0633\u06cc\u0646\u06cc\u062a\u0633\u06d2"
    ],
    "name:vol_x_preferred":[
        "Jesenice"
    ],
    "name:zho_x_preferred":[
        "\u8036\u585e\u5c3c\u91c7"
    ],
    "wof:name":"Jesenice",
    "wof:placetype":"locality"
},
  "geometry": {"coordinates":[12.47275,50.0705],"type":"Point"}
}