{
  "type": "Feature",
  "properties": {
    "gn:admin1_code":"88.0",
    "gn:admin2_code":"020B",
    "gn:asciiname":"Havirna",
    "gn:country_code":"CZ",
    "gn:dem":546,
    "gn:feature_class":"P",
    "gn:feature_code":"PPL",
    "gn:name":"Hav\u00edrna",
    "gn:population":0,
    "gn:timezone":"Europe/Prague",
    "iso:country":"CZ",
    "wof:name":"Havirna",
    "wof:placetype":"locality"
},
  "geometry": {"coordinates":[13.95719,49.66205],"type":"Point"}
}