{
  "type": "Feature",
  "properties": {
    "gn:admin1_code":"86.0",
    "gn:admin2_code":"0534",
    "gn:asciiname":"Lhotka",
    "gn:country_code":"CZ",
    "gn:dem":487,
    "gn:feature_class":"P",
    "gn:feature_code":"PPL",
    "gn:name":"Lhotka",
    "gn:population":0,
    "gn:timezone":"Europe/Prague",
    "iso:country":"CZ",
    "name:ceb_x_preferred":[
        "Lhotka"
    ],
    "name:ces_x_preferred":[
        "Lhotka"
    ],
    "name:deu_x_preferred":[
        "Lhotka"
    ],
    "name:epo_x_preferred":[
        "Lhotka"
    ],
    "name:fra_x_preferred":[
        "Lhotka"
    ],
    "name:ita_x_preferred":[
        "Lhotka"
    ],
    "name:nld_x_preferred":[
        "Lhotka"
    ],
    "name:oci_x_preferred":[
        "Lhotka"
    ],
    "name:pol_x_preferred":[
        "Lhotka"
    ],
    "name:slk_x_preferred":[
        "Lhotka"
    ],
    "name:srp_x_preferred":[
        "\u041b\u0445\u043e\u0442\u043a\u0430"
    ],
    "name:swe_x_preferred":[
        "Lhotka"
    ],
    "wof:name":"Lhotka",
    "wof:placetype":"locality"
},
  "geometry": {"coordinates":[16.55949,50.10506],"type":"Point"}
}