{
  "type": "Feature",
  "properties": {
    "gn:admin1_code":"84.0",
    "gn:admin2_code":"0713",
    "gn:asciiname":"Cechuvky",
    "gn:country_code":"CZ",
    "gn:dem":212,
    "gn:feature_class":"P",
    "gn:feature_code":"PPL",
    "gn:name":"\u010cech\u016fvky",
    "gn:population":0,
    "gn:timezone":"Europe/Prague",
    "iso:country":"CZ",
    "wof:name":"Cechuvky",
    "wof:placetype":"locality"
},
  "geometry": {"coordinates":[17.16176,49.47314],"type":"Point"}
}