{
  "type": "Feature",
  "properties": {
    "gn:admin1_code":"87.0",
    "gn:admin2_code":"0327",
    "gn:asciiname":"Loucky",
    "gn:country_code":"CZ",
    "gn:dem":664,
    "gn:feature_class":"P",
    "gn:feature_code":"PPL",
    "gn:name":"Lou\u010dky",
    "gn:population":0,
    "gn:timezone":"Europe/Prague",
    "iso:country":"CZ",
    "name:und_x_variant":[
        "Lutschkah\u00e4useln",
        "Lou\u010dky"
    ],
    "wof:name":"Loucky",
    "wof:placetype":"locality"
},
  "geometry": {"coordinates":[12.90468,49.92623],"type":"Point"}
}