{
  "type": "Feature",
  "properties": {
    "iso:country":"CZ",
    "name:ceb_x_preferred":[
        "Hvozdec"
    ],
    "name:ces_x_preferred":[
        "Hvozdec"
    ],
    "name:deu_x_preferred":[
        "Hvozdec"
    ],
    "name:fra_x_preferred":[
        "Hvozdec"
    ],
    "name:ita_x_preferred":[
        "Hvozdec"
    ],
    "name:nld_x_preferred":[
        "Hvozdec"
    ],
    "name:oci_x_preferred":[
        "Hvozdec"
    ],
    "name:pol_x_preferred":[
        "Hvozdec"
    ],
    "name:slk_x_preferred":[
        "Hvozdec"
    ],
    "name:srp_x_preferred":[
        "\u0425\u0432\u043e\u0437\u0434\u0435\u0446"
    ],
    "name:swe_x_preferred":[
        "Hvozdec"
    ],
    "qs_pg:aaroncc":"CZ",
    "qs_pg:name":"Hvozdec",
    "qs_pg:name_adm0":"\u010cesk\u00e1 republika",
    "qs_pg:name_adm1":"Jihomoravsk\u00fd kraj",
    "qs_pg:photos":21,
    "qs_pg:photos_1k":4,
    "qs_pg:photos_9k":1,
    "qs_pg:photos_9r":1,
    "qs_pg:photos_all":21,
    "qs_pg:photos_sr":1,
    "qs_pg:pop_sr":0,
    "qs_pg:qs_pg_placetype":"localadmin",
    "qs_pg:qs_pg_placetype_gp":"LocalAdmin",
    "qs_pg:woe_adm0":23424810,
    "woe:adm0_id":23424810,
    "woe:name_adm0":"\u010cesk\u00e1 republika",
    "woe:name_adm1":"Jihomoravsk\u00fd kraj",
    "woe:placetype":"LocalAdmin",
    "wof:name":"Hvozdec",
    "wof:placetype":"localadmin"
},
  "geometry": {"coordinates":[16.42147,49.25761],"type":"Point"}
}