{
  "type": "Feature",
  "properties": {
    "gn:admin1_code":"86.0",
    "gn:admin2_code":"0531",
    "gn:asciiname":"Licomerice",
    "gn:country_code":"CZ",
    "gn:dem":349,
    "gn:feature_class":"P",
    "gn:feature_code":"PPL",
    "gn:name":"Licom\u011b\u0159ice",
    "gn:population":0,
    "gn:timezone":"Europe/Prague",
    "iso:country":"CZ",
    "wof:name":"Licomerice",
    "wof:placetype":"locality"
},
  "geometry": {"coordinates":[15.55395,49.91694],"type":"Point"}
}