{
  "type": "Feature",
  "properties": {
    "gn:admin1_code":"79.0",
    "gn:admin2_code":"0316",
    "gn:asciiname":"Dresinek",
    "gn:country_code":"CZ",
    "gn:dem":619,
    "gn:feature_class":"P",
    "gn:feature_code":"PPL",
    "gn:name":"D\u0159e\u0161\u00ednek",
    "gn:population":0,
    "gn:timezone":"Europe/Prague",
    "iso:country":"CZ",
    "wof:name":"Dresinek",
    "wof:placetype":"locality"
},
  "geometry": {"coordinates":[13.77222,49.16818],"type":"Point"}
}