{
  "type": "Feature",
  "properties": {
    "gn:admin1_code":"82.0",
    "gn:admin2_code":"0523",
    "gn:asciiname":"Rozmital",
    "gn:country_code":"CZ",
    "gn:dem":443,
    "gn:feature_class":"P",
    "gn:feature_code":"PPL",
    "gn:name":"Ro\u017emit\u00e1l",
    "gn:population":0,
    "gn:timezone":"Europe/Prague",
    "iso:country":"CZ",
    "name:und_x_variant":[
        "Rosenthal",
        "Ro\u017emit\u00e1l"
    ],
    "wof:name":"Rozmital",
    "wof:placetype":"locality"
},
  "geometry": {"coordinates":[16.37084,50.60024],"type":"Point"}
}