{
  "type": "Feature",
  "properties": {
    "gn:gn_country":"CZ",
    "gn:gn_fcode":"PPL",
    "gn:gn_pop":77,
    "gn:population":77,
    "iso:country":"CZ",
    "name:ces_x_preferred":[
        "He\u0159manice"
    ],
    "name:deu_x_preferred":[
        "He\u0159manice"
    ],
    "name:epo_x_preferred":[
        "He\u0159manice"
    ],
    "name:fra_x_preferred":[
        "He\u0159manice"
    ],
    "name:ita_x_preferred":[
        "He\u0159manice"
    ],
    "name:nld_x_preferred":[
        "He\u0159manice"
    ],
    "name:pol_x_preferred":[
        "He\u0159manice"
    ],
    "name:slk_x_preferred":[
        "He\u0159manice"
    ],
    "name:srp_x_preferred":[
        "\u0425\u0435\u0440\u043c\u0430\u045a\u0438\u0446\u0435"
    ],
    "qs_pg:aaroncc":"CZ",
    "qs_pg:gn_country":"CZ",
    "qs_pg:gn_fcode":"PPL",
    "qs_pg:gn_pop":77,
    "qs_pg:name":"He\u0159manice",
    "qs_pg:photos_9r":0,
    "qs_pg:photos_sr":0,
    "qs_pg:pop_sr":1,
    "qs_pg:qs_pg_placetype":"locality",
    "wof:name":"He\u0159manice",
    "wof:placetype":"locality",
    "wof:population":77
},
  "geometry": {"coordinates":[16.1525,49.07505],"type":"Point"}
}