{
  "type": "Feature",
  "properties": {
    "gn:admin1_code":"83",
    "gn:admin2_code":"0513",
    "gn:asciiname":"Ves",
    "gn:country_code":"CZ",
    "gn:dem":222,
    "gn:feature_class":"P",
    "gn:feature_code":"PPL",
    "gn:name":"Ves",
    "gn:population":0,
    "gn:timezone":"Europe/Prague",
    "iso:country":"CZ",
    "name:und_x_variant":[
        "Wiese",
        "Ves"
    ],
    "wof:name":"Ves",
    "wof:placetype":"locality"
},
  "geometry": {"coordinates":[15.02902,51.01651],"type":"Point"}
}