{
  "type": "Feature",
  "properties": {
    "iso:country":"CZ",
    "name:afr_x_preferred":[
        "Doubravka"
    ],
    "name:arg_x_preferred":[
        "Doubravka"
    ],
    "name:ast_x_preferred":[
        "Doubravka"
    ],
    "name:aze_x_preferred":[
        "Doubravka"
    ],
    "name:cat_x_preferred":[
        "Doubravka"
    ],
    "name:ces_x_preferred":[
        "Doubravka"
    ],
    "name:cym_x_preferred":[
        "Doubravka"
    ],
    "name:dan_x_preferred":[
        "Doubravka"
    ],
    "name:deu_x_preferred":[
        "Doubravka"
    ],
    "name:eng_x_preferred":[
        "Doubravka"
    ],
    "name:epo_x_preferred":[
        "Doubravka"
    ],
    "name:est_x_preferred":[
        "Doubravka"
    ],
    "name:eus_x_preferred":[
        "Doubravka"
    ],
    "name:fin_x_preferred":[
        "Doubravka"
    ],
    "name:fra_x_preferred":[
        "Doubravka"
    ],
    "name:gle_x_preferred":[
        "Doubravka"
    ],
    "name:hun_x_preferred":[
        "Doubravka"
    ],
    "name:ind_x_preferred":[
        "Doubravka"
    ],
    "name:isl_x_preferred":[
        "Doubravka"
    ],
    "name:ita_x_preferred":[
        "Doubravka"
    ],
    "name:lav_x_preferred":[
        "Doubravka"
    ],
    "name:ltz_x_preferred":[
        "Doubravka"
    ],
    "name:nld_x_preferred":[
        "Doubravka"
    ],
    "name:nno_x_preferred":[
        "Doubravka"
    ],
    "name:nob_x_preferred":[
        "Doubravka"
    ],
    "name:oci_x_preferred":[
        "Doubravka"
    ],
    "name:pol_x_preferred":[
        "Doubravka"
    ],
    "name:por_x_preferred":[
        "Doubravka"
    ],
    "name:roh_x_preferred":[
        "Doubravka"
    ],
    "name:ron_x_preferred":[
        "Doubravka"
    ],
    "name:sco_x_preferred":[
        "Doubravka"
    ],
    "name:slk_x_preferred":[
        "Doubravka"
    ],
    "name:slv_x_preferred":[
        "Doubravka"
    ],
    "name:spa_x_preferred":[
        "Doubravka"
    ],
    "name:sqi_x_preferred":[
        "Doubravka"
    ],
    "name:srp_x_preferred":[
        "\u0414\u0443\u0431\u0440\u0430\u0432\u043a\u0430"
    ],
    "name:swe_x_preferred":[
        "Doubravka"
    ],
    "name:tur_x_preferred":[
        "Doubravka"
    ],
    "name:vec_x_preferred":[
        "Doubravka"
    ],
    "qs:gn_fcode":"PPL",
    "qs:gn_local":0,
    "qs:gn_namadm1":"87",
    "qs:gn_name":"Doubravka",
    "qs:local_max":1309,
    "qs:local_sum":4721,
    "qs:localhoods":13,
    "qs:name":"Doubravka",
    "qs:name_adm0":"\u010cesk\u00e1 republika",
    "qs:name_adm1":"Plze\u0148sk\u00fd kraj",
    "qs:name_adm2":"Plze\u0148-M\u011bsto",
    "qs:name_lau":"Plze\u0148",
    "qs:name_local":"Plze\u0148",
    "qs:photo_max":96,
    "qs:photo_sum":404,
    "qs:placetype":"Suburb",
    "qs:quad_count":40,
    "qs:woe_adm0":23424810,
    "qs:woe_adm1":20070501,
    "qs:woe_adm2":12582609,
    "qs:woe_lau":12610042,
    "qs:woe_local":12610042,
    "qs:woe_ver":"7.10.0",
    "wd:wordcount":102,
    "wof:lang":[
        "cze"
    ],
    "wof:name":"Doubravka",
    "wof:placetype":"neighbourhood"
},
  "geometry": {"coordinates":[13.398338,49.74996],"type":"Point"}
}