{
  "type": "Feature",
  "properties": {
    "gn:gn_country":"CZ",
    "gn:gn_fcode":"PPL",
    "gn:gn_pop":701,
    "gn:population":701,
    "iso:country":"CZ",
    "name:ceb_x_preferred":[
        "Uh\u0159ice"
    ],
    "name:ces_x_preferred":[
        "Uh\u0159ice"
    ],
    "name:deu_x_preferred":[
        "Uh\u0159ice"
    ],
    "name:fra_x_preferred":[
        "Uh\u0159ice"
    ],
    "name:ita_x_preferred":[
        "Uh\u0159ice"
    ],
    "name:nld_x_preferred":[
        "Uh\u0159ice"
    ],
    "name:pol_x_preferred":[
        "Uh\u0159ice"
    ],
    "name:slk_x_preferred":[
        "Uh\u0159ice"
    ],
    "name:srp_x_preferred":[
        "\u0423\u0445\u0440\u0438\u0446\u0435"
    ],
    "name:swe_x_preferred":[
        "Uh\u0159ice"
    ],
    "qs_pg:aaroncc":"CZ",
    "qs_pg:gn_country":"CZ",
    "qs_pg:gn_fcode":"PPL",
    "qs_pg:gn_pop":701,
    "qs_pg:name":"Uh\u0159ice",
    "qs_pg:name_adm0":"\u010cesk\u00e1 republika",
    "qs_pg:name_adm1":"Jihomoravsk\u00fd kraj",
    "qs_pg:photos_9r":0,
    "qs_pg:photos_sr":0,
    "qs_pg:pop_sr":2,
    "qs_pg:qs_pg_placetype":"locality",
    "qs_pg:qs_pg_placetype_gp":"Town",
    "qs_pg:woe_adm0":23424810,
    "woe:adm0_id":23424810,
    "woe:name_adm0":"\u010cesk\u00e1 republika",
    "woe:name_adm1":"Jihomoravsk\u00fd kraj",
    "woe:placetype":"Town",
    "wof:name":"Uh\u0159ice",
    "wof:placetype":"locality",
    "wof:population":701
},
  "geometry": {"coordinates":[16.94758,49.05035],"type":"Point"}
}