{
  "type": "Feature",
  "properties": {
    "gn:gn_country":"CZ",
    "gn:gn_fcode":"PPL",
    "gn:gn_pop":107,
    "gn:population":107,
    "iso:country":"CZ",
    "name:azb_x_preferred":[
        "\u0631\u0648\u062e\u0648\u0648"
    ],
    "name:bul_x_preferred":[
        "\u0420\u043e\u0447\u043e\u0432"
    ],
    "name:ceb_x_preferred":[
        "Rochov"
    ],
    "name:ces_x_preferred":[
        "Rochov"
    ],
    "name:deu_x_preferred":[
        "Rochov"
    ],
    "name:eng_x_preferred":[
        "Rochov"
    ],
    "name:epo_x_preferred":[
        "Rochov"
    ],
    "name:eus_x_preferred":[
        "Rochov"
    ],
    "name:fas_x_preferred":[
        "\u0631\u0648\u062e\u0648\u0648"
    ],
    "name:fra_x_preferred":[
        "Rochov"
    ],
    "name:hun_x_preferred":[
        "Rochov"
    ],
    "name:ita_x_preferred":[
        "Rochov"
    ],
    "name:msa_x_preferred":[
        "Rochov"
    ],
    "name:nan_x_preferred":[
        "Rochov"
    ],
    "name:nld_x_preferred":[
        "Rochov"
    ],
    "name:por_x_preferred":[
        "Rochov"
    ],
    "name:rup_x_preferred":[
        "Rochov"
    ],
    "name:slk_x_preferred":[
        "Rochov"
    ],
    "name:spa_x_preferred":[
        "Rochov"
    ],
    "name:srp_x_preferred":[
        "\u0420\u043e\u0445\u043e\u0432"
    ],
    "name:swe_x_preferred":[
        "Rochov"
    ],
    "name:vie_x_preferred":[
        "Rochov"
    ],
    "qs_pg:aaroncc":"CZ",
    "qs_pg:gn_country":"CZ",
    "qs_pg:gn_fcode":"PPL",
    "qs_pg:gn_pop":107,
    "qs_pg:name":"Rochov",
    "qs_pg:name_adm0":"\u010cesk\u00e1 republika",
    "qs_pg:name_adm1":"\u00dasteck\u00fd kraj",
    "qs_pg:photos_9r":0,
    "qs_pg:photos_sr":0,
    "qs_pg:pop_sr":1,
    "qs_pg:qs_pg_placetype":"locality",
    "qs_pg:qs_pg_placetype_gp":"Town",
    "qs_pg:woe_adm0":23424810,
    "woe:adm0_id":23424810,
    "woe:name_adm0":"\u010cesk\u00e1 republika",
    "woe:name_adm1":"\u00dasteck\u00fd kraj",
    "woe:placetype":"Town",
    "wof:name":"Rochov",
    "wof:placetype":"locality",
    "wof:population":107
},
  "geometry": {"coordinates":[14.11744,50.45939],"type":"Point"}
}