{
  "type": "Feature",
  "properties": {
    "gn:admin1_code":"90.0",
    "gn:admin2_code":"0722",
    "gn:asciiname":"Kralov",
    "gn:country_code":"CZ",
    "gn:dem":249,
    "gn:feature_class":"P",
    "gn:feature_code":"PPL",
    "gn:name":"Kr\u00e1lov",
    "gn:population":0,
    "gn:timezone":"Europe/Prague",
    "iso:country":"CZ",
    "name:und_x_variant":[
        "Dv\u016dr Kr\u00e1lov",
        "Kr\u00e1lov"
    ],
    "wof:name":"Kralov",
    "wof:placetype":"locality"
},
  "geometry": {"coordinates":[17.68452000000001,49.00493],"type":"Point"}
}