{
  "type": "Feature",
  "properties": {
    "gn:gn_country":"CZ",
    "gn:gn_fcode":"PPL",
    "gn:gn_pop":303,
    "gn:population":303,
    "iso:country":"CZ",
    "name:ces_x_preferred":[
        "Hulice"
    ],
    "name:eng_x_preferred":[
        "Hulice"
    ],
    "name:fas_x_preferred":[
        "\u0647\u0648\u0644\u06cc\u062a\u0633\u0647"
    ],
    "name:fra_x_preferred":[
        "Hulice"
    ],
    "name:hun_x_preferred":[
        "Hulice"
    ],
    "name:ita_x_preferred":[
        "Hulice"
    ],
    "name:msa_x_preferred":[
        "Hulice"
    ],
    "name:nld_x_preferred":[
        "Hulice"
    ],
    "name:pol_x_preferred":[
        "Hulice"
    ],
    "name:por_x_preferred":[
        "Hulice"
    ],
    "name:slk_x_preferred":[
        "Hulice"
    ],
    "name:srp_x_preferred":[
        "\u0425\u0443\u043b\u0438\u0446\u0435"
    ],
    "name:swe_x_preferred":[
        "Hulice"
    ],
    "name:vie_x_preferred":[
        "Hulice"
    ],
    "qs_pg:aaroncc":"CZ",
    "qs_pg:gn_country":"CZ",
    "qs_pg:gn_fcode":"PPL",
    "qs_pg:gn_pop":303,
    "qs_pg:name":"Hulice",
    "qs_pg:name_adm0":"\u010cesk\u00e1 republika",
    "qs_pg:name_adm1":"St\u0159edo\u010desk\u00fd kraj",
    "qs_pg:photos_9r":0,
    "qs_pg:photos_sr":0,
    "qs_pg:pop_sr":2,
    "qs_pg:qs_pg_placetype":"locality",
    "qs_pg:qs_pg_placetype_gp":"Town",
    "qs_pg:woe_adm0":23424810,
    "woe:adm0_id":23424810,
    "woe:name_adm0":"\u010cesk\u00e1 republika",
    "woe:name_adm1":"St\u0159edo\u010desk\u00fd kraj",
    "woe:placetype":"Town",
    "wof:name":"Hulice",
    "wof:placetype":"locality",
    "wof:population":303
},
  "geometry": {"coordinates":[15.08759,49.7096],"type":"Point"}
}