{
  "type": "Feature",
  "properties": {
    "gn:admin1_code":"88.0",
    "gn:admin2_code":"020B",
    "gn:asciiname":"Radesice",
    "gn:country_code":"CZ",
    "gn:dem":520,
    "gn:feature_class":"P",
    "gn:feature_code":"PPL",
    "gn:name":"Rade\u0161ice",
    "gn:population":0,
    "gn:timezone":"Europe/Prague",
    "iso:country":"CZ",
    "wof:name":"Radesice",
    "wof:placetype":"locality"
},
  "geometry": {"coordinates":[14.3975,49.55222],"type":"Point"}
}