{
  "type": "Feature",
  "properties": {
    "gn:admin1_code":"80",
    "gn:admin2_code":"0613",
    "gn:asciiname":"Vlasenice",
    "gn:country_code":"CZ",
    "gn:dem":619,
    "gn:feature_class":"P",
    "gn:feature_code":"PPL",
    "gn:name":"Vlasenice",
    "gn:population":0,
    "gn:timezone":"Europe/Prague",
    "iso:country":"CZ",
    "wof:name":"Vlasenice",
    "wof:placetype":"locality"
},
  "geometry": {"coordinates":[15.12458,49.30162],"type":"Point"}
}