{
  "type": "Feature",
  "properties": {
    "gn:admin1_code":"83.0",
    "gn:admin2_code":"0513",
    "gn:asciiname":"Doleni Paseky",
    "gn:country_code":"CZ",
    "gn:dem":472,
    "gn:feature_class":"P",
    "gn:feature_code":"PPL",
    "gn:name":"Dolen\u00ed Paseky",
    "gn:population":0,
    "gn:timezone":"Europe/Prague",
    "iso:country":"CZ",
    "wof:name":"Doleni Paseky",
    "wof:placetype":"locality"
},
  "geometry": {"coordinates":[14.96535,50.70973],"type":"Point"}
}