{
  "type": "Feature",
  "properties": {
    "gn:admin1_code":"85.0",
    "gn:admin2_code":"0802",
    "gn:asciiname":"Nova Staric",
    "gn:country_code":"CZ",
    "gn:dem":303,
    "gn:feature_class":"P",
    "gn:feature_code":"PPL",
    "gn:name":"Nov\u00e1 Sta\u0159\u00ed\u010d",
    "gn:population":0,
    "gn:timezone":"Europe/Prague",
    "iso:country":"CZ",
    "wof:name":"Nova Staric",
    "wof:placetype":"locality"
},
  "geometry": {"coordinates":[18.28333,49.68333],"type":"Point"}
}