{
  "type": "Feature",
  "properties": {
    "gn:admin1_code":"79.0",
    "gn:admin2_code":"0312",
    "gn:asciiname":"Cipin",
    "gn:country_code":"CZ",
    "gn:dem":729,
    "gn:feature_class":"P",
    "gn:feature_code":"PPL",
    "gn:name":"Cip\u00edn",
    "gn:population":0,
    "gn:timezone":"Europe/Prague",
    "iso:country":"CZ",
    "name:und_x_variant":[
        "Zippendorf",
        "Cip\u00edn"
    ],
    "wof:name":"Cipin",
    "wof:placetype":"locality"
},
  "geometry": {"coordinates":[14.21667,48.75],"type":"Point"}
}