{
  "type": "Feature",
  "properties": {
    "gn:gn_country":"CZ",
    "gn:gn_fcode":"PPL",
    "gn:gn_pop":47,
    "gn:population":47,
    "iso:country":"CZ",
    "name:azb_x_preferred":[
        "\u0644\u0648\u0698\u06cc\u062a\u0633\u0647"
    ],
    "name:ces_x_preferred":[
        "Lu\u017eice"
    ],
    "name:deu_x_preferred":[
        "Lu\u017eice u Netolic"
    ],
    "name:eng_x_preferred":[
        "Lu\u017eice"
    ],
    "name:epo_x_preferred":[
        "Lu\u017eice"
    ],
    "name:eus_x_preferred":[
        "Lu\u017eice"
    ],
    "name:fas_x_preferred":[
        "\u0644\u0648\u0698\u06cc\u062a\u0633\u0647"
    ],
    "name:fra_x_preferred":[
        "Lu\u017eice"
    ],
    "name:hun_x_preferred":[
        "Lu\u017eice"
    ],
    "name:ita_x_preferred":[
        "Lu\u017eice"
    ],
    "name:msa_x_preferred":[
        "Lu\u017eice"
    ],
    "name:nan_x_preferred":[
        "Lu\u017eice"
    ],
    "name:nld_x_preferred":[
        "Lu\u017eice"
    ],
    "name:por_x_preferred":[
        "Lu\u017eice"
    ],
    "name:rup_x_preferred":[
        "Lu\u017eice"
    ],
    "name:rus_x_preferred":[
        "\u041b\u0443\u0436\u0438\u0446\u0435"
    ],
    "name:slk_x_preferred":[
        "Lu\u017eice"
    ],
    "name:spa_x_preferred":[
        "Lu\u017eice"
    ],
    "name:srp_x_preferred":[
        "\u041b\u0443\u0436\u0438\u0446\u0435"
    ],
    "name:vie_x_preferred":[
        "Lu\u017eice"
    ],
    "qs_pg:aaroncc":"CZ",
    "qs_pg:gn_country":"CZ",
    "qs_pg:gn_fcode":"PPL",
    "qs_pg:gn_pop":47,
    "qs_pg:name":"Lu\u017eice",
    "qs_pg:name_adm0":"\u010cesk\u00e1 republika",
    "qs_pg:name_adm1":"Jiho\u010desk\u00fd kraj",
    "qs_pg:photos_9r":0,
    "qs_pg:photos_sr":0,
    "qs_pg:pop_sr":1,
    "qs_pg:qs_pg_placetype":"locality",
    "qs_pg:qs_pg_placetype_gp":"Town",
    "qs_pg:woe_adm0":23424810,
    "woe:adm0_id":23424810,
    "woe:name_adm0":"\u010cesk\u00e1 republika",
    "woe:name_adm1":"Jiho\u010desk\u00fd kraj",
    "woe:placetype":"Town",
    "wof:name":"Lu\u017eice",
    "wof:placetype":"locality",
    "wof:population":47
},
  "geometry": {"coordinates":[14.20494,49.03129],"type":"Point"}
}