{
  "type": "Feature",
  "properties": {
    "gn:country":"CZ",
    "gn:fcode":"PPL",
    "gn:population":440,
    "iso:country":"CZ",
    "name:ceb_x_preferred":[
        "Rybn\u00e1 nad Zdobnic\u00ed"
    ],
    "name:ces_x_preferred":[
        "Rybn\u00e1 nad Zdobnic\u00ed"
    ],
    "name:deu_x_preferred":[
        "Rybn\u00e1 nad Zdobnic\u00ed"
    ],
    "name:eng_x_preferred":[
        "Rybn\u00e1 nad Zdobnic\u00ed"
    ],
    "name:eus_x_preferred":[
        "Rybn\u00e1 nad Zdobnic\u00ed"
    ],
    "name:fas_x_preferred":[
        "\u0631\u06cc\u0628\u0646\u0627 \u0646\u0627\u062f \u0632\u062f\u0648\u0628\u0646\u06cc\u062a\u0633\u06cc"
    ],
    "name:fra_x_preferred":[
        "Rybn\u00e1 nad Zdobnic\u00ed"
    ],
    "name:hun_x_preferred":[
        "Rybn\u00e1 nad Zdobnic\u00ed"
    ],
    "name:ita_x_preferred":[
        "Rybn\u00e1 nad Zdobnic\u00ed"
    ],
    "name:msa_x_preferred":[
        "Rybn\u00e1 nad Zdobnic\u00ed"
    ],
    "name:nan_x_preferred":[
        "Rybn\u00e1 nad Zdobnic\u00ed"
    ],
    "name:nld_x_preferred":[
        "Rybn\u00e1 nad Zdobnic\u00ed"
    ],
    "name:pol_x_preferred":[
        "Rybn\u00e1 nad Zdobnic\u00ed"
    ],
    "name:por_x_preferred":[
        "Rybn\u00e1 nad Zdobnic\u00ed"
    ],
    "name:rup_x_preferred":[
        "Rybn\u00e1 nad Zdobnic\u00ed"
    ],
    "name:slk_x_preferred":[
        "Rybn\u00e1 nad Zdobnic\u00ed"
    ],
    "name:spa_x_preferred":[
        "Rybn\u00e1 nad Zdobnic\u00ed"
    ],
    "name:srp_x_preferred":[
        "\u0420\u0438\u0431\u043d\u0430 \u043d\u0430 \u0417\u0434\u043e\u0431\u045a\u0438\u0446\u0438"
    ],
    "name:swe_x_preferred":[
        "Rybn\u00e1 nad Zdobnic\u00ed"
    ],
    "name:und_x_variant":[
        "N\u011bmeck\u00e1 Rybn\u00e1"
    ],
    "name:vie_x_preferred":[
        "Rybn\u00e1 nad Zdobnic\u00ed"
    ],
    "qs_pg:aaroncc":"CZ",
    "qs_pg:gn_country":"CZ",
    "qs_pg:gn_fcode":"PPL",
    "qs_pg:gn_pop":440,
    "qs_pg:name":"Rybn\u00e1 nad Zdobnic\u00ed",
    "qs_pg:name_adm0":"\u010cesk\u00e1 republika",
    "qs_pg:name_adm1":"Kr\u00e1lov\u00e9hradeck\u00fd kraj",
    "qs_pg:photos_9k":1,
    "qs_pg:photos_9r":1,
    "qs_pg:photos_all":1,
    "qs_pg:photos_sr":0,
    "qs_pg:pop_sr":2,
    "qs_pg:qs_pg_placetype":"locality",
    "qs_pg:qs_pg_placetype_gp":"Town",
    "qs_pg:woe_adm0":23424810,
    "woe:adm0_id":23424810,
    "woe:name_adm0":"\u010cesk\u00e1 republika",
    "woe:name_adm1":"Kr\u00e1lov\u00e9hradeck\u00fd kraj",
    "woe:placetype":"Town",
    "wof:name":"Rybn\u00e1 nad Zdobnic\u00ed",
    "wof:placetype":"locality",
    "wof:population":440
},
  "geometry": {"coordinates":[16.36576,50.10869],"type":"Point"}
}