{
  "type": "Feature",
  "properties": {
    "gn:admin1_code":"82",
    "gn:admin2_code":"0525",
    "gn:asciiname":"Vestrev",
    "gn:country_code":"CZ",
    "gn:dem":344,
    "gn:feature_class":"P",
    "gn:feature_code":"PPL",
    "gn:name":"Vest\u0159ev",
    "gn:population":0,
    "gn:timezone":"Europe/Prague",
    "iso:country":"CZ",
    "name:und_x_variant":[
        "Neustadtl",
        "Vest\u0159ev"
    ],
    "wof:name":"Vestrev",
    "wof:placetype":"locality"
},
  "geometry": {"coordinates":[15.72768,50.5191],"type":"Point"}
}