{
  "type": "Feature",
  "properties": {
    "gn:country":"CZ",
    "gn:fcode":"PPL",
    "gn:population":1097,
    "iso:country":"CZ",
    "name:cat_x_preferred":[
        "\u010cerno\u0161\u00edn"
    ],
    "name:ceb_x_preferred":[
        "\u010cerno\u0161\u00edn"
    ],
    "name:ces_x_preferred":[
        "\u010cerno\u0161\u00edn"
    ],
    "name:deu_x_preferred":[
        "\u010cerno\u0161\u00edn"
    ],
    "name:eng_x_preferred":[
        "\u010cerno\u0161\u00edn"
    ],
    "name:epo_x_preferred":[
        "\u010cerno\u0161\u00edn"
    ],
    "name:est_x_preferred":[
        "\u010cerno\u0161\u00edn"
    ],
    "name:eus_x_preferred":[
        "\u010cerno\u0161\u00edn"
    ],
    "name:fas_x_preferred":[
        "\u062a\u0634\u0631\u0646\u0648\u0634\u06cc\u0646"
    ],
    "name:fra_x_preferred":[
        "\u010cerno\u0161\u00edn"
    ],
    "name:gle_x_preferred":[
        "\u010cerno\u0161\u00edn"
    ],
    "name:hun_x_preferred":[
        "\u010cerno\u0161\u00edn"
    ],
    "name:ita_x_preferred":[
        "\u010cerno\u0161\u00edn"
    ],
    "name:lmo_x_preferred":[
        "\u010cerno\u0161\u00edn"
    ],
    "name:msa_x_preferred":[
        "\u010cerno\u0161\u00edn"
    ],
    "name:nan_x_preferred":[
        "\u010cerno\u0161\u00edn"
    ],
    "name:nld_x_preferred":[
        "\u010cerno\u0161\u00edn"
    ],
    "name:pol_x_preferred":[
        "\u010cerno\u0161\u00edn"
    ],
    "name:por_x_preferred":[
        "\u010cerno\u0161\u00edn"
    ],
    "name:rup_x_preferred":[
        "\u010cerno\u0161\u00edn"
    ],
    "name:rus_x_preferred":[
        "\u0427\u0435\u0440\u043d\u043e\u0448\u0438\u043d"
    ],
    "name:slk_x_preferred":[
        "\u010cerno\u0161\u00edn"
    ],
    "name:spa_x_preferred":[
        "\u010cerno\u0161\u00edn"
    ],
    "name:srp_x_preferred":[
        "\u0427\u0435\u0440\u043d\u043e\u0448\u0438\u043d"
    ],
    "name:swe_x_preferred":[
        "\u010cerno\u0161\u00edn"
    ],
    "name:tat_x_preferred":[
        "\u0427\u0435\u0440\u043d\u043e\u0448\u0438\u043d"
    ],
    "name:und_x_variant":[
        "Tschernoschin"
    ],
    "name:uzb_x_preferred":[
        "\u010cerno\u0161\u00edn"
    ],
    "name:vie_x_preferred":[
        "\u010cerno\u0161\u00edn"
    ],
    "name:zho_x_preferred":[
        "\u5207\u723e\u8afe\u6b23"
    ],
    "qs_pg:aaroncc":"CZ",
    "qs_pg:gn_country":"CZ",
    "qs_pg:gn_fcode":"PPL",
    "qs_pg:gn_pop":1097,
    "qs_pg:name":"\u010cerno\u0161\u00edn",
    "qs_pg:name_adm0":"\u010cesk\u00e1 republika",
    "qs_pg:name_adm1":"Plze\u0148sk\u00fd kraj",
    "qs_pg:photos_9k":1,
    "qs_pg:photos_9r":1,
    "qs_pg:photos_all":2,
    "qs_pg:photos_sr":0,
    "qs_pg:pop_sr":3,
    "qs_pg:qs_pg_placetype":"locality",
    "qs_pg:qs_pg_placetype_gp":"Town",
    "qs_pg:woe_adm0":23424810,
    "woe:adm0_id":23424810,
    "woe:name_adm0":"\u010cesk\u00e1 republika",
    "woe:name_adm1":"Plze\u0148sk\u00fd kraj",
    "woe:placetype":"Town",
    "wof:name":"\u010cerno\u0161\u00edn",
    "wof:placetype":"locality",
    "wof:population":1097
},
  "geometry": {"coordinates":[12.88381,49.81613],"type":"Point"}
}