{
  "type": "Feature",
  "properties": {
    "gn:gn_country":"CZ",
    "gn:gn_fcode":"PPL",
    "gn:gn_pop":405,
    "gn:population":405,
    "iso:country":"CZ",
    "name:ceb_x_preferred":[
        "Tehov"
    ],
    "name:ces_x_preferred":[
        "Tehov"
    ],
    "name:fra_x_preferred":[
        "Tehov"
    ],
    "name:ita_x_preferred":[
        "Tehov"
    ],
    "name:nld_x_preferred":[
        "Tehov"
    ],
    "name:oci_x_preferred":[
        "Tehov"
    ],
    "name:pol_x_preferred":[
        "Tehov"
    ],
    "name:slk_x_preferred":[
        "Tehov"
    ],
    "name:srp_x_preferred":[
        "\u0422\u0435\u0445\u043e\u0432"
    ],
    "name:swe_x_preferred":[
        "Tehov"
    ],
    "name:unk_x_variant":[
        "Tehau"
    ],
    "qs_pg:aaroncc":"CZ",
    "qs_pg:gn_country":"CZ",
    "qs_pg:gn_fcode":"PPL",
    "qs_pg:gn_pop":405,
    "qs_pg:name":"Tehov",
    "qs_pg:name_adm0":"\u010cesk\u00e1 republika",
    "qs_pg:name_adm1":"St\u0159edo\u010desk\u00fd kraj",
    "qs_pg:photos_9r":0,
    "qs_pg:photos_sr":0,
    "qs_pg:pop_sr":2,
    "qs_pg:qs_pg_placetype":"locality",
    "qs_pg:qs_pg_placetype_gp":"Town",
    "qs_pg:woe_adm0":23424810,
    "woe:adm0_id":23424810,
    "woe:name_adm0":"\u010cesk\u00e1 republika",
    "woe:name_adm1":"St\u0159edo\u010desk\u00fd kraj",
    "woe:placetype":"Town",
    "wof:name":"Tehov",
    "wof:placetype":"locality",
    "wof:population":405
},
  "geometry": {"coordinates":[14.69379,49.97152],"type":"Point"}
}