{
  "type": "Feature",
  "properties": {
    "gn:admin1_code":"84.0",
    "gn:admin2_code":"0715",
    "gn:asciiname":"Dlouha Ves",
    "gn:country_code":"CZ",
    "gn:dem":556,
    "gn:feature_class":"P",
    "gn:feature_code":"PPL",
    "gn:name":"Dlouh\u00e1 Ves",
    "gn:population":0,
    "gn:timezone":"Europe/Prague",
    "iso:country":"CZ",
    "name:und_x_variant":[
        "Grunddorf",
        "Dlouh\u00e1 Ves"
    ],
    "wof:name":"Dlouha Ves",
    "wof:placetype":"locality"
},
  "geometry": {"coordinates":[16.79631,49.82988],"type":"Point"}
}