{
  "type": "Feature",
  "properties": {
    "gn:admin1_code":"80.0",
    "gn:admin2_code":"0611",
    "gn:asciiname":"Skrivanek",
    "gn:country_code":"CZ",
    "gn:dem":578,
    "gn:feature_class":"P",
    "gn:feature_code":"PPL",
    "gn:name":"Sk\u0159iv\u00e1nek",
    "gn:population":0,
    "gn:timezone":"Europe/Prague",
    "iso:country":"CZ",
    "wof:name":"Skrivanek",
    "wof:placetype":"locality"
},
  "geometry": {"coordinates":[15.59036,49.53388],"type":"Point"}
}