{
  "type": "Feature",
  "properties": {
    "gn:gn_country":"CZ",
    "gn:gn_fcode":"PPL",
    "gn:gn_pop":191,
    "gn:population":191,
    "iso:country":"CZ",
    "name:cze_x_preferred":[
        "Skryje"
    ],
    "name:dut_x_preferred":[
        "Skryje"
    ],
    "name:eng_x_preferred":[
        "Skryje"
    ],
    "name:fre_x_preferred":[
        "Skryje"
    ],
    "name:hun_x_preferred":[
        "Skryje"
    ],
    "name:ita_x_preferred":[
        "Skryje"
    ],
    "name:may_x_preferred":[
        "Skryje"
    ],
    "name:per_x_preferred":[
        "\u0633\u06a9\u0631\u06cc\u06cc\u0647"
    ],
    "name:por_x_preferred":[
        "Skryje"
    ],
    "name:rup_x_preferred":[
        "Skryje"
    ],
    "name:slo_x_preferred":[
        "Skryje"
    ],
    "name:srp_x_preferred":[
        "\u0421\u043a\u0440\u0438\u0458\u0435"
    ],
    "name:swe_x_preferred":[
        "Skryje"
    ],
    "name:vie_x_preferred":[
        "Skryje"
    ],
    "qs_pg:aaroncc":"CZ",
    "qs_pg:gn_country":"CZ",
    "qs_pg:gn_fcode":"PPL",
    "qs_pg:gn_pop":191,
    "qs_pg:name":"Skryje",
    "qs_pg:name_adm0":"\u010cesk\u00e1 republika",
    "qs_pg:name_adm1":"Kraj Vyso\u010dina",
    "qs_pg:photos_9r":0,
    "qs_pg:photos_sr":0,
    "qs_pg:pop_sr":1,
    "qs_pg:qs_pg_placetype":"locality",
    "qs_pg:qs_pg_placetype_gp":"Town",
    "qs_pg:woe_adm0":23424810,
    "woe:adm0_id":23424810,
    "woe:name_adm0":"\u010cesk\u00e1 republika",
    "woe:name_adm1":"Kraj Vyso\u010dina",
    "woe:placetype":"Town",
    "wof:name":"Skryje",
    "wof:placetype":"locality",
    "wof:population":191
},
  "geometry": {"coordinates":[15.48678,49.84302],"type":"Point"}
}