{
  "type": "Feature",
  "properties": {
    "gn:admin1_code":"80.0",
    "gn:admin2_code":"0612",
    "gn:asciiname":"Helenin",
    "gn:country_code":"CZ",
    "gn:dem":471,
    "gn:feature_class":"P",
    "gn:feature_code":"PPL",
    "gn:name":"Helen\u00edn",
    "gn:population":0,
    "gn:timezone":"Europe/Prague",
    "iso:country":"CZ",
    "name:und_x_variant":[
        "Helenenthal",
        "Helen\u00edn"
    ],
    "wof:name":"Helenin",
    "wof:placetype":"locality"
},
  "geometry": {"coordinates":[15.62212,49.4055],"type":"Point"}
}