{
  "type": "Feature",
  "properties": {
    "gn:gn_country":"CZ",
    "gn:gn_fcode":"PPL",
    "gn:gn_pop":575,
    "gn:population":575,
    "iso:country":"CZ",
    "name:ces_x_preferred":[
        "Le\u0161any"
    ],
    "name:eng_x_preferred":[
        "Le\u0161any"
    ],
    "name:fas_x_preferred":[
        "\u0644\u0634\u0627\u0646\u06cc"
    ],
    "name:fra_x_preferred":[
        "Le\u0161any"
    ],
    "name:hun_x_preferred":[
        "Le\u0161any"
    ],
    "name:ita_x_preferred":[
        "Le\u0161any"
    ],
    "name:msa_x_preferred":[
        "Le\u0161any"
    ],
    "name:nld_x_preferred":[
        "Le\u0161any"
    ],
    "name:pol_x_preferred":[
        "Le\u0161any"
    ],
    "name:por_x_preferred":[
        "Le\u0161any"
    ],
    "name:rup_x_preferred":[
        "Le\u0161any"
    ],
    "name:slk_x_preferred":[
        "Le\u0161any"
    ],
    "name:srp_x_preferred":[
        "\u041b\u0435\u0448\u0430\u043d\u0438"
    ],
    "name:swe_x_preferred":[
        "Le\u0161any"
    ],
    "name:unk_x_variant":[
        "Leschan"
    ],
    "name:vie_x_preferred":[
        "Le\u0161any"
    ],
    "qs_pg:aaroncc":"CZ",
    "qs_pg:gn_country":"CZ",
    "qs_pg:gn_fcode":"PPL",
    "qs_pg:gn_pop":575,
    "qs_pg:name":"Le\u0161any",
    "qs_pg:name_adm0":"\u010cesk\u00e1 republika",
    "qs_pg:name_adm1":"St\u0159edo\u010desk\u00fd kraj",
    "qs_pg:photos_9r":0,
    "qs_pg:photos_sr":0,
    "qs_pg:pop_sr":2,
    "qs_pg:qs_pg_placetype":"locality",
    "qs_pg:qs_pg_placetype_gp":"Town",
    "qs_pg:woe_adm0":23424810,
    "woe:adm0_id":23424810,
    "woe:name_adm0":"\u010cesk\u00e1 republika",
    "woe:name_adm1":"St\u0159edo\u010desk\u00fd kraj",
    "woe:placetype":"Town",
    "wof:name":"Le\u0161any",
    "wof:placetype":"locality",
    "wof:population":575
},
  "geometry": {"coordinates":[14.52495,49.84417],"type":"Point"}
}