{
  "type": "Feature",
  "properties": {
    "gn:admin1_code":"84.0",
    "gn:admin2_code":"0715",
    "gn:asciiname":"Horni Olesna",
    "gn:country_code":"CZ",
    "gn:dem":335,
    "gn:feature_class":"P",
    "gn:feature_code":"PPL",
    "gn:name":"Horn\u00ed Ole\u0161n\u00e1",
    "gn:population":0,
    "gn:timezone":"Europe/Prague",
    "iso:country":"CZ",
    "name:und_x_variant":[
        "Ober-Ullischen",
        "Horn\u00ed Ole\u0161n\u00e1"
    ],
    "wof:name":"Horni Olesna",
    "wof:placetype":"locality"
},
  "geometry": {"coordinates":[17.02072,49.91107],"type":"Point"}
}