{
  "type": "Feature",
  "properties": {
    "gn:gn_country":"CZ",
    "gn:gn_fcode":"PPL",
    "gn:gn_pop":96,
    "gn:population":96,
    "iso:country":"CZ",
    "name:azb_x_preferred":[
        "\u062a\u0634\u0644\u062e\u0648\u0648\u06cc\u062a\u0633\u0647"
    ],
    "name:ces_x_preferred":[
        "\u010celechovice"
    ],
    "name:deu_x_preferred":[
        "\u010celechovice"
    ],
    "name:eng_x_preferred":[
        "\u010celechovice"
    ],
    "name:epo_x_preferred":[
        "\u010celechovice"
    ],
    "name:eus_x_preferred":[
        "\u010celechovice"
    ],
    "name:fas_x_preferred":[
        "\u062a\u0634\u0644\u062e\u0648\u0648\u06cc\u062a\u0633\u0647"
    ],
    "name:fra_x_preferred":[
        "\u010celechovice"
    ],
    "name:hun_x_preferred":[
        "\u010celechovice"
    ],
    "name:ita_x_preferred":[
        "\u010celechovice"
    ],
    "name:msa_x_preferred":[
        "\u010celechovice"
    ],
    "name:nan_x_preferred":[
        "\u010celechovice"
    ],
    "name:nld_x_preferred":[
        "\u010celechovice"
    ],
    "name:pol_x_preferred":[
        "\u010celechovice"
    ],
    "name:por_x_preferred":[
        "\u010celechovice"
    ],
    "name:rup_x_preferred":[
        "\u010celechovice"
    ],
    "name:slk_x_preferred":[
        "\u010celechovice"
    ],
    "name:spa_x_preferred":[
        "\u010celechovice"
    ],
    "name:srp_x_preferred":[
        "\u0427\u0435\u043b\u0435\u0445\u043e\u0432\u0438\u0446\u0435"
    ],
    "name:vie_x_preferred":[
        "\u010celechovice"
    ],
    "qs_pg:aaroncc":"CZ",
    "qs_pg:gn_country":"CZ",
    "qs_pg:gn_fcode":"PPL",
    "qs_pg:gn_pop":96,
    "qs_pg:name":"\u010celechovice",
    "qs_pg:name_adm0":"\u010cesk\u00e1 republika",
    "qs_pg:name_adm1":"Olomouck\u00fd kraj",
    "qs_pg:photos_9r":0,
    "qs_pg:photos_sr":0,
    "qs_pg:pop_sr":1,
    "qs_pg:qs_pg_placetype":"locality",
    "qs_pg:qs_pg_placetype_gp":"Town",
    "qs_pg:woe_adm0":23424810,
    "woe:adm0_id":23424810,
    "woe:name_adm0":"\u010cesk\u00e1 republika",
    "woe:name_adm1":"Olomouck\u00fd kraj",
    "woe:placetype":"Town",
    "wof:name":"\u010celechovice",
    "wof:placetype":"locality",
    "wof:population":96
},
  "geometry": {"coordinates":[17.37214,49.51004],"type":"Point"}
}