{
  "type": "Feature",
  "properties": {
    "gn:country":"CZ",
    "iso:country":"CZ",
    "name:ceb_x_preferred":[
        "H\u0159ensko"
    ],
    "name:ces_x_preferred":[
        "H\u0159ensko"
    ],
    "name:deu_x_preferred":[
        "H\u0159ensko"
    ],
    "name:epo_x_preferred":[
        "H\u0159ensko"
    ],
    "name:eus_x_preferred":[
        "H\u0159ensko"
    ],
    "name:fra_x_preferred":[
        "H\u0159ensko"
    ],
    "name:hsb_x_preferred":[
        "H\u0159ensko"
    ],
    "name:hun_x_preferred":[
        "H\u0159ensko"
    ],
    "name:ita_x_preferred":[
        "H\u0159ensko"
    ],
    "name:msa_x_preferred":[
        "H\u0159ensko"
    ],
    "name:nld_x_preferred":[
        "H\u0159ensko"
    ],
    "name:pol_x_preferred":[
        "H\u0159ensko"
    ],
    "name:por_x_preferred":[
        "H\u0159ensko"
    ],
    "name:ron_x_preferred":[
        "H\u0159ensko"
    ],
    "name:slk_x_preferred":[
        "H\u0159ensko"
    ],
    "name:spa_x_preferred":[
        "H\u0159ensko"
    ],
    "name:srp_x_preferred":[
        "\u0425\u0440\u0435\u043d\u0441\u043a\u043e"
    ],
    "name:swe_x_preferred":[
        "H\u0159ensko"
    ],
    "name:vie_x_preferred":[
        "H\u0159ensko"
    ],
    "qs_pg:aaroncc":"CZ",
    "qs_pg:gn_country":"CZ",
    "qs_pg:name":"H\u0159ensko",
    "qs_pg:name_adm0":"\u010cesk\u00e1 republika",
    "qs_pg:name_adm1":"\u00dasteck\u00fd kraj",
    "qs_pg:photos":16,
    "qs_pg:photos_1k":3,
    "qs_pg:photos_9k":5,
    "qs_pg:photos_9r":7,
    "qs_pg:photos_all":1235,
    "qs_pg:photos_sr":1,
    "qs_pg:pop_sr":0,
    "qs_pg:qs_pg_placetype":"localadmin",
    "qs_pg:qs_pg_placetype_gp":"LocalAdmin",
    "qs_pg:woe_adm0":23424810,
    "woe:adm0_id":23424810,
    "woe:name_adm0":"\u010cesk\u00e1 republika",
    "woe:name_adm1":"\u00dasteck\u00fd kraj",
    "woe:placetype":"LocalAdmin",
    "wof:name":"H\u0159ensko",
    "wof:placetype":"localadmin"
},
  "geometry": {"coordinates":[14.244649,50.8841],"type":"Point"}
}