{
  "type": "Feature",
  "properties": {
    "gn:country":"CZ",
    "gn:fcode":"PPL",
    "gn:population":146,
    "iso:country":"CZ",
    "name:azb_x_preferred":[
        "\u062f\u0631\u0627\u0698\u0648\u0648\u06cc\u062a\u0633\u0647"
    ],
    "name:cat_x_preferred":[
        "Dra\u017eovice"
    ],
    "name:ceb_x_preferred":[
        "Dra\u017eovice"
    ],
    "name:ces_x_preferred":[
        "Dra\u017eovice"
    ],
    "name:che_x_preferred":[
        "\u0414\u0440\u0430\u0436\u043e\u0432\u0438\u0446\u0435"
    ],
    "name:deu_x_preferred":[
        "Dra\u017eovice u Su\u0161ice"
    ],
    "name:eng_x_preferred":[
        "Dra\u017eovice"
    ],
    "name:epo_x_preferred":[
        "Dra\u017eovice"
    ],
    "name:eus_x_preferred":[
        "Dra\u017eovice"
    ],
    "name:fas_x_preferred":[
        "\u062f\u0631\u0627\u0698\u0648\u0648\u06cc\u062a\u0633\u0647"
    ],
    "name:fra_x_preferred":[
        "Dra\u017eovice"
    ],
    "name:gle_x_preferred":[
        "Dra\u017eovice"
    ],
    "name:hun_x_preferred":[
        "Dra\u017eovice"
    ],
    "name:ita_x_preferred":[
        "Dra\u017eovice"
    ],
    "name:lmo_x_preferred":[
        "Dra\u017eovice"
    ],
    "name:msa_x_preferred":[
        "Dra\u017eovice"
    ],
    "name:nan_x_preferred":[
        "Dra\u017eovice"
    ],
    "name:nld_x_preferred":[
        "Dra\u017eovice"
    ],
    "name:pol_x_preferred":[
        "Dra\u017eovice"
    ],
    "name:por_x_preferred":[
        "Dra\u017eovice"
    ],
    "name:rup_x_preferred":[
        "Dra\u017eovice"
    ],
    "name:slk_x_preferred":[
        "Dra\u017eovice"
    ],
    "name:spa_x_preferred":[
        "Dra\u017eovice"
    ],
    "name:srp_x_preferred":[
        "\u0414\u0440\u0430\u0436\u043e\u0432\u0438\u0446\u0435"
    ],
    "name:swe_x_preferred":[
        "Dra\u017eovice"
    ],
    "name:tat_x_preferred":[
        "\u0414\u0440\u0430\u0436\u043e\u0432\u0438\u0446\u0435"
    ],
    "name:vie_x_preferred":[
        "Dra\u017eovice"
    ],
    "qs_pg:aaroncc":"CZ",
    "qs_pg:gn_country":"CZ",
    "qs_pg:gn_fcode":"PPL",
    "qs_pg:gn_pop":146,
    "qs_pg:name":"Dra\u017eovice",
    "qs_pg:name_adm0":"\u010cesk\u00e1 republika",
    "qs_pg:name_adm1":"Plze\u0148sk\u00fd kraj",
    "qs_pg:photos_9r":0,
    "qs_pg:photos_sr":0,
    "qs_pg:pop_sr":1,
    "qs_pg:qs_pg_placetype":"locality",
    "qs_pg:qs_pg_placetype_gp":"Town",
    "qs_pg:woe_adm0":23424810,
    "woe:adm0_id":23424810,
    "woe:name_adm0":"\u010cesk\u00e1 republika",
    "woe:name_adm1":"Plze\u0148sk\u00fd kraj",
    "woe:placetype":"Town",
    "wof:name":"Dra\u017eovice",
    "wof:placetype":"locality",
    "wof:population":146
},
  "geometry": {"coordinates":[13.60701,49.22467],"type":"Point"}
}