{
  "type": "Feature",
  "properties": {
    "gn:admin1_code":"88.0",
    "gn:admin2_code":"0205",
    "gn:asciiname":"Otryby",
    "gn:country_code":"CZ",
    "gn:dem":415,
    "gn:feature_class":"P",
    "gn:feature_code":"PPL",
    "gn:name":"Otryby",
    "gn:population":0,
    "gn:timezone":"Europe/Prague",
    "iso:country":"CZ",
    "wof:name":"Otryby",
    "wof:placetype":"locality"
},
  "geometry": {"coordinates":[14.97664,49.80331],"type":"Point"}
}