{
  "type": "Feature",
  "properties": {
    "gn:admin1_code":"80",
    "gn:admin2_code":"0613",
    "gn:asciiname":"Tymova Ves",
    "gn:country_code":"CZ",
    "gn:dem":637,
    "gn:feature_class":"P",
    "gn:feature_code":"PPL",
    "gn:name":"T\u00fdmova Ves",
    "gn:population":0,
    "gn:timezone":"Europe/Prague",
    "iso:country":"CZ",
    "wof:name":"Tymova Ves",
    "wof:placetype":"locality"
},
  "geometry": {"coordinates":[14.97977,49.55161],"type":"Point"}
}