{
  "type": "Feature",
  "properties": {
    "gn:gn_country":"CZ",
    "gn:gn_fcode":"PPL",
    "gn:gn_pop":94,
    "gn:population":94,
    "iso:country":"CZ",
    "name:azb_x_preferred":[
        "\u067e\u0648\u0645\u0632\u06cc \u0646\u0627\u062f \u0627\u0648\u0647\u0631\u06cc"
    ],
    "name:ces_x_preferred":[
        "Pomez\u00ed nad Oh\u0159\u00ed"
    ],
    "name:deu_x_preferred":[
        "Pomez\u00ed nad Oh\u0159\u00ed"
    ],
    "name:eng_x_preferred":[
        "Pomez\u00ed nad Oh\u0159\u00ed"
    ],
    "name:eus_x_preferred":[
        "Pomez\u00ed nad Oh\u0159\u00ed"
    ],
    "name:fas_x_preferred":[
        "\u067e\u0648\u0645\u0632\u06cc \u0646\u0627\u062f \u0627\u0648\u0647\u0631\u06cc"
    ],
    "name:fra_x_preferred":[
        "Pomez\u00ed nad Oh\u0159\u00ed"
    ],
    "name:hun_x_preferred":[
        "Pomez\u00ed nad Oh\u0159\u00ed"
    ],
    "name:ita_x_preferred":[
        "Pomez\u00ed nad Oh\u0159\u00ed"
    ],
    "name:msa_x_preferred":[
        "Pomez\u00ed nad Oh\u0159\u00ed"
    ],
    "name:nan_x_preferred":[
        "Pomez\u00ed nad Oh\u0159\u00ed"
    ],
    "name:nld_x_preferred":[
        "Pomez\u00ed nad Oh\u0159\u00ed"
    ],
    "name:pol_x_preferred":[
        "Pomez\u00ed nad Oh\u0159\u00ed"
    ],
    "name:por_x_preferred":[
        "Pomez\u00ed nad Oh\u0159\u00ed"
    ],
    "name:rup_x_preferred":[
        "Pomez\u00ed nad Oh\u0159\u00ed"
    ],
    "name:slk_x_preferred":[
        "Pomez\u00ed nad Oh\u0159\u00ed"
    ],
    "name:spa_x_preferred":[
        "Pomez\u00ed nad Oh\u0159\u00ed"
    ],
    "name:srp_x_preferred":[
        "\u041f\u043e\u043c\u0435\u0437\u0438 \u043d\u0430 \u041e\u0445\u0440\u0438"
    ],
    "name:unk_x_variant":[
        "Muehlbach"
    ],
    "name:vie_x_preferred":[
        "Pomez\u00ed nad Oh\u0159\u00ed"
    ],
    "qs_pg:aaroncc":"CZ",
    "qs_pg:gn_country":"CZ",
    "qs_pg:gn_fcode":"PPL",
    "qs_pg:gn_pop":94,
    "qs_pg:name":"Pomez\u00ed nad Oh\u0159\u00ed",
    "qs_pg:name_adm0":"\u010cesk\u00e1 republika",
    "qs_pg:name_adm1":"Karlovarsk\u00fd kraj",
    "qs_pg:photos_9k":1,
    "qs_pg:photos_9r":1,
    "qs_pg:photos_all":1,
    "qs_pg:photos_sr":0,
    "qs_pg:pop_sr":1,
    "qs_pg:qs_pg_placetype":"locality",
    "qs_pg:qs_pg_placetype_gp":"Town",
    "qs_pg:woe_adm0":23424810,
    "woe:adm0_id":23424810,
    "woe:name_adm0":"\u010cesk\u00e1 republika",
    "woe:name_adm1":"Karlovarsk\u00fd kraj",
    "woe:placetype":"Town",
    "wof:name":"Pomez\u00ed nad Oh\u0159\u00ed",
    "wof:placetype":"locality",
    "wof:population":94
},
  "geometry": {"coordinates":[12.27842,50.08601],"type":"Point"}
}