{
  "type": "Feature",
  "properties": {
    "gn:admin1_code":"89",
    "gn:admin2_code":"0426",
    "gn:asciiname":"Zichlice",
    "gn:country_code":"CZ",
    "gn:dem":283,
    "gn:feature_class":"P",
    "gn:feature_code":"PPL",
    "gn:name":"\u017dichlice",
    "gn:population":0,
    "gn:timezone":"Europe/Prague",
    "iso:country":"CZ",
    "wof:name":"Zichlice",
    "wof:placetype":"locality"
},
  "geometry": {"coordinates":[13.91667,50.63333],"type":"Point"}
}