{
  "type": "Feature",
  "properties": {
    "gn:admin1_code":"90.0",
    "gn:admin2_code":"0721",
    "gn:asciiname":"Dobrotice",
    "gn:country_code":"CZ",
    "gn:dem":250,
    "gn:feature_class":"P",
    "gn:feature_code":"PPL",
    "gn:name":"Dobrotice",
    "gn:population":0,
    "gn:timezone":"Europe/Prague",
    "iso:country":"CZ",
    "wof:name":"Dobrotice",
    "wof:placetype":"locality"
},
  "geometry": {"coordinates":[17.60477000000001,49.34393],"type":"Point"}
}