{
  "type": "Feature",
  "properties": {
    "gn:gn_country":"CZ",
    "gn:gn_fcode":"PPL",
    "gn:gn_pop":511,
    "gn:population":511,
    "iso:country":"CZ",
    "name:ces_x_preferred":[
        "Tov\u00e9\u0159"
    ],
    "name:deu_x_preferred":[
        "Tov\u00e9\u0159"
    ],
    "name:eng_x_preferred":[
        "Tov\u00e9\u0159"
    ],
    "name:fra_x_preferred":[
        "Tov\u00e9\u0159"
    ],
    "name:hun_x_preferred":[
        "Tov\u00e9\u0159"
    ],
    "name:ita_x_preferred":[
        "Tov\u00e9\u0159"
    ],
    "name:msa_x_preferred":[
        "Tov\u00e9\u0159"
    ],
    "name:nld_x_preferred":[
        "Tov\u00e9\u0159"
    ],
    "name:pol_x_preferred":[
        "Tov\u00e9\u0159"
    ],
    "name:por_x_preferred":[
        "Tov\u00e9\u0159"
    ],
    "name:slk_x_preferred":[
        "Tov\u00e9\u0159"
    ],
    "name:srp_x_preferred":[
        "\u0422\u043e\u0432\u0435\u0440\u0436"
    ],
    "name:swe_x_preferred":[
        "Tov\u00e9\u0159"
    ],
    "name:vie_x_preferred":[
        "Tov\u00e9\u0159"
    ],
    "qs_pg:aaroncc":"CZ",
    "qs_pg:gn_country":"CZ",
    "qs_pg:gn_fcode":"PPL",
    "qs_pg:gn_pop":511,
    "qs_pg:name":"Tov\u00e9\u0159",
    "qs_pg:name_adm0":"\u010cesk\u00e1 republika",
    "qs_pg:name_adm1":"Olomouck\u00fd kraj",
    "qs_pg:photos_9r":0,
    "qs_pg:photos_sr":0,
    "qs_pg:pop_sr":2,
    "qs_pg:qs_pg_placetype":"locality",
    "qs_pg:qs_pg_placetype_gp":"Town",
    "qs_pg:woe_adm0":23424810,
    "woe:adm0_id":23424810,
    "woe:name_adm0":"\u010cesk\u00e1 republika",
    "woe:name_adm1":"Olomouck\u00fd kraj",
    "woe:placetype":"Town",
    "wof:name":"Tov\u00e9\u0159",
    "wof:placetype":"locality",
    "wof:population":511
},
  "geometry": {"coordinates":[17.31901,49.64003],"type":"Point"}
}