{
  "type": "Feature",
  "properties": {
    "gn:admin1_code":"87",
    "gn:admin2_code":"0327",
    "gn:asciiname":"Vrhavec",
    "gn:country_code":"CZ",
    "gn:dem":437,
    "gn:feature_class":"P",
    "gn:feature_code":"PPL",
    "gn:name":"Vrhave\u010d",
    "gn:population":0,
    "gn:timezone":"Europe/Prague",
    "iso:country":"CZ",
    "name:und_x_variant":[
        "Worhabschen",
        "Vrhave\u010d"
    ],
    "wof:name":"Vrhavec",
    "wof:placetype":"locality"
},
  "geometry": {"coordinates":[13.05489,49.68629],"type":"Point"}
}