{
  "type": "Feature",
  "properties": {
    "gn:admin1_code":"83.0",
    "gn:admin2_code":"0512",
    "gn:asciiname":"Haratice",
    "gn:country_code":"CZ",
    "gn:dem":528,
    "gn:feature_class":"P",
    "gn:feature_code":"PPL",
    "gn:name":"Haratice",
    "gn:population":0,
    "gn:timezone":"Europe/Prague",
    "iso:country":"CZ",
    "wof:name":"Haratice",
    "wof:placetype":"locality"
},
  "geometry": {"coordinates":[15.34585,50.70286],"type":"Point"}
}