{
  "type": "Feature",
  "properties": {
    "gn:admin1_code":"79.0",
    "gn:admin2_code":"0313",
    "gn:asciiname":"Slavetin",
    "gn:country_code":"CZ",
    "gn:dem":501,
    "gn:feature_class":"P",
    "gn:feature_code":"PPL",
    "gn:name":"Slav\u011bt\u00edn",
    "gn:population":0,
    "gn:timezone":"Europe/Prague",
    "iso:country":"CZ",
    "name:und_x_variant":[
        "Slawathen",
        "Slav\u011bt\u00edn"
    ],
    "wof:name":"Slavetin",
    "wof:placetype":"locality"
},
  "geometry": {"coordinates":[15.39862,48.98244],"type":"Point"}
}