{
  "type": "Feature",
  "properties": {
    "gn:admin1_code":"90.0",
    "gn:admin2_code":"0723",
    "gn:asciiname":"Jasenka",
    "gn:country_code":"CZ",
    "gn:dem":381,
    "gn:feature_class":"P",
    "gn:feature_code":"PPL",
    "gn:name":"Jasenka",
    "gn:population":0,
    "gn:timezone":"Europe/Prague",
    "iso:country":"CZ",
    "wof:name":"Jasenka",
    "wof:placetype":"locality"
},
  "geometry": {"coordinates":[18.00025,49.35334],"type":"Point"}
}