{
  "type": "Feature",
  "properties": {
    "gn:country":"CZ",
    "gn:fcode":"PPL",
    "gn:population":505,
    "iso:country":"CZ",
    "name:azb_x_preferred":[
        "\u0698\u0627\u0644\u0647\u0648\u0633\u062a\u06cc\u062a\u0633\u0647"
    ],
    "name:ceb_x_preferred":[
        "\u017dalhostice"
    ],
    "name:ces_x_preferred":[
        "\u017dalhostice"
    ],
    "name:deu_x_preferred":[
        "\u017dalhostice"
    ],
    "name:eng_x_preferred":[
        "\u017dalhostice"
    ],
    "name:epo_x_preferred":[
        "\u017dalhostice"
    ],
    "name:eus_x_preferred":[
        "\u017dalhostice"
    ],
    "name:fas_x_preferred":[
        "\u0698\u0627\u0644\u0647\u0648\u0633\u062a\u06cc\u062a\u0633\u0647"
    ],
    "name:fra_x_preferred":[
        "\u017dalhostice"
    ],
    "name:hun_x_preferred":[
        "\u017dalhostice"
    ],
    "name:ita_x_preferred":[
        "\u017dalhostice"
    ],
    "name:msa_x_preferred":[
        "\u017dalhostice"
    ],
    "name:nan_x_preferred":[
        "\u017dalhostice"
    ],
    "name:nld_x_preferred":[
        "\u017dalhostice"
    ],
    "name:por_x_preferred":[
        "\u017dalhostice"
    ],
    "name:rup_x_preferred":[
        "\u017dalhostice"
    ],
    "name:slk_x_preferred":[
        "\u017dalhostice"
    ],
    "name:spa_x_preferred":[
        "\u017dalhostice"
    ],
    "name:srp_x_preferred":[
        "\u0416\u0430\u043b\u0445\u043e\u0441\u0442\u0438\u0446\u0435"
    ],
    "name:swe_x_preferred":[
        "\u017dalhostice"
    ],
    "name:und_x_variant":[
        "C\u017ealositz"
    ],
    "name:vie_x_preferred":[
        "\u017dalhostice"
    ],
    "qs_pg:aaroncc":"CZ",
    "qs_pg:gn_country":"CZ",
    "qs_pg:gn_fcode":"PPL",
    "qs_pg:gn_pop":505,
    "qs_pg:name":"\u017dalhostice",
    "qs_pg:name_adm0":"\u010cesk\u00e1 republika",
    "qs_pg:name_adm1":"\u00dasteck\u00fd kraj",
    "qs_pg:photos_9k":1,
    "qs_pg:photos_9r":1,
    "qs_pg:photos_all":11,
    "qs_pg:photos_sr":0,
    "qs_pg:pop_sr":2,
    "qs_pg:qs_pg_placetype":"locality",
    "qs_pg:qs_pg_placetype_gp":"Town",
    "qs_pg:woe_adm0":23424810,
    "woe:adm0_id":23424810,
    "woe:name_adm0":"\u010cesk\u00e1 republika",
    "woe:name_adm1":"\u00dasteck\u00fd kraj",
    "woe:placetype":"Town",
    "wof:name":"\u017dalhostice",
    "wof:placetype":"locality",
    "wof:population":505
},
  "geometry": {"coordinates":[14.09136,50.52309],"type":"Point"}
}