{
  "type": "Feature",
  "properties": {
    "gn:admin1_code":"79.0",
    "gn:admin2_code":"0315",
    "gn:asciiname":"Repesin",
    "gn:country_code":"CZ",
    "gn:dem":634,
    "gn:feature_class":"P",
    "gn:feature_code":"PPL",
    "gn:name":"\u0158epe\u0161\u00edn",
    "gn:population":0,
    "gn:timezone":"Europe/Prague",
    "iso:country":"CZ",
    "wof:name":"Repesin",
    "wof:placetype":"locality"
},
  "geometry": {"coordinates":[13.9104,49.0004],"type":"Point"}
}