{
  "type": "Feature",
  "properties": {
    "gn:admin1_code":"88.0",
    "gn:admin2_code":"0205",
    "gn:asciiname":"Rozkos",
    "gn:country_code":"CZ",
    "gn:dem":455,
    "gn:feature_class":"P",
    "gn:feature_code":"PPL",
    "gn:name":"Rozko\u0161",
    "gn:population":0,
    "gn:timezone":"Europe/Prague",
    "iso:country":"CZ",
    "wof:name":"Rozkos",
    "wof:placetype":"locality"
},
  "geometry": {"coordinates":[15.1401,49.91659],"type":"Point"}
}