{
  "type": "Feature",
  "properties": {
    "gn:gn_country":"CZ",
    "gn:gn_fcode":"PPL",
    "gn:gn_pop":497,
    "gn:population":497,
    "iso:country":"CZ",
    "name:ces_x_preferred":[
        "Tisov\u00e1"
    ],
    "name:eng_x_preferred":[
        "Tisov\u00e1"
    ],
    "name:epo_x_preferred":[
        "Tisov\u00e1"
    ],
    "name:fas_x_preferred":[
        "\u062a\u06cc\u0633\u0648\u0648\u0627"
    ],
    "name:fra_x_preferred":[
        "Tisov\u00e1"
    ],
    "name:hun_x_preferred":[
        "Tisov\u00e1"
    ],
    "name:ita_x_preferred":[
        "Tisov\u00e1"
    ],
    "name:msa_x_preferred":[
        "Tisov\u00e1"
    ],
    "name:nan_x_preferred":[
        "Tisov\u00e1"
    ],
    "name:nld_x_preferred":[
        "Tisov\u00e1"
    ],
    "name:por_x_preferred":[
        "Tisov\u00e1"
    ],
    "name:rup_x_preferred":[
        "Tisov\u00e1"
    ],
    "name:slk_x_preferred":[
        "Tisov\u00e1"
    ],
    "name:srp_x_preferred":[
        "\u0422\u0438\u0441\u043e\u0432\u0430"
    ],
    "name:swe_x_preferred":[
        "Tisov\u00e1"
    ],
    "name:unk_x_variant":[
        "Tisau"
    ],
    "name:vie_x_preferred":[
        "Tisov\u00e1"
    ],
    "qs_pg:aaroncc":"CZ",
    "qs_pg:gn_country":"CZ",
    "qs_pg:gn_fcode":"PPL",
    "qs_pg:gn_pop":497,
    "qs_pg:name":"Tisov\u00e1",
    "qs_pg:name_adm0":"\u010cesk\u00e1 republika",
    "qs_pg:name_adm1":"Pardubick\u00fd kraj",
    "qs_pg:photos_9r":0,
    "qs_pg:photos_sr":0,
    "qs_pg:pop_sr":2,
    "qs_pg:qs_pg_placetype":"locality",
    "qs_pg:qs_pg_placetype_gp":"Town",
    "qs_pg:woe_adm0":23424810,
    "woe:adm0_id":23424810,
    "woe:name_adm0":"\u010cesk\u00e1 republika",
    "woe:name_adm1":"Pardubick\u00fd kraj",
    "woe:placetype":"Town",
    "wof:name":"Tisov\u00e1",
    "wof:placetype":"locality",
    "wof:population":497
},
  "geometry": {"coordinates":[16.22453,49.93616],"type":"Point"}
}