{
  "type": "Feature",
  "properties": {
    "gn:gn_country":"CZ",
    "gn:gn_fcode":"PPL",
    "gn:gn_pop":115,
    "gn:population":115,
    "iso:country":"CZ",
    "name:ces_x_preferred":[
        "Svat\u00fd Jan pod Skalou"
    ],
    "name:deu_x_preferred":[
        "Svat\u00fd Jan pod Skalou"
    ],
    "name:eng_x_preferred":[
        "Svat\u00fd Jan pod Skalou"
    ],
    "name:epo_x_preferred":[
        "Svat\u00fd Jan pod Skalou"
    ],
    "name:fas_x_preferred":[
        "\u0633\u0648\u0627\u062a\u06cc \u06cc\u0627\u0646 \u067e\u0648\u062f \u0633\u06a9\u0627\u0644\u0648\u0648"
    ],
    "name:fra_x_preferred":[
        "Svat\u00fd Jan pod Skalou"
    ],
    "name:hun_x_preferred":[
        "Svat\u00fd Jan pod Skalou"
    ],
    "name:ita_x_preferred":[
        "Svat\u00fd Jan pod Skalou"
    ],
    "name:msa_x_preferred":[
        "Svat\u00fd Jan pod Skalou"
    ],
    "name:nan_x_preferred":[
        "Svat\u00fd Jan pod Skalou"
    ],
    "name:nld_x_preferred":[
        "Svat\u00fd Jan pod Skalou"
    ],
    "name:pol_x_preferred":[
        "Svat\u00fd Jan pod Skalou"
    ],
    "name:por_x_preferred":[
        "Svat\u00fd Jan pod Skalou"
    ],
    "name:rup_x_preferred":[
        "Svat\u00fd Jan pod Skalou"
    ],
    "name:slk_x_preferred":[
        "Svat\u00fd Jan pod Skalou"
    ],
    "name:srp_x_preferred":[
        "\u0421\u0432\u0430\u0442\u0438 \u0408\u0430\u043d \u043f\u043e\u0434 \u0421\u043a\u0430\u043b\u043e\u043c"
    ],
    "name:swe_x_preferred":[
        "Svat\u00fd Jan pod Skalou"
    ],
    "name:vie_x_preferred":[
        "Svat\u00fd Jan pod Skalou"
    ],
    "qs_pg:aaroncc":"CZ",
    "qs_pg:gn_country":"CZ",
    "qs_pg:gn_fcode":"PPL",
    "qs_pg:gn_pop":115,
    "qs_pg:name":"Svat\u00fd Jan pod Skalou",
    "qs_pg:name_adm0":"\u010cesk\u00e1 republika",
    "qs_pg:name_adm1":"St\u0159edo\u010desk\u00fd kraj",
    "qs_pg:photos":36,
    "qs_pg:photos_1k":7,
    "qs_pg:photos_9k":1,
    "qs_pg:photos_9r":2,
    "qs_pg:photos_all":36,
    "qs_pg:photos_sr":2,
    "qs_pg:pop_sr":1,
    "qs_pg:qs_pg_placetype":"locality",
    "qs_pg:qs_pg_placetype_gp":"Town",
    "qs_pg:woe_adm0":23424810,
    "woe:adm0_id":23424810,
    "woe:name_adm0":"\u010cesk\u00e1 republika",
    "woe:name_adm1":"St\u0159edo\u010desk\u00fd kraj",
    "woe:placetype":"Town",
    "wof:name":"Svat\u00fd Jan pod Skalou",
    "wof:placetype":"locality",
    "wof:population":115
},
  "geometry": {"coordinates":[14.13316,49.96891],"type":"Point"}
}