{
  "type": "Feature",
  "properties": {
    "gn:admin1_code":"88.0",
    "gn:admin2_code":"0201",
    "gn:asciiname":"Bezdekov",
    "gn:country_code":"CZ",
    "gn:dem":354,
    "gn:feature_class":"P",
    "gn:feature_code":"PPL",
    "gn:name":"Bezd\u011bkov",
    "gn:population":0,
    "gn:timezone":"Europe/Prague",
    "iso:country":"CZ",
    "name:und_x_variant":[
        "Besdiekow",
        "Bezd\u011bkov"
    ],
    "wof:name":"Bezdekov",
    "wof:placetype":"locality"
},
  "geometry": {"coordinates":[14.75225,49.86439],"type":"Point"}
}