{
  "type": "Feature",
  "properties": {
    "gn:admin1_code":"85.0",
    "gn:admin2_code":"0803",
    "gn:asciiname":"Podlesi",
    "gn:country_code":"CZ",
    "gn:dem":228,
    "gn:feature_class":"P",
    "gn:feature_code":"PPL",
    "gn:name":"Podles\u00ed",
    "gn:population":0,
    "gn:timezone":"Europe/Prague",
    "iso:country":"CZ",
    "wof:name":"Podlesi",
    "wof:placetype":"locality"
},
  "geometry": {"coordinates":[18.37392,49.85262],"type":"Point"}
}