{
  "type": "Feature",
  "properties": {
    "gn:country":"CZ",
    "gn:fcode":"PPL",
    "gn:population":1686,
    "iso:country":"CZ",
    "name:ceb_x_preferred":[
        "Se\u010d"
    ],
    "name:ces_x_preferred":[
        "Se\u010d"
    ],
    "name:deu_x_preferred":[
        "Se\u010d"
    ],
    "name:epo_x_preferred":[
        "Se\u010d"
    ],
    "name:fra_x_preferred":[
        "Se\u010d"
    ],
    "name:ita_x_preferred":[
        "Se\u010d"
    ],
    "name:nld_x_preferred":[
        "Se\u010d"
    ],
    "name:rus_x_preferred":[
        "\u0421\u0435\u0447"
    ],
    "name:slk_x_preferred":[
        "Se\u010d"
    ],
    "name:srp_x_preferred":[
        "\u0421\u0435\u0447"
    ],
    "name:swe_x_preferred":[
        "Se\u010d"
    ],
    "qs_pg:aaroncc":"CZ",
    "qs_pg:gn_country":"CZ",
    "qs_pg:gn_fcode":"PPL",
    "qs_pg:gn_pop":1686,
    "qs_pg:name":"Se\u010d",
    "qs_pg:name_adm0":"\u010cesk\u00e1 republika",
    "qs_pg:name_adm1":"Pardubick\u00fd kraj",
    "qs_pg:photos":56,
    "qs_pg:photos_1k":11,
    "qs_pg:photos_9k":1,
    "qs_pg:photos_9r":2,
    "qs_pg:photos_all":56,
    "qs_pg:photos_sr":2,
    "qs_pg:pop_sr":3,
    "qs_pg:qs_pg_placetype":"locality",
    "qs_pg:qs_pg_placetype_gp":"Town",
    "qs_pg:woe_adm0":23424810,
    "woe:adm0_id":23424810,
    "woe:name_adm0":"\u010cesk\u00e1 republika",
    "woe:name_adm1":"Pardubick\u00fd kraj",
    "woe:placetype":"Town",
    "wof:name":"Se\u010d",
    "wof:placetype":"locality",
    "wof:population":1686
},
  "geometry": {"coordinates":[15.65643,49.84694],"type":"Point"}
}