{
  "type": "Feature",
  "properties": {
    "gn:gn_country":"CZ",
    "gn:gn_fcode":"PPL",
    "gn:gn_pop":353,
    "gn:population":353,
    "iso:country":"CZ",
    "name:ces_x_preferred":[
        "Jabkenice"
    ],
    "name:deu_x_preferred":[
        "Jabkenice"
    ],
    "name:eng_x_preferred":[
        "Jabkenice"
    ],
    "name:epo_x_preferred":[
        "Jabkenice"
    ],
    "name:fra_x_preferred":[
        "Jabkenice"
    ],
    "name:hun_x_preferred":[
        "Jabkenice"
    ],
    "name:ita_x_preferred":[
        "Jabkenice"
    ],
    "name:jpn_x_preferred":[
        "\u30e4\u30d6\u30b1\u30cb\u30bb"
    ],
    "name:msa_x_preferred":[
        "Jabkenice"
    ],
    "name:nan_x_preferred":[
        "Jabkenice"
    ],
    "name:nld_x_preferred":[
        "Jabkenice"
    ],
    "name:pol_x_preferred":[
        "Jabkenice"
    ],
    "name:por_x_preferred":[
        "Jabkenice"
    ],
    "name:rup_x_preferred":[
        "Jabkenice"
    ],
    "name:slk_x_preferred":[
        "Jabkenice"
    ],
    "name:srp_x_preferred":[
        "\u0408\u0430\u043f\u043a\u0435\u045a\u0438\u0446\u0435"
    ],
    "name:swe_x_preferred":[
        "Jabkenice"
    ],
    "name:unk_x_variant":[
        "Jablkynice"
    ],
    "name:vie_x_preferred":[
        "Jabkenice"
    ],
    "qs_pg:aaroncc":"CZ",
    "qs_pg:gn_country":"CZ",
    "qs_pg:gn_fcode":"PPL",
    "qs_pg:gn_pop":353,
    "qs_pg:name":"Jabkenice",
    "qs_pg:name_adm0":"\u010cesk\u00e1 republika",
    "qs_pg:name_adm1":"St\u0159edo\u010desk\u00fd kraj",
    "qs_pg:photos_9r":0,
    "qs_pg:photos_sr":0,
    "qs_pg:pop_sr":2,
    "qs_pg:qs_pg_placetype":"locality",
    "qs_pg:qs_pg_placetype_gp":"Town",
    "qs_pg:woe_adm0":23424810,
    "woe:adm0_id":23424810,
    "woe:name_adm0":"\u010cesk\u00e1 republika",
    "woe:name_adm1":"St\u0159edo\u010desk\u00fd kraj",
    "woe:placetype":"Town",
    "wof:name":"Jabkenice",
    "wof:placetype":"locality",
    "wof:population":353
},
  "geometry": {"coordinates":[15.01477,50.32407],"type":"Point"}
}