{
  "type": "Feature",
  "properties": {
    "iso:country":"CZ",
    "name:ces_x_preferred":[
        "Zelen\u00e9 P\u0159edm\u011bst\u00ed-\u010c\u00e1st"
    ],
    "name:cze_x_colloquial":[
        "Zelene Poedmisti-east",
        "Zelene Poeedmisti-east",
        "Zelene Predmesti-cast"
    ],
    "name:cze_x_variant":[
        "Zelen\u00e9 P\u00f8edm\u00ecst\u00ed-\u00c8\u00e1st"
    ],
    "qs:gn_adm0_cc":"CZ",
    "qs:gn_local":3068582,
    "qs:gn_nam_loc":"Pardubice, Pardubice, Pardubice, Pardubick\u00fd kraj, CZ",
    "qs:gn_namadm1":"86",
    "qs:local_max":718,
    "qs:local_sum":1556,
    "qs:localhoods":5,
    "qs:name":"Zelen\u00e9 P\u0159edm\u011bst\u00ed-\u010c\u00e1st",
    "qs:name_adm0":"\u010cesk\u00e1 republika",
    "qs:name_adm1":"Pardubick\u00fd kraj",
    "qs:name_adm2":"Pardubice",
    "qs:name_lau":"Pardubice",
    "qs:name_local":"Pardubice",
    "qs:photo_max":110,
    "qs:photo_sum":491,
    "qs:placetype":"Suburb",
    "qs:quad_count":32,
    "qs:woe_adm0":23424810,
    "qs:woe_adm1":20070465,
    "qs:woe_adm2":12582598,
    "qs:woe_lau":12608891,
    "qs:woe_local":795793,
    "qs:woe_ver":"7.10.0",
    "wof:lang":[
        "cze"
    ],
    "wof:name":"Zelen\u00e9 P\u0159edm\u011bst\u00ed-\u010c\u00e1st",
    "wof:placetype":"neighbourhood"
},
  "geometry": {"coordinates":[15.771448,50.036766],"type":"Point"}
}