{
  "type": "Feature",
  "properties": {
    "gn:admin1_code":"80.0",
    "gn:admin2_code":"0615",
    "gn:asciiname":"Dolni Radslavice",
    "gn:country_code":"CZ",
    "gn:dem":500,
    "gn:feature_class":"P",
    "gn:feature_code":"PPL",
    "gn:name":"Doln\u00ed Radslavice",
    "gn:population":0,
    "gn:timezone":"Europe/Prague",
    "iso:country":"CZ",
    "wof:name":"Dolni Radslavice",
    "wof:placetype":"locality"
},
  "geometry": {"coordinates":[16.05558,49.34878],"type":"Point"}
}