{
  "type": "Feature",
  "properties": {
    "gn:admin1_code":"88",
    "gn:admin2_code":"0201",
    "gn:asciiname":"Zahorany",
    "gn:country_code":"CZ",
    "gn:dem":366,
    "gn:feature_class":"P",
    "gn:feature_code":"PPL",
    "gn:name":"Zaho\u0159any",
    "gn:population":0,
    "gn:timezone":"Europe/Prague",
    "iso:country":"CZ",
    "wof:name":"Zahorany",
    "wof:placetype":"locality"
},
  "geometry": {"coordinates":[14.61071,49.72907],"type":"Point"}
}