{
  "type": "Feature",
  "properties": {
    "gn:admin1_code":"85.0",
    "gn:admin2_code":"0804",
    "gn:asciiname":"Kojetin",
    "gn:country_code":"CZ",
    "gn:dem":465,
    "gn:feature_class":"P",
    "gn:feature_code":"PPL",
    "gn:name":"Kojet\u00edn",
    "gn:population":0,
    "gn:timezone":"Europe/Prague",
    "iso:country":"CZ",
    "name:deu_x_preferred":[
        "Kojetein"
    ],
    "wof:name":"Kojetin",
    "wof:placetype":"locality"
},
  "geometry": {"coordinates":[17.98299,49.56085],"type":"Point"}
}