{
  "type": "Feature",
  "properties": {
    "gn:admin1_code":"80",
    "gn:admin2_code":"0615",
    "gn:asciiname":"Stary Teleckov",
    "gn:country_code":"CZ",
    "gn:dem":603,
    "gn:feature_class":"P",
    "gn:feature_code":"PPL",
    "gn:name":"Star\u00fd Tele\u010dkov",
    "gn:population":0,
    "gn:timezone":"Europe/Prague",
    "iso:country":"CZ",
    "wof:name":"Stary Teleckov",
    "wof:placetype":"locality"
},
  "geometry": {"coordinates":[15.89861,49.45905],"type":"Point"}
}