{
  "type": "Feature",
  "properties": {
    "gn:country":"CZ",
    "gn:fcode":"PPL",
    "gn:population":249,
    "iso:country":"CZ",
    "name:azb_x_preferred":[
        "\u067e\u0648\u062f\u0648\u0644\u0634\u06cc"
    ],
    "name:cat_x_preferred":[
        "Pod\u016fl\u0161\u00ed"
    ],
    "name:ceb_x_preferred":[
        "Pod\u016fl\u0161\u00ed"
    ],
    "name:ces_x_preferred":[
        "Pod\u016fl\u0161\u00ed"
    ],
    "name:che_x_preferred":[
        "\u041f\u043e\u0434\u0443\u043b\u0448\u0438"
    ],
    "name:eng_x_preferred":[
        "Pod\u016fl\u0161\u00ed"
    ],
    "name:epo_x_preferred":[
        "Pod\u016fl\u0161\u00ed"
    ],
    "name:eus_x_preferred":[
        "Pod\u016fl\u0161\u00ed"
    ],
    "name:fas_x_preferred":[
        "\u067e\u0648\u062f\u0648\u0644\u0634\u06cc"
    ],
    "name:fra_x_preferred":[
        "Pod\u016fl\u0161\u00ed"
    ],
    "name:gle_x_preferred":[
        "Pod\u016fl\u0161\u00ed"
    ],
    "name:hun_x_preferred":[
        "Pod\u016fl\u0161\u00ed"
    ],
    "name:ita_x_preferred":[
        "Pod\u016fl\u0161\u00ed"
    ],
    "name:lmo_x_preferred":[
        "Pod\u016fl\u0161\u00ed"
    ],
    "name:msa_x_preferred":[
        "Pod\u016fl\u0161\u00ed"
    ],
    "name:nan_x_preferred":[
        "Pod\u016fl\u0161\u00ed"
    ],
    "name:nld_x_preferred":[
        "Pod\u016fl\u0161\u00ed"
    ],
    "name:pol_x_preferred":[
        "Pod\u016fl\u0161\u00ed"
    ],
    "name:por_x_preferred":[
        "Pod\u016fl\u0161\u00ed"
    ],
    "name:slk_x_preferred":[
        "Pod\u016fl\u0161\u00ed"
    ],
    "name:spa_x_preferred":[
        "Pod\u016fl\u0161\u00ed"
    ],
    "name:srp_x_preferred":[
        "\u041f\u043e\u0434\u0443\u043b\u0448\u0438"
    ],
    "name:swe_x_preferred":[
        "Pod\u016fl\u0161\u00ed"
    ],
    "name:tat_x_preferred":[
        "\u041f\u043e\u0434\u0443\u043b\u0448\u0438"
    ],
    "name:vie_x_preferred":[
        "Pod\u016fl\u0161\u00ed"
    ],
    "qs_pg:aaroncc":"CZ",
    "qs_pg:gn_country":"CZ",
    "qs_pg:gn_fcode":"PPL",
    "qs_pg:gn_pop":249,
    "qs_pg:name":"Pod\u016fl\u0161\u00ed",
    "qs_pg:name_adm0":"\u010cesk\u00e1 republika",
    "qs_pg:name_adm1":"Kr\u00e1lov\u00e9hradeck\u00fd kraj",
    "qs_pg:photos_9r":0,
    "qs_pg:photos_sr":0,
    "qs_pg:pop_sr":2,
    "qs_pg:qs_pg_placetype":"locality",
    "qs_pg:qs_pg_placetype_gp":"Town",
    "qs_pg:woe_adm0":23424810,
    "woe:adm0_id":23424810,
    "woe:name_adm0":"\u010cesk\u00e1 republika",
    "woe:name_adm1":"Kr\u00e1lov\u00e9hradeck\u00fd kraj",
    "woe:placetype":"Town",
    "wof:name":"Pod\u016fl\u0161\u00ed",
    "wof:placetype":"locality",
    "wof:population":249
},
  "geometry": {"coordinates":[15.3428,50.47607],"type":"Point"}
}