{
  "type": "Feature",
  "properties": {
    "gn:admin1_code":"85.0",
    "gn:admin2_code":"0802",
    "gn:asciiname":"Lojkascanka",
    "gn:country_code":"CZ",
    "gn:dem":517,
    "gn:feature_class":"P",
    "gn:feature_code":"PPL",
    "gn:name":"Lojka\u0161\u010danka",
    "gn:population":0,
    "gn:timezone":"Europe/Prague",
    "iso:country":"CZ",
    "wof:name":"Lojkascanka",
    "wof:placetype":"locality"
},
  "geometry": {"coordinates":[18.43333,49.46667],"type":"Point"}
}