{
  "type": "Feature",
  "properties": {
    "gn:admin1_code":"86",
    "gn:admin2_code":"0534",
    "gn:asciiname":"Sumvald",
    "gn:country_code":"CZ",
    "gn:dem":595,
    "gn:feature_class":"P",
    "gn:feature_code":"PPL",
    "gn:name":"\u0160umvald",
    "gn:population":0,
    "gn:timezone":"Europe/Prague",
    "iso:country":"CZ",
    "wof:name":"Sumvald",
    "wof:placetype":"locality"
},
  "geometry": {"coordinates":[16.71167,49.91905],"type":"Point"}
}