{
  "type": "Feature",
  "properties": {
    "iso:country":"CZ",
    "name:ceb_x_preferred":[
        "Chlumec"
    ],
    "name:ces_x_preferred":[
        "Chlumec"
    ],
    "name:deu_x_preferred":[
        "Chlumec"
    ],
    "name:fra_x_preferred":[
        "Chlumec"
    ],
    "name:ita_x_preferred":[
        "Chlumec"
    ],
    "name:nld_x_preferred":[
        "Chlumec"
    ],
    "name:pol_x_preferred":[
        "Chlumec"
    ],
    "name:slk_x_preferred":[
        "Chlumec"
    ],
    "name:srp_x_preferred":[
        "\u0425\u043b\u0443\u043c\u0435\u0446"
    ],
    "name:swe_x_preferred":[
        "Chlumec"
    ],
    "qs_pg:aaroncc":"CZ",
    "qs_pg:name":"Chlumec",
    "qs_pg:name_adm0":"\u010cesk\u00e1 republika",
    "qs_pg:name_adm1":"\u00dasteck\u00fd kraj",
    "qs_pg:photos":2,
    "qs_pg:photos_1k":1,
    "qs_pg:photos_9k":1,
    "qs_pg:photos_9r":1,
    "qs_pg:photos_all":2,
    "qs_pg:photos_sr":1,
    "qs_pg:pop_sr":0,
    "qs_pg:qs_pg_placetype":"localadmin",
    "qs_pg:qs_pg_placetype_gp":"LocalAdmin",
    "qs_pg:woe_adm0":23424810,
    "woe:adm0_id":23424810,
    "woe:name_adm0":"\u010cesk\u00e1 republika",
    "woe:name_adm1":"\u00dasteck\u00fd kraj",
    "woe:placetype":"LocalAdmin",
    "wof:name":"Chlumec",
    "wof:placetype":"localadmin"
},
  "geometry": {"coordinates":[13.898906,50.731565],"type":"Point"}
}