{
  "type": "Feature",
  "properties": {
    "iso:country":"CZ",
    "name:ceb_x_preferred":[
        "Hor\u0161ovsk\u00fd T\u00fdn"
    ],
    "name:ces_x_preferred":[
        "Hor\u0161ovsk\u00fd T\u00fdn"
    ],
    "name:deu_x_preferred":[
        "Hor\u0161ovsk\u00fd T\u00fdn"
    ],
    "name:eus_x_preferred":[
        "Hor\u0161ovsk\u00fd T\u00fdn"
    ],
    "name:fas_x_preferred":[
        "\u0647\u0648\u0631\u0634\u0648\u0648\u0633\u06a9\u06cc \u062a\u06cc\u0646"
    ],
    "name:fra_x_preferred":[
        "Hor\u0161ovsk\u00fd T\u00fdn"
    ],
    "name:hun_x_preferred":[
        "Hor\u0161ovsk\u00fd T\u00fdn"
    ],
    "name:ita_x_preferred":[
        "Hor\u0161ovsk\u00fd T\u00fdn"
    ],
    "name:msa_x_preferred":[
        "Hor\u0161ovsk\u00fd T\u00fdn"
    ],
    "name:nld_x_preferred":[
        "Hor\u0161ovsk\u00fd T\u00fdn"
    ],
    "name:pol_x_preferred":[
        "Hor\u0161ovsk\u00fd T\u00fdn"
    ],
    "name:por_x_preferred":[
        "Hor\u0161ovsk\u00fd T\u00fdn"
    ],
    "name:rus_x_preferred":[
        "\u0413\u043e\u0440\u0448\u043e\u0432\u0441\u043a\u0438-\u0422\u0438\u043d"
    ],
    "name:slk_x_preferred":[
        "Hor\u0161ovsk\u00fd T\u00fdn"
    ],
    "name:spa_x_preferred":[
        "Hor\u0161ovsk\u00fd T\u00fdn"
    ],
    "name:srp_x_preferred":[
        "\u0425\u043e\u0440\u0448\u043e\u0432\u0441\u043a\u0438 \u0422\u0438\u043d"
    ],
    "name:swe_x_preferred":[
        "Hor\u0161ovsk\u00fd T\u00fdn"
    ],
    "name:urd_x_preferred":[
        "\u06c1\u0648\u0631\u0634\u0648\u0641\u0633\u06a9\u06cc \u062a\u06cc\u0646"
    ],
    "name:vie_x_preferred":[
        "Hor\u0161ovsk\u00fd T\u00fdn"
    ],
    "qs_pg:aaroncc":"CZ",
    "qs_pg:name":"Hor\u0161ovsk\u00fd T\u00fdn",
    "qs_pg:name_adm0":"\u010cesk\u00e1 republika",
    "qs_pg:name_adm1":"Plze\u0148sk\u00fd kraj",
    "qs_pg:photos":7,
    "qs_pg:photos_1k":1,
    "qs_pg:photos_9k":1,
    "qs_pg:photos_9r":2,
    "qs_pg:photos_all":64,
    "qs_pg:photos_sr":1,
    "qs_pg:pop_sr":0,
    "qs_pg:qs_pg_placetype":"localadmin",
    "qs_pg:qs_pg_placetype_gp":"LocalAdmin",
    "qs_pg:woe_adm0":23424810,
    "woe:adm0_id":23424810,
    "woe:name_adm0":"\u010cesk\u00e1 republika",
    "woe:name_adm1":"Plze\u0148sk\u00fd kraj",
    "woe:placetype":"LocalAdmin",
    "wof:name":"Hor\u0161ovsk\u00fd T\u00fdn",
    "wof:placetype":"localadmin"
},
  "geometry": {"coordinates":[12.943525,49.530786],"type":"Point"}
}