{
  "type": "Feature",
  "properties": {
    "gn:admin1_code":"88",
    "gn:admin2_code":"020B",
    "gn:asciiname":"Stary Knin",
    "gn:country_code":"CZ",
    "gn:dem":319,
    "gn:feature_class":"P",
    "gn:feature_code":"PPL",
    "gn:name":"Star\u00fd Kn\u00edn",
    "gn:population":0,
    "gn:timezone":"Europe/Prague",
    "iso:country":"CZ",
    "name:und_x_variant":[
        "Alt Kn\u00edn",
        "Star\u00fd Kn\u00edn"
    ],
    "wof:name":"Stary Knin",
    "wof:placetype":"locality"
},
  "geometry": {"coordinates":[14.28345,49.78736],"type":"Point"}
}