{
  "type": "Feature",
  "properties": {
    "gn:country":"CZ",
    "gn:fcode":"PPL",
    "gn:population":312,
    "iso:country":"CZ",
    "name:cat_x_preferred":[
        "Ban\u00edn"
    ],
    "name:ceb_x_preferred":[
        "Ban\u00edn"
    ],
    "name:ces_x_preferred":[
        "Ban\u00edn"
    ],
    "name:che_x_preferred":[
        "\u0411\u0430\u043d\u0438\u043d"
    ],
    "name:deu_x_preferred":[
        "Ban\u00edn"
    ],
    "name:eng_x_preferred":[
        "Ban\u00edn"
    ],
    "name:epo_x_preferred":[
        "Ban\u00edn"
    ],
    "name:eus_x_preferred":[
        "Ban\u00edn"
    ],
    "name:fra_x_preferred":[
        "Ban\u00edn"
    ],
    "name:gle_x_preferred":[
        "Ban\u00edn"
    ],
    "name:hun_x_preferred":[
        "Ban\u00edn"
    ],
    "name:ita_x_preferred":[
        "Ban\u00edn"
    ],
    "name:lmo_x_preferred":[
        "Ban\u00edn"
    ],
    "name:msa_x_preferred":[
        "Ban\u00edn"
    ],
    "name:nan_x_preferred":[
        "Ban\u00edn"
    ],
    "name:nld_x_preferred":[
        "Ban\u00edn"
    ],
    "name:pol_x_preferred":[
        "Ban\u00edn"
    ],
    "name:por_x_preferred":[
        "Ban\u00edn"
    ],
    "name:rup_x_preferred":[
        "Ban\u00edn"
    ],
    "name:slk_x_preferred":[
        "Ban\u00edn"
    ],
    "name:spa_x_preferred":[
        "Ban\u00edn"
    ],
    "name:srp_x_preferred":[
        "\u0411\u0430\u045a\u0438\u043d"
    ],
    "name:swe_x_preferred":[
        "Ban\u00edn"
    ],
    "name:szl_x_preferred":[
        "Ban\u00edn"
    ],
    "name:tat_x_preferred":[
        "\u0411\u0430\u043d\u0438\u043d"
    ],
    "name:und_x_variant":[
        "Bohnau"
    ],
    "name:vie_x_preferred":[
        "Ban\u00edn"
    ],
    "qs_pg:aaroncc":"CZ",
    "qs_pg:gn_country":"CZ",
    "qs_pg:gn_fcode":"PPL",
    "qs_pg:gn_pop":312,
    "qs_pg:name":"Ban\u00edn",
    "qs_pg:name_adm0":"\u010cesk\u00e1 republika",
    "qs_pg:name_adm1":"Pardubick\u00fd kraj",
    "qs_pg:photos_9k":1,
    "qs_pg:photos_9r":1,
    "qs_pg:photos_all":2,
    "qs_pg:photos_sr":0,
    "qs_pg:pop_sr":2,
    "qs_pg:qs_pg_placetype":"locality",
    "qs_pg:qs_pg_placetype_gp":"Town",
    "qs_pg:woe_adm0":23424810,
    "woe:adm0_id":23424810,
    "woe:name_adm0":"\u010cesk\u00e1 republika",
    "woe:name_adm1":"Pardubick\u00fd kraj",
    "woe:placetype":"Town",
    "wof:name":"Ban\u00edn",
    "wof:placetype":"locality",
    "wof:population":312
},
  "geometry": {"coordinates":[16.46192,49.66561],"type":"Point"}
}