{
  "type": "Feature",
  "properties": {
    "gn:admin1_code":"84.0",
    "gn:admin2_code":"0712",
    "gn:asciiname":"Olsany",
    "gn:country_code":"CZ",
    "gn:dem":215,
    "gn:feature_class":"P",
    "gn:feature_code":"PPL",
    "gn:name":"Ol\u0161any",
    "gn:population":0,
    "gn:timezone":"Europe/Prague",
    "iso:country":"CZ",
    "name:und_x_variant":[
        "Olschan"
    ],
    "wof:name":"Olsany",
    "wof:placetype":"locality"
},
  "geometry": {"coordinates":[17.16494,49.53635],"type":"Point"}
}