{
  "type": "Feature",
  "properties": {
    "gn:admin1_code":"82.0",
    "gn:admin2_code":"0525",
    "gn:asciiname":"Horni Zd'ar",
    "gn:country_code":"CZ",
    "gn:dem":491,
    "gn:feature_class":"P",
    "gn:feature_code":"PPL",
    "gn:name":"Horn\u00ed \u017d\u010f\u00e1r",
    "gn:population":0,
    "gn:timezone":"Europe/Prague",
    "iso:country":"CZ",
    "name:und_x_variant":[
        "Ober-Soor",
        "Horn\u00ed \u017d\u010f\u00e1r"
    ],
    "wof:name":"Horni Zd'ar",
    "wof:placetype":"locality"
},
  "geometry": {"coordinates":[15.87528,50.49017],"type":"Point"}
}