{
  "type": "Feature",
  "properties": {
    "gn:gn_country":"CZ",
    "gn:gn_fcode":"PPL",
    "gn:gn_pop":705,
    "gn:population":705,
    "iso:country":"CZ",
    "name:cze_x_preferred":[
        "B\u011bl\u00e1"
    ],
    "name:dut_x_preferred":[
        "B\u011bl\u00e1"
    ],
    "name:eng_x_preferred":[
        "B\u011bl\u00e1"
    ],
    "name:epo_x_preferred":[
        "B\u011bl\u00e1"
    ],
    "name:hun_x_preferred":[
        "B\u011bl\u00e1"
    ],
    "name:ita_x_preferred":[
        "B\u011bl\u00e1"
    ],
    "name:may_x_preferred":[
        "B\u011bl\u00e1"
    ],
    "name:pol_x_preferred":[
        "Bia\u0142a"
    ],
    "name:por_x_preferred":[
        "B\u011bl\u00e1"
    ],
    "name:rup_x_preferred":[
        "B\u011bl\u00e1"
    ],
    "name:slo_x_preferred":[
        "B\u011bl\u00e1"
    ],
    "name:srp_x_preferred":[
        "\u0411\u0458\u0435\u043b\u0430"
    ],
    "name:swe_x_preferred":[
        "Bel\u00e1"
    ],
    "name:vie_x_preferred":[
        "B\u011bl\u00e1"
    ],
    "qs_pg:aaroncc":"CZ",
    "qs_pg:gn_country":"CZ",
    "qs_pg:gn_fcode":"PPL",
    "qs_pg:gn_pop":705,
    "qs_pg:name":"B\u011bl\u00e1",
    "qs_pg:name_adm0":"\u010cesk\u00e1 republika",
    "qs_pg:name_adm1":"Moravskoslezsk\u00fd kraj",
    "qs_pg:photos_9r":0,
    "qs_pg:photos_sr":0,
    "qs_pg:pop_sr":2,
    "qs_pg:qs_pg_placetype":"locality",
    "qs_pg:qs_pg_placetype_gp":"Town",
    "qs_pg:woe_adm0":23424810,
    "woe:adm0_id":23424810,
    "woe:name_adm0":"\u010cesk\u00e1 republika",
    "woe:name_adm1":"Moravskoslezsk\u00fd kraj",
    "woe:placetype":"Town",
    "wof:name":"B\u011bl\u00e1",
    "wof:placetype":"locality",
    "wof:population":705
},
  "geometry": {"coordinates":[18.14489,49.97233],"type":"Point"}
}