{
  "type": "Feature",
  "properties": {
    "gn:admin1_code":"84.0",
    "gn:admin2_code":"0712",
    "gn:asciiname":"Ranosov",
    "gn:country_code":"CZ",
    "gn:dem":506,
    "gn:feature_class":"P",
    "gn:feature_code":"PPL",
    "gn:name":"Rano\u0161ov",
    "gn:population":0,
    "gn:timezone":"Europe/Prague",
    "iso:country":"CZ",
    "name:und_x_variant":[
        "Prusinowitz",
        "Rano\u0161ov"
    ],
    "wof:name":"Ranosov",
    "wof:placetype":"locality"
},
  "geometry": {"coordinates":[17.54572000000001,49.58869],"type":"Point"}
}