{
  "type": "Feature",
  "properties": {
    "gn:gn_country":"CZ",
    "gn:gn_fcode":"PPL",
    "gn:gn_pop":228,
    "gn:population":228,
    "iso:country":"CZ",
    "name:ces_x_preferred":[
        "Horn\u00ed \u0158asnice"
    ],
    "name:deu_x_preferred":[
        "Horn\u00ed \u0158asnice"
    ],
    "name:eng_x_preferred":[
        "Horn\u00ed \u0158asnice"
    ],
    "name:fra_x_preferred":[
        "Horn\u00ed \u0158asnice"
    ],
    "name:hun_x_preferred":[
        "Horn\u00ed \u0158asnice"
    ],
    "name:ita_x_preferred":[
        "Horn\u00ed \u0158asnice"
    ],
    "name:msa_x_preferred":[
        "Horn\u00ed \u0158asnice"
    ],
    "name:nld_x_preferred":[
        "Horn\u00ed \u0158asnice"
    ],
    "name:pol_x_preferred":[
        "Horn\u00ed \u0158asnice"
    ],
    "name:por_x_preferred":[
        "Horn\u00ed \u0158asnice"
    ],
    "name:rup_x_preferred":[
        "Horn\u00ed \u0158asnice"
    ],
    "name:slk_x_preferred":[
        "Horn\u00ed \u0158asnice"
    ],
    "name:srp_x_preferred":[
        "\u0425\u043e\u0440\u045a\u0438 \u0420\u0430\u0441\u045a\u0438\u0446\u0435"
    ],
    "name:swe_x_preferred":[
        "Horn\u00ed \u0158asnice"
    ],
    "name:unk_x_variant":[
        "Bernsdorf pod Smrkem"
    ],
    "name:vie_x_preferred":[
        "Horn\u00ed \u0158asnice"
    ],
    "qs_pg:aaroncc":"CZ",
    "qs_pg:gn_country":"CZ",
    "qs_pg:gn_fcode":"PPL",
    "qs_pg:gn_pop":228,
    "qs_pg:name":"Horn\u00ed \u0158asnice",
    "qs_pg:name_adm0":"\u010cesk\u00e1 republika",
    "qs_pg:name_adm1":"Libereck\u00fd kraj",
    "qs_pg:photos_9k":1,
    "qs_pg:photos_9r":1,
    "qs_pg:photos_all":1,
    "qs_pg:photos_sr":0,
    "qs_pg:pop_sr":2,
    "qs_pg:qs_pg_placetype":"locality",
    "qs_pg:qs_pg_placetype_gp":"Town",
    "qs_pg:woe_adm0":23424810,
    "woe:adm0_id":23424810,
    "woe:name_adm0":"\u010cesk\u00e1 republika",
    "woe:name_adm1":"Libereck\u00fd kraj",
    "woe:placetype":"Town",
    "wof:name":"Horn\u00ed \u0158asnice",
    "wof:placetype":"locality",
    "wof:population":228
},
  "geometry": {"coordinates":[15.20149,50.96546],"type":"Point"}
}