{
  "type": "Feature",
  "properties": {
    "gn:admin1_code":"79.0",
    "gn:admin2_code":"0313",
    "gn:asciiname":"Lipova",
    "gn:country_code":"CZ",
    "gn:dem":539,
    "gn:feature_class":"P",
    "gn:feature_code":"PPL",
    "gn:name":"Lipov\u00e1",
    "gn:population":0,
    "gn:timezone":"Europe/Prague",
    "iso:country":"CZ",
    "wof:name":"Lipova",
    "wof:placetype":"locality"
},
  "geometry": {"coordinates":[15.38886,49.12623],"type":"Point"}
}