{
  "type": "Feature",
  "properties": {
    "gn:admin1_code":"79.0",
    "gn:admin2_code":"0313",
    "gn:asciiname":"Lipova",
    "gn:country_code":"CZ",
    "gn:dem":539,
    "gn:feature_class":"P",
    "gn:feature_code":"PPL",
    "gn:name":"Lipov\u00e1",
    "gn:population":0,
    "gn:timezone":"Europe/Prague",
    "iso:country":"CZ",
    "name:ceb_x_preferred":[
        "Lipova"
    ],
    "name:deu_x_preferred":[
        "Lipova"
    ],
    "name:fra_x_preferred":[
        "Lipova"
    ],
    "name:hrv_x_preferred":[
        "Lipova"
    ],
    "name:nld_x_preferred":[
        "Lipova"
    ],
    "name:ron_x_preferred":[
        "Lipova"
    ],
    "name:srp_x_preferred":[
        "\u041b\u0438\u043f\u043e\u0432\u0430"
    ],
    "name:swe_x_preferred":[
        "Lipova"
    ],
    "name:tur_x_preferred":[
        "Lipova"
    ],
    "name:ukr_x_preferred":[
        "\u041b\u0456\u043f\u043e\u0432\u0430"
    ],
    "wof:name":"Lipova",
    "wof:placetype":"locality"
},
  "geometry": {"coordinates":[15.38886,49.12623],"type":"Point"}
}