{
  "type": "Feature",
  "properties": {
    "gn:admin1_code":"88.0",
    "gn:admin2_code":"020B",
    "gn:asciiname":"Josefovo Udoli",
    "gn:country_code":"CZ",
    "gn:dem":353,
    "gn:feature_class":"P",
    "gn:feature_code":"PPL",
    "gn:name":"Josefovo \u00dadol\u00ed",
    "gn:population":0,
    "gn:timezone":"Europe/Prague",
    "iso:country":"CZ",
    "wof:name":"Josefovo Udoli",
    "wof:placetype":"locality"
},
  "geometry": {"coordinates":[14.21095,49.77438],"type":"Point"}
}