{
  "type": "Feature",
  "properties": {
    "iso:country":"CZ",
    "name:ara_x_preferred":[
        "\u0647\u0648\u062f\u0648\u0646\u064a\u0646"
    ],
    "name:bul_x_preferred":[
        "\u0425\u043e\u0434\u043e\u043d\u0438\u043d"
    ],
    "name:ces_x_preferred":[
        "Hodon\u00edn"
    ],
    "name:deu_x_preferred":[
        "Hodon\u00edn"
    ],
    "name:epo_x_preferred":[
        "Hodon\u00edn"
    ],
    "name:eus_x_preferred":[
        "Hodon\u00edn"
    ],
    "name:fas_x_preferred":[
        "\u0647\u062f\u0646\u06cc\u0646"
    ],
    "name:fra_x_preferred":[
        "Hodon\u00edn"
    ],
    "name:gla_x_preferred":[
        "Hodon\u00edn"
    ],
    "name:hun_x_preferred":[
        "Hodon\u00edn"
    ],
    "name:ind_x_preferred":[
        "Hodon\u00edn"
    ],
    "name:ita_x_preferred":[
        "Hodon\u00edn"
    ],
    "name:jpn_x_preferred":[
        "\u30db\u30c9\u30cb\u30fc\u30f3"
    ],
    "name:kor_x_preferred":[
        "\ud638\ub3c4\ub2cc"
    ],
    "name:lav_x_preferred":[
        "Hodon\u012bna"
    ],
    "name:lit_x_preferred":[
        "Hodonynas"
    ],
    "name:msa_x_preferred":[
        "Hodon\u00edn"
    ],
    "name:nld_x_preferred":[
        "Hodon\u00edn"
    ],
    "name:pol_x_preferred":[
        "Hodon\u00edn"
    ],
    "name:por_x_preferred":[
        "Hodon\u00edn"
    ],
    "name:ron_x_preferred":[
        "Hodon\u00edn"
    ],
    "name:rus_x_preferred":[
        "\u0413\u043e\u0434\u043e\u043d\u0438\u043d"
    ],
    "name:sco_x_preferred":[
        "Hodon\u00edn"
    ],
    "name:slk_x_preferred":[
        "Hodon\u00edn"
    ],
    "name:spa_x_preferred":[
        "H\u00f3donin"
    ],
    "name:srp_x_preferred":[
        "\u0425\u043e\u0434\u043e\u045a\u0438\u043d"
    ],
    "name:swe_x_preferred":[
        "Hodon\u00edn"
    ],
    "name:tgk_x_preferred":[
        "\u0413\u043e\u0434\u043e\u043d\u0438\u043d"
    ],
    "name:tur_x_preferred":[
        "Hodon\u00edn"
    ],
    "name:ukr_x_preferred":[
        "\u0413\u043e\u0434\u043e\u043d\u0456\u043d"
    ],
    "name:vie_x_preferred":[
        "Hodon\u00edn"
    ],
    "name:war_x_preferred":[
        "Hodon\u00edn"
    ],
    "name:zho_x_preferred":[
        "\u970d\u591a\u5b81"
    ],
    "qs_pg:aaroncc":"CZ",
    "qs_pg:name":"Hodon\u00edn",
    "qs_pg:name_adm0":"\u010cesk\u00e1 republika",
    "qs_pg:name_adm1":"Jihomoravsk\u00fd kraj",
    "qs_pg:photos":198,
    "qs_pg:photos_1k":40,
    "qs_pg:photos_9k":1,
    "qs_pg:photos_9r":5,
    "qs_pg:photos_all":330,
    "qs_pg:photos_sr":4,
    "qs_pg:pop_sr":0,
    "qs_pg:qs_pg_placetype":"localadmin",
    "qs_pg:qs_pg_placetype_gp":"LocalAdmin",
    "qs_pg:woe_adm0":23424810,
    "woe:adm0_id":23424810,
    "woe:name_adm0":"\u010cesk\u00e1 republika",
    "woe:name_adm1":"Jihomoravsk\u00fd kraj",
    "woe:placetype":"LocalAdmin",
    "wof:name":"Hodon\u00edn",
    "wof:placetype":"localadmin"
},
  "geometry": {"coordinates":[17.109575,48.862032],"type":"Point"}
}