{
  "type": "Feature",
  "properties": {
    "iso:country":"CZ",
    "name:azb_x_preferred":[
        "\u067e\u0644\u0648\u0647\u0648\u0641 \u0698\u062f\u0627\u0631"
    ],
    "name:ces_x_preferred":[
        "Pluh\u016fv \u017d\u010f\u00e1r"
    ],
    "name:deu_x_preferred":[
        "Pluh\u016fv \u017d\u010f\u00e1r"
    ],
    "name:eus_x_preferred":[
        "Pluh\u016fv \u017d\u010f\u00e1r"
    ],
    "name:fas_x_preferred":[
        "\u067e\u0644\u0648\u0647\u0648\u0641 \u0698\u062f\u0627\u0631"
    ],
    "name:fra_x_preferred":[
        "Pluh\u016fv \u017d\u010f\u00e1r"
    ],
    "name:hun_x_preferred":[
        "Pluh\u016fv \u017d\u010f\u00e1r"
    ],
    "name:ita_x_preferred":[
        "Pluh\u016fv \u017d\u010f\u00e1r"
    ],
    "name:msa_x_preferred":[
        "Pluh\u016fv \u017d\u010f\u00e1r"
    ],
    "name:nld_x_preferred":[
        "Pluh\u016fv \u017d\u010f\u00e1r"
    ],
    "name:pol_x_preferred":[
        "Pluh\u016fv \u017d\u010f\u00e1r"
    ],
    "name:por_x_preferred":[
        "Pluh\u016fv \u017d\u010f\u00e1r"
    ],
    "name:slk_x_preferred":[
        "Pluh\u016fv \u017d\u010f\u00e1r"
    ],
    "name:spa_x_preferred":[
        "Pluh\u016fv \u017d\u010f\u00e1r"
    ],
    "name:srp_x_preferred":[
        "\u041f\u043b\u0443\u0445\u0443\u0432 \u0416\u0434\u0458\u0430\u0440"
    ],
    "name:vie_x_preferred":[
        "Pluh\u016fv \u017d\u010f\u00e1r"
    ],
    "qs_pg:aaroncc":"CZ",
    "qs_pg:name":"Pluh\u016fv \u017d\u010f\u00e1r",
    "qs_pg:name_adm0":"\u010cesk\u00e1 republika",
    "qs_pg:name_adm1":"Jiho\u010desk\u00fd kraj",
    "qs_pg:photos":1,
    "qs_pg:photos_1k":1,
    "qs_pg:photos_9k":1,
    "qs_pg:photos_9r":4,
    "qs_pg:photos_all":244,
    "qs_pg:photos_sr":1,
    "qs_pg:pop_sr":0,
    "qs_pg:qs_pg_placetype":"localadmin",
    "qs_pg:qs_pg_placetype_gp":"LocalAdmin",
    "qs_pg:woe_adm0":23424810,
    "woe:adm0_id":23424810,
    "woe:name_adm0":"\u010cesk\u00e1 republika",
    "woe:name_adm1":"Jiho\u010desk\u00fd kraj",
    "woe:placetype":"LocalAdmin",
    "wof:name":"Pluh\u016fv \u017d\u010f\u00e1r",
    "wof:placetype":"localadmin"
},
  "geometry": {"coordinates":[14.884441,49.247676],"type":"Point"}
}