{
  "type": "Feature",
  "properties": {
    "gn:admin1_code":"82.0",
    "gn:admin2_code":"0525",
    "gn:asciiname":"Horni Debrne",
    "gn:country_code":"CZ",
    "gn:dem":334,
    "gn:feature_class":"P",
    "gn:feature_code":"PPL",
    "gn:name":"Horn\u00ed Debrn\u00e9",
    "gn:population":0,
    "gn:timezone":"Europe/Prague",
    "iso:country":"CZ",
    "name:und_x_variant":[
        "Schurzer Dobernei",
        "Horn\u00ed Debrn\u00e9"
    ],
    "wof:name":"Horni Debrne",
    "wof:placetype":"locality"
},
  "geometry": {"coordinates":[15.74046,50.49687],"type":"Point"}
}