{
  "type": "Feature",
  "properties": {
    "gn:admin1_code":"79.0",
    "gn:admin2_code":"0314",
    "gn:asciiname":"Podoli Druhe",
    "gn:cc2":"CZ",
    "gn:country_code":"CZ",
    "gn:dem":464,
    "gn:feature_class":"P",
    "gn:feature_code":"PPL",
    "gn:name":"Podol\u00ed Druh\u00e9",
    "gn:population":0,
    "gn:timezone":"Europe/Prague",
    "iso:country":"CZ",
    "name:und_x_variant":[
        "Podol\u00ed II"
    ],
    "wof:name":"Podoli Druhe",
    "wof:placetype":"locality"
},
  "geometry": {"coordinates":[14.0425,49.37069],"type":"Point"}
}