{
  "type": "Feature",
  "properties": {
    "gn:admin1_code":"83.0",
    "gn:admin2_code":"0514",
    "gn:asciiname":"Nova Ves",
    "gn:country_code":"CZ",
    "gn:dem":441,
    "gn:feature_class":"P",
    "gn:feature_code":"PPL",
    "gn:name":"Nov\u00e1 Ves",
    "gn:population":0,
    "gn:timezone":"Europe/Prague",
    "iso:country":"CZ",
    "name:hrv_x_preferred":[
        "Nova Ves"
    ],
    "wof:name":"Nova Ves",
    "wof:placetype":"locality"
},
  "geometry": {"coordinates":[15.47237,50.64446],"type":"Point"}
}