{
  "type": "Feature",
  "properties": {
    "gn:country":"CZ",
    "gn:fcode":"PPL",
    "gn:population":93,
    "iso:country":"CZ",
    "name:azb_x_preferred":[
        "\u062a\u0645\u0634\u0648\u0627\u0631"
    ],
    "name:ces_x_preferred":[
        "Teme\u0161v\u00e1r"
    ],
    "name:deu_x_preferred":[
        "Teme\u0161v\u00e1r"
    ],
    "name:eng_x_preferred":[
        "Teme\u0161v\u00e1r"
    ],
    "name:epo_x_preferred":[
        "Teme\u0161v\u00e1r"
    ],
    "name:eus_x_preferred":[
        "Teme\u0161v\u00e1r"
    ],
    "name:fas_x_preferred":[
        "\u062a\u0645\u0634\u0648\u0627\u0631"
    ],
    "name:fra_x_preferred":[
        "Teme\u0161v\u00e1r"
    ],
    "name:hun_x_preferred":[
        "Teme\u0161v\u00e1r"
    ],
    "name:ita_x_preferred":[
        "Teme\u0161v\u00e1r"
    ],
    "name:msa_x_preferred":[
        "Teme\u0161v\u00e1r"
    ],
    "name:nan_x_preferred":[
        "Teme\u0161v\u00e1r"
    ],
    "name:nld_x_preferred":[
        "Teme\u0161v\u00e1r"
    ],
    "name:por_x_preferred":[
        "Teme\u0161v\u00e1r"
    ],
    "name:rup_x_preferred":[
        "Teme\u0161v\u00e1r"
    ],
    "name:slk_x_preferred":[
        "Teme\u0161v\u00e1r"
    ],
    "name:spa_x_preferred":[
        "Teme\u0161v\u00e1r"
    ],
    "name:srp_x_preferred":[
        "\u0422\u0435\u043c\u0435\u0448\u0432\u0430\u0440"
    ],
    "name:vie_x_preferred":[
        "Teme\u0161v\u00e1r"
    ],
    "qs_pg:aaroncc":"CZ",
    "qs_pg:gn_country":"CZ",
    "qs_pg:gn_fcode":"PPL",
    "qs_pg:gn_pop":93,
    "qs_pg:name":"Teme\u0161v\u00e1r",
    "qs_pg:name_adm0":"\u010cesk\u00e1 republika",
    "qs_pg:name_adm1":"Jiho\u010desk\u00fd kraj",
    "qs_pg:photos_9k":1,
    "qs_pg:photos_9r":1,
    "qs_pg:photos_all":1,
    "qs_pg:photos_sr":0,
    "qs_pg:pop_sr":1,
    "qs_pg:qs_pg_placetype":"locality",
    "qs_pg:qs_pg_placetype_gp":"Town",
    "qs_pg:woe_adm0":23424810,
    "woe:adm0_id":23424810,
    "woe:name_adm0":"\u010cesk\u00e1 republika",
    "woe:name_adm1":"Jiho\u010desk\u00fd kraj",
    "woe:placetype":"Town",
    "wof:name":"Teme\u0161v\u00e1r",
    "wof:placetype":"locality",
    "wof:population":93
},
  "geometry": {"coordinates":[14.26353,49.35638],"type":"Point"}
}