{
  "type": "Feature",
  "properties": {
    "gn:admin1_code":"87",
    "gn:admin2_code":"0327",
    "gn:asciiname":"Valcha",
    "gn:country_code":"CZ",
    "gn:dem":454,
    "gn:feature_class":"P",
    "gn:feature_code":"PPL",
    "gn:name":"Valcha",
    "gn:population":0,
    "gn:timezone":"Europe/Prague",
    "iso:country":"CZ",
    "name:und_x_variant":[
        "Walk",
        "Valcha"
    ],
    "wof:name":"Valcha",
    "wof:placetype":"locality"
},
  "geometry": {"coordinates":[12.77976,49.65031],"type":"Point"}
}