{
  "type": "Feature",
  "properties": {
    "gn:country":"CZ",
    "gn:fcode":"PPL",
    "gn:population":224,
    "iso:country":"CZ",
    "name:azb_x_preferred":[
        "\u0633\u0627\u062f\u06a9"
    ],
    "name:ceb_x_preferred":[
        "S\u00e1dek"
    ],
    "name:ces_x_preferred":[
        "S\u00e1dek"
    ],
    "name:deu_x_preferred":[
        "S\u00e1dek"
    ],
    "name:eng_x_preferred":[
        "S\u00e1dek"
    ],
    "name:eus_x_preferred":[
        "S\u00e1dek"
    ],
    "name:fas_x_preferred":[
        "\u0633\u0627\u062f\u06a9"
    ],
    "name:fra_x_preferred":[
        "S\u00e1dek"
    ],
    "name:hun_x_preferred":[
        "S\u00e1dek"
    ],
    "name:ita_x_preferred":[
        "S\u00e1dek"
    ],
    "name:msa_x_preferred":[
        "S\u00e1dek"
    ],
    "name:nan_x_preferred":[
        "S\u00e1dek"
    ],
    "name:nld_x_preferred":[
        "S\u00e1dek"
    ],
    "name:por_x_preferred":[
        "S\u00e1dek"
    ],
    "name:rup_x_preferred":[
        "S\u00e1dek"
    ],
    "name:slk_x_preferred":[
        "S\u00e1dek"
    ],
    "name:spa_x_preferred":[
        "S\u00e1dek"
    ],
    "name:srp_x_preferred":[
        "\u0421\u0430\u0434\u0435\u043a"
    ],
    "name:swe_x_preferred":[
        "S\u00e1dek"
    ],
    "name:urd_x_preferred":[
        "\u0633\u062f\u06a9"
    ],
    "name:vie_x_preferred":[
        "S\u00e1dek"
    ],
    "qs_pg:aaroncc":"CZ",
    "qs_pg:gn_country":"CZ",
    "qs_pg:gn_fcode":"PPL",
    "qs_pg:gn_pop":224,
    "qs_pg:name":"S\u00e1dek",
    "qs_pg:name_adm0":"\u010cesk\u00e1 republika",
    "qs_pg:name_adm1":"St\u0159edo\u010desk\u00fd kraj",
    "qs_pg:photos_9r":0,
    "qs_pg:photos_sr":0,
    "qs_pg:pop_sr":2,
    "qs_pg:qs_pg_placetype":"locality",
    "qs_pg:qs_pg_placetype_gp":"Town",
    "qs_pg:woe_adm0":23424810,
    "woe:adm0_id":23424810,
    "woe:name_adm0":"\u010cesk\u00e1 republika",
    "woe:name_adm1":"St\u0159edo\u010desk\u00fd kraj",
    "woe:placetype":"Town",
    "wof:name":"S\u00e1dek",
    "wof:placetype":"locality",
    "wof:population":224
},
  "geometry": {"coordinates":[13.98312,49.73321],"type":"Point"}
}