{
  "type": "Feature",
  "properties": {
    "gn:admin1_code":"89.0",
    "gn:admin2_code":"0423",
    "gn:asciiname":"Mystice",
    "gn:cc2":"CZ",
    "gn:country_code":"CZ",
    "gn:dem":309,
    "gn:feature_class":"P",
    "gn:feature_code":"PPL",
    "gn:name":"My\u0161tice",
    "gn:population":0,
    "gn:timezone":"Europe/Prague",
    "iso:country":"CZ",
    "name:und_x_variant":[
        "Michzen"
    ],
    "wof:name":"Mystice",
    "wof:placetype":"locality"
},
  "geometry": {"coordinates":[14.18369,50.57223],"type":"Point"}
}