{
  "type": "Feature",
  "properties": {
    "gn:country":"CZ",
    "gn:fcode":"PPL",
    "gn:population":316,
    "iso:country":"CZ",
    "name:azb_x_preferred":[
        "\u062c\u0628\u0627\u0646\u0648\u0641"
    ],
    "name:ceb_x_preferred":[
        "D\u017eb\u00e1nov"
    ],
    "name:ces_x_preferred":[
        "D\u017eb\u00e1nov"
    ],
    "name:deu_x_preferred":[
        "D\u017eb\u00e1nov"
    ],
    "name:eng_x_preferred":[
        "D\u017eb\u00e1nov"
    ],
    "name:epo_x_preferred":[
        "D\u017eb\u00e1nov"
    ],
    "name:eus_x_preferred":[
        "D\u017eb\u00e1nov"
    ],
    "name:fas_x_preferred":[
        "\u062c\u0628\u0627\u0646\u0648\u0641"
    ],
    "name:fra_x_preferred":[
        "D\u017eb\u00e1nov"
    ],
    "name:hun_x_preferred":[
        "D\u017eb\u00e1nov"
    ],
    "name:ita_x_preferred":[
        "D\u017eb\u00e1nov"
    ],
    "name:msa_x_preferred":[
        "D\u017eb\u00e1nov"
    ],
    "name:nan_x_preferred":[
        "D\u017eb\u00e1nov"
    ],
    "name:nld_x_preferred":[
        "D\u017eb\u00e1nov"
    ],
    "name:por_x_preferred":[
        "D\u017eb\u00e1nov"
    ],
    "name:rup_x_preferred":[
        "D\u017eb\u00e1nov"
    ],
    "name:slk_x_preferred":[
        "D\u017eb\u00e1nov"
    ],
    "name:spa_x_preferred":[
        "D\u017eb\u00e1nov"
    ],
    "name:srp_x_preferred":[
        "\u040f\u0431\u0430\u043d\u043e\u0432"
    ],
    "name:swe_x_preferred":[
        "D\u017eb\u00e1nov"
    ],
    "name:vie_x_preferred":[
        "D\u017eb\u00e1nov"
    ],
    "qs_pg:aaroncc":"CZ",
    "qs_pg:gn_country":"CZ",
    "qs_pg:gn_fcode":"PPL",
    "qs_pg:gn_pop":316,
    "qs_pg:name":"D\u017eb\u00e1nov",
    "qs_pg:photos_9r":0,
    "qs_pg:photos_sr":0,
    "qs_pg:pop_sr":2,
    "qs_pg:qs_pg_placetype":"locality",
    "wof:name":"D\u017eb\u00e1nov",
    "wof:placetype":"locality",
    "wof:population":316
},
  "geometry": {"coordinates":[16.1595,49.91636],"type":"Point"}
}