{
  "type": "Feature",
  "properties": {
    "gn:admin1_code":"83.0",
    "gn:admin2_code":"0511",
    "gn:asciiname":"Hermanicky",
    "gn:country_code":"CZ",
    "gn:dem":258,
    "gn:feature_class":"P",
    "gn:feature_code":"PPL",
    "gn:name":"He\u0159mani\u010dky",
    "gn:population":0,
    "gn:timezone":"Europe/Prague",
    "iso:country":"CZ",
    "name:und_x_variant":[
        "He\u0159manice",
        "Hermsdorf",
        "He\u0159mani\u010dky"
    ],
    "wof:name":"Hermanicky",
    "wof:placetype":"locality"
},
  "geometry": {"coordinates":[14.6115,50.66292],"type":"Point"}
}