{
  "type": "Feature",
  "properties": {
    "gn:admin1_code":"86.0",
    "gn:admin2_code":"0531",
    "gn:asciiname":"Brezovice",
    "gn:country_code":"CZ",
    "gn:dem":259,
    "gn:feature_class":"P",
    "gn:feature_code":"PPL",
    "gn:name":"B\u0159ezovice",
    "gn:population":0,
    "gn:timezone":"Europe/Prague",
    "iso:country":"CZ",
    "wof:name":"Brezovice",
    "wof:placetype":"locality"
},
  "geometry": {"coordinates":[15.96837,49.95748],"type":"Point"}
}