{
  "type": "Feature",
  "properties": {
    "gn:admin1_code":"86.0",
    "gn:admin2_code":"0531",
    "gn:asciiname":"Brezovice",
    "gn:country_code":"CZ",
    "gn:dem":259,
    "gn:feature_class":"P",
    "gn:feature_code":"PPL",
    "gn:name":"B\u0159ezovice",
    "gn:population":0,
    "gn:timezone":"Europe/Prague",
    "iso:country":"CZ",
    "name:bos_x_preferred":[
        "Brezovice"
    ],
    "name:ceb_x_preferred":[
        "Brezovice"
    ],
    "name:fra_x_preferred":[
        "Brezovice"
    ],
    "name:hrv_x_preferred":[
        "Brezovice"
    ],
    "name:nld_x_preferred":[
        "Brezovice"
    ],
    "name:slv_x_preferred":[
        "Brezovice"
    ],
    "name:srp_x_preferred":[
        "\u0411\u0440\u0435\u0437\u043e\u0432\u0438\u0446\u0435"
    ],
    "name:swe_x_preferred":[
        "Brezovice"
    ],
    "wof:name":"Brezovice",
    "wof:placetype":"locality"
},
  "geometry": {"coordinates":[15.96837,49.95748],"type":"Point"}
}