{
  "type": "Feature",
  "properties": {
    "gn:admin1_code":"83",
    "gn:admin2_code":"0511",
    "gn:asciiname":"Srni",
    "gn:country_code":"CZ",
    "gn:dem":275,
    "gn:feature_class":"P",
    "gn:feature_code":"PPL",
    "gn:name":"Srn\u00ed",
    "gn:population":0,
    "gn:timezone":"Europe/Prague",
    "iso:country":"CZ",
    "name:und_x_variant":[
        "Rehd\u00f6rfel",
        "Srn\u00ed"
    ],
    "wof:name":"Srni",
    "wof:placetype":"locality"
},
  "geometry": {"coordinates":[14.58332,50.63801],"type":"Point"}
}