{
  "type": "Feature",
  "properties": {
    "gn:admin1_code":"86.0",
    "gn:admin2_code":"0533",
    "gn:asciiname":"Lazany",
    "gn:country_code":"CZ",
    "gn:dem":360,
    "gn:feature_class":"P",
    "gn:feature_code":"PPL",
    "gn:name":"La\u017eany",
    "gn:population":0,
    "gn:timezone":"Europe/Prague",
    "iso:country":"CZ",
    "name:deu_x_preferred":[
        "Lazany"
    ],
    "name:epo_x_preferred":[
        "Lazany"
    ],
    "name:eus_x_preferred":[
        "Lazany"
    ],
    "name:hun_x_preferred":[
        "Lazany"
    ],
    "name:slk_x_preferred":[
        "Lazany"
    ],
    "wof:name":"Lazany",
    "wof:placetype":"locality"
},
  "geometry": {"coordinates":[16.24285,49.86162],"type":"Point"}
}