{
  "type": "Feature",
  "properties": {
    "gn:gn_country":"CZ",
    "gn:gn_fcode":"PPL",
    "gn:gn_pop":294,
    "gn:population":294,
    "iso:country":"CZ",
    "name:azb_x_preferred":[
        "\u062f\u0644\u0648\u0648\u0647\u06cc \u0648\u06cc\u0632\u062f"
    ],
    "name:ceb_x_preferred":[
        "Dlouh\u00fd \u00dajezd"
    ],
    "name:ces_x_preferred":[
        "Dlouh\u00fd \u00dajezd"
    ],
    "name:deu_x_preferred":[
        "Dlouh\u00fd \u00dajezd"
    ],
    "name:eus_x_preferred":[
        "Dlouh\u00fd \u00dajezd"
    ],
    "name:fas_x_preferred":[
        "\u062f\u0644\u0648\u0648\u0647\u06cc \u0648\u06cc\u0632\u062f"
    ],
    "name:fra_x_preferred":[
        "Dlouh\u00fd \u00dajezd"
    ],
    "name:hun_x_preferred":[
        "Dlouh\u00fd \u00dajezd"
    ],
    "name:ita_x_preferred":[
        "Dlouh\u00fd \u00dajezd"
    ],
    "name:msa_x_preferred":[
        "Dlouh\u00fd \u00dajezd"
    ],
    "name:nld_x_preferred":[
        "Dlouh\u00fd \u00dajezd"
    ],
    "name:por_x_preferred":[
        "Dlouh\u00fd \u00dajezd"
    ],
    "name:slk_x_preferred":[
        "Dlouh\u00fd \u00dajezd"
    ],
    "name:spa_x_preferred":[
        "Dlouh\u00fd \u00dajezd"
    ],
    "name:srp_x_preferred":[
        "\u0414\u043b\u043e\u0443\u0445\u0438 \u0423\u0458\u0435\u0437\u0434"
    ],
    "name:swe_x_preferred":[
        "Dlouh\u00fd \u00dajezd"
    ],
    "name:unk_x_variant":[
        "Langend\u00f6rflas"
    ],
    "name:vie_x_preferred":[
        "Dlouh\u00fd \u00dajezd"
    ],
    "qs_pg:aaroncc":"CZ",
    "qs_pg:gn_country":"CZ",
    "qs_pg:gn_fcode":"PPL",
    "qs_pg:gn_pop":294,
    "qs_pg:name":"Dlouh\u00fd \u00dajezd",
    "qs_pg:name_adm0":"\u010cesk\u00e1 republika",
    "qs_pg:name_adm1":"Plze\u0148sk\u00fd kraj",
    "qs_pg:photos":1,
    "qs_pg:photos_1k":1,
    "qs_pg:photos_9k":1,
    "qs_pg:photos_9r":1,
    "qs_pg:photos_all":1,
    "qs_pg:photos_sr":1,
    "qs_pg:pop_sr":2,
    "qs_pg:qs_pg_placetype":"localadmin",
    "qs_pg:qs_pg_placetype_gp":"LocalAdmin",
    "qs_pg:woe_adm0":23424810,
    "woe:adm0_id":23424810,
    "woe:name_adm0":"\u010cesk\u00e1 republika",
    "woe:name_adm1":"Plze\u0148sk\u00fd kraj",
    "woe:placetype":"LocalAdmin",
    "wof:name":"Dlouh\u00fd \u00dajezd",
    "wof:placetype":"localadmin",
    "wof:population":294
},
  "geometry": {"coordinates":[12.62847,49.76829],"type":"Point"}
}