{
  "type": "Feature",
  "properties": {
    "gn:admin1_code":"88.0",
    "gn:admin2_code":"020A",
    "gn:asciiname":"Chouzava",
    "gn:country_code":"CZ",
    "gn:dem":434,
    "gn:feature_class":"P",
    "gn:feature_code":"PPL",
    "gn:name":"Chouzav\u00e1",
    "gn:population":0,
    "gn:timezone":"Europe/Prague",
    "iso:country":"CZ",
    "wof:name":"Chouzava",
    "wof:placetype":"locality"
},
  "geometry": {"coordinates":[14.22599,49.83795],"type":"Point"}
}