{
  "type": "Feature",
  "properties": {
    "gn:country":"CZ",
    "gn:fcode":"PPL",
    "gn:population":201,
    "iso:country":"CZ",
    "name:azb_x_preferred":[
        "\u0633\u0644\u0627\u0648\u06cc\u062a\u06cc\u0646"
    ],
    "name:ceb_x_preferred":[
        "Slavet\u00edn"
    ],
    "name:ces_x_preferred":[
        "Slav\u011bt\u00edn"
    ],
    "name:deu_x_preferred":[
        "Slav\u011bt\u00edn u Litovle"
    ],
    "name:eng_x_preferred":[
        "Slav\u011bt\u00edn"
    ],
    "name:epo_x_preferred":[
        "Slav\u011bt\u00edn"
    ],
    "name:eus_x_preferred":[
        "Slav\u011bt\u00edn"
    ],
    "name:fas_x_preferred":[
        "\u0633\u0644\u0627\u0648\u06cc\u062a\u06cc\u0646"
    ],
    "name:fra_x_preferred":[
        "Slav\u011bt\u00edn"
    ],
    "name:hun_x_preferred":[
        "Slav\u011bt\u00edn"
    ],
    "name:ita_x_preferred":[
        "Slav\u011bt\u00edn"
    ],
    "name:msa_x_preferred":[
        "Slav\u011bt\u00edn"
    ],
    "name:nan_x_preferred":[
        "Slav\u011bt\u00edn"
    ],
    "name:nld_x_preferred":[
        "Slav\u011bt\u00edn"
    ],
    "name:pol_x_preferred":[
        "Slav\u011bt\u00edn"
    ],
    "name:por_x_preferred":[
        "Slav\u011bt\u00edn"
    ],
    "name:rup_x_preferred":[
        "Slav\u011bt\u00edn"
    ],
    "name:slk_x_preferred":[
        "Slav\u011bt\u00edn"
    ],
    "name:spa_x_preferred":[
        "Slav\u011bt\u00edn"
    ],
    "name:srp_x_preferred":[
        "\u0421\u043b\u0430\u0432\u0458\u0435\u0442\u0438\u043d"
    ],
    "name:swe_x_preferred":[
        "Slavet\u00edn"
    ],
    "name:vie_x_preferred":[
        "Slav\u011bt\u00edn"
    ],
    "qs_pg:aaroncc":"CZ",
    "qs_pg:gn_country":"CZ",
    "qs_pg:gn_fcode":"PPL",
    "qs_pg:gn_pop":201,
    "qs_pg:name":"Slav\u011bt\u00edn",
    "qs_pg:name_adm0":"\u010cesk\u00e1 republika",
    "qs_pg:name_adm1":"Olomouck\u00fd kraj",
    "qs_pg:photos_9r":0,
    "qs_pg:photos_sr":0,
    "qs_pg:pop_sr":2,
    "qs_pg:qs_pg_placetype":"locality",
    "qs_pg:qs_pg_placetype_gp":"Town",
    "qs_pg:woe_adm0":23424810,
    "woe:adm0_id":23424810,
    "woe:name_adm0":"\u010cesk\u00e1 republika",
    "woe:name_adm1":"Olomouck\u00fd kraj",
    "woe:placetype":"Town",
    "wof:name":"Slav\u011bt\u00edn",
    "wof:placetype":"locality",
    "wof:population":201
},
  "geometry": {"coordinates":[16.96507,49.67274],"type":"Point"}
}