{
  "type": "Feature",
  "properties": {
    "gn:admin1_code":"85.0",
    "gn:admin2_code":"0801",
    "gn:asciiname":"Dubnice",
    "gn:country_code":"CZ",
    "gn:dem":484,
    "gn:feature_class":"P",
    "gn:feature_code":"PPL",
    "gn:name":"Dubnice",
    "gn:population":0,
    "gn:timezone":"Europe/Prague",
    "iso:country":"CZ",
    "name:und_x_variant":[
        "Taubnitz",
        "Dubnice"
    ],
    "wof:name":"Dubnice",
    "wof:placetype":"locality"
},
  "geometry": {"coordinates":[17.64039,50.04115],"type":"Point"}
}