{
  "type": "Feature",
  "properties": {
    "gn:admin1_code":"85.0",
    "gn:admin2_code":"0801",
    "gn:asciiname":"Dubnice",
    "gn:country_code":"CZ",
    "gn:dem":484,
    "gn:feature_class":"P",
    "gn:feature_code":"PPL",
    "gn:name":"Dubnice",
    "gn:population":0,
    "gn:timezone":"Europe/Prague",
    "iso:country":"CZ",
    "name:azb_x_preferred":[
        "\u062f\u0648\u0628\u0646\u06cc\u062a\u0633\u0647"
    ],
    "name:ceb_x_preferred":[
        "Dubnice"
    ],
    "name:ces_x_preferred":[
        "Dubnice"
    ],
    "name:eus_x_preferred":[
        "Dubnice"
    ],
    "name:fas_x_preferred":[
        "\u062f\u0648\u0628\u0646\u06cc\u062a\u0633\u0647"
    ],
    "name:fra_x_preferred":[
        "Dubnice"
    ],
    "name:hun_x_preferred":[
        "Dubnice"
    ],
    "name:ita_x_preferred":[
        "Dubnice"
    ],
    "name:msa_x_preferred":[
        "Dubnice"
    ],
    "name:nld_x_preferred":[
        "Dubnice"
    ],
    "name:pol_x_preferred":[
        "Dubnice"
    ],
    "name:por_x_preferred":[
        "Dubnice"
    ],
    "name:slk_x_preferred":[
        "Dubnice"
    ],
    "name:spa_x_preferred":[
        "Dubnice"
    ],
    "name:srp_x_preferred":[
        "\u0414\u0443\u0431\u045a\u0438\u0446\u0435"
    ],
    "name:swe_x_preferred":[
        "Dubnice"
    ],
    "name:und_x_variant":[
        "Taubnitz"
    ],
    "name:vie_x_preferred":[
        "Dubnice"
    ],
    "wof:name":"Dubnice",
    "wof:placetype":"locality"
},
  "geometry": {"coordinates":[17.64039,50.04115],"type":"Point"}
}