{
  "type": "Feature",
  "properties": {
    "gn:country":"CZ",
    "gn:fcode":"PPL",
    "gn:population":676,
    "iso:country":"CZ",
    "name:ceb_x_preferred":[
        "K\u0159ivokl\u00e1t"
    ],
    "name:ces_x_preferred":[
        "K\u0159ivokl\u00e1t"
    ],
    "name:deu_x_preferred":[
        "P\u00fcrglitz"
    ],
    "name:deu_x_variant":[
        "K\u0159ivokl\u00e1t"
    ],
    "name:eng_x_preferred":[
        "K\u0159ivokl\u00e1t"
    ],
    "name:epo_x_preferred":[
        "K\u0159ivokl\u00e1t"
    ],
    "name:eus_x_preferred":[
        "K\u0159ivokl\u00e1t"
    ],
    "name:fas_x_preferred":[
        "\u06a9\u0631\u06cc\u0648\u0648\u06a9\u0644\u0627\u062a"
    ],
    "name:fra_x_preferred":[
        "K\u0159ivokl\u00e1t"
    ],
    "name:hun_x_preferred":[
        "K\u0159ivokl\u00e1t"
    ],
    "name:ita_x_preferred":[
        "K\u0159ivokl\u00e1t"
    ],
    "name:msa_x_preferred":[
        "K\u0159ivokl\u00e1t"
    ],
    "name:nan_x_preferred":[
        "K\u0159ivokl\u00e1t"
    ],
    "name:nld_x_preferred":[
        "K\u0159ivokl\u00e1t"
    ],
    "name:pol_x_preferred":[
        "K\u0159ivokl\u00e1t"
    ],
    "name:por_x_preferred":[
        "K\u0159ivokl\u00e1t"
    ],
    "name:rup_x_preferred":[
        "K\u0159ivokl\u00e1t"
    ],
    "name:rus_x_preferred":[
        "\u041a\u0440\u0448\u0438\u0432\u043e\u043a\u043b\u0430\u0442"
    ],
    "name:slk_x_preferred":[
        "K\u0159ivokl\u00e1t"
    ],
    "name:spa_x_preferred":[
        "K\u0159ivokl\u00e1t"
    ],
    "name:srp_x_preferred":[
        "\u041a\u0440\u0438\u0432\u043e\u043a\u043b\u0430\u0442"
    ],
    "name:swe_x_preferred":[
        "K\u0159ivokl\u00e1t"
    ],
    "name:vie_x_preferred":[
        "K\u0159ivokl\u00e1t"
    ],
    "name:zho_x_preferred":[
        "\u514b\u91cc\u6c83\u514b\u62c9"
    ],
    "qs_pg:aaroncc":"CZ",
    "qs_pg:gn_country":"CZ",
    "qs_pg:gn_fcode":"PPL",
    "qs_pg:gn_pop":676,
    "qs_pg:name":"K\u0159ivokl\u00e1t",
    "qs_pg:name_adm0":"\u010cesk\u00e1 republika",
    "qs_pg:name_adm1":"St\u0159edo\u010desk\u00fd kraj",
    "qs_pg:photos":487,
    "qs_pg:photos_1k":99,
    "qs_pg:photos_9k":2,
    "qs_pg:photos_9r":5,
    "qs_pg:photos_all":487,
    "qs_pg:photos_sr":7,
    "qs_pg:pop_sr":2,
    "qs_pg:qs_pg_placetype":"locality",
    "qs_pg:qs_pg_placetype_gp":"Town",
    "qs_pg:woe_adm0":23424810,
    "woe:adm0_id":23424810,
    "woe:name_adm0":"\u010cesk\u00e1 republika",
    "woe:name_adm1":"St\u0159edo\u010desk\u00fd kraj",
    "woe:placetype":"Town",
    "wof:name":"K\u0159ivokl\u00e1t",
    "wof:placetype":"locality",
    "wof:population":676
},
  "geometry": {"coordinates":[13.87036,50.03785],"type":"Point"}
}