{
  "type": "Feature",
  "properties": {
    "gn:gn_country":"CZ",
    "gn:gn_fcode":"PPL",
    "gn:gn_pop":463,
    "gn:population":463,
    "iso:country":"CZ",
    "name:cze_x_preferred":[
        "Chot\u00fd\u0161any"
    ],
    "name:dut_x_preferred":[
        "Chot\u00fd\u0161any"
    ],
    "name:eng_x_preferred":[
        "Chot\u00fd\u0161any"
    ],
    "name:fre_x_preferred":[
        "Chot\u00fd\u0161any"
    ],
    "name:hun_x_preferred":[
        "Chot\u00fd\u0161any"
    ],
    "name:ita_x_preferred":[
        "Chot\u00fd\u0161any"
    ],
    "name:may_x_preferred":[
        "Chot\u00fd\u0161any"
    ],
    "name:per_x_preferred":[
        "\u062e\u0648\u062a\u06cc\u0634\u0627\u0646\u06cc"
    ],
    "name:pol_x_preferred":[
        "Chot\u00fd\u0161any"
    ],
    "name:por_x_preferred":[
        "Chot\u00fd\u0161any"
    ],
    "name:slo_x_preferred":[
        "Chot\u00fd\u0161any"
    ],
    "name:srp_x_preferred":[
        "\u0425\u043e\u0442\u0438\u0448\u0430\u043d\u0438"
    ],
    "name:swe_x_preferred":[
        "Chot\u00fd\u0161any"
    ],
    "name:unk_x_variant":[
        "Chot\u00fd\u010dany"
    ],
    "name:vie_x_preferred":[
        "Chot\u00fd\u0161any"
    ],
    "qs_pg:aaroncc":"CZ",
    "qs_pg:gn_country":"CZ",
    "qs_pg:gn_fcode":"PPL",
    "qs_pg:gn_pop":463,
    "qs_pg:name":"Chot\u00fd\u0161any",
    "qs_pg:name_adm0":"\u010cesk\u00e1 republika",
    "qs_pg:name_adm1":"St\u0159edo\u010desk\u00fd kraj",
    "qs_pg:photos_9r":0,
    "qs_pg:photos_sr":0,
    "qs_pg:pop_sr":2,
    "qs_pg:qs_pg_placetype":"locality",
    "qs_pg:qs_pg_placetype_gp":"Town",
    "qs_pg:woe_adm0":23424810,
    "woe:adm0_id":23424810,
    "woe:name_adm0":"\u010cesk\u00e1 republika",
    "woe:name_adm1":"St\u0159edo\u010desk\u00fd kraj",
    "woe:placetype":"Town",
    "wof:name":"Chot\u00fd\u0161any",
    "wof:placetype":"locality",
    "wof:population":463
},
  "geometry": {"coordinates":[14.81458,49.7441],"type":"Point"}
}