{
  "type": "Feature",
  "properties": {
    "iso:country":"CZ",
    "name:ces_x_preferred":[
        "Bystrc"
    ],
    "name:eng_x_preferred":[
        "Brno-Bystrc"
    ],
    "name:fra_x_preferred":[
        "Bystrc"
    ],
    "name:pol_x_preferred":[
        "Bystrc"
    ],
    "name:slk_x_preferred":[
        "Brno-Bystrc"
    ],
    "qs_pg:aaroncc":"CZ",
    "qs_pg:name":"Brno-Bystrc",
    "qs_pg:name_adm0":"\u010cesk\u00e1 republika",
    "qs_pg:name_adm1":"Jihomoravsk\u00fd kraj",
    "qs_pg:photos":1642,
    "qs_pg:photos_1k":333,
    "qs_pg:photos_9k":7,
    "qs_pg:photos_9r":8,
    "qs_pg:photos_all":1642,
    "qs_pg:photos_sr":13,
    "qs_pg:pop_sr":0,
    "qs_pg:qs_pg_placetype":"locality",
    "qs_pg:qs_pg_placetype_gp":"Town",
    "qs_pg:woe_adm0":23424810,
    "woe:adm0_id":23424810,
    "woe:name_adm0":"\u010cesk\u00e1 republika",
    "woe:name_adm1":"Jihomoravsk\u00fd kraj",
    "woe:placetype":"Town",
    "wof:name":"Brno-Bystrc",
    "wof:placetype":"locality"
},
  "geometry": {"coordinates":[16.516656,49.229999],"type":"Point"}
}