{
  "type": "Feature",
  "properties": {
    "gn:gn_country":"CZ",
    "gn:gn_fcode":"PPL",
    "gn:gn_pop":638,
    "gn:population":638,
    "iso:country":"CZ",
    "name:cze_x_preferred":[
        "Huzov\u00e1"
    ],
    "name:dut_x_preferred":[
        "Huzov\u00e1"
    ],
    "name:eng_x_preferred":[
        "Huzov\u00e1"
    ],
    "name:fre_x_preferred":[
        "Huzov\u00e1"
    ],
    "name:ger_x_preferred":[
        "Huzov\u00e1"
    ],
    "name:hun_x_preferred":[
        "Huzov\u00e1"
    ],
    "name:ita_x_preferred":[
        "Huzov\u00e1"
    ],
    "name:may_x_preferred":[
        "Huzov\u00e1"
    ],
    "name:per_x_preferred":[
        "\u0647\u0648\u0632\u0648\u0648\u0627"
    ],
    "name:pol_x_preferred":[
        "Huzov\u00e1"
    ],
    "name:por_x_preferred":[
        "Huzov\u00e1"
    ],
    "name:slo_x_preferred":[
        "Huzov\u00e1"
    ],
    "name:srp_x_preferred":[
        "\u0425\u0443\u0437\u043e\u0432\u0430"
    ],
    "name:swe_x_preferred":[
        "H\u016fzov\u00e1"
    ],
    "name:unk_x_variant":[
        "N\u011bmeck\u00e1 H\u00fazov\u00e1"
    ],
    "name:vie_x_preferred":[
        "Huzov\u00e1"
    ],
    "qs_pg:aaroncc":"CZ",
    "qs_pg:gn_country":"CZ",
    "qs_pg:gn_fcode":"PPL",
    "qs_pg:gn_pop":638,
    "qs_pg:name":"Huzov\u00e1",
    "qs_pg:name_adm0":"\u010cesk\u00e1 republika",
    "qs_pg:name_adm1":"Moravskoslezsk\u00fd kraj",
    "qs_pg:photos_9k":1,
    "qs_pg:photos_9r":1,
    "qs_pg:photos_all":9,
    "qs_pg:photos_sr":0,
    "qs_pg:pop_sr":2,
    "qs_pg:qs_pg_placetype":"locality",
    "qs_pg:qs_pg_placetype_gp":"Town",
    "qs_pg:woe_adm0":23424810,
    "woe:adm0_id":23424810,
    "woe:name_adm0":"\u010cesk\u00e1 republika",
    "woe:name_adm1":"Moravskoslezsk\u00fd kraj",
    "woe:placetype":"Town",
    "wof:name":"Huzov\u00e1",
    "wof:placetype":"locality",
    "wof:population":638
},
  "geometry": {"coordinates":[17.29796,49.81997],"type":"Point"}
}