{
  "type": "Feature",
  "properties": {
    "gn:admin1_code":"84",
    "gn:admin2_code":"0714",
    "gn:asciiname":"Zbrasov",
    "gn:country_code":"CZ",
    "gn:dem":320,
    "gn:feature_class":"P",
    "gn:feature_code":"PPL",
    "gn:name":"Zbra\u0161ov",
    "gn:population":0,
    "gn:timezone":"Europe/Prague",
    "iso:country":"CZ",
    "wof:name":"Zbrasov",
    "wof:placetype":"locality"
},
  "geometry": {"coordinates":[17.75,49.53333],"type":"Point"}
}