{
  "type": "Feature",
  "properties": {
    "gn:admin1_code":"89",
    "gn:admin2_code":"0424",
    "gn:asciiname":"Stachov",
    "gn:country_code":"CZ",
    "gn:dem":315,
    "gn:feature_class":"P",
    "gn:feature_code":"PPL",
    "gn:name":"Stachov",
    "gn:population":0,
    "gn:timezone":"Europe/Prague",
    "iso:country":"CZ",
    "wof:name":"Stachov",
    "wof:placetype":"locality"
},
  "geometry": {"coordinates":[13.49327,50.21855],"type":"Point"}
}