{
  "type": "Feature",
  "properties": {
    "gn:admin1_code":"87.0",
    "gn:admin2_code":"0324",
    "gn:asciiname":"Hradist'any",
    "gn:country_code":"CZ",
    "gn:dem":400,
    "gn:feature_class":"P",
    "gn:feature_code":"PPL",
    "gn:name":"Hradi\u0161\u0165any",
    "gn:population":0,
    "gn:timezone":"Europe/Prague",
    "iso:country":"CZ",
    "name:und_x_variant":[
        "Radelstein",
        "Hradi\u0161\u0165any"
    ],
    "wof:name":"Hradist'any",
    "wof:placetype":"locality"
},
  "geometry": {"coordinates":[13.03099,49.6315],"type":"Point"}
}