{
  "type": "Feature",
  "properties": {
    "gn:country":"CZ",
    "gn:fcode":"PPL",
    "gn:population":856,
    "iso:country":"CZ",
    "name:cat_x_preferred":[
        "Vysok\u00e9 Vesel\u00ed"
    ],
    "name:ceb_x_preferred":[
        "Vysok\u00e9 Vesel\u00ed"
    ],
    "name:ces_x_preferred":[
        "Vysok\u00e9 Vesel\u00ed"
    ],
    "name:deu_x_preferred":[
        "Vysok\u00e9 Vesel\u00ed"
    ],
    "name:ell_x_preferred":[
        "\u0392\u03c5\u03b6\u03cc\u03ba\u03b5 \u0392\u03b5\u03c3\u03ad\u03bb\u03b9"
    ],
    "name:eng_x_preferred":[
        "Vysok\u00e9 Vesel\u00ed"
    ],
    "name:est_x_preferred":[
        "Vysok\u00e9 Vesel\u00ed"
    ],
    "name:eus_x_preferred":[
        "Vysok\u00e9 Vesel\u00ed"
    ],
    "name:fas_x_preferred":[
        "\u0648\u06cc\u0633\u0648\u06a9\u0647 \u0648\u0633\u0644\u06cc"
    ],
    "name:fra_x_preferred":[
        "Vysok\u00e9 Vesel\u00ed"
    ],
    "name:gle_x_preferred":[
        "Vysok\u00e9 Vesel\u00ed"
    ],
    "name:hun_x_preferred":[
        "Vysok\u00e9 Vesel\u00ed"
    ],
    "name:ita_x_preferred":[
        "Vysok\u00e9 Vesel\u00ed"
    ],
    "name:lmo_x_preferred":[
        "Vysok\u00e9 Vesel\u00ed"
    ],
    "name:msa_x_preferred":[
        "Vysok\u00e9 Vesel\u00ed"
    ],
    "name:nan_x_preferred":[
        "Vysok\u00e9 Vesel\u00ed"
    ],
    "name:nld_x_preferred":[
        "Vysok\u00e9 Vesel\u00ed"
    ],
    "name:pol_x_preferred":[
        "Vysok\u00e9 Vesel\u00ed"
    ],
    "name:por_x_preferred":[
        "Vysok\u00e9 Vesel\u00ed"
    ],
    "name:rup_x_preferred":[
        "Vysok\u00e9 Vesel\u00ed"
    ],
    "name:rus_x_preferred":[
        "\u0412\u044b\u0441\u043e\u043a\u0435 \u0412\u0435\u0441\u0435\u043b\u0438"
    ],
    "name:slk_x_preferred":[
        "Vysok\u00e9 Vesel\u00ed"
    ],
    "name:spa_x_preferred":[
        "Vysok\u00e9 Vesel\u00ed"
    ],
    "name:srp_x_preferred":[
        "\u0412\u0438\u0441\u043e\u043a\u0435 \u0412\u0435\u0441\u0435\u043b\u0438"
    ],
    "name:swe_x_preferred":[
        "Vysok\u00e9 Vesel\u00ed"
    ],
    "name:tat_x_preferred":[
        "\u0412\u0438\u0441\u043e\u043a\u0435-\u0412\u0435\u0441\u0435\u043b\u0438"
    ],
    "name:und_x_variant":[
        "Hoch-Wesley"
    ],
    "name:vie_x_preferred":[
        "Vysok\u00e9 Vesel\u00ed"
    ],
    "name:zho_x_preferred":[
        "\u4e0a\u97cb\u585e\u5229"
    ],
    "qs_pg:aaroncc":"CZ",
    "qs_pg:gn_country":"CZ",
    "qs_pg:gn_fcode":"PPL",
    "qs_pg:gn_pop":856,
    "qs_pg:name":"Vysok\u00e9 Vesel\u00ed",
    "qs_pg:name_adm0":"\u010cesk\u00e1 republika",
    "qs_pg:name_adm1":"Kr\u00e1lov\u00e9hradeck\u00fd kraj",
    "qs_pg:photos_9k":1,
    "qs_pg:photos_9r":1,
    "qs_pg:photos_all":1,
    "qs_pg:photos_sr":0,
    "qs_pg:pop_sr":2,
    "qs_pg:qs_pg_placetype":"locality",
    "qs_pg:qs_pg_placetype_gp":"Town",
    "qs_pg:woe_adm0":23424810,
    "woe:adm0_id":23424810,
    "woe:name_adm0":"\u010cesk\u00e1 republika",
    "woe:name_adm1":"Kr\u00e1lov\u00e9hradeck\u00fd kraj",
    "woe:placetype":"Town",
    "wof:name":"Vysok\u00e9 Vesel\u00ed",
    "wof:placetype":"locality",
    "wof:population":856
},
  "geometry": {"coordinates":[15.43631,50.33096],"type":"Point"}
}