{
  "type": "Feature",
  "properties": {
    "gn:gn_country":"CZ",
    "gn:gn_fcode":"PPL",
    "gn:gn_pop":856,
    "gn:population":856,
    "iso:country":"CZ",
    "name:chi_x_preferred":[
        "\u4e0a\u97cb\u585e\u5229"
    ],
    "name:cze_x_preferred":[
        "Vysok\u00e9 Vesel\u00ed"
    ],
    "name:dut_x_preferred":[
        "Vysok\u00e9 Vesel\u00ed"
    ],
    "name:eng_x_preferred":[
        "Vysok\u00e9 Vesel\u00ed"
    ],
    "name:fre_x_preferred":[
        "Vysok\u00e9 Vesel\u00ed"
    ],
    "name:ger_x_preferred":[
        "Vysok\u00e9 Vesel\u00ed"
    ],
    "name:hun_x_preferred":[
        "Vysok\u00e9 Vesel\u00ed"
    ],
    "name:ita_x_preferred":[
        "Vysok\u00e9 Vesel\u00ed"
    ],
    "name:may_x_preferred":[
        "Vysok\u00e9 Vesel\u00ed"
    ],
    "name:nan_x_preferred":[
        "Vysok\u00e9 Vesel\u00ed"
    ],
    "name:per_x_preferred":[
        "\u0648\u06cc\u0633\u0648\u06a9\u0647 \u0648\u0633\u0644\u06cc"
    ],
    "name:pol_x_preferred":[
        "Vysok\u00e9 Vesel\u00ed"
    ],
    "name:por_x_preferred":[
        "Vysok\u00e9 Vesel\u00ed"
    ],
    "name:rup_x_preferred":[
        "Vysok\u00e9 Vesel\u00ed"
    ],
    "name:slo_x_preferred":[
        "Vysok\u00e9 Vesel\u00ed"
    ],
    "name:srp_x_preferred":[
        "\u0412\u0438\u0441\u043e\u043a\u0435 \u0412\u0435\u0441\u0435\u043b\u0438"
    ],
    "name:swe_x_preferred":[
        "Vysok\u00e9 Vesel\u00ed"
    ],
    "name:tat_x_preferred":[
        "\u0412\u0438\u0441\u043e\u043a\u0435-\u0412\u0435\u0441\u0435\u043b\u0438"
    ],
    "name:unk_x_variant":[
        "Hoch-Wesley"
    ],
    "name:vie_x_preferred":[
        "Vysok\u00e9 Vesel\u00ed"
    ],
    "qs_pg:aaroncc":"CZ",
    "qs_pg:gn_country":"CZ",
    "qs_pg:gn_fcode":"PPL",
    "qs_pg:gn_pop":856,
    "qs_pg:name":"Vysok\u00e9 Vesel\u00ed",
    "qs_pg:name_adm0":"\u010cesk\u00e1 republika",
    "qs_pg:name_adm1":"Kr\u00e1lov\u00e9hradeck\u00fd kraj",
    "qs_pg:photos_9k":1,
    "qs_pg:photos_9r":1,
    "qs_pg:photos_all":1,
    "qs_pg:photos_sr":0,
    "qs_pg:pop_sr":2,
    "qs_pg:qs_pg_placetype":"locality",
    "qs_pg:qs_pg_placetype_gp":"Town",
    "qs_pg:woe_adm0":23424810,
    "woe:adm0_id":23424810,
    "woe:name_adm0":"\u010cesk\u00e1 republika",
    "woe:name_adm1":"Kr\u00e1lov\u00e9hradeck\u00fd kraj",
    "woe:placetype":"Town",
    "wof:name":"Vysok\u00e9 Vesel\u00ed",
    "wof:placetype":"locality",
    "wof:population":856
},
  "geometry": {"coordinates":[15.43631,50.33096],"type":"Point"}
}