{
  "type": "Feature",
  "properties": {
    "gn:admin1_code":"88",
    "gn:admin2_code":"0203",
    "gn:asciiname":"Vasirov",
    "gn:country_code":"CZ",
    "gn:dem":427,
    "gn:feature_class":"P",
    "gn:feature_code":"PPL",
    "gn:name":"Va\u0161\u00edrov",
    "gn:population":0,
    "gn:timezone":"Europe/Prague",
    "iso:country":"CZ",
    "name:und_x_variant":[
        "Va\u0161\u00edrov"
    ],
    "wof:name":"Vasirov",
    "wof:placetype":"locality"
},
  "geometry": {"coordinates":[13.95,50.13333],"type":"Point"}
}