{
  "type": "Feature",
  "properties": {
    "gn:admin1_code":"79.0",
    "gn:admin2_code":"0312",
    "gn:asciiname":"Horni Svince",
    "gn:country_code":"CZ",
    "gn:dem":540,
    "gn:feature_class":"P",
    "gn:feature_code":"PPL",
    "gn:name":"Horn\u00ed Svince",
    "gn:population":0,
    "gn:timezone":"Europe/Prague",
    "iso:country":"CZ",
    "wof:name":"Horni Svince",
    "wof:placetype":"locality"
},
  "geometry": {"coordinates":[14.44091,48.84443],"type":"Point"}
}