{
  "type": "Feature",
  "properties": {
    "gn:admin1_code":"87.0",
    "gn:admin2_code":"0327",
    "gn:asciiname":"Labut'",
    "gn:country_code":"CZ",
    "gn:dem":525,
    "gn:feature_class":"P",
    "gn:feature_code":"PPL",
    "gn:name":"Labu\u0165",
    "gn:population":0,
    "gn:timezone":"Europe/Prague",
    "iso:country":"CZ",
    "name:und_x_variant":[
        "Labant",
        "Labu\u0165"
    ],
    "wof:name":"Labut'",
    "wof:placetype":"locality"
},
  "geometry": {"coordinates":[12.66972,49.71026],"type":"Point"}
}