{
  "type": "Feature",
  "properties": {
    "gn:admin1_code":"79.0",
    "gn:admin2_code":"0313",
    "gn:asciiname":"Pilar",
    "gn:country_code":"CZ",
    "gn:dem":442,
    "gn:feature_class":"P",
    "gn:feature_code":"PPL",
    "gn:name":"Pila\u0159",
    "gn:population":0,
    "gn:timezone":"Europe/Prague",
    "iso:country":"CZ",
    "wof:name":"Pilar",
    "wof:placetype":"locality"
},
  "geometry": {"coordinates":[14.87969,48.94624],"type":"Point"}
}