{
  "type": "Feature",
  "properties": {
    "gn:admin1_code":"89",
    "gn:admin2_code":"0423",
    "gn:asciiname":"Zelechovice",
    "gn:country_code":"CZ",
    "gn:dem":172,
    "gn:feature_class":"P",
    "gn:feature_code":"PPL",
    "gn:name":"\u017delechovice",
    "gn:population":0,
    "gn:timezone":"Europe/Prague",
    "iso:country":"CZ",
    "wof:name":"Zelechovice",
    "wof:placetype":"locality"
},
  "geometry": {"coordinates":[14.04205,50.47621],"type":"Point"}
}