{
  "type": "Feature",
  "properties": {
    "gn:admin1_code":"80.0",
    "gn:admin2_code":"0615",
    "gn:asciiname":"Kobylnice",
    "gn:country_code":"CZ",
    "gn:dem":559,
    "gn:feature_class":"P",
    "gn:feature_code":"PPL",
    "gn:name":"Kobylnice",
    "gn:population":0,
    "gn:timezone":"Europe/Prague",
    "iso:country":"CZ",
    "name:ceb_x_preferred":[
        "Kobylnice"
    ],
    "name:ces_x_preferred":[
        "Kobylnice"
    ],
    "name:deu_x_preferred":[
        "Kobylnice"
    ],
    "name:epo_x_preferred":[
        "Kobylnice"
    ],
    "name:eus_x_preferred":[
        "Kobylnice"
    ],
    "name:fra_x_preferred":[
        "Kobylnice"
    ],
    "name:ita_x_preferred":[
        "Kobylnice"
    ],
    "name:nld_x_preferred":[
        "Kobylnice"
    ],
    "name:pol_x_preferred":[
        "Kobylnice"
    ],
    "name:slk_x_preferred":[
        "Kobylnice"
    ],
    "name:srp_x_preferred":[
        "\u041a\u043e\u0431\u0438\u043b\u045a\u0438\u0446\u0435"
    ],
    "name:swe_x_preferred":[
        "Kobylnice"
    ],
    "wof:name":"Kobylnice",
    "wof:placetype":"locality"
},
  "geometry": {"coordinates":[16.33048,49.53583],"type":"Point"}
}