{
  "type": "Feature",
  "properties": {
    "gn:admin1_code":"80.0",
    "gn:admin2_code":"0615",
    "gn:asciiname":"Kobylnice",
    "gn:country_code":"CZ",
    "gn:dem":559,
    "gn:feature_class":"P",
    "gn:feature_code":"PPL",
    "gn:name":"Kobylnice",
    "gn:population":0,
    "gn:timezone":"Europe/Prague",
    "iso:country":"CZ",
    "wof:name":"Kobylnice",
    "wof:placetype":"locality"
},
  "geometry": {"coordinates":[16.33048,49.53583],"type":"Point"}
}