{
  "type": "Feature",
  "properties": {
    "gn:admin1_code":"81",
    "gn:admin2_code":"0411",
    "gn:asciiname":"Svaty Vojtech",
    "gn:country_code":"CZ",
    "gn:dem":695,
    "gn:feature_class":"P",
    "gn:feature_code":"PPL",
    "gn:name":"Svat\u00fd Vojt\u011bch",
    "gn:population":0,
    "gn:timezone":"Europe/Prague",
    "iso:country":"CZ",
    "name:und_x_variant":[
        "Sankt Adalbert",
        "Svat\u00fd Vojt\u011bch"
    ],
    "wof:name":"Svaty Vojtech",
    "wof:placetype":"locality"
},
  "geometry": {"coordinates":[12.83333,49.95],"type":"Point"}
}