{
  "type": "Feature",
  "properties": {
    "gn:admin1_code":"89",
    "gn:admin2_code":"0427",
    "gn:asciiname":"Strekov",
    "gn:country_code":"CZ",
    "gn:dem":216,
    "gn:feature_class":"P",
    "gn:feature_code":"PPL",
    "gn:name":"St\u0159ekov",
    "gn:population":0,
    "gn:timezone":"Europe/Prague",
    "iso:country":"CZ",
    "name:cat_x_preferred":[
        "Strekov"
    ],
    "name:deu_x_preferred":[
        "Strekov"
    ],
    "name:epo_x_preferred":[
        "Strekov"
    ],
    "name:eus_x_preferred":[
        "Strekov"
    ],
    "name:fra_x_preferred":[
        "Strekov"
    ],
    "name:hun_x_preferred":[
        "K\u00fcrt"
    ],
    "name:ita_x_preferred":[
        "Strekov"
    ],
    "name:msa_x_preferred":[
        "Strekov"
    ],
    "name:nld_x_preferred":[
        "Strekov"
    ],
    "name:ron_x_preferred":[
        "Strekov"
    ],
    "name:slk_x_preferred":[
        "Strekov"
    ],
    "name:spa_x_preferred":[
        "Strekov"
    ],
    "name:srp_x_preferred":[
        "\u0421\u0442\u0440\u0435\u043a\u043e\u0432"
    ],
    "name:und_x_variant":[
        "Schreckenstein",
        "St\u0159ekov"
    ],
    "name:war_x_preferred":[
        "Strekov"
    ],
    "wof:name":"Strekov",
    "wof:placetype":"locality"
},
  "geometry": {"coordinates":[14.06196,50.65457],"type":"Point"}
}