{
  "type": "Feature",
  "properties": {
    "gn:admin1_code":"89",
    "gn:admin2_code":"0427",
    "gn:asciiname":"Strekov",
    "gn:country_code":"CZ",
    "gn:dem":216,
    "gn:feature_class":"P",
    "gn:feature_code":"PPL",
    "gn:name":"St\u0159ekov",
    "gn:population":0,
    "gn:timezone":"Europe/Prague",
    "iso:country":"CZ",
    "name:und_x_variant":[
        "Schreckenstein",
        "St\u0159ekov"
    ],
    "wof:name":"Strekov",
    "wof:placetype":"locality"
},
  "geometry": {"coordinates":[14.06196,50.65457],"type":"Point"}
}