{
  "type": "Feature",
  "properties": {
    "gn:admin1_code":"80.0",
    "gn:admin2_code":"0613",
    "gn:asciiname":"Nemojov",
    "gn:country_code":"CZ",
    "gn:dem":566,
    "gn:feature_class":"P",
    "gn:feature_code":"PPL",
    "gn:name":"Nemojov",
    "gn:population":0,
    "gn:timezone":"Europe/Prague",
    "iso:country":"CZ",
    "wof:name":"Nemojov",
    "wof:placetype":"locality"
},
  "geometry": {"coordinates":[15.27215,49.39978],"type":"Point"}
}