{
  "type": "Feature",
  "properties": {
    "gn:admin1_code":"80.0",
    "gn:admin2_code":"0613",
    "gn:asciiname":"Nemojov",
    "gn:country_code":"CZ",
    "gn:dem":566,
    "gn:feature_class":"P",
    "gn:feature_code":"PPL",
    "gn:name":"Nemojov",
    "gn:population":0,
    "gn:timezone":"Europe/Prague",
    "iso:country":"CZ",
    "name:azb_x_preferred":[
        "\u0646\u0645\u0648\u06cc\u0648\u0648"
    ],
    "name:ceb_x_preferred":[
        "Nemojov"
    ],
    "name:ces_x_preferred":[
        "Nemojov"
    ],
    "name:deu_x_preferred":[
        "Nemojov"
    ],
    "name:eus_x_preferred":[
        "Nemojov"
    ],
    "name:fas_x_preferred":[
        "\u0646\u0645\u0648\u06cc\u0648\u0648"
    ],
    "name:fra_x_preferred":[
        "Nemojov"
    ],
    "name:hun_x_preferred":[
        "Nemojov"
    ],
    "name:ita_x_preferred":[
        "Nemojov"
    ],
    "name:msa_x_preferred":[
        "Nemojov"
    ],
    "name:nld_x_preferred":[
        "Nemojov"
    ],
    "name:pol_x_preferred":[
        "Nemojov"
    ],
    "name:por_x_preferred":[
        "Nemojov"
    ],
    "name:slk_x_preferred":[
        "Nemojov"
    ],
    "name:spa_x_preferred":[
        "Nemojov"
    ],
    "name:srp_x_preferred":[
        "\u041d\u0435\u043c\u043e\u0458\u043e\u0432"
    ],
    "name:swe_x_preferred":[
        "Nemojov"
    ],
    "name:vie_x_preferred":[
        "Nemojov"
    ],
    "wof:name":"Nemojov",
    "wof:placetype":"locality"
},
  "geometry": {"coordinates":[15.27215,49.39978],"type":"Point"}
}