{
  "type": "Feature",
  "properties": {
    "gn:admin1_code":"80",
    "gn:admin2_code":"0614",
    "gn:asciiname":"Znatky",
    "gn:country_code":"CZ",
    "gn:dem":420,
    "gn:feature_class":"P",
    "gn:feature_code":"PPL",
    "gn:name":"Z\u0148\u00e1tky",
    "gn:population":0,
    "gn:timezone":"Europe/Prague",
    "iso:country":"CZ",
    "wof:name":"Znatky",
    "wof:placetype":"locality"
},
  "geometry": {"coordinates":[16.14241,49.19188],"type":"Point"}
}