{
  "type": "Feature",
  "properties": {
    "gn:admin1_code":"80.0",
    "gn:admin2_code":"0614",
    "gn:asciiname":"Sasovice",
    "gn:country_code":"CZ",
    "gn:dem":562,
    "gn:feature_class":"P",
    "gn:feature_code":"PPL",
    "gn:name":"\u0160a\u0161ovice",
    "gn:population":0,
    "gn:timezone":"Europe/Prague",
    "iso:country":"CZ",
    "wof:name":"Sasovice",
    "wof:placetype":"locality"
},
  "geometry": {"coordinates":[15.67614,49.1216],"type":"Point"}
}