{
  "type": "Feature",
  "properties": {
    "gn:gn_country":"CZ",
    "gn:gn_fcode":"PPL",
    "gn:gn_pop":571,
    "gn:population":571,
    "iso:country":"CZ",
    "name:bul_x_preferred":[
        "\u0411\u043e\u0437\u043a\u043e\u0432"
    ],
    "name:ces_x_preferred":[
        "Bozkov"
    ],
    "name:deu_x_preferred":[
        "Bozkov"
    ],
    "name:eng_x_preferred":[
        "Bozkov"
    ],
    "name:fas_x_preferred":[
        "\u0628\u0648\u0632\u06a9\u0648\u0648"
    ],
    "name:fra_x_preferred":[
        "Bozkov"
    ],
    "name:hun_x_preferred":[
        "Bozkov"
    ],
    "name:ita_x_preferred":[
        "Bozkov"
    ],
    "name:msa_x_preferred":[
        "Bozkov"
    ],
    "name:nan_x_preferred":[
        "Bozkov"
    ],
    "name:nld_x_preferred":[
        "Bozkov"
    ],
    "name:pol_x_preferred":[
        "Bozkov"
    ],
    "name:por_x_preferred":[
        "Bozkov"
    ],
    "name:rup_x_preferred":[
        "Bozkov"
    ],
    "name:slk_x_preferred":[
        "Bozkov"
    ],
    "name:srp_x_preferred":[
        "\u0411\u043e\u0441\u043a\u043e\u0432"
    ],
    "name:swe_x_preferred":[
        "Bozkov"
    ],
    "name:unk_x_variant":[
        "Boskow"
    ],
    "name:vie_x_preferred":[
        "Bozkov"
    ],
    "qs_pg:aaroncc":"CZ",
    "qs_pg:gn_country":"CZ",
    "qs_pg:gn_fcode":"PPL",
    "qs_pg:gn_pop":571,
    "qs_pg:name":"Bozkov",
    "qs_pg:name_adm0":"\u010cesk\u00e1 republika",
    "qs_pg:name_adm1":"Libereck\u00fd kraj",
    "qs_pg:photos_9k":1,
    "qs_pg:photos_9r":1,
    "qs_pg:photos_all":2,
    "qs_pg:photos_sr":0,
    "qs_pg:pop_sr":2,
    "qs_pg:qs_pg_placetype":"locality",
    "qs_pg:qs_pg_placetype_gp":"Town",
    "qs_pg:woe_adm0":23424810,
    "woe:adm0_id":23424810,
    "woe:name_adm0":"\u010cesk\u00e1 republika",
    "woe:name_adm1":"Libereck\u00fd kraj",
    "woe:placetype":"Town",
    "wof:name":"Bozkov",
    "wof:placetype":"locality",
    "wof:population":571
},
  "geometry": {"coordinates":[15.3371,50.64007],"type":"Point"}
}