{
  "type": "Feature",
  "properties": {
    "gn:gn_country":"CZ",
    "gn:gn_fcode":"PPL",
    "gn:gn_pop":285,
    "gn:population":285,
    "iso:country":"CZ",
    "name:ces_x_preferred":[
        "\u00dadrnice"
    ],
    "name:eng_x_preferred":[
        "\u00dadrnice"
    ],
    "name:fas_x_preferred":[
        "\u0627\u0648\u062f\u0631\u0646\u06cc\u062a\u0633\u0647"
    ],
    "name:fra_x_preferred":[
        "\u00dadrnice"
    ],
    "name:hun_x_preferred":[
        "\u00dadrnice"
    ],
    "name:ita_x_preferred":[
        "\u00dadrnice"
    ],
    "name:msa_x_preferred":[
        "\u00dadrnice"
    ],
    "name:nld_x_preferred":[
        "\u00dadrnice"
    ],
    "name:pol_x_preferred":[
        "\u00dadrnice"
    ],
    "name:por_x_preferred":[
        "\u00dadrnice"
    ],
    "name:slk_x_preferred":[
        "\u00dadrnice"
    ],
    "name:srp_x_preferred":[
        "\u0423\u0434\u0440\u045a\u0438\u0446\u0435"
    ],
    "name:swe_x_preferred":[
        "\u00dadrnice"
    ],
    "name:vie_x_preferred":[
        "\u00dadrnice"
    ],
    "qs_pg:aaroncc":"CZ",
    "qs_pg:gn_country":"CZ",
    "qs_pg:gn_fcode":"PPL",
    "qs_pg:gn_pop":285,
    "qs_pg:name":"\u00dadrnice",
    "qs_pg:name_adm0":"\u010cesk\u00e1 republika",
    "qs_pg:name_adm1":"Kr\u00e1lov\u00e9hradeck\u00fd kraj",
    "qs_pg:photos_9r":0,
    "qs_pg:photos_sr":0,
    "qs_pg:pop_sr":2,
    "qs_pg:qs_pg_placetype":"locality",
    "qs_pg:qs_pg_placetype_gp":"Town",
    "qs_pg:woe_adm0":23424810,
    "woe:adm0_id":23424810,
    "woe:name_adm0":"\u010cesk\u00e1 republika",
    "woe:name_adm1":"Kr\u00e1lov\u00e9hradeck\u00fd kraj",
    "woe:placetype":"Town",
    "wof:name":"\u00dadrnice",
    "wof:placetype":"locality",
    "wof:population":285
},
  "geometry": {"coordinates":[15.26157,50.37438],"type":"Point"}
}