{
  "type": "Feature",
  "properties": {
    "gn:gn_country":"CZ",
    "gn:gn_fcode":"PPL",
    "gn:gn_pop":208,
    "gn:population":208,
    "iso:country":"CZ",
    "name:ces_x_preferred":[
        "\u017dabonosy"
    ],
    "name:cym_x_preferred":[
        "\u017dabonosy"
    ],
    "name:eng_x_preferred":[
        "\u017dabonosy"
    ],
    "name:fas_x_preferred":[
        "\u0698\u0627\u0628\u0648\u0646\u0648\u0633\u06cc"
    ],
    "name:fra_x_preferred":[
        "\u017dabonosy"
    ],
    "name:hun_x_preferred":[
        "\u017dabonosy"
    ],
    "name:ita_x_preferred":[
        "\u017dabonosy"
    ],
    "name:msa_x_preferred":[
        "\u017dabonosy"
    ],
    "name:nld_x_preferred":[
        "\u017dabonosy"
    ],
    "name:pol_x_preferred":[
        "\u017dabonosy"
    ],
    "name:por_x_preferred":[
        "\u017dabonosy"
    ],
    "name:slk_x_preferred":[
        "\u017dabonosy"
    ],
    "name:srp_x_preferred":[
        "\u0416\u0430\u0431\u043e\u043d\u043e\u0441\u0438"
    ],
    "name:swe_x_preferred":[
        "\u017dabonosy"
    ],
    "name:urd_x_preferred":[
        "\u0632\u0627\u0628\u0648\u0646\u0648\u0633\u06d2"
    ],
    "name:vie_x_preferred":[
        "\u017dabonosy"
    ],
    "qs_pg:aaroncc":"CZ",
    "qs_pg:gn_country":"CZ",
    "qs_pg:gn_fcode":"PPL",
    "qs_pg:gn_pop":208,
    "qs_pg:name":"\u017dabonosy",
    "qs_pg:name_adm0":"\u010cesk\u00e1 republika",
    "qs_pg:name_adm1":"St\u0159edo\u010desk\u00fd kraj",
    "qs_pg:photos_9r":0,
    "qs_pg:photos_sr":0,
    "qs_pg:pop_sr":2,
    "qs_pg:qs_pg_placetype":"locality",
    "qs_pg:qs_pg_placetype_gp":"Town",
    "qs_pg:woe_adm0":23424810,
    "woe:adm0_id":23424810,
    "woe:name_adm0":"\u010cesk\u00e1 republika",
    "woe:name_adm1":"St\u0159edo\u010desk\u00fd kraj",
    "woe:placetype":"Town",
    "wof:name":"\u017dabonosy",
    "wof:placetype":"locality",
    "wof:population":208
},
  "geometry": {"coordinates":[15.02721,50.03537],"type":"Point"}
}