{
  "type": "Feature",
  "properties": {
    "gn:admin1_code":"89.0",
    "gn:admin2_code":"0426",
    "gn:asciiname":"Dolni Haj",
    "gn:country_code":"CZ",
    "gn:dem":262,
    "gn:feature_class":"P",
    "gn:feature_code":"PPL",
    "gn:name":"Doln\u00ed H\u00e1j",
    "gn:population":0,
    "gn:timezone":"Europe/Prague",
    "iso:country":"CZ",
    "name:und_x_variant":[
        "Unter-Haan",
        "Doln\u00ed H\u00e1j"
    ],
    "wof:name":"Dolni Haj",
    "wof:placetype":"locality"
},
  "geometry": {"coordinates":[13.71841,50.62704],"type":"Point"}
}