{
  "type": "Feature",
  "properties": {
    "gn:admin1_code":"88",
    "gn:admin2_code":"0201",
    "gn:asciiname":"Zivohost'",
    "gn:cc2":"CZ",
    "gn:country_code":"CZ",
    "gn:dem":286,
    "gn:feature_class":"P",
    "gn:feature_code":"PPL",
    "gn:name":"\u017divoho\u0161\u0165",
    "gn:population":0,
    "gn:timezone":"Europe/Prague",
    "iso:country":"CZ",
    "name:und_x_variant":[
        "Schiwohoscht",
        "\u017diwohonscht",
        "\u017diwohoscht"
    ],
    "wof:name":"Zivohost'",
    "wof:placetype":"locality"
},
  "geometry": {"coordinates":[14.40994,49.75149],"type":"Point"}
}