{
  "type": "Feature",
  "properties": {
    "gn:admin1_code":"81.0",
    "gn:admin2_code":"0412",
    "gn:asciiname":"Nove Tuhnice",
    "gn:country_code":"CZ",
    "gn:dem":407,
    "gn:feature_class":"P",
    "gn:feature_code":"PPL",
    "gn:name":"Nov\u00e9 Tuhnice",
    "gn:population":0,
    "gn:timezone":"Europe/Prague",
    "iso:country":"CZ",
    "name:und_x_variant":[
        "Neu-Donitz",
        "Nov\u00e9 Tuhnice"
    ],
    "wof:name":"Nove Tuhnice",
    "wof:placetype":"locality"
},
  "geometry": {"coordinates":[12.83333,50.21667],"type":"Point"}
}