{
  "type": "Feature",
  "properties": {
    "gn:admin1_code":"81",
    "gn:admin2_code":"0412",
    "gn:asciiname":"Tasovice",
    "gn:country_code":"CZ",
    "gn:dem":658,
    "gn:feature_class":"P",
    "gn:feature_code":"PPL",
    "gn:name":"Ta\u0161ovice",
    "gn:population":0,
    "gn:timezone":"Europe/Prague",
    "iso:country":"CZ",
    "name:und_x_variant":[
        "Taschwitz",
        "Ta\u0161ovice"
    ],
    "wof:name":"Tasovice",
    "wof:placetype":"locality"
},
  "geometry": {"coordinates":[13.00946,50.16686],"type":"Point"}
}