{
  "type": "Feature",
  "properties": {
    "gn:admin1_code":"88.0",
    "gn:admin2_code":"020A",
    "gn:asciiname":"Luka",
    "gn:country_code":"CZ",
    "gn:dem":351,
    "gn:feature_class":"P",
    "gn:feature_code":"PPL",
    "gn:name":"Luka",
    "gn:population":0,
    "gn:timezone":"Europe/Prague",
    "iso:country":"CZ",
    "name:und_x_variant":[
        "Luk",
        "Luka"
    ],
    "wof:name":"Luka",
    "wof:placetype":"locality"
},
  "geometry": {"coordinates":[14.4675,49.87176],"type":"Point"}
}