{
  "type": "Feature",
  "properties": {
    "gn:admin1_code":"87.0",
    "gn:admin2_code":"0322",
    "gn:asciiname":"Sedlo",
    "gn:country_code":"CZ",
    "gn:dem":853,
    "gn:feature_class":"P",
    "gn:feature_code":"PPL",
    "gn:name":"Sedlo",
    "gn:population":0,
    "gn:timezone":"Europe/Prague",
    "iso:country":"CZ",
    "name:und_x_variant":[
        "Sattelberg",
        "Sedlo"
    ],
    "wof:name":"Sedlo",
    "wof:placetype":"locality"
},
  "geometry": {"coordinates":[13.47248,49.10061],"type":"Point"}
}