{
  "type": "Feature",
  "properties": {
    "gn:admin1_code":"86.0",
    "gn:admin2_code":"0534",
    "gn:asciiname":"Mokra Lhota",
    "gn:country_code":"CZ",
    "gn:dem":418,
    "gn:feature_class":"P",
    "gn:feature_code":"PPL",
    "gn:name":"Mokr\u00e1 Lhota",
    "gn:population":0,
    "gn:timezone":"Europe/Prague",
    "iso:country":"CZ",
    "wof:name":"Mokra Lhota",
    "wof:placetype":"locality"
},
  "geometry": {"coordinates":[16.13143,49.85714],"type":"Point"}
}