{
  "type": "Feature",
  "properties": {
    "gn:admin1_code":"84.0",
    "gn:admin2_code":"0715",
    "gn:asciiname":"Rajec",
    "gn:country_code":"CZ",
    "gn:dem":273,
    "gn:feature_class":"P",
    "gn:feature_code":"PPL",
    "gn:name":"R\u00e1jec",
    "gn:population":484,
    "gn:timezone":"Europe/Prague",
    "iso:country":"CZ",
    "wof:name":"Rajec",
    "wof:placetype":"locality",
    "wof:population":484
},
  "geometry": {"coordinates":[16.90296,49.85648],"type":"Point"}
}