{
  "type": "Feature",
  "properties": {
    "gn:admin1_code":"84.0",
    "gn:admin2_code":"0715",
    "gn:asciiname":"Rajec",
    "gn:country_code":"CZ",
    "gn:dem":273,
    "gn:feature_class":"P",
    "gn:feature_code":"PPL",
    "gn:name":"R\u00e1jec",
    "gn:population":484,
    "gn:timezone":"Europe/Prague",
    "iso:country":"CZ",
    "name:azb_x_preferred":[
        "\u0631\u0627\u06cc\u062a\u0633"
    ],
    "name:ceb_x_preferred":[
        "R\u00e1jec"
    ],
    "name:ces_x_preferred":[
        "R\u00e1jec"
    ],
    "name:eus_x_preferred":[
        "R\u00e1jec"
    ],
    "name:fas_x_preferred":[
        "\u0631\u0627\u06cc\u062a\u0633"
    ],
    "name:hun_x_preferred":[
        "R\u00e1jec"
    ],
    "name:ita_x_preferred":[
        "R\u00e1jec"
    ],
    "name:msa_x_preferred":[
        "R\u00e1jec"
    ],
    "name:nld_x_preferred":[
        "R\u00e1jec"
    ],
    "name:pol_x_preferred":[
        "R\u00e1jec"
    ],
    "name:por_x_preferred":[
        "R\u00e1jec"
    ],
    "name:slk_x_preferred":[
        "R\u00e1jec"
    ],
    "name:spa_x_preferred":[
        "R\u00e1jec"
    ],
    "name:srp_x_preferred":[
        "\u0420\u0430\u0458\u0435\u0446"
    ],
    "name:swe_x_preferred":[
        "R\u00e1jec"
    ],
    "name:vie_x_preferred":[
        "R\u00e1jec"
    ],
    "wof:name":"Rajec",
    "wof:placetype":"locality",
    "wof:population":484
},
  "geometry": {"coordinates":[16.90296,49.85648],"type":"Point"}
}