{
  "type": "Feature",
  "properties": {
    "gn:admin1_code":"80.0",
    "gn:admin2_code":"0614",
    "gn:asciiname":"Batouchovice",
    "gn:country_code":"CZ",
    "gn:dem":541,
    "gn:feature_class":"P",
    "gn:feature_code":"PPL",
    "gn:name":"Batouchovice",
    "gn:population":0,
    "gn:timezone":"Europe/Prague",
    "iso:country":"CZ",
    "wof:name":"Batouchovice",
    "wof:placetype":"locality"
},
  "geometry": {"coordinates":[15.90335,49.31183],"type":"Point"}
}