{
  "type": "Feature",
  "properties": {
    "iso:country":"CZ",
    "name:ceb_x_preferred":[
        "Smr\u017eovka"
    ],
    "name:ces_x_preferred":[
        "Smr\u017eovka"
    ],
    "name:deu_x_preferred":[
        "Smr\u017eovka"
    ],
    "name:eus_x_preferred":[
        "Smr\u017eovka"
    ],
    "name:fas_x_preferred":[
        "\u0633\u0645\u0631\u0698\u0648\u0648\u06a9\u0627"
    ],
    "name:fra_x_preferred":[
        "Smr\u017eovka"
    ],
    "name:hun_x_preferred":[
        "Smr\u017eovka"
    ],
    "name:ita_x_preferred":[
        "Smr\u017eovka"
    ],
    "name:msa_x_preferred":[
        "Smr\u017eovka"
    ],
    "name:nld_x_preferred":[
        "Smr\u017eovka"
    ],
    "name:pol_x_preferred":[
        "Smr\u017eovka"
    ],
    "name:por_x_preferred":[
        "Smr\u017eovka"
    ],
    "name:slk_x_preferred":[
        "Smr\u017eovka"
    ],
    "name:spa_x_preferred":[
        "Smr\u017eovka"
    ],
    "name:srp_x_preferred":[
        "\u0421\u043c\u0440\u0436\u043e\u0432\u043a\u0430"
    ],
    "name:swe_x_preferred":[
        "Smr\u017eovka"
    ],
    "name:vie_x_preferred":[
        "Smr\u017eovka"
    ],
    "name:zho_x_preferred":[
        "\u65af\u59c6\u723e\u82e5\u592b\u5361"
    ],
    "qs_pg:aaroncc":"CZ",
    "qs_pg:name":"Smr\u017eovka",
    "qs_pg:name_adm0":"\u010cesk\u00e1 republika",
    "qs_pg:name_adm1":"Libereck\u00fd kraj",
    "qs_pg:photos":1,
    "qs_pg:photos_1k":1,
    "qs_pg:photos_9k":1,
    "qs_pg:photos_9r":2,
    "qs_pg:photos_all":63,
    "qs_pg:photos_sr":1,
    "qs_pg:pop_sr":0,
    "qs_pg:qs_pg_placetype":"localadmin",
    "qs_pg:qs_pg_placetype_gp":"LocalAdmin",
    "qs_pg:woe_adm0":23424810,
    "woe:adm0_id":23424810,
    "woe:name_adm0":"\u010cesk\u00e1 republika",
    "woe:name_adm1":"Libereck\u00fd kraj",
    "woe:placetype":"LocalAdmin",
    "wof:name":"Smr\u017eovka",
    "wof:placetype":"localadmin"
},
  "geometry": {"coordinates":[15.2479395,50.740257],"type":"Point"}
}