{
  "type": "Feature",
  "properties": {
    "gn:gn_country":"CZ",
    "gn:gn_fcode":"PPL",
    "gn:gn_pop":411,
    "gn:population":411,
    "iso:country":"CZ",
    "name:ceb_x_preferred":[
        "Kojice"
    ],
    "name:ces_x_preferred":[
        "Kojice"
    ],
    "name:deu_x_preferred":[
        "Kojice"
    ],
    "name:eng_x_preferred":[
        "Kojice"
    ],
    "name:epo_x_preferred":[
        "Kojice"
    ],
    "name:eus_x_preferred":[
        "Kojice"
    ],
    "name:fra_x_preferred":[
        "Kojice"
    ],
    "name:hun_x_preferred":[
        "Kojice"
    ],
    "name:ita_x_preferred":[
        "Kojice"
    ],
    "name:msa_x_preferred":[
        "Kojice"
    ],
    "name:nan_x_preferred":[
        "Kojice"
    ],
    "name:nld_x_preferred":[
        "Kojice"
    ],
    "name:pol_x_preferred":[
        "Kojice"
    ],
    "name:por_x_preferred":[
        "Kojice"
    ],
    "name:slk_x_preferred":[
        "Kojice"
    ],
    "name:spa_x_preferred":[
        "Kojice"
    ],
    "name:srp_x_preferred":[
        "\u041a\u043e\u0458\u0438\u0446\u0435"
    ],
    "name:swe_x_preferred":[
        "Kojice"
    ],
    "name:vie_x_preferred":[
        "Kojice"
    ],
    "qs_pg:aaroncc":"CZ",
    "qs_pg:gn_country":"CZ",
    "qs_pg:gn_fcode":"PPL",
    "qs_pg:gn_pop":411,
    "qs_pg:name":"Kojice",
    "qs_pg:name_adm0":"\u010cesk\u00e1 republika",
    "qs_pg:name_adm1":"Pardubick\u00fd kraj",
    "qs_pg:photos_9r":0,
    "qs_pg:photos_sr":0,
    "qs_pg:pop_sr":2,
    "qs_pg:qs_pg_placetype":"locality",
    "qs_pg:qs_pg_placetype_gp":"Town",
    "qs_pg:woe_adm0":23424810,
    "woe:adm0_id":23424810,
    "woe:name_adm0":"\u010cesk\u00e1 republika",
    "woe:name_adm1":"Pardubick\u00fd kraj",
    "woe:placetype":"Town",
    "wof:name":"Kojice",
    "wof:placetype":"locality",
    "wof:population":411
},
  "geometry": {"coordinates":[15.38658,50.04298],"type":"Point"}
}