{
  "type": "Feature",
  "properties": {
    "gn:country":"CZ",
    "gn:fcode":"PPL",
    "gn:population":480,
    "iso:country":"CZ",
    "name:ces_x_preferred":[
        "Sloupno"
    ],
    "name:deu_x_preferred":[
        "Sloupno"
    ],
    "name:fra_x_preferred":[
        "Sloupno"
    ],
    "name:ita_x_preferred":[
        "Sloupno"
    ],
    "name:nld_x_preferred":[
        "Sloupno"
    ],
    "name:slk_x_preferred":[
        "Sloupno"
    ],
    "name:srp_x_preferred":[
        "\u0421\u043b\u043e\u0443\u043f\u043d\u043e"
    ],
    "qs_pg:aaroncc":"CZ",
    "qs_pg:gn_country":"CZ",
    "qs_pg:gn_fcode":"PPL",
    "qs_pg:gn_pop":480,
    "qs_pg:name":"Sloupno",
    "qs_pg:name_adm0":"\u010cesk\u00e1 republika",
    "qs_pg:name_adm1":"Kr\u00e1lov\u00e9hradeck\u00fd kraj",
    "qs_pg:photos_9r":0,
    "qs_pg:photos_sr":0,
    "qs_pg:pop_sr":2,
    "qs_pg:qs_pg_placetype":"locality",
    "qs_pg:qs_pg_placetype_gp":"Town",
    "qs_pg:woe_adm0":23424810,
    "woe:adm0_id":23424810,
    "woe:name_adm0":"\u010cesk\u00e1 republika",
    "woe:name_adm1":"Kr\u00e1lov\u00e9hradeck\u00fd kraj",
    "woe:placetype":"Town",
    "wof:name":"Sloupno",
    "wof:placetype":"locality",
    "wof:population":480
},
  "geometry": {"coordinates":[15.50197,50.25732],"type":"Point"}
}