{
  "type": "Feature",
  "properties": {
    "gn:gn_country":"CZ",
    "gn:gn_fcode":"PPL",
    "gn:gn_pop":292,
    "gn:population":292,
    "iso:country":"CZ",
    "name:ces_x_preferred":[
        "Kru\u017eberk"
    ],
    "name:deu_x_preferred":[
        "Kru\u017eberk"
    ],
    "name:eng_x_preferred":[
        "Kru\u017eberk"
    ],
    "name:epo_x_preferred":[
        "Kru\u017eberk"
    ],
    "name:fas_x_preferred":[
        "\u06a9\u0631\u0648\u0698\u0628\u0631\u06a9"
    ],
    "name:fra_x_preferred":[
        "Kru\u017eberk"
    ],
    "name:hun_x_preferred":[
        "Kru\u017eberk"
    ],
    "name:ita_x_preferred":[
        "Kru\u017eberk"
    ],
    "name:msa_x_preferred":[
        "Kru\u017eberk"
    ],
    "name:nld_x_preferred":[
        "Kru\u017eberk"
    ],
    "name:pol_x_preferred":[
        "Kru\u017eberk"
    ],
    "name:por_x_preferred":[
        "Kru\u017eberk"
    ],
    "name:rup_x_preferred":[
        "Kru\u017eberk"
    ],
    "name:slk_x_preferred":[
        "Kru\u017eberk"
    ],
    "name:srp_x_preferred":[
        "\u041a\u0440\u0443\u0436\u0431\u0435\u0440\u043a"
    ],
    "name:swe_x_preferred":[
        "Kru\u017eberk"
    ],
    "name:unk_x_variant":[
        "Kreuzberg"
    ],
    "name:vie_x_preferred":[
        "Kru\u017eberk"
    ],
    "qs_pg:aaroncc":"CZ",
    "qs_pg:gn_country":"CZ",
    "qs_pg:gn_fcode":"PPL",
    "qs_pg:gn_pop":292,
    "qs_pg:name":"Kru\u017eberk",
    "qs_pg:name_adm0":"\u010cesk\u00e1 republika",
    "qs_pg:name_adm1":"Moravskoslezsk\u00fd kraj",
    "qs_pg:photos_9k":1,
    "qs_pg:photos_9r":3,
    "qs_pg:photos_all":104,
    "qs_pg:photos_sr":0,
    "qs_pg:pop_sr":2,
    "qs_pg:qs_pg_placetype":"locality",
    "qs_pg:qs_pg_placetype_gp":"Town",
    "qs_pg:woe_adm0":23424810,
    "woe:adm0_id":23424810,
    "woe:name_adm0":"\u010cesk\u00e1 republika",
    "woe:name_adm1":"Moravskoslezsk\u00fd kraj",
    "woe:placetype":"Town",
    "wof:name":"Kru\u017eberk",
    "wof:placetype":"locality",
    "wof:population":292
},
  "geometry": {"coordinates":[17.68319,49.83178],"type":"Point"}
}