{
  "type": "Feature",
  "properties": {
    "gn:country":"CZ",
    "gn:fcode":"PPL",
    "gn:population":159,
    "iso:country":"CZ",
    "name:azb_x_preferred":[
        "\u06a9\u0648\u06cc\u062a\u06a9\u0648\u0648"
    ],
    "name:cat_x_preferred":[
        "Kv\u00edtkov"
    ],
    "name:ceb_x_preferred":[
        "Kv\u00edtkov"
    ],
    "name:ces_x_preferred":[
        "Kv\u00edtkov"
    ],
    "name:che_x_preferred":[
        "\u041a\u0432\u0438\u0442\u043a\u043e\u0432"
    ],
    "name:deu_x_preferred":[
        "Kv\u00edtkov"
    ],
    "name:eng_x_preferred":[
        "Kv\u00edtkov"
    ],
    "name:epo_x_preferred":[
        "Kv\u00edtkov"
    ],
    "name:eus_x_preferred":[
        "Kv\u00edtkov"
    ],
    "name:fas_x_preferred":[
        "\u06a9\u0648\u06cc\u062a\u06a9\u0648\u0648"
    ],
    "name:fra_x_preferred":[
        "Kv\u00edtkov"
    ],
    "name:gle_x_preferred":[
        "Kv\u00edtkov"
    ],
    "name:hun_x_preferred":[
        "Kv\u00edtkov"
    ],
    "name:ita_x_preferred":[
        "Kv\u00edtkov"
    ],
    "name:lmo_x_preferred":[
        "Kv\u00edtkov"
    ],
    "name:msa_x_preferred":[
        "Kv\u00edtkov"
    ],
    "name:nan_x_preferred":[
        "Kv\u00edtkov"
    ],
    "name:nld_x_preferred":[
        "Kv\u00edtkov"
    ],
    "name:pol_x_preferred":[
        "Kv\u00edtkov"
    ],
    "name:por_x_preferred":[
        "Kv\u00edtkov"
    ],
    "name:slk_x_preferred":[
        "Kv\u00edtkov"
    ],
    "name:spa_x_preferred":[
        "Kv\u00edtkov"
    ],
    "name:srp_x_preferred":[
        "\u041a\u0432\u0438\u0442\u043a\u043e\u0432"
    ],
    "name:swe_x_preferred":[
        "Kv\u00edtkov"
    ],
    "name:tat_x_preferred":[
        "\u041a\u0432\u0438\u0442\u043a\u043e\u0432"
    ],
    "name:uzb_x_preferred":[
        "Kv\u00edtkov"
    ],
    "name:vie_x_preferred":[
        "Kv\u00edtkov"
    ],
    "qs_pg:aaroncc":"CZ",
    "qs_pg:gn_country":"CZ",
    "qs_pg:gn_fcode":"PPL",
    "qs_pg:gn_pop":159,
    "qs_pg:name":"Kv\u00edtkov",
    "qs_pg:name_adm0":"\u010cesk\u00e1 republika",
    "qs_pg:name_adm1":"Libereck\u00fd kraj",
    "qs_pg:photos_9k":1,
    "qs_pg:photos_9r":1,
    "qs_pg:photos_all":1,
    "qs_pg:photos_sr":0,
    "qs_pg:pop_sr":1,
    "qs_pg:qs_pg_placetype":"locality",
    "qs_pg:qs_pg_placetype_gp":"Town",
    "qs_pg:woe_adm0":23424810,
    "woe:adm0_id":23424810,
    "woe:name_adm0":"\u010cesk\u00e1 republika",
    "woe:name_adm1":"Libereck\u00fd kraj",
    "woe:placetype":"Town",
    "wof:name":"Kv\u00edtkov",
    "wof:placetype":"locality",
    "wof:population":159
},
  "geometry": {"coordinates":[14.48666,50.65492],"type":"Point"}
}