{
  "type": "Feature",
  "properties": {
    "gn:admin1_code":"89",
    "gn:admin2_code":"0427",
    "gn:asciiname":"Zandov",
    "gn:country_code":"CZ",
    "gn:dem":272,
    "gn:feature_class":"P",
    "gn:feature_code":"PPL",
    "gn:name":"\u017dandov",
    "gn:population":0,
    "gn:timezone":"Europe/Prague",
    "iso:country":"CZ",
    "name:deu_x_preferred":[
        "Schanda"
    ],
    "wof:name":"Zandov",
    "wof:placetype":"locality"
},
  "geometry": {"coordinates":[13.94629,50.70733],"type":"Point"}
}