{
  "type": "Feature",
  "properties": {
    "gn:gn_country":"CZ",
    "gn:gn_fcode":"PPL",
    "gn:gn_pop":444,
    "gn:population":444,
    "iso:country":"CZ",
    "name:ceb_x_preferred":[
        "Jeni\u0161ovice"
    ],
    "name:ces_x_preferred":[
        "Jeni\u0161ovice"
    ],
    "name:deu_x_preferred":[
        "Jeni\u0161ovice u Chrudimi"
    ],
    "name:eng_x_preferred":[
        "Jeni\u0161ovice"
    ],
    "name:epo_x_preferred":[
        "Jeni\u0161ovice"
    ],
    "name:hun_x_preferred":[
        "Jeni\u0161ovice"
    ],
    "name:ita_x_preferred":[
        "Jeni\u0161ovice"
    ],
    "name:msa_x_preferred":[
        "Jeni\u0161ovice"
    ],
    "name:nan_x_preferred":[
        "Jeni\u0161ovice"
    ],
    "name:nld_x_preferred":[
        "Jeni\u0161ovice"
    ],
    "name:pol_x_preferred":[
        "Jeni\u0161ovice"
    ],
    "name:por_x_preferred":[
        "Jeni\u0161ovice"
    ],
    "name:rup_x_preferred":[
        "Jeni\u0161ovice"
    ],
    "name:slk_x_preferred":[
        "Jeni\u0161ovice"
    ],
    "name:spa_x_preferred":[
        "Jeni\u0161ovice"
    ],
    "name:srp_x_preferred":[
        "\u0408\u0435\u045a\u0438\u0448\u043e\u0432\u0438\u0446\u0435"
    ],
    "name:swe_x_preferred":[
        "Jeni\u0161ovice"
    ],
    "name:vie_x_preferred":[
        "Jeni\u0161ovice"
    ],
    "qs_pg:aaroncc":"CZ",
    "qs_pg:gn_country":"CZ",
    "qs_pg:gn_fcode":"PPL",
    "qs_pg:gn_pop":444,
    "qs_pg:name":"Jeni\u0161ovice",
    "qs_pg:name_adm0":"\u010cesk\u00e1 republika",
    "qs_pg:name_adm1":"Pardubick\u00fd kraj",
    "qs_pg:photos_9r":0,
    "qs_pg:photos_sr":0,
    "qs_pg:pop_sr":2,
    "qs_pg:qs_pg_placetype":"locality",
    "qs_pg:qs_pg_placetype_gp":"Town",
    "qs_pg:woe_adm0":23424810,
    "woe:adm0_id":23424810,
    "woe:name_adm0":"\u010cesk\u00e1 republika",
    "woe:name_adm1":"Pardubick\u00fd kraj",
    "woe:placetype":"Town",
    "wof:name":"Jeni\u0161ovice",
    "wof:placetype":"locality",
    "wof:population":444
},
  "geometry": {"coordinates":[16.03102,49.92955],"type":"Point"}
}