{
  "type": "Feature",
  "properties": {
    "gn:gn_country":"CZ",
    "gn:gn_fcode":"PPL",
    "gn:gn_pop":420,
    "gn:population":420,
    "iso:country":"CZ",
    "name:azb_x_preferred":[
        "\u0633\u06a9\u0648\u0631\u0646\u06cc\u062a\u0633\u0647"
    ],
    "name:ceb_x_preferred":[
        "Sko\u0159enice"
    ],
    "name:ces_x_preferred":[
        "Sko\u0159enice"
    ],
    "name:deu_x_preferred":[
        "Sko\u0159enice"
    ],
    "name:eng_x_preferred":[
        "Sko\u0159enice"
    ],
    "name:epo_x_preferred":[
        "Sko\u0159enice"
    ],
    "name:eus_x_preferred":[
        "Sko\u0159enice"
    ],
    "name:fas_x_preferred":[
        "\u0633\u06a9\u0648\u0631\u0646\u06cc\u062a\u0633\u0647"
    ],
    "name:fra_x_preferred":[
        "Sko\u0159enice"
    ],
    "name:hun_x_preferred":[
        "Sko\u0159enice"
    ],
    "name:ita_x_preferred":[
        "Sko\u0159enice"
    ],
    "name:msa_x_preferred":[
        "Sko\u0159enice"
    ],
    "name:nan_x_preferred":[
        "Sko\u0159enice"
    ],
    "name:nld_x_preferred":[
        "Sko\u0159enice"
    ],
    "name:por_x_preferred":[
        "Sko\u0159enice"
    ],
    "name:slk_x_preferred":[
        "Sko\u0159enice"
    ],
    "name:spa_x_preferred":[
        "Sko\u0159enice"
    ],
    "name:srp_x_preferred":[
        "\u0421\u043a\u043e\u0440\u0436\u0435\u045a\u0438\u0446\u0435"
    ],
    "name:swe_x_preferred":[
        "Sko\u0159enice"
    ],
    "name:vie_x_preferred":[
        "Sko\u0159enice"
    ],
    "qs_pg:aaroncc":"CZ",
    "qs_pg:gn_country":"CZ",
    "qs_pg:gn_fcode":"PPL",
    "qs_pg:gn_pop":420,
    "qs_pg:name":"Sko\u0159enice",
    "qs_pg:name_adm0":"\u010cesk\u00e1 republika",
    "qs_pg:name_adm1":"Pardubick\u00fd kraj",
    "qs_pg:photos_9r":0,
    "qs_pg:photos_sr":0,
    "qs_pg:pop_sr":2,
    "qs_pg:qs_pg_placetype":"locality",
    "qs_pg:qs_pg_placetype_gp":"Town",
    "qs_pg:woe_adm0":23424810,
    "woe:adm0_id":23424810,
    "woe:name_adm0":"\u010cesk\u00e1 republika",
    "woe:name_adm1":"Pardubick\u00fd kraj",
    "woe:placetype":"Town",
    "wof:name":"Sko\u0159enice",
    "wof:placetype":"locality",
    "wof:population":420
},
  "geometry": {"coordinates":[16.22196,50.03126],"type":"Point"}
}