{
  "type": "Feature",
  "properties": {
    "gn:gn_country":"CZ",
    "gn:gn_fcode":"PPL",
    "gn:gn_pop":442,
    "gn:population":442,
    "iso:country":"CZ",
    "name:cze_x_preferred":[
        "Horn\u00ed V\u011bstonice"
    ],
    "name:dut_x_preferred":[
        "Horn\u00ed V\u011bstonice"
    ],
    "name:eng_x_preferred":[
        "Horn\u00ed V\u011bstonice"
    ],
    "name:fre_x_preferred":[
        "Horn\u00ed V\u011bstonice"
    ],
    "name:ger_x_preferred":[
        "Horn\u00ed V\u011bstonice"
    ],
    "name:hun_x_preferred":[
        "Horn\u00ed V\u011bstonice"
    ],
    "name:ita_x_preferred":[
        "Horn\u00ed V\u011bstonice"
    ],
    "name:may_x_preferred":[
        "Horn\u00ed V\u011bstonice"
    ],
    "name:per_x_preferred":[
        "\u0647\u0648\u0631\u0646\u06cc \u0648\u06cc\u0633\u062a\u0648\u0646\u06cc\u062a\u0633\u0647"
    ],
    "name:pol_x_preferred":[
        "Horn\u00ed V\u011bstonice"
    ],
    "name:por_x_preferred":[
        "Horn\u00ed V\u011bstonice"
    ],
    "name:rup_x_preferred":[
        "Horn\u00ed V\u011bstonice"
    ],
    "name:sgs_x_preferred":[
        "Huorn\u0117 Vestuon\u0117c\u0113"
    ],
    "name:slo_x_preferred":[
        "Horn\u00ed V\u011bstonice"
    ],
    "name:srp_x_preferred":[
        "\u0425\u043e\u0440\u045a\u0438 \u0412\u0458\u0435\u0441\u0442\u043e\u045a\u0438\u0446\u0435"
    ],
    "name:swe_x_preferred":[
        "Horn\u00ed V\u011bstonice"
    ],
    "name:unk_x_variant":[
        "Ober-Wisternitz"
    ],
    "name:vie_x_preferred":[
        "Horn\u00ed V\u011bstonice"
    ],
    "qs_pg:aaroncc":"CZ",
    "qs_pg:gn_country":"CZ",
    "qs_pg:gn_fcode":"PPL",
    "qs_pg:gn_pop":442,
    "qs_pg:name":"Horn\u00ed V\u011bstonice",
    "qs_pg:name_adm0":"\u010cesk\u00e1 republika",
    "qs_pg:name_adm1":"Jihomoravsk\u00fd kraj",
    "qs_pg:photos":27,
    "qs_pg:photos_1k":5,
    "qs_pg:photos_9k":1,
    "qs_pg:photos_9r":2,
    "qs_pg:photos_all":27,
    "qs_pg:photos_sr":2,
    "qs_pg:pop_sr":2,
    "qs_pg:qs_pg_placetype":"locality",
    "qs_pg:qs_pg_placetype_gp":"Town",
    "qs_pg:woe_adm0":23424810,
    "woe:adm0_id":23424810,
    "woe:name_adm0":"\u010cesk\u00e1 republika",
    "woe:name_adm1":"Jihomoravsk\u00fd kraj",
    "woe:placetype":"Town",
    "wof:name":"Horn\u00ed V\u011bstonice",
    "wof:placetype":"locality",
    "wof:population":442
},
  "geometry": {"coordinates":[16.62556,48.87455],"type":"Point"}
}