{
  "type": "Feature",
  "properties": {
    "gn:admin1_code":"82.0",
    "gn:admin2_code":"0521",
    "gn:asciiname":"Janatov",
    "gn:country_code":"CZ",
    "gn:dem":242,
    "gn:feature_class":"P",
    "gn:feature_code":"PPL",
    "gn:name":"Janatov",
    "gn:population":0,
    "gn:timezone":"Europe/Prague",
    "iso:country":"CZ",
    "wof:name":"Janatov",
    "wof:placetype":"locality"
},
  "geometry": {"coordinates":[15.57832,50.27143],"type":"Point"}
}