{
  "type": "Feature",
  "properties": {
    "gn:admin1_code":"88",
    "gn:admin2_code":"0201",
    "gn:asciiname":"Strzenec",
    "gn:country_code":"CZ",
    "gn:dem":508,
    "gn:feature_class":"P",
    "gn:feature_code":"PPL",
    "gn:name":"Str\u017eenec",
    "gn:population":0,
    "gn:timezone":"Europe/Prague",
    "iso:country":"CZ",
    "wof:name":"Strzenec",
    "wof:placetype":"locality"
},
  "geometry": {"coordinates":[14.70507,49.68267],"type":"Point"}
}