{
  "type": "Feature",
  "properties": {
    "gn:admin1_code":"84.0",
    "gn:admin2_code":"0711",
    "gn:asciiname":"Rokliny",
    "gn:country_code":"CZ",
    "gn:dem":310,
    "gn:feature_class":"P",
    "gn:feature_code":"PPL",
    "gn:name":"Rokliny",
    "gn:population":0,
    "gn:timezone":"Europe/Prague",
    "iso:country":"CZ",
    "name:und_x_variant":[
        "\u0160ropengrunt",
        "Rokliny"
    ],
    "wof:name":"Rokliny",
    "wof:placetype":"locality"
},
  "geometry": {"coordinates":[17.17213,50.32074],"type":"Point"}
}