{
  "type": "Feature",
  "properties": {
    "gn:gn_country":"CZ",
    "gn:gn_fcode":"PPL",
    "gn:gn_pop":411,
    "gn:population":411,
    "iso:country":"CZ",
    "name:cze_x_preferred":[
        "K\u0159tomil"
    ],
    "name:dut_x_preferred":[
        "K\u0159tomil"
    ],
    "name:eng_x_preferred":[
        "K\u0159tomil"
    ],
    "name:epo_x_preferred":[
        "K\u0159tomil"
    ],
    "name:fre_x_preferred":[
        "K\u0159tomil"
    ],
    "name:ger_x_preferred":[
        "K\u0159tomil"
    ],
    "name:hun_x_preferred":[
        "K\u0159tomil"
    ],
    "name:ita_x_preferred":[
        "K\u0159tomil"
    ],
    "name:may_x_preferred":[
        "K\u0159tomil"
    ],
    "name:per_x_preferred":[
        "\u06a9\u0631\u062a\u0648\u0645\u06cc\u0644"
    ],
    "name:pol_x_preferred":[
        "K\u0159tomil"
    ],
    "name:por_x_preferred":[
        "K\u0159tomil"
    ],
    "name:rup_x_preferred":[
        "K\u0159tomil"
    ],
    "name:slo_x_preferred":[
        "K\u0159tomil"
    ],
    "name:srp_x_preferred":[
        "\u041a\u0440\u0442\u043e\u043c\u0438\u043b"
    ],
    "name:swe_x_preferred":[
        "K\u0159tomil"
    ],
    "name:vie_x_preferred":[
        "K\u0159tomil"
    ],
    "qs_pg:aaroncc":"CZ",
    "qs_pg:gn_country":"CZ",
    "qs_pg:gn_fcode":"PPL",
    "qs_pg:gn_pop":411,
    "qs_pg:name":"K\u0159tomil",
    "qs_pg:name_adm0":"\u010cesk\u00e1 republika",
    "qs_pg:name_adm1":"Olomouck\u00fd kraj",
    "qs_pg:photos_9r":0,
    "qs_pg:photos_sr":0,
    "qs_pg:pop_sr":2,
    "qs_pg:qs_pg_placetype":"locality",
    "qs_pg:qs_pg_placetype_gp":"Town",
    "qs_pg:woe_adm0":23424810,
    "woe:adm0_id":23424810,
    "woe:name_adm0":"\u010cesk\u00e1 republika",
    "woe:name_adm1":"Olomouck\u00fd kraj",
    "woe:placetype":"Town",
    "wof:name":"K\u0159tomil",
    "wof:placetype":"locality",
    "wof:population":411
},
  "geometry": {"coordinates":[17.62622,49.40909],"type":"Point"}
}