{
  "type": "Feature",
  "properties": {
    "gn:admin1_code":"79.0",
    "gn:admin2_code":"0312",
    "gn:asciiname":"Mostky",
    "gn:country_code":"CZ",
    "gn:dem":575,
    "gn:feature_class":"P",
    "gn:feature_code":"PPL",
    "gn:name":"Mostky",
    "gn:population":0,
    "gn:timezone":"Europe/Prague",
    "iso:country":"CZ",
    "name:und_x_variant":[
        "Pernlesdorf",
        "Mostky"
    ],
    "wof:name":"Mostky",
    "wof:placetype":"locality"
},
  "geometry": {"coordinates":[14.51628,48.72303],"type":"Point"}
}