{
  "type": "Feature",
  "properties": {
    "gn:admin1_code":"82.0",
    "gn:admin2_code":"0522",
    "gn:asciiname":"Bela u Pecky",
    "gn:country_code":"CZ",
    "gn:dem":346,
    "gn:feature_class":"P",
    "gn:feature_code":"PPL",
    "gn:name":"B\u011bl\u00e1 u Pecky",
    "gn:population":0,
    "gn:timezone":"Europe/Prague",
    "iso:country":"CZ",
    "wof:name":"Bela u Pecky",
    "wof:placetype":"locality"
},
  "geometry": {"coordinates":[15.58309,50.47415],"type":"Point"}
}