{
  "type": "Feature",
  "properties": {
    "gn:admin1_code":"82",
    "gn:admin2_code":"0525",
    "gn:asciiname":"Velka Upa",
    "gn:country_code":"CZ",
    "gn:dem":703,
    "gn:feature_class":"P",
    "gn:feature_code":"PPL",
    "gn:name":"Velk\u00e1 \u00dapa",
    "gn:population":0,
    "gn:timezone":"Europe/Prague",
    "iso:country":"CZ",
    "name:und_x_variant":[
        "Gross-Aupa",
        "Velk\u00e1 \u00dapa II",
        "Velk\u00e1 Upa I"
    ],
    "wof:name":"Velka Upa",
    "wof:placetype":"locality"
},
  "geometry": {"coordinates":[15.76907,50.68982000000001],"type":"Point"}
}