{
  "type": "Feature",
  "properties": {
    "gn:gn_country":"CZ",
    "gn:gn_fcode":"PPL",
    "gn:gn_pop":213,
    "gn:population":213,
    "iso:country":"CZ",
    "name:cze_x_preferred":[
        "T\u0159ebom"
    ],
    "name:dut_x_preferred":[
        "T\u0159ebom"
    ],
    "name:eng_x_preferred":[
        "T\u0159ebom"
    ],
    "name:epo_x_preferred":[
        "T\u0159ebom"
    ],
    "name:fre_x_preferred":[
        "T\u0159ebom"
    ],
    "name:ger_x_preferred":[
        "T\u0159ebom"
    ],
    "name:hun_x_preferred":[
        "T\u0159ebom"
    ],
    "name:ita_x_preferred":[
        "T\u0159ebom"
    ],
    "name:may_x_preferred":[
        "T\u0159ebom"
    ],
    "name:pol_x_preferred":[
        "T\u0159ebom"
    ],
    "name:por_x_preferred":[
        "T\u0159ebom"
    ],
    "name:rup_x_preferred":[
        "T\u0159ebom"
    ],
    "name:slo_x_preferred":[
        "T\u0159ebom"
    ],
    "name:spa_x_preferred":[
        "T\u0159ebom"
    ],
    "name:srp_x_preferred":[
        "\u0422\u0440\u0435\u0431\u043e\u043c"
    ],
    "name:swe_x_preferred":[
        "T\u0159ebom"
    ],
    "name:unk_x_variant":[
        "Thr\u00f6m"
    ],
    "name:vie_x_preferred":[
        "T\u0159ebom"
    ],
    "qs_pg:aaroncc":"CZ",
    "qs_pg:gn_country":"CZ",
    "qs_pg:gn_fcode":"PPL",
    "qs_pg:gn_pop":213,
    "qs_pg:name":"T\u0159ebom",
    "qs_pg:name_adm0":"\u010cesk\u00e1 republika",
    "qs_pg:name_adm1":"Moravskoslezsk\u00fd kraj",
    "qs_pg:photos_9r":0,
    "qs_pg:photos_sr":0,
    "qs_pg:pop_sr":2,
    "qs_pg:qs_pg_placetype":"locality",
    "qs_pg:qs_pg_placetype_gp":"Town",
    "qs_pg:woe_adm0":23424810,
    "woe:adm0_id":23424810,
    "woe:name_adm0":"\u010cesk\u00e1 republika",
    "woe:name_adm1":"Moravskoslezsk\u00fd kraj",
    "woe:placetype":"Town",
    "wof:name":"T\u0159ebom",
    "wof:placetype":"locality",
    "wof:population":213
},
  "geometry": {"coordinates":[18.02528,50.04615],"type":"Point"}
}