{
  "type": "Feature",
  "properties": {
    "gn:admin1_code":"83",
    "gn:admin2_code":"0512",
    "gn:asciiname":"Svarov",
    "gn:country_code":"CZ",
    "gn:dem":503,
    "gn:feature_class":"P",
    "gn:feature_code":"PPL",
    "gn:name":"Sv\u00e1rov",
    "gn:population":0,
    "gn:timezone":"Europe/Prague",
    "iso:country":"CZ",
    "wof:name":"Svarov",
    "wof:placetype":"locality"
},
  "geometry": {"coordinates":[15.32296,50.72091],"type":"Point"}
}