{
  "type": "Feature",
  "properties": {
    "gn:admin1_code":"80.0",
    "gn:admin2_code":"0613",
    "gn:asciiname":"Nizka Lhota",
    "gn:country_code":"CZ",
    "gn:dem":544,
    "gn:feature_class":"P",
    "gn:feature_code":"PPL",
    "gn:name":"N\u00edzk\u00e1 Lhota",
    "gn:population":0,
    "gn:timezone":"Europe/Prague",
    "iso:country":"CZ",
    "name:und_x_variant":[
        "N\u011bmeck\u00e1 Lhota",
        "N\u00edzk\u00e1 Lhota"
    ],
    "wof:name":"Nizka Lhota",
    "wof:placetype":"locality"
},
  "geometry": {"coordinates":[15.03069,49.43833],"type":"Point"}
}