{
  "type": "Feature",
  "properties": {
    "iso:country":"CZ",
    "name:arg_x_preferred":[
        "Lenora"
    ],
    "name:ceb_x_preferred":[
        "Lenora"
    ],
    "name:ces_x_preferred":[
        "Lenora"
    ],
    "name:deu_x_preferred":[
        "Lenora"
    ],
    "name:ita_x_preferred":[
        "Lenora"
    ],
    "name:nld_x_preferred":[
        "Lenora"
    ],
    "name:pol_x_preferred":[
        "Lenora"
    ],
    "name:srp_x_preferred":[
        "\u041b\u0435\u043d\u043e\u0440\u0430"
    ],
    "name:swe_x_preferred":[
        "Lenora"
    ],
    "qs_pg:aaroncc":"CZ",
    "qs_pg:name":"Lenora",
    "qs_pg:name_adm0":"\u010cesk\u00e1 republika",
    "qs_pg:name_adm1":"Jiho\u010desk\u00fd kraj",
    "qs_pg:photos":1,
    "qs_pg:photos_1k":1,
    "qs_pg:photos_9k":1,
    "qs_pg:photos_9r":1,
    "qs_pg:photos_all":24,
    "qs_pg:photos_sr":1,
    "qs_pg:pop_sr":0,
    "qs_pg:qs_pg_placetype":"localadmin",
    "qs_pg:qs_pg_placetype_gp":"LocalAdmin",
    "qs_pg:woe_adm0":23424810,
    "woe:adm0_id":23424810,
    "woe:name_adm0":"\u010cesk\u00e1 republika",
    "woe:name_adm1":"Jiho\u010desk\u00fd kraj",
    "woe:placetype":"LocalAdmin",
    "wof:name":"Lenora",
    "wof:placetype":"localadmin"
},
  "geometry": {"coordinates":[13.806605,48.921766],"type":"Point"}
}