{
  "type": "Feature",
  "properties": {
    "gn:admin1_code":"85",
    "gn:admin2_code":"0801",
    "gn:asciiname":"Volarna",
    "gn:country_code":"CZ",
    "gn:dem":605,
    "gn:feature_class":"P",
    "gn:feature_code":"PPL",
    "gn:name":"Vol\u00e1rna",
    "gn:population":0,
    "gn:timezone":"Europe/Prague",
    "iso:country":"CZ",
    "name:und_x_variant":[
        "Ochsenstall",
        "Vol\u00e1rna"
    ],
    "wof:name":"Volarna",
    "wof:placetype":"locality"
},
  "geometry": {"coordinates":[17.48464,49.89048],"type":"Point"}
}