{
  "type": "Feature",
  "properties": {
    "gn:admin1_code":"89.0",
    "gn:admin2_code":"0424",
    "gn:asciiname":"Nehasice",
    "gn:country_code":"CZ",
    "gn:dem":230,
    "gn:feature_class":"P",
    "gn:feature_code":"PPL",
    "gn:name":"Nehasice",
    "gn:population":0,
    "gn:timezone":"Europe/Prague",
    "iso:country":"CZ",
    "name:deu_x_preferred":[
        "Nehasitz"
    ],
    "wof:name":"Nehasice",
    "wof:placetype":"locality"
},
  "geometry": {"coordinates":[13.59627,50.38554],"type":"Point"}
}