{
  "type": "Feature",
  "properties": {
    "gn:admin1_code":"86",
    "gn:admin2_code":"0532",
    "gn:asciiname":"Tupesy",
    "gn:country_code":"CZ",
    "gn:dem":245,
    "gn:feature_class":"P",
    "gn:feature_code":"PPL",
    "gn:name":"Tupesy",
    "gn:population":0,
    "gn:timezone":"Europe/Prague",
    "iso:country":"CZ",
    "wof:name":"Tupesy",
    "wof:placetype":"locality"
},
  "geometry": {"coordinates":[15.56969,49.99514],"type":"Point"}
}