{
  "type": "Feature",
  "properties": {
    "gn:admin1_code":"86",
    "gn:admin2_code":"0532",
    "gn:asciiname":"Tupesy",
    "gn:country_code":"CZ",
    "gn:dem":245,
    "gn:feature_class":"P",
    "gn:feature_code":"PPL",
    "gn:name":"Tupesy",
    "gn:population":0,
    "gn:timezone":"Europe/Prague",
    "iso:country":"CZ",
    "name:azb_x_preferred":[
        "\u062a\u0648\u067e\u0633\u06cc"
    ],
    "name:ceb_x_preferred":[
        "Tupesy"
    ],
    "name:ces_x_preferred":[
        "Tupesy"
    ],
    "name:eus_x_preferred":[
        "Tupesy"
    ],
    "name:fas_x_preferred":[
        "\u062a\u0648\u067e\u0633\u06cc"
    ],
    "name:fra_x_preferred":[
        "Tupesy"
    ],
    "name:hun_x_preferred":[
        "Tupesy"
    ],
    "name:ita_x_preferred":[
        "Tupesy"
    ],
    "name:msa_x_preferred":[
        "Tupesy"
    ],
    "name:nld_x_preferred":[
        "Tupesy"
    ],
    "name:pol_x_preferred":[
        "Tupesy"
    ],
    "name:por_x_preferred":[
        "Tupesy"
    ],
    "name:slk_x_preferred":[
        "Tupesy"
    ],
    "name:spa_x_preferred":[
        "Tupesy"
    ],
    "name:srp_x_preferred":[
        "\u0422\u0443\u043f\u0435\u0441\u0438"
    ],
    "name:swe_x_preferred":[
        "Tupesy"
    ],
    "name:vie_x_preferred":[
        "Tupesy"
    ],
    "wof:name":"Tupesy",
    "wof:placetype":"locality"
},
  "geometry": {"coordinates":[15.56969,49.99514],"type":"Point"}
}