{
  "type": "Feature",
  "properties": {
    "gn:admin1_code":"78.0",
    "gn:admin2_code":"0621",
    "gn:asciiname":"Klamovka",
    "gn:country_code":"CZ",
    "gn:dem":409,
    "gn:feature_class":"P",
    "gn:feature_code":"PPL",
    "gn:name":"Klamovka",
    "gn:population":0,
    "gn:timezone":"Europe/Prague",
    "iso:country":"CZ",
    "wof:name":"Klamovka",
    "wof:placetype":"locality"
},
  "geometry": {"coordinates":[16.63691,49.34096],"type":"Point"}
}