{
  "type": "Feature",
  "properties": {
    "gn:admin1_code":"86",
    "gn:admin2_code":"0531",
    "gn:asciiname":"Zalibene",
    "gn:country_code":"CZ",
    "gn:dem":618,
    "gn:feature_class":"P",
    "gn:feature_code":"PPL",
    "gn:name":"Zal\u00edben\u00e9",
    "gn:population":0,
    "gn:timezone":"Europe/Prague",
    "iso:country":"CZ",
    "wof:name":"Zalibene",
    "wof:placetype":"locality"
},
  "geometry": {"coordinates":[15.9015,49.7168],"type":"Point"}
}