{
  "type": "Feature",
  "properties": {
    "gn:admin1_code":"87.0",
    "gn:admin2_code":"0321",
    "gn:asciiname":"Liskova",
    "gn:country_code":"CZ",
    "gn:dem":631,
    "gn:feature_class":"P",
    "gn:feature_code":"PPL",
    "gn:name":"L\u00edskov\u00e1",
    "gn:population":0,
    "gn:timezone":"Europe/Prague",
    "iso:country":"CZ",
    "name:und_x_variant":[
        "Haselbach",
        "L\u00edskov\u00e1"
    ],
    "wof:name":"Liskova",
    "wof:placetype":"locality"
},
  "geometry": {"coordinates":[12.72235,49.4142],"type":"Point"}
}