{
  "type": "Feature",
  "properties": {
    "gn:admin1_code":"87.0",
    "gn:admin2_code":"0322",
    "gn:asciiname":"Odolenov",
    "gn:country_code":"CZ",
    "gn:dem":674,
    "gn:feature_class":"P",
    "gn:feature_code":"PPL",
    "gn:name":"Odolenov",
    "gn:population":0,
    "gn:timezone":"Europe/Prague",
    "iso:country":"CZ",
    "wof:name":"Odolenov",
    "wof:placetype":"locality"
},
  "geometry": {"coordinates":[13.47906,49.24308],"type":"Point"}
}