{
  "type": "Feature",
  "properties": {
    "gn:admin1_code":"88.0",
    "gn:admin2_code":"0201",
    "gn:asciiname":"Ruzkovy Lhotice",
    "gn:country_code":"CZ",
    "gn:dem":507,
    "gn:feature_class":"P",
    "gn:feature_code":"PPL",
    "gn:name":"R\u016f\u017ekovy Lhotice",
    "gn:population":0,
    "gn:timezone":"Europe/Prague",
    "iso:country":"CZ",
    "wof:name":"Ruzkovy Lhotice",
    "wof:placetype":"locality"
},
  "geometry": {"coordinates":[15.07187,49.60604],"type":"Point"}
}