{
  "type": "Feature",
  "properties": {
    "gn:admin1_code":"80.0",
    "gn:admin2_code":"0613",
    "gn:asciiname":"Rutov",
    "gn:country_code":"CZ",
    "gn:dem":625,
    "gn:feature_class":"P",
    "gn:feature_code":"PPL",
    "gn:name":"Rutov",
    "gn:population":0,
    "gn:timezone":"Europe/Prague",
    "iso:country":"CZ",
    "wof:name":"Rutov",
    "wof:placetype":"locality"
},
  "geometry": {"coordinates":[14.97488,49.32608],"type":"Point"}
}