{
  "type": "Feature",
  "properties": {
    "gn:admin1_code":"88.0",
    "gn:admin2_code":"0209",
    "gn:asciiname":"Hostice",
    "gn:country_code":"CZ",
    "gn:dem":251,
    "gn:feature_class":"P",
    "gn:feature_code":"PPL",
    "gn:name":"Ho\u0161tice",
    "gn:population":0,
    "gn:timezone":"Europe/Prague",
    "iso:country":"CZ",
    "wof:name":"Hostice",
    "wof:placetype":"locality"
},
  "geometry": {"coordinates":[14.40625,50.20245],"type":"Point"}
}