{
  "type": "Feature",
  "properties": {
    "gn:admin1_code":"88.0",
    "gn:admin2_code":"0209",
    "gn:asciiname":"Hostice",
    "gn:country_code":"CZ",
    "gn:dem":251,
    "gn:feature_class":"P",
    "gn:feature_code":"PPL",
    "gn:name":"Ho\u0161tice",
    "gn:population":0,
    "gn:timezone":"Europe/Prague",
    "iso:country":"CZ",
    "name:cat_x_preferred":[
        "Hostice"
    ],
    "name:ces_x_preferred":[
        "Hostice"
    ],
    "name:deu_x_preferred":[
        "Hostice"
    ],
    "name:epo_x_preferred":[
        "Hostice"
    ],
    "name:eus_x_preferred":[
        "Hostice"
    ],
    "name:fra_x_preferred":[
        "Hostice"
    ],
    "name:hun_x_preferred":[
        "Gesztete"
    ],
    "name:ita_x_preferred":[
        "Hostice"
    ],
    "name:msa_x_preferred":[
        "Hostice"
    ],
    "name:nld_x_preferred":[
        "Hostice"
    ],
    "name:pol_x_preferred":[
        "Hostice"
    ],
    "name:ron_x_preferred":[
        "Hostice"
    ],
    "name:slk_x_preferred":[
        "Hostice"
    ],
    "name:spa_x_preferred":[
        "Hostice"
    ],
    "name:srp_x_preferred":[
        "\u0425\u043e\u0441\u0442\u0438\u0446\u0435"
    ],
    "name:ukr_x_preferred":[
        "\u0413\u043e\u0441\u0442\u0456\u0446\u0435"
    ],
    "name:war_x_preferred":[
        "Hostice"
    ],
    "wof:name":"Hostice",
    "wof:placetype":"locality"
},
  "geometry": {"coordinates":[14.40625,50.20245],"type":"Point"}
}