{
  "type": "Feature",
  "properties": {
    "gn:admin1_code":"88.0",
    "gn:admin2_code":"0207",
    "gn:asciiname":"Sezemice",
    "gn:country_code":"CZ",
    "gn:dem":297,
    "gn:feature_class":"P",
    "gn:feature_code":"PPL",
    "gn:name":"Sezemice",
    "gn:population":99,
    "gn:timezone":"Europe/Prague",
    "iso:country":"CZ",
    "name:azb_x_preferred":[
        "\u0633\u0632\u0645\u06cc\u062a\u0633\u0647"
    ],
    "name:ces_x_preferred":[
        "Sezemice"
    ],
    "name:eus_x_preferred":[
        "Sezemice"
    ],
    "name:fas_x_preferred":[
        "\u0633\u0632\u0645\u06cc\u062a\u0633\u0647"
    ],
    "name:hun_x_preferred":[
        "Sezemice"
    ],
    "name:ita_x_preferred":[
        "Sezemice"
    ],
    "name:msa_x_preferred":[
        "Sezemice"
    ],
    "name:nld_x_preferred":[
        "Sezemice"
    ],
    "name:pol_x_preferred":[
        "Sezemice"
    ],
    "name:por_x_preferred":[
        "Sezemice"
    ],
    "name:slk_x_preferred":[
        "Sezemice"
    ],
    "name:spa_x_preferred":[
        "Sezemice"
    ],
    "name:srp_x_preferred":[
        "\u0421\u0435\u0437\u0435\u043c\u0438\u0446\u0435"
    ],
    "name:vie_x_preferred":[
        "Sezemice"
    ],
    "wof:name":"Sezemice",
    "wof:placetype":"locality",
    "wof:population":99
},
  "geometry": {"coordinates":[15.00509,50.58555],"type":"Point"}
}