{
  "type": "Feature",
  "properties": {
    "gn:admin1_code":"88.0",
    "gn:admin2_code":"0207",
    "gn:asciiname":"Sezemice",
    "gn:country_code":"CZ",
    "gn:dem":297,
    "gn:feature_class":"P",
    "gn:feature_code":"PPL",
    "gn:name":"Sezemice",
    "gn:population":99,
    "gn:timezone":"Europe/Prague",
    "iso:country":"CZ",
    "wof:name":"Sezemice",
    "wof:placetype":"locality",
    "wof:population":99
},
  "geometry": {"coordinates":[15.00509,50.58555],"type":"Point"}
}