{
  "type": "Feature",
  "properties": {
    "gn:admin1_code":"88.0",
    "gn:admin2_code":"0201",
    "gn:asciiname":"Lhota Veselka",
    "gn:country_code":"CZ",
    "gn:dem":407,
    "gn:feature_class":"P",
    "gn:feature_code":"PPL",
    "gn:name":"Lhota Veselka",
    "gn:population":0,
    "gn:timezone":"Europe/Prague",
    "iso:country":"CZ",
    "wof:name":"Lhota Veselka",
    "wof:placetype":"locality"
},
  "geometry": {"coordinates":[14.79897,49.72671],"type":"Point"}
}