{
  "type": "Feature",
  "properties": {
    "gn:admin1_code":"80.0",
    "gn:admin2_code":"0615",
    "gn:asciiname":"Nove Sady u Velke Bitese",
    "gn:country_code":"CZ",
    "gn:dem":517,
    "gn:feature_class":"P",
    "gn:feature_code":"PPL",
    "gn:name":"Nov\u00e9 Sady u Velk\u00e9 B\u00edte\u0161e",
    "gn:population":0,
    "gn:timezone":"Europe/Prague",
    "iso:country":"CZ",
    "name:deu_x_preferred":[
        "Nov\u00e9 Sady u Velk\u00e9 B\u00edte\u0161e"
    ],
    "wof:name":"Nove Sady u Velke Bitese",
    "wof:placetype":"locality"
},
  "geometry": {"coordinates":[16.18829,49.29285],"type":"Point"}
}