{
  "type": "Feature",
  "properties": {
    "gn:admin1_code":"81.0",
    "gn:admin2_code":"0411",
    "gn:asciiname":"Haj",
    "gn:country_code":"CZ",
    "gn:dem":667,
    "gn:feature_class":"P",
    "gn:feature_code":"PPL",
    "gn:name":"H\u00e1j",
    "gn:population":0,
    "gn:timezone":"Europe/Prague",
    "iso:country":"CZ",
    "name:und_x_variant":[
        "Grafengr\u00fcn",
        "H\u00e1j"
    ],
    "wof:name":"Haj",
    "wof:placetype":"locality"
},
  "geometry": {"coordinates":[12.54064,49.96396],"type":"Point"}
}