{
  "type": "Feature",
  "properties": {
    "gn:admin1_code":"84.0",
    "gn:admin2_code":"0712",
    "gn:asciiname":"Dremovice",
    "gn:country_code":"CZ",
    "gn:dem":521,
    "gn:feature_class":"P",
    "gn:feature_code":"PPL",
    "gn:name":"D\u0159emovice",
    "gn:population":0,
    "gn:timezone":"Europe/Prague",
    "iso:country":"CZ",
    "name:und_x_variant":[
        "Dr\u00f6msdorf",
        "D\u0159emovice"
    ],
    "wof:name":"Dremovice",
    "wof:placetype":"locality"
},
  "geometry": {"coordinates":[17.52119,49.71667],"type":"Point"}
}