{
  "type": "Feature",
  "properties": {
    "gn:admin1_code":"81.0",
    "gn:admin2_code":"0412",
    "gn:asciiname":"Nova Viska",
    "gn:cc2":"CZ",
    "gn:country_code":"CZ",
    "gn:dem":617,
    "gn:feature_class":"P",
    "gn:feature_code":"PPL",
    "gn:name":"Nov\u00e1 V\u00edska",
    "gn:population":0,
    "gn:timezone":"Europe/Prague",
    "iso:country":"CZ",
    "name:und_x_variant":[
        "Neud\u00f6rfel"
    ],
    "wof:name":"Nova Viska",
    "wof:placetype":"locality"
},
  "geometry": {"coordinates":[12.98429,50.17899],"type":"Point"}
}