{
  "type": "Feature",
  "properties": {
    "gn:admin1_code":"80.0",
    "gn:admin2_code":"0614",
    "gn:asciiname":"Okrasovice",
    "gn:country_code":"CZ",
    "gn:dem":497,
    "gn:feature_class":"P",
    "gn:feature_code":"PPL",
    "gn:name":"Okra\u0161ovice",
    "gn:population":0,
    "gn:timezone":"Europe/Prague",
    "iso:country":"CZ",
    "wof:name":"Okrasovice",
    "wof:placetype":"locality"
},
  "geometry": {"coordinates":[15.95759,49.18465],"type":"Point"}
}