{
  "type": "Feature",
  "properties": {
    "gn:admin1_code":"88.0",
    "gn:admin2_code":"020A",
    "gn:asciiname":"Skochovice",
    "gn:cc2":"CZ",
    "gn:country_code":"CZ",
    "gn:dem":207,
    "gn:feature_class":"P",
    "gn:feature_code":"PPL",
    "gn:name":"Skochovice",
    "gn:population":0,
    "gn:timezone":"Europe/Prague",
    "iso:country":"CZ",
    "name:und_x_variant":[
        "Skochowitz"
    ],
    "wof:name":"Skochovice",
    "wof:placetype":"locality"
},
  "geometry": {"coordinates":[14.37389,49.9265],"type":"Point"}
}