{
  "type": "Feature",
  "properties": {
    "gn:country":"CZ",
    "gn:fcode":"PPL",
    "gn:population":152,
    "iso:country":"CZ",
    "name:azb_x_preferred":[
        "\u0633\u062a\u0631\u0627\u062e\u0648\u06cc\u0648\u0648"
    ],
    "name:cat_x_preferred":[
        "Strachujov"
    ],
    "name:ceb_x_preferred":[
        "Strachujov"
    ],
    "name:ces_x_preferred":[
        "Strachujov"
    ],
    "name:deu_x_preferred":[
        "Strachujov"
    ],
    "name:eng_x_preferred":[
        "Strachujov"
    ],
    "name:eus_x_preferred":[
        "Strachujov"
    ],
    "name:fas_x_preferred":[
        "\u0633\u062a\u0631\u0627\u062e\u0648\u06cc\u0648\u0648"
    ],
    "name:fra_x_preferred":[
        "Strachujov"
    ],
    "name:hun_x_preferred":[
        "Strachujov"
    ],
    "name:ita_x_preferred":[
        "Strachujov"
    ],
    "name:msa_x_preferred":[
        "Strachujov"
    ],
    "name:nan_x_preferred":[
        "Strachujov"
    ],
    "name:nld_x_preferred":[
        "Strachujov"
    ],
    "name:oci_x_preferred":[
        "Strachujov"
    ],
    "name:por_x_preferred":[
        "Strachujov"
    ],
    "name:rup_x_preferred":[
        "Strachujov"
    ],
    "name:slk_x_preferred":[
        "Strachujov"
    ],
    "name:spa_x_preferred":[
        "Strachujov"
    ],
    "name:swe_x_preferred":[
        "Strachujov"
    ],
    "name:vie_x_preferred":[
        "Strachujov"
    ],
    "qs_pg:aaroncc":"CZ",
    "qs_pg:gn_country":"CZ",
    "qs_pg:gn_fcode":"PPL",
    "qs_pg:gn_pop":152,
    "qs_pg:name":"Strachujov",
    "qs_pg:name_adm0":"\u010cesk\u00e1 republika",
    "qs_pg:name_adm1":"Kraj Vyso\u010dina",
    "qs_pg:photos_9r":0,
    "qs_pg:photos_sr":0,
    "qs_pg:pop_sr":1,
    "qs_pg:qs_pg_placetype":"locality",
    "qs_pg:qs_pg_placetype_gp":"Town",
    "qs_pg:woe_adm0":23424810,
    "woe:adm0_id":23424810,
    "woe:name_adm0":"\u010cesk\u00e1 republika",
    "woe:name_adm1":"Kraj Vyso\u010dina",
    "woe:placetype":"Town",
    "wof:name":"Strachujov",
    "wof:placetype":"locality",
    "wof:population":152
},
  "geometry": {"coordinates":[16.22676,49.6131],"type":"Point"}
}