{
  "type": "Feature",
  "properties": {
    "gn:admin1_code":"81.0",
    "gn:admin2_code":"0412",
    "gn:asciiname":"Jirov",
    "gn:country_code":"CZ",
    "gn:dem":838,
    "gn:feature_class":"P",
    "gn:feature_code":"PPL",
    "gn:name":"J\u00edrov",
    "gn:population":0,
    "gn:timezone":"Europe/Prague",
    "iso:country":"CZ",
    "name:und_x_variant":[
        "Jurau",
        "J\u00edrov"
    ],
    "wof:name":"Jirov",
    "wof:placetype":"locality"
},
  "geometry": {"coordinates":[13.14345,50.21913],"type":"Point"}
}