{
  "type": "Feature",
  "properties": {
    "gn:admin1_code":"52.0",
    "gn:asciiname":"Katerinky",
    "gn:country_code":"CZ",
    "gn:dem":302,
    "gn:feature_class":"P",
    "gn:feature_code":"PPL",
    "gn:name":"Kate\u0159inky",
    "gn:population":0,
    "gn:timezone":"Europe/Prague",
    "iso:country":"CZ",
    "name:ces_x_preferred":[
        "Kate\u0159inky"
    ],
    "wof:name":"Katerinky",
    "wof:placetype":"locality"
},
  "geometry": {"coordinates":[14.52198,50.02409],"type":"Point"}
}