{
  "type": "Feature",
  "properties": {
    "gn:admin1_code":"79",
    "gn:admin2_code":"0314",
    "gn:asciiname":"Vesec",
    "gn:country_code":"CZ",
    "gn:dem":490,
    "gn:feature_class":"P",
    "gn:feature_code":"PPL",
    "gn:name":"Vesec",
    "gn:population":0,
    "gn:timezone":"Europe/Prague",
    "iso:country":"CZ",
    "wof:name":"Vesec",
    "wof:placetype":"locality"
},
  "geometry": {"coordinates":[14.2585,49.51335],"type":"Point"}
}