{
  "type": "Feature",
  "properties": {
    "gn:admin1_code":"79.0",
    "gn:admin2_code":"0315",
    "gn:asciiname":"Bolikovice",
    "gn:country_code":"CZ",
    "gn:dem":700,
    "gn:feature_class":"P",
    "gn:feature_code":"PPL",
    "gn:name":"Bol\u00edkovice",
    "gn:population":0,
    "gn:timezone":"Europe/Prague",
    "iso:country":"CZ",
    "wof:name":"Bolikovice",
    "wof:placetype":"locality"
},
  "geometry": {"coordinates":[13.89995,49.08953],"type":"Point"}
}