{
  "type": "Feature",
  "properties": {
    "iso:country":"CZ",
    "name:ceb_x_preferred":[
        "Osoblaha"
    ],
    "name:ces_x_preferred":[
        "Osoblaha"
    ],
    "name:deu_x_preferred":[
        "Osoblaha"
    ],
    "name:epo_x_preferred":[
        "Osoblaha"
    ],
    "name:eus_x_preferred":[
        "Osoblaha"
    ],
    "name:fas_x_preferred":[
        "\u0627\u0648\u0633\u0648\u0628\u0644\u0627\u0647\u0627"
    ],
    "name:fra_x_preferred":[
        "Osoblaha"
    ],
    "name:hun_x_preferred":[
        "Osoblaha"
    ],
    "name:ita_x_preferred":[
        "Osoblaha"
    ],
    "name:msa_x_preferred":[
        "Osoblaha"
    ],
    "name:nld_x_preferred":[
        "Osoblaha"
    ],
    "name:pol_x_preferred":[
        "Osob\u0142oga"
    ],
    "name:por_x_preferred":[
        "Osoblaha"
    ],
    "name:rus_x_preferred":[
        "\u041e\u0441\u043e\u0431\u043b\u0430\u0433\u0430"
    ],
    "name:slk_x_preferred":[
        "Osoblaha"
    ],
    "name:spa_x_preferred":[
        "Osoblaha"
    ],
    "name:srp_x_preferred":[
        "\u041e\u0441\u043e\u0431\u043b\u0430\u0445\u0430"
    ],
    "name:swe_x_preferred":[
        "Osoblaha"
    ],
    "name:vie_x_preferred":[
        "Osoblaha"
    ],
    "qs_pg:aaroncc":"CZ",
    "qs_pg:name":"Osoblaha",
    "qs_pg:name_adm0":"\u010cesk\u00e1 republika",
    "qs_pg:name_adm1":"Moravskoslezsk\u00fd kraj",
    "qs_pg:photos":1,
    "qs_pg:photos_1k":1,
    "qs_pg:photos_9k":1,
    "qs_pg:photos_9r":2,
    "qs_pg:photos_all":36,
    "qs_pg:photos_sr":1,
    "qs_pg:pop_sr":0,
    "qs_pg:qs_pg_placetype":"localadmin",
    "qs_pg:qs_pg_placetype_gp":"LocalAdmin",
    "qs_pg:woe_adm0":23424810,
    "woe:adm0_id":23424810,
    "woe:name_adm0":"\u010cesk\u00e1 republika",
    "woe:name_adm1":"Moravskoslezsk\u00fd kraj",
    "woe:placetype":"LocalAdmin",
    "wof:name":"Osoblaha",
    "wof:placetype":"localadmin"
},
  "geometry": {"coordinates":[17.72232,50.269044],"type":"Point"}
}