{
  "type": "Feature",
  "properties": {
    "gn:country":"CZ",
    "gn:fcode":"PPL",
    "gn:population":834,
    "iso:country":"CZ",
    "name:azb_x_preferred":[
        "\u0628\u0646\u0634\u0648\u0641 \u0648 \u0633\u0645\u06cc\u0644"
    ],
    "name:cat_x_preferred":[
        "Bene\u0161ov u Semil"
    ],
    "name:ceb_x_preferred":[
        "Bene\u0161ov u Semil"
    ],
    "name:ces_x_preferred":[
        "Bene\u0161ov u Semil"
    ],
    "name:che_x_preferred":[
        "\u0411\u0435\u043d\u0435\u0448\u043e\u0432 \u0421\u0435\u043c\u0438\u043b"
    ],
    "name:deu_x_preferred":[
        "Bene\u0161ov u Semil"
    ],
    "name:eng_x_preferred":[
        "Bene\u0161ov u Semil"
    ],
    "name:epo_x_preferred":[
        "Bene\u0161ov u Semil"
    ],
    "name:eus_x_preferred":[
        "Bene\u0161ov u Semil"
    ],
    "name:fas_x_preferred":[
        "\u0628\u0646\u0634\u0648\u0641 \u0648 \u0633\u0645\u06cc\u0644"
    ],
    "name:fra_x_preferred":[
        "Bene\u0161ov u Semil"
    ],
    "name:gle_x_preferred":[
        "Bene\u0161ov u Semil"
    ],
    "name:hun_x_preferred":[
        "Bene\u0161ov u Semil"
    ],
    "name:ita_x_preferred":[
        "Bene\u0161ov u Semil"
    ],
    "name:lmo_x_preferred":[
        "Bene\u0161ov u Semil"
    ],
    "name:msa_x_preferred":[
        "Bene\u0161ov u Semil"
    ],
    "name:nan_x_preferred":[
        "Bene\u0161ov u Semil"
    ],
    "name:nld_x_preferred":[
        "Bene\u0161ov u Semil"
    ],
    "name:pol_x_preferred":[
        "Bene\u0161ov u Semil"
    ],
    "name:por_x_preferred":[
        "Bene\u0161ov u Semil"
    ],
    "name:rup_x_preferred":[
        "Bene\u0161ov u Semil"
    ],
    "name:slk_x_preferred":[
        "Bene\u0161ov u Semil"
    ],
    "name:spa_x_preferred":[
        "Bene\u0161ov u Semil"
    ],
    "name:srp_x_preferred":[
        "\u0411\u0435\u043d\u0435\u0448\u043e\u0432 \u0443 \u0421\u0435\u043c\u0438\u043b\u0443"
    ],
    "name:swe_x_preferred":[
        "Bene\u0161ov u Semil"
    ],
    "name:tat_x_preferred":[
        "\u0411\u0435\u043d\u0435\u0448\u043e\u0432 \u0421\u0435\u043c\u0438\u043b"
    ],
    "name:vie_x_preferred":[
        "Bene\u0161ov u Semil"
    ],
    "qs_pg:aaroncc":"CZ",
    "qs_pg:gn_country":"CZ",
    "qs_pg:gn_fcode":"PPL",
    "qs_pg:gn_pop":834,
    "qs_pg:name":"Bene\u0161ov u Semil",
    "qs_pg:name_adm0":"\u010cesk\u00e1 republika",
    "qs_pg:name_adm1":"Libereck\u00fd kraj",
    "qs_pg:photos_9r":0,
    "qs_pg:photos_sr":0,
    "qs_pg:pop_sr":2,
    "qs_pg:qs_pg_placetype":"locality",
    "qs_pg:qs_pg_placetype_gp":"Town",
    "qs_pg:woe_adm0":23424810,
    "woe:adm0_id":23424810,
    "woe:name_adm0":"\u010cesk\u00e1 republika",
    "woe:name_adm1":"Libereck\u00fd kraj",
    "woe:placetype":"Town",
    "wof:name":"Bene\u0161ov u Semil",
    "wof:placetype":"locality",
    "wof:population":834
},
  "geometry": {"coordinates":[15.36837,50.60316],"type":"Point"}
}