{
  "type": "Feature",
  "properties": {
    "gn:admin1_code":"79.0",
    "gn:admin2_code":"0317",
    "gn:asciiname":"Elbancice",
    "gn:country_code":"CZ",
    "gn:dem":482,
    "gn:feature_class":"P",
    "gn:feature_code":"PPL",
    "gn:name":"Elban\u010dice",
    "gn:population":0,
    "gn:timezone":"Europe/Prague",
    "iso:country":"CZ",
    "wof:name":"Elbancice",
    "wof:placetype":"locality"
},
  "geometry": {"coordinates":[14.85596,49.54978],"type":"Point"}
}