{
  "type": "Feature",
  "properties": {
    "gn:admin1_code":"89",
    "gn:admin2_code":"0423",
    "gn:asciiname":"Vojnicky",
    "gn:country_code":"CZ",
    "gn:dem":195,
    "gn:feature_class":"P",
    "gn:feature_code":"PPL",
    "gn:name":"Vojni\u010dky",
    "gn:population":0,
    "gn:timezone":"Europe/Prague",
    "iso:country":"CZ",
    "wof:name":"Vojnicky",
    "wof:placetype":"locality"
},
  "geometry": {"coordinates":[13.93054,50.42848],"type":"Point"}
}