{
  "type": "Feature",
  "properties": {
    "gn:admin1_code":"83.0",
    "gn:admin2_code":"0511",
    "gn:asciiname":"Palohlavy",
    "gn:country_code":"CZ",
    "gn:dem":377,
    "gn:feature_class":"P",
    "gn:feature_code":"PPL",
    "gn:name":"Palohlavy",
    "gn:population":0,
    "gn:timezone":"Europe/Prague",
    "iso:country":"CZ",
    "name:und_x_variant":[
        "Halbehapt",
        "Palohlavy"
    ],
    "wof:name":"Palohlavy",
    "wof:placetype":"locality"
},
  "geometry": {"coordinates":[14.87316,50.6435],"type":"Point"}
}