{
  "type": "Feature",
  "properties": {
    "gn:gn_country":"CZ",
    "gn:gn_fcode":"PPL",
    "gn:gn_pop":236,
    "gn:population":236,
    "iso:country":"CZ",
    "name:azb_x_preferred":[
        "\u0698\u06cc\u062f\u0646\u06cc\u0648\u0633"
    ],
    "name:ceb_x_preferred":[
        "\u017didn\u011bves"
    ],
    "name:ces_x_preferred":[
        "\u017didn\u011bves"
    ],
    "name:deu_x_preferred":[
        "\u017didn\u011bves"
    ],
    "name:eng_x_preferred":[
        "\u017didn\u011bves"
    ],
    "name:eus_x_preferred":[
        "\u017didn\u011bves"
    ],
    "name:fas_x_preferred":[
        "\u0698\u06cc\u062f\u0646\u06cc\u0648\u0633"
    ],
    "name:fra_x_preferred":[
        "\u017didn\u011bves"
    ],
    "name:hun_x_preferred":[
        "\u017didn\u011bves"
    ],
    "name:ita_x_preferred":[
        "\u017didn\u011bves"
    ],
    "name:msa_x_preferred":[
        "\u017didn\u011bves"
    ],
    "name:nan_x_preferred":[
        "\u017didn\u011bves"
    ],
    "name:nld_x_preferred":[
        "\u017didn\u011bves"
    ],
    "name:pol_x_preferred":[
        "\u017didn\u011bves"
    ],
    "name:por_x_preferred":[
        "\u017didn\u011bves"
    ],
    "name:rup_x_preferred":[
        "\u017didn\u011bves"
    ],
    "name:rus_x_preferred":[
        "\u0416\u0438\u0434\u043d\u0435\u0432\u0435\u0441"
    ],
    "name:slk_x_preferred":[
        "\u017didn\u011bves"
    ],
    "name:spa_x_preferred":[
        "\u017didn\u011bves"
    ],
    "name:srp_x_preferred":[
        "\u0416\u0438\u0434\u045a\u0435\u0432\u0435\u0441"
    ],
    "name:swe_x_preferred":[
        "\u017didn\u011bves"
    ],
    "name:vie_x_preferred":[
        "\u017didn\u011bves"
    ],
    "qs_pg:aaroncc":"CZ",
    "qs_pg:gn_country":"CZ",
    "qs_pg:gn_fcode":"PPL",
    "qs_pg:gn_pop":236,
    "qs_pg:name":"\u017didn\u011bves",
    "qs_pg:name_adm0":"\u010cesk\u00e1 republika",
    "qs_pg:name_adm1":"St\u0159edo\u010desk\u00fd kraj",
    "qs_pg:photos_9r":0,
    "qs_pg:photos_sr":0,
    "qs_pg:pop_sr":2,
    "qs_pg:qs_pg_placetype":"locality",
    "qs_pg:qs_pg_placetype_gp":"Town",
    "qs_pg:woe_adm0":23424810,
    "woe:adm0_id":23424810,
    "woe:name_adm0":"\u010cesk\u00e1 republika",
    "woe:name_adm1":"St\u0159edo\u010desk\u00fd kraj",
    "woe:placetype":"Town",
    "wof:name":"\u017didn\u011bves",
    "wof:placetype":"locality",
    "wof:population":236
},
  "geometry": {"coordinates":[14.99453,50.41163],"type":"Point"}
}