{
  "type": "Feature",
  "properties": {
    "gn:admin1_code":"80.0",
    "gn:admin2_code":"0611",
    "gn:asciiname":"Nemojov",
    "gn:country_code":"CZ",
    "gn:dem":568,
    "gn:feature_class":"P",
    "gn:feature_code":"PPL",
    "gn:name":"Nemojov",
    "gn:population":0,
    "gn:timezone":"Europe/Prague",
    "iso:country":"CZ",
    "name:und_x_variant":[
        "Dv\u016dr Nemojov",
        "Nemojov"
    ],
    "wof:name":"Nemojov",
    "wof:placetype":"locality"
},
  "geometry": {"coordinates":[15.66816,49.67735],"type":"Point"}
}