{
  "type": "Feature",
  "properties": {
    "gn:admin1_code":"78.0",
    "gn:admin2_code":"0626",
    "gn:asciiname":"Radslavice",
    "gn:country_code":"CZ",
    "gn:dem":331,
    "gn:feature_class":"P",
    "gn:feature_code":"PPL",
    "gn:name":"Radslavice",
    "gn:population":385,
    "gn:timezone":"Europe/Prague",
    "iso:country":"CZ",
    "wof:name":"Radslavice",
    "wof:placetype":"locality",
    "wof:population":385
},
  "geometry": {"coordinates":[17.00382999999999,49.32291],"type":"Point"}
}