{
  "type": "Feature",
  "properties": {
    "gn:admin1_code":"78.0",
    "gn:admin2_code":"0626",
    "gn:asciiname":"Radslavice",
    "gn:country_code":"CZ",
    "gn:dem":331,
    "gn:feature_class":"P",
    "gn:feature_code":"PPL",
    "gn:name":"Radslavice",
    "gn:population":385,
    "gn:timezone":"Europe/Prague",
    "iso:country":"CZ",
    "name:azb_x_preferred":[
        "\u0631\u0627\u062f\u0633\u0644\u0627\u0648\u06cc\u062a\u0633\u0647"
    ],
    "name:ceb_x_preferred":[
        "Radslavice"
    ],
    "name:ces_x_preferred":[
        "Radslavice"
    ],
    "name:eus_x_preferred":[
        "Radslavice"
    ],
    "name:fas_x_preferred":[
        "\u0631\u0627\u062f\u0633\u0644\u0627\u0648\u06cc\u062a\u0633\u0647"
    ],
    "name:hun_x_preferred":[
        "Radslavice"
    ],
    "name:ita_x_preferred":[
        "Radslavice"
    ],
    "name:msa_x_preferred":[
        "Radslavice"
    ],
    "name:nld_x_preferred":[
        "Radslavice"
    ],
    "name:slk_x_preferred":[
        "Radslavice"
    ],
    "name:spa_x_preferred":[
        "Radslavice"
    ],
    "name:srp_x_preferred":[
        "\u0420\u0430\u0434\u0441\u043b\u0430\u0432\u0438\u0446\u0435"
    ],
    "name:vie_x_preferred":[
        "Radslavice"
    ],
    "wof:name":"Radslavice",
    "wof:placetype":"locality",
    "wof:population":385
},
  "geometry": {"coordinates":[17.00382999999999,49.32291],"type":"Point"}
}