{
  "type": "Feature",
  "properties": {
    "gn:country":"CZ",
    "gn:fcode":"PPL",
    "gn:population":769,
    "iso:country":"CZ",
    "name:azb_x_preferred":[
        "\u062e\u0627\u0631\u0648\u0627\u062a\u06cc"
    ],
    "name:cat_x_preferred":[
        "Charv\u00e1ty"
    ],
    "name:ceb_x_preferred":[
        "Charv\u00e1ty"
    ],
    "name:ces_x_preferred":[
        "Charv\u00e1ty"
    ],
    "name:che_x_preferred":[
        "\u0425\u0430\u0440\u0432\u0430\u0442\u0438"
    ],
    "name:deu_x_preferred":[
        "Charv\u00e1ty"
    ],
    "name:eng_x_preferred":[
        "Charv\u00e1ty"
    ],
    "name:epo_x_preferred":[
        "Charv\u00e1ty"
    ],
    "name:eus_x_preferred":[
        "Charv\u00e1ty"
    ],
    "name:fas_x_preferred":[
        "\u062e\u0627\u0631\u0648\u0627\u062a\u06cc"
    ],
    "name:fra_x_preferred":[
        "Charv\u00e1ty"
    ],
    "name:gle_x_preferred":[
        "Charv\u00e1ty"
    ],
    "name:hrv_x_preferred":[
        "Charv\u00e1ty"
    ],
    "name:hun_x_preferred":[
        "Charv\u00e1ty"
    ],
    "name:ind_x_preferred":[
        "Charv\u00e1ty"
    ],
    "name:ita_x_preferred":[
        "Charv\u00e1ty"
    ],
    "name:lmo_x_preferred":[
        "Charv\u00e1ty"
    ],
    "name:msa_x_preferred":[
        "Charv\u00e1ty"
    ],
    "name:nan_x_preferred":[
        "Charv\u00e1ty"
    ],
    "name:nld_x_preferred":[
        "Charv\u00e1ty"
    ],
    "name:pol_x_preferred":[
        "Charv\u00e1ty"
    ],
    "name:por_x_preferred":[
        "Charv\u00e1ty"
    ],
    "name:rup_x_preferred":[
        "Charv\u00e1ty"
    ],
    "name:slk_x_preferred":[
        "Charv\u00e1ty"
    ],
    "name:spa_x_preferred":[
        "Charv\u00e1ty"
    ],
    "name:srp_x_preferred":[
        "\u0425\u0430\u0440\u0432\u0430\u0442\u0438"
    ],
    "name:swe_x_preferred":[
        "Charv\u00e1ty"
    ],
    "name:tat_x_preferred":[
        "\u0425\u0430\u0440\u0432\u0430\u0442\u0438"
    ],
    "name:vie_x_preferred":[
        "Charv\u00e1ty"
    ],
    "qs_pg:aaroncc":"CZ",
    "qs_pg:gn_country":"CZ",
    "qs_pg:gn_fcode":"PPL",
    "qs_pg:gn_pop":769,
    "qs_pg:name":"Charv\u00e1ty",
    "qs_pg:name_adm0":"\u010cesk\u00e1 republika",
    "qs_pg:name_adm1":"Olomouck\u00fd kraj",
    "qs_pg:photos_9r":0,
    "qs_pg:photos_sr":0,
    "qs_pg:pop_sr":2,
    "qs_pg:qs_pg_placetype":"locality",
    "qs_pg:qs_pg_placetype_gp":"Town",
    "qs_pg:woe_adm0":23424810,
    "woe:adm0_id":23424810,
    "woe:name_adm0":"\u010cesk\u00e1 republika",
    "woe:name_adm1":"Olomouck\u00fd kraj",
    "woe:placetype":"Town",
    "wof:name":"Charv\u00e1ty",
    "wof:placetype":"locality",
    "wof:population":769
},
  "geometry": {"coordinates":[17.25396,49.51836],"type":"Point"}
}