{
  "type": "Feature",
  "properties": {
    "gn:admin1_code":"84",
    "gn:admin2_code":"0714",
    "gn:asciiname":"Zavadilka",
    "gn:country_code":"CZ",
    "gn:dem":384,
    "gn:feature_class":"P",
    "gn:feature_code":"PPL",
    "gn:name":"Zavadilka",
    "gn:population":0,
    "gn:timezone":"Europe/Prague",
    "iso:country":"CZ",
    "wof:name":"Zavadilka",
    "wof:placetype":"locality"
},
  "geometry": {"coordinates":[17.50893,49.55929],"type":"Point"}
}