{
  "type": "Feature",
  "properties": {
    "gn:admin1_code":"79.0",
    "gn:admin2_code":"0317",
    "gn:asciiname":"Dolni Svetla",
    "gn:country_code":"CZ",
    "gn:dem":583,
    "gn:feature_class":"P",
    "gn:feature_code":"PPL",
    "gn:name":"Doln\u00ed Sv\u011btl\u00e1",
    "gn:population":0,
    "gn:timezone":"Europe/Prague",
    "iso:country":"CZ",
    "wof:name":"Dolni Svetla",
    "wof:placetype":"locality"
},
  "geometry": {"coordinates":[14.90038,49.48536],"type":"Point"}
}