{
  "type": "Feature",
  "properties": {
    "gn:admin1_code":"90",
    "gn:admin2_code":"0721",
    "gn:asciiname":"Zlamanka",
    "gn:country_code":"CZ",
    "gn:dem":225,
    "gn:feature_class":"P",
    "gn:feature_code":"PPL",
    "gn:name":"Zl\u00e1manka",
    "gn:population":0,
    "gn:timezone":"Europe/Prague",
    "iso:country":"CZ",
    "wof:name":"Zlamanka",
    "wof:placetype":"locality"
},
  "geometry": {"coordinates":[17.37689,49.23912],"type":"Point"}
}