{
  "type": "Feature",
  "properties": {
    "gn:admin1_code":"79.0",
    "gn:admin2_code":"0312",
    "gn:asciiname":"Daleke Popelice",
    "gn:country_code":"CZ",
    "gn:dem":764,
    "gn:feature_class":"P",
    "gn:feature_code":"PPL",
    "gn:name":"Dalek\u00e9 Popelice",
    "gn:population":0,
    "gn:timezone":"Europe/Prague",
    "iso:country":"CZ",
    "wof:name":"Daleke Popelice",
    "wof:placetype":"locality"
},
  "geometry": {"coordinates":[14.59787,48.76103],"type":"Point"}
}