{
  "type": "Feature",
  "properties": {
    "gn:admin1_code":"81.0",
    "gn:admin2_code":"0412",
    "gn:asciiname":"Cankov",
    "gn:country_code":"CZ",
    "gn:dem":426,
    "gn:feature_class":"P",
    "gn:feature_code":"PPL",
    "gn:name":"\u010cankov",
    "gn:population":0,
    "gn:timezone":"Europe/Prague",
    "iso:country":"CZ",
    "name:und_x_variant":[
        "Schankau",
        "\u010cankov"
    ],
    "wof:name":"Cankov",
    "wof:placetype":"locality"
},
  "geometry": {"coordinates":[12.84889,50.25925],"type":"Point"}
}