{
  "type": "Feature",
  "properties": {
    "gn:gn_country":"CZ",
    "gn:gn_fcode":"PPL",
    "gn:gn_pop":831,
    "gn:population":831,
    "iso:country":"CZ",
    "name:unk_x_variant":[
        "Neuhof"
    ],
    "qs_pg:aaroncc":"CZ",
    "qs_pg:gn_country":"CZ",
    "qs_pg:gn_fcode":"PPL",
    "qs_pg:gn_pop":831,
    "qs_pg:name":"Nov\u00e9 Dvory",
    "qs_pg:photos_9r":0,
    "qs_pg:photos_sr":0,
    "qs_pg:pop_sr":2,
    "qs_pg:qs_pg_placetype":"locality",
    "wof:name":"Nov\u00e9 Dvory",
    "wof:placetype":"locality",
    "wof:population":831
},
  "geometry": {"coordinates":[15.3279,49.96821],"type":"Point"}
}