{
  "type": "Feature",
  "properties": {
    "gn:gn_country":"CZ",
    "gn:gn_fcode":"PPL",
    "gn:gn_pop":438,
    "gn:population":438,
    "iso:country":"CZ",
    "name:ceb_x_preferred":[
        "Kojetice"
    ],
    "name:ces_x_preferred":[
        "Kojetice"
    ],
    "name:deu_x_preferred":[
        "Kojetice na Morav\u011b"
    ],
    "name:eng_x_preferred":[
        "Kojetice"
    ],
    "name:eus_x_preferred":[
        "Kojetice"
    ],
    "name:fas_x_preferred":[
        "\u06a9\u0648\u06cc\u062a\u06cc\u062a\u0633\u0647"
    ],
    "name:fra_x_preferred":[
        "Kojetice"
    ],
    "name:heb_x_preferred":[
        "\u05e7\u05d5\u05d9\u05d9\u05d8\u05d9\u05e6\u05d4"
    ],
    "name:hun_x_preferred":[
        "Kojetice"
    ],
    "name:ita_x_preferred":[
        "Kojetice"
    ],
    "name:msa_x_preferred":[
        "Kojetice"
    ],
    "name:nan_x_preferred":[
        "Kojetice"
    ],
    "name:nld_x_preferred":[
        "Kojetice"
    ],
    "name:nob_x_preferred":[
        "Kojetice"
    ],
    "name:por_x_preferred":[
        "Kojetice"
    ],
    "name:rup_x_preferred":[
        "Kojetice"
    ],
    "name:slk_x_preferred":[
        "Kojetice"
    ],
    "name:spa_x_preferred":[
        "Kojetice"
    ],
    "name:swe_x_preferred":[
        "Kojetice"
    ],
    "name:vie_x_preferred":[
        "Kojetice"
    ],
    "qs_pg:aaroncc":"CZ",
    "qs_pg:gn_country":"CZ",
    "qs_pg:gn_fcode":"PPL",
    "qs_pg:gn_pop":438,
    "qs_pg:name":"Kojetice",
    "qs_pg:name_adm0":"\u010cesk\u00e1 republika",
    "qs_pg:name_adm1":"Kraj Vyso\u010dina",
    "qs_pg:photos_9r":0,
    "qs_pg:photos_sr":0,
    "qs_pg:pop_sr":2,
    "qs_pg:qs_pg_placetype":"locality",
    "qs_pg:qs_pg_placetype_gp":"Town",
    "qs_pg:woe_adm0":23424810,
    "woe:adm0_id":23424810,
    "woe:name_adm0":"\u010cesk\u00e1 republika",
    "woe:name_adm1":"Kraj Vyso\u010dina",
    "woe:placetype":"Town",
    "wof:name":"Kojetice",
    "wof:placetype":"locality",
    "wof:population":438
},
  "geometry": {"coordinates":[15.81804,49.15782],"type":"Point"}
}