{
  "type": "Feature",
  "properties": {
    "gn:admin1_code":"79.0",
    "gn:admin2_code":"0314",
    "gn:asciiname":"Bilina",
    "gn:country_code":"CZ",
    "gn:dem":463,
    "gn:feature_class":"P",
    "gn:feature_code":"PPL",
    "gn:name":"B\u00edlina",
    "gn:population":0,
    "gn:timezone":"Europe/Prague",
    "iso:country":"CZ",
    "name:ceb_x_preferred":[
        "Bilina"
    ],
    "name:deu_x_preferred":[
        "Bilina"
    ],
    "name:pol_x_preferred":[
        "Bilina"
    ],
    "name:ron_x_preferred":[
        "Bilina"
    ],
    "name:rus_x_preferred":[
        "\u0411\u0438\u043b\u0438\u043d\u0430"
    ],
    "name:swe_x_preferred":[
        "Bilina"
    ],
    "name:ukr_x_preferred":[
        "\u0411\u0456\u043b\u0456\u043d\u0430"
    ],
    "wof:name":"Bilina",
    "wof:placetype":"locality"
},
  "geometry": {"coordinates":[14.36565,49.38176],"type":"Point"}
}