{
  "type": "Feature",
  "properties": {
    "gn:admin1_code":"86.0",
    "gn:admin2_code":"0531",
    "gn:asciiname":"Rychnov",
    "gn:country_code":"CZ",
    "gn:dem":555,
    "gn:feature_class":"P",
    "gn:feature_code":"PPL",
    "gn:name":"Rychnov",
    "gn:population":0,
    "gn:timezone":"Europe/Prague",
    "iso:country":"CZ",
    "name:ces_x_preferred":[
        "Rychnov"
    ],
    "name:deu_x_preferred":[
        "Rychnov"
    ],
    "wof:name":"Rychnov",
    "wof:placetype":"locality"
},
  "geometry": {"coordinates":[16.06707,49.77626],"type":"Point"}
}