{
  "type": "Feature",
  "properties": {
    "gn:admin1_code":"87.0",
    "gn:admin2_code":"0324",
    "gn:asciiname":"Hradist'ska Lhotka",
    "gn:country_code":"CZ",
    "gn:dem":492,
    "gn:feature_class":"P",
    "gn:feature_code":"PPL",
    "gn:name":"Hradi\u0161\u0165sk\u00e1 Lhotka",
    "gn:population":0,
    "gn:timezone":"Europe/Prague",
    "iso:country":"CZ",
    "wof:name":"Hradist'ska Lhotka",
    "wof:placetype":"locality"
},
  "geometry": {"coordinates":[13.58653,49.5662],"type":"Point"}
}