{
  "type": "Feature",
  "properties": {
    "gn:admin1_code":"87.0",
    "gn:admin2_code":"0322",
    "gn:asciiname":"Petrovice",
    "gn:country_code":"CZ",
    "gn:dem":578,
    "gn:feature_class":"P",
    "gn:feature_code":"PPL",
    "gn:name":"Petrovice",
    "gn:population":0,
    "gn:timezone":"Europe/Prague",
    "iso:country":"CZ",
    "name:bos_x_preferred":[
        "Petrovice"
    ],
    "name:ceb_x_preferred":[
        "Petrovice"
    ],
    "name:ces_x_preferred":[
        "Petrovice"
    ],
    "name:deu_x_preferred":[
        "Petrovice"
    ],
    "name:epo_x_preferred":[
        "Petrovice"
    ],
    "name:fra_x_preferred":[
        "Petrovice"
    ],
    "name:ita_x_preferred":[
        "Petrovice"
    ],
    "name:nld_x_preferred":[
        "Petrovice"
    ],
    "name:pol_x_preferred":[
        "Petrovice"
    ],
    "name:slk_x_preferred":[
        "Petrovice"
    ],
    "name:srp_x_preferred":[
        "\u041f\u0435\u0442\u0440\u043e\u0432\u0438\u0446\u0435"
    ],
    "name:swe_x_preferred":[
        "Petrovice"
    ],
    "name:und_x_variant":[
        "Petrowitz",
        "Petrovice"
    ],
    "wof:name":"Petrovice",
    "wof:placetype":"locality"
},
  "geometry": {"coordinates":[13.44194,49.21872000000001],"type":"Point"}
}