{
  "type": "Feature",
  "properties": {
    "gn:gn_country":"CZ",
    "gn:gn_fcode":"PPL",
    "gn:gn_pop":1212,
    "gn:population":1212,
    "iso:country":"CZ",
    "name:azb_x_preferred":[
        "\u062a\u0634\u062a\u06cc\u06a9"
    ],
    "name:ceb_x_preferred":[
        "Te\u0161etice"
    ],
    "name:ces_x_preferred":[
        "T\u011b\u0161etice"
    ],
    "name:eng_x_preferred":[
        "T\u011b\u0161etice"
    ],
    "name:eus_x_preferred":[
        "T\u011b\u0161etice"
    ],
    "name:fas_x_preferred":[
        "\u062a\u0634\u062a\u06cc\u06a9"
    ],
    "name:fra_x_preferred":[
        "T\u011b\u0161etice"
    ],
    "name:hun_x_preferred":[
        "T\u011b\u0161etice"
    ],
    "name:ita_x_preferred":[
        "T\u011b\u0161etice"
    ],
    "name:msa_x_preferred":[
        "T\u011b\u0161etice"
    ],
    "name:nan_x_preferred":[
        "T\u011b\u0161etice"
    ],
    "name:nld_x_preferred":[
        "T\u011b\u0161etice"
    ],
    "name:pol_x_preferred":[
        "T\u011b\u0161etice"
    ],
    "name:por_x_preferred":[
        "T\u011b\u0161etice"
    ],
    "name:rup_x_preferred":[
        "T\u011b\u0161etice"
    ],
    "name:slk_x_preferred":[
        "T\u011b\u0161etice"
    ],
    "name:spa_x_preferred":[
        "T\u011b\u0161etice"
    ],
    "name:srp_x_preferred":[
        "\u0422\u0458\u0435\u0448\u0435\u0442\u0438\u0446\u0435"
    ],
    "name:swe_x_preferred":[
        "Te\u0161etice"
    ],
    "name:vie_x_preferred":[
        "T\u011b\u0161etice"
    ],
    "qs_pg:aaroncc":"CZ",
    "qs_pg:gn_country":"CZ",
    "qs_pg:gn_fcode":"PPL",
    "qs_pg:gn_pop":1212,
    "qs_pg:name":"T\u011b\u0161etice",
    "qs_pg:name_adm0":"\u010cesk\u00e1 republika",
    "qs_pg:name_adm1":"Olomouck\u00fd kraj",
    "qs_pg:photos_9r":0,
    "qs_pg:photos_sr":0,
    "qs_pg:pop_sr":3,
    "qs_pg:qs_pg_placetype":"locality",
    "qs_pg:qs_pg_placetype_gp":"Town",
    "qs_pg:woe_adm0":23424810,
    "woe:adm0_id":23424810,
    "woe:name_adm0":"\u010cesk\u00e1 republika",
    "woe:name_adm1":"Olomouck\u00fd kraj",
    "woe:placetype":"Town",
    "wof:name":"T\u011b\u0161etice",
    "wof:placetype":"locality",
    "wof:population":1212
},
  "geometry": {"coordinates":[17.12607,49.59317],"type":"Point"}
}