{
  "type": "Feature",
  "properties": {
    "gn:admin1_code":"79",
    "gn:admin2_code":"0317",
    "gn:asciiname":"Stara Vozice",
    "gn:country_code":"CZ",
    "gn:dem":542,
    "gn:feature_class":"P",
    "gn:feature_code":"PPL",
    "gn:name":"Star\u00e1 Vo\u017eice",
    "gn:population":0,
    "gn:timezone":"Europe/Prague",
    "iso:country":"CZ",
    "wof:name":"Stara Vozice",
    "wof:placetype":"locality"
},
  "geometry": {"coordinates":[14.77336,49.50147],"type":"Point"}
}