{
  "type": "Feature",
  "properties": {
    "gn:admin1_code":"88.0",
    "gn:admin2_code":"0201",
    "gn:asciiname":"Martinice u Dolnich Kralovic",
    "gn:country_code":"CZ",
    "gn:dem":466,
    "gn:feature_class":"P",
    "gn:feature_code":"PPL",
    "gn:name":"Martinice u Doln\u00edch Kralovic",
    "gn:population":0,
    "gn:timezone":"Europe/Prague",
    "iso:country":"CZ",
    "wof:name":"Martinice u Dolnich Kralovic",
    "wof:placetype":"locality"
},
  "geometry": {"coordinates":[15.20419,49.64015],"type":"Point"}
}