{
  "type": "Feature",
  "properties": {
    "gn:admin1_code":"86.0",
    "gn:admin2_code":"0534",
    "gn:asciiname":"Hylvaty",
    "gn:country_code":"CZ",
    "gn:dem":440,
    "gn:feature_class":"P",
    "gn:feature_code":"PPL",
    "gn:name":"Hylv\u00e1ty",
    "gn:population":0,
    "gn:timezone":"Europe/Prague",
    "iso:country":"CZ",
    "name:und_x_variant":[
        "Hilbetten",
        "Hilbeten",
        "Hylv\u00e1ty"
    ],
    "wof:name":"Hylvaty",
    "wof:placetype":"locality"
},
  "geometry": {"coordinates":[16.38332999999999,49.95],"type":"Point"}
}