{
  "type": "Feature",
  "properties": {
    "gn:country":"CZ",
    "gn:fcode":"PPL",
    "gn:population":161,
    "iso:country":"CZ",
    "name:azb_x_preferred":[
        "\u067e\u0631\u06cc\u0644\u0648\u06a9\u0627"
    ],
    "name:cat_x_preferred":[
        "P\u0159\u00edluka"
    ],
    "name:ceb_x_preferred":[
        "P\u0159\u00edluka"
    ],
    "name:ces_x_preferred":[
        "P\u0159\u00edluka"
    ],
    "name:che_x_preferred":[
        "\u041f\u0440\u0436\u0438\u043b\u0443\u043a\u0430"
    ],
    "name:deu_x_preferred":[
        "P\u0159\u00edluka"
    ],
    "name:eng_x_preferred":[
        "P\u0159\u00edluka"
    ],
    "name:epo_x_preferred":[
        "P\u0159\u00edluka"
    ],
    "name:eus_x_preferred":[
        "P\u0159\u00edluka"
    ],
    "name:fas_x_preferred":[
        "\u067e\u0631\u06cc\u0644\u0648\u06a9\u0627"
    ],
    "name:fra_x_preferred":[
        "P\u0159\u00edluka"
    ],
    "name:gle_x_preferred":[
        "P\u0159\u00edluka"
    ],
    "name:hun_x_preferred":[
        "P\u0159\u00edluka"
    ],
    "name:ita_x_preferred":[
        "P\u0159\u00edluka"
    ],
    "name:lmo_x_preferred":[
        "P\u0159\u00edluka"
    ],
    "name:msa_x_preferred":[
        "P\u0159\u00edluka"
    ],
    "name:nan_x_preferred":[
        "P\u0159\u00edluka"
    ],
    "name:nld_x_preferred":[
        "P\u0159\u00edluka"
    ],
    "name:pol_x_preferred":[
        "P\u0159\u00edluka"
    ],
    "name:por_x_preferred":[
        "P\u0159\u00edluka"
    ],
    "name:slk_x_preferred":[
        "P\u0159\u00edluka"
    ],
    "name:spa_x_preferred":[
        "P\u0159\u00edluka"
    ],
    "name:srp_x_preferred":[
        "\u041f\u0440\u0438\u043b\u0443\u043a\u0430"
    ],
    "name:swe_x_preferred":[
        "P\u0159\u00edluka"
    ],
    "name:tat_x_preferred":[
        "\u041f\u0440\u0436\u0438\u043b\u0443\u043a\u0430"
    ],
    "name:vie_x_preferred":[
        "P\u0159\u00edluka"
    ],
    "qs_pg:aaroncc":"CZ",
    "qs_pg:gn_country":"CZ",
    "qs_pg:gn_fcode":"PPL",
    "qs_pg:gn_pop":161,
    "qs_pg:name":"P\u0159\u00edluka",
    "qs_pg:name_adm0":"\u010cesk\u00e1 republika",
    "qs_pg:name_adm1":"Pardubick\u00fd kraj",
    "qs_pg:photos_9r":0,
    "qs_pg:photos_sr":0,
    "qs_pg:pop_sr":1,
    "qs_pg:qs_pg_placetype":"locality",
    "qs_pg:qs_pg_placetype_gp":"Town",
    "qs_pg:woe_adm0":23424810,
    "woe:adm0_id":23424810,
    "woe:name_adm0":"\u010cesk\u00e1 republika",
    "woe:name_adm1":"Pardubick\u00fd kraj",
    "woe:placetype":"Town",
    "wof:name":"P\u0159\u00edluka",
    "wof:placetype":"locality",
    "wof:population":161
},
  "geometry": {"coordinates":[16.15653,49.86487],"type":"Point"}
}