{
  "type": "Feature",
  "properties": {
    "iso:country":"CZ",
    "name:azb_x_preferred":[
        "\u062f\u0648\u0628\u0631\u06cc\u0648"
    ],
    "name:ceb_x_preferred":[
        "Dob\u0159\u00edv"
    ],
    "name:ces_x_preferred":[
        "Dob\u0159\u00edv"
    ],
    "name:deu_x_preferred":[
        "Dob\u0159\u00edv"
    ],
    "name:eus_x_preferred":[
        "Dob\u0159\u00edv"
    ],
    "name:fas_x_preferred":[
        "\u062f\u0648\u0628\u0631\u06cc\u0648"
    ],
    "name:fra_x_preferred":[
        "Dob\u0159\u00edv"
    ],
    "name:hun_x_preferred":[
        "Dob\u0159\u00edv"
    ],
    "name:ita_x_preferred":[
        "Dob\u0159\u00edv"
    ],
    "name:msa_x_preferred":[
        "Dob\u0159\u00edv"
    ],
    "name:nld_x_preferred":[
        "Dob\u0159\u00edv"
    ],
    "name:pol_x_preferred":[
        "Dob\u0159\u00edv"
    ],
    "name:por_x_preferred":[
        "Dob\u0159\u00edv"
    ],
    "name:slk_x_preferred":[
        "Dob\u0159\u00edv"
    ],
    "name:spa_x_preferred":[
        "Dob\u0159\u00edv"
    ],
    "name:srp_x_preferred":[
        "\u0414\u043e\u0431\u0440\u0438\u0432"
    ],
    "name:swe_x_preferred":[
        "Dob\u0159\u00edv"
    ],
    "name:vie_x_preferred":[
        "Dob\u0159\u00edv"
    ],
    "qs_pg:aaroncc":"CZ",
    "qs_pg:name":"Dob\u0159\u00edv",
    "qs_pg:name_adm0":"\u010cesk\u00e1 republika",
    "qs_pg:name_adm1":"Plze\u0148sk\u00fd kraj",
    "qs_pg:photos":49,
    "qs_pg:photos_1k":10,
    "qs_pg:photos_9k":1,
    "qs_pg:photos_9r":2,
    "qs_pg:photos_all":49,
    "qs_pg:photos_sr":2,
    "qs_pg:pop_sr":0,
    "qs_pg:qs_pg_placetype":"localadmin",
    "qs_pg:qs_pg_placetype_gp":"LocalAdmin",
    "qs_pg:woe_adm0":23424810,
    "woe:adm0_id":23424810,
    "woe:name_adm0":"\u010cesk\u00e1 republika",
    "woe:name_adm1":"Plze\u0148sk\u00fd kraj",
    "woe:placetype":"LocalAdmin",
    "wof:name":"Dob\u0159\u00edv",
    "wof:placetype":"localadmin"
},
  "geometry": {"coordinates":[13.68681,49.71566],"type":"Point"}
}