{
  "type": "Feature",
  "properties": {
    "gn:admin1_code":"82.0",
    "gn:admin2_code":"0525",
    "gn:asciiname":"Nove Zabori",
    "gn:country_code":"CZ",
    "gn:dem":510,
    "gn:feature_class":"P",
    "gn:feature_code":"PPL",
    "gn:name":"Nov\u00e9 Z\u00e1bo\u0159\u00ed",
    "gn:population":0,
    "gn:timezone":"Europe/Prague",
    "iso:country":"CZ",
    "wof:name":"Nove Zabori",
    "wof:placetype":"locality"
},
  "geometry": {"coordinates":[15.84364,50.4786],"type":"Point"}
}