{
  "type": "Feature",
  "properties": {
    "gn:gn_country":"CZ",
    "gn:gn_fcode":"PPL",
    "gn:gn_pop":334,
    "gn:population":334,
    "iso:country":"CZ",
    "name:cze_x_preferred":[
        "Seni\u010dka"
    ],
    "name:dut_x_preferred":[
        "Seni\u010dka"
    ],
    "name:eng_x_preferred":[
        "Seni\u010dka"
    ],
    "name:fre_x_preferred":[
        "Seni\u010dka"
    ],
    "name:ger_x_preferred":[
        "Seni\u010dka"
    ],
    "name:hun_x_preferred":[
        "Seni\u010dka"
    ],
    "name:ita_x_preferred":[
        "Seni\u010dka"
    ],
    "name:may_x_preferred":[
        "Seni\u010dka"
    ],
    "name:per_x_preferred":[
        "\u0633\u0646\u06cc\u062a\u0634\u06a9\u0627"
    ],
    "name:pol_x_preferred":[
        "Seni\u010dka"
    ],
    "name:por_x_preferred":[
        "Seni\u010dka"
    ],
    "name:slo_x_preferred":[
        "Seni\u010dka"
    ],
    "name:srp_x_preferred":[
        "\u0421\u0435\u045a\u0438\u0447\u043a\u0430"
    ],
    "name:swe_x_preferred":[
        "Seni\u010dka"
    ],
    "name:unk_x_variant":[
        "Klein Senitz"
    ],
    "name:vie_x_preferred":[
        "Seni\u010dka"
    ],
    "qs_pg:aaroncc":"CZ",
    "qs_pg:gn_country":"CZ",
    "qs_pg:gn_fcode":"PPL",
    "qs_pg:gn_pop":334,
    "qs_pg:name":"Seni\u010dka",
    "qs_pg:name_adm0":"\u010cesk\u00e1 republika",
    "qs_pg:name_adm1":"Olomouck\u00fd kraj",
    "qs_pg:photos_9k":1,
    "qs_pg:photos_9r":1,
    "qs_pg:photos_all":1,
    "qs_pg:photos_sr":0,
    "qs_pg:pop_sr":2,
    "qs_pg:qs_pg_placetype":"locality",
    "qs_pg:qs_pg_placetype_gp":"Town",
    "qs_pg:woe_adm0":23424810,
    "woe:adm0_id":23424810,
    "woe:name_adm0":"\u010cesk\u00e1 republika",
    "woe:name_adm1":"Olomouck\u00fd kraj",
    "woe:placetype":"Town",
    "wof:name":"Seni\u010dka",
    "wof:placetype":"locality",
    "wof:population":334
},
  "geometry": {"coordinates":[17.05628,49.63222],"type":"Point"}
}