{
  "type": "Feature",
  "properties": {
    "gn:admin1_code":"89",
    "gn:admin2_code":"0422",
    "gn:asciiname":"Vykmanov",
    "gn:country_code":"CZ",
    "gn:dem":657,
    "gn:feature_class":"P",
    "gn:feature_code":"PPL",
    "gn:name":"Vykmanov",
    "gn:population":0,
    "gn:timezone":"Europe/Prague",
    "iso:country":"CZ",
    "name:und_x_variant":[
        "Weigensdorf",
        "Vykmanov"
    ],
    "wof:name":"Vykmanov",
    "wof:placetype":"locality"
},
  "geometry": {"coordinates":[13.07044,50.39968],"type":"Point"}
}