{
  "type": "Feature",
  "properties": {
    "gn:admin1_code":"83.0",
    "gn:admin2_code":"0514",
    "gn:asciiname":"Helkovice",
    "gn:country_code":"CZ",
    "gn:dem":549,
    "gn:feature_class":"P",
    "gn:feature_code":"PPL",
    "gn:name":"Helkovice",
    "gn:population":0,
    "gn:timezone":"Europe/Prague",
    "iso:country":"CZ",
    "wof:name":"Helkovice",
    "wof:placetype":"locality"
},
  "geometry": {"coordinates":[15.38901,50.65419],"type":"Point"}
}