{
  "type": "Feature",
  "properties": {
    "gn:gn_country":"CZ",
    "gn:gn_fcode":"PPL",
    "gn:gn_pop":100,
    "gn:population":100,
    "iso:country":"CZ",
    "name:ceb_x_preferred":[
        "Nov\u00e1 Ves"
    ],
    "name:ces_x_preferred":[
        "Nov\u00e1 Ves"
    ],
    "name:deu_x_preferred":[
        "Nov\u00e1 Ves"
    ],
    "name:dsb_x_preferred":[
        "Nowa Wjas"
    ],
    "name:epo_x_preferred":[
        "Nov\u00e1 Ves"
    ],
    "name:eus_x_preferred":[
        "Nov\u00e1 Ves"
    ],
    "name:fra_x_preferred":[
        "Nov\u00e1 Ves"
    ],
    "name:hun_x_preferred":[
        "Nov\u00e1 Ves"
    ],
    "name:ita_x_preferred":[
        "Nov\u00e1 Ves"
    ],
    "name:nld_x_preferred":[
        "Nov\u00e1 Ves"
    ],
    "name:pol_x_preferred":[
        "Nov\u00e1 Ves"
    ],
    "name:slk_x_preferred":[
        "Nov\u00e1 Ves"
    ],
    "name:spa_x_preferred":[
        "Nov\u00e1 Ves"
    ],
    "name:swe_x_preferred":[
        "Nov\u00e1 Ves"
    ],
    "name:ukr_x_preferred":[
        "\u041d\u043e\u0432\u0430 \u0412\u0435\u0441"
    ],
    "qs_pg:aaroncc":"CZ",
    "qs_pg:gn_country":"CZ",
    "qs_pg:gn_fcode":"PPL",
    "qs_pg:gn_pop":100,
    "qs_pg:name":"Nov\u00e1 Ves",
    "qs_pg:name_adm0":"\u010cesk\u00e1 republika",
    "qs_pg:name_adm1":"\u00dasteck\u00fd kraj",
    "qs_pg:photos_9k":1,
    "qs_pg:photos_9r":1,
    "qs_pg:photos_all":1,
    "qs_pg:photos_sr":0,
    "qs_pg:pop_sr":1,
    "qs_pg:qs_pg_placetype":"locality",
    "qs_pg:qs_pg_placetype_gp":"Town",
    "qs_pg:woe_adm0":23424810,
    "woe:adm0_id":23424810,
    "woe:name_adm0":"\u010cesk\u00e1 republika",
    "woe:name_adm1":"\u00dasteck\u00fd kraj",
    "woe:placetype":"Town",
    "wof:name":"Nov\u00e1 Ves",
    "wof:placetype":"locality",
    "wof:population":100
},
  "geometry": {"coordinates":[13.84268,50.28585],"type":"Point"}
}