{
  "type": "Feature",
  "properties": {
    "gn:admin1_code":"81.0",
    "gn:admin2_code":"0413",
    "gn:asciiname":"Hradecka",
    "gn:country_code":"CZ",
    "gn:dem":672,
    "gn:feature_class":"P",
    "gn:feature_code":"PPL",
    "gn:name":"Hradeck\u00e1",
    "gn:population":0,
    "gn:timezone":"Europe/Prague",
    "iso:country":"CZ",
    "name:und_x_variant":[
        "Scheft",
        "Hradeck\u00e1"
    ],
    "wof:name":"Hradecka",
    "wof:placetype":"locality"
},
  "geometry": {"coordinates":[12.65641,50.29321],"type":"Point"}
}