{
  "type": "Feature",
  "properties": {
    "gn:admin1_code":"85",
    "gn:admin2_code":"0801",
    "gn:asciiname":"Zary",
    "gn:country_code":"CZ",
    "gn:dem":504,
    "gn:feature_class":"P",
    "gn:feature_code":"PPL",
    "gn:name":"\u017d\u00e1ry",
    "gn:population":0,
    "gn:timezone":"Europe/Prague",
    "iso:country":"CZ",
    "name:und_x_variant":[
        "Oberschaar"
    ],
    "wof:name":"Zary",
    "wof:placetype":"locality"
},
  "geometry": {"coordinates":[17.55615,50.15227],"type":"Point"}
}