{
  "type": "Feature",
  "properties": {
    "gn:admin1_code":"88.0",
    "gn:admin2_code":"0201",
    "gn:asciiname":"Boretice",
    "gn:country_code":"CZ",
    "gn:dem":510,
    "gn:feature_class":"P",
    "gn:feature_code":"PPL",
    "gn:name":"Bo\u0159etice",
    "gn:population":0,
    "gn:timezone":"Europe/Prague",
    "iso:country":"CZ",
    "wof:name":"Boretice",
    "wof:placetype":"locality"
},
  "geometry": {"coordinates":[14.70946,49.61137],"type":"Point"}
}