{
  "type": "Feature",
  "properties": {
    "gn:admin1_code":"88.0",
    "gn:admin2_code":"020C",
    "gn:asciiname":"Ducice",
    "gn:country_code":"CZ",
    "gn:dem":396,
    "gn:feature_class":"P",
    "gn:feature_code":"PPL",
    "gn:name":"Du\u010dice",
    "gn:population":0,
    "gn:timezone":"Europe/Prague",
    "iso:country":"CZ",
    "wof:name":"Ducice",
    "wof:placetype":"locality"
},
  "geometry": {"coordinates":[13.82958,50.21724],"type":"Point"}
}