{
  "type": "Feature",
  "properties": {
    "gn:admin1_code":"89.0",
    "gn:admin2_code":"0422",
    "gn:asciiname":"Haj",
    "gn:cc2":"CZ",
    "gn:country_code":"CZ",
    "gn:dem":362,
    "gn:feature_class":"P",
    "gn:feature_code":"PPL",
    "gn:name":"H\u00e1j",
    "gn:population":0,
    "gn:timezone":"Europe/Prague",
    "iso:country":"CZ",
    "name:und_x_variant":[
        "Gehae"
    ],
    "wof:name":"Haj",
    "wof:placetype":"locality"
},
  "geometry": {"coordinates":[13.24368,50.28737],"type":"Point"}
}