{
  "type": "Feature",
  "properties": {
    "iso:country":"CZ",
    "name:ceb_x_preferred":[
        "Raspenava"
    ],
    "name:ces_x_preferred":[
        "Raspenava"
    ],
    "name:deu_x_preferred":[
        "Raspenava"
    ],
    "name:epo_x_preferred":[
        "Raspenava"
    ],
    "name:eus_x_preferred":[
        "Raspenava"
    ],
    "name:fas_x_preferred":[
        "\u0631\u0627\u0633\u067e\u0646\u0627\u0648\u0627"
    ],
    "name:fra_x_preferred":[
        "Raspenava"
    ],
    "name:hun_x_preferred":[
        "Raspenava"
    ],
    "name:ita_x_preferred":[
        "Raspenava"
    ],
    "name:msa_x_preferred":[
        "Raspenava"
    ],
    "name:nld_x_preferred":[
        "Raspenava"
    ],
    "name:pol_x_preferred":[
        "Raspenava"
    ],
    "name:por_x_preferred":[
        "Raspenava"
    ],
    "name:rus_x_preferred":[
        "\u0420\u0430\u0441\u043f\u0435\u043d\u0430\u0432\u0430"
    ],
    "name:slk_x_preferred":[
        "Raspenava"
    ],
    "name:spa_x_preferred":[
        "Raspenava"
    ],
    "name:srp_x_preferred":[
        "\u0420\u0430\u0441\u043f\u0435\u043d\u0430\u0432\u0430"
    ],
    "name:swe_x_preferred":[
        "Raspenava"
    ],
    "name:vie_x_preferred":[
        "Raspenava"
    ],
    "name:zho_x_preferred":[
        "\u62c9\u65af\u4f69\u7d0d\u74e6"
    ],
    "qs_pg:aaroncc":"CZ",
    "qs_pg:name":"Raspenava",
    "qs_pg:name_adm0":"\u010cesk\u00e1 republika",
    "qs_pg:name_adm1":"Libereck\u00fd kraj",
    "qs_pg:photos":2,
    "qs_pg:photos_1k":1,
    "qs_pg:photos_9k":1,
    "qs_pg:photos_9r":4,
    "qs_pg:photos_all":157,
    "qs_pg:photos_sr":1,
    "qs_pg:pop_sr":0,
    "qs_pg:qs_pg_placetype":"localadmin",
    "qs_pg:qs_pg_placetype_gp":"LocalAdmin",
    "qs_pg:woe_adm0":23424810,
    "woe:adm0_id":23424810,
    "woe:name_adm0":"\u010cesk\u00e1 republika",
    "woe:name_adm1":"Libereck\u00fd kraj",
    "woe:placetype":"LocalAdmin",
    "wof:name":"Raspenava",
    "wof:placetype":"localadmin"
},
  "geometry": {"coordinates":[15.142743,50.896943],"type":"Point"}
}