{
  "type": "Feature",
  "properties": {
    "gn:admin1_code":"83.0",
    "gn:admin2_code":"0512",
    "gn:asciiname":"Jindrichov",
    "gn:country_code":"CZ",
    "gn:dem":616,
    "gn:feature_class":"P",
    "gn:feature_code":"PPL",
    "gn:name":"Jind\u0159ichov",
    "gn:population":0,
    "gn:timezone":"Europe/Prague",
    "iso:country":"CZ",
    "name:ceb_x_preferred":[
        "Jind\u0159ichov"
    ],
    "name:ces_x_preferred":[
        "Jind\u0159ichov"
    ],
    "name:deu_x_preferred":[
        "Jind\u0159ichov"
    ],
    "name:epo_x_preferred":[
        "Jind\u0159ichov"
    ],
    "name:fra_x_preferred":[
        "Jind\u0159ichov"
    ],
    "name:hun_x_preferred":[
        "Jind\u0159ichov"
    ],
    "name:ita_x_preferred":[
        "Jind\u0159ichov"
    ],
    "name:nld_x_preferred":[
        "Jind\u0159ichov"
    ],
    "name:pol_x_preferred":[
        "Jind\u0159ichov"
    ],
    "name:slk_x_preferred":[
        "Jind\u0159ichov"
    ],
    "name:srp_x_preferred":[
        "\u0408\u0438\u043d\u0434\u0440\u0438\u0445\u043e\u0432"
    ],
    "name:swe_x_preferred":[
        "Jind\u0159ichov"
    ],
    "name:und_x_variant":[
        "Hennersdorf"
    ],
    "wof:name":"Jindrichov",
    "wof:placetype":"locality"
},
  "geometry": {"coordinates":[15.19394,50.7511],"type":"Point"}
}