{
  "type": "Feature",
  "properties": {
    "gn:admin1_code":"83.0",
    "gn:admin2_code":"0512",
    "gn:asciiname":"Jindrichov",
    "gn:country_code":"CZ",
    "gn:dem":616,
    "gn:feature_class":"P",
    "gn:feature_code":"PPL",
    "gn:name":"Jind\u0159ichov",
    "gn:population":0,
    "gn:timezone":"Europe/Prague",
    "iso:country":"CZ",
    "name:und_x_variant":[
        "Hennersdorf",
        "Jind\u0159ichov"
    ],
    "wof:name":"Jindrichov",
    "wof:placetype":"locality"
},
  "geometry": {"coordinates":[15.19394,50.7511],"type":"Point"}
}