{
  "type": "Feature",
  "properties": {
    "gn:admin1_code":"79.0",
    "gn:admin2_code":"0311",
    "gn:asciiname":"Sindlovy Dvory",
    "gn:country_code":"CZ",
    "gn:dem":404,
    "gn:feature_class":"P",
    "gn:feature_code":"PPL",
    "gn:name":"\u0160indlovy Dvory",
    "gn:population":0,
    "gn:timezone":"Europe/Prague",
    "iso:country":"CZ",
    "name:und_x_variant":[
        "Schindelhof",
        "\u0160indlovy Dvory"
    ],
    "wof:name":"Sindlovy Dvory",
    "wof:placetype":"locality"
},
  "geometry": {"coordinates":[14.43689,48.96347],"type":"Point"}
}