{
  "type": "Feature",
  "properties": {
    "gn:admin1_code":"79.0",
    "gn:admin2_code":"0314",
    "gn:asciiname":"Drzov",
    "gn:country_code":"CZ",
    "gn:dem":419,
    "gn:feature_class":"P",
    "gn:feature_code":"PPL",
    "gn:name":"Dr\u017eov",
    "gn:population":0,
    "gn:timezone":"Europe/Prague",
    "iso:country":"CZ",
    "name:ces_x_preferred":[
        "Dr\u017eov"
    ],
    "name:und_x_variant":[
        "Dr\u017eov"
    ],
    "wof:name":"Drzov",
    "wof:placetype":"locality"
},
  "geometry": {"coordinates":[14.16915,49.36217],"type":"Point"}
}