{
  "type": "Feature",
  "properties": {
    "gn:admin1_code":"80.0",
    "gn:admin2_code":"0611",
    "gn:asciiname":"Dolni Prosicka",
    "gn:country_code":"CZ",
    "gn:dem":512,
    "gn:feature_class":"P",
    "gn:feature_code":"PPL",
    "gn:name":"Doln\u00ed Pros\u00ed\u010dka",
    "gn:population":0,
    "gn:timezone":"Europe/Prague",
    "iso:country":"CZ",
    "wof:name":"Dolni Prosicka",
    "wof:placetype":"locality"
},
  "geometry": {"coordinates":[15.32143,49.72789],"type":"Point"}
}