{
  "type": "Feature",
  "properties": {
    "gn:admin1_code":"79.0",
    "gn:admin2_code":"0317",
    "gn:asciiname":"Lazany",
    "gn:country_code":"CZ",
    "gn:dem":486,
    "gn:feature_class":"P",
    "gn:feature_code":"PPL",
    "gn:name":"La\u017eany",
    "gn:population":0,
    "gn:timezone":"Europe/Prague",
    "iso:country":"CZ",
    "name:deu_x_preferred":[
        "Lazany"
    ],
    "name:epo_x_preferred":[
        "Lazany"
    ],
    "name:eus_x_preferred":[
        "Lazany"
    ],
    "name:hun_x_preferred":[
        "Lazany"
    ],
    "name:slk_x_preferred":[
        "Lazany"
    ],
    "wof:name":"Lazany",
    "wof:placetype":"locality"
},
  "geometry": {"coordinates":[14.84853,49.39772],"type":"Point"}
}