{
  "type": "Feature",
  "properties": {
    "gn:country":"CZ",
    "gn:fcode":"PPL",
    "gn:population":209,
    "iso:country":"CZ",
    "name:azb_x_preferred":[
        "\u0646\u06cc\u0631\u0648\u0648"
    ],
    "name:cat_x_preferred":[
        "N\u00fdrov"
    ],
    "name:ceb_x_preferred":[
        "N\u00fdrov"
    ],
    "name:ces_x_preferred":[
        "N\u00fdrov"
    ],
    "name:che_x_preferred":[
        "\u041d\u0438\u0440\u043e\u0432"
    ],
    "name:deu_x_preferred":[
        "N\u00fdrov"
    ],
    "name:eng_x_preferred":[
        "N\u00fdrov"
    ],
    "name:epo_x_preferred":[
        "N\u00fdrov"
    ],
    "name:eus_x_preferred":[
        "N\u00fdrov"
    ],
    "name:fas_x_preferred":[
        "\u0646\u06cc\u0631\u0648\u0648"
    ],
    "name:fra_x_preferred":[
        "N\u00fdrov"
    ],
    "name:gle_x_preferred":[
        "N\u00fdrov"
    ],
    "name:hun_x_preferred":[
        "N\u00fdrov"
    ],
    "name:ita_x_preferred":[
        "N\u00fdrov"
    ],
    "name:lmo_x_preferred":[
        "N\u00fdrov"
    ],
    "name:msa_x_preferred":[
        "N\u00fdrov"
    ],
    "name:nan_x_preferred":[
        "N\u00fdrov"
    ],
    "name:nld_x_preferred":[
        "N\u00fdrov"
    ],
    "name:pol_x_preferred":[
        "N\u00fdrov"
    ],
    "name:por_x_preferred":[
        "N\u00fdrov"
    ],
    "name:slk_x_preferred":[
        "N\u00fdrov"
    ],
    "name:spa_x_preferred":[
        "N\u00fdrov"
    ],
    "name:srp_x_preferred":[
        "\u041d\u0438\u0440\u043e\u0432"
    ],
    "name:swe_x_preferred":[
        "N\u00fdrov"
    ],
    "name:tat_x_preferred":[
        "\u041d\u0438\u0440\u043e\u0432"
    ],
    "name:vie_x_preferred":[
        "N\u00fdrov"
    ],
    "qs_pg:aaroncc":"CZ",
    "qs_pg:gn_country":"CZ",
    "qs_pg:gn_fcode":"PPL",
    "qs_pg:gn_pop":209,
    "qs_pg:name":"N\u00fdrov",
    "qs_pg:name_adm0":"\u010cesk\u00e1 republika",
    "qs_pg:name_adm1":"Jihomoravsk\u00fd kraj",
    "qs_pg:photos_9r":0,
    "qs_pg:photos_sr":0,
    "qs_pg:pop_sr":2,
    "qs_pg:qs_pg_placetype":"locality",
    "qs_pg:qs_pg_placetype_gp":"Town",
    "qs_pg:woe_adm0":23424810,
    "woe:adm0_id":23424810,
    "woe:name_adm0":"\u010cesk\u00e1 republika",
    "woe:name_adm1":"Jihomoravsk\u00fd kraj",
    "woe:placetype":"Town",
    "wof:name":"N\u00fdrov",
    "wof:placetype":"locality",
    "wof:population":209
},
  "geometry": {"coordinates":[16.54262,49.5253],"type":"Point"}
}