{
  "type": "Feature",
  "properties": {
    "gn:gn_country":"CZ",
    "gn:gn_fcode":"PPL",
    "gn:gn_pop":367,
    "gn:population":367,
    "iso:country":"CZ",
    "name:ara_x_preferred":[
        "\u0646\u064a\u0641\u0627"
    ],
    "name:bul_x_preferred":[
        "\u041d\u0438\u0432\u0430"
    ],
    "name:ceb_x_preferred":[
        "Niva"
    ],
    "name:ces_x_preferred":[
        "Niva"
    ],
    "name:deu_x_preferred":[
        "Niva"
    ],
    "name:epo_x_preferred":[
        "Niva"
    ],
    "name:est_x_preferred":[
        "Niva"
    ],
    "name:fin_x_preferred":[
        "Niva"
    ],
    "name:fra_x_preferred":[
        "Niva"
    ],
    "name:hye_x_preferred":[
        "\u0546\u056b\u057e\u0561"
    ],
    "name:ita_x_preferred":[
        "Niva"
    ],
    "name:lit_x_preferred":[
        "Niva"
    ],
    "name:nld_x_preferred":[
        "Niva"
    ],
    "name:nor_x_preferred":[
        "Niva"
    ],
    "name:rus_x_preferred":[
        "\u041d\u0438\u0432\u0430"
    ],
    "name:slk_x_preferred":[
        "Niva"
    ],
    "name:spa_x_preferred":[
        "Niva"
    ],
    "name:ukr_x_preferred":[
        "\u041d\u0438\u0432\u0430"
    ],
    "name:unk_x_variant":[
        "Hartmanice"
    ],
    "qs_pg:aaroncc":"CZ",
    "qs_pg:gn_country":"CZ",
    "qs_pg:gn_fcode":"PPL",
    "qs_pg:gn_pop":367,
    "qs_pg:name":"Niva",
    "qs_pg:name_adm0":"\u010cesk\u00e1 republika",
    "qs_pg:name_adm1":"Olomouck\u00fd kraj",
    "qs_pg:photos_9r":0,
    "qs_pg:photos_sr":0,
    "qs_pg:pop_sr":2,
    "qs_pg:qs_pg_placetype":"locality",
    "qs_pg:qs_pg_placetype_gp":"Town",
    "qs_pg:woe_adm0":23424810,
    "woe:adm0_id":23424810,
    "woe:name_adm0":"\u010cesk\u00e1 republika",
    "woe:name_adm1":"Olomouck\u00fd kraj",
    "woe:placetype":"Town",
    "wof:name":"Niva",
    "wof:placetype":"locality",
    "wof:population":367
},
  "geometry": {"coordinates":[16.85181,49.44522],"type":"Point"}
}