{
  "type": "Feature",
  "properties": {
    "gn:admin1_code":"78.0",
    "gn:admin2_code":"0621",
    "gn:asciiname":"Dvoriste",
    "gn:country_code":"CZ",
    "gn:dem":479,
    "gn:feature_class":"P",
    "gn:feature_code":"PPL",
    "gn:name":"Dvo\u0159i\u0161t\u011b",
    "gn:population":0,
    "gn:timezone":"Europe/Prague",
    "iso:country":"CZ",
    "name:und_x_variant":[
        "Fr\u00fddnt\u00e1l",
        "Dvo\u0159i\u0161t\u011b"
    ],
    "wof:name":"Dvoriste",
    "wof:placetype":"locality"
},
  "geometry": {"coordinates":[16.67677999999999,49.59083],"type":"Point"}
}