{
  "type": "Feature",
  "properties": {
    "gn:gn_country":"CZ",
    "gn:gn_fcode":"PPL",
    "gn:gn_pop":475,
    "gn:population":475,
    "iso:country":"CZ",
    "name:ces_x_preferred":[
        "Kozoj\u00eddky"
    ],
    "name:deu_x_preferred":[
        "Kozoj\u00eddky"
    ],
    "name:eng_x_preferred":[
        "Kozoj\u00eddky"
    ],
    "name:fas_x_preferred":[
        "\u06a9\u0648\u0632\u0648\u06cc\u06cc\u062f\u06a9\u06cc"
    ],
    "name:fra_x_preferred":[
        "Kozoj\u00eddky"
    ],
    "name:hun_x_preferred":[
        "Kozoj\u00eddky"
    ],
    "name:ita_x_preferred":[
        "Kozoj\u00eddky"
    ],
    "name:msa_x_preferred":[
        "Kozoj\u00eddky"
    ],
    "name:nld_x_preferred":[
        "Kozoj\u00eddky"
    ],
    "name:pol_x_preferred":[
        "Kozoj\u00eddky"
    ],
    "name:por_x_preferred":[
        "Kozoj\u00eddky"
    ],
    "name:slk_x_preferred":[
        "Kozoj\u00eddky"
    ],
    "name:srp_x_preferred":[
        "\u041a\u043e\u0437\u043e\u0458\u0438\u0442\u043a\u0438"
    ],
    "name:swe_x_preferred":[
        "Kozoj\u00eddky"
    ],
    "name:vie_x_preferred":[
        "Kozoj\u00eddky"
    ],
    "qs_pg:aaroncc":"CZ",
    "qs_pg:gn_country":"CZ",
    "qs_pg:gn_fcode":"PPL",
    "qs_pg:gn_pop":475,
    "qs_pg:name":"Kozoj\u00eddky",
    "qs_pg:name_adm0":"\u010cesk\u00e1 republika",
    "qs_pg:name_adm1":"Jihomoravsk\u00fd kraj",
    "qs_pg:photos_9r":0,
    "qs_pg:photos_sr":0,
    "qs_pg:pop_sr":2,
    "qs_pg:qs_pg_placetype":"locality",
    "qs_pg:qs_pg_placetype_gp":"Town",
    "qs_pg:woe_adm0":23424810,
    "woe:adm0_id":23424810,
    "woe:name_adm0":"\u010cesk\u00e1 republika",
    "woe:name_adm1":"Jihomoravsk\u00fd kraj",
    "woe:placetype":"Town",
    "wof:name":"Kozoj\u00eddky",
    "wof:placetype":"locality",
    "wof:population":475
},
  "geometry": {"coordinates":[17.39962,48.91864],"type":"Point"}
}