{
  "type": "Feature",
  "properties": {
    "gn:admin1_code":"83.0",
    "gn:admin2_code":"0513",
    "gn:asciiname":"Grabstejn",
    "gn:country_code":"CZ",
    "gn:dem":312,
    "gn:feature_class":"P",
    "gn:feature_code":"PPL",
    "gn:name":"Grab\u0161tejn",
    "gn:population":0,
    "gn:timezone":"Europe/Prague",
    "iso:country":"CZ",
    "name:ces_x_preferred":[
        "Grab\u0161tejn"
    ],
    "name:deu_x_preferred":[
        "Burg Grab\u0161tejn"
    ],
    "name:epo_x_preferred":[
        "Grab\u0161tejn"
    ],
    "name:fra_x_preferred":[
        "Grabstejn"
    ],
    "name:hun_x_preferred":[
        "Grab\u0161tejn"
    ],
    "name:pol_x_preferred":[
        "Grab\u0161tejn"
    ],
    "name:rus_x_preferred":[
        "\u0413\u0440\u0430\u0431\u0448\u0442\u0435\u0439\u043d"
    ],
    "name:slk_x_preferred":[
        "Hrad Grab\u0161tejn"
    ],
    "name:srp_x_preferred":[
        "\u0413\u0440\u0430\u0431\u0448\u0442\u0435\u0458\u043d"
    ],
    "name:tur_x_preferred":[
        "Grab\u0161tejn"
    ],
    "wof:name":"Grabstejn",
    "wof:placetype":"locality"
},
  "geometry": {"coordinates":[14.87772,50.84936],"type":"Point"}
}