{
  "type": "Feature",
  "properties": {
    "gn:admin1_code":"82.0",
    "gn:admin2_code":"0523",
    "gn:asciiname":"Brezova",
    "gn:country_code":"CZ",
    "gn:dem":456,
    "gn:feature_class":"P",
    "gn:feature_code":"PPL",
    "gn:name":"B\u0159ezov\u00e1",
    "gn:population":0,
    "gn:timezone":"Europe/Prague",
    "iso:country":"CZ",
    "name:bos_x_preferred":[
        "Brezova"
    ],
    "name:ceb_x_preferred":[
        "Brezova"
    ],
    "name:fra_x_preferred":[
        "Brezova"
    ],
    "name:hrv_x_preferred":[
        "Brezova"
    ],
    "name:hun_x_preferred":[
        "Brezova"
    ],
    "name:nld_x_preferred":[
        "Brezova"
    ],
    "name:por_x_preferred":[
        "Brezova"
    ],
    "name:slv_x_preferred":[
        "Brezova"
    ],
    "name:srp_x_preferred":[
        "\u0411\u0440\u0435\u0437\u043e\u0432\u0430"
    ],
    "name:swe_x_preferred":[
        "Brezova"
    ],
    "name:und_x_variant":[
        "Birkigt",
        "B\u0159ezov\u00e1"
    ],
    "wof:name":"Brezova",
    "wof:placetype":"locality"
},
  "geometry": {"coordinates":[16.23061,50.60938],"type":"Point"}
}