{
  "type": "Feature",
  "properties": {
    "gn:admin1_code":"82.0",
    "gn:admin2_code":"0523",
    "gn:asciiname":"Brezova",
    "gn:country_code":"CZ",
    "gn:dem":456,
    "gn:feature_class":"P",
    "gn:feature_code":"PPL",
    "gn:name":"B\u0159ezov\u00e1",
    "gn:population":0,
    "gn:timezone":"Europe/Prague",
    "iso:country":"CZ",
    "name:und_x_variant":[
        "Birkigt",
        "B\u0159ezov\u00e1"
    ],
    "wof:name":"Brezova",
    "wof:placetype":"locality"
},
  "geometry": {"coordinates":[16.23061,50.60938],"type":"Point"}
}