{
  "type": "Feature",
  "properties": {
    "gn:admin1_code":"83.0",
    "gn:admin2_code":"0511",
    "gn:asciiname":"Kracmanov",
    "gn:country_code":"CZ",
    "gn:dem":358,
    "gn:feature_class":"P",
    "gn:feature_code":"PPL",
    "gn:name":"Kracmanov",
    "gn:population":0,
    "gn:timezone":"Europe/Prague",
    "iso:country":"CZ",
    "name:und_x_variant":[
        "Kratzdorf",
        "Kracmanov"
    ],
    "wof:name":"Kracmanov",
    "wof:placetype":"locality"
},
  "geometry": {"coordinates":[14.87278,50.61852],"type":"Point"}
}