{
  "type": "Feature",
  "properties": {
    "gn:admin1_code":"85.0",
    "gn:admin2_code":"0801",
    "gn:asciiname":"Kreuz",
    "gn:country_code":"CZ",
    "gn:dem":541,
    "gn:feature_class":"P",
    "gn:feature_code":"PPL",
    "gn:name":"Kreuz",
    "gn:population":0,
    "gn:timezone":"Europe/Prague",
    "iso:country":"CZ",
    "name:bre_x_preferred":[
        "Kreuz"
    ],
    "name:ceb_x_preferred":[
        "Kreuz"
    ],
    "name:deu_x_preferred":[
        "Kreuz"
    ],
    "name:epo_x_preferred":[
        "Kreuz"
    ],
    "name:ita_x_preferred":[
        "Kreuz"
    ],
    "name:swe_x_preferred":[
        "Kreuz"
    ],
    "name:und_x_variant":[
        "K\u0159\u00ed\u017eov"
    ],
    "wof:name":"Kreuz",
    "wof:placetype":"locality"
},
  "geometry": {"coordinates":[17.25998,49.83895],"type":"Point"}
}