{
  "type": "Feature",
  "properties": {
    "gn:admin1_code":"85.0",
    "gn:admin2_code":"0801",
    "gn:asciiname":"Petrovice",
    "gn:country_code":"CZ",
    "gn:dem":473,
    "gn:feature_class":"P",
    "gn:feature_code":"PPL",
    "gn:name":"Petrovice",
    "gn:population":140,
    "gn:timezone":"Europe/Prague",
    "iso:country":"CZ",
    "name:und_x_variant":[
        "Petersdorf"
    ],
    "wof:name":"Petrovice",
    "wof:placetype":"locality",
    "wof:population":140
},
  "geometry": {"coordinates":[17.44838,50.23893],"type":"Point"}
}