{
  "type": "Feature",
  "properties": {
    "gn:admin1_code":"85.0",
    "gn:admin2_code":"0801",
    "gn:asciiname":"Petrovice",
    "gn:country_code":"CZ",
    "gn:dem":473,
    "gn:feature_class":"P",
    "gn:feature_code":"PPL",
    "gn:name":"Petrovice",
    "gn:population":140,
    "gn:timezone":"Europe/Prague",
    "iso:country":"CZ",
    "name:azb_x_preferred":[
        "\u067e\u062a\u0631\u0648\u0648\u06cc\u062a\u0633\u0647"
    ],
    "name:ces_x_preferred":[
        "Petrovice"
    ],
    "name:epo_x_preferred":[
        "Petrovice"
    ],
    "name:eus_x_preferred":[
        "Petrovice"
    ],
    "name:fas_x_preferred":[
        "\u067e\u062a\u0631\u0648\u0648\u06cc\u062a\u0633\u0647"
    ],
    "name:hun_x_preferred":[
        "Petrovice"
    ],
    "name:ita_x_preferred":[
        "Petrovice"
    ],
    "name:msa_x_preferred":[
        "Petrovice"
    ],
    "name:nld_x_preferred":[
        "Petrovice"
    ],
    "name:pol_x_preferred":[
        "Petrovice"
    ],
    "name:por_x_preferred":[
        "Petrovice"
    ],
    "name:slk_x_preferred":[
        "Petrovice"
    ],
    "name:spa_x_preferred":[
        "Petrovice"
    ],
    "name:srp_x_preferred":[
        "\u041f\u0435\u0442\u0440\u043e\u0432\u0438\u0446\u0435"
    ],
    "name:und_x_variant":[
        "Petersdorf"
    ],
    "name:vie_x_preferred":[
        "Petrovice"
    ],
    "wof:name":"Petrovice",
    "wof:placetype":"locality",
    "wof:population":140
},
  "geometry": {"coordinates":[17.44838,50.23893],"type":"Point"}
}