{
  "type": "Feature",
  "properties": {
    "gn:admin1_code":"88.0",
    "gn:admin2_code":"0206",
    "gn:asciiname":"Horni Zimor",
    "gn:country_code":"CZ",
    "gn:dem":241,
    "gn:feature_class":"P",
    "gn:feature_code":"PPL",
    "gn:name":"Horn\u00ed Zimo\u0159",
    "gn:population":0,
    "gn:timezone":"Europe/Prague",
    "iso:country":"CZ",
    "wof:name":"Horni Zimor",
    "wof:placetype":"locality"
},
  "geometry": {"coordinates":[14.50221,50.42944],"type":"Point"}
}