{
  "type": "Feature",
  "properties": {
    "gn:admin1_code":"83.0",
    "gn:admin2_code":"0511",
    "gn:asciiname":"Luka",
    "gn:country_code":"CZ",
    "gn:dem":335,
    "gn:feature_class":"P",
    "gn:feature_code":"PPL",
    "gn:name":"Luka",
    "gn:population":107,
    "gn:timezone":"Europe/Prague",
    "iso:country":"CZ",
    "wof:name":"Luka",
    "wof:placetype":"locality",
    "wof:population":107
},
  "geometry": {"coordinates":[14.66407,50.51241],"type":"Point"}
}