{
  "type": "Feature",
  "properties": {
    "gn:admin1_code":"83.0",
    "gn:admin2_code":"0511",
    "gn:asciiname":"Luka",
    "gn:country_code":"CZ",
    "gn:dem":335,
    "gn:feature_class":"P",
    "gn:feature_code":"PPL",
    "gn:name":"Luka",
    "gn:population":107,
    "gn:timezone":"Europe/Prague",
    "iso:country":"CZ",
    "name:azb_x_preferred":[
        "\u0644\u0648\u06a9\u0627"
    ],
    "name:ceb_x_preferred":[
        "Luka"
    ],
    "name:ces_x_preferred":[
        "Luka"
    ],
    "name:eus_x_preferred":[
        "Luka"
    ],
    "name:fas_x_preferred":[
        "\u0644\u0648\u06a9\u0627"
    ],
    "name:hun_x_preferred":[
        "Luka"
    ],
    "name:ita_x_preferred":[
        "Luka"
    ],
    "name:msa_x_preferred":[
        "Luka"
    ],
    "name:nld_x_preferred":[
        "Luka"
    ],
    "name:pol_x_preferred":[
        "Luka"
    ],
    "name:por_x_preferred":[
        "Luka"
    ],
    "name:slk_x_preferred":[
        "Luka"
    ],
    "name:spa_x_preferred":[
        "Luka"
    ],
    "name:srp_x_preferred":[
        "\u041b\u0443\u043a\u0430"
    ],
    "name:vie_x_preferred":[
        "Luka"
    ],
    "wof:name":"Luka",
    "wof:placetype":"locality",
    "wof:population":107
},
  "geometry": {"coordinates":[14.66407,50.51241],"type":"Point"}
}