{
  "type": "Feature",
  "properties": {
    "gn:gn_country":"CZ",
    "gn:gn_fcode":"PPL",
    "gn:gn_pop":670,
    "gn:population":670,
    "iso:country":"CZ",
    "name:cze_x_preferred":[
        "Kocl\u00ed\u0159ov"
    ],
    "name:dut_x_preferred":[
        "Kocl\u00ed\u0159ov"
    ],
    "name:eng_x_preferred":[
        "Kocl\u00ed\u0159ov"
    ],
    "name:epo_x_preferred":[
        "Kocl\u00ed\u0159ov"
    ],
    "name:fre_x_preferred":[
        "Kocl\u00ed\u0159ov"
    ],
    "name:hun_x_preferred":[
        "Kocl\u00ed\u0159ov"
    ],
    "name:ita_x_preferred":[
        "Kocl\u00ed\u0159ov"
    ],
    "name:may_x_preferred":[
        "Kocl\u00ed\u0159ov"
    ],
    "name:per_x_preferred":[
        "\u06a9\u0648\u062a\u0633\u0644\u06cc\u0631\u0648\u0648"
    ],
    "name:pol_x_preferred":[
        "Kocl\u00ed\u0159ov"
    ],
    "name:por_x_preferred":[
        "Kocl\u00ed\u0159ov"
    ],
    "name:slo_x_preferred":[
        "Kocl\u00ed\u0159ov"
    ],
    "name:srp_x_preferred":[
        "\u041a\u043e\u0446\u043b\u0438\u0440\u0436\u043e\u0432"
    ],
    "name:swe_x_preferred":[
        "Kocl\u00ed\u0159ov"
    ],
    "name:unk_x_variant":[
        "Ketzelsdorf"
    ],
    "name:vie_x_preferred":[
        "Kocl\u00ed\u0159ov"
    ],
    "qs_pg:aaroncc":"CZ",
    "qs_pg:gn_country":"CZ",
    "qs_pg:gn_fcode":"PPL",
    "qs_pg:gn_pop":670,
    "qs_pg:name":"Kocl\u00ed\u0159ov",
    "qs_pg:name_adm0":"\u010cesk\u00e1 republika",
    "qs_pg:name_adm1":"Pardubick\u00fd kraj",
    "qs_pg:photos_9r":0,
    "qs_pg:photos_sr":0,
    "qs_pg:pop_sr":2,
    "qs_pg:qs_pg_placetype":"locality",
    "qs_pg:qs_pg_placetype_gp":"Town",
    "qs_pg:woe_adm0":23424810,
    "woe:adm0_id":23424810,
    "woe:name_adm0":"\u010cesk\u00e1 republika",
    "woe:name_adm1":"Pardubick\u00fd kraj",
    "woe:placetype":"Town",
    "wof:name":"Kocl\u00ed\u0159ov",
    "wof:placetype":"locality",
    "wof:population":670
},
  "geometry": {"coordinates":[16.53983,49.76629],"type":"Point"}
}