{
  "type": "Feature",
  "properties": {
    "gn:gn_country":"CZ",
    "gn:gn_fcode":"PPL",
    "gn:gn_pop":574,
    "gn:population":574,
    "iso:country":"CZ",
    "name:ceb_x_preferred":[
        "Li\u010dno"
    ],
    "name:ces_x_preferred":[
        "Li\u010dno"
    ],
    "name:deu_x_preferred":[
        "Li\u010dno"
    ],
    "name:eng_x_preferred":[
        "Li\u010dno"
    ],
    "name:eus_x_preferred":[
        "Li\u010dno"
    ],
    "name:fas_x_preferred":[
        "\u0644\u06cc\u062a\u0634\u0646\u0648"
    ],
    "name:fra_x_preferred":[
        "Li\u010dno"
    ],
    "name:hun_x_preferred":[
        "Li\u010dno"
    ],
    "name:ita_x_preferred":[
        "Li\u010dno"
    ],
    "name:msa_x_preferred":[
        "Li\u010dno"
    ],
    "name:nan_x_preferred":[
        "Li\u010dno"
    ],
    "name:nld_x_preferred":[
        "Li\u010dno"
    ],
    "name:pol_x_preferred":[
        "Li\u010dno"
    ],
    "name:por_x_preferred":[
        "Li\u010dno"
    ],
    "name:rus_x_preferred":[
        "\u041b\u0438\u0447\u043d\u043e"
    ],
    "name:slk_x_preferred":[
        "Li\u010dno"
    ],
    "name:spa_x_preferred":[
        "Li\u010dno"
    ],
    "name:srp_x_preferred":[
        "\u041b\u0438\u0447\u043d\u043e"
    ],
    "name:swe_x_preferred":[
        "Li\u010dno"
    ],
    "name:vie_x_preferred":[
        "Li\u010dno"
    ],
    "qs_pg:aaroncc":"CZ",
    "qs_pg:gn_country":"CZ",
    "qs_pg:gn_fcode":"PPL",
    "qs_pg:gn_pop":574,
    "qs_pg:name":"Li\u010dno",
    "qs_pg:name_adm0":"\u010cesk\u00e1 republika",
    "qs_pg:name_adm1":"Kr\u00e1lov\u00e9hradeck\u00fd kraj",
    "qs_pg:photos_9r":0,
    "qs_pg:photos_sr":0,
    "qs_pg:pop_sr":2,
    "qs_pg:qs_pg_placetype":"locality",
    "qs_pg:qs_pg_placetype_gp":"Town",
    "qs_pg:woe_adm0":23424810,
    "woe:adm0_id":23424810,
    "woe:name_adm0":"\u010cesk\u00e1 republika",
    "woe:name_adm1":"Kr\u00e1lov\u00e9hradeck\u00fd kraj",
    "woe:placetype":"Town",
    "wof:name":"Li\u010dno",
    "wof:placetype":"locality",
    "wof:population":574
},
  "geometry": {"coordinates":[16.17202,50.17787],"type":"Point"}
}