{
  "type": "Feature",
  "properties": {
    "gn:country":"CZ",
    "gn:fcode":"PPL",
    "gn:population":65,
    "iso:country":"CZ",
    "name:ces_x_preferred":[
        "Rybn\u00ed\u010dek"
    ],
    "name:deu_x_preferred":[
        "Rybn\u00ed\u010dek"
    ],
    "name:fra_x_preferred":[
        "Rybn\u00ed\u010dek"
    ],
    "name:ita_x_preferred":[
        "Rybn\u00ed\u010dek"
    ],
    "name:nld_x_preferred":[
        "Rybn\u00ed\u010dek"
    ],
    "name:slk_x_preferred":[
        "Rybn\u00ed\u010dek"
    ],
    "name:srp_x_preferred":[
        "\u0420\u0438\u0431\u045a\u0438\u0447\u0435\u043a"
    ],
    "qs_pg:aaroncc":"CZ",
    "qs_pg:gn_country":"CZ",
    "qs_pg:gn_fcode":"PPL",
    "qs_pg:gn_pop":65,
    "qs_pg:name":"Rybn\u00ed\u010dek",
    "qs_pg:name_adm0":"\u010cesk\u00e1 republika",
    "qs_pg:name_adm1":"Kraj Vyso\u010dina",
    "qs_pg:photos_9r":0,
    "qs_pg:photos_sr":0,
    "qs_pg:pop_sr":1,
    "qs_pg:qs_pg_placetype":"locality",
    "qs_pg:qs_pg_placetype_gp":"Town",
    "qs_pg:woe_adm0":23424810,
    "woe:adm0_id":23424810,
    "woe:name_adm0":"\u010cesk\u00e1 republika",
    "woe:name_adm1":"Kraj Vyso\u010dina",
    "woe:placetype":"Town",
    "wof:name":"Rybn\u00ed\u010dek",
    "wof:placetype":"locality",
    "wof:population":65
},
  "geometry": {"coordinates":[15.30014,49.46218],"type":"Point"}
}