{
  "type": "Feature",
  "properties": {
    "gn:admin1_code":"87.0",
    "gn:admin2_code":"0322",
    "gn:asciiname":"Smrkovec",
    "gn:country_code":"CZ",
    "gn:dem":472,
    "gn:feature_class":"P",
    "gn:feature_code":"PPL",
    "gn:name":"Smrkovec",
    "gn:population":0,
    "gn:timezone":"Europe/Prague",
    "iso:country":"CZ",
    "wof:name":"Smrkovec",
    "wof:placetype":"locality"
},
  "geometry": {"coordinates":[13.59955,49.34225],"type":"Point"}
}