{
  "type": "Feature",
  "properties": {
    "gn:admin1_code":"86.0",
    "gn:admin2_code":"0533",
    "gn:asciiname":"Novy Valdek",
    "gn:country_code":"CZ",
    "gn:dem":463,
    "gn:feature_class":"P",
    "gn:feature_code":"PPL",
    "gn:name":"Nov\u00fd Valdek",
    "gn:population":0,
    "gn:timezone":"Europe/Prague",
    "iso:country":"CZ",
    "name:und_x_variant":[
        "Neu Valdek",
        "Nov\u00fd Valdek"
    ],
    "wof:name":"Novy Valdek",
    "wof:placetype":"locality"
},
  "geometry": {"coordinates":[16.46394,49.79517],"type":"Point"}
}