{
  "type": "Feature",
  "properties": {
    "gn:admin1_code":"88.0",
    "gn:admin2_code":"0201",
    "gn:asciiname":"Mechnov",
    "gn:country_code":"CZ",
    "gn:dem":476,
    "gn:feature_class":"P",
    "gn:feature_code":"PPL",
    "gn:name":"M\u011bchnov",
    "gn:population":0,
    "gn:timezone":"Europe/Prague",
    "iso:country":"CZ",
    "name:und_x_variant":[
        "M\u011bchnov"
    ],
    "wof:name":"Mechnov",
    "wof:placetype":"locality"
},
  "geometry": {"coordinates":[14.89949,49.79559],"type":"Point"}
}