{
  "type": "Feature",
  "properties": {
    "gn:gn_country":"CZ",
    "gn:gn_fcode":"PPL",
    "gn:gn_pop":396,
    "gn:population":396,
    "iso:country":"CZ",
    "name:ceb_x_preferred":[
        "Ov\u010d\u00e1ry"
    ],
    "name:ces_x_preferred":[
        "Ov\u010d\u00e1ry"
    ],
    "name:deu_x_preferred":[
        "Ov\u010d\u00e1ry"
    ],
    "name:fra_x_preferred":[
        "Ov\u010d\u00e1ry"
    ],
    "name:ita_x_preferred":[
        "Ov\u010d\u00e1ry"
    ],
    "name:nld_x_preferred":[
        "Ov\u010d\u00e1ry"
    ],
    "name:pol_x_preferred":[
        "Ov\u010d\u00e1ry"
    ],
    "name:slk_x_preferred":[
        "Ov\u010d\u00e1ry"
    ],
    "name:srp_x_preferred":[
        "\u041e\u0432\u0447\u0430\u0440\u0438"
    ],
    "name:swe_x_preferred":[
        "Ov\u010d\u00e1ry"
    ],
    "qs_pg:aaroncc":"CZ",
    "qs_pg:gn_country":"CZ",
    "qs_pg:gn_fcode":"PPL",
    "qs_pg:gn_pop":396,
    "qs_pg:name":"Ov\u010d\u00e1ry",
    "qs_pg:name_adm0":"\u010cesk\u00e1 republika",
    "qs_pg:name_adm1":"St\u0159edo\u010desk\u00fd kraj",
    "qs_pg:photos_9k":1,
    "qs_pg:photos_9r":1,
    "qs_pg:photos_all":2,
    "qs_pg:photos_sr":0,
    "qs_pg:pop_sr":2,
    "qs_pg:qs_pg_placetype":"locality",
    "qs_pg:qs_pg_placetype_gp":"Town",
    "qs_pg:woe_adm0":23424810,
    "woe:adm0_id":23424810,
    "woe:name_adm0":"\u010cesk\u00e1 republika",
    "woe:name_adm1":"St\u0159edo\u010desk\u00fd kraj",
    "woe:placetype":"Town",
    "wof:name":"Ov\u010d\u00e1ry",
    "wof:placetype":"locality",
    "wof:population":396
},
  "geometry": {"coordinates":[14.61385,50.25305],"type":"Point"}
}