{
  "type": "Feature",
  "properties": {
    "gn:gn_country":"CZ",
    "gn:gn_fcode":"PPL",
    "gn:gn_pop":64,
    "gn:population":64,
    "iso:country":"CZ",
    "name:ces_x_preferred":[
        "Vele\u010d\u00edn"
    ],
    "name:deu_x_preferred":[
        "Vele\u010d\u00edn"
    ],
    "name:eng_x_preferred":[
        "Vele\u010d\u00edn"
    ],
    "name:fas_x_preferred":[
        "\u0648\u0644\u0686\u06cc\u0646"
    ],
    "name:fra_x_preferred":[
        "Vele\u010d\u00edn"
    ],
    "name:hun_x_preferred":[
        "Vele\u010d\u00edn"
    ],
    "name:ita_x_preferred":[
        "Vele\u010d\u00edn"
    ],
    "name:msa_x_preferred":[
        "Vele\u010d\u00edn"
    ],
    "name:nld_x_preferred":[
        "Vele\u010d\u00edn"
    ],
    "name:por_x_preferred":[
        "Vele\u010d\u00edn"
    ],
    "name:slk_x_preferred":[
        "Vele\u010d\u00edn"
    ],
    "name:srp_x_preferred":[
        "\u0412\u0435\u043b\u0435\u0447\u0438\u043d"
    ],
    "name:vie_x_preferred":[
        "Vele\u010d\u00edn"
    ],
    "qs_pg:aaroncc":"CZ",
    "qs_pg:gn_country":"CZ",
    "qs_pg:gn_fcode":"PPL",
    "qs_pg:gn_pop":64,
    "qs_pg:name":"Vele\u010d\u00edn",
    "qs_pg:name_adm0":"\u010cesk\u00e1 republika",
    "qs_pg:name_adm1":"Plze\u0148sk\u00fd kraj",
    "qs_pg:photos_9r":0,
    "qs_pg:photos_sr":0,
    "qs_pg:pop_sr":1,
    "qs_pg:qs_pg_placetype":"locality",
    "qs_pg:qs_pg_placetype_gp":"Town",
    "qs_pg:woe_adm0":23424810,
    "woe:adm0_id":23424810,
    "woe:name_adm0":"\u010cesk\u00e1 republika",
    "woe:name_adm1":"Plze\u0148sk\u00fd kraj",
    "woe:placetype":"Town",
    "wof:name":"Vele\u010d\u00edn",
    "wof:placetype":"locality",
    "wof:population":64
},
  "geometry": {"coordinates":[13.4016,50.07431],"type":"Point"}
}