{
  "type": "Feature",
  "properties": {
    "gn:admin1_code":"88.0",
    "gn:admin2_code":"0202",
    "gn:asciiname":"Nerezin",
    "gn:country_code":"CZ",
    "gn:dem":458,
    "gn:feature_class":"P",
    "gn:feature_code":"PPL",
    "gn:name":"Ne\u0159e\u017e\u00edn",
    "gn:population":0,
    "gn:timezone":"Europe/Prague",
    "iso:country":"CZ",
    "wof:name":"Nerezin",
    "wof:placetype":"locality"
},
  "geometry": {"coordinates":[13.88194,49.78612],"type":"Point"}
}