{
  "type": "Feature",
  "properties": {
    "gn:admin1_code":"79.0",
    "gn:admin2_code":"0313",
    "gn:asciiname":"Brabec",
    "gn:country_code":"CZ",
    "gn:dem":519,
    "gn:feature_class":"P",
    "gn:feature_code":"PPL",
    "gn:name":"Brabec",
    "gn:population":0,
    "gn:timezone":"Europe/Prague",
    "iso:country":"CZ",
    "name:slk_x_preferred":[
        "Brabec"
    ],
    "wof:name":"Brabec",
    "wof:placetype":"locality"
},
  "geometry": {"coordinates":[15.08333,49.23333],"type":"Point"}
}