{
  "type": "Feature",
  "properties": {
    "iso:country":"CZ",
    "name:ceb_x_preferred":[
        "Radnice"
    ],
    "name:ces_x_preferred":[
        "Radnice"
    ],
    "name:deu_x_preferred":[
        "Radnice"
    ],
    "name:eus_x_preferred":[
        "Radnice"
    ],
    "name:hun_x_preferred":[
        "Radnice"
    ],
    "name:ita_x_preferred":[
        "Radnice"
    ],
    "name:msa_x_preferred":[
        "Radnice"
    ],
    "name:nld_x_preferred":[
        "Radnice"
    ],
    "name:pol_x_preferred":[
        "Radnice"
    ],
    "name:por_x_preferred":[
        "Radnice"
    ],
    "name:rus_x_preferred":[
        "\u0420\u0430\u0434\u043d\u0438\u0446\u0435"
    ],
    "name:slk_x_preferred":[
        "Radnice"
    ],
    "name:spa_x_preferred":[
        "Radnice"
    ],
    "name:srp_x_preferred":[
        "\u0420\u0430\u0434\u045a\u0438\u0446\u0435"
    ],
    "name:swe_x_preferred":[
        "Radnice"
    ],
    "name:vie_x_preferred":[
        "Radnice"
    ],
    "name:zho_x_preferred":[
        "\u62c9\u5fb7\u5c3c\u91c7"
    ],
    "qs_pg:aaroncc":"CZ",
    "qs_pg:name":"Radnice",
    "qs_pg:name_adm0":"\u010cesk\u00e1 republika",
    "qs_pg:name_adm1":"Plze\u0148sk\u00fd kraj",
    "qs_pg:photos":20,
    "qs_pg:photos_1k":4,
    "qs_pg:photos_9k":1,
    "qs_pg:photos_9r":1,
    "qs_pg:photos_all":20,
    "qs_pg:photos_sr":1,
    "qs_pg:pop_sr":0,
    "qs_pg:qs_pg_placetype":"localadmin",
    "qs_pg:qs_pg_placetype_gp":"LocalAdmin",
    "qs_pg:woe_adm0":23424810,
    "woe:adm0_id":23424810,
    "woe:name_adm0":"\u010cesk\u00e1 republika",
    "woe:name_adm1":"Plze\u0148sk\u00fd kraj",
    "woe:placetype":"LocalAdmin",
    "wof:name":"Radnice",
    "wof:placetype":"localadmin"
},
  "geometry": {"coordinates":[13.672485,49.944145],"type":"Point"}
}