{
  "type": "Feature",
  "properties": {
    "gn:country":"CZ",
    "gn:fcode":"PPL",
    "gn:population":359,
    "iso:country":"CZ",
    "name:azb_x_preferred":[
        "\u0633\u0645\u062e\u0646\u06cc\u062a\u0633\u0647"
    ],
    "name:ceb_x_preferred":[
        "Semechnice"
    ],
    "name:ces_x_preferred":[
        "Semechnice"
    ],
    "name:deu_x_preferred":[
        "Semechnice"
    ],
    "name:eng_x_preferred":[
        "Semechnice"
    ],
    "name:eus_x_preferred":[
        "Semechnice"
    ],
    "name:fas_x_preferred":[
        "\u0633\u0645\u062e\u0646\u06cc\u062a\u0633\u0647"
    ],
    "name:fra_x_preferred":[
        "Semechnice"
    ],
    "name:hun_x_preferred":[
        "Semechnice"
    ],
    "name:ita_x_preferred":[
        "Semechnice"
    ],
    "name:msa_x_preferred":[
        "Semechnice"
    ],
    "name:nan_x_preferred":[
        "Semechnice"
    ],
    "name:nld_x_preferred":[
        "Semechnice"
    ],
    "name:pol_x_preferred":[
        "Semechnice"
    ],
    "name:por_x_preferred":[
        "Semechnice"
    ],
    "name:slk_x_preferred":[
        "Semechnice"
    ],
    "name:spa_x_preferred":[
        "Semechnice"
    ],
    "name:srp_x_preferred":[
        "\u0421\u0435\u043c\u0435\u0445\u045a\u0438\u0446\u0435"
    ],
    "name:swe_x_preferred":[
        "Semechnice"
    ],
    "name:und_x_variant":[
        "Semechnitz"
    ],
    "name:vie_x_preferred":[
        "Semechnice"
    ],
    "qs_pg:aaroncc":"CZ",
    "qs_pg:gn_country":"CZ",
    "qs_pg:gn_fcode":"PPL",
    "qs_pg:gn_pop":359,
    "qs_pg:name":"Semechnice",
    "qs_pg:name_adm0":"\u010cesk\u00e1 republika",
    "qs_pg:name_adm1":"Kr\u00e1lov\u00e9hradeck\u00fd kraj",
    "qs_pg:photos_9r":0,
    "qs_pg:photos_sr":0,
    "qs_pg:pop_sr":2,
    "qs_pg:qs_pg_placetype":"locality",
    "qs_pg:qs_pg_placetype_gp":"Town",
    "qs_pg:woe_adm0":23424810,
    "woe:adm0_id":23424810,
    "woe:name_adm0":"\u010cesk\u00e1 republika",
    "woe:name_adm1":"Kr\u00e1lov\u00e9hradeck\u00fd kraj",
    "woe:placetype":"Town",
    "wof:name":"Semechnice",
    "wof:placetype":"locality",
    "wof:population":359
},
  "geometry": {"coordinates":[16.14839,50.26024],"type":"Point"}
}