{
  "type": "Feature",
  "properties": {
    "gn:admin1_code":"85.0",
    "gn:admin2_code":"0802",
    "gn:asciiname":"Kycera",
    "gn:country_code":"CZ",
    "gn:dem":755,
    "gn:feature_class":"P",
    "gn:feature_code":"PPL",
    "gn:name":"Ky\u010dera",
    "gn:population":0,
    "gn:timezone":"Europe/Prague",
    "iso:country":"CZ",
    "wof:name":"Kycera",
    "wof:placetype":"locality"
},
  "geometry": {"coordinates":[18.39548,49.42131],"type":"Point"}
}