{
  "type": "Feature",
  "properties": {
    "gn:admin1_code":"86.0",
    "gn:admin2_code":"0533",
    "gn:asciiname":"Pacov",
    "gn:country_code":"CZ",
    "gn:dem":388,
    "gn:feature_class":"P",
    "gn:feature_code":"PPL",
    "gn:name":"Pacov",
    "gn:population":0,
    "gn:timezone":"Europe/Prague",
    "iso:country":"CZ",
    "name:und_x_variant":[
        "Putzendorf",
        "Pacov"
    ],
    "wof:name":"Pacov",
    "wof:placetype":"locality"
},
  "geometry": {"coordinates":[16.68179,49.7025],"type":"Point"}
}