{
  "type": "Feature",
  "properties": {
    "gn:admin1_code":"86.0",
    "gn:admin2_code":"0533",
    "gn:asciiname":"Pacov",
    "gn:country_code":"CZ",
    "gn:dem":388,
    "gn:feature_class":"P",
    "gn:feature_code":"PPL",
    "gn:name":"Pacov",
    "gn:population":0,
    "gn:timezone":"Europe/Prague",
    "iso:country":"CZ",
    "name:cat_x_preferred":[
        "Pacov"
    ],
    "name:ceb_x_preferred":[
        "Pacov"
    ],
    "name:ces_x_preferred":[
        "Pacov"
    ],
    "name:deu_x_preferred":[
        "Pacov"
    ],
    "name:epo_x_preferred":[
        "Pacov"
    ],
    "name:eus_x_preferred":[
        "Pacov"
    ],
    "name:fas_x_preferred":[
        "\u067e\u0627\u062a\u0633\u0648\u0648"
    ],
    "name:fra_x_preferred":[
        "Pacov"
    ],
    "name:hun_x_preferred":[
        "Pacov"
    ],
    "name:ita_x_preferred":[
        "Pacov"
    ],
    "name:lav_x_preferred":[
        "Pacova"
    ],
    "name:msa_x_preferred":[
        "Pacov"
    ],
    "name:nld_x_preferred":[
        "Pacov"
    ],
    "name:pol_x_preferred":[
        "Pacov"
    ],
    "name:por_x_preferred":[
        "Pacov"
    ],
    "name:rus_x_preferred":[
        "\u041f\u0430\u0446\u043e\u0432"
    ],
    "name:slk_x_preferred":[
        "Pacov"
    ],
    "name:spa_x_preferred":[
        "Pacov"
    ],
    "name:srp_x_preferred":[
        "\u041f\u0430\u0446\u043e\u0432"
    ],
    "name:swe_x_preferred":[
        "Pacov"
    ],
    "name:und_x_variant":[
        "Putzendorf"
    ],
    "name:vie_x_preferred":[
        "Pacov"
    ],
    "name:zho_x_preferred":[
        "\u5e15\u4f50\u592b"
    ],
    "wof:name":"Pacov",
    "wof:placetype":"locality"
},
  "geometry": {"coordinates":[16.68179,49.7025],"type":"Point"}
}