{
  "type": "Feature",
  "properties": {
    "gn:country":"CZ",
    "gn:fcode":"PPL",
    "gn:population":322,
    "iso:country":"CZ",
    "name:ceb_x_preferred":[
        "\u010cernousy"
    ],
    "name:ces_x_preferred":[
        "\u010cernousy"
    ],
    "name:deu_x_preferred":[
        "\u010cernousy"
    ],
    "name:eng_x_preferred":[
        "\u010cernousy"
    ],
    "name:eus_x_preferred":[
        "\u010cernousy"
    ],
    "name:fra_x_preferred":[
        "\u010cernousy"
    ],
    "name:hun_x_preferred":[
        "\u010cernousy"
    ],
    "name:ita_x_preferred":[
        "\u010cernousy"
    ],
    "name:msa_x_preferred":[
        "\u010cernousy"
    ],
    "name:nld_x_preferred":[
        "\u010cernousy"
    ],
    "name:pol_x_preferred":[
        "\u010cernousy"
    ],
    "name:por_x_preferred":[
        "\u010cernousy"
    ],
    "name:rup_x_preferred":[
        "\u010cernousy"
    ],
    "name:slk_x_preferred":[
        "\u010cernousy"
    ],
    "name:spa_x_preferred":[
        "\u010cernousy"
    ],
    "name:srp_x_preferred":[
        "\u0427\u0435\u0440\u043d\u043e\u0443\u0441\u0438"
    ],
    "name:swe_x_preferred":[
        "\u010cernousy"
    ],
    "name:und_x_variant":[
        "Tschernhausen"
    ],
    "name:vie_x_preferred":[
        "\u010cernousy"
    ],
    "qs_pg:aaroncc":"CZ",
    "qs_pg:gn_country":"CZ",
    "qs_pg:gn_fcode":"PPL",
    "qs_pg:gn_pop":322,
    "qs_pg:name":"\u010cernousy",
    "qs_pg:name_adm0":"\u010cesk\u00e1 republika",
    "qs_pg:name_adm1":"Libereck\u00fd kraj",
    "qs_pg:photos_9k":1,
    "qs_pg:photos_9r":1,
    "qs_pg:photos_all":1,
    "qs_pg:photos_sr":0,
    "qs_pg:pop_sr":2,
    "qs_pg:qs_pg_placetype":"locality",
    "qs_pg:qs_pg_placetype_gp":"Town",
    "qs_pg:woe_adm0":23424810,
    "woe:adm0_id":23424810,
    "woe:name_adm0":"\u010cesk\u00e1 republika",
    "woe:name_adm1":"Libereck\u00fd kraj",
    "woe:placetype":"Town",
    "wof:name":"\u010cernousy",
    "wof:placetype":"locality",
    "wof:population":322
},
  "geometry": {"coordinates":[15.05046,51.00446],"type":"Point"}
}