{
  "type": "Feature",
  "properties": {
    "gn:admin1_code":"89",
    "gn:admin2_code":"0423",
    "gn:asciiname":"Vrbka",
    "gn:country_code":"CZ",
    "gn:dem":180,
    "gn:feature_class":"P",
    "gn:feature_code":"PPL",
    "gn:name":"Vrbka",
    "gn:population":0,
    "gn:timezone":"Europe/Prague",
    "iso:country":"CZ",
    "wof:name":"Vrbka",
    "wof:placetype":"locality"
},
  "geometry": {"coordinates":[14.14215,50.39024000000001],"type":"Point"}
}