{
  "type": "Feature",
  "properties": {
    "gn:admin1_code":"82",
    "gn:admin2_code":"0523",
    "gn:asciiname":"Zajezd",
    "gn:country_code":"CZ",
    "gn:dem":282,
    "gn:feature_class":"P",
    "gn:feature_code":"PPL",
    "gn:name":"Z\u00e1jezd",
    "gn:population":0,
    "gn:timezone":"Europe/Prague",
    "iso:country":"CZ",
    "wof:name":"Zajezd",
    "wof:placetype":"locality"
},
  "geometry": {"coordinates":[16.02463,50.39741],"type":"Point"}
}