{
  "type": "Feature",
  "properties": {
    "gn:admin1_code":"79.0",
    "gn:admin2_code":"0312",
    "gn:asciiname":"Blansko",
    "gn:country_code":"CZ",
    "gn:dem":590,
    "gn:feature_class":"P",
    "gn:feature_code":"PPL",
    "gn:name":"Blansko",
    "gn:population":0,
    "gn:timezone":"Europe/Prague",
    "iso:country":"CZ",
    "name:ara_x_preferred":[
        "\u0628\u0644\u0627\u0646\u0633\u0643\u0648"
    ],
    "name:ast_x_preferred":[
        "Blansko"
    ],
    "name:bak_x_preferred":[
        "\u0411\u043b\u0430\u043d\u0441\u043a\u043e"
    ],
    "name:bul_x_preferred":[
        "\u0411\u043b\u0430\u043d\u0441\u043a\u043e"
    ],
    "name:ceb_x_preferred":[
        "Blansko"
    ],
    "name:ces_x_preferred":[
        "Blansko"
    ],
    "name:deu_x_preferred":[
        "Blansko"
    ],
    "name:epo_x_preferred":[
        "Blansko"
    ],
    "name:eus_x_preferred":[
        "Blansko"
    ],
    "name:fas_x_preferred":[
        "\u0628\u0644\u0627\u0646\u0633\u06a9\u0648"
    ],
    "name:fra_x_preferred":[
        "Blansko"
    ],
    "name:hrv_x_preferred":[
        "Blansko"
    ],
    "name:hun_x_preferred":[
        "Blansko"
    ],
    "name:hye_x_preferred":[
        "\u0532\u056c\u0561\u0576\u057d\u056f\u0578"
    ],
    "name:ita_x_preferred":[
        "Blansko"
    ],
    "name:lav_x_preferred":[
        "Blansko"
    ],
    "name:lit_x_preferred":[
        "Blanskas"
    ],
    "name:msa_x_preferred":[
        "Blansko"
    ],
    "name:nld_x_preferred":[
        "Blansko"
    ],
    "name:pol_x_preferred":[
        "Blansko"
    ],
    "name:por_x_preferred":[
        "Blansko"
    ],
    "name:ron_x_preferred":[
        "Blansko"
    ],
    "name:rus_x_preferred":[
        "\u0411\u043b\u0430\u043d\u0441\u043a\u043e"
    ],
    "name:slk_x_preferred":[
        "Blansko"
    ],
    "name:spa_x_preferred":[
        "Blansko"
    ],
    "name:srp_x_preferred":[
        "\u0411\u043b\u0430\u043d\u0441\u043a\u043e"
    ],
    "name:tur_x_preferred":[
        "Blansko"
    ],
    "name:ukr_x_preferred":[
        "\u0411\u043b\u0430\u043d\u0441\u043a\u043e"
    ],
    "name:und_x_variant":[
        "Pflanzen"
    ],
    "name:vie_x_preferred":[
        "Blansko"
    ],
    "name:war_x_preferred":[
        "Blansko"
    ],
    "name:zho_x_preferred":[
        "\u5e03\u862d\u65af\u79d1"
    ],
    "wof:name":"Blansko",
    "wof:placetype":"locality"
},
  "geometry": {"coordinates":[14.517,48.7412],"type":"Point"}
}