{
  "type": "Feature",
  "properties": {
    "gn:admin1_code":"79.0",
    "gn:admin2_code":"0312",
    "gn:asciiname":"Blansko",
    "gn:country_code":"CZ",
    "gn:dem":590,
    "gn:feature_class":"P",
    "gn:feature_code":"PPL",
    "gn:name":"Blansko",
    "gn:population":0,
    "gn:timezone":"Europe/Prague",
    "iso:country":"CZ",
    "name:und_x_variant":[
        "Pflanzen",
        "Blansko"
    ],
    "wof:name":"Blansko",
    "wof:placetype":"locality"
},
  "geometry": {"coordinates":[14.517,48.7412],"type":"Point"}
}