{
  "type": "Feature",
  "properties": {
    "gn:admin1_code":"85.0",
    "gn:admin2_code":"0802",
    "gn:asciiname":"Brestovy",
    "gn:country_code":"CZ",
    "gn:dem":645,
    "gn:feature_class":"P",
    "gn:feature_code":"PPL",
    "gn:name":"B\u0159estov\u00fd",
    "gn:population":0,
    "gn:timezone":"Europe/Prague",
    "iso:country":"CZ",
    "wof:name":"Brestovy",
    "wof:placetype":"locality"
},
  "geometry": {"coordinates":[18.39081,49.47834],"type":"Point"}
}