{
  "type": "Feature",
  "properties": {
    "gn:admin1_code":"87.0",
    "gn:admin2_code":"0327",
    "gn:asciiname":"Bretislav",
    "gn:country_code":"CZ",
    "gn:dem":486,
    "gn:feature_class":"P",
    "gn:feature_code":"PPL",
    "gn:name":"B\u0159etislav",
    "gn:population":0,
    "gn:timezone":"Europe/Prague",
    "iso:country":"CZ",
    "name:und_x_variant":[
        "Setzlaw",
        "B\u0159etislav"
    ],
    "wof:name":"Bretislav",
    "wof:placetype":"locality"
},
  "geometry": {"coordinates":[12.96656,49.8735],"type":"Point"}
}