{
  "type": "Feature",
  "properties": {
    "gn:admin1_code":"80",
    "gn:admin2_code":"0611",
    "gn:asciiname":"Splav",
    "gn:country_code":"CZ",
    "gn:dem":542,
    "gn:feature_class":"P",
    "gn:feature_code":"PPL",
    "gn:name":"Splav",
    "gn:population":0,
    "gn:timezone":"Europe/Prague",
    "iso:country":"CZ",
    "wof:name":"Splav",
    "wof:placetype":"locality"
},
  "geometry": {"coordinates":[15.42253,49.54501],"type":"Point"}
}