{
  "type": "Feature",
  "properties": {
    "gn:admin1_code":"83.0",
    "gn:admin2_code":"0511",
    "gn:asciiname":"Kurivody",
    "gn:country_code":"CZ",
    "gn:dem":336,
    "gn:feature_class":"P",
    "gn:feature_code":"PPL",
    "gn:name":"Ku\u0159\u00edvody",
    "gn:population":0,
    "gn:timezone":"Europe/Prague",
    "iso:country":"CZ",
    "name:und_x_variant":[
        "H\u00fchnerwasser",
        "Ku\u0159\u00edvody"
    ],
    "wof:name":"Kurivody",
    "wof:placetype":"locality"
},
  "geometry": {"coordinates":[14.80431,50.58556],"type":"Point"}
}