{
  "type": "Feature",
  "properties": {
    "gn:gn_country":"CZ",
    "gn:gn_fcode":"PPL",
    "gn:gn_pop":422,
    "gn:population":422,
    "iso:country":"CZ",
    "name:azb_x_preferred":[
        "\u0631\u0647\u0646\u06cc\u062a\u0633\u0647"
    ],
    "name:ceb_x_preferred":[
        "\u0158ehenice"
    ],
    "name:ces_x_preferred":[
        "\u0158ehenice"
    ],
    "name:eng_x_preferred":[
        "\u0158ehenice"
    ],
    "name:eus_x_preferred":[
        "\u0158ehenice"
    ],
    "name:fas_x_preferred":[
        "\u0631\u0647\u0646\u06cc\u062a\u0633\u0647"
    ],
    "name:fra_x_preferred":[
        "\u0158ehenice"
    ],
    "name:hun_x_preferred":[
        "\u0158ehenice"
    ],
    "name:ita_x_preferred":[
        "\u0158ehenice"
    ],
    "name:msa_x_preferred":[
        "\u0158ehenice"
    ],
    "name:nan_x_preferred":[
        "\u0158ehenice"
    ],
    "name:nld_x_preferred":[
        "\u0158ehenice"
    ],
    "name:oci_x_preferred":[
        "\u0158ehenice"
    ],
    "name:pol_x_preferred":[
        "\u0158ehenice"
    ],
    "name:por_x_preferred":[
        "\u0158ehenice"
    ],
    "name:slk_x_preferred":[
        "\u0158ehenice"
    ],
    "name:spa_x_preferred":[
        "\u0158ehenice"
    ],
    "name:srp_x_preferred":[
        "\u0420\u0435\u0445\u0435\u045a\u0438\u0446\u0435"
    ],
    "name:swe_x_preferred":[
        "\u0158ehenice"
    ],
    "name:unk_x_variant":[
        "Rehenitz"
    ],
    "name:vie_x_preferred":[
        "\u0158ehenice"
    ],
    "qs_pg:aaroncc":"CZ",
    "qs_pg:gn_country":"CZ",
    "qs_pg:gn_fcode":"PPL",
    "qs_pg:gn_pop":422,
    "qs_pg:name":"\u0158ehenice",
    "qs_pg:name_adm0":"\u010cesk\u00e1 republika",
    "qs_pg:name_adm1":"St\u0159edo\u010desk\u00fd kraj",
    "qs_pg:photos_9r":0,
    "qs_pg:photos_sr":0,
    "qs_pg:pop_sr":2,
    "qs_pg:qs_pg_placetype":"locality",
    "qs_pg:qs_pg_placetype_gp":"Town",
    "qs_pg:woe_adm0":23424810,
    "woe:adm0_id":23424810,
    "woe:name_adm0":"\u010cesk\u00e1 republika",
    "woe:name_adm1":"St\u0159edo\u010desk\u00fd kraj",
    "woe:placetype":"Town",
    "wof:name":"\u0158ehenice",
    "wof:placetype":"locality",
    "wof:population":422
},
  "geometry": {"coordinates":[14.65023,49.86975],"type":"Point"}
}