{
  "type": "Feature",
  "properties": {
    "gn:admin1_code":"79.0",
    "gn:admin2_code":"0315",
    "gn:asciiname":"Slunecna",
    "gn:country_code":"CZ",
    "gn:dem":794,
    "gn:feature_class":"P",
    "gn:feature_code":"PPL",
    "gn:name":"Slune\u010dn\u00e1",
    "gn:population":0,
    "gn:timezone":"Europe/Prague",
    "iso:country":"CZ",
    "name:und_x_variant":[
        "\u017dumberk",
        "Sonnberg",
        "Slune\u010dn\u00e1"
    ],
    "wof:name":"Slunecna",
    "wof:placetype":"locality"
},
  "geometry": {"coordinates":[13.96607,48.82114],"type":"Point"}
}