{
  "type": "Feature",
  "properties": {
    "iso:country":"CZ",
    "name:bul_x_preferred":[
        "\u0411\u043e\u0441\u043a\u043e\u0432\u0438\u0446\u0435"
    ],
    "name:ceb_x_preferred":[
        "Boskovice"
    ],
    "name:ces_x_preferred":[
        "Boskovice"
    ],
    "name:deu_x_preferred":[
        "Boskovice"
    ],
    "name:epo_x_preferred":[
        "Boskovice"
    ],
    "name:eus_x_preferred":[
        "Boskovice"
    ],
    "name:fas_x_preferred":[
        "\u0628\u0648\u0633\u06a9\u0648\u0648\u06cc\u062a\u0633\u0647"
    ],
    "name:fra_x_preferred":[
        "Boskovice"
    ],
    "name:hun_x_preferred":[
        "Boskovice"
    ],
    "name:ita_x_preferred":[
        "Boskovice"
    ],
    "name:lav_x_preferred":[
        "Boskovice"
    ],
    "name:msa_x_preferred":[
        "Boskovice"
    ],
    "name:nld_x_preferred":[
        "Boskovice"
    ],
    "name:pol_x_preferred":[
        "Boskovice"
    ],
    "name:por_x_preferred":[
        "Boskovice"
    ],
    "name:rus_x_preferred":[
        "\u0411\u043e\u0441\u043a\u043e\u0432\u0438\u0446\u0435"
    ],
    "name:slk_x_preferred":[
        "Boskovice"
    ],
    "name:spa_x_preferred":[
        "Boskovice"
    ],
    "name:srp_x_preferred":[
        "\u0411\u043e\u0441\u043a\u043e\u0432\u0438\u0446\u0435"
    ],
    "name:swe_x_preferred":[
        "Boskovice"
    ],
    "name:vie_x_preferred":[
        "Boskovice"
    ],
    "name:zho_x_preferred":[
        "\u535a\u65af\u79d1\u7dad\u91c7"
    ],
    "qs_pg:aaroncc":"CZ",
    "qs_pg:name":"Boskovice",
    "qs_pg:name_adm0":"\u010cesk\u00e1 republika",
    "qs_pg:name_adm1":"Jihomoravsk\u00fd kraj",
    "qs_pg:photos":1,
    "qs_pg:photos_1k":1,
    "qs_pg:photos_9k":1,
    "qs_pg:photos_9r":4,
    "qs_pg:photos_all":282,
    "qs_pg:photos_sr":1,
    "qs_pg:pop_sr":0,
    "qs_pg:qs_pg_placetype":"localadmin",
    "qs_pg:qs_pg_placetype_gp":"LocalAdmin",
    "qs_pg:woe_adm0":23424810,
    "woe:adm0_id":23424810,
    "woe:name_adm0":"\u010cesk\u00e1 republika",
    "woe:name_adm1":"Jihomoravsk\u00fd kraj",
    "woe:placetype":"LocalAdmin",
    "wof:name":"Boskovice",
    "wof:placetype":"localadmin"
},
  "geometry": {"coordinates":[16.657236,49.490876],"type":"Point"}
}