{
  "type": "Feature",
  "properties": {
    "gn:admin1_code":"80.0",
    "gn:admin2_code":"0613",
    "gn:asciiname":"Petrkov",
    "gn:country_code":"CZ",
    "gn:dem":562,
    "gn:feature_class":"P",
    "gn:feature_code":"PPL",
    "gn:name":"Petrkov",
    "gn:population":0,
    "gn:timezone":"Europe/Prague",
    "iso:country":"CZ",
    "wof:name":"Petrkov",
    "wof:placetype":"locality"
},
  "geometry": {"coordinates":[15.35847,49.45548],"type":"Point"}
}