{
  "type": "Feature",
  "properties": {
    "gn:admin1_code":"78.0",
    "gn:admin2_code":"0623",
    "gn:asciiname":"Nova Ves",
    "gn:country_code":"CZ",
    "gn:dem":175,
    "gn:feature_class":"P",
    "gn:feature_code":"PPL",
    "gn:name":"Nov\u00e1 Ves",
    "gn:population":0,
    "gn:timezone":"Europe/Prague",
    "iso:country":"CZ",
    "name:hrv_x_preferred":[
        "Nova Ves"
    ],
    "name:und_x_variant":[
        "Mariahilf",
        "Nov\u00e1 Ves"
    ],
    "wof:name":"Nova Ves",
    "wof:placetype":"locality"
},
  "geometry": {"coordinates":[16.53333,48.93333],"type":"Point"}
}