{
  "type": "Feature",
  "properties": {
    "gn:admin1_code":"88.0",
    "gn:admin2_code":"0208",
    "gn:asciiname":"Polabec",
    "gn:country_code":"CZ",
    "gn:dem":187,
    "gn:feature_class":"P",
    "gn:feature_code":"PPL",
    "gn:name":"Polabec",
    "gn:population":0,
    "gn:timezone":"Europe/Prague",
    "iso:country":"CZ",
    "wof:name":"Polabec",
    "wof:placetype":"locality"
},
  "geometry": {"coordinates":[15.1036,50.14244],"type":"Point"}
}