{
  "type": "Feature",
  "properties": {
    "gn:admin1_code":"79.0",
    "gn:admin2_code":"0317",
    "gn:asciiname":"Skrychov",
    "gn:country_code":"CZ",
    "gn:dem":500,
    "gn:feature_class":"P",
    "gn:feature_code":"PPL",
    "gn:name":"Skr\u00fdchov",
    "gn:population":0,
    "gn:timezone":"Europe/Prague",
    "iso:country":"CZ",
    "wof:name":"Skrychov",
    "wof:placetype":"locality"
},
  "geometry": {"coordinates":[14.48195,49.42426],"type":"Point"}
}