{
  "type": "Feature",
  "properties": {
    "gn:country":"CZ",
    "gn:fcode":"PPL",
    "gn:population":98,
    "iso:country":"CZ",
    "name:azb_x_preferred":[
        "\u0632\u0627\u06cc\u0632\u062f"
    ],
    "name:cat_x_preferred":[
        "Z\u00e1jezd"
    ],
    "name:ces_x_preferred":[
        "Z\u00e1jezd"
    ],
    "name:che_x_preferred":[
        "\u0417\u0430\u0435\u0437\u0434"
    ],
    "name:deu_x_preferred":[
        "Z\u00e1jezd"
    ],
    "name:eng_x_preferred":[
        "Z\u00e1jezd"
    ],
    "name:epo_x_preferred":[
        "Z\u00e1jezd"
    ],
    "name:eus_x_preferred":[
        "Z\u00e1jezd"
    ],
    "name:fas_x_preferred":[
        "\u0632\u0627\u06cc\u0632\u062f"
    ],
    "name:fra_x_preferred":[
        "Z\u00e1jezd"
    ],
    "name:gle_x_preferred":[
        "Z\u00e1jezd"
    ],
    "name:hun_x_preferred":[
        "Z\u00e1jezd"
    ],
    "name:ita_x_preferred":[
        "Z\u00e1jezd"
    ],
    "name:lmo_x_preferred":[
        "Z\u00e1jezd"
    ],
    "name:msa_x_preferred":[
        "Z\u00e1jezd"
    ],
    "name:nan_x_preferred":[
        "Z\u00e1jezd"
    ],
    "name:nld_x_preferred":[
        "Z\u00e1jezd"
    ],
    "name:pol_x_preferred":[
        "Z\u00e1jezd"
    ],
    "name:por_x_preferred":[
        "Z\u00e1jezd"
    ],
    "name:rup_x_preferred":[
        "Z\u00e1jezd"
    ],
    "name:rus_x_preferred":[
        "\u0417\u0430\u0435\u0437\u0434"
    ],
    "name:slk_x_preferred":[
        "Z\u00e1jezd"
    ],
    "name:spa_x_preferred":[
        "Z\u00e1jezd"
    ],
    "name:srp_x_preferred":[
        "\u0417\u0430\u0458\u0435\u0437\u0434"
    ],
    "name:tat_x_preferred":[
        "\u0417\u0430\u0435\u0437\u0434"
    ],
    "name:vie_x_preferred":[
        "Z\u00e1jezd"
    ],
    "qs_pg:aaroncc":"CZ",
    "qs_pg:gn_country":"CZ",
    "qs_pg:gn_fcode":"PPL",
    "qs_pg:gn_pop":98,
    "qs_pg:name":"Z\u00e1jezd",
    "qs_pg:name_adm0":"\u010cesk\u00e1 republika",
    "qs_pg:name_adm1":"St\u0159edo\u010desk\u00fd kraj",
    "qs_pg:photos_9r":0,
    "qs_pg:photos_sr":0,
    "qs_pg:pop_sr":1,
    "qs_pg:qs_pg_placetype":"locality",
    "qs_pg:qs_pg_placetype_gp":"Town",
    "qs_pg:woe_adm0":23424810,
    "woe:adm0_id":23424810,
    "woe:name_adm0":"\u010cesk\u00e1 republika",
    "woe:name_adm1":"St\u0159edo\u010desk\u00fd kraj",
    "woe:placetype":"Town",
    "wof:name":"Z\u00e1jezd",
    "wof:placetype":"locality",
    "wof:population":98
},
  "geometry": {"coordinates":[14.2205,50.16598],"type":"Point"}
}