{
  "type": "Feature",
  "properties": {
    "gn:admin1_code":"86.0",
    "gn:admin2_code":"0534",
    "gn:asciiname":"Horni Houzovec",
    "gn:country_code":"CZ",
    "gn:dem":433,
    "gn:feature_class":"P",
    "gn:feature_code":"PPL",
    "gn:name":"Horn\u00ed Hou\u017eovec",
    "gn:population":0,
    "gn:timezone":"Europe/Prague",
    "iso:country":"CZ",
    "name:und_x_variant":[
        "Hertersdorf"
    ],
    "wof:name":"Horni Houzovec",
    "wof:placetype":"locality"
},
  "geometry": {"coordinates":[16.47503,49.95823],"type":"Point"}
}