{
  "type": "Feature",
  "properties": {
    "gn:country":"CZ",
    "gn:fcode":"PPL",
    "gn:population":412,
    "iso:country":"CZ",
    "name:ceb_x_preferred":[
        "Sosnov\u00e1"
    ],
    "name:ces_x_preferred":[
        "Sosnov\u00e1"
    ],
    "name:deu_x_preferred":[
        "Sosnov\u00e1"
    ],
    "name:eng_x_preferred":[
        "Sosnov\u00e1"
    ],
    "name:epo_x_preferred":[
        "Sosnov\u00e1"
    ],
    "name:eus_x_preferred":[
        "Sosnov\u00e1"
    ],
    "name:fra_x_preferred":[
        "Sosnov\u00e1"
    ],
    "name:hun_x_preferred":[
        "Sosnov\u00e1"
    ],
    "name:ita_x_preferred":[
        "Sosnov\u00e1"
    ],
    "name:msa_x_preferred":[
        "Sosnov\u00e1"
    ],
    "name:nan_x_preferred":[
        "Sosnov\u00e1"
    ],
    "name:nld_x_preferred":[
        "Sosnov\u00e1"
    ],
    "name:pol_x_preferred":[
        "Sosnov\u00e1"
    ],
    "name:por_x_preferred":[
        "Sosnov\u00e1"
    ],
    "name:rup_x_preferred":[
        "Sosnov\u00e1"
    ],
    "name:slk_x_preferred":[
        "Sosnov\u00e1"
    ],
    "name:spa_x_preferred":[
        "Sosnov\u00e1"
    ],
    "name:srp_x_preferred":[
        "\u0421\u043e\u0441\u043d\u043e\u0432\u0430"
    ],
    "name:swe_x_preferred":[
        "Sosnov\u00e1"
    ],
    "name:und_x_variant":[
        "Zossen"
    ],
    "name:vie_x_preferred":[
        "Sosnov\u00e1"
    ],
    "qs_pg:aaroncc":"CZ",
    "qs_pg:gn_country":"CZ",
    "qs_pg:gn_fcode":"PPL",
    "qs_pg:gn_pop":412,
    "qs_pg:name":"Sosnov\u00e1",
    "qs_pg:name_adm0":"\u010cesk\u00e1 republika",
    "qs_pg:name_adm1":"Moravskoslezsk\u00fd kraj",
    "qs_pg:photos_9r":0,
    "qs_pg:photos_sr":0,
    "qs_pg:pop_sr":2,
    "qs_pg:qs_pg_placetype":"locality",
    "qs_pg:qs_pg_placetype_gp":"Town",
    "qs_pg:woe_adm0":23424810,
    "woe:adm0_id":23424810,
    "woe:name_adm0":"\u010cesk\u00e1 republika",
    "woe:name_adm1":"Moravskoslezsk\u00fd kraj",
    "woe:placetype":"Town",
    "wof:name":"Sosnov\u00e1",
    "wof:placetype":"locality",
    "wof:population":412
},
  "geometry": {"coordinates":[17.66302,49.99864],"type":"Point"}
}