{
  "type": "Feature",
  "properties": {
    "gn:admin1_code":"87.0",
    "gn:admin2_code":"0321",
    "gn:asciiname":"Oplotec",
    "gn:country_code":"CZ",
    "gn:dem":434,
    "gn:feature_class":"P",
    "gn:feature_code":"PPL",
    "gn:name":"Oplotec",
    "gn:population":0,
    "gn:timezone":"Europe/Prague",
    "iso:country":"CZ",
    "name:und_x_variant":[
        "Amplatz",
        "Oplotec"
    ],
    "wof:name":"Oplotec",
    "wof:placetype":"locality"
},
  "geometry": {"coordinates":[12.82956,49.57987],"type":"Point"}
}