{
  "type": "Feature",
  "properties": {
    "gn:country":"CZ",
    "gn:fcode":"PPL",
    "gn:population":399,
    "iso:country":"CZ",
    "name:ceb_x_preferred":[
        "Trhov\u00e9 Du\u0161n\u00edky"
    ],
    "name:ces_x_preferred":[
        "Trhov\u00e9 Du\u0161n\u00edky"
    ],
    "name:deu_x_preferred":[
        "Trhov\u00e9 Du\u0161n\u00edky"
    ],
    "name:eng_x_preferred":[
        "Trhov\u00e9 Du\u0161n\u00edky"
    ],
    "name:eus_x_preferred":[
        "Trhov\u00e9 Du\u0161n\u00edky"
    ],
    "name:fas_x_preferred":[
        "\u062a\u0631\u0647\u0648\u0648\u0647 \u062f\u0648\u0634\u0646\u06cc\u06a9\u06cc"
    ],
    "name:fra_x_preferred":[
        "Trhov\u00e9 Du\u0161n\u00edky"
    ],
    "name:hun_x_preferred":[
        "Trhov\u00e9 Du\u0161n\u00edky"
    ],
    "name:hye_x_preferred":[
        "\u054f\u0580\u0570\u0578\u057e\u0565 \u0534\u0578\u0582\u0577\u0576\u056b\u056f\u056b"
    ],
    "name:ita_x_preferred":[
        "Trhov\u00e9 Du\u0161n\u00edky"
    ],
    "name:msa_x_preferred":[
        "Trhov\u00e9 Du\u0161n\u00edky"
    ],
    "name:nan_x_preferred":[
        "Trhov\u00e9 Du\u0161n\u00edky"
    ],
    "name:nld_x_preferred":[
        "Trhov\u00e9 Du\u0161n\u00edky"
    ],
    "name:pol_x_preferred":[
        "Trhov\u00e9 Du\u0161n\u00edky"
    ],
    "name:por_x_preferred":[
        "Trhov\u00e9 Du\u0161n\u00edky"
    ],
    "name:rup_x_preferred":[
        "Trhov\u00e9 Du\u0161n\u00edky"
    ],
    "name:slk_x_preferred":[
        "Trhov\u00e9 Du\u0161n\u00edky"
    ],
    "name:spa_x_preferred":[
        "Trhov\u00e9 Du\u0161n\u00edky"
    ],
    "name:srp_x_preferred":[
        "\u0422\u0440\u0445\u043e\u0432\u0435 \u0414\u0443\u0448\u045a\u0438\u043a\u0438"
    ],
    "name:swe_x_preferred":[
        "Trhov\u00e9 Du\u0161n\u00edky"
    ],
    "name:vie_x_preferred":[
        "Trhov\u00e9 Du\u0161n\u00edky"
    ],
    "qs_pg:aaroncc":"CZ",
    "qs_pg:gn_country":"CZ",
    "qs_pg:gn_fcode":"PPL",
    "qs_pg:gn_pop":399,
    "qs_pg:name":"Trhov\u00e9 Du\u0161n\u00edky",
    "qs_pg:name_adm0":"\u010cesk\u00e1 republika",
    "qs_pg:name_adm1":"St\u0159edo\u010desk\u00fd kraj",
    "qs_pg:photos_9r":0,
    "qs_pg:photos_sr":0,
    "qs_pg:pop_sr":2,
    "qs_pg:qs_pg_placetype":"locality",
    "qs_pg:qs_pg_placetype_gp":"Town",
    "qs_pg:woe_adm0":23424810,
    "woe:adm0_id":23424810,
    "woe:name_adm0":"\u010cesk\u00e1 republika",
    "woe:name_adm1":"St\u0159edo\u010desk\u00fd kraj",
    "woe:placetype":"Town",
    "wof:name":"Trhov\u00e9 Du\u0161n\u00edky",
    "wof:placetype":"locality",
    "wof:population":399
},
  "geometry": {"coordinates":[14.01226,49.71379],"type":"Point"}
}