{
  "type": "Feature",
  "properties": {
    "gn:admin1_code":"86.0",
    "gn:admin2_code":"0534",
    "gn:asciiname":"Lansperk",
    "gn:country_code":"CZ",
    "gn:dem":436,
    "gn:feature_class":"P",
    "gn:feature_code":"PPL",
    "gn:name":"Lan\u0161perk",
    "gn:population":0,
    "gn:timezone":"Europe/Prague",
    "iso:country":"CZ",
    "wof:name":"Lansperk",
    "wof:placetype":"locality"
},
  "geometry": {"coordinates":[16.45518,49.99504],"type":"Point"}
}