{
  "type": "Feature",
  "properties": {
    "gn:admin1_code":"79",
    "gn:admin2_code":"0316",
    "gn:asciiname":"Zadni Ptakovice",
    "gn:country_code":"CZ",
    "gn:dem":461,
    "gn:feature_class":"P",
    "gn:feature_code":"PPL",
    "gn:name":"Zadn\u00ed Pt\u00e1kovice",
    "gn:population":0,
    "gn:timezone":"Europe/Prague",
    "iso:country":"CZ",
    "wof:name":"Zadni Ptakovice",
    "wof:placetype":"locality"
},
  "geometry": {"coordinates":[13.95,49.23333],"type":"Point"}
}