{
  "type": "Feature",
  "properties": {
    "gn:admin1_code":"83.0",
    "gn:admin2_code":"0514",
    "gn:asciiname":"Sekerkovy Loucky",
    "gn:cc2":"CZ",
    "gn:country_code":"CZ",
    "gn:dem":305,
    "gn:feature_class":"P",
    "gn:feature_code":"PPL",
    "gn:name":"Sekerkovy Lou\u010dky",
    "gn:population":0,
    "gn:timezone":"Europe/Prague",
    "iso:country":"CZ",
    "name:und_x_variant":[
        "Lou\u010dky"
    ],
    "wof:name":"Sekerkovy Loucky",
    "wof:placetype":"locality"
},
  "geometry": {"coordinates":[15.21091,50.578],"type":"Point"}
}