{
  "type": "Feature",
  "properties": {
    "gn:gn_country":"CZ",
    "gn:gn_fcode":"PPL",
    "gn:gn_pop":637,
    "gn:population":637,
    "iso:country":"CZ",
    "name:ces_x_preferred":[
        "V\u00e1\u017eany nad Litavou"
    ],
    "name:deu_x_preferred":[
        "V\u00e1\u017eany nad Litavou"
    ],
    "name:eng_x_preferred":[
        "V\u00e1\u017eany nad Litavou"
    ],
    "name:fas_x_preferred":[
        "\u0648\u0627\u0698\u0627\u0646\u06cc \u0646\u0627\u062f \u0644\u06cc\u062a\u0627\u0648\u0648"
    ],
    "name:fra_x_preferred":[
        "V\u00e1\u017eany nad Litavou"
    ],
    "name:hun_x_preferred":[
        "V\u00e1\u017eany nad Litavou"
    ],
    "name:ita_x_preferred":[
        "V\u00e1\u017eany nad Litavou"
    ],
    "name:msa_x_preferred":[
        "V\u00e1\u017eany nad Litavou"
    ],
    "name:nld_x_preferred":[
        "V\u00e1\u017eany nad Litavou"
    ],
    "name:por_x_preferred":[
        "V\u00e1\u017eany nad Litavou"
    ],
    "name:rup_x_preferred":[
        "V\u00e1\u017eany nad Litavou"
    ],
    "name:slk_x_preferred":[
        "V\u00e1\u017eany nad Litavou"
    ],
    "name:srp_x_preferred":[
        "\u0412\u0430\u0436\u0430\u043d\u0438 \u043d\u0430 \u041b\u0438\u0442\u0430\u0432\u0438"
    ],
    "name:swe_x_preferred":[
        "V\u00e1\u017eany nad Litavou"
    ],
    "name:unk_x_variant":[
        "Linhartske-V\u00e1\u017eany"
    ],
    "name:vie_x_preferred":[
        "V\u00e1\u017eany nad Litavou"
    ],
    "qs_pg:aaroncc":"CZ",
    "qs_pg:gn_country":"CZ",
    "qs_pg:gn_fcode":"PPL",
    "qs_pg:gn_pop":637,
    "qs_pg:name":"V\u00e1\u017eany nad Litavou",
    "qs_pg:name_adm0":"\u010cesk\u00e1 republika",
    "qs_pg:name_adm1":"Jihomoravsk\u00fd kraj",
    "qs_pg:photos_9r":0,
    "qs_pg:photos_sr":0,
    "qs_pg:pop_sr":2,
    "qs_pg:qs_pg_placetype":"locality",
    "qs_pg:qs_pg_placetype_gp":"Town",
    "qs_pg:woe_adm0":23424810,
    "woe:adm0_id":23424810,
    "woe:name_adm0":"\u010cesk\u00e1 republika",
    "woe:name_adm1":"Jihomoravsk\u00fd kraj",
    "woe:placetype":"Town",
    "wof:name":"V\u00e1\u017eany nad Litavou",
    "wof:placetype":"locality",
    "wof:population":637
},
  "geometry": {"coordinates":[16.85707,49.12882],"type":"Point"}
}