{
  "type": "Feature",
  "properties": {
    "gn:admin1_code":"79.0",
    "gn:admin2_code":"0313",
    "gn:asciiname":"Malikov nad Nezarkou",
    "gn:country_code":"CZ",
    "gn:dem":510,
    "gn:feature_class":"P",
    "gn:feature_code":"PPL",
    "gn:name":"Mal\u00edkov nad Ne\u017e\u00e1rkou",
    "gn:population":0,
    "gn:timezone":"Europe/Prague",
    "iso:country":"CZ",
    "name:und_x_variant":[
        "Deutsch Moliken",
        "N\u011bmeck\u00fd Mall\u00edkov",
        "Mal\u00edkov nad Ne\u017e\u00e1rkou"
    ],
    "wof:name":"Malikov nad Nezarkou",
    "wof:placetype":"locality"
},
  "geometry": {"coordinates":[15.01122,49.09478],"type":"Point"}
}