{
  "type": "Feature",
  "properties": {
    "gn:admin1_code":"81",
    "gn:admin2_code":"0411",
    "gn:asciiname":"Amongsgruen",
    "gn:country_code":"CZ",
    "gn:dem":527,
    "gn:feature_class":"P",
    "gn:feature_code":"PPL",
    "gn:name":"Amongsgruen",
    "gn:population":0,
    "gn:timezone":"Europe/Prague",
    "iso:country":"CZ",
    "name:und_x_variant":[
        "Amonsgr\u00fcn",
        "Amongsgruen",
        "\u00dabo\u010d\u00ed"
    ],
    "wof:name":"Amongsgruen",
    "wof:placetype":"locality"
},
  "geometry": {"coordinates":[12.56629,50.02838],"type":"Point"}
}