{
  "type": "Feature",
  "properties": {
    "gn:admin1_code":"88.0",
    "gn:admin2_code":"020A",
    "gn:asciiname":"Horni Mokropsy",
    "gn:country_code":"CZ",
    "gn:dem":239,
    "gn:feature_class":"P",
    "gn:feature_code":"PPL",
    "gn:name":"Horn\u00ed Mokropsy",
    "gn:population":0,
    "gn:timezone":"Europe/Prague",
    "iso:country":"CZ",
    "wof:name":"Horni Mokropsy",
    "wof:placetype":"locality"
},
  "geometry": {"coordinates":[14.31667,49.93333],"type":"Point"}
}