{
  "type": "Feature",
  "properties": {
    "gn:country":"CZ",
    "gn:fcode":"PPL",
    "gn:population":380,
    "iso:country":"CZ",
    "name:azb_x_preferred":[
        "\u0644\u0648\u0698\u0646\u06cc\u062a\u0633\u0647"
    ],
    "name:ceb_x_preferred":[
        "Lu\u017enice"
    ],
    "name:ces_x_preferred":[
        "Lu\u017enice"
    ],
    "name:deu_x_preferred":[
        "Lu\u017enice"
    ],
    "name:eng_x_preferred":[
        "Lu\u017enice"
    ],
    "name:eus_x_preferred":[
        "Lu\u017enice"
    ],
    "name:fas_x_preferred":[
        "\u0644\u0648\u0698\u0646\u06cc\u062a\u0633\u0647"
    ],
    "name:fra_x_preferred":[
        "Lu\u017enice"
    ],
    "name:hun_x_preferred":[
        "Lu\u017enice"
    ],
    "name:ita_x_preferred":[
        "Lu\u017enice"
    ],
    "name:msa_x_preferred":[
        "Lu\u017enice"
    ],
    "name:nan_x_preferred":[
        "Lu\u017enice"
    ],
    "name:nld_x_preferred":[
        "Lu\u017enice"
    ],
    "name:pol_x_preferred":[
        "Lu\u017enice"
    ],
    "name:por_x_preferred":[
        "Lu\u017enice"
    ],
    "name:rup_x_preferred":[
        "Lu\u017enice"
    ],
    "name:slk_x_preferred":[
        "Lu\u017enice"
    ],
    "name:spa_x_preferred":[
        "Lu\u017enice"
    ],
    "name:srp_x_preferred":[
        "\u041b\u0443\u0436\u045a\u0438\u0446\u0435"
    ],
    "name:swe_x_preferred":[
        "Lu\u017enice"
    ],
    "name:und_x_variant":[
        "Lu\u017enitz"
    ],
    "name:vie_x_preferred":[
        "Lu\u017enice"
    ],
    "qs_pg:aaroncc":"CZ",
    "qs_pg:gn_country":"CZ",
    "qs_pg:gn_fcode":"PPL",
    "qs_pg:gn_pop":380,
    "qs_pg:name":"Lu\u017enice",
    "qs_pg:name_adm0":"\u010cesk\u00e1 republika",
    "qs_pg:name_adm1":"Jiho\u010desk\u00fd kraj",
    "qs_pg:photos_9k":1,
    "qs_pg:photos_9r":1,
    "qs_pg:photos_all":1,
    "qs_pg:photos_sr":0,
    "qs_pg:pop_sr":2,
    "qs_pg:qs_pg_placetype":"locality",
    "qs_pg:qs_pg_placetype_gp":"Town",
    "qs_pg:woe_adm0":23424810,
    "woe:adm0_id":23424810,
    "woe:name_adm0":"\u010cesk\u00e1 republika",
    "woe:name_adm1":"Jiho\u010desk\u00fd kraj",
    "woe:placetype":"Town",
    "wof:name":"Lu\u017enice",
    "wof:placetype":"locality",
    "wof:population":380
},
  "geometry": {"coordinates":[14.75618,49.06298],"type":"Point"}
}