{
  "type": "Feature",
  "properties": {
    "gn:admin1_code":"90.0",
    "gn:admin2_code":"0722",
    "gn:asciiname":"Popovice",
    "gn:country_code":"CZ",
    "gn:dem":262,
    "gn:feature_class":"P",
    "gn:feature_code":"PPL",
    "gn:name":"Popovice",
    "gn:population":1091,
    "gn:timezone":"Europe/Prague",
    "iso:country":"CZ",
    "name:und_x_variant":[
        "Popowitz"
    ],
    "wof:name":"Popovice",
    "wof:placetype":"locality",
    "wof:population":1091
},
  "geometry": {"coordinates":[17.52712,49.05255],"type":"Point"}
}