{
  "type": "Feature",
  "properties": {
    "gn:admin1_code":"90.0",
    "gn:admin2_code":"0722",
    "gn:asciiname":"Popovice",
    "gn:country_code":"CZ",
    "gn:dem":262,
    "gn:feature_class":"P",
    "gn:feature_code":"PPL",
    "gn:name":"Popovice",
    "gn:population":1091,
    "gn:timezone":"Europe/Prague",
    "iso:country":"CZ",
    "name:azb_x_preferred":[
        "\u067e\u0648\u067e\u0648\u0648\u06cc\u062a\u0633\u0647"
    ],
    "name:ceb_x_preferred":[
        "Popovice"
    ],
    "name:ces_x_preferred":[
        "Popovice"
    ],
    "name:eus_x_preferred":[
        "Popovice"
    ],
    "name:fas_x_preferred":[
        "\u067e\u0648\u067e\u0648\u0648\u06cc\u062a\u0633\u0647"
    ],
    "name:fra_x_preferred":[
        "Popovice"
    ],
    "name:hun_x_preferred":[
        "Popovice"
    ],
    "name:ita_x_preferred":[
        "Popovice"
    ],
    "name:msa_x_preferred":[
        "Popovice"
    ],
    "name:nld_x_preferred":[
        "Popovice"
    ],
    "name:pol_x_preferred":[
        "Popovice"
    ],
    "name:por_x_preferred":[
        "Popovice"
    ],
    "name:slk_x_preferred":[
        "Popovice"
    ],
    "name:spa_x_preferred":[
        "Popovice"
    ],
    "name:srp_x_preferred":[
        "\u041f\u043e\u043f\u043e\u0432\u0438\u0446\u0435"
    ],
    "name:und_x_variant":[
        "Popowitz"
    ],
    "name:vie_x_preferred":[
        "Popovice"
    ],
    "wof:name":"Popovice",
    "wof:placetype":"locality",
    "wof:population":1091
},
  "geometry": {"coordinates":[17.52712,49.05255],"type":"Point"}
}