{
  "type": "Feature",
  "properties": {
    "gn:gn_country":"CZ",
    "gn:gn_fcode":"PPL",
    "gn:gn_pop":121,
    "gn:population":121,
    "iso:country":"CZ",
    "name:bul_x_preferred":[
        "\u041a\u0430\u043b\u0445\u043e\u0432"
    ],
    "name:ces_x_preferred":[
        "Kalhov"
    ],
    "name:deu_x_preferred":[
        "Kalhov"
    ],
    "name:eng_x_preferred":[
        "Kalhov"
    ],
    "name:fas_x_preferred":[
        "\u06a9\u0627\u0644\u0647\u0648\u0648"
    ],
    "name:fra_x_preferred":[
        "Kalhov"
    ],
    "name:hsb_x_preferred":[
        "Kalhov"
    ],
    "name:hun_x_preferred":[
        "Kalhov"
    ],
    "name:ita_x_preferred":[
        "Kalhov"
    ],
    "name:msa_x_preferred":[
        "Kalhov"
    ],
    "name:nan_x_preferred":[
        "Kalhov"
    ],
    "name:nld_x_preferred":[
        "Kalhov"
    ],
    "name:pol_x_preferred":[
        "Kalhov"
    ],
    "name:por_x_preferred":[
        "Kalhov"
    ],
    "name:rup_x_preferred":[
        "Kalhov"
    ],
    "name:slk_x_preferred":[
        "Kalhov"
    ],
    "name:srp_x_preferred":[
        "\u041a\u0430\u043b\u0445\u043e\u0432"
    ],
    "name:swe_x_preferred":[
        "Kalhov"
    ],
    "name:vie_x_preferred":[
        "Kalhov"
    ],
    "qs_pg:aaroncc":"CZ",
    "qs_pg:gn_country":"CZ",
    "qs_pg:gn_fcode":"PPL",
    "qs_pg:gn_pop":121,
    "qs_pg:name":"Kalhov",
    "qs_pg:name_adm0":"\u010cesk\u00e1 republika",
    "qs_pg:name_adm1":"Kraj Vyso\u010dina",
    "qs_pg:photos_9r":0,
    "qs_pg:photos_sr":0,
    "qs_pg:pop_sr":1,
    "qs_pg:qs_pg_placetype":"locality",
    "qs_pg:qs_pg_placetype_gp":"Town",
    "qs_pg:woe_adm0":23424810,
    "woe:adm0_id":23424810,
    "woe:name_adm0":"\u010cesk\u00e1 republika",
    "woe:name_adm1":"Kraj Vyso\u010dina",
    "woe:placetype":"Town",
    "wof:name":"Kalhov",
    "wof:placetype":"locality",
    "wof:population":121
},
  "geometry": {"coordinates":[15.44143,49.48103],"type":"Point"}
}