{
  "type": "Feature",
  "properties": {
    "gn:admin1_code":"85.0",
    "gn:admin2_code":"0805",
    "gn:asciiname":"Podvihov",
    "gn:country_code":"CZ",
    "gn:dem":404,
    "gn:feature_class":"P",
    "gn:feature_code":"PPL",
    "gn:name":"Podvihov",
    "gn:population":0,
    "gn:timezone":"Europe/Prague",
    "iso:country":"CZ",
    "wof:name":"Podvihov",
    "wof:placetype":"locality"
},
  "geometry": {"coordinates":[17.97547999999999,49.87548],"type":"Point"}
}