{
  "type": "Feature",
  "properties": {
    "gn:admin1_code":"89.0",
    "gn:admin2_code":"0427",
    "gn:asciiname":"Panenska",
    "gn:country_code":"CZ",
    "gn:dem":677,
    "gn:feature_class":"P",
    "gn:feature_code":"PPL",
    "gn:name":"Panensk\u00e1",
    "gn:population":0,
    "gn:timezone":"Europe/Prague",
    "iso:country":"CZ",
    "name:und_x_variant":[
        "Jungferndorf",
        "Panensk\u00e1"
    ],
    "wof:name":"Panenska",
    "wof:placetype":"locality"
},
  "geometry": {"coordinates":[13.97598,50.76007],"type":"Point"}
}