{
  "type": "Feature",
  "properties": {
    "gn:admin1_code":"81.0",
    "gn:admin2_code":"0411",
    "gn:asciiname":"Lesna",
    "gn:country_code":"CZ",
    "gn:dem":461,
    "gn:feature_class":"P",
    "gn:feature_code":"PPL",
    "gn:name":"Lesn\u00e1",
    "gn:population":0,
    "gn:timezone":"Europe/Prague",
    "iso:country":"CZ",
    "name:und_x_variant":[
        "Valdov",
        "Wallhof",
        "Lesn\u00e1"
    ],
    "wof:name":"Lesna",
    "wof:placetype":"locality"
},
  "geometry": {"coordinates":[12.44593,50.20367],"type":"Point"}
}