{
  "type": "Feature",
  "properties": {
    "gn:gn_country":"CZ",
    "gn:gn_fcode":"PPL",
    "gn:gn_pop":381,
    "gn:population":381,
    "iso:country":"CZ",
    "name:azb_x_preferred":[
        "\u067e\u0648\u062f\u0647\u0631\u0627\u062f\u06cc"
    ],
    "name:ceb_x_preferred":[
        "Podhrad\u00ed"
    ],
    "name:ces_x_preferred":[
        "Podhrad\u00ed"
    ],
    "name:deu_x_preferred":[
        "Podhrad\u00ed u Ji\u010d\u00edna"
    ],
    "name:eng_x_preferred":[
        "Podhrad\u00ed"
    ],
    "name:eus_x_preferred":[
        "Podhrad\u00ed"
    ],
    "name:fas_x_preferred":[
        "\u067e\u0648\u062f\u0647\u0631\u0627\u062f\u06cc"
    ],
    "name:hun_x_preferred":[
        "Podhrad\u00ed"
    ],
    "name:ita_x_preferred":[
        "Podhrad\u00ed"
    ],
    "name:msa_x_preferred":[
        "Podhrad\u00ed"
    ],
    "name:nan_x_preferred":[
        "Podhrad\u00ed"
    ],
    "name:nld_x_preferred":[
        "Podhrad\u00ed"
    ],
    "name:pol_x_preferred":[
        "Podhrad\u00ed"
    ],
    "name:por_x_preferred":[
        "Podhrad\u00ed"
    ],
    "name:rup_x_preferred":[
        "Podhrad\u00ed"
    ],
    "name:slk_x_preferred":[
        "Podhrad\u00ed"
    ],
    "name:spa_x_preferred":[
        "Podhrad\u00ed"
    ],
    "name:srp_x_preferred":[
        "\u041f\u043e\u0434\u0445\u0440\u0430\u0434\u0438"
    ],
    "name:swe_x_preferred":[
        "Podhrad\u00ed"
    ],
    "name:unk_x_variant":[
        "Podhrad"
    ],
    "name:vie_x_preferred":[
        "Podhrad\u00ed"
    ],
    "qs_pg:aaroncc":"CZ",
    "qs_pg:gn_country":"CZ",
    "qs_pg:gn_fcode":"PPL",
    "qs_pg:gn_pop":381,
    "qs_pg:name":"Podhrad\u00ed",
    "qs_pg:name_adm0":"\u010cesk\u00e1 republika",
    "qs_pg:name_adm1":"Kr\u00e1lov\u00e9hradeck\u00fd kraj",
    "qs_pg:photos_9k":1,
    "qs_pg:photos_9r":1,
    "qs_pg:photos_all":3,
    "qs_pg:photos_sr":0,
    "qs_pg:pop_sr":2,
    "qs_pg:qs_pg_placetype":"locality",
    "qs_pg:qs_pg_placetype_gp":"Town",
    "qs_pg:woe_adm0":23424810,
    "woe:adm0_id":23424810,
    "woe:name_adm0":"\u010cesk\u00e1 republika",
    "woe:name_adm1":"Kr\u00e1lov\u00e9hradeck\u00fd kraj",
    "woe:placetype":"Town",
    "wof:name":"Podhrad\u00ed",
    "wof:placetype":"locality",
    "wof:population":381
},
  "geometry": {"coordinates":[15.31053,50.41847],"type":"Point"}
}