{
  "type": "Feature",
  "properties": {
    "gn:admin1_code":"88",
    "gn:admin2_code":"0208",
    "gn:asciiname":"Vapensko",
    "gn:country_code":"CZ",
    "gn:dem":192,
    "gn:feature_class":"P",
    "gn:feature_code":"PPL",
    "gn:name":"V\u00e1pensko",
    "gn:population":0,
    "gn:timezone":"Europe/Prague",
    "iso:country":"CZ",
    "wof:name":"Vapensko",
    "wof:placetype":"locality"
},
  "geometry": {"coordinates":[14.92901,50.21505],"type":"Point"}
}