{
  "type": "Feature",
  "properties": {
    "gn:admin1_code":"80.0",
    "gn:admin2_code":"0615",
    "gn:asciiname":"Brt'ovi",
    "gn:country_code":"CZ",
    "gn:dem":498,
    "gn:feature_class":"P",
    "gn:feature_code":"PPL",
    "gn:name":"Br\u0165ov\u00ed",
    "gn:population":0,
    "gn:timezone":"Europe/Prague",
    "iso:country":"CZ",
    "wof:name":"Brt'ovi",
    "wof:placetype":"locality"
},
  "geometry": {"coordinates":[16.37035,49.53119],"type":"Point"}
}